{
  "type": "Feature",
  "properties": {
    "iso:country":"US",
    "sg:address":"2835 S Wagner Rd",
    "sg:city":"Ann Arbor",
    "sg:classifiers":[
        {
            "category":"Building & Trades",
            "subcategory":"Construction",
            "type":"Services"
        }
    ],
    "sg:phone":"+1 734 996 3879",
    "sg:postcode":"48103",
    "sg:province":"MI",
    "sg:tags":[
        "house"
    ],
    "wof:name":"Brentford Group",
    "wof:placetype":"venue"
},
  "geometry": {"coordinates":[-83.798474,42.245743],"type":"Point"}
}