{
  "type": "Feature",
  "properties": {
    "iso:country":"US",
    "sg:address":"2521 Glazier Way",
    "sg:city":"Ann Arbor",
    "sg:classifiers":[
        {
            "category":"Real Estate",
            "subcategory":"Developer",
            "type":"Services"
        }
    ],
    "sg:phone":"+1 734 761 4572",
    "sg:postcode":"48105",
    "sg:province":"MI",
    "sg:tags":[
        "cemetery"
    ],
    "wof:name":"Arborcrest Memorial Park",
    "wof:placetype":"venue"
},
  "geometry": {"coordinates":[-83.70925800000001,42.287718],"type":"Point"}
}