{
  "type": "Feature",
  "properties": {
    "iso:country":"US",
    "sg:address":"6264 Dixie Hwy",
    "sg:city":"Bridgeport",
    "sg:classifiers":[
        {
            "category":"Education",
            "subcategory":"Special Training",
            "type":"Public Place"
        }
    ],
    "sg:phone":"+1 989 777 4420",
    "sg:postcode":"48722",
    "sg:province":"MI",
    "sg:tags":[
        "profit",
        "student",
        "exchange"
    ],
    "wof:name":"Exchange Student Program",
    "wof:placetype":"venue"
},
  "geometry": {"coordinates":[-83.873704,43.354903],"type":"Point"}
}