{
  "type": "Feature",
  "properties": {
    "iso:country":"US",
    "sg:address":"3044 W Grand Blvd",
    "sg:city":"Detroit",
    "sg:classifiers":[
        {
            "category":"Restaurant",
            "type":"Food & Drink"
        }
    ],
    "sg:menulink":"http://www.allmenus.com/mi/detroit/56862-subway/menu/",
    "sg:phone":"+1 313 875 7185",
    "sg:postcode":"48202",
    "sg:province":"MI",
    "sg:tags":[
        "american",
        "sandwich"
    ],
    "wof:name":"Subway",
    "wof:placetype":"venue"
},
  "geometry": {"coordinates":[-83.07549299999999,42.369342],"type":"Point"}
}