{
  "type": "Feature",
  "properties": {
    "iso:country":"US",
    "sg:address":"8549 Eldora Dr SW",
    "sg:city":"Byron Center",
    "sg:classifiers":[
        {
            "category":"Professional",
            "subcategory":"Computer Services",
            "type":"Services"
        }
    ],
    "sg:phone":"+1 616 878 4020",
    "sg:postcode":"49315",
    "sg:province":"MI",
    "wof:name":"Radix Solutions",
    "wof:placetype":"venue"
},
  "geometry": {"coordinates":[-85.73605999999999,42.807005],"type":"Point"}
}