{
  "type": "Feature",
  "properties": {
    "iso:country":"US",
    "sg:address":"2200 Fuller Rd",
    "sg:city":"Ann Arbor",
    "sg:classifiers":[
        {
            "category":"Social Services",
            "type":"Services"
        }
    ],
    "sg:phone":"+1 734 769 1232",
    "sg:postcode":"48105",
    "sg:province":"MI",
    "wof:name":"Moncur Rom Msw Bcd",
    "wof:placetype":"venue"
},
  "geometry": {"coordinates":[-83.715828,42.287401],"type":"Point"}
}