{
  "type": "Feature",
  "properties": {
    "iso:country":"US",
    "sg:address":"23333 S Woodward Ave",
    "sg:city":"Ferndale",
    "sg:classifiers":[
        {
            "category":"Real Estate",
            "subcategory":"Real Estate Agent",
            "type":"Services"
        }
    ],
    "sg:phone":"+1 248 288 8080",
    "sg:postcode":"48220",
    "sg:province":"MI",
    "sg:website":"www.remaxavenue.com",
    "wof:name":"Remax Avenue",
    "wof:placetype":"venue"
},
  "geometry": {"coordinates":[-83.1386,42.466127],"type":"Point"}
}