{
  "type": "Feature",
  "properties": {
    "iso:country":"US",
    "sg:address":"700 W Blue Star Dr",
    "sg:city":"Traverse City",
    "sg:classifiers":[
        {
            "category":"Home & Garden",
            "subcategory":"Garden Supply",
            "type":"Retail Goods"
        }
    ],
    "sg:phone":"+1 231 943 3990",
    "sg:postcode":"49684",
    "sg:province":"MI",
    "sg:tags":[
        "landscaping",
        "equipment"
    ],
    "wof:name":"Blue Star Landscape Supply",
    "wof:placetype":"venue"
},
  "geometry": {"coordinates":[-85.655008,44.695492],"type":"Point"}
}