{
  "type": "Feature",
  "properties": {
    "iso:country":"US",
    "sg:address":"5116 Flaxton Dr",
    "sg:city":"Saginaw",
    "sg:classifiers":[
        {
            "category":"Social Services",
            "subcategory":"Child Care",
            "type":"Services"
        }
    ],
    "sg:phone":"+1 989 791 1758",
    "sg:postcode":"48603",
    "sg:province":"MI",
    "wof:name":"Welcome Home Day Care",
    "wof:placetype":"venue"
},
  "geometry": {"coordinates":[-84.018596,43.458619],"type":"Point"}
}