{
  "type": "Feature",
  "properties": {
    "iso:country":"US",
    "sg:address":"9999 Red Arrow Hwy",
    "sg:city":"Bridgman",
    "sg:classifiers":[
        {
            "category":"Travel",
            "subcategory":"Hotels & Motels",
            "type":"Entertainment"
        }
    ],
    "sg:phone":"+1 269 465 3187",
    "sg:postcode":"49106",
    "sg:province":"MI",
    "sg:tags":[
        "operation"
    ],
    "wof:name":"Bridgman Inn",
    "wof:placetype":"venue"
},
  "geometry": {"coordinates":[-86.56619999999999,41.937612],"type":"Point"}
}