{
  "type": "Feature",
  "properties": {
    "iso:country":"US",
    "sg:address":"409 E Lansing Rd",
    "sg:city":"East Lansing",
    "sg:classifiers":[
        {
            "category":"Professional",
            "subcategory":"Management & Consulting",
            "type":"Services"
        }
    ],
    "sg:phone":"+1 517 353 3131",
    "sg:postcode":"48857",
    "sg:province":"MI",
    "sg:tags":[
        "employment",
        "relations"
    ],
    "wof:name":"Project On Innovative",
    "wof:placetype":"venue"
},
  "geometry": {"coordinates":[-84.15598300000001,42.853172],"type":"Point"}
}