{
  "type": "Feature",
  "properties": {
    "iso:country":"US",
    "sg:address":"10900 Bigelow Rd",
    "sg:city":"Davisburg",
    "sg:classifiers":[
        {
            "category":"Building & Trades",
            "subcategory":"Cleaning & Sanitation",
            "type":"Services"
        }
    ],
    "sg:phone":"+1 248 625 6543",
    "sg:postcode":"48350",
    "sg:province":"MI",
    "sg:tags":[
        "janitor"
    ],
    "wof:name":"David Hart Maintenance Co",
    "wof:placetype":"venue"
},
  "geometry": {"coordinates":[-83.51247499999999,42.768044],"type":"Point"}
}