{
  "type": "Feature",
  "properties": {
    "iso:country":"US",
    "sg:address":"4901 Fontaine Blvd",
    "sg:city":"Saginaw",
    "sg:classifiers":[
        {
            "category":"Real Estate",
            "subcategory":"Real Estate Operator",
            "type":"Services"
        }
    ],
    "sg:phone":"+1 989 790 8328",
    "sg:postcode":"48603",
    "sg:province":"MI",
    "sg:tags":[
        "apartment"
    ],
    "wof:name":"Fontaine Garden Apartments",
    "wof:placetype":"venue"
},
  "geometry": {"coordinates":[-84.013999,43.439819],"type":"Point"}
}