{
  "type": "Feature",
  "properties": {
    "iso:country":"US",
    "sg:address":"6710 Bloomfield Ln",
    "sg:city":"West Bloomfield",
    "sg:classifiers":[
        {
            "category":"Organizations",
            "subcategory":"Religious Organization",
            "type":"Services"
        }
    ],
    "sg:phone":"+1 248 681 8802",
    "sg:postcode":"48322",
    "sg:province":"MI",
    "sg:tags":[
        "clergy"
    ],
    "wof:name":"M Robert Syme",
    "wof:placetype":"venue"
},
  "geometry": {"coordinates":[-83.332801,42.542517],"type":"Point"}
}