{
  "type": "Feature",
  "properties": {
    "iso:country":"US",
    "sg:address":"3133 Caswell Dr",
    "sg:city":"Troy",
    "sg:classifiers":[
        {
            "category":"Insurance",
            "subcategory":"Hazard Insurance",
            "type":"Services"
        }
    ],
    "sg:phone":"+1 248 709 0742",
    "sg:postcode":"48084",
    "sg:province":"MI",
    "sg:tags":[
        "funds",
        "health",
        "pension",
        "welfare"
    ],
    "wof:name":"Quorum Solutions LLC",
    "wof:placetype":"venue"
},
  "geometry": {"coordinates":[-83.198382,42.563962],"type":"Point"}
}