{
  "type": "Feature",
  "properties": {
    "iso:country":"US",
    "sg:address":"2325 Click Rd",
    "sg:city":"Petoskey",
    "sg:classifiers":[
        {
            "category":"Organizations",
            "subcategory":"Professional Association",
            "type":"Services"
        }
    ],
    "sg:phone":"+1 231 348 9147",
    "sg:postcode":"49770",
    "sg:province":"MI",
    "wof:name":"Petoskey Youth Soccer Assoc",
    "wof:placetype":"venue"
},
  "geometry": {"coordinates":[-84.92247,45.334041],"type":"Point"}
}