{
  "type": "Feature",
  "properties": {
    "iso:country":"US",
    "sg:address":"1 Heritage Pl",
    "sg:city":"Southgate",
    "sg:classifiers":[
        {
            "category":"Banks & Credit Unions",
            "subcategory":"Investment Brokerage",
            "type":"Services"
        }
    ],
    "sg:phone":"+1 734 283 1200",
    "sg:postcode":"48195",
    "sg:province":"MI",
    "wof:name":"Taylor & Associates LLC",
    "wof:placetype":"venue"
},
  "geometry": {"coordinates":[-83.22283899999999,42.210951],"type":"Point"}
}