{
  "type": "Feature",
  "properties": {
    "iso:country":"US",
    "sg:address":"2370 Maplecrest Dr",
    "sg:city":"Waterford",
    "sg:classifiers":[
        {
            "category":"Autos & Motor Vehicles",
            "subcategory":"Automobile Sales",
            "type":"Retail Goods"
        }
    ],
    "sg:phone":"+1 248 623 6673",
    "sg:postcode":"48327",
    "sg:province":"MI",
    "sg:tags":[
        "car",
        "dealer"
    ],
    "wof:name":"Drayton Motors",
    "wof:placetype":"venue"
},
  "geometry": {"coordinates":[-83.412161,42.674099],"type":"Point"}
}