{
  "type": "Feature",
  "properties": {
    "iso:country":"US",
    "sg:address":"426 W Front St",
    "sg:city":"Traverse City",
    "sg:classifiers":[
        {
            "category":"Insurance",
            "subcategory":"Hazard Insurance",
            "type":"Services"
        }
    ],
    "sg:phone":"+1 231 935 4860",
    "sg:postcode":"49684",
    "sg:province":"MI",
    "sg:tags":[
        "carrier"
    ],
    "wof:name":"All Amercian Financial Svcs",
    "wof:placetype":"venue"
},
  "geometry": {"coordinates":[-85.6288,44.764113],"type":"Point"}
}