{
  "type": "Feature",
  "properties": {
    "iso:country":"US",
    "sg:address":"15826 Novara St",
    "sg:city":"Detroit",
    "sg:classifiers":[
        {
            "category":"Shopping",
            "subcategory":"Optical Goods",
            "type":"Retail Goods"
        }
    ],
    "sg:phone":"+1 313 595 7373",
    "sg:postcode":"48205",
    "sg:province":"MI",
    "wof:name":"Spex Optical",
    "wof:placetype":"venue"
},
  "geometry": {"coordinates":[-82.956121,42.439121],"type":"Point"}
}