{
  "type": "Feature",
  "properties": {
    "iso:country":"US",
    "sg:address":"624 Lavender St",
    "sg:city":"Monroe",
    "sg:classifiers":[
        {
            "category":"Building & Trades",
            "subcategory":"Landscaping Services",
            "type":"Services"
        }
    ],
    "sg:phone":"+1 734 457 0187",
    "sg:postcode":"48162",
    "sg:province":"MI",
    "sg:tags":[
        "landscape",
        "contractor"
    ],
    "wof:name":"L A Lawn & Landscaping",
    "wof:placetype":"venue"
},
  "geometry": {"coordinates":[-83.403282,41.927998],"type":"Point"}
}