{
  "type": "Feature",
  "properties": {
    "iso:country":"US",
    "sg:address":"222 E 11 Mile Rd",
    "sg:city":"Royal Oak",
    "sg:classifiers":[
        {
            "category":"Education",
            "subcategory":"Library",
            "type":"Public Place"
        }
    ],
    "sg:phone":"+1 248 246 3700",
    "sg:postcode":"48068",
    "sg:province":"MI",
    "sg:website":"www.ropl.org",
    "wof:name":"Royal Oak Public Library",
    "wof:placetype":"venue"
},
  "geometry": {"coordinates":[-83.14285599999999,42.48986],"type":"Point"}
}