{
  "type": "Feature",
  "properties": {
    "iso:country":"US",
    "sg:address":"8587 Narrow Lake Rd",
    "sg:city":"Springport",
    "sg:classifiers":[
        {
            "category":"Food & Beverages",
            "subcategory":"Groceries & Convenience Stores",
            "type":"Retail Goods"
        }
    ],
    "sg:phone":"+1 517 543 2538",
    "sg:postcode":"49284",
    "sg:province":"MI",
    "sg:tags":[
        "grocer"
    ],
    "wof:name":"Narrow Lake Country Store",
    "wof:placetype":"venue"
},
  "geometry": {"coordinates":[-84.77894499999999,42.442105],"type":"Point"}
}