{
  "type": "Feature",
  "properties": {
    "iso:country":"US",
    "sg:address":"1246 Railroad Rd",
    "sg:city":"Union City",
    "sg:classifiers":[
        {
            "category":"Personal",
            "subcategory":"Beauty Salon",
            "type":"Services"
        }
    ],
    "sg:phone":"+1 517 741 5351",
    "sg:postcode":"49094",
    "sg:province":"MI",
    "wof:name":"Snip 'n Curl Beauty Shop",
    "wof:placetype":"venue"
},
  "geometry": {"coordinates":[-85.119389,42.064884],"type":"Point"}
}