{
  "type": "Feature",
  "properties": {
    "iso:country":"US",
    "sg:address":"132 W Main St",
    "sg:city":"Gaylord",
    "sg:classifiers":[
        {
            "category":"Shopping",
            "subcategory":"Gifts & Souvenirs",
            "type":"Retail Goods"
        }
    ],
    "sg:phone":"+1 989 705 2733",
    "sg:postcode":"49735",
    "sg:province":"MI",
    "wof:name":"Vans Rock Works",
    "wof:placetype":"venue"
},
  "geometry": {"coordinates":[-84.674325,45.027445],"type":"Point"}
}