{
  "type": "Feature",
  "properties": {
    "iso:country":"US",
    "sg:address":"1204 Edwin St",
    "sg:city":"Westland",
    "sg:classifiers":[
        {
            "category":"Building & Trades",
            "subcategory":"Construction",
            "type":"Services"
        }
    ],
    "sg:phone":"+1 734 595 8301",
    "sg:postcode":"48186",
    "sg:province":"MI",
    "sg:tags":[
        "residential"
    ],
    "wof:name":"Building Concepts",
    "wof:placetype":"venue"
},
  "geometry": {"coordinates":[-83.411333,42.299149],"type":"Point"}
}