{
  "type": "Feature",
  "properties": {
    "iso:country":"US",
    "sg:address":"32512 Pierce St",
    "sg:city":"Garden City",
    "sg:classifiers":[
        {
            "category":"Building & Trades",
            "subcategory":"Plumbing",
            "type":"Services"
        }
    ],
    "sg:phone":"+1 248 209 6135",
    "sg:postcode":"48135",
    "sg:province":"MI",
    "wof:name":"Birmingham Plumbing Company Llc",
    "wof:placetype":"venue"
},
  "geometry": {"coordinates":[-83.361558,42.320559],"type":"Point"}
}