{
  "type": "Feature",
  "properties": {
    "iso:country":"US",
    "sg:address":"24559 Emily Dr",
    "sg:city":"Trenton",
    "sg:classifiers":[
        {
            "category":"Personal",
            "subcategory":"Barber",
            "type":"Services"
        }
    ],
    "sg:phone":"+1 734 782 8903",
    "sg:postcode":"48183",
    "sg:province":"MI",
    "sg:tags":[
        "shop"
    ],
    "wof:name":"Gurkerm Inc",
    "wof:placetype":"venue"
},
  "geometry": {"coordinates":[-83.256552,42.12702],"type":"Point"}
}