{
  "type": "Feature",
  "properties": {
    "iso:country":"US",
    "sg:address":"136 Inverness",
    "sg:city":"Highland",
    "sg:classifiers":[
        {
            "category":"Sports & Exercise",
            "subcategory":"Golf",
            "type":"Entertainment"
        },
        {
            "category":"Recreation",
            "type":"Entertainment"
        }
    ],
    "sg:phone":"+1 248 887 1762",
    "sg:postcode":"48357",
    "sg:province":"MI",
    "sg:tags":[
        "course",
        "membership"
    ],
    "wof:name":"Prestwick Village Golf Club",
    "wof:placetype":"venue"
},
  "geometry": {"coordinates":[-83.644972,42.634009],"type":"Point"}
}