{
  "type": "Feature",
  "properties": {
    "iso:country":"US",
    "sg:address":"3471 Ella",
    "sg:city":"Deckerville",
    "sg:classifiers":[
        {
            "category":"Real Estate",
            "subcategory":"Real Estate Agent",
            "type":"Services"
        }
    ],
    "sg:phone":"+1 810 376 4416",
    "sg:postcode":"48427",
    "sg:province":"MI",
    "wof:name":"Sanilac Realty",
    "wof:placetype":"venue"
},
  "geometry": {"coordinates":[-82.73638699999999,43.526571],"type":"Point"}
}