{
  "type": "Feature",
  "properties": {
    "iso:country":"US",
    "sg:address":"852 S Hooper St",
    "sg:city":"Caro",
    "sg:classifiers":[
        {
            "category":"Insurance",
            "subcategory":"Insurance Agent",
            "type":"Services"
        }
    ],
    "sg:phone":"+1 989 673 0330",
    "sg:postcode":"48723",
    "sg:province":"MI",
    "wof:name":"Sherman & Assoc",
    "wof:placetype":"venue"
},
  "geometry": {"coordinates":[-83.406297,43.48178],"type":"Point"}
}