{
  "type": "Feature",
  "properties": {
    "iso:country":"US",
    "sg:address":"609 Buckley St",
    "sg:city":"Elk Rapids",
    "sg:classifiers":[
        {
            "category":"Retail",
            "subcategory":"Laundry & Dry Cleaning",
            "type":"Services"
        }
    ],
    "sg:phone":"+1 231 264 8399",
    "sg:postcode":"49629",
    "sg:province":"MI",
    "wof:name":"East Bay Cleaning",
    "wof:placetype":"venue"
},
  "geometry": {"coordinates":[-85.395664,44.897538],"type":"Point"}
}