{
  "type": "Feature",
  "properties": {
    "iso:country":"US",
    "sg:address":"3940 Fenkell St",
    "sg:city":"Detroit",
    "sg:classifiers":[
        {
            "category":"Organizations",
            "subcategory":"Religious Organization",
            "type":"Services"
        }
    ],
    "sg:phone":"+1 313 585 4089",
    "sg:postcode":"48238",
    "sg:province":"MI",
    "sg:tags":[
        "baptist",
        "church"
    ],
    "wof:name":"Second Hstrcal Hwy Bptst Chrch",
    "wof:placetype":"venue"
},
  "geometry": {"coordinates":[-83.13761700000001,42.402802],"type":"Point"}
}