{
  "type": "Feature",
  "properties": {
    "iso:country":"US",
    "sg:address":"65220 Lowe Plank Rd",
    "sg:city":"New Haven",
    "sg:classifiers":[
        {
            "category":"Building & Trades",
            "subcategory":"Construction",
            "type":"Services"
        }
    ],
    "sg:phone":"+1 586 727 4884",
    "sg:postcode":"48050",
    "sg:province":"MI",
    "sg:tags":[
        "water",
        "well",
        "drilling"
    ],
    "wof:name":"Robertson & Sons Well Drilling",
    "wof:placetype":"venue"
},
  "geometry": {"coordinates":[-82.773498,42.793731],"type":"Point"}
}