{
  "type": "Feature",
  "properties": {
    "iso:country":"US",
    "sg:address":"511 N Main St",
    "sg:city":"Frankenmuth",
    "sg:classifiers":[
        {
            "category":"Autos & Motor Vehicles",
            "subcategory":"Automobile Sales",
            "type":"Retail Goods"
        }
    ],
    "sg:phone":"+1 989 652 9906",
    "sg:postcode":"48734",
    "sg:province":"MI",
    "sg:tags":[
        "car",
        "dealer"
    ],
    "sg:website":"www.zehnderchevy.com",
    "wof:name":"Zehnder Chevrolet Buick Geo",
    "wof:placetype":"venue"
},
  "geometry": {"coordinates":[-83.738131,43.341726],"type":"Point"}
}