{
  "type": "Feature",
  "properties": {
    "iso:country":"US",
    "sg:address":"3313 Richfield Rd",
    "sg:city":"Flint",
    "sg:classifiers":[
        {
            "category":"Retail",
            "subcategory":"Repair Shop",
            "type":"Services"
        }
    ],
    "sg:phone":"+1 810 736 2110",
    "sg:postcode":"48506",
    "sg:province":"MI",
    "sg:tags":[
        "ironwork"
    ],
    "wof:name":"Richfield Iron Works",
    "wof:placetype":"venue"
},
  "geometry": {"coordinates":[-83.644667,43.050929],"type":"Point"}
}