{
  "type": "Feature",
  "properties": {
    "iso:country":"US",
    "sg:address":"23548 Suttons Bay",
    "sg:city":"Clinton Township",
    "sg:classifiers":[
        {
            "category":"Home & Garden",
            "subcategory":"Carpets & Floor Coverings",
            "type":"Retail Goods"
        }
    ],
    "sg:phone":"+1 586 463 1636",
    "sg:postcode":"48036",
    "sg:province":"MI",
    "wof:name":"Feltons Custom Carpet",
    "wof:placetype":"venue"
},
  "geometry": {"coordinates":[-82.86937500000001,42.620444],"type":"Point"}
}