{
  "type": "Feature",
  "properties": {
    "iso:country":"US",
    "sg:address":"1213 W Civic Center Dr",
    "sg:city":"Traverse City",
    "sg:classifiers":[
        {
            "category":"Government",
            "subcategory":"Office",
            "type":"Public Place"
        }
    ],
    "sg:phone":"+1 231 922 4830",
    "sg:postcode":"49686",
    "sg:province":"MI",
    "wof:name":"Grand Traverse Ice Arena",
    "wof:placetype":"venue"
},
  "geometry": {"coordinates":[-85.593346,44.762438],"type":"Point"}
}