{
  "type": "Feature",
  "properties": {
    "iso:country":"US",
    "sg:address":"490 W Ontario St",
    "sg:city":"Rogers City",
    "sg:classifiers":[
        {
            "category":"Professional",
            "subcategory":"Engineering",
            "type":"Services"
        }
    ],
    "sg:phone":"+1 989 734 0655",
    "sg:postcode":"49779",
    "sg:province":"MI",
    "wof:name":"Verys",
    "wof:placetype":"venue"
},
  "geometry": {"coordinates":[-83.81926799999999,45.415419],"type":"Point"}
}