{
  "type": "Feature",
  "properties": {
    "iso:country":"US",
    "sg:address":"363 N 2nd St",
    "sg:city":"Kalamazoo",
    "sg:classifiers":[
        {
            "category":"Recreation",
            "type":"Entertainment"
        }
    ],
    "sg:phone":"+1 269 372 1965",
    "sg:postcode":"49009",
    "sg:province":"MI",
    "sg:tags":[
        "club",
        "membership"
    ],
    "wof:name":"Experimental Aircraft Assoc",
    "wof:placetype":"venue"
},
  "geometry": {"coordinates":[-85.74543799999999,42.292212],"type":"Point"}
}