{
  "type": "Feature",
  "properties": {
    "iso:country":"US",
    "sg:address":"12379 Collier Hwy",
    "sg:city":"Tipton",
    "sg:classifiers":[
        {
            "category":"Building & Trades",
            "subcategory":"Construction",
            "type":"Services"
        }
    ],
    "sg:phone":"+1 517 431 8613",
    "sg:postcode":"49287",
    "sg:province":"MI",
    "sg:tags":[
        "carpentry",
        "contractor"
    ],
    "wof:name":"JW Carpentry",
    "wof:placetype":"venue"
},
  "geometry": {"coordinates":[-84.106582,42.065054],"type":"Point"}
}