{
  "type": "Feature",
  "properties": {
    "iso:country":"US",
    "sg:address":"7501 Kirkridge St",
    "sg:city":"Belleville",
    "sg:classifiers":[
        {
            "category":"Personal",
            "type":"Services"
        }
    ],
    "sg:phone":"+1 734 699 8211",
    "sg:postcode":"48111",
    "sg:province":"MI",
    "sg:tags":[
        "home",
        "improvement",
        "contractor"
    ],
    "wof:name":"New Horizons Home Improv",
    "wof:placetype":"venue"
},
  "geometry": {"coordinates":[-83.45688800000001,42.24744],"type":"Point"}
}