{
  "type": "Feature",
  "properties": {
    "iso:country":"US",
    "sg:address":"9184 Brady",
    "sg:city":"Redford",
    "sg:classifiers":[
        {
            "category":"Organizations",
            "subcategory":"Membership Organization",
            "type":"Services"
        }
    ],
    "sg:phone":"+1 313 534 9077",
    "sg:postcode":"48239",
    "sg:province":"MI",
    "sg:tags":[
        "religious"
    ],
    "wof:name":"Embroiderers Guild of AME",
    "wof:placetype":"venue"
},
  "geometry": {"coordinates":[-83.286411,42.361633],"type":"Point"}
}