{
  "type": "Feature",
  "properties": {
    "iso:country":"US",
    "sg:address":"1575 44th St SW",
    "sg:city":"Wyoming",
    "sg:classifiers":[
        {
            "category":"Real Estate",
            "subcategory":"Real Estate Agent",
            "type":"Services"
        }
    ],
    "sg:phone":"+1 616 257 4406",
    "sg:postcode":"49509",
    "sg:province":"MI",
    "wof:name":"Pikaart Realty",
    "wof:placetype":"venue"
},
  "geometry": {"coordinates":[-85.704578,42.88449],"type":"Point"}
}