{
  "type": "Feature",
  "properties": {
    "iso:country":"US",
    "sg:address":"58 Apple Blossom Ln",
    "sg:city":"Okemos",
    "sg:classifiers":[
        {
            "category":"Building & Trades",
            "subcategory":"Construction",
            "type":"Services"
        }
    ],
    "sg:phone":"+1 517 655 2422",
    "sg:postcode":"48864",
    "sg:province":"MI",
    "sg:tags":[
        "contractor"
    ],
    "wof:name":"Wilbrink & Sons Construction",
    "wof:placetype":"venue"
},
  "geometry": {"coordinates":[-84.360945,42.676742],"type":"Point"}
}