{
  "type": "Feature",
  "properties": {
    "iso:country":"US",
    "sg:address":"4270 Plainfield Ave NE",
    "sg:city":"Grand Rapids",
    "sg:classifiers":[
        {
            "category":"Health Services",
            "subcategory":"Doctor",
            "type":"Services"
        }
    ],
    "sg:phone":"+1 616 361 9497",
    "sg:postcode":"49525",
    "sg:province":"MI",
    "wof:name":"M Terry Hurt DDS",
    "wof:placetype":"venue"
},
  "geometry": {"coordinates":[-85.609467,43.039467],"type":"Point"}
}