{
  "type": "Feature",
  "properties": {
    "iso:country":"US",
    "sg:address":"517 N 8th St",
    "sg:city":"Kalamazoo",
    "sg:classifiers":[
        {
            "category":"Shopping",
            "type":"Retail Goods"
        }
    ],
    "sg:phone":"+1 269 372 4494",
    "sg:postcode":"49009",
    "sg:province":"MI",
    "sg:tags":[
        "equipment",
        "telephone",
        "supply"
    ],
    "wof:name":"Interconnect Services",
    "wof:placetype":"venue"
},
  "geometry": {"coordinates":[-85.687251,42.292039],"type":"Point"}
}