{
  "type": "Feature",
  "properties": {
    "iso:country":"US",
    "sg:address":"53387 Pimpernil",
    "sg:city":"Chesterfield",
    "sg:classifiers":[
        {
            "category":"Wholesale",
            "subcategory":"Fruits & Vegetables",
            "type":"Manufacturing & Wholesale Goods"
        }
    ],
    "sg:phone":"+1 586 749 8261",
    "sg:postcode":"48051",
    "sg:province":"MI",
    "wof:name":"C & C Wholesale Produce",
    "wof:placetype":"venue"
},
  "geometry": {"coordinates":[-82.799952,42.691195],"type":"Point"}
}