{
  "type": "Feature",
  "properties": {
    "iso:country":"US",
    "sg:address":"28730 Massachusetts St",
    "sg:city":"Roseville",
    "sg:classifiers":[
        {
            "category":"Building & Trades",
            "subcategory":"Construction",
            "type":"Services"
        }
    ],
    "sg:phone":"+1 586 779 2731",
    "sg:postcode":"48066",
    "sg:province":"MI",
    "sg:tags":[
        "carpentry",
        "contractor"
    ],
    "wof:name":"J & R Overhead Door",
    "wof:placetype":"venue"
},
  "geometry": {"coordinates":[-82.92449499999999,42.509027],"type":"Point"}
}