{
  "type": "Feature",
  "properties": {
    "iso:country":"US",
    "sg:address":"1668 142nd Ave",
    "sg:city":"Dorr",
    "sg:classifiers":[
        {
            "category":"Insurance",
            "subcategory":"Insurance Agent",
            "type":"Services"
        }
    ],
    "sg:phone":"+1 616 681 2608",
    "sg:postcode":"49323",
    "sg:province":"MI",
    "wof:name":"Brown Consulting Insurance",
    "wof:placetype":"venue"
},
  "geometry": {"coordinates":[-85.709845,42.72498],"type":"Point"}
}