{
  "type": "Feature",
  "properties": {
    "iso:country":"US",
    "sg:address":"32100 Telegraph Rd",
    "sg:city":"Bingham Farms",
    "sg:classifiers":[
        {
            "category":"Building & Trades",
            "subcategory":"Construction",
            "type":"Services"
        }
    ],
    "sg:phone":"+1 248 723 7727",
    "sg:postcode":"48025",
    "sg:province":"MI",
    "sg:tags":[
        "repairing",
        "remodeling",
        "contractor"
    ],
    "wof:name":"Owens Corning Basements",
    "wof:placetype":"venue"
},
  "geometry": {"coordinates":[-83.285427,42.523723],"type":"Point"}
}