{
  "type": "Feature",
  "properties": {
    "iso:country":"US",
    "sg:address":"7851 Double Tree Ct",
    "sg:city":"Kalamazoo",
    "sg:classifiers":[
        {
            "category":"Professional",
            "subcategory":"Management & Consulting",
            "type":"Services"
        }
    ],
    "sg:phone":"+1 269 353 4948",
    "sg:postcode":"49009",
    "sg:province":"MI",
    "wof:name":"Strike Zone Marketing",
    "wof:placetype":"venue"
},
  "geometry": {"coordinates":[-85.661636,42.203813],"type":"Point"}
}