{
  "type": "Feature",
  "properties": {
    "iso:country":"US",
    "sg:address":"3260 Chicago Dr SW",
    "sg:city":"Grandville",
    "sg:classifiers":[
        {
            "category":"Autos & Motor Vehicles",
            "subcategory":"Auto Supplies",
            "type":"Retail Goods"
        }
    ],
    "sg:phone":"+1 616 534 4230",
    "sg:postcode":"49418",
    "sg:province":"MI",
    "sg:tags":[
        "tire"
    ],
    "wof:name":"Eagle Tire Inc",
    "wof:placetype":"venue"
},
  "geometry": {"coordinates":[-85.745901,42.917286],"type":"Point"}
}