{
  "type": "Feature",
  "properties": {
    "iso:country":"US",
    "sg:address":"311 N Lackie Rd",
    "sg:city":"Bad Axe",
    "sg:classifiers":[
        {
            "category":"Building & Trades",
            "subcategory":"Construction",
            "type":"Services"
        }
    ],
    "sg:phone":"+1 989 269 2949",
    "sg:postcode":"48413",
    "sg:province":"MI",
    "sg:tags":[
        "paving",
        "asphalt",
        "contractor"
    ],
    "wof:name":"Yaroch Asphalt",
    "wof:placetype":"venue"
},
  "geometry": {"coordinates":[-83.081012,43.827532],"type":"Point"}
}