{
  "type": "Feature",
  "properties": {
    "iso:country":"US",
    "sg:address":"394 US Hwy 41",
    "sg:city":"Negaunee",
    "sg:classifiers":[
        {
            "category":"Personal",
            "subcategory":"Beauty Salon",
            "type":"Services"
        }
    ],
    "sg:phone":"+1 906 475 7524",
    "sg:postcode":"49866",
    "sg:province":"MI",
    "sg:tags":[
        "shop"
    ],
    "wof:name":"Hair Repair",
    "wof:placetype":"venue"
},
  "geometry": {"coordinates":[-87.60518999999999,46.50995],"type":"Point"}
}