{
  "type": "Feature",
  "properties": {
    "iso:country":"US",
    "sg:address":"516 W Kilgore Rd",
    "sg:city":"Kalamazoo",
    "sg:classifiers":[
        {
            "category":"Shopping",
            "subcategory":"Optical Goods",
            "type":"Retail Goods"
        }
    ],
    "sg:phone":"+1 269 343 9292",
    "sg:postcode":"49008",
    "sg:province":"MI",
    "wof:name":"Kent Optical Inc",
    "wof:placetype":"venue"
},
  "geometry": {"coordinates":[-85.594548,42.245247],"type":"Point"}
}