{
  "type": "Feature",
  "properties": {
    "iso:country":"US",
    "sg:address":"3697 N Farver Rd",
    "sg:city":"Elkton",
    "sg:phone":"+1 989 375 4349",
    "sg:postcode":"48731",
    "sg:province":"MI",
    "sg:tags":[
        "farm",
        "corn",
        "soybean"
    ],
    "wof:name":"Leo Mc Ardle",
    "wof:placetype":"venue"
},
  "geometry": {"coordinates":[-83.20240200000001,43.892623],"type":"Point"}
}