{
  "type": "Feature",
  "properties": {
    "iso:country":"US",
    "sg:address":"215 Garden Ln",
    "sg:city":"Saginaw",
    "sg:classifiers":[
        {
            "category":"Organizations",
            "subcategory":"Religious Organization",
            "type":"Services"
        }
    ],
    "sg:phone":"+1 989 791 1530",
    "sg:postcode":"48602",
    "sg:province":"MI",
    "wof:name":"Body of Christ Inc",
    "wof:placetype":"venue"
},
  "geometry": {"coordinates":[-83.98527300000001,43.414316],"type":"Point"}
}