{
  "type": "Feature",
  "properties": {
    "iso:country":"US",
    "sg:address":"9387 US Hwy 31",
    "sg:city":"Berrien Springs",
    "sg:classifiers":[
        {
            "category":"Building & Trades",
            "subcategory":"Construction",
            "type":"Services"
        }
    ],
    "sg:phone":"+1 269 471 3756",
    "sg:postcode":"49103",
    "sg:province":"MI",
    "sg:tags":[
        "hanging",
        "contractor"
    ],
    "wof:name":"Traditional Painting",
    "wof:placetype":"venue"
},
  "geometry": {"coordinates":[-86.33189400000001,41.94965],"type":"Point"}
}