{
  "type": "Feature",
  "properties": {
    "iso:country":"US",
    "sg:address":"227 Silver Lake Rd",
    "sg:city":"Linden",
    "sg:classifiers":[
        {
            "category":"Fast Food",
            "type":"Food & Drink"
        },
        {
            "category":"Restaurant",
            "type":"Food & Drink"
        }
    ],
    "sg:phone":"+1 810 750 0200",
    "sg:postcode":"48451",
    "sg:province":"MI",
    "sg:tags":[
        "take",
        "pizza"
    ],
    "wof:name":"Cottage Inn Pizza",
    "wof:placetype":"venue"
},
  "geometry": {"coordinates":[-83.773595,42.813321],"type":"Point"}
}