{
  "type": "Feature",
  "properties": {
    "iso:country":"US",
    "sg:address":"800 Park St",
    "sg:city":"St Joseph",
    "sg:classifiers":[
        {
            "category":"Building & Trades",
            "subcategory":"Construction",
            "type":"Services"
        }
    ],
    "sg:phone":"+1 269 468 3847",
    "sg:postcode":"49085",
    "sg:province":"MI",
    "sg:tags":[
        "siding",
        "contractor"
    ],
    "wof:name":"Steven M Jones Construction",
    "wof:placetype":"venue"
},
  "geometry": {"coordinates":[-86.481647,42.10403],"type":"Point"}
}