{
  "type": "Feature",
  "properties": {
    "iso:country":"US",
    "sg:address":"24502 Campbell Ave",
    "sg:city":"Warren",
    "sg:classifiers":[
        {
            "category":"Organizations",
            "subcategory":"Religious Organization",
            "type":"Services"
        }
    ],
    "sg:phone":"+1 586 427 4455",
    "sg:postcode":"48089",
    "sg:province":"MI",
    "sg:tags":[
        "church"
    ],
    "wof:name":"Power Of Faith Pentecostal Chr",
    "wof:placetype":"venue"
},
  "geometry": {"coordinates":[-83.01345000000001,42.477707],"type":"Point"}
}