{
  "type": "Feature",
  "properties": {
    "iso:country":"US",
    "sg:address":"1869 Christy Ct",
    "sg:city":"Rochester Hills",
    "sg:classifiers":[
        {
            "category":"Wholesale",
            "subcategory":"Electrical",
            "type":"Manufacturing & Wholesale Goods"
        }
    ],
    "sg:phone":"+1 248 652 4500",
    "sg:postcode":"48309",
    "sg:province":"MI",
    "sg:tags":[
        "electric"
    ],
    "wof:name":"Engineered Controls",
    "wof:placetype":"venue"
},
  "geometry": {"coordinates":[-83.166556,42.653389],"type":"Point"}
}