{
  "type": "Feature",
  "properties": {
    "iso:country":"US",
    "sg:address":"14500 Hall Rd.",
    "sg:city":"Sterling Heights",
    "sg:classifiers":[
        {
            "category":"Community Center",
            "type":"Public Place"
        }
    ],
    "sg:phone":"+1 810 247 2700",
    "sg:postcode":"48313",
    "sg:province":"MI",
    "sg:tags":[
        "medical"
    ],
    "sg:website":"www.henryfordhealth.org",
    "wof:name":"Henry Ford Medical Center",
    "wof:placetype":"venue"
},
  "geometry": {"coordinates":[-82.981183,42.626162],"type":"Point"}
}