{
  "type": "Feature",
  "properties": {
    "iso:country":"US",
    "sg:address":"1200 S Carney Dr",
    "sg:city":"St Clair",
    "sg:classifiers":[
        {
            "category":"Autos & Motor Vehicles",
            "subcategory":"Automobile Sales",
            "type":"Retail Goods"
        }
    ],
    "sg:phone":"+1 810 329 6601",
    "sg:postcode":"48079",
    "sg:province":"MI",
    "sg:tags":[
        "car",
        "dealer"
    ],
    "wof:name":"Bill Mac Donald Ford",
    "wof:placetype":"venue"
},
  "geometry": {"coordinates":[-82.505285,42.817491],"type":"Point"}
}