{
  "type": "Feature",
  "properties": {
    "iso:country":"US",
    "sg:address":"17056 Ferris St",
    "sg:city":"Grand Haven",
    "sg:classifiers":[
        {
            "category":"Insurance",
            "subcategory":"Life Insurance",
            "type":"Services"
        }
    ],
    "sg:phone":"+1 616 842 7038",
    "sg:postcode":"49417",
    "sg:province":"MI",
    "sg:tags":[
        "carrier"
    ],
    "wof:name":"Charles E Westra Agency",
    "wof:placetype":"venue"
},
  "geometry": {"coordinates":[-86.21100800000001,43.008501],"type":"Point"}
}