{
  "type": "Feature",
  "properties": {
    "iso:country":"US",
    "sg:address":"29402 Northwestern Hwy",
    "sg:city":"Southfield",
    "sg:classifiers":[
        {
            "category":"Personal",
            "subcategory":"Beauty Salon",
            "type":"Services"
        }
    ],
    "sg:phone":"+1 248 351 9094",
    "sg:postcode":"48034",
    "sg:province":"MI",
    "sg:tags":[
        "manicuring"
    ],
    "wof:name":"Mo Treses",
    "wof:placetype":"venue"
},
  "geometry": {"coordinates":[-83.314183,42.504169],"type":"Point"}
}