{
  "type": "Feature",
  "properties": {
    "iso:country":"US",
    "sg:address":"322 Virginia Ave",
    "sg:city":"Ann Arbor",
    "sg:classifiers":[
        {
            "category":"Professional",
            "subcategory":"Computer Services",
            "type":"Services"
        }
    ],
    "sg:phone":"+1 734 668 6379",
    "sg:postcode":"48103",
    "sg:province":"MI",
    "sg:tags":[
        "related"
    ],
    "wof:name":"Combo Computer Consulting",
    "wof:placetype":"venue"
},
  "geometry": {"coordinates":[-83.767684,42.279324],"type":"Point"}
}