{
  "type": "Feature",
  "properties": {
    "iso:country":"US",
    "sg:address":"5501 W Mason Rd",
    "sg:city":"Fowlerville",
    "sg:classifiers":[
        {
            "category":"Building & Trades",
            "subcategory":"Construction",
            "type":"Services"
        }
    ],
    "sg:phone":"+1 517 545 9365",
    "sg:postcode":"48836",
    "sg:province":"MI",
    "sg:tags":[
        "general",
        "contractor"
    ],
    "wof:name":"Nadeau Construction & Concrete",
    "wof:placetype":"venue"
},
  "geometry": {"coordinates":[-84.020498,42.599464],"type":"Point"}
}