{
  "type": "Feature",
  "properties": {
    "iso:country":"US",
    "sg:address":"10020 Seyforth Rd",
    "sg:city":"Silverwood",
    "sg:classifiers":[
        {
            "category":"Retail",
            "subcategory":"Laundry & Dry Cleaning",
            "type":"Services"
        }
    ],
    "sg:phone":"+1 989 761 7799",
    "sg:postcode":"48760",
    "sg:province":"MI",
    "wof:name":"Davis Cleaning Co",
    "wof:placetype":"venue"
},
  "geometry": {"coordinates":[-83.25769099999999,43.324325],"type":"Point"}
}