{
  "type": "Feature",
  "properties": {
    "iso:country":"US",
    "sg:address":"7374 Woodlore Dr",
    "sg:city":"West Bloomfield",
    "sg:classifiers":[
        {
            "category":"Professional",
            "subcategory":"Research",
            "type":"Services"
        }
    ],
    "sg:phone":"+1 248 926 9614",
    "sg:postcode":"48323",
    "sg:province":"MI",
    "sg:tags":[
        "organization",
        "noncommercial"
    ],
    "wof:name":"Adam J Milatz Foundation",
    "wof:placetype":"venue"
},
  "geometry": {"coordinates":[-83.429892,42.568468],"type":"Point"}
}