{
  "type": "Feature",
  "properties": {
    "iso:country":"US",
    "sg:address":"1855 Northfield Dr",
    "sg:city":"Rochester Hills",
    "sg:classifiers":[
        {
            "category":"Recreation",
            "type":"Entertainment"
        }
    ],
    "sg:phone":"+1 248 844 1386",
    "sg:postcode":"48309",
    "sg:province":"MI",
    "sg:tags":[
        "amusement"
    ],
    "wof:name":"Sports Advantage Inc",
    "wof:placetype":"venue"
},
  "geometry": {"coordinates":[-83.167222,42.638525],"type":"Point"}
}