{
  "type": "Feature",
  "properties": {
    "iso:country":"US",
    "sg:address":"2476 Ashwood Dr",
    "sg:city":"Flint",
    "sg:classifiers":[
        {
            "category":"Professional",
            "subcategory":"Employment Agencies",
            "type":"Services"
        }
    ],
    "sg:phone":"+1 810 732 5147",
    "sg:postcode":"48504",
    "sg:province":"MI",
    "sg:tags":[
        "opportunity"
    ],
    "wof:name":"Teletemps",
    "wof:placetype":"venue"
},
  "geometry": {"coordinates":[-83.74494799999999,43.043464],"type":"Point"}
}