{
  "type": "Feature",
  "properties": {
    "iso:country":"US",
    "sg:address":"4031 Edmonds Rd",
    "sg:city":"Battle Creek",
    "sg:classifiers":[
        {
            "category":"Building & Trades",
            "subcategory":"Landscaping Services",
            "type":"Services"
        }
    ],
    "sg:phone":"+1 269 964 0099",
    "sg:postcode":"49017",
    "sg:province":"MI",
    "sg:tags":[
        "landscape",
        "contractor"
    ],
    "wof:name":"Mark WILK Landscape Inc",
    "wof:placetype":"venue"
},
  "geometry": {"coordinates":[-85.21387799999999,42.395257],"type":"Point"}
}