{
  "type": "Feature",
  "properties": {
    "iso:country":"US",
    "sg:address":"2745 Birchcrest Dr SE",
    "sg:city":"Grand Rapids",
    "sg:classifiers":[
        {
            "category":"Real Estate",
            "subcategory":"Real Estate Operator",
            "type":"Services"
        }
    ],
    "sg:phone":"+1 616 949 2760",
    "sg:postcode":"49506",
    "sg:province":"MI",
    "sg:tags":[
        "apartment",
        "complex"
    ],
    "wof:name":"Viewpoint Apartments",
    "wof:placetype":"venue"
},
  "geometry": {"coordinates":[-85.61100500000001,42.912807],"type":"Point"}
}