{
  "type": "Feature",
  "properties": {
    "iso:country":"US",
    "sg:address":"310 Burr St",
    "sg:city":"Battle Creek",
    "sg:classifiers":[
        {
            "category":"Building & Trades",
            "subcategory":"Pest Control",
            "type":"Services"
        }
    ],
    "sg:phone":"+1 800 305 0205",
    "sg:postcode":"49015",
    "sg:province":"MI",
    "wof:name":"J & S Sanitation",
    "wof:placetype":"venue"
},
  "geometry": {"coordinates":[-85.210143,42.310197],"type":"Point"}
}