{
  "type": "Feature",
  "properties": {
    "iso:country":"US",
    "sg:address":"1 W Carleton Rd",
    "sg:city":"Hillsdale",
    "sg:classifiers":[
        {
            "category":"Banks & Credit Unions",
            "subcategory":"Bank",
            "type":"Services"
        }
    ],
    "sg:phone":"+1 517 439 1790",
    "sg:postcode":"49242",
    "sg:province":"MI",
    "wof:name":"Monarch Community Bank",
    "wof:placetype":"venue"
},
  "geometry": {"coordinates":[-84.636185,41.925295],"type":"Point"}
}