{
  "type": "Feature",
  "properties": {
    "iso:country":"US",
    "sg:address":"2223 Packard St",
    "sg:city":"Ann Arbor",
    "sg:classifiers":[
        {
            "category":"Social Services",
            "type":"Services"
        }
    ],
    "sg:phone":"+1 734 668 1040",
    "sg:postcode":"48104",
    "sg:province":"MI",
    "wof:name":"Eileen Bond Acsw",
    "wof:placetype":"venue"
},
  "geometry": {"coordinates":[-83.725751,42.255068],"type":"Point"}
}