{
  "type": "Feature",
  "properties": {
    "iso:country":"US",
    "sg:address":"280 E Square Lake Rd",
    "sg:city":"Troy",
    "sg:classifiers":[
        {
            "category":"Education",
            "subcategory":"School",
            "type":"Public Place"
        },
        {
            "category":"Organizations",
            "subcategory":"Religious Organization",
            "type":"Services"
        }
    ],
    "sg:phone":"+1 248 879 1310",
    "sg:postcode":"48085",
    "sg:province":"MI",
    "wof:name":"St Elizabeth Ann Seton Church",
    "wof:placetype":"venue"
},
  "geometry": {"coordinates":[-83.145302,42.6064],"type":"Point"}
}