{
  "type": "Feature",
  "properties": {
    "iso:country":"US",
    "sg:address":"380 N Old Woodward Ave Ste 120",
    "sg:city":"Birmingham",
    "sg:classifiers":[
        {
            "category":"Professional",
            "subcategory":"Lawyer & Legal Services",
            "type":"Services"
        }
    ],
    "sg:phone":"+1 248 646 0888",
    "sg:postcode":"48009",
    "sg:province":"MI",
    "sg:website":"www.steinhardtpesickandcohen.com",
    "wof:name":"Steinhardt Pesick & Cohen",
    "wof:placetype":"venue"
},
  "geometry": {"coordinates":[-83.21633199999999,42.549352],"type":"Point"}
}