{
  "type": "Feature",
  "properties": {
    "iso:country":"US",
    "sg:address":"34639 Whittaker St",
    "sg:city":"Clinton Twp",
    "sg:classifiers":[
        {
            "category":"Professional",
            "subcategory":"Business Services",
            "type":"Services"
        }
    ],
    "sg:phone":"+1 586 792 8788",
    "sg:postcode":"48035",
    "sg:province":"MI",
    "sg:tags":[
        "automobile",
        "appraiser"
    ],
    "wof:name":"Wreckamended Appraisal Svc",
    "wof:placetype":"venue"
},
  "geometry": {"coordinates":[-82.92231200000001,42.55109],"type":"Point"}
}