{
  "type": "Feature",
  "properties": {
    "iso:country":"US",
    "sg:address":"412 W 24th St",
    "sg:city":"Holland",
    "sg:classifiers":[
        {
            "category":"Organizations",
            "subcategory":"Labor Organization",
            "type":"Services"
        }
    ],
    "sg:phone":"+1 616 396 1530",
    "sg:postcode":"49423",
    "sg:province":"MI",
    "wof:name":"Communications Workers-America",
    "wof:placetype":"venue"
},
  "geometry": {"coordinates":[-86.126024,42.775602],"type":"Point"}
}