{
  "type": "Feature",
  "properties": {
    "iso:country":"US",
    "sg:address":"1888 Spaulding Rd",
    "sg:city":"Monroe",
    "sg:classifiers":[
        {
            "category":"Insurance",
            "subcategory":"Insurance Agent",
            "type":"Services"
        }
    ],
    "sg:phone":"+1 734 241 9483",
    "sg:postcode":"48162",
    "sg:province":"MI",
    "wof:name":"Mike OBryan Insurance",
    "wof:placetype":"venue"
},
  "geometry": {"coordinates":[-83.367031,41.934515],"type":"Point"}
}