{
  "type": "Feature",
  "properties": {
    "iso:country":"US",
    "sg:address":"3618 W Miller Rd",
    "sg:city":"Lansing",
    "sg:classifiers":[
        {
            "category":"Real Estate",
            "subcategory":"Real Estate Operator",
            "type":"Services"
        }
    ],
    "sg:phone":"+1 517 882 3518",
    "sg:postcode":"48911",
    "sg:province":"MI",
    "sg:tags":[
        "apartment"
    ],
    "wof:name":"Pinebrook Manor",
    "wof:placetype":"venue"
},
  "geometry": {"coordinates":[-84.60301800000001,42.669341],"type":"Point"}
}