{
  "type": "Feature",
  "properties": {
    "iso:country":"US",
    "sg:address":"9834 S Clearwater St",
    "sg:city":"Grant",
    "sg:classifiers":[
        {
            "category":"Organizations",
            "subcategory":"Religious Organization",
            "type":"Services"
        }
    ],
    "sg:phone":"+1 231 834 1488",
    "sg:postcode":"49327",
    "sg:province":"MI",
    "wof:name":"Lighted Pathway Ministries",
    "wof:placetype":"venue"
},
  "geometry": {"coordinates":[-85.760735,43.376333],"type":"Point"}
}