{
  "type": "Feature",
  "properties": {
    "iso:country":"US",
    "sg:address":"2901 Rochester St",
    "sg:city":"Detroit",
    "sg:classifiers":[
        {
            "category":"Organizations",
            "subcategory":"Religious Organization",
            "type":"Services"
        }
    ],
    "sg:phone":"+1 313 361 1110",
    "sg:postcode":"48206",
    "sg:province":"MI",
    "sg:tags":[
        "church"
    ],
    "wof:name":"Bethlehem Temple",
    "wof:placetype":"venue"
},
  "geometry": {"coordinates":[-83.116918,42.375416],"type":"Point"}
}