{
  "type": "Feature",
  "properties": {
    "iso:country":"US",
    "sg:address":"629 E 3rd St",
    "sg:city":"Royal Oak",
    "sg:classifiers":[
        {
            "category":"Building & Trades",
            "subcategory":"Electrical",
            "type":"Services"
        }
    ],
    "sg:phone":"+1 248 544 4777",
    "sg:postcode":"48067",
    "sg:province":"MI",
    "sg:tags":[
        "electrician"
    ],
    "wof:name":"Dynamic Electric Inc",
    "wof:placetype":"venue"
},
  "geometry": {"coordinates":[-83.138013,42.488206],"type":"Point"}
}