{
  "type": "Feature",
  "properties": {
    "iso:country":"US",
    "sg:address":"308 W 12th St",
    "sg:city":"Holland",
    "sg:classifiers":[
        {
            "category":"Social Services",
            "subcategory":"Child Care",
            "type":"Services"
        }
    ],
    "sg:phone":"+1 616 392 7690",
    "sg:postcode":"49423",
    "sg:province":"MI",
    "sg:tags":[
        "home",
        "day"
    ],
    "wof:name":"Boeve Rozalyn",
    "wof:placetype":"venue"
},
  "geometry": {"coordinates":[-86.12282399999999,42.786456],"type":"Point"}
}