{
  "type": "Feature",
  "properties": {
    "iso:country":"US",
    "sg:address":"1531 E Larned St",
    "sg:city":"Detroit",
    "sg:classifiers":[
        {
            "category":"Real Estate",
            "subcategory":"Real Estate Operator",
            "type":"Services"
        }
    ],
    "sg:phone":"+1 313 259 4450",
    "sg:postcode":"48207",
    "sg:province":"MI",
    "sg:tags":[
        "apartment"
    ],
    "wof:name":"Orleans East Apartments",
    "wof:placetype":"venue"
},
  "geometry": {"coordinates":[-83.0308,42.335999],"type":"Point"}
}