{
  "type": "Feature",
  "properties": {
    "iso:country":"US",
    "sg:address":"1924 Birchwood Dr",
    "sg:city":"Troy",
    "sg:classifiers":[
        {
            "category":"Utilities",
            "type":"Services"
        }
    ],
    "sg:phone":"+1 248 680 1840",
    "sg:postcode":"48083",
    "sg:province":"MI",
    "sg:tags":[
        "sweeping"
    ],
    "wof:name":"American Power Sweeping",
    "wof:placetype":"venue"
},
  "geometry": {"coordinates":[-83.108172,42.550721],"type":"Point"}
}