{
  "type": "Feature",
  "properties": {
    "iso:country":"US",
    "sg:address":"189 W Garfield Ave",
    "sg:city":"Coldwater",
    "sg:classifiers":[
        {
            "category":"Wholesale",
            "subcategory":"Groceries",
            "type":"Manufacturing & Wholesale Goods"
        }
    ],
    "sg:phone":"+1 517 278 2370",
    "sg:postcode":"49036",
    "sg:province":"MI",
    "sg:tags":[
        "baker"
    ],
    "wof:name":"Coldwater Bakery Inc",
    "wof:placetype":"venue"
},
  "geometry": {"coordinates":[-85.01376,41.927174],"type":"Point"}
}