{
  "type": "Feature",
  "properties": {
    "iso:country":"US",
    "sg:address":"9252 Yorkshire Dr",
    "sg:city":"Saline",
    "sg:classifiers":[
        {
            "category":"Professional",
            "subcategory":"Computer Services",
            "type":"Services"
        }
    ],
    "sg:phone":"+1 734 944 1206",
    "sg:postcode":"48176",
    "sg:province":"MI",
    "sg:tags":[
        "related"
    ],
    "wof:name":"Health Data Management",
    "wof:placetype":"venue"
},
  "geometry": {"coordinates":[-83.74258500000001,42.150981],"type":"Point"}
}