{
  "type": "Feature",
  "properties": {
    "iso:country":"US",
    "sg:address":"1100 N Opdyke Rd",
    "sg:city":"Auburn Hills",
    "sg:classifiers":[
        {
            "category":"Professional",
            "subcategory":"Management & Consulting",
            "type":"Services"
        }
    ],
    "sg:phone":"+1 248 340 6191",
    "sg:postcode":"48326",
    "sg:province":"MI",
    "sg:tags":[
        "public",
        "relations"
    ],
    "wof:name":"Don Rose Associates",
    "wof:placetype":"venue"
},
  "geometry": {"coordinates":[-83.245664,42.658319],"type":"Point"}
}