{
  "type": "Feature",
  "properties": {
    "iso:country":"US",
    "sg:address":"6900 Platt Rd",
    "sg:city":"Ypsilanti",
    "sg:classifiers":[
        {
            "category":"Home & Garden",
            "subcategory":"Building Materials",
            "type":"Retail Goods"
        }
    ],
    "sg:phone":"+1 734 665 5576",
    "sg:postcode":"48197",
    "sg:province":"MI",
    "wof:name":"Elite Garage Door Sales",
    "wof:placetype":"venue"
},
  "geometry": {"coordinates":[-83.698874,42.190103],"type":"Point"}
}