{
  "type": "Feature",
  "properties": {
    "iso:country":"US",
    "sg:address":"1410 Wadhams Rd",
    "sg:city":"Smiths Creek",
    "sg:classifiers":[
        {
            "category":"Social Services",
            "subcategory":"Adult Care",
            "type":"Services"
        }
    ],
    "sg:phone":"+1 810 367 3637",
    "sg:postcode":"48074",
    "sg:province":"MI",
    "sg:tags":[
        "residential"
    ],
    "wof:name":"Gails Living",
    "wof:placetype":"venue"
},
  "geometry": {"coordinates":[-82.542175,42.942248],"type":"Point"}
}