{
  "type": "Feature",
  "properties": {
    "iso:country":"US",
    "sg:address":"5606 S Occidental Hwy",
    "sg:city":"Tecumseh",
    "sg:classifiers":[
        {
            "category":"Building & Trades",
            "subcategory":"Construction",
            "type":"Services"
        }
    ],
    "sg:phone":"+1 517 423 4064",
    "sg:postcode":"49286",
    "sg:province":"MI",
    "sg:tags":[
        "fence",
        "contractor"
    ],
    "wof:name":"Adrian Fence Co",
    "wof:placetype":"venue"
},
  "geometry": {"coordinates":[-83.965593,41.973514],"type":"Point"}
}