{
  "type": "Feature",
  "properties": {
    "iso:country":"US",
    "sg:address":"429 W Garfield Ave",
    "sg:city":"Hazel Park",
    "sg:classifiers":[
        {
            "category":"Professional",
            "subcategory":"Business Services",
            "type":"Services"
        }
    ],
    "sg:phone":"+1 248 548 0357",
    "sg:postcode":"48030",
    "sg:province":"MI",
    "wof:name":"WD Design & Drafting Svc",
    "wof:placetype":"venue"
},
  "geometry": {"coordinates":[-83.10978799999999,42.471554],"type":"Point"}
}