{
  "type": "Feature",
  "properties": {
    "iso:country":"US",
    "sg:address":"11556 Dixie Hwy",
    "sg:city":"Birch Run",
    "sg:classifiers":[
        {
            "category":"Building & Trades",
            "subcategory":"Construction",
            "type":"Services"
        }
    ],
    "sg:phone":"+1 989 624 9000",
    "sg:postcode":"48415",
    "sg:province":"MI",
    "sg:tags":[
        "resurfacing",
        "laying",
        "refinishing",
        "floor"
    ],
    "wof:name":"Estate Hardwood Floors",
    "wof:placetype":"venue"
},
  "geometry": {"coordinates":[-83.772958,43.254875],"type":"Point"}
}