{
  "type": "Feature",
  "properties": {
    "iso:country":"US",
    "sg:address":"42310 Hayes Rd",
    "sg:city":"Clinton Township",
    "sg:classifiers":[
        {
            "category":"Personal",
            "subcategory":"Nail Salon",
            "type":"Services"
        }
    ],
    "sg:phone":"+1 586 412 6642",
    "sg:postcode":"48038",
    "sg:province":"MI",
    "wof:name":"Luann's Nails",
    "wof:placetype":"venue"
},
  "geometry": {"coordinates":[-82.97229799999999,42.606899],"type":"Point"}
}