{
  "type": "Feature",
  "properties": {
    "iso:country":"US",
    "sg:address":"41468 Village Green Blvd W",
    "sg:city":"Canton",
    "sg:classifiers":[
        {
            "category":"Professional",
            "subcategory":"Computer Services",
            "type":"Services"
        }
    ],
    "sg:phone":"+1 734 844 8509",
    "sg:postcode":"48187",
    "sg:province":"MI",
    "sg:tags":[
        "datum"
    ],
    "wof:name":"Kapow Computing",
    "wof:placetype":"venue"
},
  "geometry": {"coordinates":[-83.45094,42.312049],"type":"Point"}
}