{
  "type": "Feature",
  "properties": {
    "iso:country":"US",
    "sg:address":"2210 Wilbur Ave",
    "sg:city":"Kalamazoo",
    "sg:classifiers":[
        {
            "category":"Social Services",
            "subcategory":"Child Care",
            "type":"Services"
        }
    ],
    "sg:phone":"+1 269 387 2277",
    "sg:postcode":"49006",
    "sg:province":"MI",
    "wof:name":"Children's Place Learning Ctr",
    "wof:placetype":"venue"
},
  "geometry": {"coordinates":[-85.617813,42.284362],"type":"Point"}
}