{
  "type": "Feature",
  "properties": {
    "iso:country":"US",
    "sg:address":"30519 Ford Rd",
    "sg:city":"Garden City",
    "sg:classifiers":[
        {
            "category":"Professional",
            "subcategory":"Research",
            "type":"Services"
        }
    ],
    "sg:phone":"+1 734 421 2690",
    "sg:postcode":"48135",
    "sg:province":"MI",
    "sg:tags":[
        "nonphysical",
        "commercial"
    ],
    "wof:name":"National Inst Common Sense",
    "wof:placetype":"venue"
},
  "geometry": {"coordinates":[-83.343395,42.325225],"type":"Point"}
}