{
  "type": "Feature",
  "properties": {
    "iso:country":"US",
    "sg:address":"11109 N Manistee County Line Rd",
    "sg:city":"Benzonia",
    "sg:classifiers":[
        {
            "category":"Farming",
            "subcategory":"Livestock Farm",
            "type":"Manufacturing & Wholesale Goods"
        }
    ],
    "sg:phone":"+1 231 882 4293",
    "sg:postcode":"49616",
    "sg:province":"MI",
    "sg:tags":[
        "equine"
    ],
    "wof:name":"Vernon Merrill",
    "wof:placetype":"venue"
},
  "geometry": {"coordinates":[-86.078974,44.515145],"type":"Point"}
}