{
  "type": "Feature",
  "properties": {
    "iso:country":"US",
    "sg:address":"4084 John R Rd",
    "sg:city":"Troy",
    "sg:classifiers":[
        {
            "category":"Banks & Credit Unions",
            "subcategory":"Financial Services",
            "type":"Services"
        }
    ],
    "sg:phone":"+1 248 989 8900",
    "sg:postcode":"48085",
    "sg:province":"MI",
    "sg:tags":[
        "broker",
        "mortgage"
    ],
    "sg:website":"www.genuinemortgagegroup.com",
    "wof:name":"Genuine Mortgage Group",
    "wof:placetype":"venue"
},
  "geometry": {"coordinates":[-83.108738,42.57965],"type":"Point"}
}