{
  "type": "Feature",
  "properties": {
    "iso:country":"US",
    "sg:address":"6814 Hardwood Ct",
    "sg:city":"Harbor Springs",
    "sg:classifiers":[
        {
            "category":"Manufacturing",
            "subcategory":"Printing",
            "type":"Manufacturing & Wholesale Goods"
        }
    ],
    "sg:phone":"+1 231 526 8091",
    "sg:postcode":"49740",
    "sg:province":"MI",
    "sg:tags":[
        "publishing"
    ],
    "wof:name":"Information Press",
    "wof:placetype":"venue"
},
  "geometry": {"coordinates":[-84.917597,45.452694],"type":"Point"}
}