{
  "type": "Feature",
  "properties": {
    "iso:country":"US",
    "sg:address":"6150 Country Ridge Dr",
    "sg:city":"Troy",
    "sg:classifiers":[
        {
            "category":"Social Services",
            "subcategory":"Child Care",
            "type":"Services"
        }
    ],
    "sg:phone":"+1 248 879 5150",
    "sg:postcode":"48098",
    "sg:province":"MI",
    "sg:tags":[
        "day"
    ],
    "wof:name":"Sunshine Day Care",
    "wof:placetype":"venue"
},
  "geometry": {"coordinates":[-83.187085,42.606448],"type":"Point"}
}