{
  "type": "Feature",
  "properties": {
    "iso:country":"US",
    "sg:address":"215 Maple Island Rd",
    "sg:city":"Muskegon",
    "sg:classifiers":[
        {
            "category":"Building & Trades",
            "subcategory":"Landscaping Services",
            "type":"Services"
        }
    ],
    "sg:phone":"+1 231 788 4112",
    "sg:postcode":"49442",
    "sg:province":"MI",
    "sg:tags":[
        "tree"
    ],
    "wof:name":"Workman Tree Svc & Excavating",
    "wof:placetype":"venue"
},
  "geometry": {"coordinates":[-86.067948,43.249184],"type":"Point"}
}