{
  "type": "Feature",
  "properties": {
    "iso:country":"US",
    "sg:address":"3800 Puritan St",
    "sg:city":"Detroit",
    "sg:classifiers":[
        {
            "category":"Organizations",
            "subcategory":"Non-profit Organization",
            "type":"Services"
        }
    ],
    "sg:phone":"+1 313 341 9088",
    "sg:postcode":"48238",
    "sg:province":"MI",
    "sg:tags":[
        "social"
    ],
    "wof:name":"North Star Community Dev",
    "wof:placetype":"venue"
},
  "geometry": {"coordinates":[-83.136364,42.410057],"type":"Point"}
}