{
  "type": "Feature",
  "properties": {
    "iso:country":"US",
    "sg:address":"66 Macomb Pl",
    "sg:city":"Mount Clemens",
    "sg:classifiers":[
        {
            "category":"Shopping",
            "subcategory":"Jewelry",
            "type":"Retail Goods"
        }
    ],
    "sg:phone":"+1 586 468 6130",
    "sg:postcode":"48043",
    "sg:province":"MI",
    "sg:tags":[
        "jeweler"
    ],
    "wof:name":"Nevin Thomas Jewelers",
    "wof:placetype":"venue"
},
  "geometry": {"coordinates":[-82.878502,42.598499],"type":"Point"}
}