{
  "type": "Feature",
  "properties": {
    "iso:country":"US",
    "sg:address":"2363 30th St SW",
    "sg:city":"Grand Rapids",
    "sg:classifiers":[
        {
            "category":"Social Services",
            "subcategory":"Child Care",
            "type":"Services"
        }
    ],
    "sg:phone":"+1 616 534 9597",
    "sg:postcode":"49519",
    "sg:province":"MI",
    "sg:tags":[
        "day"
    ],
    "wof:name":"Sandras Daycare",
    "wof:placetype":"venue"
},
  "geometry": {"coordinates":[-85.72359899999999,42.910259],"type":"Point"}
}