{
  "type": "Feature",
  "properties": {
    "iso:country":"US",
    "sg:address":"601 N Mechanic St",
    "sg:city":"Berrien Springs",
    "sg:classifiers":[
        {
            "category":"Social Services",
            "subcategory":"Child Care",
            "type":"Services"
        }
    ],
    "sg:phone":"+1 269 471 9313",
    "sg:postcode":"49103",
    "sg:province":"MI",
    "sg:tags":[
        "day"
    ],
    "wof:name":"Tiny Tots Daycare",
    "wof:placetype":"venue"
},
  "geometry": {"coordinates":[-86.34281799999999,41.953658],"type":"Point"}
}