{
  "type": "Feature",
  "properties": {
    "iso:country":"US",
    "sg:address":"19341 Allen Rd",
    "sg:city":"Trenton",
    "sg:classifiers":[
        {
            "category":"Health Services",
            "subcategory":"Nursing And Care Facility",
            "type":"Services"
        }
    ],
    "sg:phone":"+1 734 675 2700",
    "sg:postcode":"48183",
    "sg:province":"MI",
    "wof:name":"Brownstowns Forest Vw Asstd",
    "wof:placetype":"venue"
},
  "geometry": {"coordinates":[-83.22712199999999,42.169623],"type":"Point"}
}