{
  "type": "Feature",
  "properties": {
    "iso:country":"US",
    "sg:address":"3561 Mount Elliott St",
    "sg:city":"Detroit",
    "sg:classifiers":[
        {
            "category":"Building & Trades",
            "subcategory":"Locksmith",
            "type":"Services"
        }
    ],
    "sg:phone":"+1 313 263 3706",
    "sg:postcode":"48207",
    "sg:province":"MI",
    "sg:tags":[
        "key"
    ],
    "wof:name":"24 Hour Emergency Locksmith",
    "wof:placetype":"venue"
},
  "geometry": {"coordinates":[-83.021585,42.360925],"type":"Point"}
}