{
  "type": "Feature",
  "properties": {
    "iso:country":"US",
    "sg:address":"4080 W Maple Rd",
    "sg:city":"Bloomfield Hills",
    "sg:classifiers":[
        {
            "category":"Insurance",
            "subcategory":"Insurance Agent",
            "type":"Services"
        }
    ],
    "sg:phone":"+1 248 644 8904",
    "sg:postcode":"48301",
    "sg:province":"MI",
    "wof:name":"Bates Alvin Jr Agency Inc",
    "wof:placetype":"venue"
},
  "geometry": {"coordinates":[-83.282786,42.544941],"type":"Point"}
}