{
  "type": "Feature",
  "properties": {
    "iso:country":"US",
    "sg:address":"835 Willard Ave",
    "sg:city":"Rochester",
    "sg:classifiers":[
        {
            "category":"Retail",
            "subcategory":"Repair Shop",
            "type":"Services"
        }
    ],
    "sg:phone":"+1 248 652 2236",
    "sg:postcode":"48307",
    "sg:province":"MI",
    "wof:name":"Joanne Gartland",
    "wof:placetype":"venue"
},
  "geometry": {"coordinates":[-83.11705499999999,42.667112],"type":"Point"}
}