{
  "type": "Feature",
  "properties": {
    "iso:country":"US",
    "sg:address":"340 N Main St",
    "sg:city":"Plymouth",
    "sg:classifiers":[
        {
            "category":"Manufacturing",
            "subcategory":"Metals",
            "type":"Manufacturing & Wholesale Goods"
        }
    ],
    "sg:phone":"+1 734 455 1090",
    "sg:postcode":"48170",
    "sg:province":"MI",
    "sg:tags":[
        "blast",
        "furnace",
        "works"
    ],
    "wof:name":"Nucor Corporation",
    "wof:placetype":"venue"
},
  "geometry": {"coordinates":[-83.463572,42.374864],"type":"Point"}
}