{
  "type": "Feature",
  "properties": {
    "iso:country":"US",
    "sg:address":"33 Warner Rd",
    "sg:city":"Grosse Pointe",
    "sg:classifiers":[
        {
            "category":"Arts & Performance",
            "subcategory":"Theater",
            "type":"Entertainment"
        }
    ],
    "sg:phone":"+1 313 884 3210",
    "sg:postcode":"48236",
    "sg:province":"MI",
    "sg:tags":[
        "group"
    ],
    "wof:name":"Spangler Blues Productions",
    "wof:placetype":"venue"
},
  "geometry": {"coordinates":[-82.896091,42.391262],"type":"Point"}
}