{
  "type": "Feature",
  "properties": {
    "iso:country":"US",
    "sg:address":"2812 Broadmoor Dr",
    "sg:city":"Rochester Hills",
    "sg:classifiers":[
        {
            "category":"Shopping",
            "subcategory":"Optical Goods",
            "type":"Retail Goods"
        }
    ],
    "sg:phone":"+1 248 375 9170",
    "sg:postcode":"48309",
    "sg:province":"MI",
    "sg:tags":[
        "optician"
    ],
    "wof:name":"Mature Vision Care",
    "wof:placetype":"venue"
},
  "geometry": {"coordinates":[-83.190732,42.685981],"type":"Point"}
}