{
  "type": "Feature",
  "properties": {
    "iso:country":"US",
    "sg:address":"12901 Airport Rd",
    "sg:city":"Atlanta",
    "sg:classifiers":[
        {
            "category":"Autos & Motor Vehicles",
            "subcategory":"Auto Supplies",
            "type":"Retail Goods"
        }
    ],
    "sg:phone":"+1 989 785 4418",
    "sg:postcode":"49709",
    "sg:province":"MI",
    "wof:name":"Engleharts Used Auto Parts",
    "wof:placetype":"venue"
},
  "geometry": {"coordinates":[-84.135761,45.000024],"type":"Point"}
}