{
  "type": "Feature",
  "properties": {
    "iso:country":"US",
    "sg:address":"207 Misson Rd",
    "sg:city":"Sault Sainte Marie",
    "sg:classifiers":[
        {
            "category":"Restaurant",
            "type":"Food & Drink"
        }
    ],
    "sg:phone":"+1 906 248 3090",
    "sg:postcode":"49783",
    "sg:province":"MI",
    "sg:tags":[
        "lounge",
        "motel"
    ],
    "wof:name":"Willabees Rest Lounge & Mtl",
    "wof:placetype":"venue"
},
  "geometry": {"coordinates":[-84.310332,46.488232],"type":"Point"}
}