{
  "type": "Feature",
  "properties": {
    "iso:country":"US",
    "sg:address":"2500 Chicago Dr",
    "sg:city":"Hudsonville",
    "sg:classifiers":[
        {
            "category":"Retail",
            "subcategory":"Portrait Studio",
            "type":"Services"
        }
    ],
    "sg:phone":"+1 616 669 1755",
    "sg:postcode":"49426",
    "sg:province":"MI",
    "sg:tags":[
        "photographer"
    ],
    "wof:name":"John Dykstra Photography",
    "wof:placetype":"venue"
},
  "geometry": {"coordinates":[-85.849805,42.876856],"type":"Point"}
}