{
  "type": "Feature",
  "properties": {
    "iso:country":"US",
    "sg:address":"6215 US Hwy 2",
    "sg:city":"Naubinway",
    "sg:classifiers":[
        {
            "category":"Building & Trades",
            "subcategory":"Construction",
            "type":"Services"
        }
    ],
    "sg:phone":"+1 906 292 5510",
    "sg:postcode":"49762",
    "sg:province":"MI",
    "sg:tags":[
        "excavating",
        "contractor"
    ],
    "wof:name":"Bigelow Excavation",
    "wof:placetype":"venue"
},
  "geometry": {"coordinates":[-85.16134,46.056528],"type":"Point"}
}