{
  "type": "Feature",
  "properties": {
    "iso:country":"US",
    "sg:address":"280 S Center St",
    "sg:city":"Northville",
    "sg:classifiers":[
        {
            "category":"Building & Trades",
            "subcategory":"Construction",
            "type":"Services"
        }
    ],
    "sg:phone":"+1 248 449 5063",
    "sg:postcode":"48167",
    "sg:province":"MI",
    "sg:tags":[
        "contractor"
    ],
    "wof:name":"Douglas S Merriman",
    "wof:placetype":"venue"
},
  "geometry": {"coordinates":[-83.48309999999999,42.429622],"type":"Point"}
}