{
  "type": "Feature",
  "properties": {
    "iso:country":"US",
    "sg:address":"33878 Dequindre Rd",
    "sg:city":"Sterling Heights",
    "sg:classifiers":[
        {
            "category":"Food & Beverages",
            "subcategory":"Groceries & Convenience Stores",
            "type":"Retail Goods"
        }
    ],
    "sg:phone":"+1 586 274 1141",
    "sg:postcode":"48310",
    "sg:province":"MI",
    "wof:name":"India Mart",
    "wof:placetype":"venue"
},
  "geometry": {"coordinates":[-83.08730300000001,42.541],"type":"Point"}
}