{
  "type": "Feature",
  "properties": {
    "iso:country":"US",
    "sg:address":"5320 N Bahr Dr",
    "sg:city":"Irons",
    "sg:classifiers":[
        {
            "category":"Manufacturing",
            "subcategory":"Food",
            "type":"Manufacturing & Wholesale Goods"
        }
    ],
    "sg:phone":"+1 231 266 5137",
    "sg:postcode":"49644",
    "sg:province":"MI",
    "sg:tags":[
        "canned",
        "mfg"
    ],
    "wof:name":"Golden Fruit Co",
    "wof:placetype":"venue"
},
  "geometry": {"coordinates":[-85.97760100000001,44.066141],"type":"Point"}
}