{
  "type": "Feature",
  "properties": {
    "iso:country":"US",
    "sg:address":"600 11th St NW",
    "sg:city":"Grand Rapids",
    "sg:classifiers":[
        {
            "category":"Professional",
            "type":"Services"
        }
    ],
    "sg:phone":"+1 616 458 2426",
    "sg:postcode":"49504",
    "sg:province":"MI",
    "sg:tags":[
        "establishment"
    ],
    "wof:name":"Ridin High Inc",
    "wof:placetype":"venue"
},
  "geometry": {"coordinates":[-85.683065,42.981452],"type":"Point"}
}