{
  "type": "Feature",
  "properties": {
    "iso:country":"US",
    "sg:address":"11396 Whispering Pines Trl",
    "sg:city":"Fenton",
    "sg:classifiers":[
        {
            "category":"Professional",
            "subcategory":"Computer Services",
            "type":"Services"
        }
    ],
    "sg:phone":"+1 810 750 8658",
    "sg:postcode":"48430",
    "sg:province":"MI",
    "sg:tags":[
        "website",
        "design",
        "datum"
    ],
    "wof:name":"Creative Web Spinner Inc",
    "wof:placetype":"venue"
},
  "geometry": {"coordinates":[-83.74202699999999,42.780087],"type":"Point"}
}