{
  "type": "Feature",
  "properties": {
    "iso:country":"US",
    "sg:address":"2991 N Mason Rd",
    "sg:city":"Merrill",
    "sg:phone":"+1 989 842 5656",
    "sg:postcode":"48637",
    "sg:province":"MI",
    "sg:tags":[
        "farm",
        "corn",
        "soybean"
    ],
    "wof:name":"Brian Gulick",
    "wof:placetype":"venue"
},
  "geometry": {"coordinates":[-84.38969,43.328594],"type":"Point"}
}