{
  "type": "Feature",
  "properties": {
    "iso:country":"US",
    "sg:address":"3161 28th St SE",
    "sg:city":"Grand Rapids",
    "sg:classifiers":[
        {
            "category":"Manufacturing",
            "subcategory":"Printing",
            "type":"Manufacturing & Wholesale Goods"
        }
    ],
    "sg:phone":"+1 616 464 6050",
    "sg:postcode":"49512",
    "sg:province":"MI",
    "sg:tags":[
        "screen"
    ],
    "wof:name":"B T Fun Embroidery",
    "wof:placetype":"venue"
},
  "geometry": {"coordinates":[-85.58969999999999,42.912593],"type":"Point"}
}