{
  "type": "Feature",
  "properties": {
    "iso:country":"US",
    "sg:address":"31451 Cherry Hill Rd",
    "sg:city":"Westland",
    "sg:classifiers":[
        {
            "category":"Cinema",
            "subcategory":"Movie Rental",
            "type":"Entertainment"
        }
    ],
    "sg:phone":"+1 734 729 4314",
    "sg:postcode":"48186",
    "sg:province":"MI",
    "sg:tags":[
        "game",
        "video"
    ],
    "sg:website":"www.blockbuster.com",
    "wof:name":"Blockbuster Video",
    "wof:placetype":"venue"
},
  "geometry": {"coordinates":[-83.350098,42.310699],"type":"Point"}
}