{
  "type": "Feature",
  "properties": {
    "iso:country":"US",
    "sg:address":"4509 Lake St",
    "sg:city":"Bridgman",
    "sg:classifiers":[
        {
            "category":"Banks & Credit Unions",
            "subcategory":"Bank",
            "type":"Services"
        }
    ],
    "sg:phone":"+1 269 465 5500",
    "sg:postcode":"49106",
    "sg:province":"MI",
    "wof:name":"LA Salle Federal Savings Bank",
    "wof:placetype":"venue"
},
  "geometry": {"coordinates":[-86.563344,41.943007],"type":"Point"}
}