{
  "type": "Feature",
  "properties": {
    "iso:country":"US",
    "sg:address":"759 Boone Rd",
    "sg:city":"Quincy",
    "sg:classifiers":[
        {
            "category":"Professional",
            "subcategory":"Business Services",
            "type":"Services"
        }
    ],
    "sg:phone":"+1 517 639 3866",
    "sg:postcode":"49082",
    "sg:province":"MI",
    "wof:name":"J & D Enterprises",
    "wof:placetype":"venue"
},
  "geometry": {"coordinates":[-84.840779,41.998396],"type":"Point"}
}