{
  "type": "Feature",
  "properties": {
    "iso:country":"US",
    "sg:address":"59201 Preston Ct",
    "sg:city":"New Hudson",
    "sg:classifiers":[
        {
            "category":"Building & Trades",
            "subcategory":"Construction",
            "type":"Services"
        }
    ],
    "sg:phone":"+1 248 446 8672",
    "sg:postcode":"48165",
    "sg:province":"MI",
    "sg:tags":[
        "contractor"
    ],
    "wof:name":"Sartor Tile Co",
    "wof:placetype":"venue"
},
  "geometry": {"coordinates":[-83.636635,42.509848],"type":"Point"}
}