{
  "type": "Feature",
  "properties": {
    "iso:country":"US",
    "sg:address":"500 Whitehall Rd",
    "sg:city":"Muskegon",
    "sg:classifiers":[
        {
            "category":"Shopping",
            "subcategory":"Department Store",
            "type":"Retail Goods"
        }
    ],
    "sg:phone":"+1 231 719 8918",
    "sg:postcode":"49445",
    "sg:province":"MI",
    "sg:tags":[
        "shop"
    ],
    "wof:name":"Family Dollar Store",
    "wof:placetype":"venue"
},
  "geometry": {"coordinates":[-86.25182700000001,43.267478],"type":"Point"}
}