{
  "type": "Feature",
  "properties": {
    "iso:country":"US",
    "sg:address":"1251 100th St SW",
    "sg:city":"Byron Center",
    "sg:classifiers":[
        {
            "category":"Wholesale",
            "subcategory":"Chemicals & Plastics",
            "type":"Manufacturing & Wholesale Goods"
        }
    ],
    "sg:phone":"+1 616 878 5015",
    "sg:postcode":"49315",
    "sg:province":"MI",
    "wof:name":"Young Chemical",
    "wof:placetype":"venue"
},
  "geometry": {"coordinates":[-85.69435799999999,42.782637],"type":"Point"}
}