{
  "type": "Feature",
  "properties": {
    "iso:country":"US",
    "sg:address":"610 S Burdick St",
    "sg:city":"Kalamazoo",
    "sg:classifiers":[
        {
            "category":"Social Services",
            "type":"Services"
        }
    ],
    "sg:phone":"+1 269 381 3700",
    "sg:postcode":"49007",
    "sg:province":"MI",
    "sg:tags":[
        "counseling"
    ],
    "wof:name":"Interact of Michigan Inc",
    "wof:placetype":"venue"
},
  "geometry": {"coordinates":[-85.583045,42.285773],"type":"Point"}
}