{
  "type": "Feature",
  "properties": {
    "iso:country":"US",
    "sg:address":"827 Royal Ave",
    "sg:city":"Royal Oak",
    "sg:classifiers":[
        {
            "category":"Personal",
            "type":"Services"
        }
    ],
    "sg:phone":"+1 248 585 2090",
    "sg:postcode":"48073",
    "sg:province":"MI",
    "sg:tags":[
        "mover"
    ],
    "wof:name":"Monty's Cartage",
    "wof:placetype":"venue"
},
  "geometry": {"coordinates":[-83.15450300000001,42.5145],"type":"Point"}
}