{
  "type": "Feature",
  "properties": {
    "iso:country":"US",
    "sg:address":"5684 E Highland Rd",
    "sg:city":"Howell",
    "sg:classifiers":[
        {
            "category":"Wholesale",
            "subcategory":"Durable Goods & Equipment",
            "type":"Manufacturing & Wholesale Goods"
        }
    ],
    "sg:phone":"+1 517 548 6414",
    "sg:postcode":"48843",
    "sg:province":"MI",
    "sg:tags":[
        "representative",
        "manufacturer"
    ],
    "wof:name":"Tri-Matic Screw Products",
    "wof:placetype":"venue"
},
  "geometry": {"coordinates":[-83.83840600000001,42.630363],"type":"Point"}
}