{
  "type": "Feature",
  "properties": {
    "iso:country":"US",
    "sg:address":"12173 Market St",
    "sg:city":"Livonia",
    "sg:classifiers":[
        {
            "category":"Building & Trades",
            "subcategory":"Equipment Rental",
            "type":"Services"
        }
    ],
    "sg:phone":"+1 734 591 6111",
    "sg:postcode":"48150",
    "sg:province":"MI",
    "sg:tags":[
        "industrial"
    ],
    "wof:name":"Blk Equipment Ltd Partnership",
    "wof:placetype":"venue"
},
  "geometry": {"coordinates":[-83.40518299999999,42.368394],"type":"Point"}
}