{
  "type": "Feature",
  "properties": {
    "iso:country":"US",
    "sg:address":"305 Community St",
    "sg:city":"Lansing",
    "sg:classifiers":[
        {
            "category":"Manufacturing",
            "subcategory":"Glass & Minerals",
            "type":"Manufacturing & Wholesale Goods"
        }
    ],
    "sg:phone":"+1 517 484 5297",
    "sg:postcode":"48906",
    "sg:province":"MI",
    "sg:tags":[
        "product",
        "mfg"
    ],
    "wof:name":"Diversity Glass & Art",
    "wof:placetype":"venue"
},
  "geometry": {"coordinates":[-84.54833600000001,42.76575],"type":"Point"}
}