{
  "type": "Feature",
  "properties": {
    "iso:country":"US",
    "sg:address":"3615 Maple Dr",
    "sg:city":"Melvindale",
    "sg:classifiers":[
        {
            "category":"Organizations",
            "subcategory":"Political Organization",
            "type":"Services"
        }
    ],
    "sg:phone":"+1 313 382 6538",
    "sg:postcode":"48122",
    "sg:province":"MI",
    "wof:name":"Melvindale Democratic Club",
    "wof:placetype":"venue"
},
  "geometry": {"coordinates":[-83.179607,42.284203],"type":"Point"}
}