{
  "type": "Feature",
  "properties": {
    "iso:country":"US",
    "sg:address":"853 Dery St",
    "sg:city":"Quincy",
    "sg:classifiers":[
        {
            "category":"Building & Trades",
            "subcategory":"Construction",
            "type":"Services"
        }
    ],
    "sg:phone":"+1 517 639 5797",
    "sg:postcode":"49082",
    "sg:province":"MI",
    "sg:tags":[
        "general",
        "contractor"
    ],
    "wof:name":"Ed's Construction",
    "wof:placetype":"venue"
},
  "geometry": {"coordinates":[-84.90716999999999,41.945046],"type":"Point"}
}