{
  "type": "Feature",
  "properties": {
    "iso:country":"US",
    "sg:address":"2851 Buchanan Ave SW",
    "sg:city":"Grand Rapids",
    "sg:classifiers":[
        {
            "category":"Shopping",
            "subcategory":"Computers & Home Electronics",
            "type":"Retail Goods"
        }
    ],
    "sg:phone":"+1 616 831 0080",
    "sg:postcode":"49548",
    "sg:province":"MI",
    "sg:tags":[
        "television",
        "radio"
    ],
    "sg:website":"www.bursma.com",
    "wof:name":"Bursma Electronic Distributing",
    "wof:placetype":"venue"
},
  "geometry": {"coordinates":[-85.670912,42.911577],"type":"Point"}
}