{
  "type": "Feature",
  "properties": {
    "iso:country":"US",
    "sg:address":"1790 Packard Hwy",
    "sg:city":"Charlotte",
    "sg:classifiers":[
        {
            "category":"Education",
            "subcategory":"Special Training",
            "type":"Public Place"
        }
    ],
    "sg:phone":"+1 517 543 5500",
    "sg:postcode":"48813",
    "sg:province":"MI",
    "sg:tags":[
        "management"
    ],
    "wof:name":"Meadowview School",
    "wof:placetype":"venue"
},
  "geometry": {"coordinates":[-84.802588,42.581972],"type":"Point"}
}