{
  "type": "Feature",
  "properties": {
    "iso:country":"US",
    "sg:address":"9925 Spencer Rd",
    "sg:city":"Brighton",
    "sg:classifiers":[
        {
            "category":"Autos & Motor Vehicles",
            "subcategory":"Fuel & Gas Station",
            "type":"Retail Goods"
        }
    ],
    "sg:phone":"+1 810 227 8197",
    "sg:postcode":"48114",
    "sg:province":"MI",
    "sg:tags":[
        "oil"
    ],
    "wof:name":"Spencer Road Mobil",
    "wof:placetype":"venue"
},
  "geometry": {"coordinates":[-83.75449999999999,42.536532],"type":"Point"}
}