{
  "type": "Feature",
  "properties": {
    "iso:country":"US",
    "sg:address":"3625 Russell St",
    "sg:city":"Detroit",
    "sg:classifiers":[
        {
            "category":"Professional",
            "subcategory":"Management & Consulting",
            "type":"Services"
        }
    ],
    "sg:phone":"+1 313 832 3942",
    "sg:postcode":"48207",
    "sg:province":"MI",
    "sg:tags":[
        "business"
    ],
    "wof:name":"Aestethics Consulting",
    "wof:placetype":"venue"
},
  "geometry": {"coordinates":[-83.04478,42.35272],"type":"Point"}
}