{
  "type": "Feature",
  "properties": {
    "iso:country":"US",
    "sg:address":"56955 State Hwy 43",
    "sg:city":"Bangor",
    "sg:classifiers":[
        {
            "category":"Home & Garden",
            "subcategory":"Carpets & Floor Coverings",
            "type":"Retail Goods"
        }
    ],
    "sg:phone":"+1 269 427 1144",
    "sg:postcode":"49013",
    "sg:province":"MI",
    "sg:tags":[
        "dealer",
        "rug"
    ],
    "wof:name":"Watkins Carpet Corner Inc",
    "wof:placetype":"venue"
},
  "geometry": {"coordinates":[-86.099639,42.309125],"type":"Point"}
}