{
  "type": "Feature",
  "properties": {
    "iso:country":"US",
    "sg:address":"3520 Pollina Ave",
    "sg:city":"Fort Gratiot",
    "sg:classifiers":[
        {
            "category":"Social Services",
            "subcategory":"Child Care",
            "type":"Services"
        }
    ],
    "sg:phone":"+1 810 982 3191",
    "sg:postcode":"48059",
    "sg:province":"MI",
    "sg:tags":[
        "day"
    ],
    "wof:name":"Bright Beginnings Child Care",
    "wof:placetype":"venue"
},
  "geometry": {"coordinates":[-82.48459800000001,43.012658],"type":"Point"}
}