{
  "type": "Feature",
  "properties": {
    "iso:country":"US",
    "sg:address":"21226 Gratiot Ave",
    "sg:city":"Eastpointe",
    "sg:classifiers":[
        {
            "category":"Wholesale",
            "subcategory":"Home Furnishings",
            "type":"Manufacturing & Wholesale Goods"
        }
    ],
    "sg:phone":"+1 586 771 3190",
    "sg:postcode":"48021",
    "sg:province":"MI",
    "sg:tags":[
        "rug",
        "carpet"
    ],
    "wof:name":"Huron Associates",
    "wof:placetype":"venue"
},
  "geometry": {"coordinates":[-82.96476800000001,42.453886],"type":"Point"}
}