{
  "type": "Feature",
  "properties": {
    "iso:country":"US",
    "sg:address":"421 W Fifth Ave",
    "sg:city":"Flint",
    "sg:classifiers":[
        {
            "category":"Government",
            "subcategory":"Office",
            "type":"Public Place"
        }
    ],
    "sg:phone":"+1 810 766 7085",
    "sg:postcode":"48503",
    "sg:province":"MI",
    "sg:tags":[
        "village"
    ],
    "wof:name":"Vista Drop-In Ctr",
    "wof:placetype":"venue"
},
  "geometry": {"coordinates":[-83.701126,43.02083],"type":"Point"}
}