{
  "type": "Feature",
  "properties": {
    "iso:country":"US",
    "sg:address":"8951 Michigan Ave",
    "sg:city":"Detroit",
    "sg:classifiers":[
        {
            "category":"Retail",
            "subcategory":"Auto Repair",
            "type":"Services"
        }
    ],
    "sg:phone":"+1 313 945 9700",
    "sg:postcode":"48210",
    "sg:province":"MI",
    "wof:name":"U S Car Service Inc",
    "wof:placetype":"venue"
},
  "geometry": {"coordinates":[-83.15160400000001,42.329102],"type":"Point"}
}