{
  "type": "Feature",
  "properties": {
    "iso:country":"US",
    "sg:address":"33450 W 12 Mile Rd Ste 103",
    "sg:city":"Farmingtn Hls",
    "sg:classifiers":[
        {
            "category":"Professional",
            "subcategory":"Accounting & Tax Preparation",
            "type":"Services"
        }
    ],
    "sg:phone":"+1 248 553 0350",
    "sg:postcode":"48331",
    "sg:province":"MI",
    "sg:tags":[
        "accountant"
    ],
    "wof:name":"Johnson Kula & Company PC",
    "wof:placetype":"venue"
},
  "geometry": {"coordinates":[-83.378197,42.498699],"type":"Point"}
}