{
  "type": "Feature",
  "properties": {
    "iso:country":"US",
    "sg:address":"2280 S Center Rd",
    "sg:city":"Burton",
    "sg:classifiers":[
        {
            "category":"Restaurant",
            "type":"Food & Drink"
        }
    ],
    "sg:phone":"+1 810 742 8695",
    "sg:postcode":"48519",
    "sg:province":"MI",
    "wof:name":"Paul's Coney Island Family Restaurant",
    "wof:placetype":"venue"
},
  "geometry": {"coordinates":[-83.634201,42.996498],"type":"Point"}
}