{
  "type": "Feature",
  "properties": {
    "iso:country":"US",
    "sg:address":"50 E Columbia Ave",
    "sg:city":"Battle Creek",
    "sg:classifiers":[
        {
            "category":"Shopping",
            "subcategory":"Computers & Home Electronics",
            "type":"Retail Goods"
        }
    ],
    "sg:phone":"+1 269 963 4068",
    "sg:postcode":"49015",
    "sg:province":"MI",
    "sg:tags":[
        "equipment",
        "satellite",
        "system"
    ],
    "wof:name":"Satellite Recivers LTD",
    "wof:placetype":"venue"
},
  "geometry": {"coordinates":[-85.197834,42.298485],"type":"Point"}
}