{
  "type": "Feature",
  "properties": {
    "iso:country":"US",
    "sg:address":"7545 Teal Rd",
    "sg:city":"Oscoda",
    "sg:classifiers":[
        {
            "category":"Professional",
            "subcategory":"Detective & Security Services",
            "type":"Services"
        }
    ],
    "sg:phone":"+1 989 739 2077",
    "sg:postcode":"48750",
    "sg:province":"MI",
    "sg:tags":[
        "system"
    ],
    "wof:name":"Royal Alarm & Sound Systems In",
    "wof:placetype":"venue"
},
  "geometry": {"coordinates":[-83.33798299999999,44.500688],"type":"Point"}
}