{
  "type": "Feature",
  "properties": {
    "iso:country":"US",
    "sg:address":"8857 Coleman Rd",
    "sg:city":"Haslett",
    "sg:classifiers":[
        {
            "category":"Retail",
            "subcategory":"Repair Shop",
            "type":"Services"
        }
    ],
    "sg:phone":"+1 517 339 9095",
    "sg:postcode":"48840",
    "sg:province":"MI",
    "wof:name":"Michigan Satellite TV",
    "wof:placetype":"venue"
},
  "geometry": {"coordinates":[-84.381699,42.773988],"type":"Point"}
}