{
  "type": "Feature",
  "properties": {
    "iso:country":"US",
    "sg:address":"4130 Wilder Rd",
    "sg:city":"Bay City",
    "sg:classifiers":[
        {
            "category":"Shopping",
            "subcategory":"Computers & Home Electronics",
            "type":"Retail Goods"
        }
    ],
    "sg:phone":"+1 989 686 4085",
    "sg:postcode":"48706",
    "sg:province":"MI",
    "sg:tags":[
        "television",
        "radio"
    ],
    "wof:name":"Rex TV",
    "wof:placetype":"venue"
},
  "geometry": {"coordinates":[-83.892521,43.623725],"type":"Point"}
}