{
  "type": "Feature",
  "properties": {
    "iso:country":"US",
    "sg:address":"121 W Flint Park Blvd",
    "sg:city":"Flint",
    "sg:classifiers":[
        {
            "category":"Shopping",
            "subcategory":"Clothing, Apparel, & Fashions",
            "type":"Retail Goods"
        }
    ],
    "sg:phone":"+1 810 244 8596",
    "sg:postcode":"48505",
    "sg:province":"MI",
    "sg:tags":[
        "item",
        "boutique"
    ],
    "wof:name":"Zeke's Ware",
    "wof:placetype":"venue"
},
  "geometry": {"coordinates":[-83.709592,43.055823],"type":"Point"}
}