{
  "type": "Feature",
  "properties": {
    "iso:country":"US",
    "sg:address":"16207 Lindsay St",
    "sg:city":"Detroit",
    "sg:classifiers":[
        {
            "category":"Banks & Credit Unions",
            "subcategory":"Bank",
            "type":"Services"
        }
    ],
    "sg:phone":"+1 313 587 5031",
    "sg:postcode":"48235",
    "sg:province":"MI",
    "sg:tags":[
        "company",
        "mortgage"
    ],
    "wof:name":"J Todd & Associates",
    "wof:placetype":"venue"
},
  "geometry": {"coordinates":[-83.21314700000001,42.409765],"type":"Point"}
}