{
  "type": "Feature",
  "properties": {
    "iso:country":"US",
    "sg:address":"14221 Park St",
    "sg:city":"Rockwood",
    "sg:classifiers":[
        {
            "category":"Real Estate",
            "subcategory":"Real Estate Operator",
            "type":"Services"
        }
    ],
    "sg:phone":"+1 734 675 8090",
    "sg:postcode":"48173",
    "sg:province":"MI",
    "sg:tags":[
        "building",
        "apartment"
    ],
    "wof:name":"Marina Bay Club Apartments",
    "wof:placetype":"venue"
},
  "geometry": {"coordinates":[-83.195297,42.099499],"type":"Point"}
}