{
  "type": "Feature",
  "properties": {
    "iso:country":"US",
    "sg:address":"2340 28th St SE",
    "sg:city":"Grand Rapids",
    "sg:classifiers":[
        {
            "category":"Health Services",
            "subcategory":"Doctor",
            "type":"Services"
        }
    ],
    "sg:phone":"+1 616 243 4877",
    "sg:postcode":"49508",
    "sg:province":"MI",
    "sg:tags":[
        "medical"
    ],
    "wof:name":"Andrew Daugavietis MD",
    "wof:placetype":"venue"
},
  "geometry": {"coordinates":[-85.609296,42.912559],"type":"Point"}
}