{
  "type": "Feature",
  "properties": {
    "iso:country":"US",
    "sg:address":"7300 Piebert Ct",
    "sg:city":"Pinckney",
    "sg:classifiers":[
        {
            "category":"Utilities",
            "subcategory":"Fuel Oil & Lpg",
            "type":"Services"
        }
    ],
    "sg:phone":"+1 734 878 3885",
    "sg:postcode":"48169",
    "sg:province":"MI",
    "sg:tags":[
        "wood",
        "pellet"
    ],
    "wof:name":"MSR Sales",
    "wof:placetype":"venue"
},
  "geometry": {"coordinates":[-83.907521,42.490136],"type":"Point"}
}