{
  "type": "Feature",
  "properties": {
    "iso:country":"US",
    "sg:address":"1551 Filmore Ave",
    "sg:city":"Cadillac",
    "sg:classifiers":[
        {
            "category":"Manufacturing",
            "subcategory":"Metals",
            "type":"Manufacturing & Wholesale Goods"
        }
    ],
    "sg:phone":"+1 231 775 4990",
    "sg:postcode":"49601",
    "sg:province":"MI",
    "sg:tags":[
        "product"
    ],
    "wof:name":"Rh Metal Craft Inc",
    "wof:placetype":"venue"
},
  "geometry": {"coordinates":[-85.40743500000001,44.271663],"type":"Point"}
}