{
  "type": "Feature",
  "properties": {
    "iso:country":"US",
    "sg:address":"3540 S County Line Hwy",
    "sg:city":"Deerfield",
    "sg:classifiers":[
        {
            "category":"Retail",
            "subcategory":"Repair Shop",
            "type":"Services"
        }
    ],
    "sg:phone":"+1 517 447 3254",
    "sg:postcode":"49238",
    "sg:province":"MI",
    "sg:tags":[
        "refrigeration"
    ],
    "wof:name":"McCarty Refrigeration",
    "wof:placetype":"venue"
},
  "geometry": {"coordinates":[-83.769018,41.870249],"type":"Point"}
}