{
  "type": "Feature",
  "properties": {
    "iso:country":"US",
    "sg:address":"500 N State St",
    "sg:city":"Sparta",
    "sg:classifiers":[
        {
            "category":"Restaurant",
            "type":"Food & Drink"
        }
    ],
    "sg:phone":"+1 616 887 7071",
    "sg:postcode":"49345",
    "sg:province":"MI",
    "wof:name":"Gardoli's Pizza & Mexican",
    "wof:placetype":"venue"
},
  "geometry": {"coordinates":[-85.710201,43.168113],"type":"Point"}
}