{
  "type": "Feature",
  "properties": {
    "iso:country":"US",
    "sg:address":"2903 Trumbull St",
    "sg:city":"Detroit",
    "sg:classifiers":[
        {
            "category":"Retail",
            "subcategory":"Laundry & Dry Cleaning",
            "type":"Services"
        }
    ],
    "sg:phone":"+1 313 963 8720",
    "sg:postcode":"48216",
    "sg:province":"MI",
    "wof:name":"Knox Cleaners",
    "wof:placetype":"venue"
},
  "geometry": {"coordinates":[-83.07089999999999,42.3381],"type":"Point"}
}