{
  "type": "Feature",
  "properties": {
    "iso:country":"US",
    "sg:address":"205 Main St",
    "sg:city":"St Joseph",
    "sg:classifiers":[
        {
            "category":"Government",
            "subcategory":"Post Office",
            "type":"Public Place"
        }
    ],
    "sg:phone":"+1 269 000 1111",
    "sg:postcode":"49085",
    "sg:province":"MI",
    "sg:website":"www.usps.com",
    "wof:name":"US Post Office",
    "wof:placetype":"venue"
},
  "geometry": {"coordinates":[-86.480571,42.108999],"type":"Point"}
}