{
  "type": "Feature",
  "properties": {
    "iso:country":"US",
    "sg:address":"15172 Willowwood",
    "sg:city":"Grand Haven",
    "sg:classifiers":[
        {
            "category":"Building & Trades",
            "subcategory":"Equipment Rental",
            "type":"Services"
        }
    ],
    "sg:phone":"+1 616 296 0252",
    "sg:postcode":"49417",
    "sg:province":"MI",
    "wof:name":"Matrix Leasing & Dev LLC",
    "wof:placetype":"venue"
},
  "geometry": {"coordinates":[-86.16528599999999,43.041431],"type":"Point"}
}