{
  "type": "Feature",
  "properties": {
    "iso:country":"US",
    "sg:address":"13603 148th Ave",
    "sg:city":"Grand Haven",
    "sg:classifiers":[
        {
            "category":"Building & Trades",
            "subcategory":"Pest Control",
            "type":"Services"
        }
    ],
    "sg:phone":"+1 616 842 8776",
    "sg:postcode":"49417",
    "sg:province":"MI",
    "wof:name":"Edelmayer Ed Trmt & Pest Ctrl",
    "wof:placetype":"venue"
},
  "geometry": {"coordinates":[-86.15501999999999,43.01757],"type":"Point"}
}