{
  "type": "Feature",
  "properties": {
    "iso:country":"US",
    "sg:address":"8812 Sandy Crest Ct",
    "sg:city":"White Lake",
    "sg:classifiers":[
        {
            "category":"Building & Trades",
            "subcategory":"Construction",
            "type":"Services"
        }
    ],
    "sg:phone":"+1 248 698 3487",
    "sg:postcode":"48386",
    "sg:province":"MI",
    "sg:tags":[
        "nonresidential"
    ],
    "wof:name":"Bunker Building Co",
    "wof:placetype":"venue"
},
  "geometry": {"coordinates":[-83.460596,42.645852],"type":"Point"}
}