{
  "type": "Feature",
  "properties": {
    "iso:country":"US",
    "sg:address":"117 S Broadway St",
    "sg:city":"Cassopolis",
    "sg:classifiers":[
        {
            "category":"Government",
            "subcategory":"Police Station",
            "type":"Public Place"
        }
    ],
    "sg:phone":"+1 269 445 8100",
    "sg:postcode":"49031",
    "sg:province":"MI",
    "sg:tags":[
        "department"
    ],
    "wof:name":"Cassopolis Police Dept",
    "wof:placetype":"venue"
},
  "geometry": {"coordinates":[-86.012466,41.911282],"type":"Point"}
}