{
  "type": "Feature",
  "properties": {
    "iso:country":"US",
    "sg:address":"5051 W Main St",
    "sg:city":"Kalamazoo",
    "sg:classifiers":[
        {
            "category":"Health Services",
            "subcategory":"Optometrist",
            "type":"Services"
        }
    ],
    "sg:phone":"+1 269 381 8972",
    "sg:postcode":"49009",
    "sg:province":"MI",
    "wof:name":"Lounge Optical",
    "wof:placetype":"venue"
},
  "geometry": {"coordinates":[-85.65047800000001,42.296181],"type":"Point"}
}