{
  "type": "Feature",
  "properties": {
    "iso:country":"US",
    "sg:address":"1505 Oak Hollow Dr",
    "sg:city":"Milford",
    "sg:classifiers":[
        {
            "category":"Sports & Exercise",
            "subcategory":"Race Track",
            "type":"Entertainment"
        }
    ],
    "sg:phone":"+1 248 685 7300",
    "sg:postcode":"48380",
    "sg:province":"MI",
    "sg:tags":[
        "operation",
        "racing",
        "or"
    ],
    "wof:name":"Hole-Shot Racing Inc",
    "wof:placetype":"venue"
},
  "geometry": {"coordinates":[-83.664338,42.561707],"type":"Point"}
}