{
  "type": "Feature",
  "properties": {
    "iso:country":"US",
    "sg:address":"101 W Coldwater Rd",
    "sg:city":"Union City",
    "sg:classifiers":[
        {
            "category":"Retail",
            "subcategory":"Car Wash",
            "type":"Services"
        }
    ],
    "sg:phone":"+1 517 741 4004",
    "sg:postcode":"49094",
    "sg:province":"MI",
    "sg:tags":[
        "automotive",
        "detailing",
        "detail",
        "clean",
        "automobile"
    ],
    "wof:name":"Musselman's Detail Shop",
    "wof:placetype":"venue"
},
  "geometry": {"coordinates":[-85.060711,42.014708],"type":"Point"}
}