{
  "type": "Feature",
  "properties": {
    "iso:country":"US",
    "sg:address":"3056 Dixie Ave SW",
    "sg:city":"Grandville",
    "sg:classifiers":[
        {
            "category":"Manufacturing",
            "subcategory":"Metals",
            "type":"Manufacturing & Wholesale Goods"
        }
    ],
    "sg:phone":"+1 616 538 1140",
    "sg:postcode":"49418",
    "sg:province":"MI",
    "sg:tags":[
        "steel"
    ],
    "wof:name":"Jenco Industries",
    "wof:placetype":"venue"
},
  "geometry": {"coordinates":[-85.73769299999999,42.907945],"type":"Point"}
}