{
  "type": "Feature",
  "properties": {
    "iso:country":"US",
    "sg:address":"2150 Butterfield Dr",
    "sg:city":"Troy",
    "sg:classifiers":[
        {
            "category":"Insurance",
            "subcategory":"Insurance Agent",
            "type":"Services"
        }
    ],
    "sg:phone":"+1 248 643 7475",
    "sg:postcode":"48084",
    "sg:province":"MI",
    "wof:name":"Bosquett & Co",
    "wof:placetype":"venue"
},
  "geometry": {"coordinates":[-83.17520399999999,42.559227],"type":"Point"}
}