{
  "type": "Feature",
  "properties": {
    "iso:country":"US",
    "sg:address":"777 Butternut Dr",
    "sg:city":"Holland",
    "sg:classifiers":[
        {
            "category":"Real Estate",
            "subcategory":"Real Estate Operator",
            "type":"Services"
        }
    ],
    "sg:phone":"+1 616 399 7224",
    "sg:postcode":"49424",
    "sg:province":"MI",
    "sg:tags":[
        "building",
        "apartment"
    ],
    "wof:name":"McIntosh Manor Non-Prft Hsng",
    "wof:placetype":"venue"
},
  "geometry": {"coordinates":[-86.128739,42.820157],"type":"Point"}
}