{
  "type": "Feature",
  "properties": {
    "iso:country":"US",
    "sg:address":"5565 Allen Rd",
    "sg:city":"Allen Park",
    "sg:classifiers":[
        {
            "category":"Personal",
            "subcategory":"Barber",
            "type":"Services"
        }
    ],
    "sg:phone":"+1 313 388 7575",
    "sg:postcode":"48101",
    "sg:province":"MI",
    "wof:name":"Donna's Barber Shop",
    "wof:placetype":"venue"
},
  "geometry": {"coordinates":[-83.202952,42.262535],"type":"Point"}
}