{
  "type": "Feature",
  "properties": {
    "iso:country":"US",
    "sg:address":"1520 E Main St",
    "sg:city":"Owosso",
    "sg:classifiers":[
        {
            "category":"Shopping",
            "subcategory":"Clothing, Apparel, & Fashions",
            "type":"Retail Goods"
        }
    ],
    "sg:phone":"+1 989 729 0029",
    "sg:postcode":"48867",
    "sg:province":"MI",
    "sg:tags":[
        "dancing",
        "supply"
    ],
    "wof:name":"Turning Pointe",
    "wof:placetype":"venue"
},
  "geometry": {"coordinates":[-84.14792,42.99775],"type":"Point"}
}