{
  "type": "Feature",
  "properties": {
    "iso:country":"US",
    "sg:address":"4164 S Saginaw St",
    "sg:city":"Burton",
    "sg:classifiers":[
        {
            "category":"Shopping",
            "subcategory":"Books",
            "type":"Retail Goods"
        }
    ],
    "sg:phone":"+1 810 744 3942",
    "sg:postcode":"48529",
    "sg:province":"MI",
    "sg:tags":[
        "dealer"
    ],
    "wof:name":"Northern Lights Bookstore",
    "wof:placetype":"venue"
},
  "geometry": {"coordinates":[-83.672156,42.96951],"type":"Point"}
}