{
  "type": "Feature",
  "properties": {
    "iso:country":"US",
    "sg:address":"3289 S Center Rd",
    "sg:city":"Burton",
    "sg:classifiers":[
        {
            "category":"Health Services",
            "subcategory":"Chiropractor",
            "type":"Services"
        }
    ],
    "sg:phone":"+1 810 744 3030",
    "sg:postcode":"48519",
    "sg:province":"MI",
    "wof:name":"Guelde Donald F DC",
    "wof:placetype":"venue"
},
  "geometry": {"coordinates":[-83.633202,42.9818],"type":"Point"}
}