{
  "type": "Feature",
  "properties": {
    "iso:country":"US",
    "sg:address":"49015 Romeo Plank Rd",
    "sg:city":"Macomb",
    "sg:classifiers":[
        {
            "category":"Building & Trades",
            "subcategory":"Construction",
            "type":"Services"
        }
    ],
    "sg:phone":"+1 586 263 3482",
    "sg:postcode":"48044",
    "sg:province":"MI",
    "sg:tags":[
        "floor",
        "laying",
        "contractor"
    ],
    "wof:name":"Eds Carpet & Total Floors",
    "wof:placetype":"venue"
},
  "geometry": {"coordinates":[-82.937212,42.657482],"type":"Point"}
}