{
  "type": "Feature",
  "properties": {
    "iso:country":"US",
    "sg:address":"6612 W Price Rd",
    "sg:city":"Saint Johns",
    "sg:classifiers":[
        {
            "category":"Real Estate",
            "subcategory":"Real Estate Operator",
            "type":"Services"
        }
    ],
    "sg:phone":"+1 989 224 2451",
    "sg:postcode":"48879",
    "sg:province":"MI",
    "sg:tags":[
        "property",
        "lessor"
    ],
    "wof:name":"Lester Sehlke",
    "wof:placetype":"venue"
},
  "geometry": {"coordinates":[-84.660263,42.929508],"type":"Point"}
}