{
  "type": "Feature",
  "properties": {
    "iso:country":"US",
    "sg:address":"6521 Lansing Rd",
    "sg:city":"Charlotte",
    "sg:classifiers":[
        {
            "category":"Shopping",
            "type":"Retail Goods"
        }
    ],
    "sg:phone":"+1 517 322 0443",
    "sg:postcode":"48813",
    "sg:province":"MI",
    "sg:tags":[
        "enforcement",
        "law",
        "supply"
    ],
    "wof:name":"Michigan Police Equipment Co",
    "wof:placetype":"venue"
},
  "geometry": {"coordinates":[-84.67510799999999,42.661747],"type":"Point"}
}