{
  "type": "Feature",
  "properties": {
    "iso:country":"US",
    "sg:address":"19245 W 8 Mile Rd",
    "sg:city":"Detroit",
    "sg:classifiers":[
        {
            "category":"Restaurant",
            "type":"Food & Drink"
        }
    ],
    "sg:phone":"+1 313 535 6224",
    "sg:postcode":"48219",
    "sg:province":"MI",
    "wof:name":"Cheetah's On the Strip",
    "wof:placetype":"venue"
},
  "geometry": {"coordinates":[-83.232597,42.443802],"type":"Point"}
}