{
  "type": "Feature",
  "properties": {
    "iso:country":"US",
    "sg:address":"1450 E Lansing Dr",
    "sg:city":"East Lansing",
    "sg:classifiers":[
        {
            "category":"Professional",
            "subcategory":"Art Services",
            "type":"Services"
        }
    ],
    "sg:phone":"+1 517 332 8737",
    "sg:postcode":"48823",
    "sg:province":"MI",
    "sg:tags":[
        "graphic",
        "designer"
    ],
    "wof:name":"Adventures With Nature",
    "wof:placetype":"venue"
},
  "geometry": {"coordinates":[-84.452245,42.748752],"type":"Point"}
}