{
  "type": "Feature",
  "properties": {
    "iso:country":"US",
    "sg:address":"2360 28th St SW",
    "sg:city":"Wyoming",
    "sg:classifiers":[
        {
            "category":"Manufacturing",
            "subcategory":"Petroleum Products",
            "type":"Manufacturing & Wholesale Goods"
        }
    ],
    "sg:phone":"+1 616 538 5490",
    "sg:postcode":"49519",
    "sg:province":"MI",
    "sg:tags":[
        "oil",
        "refiner"
    ],
    "wof:name":"Consolidated Stations",
    "wof:placetype":"venue"
},
  "geometry": {"coordinates":[-85.724642,42.913857],"type":"Point"}
}