{
  "type": "Feature",
  "properties": {
    "iso:country":"US",
    "sg:address":"20506 80th Ave",
    "sg:city":"Marion",
    "sg:classifiers":[
        {
            "category":"Professional",
            "subcategory":"Business Services",
            "type":"Services"
        }
    ],
    "sg:phone":"+1 231 743 6210",
    "sg:postcode":"49665",
    "sg:province":"MI",
    "wof:name":"Heuker Auctions",
    "wof:placetype":"venue"
},
  "geometry": {"coordinates":[-85.246341,44.113025],"type":"Point"}
}