{
  "type": "Feature",
  "properties": {
    "iso:country":"US",
    "sg:address":"10328 W McNichols Rd",
    "sg:city":"Detroit",
    "sg:classifiers":[
        {
            "category":"Personal",
            "subcategory":"Barber",
            "type":"Services"
        }
    ],
    "sg:phone":"+1 313 864 7311",
    "sg:postcode":"48221",
    "sg:province":"MI",
    "wof:name":"Hands of Precision Barber Shop",
    "wof:placetype":"venue"
},
  "geometry": {"coordinates":[-83.164299,42.416901],"type":"Point"}
}