{
  "type": "Feature",
  "properties": {
    "iso:country":"US",
    "sg:address":"22564 Pembroke Ave",
    "sg:city":"Detroit",
    "sg:classifiers":[
        {
            "category":"Social Services",
            "type":"Services"
        }
    ],
    "sg:phone":"+1 313 533 2721",
    "sg:postcode":"48219",
    "sg:province":"MI",
    "wof:name":"H & S Information Network",
    "wof:placetype":"venue"
},
  "geometry": {"coordinates":[-83.26769299999999,42.436341],"type":"Point"}
}