{
  "type": "Feature",
  "properties": {
    "iso:country":"US",
    "sg:address":"75 Sheldon Ave NE",
    "sg:city":"Grand Rapids",
    "sg:classifiers":[
        {
            "category":"Health Services",
            "subcategory":"Clinic",
            "type":"Services"
        }
    ],
    "sg:phone":"+1 616 451 2135",
    "sg:postcode":"49503",
    "sg:province":"MI",
    "wof:name":"Cherry Street Health Svc",
    "wof:placetype":"venue"
},
  "geometry": {"coordinates":[-85.666877,42.963486],"type":"Point"}
}