{
  "type": "Feature",
  "properties": {
    "iso:country":"US",
    "sg:address":"8278 Mills St",
    "sg:city":"Taylor",
    "sg:classifiers":[
        {
            "category":"Restaurant",
            "type":"Food & Drink"
        }
    ],
    "sg:phone":"+1 313 292 7340",
    "sg:postcode":"48180",
    "sg:province":"MI",
    "sg:tags":[
        "eating"
    ],
    "wof:name":"Slice of Life Pizza",
    "wof:placetype":"venue"
},
  "geometry": {"coordinates":[-83.28374599999999,42.247533],"type":"Point"}
}