{
  "type": "Feature",
  "properties": {
    "iso:country":"US",
    "sg:address":"501 E Cass St",
    "sg:city":"Saint Johns",
    "sg:classifiers":[
        {
            "category":"Health Services",
            "subcategory":"Medical Lab",
            "type":"Services"
        }
    ],
    "sg:phone":"+1 989 224 6636",
    "sg:postcode":"48879",
    "sg:province":"MI",
    "sg:tags":[
        "laboratory",
        "dental"
    ],
    "wof:name":"Cass Dental Lab",
    "wof:placetype":"venue"
},
  "geometry": {"coordinates":[-84.55111599999999,43.000029],"type":"Point"}
}