{
  "type": "Feature",
  "properties": {
    "iso:country":"US",
    "sg:address":"40028 Grand River Ave",
    "sg:city":"Novi",
    "sg:classifiers":[
        {
            "category":"Professional",
            "subcategory":"Management & Consulting",
            "type":"Services"
        }
    ],
    "sg:phone":"+1 248 471 1900",
    "sg:postcode":"48375",
    "sg:province":"MI",
    "sg:tags":[
        "home",
        "company",
        "construction",
        "family",
        "for"
    ],
    "wof:name":"A & M Custom Built Homes Inc",
    "wof:placetype":"venue"
},
  "geometry": {"coordinates":[-83.44229300000001,42.473398],"type":"Point"}
}