{
  "type": "Feature",
  "properties": {
    "iso:country":"US",
    "sg:address":"882 Wildemere Dr",
    "sg:city":"Mason",
    "sg:classifiers":[
        {
            "category":"Real Estate",
            "subcategory":"Real Estate Agent",
            "type":"Services"
        }
    ],
    "sg:phone":"+1 517 676 5982",
    "sg:postcode":"48854",
    "sg:province":"MI",
    "wof:name":"Van Co LLC",
    "wof:placetype":"venue"
},
  "geometry": {"coordinates":[-84.428625,42.583033],"type":"Point"}
}