{
  "type": "Feature",
  "properties": {
    "iso:country":"US",
    "sg:address":"611 Woodward Ave",
    "sg:city":"Detroit",
    "sg:classifiers":[
        {
            "category":"Real Estate",
            "subcategory":"Real Estate Operator",
            "type":"Services"
        }
    ],
    "sg:phone":"+1 313 225 1559",
    "sg:postcode":"48226",
    "sg:province":"MI",
    "sg:tags":[
        "building",
        "nonresidential"
    ],
    "wof:name":"Jones Lang Lasalle Americas",
    "wof:placetype":"venue"
},
  "geometry": {"coordinates":[-83.046037,42.330222],"type":"Point"}
}