{
  "type": "Feature",
  "properties": {
    "iso:country":"US",
    "sg:address":"1209 Rough Ct",
    "sg:city":"Roscommon",
    "sg:classifiers":[
        {
            "category":"Social Services",
            "subcategory":"Adult Care",
            "type":"Services"
        }
    ],
    "sg:phone":"+1 989 275 4090",
    "sg:postcode":"48653",
    "sg:province":"MI",
    "sg:tags":[
        "foster",
        "provider"
    ],
    "wof:name":"Earl & Janet Deloge",
    "wof:placetype":"venue"
},
  "geometry": {"coordinates":[-84.63525199999999,44.495977],"type":"Point"}
}