{
  "type": "Feature",
  "properties": {
    "iso:country":"US",
    "sg:address":"2791 Hemmeter Rd",
    "sg:city":"Saginaw",
    "sg:classifiers":[
        {
            "category":"Social Services",
            "subcategory":"Job Training",
            "type":"Services"
        }
    ],
    "sg:phone":"+1 989 793 2856",
    "sg:postcode":"48603",
    "sg:province":"MI",
    "sg:tags":[
        "rehabilitation"
    ],
    "wof:name":"In Home Rehab",
    "wof:placetype":"venue"
},
  "geometry": {"coordinates":[-84.005178,43.449871],"type":"Point"}
}