{
  "type": "Feature",
  "properties": {
    "iso:country":"US",
    "sg:address":"883 Crescent Ln",
    "sg:city":"Grosse Pointe",
    "sg:classifiers":[
        {
            "category":"Manufacturing",
            "subcategory":"Jewelry",
            "type":"Manufacturing & Wholesale Goods"
        }
    ],
    "sg:phone":"+1 313 885 7227",
    "sg:postcode":"48236",
    "sg:province":"MI",
    "sg:tags":[
        "material",
        "mfg"
    ],
    "wof:name":"Barb Quenneville-Gustine",
    "wof:placetype":"venue"
},
  "geometry": {"coordinates":[-82.897716,42.422515],"type":"Point"}
}