{
  "type": "Feature",
  "properties": {
    "iso:country":"US",
    "sg:address":"2468 Plainfield Ave NE",
    "sg:city":"Grand Rapids",
    "sg:classifiers":[
        {
            "category":"Food & Beverages",
            "subcategory":"Meat & Fish",
            "type":"Retail Goods"
        }
    ],
    "sg:phone":"+1 616 363 8419",
    "sg:postcode":"49505",
    "sg:province":"MI",
    "sg:tags":[
        "seafood"
    ],
    "wof:name":"Sanitary Sea Foods",
    "wof:placetype":"venue"
},
  "geometry": {"coordinates":[-85.64948800000001,43.008213],"type":"Point"}
}