{
  "type": "Feature",
  "properties": {
    "iso:country":"US",
    "sg:address":"320 E Maple Rd",
    "sg:city":"Birmingham",
    "sg:classifiers":[
        {
            "category":"Professional",
            "subcategory":"Computer Services",
            "type":"Services"
        }
    ],
    "sg:phone":"+1 248 649 5447",
    "sg:postcode":"48009",
    "sg:province":"MI",
    "sg:tags":[
        "design",
        "system"
    ],
    "wof:name":"1224 Web Drink",
    "wof:placetype":"venue"
},
  "geometry": {"coordinates":[-83.211471,42.546774],"type":"Point"}
}