{
  "type": "Feature",
  "properties": {
    "iso:country":"US",
    "sg:address":"495 W Sanilac Rd",
    "sg:city":"Sandusky",
    "sg:classifiers":[
        {
            "category":"Autos & Motor Vehicles",
            "subcategory":"Automobile Sales",
            "type":"Retail Goods"
        }
    ],
    "sg:phone":"+1 810 648 9850",
    "sg:postcode":"48471",
    "sg:province":"MI",
    "sg:tags":[
        "car",
        "dealer"
    ],
    "wof:name":"Graff Chevrolet Buick Oldsmobi",
    "wof:placetype":"venue"
},
  "geometry": {"coordinates":[-82.85018599999999,43.420879],"type":"Point"}
}