{
  "type": "Feature",
  "properties": {
    "iso:country":"US",
    "sg:address":"1912 N Wayne St",
    "sg:city":"Angola",
    "sg:classifiers":[
        {
            "category":"Autos & Motor Vehicles",
            "subcategory":"Automobile Sales",
            "type":"Retail Goods"
        }
    ],
    "sg:phone":"+1 260 665 6336",
    "sg:postcode":"46703",
    "sg:province":"MI",
    "sg:tags":[
        "car",
        "dealer"
    ],
    "wof:name":"J D Byrider",
    "wof:placetype":"venue"
},
  "geometry": {"coordinates":[-84.99945099999999,41.655445],"type":"Point"}
}