{
  "type": "Feature",
  "properties": {
    "iso:country":"US",
    "sg:address":"7062 W Lake Dr",
    "sg:city":"Fremont",
    "sg:classifiers":[
        {
            "category":"Travel",
            "subcategory":"Travel Agent",
            "type":"Entertainment"
        }
    ],
    "sg:phone":"+1 231 924 9323",
    "sg:postcode":"49412",
    "sg:province":"MI",
    "sg:tags":[
        "agency",
        "bureau"
    ],
    "wof:name":"Sandie's Travel Svc",
    "wof:placetype":"venue"
},
  "geometry": {"coordinates":[-85.974585,43.458112],"type":"Point"}
}