{
  "type": "Feature",
  "properties": {
    "iso:country":"US",
    "sg:address":"114 Main St",
    "sg:city":"Hanover",
    "sg:classifiers":[
        {
            "category":"Restaurant",
            "type":"Food & Drink"
        }
    ],
    "sg:phone":"+1 517 563 8092",
    "sg:postcode":"49241",
    "sg:province":"MI",
    "wof:name":"Peppi's Pizza Hanover",
    "wof:placetype":"venue"
},
  "geometry": {"coordinates":[-84.554209,42.101981],"type":"Point"}
}