{
  "type": "Feature",
  "properties": {
    "iso:country":"US",
    "sg:address":"4630 Lexington Ave",
    "sg:city":"Portage",
    "sg:classifiers":[
        {
            "category":"Building & Trades",
            "subcategory":"Cleaning & Sanitation",
            "type":"Services"
        }
    ],
    "sg:phone":"+1 269 324 0656",
    "sg:postcode":"49002",
    "sg:province":"MI",
    "sg:tags":[
        "maintenance"
    ],
    "wof:name":"Kathy S Cleaning",
    "wof:placetype":"venue"
},
  "geometry": {"coordinates":[-85.53502400000001,42.236536],"type":"Point"}
}