{
  "type": "Feature",
  "properties": {
    "iso:country":"US",
    "sg:address":"2874 E Ashby Rd",
    "sg:city":"Midland",
    "sg:classifiers":[
        {
            "category":"Shopping",
            "subcategory":"Clothing, Apparel, & Fashions",
            "type":"Retail Goods"
        }
    ],
    "sg:phone":"+1 989 832 4405",
    "sg:postcode":"48640",
    "sg:province":"MI",
    "sg:tags":[
        "sportswear"
    ],
    "wof:name":"Kreg'z Active Wear",
    "wof:placetype":"venue"
},
  "geometry": {"coordinates":[-84.25955999999999,43.590433],"type":"Point"}
}