{
  "type": "Feature",
  "properties": {
    "iso:country":"US",
    "sg:address":"7767 Gratiot Rd",
    "sg:city":"Saginaw",
    "sg:classifiers":[
        {
            "category":"Building & Trades",
            "subcategory":"Construction",
            "type":"Services"
        }
    ],
    "sg:phone":"+1 989 832 2700",
    "sg:postcode":"48609",
    "sg:province":"MI",
    "sg:tags":[
        "designer",
        "dealer",
        "pool",
        "swimming"
    ],
    "wof:name":"Sunshine Pools Inc",
    "wof:placetype":"venue"
},
  "geometry": {"coordinates":[-84.068443,43.415833],"type":"Point"}
}