{
  "type": "Feature",
  "properties": {
    "iso:country":"US",
    "sg:address":"1302 Carpenter Ave",
    "sg:city":"Iron Mountain",
    "sg:classifiers":[
        {
            "category":"Government",
            "subcategory":"Office",
            "type":"Public Place"
        }
    ],
    "sg:phone":"+1 906 779 1430",
    "sg:postcode":"49801",
    "sg:province":"MI",
    "sg:tags":[
        "federal",
        "taxation"
    ],
    "wof:name":"US Comptroller Of The Currency",
    "wof:placetype":"venue"
},
  "geometry": {"coordinates":[-88.068702,45.809741],"type":"Point"}
}