{
  "type": "Feature",
  "properties": {
    "iso:country":"US",
    "sg:address":"20289 Woodcreek Blvd",
    "sg:city":"Northville",
    "sg:classifiers":[
        {
            "category":"Manufacturing",
            "subcategory":"Printing",
            "type":"Manufacturing & Wholesale Goods"
        }
    ],
    "sg:phone":"+1 248 344 1644",
    "sg:postcode":"48167",
    "sg:province":"MI",
    "sg:tags":[
        "lithographic",
        "commercial"
    ],
    "wof:name":"Precision Print & Label",
    "wof:placetype":"venue"
},
  "geometry": {"coordinates":[-83.45586900000001,42.434925],"type":"Point"}
}