{
  "type": "Feature",
  "properties": {
    "iso:country":"US",
    "sg:address":"22425 Heslip Dr",
    "sg:city":"Novi",
    "sg:classifiers":[
        {
            "category":"Manufacturing",
            "subcategory":"Tools & Machinery",
            "type":"Manufacturing & Wholesale Goods"
        }
    ],
    "sg:phone":"+1 248 349 8100",
    "sg:postcode":"48375",
    "sg:province":"MI",
    "sg:tags":[
        "analytical",
        "laboratory",
        "instrument"
    ],
    "sg:website":"www.kaltecsci.com",
    "wof:name":"Kaltec Scientific Inc",
    "wof:placetype":"venue"
},
  "geometry": {"coordinates":[-83.467812,42.456864],"type":"Point"}
}