{
  "type": "Feature",
  "properties": {
    "iso:country":"US",
    "sg:address":"5419 Duke Ct",
    "sg:city":"Warren",
    "sg:classifiers":[
        {
            "category":"Sports & Exercise",
            "subcategory":"Gym",
            "type":"Entertainment"
        }
    ],
    "sg:phone":"+1 586 757 8210",
    "sg:postcode":"48091",
    "sg:province":"MI",
    "sg:tags":[
        "club",
        "health",
        "studio",
        "gymnasium"
    ],
    "wof:name":"Divine Fitness LLC",
    "wof:placetype":"venue"
},
  "geometry": {"coordinates":[-83.048272,42.482278],"type":"Point"}
}