{
  "type": "Feature",
  "properties": {
    "iso:country":"US",
    "sg:address":"15631 Plymouth Rd",
    "sg:city":"Detroit",
    "sg:classifiers":[
        {
            "category":"Retail",
            "subcategory":"Auto Repair",
            "type":"Services"
        }
    ],
    "sg:phone":"+1 313 272 7888",
    "sg:postcode":"48227",
    "sg:province":"MI",
    "wof:name":"Budget Auto Repair 1 & Performance Center",
    "wof:placetype":"venue"
},
  "geometry": {"coordinates":[-83.1991,42.372398],"type":"Point"}
}