{
  "type": "Feature",
  "properties": {
    "iso:country":"US",
    "sg:address":"1622 W Home Ave",
    "sg:city":"Flint",
    "sg:classifiers":[
        {
            "category":"Retail",
            "subcategory":"Portrait Studio",
            "type":"Services"
        }
    ],
    "sg:phone":"+1 810 785 4206",
    "sg:postcode":"48504",
    "sg:province":"MI",
    "sg:tags":[
        "photo"
    ],
    "wof:name":"Images of You Photography",
    "wof:placetype":"venue"
},
  "geometry": {"coordinates":[-83.725272,43.067684],"type":"Point"}
}