{
  "type": "Feature",
  "properties": {
    "iso:country":"US",
    "sg:address":"1349 S Rochester Rd",
    "sg:city":"Rochester Hills",
    "sg:classifiers":[
        {
            "category":"Real Estate",
            "subcategory":"Real Estate Services",
            "type":"Services"
        }
    ],
    "sg:phone":"+1 248 601 3800",
    "sg:postcode":"48307",
    "sg:province":"MI",
    "sg:tags":[
        "company",
        "title"
    ],
    "wof:name":"Philip F Greco Title Co",
    "wof:placetype":"venue"
},
  "geometry": {"coordinates":[-83.13276,42.657016],"type":"Point"}
}