{
  "type": "Feature",
  "properties": {
    "iso:country":"US",
    "sg:address":"29777 Telegraph Rd Ste 2100",
    "sg:city":"Southfield",
    "sg:classifiers":[
        {
            "category":"Real Estate",
            "subcategory":"Real Estate Services",
            "type":"Services"
        }
    ],
    "sg:phone":"+1 248 353 1575",
    "sg:postcode":"48034",
    "sg:province":"MI",
    "sg:tags":[
        "management",
        "property"
    ],
    "wof:name":"Wingate Management Corp",
    "wof:placetype":"venue"
},
  "geometry": {"coordinates":[-83.285599,42.5061],"type":"Point"}
}