{
  "type": "Feature",
  "properties": {
    "iso:country":"US",
    "sg:address":"953 Irvin St",
    "sg:city":"Plymouth",
    "sg:classifiers":[
        {
            "category":"Professional",
            "subcategory":"Computer Services",
            "type":"Services"
        }
    ],
    "sg:phone":"+1 734 451 2014",
    "sg:postcode":"48170",
    "sg:province":"MI",
    "sg:tags":[
        "design",
        "integrated",
        "system"
    ],
    "wof:name":"Design & Development Inc",
    "wof:placetype":"venue"
},
  "geometry": {"coordinates":[-83.473499,42.37996],"type":"Point"}
}