{
  "type": "Feature",
  "properties": {
    "iso:country":"US",
    "sg:address":"2929 S Tower Hill Rd",
    "sg:city":"Houghton Lake",
    "sg:classifiers":[
        {
            "category":"Recreation",
            "type":"Entertainment"
        }
    ],
    "sg:phone":"+1 989 422 3987",
    "sg:postcode":"48629",
    "sg:province":"MI",
    "sg:tags":[
        "club",
        "membership"
    ],
    "wof:name":"Houghton Lake Sportsman Club",
    "wof:placetype":"venue"
},
  "geometry": {"coordinates":[-84.75323299999999,44.29123],"type":"Point"}
}