{
  "type": "Feature",
  "properties": {
    "iso:country":"US",
    "sg:address":"12626 Payton St",
    "sg:city":"Detroit",
    "sg:classifiers":[
        {
            "category":"Social Services",
            "subcategory":"Child Care",
            "type":"Services"
        }
    ],
    "sg:phone":"+1 313 499 5329",
    "sg:postcode":"48224",
    "sg:province":"MI",
    "sg:tags":[
        "day"
    ],
    "wof:name":"Renes Daycare",
    "wof:placetype":"venue"
},
  "geometry": {"coordinates":[-82.955158,42.429747],"type":"Point"}
}