{
  "type": "Feature",
  "properties": {
    "iso:country":"US",
    "sg:address":"709 Michigan St NE",
    "sg:city":"Grand Rapids",
    "sg:classifiers":[
        {
            "category":"Banks & Credit Unions",
            "subcategory":"Bank",
            "type":"Services"
        }
    ],
    "sg:phone":"+1 616 451 4600",
    "sg:postcode":"49503",
    "sg:province":"MI",
    "sg:tags":[
        "broker",
        "mortgage"
    ],
    "wof:name":"Big Lake Mortgage Corp",
    "wof:placetype":"venue"
},
  "geometry": {"coordinates":[-85.651088,42.970152],"type":"Point"}
}