{
  "type": "Feature",
  "properties": {
    "iso:country":"US",
    "sg:address":"207 W Hovey Ave",
    "sg:city":"Muskegon",
    "sg:classifiers":[
        {
            "category":"Manufacturing",
            "subcategory":"Tools & Machinery",
            "type":"Manufacturing & Wholesale Goods"
        }
    ],
    "sg:phone":"+1 231 830 9522",
    "sg:postcode":"49444",
    "sg:province":"MI",
    "sg:tags":[
        "machine",
        "shop"
    ],
    "wof:name":"D & J Mfg & Machining",
    "wof:placetype":"venue"
},
  "geometry": {"coordinates":[-86.250674,43.208715],"type":"Point"}
}