{
  "type": "Feature",
  "properties": {
    "iso:country":"US",
    "sg:address":"3141 West 12 Mile",
    "sg:city":"Berkley",
    "sg:classifiers":[
        {
            "category":"Shopping",
            "type":"Retail Goods"
        }
    ],
    "sg:phone":"+1 248 336 2038",
    "sg:postcode":"48072",
    "sg:province":"MI",
    "sg:website":"www.yellowdoorartmarket.com/",
    "wof:name":"Yellow Door Art Market",
    "wof:placetype":"venue"
},
  "geometry": {"coordinates":[-83.19085800000001,42.503065],"type":"Point"}
}