{
  "type": "Feature",
  "properties": {
    "iso:country":"US",
    "sg:address":"509 W Ann Arbor Trl",
    "sg:city":"Plymouth",
    "sg:classifiers":[
        {
            "category":"Retail",
            "subcategory":"Veterinary Services",
            "type":"Services"
        }
    ],
    "sg:phone":"+1 734 451 2870",
    "sg:postcode":"48170",
    "sg:province":"MI",
    "sg:tags":[
        "veterinarian"
    ],
    "wof:name":"Roose Animal Hospital",
    "wof:placetype":"venue"
},
  "geometry": {"coordinates":[-83.466133,42.369194],"type":"Point"}
}