{
  "type": "Feature",
  "properties": {
    "iso:country":"US",
    "sg:address":"4344 Plainfield Ave NE",
    "sg:city":"Grand Rapids",
    "sg:classifiers":[
        {
            "category":"Banks & Credit Unions",
            "subcategory":"Bank",
            "type":"Services"
        }
    ],
    "sg:phone":"+1 616 301 3217",
    "sg:postcode":"49525",
    "sg:province":"MI",
    "sg:tags":[
        "broker",
        "mortgage"
    ],
    "wof:name":"Mortgage Team LLC",
    "wof:placetype":"venue"
},
  "geometry": {"coordinates":[-85.607287,43.042531],"type":"Point"}
}