{
  "type": "Feature",
  "properties": {
    "iso:country":"US",
    "sg:address":"32321 Tareyton St",
    "sg:city":"Farmington",
    "sg:classifiers":[
        {
            "category":"Professional",
            "subcategory":"Business Services",
            "type":"Services"
        }
    ],
    "sg:phone":"+1 248 737 7013",
    "sg:postcode":"48334",
    "sg:province":"MI",
    "sg:tags":[
        "project",
        "consulting",
        "management"
    ],
    "wof:name":"Isaac & Alexander LLC",
    "wof:placetype":"venue"
},
  "geometry": {"coordinates":[-83.341866,42.524592],"type":"Point"}
}