{
  "type": "Feature",
  "properties": {
    "iso:country":"US",
    "sg:address":"28966 Woodward Ave",
    "sg:city":"Royal Oak",
    "sg:classifiers":[
        {
            "category":"Building & Trades",
            "subcategory":"Construction",
            "type":"Services"
        }
    ],
    "sg:phone":"+1 248 543 1050",
    "sg:postcode":"48067",
    "sg:province":"MI",
    "sg:tags":[
        "contractor"
    ],
    "wof:name":"J & R Image Builders",
    "wof:placetype":"venue"
},
  "geometry": {"coordinates":[-83.171188,42.502606],"type":"Point"}
}