{
  "type": "Feature",
  "properties": {
    "iso:country":"US",
    "sg:address":"104 W Cork St",
    "sg:city":"Kalamazoo",
    "sg:classifiers":[
        {
            "category":"Shopping",
            "subcategory":"Pets & Pet Supplies",
            "type":"Retail Goods"
        },
        {
            "category":"Retail",
            "subcategory":"Veterinary Services",
            "type":"Services"
        }
    ],
    "sg:phone":"+1 269 381 1570",
    "sg:postcode":"49001",
    "sg:province":"MI",
    "sg:tags":[
        "emergency",
        "food",
        "hospital",
        "specialty",
        "clinic",
        "veterinarian"
    ],
    "sg:website":"http://www.kalamazooanimalhospital.vetsuite.com",
    "wof:name":"Kalamazoo Animal Hospital PC",
    "wof:placetype":"venue"
},
  "geometry": {"coordinates":[-85.582477,42.259635],"type":"Point"}
}