{
  "type": "Feature",
  "properties": {
    "iso:country":"US",
    "sg:address":"17182 Brady",
    "sg:city":"Redford",
    "sg:classifiers":[
        {
            "category":"Professional",
            "subcategory":"Art Services",
            "type":"Services"
        }
    ],
    "sg:phone":"+1 313 531 3551",
    "sg:postcode":"48240",
    "sg:province":"MI",
    "sg:tags":[
        "photographer"
    ],
    "sg:website":"ronaldponkeyphotography.net",
    "wof:name":"Ronald Ponkey Photography",
    "wof:placetype":"venue"
},
  "geometry": {"coordinates":[-83.287685,42.415543],"type":"Point"}
}