{
  "type": "Feature",
  "properties": {
    "iso:country":"US",
    "sg:address":"2821 N Chapin Rd",
    "sg:city":"Merrill",
    "sg:classifiers":[
        {
            "category":"Home & Garden",
            "subcategory":"Garden Supply",
            "type":"Retail Goods"
        }
    ],
    "sg:phone":"+1 989 643 7586",
    "sg:postcode":"48637",
    "sg:province":"MI",
    "sg:tags":[
        "lawn",
        "mower"
    ],
    "wof:name":"Den's",
    "wof:placetype":"venue"
},
  "geometry": {"coordinates":[-84.310675,43.44703],"type":"Point"}
}