{
  "type": "Feature",
  "properties": {
    "iso:country":"US",
    "sg:address":"105 Abbott St",
    "sg:city":"River Rouge",
    "sg:classifiers":[
        {
            "category":"Professional",
            "subcategory":"Management & Consulting",
            "type":"Services"
        }
    ],
    "sg:phone":"+1 313 538 8738",
    "sg:postcode":"48218",
    "sg:province":"MI",
    "wof:name":"Shorties Creations",
    "wof:placetype":"venue"
},
  "geometry": {"coordinates":[-83.132144,42.263869],"type":"Point"}
}