{
  "type": "Feature",
  "properties": {
    "iso:country":"US",
    "sg:address":"5104 Snow Ave SE",
    "sg:city":"Ada",
    "sg:classifiers":[
        {
            "category":"Professional",
            "subcategory":"Business Services",
            "type":"Services"
        }
    ],
    "sg:phone":"+1 616 868 6951",
    "sg:postcode":"49301",
    "sg:province":"MI",
    "wof:name":"Lotterman Auction Svc",
    "wof:placetype":"venue"
},
  "geometry": {"coordinates":[-85.42957,42.872457],"type":"Point"}
}