{
  "type": "Feature",
  "properties": {
    "iso:country":"US",
    "sg:address":"154 Pheasant Run",
    "sg:city":"Battle Creek",
    "sg:classifiers":[
        {
            "category":"Professional",
            "subcategory":"Business Services",
            "type":"Services"
        }
    ],
    "sg:phone":"+1 269 964 7676",
    "sg:postcode":"49015",
    "sg:province":"MI",
    "wof:name":"Brown Marketing Group Inc",
    "wof:placetype":"venue"
},
  "geometry": {"coordinates":[-85.211365,42.27229],"type":"Point"}
}