{
  "type": "Feature",
  "properties": {
    "iso:country":"US",
    "sg:address":"12765 S Saginaw St",
    "sg:city":"Grand Blanc",
    "sg:classifiers":[
        {
            "category":"Government",
            "subcategory":"Office",
            "type":"Public Place"
        }
    ],
    "sg:phone":"+1 810 695 2007",
    "sg:postcode":"48439",
    "sg:province":"MI",
    "sg:tags":[
        "federal",
        "affairs",
        "govt",
        "admin"
    ],
    "wof:name":"Us Veterans Affairs Dept",
    "wof:placetype":"venue"
},
  "geometry": {"coordinates":[-83.620212,42.920016],"type":"Point"}
}