{
  "type": "Feature",
  "properties": {
    "iso:country":"US",
    "sg:address":"9123 Ascot Dr",
    "sg:city":"Ypsilanti",
    "sg:classifiers":[
        {
            "category":"Building & Trades",
            "subcategory":"Cleaning & Sanitation",
            "type":"Services"
        }
    ],
    "sg:phone":"+1 734 709 8994",
    "sg:postcode":"48198",
    "sg:province":"MI",
    "sg:tags":[
        "janitorial"
    ],
    "wof:name":"Rock Cleaning",
    "wof:placetype":"venue"
},
  "geometry": {"coordinates":[-83.580625,42.274587],"type":"Point"}
}