{
  "type": "Feature",
  "properties": {
    "iso:country":"US",
    "sg:address":"6636 Broadbridge Rd",
    "sg:city":"Cottrellville",
    "sg:classifiers":[
        {
            "category":"Building & Trades",
            "subcategory":"Construction",
            "type":"Services"
        }
    ],
    "sg:phone":"+1 810 765 8462",
    "sg:postcode":"48039",
    "sg:province":"MI",
    "sg:tags":[
        "water",
        "well",
        "drilling"
    ],
    "wof:name":"Biscorner Well Drilling",
    "wof:placetype":"venue"
},
  "geometry": {"coordinates":[-82.57234099999999,42.688848],"type":"Point"}
}