{
  "type": "Feature",
  "properties": {
    "iso:country":"US",
    "sg:address":"18300 Henry Ct",
    "sg:city":"Ray",
    "sg:classifiers":[
        {
            "category":"Social Services",
            "subcategory":"Child Care",
            "type":"Services"
        }
    ],
    "sg:phone":"+1 586 992 0457",
    "sg:postcode":"48096",
    "sg:province":"MI",
    "sg:tags":[
        "day"
    ],
    "wof:name":"Kelly Marie Battani",
    "wof:placetype":"venue"
},
  "geometry": {"coordinates":[-82.94214599999999,42.734473],"type":"Point"}
}