{
  "type": "Feature",
  "properties": {
    "iso:country":"US",
    "sg:address":"727 28th St SE",
    "sg:city":"Grand Rapids",
    "sg:classifiers":[
        {
            "category":"Shopping",
            "subcategory":"Pharmacy",
            "type":"Retail Goods"
        }
    ],
    "sg:phone":"+1 616 514 5601",
    "sg:postcode":"49548",
    "sg:province":"MI",
    "wof:name":"CVS Pharmacy",
    "wof:placetype":"venue"
},
  "geometry": {"coordinates":[-85.647481,42.912874],"type":"Point"}
}