{
  "type": "Feature",
  "properties": {
    "iso:country":"US",
    "sg:address":"23821 Hazen St",
    "sg:city":"Southfield",
    "sg:classifiers":[
        {
            "category":"Real Estate",
            "subcategory":"Real Estate Agent",
            "type":"Services"
        }
    ],
    "sg:phone":"+1 248 356 5466",
    "sg:postcode":"48033",
    "sg:province":"MI",
    "wof:name":"Burt Realty Co",
    "wof:placetype":"venue"
},
  "geometry": {"coordinates":[-83.279156,42.474374],"type":"Point"}
}