{
  "type": "Feature",
  "properties": {
    "iso:country":"US",
    "sg:address":"43456 Hillsboro Dr",
    "sg:city":"Clinton Twp",
    "sg:classifiers":[
        {
            "category":"Food & Beverages",
            "subcategory":"Specialty",
            "type":"Retail Goods"
        }
    ],
    "sg:phone":"+1 586 228 0799",
    "sg:postcode":"48038",
    "sg:province":"MI",
    "sg:tags":[
        "vitamin"
    ],
    "wof:name":"Phyto Tech",
    "wof:placetype":"venue"
},
  "geometry": {"coordinates":[-82.925698,42.619302],"type":"Point"}
}