{
  "type": "Feature",
  "properties": {
    "iso:country":"US",
    "sg:address":"3648 Shaddick Rd",
    "sg:city":"Waterford",
    "sg:classifiers":[
        {
            "category":"Shopping",
            "subcategory":"Gifts & Souvenirs",
            "type":"Retail Goods"
        }
    ],
    "sg:phone":"+1 248 682 0329",
    "sg:postcode":"48328",
    "sg:province":"MI",
    "wof:name":"Bay Court Collectibles",
    "wof:placetype":"venue"
},
  "geometry": {"coordinates":[-83.362632,42.64976],"type":"Point"}
}