{
  "type": "Feature",
  "properties": {
    "iso:country":"US",
    "sg:address":"32950 Middlebelt Rd",
    "sg:city":"Farmington Hills",
    "sg:classifiers":[
        {
            "category":"Retail",
            "subcategory":"Auto Repair",
            "type":"Services"
        }
    ],
    "sg:phone":"+1 248 865 7805",
    "sg:postcode":"48334",
    "sg:province":"MI",
    "wof:name":"T & M Auto Repair",
    "wof:placetype":"venue"
},
  "geometry": {"coordinates":[-83.340401,42.528801],"type":"Point"}
}