{
  "type": "Feature",
  "properties": {
    "iso:country":"US",
    "sg:address":"14 S Center St",
    "sg:city":"Hartford",
    "sg:classifiers":[
        {
            "category":"Professional",
            "subcategory":"Advertising",
            "type":"Services"
        }
    ],
    "sg:phone":"+1 269 621 3124",
    "sg:postcode":"49057",
    "sg:province":"MI",
    "sg:tags":[
        "distributing",
        "sample"
    ],
    "wof:name":"Miller Thermometer Co",
    "wof:placetype":"venue"
},
  "geometry": {"coordinates":[-86.166815,42.206725],"type":"Point"}
}