{
  "type": "Feature",
  "properties": {
    "iso:country":"US",
    "sg:address":"11758 Sonoma Rd",
    "sg:city":"Battle Creek",
    "sg:classifiers":[
        {
            "category":"Building & Trades",
            "subcategory":"Construction",
            "type":"Services"
        }
    ],
    "sg:phone":"+1 269 979 2586",
    "sg:postcode":"49015",
    "sg:province":"MI",
    "sg:tags":[
        "handyman"
    ],
    "wof:name":"Handyman Services",
    "wof:placetype":"venue"
},
  "geometry": {"coordinates":[-85.21819000000001,42.246694],"type":"Point"}
}