{
  "type": "Feature",
  "properties": {
    "iso:country":"US",
    "sg:address":"24287 Novi Rd",
    "sg:city":"Novi",
    "sg:classifiers":[
        {
            "category":"Shopping",
            "subcategory":"Bicycles & Sporting Goods",
            "type":"Retail Goods"
        }
    ],
    "sg:phone":"+1 248 449 4544",
    "sg:postcode":"48375",
    "sg:province":"MI",
    "wof:name":"Play It Again Sports",
    "wof:placetype":"venue"
},
  "geometry": {"coordinates":[-83.47515799999999,42.472472],"type":"Point"}
}