{
  "type": "Feature",
  "properties": {
    "iso:country":"US",
    "sg:address":"38033 Ford Rd",
    "sg:city":"Westland",
    "sg:classifiers":[
        {
            "category":"Retail",
            "subcategory":"Auto Repair",
            "type":"Services"
        }
    ],
    "sg:phone":"+1 734 721 1980",
    "sg:postcode":"48185",
    "sg:province":"MI",
    "sg:tags":[
        "body",
        "shop"
    ],
    "wof:name":"Knudsen Brothers Collision",
    "wof:placetype":"venue"
},
  "geometry": {"coordinates":[-83.41300200000001,42.323799],"type":"Point"}
}