{
  "type": "Feature",
  "properties": {
    "iso:country":"US",
    "sg:address":"126 W Walnut St",
    "sg:city":"Hastings",
    "sg:classifiers":[
        {
            "category":"Building & Trades",
            "subcategory":"Construction",
            "type":"Services"
        }
    ],
    "sg:phone":"+1 269 945 9929",
    "sg:postcode":"49058",
    "sg:province":"MI",
    "sg:tags":[
        "concrete",
        "contractor"
    ],
    "wof:name":"Hastings Concrete Construction",
    "wof:placetype":"venue"
},
  "geometry": {"coordinates":[-85.2889,42.644959],"type":"Point"}
}