{
  "type": "Feature",
  "properties": {
    "iso:country":"US",
    "sg:address":"9242 E N Ave",
    "sg:city":"Kalamazoo",
    "sg:classifiers":[
        {
            "category":"Building & Trades",
            "subcategory":"Construction",
            "type":"Services"
        }
    ],
    "sg:phone":"+1 269 665 6330",
    "sg:postcode":"49048",
    "sg:province":"MI",
    "sg:tags":[
        "dry wall",
        "contractor"
    ],
    "wof:name":"Dave Moore Drywall",
    "wof:placetype":"venue"
},
  "geometry": {"coordinates":[-85.453813,42.244965],"type":"Point"}
}