{
  "type": "Feature",
  "properties": {
    "iso:country":"US",
    "sg:address":"5588 Montclair St",
    "sg:city":"Detroit",
    "sg:classifiers":[
        {
            "category":"Freight",
            "type":"Transportation"
        }
    ],
    "sg:phone":"+1 313 921 5461",
    "sg:postcode":"48213",
    "sg:province":"MI",
    "wof:name":"Quik Transit Trnsp Svc",
    "wof:placetype":"venue"
},
  "geometry": {"coordinates":[-82.99350800000001,42.390717],"type":"Point"}
}