{
  "type": "Feature",
  "properties": {
    "iso:country":"US",
    "sg:address":"981 W Auburn Rd",
    "sg:city":"Rochester Hills",
    "sg:classifiers":[
        {
            "category":"Retail",
            "subcategory":"Auto Repair",
            "type":"Services"
        }
    ],
    "sg:phone":"+1 248 852 1551",
    "sg:postcode":"48307",
    "sg:province":"MI",
    "sg:tags":[
        "automotive"
    ],
    "wof:name":"Avon Radiator Service",
    "wof:placetype":"venue"
},
  "geometry": {"coordinates":[-83.15129899999999,42.635502],"type":"Point"}
}