{
  "type": "Feature",
  "properties": {
    "iso:country":"US",
    "sg:address":"122 E Maumee St",
    "sg:city":"Adrian",
    "sg:classifiers":[
        {
            "category":"Insurance",
            "subcategory":"Hazard Insurance",
            "type":"Services"
        }
    ],
    "sg:phone":"+1 517 265 7683",
    "sg:postcode":"49221",
    "sg:province":"MI",
    "sg:tags":[
        "employee",
        "benefit",
        "compensation",
        "plan"
    ],
    "sg:website":"www.brbowerscompany.com",
    "wof:name":"B R Bowers & Co",
    "wof:placetype":"venue"
},
  "geometry": {"coordinates":[-84.036142,41.89865],"type":"Point"}
}