{
  "type": "Feature",
  "properties": {
    "iso:country":"US",
    "sg:address":"331 W Main St",
    "sg:city":"Ionia",
    "sg:classifiers":[
        {
            "category":"Home & Garden",
            "subcategory":"Building Materials",
            "type":"Retail Goods"
        }
    ],
    "sg:phone":"+1 616 527 0610",
    "sg:postcode":"48846",
    "sg:province":"MI",
    "sg:tags":[
        "paint"
    ],
    "wof:name":"Jerry's Paint Store",
    "wof:placetype":"venue"
},
  "geometry": {"coordinates":[-85.066664,42.982349],"type":"Point"}
}