{
  "type": "Feature",
  "properties": {
    "iso:country":"US",
    "sg:address":"14316 Michigan Ave",
    "sg:city":"Dearborn",
    "sg:classifiers":[
        {
            "category":"Restaurant",
            "type":"Food & Drink"
        }
    ],
    "sg:phone":"+1 313 584 1515",
    "sg:postcode":"48126",
    "sg:province":"MI",
    "sg:tags":[
        "middle",
        "eastern"
    ],
    "wof:name":"Habib's Cuisine",
    "wof:placetype":"venue"
},
  "geometry": {"coordinates":[-83.181614,42.320606],"type":"Point"}
}