{
  "type": "Feature",
  "properties": {
    "iso:country":"US",
    "sg:address":"15393 15 Mile Rd",
    "sg:city":"Clinton Township",
    "sg:classifiers":[
        {
            "category":"Real Estate",
            "subcategory":"Real Estate Operator",
            "type":"Services"
        }
    ],
    "sg:phone":"+1 586 285 1680",
    "sg:postcode":"48035",
    "sg:province":"MI",
    "sg:tags":[
        "apartment"
    ],
    "wof:name":"Villages of Clinton Pointe",
    "wof:placetype":"venue"
},
  "geometry": {"coordinates":[-82.967196,42.55328],"type":"Point"}
}