{
  "type": "Feature",
  "properties": {
    "iso:country":"US",
    "sg:address":"25121 W 6 Mile Rd",
    "sg:city":"Redford",
    "sg:classifiers":[
        {
            "category":"Health Services",
            "subcategory":"Doctor",
            "type":"Services"
        }
    ],
    "sg:phone":"+1 313 537 0545",
    "sg:postcode":"48240",
    "sg:province":"MI",
    "wof:name":"Richard R Ruggerole DDS",
    "wof:placetype":"venue"
},
  "geometry": {"coordinates":[-83.28889100000001,42.414126],"type":"Point"}
}