{
  "type": "Feature",
  "properties": {
    "iso:country":"US",
    "sg:address":"16140 Woodward Ave",
    "sg:city":"Highland Park",
    "sg:classifiers":[
        {
            "category":"Communications",
            "subcategory":"Newspaper",
            "type":"Services"
        }
    ],
    "sg:phone":"+1 313 866 6020",
    "sg:postcode":"48203",
    "sg:province":"MI",
    "sg:tags":[
        "magazine"
    ],
    "wof:name":"Worldwide News",
    "wof:placetype":"venue"
},
  "geometry": {"coordinates":[-83.102699,42.4142],"type":"Point"}
}