{
  "type": "Feature",
  "properties": {
    "iso:country":"US",
    "sg:address":"839 10th Ave",
    "sg:city":"Menominee",
    "sg:classifiers":[
        {
            "category":"Professional",
            "subcategory":"Management & Consulting",
            "type":"Services"
        }
    ],
    "sg:phone":"+1 906 863 8549",
    "sg:postcode":"49858",
    "sg:province":"MI",
    "sg:tags":[
        "consultant"
    ],
    "wof:name":"Vine Co",
    "wof:placetype":"venue"
},
  "geometry": {"coordinates":[-87.612925,45.107723],"type":"Point"}
}