{
  "type": "Feature",
  "properties": {
    "iso:country":"US",
    "sg:address":"290 1st St",
    "sg:city":"Manistee",
    "sg:classifiers":[
        {
            "category":"Retail",
            "subcategory":"Animal Services",
            "type":"Services"
        }
    ],
    "sg:phone":"+1 231 398 0721",
    "sg:postcode":"49660",
    "sg:province":"MI",
    "sg:tags":[
        "pet",
        "grooming",
        "washing"
    ],
    "wof:name":"Wild Things",
    "wof:placetype":"venue"
},
  "geometry": {"coordinates":[-86.317035,44.24579],"type":"Point"}
}