{
  "type": "Feature",
  "properties": {
    "iso:country":"US",
    "sg:address":"8844 Riverside Dr",
    "sg:city":"Brighton",
    "sg:classifiers":[
        {
            "category":"Autos & Motor Vehicles",
            "subcategory":"Motorcycle Sales",
            "type":"Retail Goods"
        }
    ],
    "sg:phone":"+1 810 231 3769",
    "sg:postcode":"48116",
    "sg:province":"MI",
    "wof:name":"Motorcycle Rider Craft Ltd",
    "wof:placetype":"venue"
},
  "geometry": {"coordinates":[-83.795315,42.474849],"type":"Point"}
}