{
  "type": "Feature",
  "properties": {
    "iso:country":"US",
    "sg:address":"118 S Bridge St",
    "sg:city":"Grand Ledge",
    "sg:classifiers":[
        {
            "category":"Health Services",
            "subcategory":"Doctor",
            "type":"Services"
        }
    ],
    "sg:phone":"+1 517 627 4027",
    "sg:postcode":"48837",
    "sg:province":"MI",
    "wof:name":"Baum Todd DDS",
    "wof:placetype":"venue"
},
  "geometry": {"coordinates":[-84.745099,42.754159],"type":"Point"}
}