{
  "type": "Feature",
  "properties": {
    "iso:country":"US",
    "sg:address":"3858 Shellmar Ln",
    "sg:city":"Bloomfield Hills",
    "sg:classifiers":[
        {
            "category":"Banks & Credit Unions",
            "subcategory":"Investment Brokerage",
            "type":"Services"
        }
    ],
    "sg:phone":"+1 248 203 6556",
    "sg:postcode":"48302",
    "sg:province":"MI",
    "sg:tags":[
        "security"
    ],
    "wof:name":"John Frye Jr Inc",
    "wof:placetype":"venue"
},
  "geometry": {"coordinates":[-83.270286,42.557071],"type":"Point"}
}