{
  "type": "Feature",
  "properties": {
    "iso:country":"US",
    "sg:address":"65 Maple Valley St",
    "sg:city":"Sandusky",
    "sg:classifiers":[
        {
            "category":"Building & Trades",
            "subcategory":"Construction",
            "type":"Services"
        }
    ],
    "sg:phone":"+1 810 648 9114",
    "sg:postcode":"48471",
    "sg:province":"MI",
    "sg:tags":[
        "house"
    ],
    "wof:name":"Ram Builders",
    "wof:placetype":"venue"
},
  "geometry": {"coordinates":[-82.839918,43.419533],"type":"Point"}
}