{
  "type": "Feature",
  "properties": {
    "iso:country":"US",
    "sg:address":"8743 US Hwy 12",
    "sg:city":"Brooklyn",
    "sg:classifiers":[
        {
            "category":"Organizations",
            "subcategory":"Religious Organization",
            "type":"Services"
        },
        {
            "category":"Organizations",
            "subcategory":"Community Association",
            "type":"Services"
        }
    ],
    "sg:phone":"+1 517 467 2183",
    "sg:postcode":"49265",
    "sg:province":"MI",
    "sg:tags":[
        "church"
    ],
    "wof:name":"St Joseph's Shrine",
    "wof:placetype":"venue"
},
  "geometry": {"coordinates":[-84.170354,42.057196],"type":"Point"}
}