{
  "type": "Feature",
  "properties": {
    "iso:country":"US",
    "sg:address":"23906 Dewey Lake St",
    "sg:city":"Dowagiac",
    "sg:classifiers":[
        {
            "category":"Autos & Motor Vehicles",
            "subcategory":"Automobile Sales",
            "type":"Retail Goods"
        }
    ],
    "sg:phone":"+1 269 782 8232",
    "sg:postcode":"49047",
    "sg:province":"MI",
    "sg:tags":[
        "snowmobile"
    ],
    "wof:name":"Glenwood Snowmobile Sales Inc",
    "wof:placetype":"venue"
},
  "geometry": {"coordinates":[-86.02884299999999,42.055847],"type":"Point"}
}