{
  "type": "Feature",
  "properties": {
    "iso:country":"US",
    "sg:address":"626 Romence Rd",
    "sg:city":"Portage",
    "sg:classifiers":[
        {
            "category":"Banks & Credit Unions",
            "subcategory":"Bank",
            "type":"Services"
        }
    ],
    "sg:phone":"+1 269 321 0700",
    "sg:postcode":"49024",
    "sg:province":"MI",
    "sg:tags":[
        "loan",
        "real estate"
    ],
    "sg:website":"www.mimf.net",
    "wof:name":"Michigan Mortgage Funding",
    "wof:placetype":"venue"
},
  "geometry": {"coordinates":[-85.59286,42.215614],"type":"Point"}
}