{
  "type": "Feature",
  "properties": {
    "iso:country":"US",
    "sg:address":"6700 E Davison St",
    "sg:city":"Hamtramck",
    "sg:classifiers":[
        {
            "category":"Restaurant",
            "type":"Food & Drink"
        }
    ],
    "sg:phone":"+1 313 365 5611",
    "sg:postcode":"48212",
    "sg:province":"MI",
    "wof:name":"National Coney Island Chili Company Inc",
    "wof:placetype":"venue"
},
  "geometry": {"coordinates":[-83.03330200000001,42.423302],"type":"Point"}
}