{
  "type": "Feature",
  "properties": {
    "iso:country":"US",
    "sg:address":"132 Brady St",
    "sg:city":"Allegan",
    "sg:classifiers":[
        {
            "category":"Bars & Pubs",
            "type":"Food & Drink"
        },
        {
            "category":"Restaurant",
            "type":"Food & Drink"
        }
    ],
    "sg:menulink":"http://www.allmenus.com/mi/allegan/47739-sherwoods-cove/menu/",
    "sg:phone":"+1 269 686 0033",
    "sg:postcode":"49010",
    "sg:province":"MI",
    "sg:tags":[
        "food",
        "american",
        "pub"
    ],
    "wof:name":"Sherwood's Cove",
    "wof:placetype":"venue"
},
  "geometry": {"coordinates":[-85.848315,42.526757],"type":"Point"}
}