{
  "type": "Feature",
  "properties": {
    "iso:country":"US",
    "sg:address":"601 Ely St",
    "sg:city":"Allegan",
    "sg:classifiers":[
        {
            "category":"Health Services",
            "subcategory":"Health Practitioner",
            "type":"Services"
        }
    ],
    "sg:phone":"+1 269 673 7036",
    "sg:postcode":"49010",
    "sg:province":"MI",
    "wof:name":"Healing Touch",
    "wof:placetype":"venue"
},
  "geometry": {"coordinates":[-85.861591,42.522601],"type":"Point"}
}