{
  "type": "Feature",
  "properties": {
    "iso:country":"US",
    "sg:address":"3101 Page Ave",
    "sg:city":"Jackson",
    "sg:classifiers":[
        {
            "category":"Manufacturing",
            "subcategory":"Printing",
            "type":"Manufacturing & Wholesale Goods"
        }
    ],
    "sg:phone":"+1 517 784 1772",
    "sg:postcode":"49203",
    "sg:province":"MI",
    "sg:tags":[
        "publisher"
    ],
    "sg:website":"www.smarttan.com",
    "wof:name":"International Smart Tan",
    "wof:placetype":"venue"
},
  "geometry": {"coordinates":[-84.363711,42.240494],"type":"Point"}
}