{
  "type": "Feature",
  "properties": {
    "iso:country":"US",
    "sg:address":"12793 S Saginaw St",
    "sg:city":"Grand Blanc",
    "sg:classifiers":[
        {
            "category":"Restaurant",
            "type":"Food & Drink"
        }
    ],
    "sg:phone":"+1 810 603 2711",
    "sg:postcode":"48439",
    "sg:province":"MI",
    "sg:website":"www.kruseandmuerrestaurants.com",
    "wof:name":"Kruse & Muer",
    "wof:placetype":"venue"
},
  "geometry": {"coordinates":[-83.61685300000001,42.917777],"type":"Point"}
}