{
  "type": "Feature",
  "properties": {
    "iso:country":"US",
    "sg:address":"7805 Carpenter",
    "sg:city":"Utica",
    "sg:classifiers":[
        {
            "category":"Professional",
            "subcategory":"Business Services",
            "type":"Services"
        }
    ],
    "sg:phone":"+1 586 731 3941",
    "sg:postcode":"48317",
    "sg:province":"MI",
    "wof:name":"Noved Design Technologies",
    "wof:placetype":"venue"
},
  "geometry": {"coordinates":[-83.032804,42.635361],"type":"Point"}
}