{
  "type": "Feature",
  "properties": {
    "iso:country":"US",
    "sg:address":"5661 US Hwy 23",
    "sg:city":"Oscoda",
    "sg:classifiers":[
        {
            "category":"Autos & Motor Vehicles",
            "subcategory":"Automobile Sales",
            "type":"Retail Goods"
        }
    ],
    "sg:phone":"+1 989 739 2265",
    "sg:postcode":"48750",
    "sg:province":"MI",
    "sg:tags":[
        "car",
        "dealer"
    ],
    "wof:name":"Oscoda Auto Village",
    "wof:placetype":"venue"
},
  "geometry": {"coordinates":[-83.330152,44.446703],"type":"Point"}
}