{
  "type": "Feature",
  "properties": {
    "iso:country":"US",
    "sg:address":"941 W Milham Rd",
    "sg:city":"Portage",
    "sg:classifiers":[
        {
            "category":"Real Estate",
            "subcategory":"Real Estate Services",
            "type":"Services"
        }
    ],
    "sg:phone":"+1 269 321 3055",
    "sg:postcode":"49024",
    "sg:province":"MI",
    "sg:tags":[
        "company",
        "title"
    ],
    "wof:name":"Chicago Title Insurance Co",
    "wof:placetype":"venue"
},
  "geometry": {"coordinates":[-85.601161,42.229981],"type":"Point"}
}