{
  "type": "Feature",
  "properties": {
    "iso:country":"US",
    "sg:address":"20 Superior St",
    "sg:city":"Hillsdale",
    "sg:classifiers":[
        {
            "category":"Retail",
            "subcategory":"Repair Shop",
            "type":"Services"
        }
    ],
    "sg:phone":"+1 517 437 4800",
    "sg:postcode":"49242",
    "sg:province":"MI",
    "sg:tags":[
        "welding"
    ],
    "wof:name":"Autorack Technologies",
    "wof:placetype":"venue"
},
  "geometry": {"coordinates":[-84.620807,41.921107],"type":"Point"}
}