{
  "type": "Feature",
  "properties": {
    "iso:country":"US",
    "sg:address":"124 E Main St",
    "sg:city":"Stockbridge",
    "sg:classifiers":[
        {
            "category":"Personal",
            "subcategory":"Beauty Salon",
            "type":"Services"
        }
    ],
    "sg:phone":"+1 517 851 7062",
    "sg:postcode":"49285",
    "sg:province":"MI",
    "wof:name":"Kim & Co",
    "wof:placetype":"venue"
},
  "geometry": {"coordinates":[-84.17915600000001,42.451317],"type":"Point"}
}