{
  "type": "Feature",
  "properties": {
    "iso:country":"US",
    "sg:address":"49835 Guy Dr",
    "sg:city":"Macomb",
    "sg:classifiers":[
        {
            "category":"Health Services",
            "subcategory":"Health Practitioner",
            "type":"Services"
        }
    ],
    "sg:phone":"+1 586 226 0750",
    "sg:postcode":"48044",
    "sg:province":"MI",
    "wof:name":"Nourishing Life",
    "wof:placetype":"venue"
},
  "geometry": {"coordinates":[-82.945626,42.662885],"type":"Point"}
}