{
  "type": "Feature",
  "properties": {
    "iso:country":"US",
    "sg:address":"59639 Glacier Ridge S",
    "sg:city":"Washington",
    "sg:classifiers":[
        {
            "category":"Building & Trades",
            "subcategory":"Construction",
            "type":"Services"
        }
    ],
    "sg:phone":"+1 586 992 2757",
    "sg:postcode":"48094",
    "sg:province":"MI",
    "sg:tags":[
        "painter"
    ],
    "wof:name":"Faux Focus",
    "wof:placetype":"venue"
},
  "geometry": {"coordinates":[-83.043329,42.732731],"type":"Point"}
}