{
  "type": "Feature",
  "properties": {
    "iso:country":"US",
    "sg:address":"137 S Benzie Blvd",
    "sg:city":"Beulah",
    "sg:classifiers":[
        {
            "category":"Professional",
            "subcategory":"Accounting & Tax Preparation",
            "type":"Services"
        }
    ],
    "sg:phone":"+1 231 882 7809",
    "sg:postcode":"49617",
    "sg:province":"MI",
    "sg:tags":[
        "accountant"
    ],
    "wof:name":"Jean Luedtke Accounting & Bkpg",
    "wof:placetype":"venue"
},
  "geometry": {"coordinates":[-86.093756,44.629881],"type":"Point"}
}