{
  "type": "Feature",
  "properties": {
    "iso:country":"US",
    "sg:address":"11049 Jackson St",
    "sg:city":"Taylor",
    "sg:classifiers":[
        {
            "category":"Building & Trades",
            "subcategory":"Locksmith",
            "type":"Services"
        }
    ],
    "sg:phone":"+1 734 288 5571",
    "sg:postcode":"48180",
    "sg:province":"MI",
    "sg:tags":[
        "key"
    ],
    "wof:name":"Locksmith All Day",
    "wof:placetype":"venue"
},
  "geometry": {"coordinates":[-83.232095,42.227182],"type":"Point"}
}