{
  "type": "Feature",
  "properties": {
    "iso:country":"US",
    "sg:address":"102 W Mill St",
    "sg:city":"Capac",
    "sg:classifiers":[
        {
            "category":"Government",
            "subcategory":"Post Office",
            "type":"Public Place"
        }
    ],
    "sg:phone":"+1 810 395 7090",
    "sg:postcode":"48014",
    "sg:province":"MI",
    "wof:name":"US Post Office",
    "wof:placetype":"venue"
},
  "geometry": {"coordinates":[-82.929237,43.012605],"type":"Point"}
}