{
  "type": "Feature",
  "properties": {
    "iso:country":"US",
    "sg:address":"34301 Fairfax Ct",
    "sg:city":"Livonia",
    "sg:classifiers":[
        {
            "category":"Building & Trades",
            "subcategory":"Construction",
            "type":"Services"
        }
    ],
    "sg:phone":"+1 248 442 7837",
    "sg:postcode":"48152",
    "sg:province":"MI",
    "sg:tags":[
        "interior",
        "painting"
    ],
    "wof:name":"G M Painting Inc",
    "wof:placetype":"venue"
},
  "geometry": {"coordinates":[-83.38407100000001,42.431435],"type":"Point"}
}