{
  "type": "Feature",
  "properties": {
    "iso:country":"US",
    "sg:address":"1691 Hayes",
    "sg:city":"Ortonville",
    "sg:classifiers":[
        {
            "category":"Building & Trades",
            "subcategory":"Construction",
            "type":"Services"
        }
    ],
    "sg:phone":"+1 248 627 6756",
    "sg:postcode":"48462",
    "sg:province":"MI",
    "sg:tags":[
        "contractor"
    ],
    "wof:name":"Walter Dixon Exterior Designs",
    "wof:placetype":"venue"
},
  "geometry": {"coordinates":[-83.40097299999999,42.827139],"type":"Point"}
}