{
  "type": "Feature",
  "properties": {
    "iso:country":"US",
    "sg:address":"15041 Tireman Ave",
    "sg:city":"Dearborn",
    "sg:classifiers":[
        {
            "category":"Health Services",
            "subcategory":"Clinic",
            "type":"Services"
        }
    ],
    "sg:phone":"+1 313 584 3903",
    "sg:postcode":"48126",
    "sg:province":"MI",
    "sg:tags":[
        "welfare"
    ],
    "wof:name":"Sams Auto Clinic",
    "wof:placetype":"venue"
},
  "geometry": {"coordinates":[-83.191711,42.350983],"type":"Point"}
}