{
  "type": "Feature",
  "properties": {
    "iso:country":"US",
    "sg:address":"1610 S Main St",
    "sg:city":"Chelsea",
    "sg:classifiers":[
        {
            "category":"Restaurant",
            "type":"Food & Drink"
        }
    ],
    "sg:menulink":"http://www.allmenus.com/mi/chelsea/26387-big-boy-restaurants/menu/",
    "sg:phone":"+1 734 475 8603",
    "sg:postcode":"48118",
    "sg:province":"MI",
    "sg:tags":[
        "sandwich",
        "salad",
        "burger",
        "dog",
        "soup",
        "hot",
        "wrap",
        "american"
    ],
    "wof:name":"Big Boy Restaurants",
    "wof:placetype":"venue"
},
  "geometry": {"coordinates":[-84.024289,42.299738],"type":"Point"}
}