{
  "type": "Feature",
  "properties": {
    "iso:country":"US",
    "sg:address":"2000 S Mission St",
    "sg:city":"Mount Pleasant",
    "sg:classifiers":[
        {
            "category":"Autos & Motor Vehicles",
            "subcategory":"Motorcycle Sales",
            "type":"Retail Goods"
        }
    ],
    "sg:phone":"+1 989 773 4222",
    "sg:postcode":"48858",
    "sg:province":"MI",
    "sg:tags":[
        "equipment",
        "electrical",
        "repair"
    ],
    "wof:name":"Cactus Club",
    "wof:placetype":"venue"
},
  "geometry": {"coordinates":[-84.76746,43.582584],"type":"Point"}
}