{
  "type": "Feature",
  "properties": {
    "iso:country":"US",
    "sg:address":"87 Aniline Ave S",
    "sg:city":"Holland",
    "sg:classifiers":[
        {
            "category":"Wholesale",
            "subcategory":"Home Furnishings",
            "type":"Manufacturing & Wholesale Goods"
        }
    ],
    "sg:phone":"+1 616 396 4842",
    "sg:postcode":"49424",
    "sg:province":"MI",
    "sg:tags":[
        "picture",
        "frame"
    ],
    "wof:name":"Great Lakes Albums",
    "wof:placetype":"venue"
},
  "geometry": {"coordinates":[-86.12697900000001,42.796478],"type":"Point"}
}