{
  "type": "Feature",
  "properties": {
    "iso:country":"US",
    "sg:address":"4253 Ridgewood Dr",
    "sg:city":"Ypsilanti",
    "sg:classifiers":[
        {
            "category":"Real Estate",
            "subcategory":"Real Estate Agent",
            "type":"Services"
        }
    ],
    "sg:phone":"+1 734 717 7214",
    "sg:postcode":"48197",
    "sg:province":"MI",
    "wof:name":"Red Brick Properties",
    "wof:placetype":"venue"
},
  "geometry": {"coordinates":[-83.67503600000001,42.227021],"type":"Point"}
}