{
  "type": "Feature",
  "properties": {
    "iso:country":"US",
    "sg:address":"3401 N",
    "sg:city":"Franklin",
    "sg:classifiers":[
        {
            "category":"Autos & Motor Vehicles",
            "subcategory":"Auto Supplies",
            "type":"Retail Goods"
        }
    ],
    "sg:phone":"+1 810 341 6677",
    "sg:postcode":"48025",
    "sg:province":"MI",
    "sg:tags":[
        "glass"
    ],
    "wof:name":"Dave's Auto Glass",
    "wof:placetype":"venue"
},
  "geometry": {"coordinates":[-83.66520300000001,43.045426],"type":"Point"}
}