{
  "type": "Feature",
  "properties": {
    "iso:country":"US",
    "sg:address":"24901 Kelly Rd",
    "sg:city":"Eastpointe",
    "sg:classifiers":[
        {
            "category":"Health Services",
            "subcategory":"Doctor",
            "type":"Services"
        }
    ],
    "sg:phone":"+1 586 772 9148",
    "sg:postcode":"48021",
    "sg:province":"MI",
    "sg:tags":[
        "physician",
        "surgeon"
    ],
    "wof:name":"East Point Family Physicians",
    "wof:placetype":"venue"
},
  "geometry": {"coordinates":[-82.92727499999999,42.479392],"type":"Point"}
}