{
  "type": "Feature",
  "properties": {
    "iso:country":"US",
    "sg:address":"850 N Rochester Rd",
    "sg:city":"Clawson",
    "sg:classifiers":[
        {
            "category":"Retail",
            "subcategory":"Auto Repair",
            "type":"Services"
        }
    ],
    "sg:phone":"+1 248 589 3600",
    "sg:postcode":"48017",
    "sg:province":"MI",
    "sg:tags":[
        "body",
        "shop",
        "automobile",
        "collision",
        "automotive",
        "painting"
    ],
    "wof:name":"Collision Concepts",
    "wof:placetype":"venue"
},
  "geometry": {"coordinates":[-83.134201,42.5401],"type":"Point"}
}