{
  "type": "Feature",
  "properties": {
    "iso:country":"US",
    "sg:address":"423 1st St NW",
    "sg:city":"Grand Rapids",
    "sg:classifiers":[
        {
            "category":"Organizations",
            "subcategory":"Religious Organization",
            "type":"Services"
        }
    ],
    "sg:phone":"+1 616 459 7390",
    "sg:postcode":"49504",
    "sg:province":"MI",
    "sg:tags":[
        "church"
    ],
    "wof:name":"St Mary's",
    "wof:placetype":"venue"
},
  "geometry": {"coordinates":[-85.678887,42.971644],"type":"Point"}
}