{
  "type": "Feature",
  "properties": {
    "iso:country":"US",
    "sg:address":"201 E Main St",
    "sg:city":"Boyne City",
    "sg:classifiers":[
        {
            "category":"Education",
            "subcategory":"Library",
            "type":"Public Place"
        }
    ],
    "sg:phone":"+1 231 582 7861",
    "sg:postcode":"49712",
    "sg:province":"MI",
    "wof:name":"Boyne District Library",
    "wof:placetype":"venue"
},
  "geometry": {"coordinates":[-85.013311,45.211856],"type":"Point"}
}