{
  "type": "Feature",
  "properties": {
    "iso:country":"US",
    "sg:address":"2338 Lakes North Dr",
    "sg:city":"Interlochen",
    "sg:classifiers":[
        {
            "category":"Freight",
            "type":"Transportation"
        }
    ],
    "sg:phone":"+1 231 943 8557",
    "sg:postcode":"49643",
    "sg:province":"MI",
    "sg:tags":[
        "company",
        "trucking"
    ],
    "wof:name":"Ljp Cartage",
    "wof:placetype":"venue"
},
  "geometry": {"coordinates":[-85.78901999999999,44.657687],"type":"Point"}
}