{
  "type": "Feature",
  "properties": {
    "iso:country":"US",
    "sg:address":"900 Pannell St NW",
    "sg:city":"Grand Rapids",
    "sg:classifiers":[
        {
            "category":"Manufacturing",
            "subcategory":"Tools & Machinery",
            "type":"Manufacturing & Wholesale Goods"
        }
    ],
    "sg:phone":"+1 616 361 2842",
    "sg:postcode":"49504",
    "sg:province":"MI",
    "sg:tags":[
        "designed",
        "built"
    ],
    "wof:name":"Hansen Machine & Tool",
    "wof:placetype":"venue"
},
  "geometry": {"coordinates":[-85.693179,43.00053],"type":"Point"}
}