{
  "type": "Feature",
  "properties": {
    "iso:country":"US",
    "sg:address":"6772 Shenandoah Ave",
    "sg:city":"Allen Park",
    "sg:classifiers":[
        {
            "category":"Shopping",
            "subcategory":"Gifts & Souvenirs",
            "type":"Retail Goods"
        }
    ],
    "sg:phone":"+1 313 386 7694",
    "sg:postcode":"48101",
    "sg:province":"MI",
    "wof:name":"Sir James Gift Shop",
    "wof:placetype":"venue"
},
  "geometry": {"coordinates":[-83.220527,42.258468],"type":"Point"}
}