{
  "type": "Feature",
  "properties": {
    "iso:country":"US",
    "sg:address":"6179 Snyder Rd",
    "sg:city":"Berrien Springs",
    "sg:classifiers":[
        {
            "category":"Freight",
            "type":"Transportation"
        }
    ],
    "sg:phone":"+1 269 471 5256",
    "sg:postcode":"49103",
    "sg:province":"MI",
    "sg:tags":[
        "operator",
        "trucking"
    ],
    "wof:name":"K P Transport",
    "wof:placetype":"venue"
},
  "geometry": {"coordinates":[-86.30362100000001,41.926726],"type":"Point"}
}