{
  "type": "Feature",
  "properties": {
    "iso:country":"US",
    "sg:address":"47799 Halyard Dr",
    "sg:city":"Plymouth",
    "sg:classifiers":[
        {
            "category":"Professional",
            "subcategory":"Management & Consulting",
            "type":"Services"
        }
    ],
    "sg:phone":"+1 734 454 2000",
    "sg:postcode":"48170",
    "sg:province":"MI",
    "sg:tags":[
        "sales"
    ],
    "wof:name":"Auto & Lubr Expertise Ctr",
    "wof:placetype":"venue"
},
  "geometry": {"coordinates":[-83.519319,42.383772],"type":"Point"}
}