{
  "type": "Feature",
  "properties": {
    "iso:country":"US",
    "sg:address":"4966 Russcher Rd",
    "sg:city":"Holland",
    "sg:classifiers":[
        {
            "category":"Building & Trades",
            "subcategory":"Plumbing",
            "type":"Services"
        }
    ],
    "sg:phone":"+1 269 751 4044",
    "sg:postcode":"49423",
    "sg:province":"MI",
    "sg:tags":[
        "plumbing",
        "contractor"
    ],
    "wof:name":"Doug Wedeven Plumbing",
    "wof:placetype":"venue"
},
  "geometry": {"coordinates":[-86.030299,42.72919],"type":"Point"}
}