{
  "type": "Feature",
  "properties": {
    "iso:country":"US",
    "sg:address":"250 S Dexter St",
    "sg:city":"Pinckney",
    "sg:classifiers":[
        {
            "category":"Retail",
            "subcategory":"Repair Shop",
            "type":"Services"
        }
    ],
    "sg:phone":"+1 734 878 3233",
    "sg:postcode":"48169",
    "sg:province":"MI",
    "wof:name":"Pinckney Small Engines Repair",
    "wof:placetype":"venue"
},
  "geometry": {"coordinates":[-83.93669199999999,42.455242],"type":"Point"}
}