{
  "type": "Feature",
  "properties": {
    "iso:country":"US",
    "sg:address":"4 N Saginaw St",
    "sg:city":"Pontiac",
    "sg:classifiers":[
        {
            "category":"Communications",
            "subcategory":"Film & Video Production",
            "type":"Services"
        }
    ],
    "sg:phone":"+1 248 333 0080",
    "sg:postcode":"48342",
    "sg:province":"MI",
    "sg:tags":[
        "television",
        "commercial"
    ],
    "wof:name":"Oracle Audio",
    "wof:placetype":"venue"
},
  "geometry": {"coordinates":[-83.29217300000001,42.637591],"type":"Point"}
}