{
  "type": "Feature",
  "properties": {
    "iso:country":"US",
    "sg:address":"32626 7 Mile Rd",
    "sg:city":"Livonia",
    "sg:classifiers":[
        {
            "category":"Insurance",
            "subcategory":"Health Insurance",
            "type":"Services"
        }
    ],
    "sg:phone":"+1 248 615 0094",
    "sg:postcode":"48152",
    "sg:province":"MI",
    "sg:tags":[
        "market"
    ],
    "wof:name":"Revolutionary Nutrition",
    "wof:placetype":"venue"
},
  "geometry": {"coordinates":[-83.369152,42.426426],"type":"Point"}
}