{
  "type": "Feature",
  "properties": {
    "iso:country":"US",
    "sg:address":"612 Carpenter Ave",
    "sg:city":"Iron Mountain",
    "sg:classifiers":[
        {
            "category":"Organizations",
            "subcategory":"Religious Organization",
            "type":"Services"
        }
    ],
    "sg:phone":"+1 906 779 1387",
    "sg:postcode":"49801",
    "sg:province":"MI",
    "sg:tags":[
        "church"
    ],
    "sg:website":"www.newhopecog.org",
    "wof:name":"New Hope Church Of God",
    "wof:placetype":"venue"
},
  "geometry": {"coordinates":[-88.06844599999999,45.817446],"type":"Point"}
}