{
  "type": "Feature",
  "properties": {
    "iso:country":"US",
    "sg:address":"37837 Terra Mar St",
    "sg:city":"Harrison Twp",
    "sg:classifiers":[
        {
            "category":"Building & Trades",
            "subcategory":"Construction",
            "type":"Services"
        }
    ],
    "sg:phone":"+1 586 469 1777",
    "sg:postcode":"48045",
    "sg:province":"MI",
    "sg:tags":[
        "roofing",
        "contractor"
    ],
    "wof:name":"Ducky Roofing Co",
    "wof:placetype":"venue"
},
  "geometry": {"coordinates":[-82.816322,42.575334],"type":"Point"}
}