{
  "type": "Feature",
  "properties": {
    "iso:country":"US",
    "sg:address":"3635 Heron Hollow",
    "sg:city":"Lowell",
    "sg:classifiers":[
        {
            "category":"Real Estate",
            "subcategory":"Developer",
            "type":"Services"
        }
    ],
    "sg:phone":"+1 616 794 7193",
    "sg:postcode":"49331",
    "sg:province":"MI",
    "wof:name":"Sand Crane Ridge",
    "wof:placetype":"venue"
},
  "geometry": {"coordinates":[-85.328242,43.031771],"type":"Point"}
}