{
  "type": "Feature",
  "properties": {
    "iso:country":"US",
    "sg:address":"116 E Main St",
    "sg:city":"Boyne City",
    "sg:classifiers":[
        {
            "category":"Home & Garden",
            "subcategory":"Hardware",
            "type":"Retail Goods"
        }
    ],
    "sg:phone":"+1 231 582 3272",
    "sg:postcode":"49712",
    "sg:province":"MI",
    "sg:tags":[
        "a",
        "lock",
        "alarm",
        "system",
        "accessory",
        "locksmith"
    ],
    "wof:name":"Ats",
    "wof:placetype":"venue"
},
  "geometry": {"coordinates":[-85.01474399999999,45.211809],"type":"Point"}
}