{
  "type": "Feature",
  "properties": {
    "iso:country":"US",
    "sg:address":"9500 Banner St",
    "sg:city":"Taylor",
    "sg:classifiers":[
        {
            "category":"Professional",
            "subcategory":"Employment Agencies",
            "type":"Services"
        }
    ],
    "sg:phone":"+1 313 291 4888",
    "sg:postcode":"48180",
    "sg:province":"MI",
    "wof:name":"St Alfreds St Vincent Depaul Soc",
    "wof:placetype":"venue"
},
  "geometry": {"coordinates":[-83.271896,42.2383],"type":"Point"}
}