{
  "type": "Feature",
  "properties": {
    "iso:country":"US",
    "sg:address":"36888 Van Dyke Ave",
    "sg:city":"Sterling Heights",
    "sg:classifiers":[
        {
            "category":"Fast Food",
            "type":"Food & Drink"
        }
    ],
    "sg:phone":"+1 586 264 8700",
    "sg:postcode":"48312",
    "sg:province":"MI",
    "wof:name":"Sonic Drive-in",
    "wof:placetype":"venue"
},
  "geometry": {"coordinates":[-83.02942400000001,42.564816],"type":"Point"}
}