{
  "type": "Feature",
  "properties": {
    "iso:country":"US",
    "sg:address":"224 Plymouth Beach Dr",
    "sg:city":"Indian River",
    "sg:classifiers":[
        {
            "category":"Travel",
            "subcategory":"Hotels & Motels",
            "type":"Entertainment"
        }
    ],
    "sg:phone":"+1 231 238 0200",
    "sg:postcode":"49749",
    "sg:province":"MI",
    "sg:tags":[
        "breakfast",
        "accommodation",
        "bed"
    ],
    "wof:name":"Kristin Place On Burt Lake",
    "wof:placetype":"venue"
},
  "geometry": {"coordinates":[-84.622953,45.453652],"type":"Point"}
}