{
  "type": "Feature",
  "properties": {
    "iso:country":"US",
    "sg:address":"1357 S Main St",
    "sg:city":"Adrian",
    "sg:classifiers":[
        {
            "category":"Shopping",
            "subcategory":"Clothing, Apparel, & Fashions",
            "type":"Retail Goods"
        }
    ],
    "sg:phone":"+1 517 265 8003",
    "sg:postcode":"49221",
    "sg:province":"MI",
    "sg:tags":[
        "sportswear"
    ],
    "sg:website":"www.finishline.com",
    "wof:name":"Finish Line",
    "wof:placetype":"venue"
},
  "geometry": {"coordinates":[-84.04313500000001,41.878819],"type":"Point"}
}