{
  "type": "Feature",
  "properties": {
    "iso:country":"US",
    "sg:address":"1380 Coolidge Hwy Ste 180",
    "sg:city":"Troy",
    "sg:classifiers":[
        {
            "category":"Health Services",
            "subcategory":"Doctor",
            "type":"Services"
        },
        {
            "category":"Health Services",
            "subcategory":"Health Practitioner",
            "type":"Services"
        }
    ],
    "sg:phone":"+1 248 435 8420",
    "sg:postcode":"48084",
    "sg:province":"MI",
    "sg:tags":[
        "medicine",
        "sport",
        "therapy",
        "physical"
    ],
    "sg:website":"www.healthcareteampc.com",
    "wof:name":"Health Care Team PC",
    "wof:placetype":"venue"
},
  "geometry": {"coordinates":[-83.18514999999999,42.545295],"type":"Point"}
}