{
  "type": "Feature",
  "properties": {
    "iso:country":"US",
    "sg:address":"41610 Belknapp Dr",
    "sg:city":"Clinton Township",
    "sg:classifiers":[
        {
            "category":"Retail",
            "subcategory":"Laundry & Dry Cleaning",
            "type":"Services"
        }
    ],
    "sg:phone":"+1 586 263 0544",
    "sg:postcode":"48038",
    "sg:province":"MI",
    "wof:name":"Creative Heart",
    "wof:placetype":"venue"
},
  "geometry": {"coordinates":[-82.925444,42.604193],"type":"Point"}
}