{
  "type": "Feature",
  "properties": {
    "iso:country":"US",
    "sg:address":"709 S State Rd # A",
    "sg:city":"Davison",
    "sg:classifiers":[
        {
            "category":"Health Services",
            "subcategory":"Optometrist",
            "type":"Services"
        }
    ],
    "sg:phone":"+1 810 653 4800",
    "sg:postcode":"48423",
    "sg:province":"MI",
    "wof:name":"Davison Vision Center",
    "wof:placetype":"venue"
},
  "geometry": {"coordinates":[-83.517601,43.023201],"type":"Point"}
}