{
  "type": "Feature",
  "properties": {
    "iso:country":"US",
    "sg:address":"100 Rosewood Manor Dr",
    "sg:city":"Flint",
    "sg:classifiers":[
        {
            "category":"Real Estate",
            "subcategory":"Real Estate Operator",
            "type":"Services"
        }
    ],
    "sg:phone":"+1 810 787 4270",
    "sg:postcode":"48505",
    "sg:province":"MI",
    "sg:tags":[
        "apartment"
    ],
    "wof:name":"Rosewood Manor Ld",
    "wof:placetype":"venue"
},
  "geometry": {"coordinates":[-83.70620700000001,43.064907],"type":"Point"}
}