{
  "type": "Feature",
  "properties": {
    "iso:country":"US",
    "sg:address":"208 W Main St",
    "sg:city":"Gobles",
    "sg:classifiers":[
        {
            "category":"Retail",
            "subcategory":"Funeral Services",
            "type":"Services"
        }
    ],
    "sg:phone":"+1 269 628 2852",
    "sg:postcode":"49055",
    "sg:province":"MI",
    "sg:tags":[
        "director"
    ],
    "wof:name":"D L Miller Funeral Home",
    "wof:placetype":"venue"
},
  "geometry": {"coordinates":[-85.88134700000001,42.358656],"type":"Point"}
}