{
  "type": "Feature",
  "properties": {
    "iso:country":"US",
    "sg:address":"928 N Marion Dr",
    "sg:city":"Traverse City",
    "sg:classifiers":[
        {
            "category":"Building & Trades",
            "subcategory":"Landscaping Services",
            "type":"Services"
        }
    ],
    "sg:phone":"+1 231 275 2722",
    "sg:postcode":"49686",
    "sg:province":"MI",
    "sg:tags":[
        "designer",
        "landscape"
    ],
    "wof:name":"Environmental Planning Assoc",
    "wof:placetype":"venue"
},
  "geometry": {"coordinates":[-85.55611500000001,44.839302],"type":"Point"}
}