{
  "type": "Feature",
  "properties": {
    "iso:country":"US",
    "sg:address":"555 S Meridian Rd",
    "sg:city":"Hudson",
    "sg:classifiers":[
        {
            "category":"Retail",
            "subcategory":"Auto Repair",
            "type":"Services"
        }
    ],
    "sg:phone":"+1 517 448 4090",
    "sg:postcode":"49247",
    "sg:province":"MI",
    "sg:tags":[
        "repairing",
        "automobile",
        "general"
    ],
    "wof:name":"Winn's Automotive",
    "wof:placetype":"venue"
},
  "geometry": {"coordinates":[-84.361701,41.846919],"type":"Point"}
}