{
  "type": "Feature",
  "properties": {
    "iso:country":"US",
    "sg:address":"5063 Kasemeyer Rd",
    "sg:city":"Bay City",
    "sg:classifiers":[
        {
            "category":"Building & Trades",
            "subcategory":"Electrical",
            "type":"Services"
        }
    ],
    "sg:phone":"+1 989 684 1371",
    "sg:postcode":"48706",
    "sg:province":"MI",
    "sg:tags":[
        "electric",
        "contractor"
    ],
    "wof:name":"Paul Peil Electric",
    "wof:placetype":"venue"
},
  "geometry": {"coordinates":[-83.925296,43.594638],"type":"Point"}
}