{
  "type": "Feature",
  "properties": {
    "iso:country":"US",
    "sg:address":"2450 Oakdale Dr",
    "sg:city":"Ann Arbor",
    "sg:classifiers":[
        {
            "category":"Real Estate",
            "subcategory":"Real Estate Agent",
            "type":"Services"
        }
    ],
    "sg:phone":"+1 734 677 4334",
    "sg:postcode":"48108",
    "sg:province":"MI",
    "wof:name":"Health Training Ann or Hth",
    "wof:placetype":"venue"
},
  "geometry": {"coordinates":[-83.672907,42.251368],"type":"Point"}
}