{
  "type": "Feature",
  "properties": {
    "iso:country":"US",
    "sg:address":"5108 S Westnedge Ave",
    "sg:city":"Portage",
    "sg:classifiers":[
        {
            "category":"Freight",
            "type":"Transportation"
        }
    ],
    "sg:phone":"+1 269 385 9782",
    "sg:postcode":"49002",
    "sg:province":"MI",
    "sg:tags":[
        "delivery"
    ],
    "wof:name":"Huffy",
    "wof:placetype":"venue"
},
  "geometry": {"coordinates":[-85.58967199999999,42.243901],"type":"Point"}
}