{
  "type": "Feature",
  "properties": {
    "iso:country":"US",
    "sg:address":"21575 W 10 Mile Rd",
    "sg:city":"Southfield",
    "sg:classifiers":[
        {
            "category":"Organizations",
            "subcategory":"Non-profit Organization",
            "type":"Services"
        }
    ],
    "sg:phone":"+1 248 223 0096",
    "sg:postcode":"48075",
    "sg:province":"MI",
    "sg:tags":[
        "lesbian",
        "gay"
    ],
    "wof:name":"That All May Freely Serve",
    "wof:placetype":"venue"
},
  "geometry": {"coordinates":[-83.25611000000001,42.472485],"type":"Point"}
}