{
  "type": "Feature",
  "properties": {
    "iso:country":"US",
    "sg:address":"19548 Appoline St",
    "sg:city":"Detroit",
    "sg:classifiers":[
        {
            "category":"Social Services",
            "subcategory":"Adult Care",
            "type":"Services"
        }
    ],
    "sg:phone":"+1 313 861 6825",
    "sg:postcode":"48235",
    "sg:province":"MI",
    "sg:tags":[
        "residential",
        "travel",
        "agency"
    ],
    "wof:name":"Francine Archer",
    "wof:placetype":"venue"
},
  "geometry": {"coordinates":[-83.17195,42.434897],"type":"Point"}
}