{
  "type": "Feature",
  "properties": {
    "iso:country":"US",
    "sg:address":"2100 W Big Beaver Rd",
    "sg:city":"Troy",
    "sg:classifiers":[
        {
            "category":"Health Services",
            "subcategory":"Health Practitioner",
            "type":"Services"
        }
    ],
    "sg:phone":"+1 248 816 1999",
    "sg:postcode":"48084",
    "sg:province":"MI",
    "sg:tags":[
        "hypnotist"
    ],
    "wof:name":"Hoke Hypnotists",
    "wof:placetype":"venue"
},
  "geometry": {"coordinates":[-83.17721899999999,42.561506],"type":"Point"}
}