{
  "type": "Feature",
  "properties": {
    "iso:country":"US",
    "sg:address":"420 Huron Ave",
    "sg:city":"Port Huron",
    "sg:classifiers":[
        {
            "category":"Restaurant",
            "type":"Food & Drink"
        }
    ],
    "sg:menulink":"http://www.allmenus.com/mi/port-huron/142221-subway/menu/",
    "sg:phone":"+1 810 987 7012",
    "sg:postcode":"48060",
    "sg:province":"MI",
    "sg:tags":[
        "american",
        "sandwich"
    ],
    "wof:name":"Subway",
    "wof:placetype":"venue"
},
  "geometry": {"coordinates":[-82.42431500000001,42.978784],"type":"Point"}
}