{
  "type": "Feature",
  "properties": {
    "iso:country":"US",
    "sg:address":"4565 Wilson Ave SW",
    "sg:city":"Grandville",
    "sg:classifiers":[
        {
            "category":"Health Services",
            "subcategory":"Health Practitioner",
            "type":"Services"
        }
    ],
    "sg:phone":"+1 616 406 0602",
    "sg:postcode":"49418",
    "sg:province":"MI",
    "sg:tags":[
        "therapist",
        "physical"
    ],
    "wof:name":"Achieve Physical Therapy",
    "wof:placetype":"venue"
},
  "geometry": {"coordinates":[-85.762479,42.882241],"type":"Point"}
}