{
  "type": "Feature",
  "properties": {
    "iso:country":"US",
    "sg:address":"4500 Grow Rd NW",
    "sg:city":"Stanton",
    "sg:classifiers":[
        {
            "category":"Government",
            "subcategory":"Office",
            "type":"Public Place"
        }
    ],
    "sg:phone":"+1 989 762 8014",
    "sg:postcode":"48888",
    "sg:province":"MI",
    "sg:tags":[
        "executive",
        "off"
    ],
    "wof:name":"Douglass Township",
    "wof:placetype":"venue"
},
  "geometry": {"coordinates":[-85.15436699999999,43.358084],"type":"Point"}
}