{
  "type": "Feature",
  "properties": {
    "iso:country":"US",
    "sg:address":"2735 E Milham Ave",
    "sg:city":"Portage",
    "sg:classifiers":[
        {
            "category":"Professional",
            "subcategory":"Management & Consulting",
            "type":"Services"
        }
    ],
    "sg:phone":"+1 269 388 3804",
    "sg:postcode":"49002",
    "sg:province":"MI",
    "sg:tags":[
        "aviation",
        "consultant"
    ],
    "wof:name":"RFI",
    "wof:placetype":"venue"
},
  "geometry": {"coordinates":[-85.556352,42.230177],"type":"Point"}
}