{
  "type": "Feature",
  "properties": {
    "iso:country":"US",
    "sg:address":"6716 Bloomfield Ln",
    "sg:city":"West Bloomfield",
    "sg:classifiers":[
        {
            "category":"Manufacturing",
            "subcategory":"Retail Goods",
            "type":"Manufacturing & Wholesale Goods"
        }
    ],
    "sg:phone":"+1 248 851 7323",
    "sg:postcode":"48322",
    "sg:province":"MI",
    "sg:tags":[
        "salon",
        "beauty"
    ],
    "wof:name":"Levin Beauty Supply",
    "wof:placetype":"venue"
},
  "geometry": {"coordinates":[-83.332847,42.542595],"type":"Point"}
}