{
  "type": "Feature",
  "properties": {
    "iso:country":"US",
    "sg:address":"111 N 4th St",
    "sg:city":"Coleman",
    "sg:classifiers":[
        {
            "category":"Shopping",
            "subcategory":"Gifts & Souvenirs",
            "type":"Retail Goods"
        }
    ],
    "sg:phone":"+1 989 465 6501",
    "sg:postcode":"48618",
    "sg:province":"MI",
    "sg:tags":[
        "shop"
    ],
    "wof:name":"K-Ole Shop",
    "wof:placetype":"venue"
},
  "geometry": {"coordinates":[-84.58583,43.757001],"type":"Point"}
}