{
  "type": "Feature",
  "properties": {
    "iso:country":"US",
    "sg:address":"2511 Kibby Rd",
    "sg:city":"Jackson",
    "sg:classifiers":[
        {
            "category":"Organizations",
            "subcategory":"Religious Organization",
            "type":"Services"
        }
    ],
    "sg:phone":"+1 517 782 4877",
    "sg:postcode":"49203",
    "sg:province":"MI",
    "sg:tags":[
        "church"
    ],
    "wof:name":"New Beginnings Church Of God",
    "wof:placetype":"venue"
},
  "geometry": {"coordinates":[-84.43440200000001,42.222892],"type":"Point"}
}