{
  "type": "Feature",
  "properties": {
    "iso:country":"US",
    "sg:address":"5653 Sashabaw Rd",
    "sg:city":"Clarkston",
    "sg:classifiers":[
        {
            "category":"Health Services",
            "subcategory":"Podiatrist",
            "type":"Services"
        }
    ],
    "sg:phone":"+1 248 922 3338",
    "sg:postcode":"48346",
    "sg:province":"MI",
    "wof:name":"Clarkston Foot & Ankle Clinic",
    "wof:placetype":"venue"
},
  "geometry": {"coordinates":[-83.379124,42.72167],"type":"Point"}
}