{
  "type": "Feature",
  "properties": {
    "iso:country":"US",
    "sg:address":"4500 Dowling St",
    "sg:city":"Montague",
    "sg:classifiers":[
        {
            "category":"Personal",
            "subcategory":"Barber",
            "type":"Services"
        }
    ],
    "sg:phone":"+1 231 893 0020",
    "sg:postcode":"49437",
    "sg:province":"MI",
    "sg:tags":[
        "shop"
    ],
    "wof:name":"Barber Shop",
    "wof:placetype":"venue"
},
  "geometry": {"coordinates":[-86.352726,43.41386],"type":"Point"}
}