{
  "type": "Feature",
  "properties": {
    "iso:country":"US",
    "sg:address":"41400 Dequindre Rd Ste 100",
    "sg:city":"Sterling Heights",
    "sg:classifiers":[
        {
            "category":"Health Services",
            "subcategory":"Doctor",
            "type":"Services"
        }
    ],
    "sg:phone":"+1 248 689 6378",
    "sg:postcode":"48314",
    "sg:province":"MI",
    "sg:tags":[
        "podiatrist"
    ],
    "wof:name":"Gerber Michael L DPM PC",
    "wof:placetype":"venue"
},
  "geometry": {"coordinates":[-83.089983,42.594808],"type":"Point"}
}