{
  "type": "Feature",
  "properties": {
    "iso:country":"US",
    "sg:address":"23 S Monroe St",
    "sg:city":"Coldwater",
    "sg:classifiers":[
        {
            "category":"Personal",
            "subcategory":"Barber",
            "type":"Services"
        }
    ],
    "sg:phone":"+1 517 279 7710",
    "sg:postcode":"49036",
    "sg:province":"MI",
    "sg:tags":[
        "shop"
    ],
    "wof:name":"Shorty's Barber Shop",
    "wof:placetype":"venue"
},
  "geometry": {"coordinates":[-85.002523,41.940121],"type":"Point"}
}