{
  "type": "Feature",
  "properties": {
    "iso:country":"US",
    "sg:address":"7109 Timberwood Dr",
    "sg:city":"Davison",
    "sg:classifiers":[
        {
            "category":"Building & Trades",
            "subcategory":"Construction",
            "type":"Services"
        }
    ],
    "sg:phone":"+1 810 653 5633",
    "sg:postcode":"48423",
    "sg:province":"MI",
    "sg:tags":[
        "dry wall",
        "contractor"
    ],
    "wof:name":"Whitman's Drywall",
    "wof:placetype":"venue"
},
  "geometry": {"coordinates":[-83.57107600000001,43.040442],"type":"Point"}
}