{
  "type": "Feature",
  "properties": {
    "iso:country":"US",
    "sg:address":"16177 West Rd",
    "sg:city":"Trenton",
    "sg:classifiers":[
        {
            "category":"Restaurant",
            "type":"Food & Drink"
        }
    ],
    "sg:menulink":"http://www.allmenus.com/mi/trenton/176538-kfc---kentucky-fried-chicken/menu/",
    "sg:phone":"+1 313 671 9168",
    "sg:postcode":"48183",
    "sg:province":"MI",
    "sg:tags":[
        "american",
        "chicken"
    ],
    "wof:name":"KFC - Kentucky Fried Chicken",
    "wof:placetype":"venue"
},
  "geometry": {"coordinates":[-83.21644999999999,42.140929],"type":"Point"}
}