{
  "type": "Feature",
  "properties": {
    "iso:country":"US",
    "sg:address":"135 Veterans Dr",
    "sg:city":"Fowlerville",
    "sg:classifiers":[
        {
            "category":"Manufacturing",
            "subcategory":"Tools & Machinery",
            "type":"Manufacturing & Wholesale Goods"
        }
    ],
    "sg:phone":"+1 517 223 9181",
    "sg:postcode":"48836",
    "sg:province":"MI",
    "sg:tags":[
        "machine",
        "shop"
    ],
    "wof:name":"Deacon Manufacturing Inc",
    "wof:placetype":"venue"
},
  "geometry": {"coordinates":[-84.077168,42.660242],"type":"Point"}
}