{
  "type": "Feature",
  "properties": {
    "iso:country":"US",
    "sg:address":"1088 Marshfield St",
    "sg:city":"Ferndale",
    "sg:classifiers":[
        {
            "category":"Real Estate",
            "subcategory":"Real Estate Agent",
            "type":"Services"
        }
    ],
    "sg:phone":"+1 248 541 2400",
    "sg:postcode":"48220",
    "sg:province":"MI",
    "sg:tags":[
        "appraiser"
    ],
    "wof:name":"Brian Devries",
    "wof:placetype":"venue"
},
  "geometry": {"coordinates":[-83.14738,42.451882],"type":"Point"}
}