{
  "type": "Feature",
  "properties": {
    "iso:country":"US",
    "sg:address":"2388 Cole St",
    "sg:city":"Birmingham",
    "sg:classifiers":[
        {
            "category":"Education",
            "subcategory":"Special Training",
            "type":"Public Place"
        }
    ],
    "sg:phone":"+1 248 644 1914",
    "sg:postcode":"48009",
    "sg:province":"MI",
    "sg:tags":[
        "school",
        "specialty"
    ],
    "sg:website":"www.goldfishswimschool.com",
    "wof:name":"Goldfish Swim School",
    "wof:placetype":"venue"
},
  "geometry": {"coordinates":[-83.19212,42.54029],"type":"Point"}
}