{
  "type": "Feature",
  "properties": {
    "iso:country":"US",
    "sg:address":"108 Oak St",
    "sg:city":"Angola",
    "sg:classifiers":[
        {
            "category":"Retail",
            "subcategory":"Auto Repair",
            "type":"Services"
        }
    ],
    "sg:phone":"+1 260 665 8668",
    "sg:postcode":"46703",
    "sg:province":"MI",
    "sg:tags":[
        "automobile"
    ],
    "wof:name":"H & M Auto Detailing",
    "wof:placetype":"venue"
},
  "geometry": {"coordinates":[-84.995946,41.645956],"type":"Point"}
}