{
  "type": "Feature",
  "properties": {
    "iso:country":"US",
    "sg:address":"141 Clemens St",
    "sg:city":"Mt Clemens",
    "sg:classifiers":[
        {
            "category":"Recreation",
            "type":"Entertainment"
        }
    ],
    "sg:phone":"+1 586 466 1004",
    "sg:postcode":"48043",
    "sg:province":"MI",
    "sg:tags":[
        "range",
        "practice",
        "golf"
    ],
    "wof:name":"Island Green's Aqua Driving",
    "wof:placetype":"venue"
},
  "geometry": {"coordinates":[-82.871796,42.604314],"type":"Point"}
}