{
  "type": "Feature",
  "properties": {
    "iso:country":"US",
    "sg:address":"5300 Kalamazoo Ave SE",
    "sg:city":"Grand Rapids",
    "sg:classifiers":[
        {
            "category":"Banks & Credit Unions",
            "subcategory":"Bank",
            "type":"Services"
        }
    ],
    "sg:phone":"+1 616 281 5200",
    "sg:postcode":"49508",
    "sg:province":"MI",
    "sg:tags":[
        "state",
        "commercial"
    ],
    "wof:name":"Fifth Third Bank",
    "wof:placetype":"venue"
},
  "geometry": {"coordinates":[-85.62515399999999,42.867541],"type":"Point"}
}