{
  "type": "Feature",
  "properties": {
    "iso:country":"US",
    "sg:address":"112 Beech St",
    "sg:city":"Cadillac",
    "sg:classifiers":[
        {
            "category":"Building & Trades",
            "subcategory":"Construction",
            "type":"Services"
        }
    ],
    "sg:phone":"+1 231 775 3882",
    "sg:postcode":"49601",
    "sg:province":"MI",
    "sg:tags":[
        "general",
        "contractor"
    ],
    "sg:website":"www.roberttcoleinc.com",
    "wof:name":"Robert T Cole Inc",
    "wof:placetype":"venue"
},
  "geometry": {"coordinates":[-85.398719,44.251397],"type":"Point"}
}