{
  "type": "Feature",
  "properties": {
    "iso:country":"US",
    "sg:address":"550 W Western Ave",
    "sg:city":"Muskegon",
    "sg:classifiers":[
        {
            "category":"Health Services",
            "subcategory":"Doctor",
            "type":"Services"
        }
    ],
    "sg:phone":"+1 231 726 4498",
    "sg:postcode":"49440",
    "sg:province":"MI",
    "sg:tags":[
        "anesthetist",
        "medical"
    ],
    "wof:name":"Anesthesia Associates Mskgn",
    "wof:placetype":"venue"
},
  "geometry": {"coordinates":[-86.25588399999999,43.233695],"type":"Point"}
}