{
  "type": "Feature",
  "properties": {
    "iso:country":"US",
    "sg:address":"13210 Gera Rd",
    "sg:city":"Birch Run",
    "sg:classifiers":[
        {
            "category":"Personal",
            "type":"Services"
        }
    ],
    "sg:phone":"+1 989 624 9842",
    "sg:postcode":"48415",
    "sg:province":"MI",
    "wof:name":"C&S Kritter Kare Servcie",
    "wof:placetype":"venue"
},
  "geometry": {"coordinates":[-83.73529000000001,43.232653],"type":"Point"}
}