{
  "type": "Feature",
  "properties": {
    "iso:country":"US",
    "sg:address":"23400 W 14 Mile Rd",
    "sg:city":"Bloomfield Hills",
    "sg:classifiers":[
        {
            "category":"Professional",
            "subcategory":"Art Services",
            "type":"Services"
        }
    ],
    "sg:phone":"+1 248 647 2961",
    "sg:postcode":"48301",
    "sg:province":"MI",
    "sg:tags":[
        "commercial",
        "design"
    ],
    "wof:name":"Sunstorm Studios",
    "wof:placetype":"venue"
},
  "geometry": {"coordinates":[-83.27767,42.530416],"type":"Point"}
}