{
  "type": "Feature",
  "properties": {
    "iso:country":"US",
    "sg:address":"6045 Beachwood Dr",
    "sg:city":"West Bloomfield",
    "sg:classifiers":[
        {
            "category":"Professional",
            "subcategory":"Management & Consulting",
            "type":"Services"
        }
    ],
    "sg:phone":"+1 248 366 7993",
    "sg:postcode":"48324",
    "sg:province":"MI",
    "sg:tags":[
        "consultant"
    ],
    "wof:name":"R C Wells & Assoc Inc",
    "wof:placetype":"venue"
},
  "geometry": {"coordinates":[-83.403571,42.601348],"type":"Point"}
}