{
  "type": "Feature",
  "properties": {
    "iso:country":"US",
    "sg:address":"32530 Dequindre Rd",
    "sg:city":"Warren",
    "sg:classifiers":[
        {
            "category":"Manufacturing",
            "subcategory":"Glass & Minerals",
            "type":"Manufacturing & Wholesale Goods"
        }
    ],
    "sg:phone":"+1 586 978 1033",
    "sg:postcode":"48071",
    "sg:province":"MI",
    "sg:tags":[
        "aquarium"
    ],
    "wof:name":"Great Lakes Aquariums",
    "wof:placetype":"venue"
},
  "geometry": {"coordinates":[-83.086691,42.528366],"type":"Point"}
}