{
  "type": "Feature",
  "properties": {
    "iso:country":"US",
    "sg:address":"2700 Northern Dr SE",
    "sg:city":"Grand Rapids",
    "sg:classifiers":[
        {
            "category":"Autos & Motor Vehicles",
            "subcategory":"Auto Supplies",
            "type":"Retail Goods"
        }
    ],
    "sg:phone":"+1 616 949 3630",
    "sg:postcode":"49512",
    "sg:province":"MI",
    "sg:tags":[
        "automobile",
        "parts"
    ],
    "wof:name":"Cascade Four Wheel Drive Inc",
    "wof:placetype":"venue"
},
  "geometry": {"coordinates":[-85.543846,42.915813],"type":"Point"}
}