{
  "type": "Feature",
  "properties": {
    "iso:country":"US",
    "sg:address":"7017 S Westnedge Ave",
    "sg:city":"Portage",
    "sg:classifiers":[
        {
            "category":"Home & Garden",
            "subcategory":"Carpets & Floor Coverings",
            "type":"Retail Goods"
        }
    ],
    "sg:phone":"+1 269 329 4280",
    "sg:postcode":"49002",
    "sg:province":"MI",
    "sg:tags":[
        "dealer",
        "rug"
    ],
    "wof:name":"World Of Floors",
    "wof:placetype":"venue"
},
  "geometry": {"coordinates":[-85.58942999999999,42.219443],"type":"Point"}
}