{
  "type": "Feature",
  "properties": {
    "iso:country":"US",
    "sg:address":"10853 Ossineke Rd",
    "sg:city":"Ossineke",
    "sg:classifiers":[
        {
            "category":"Retail",
            "subcategory":"Repair Shop",
            "type":"Services"
        }
    ],
    "sg:phone":"+1 989 471 2433",
    "sg:postcode":"49766",
    "sg:province":"MI",
    "sg:tags":[
        "taxidermist"
    ],
    "wof:name":"A A Quality Taxidermy",
    "wof:placetype":"venue"
},
  "geometry": {"coordinates":[-83.435548,44.916147],"type":"Point"}
}