{
  "type": "Feature",
  "properties": {
    "iso:country":"US",
    "sg:address":"8691 Aitken St",
    "sg:city":"Montague",
    "sg:classifiers":[
        {
            "category":"Retail",
            "subcategory":"Laundry & Dry Cleaning",
            "type":"Services"
        }
    ],
    "sg:phone":"+1 231 755 6953",
    "sg:postcode":"49437",
    "sg:province":"MI",
    "sg:tags":[
        "cleaners",
        "rug",
        "carpet"
    ],
    "wof:name":"Spiffy Cleaning Svc",
    "wof:placetype":"venue"
},
  "geometry": {"coordinates":[-86.3801,43.41732],"type":"Point"}
}