{
  "type": "Feature",
  "properties": {
    "iso:country":"US",
    "sg:address":"32529 Mound Rd",
    "sg:city":"Warren",
    "sg:classifiers":[
        {
            "category":"Professional",
            "subcategory":"Business Services",
            "type":"Services"
        }
    ],
    "sg:phone":"+1 586 939 2310",
    "sg:postcode":"48092",
    "sg:province":"MI",
    "sg:tags":[
        "packaging"
    ],
    "wof:name":"Crandall Associate Inc",
    "wof:placetype":"venue"
},
  "geometry": {"coordinates":[-83.04812200000001,42.532443],"type":"Point"}
}