{
  "type": "Feature",
  "properties": {
    "iso:country":"US",
    "sg:address":"48804 Romeo Plank Rd",
    "sg:city":"Macomb",
    "sg:classifiers":[
        {
            "category":"Restaurant",
            "type":"Food & Drink"
        }
    ],
    "sg:menulink":"http://www.allmenus.com/mi/macomb/256668-super-suppers-/menu/",
    "sg:phone":"+1 586 416 7001",
    "sg:postcode":"48044",
    "sg:province":"MI",
    "sg:tags":[
        "new",
        "american"
    ],
    "wof:name":"Super Suppers ",
    "wof:placetype":"venue"
},
  "geometry": {"coordinates":[-82.937121,42.656545],"type":"Point"}
}