{
  "type": "Feature",
  "properties": {
    "iso:country":"US",
    "sg:address":"14540 Abington Ave",
    "sg:city":"Detroit",
    "sg:classifiers":[
        {
            "category":"Arts & Performance",
            "subcategory":"Art Gallery",
            "type":"Entertainment"
        }
    ],
    "sg:phone":"+1 313 835 3060",
    "sg:postcode":"48227",
    "sg:province":"MI",
    "wof:name":"Grandmont Art Gallery",
    "wof:placetype":"venue"
},
  "geometry": {"coordinates":[-83.212097,42.394901],"type":"Point"}
}