{
  "type": "Feature",
  "properties": {
    "iso:country":"US",
    "sg:address":"8340 W 6 Rd",
    "sg:city":"Mesick",
    "sg:classifiers":[
        {
            "category":"Retail",
            "subcategory":"Auto Rental",
            "type":"Services"
        }
    ],
    "sg:phone":"+1 231 269 3529",
    "sg:postcode":"49668",
    "sg:province":"MI",
    "sg:tags":[
        "truck",
        "leasing"
    ],
    "wof:name":"Northern Michigan Leasing Co",
    "wof:placetype":"venue"
},
  "geometry": {"coordinates":[-85.737317,44.483042],"type":"Point"}
}