{
  "type": "Feature",
  "properties": {
    "iso:country":"US",
    "sg:address":"116 W Nagonaba St",
    "sg:city":"Northport",
    "sg:classifiers":[
        {
            "category":"Government",
            "subcategory":"Office",
            "type":"Public Place"
        }
    ],
    "sg:phone":"+1 231 386 5182",
    "sg:postcode":"49670",
    "sg:province":"MI",
    "sg:tags":[
        "village"
    ],
    "wof:name":"Northport Village Office",
    "wof:placetype":"venue"
},
  "geometry": {"coordinates":[-85.618025,45.129825],"type":"Point"}
}