{
  "type": "Feature",
  "properties": {
    "iso:country":"US",
    "sg:address":"3951 Joslyn Rd",
    "sg:city":"Lake Orion",
    "sg:classifiers":[
        {
            "category":"Recreation",
            "type":"Entertainment"
        }
    ],
    "sg:phone":"+1 248 332 2407",
    "sg:postcode":"48359",
    "sg:province":"MI",
    "wof:name":"Mulligan S Golf Center of",
    "wof:placetype":"venue"
},
  "geometry": {"coordinates":[-83.284916,42.721276],"type":"Point"}
}