{
  "type": "Feature",
  "properties": {
    "iso:country":"US",
    "sg:address":"973 28th St SE",
    "sg:city":"Grand Rapids",
    "sg:classifiers":[
        {
            "category":"Organizations",
            "subcategory":"Religious Organization",
            "type":"Services"
        }
    ],
    "sg:phone":"+1 616 241 3173",
    "sg:postcode":"49508",
    "sg:province":"MI",
    "sg:tags":[
        "church"
    ],
    "wof:name":"New Life Reformed Church",
    "wof:placetype":"venue"
},
  "geometry": {"coordinates":[-85.644998,42.912867],"type":"Point"}
}