{
  "type": "Feature",
  "properties": {
    "iso:country":"US",
    "sg:address":"219 Cleveland Ave",
    "sg:city":"Owosso",
    "sg:classifiers":[
        {
            "category":"Real Estate",
            "subcategory":"Real Estate Operator",
            "type":"Services"
        }
    ],
    "sg:phone":"+1 989 725 1303",
    "sg:postcode":"48867",
    "sg:province":"MI",
    "sg:tags":[
        "building",
        "apartment"
    ],
    "wof:name":"Orchard Pl Manor Senior Apts",
    "wof:placetype":"venue"
},
  "geometry": {"coordinates":[-84.198926,42.998644],"type":"Point"}
}