{
  "type": "Feature",
  "properties": {
    "iso:country":"US",
    "sg:address":"16341 W Warren Ave",
    "sg:city":"Detroit",
    "sg:classifiers":[
        {
            "category":"Social Services",
            "subcategory":"Child Care",
            "type":"Services"
        }
    ],
    "sg:phone":"+1 313 228 5802",
    "sg:postcode":"48228",
    "sg:province":"MI",
    "sg:tags":[
        "day"
    ],
    "wof:name":"Kiddie University Child Care Center",
    "wof:placetype":"venue"
},
  "geometry": {"coordinates":[-83.205658,42.343402],"type":"Point"}
}