{
  "type": "Feature",
  "properties": {
    "iso:country":"US",
    "sg:address":"37175 Eureka Rd",
    "sg:city":"Romulus",
    "sg:classifiers":[
        {
            "category":"Building & Trades",
            "subcategory":"Cleaning & Sanitation",
            "type":"Services"
        }
    ],
    "sg:phone":"+1 734 955 1135",
    "sg:postcode":"48174",
    "sg:province":"MI",
    "sg:tags":[
        "home"
    ],
    "wof:name":"Carol's Maid & Janitorial Service",
    "wof:placetype":"venue"
},
  "geometry": {"coordinates":[-83.399101,42.194099],"type":"Point"}
}