{
  "type": "Feature",
  "properties": {
    "iso:country":"US",
    "sg:address":"7359 Brampton 27.5 Rd",
    "sg:city":"Rapid River",
    "sg:classifiers":[
        {
            "category":"Retail",
            "subcategory":"Veterinary Services",
            "type":"Services"
        }
    ],
    "sg:phone":"+1 906 474 6673",
    "sg:postcode":"49837",
    "sg:province":"MI",
    "sg:tags":[
        "veterinarian"
    ],
    "wof:name":"Country Vet",
    "wof:placetype":"venue"
},
  "geometry": {"coordinates":[-86.99421100000001,45.926509],"type":"Point"}
}