{
  "type": "Feature",
  "properties": {
    "iso:country":"US",
    "sg:address":"52235 Powderhorn Dr",
    "sg:city":"Macomb",
    "sg:classifiers":[
        {
            "category":"Shopping",
            "subcategory":"Computers & Home Electronics",
            "type":"Retail Goods"
        }
    ],
    "sg:phone":"+1 586 786 9245",
    "sg:postcode":"48042",
    "sg:province":"MI",
    "sg:tags":[
        "equipment",
        "dealer"
    ],
    "sg:website":"www.dkproducts.com",
    "wof:name":"D K Products",
    "wof:placetype":"venue"
},
  "geometry": {"coordinates":[-82.971425,42.679913],"type":"Point"}
}