{
  "type": "Feature",
  "properties": {
    "iso:country":"US",
    "sg:address":"8064 Haviland Beach Dr",
    "sg:city":"Linden",
    "sg:classifiers":[
        {
            "category":"Building & Trades",
            "subcategory":"Plumbing",
            "type":"Services"
        }
    ],
    "sg:phone":"+1 810 735 4155",
    "sg:postcode":"48451",
    "sg:province":"MI",
    "sg:tags":[
        "plumbing",
        "contractor"
    ],
    "wof:name":"Tri Star Plumbing",
    "wof:placetype":"venue"
},
  "geometry": {"coordinates":[-83.826232,42.78852],"type":"Point"}
}