{
  "type": "Feature",
  "properties": {
    "iso:country":"US",
    "sg:address":"5516 E Atherton Rd",
    "sg:city":"Burton",
    "sg:classifiers":[
        {
            "category":"Home & Garden",
            "subcategory":"Hardware",
            "type":"Retail Goods"
        }
    ],
    "sg:phone":"+1 810 742 6910",
    "sg:postcode":"48519",
    "sg:province":"MI",
    "sg:tags":[
        "store"
    ],
    "wof:name":"Martin's Hardware Burton",
    "wof:placetype":"venue"
},
  "geometry": {"coordinates":[-83.595901,42.990002],"type":"Point"}
}