{
  "type": "Feature",
  "properties": {
    "iso:country":"US",
    "sg:address":"9354 Lee Rd",
    "sg:city":"Jackson",
    "sg:classifiers":[
        {
            "category":"Building & Trades",
            "subcategory":"Electrical",
            "type":"Services"
        }
    ],
    "sg:phone":"+1 517 522 4547",
    "sg:postcode":"49201",
    "sg:province":"MI",
    "sg:tags":[
        "electric",
        "contractor"
    ],
    "wof:name":"Service Electric Inc",
    "wof:placetype":"venue"
},
  "geometry": {"coordinates":[-84.245895,42.217951],"type":"Point"}
}