{
  "type": "Feature",
  "properties": {
    "iso:country":"US",
    "sg:address":"39950 Hayes Rd",
    "sg:city":"Clinton Township",
    "sg:classifiers":[
        {
            "category":"Brewery",
            "type":"Food & Drink"
        }
    ],
    "sg:menulink":"http://www.allmenus.com/mi/clinton/26109-the-brewery/menu/",
    "sg:phone":"+1 586 286 3020",
    "sg:postcode":"48038",
    "sg:province":"MI",
    "sg:tags":[
        "american",
        "steakhouse"
    ],
    "wof:name":"The Brewery",
    "wof:placetype":"venue"
},
  "geometry": {"coordinates":[-82.971737,42.589892],"type":"Point"}
}