{
  "type": "Feature",
  "properties": {
    "iso:country":"US",
    "sg:address":"609 E Michigan Ave",
    "sg:city":"Paw Paw",
    "sg:classifiers":[
        {
            "category":"Organizations",
            "subcategory":"Religious Organization",
            "type":"Services"
        }
    ],
    "sg:phone":"+1 269 657 3762",
    "sg:postcode":"49079",
    "sg:province":"MI",
    "wof:name":"St Marks Episcopal Church",
    "wof:placetype":"venue"
},
  "geometry": {"coordinates":[-85.883047,42.218065],"type":"Point"}
}