{
  "type": "Feature",
  "properties": {
    "iso:country":"US",
    "sg:address":"1105 S Mueller Rd",
    "sg:city":"Saginaw",
    "sg:phone":"+1 989 755 0882",
    "sg:postcode":"48601",
    "sg:province":"MI",
    "sg:tags":[
        "farm",
        "corn"
    ],
    "wof:name":"Otto Reinbold",
    "wof:placetype":"venue"
},
  "geometry": {"coordinates":[-83.792581,43.405782],"type":"Point"}
}