{
  "type": "Feature",
  "properties": {
    "iso:country":"US",
    "sg:address":"309 Dartmouth Dr",
    "sg:city":"Midland",
    "sg:classifiers":[
        {
            "category":"Restaurant",
            "type":"Food & Drink"
        }
    ],
    "sg:phone":"+1 989 837 3090",
    "sg:postcode":"48640",
    "sg:province":"MI",
    "sg:tags":[
        "parlor",
        "ice",
        "cream"
    ],
    "wof:name":"Muncheese",
    "wof:placetype":"venue"
},
  "geometry": {"coordinates":[-84.225702,43.621772],"type":"Point"}
}