{
  "type": "Feature",
  "properties": {
    "iso:country":"US",
    "sg:address":"1275 N Williamston Rd",
    "sg:city":"Williamston",
    "sg:classifiers":[
        {
            "category":"Professional",
            "subcategory":"Credit Reporting & Collection",
            "type":"Services"
        }
    ],
    "sg:phone":"+1 517 655 1895",
    "sg:postcode":"48895",
    "sg:province":"MI",
    "wof:name":"Swan Business Solutions Inc",
    "wof:placetype":"venue"
},
  "geometry": {"coordinates":[-84.280305,42.621964],"type":"Point"}
}