{
  "type": "Feature",
  "properties": {
    "iso:country":"US",
    "sg:address":"202 E Main St",
    "sg:city":"Westphalia",
    "sg:classifiers":[
        {
            "category":"Banks & Credit Unions",
            "subcategory":"Bank",
            "type":"Services"
        }
    ],
    "sg:phone":"+1 989 587 5400",
    "sg:postcode":"48894",
    "sg:province":"MI",
    "wof:name":"Union Bank",
    "wof:placetype":"venue"
},
  "geometry": {"coordinates":[-84.796943,42.929348],"type":"Point"}
}