{
  "type": "Feature",
  "properties": {
    "iso:country":"US",
    "sg:address":"616 S Creyts Rd",
    "sg:city":"Lansing",
    "sg:classifiers":[
        {
            "category":"Real Estate",
            "subcategory":"Real Estate Services",
            "type":"Services"
        }
    ],
    "sg:phone":"+1 517 323 0739",
    "sg:postcode":"48917",
    "sg:province":"MI",
    "sg:tags":[
        "company",
        "title"
    ],
    "wof:name":"Nations Title Agency",
    "wof:placetype":"venue"
},
  "geometry": {"coordinates":[-84.642368,42.730486],"type":"Point"}
}