{
  "type": "Feature",
  "properties": {
    "iso:country":"US",
    "sg:address":"525 Romence Rd",
    "sg:city":"Portage",
    "sg:classifiers":[
        {
            "category":"Coffee & Tea",
            "type":"Food & Drink"
        }
    ],
    "sg:menulink":"http://www.allmenus.com/mi/portage/125658-starbucks-coffee/menu/",
    "sg:phone":"+1 616 329 3202",
    "sg:postcode":"49024",
    "sg:province":"MI",
    "sg:tags":[
        "american"
    ],
    "wof:name":"Starbucks Coffee",
    "wof:placetype":"venue"
},
  "geometry": {"coordinates":[-85.595078,42.215514],"type":"Point"}
}