{
  "type": "Feature",
  "properties": {
    "iso:country":"US",
    "sg:address":"56409 Precision Dr",
    "sg:city":"Chesterfield",
    "sg:classifiers":[
        {
            "category":"Manufacturing",
            "subcategory":"Metals",
            "type":"Manufacturing & Wholesale Goods"
        }
    ],
    "sg:phone":"+1 586 749 8400",
    "sg:postcode":"48051",
    "sg:province":"MI",
    "sg:tags":[
        "fabricated",
        "structural"
    ],
    "sg:website":"www.modulatedmetals.com",
    "wof:name":"Modulated Metals Inc",
    "wof:placetype":"venue"
},
  "geometry": {"coordinates":[-82.807796,42.71707],"type":"Point"}
}