{
  "type": "Feature",
  "properties": {
    "iso:country":"US",
    "sg:address":"8867 Dixie Hwy",
    "sg:city":"Ira",
    "sg:classifiers":[
        {
            "category":"Food & Beverages",
            "subcategory":"Groceries & Convenience Stores",
            "type":"Retail Goods"
        }
    ],
    "sg:phone":"+1 586 725 1515",
    "sg:postcode":"48023",
    "sg:province":"MI",
    "sg:tags":[
        "grocer"
    ],
    "wof:name":"Haven Market",
    "wof:placetype":"venue"
},
  "geometry": {"coordinates":[-82.659661,42.680652],"type":"Point"}
}