{
  "type": "Feature",
  "properties": {
    "iso:country":"US",
    "sg:address":"8938 US Hwy 31",
    "sg:city":"Berrien Springs",
    "sg:classifiers":[
        {
            "category":"Shopping",
            "subcategory":"Florist",
            "type":"Retail Goods"
        }
    ],
    "sg:phone":"+1 269 471 7714",
    "sg:postcode":"49103",
    "sg:province":"MI",
    "wof:name":"Forget Me Knotts Florist Inc",
    "wof:placetype":"venue"
},
  "geometry": {"coordinates":[-86.36603700000001,41.959437],"type":"Point"}
}