{
  "type": "Feature",
  "properties": {
    "iso:country":"US",
    "sg:address":"3193 Mack Island Rd",
    "sg:city":"Grass Lake",
    "sg:classifiers":[
        {
            "category":"Autos & Motor Vehicles",
            "subcategory":"Boat Sales",
            "type":"Retail Goods"
        }
    ],
    "sg:phone":"+1 517 522 4207",
    "sg:postcode":"49240",
    "sg:province":"MI",
    "sg:tags":[
        "dealer",
        "sales"
    ],
    "wof:name":"Butterfield Landing Marina",
    "wof:placetype":"venue"
},
  "geometry": {"coordinates":[-84.23281799999999,42.197503],"type":"Point"}
}