{
  "type": "Feature",
  "properties": {
    "iso:country":"US",
    "sg:address":"8301 White Rd",
    "sg:city":"Muskegon",
    "sg:classifiers":[
        {
            "category":"Government",
            "subcategory":"Office",
            "type":"Public Place"
        }
    ],
    "sg:phone":"+1 231 724 3440",
    "sg:postcode":"49442",
    "sg:province":"MI",
    "wof:name":"Muskegon Wastewater Mgmt Syst",
    "wof:placetype":"venue"
},
  "geometry": {"coordinates":[-86.063485,43.263991],"type":"Point"}
}