{
  "type": "Feature",
  "properties": {
    "iso:country":"US",
    "sg:address":"5603 109th Ave",
    "sg:city":"Pullman",
    "sg:classifiers":[
        {
            "category":"Shopping",
            "subcategory":"Beauty & Cosmetics",
            "type":"Retail Goods"
        }
    ],
    "sg:phone":"+1 269 236 6363",
    "sg:postcode":"49450",
    "sg:province":"MI",
    "sg:tags":[
        "shop",
        "merchandise"
    ],
    "wof:name":"Cuts By Lisa",
    "wof:placetype":"venue"
},
  "geometry": {"coordinates":[-86.09164800000001,42.484025],"type":"Point"}
}