{
  "type": "Feature",
  "properties": {
    "iso:country":"US",
    "sg:address":"1901 W Ridge St",
    "sg:city":"Marquette",
    "sg:classifiers":[
        {
            "category":"Professional",
            "subcategory":"Lawyer & Legal Services",
            "type":"Services"
        }
    ],
    "sg:phone":"+1 906 226 4600",
    "sg:postcode":"49855",
    "sg:province":"MI",
    "sg:tags":[
        "attorney"
    ],
    "wof:name":"Wideman Law Ctr",
    "wof:placetype":"venue"
},
  "geometry": {"coordinates":[-87.42992700000001,46.548651],"type":"Point"}
}