{
  "type": "Feature",
  "properties": {
    "iso:country":"US",
    "sg:address":"47777 Shelby Rd",
    "sg:city":"Utica",
    "sg:classifiers":[
        {
            "category":"Professional",
            "subcategory":"Business Services",
            "type":"Services"
        }
    ],
    "sg:phone":"+1 586 215 6824",
    "sg:postcode":"48317",
    "sg:province":"MI",
    "wof:name":"Carl W Territo",
    "wof:placetype":"venue"
},
  "geometry": {"coordinates":[-83.042356,42.644778],"type":"Point"}
}