{
  "type": "Feature",
  "properties": {
    "iso:country":"US",
    "sg:address":"4417 Fenton Rd",
    "sg:city":"Flint",
    "sg:classifiers":[
        {
            "category":"Personal",
            "subcategory":"Beauty Salon",
            "type":"Services"
        }
    ],
    "sg:phone":"+1 810 230 9484",
    "sg:postcode":"48507",
    "sg:province":"MI",
    "wof:name":"Selena's Herbal Body Wraps Inc",
    "wof:placetype":"venue"
},
  "geometry": {"coordinates":[-83.692877,42.983958],"type":"Point"}
}