{
  "type": "Feature",
  "properties": {
    "iso:country":"US",
    "sg:address":"106 Farmers Aly",
    "sg:city":"Kalamazoo",
    "sg:classifiers":[
        {
            "category":"Insurance",
            "subcategory":"Insurance Agent",
            "type":"Services"
        }
    ],
    "sg:phone":"+1 269 341 6979",
    "sg:postcode":"49007",
    "sg:province":"MI",
    "wof:name":"Iba Self Funded Group",
    "wof:placetype":"venue"
},
  "geometry": {"coordinates":[-85.58220900000001,42.291576],"type":"Point"}
}