{
  "type": "Feature",
  "properties": {
    "iso:country":"US",
    "sg:address":"3883 Telegraph Rd Ste 103",
    "sg:city":"Bloomfield Hills",
    "sg:classifiers":[
        {
            "category":"Professional",
            "subcategory":"Lawyer & Legal Services",
            "type":"Services"
        }
    ],
    "sg:phone":"+1 248 647 4242",
    "sg:postcode":"48302",
    "sg:province":"MI",
    "wof:name":"Portnoy & Roth PC",
    "wof:placetype":"venue"
},
  "geometry": {"coordinates":[-83.2808,42.583099],"type":"Point"}
}