{
  "type": "Feature",
  "properties": {
    "iso:country":"US",
    "sg:address":"3462 Lone Pine Rd",
    "sg:city":"West Bloomfield",
    "sg:classifiers":[
        {
            "category":"Arena",
            "subcategory":"Sports Club",
            "type":"Entertainment"
        }
    ],
    "sg:phone":"+1 248 737 8866",
    "sg:postcode":"48323",
    "sg:province":"MI",
    "wof:name":"Boyd Sports Management",
    "wof:placetype":"venue"
},
  "geometry": {"coordinates":[-83.34677000000001,42.573505],"type":"Point"}
}