{
  "type": "Feature",
  "properties": {
    "iso:country":"US",
    "sg:address":"204 N Church St",
    "sg:city":"Hastings",
    "sg:classifiers":[
        {
            "category":"Professional",
            "subcategory":"Computer Services",
            "type":"Services"
        }
    ],
    "sg:phone":"+1 269 945 1892",
    "sg:postcode":"49058",
    "sg:province":"MI",
    "sg:tags":[
        "internet"
    ],
    "wof:name":"Cherryland Online Svc",
    "wof:placetype":"venue"
},
  "geometry": {"coordinates":[-85.28918899999999,42.65053],"type":"Point"}
}