{
  "type": "Feature",
  "properties": {
    "iso:country":"US",
    "sg:address":"2715 29th St SE",
    "sg:city":"Grand Rapids",
    "sg:classifiers":[
        {
            "category":"Autos & Motor Vehicles",
            "subcategory":"Motorcycle Sales",
            "type":"Retail Goods"
        }
    ],
    "sg:phone":"+1 616 575 0130",
    "sg:postcode":"49512",
    "sg:province":"MI",
    "sg:tags":[
        "scooter"
    ],
    "wof:name":"Treads & Sleds Inc",
    "wof:placetype":"venue"
},
  "geometry": {"coordinates":[-85.60615300000001,42.910901],"type":"Point"}
}