{
  "type": "Feature",
  "properties": {
    "iso:country":"US",
    "sg:address":"45045 W Pontiac Trl",
    "sg:city":"Novi",
    "sg:classifiers":[
        {
            "category":"Personal",
            "subcategory":"Beauty Salon",
            "type":"Services"
        }
    ],
    "sg:phone":"+1 248 624 5103",
    "sg:postcode":"48377",
    "sg:province":"MI",
    "sg:tags":[
        "apparel",
        "woman"
    ],
    "wof:name":"Patti & Associates Hair Care",
    "wof:placetype":"venue"
},
  "geometry": {"coordinates":[-83.492976,42.525552],"type":"Point"}
}