{
  "type": "Feature",
  "properties": {
    "iso:country":"US",
    "sg:address":"2200 Crooks Rd",
    "sg:city":"Troy",
    "sg:classifiers":[
        {
            "category":"Real Estate",
            "subcategory":"Real Estate Operator",
            "type":"Services"
        }
    ],
    "sg:phone":"+1 248 362 1871",
    "sg:postcode":"48084",
    "sg:province":"MI",
    "sg:tags":[
        "building",
        "apartment"
    ],
    "wof:name":"Maplewood Manor Apartments",
    "wof:placetype":"venue"
},
  "geometry": {"coordinates":[-83.16686900000001,42.555734],"type":"Point"}
}