{
  "type": "Feature",
  "properties": {
    "iso:country":"US",
    "sg:address":"29122 Utley Rd",
    "sg:city":"Farmington",
    "sg:classifiers":[
        {
            "category":"Personal",
            "type":"Services"
        }
    ],
    "sg:phone":"+1 248 626 0484",
    "sg:postcode":"48334",
    "sg:province":"MI",
    "wof:name":"Nannys Playhouse",
    "wof:placetype":"venue"
},
  "geometry": {"coordinates":[-83.337357,42.505034],"type":"Point"}
}