{
  "type": "Feature",
  "properties": {
    "iso:country":"US",
    "sg:address":"4749 Seeger St",
    "sg:city":"Cass City",
    "sg:classifiers":[
        {
            "category":"Autos & Motor Vehicles",
            "subcategory":"Automobile Sales",
            "type":"Retail Goods"
        }
    ],
    "sg:phone":"+1 989 872 3290",
    "sg:postcode":"48726",
    "sg:province":"MI",
    "sg:tags":[
        "used"
    ],
    "wof:name":"Halls Used Cars",
    "wof:placetype":"venue"
},
  "geometry": {"coordinates":[-83.174768,43.605908],"type":"Point"}
}