{
  "type": "Feature",
  "properties": {
    "iso:country":"US",
    "sg:address":"310 Hecla St",
    "sg:city":"Calumet",
    "sg:classifiers":[
        {
            "category":"Government",
            "subcategory":"Fire Station",
            "type":"Public Place"
        }
    ],
    "sg:phone":"+1 906 337 1400",
    "sg:postcode":"49913",
    "sg:province":"MI",
    "sg:tags":[
        "protection"
    ],
    "wof:name":"Laurium Village Fire Dept",
    "wof:placetype":"venue"
},
  "geometry": {"coordinates":[-88.44302500000001,47.236973],"type":"Point"}
}