{
  "type": "Feature",
  "properties": {
    "iso:country":"US",
    "sg:address":"5075 Cascade Rd SE",
    "sg:city":"Grand Rapids",
    "sg:classifiers":[
        {
            "category":"Shopping",
            "type":"Retail Goods"
        }
    ],
    "sg:phone":"+1 616 949 6077",
    "sg:postcode":"49546",
    "sg:province":"MI",
    "sg:tags":[
        "monument"
    ],
    "wof:name":"Graceland Monuments",
    "wof:placetype":"venue"
},
  "geometry": {"coordinates":[-85.541196,42.942817],"type":"Point"}
}