{
  "type": "Feature",
  "properties": {
    "iso:country":"US",
    "sg:address":"920 Lynwood St",
    "sg:city":"Marysville",
    "sg:classifiers":[
        {
            "category":"Organizations",
            "subcategory":"Membership Organization",
            "type":"Services"
        }
    ],
    "sg:phone":"+1 810 364 6324",
    "sg:postcode":"48040",
    "sg:province":"MI",
    "wof:name":"Economic Opportunity Committee",
    "wof:placetype":"venue"
},
  "geometry": {"coordinates":[-82.469911,42.921386],"type":"Point"}
}