{
  "type": "Feature",
  "properties": {
    "iso:country":"US",
    "sg:address":"3400 Steamburg Rd",
    "sg:city":"Hillsdale",
    "sg:classifiers":[
        {
            "category":"Retail",
            "subcategory":"Animal Services",
            "type":"Services"
        }
    ],
    "sg:phone":"+1 517 437 2042",
    "sg:postcode":"49242",
    "sg:province":"MI",
    "wof:name":"Golden Opprtunity Training Ctr",
    "wof:placetype":"venue"
},
  "geometry": {"coordinates":[-84.61214099999999,41.878479],"type":"Point"}
}