{
  "type": "Feature",
  "properties": {
    "iso:country":"US",
    "sg:address":"5816 State Hwy 65",
    "sg:city":"Posen",
    "sg:classifiers":[
        {
            "category":"Organizations",
            "subcategory":"Community Association",
            "type":"Services"
        }
    ],
    "sg:phone":"+1 989 766 8043",
    "sg:postcode":"49776",
    "sg:province":"MI",
    "wof:name":"V F W Post 7804",
    "wof:placetype":"venue"
},
  "geometry": {"coordinates":[-83.70001000000001,45.338137],"type":"Point"}
}