{
  "type": "Feature",
  "properties": {
    "iso:country":"US",
    "sg:address":"9136 W Limits Rd",
    "sg:city":"Mancelona",
    "sg:classifiers":[
        {
            "category":"Building & Trades",
            "subcategory":"Plumbing",
            "type":"Services"
        }
    ],
    "sg:phone":"+1 231 587 8700",
    "sg:postcode":"49659",
    "sg:province":"MI",
    "sg:tags":[
        "plumbing",
        "contractor"
    ],
    "wof:name":"Moore Plumbing & Heating Inc",
    "wof:placetype":"venue"
},
  "geometry": {"coordinates":[-85.07163799999999,44.893339],"type":"Point"}
}