{
  "type": "Feature",
  "properties": {
    "iso:country":"US",
    "sg:address":"315 Scott St",
    "sg:city":"Marine City",
    "sg:classifiers":[
        {
            "category":"Professional",
            "type":"Services"
        }
    ],
    "sg:phone":"+1 810 765 5208",
    "sg:postcode":"48039",
    "sg:province":"MI",
    "wof:name":"Penny Dancer Performance",
    "wof:placetype":"venue"
},
  "geometry": {"coordinates":[-82.49886100000001,42.710233],"type":"Point"}
}