{
  "type": "Feature",
  "properties": {
    "iso:country":"US",
    "sg:address":"3683 Creekside Dr",
    "sg:city":"Ann Arbor",
    "sg:classifiers":[
        {
            "category":"Social Services",
            "type":"Services"
        }
    ],
    "sg:phone":"+1 734 761 2988",
    "sg:postcode":"48105",
    "sg:province":"MI",
    "wof:name":"M K Bottonari Msw",
    "wof:placetype":"venue"
},
  "geometry": {"coordinates":[-83.64912699999999,42.321319],"type":"Point"}
}