{
  "type": "Feature",
  "properties": {
    "iso:country":"US",
    "sg:address":"1275 E Townline Lake Rd",
    "sg:city":"Harrison",
    "sg:classifiers":[
        {
            "category":"Shopping",
            "subcategory":"Gifts & Souvenirs",
            "type":"Retail Goods"
        }
    ],
    "sg:phone":"+1 989 539 4107",
    "sg:postcode":"48625",
    "sg:province":"MI",
    "wof:name":"J&J Wholesalers",
    "wof:placetype":"venue"
},
  "geometry": {"coordinates":[-84.819924,44.031416],"type":"Point"}
}