{
  "type": "Feature",
  "properties": {
    "iso:country":"US",
    "sg:address":"11425 Torrey Rd",
    "sg:city":"Fenton",
    "sg:classifiers":[
        {
            "category":"Recreation",
            "type":"Entertainment"
        }
    ],
    "sg:phone":"+1 810 591 0080",
    "sg:postcode":"48430",
    "sg:province":"MI",
    "wof:name":"Southern Lakes Parks",
    "wof:placetype":"venue"
},
  "geometry": {"coordinates":[-83.72908,42.859717],"type":"Point"}
}