{
  "type": "Feature",
  "properties": {
    "iso:country":"US",
    "sg:address":"1588 Lincoln Rd",
    "sg:city":"Allegan",
    "sg:classifiers":[
        {
            "category":"Personal",
            "subcategory":"Tanning Parlor",
            "type":"Services"
        }
    ],
    "sg:phone":"+1 269 673 9538",
    "sg:postcode":"49010",
    "sg:province":"MI",
    "sg:tags":[
        "salon"
    ],
    "wof:name":"Budget Tan",
    "wof:placetype":"venue"
},
  "geometry": {"coordinates":[-85.873119,42.532649],"type":"Point"}
}