{
  "type": "Feature",
  "properties": {
    "iso:country":"US",
    "sg:address":"1344 S Airport Rd W",
    "sg:city":"Traverse City",
    "sg:classifiers":[
        {
            "category":"Manufacturing",
            "subcategory":"Printing",
            "type":"Manufacturing & Wholesale Goods"
        }
    ],
    "sg:phone":"+1 231 941 5770",
    "sg:postcode":"49686",
    "sg:province":"MI",
    "sg:tags":[
        "printer"
    ],
    "wof:name":"Allegra Print & Imaging",
    "wof:placetype":"venue"
},
  "geometry": {"coordinates":[-85.602429,44.733275],"type":"Point"}
}