{
  "type": "Feature",
  "properties": {
    "iso:country":"US",
    "sg:address":"221 W Main St",
    "sg:city":"Middleville",
    "sg:classifiers":[
        {
            "category":"Retail",
            "subcategory":"Auto Repair",
            "type":"Services"
        }
    ],
    "sg:phone":"+1 269 795 3369",
    "sg:postcode":"49333",
    "sg:province":"MI",
    "sg:tags":[
        "automotive"
    ],
    "wof:name":"Rudds Wrecker Service",
    "wof:placetype":"venue"
},
  "geometry": {"coordinates":[-85.467101,42.710937],"type":"Point"}
}