{
  "type": "Feature",
  "properties": {
    "iso:country":"US",
    "sg:address":"3250 US Hwy 12",
    "sg:city":"Niles",
    "sg:classifiers":[
        {
            "category":"Organizations",
            "subcategory":"Religious Organization",
            "type":"Services"
        }
    ],
    "sg:phone":"+1 269 663 2648",
    "sg:postcode":"49120",
    "sg:province":"MI",
    "sg:tags":[
        "church"
    ],
    "wof:name":"Community Baptist Church",
    "wof:placetype":"venue"
},
  "geometry": {"coordinates":[-86.112652,41.791073],"type":"Point"}
}