{
  "type": "Feature",
  "properties": {
    "iso:country":"US",
    "sg:address":"320 W Delaware St",
    "sg:city":"Decatur",
    "sg:classifiers":[
        {
            "category":"Retail",
            "subcategory":"Car Wash",
            "type":"Services"
        }
    ],
    "sg:phone":"+1 269 423 8212",
    "sg:postcode":"49045",
    "sg:province":"MI",
    "sg:tags":[
        "polishing",
        "washing"
    ],
    "wof:name":"Decatur Super Wash",
    "wof:placetype":"venue"
},
  "geometry": {"coordinates":[-85.980272,42.105595],"type":"Point"}
}