{
  "type": "Feature",
  "properties": {
    "iso:country":"US",
    "sg:address":"2163 Millington Rd",
    "sg:city":"Millington",
    "sg:classifiers":[
        {
            "category":"Professional",
            "subcategory":"Business Services",
            "type":"Services"
        }
    ],
    "sg:phone":"+1 989 795 2266",
    "sg:postcode":"48746",
    "sg:province":"MI",
    "wof:name":"Advantedge Solutions",
    "wof:placetype":"venue"
},
  "geometry": {"coordinates":[-83.423052,43.277035],"type":"Point"}
}