{
  "type": "Feature",
  "properties": {
    "iso:country":"US",
    "sg:address":"1184 Gratiot Blvd",
    "sg:city":"Marysville",
    "sg:classifiers":[
        {
            "category":"Retail",
            "subcategory":"Auto Repair",
            "type":"Services"
        }
    ],
    "sg:phone":"+1 810 364 7987",
    "sg:postcode":"48040",
    "sg:province":"MI",
    "sg:tags":[
        "automobile",
        "lubrication"
    ],
    "wof:name":"Quality Lube",
    "wof:placetype":"venue"
},
  "geometry": {"coordinates":[-82.473851,42.921171],"type":"Point"}
}