{
  "type": "Feature",
  "properties": {
    "iso:country":"US",
    "sg:address":"50 N Saginaw St",
    "sg:city":"Pontiac",
    "sg:classifiers":[
        {
            "category":"Organizations",
            "subcategory":"Religious Organization",
            "type":"Services"
        }
    ],
    "sg:phone":"+1 248 758 9686",
    "sg:postcode":"48342",
    "sg:province":"MI",
    "sg:tags":[
        "church"
    ],
    "wof:name":"Greater Faith Missionary Bapt",
    "wof:placetype":"venue"
},
  "geometry": {"coordinates":[-83.29242499999999,42.638143],"type":"Point"}
}