{
  "type": "Feature",
  "properties": {
    "iso:country":"US",
    "sg:address":"11383 Casa Loma",
    "sg:city":"Brighton",
    "sg:classifiers":[
        {
            "category":"Wholesale",
            "subcategory":"Machinery & Supplies",
            "type":"Manufacturing & Wholesale Goods"
        }
    ],
    "sg:phone":"+1 810 225 8474",
    "sg:postcode":"48114",
    "sg:province":"MI",
    "sg:tags":[
        "industrial"
    ],
    "wof:name":"Larz Industries Inc",
    "wof:placetype":"venue"
},
  "geometry": {"coordinates":[-83.72468600000001,42.53349],"type":"Point"}
}