{
  "type": "Feature",
  "properties": {
    "iso:country":"US",
    "sg:address":"13144 Willow Ave",
    "sg:city":"Grant",
    "sg:classifiers":[
        {
            "category":"Professional",
            "subcategory":"Business Services",
            "type":"Services"
        }
    ],
    "sg:phone":"+1 231 834 0454",
    "sg:postcode":"49327",
    "sg:province":"MI",
    "sg:tags":[
        "interior",
        "consultant",
        "design",
        "decorator"
    ],
    "wof:name":"Five Star Decorating",
    "wof:placetype":"venue"
},
  "geometry": {"coordinates":[-85.780266,43.315843],"type":"Point"}
}