{
  "type": "Feature",
  "properties": {
    "iso:country":"US",
    "sg:address":"8891 Spicer Rd",
    "sg:city":"Brighton",
    "sg:classifiers":[
        {
            "category":"Organizations",
            "subcategory":"Community Association",
            "type":"Services"
        }
    ],
    "sg:phone":"+1 810 231 1224",
    "sg:postcode":"48116",
    "sg:province":"MI",
    "sg:tags":[
        "club"
    ],
    "wof:name":"Veterans Of Foreign Wars",
    "wof:placetype":"venue"
},
  "geometry": {"coordinates":[-83.76789100000001,42.456891],"type":"Point"}
}