{
  "type": "Feature",
  "properties": {
    "iso:country":"US",
    "sg:address":"106 S Washington St",
    "sg:city":"Oxford",
    "sg:classifiers":[
        {
            "category":"Insurance",
            "subcategory":"Insurance Agent",
            "type":"Services"
        }
    ],
    "sg:phone":"+1 248 628 3110",
    "sg:postcode":"48371",
    "sg:province":"MI",
    "wof:name":"State Farm Insurance",
    "wof:placetype":"venue"
},
  "geometry": {"coordinates":[-83.26295399999999,42.822495],"type":"Point"}
}