{
  "type": "Feature",
  "properties": {
    "iso:country":"US",
    "sg:address":"22241 Roethel Dr",
    "sg:city":"Novi",
    "sg:classifiers":[
        {
            "category":"Manufacturing",
            "subcategory":"Tools & Machinery",
            "type":"Manufacturing & Wholesale Goods"
        },
        {
            "category":"Manufacturing",
            "subcategory":"Electronics",
            "type":"Manufacturing & Wholesale Goods"
        },
        {
            "category":"Wholesale",
            "subcategory":"Electrical",
            "type":"Manufacturing & Wholesale Goods"
        },
        {
            "category":"Shopping",
            "subcategory":"Computers & Home Electronics",
            "type":"Retail Goods"
        }
    ],
    "sg:phone":"+1 248 380 3458",
    "sg:postcode":"48375",
    "sg:province":"MI",
    "sg:tags":[
        "electric",
        "supply",
        "electronic",
        "equipment",
        "consumer",
        "supplies-wholesale",
        "manufacturer"
    ],
    "sg:website":"http://www.donhickey.com",
    "wof:name":"Donald J Hickey & Associates",
    "wof:placetype":"venue"
},
  "geometry": {"coordinates":[-83.466937,42.449635],"type":"Point"}
}