{
  "type": "Feature",
  "properties": {
    "iso:country":"US",
    "sg:address":"5600 W Maple Rd Ste A160",
    "sg:city":"West Bloomfield",
    "sg:classifiers":[
        {
            "category":"Professional",
            "subcategory":"Accounting & Tax Preparation",
            "type":"Services"
        }
    ],
    "sg:phone":"+1 248 855 8244",
    "sg:postcode":"48322",
    "sg:province":"MI",
    "sg:tags":[
        "accountant"
    ],
    "wof:name":"Weiner Yale",
    "wof:placetype":"venue"
},
  "geometry": {"coordinates":[-83.35606,42.543099],"type":"Point"}
}