{
  "type": "Feature",
  "properties": {
    "iso:country":"US",
    "sg:address":"19251 Mack Ave",
    "sg:city":"Grosse Pointe",
    "sg:classifiers":[
        {
            "category":"Professional",
            "subcategory":"Management & Consulting",
            "type":"Services"
        }
    ],
    "sg:phone":"+1 313 343 9009",
    "sg:postcode":"48236",
    "sg:province":"MI",
    "sg:tags":[
        "planning",
        "financial"
    ],
    "wof:name":"Business Est Fncl Coordinators",
    "wof:placetype":"venue"
},
  "geometry": {"coordinates":[-82.91000200000001,42.420805],"type":"Point"}
}