{
  "type": "Feature",
  "properties": {
    "iso:country":"US",
    "sg:address":"2735 S Wagner Rd",
    "sg:city":"Ann Arbor",
    "sg:classifiers":[
        {
            "category":"Building & Trades",
            "subcategory":"Landscaping Services",
            "type":"Services"
        }
    ],
    "sg:phone":"+1 734 997 7244",
    "sg:postcode":"48103",
    "sg:province":"MI",
    "wof:name":"Green Vision Lawn & Ldscpg",
    "wof:placetype":"venue"
},
  "geometry": {"coordinates":[-83.79861099999999,42.247626],"type":"Point"}
}