{
  "type": "Feature",
  "properties": {
    "iso:country":"US",
    "sg:address":"1 S Ionia Rd",
    "sg:city":"Vermontville",
    "sg:classifiers":[
        {
            "category":"Real Estate",
            "subcategory":"Developer",
            "type":"Services"
        }
    ],
    "sg:phone":"+1 517 726 0872",
    "sg:postcode":"49096",
    "sg:province":"MI",
    "sg:tags":[
        "cemetery"
    ],
    "wof:name":"Kalamo Cemetery",
    "wof:placetype":"venue"
},
  "geometry": {"coordinates":[-85.014116,42.567268],"type":"Point"}
}