{
  "type": "Feature",
  "properties": {
    "iso:country":"US",
    "sg:address":"1083 E Maple Rd",
    "sg:city":"Birmingham",
    "sg:classifiers":[
        {
            "category":"Health Services",
            "subcategory":"Doctor",
            "type":"Services"
        }
    ],
    "sg:phone":"+1 248 646 1330",
    "sg:postcode":"48009",
    "sg:province":"MI",
    "wof:name":"Peter G Anderson DDS",
    "wof:placetype":"venue"
},
  "geometry": {"coordinates":[-83.20652699999999,42.546977],"type":"Point"}
}