{
  "type": "Feature",
  "properties": {
    "iso:country":"US",
    "sg:address":"1000 Decker Rd",
    "sg:city":"Walled Lake",
    "sg:classifiers":[
        {
            "category":"Wholesale",
            "subcategory":"Construction Materials",
            "type":"Manufacturing & Wholesale Goods"
        }
    ],
    "sg:phone":"+1 248 669 2323",
    "sg:postcode":"48390",
    "sg:province":"MI",
    "sg:tags":[
        "building"
    ],
    "sg:website":"www.hansenmarketing.com",
    "wof:name":"Hansen Marketing Svc Inc",
    "wof:placetype":"venue"
},
  "geometry": {"coordinates":[-83.467887,42.540396],"type":"Point"}
}