{
  "type": "Feature",
  "properties": {
    "iso:country":"US",
    "sg:address":"6713 Division Ave S",
    "sg:city":"Grand Rapids",
    "sg:classifiers":[
        {
            "category":"Shopping",
            "subcategory":"Department Store",
            "type":"Retail Goods"
        }
    ],
    "sg:phone":"+1 616 301 7820",
    "sg:postcode":"49548",
    "sg:province":"MI",
    "sg:tags":[
        "shop"
    ],
    "wof:name":"Village Dollar",
    "wof:placetype":"venue"
},
  "geometry": {"coordinates":[-85.66377,42.842565],"type":"Point"}
}