{
  "type": "Feature",
  "properties": {
    "iso:country":"US",
    "sg:address":"3375 Eden Rd",
    "sg:city":"Leslie",
    "sg:classifiers":[
        {
            "category":"Freight",
            "type":"Transportation"
        }
    ],
    "sg:phone":"+1 517 589 9689",
    "sg:postcode":"49251",
    "sg:province":"MI",
    "sg:tags":[
        "hauling",
        "trucking"
    ],
    "wof:name":"R M Brownlee Trucking",
    "wof:placetype":"venue"
},
  "geometry": {"coordinates":[-84.425954,42.489518],"type":"Point"}
}