{
  "type": "Feature",
  "properties": {
    "iso:country":"US",
    "sg:address":"3602 W Monroe Rd",
    "sg:city":"Hart",
    "sg:classifiers":[
        {
            "category":"Farming",
            "subcategory":"Livestock Farm",
            "type":"Manufacturing & Wholesale Goods"
        }
    ],
    "sg:phone":"+1 231 873 4480",
    "sg:postcode":"49420",
    "sg:province":"MI",
    "sg:tags":[
        "equine"
    ],
    "wof:name":"Michael Potter",
    "wof:placetype":"venue"
},
  "geometry": {"coordinates":[-86.36806199999999,43.761408],"type":"Point"}
}