{
  "type": "Feature",
  "properties": {
    "iso:country":"US",
    "sg:address":"348 S Waverly Rd",
    "sg:city":"Holland",
    "sg:classifiers":[
        {
            "category":"Insurance",
            "subcategory":"Insurance Agent",
            "type":"Services"
        }
    ],
    "sg:phone":"+1 616 355 2920",
    "sg:postcode":"49423",
    "sg:province":"MI",
    "wof:name":"KOOP & Burr Insurance",
    "wof:placetype":"venue"
},
  "geometry": {"coordinates":[-86.077656,42.784682],"type":"Point"}
}