{
  "type": "Feature",
  "properties": {
    "iso:country":"US",
    "sg:address":"4600 Woodward Ave",
    "sg:city":"Detroit",
    "sg:classifiers":[
        {
            "category":"Real Estate",
            "subcategory":"Real Estate Operator",
            "type":"Services"
        }
    ],
    "sg:phone":"+1 313 832 6071",
    "sg:postcode":"48201",
    "sg:province":"MI",
    "sg:tags":[
        "apartment"
    ],
    "wof:name":"The Lofts at Garfield",
    "wof:placetype":"venue"
},
  "geometry": {"coordinates":[-83.062202,42.353699],"type":"Point"}
}