{
  "type": "Feature",
  "properties": {
    "iso:country":"US",
    "sg:address":"32931 Middlebelt Rd",
    "sg:city":"Farmington Hills",
    "sg:classifiers":[
        {
            "category":"Health Services",
            "subcategory":"Doctor",
            "type":"Services"
        }
    ],
    "sg:phone":"+1 248 737 9430",
    "sg:postcode":"48334",
    "sg:province":"MI",
    "sg:tags":[
        "dentist"
    ],
    "wof:name":"Bernard Maza DDS PC",
    "wof:placetype":"venue"
},
  "geometry": {"coordinates":[-83.340587,42.5281],"type":"Point"}
}