{
  "type": "Feature",
  "properties": {
    "iso:country":"US",
    "sg:address":"5100 McCue Rd",
    "sg:city":"Holt",
    "sg:classifiers":[
        {
            "category":"Building & Trades",
            "subcategory":"Construction",
            "type":"Services"
        }
    ],
    "sg:phone":"+1 517 699 1816",
    "sg:postcode":"48842",
    "sg:province":"MI",
    "sg:tags":[
        "carpentry",
        "contractor"
    ],
    "wof:name":"Lee A Secord",
    "wof:placetype":"venue"
},
  "geometry": {"coordinates":[-84.554963,42.625928],"type":"Point"}
}