{
  "type": "Feature",
  "properties": {
    "iso:country":"US",
    "sg:address":"6430 Coulson Ct",
    "sg:city":"Lansing",
    "sg:classifiers":[
        {
            "category":"Professional",
            "type":"Services"
        }
    ],
    "sg:phone":"+1 517 394 6635",
    "sg:postcode":"48911",
    "sg:province":"MI",
    "sg:tags":[
        "establishment"
    ],
    "wof:name":"Residential Treatment Of West",
    "wof:placetype":"venue"
},
  "geometry": {"coordinates":[-84.55249999999999,42.668409],"type":"Point"}
}