{
  "type": "Feature",
  "properties": {
    "iso:country":"US",
    "sg:address":"30233 Southfield Rd",
    "sg:city":"Southfield",
    "sg:classifiers":[
        {
            "category":"Banks & Credit Unions",
            "subcategory":"Bank",
            "type":"Services"
        }
    ],
    "sg:phone":"+1 248 644 4380",
    "sg:postcode":"48076",
    "sg:province":"MI",
    "sg:tags":[
        "personal",
        "institution"
    ],
    "wof:name":"Old Republic",
    "wof:placetype":"venue"
},
  "geometry": {"coordinates":[-83.223106,42.511547],"type":"Point"}
}