{
  "type": "Feature",
  "properties": {
    "iso:country":"US",
    "sg:address":"47 W Michigan Ave",
    "sg:city":"Galesburg",
    "sg:classifiers":[
        {
            "category":"Shopping",
            "subcategory":"Jewelry",
            "type":"Retail Goods"
        }
    ],
    "sg:phone":"+1 269 665 7570",
    "sg:postcode":"49053",
    "sg:province":"MI",
    "sg:tags":[
        "designer"
    ],
    "wof:name":"C P French",
    "wof:placetype":"venue"
},
  "geometry": {"coordinates":[-85.41864,42.28882],"type":"Point"}
}