{
  "type": "Feature",
  "properties": {
    "iso:country":"US",
    "sg:address":"2663 N Euclid Ave",
    "sg:city":"Bay City",
    "sg:classifiers":[
        {
            "category":"Shopping",
            "subcategory":"Hobbies, Toys, & Games",
            "type":"Retail Goods"
        }
    ],
    "sg:phone":"+1 989 667 6912",
    "sg:postcode":"48706",
    "sg:province":"MI",
    "sg:tags":[
        "bingo",
        "supply"
    ],
    "wof:name":"J D Bingo Sales",
    "wof:placetype":"venue"
},
  "geometry": {"coordinates":[-83.91229300000001,43.665302],"type":"Point"}
}