{
  "type": "Feature",
  "properties": {
    "iso:country":"US",
    "sg:address":"1120 E State Fair",
    "sg:city":"Highland Park",
    "sg:classifiers":[
        {
            "category":"Retail",
            "subcategory":"Funeral Services",
            "type":"Services"
        }
    ],
    "sg:phone":"+1 313 368 7773",
    "sg:postcode":"48203",
    "sg:province":"MI",
    "sg:tags":[
        "cemetery"
    ],
    "wof:name":"Barksdale Funeral Homes",
    "wof:placetype":"venue"
},
  "geometry": {"coordinates":[-83.092499,42.439701],"type":"Point"}
}