{
  "type": "Feature",
  "properties": {
    "iso:country":"US",
    "sg:address":"4380 W Pierson Rd",
    "sg:city":"Flint",
    "sg:classifiers":[
        {
            "category":"Travel",
            "subcategory":"Hotels & Motels",
            "type":"Entertainment"
        }
    ],
    "sg:phone":"+1 810 733 7570",
    "sg:postcode":"48504",
    "sg:province":"MI",
    "wof:name":"Great Western",
    "wof:placetype":"venue"
},
  "geometry": {"coordinates":[-83.764037,43.060704],"type":"Point"}
}