{
  "type": "Feature",
  "properties": {
    "iso:country":"US",
    "sg:address":"715 Hill Ave NW",
    "sg:city":"Grand Rapids",
    "sg:classifiers":[
        {
            "category":"Professional",
            "subcategory":"Management & Consulting",
            "type":"Services"
        }
    ],
    "sg:phone":"+1 616 453 8373",
    "sg:postcode":"49504",
    "sg:province":"MI",
    "wof:name":"Kenneth Nysson Assoc",
    "wof:placetype":"venue"
},
  "geometry": {"coordinates":[-85.70371799999999,42.977076],"type":"Point"}
}