{
  "type": "Feature",
  "properties": {
    "iso:country":"US",
    "sg:address":"415 E Maple Rd",
    "sg:city":"Troy",
    "sg:classifiers":[
        {
            "category":"Shopping",
            "subcategory":"Optician",
            "type":"Retail Goods"
        }
    ],
    "sg:phone":"+1 248 526 1616",
    "sg:postcode":"48083",
    "sg:province":"MI",
    "sg:tags":[
        "eyewear"
    ],
    "wof:name":"Troy Optical",
    "wof:placetype":"venue"
},
  "geometry": {"coordinates":[-83.13911400000001,42.548637],"type":"Point"}
}