{
  "type": "Feature",
  "properties": {
    "iso:country":"US",
    "sg:address":"10117 N State Rd",
    "sg:city":"Luther",
    "sg:classifiers":[
        {
            "category":"Sports & Exercise",
            "subcategory":"Golf",
            "type":"Entertainment"
        }
    ],
    "sg:phone":"+1 231 862 3570",
    "sg:postcode":"49656",
    "sg:province":"MI",
    "sg:tags":[
        "course",
        "public"
    ],
    "wof:name":"Redfoot Hills Golf Course",
    "wof:placetype":"venue"
},
  "geometry": {"coordinates":[-85.683677,44.137503],"type":"Point"}
}