{
  "type": "Feature",
  "properties": {
    "iso:country":"US",
    "sg:address":"1810 Breton Rd SE",
    "sg:city":"Grand Rapids",
    "sg:classifiers":[
        {
            "category":"Autos & Motor Vehicles",
            "subcategory":"Fuel & Gas Station",
            "type":"Retail Goods"
        }
    ],
    "sg:phone":"+1 616 949 5161",
    "sg:postcode":"49506",
    "sg:province":"MI",
    "sg:tags":[
        "oil"
    ],
    "wof:name":"Parini's Breton Village Amoco",
    "wof:placetype":"venue"
},
  "geometry": {"coordinates":[-85.609284,42.929591],"type":"Point"}
}