{
  "type": "Feature",
  "properties": {
    "iso:country":"US",
    "sg:address":"527 W Spruce St",
    "sg:city":"St Charles",
    "sg:phone":"+1 989 865 9718",
    "sg:postcode":"48655",
    "sg:province":"MI",
    "sg:tags":[
        "oil"
    ],
    "wof:name":"Gibson Oil Co",
    "wof:placetype":"venue"
},
  "geometry": {"coordinates":[-84.14849700000001,43.296595],"type":"Point"}
}