{
  "type": "Feature",
  "properties": {
    "iso:country":"US",
    "sg:address":"5100 Marsh Rd",
    "sg:city":"Okemos",
    "sg:classifiers":[
        {
            "category":"Home & Garden",
            "subcategory":"Building Materials",
            "type":"Retail Goods"
        }
    ],
    "sg:phone":"+1 517 347 0667",
    "sg:postcode":"48864",
    "sg:province":"MI",
    "sg:tags":[
        "window",
        "wallpaper",
        "treatment",
        "accessory"
    ],
    "wof:name":"Wallpaper Emporium",
    "wof:placetype":"venue"
},
  "geometry": {"coordinates":[-84.413133,42.729102],"type":"Point"}
}