{
  "type": "Feature",
  "properties": {
    "iso:country":"US",
    "sg:address":"16013 Wilson Ave",
    "sg:city":"Eastpointe",
    "sg:classifiers":[
        {
            "category":"Animal Shelter",
            "type":"Public Place"
        },
        {
            "category":"Shopping",
            "subcategory":"Pets & Pet Supplies",
            "type":"Retail Goods"
        }
    ],
    "sg:phone":"+1 586 563 1738",
    "sg:postcode":"48021",
    "sg:province":"MI",
    "sg:tags":[
        "store"
    ],
    "wof:name":"Fortunate Feline Adoption League",
    "wof:placetype":"venue"
},
  "geometry": {"coordinates":[-82.956855,42.473492],"type":"Point"}
}