{
  "type": "Feature",
  "properties": {
    "iso:country":"US",
    "sg:address":"4700 36th St SE",
    "sg:city":"Grand Rapids",
    "sg:classifiers":[
        {
            "category":"Freight",
            "type":"Transportation"
        }
    ],
    "sg:phone":"+1 616 942 2332",
    "sg:postcode":"49512",
    "sg:province":"MI",
    "sg:tags":[
        "broker",
        "customs"
    ],
    "wof:name":"Trans-Overseas Corp",
    "wof:placetype":"venue"
},
  "geometry": {"coordinates":[-85.548654,42.897969],"type":"Point"}
}