{
  "type": "Feature",
  "properties": {
    "iso:country":"US",
    "sg:address":"9284 Mitchell Rd",
    "sg:city":"Petoskey",
    "sg:classifiers":[
        {
            "category":"Building & Trades",
            "subcategory":"Cleaning & Sanitation",
            "type":"Services"
        }
    ],
    "sg:phone":"+1 231 348 2794",
    "sg:postcode":"49770",
    "sg:province":"MI",
    "sg:tags":[
        "maintenance"
    ],
    "wof:name":"Aarons Job Clean Maint & Repr",
    "wof:placetype":"venue"
},
  "geometry": {"coordinates":[-84.77724000000001,45.360432],"type":"Point"}
}