{
  "type": "Feature",
  "properties": {
    "iso:country":"US",
    "sg:address":"2780 Holton Whitehall Rd",
    "sg:city":"Whitehall",
    "sg:classifiers":[
        {
            "category":"Manufacturing",
            "subcategory":"Tools & Machinery",
            "type":"Manufacturing & Wholesale Goods"
        }
    ],
    "sg:phone":"+1 231 893 0031",
    "sg:postcode":"49461",
    "sg:province":"MI",
    "sg:tags":[
        "mold",
        "special"
    ],
    "sg:website":"www.vikingtooleng.com",
    "wof:name":"Viking Tool & Engineering",
    "wof:placetype":"venue"
},
  "geometry": {"coordinates":[-86.31157399999999,43.410014],"type":"Point"}
}