{
  "type": "Feature",
  "properties": {
    "iso:country":"US",
    "sg:address":"801 Pleasant",
    "sg:city":"Mt Pleasant",
    "sg:classifiers":[
        {
            "category":"Manufacturing",
            "subcategory":"Tools & Machinery",
            "type":"Manufacturing & Wholesale Goods"
        }
    ],
    "sg:phone":"+1 989 773 6921",
    "sg:postcode":"48858",
    "sg:province":"MI",
    "sg:tags":[
        "power",
        "mechanical"
    ],
    "sg:website":"www.tbwoods.com",
    "wof:name":"T B Wood's Inc",
    "wof:placetype":"venue"
},
  "geometry": {"coordinates":[-84.779983,43.596903],"type":"Point"}
}