{
  "type": "Feature",
  "properties": {
    "iso:country":"US",
    "sg:address":"3025 E Hill Rd",
    "sg:city":"Grand Blanc",
    "sg:classifiers":[
        {
            "category":"Utilities",
            "subcategory":"Mobile Phone",
            "type":"Services"
        }
    ],
    "sg:phone":"+1 810 695 0400",
    "sg:postcode":"48439",
    "sg:province":"MI",
    "sg:tags":[
        "equipment",
        "paging",
        "signaling",
        "system"
    ],
    "wof:name":"Duke's Car Stereo",
    "wof:placetype":"venue"
},
  "geometry": {"coordinates":[-83.651217,42.944655],"type":"Point"}
}