{
  "type": "Feature",
  "properties": {
    "iso:country":"US",
    "sg:address":"603 E South St",
    "sg:city":"Jackson",
    "sg:classifiers":[
        {
            "category":"Autos & Motor Vehicles",
            "subcategory":"Automobile Sales",
            "type":"Retail Goods"
        }
    ],
    "sg:phone":"+1 517 782 3900",
    "sg:postcode":"49203",
    "sg:province":"MI",
    "sg:tags":[
        "car",
        "dealer"
    ],
    "wof:name":"Knuckles Malone's Motorcars",
    "wof:placetype":"venue"
},
  "geometry": {"coordinates":[-84.38716100000001,42.22574],"type":"Point"}
}