{
  "type": "Feature",
  "properties": {
    "iso:country":"US",
    "sg:address":"922 Lincoln Pkwy",
    "sg:city":"Plainwell",
    "sg:classifiers":[
        {
            "category":"Wholesale",
            "subcategory":"Machinery & Supplies",
            "type":"Manufacturing & Wholesale Goods"
        }
    ],
    "sg:phone":"+1 269 685 9361",
    "sg:postcode":"49080",
    "sg:province":"MI",
    "sg:tags":[
        "equipment",
        "industrial"
    ],
    "wof:name":"Inspection Equipment",
    "wof:placetype":"venue"
},
  "geometry": {"coordinates":[-85.62839099999999,42.449963],"type":"Point"}
}