{
  "type": "Feature",
  "properties": {
    "iso:country":"US",
    "sg:address":"7701 Sylvester St",
    "sg:city":"Detroit",
    "sg:classifiers":[
        {
            "category":"Education",
            "subcategory":"School",
            "type":"Public Place"
        }
    ],
    "sg:phone":"+1 313 866 4510",
    "sg:postcode":"48214",
    "sg:province":"MI",
    "wof:name":"Garvey Marcus Academy",
    "wof:placetype":"venue"
},
  "geometry": {"coordinates":[-83.01047699999999,42.368229],"type":"Point"}
}