{
  "type": "Feature",
  "properties": {
    "iso:country":"US",
    "sg:address":"5693 S Saginaw Rd",
    "sg:city":"Flint",
    "sg:classifiers":[
        {
            "category":"Building & Trades",
            "subcategory":"Construction",
            "type":"Services"
        }
    ],
    "sg:phone":"+1 810 579 1621",
    "sg:postcode":"48507",
    "sg:province":"MI",
    "sg:tags":[
        "general",
        "contractor"
    ],
    "wof:name":"Michigan Improvements Inc",
    "wof:placetype":"venue"
},
  "geometry": {"coordinates":[-83.651439,42.945598],"type":"Point"}
}