{
  "type": "Feature",
  "properties": {
    "iso:country":"US",
    "sg:address":"24366 Grand River Ave",
    "sg:city":"Detroit",
    "sg:classifiers":[
        {
            "category":"Health Services",
            "subcategory":"Doctor",
            "type":"Services"
        }
    ],
    "sg:phone":"+1 313 535 2273",
    "sg:postcode":"48219",
    "sg:province":"MI",
    "sg:tags":[
        "surgeon",
        "oral"
    ],
    "wof:name":"Azzouz Abraham L DDS",
    "wof:placetype":"venue"
},
  "geometry": {"coordinates":[-83.28190499999999,42.426425],"type":"Point"}
}