{
  "type": "Feature",
  "properties": {
    "iso:country":"US",
    "sg:address":"5995 State St",
    "sg:city":"Kingston",
    "sg:classifiers":[
        {
            "category":"Restaurant",
            "type":"Food & Drink"
        }
    ],
    "sg:phone":"+1 989 683 2189",
    "sg:postcode":"48741",
    "sg:province":"MI",
    "sg:tags":[
        "caterer"
    ],
    "wof:name":"Suzie Q Restaurant & Catering",
    "wof:placetype":"venue"
},
  "geometry": {"coordinates":[-83.18645100000001,43.413017],"type":"Point"}
}