{
  "type": "Feature",
  "properties": {
    "iso:country":"US",
    "sg:address":"989 Brenthaven Dr",
    "sg:city":"Bloomfield Hills",
    "sg:classifiers":[
        {
            "category":"Professional",
            "type":"Services"
        }
    ],
    "sg:phone":"+1 248 335 8558",
    "sg:postcode":"48304",
    "sg:province":"MI",
    "wof:name":"Newman & Assoc Tax Svc",
    "wof:placetype":"venue"
},
  "geometry": {"coordinates":[-83.224214,42.608342],"type":"Point"}
}