{
  "type": "Feature",
  "properties": {
    "iso:country":"US",
    "sg:address":"45554 Turtlehead Ct S",
    "sg:city":"Plymouth",
    "sg:classifiers":[
        {
            "category":"Wholesale",
            "subcategory":"Non-durable Goods",
            "type":"Manufacturing & Wholesale Goods"
        }
    ],
    "sg:phone":"+1 734 453 2561",
    "sg:postcode":"48170",
    "sg:province":"MI",
    "wof:name":"Trillium Gardens",
    "wof:placetype":"venue"
},
  "geometry": {"coordinates":[-83.490458,42.358807],"type":"Point"}
}