{
  "type": "Feature",
  "properties": {
    "iso:country":"US",
    "sg:address":"616 W Hancock St",
    "sg:city":"Detroit",
    "sg:classifiers":[
        {
            "category":"Organizations",
            "subcategory":"Religious Organization",
            "type":"Services"
        }
    ],
    "sg:phone":"+1 313 832 6880",
    "sg:postcode":"48201",
    "sg:province":"MI",
    "wof:name":"Central Allinace Church",
    "wof:placetype":"venue"
},
  "geometry": {"coordinates":[-83.06923500000001,42.353899],"type":"Point"}
}