{
  "type": "Feature",
  "properties": {
    "iso:country":"US",
    "sg:address":"29777 Telegraph Rd Ste 2590",
    "sg:city":"Southfield",
    "sg:classifiers":[
        {
            "category":"Banks & Credit Unions",
            "subcategory":"Atm",
            "type":"Services"
        }
    ],
    "sg:phone":"+1 248 351 9311",
    "sg:postcode":"48034",
    "sg:province":"MI",
    "sg:tags":[
        "bankruptcy"
    ],
    "sg:website":"www.debtproblemsgone.com",
    "wof:name":"Danton & Smyk Pllc",
    "wof:placetype":"venue"
},
  "geometry": {"coordinates":[-83.285781,42.50642],"type":"Point"}
}