{
  "type": "Feature",
  "properties": {
    "iso:country":"US",
    "sg:address":"8950 Howard City Edmore Rd",
    "sg:city":"Vestaburg",
    "sg:classifiers":[
        {
            "category":"Food & Beverages",
            "subcategory":"Groceries & Convenience Stores",
            "type":"Retail Goods"
        }
    ],
    "sg:phone":"+1 989 268 5000",
    "sg:postcode":"48891",
    "sg:province":"MI",
    "sg:tags":[
        "grocer"
    ],
    "wof:name":"Uncle Paul's Foods",
    "wof:placetype":"venue"
},
  "geometry": {"coordinates":[-84.90923100000001,43.408122],"type":"Point"}
}