{
  "type": "Feature",
  "properties": {
    "iso:country":"US",
    "sg:address":"3890 S 198th Ave",
    "sg:city":"Hesperia",
    "sg:classifiers":[
        {
            "category":"Real Estate",
            "subcategory":"Developer",
            "type":"Services"
        }
    ],
    "sg:phone":"+1 231 854 4702",
    "sg:postcode":"49421",
    "sg:province":"MI",
    "sg:tags":[
        "cemetery"
    ],
    "wof:name":"New Field Township Hall",
    "wof:placetype":"venue"
},
  "geometry": {"coordinates":[-86.064369,43.570826],"type":"Point"}
}