{
  "type": "Feature",
  "properties": {
    "iso:country":"US",
    "sg:address":"207 W Wilson Rd",
    "sg:city":"Scottville",
    "sg:classifiers":[
        {
            "category":"Personal",
            "subcategory":"Beauty Salon",
            "type":"Services"
        }
    ],
    "sg:phone":"+1 231 757 2427",
    "sg:postcode":"49454",
    "sg:province":"MI",
    "wof:name":"Charp Hair",
    "wof:placetype":"venue"
},
  "geometry": {"coordinates":[-86.284069,43.918843],"type":"Point"}
}