{
  "type": "Feature",
  "properties": {
    "iso:country":"US",
    "sg:address":"118 Main St",
    "sg:city":"Hanover",
    "sg:classifiers":[
        {
            "category":"Education",
            "subcategory":"Library",
            "type":"Public Place"
        }
    ],
    "sg:phone":"+1 517 563 8344",
    "sg:postcode":"49241",
    "sg:province":"MI",
    "wof:name":"Jackson District Library",
    "wof:placetype":"venue"
},
  "geometry": {"coordinates":[-84.554373,42.10198],"type":"Point"}
}