{
  "type": "Feature",
  "properties": {
    "iso:country":"US",
    "sg:address":"600 School Dr",
    "sg:city":"Plainwell",
    "sg:classifiers":[
        {
            "category":"Education",
            "subcategory":"School",
            "type":"Public Place"
        }
    ],
    "sg:phone":"+1 269 685 5823",
    "sg:postcode":"49080",
    "sg:province":"MI",
    "sg:website":"www.plainwellschools.org",
    "wof:name":"Plainwell Community School Dst",
    "wof:placetype":"venue"
},
  "geometry": {"coordinates":[-85.650082,42.437121],"type":"Point"}
}