{
  "type": "Feature",
  "properties": {
    "iso:country":"US",
    "sg:address":"3402 Yale St",
    "sg:city":"Flint",
    "sg:classifiers":[
        {
            "category":"Professional",
            "subcategory":"Business Services",
            "type":"Services"
        }
    ],
    "sg:phone":"+1 810 238 6128",
    "sg:postcode":"48503",
    "sg:province":"MI",
    "wof:name":"1 Hour Bail Bonds",
    "wof:placetype":"venue"
},
  "geometry": {"coordinates":[-83.73289800000001,42.993255],"type":"Point"}
}