{
  "type": "Feature",
  "properties": {
    "iso:country":"US",
    "sg:address":"100 N Maple Grove Ave",
    "sg:city":"Hudson",
    "sg:classifiers":[
        {
            "category":"Food & Beverages",
            "subcategory":"Bakery",
            "type":"Retail Goods"
        }
    ],
    "sg:phone":"+1 517 448 8618",
    "sg:postcode":"49247",
    "sg:province":"MI",
    "sg:tags":[
        "baker"
    ],
    "wof:name":"Mc Carty's Old World Bakery",
    "wof:placetype":"venue"
},
  "geometry": {"coordinates":[-84.348551,41.855909],"type":"Point"}
}