{
  "type": "Feature",
  "properties": {
    "iso:country":"US",
    "sg:address":"4883 Haggerty Rd",
    "sg:city":"West Bloomfield",
    "sg:classifiers":[
        {
            "category":"Health Services",
            "subcategory":"Podiatrist",
            "type":"Services"
        }
    ],
    "sg:phone":"+1 248 960 9895",
    "sg:postcode":"48323",
    "sg:province":"MI",
    "wof:name":"Foot EFX",
    "wof:placetype":"venue"
},
  "geometry": {"coordinates":[-83.44001799999999,42.576737],"type":"Point"}
}