{
  "type": "Feature",
  "properties": {
    "iso:country":"US",
    "sg:address":"19111 W 10 Mile Rd",
    "sg:city":"Southfield",
    "sg:classifiers":[
        {
            "category":"Utilities",
            "subcategory":"Telephone",
            "type":"Services"
        }
    ],
    "sg:phone":"+1 248 213 0030",
    "sg:postcode":"48075",
    "sg:province":"MI",
    "sg:tags":[
        "company"
    ],
    "wof:name":"Global Deregulated Svc",
    "wof:placetype":"venue"
},
  "geometry": {"coordinates":[-83.233189,42.473025],"type":"Point"}
}