{
  "type": "Feature",
  "properties": {
    "iso:country":"US",
    "sg:address":"10883 E Fort Rd",
    "sg:city":"Suttons Bay",
    "sg:classifiers":[
        {
            "category":"Autos & Motor Vehicles",
            "subcategory":"Auto Supplies",
            "type":"Retail Goods"
        }
    ],
    "sg:phone":"+1 231 271 6766",
    "sg:postcode":"49682",
    "sg:province":"MI",
    "wof:name":"Dd Auto Speed Shop",
    "wof:placetype":"venue"
},
  "geometry": {"coordinates":[-85.633742,44.917776],"type":"Point"}
}