{
  "type": "Feature",
  "properties": {
    "iso:country":"US",
    "sg:address":"3521 E Cork St",
    "sg:city":"Kalamazoo",
    "sg:classifiers":[
        {
            "category":"Freight",
            "type":"Transportation"
        }
    ],
    "sg:phone":"+1 269 349 1588",
    "sg:postcode":"49001",
    "sg:province":"MI",
    "sg:tags":[
        "operator",
        "trucking"
    ],
    "wof:name":"Fedex",
    "wof:placetype":"venue"
},
  "geometry": {"coordinates":[-85.535628,42.259628],"type":"Point"}
}