{
  "type": "Feature",
  "properties": {
    "iso:country":"US",
    "sg:address":"615 E Main St",
    "sg:city":"Centreville",
    "sg:classifiers":[
        {
            "category":"Social Services",
            "type":"Services"
        }
    ],
    "sg:phone":"+1 269 467 1200",
    "sg:postcode":"49032",
    "sg:province":"MI",
    "sg:tags":[
        "counseling",
        "family"
    ],
    "wof:name":"Family Independence Agcy Mich",
    "wof:placetype":"venue"
},
  "geometry": {"coordinates":[-85.512781,41.922748],"type":"Point"}
}