{
  "type": "Feature",
  "properties": {
    "iso:country":"US",
    "sg:address":"23148 Elmira St",
    "sg:city":"Clinton Township",
    "sg:classifiers":[
        {
            "category":"Building & Trades",
            "subcategory":"Cleaning & Sanitation",
            "type":"Services"
        }
    ],
    "sg:phone":"+1 586 296 0695",
    "sg:postcode":"48035",
    "sg:province":"MI",
    "sg:tags":[
        "maintenance"
    ],
    "wof:name":"T & Ms Window Cleaning",
    "wof:placetype":"venue"
},
  "geometry": {"coordinates":[-82.879172,42.540893],"type":"Point"}
}