{
  "type": "Feature",
  "properties": {
    "iso:country":"US",
    "sg:address":"11320 S 34th St",
    "sg:city":"Vicksburg",
    "sg:classifiers":[
        {
            "category":"Building & Trades",
            "subcategory":"Construction",
            "type":"Services"
        }
    ],
    "sg:phone":"+1 269 649 2611",
    "sg:postcode":"49097",
    "sg:province":"MI",
    "sg:tags":[
        "excavation",
        "contractor"
    ],
    "wof:name":"Yard Bird",
    "wof:placetype":"venue"
},
  "geometry": {"coordinates":[-85.43204,42.153675],"type":"Point"}
}