{
  "type": "Feature",
  "properties": {
    "iso:country":"US",
    "sg:address":"32440 Susanne Dr",
    "sg:city":"Franklin",
    "sg:classifiers":[
        {
            "category":"Shopping",
            "subcategory":"Computers & Home Electronics",
            "type":"Retail Goods"
        }
    ],
    "sg:phone":"+1 248 855 1757",
    "sg:postcode":"48025",
    "sg:province":"MI",
    "sg:tags":[
        "equipment",
        "dealer"
    ],
    "wof:name":"Spectrum Computer Forensic",
    "wof:placetype":"venue"
},
  "geometry": {"coordinates":[-83.29160899999999,42.525525],"type":"Point"}
}