{
  "type": "Feature",
  "properties": {
    "iso:country":"US",
    "sg:address":"3770 Baumhoff Ave NW",
    "sg:city":"Comstock Park",
    "sg:classifiers":[
        {
            "category":"Building & Trades",
            "subcategory":"Construction",
            "type":"Services"
        }
    ],
    "sg:phone":"+1 616 784 9536",
    "sg:postcode":"49321",
    "sg:province":"MI",
    "sg:tags":[
        "residential",
        "contractor"
    ],
    "wof:name":"William D Towns Builder",
    "wof:placetype":"venue"
},
  "geometry": {"coordinates":[-85.71901099999999,43.030879],"type":"Point"}
}