{
  "type": "Feature",
  "properties": {
    "iso:country":"US",
    "sg:address":"5505 Red Arrow Hwy",
    "sg:city":"Stevensville",
    "sg:classifiers":[
        {
            "category":"Retail",
            "subcategory":"Auto Repair",
            "type":"Services"
        }
    ],
    "sg:phone":"+1 269 429 3522",
    "sg:postcode":"49127",
    "sg:province":"MI",
    "sg:tags":[
        "body",
        "automobile",
        "painting"
    ],
    "wof:name":"P & R Body Shop",
    "wof:placetype":"venue"
},
  "geometry": {"coordinates":[-86.52703099999999,42.021019],"type":"Point"}
}