{
  "type": "Feature",
  "properties": {
    "iso:country":"US",
    "sg:address":"700 36th St SE",
    "sg:city":"Grand Rapids",
    "sg:classifiers":[
        {
            "category":"Banks & Credit Unions",
            "subcategory":"Bank",
            "type":"Services"
        }
    ],
    "sg:phone":"+1 616 246 5442",
    "sg:postcode":"49548",
    "sg:province":"MI",
    "sg:tags":[
        "mortgage"
    ],
    "wof:name":"Home Lending Center",
    "wof:placetype":"venue"
},
  "geometry": {"coordinates":[-85.64945400000001,42.898288],"type":"Point"}
}