{
  "type": "Feature",
  "properties": {
    "iso:country":"US",
    "sg:address":"4333 W Willow Hwy",
    "sg:city":"Lansing",
    "sg:classifiers":[
        {
            "category":"Social Services",
            "subcategory":"Child Care",
            "type":"Services"
        }
    ],
    "sg:phone":"+1 517 886 1212",
    "sg:postcode":"48917",
    "sg:province":"MI",
    "wof:name":"St Gerard Church Child Care",
    "wof:placetype":"venue"
},
  "geometry": {"coordinates":[-84.612126,42.748258],"type":"Point"}
}