{
  "type": "Feature",
  "properties": {
    "iso:country":"US",
    "sg:address":"2801 E Beltline Ave NE",
    "sg:city":"Grand Rapids",
    "sg:classifiers":[
        {
            "category":"Building & Trades",
            "subcategory":"Construction",
            "type":"Services"
        }
    ],
    "sg:phone":"+1 616 364 6161",
    "sg:postcode":"49525",
    "sg:province":"MI",
    "sg:tags":[
        "work",
        "sub",
        "carpentry"
    ],
    "wof:name":"Shawnlee Construction LLC",
    "wof:placetype":"venue"
},
  "geometry": {"coordinates":[-85.590481,43.015491],"type":"Point"}
}