{
  "type": "Feature",
  "properties": {
    "iso:country":"US",
    "sg:address":"850 S Old Woodward Ave",
    "sg:city":"Birmingham",
    "sg:classifiers":[
        {
            "category":"Shopping",
            "subcategory":"Antiques",
            "type":"Retail Goods"
        },
        {
            "category":"Home & Garden",
            "subcategory":"Carpets & Floor Coverings",
            "type":"Retail Goods"
        }
    ],
    "sg:phone":"+1 248 646 7847",
    "sg:postcode":"48009",
    "sg:province":"MI",
    "sg:tags":[
        "carpeting"
    ],
    "wof:name":"Hagopian Carpet Cleaners the Original",
    "wof:placetype":"venue"
},
  "geometry": {"coordinates":[-83.2089,42.5411],"type":"Point"}
}