{
  "type": "Feature",
  "properties": {
    "iso:country":"US",
    "sg:address":"8471 Gutchess Rd",
    "sg:city":"Alpena",
    "sg:classifiers":[
        {
            "category":"Building & Trades",
            "subcategory":"Construction",
            "type":"Services"
        }
    ],
    "sg:phone":"+1 989 595 2352",
    "sg:postcode":"49707",
    "sg:province":"MI",
    "sg:tags":[
        "general",
        "contractor"
    ],
    "wof:name":"Kurt Broers Builders",
    "wof:placetype":"venue"
},
  "geometry": {"coordinates":[-83.423547,45.169196],"type":"Point"}
}