{
  "type": "Feature",
  "properties": {
    "iso:country":"US",
    "sg:address":"11330 Gratiot Ave",
    "sg:city":"Detroit",
    "sg:classifiers":[
        {
            "category":"Shopping",
            "subcategory":"Shoes",
            "type":"Retail Goods"
        }
    ],
    "sg:phone":"+1 313 521 2910",
    "sg:postcode":"48213",
    "sg:province":"MI",
    "sg:tags":[
        "store"
    ],
    "sg:website":"www.payless.com",
    "wof:name":"Payless Shoesource",
    "wof:placetype":"venue"
},
  "geometry": {"coordinates":[-82.9944,42.409401],"type":"Point"}
}