{
  "type": "Feature",
  "properties": {
    "iso:country":"US",
    "sg:address":"3965 Okemos Rd",
    "sg:city":"Okemos",
    "sg:classifiers":[
        {
            "category":"Banks & Credit Unions",
            "subcategory":"Investment Brokerage",
            "type":"Services"
        }
    ],
    "sg:phone":"+1 517 349 9400",
    "sg:postcode":"48864",
    "sg:province":"MI",
    "sg:tags":[
        "security"
    ],
    "sg:website":"www.age.com",
    "wof:name":"A G Edwards & Sons Inc",
    "wof:placetype":"venue"
},
  "geometry": {"coordinates":[-84.432468,42.69636],"type":"Point"}
}