{
  "type": "Feature",
  "properties": {
    "iso:country":"US",
    "sg:address":"14971 E 10 Mile Rd",
    "sg:city":"Warren",
    "sg:classifiers":[
        {
            "category":"Food & Beverages",
            "subcategory":"Groceries & Convenience Stores",
            "type":"Retail Goods"
        }
    ],
    "sg:phone":"+1 586 774 4441",
    "sg:postcode":"48089",
    "sg:province":"MI",
    "wof:name":"7-Eleven",
    "wof:placetype":"venue"
},
  "geometry": {"coordinates":[-82.96715500000001,42.4796],"type":"Point"}
}