{
  "type": "Feature",
  "properties": {
    "iso:country":"US",
    "sg:address":"26339 Woodward Ave",
    "sg:city":"Huntington Wd",
    "sg:classifiers":[
        {
            "category":"Professional",
            "subcategory":"Lawyer & Legal Services",
            "type":"Services"
        }
    ],
    "sg:phone":"+1 248 548 1200",
    "sg:postcode":"48070",
    "sg:province":"MI",
    "wof:name":"Schlussel Barry N Atty",
    "wof:placetype":"venue"
},
  "geometry": {"coordinates":[-83.153801,42.4841],"type":"Point"}
}