{
  "type": "Feature",
  "properties": {
    "iso:country":"US",
    "sg:address":"10 W Huron St",
    "sg:city":"Pontiac",
    "sg:classifiers":[
        {
            "category":"Professional",
            "subcategory":"Computer Services",
            "type":"Services"
        }
    ],
    "sg:phone":"+1 248 628 8000",
    "sg:postcode":"48342",
    "sg:province":"MI",
    "sg:tags":[
        "consultant",
        "consulting",
        "designer"
    ],
    "sg:website":"www.sabrecon.com",
    "wof:name":"Sabre Consulting Inc",
    "wof:placetype":"venue"
},
  "geometry": {"coordinates":[-83.293752,42.638696],"type":"Point"}
}