{
  "type": "Feature",
  "properties": {
    "iso:country":"US",
    "sg:address":"44902 Vic Wertz Dr",
    "sg:city":"Clinton Twp",
    "sg:classifiers":[
        {
            "category":"Manufacturing",
            "subcategory":"Printing",
            "type":"Manufacturing & Wholesale Goods"
        }
    ],
    "sg:phone":"+1 586 465 6777",
    "sg:postcode":"48036",
    "sg:province":"MI",
    "sg:tags":[
        "printer"
    ],
    "wof:name":"Elklitho Service",
    "wof:placetype":"venue"
},
  "geometry": {"coordinates":[-82.869635,42.628316],"type":"Point"}
}