{
  "type": "Feature",
  "properties": {
    "iso:country":"US",
    "sg:address":"1065 N Telegraph Rd",
    "sg:city":"Monroe",
    "sg:classifiers":[
        {
            "category":"Wholesale",
            "subcategory":"Beer",
            "type":"Manufacturing & Wholesale Goods"
        }
    ],
    "sg:phone":"+1 734 242 4646",
    "sg:postcode":"48162",
    "sg:province":"MI",
    "sg:tags":[
        "ale"
    ],
    "wof:name":"Custer Beer Co",
    "wof:placetype":"venue"
},
  "geometry": {"coordinates":[-83.408458,41.934974],"type":"Point"}
}