{
  "type": "Feature",
  "properties": {
    "iso:country":"US",
    "sg:address":"4864 Lapeer Rd",
    "sg:city":"Kimball",
    "sg:classifiers":[
        {
            "category":"Organizations",
            "subcategory":"Religious Organization",
            "type":"Services"
        }
    ],
    "sg:phone":"+1 810 987 1478",
    "sg:postcode":"48074",
    "sg:province":"MI",
    "sg:tags":[
        "church"
    ],
    "sg:website":"www.thatchurch.com",
    "wof:name":"Life Of Faith Fellowship Chr",
    "wof:placetype":"venue"
},
  "geometry": {"coordinates":[-82.520518,42.983403],"type":"Point"}
}