{
  "type": "Feature",
  "properties": {
    "iso:country":"US",
    "sg:address":"108 Arthur Dr",
    "sg:city":"Troy",
    "sg:classifiers":[
        {
            "category":"Wholesale",
            "subcategory":"Auto Parts",
            "type":"Manufacturing & Wholesale Goods"
        }
    ],
    "sg:phone":"+1 248 740 9565",
    "sg:postcode":"48083",
    "sg:province":"MI",
    "wof:name":"Daaron Trading Co",
    "wof:placetype":"venue"
},
  "geometry": {"coordinates":[-83.14451200000001,42.55246],"type":"Point"}
}