{
  "type": "Feature",
  "properties": {
    "iso:country":"US",
    "sg:address":"200 Maple Park Blvd",
    "sg:city":"St Clair Shores",
    "sg:classifiers":[
        {
            "category":"Wholesale",
            "subcategory":"Motor Vehicles",
            "type":"Manufacturing & Wholesale Goods"
        }
    ],
    "sg:phone":"+1 586 498 9707",
    "sg:postcode":"48081",
    "sg:province":"MI",
    "sg:tags":[
        "automobile",
        "truck",
        "broker"
    ],
    "wof:name":"C Neumann Assoc",
    "wof:placetype":"venue"
},
  "geometry": {"coordinates":[-82.89459600000001,42.478906],"type":"Point"}
}