{
  "type": "Feature",
  "properties": {
    "iso:country":"US",
    "sg:address":"10640 Waterman Rd",
    "sg:city":"Brooklyn",
    "sg:classifiers":[
        {
            "category":"Education",
            "subcategory":"Special Training",
            "type":"Public Place"
        }
    ],
    "sg:phone":"+1 517 592 8235",
    "sg:postcode":"49230",
    "sg:province":"MI",
    "wof:name":"Jeffreys Driving School",
    "wof:placetype":"venue"
},
  "geometry": {"coordinates":[-84.228516,42.10965],"type":"Point"}
}