{
  "type": "Feature",
  "properties": {
    "iso:country":"US",
    "sg:address":"11955 Dewey Rd",
    "sg:city":"Munith",
    "sg:classifiers":[
        {
            "category":"Sports & Exercise",
            "subcategory":"Race Track",
            "type":"Entertainment"
        }
    ],
    "sg:phone":"+1 517 596 3266",
    "sg:postcode":"49259",
    "sg:province":"MI",
    "sg:tags":[
        "operation",
        "racing",
        "or"
    ],
    "wof:name":"P&K Racing",
    "wof:placetype":"venue"
},
  "geometry": {"coordinates":[-84.225013,42.397761],"type":"Point"}
}