{
  "type": "Feature",
  "properties": {
    "iso:country":"US",
    "sg:address":"404 S Dayton St",
    "sg:city":"Davison",
    "sg:classifiers":[
        {
            "category":"Organizations",
            "subcategory":"Non-profit Organization",
            "type":"Services"
        }
    ],
    "sg:phone":"+1 810 653 5967",
    "sg:postcode":"48423",
    "sg:province":"MI",
    "sg:tags":[
        "action",
        "agency",
        "community"
    ],
    "wof:name":"Gccard Headstart",
    "wof:placetype":"venue"
},
  "geometry": {"coordinates":[-83.520574,43.026957],"type":"Point"}
}