{
  "type": "Feature",
  "properties": {
    "iso:country":"US",
    "sg:address":"11285 Peet Rd",
    "sg:city":"Chesaning",
    "sg:classifiers":[
        {
            "category":"Shopping",
            "subcategory":"Gifts & Souvenirs",
            "type":"Retail Goods"
        }
    ],
    "sg:phone":"+1 989 845 3923",
    "sg:postcode":"48616",
    "sg:province":"MI",
    "wof:name":"Mole Catcher",
    "wof:placetype":"venue"
},
  "geometry": {"coordinates":[-84.132227,43.173061],"type":"Point"}
}