{
  "type": "Feature",
  "properties": {
    "iso:country":"US",
    "sg:address":"3557 Fort St",
    "sg:city":"Wyandotte",
    "sg:classifiers":[
        {
            "category":"Professional",
            "subcategory":"Printing & Photocopies",
            "type":"Services"
        }
    ],
    "sg:phone":"+1 734 284 5330",
    "sg:postcode":"48192",
    "sg:province":"MI",
    "wof:name":"American Speedy Printing Centers",
    "wof:placetype":"venue"
},
  "geometry": {"coordinates":[-83.179802,42.1964],"type":"Point"}
}