{
  "type": "Feature",
  "properties": {
    "iso:country":"US",
    "sg:address":"514 S River St",
    "sg:city":"Eaton Rapids",
    "sg:classifiers":[
        {
            "category":"Manufacturing",
            "subcategory":"Printing",
            "type":"Manufacturing & Wholesale Goods"
        }
    ],
    "sg:phone":"+1 517 663 3275",
    "sg:postcode":"48827",
    "sg:province":"MI",
    "sg:tags":[
        "printer"
    ],
    "wof:name":"Just Fred Inc",
    "wof:placetype":"venue"
},
  "geometry": {"coordinates":[-84.653409,42.507582],"type":"Point"}
}