{
  "type": "Feature",
  "properties": {
    "iso:country":"US",
    "sg:address":"6670 Heatheridge Dr",
    "sg:city":"Saline",
    "sg:classifiers":[
        {
            "category":"Professional",
            "subcategory":"Management & Consulting",
            "type":"Services"
        }
    ],
    "sg:phone":"+1 734 429 1158",
    "sg:postcode":"48176",
    "sg:province":"MI",
    "sg:tags":[
        "business"
    ],
    "wof:name":"Buzas Consulting",
    "wof:placetype":"venue"
},
  "geometry": {"coordinates":[-83.807723,42.186645],"type":"Point"}
}