{
  "type": "Feature",
  "properties": {
    "iso:country":"US",
    "sg:address":"6717 Lindsey Rd",
    "sg:city":"Delton",
    "sg:classifiers":[
        {
            "category":"Building & Trades",
            "subcategory":"Landscaping Services",
            "type":"Services"
        }
    ],
    "sg:phone":"+1 269 623 2272",
    "sg:postcode":"49046",
    "sg:province":"MI",
    "sg:tags":[
        "designer",
        "landscape"
    ],
    "wof:name":"Dustin's Lawn Care & Snow Plwg",
    "wof:placetype":"venue"
},
  "geometry": {"coordinates":[-85.50620499999999,42.558051],"type":"Point"}
}