{
  "type": "Feature",
  "properties": {
    "iso:country":"US",
    "sg:address":"1007 Washington Ave",
    "sg:city":"Bay City",
    "sg:classifiers":[
        {
            "category":"Restaurant",
            "type":"Food & Drink"
        }
    ],
    "sg:phone":"+1 989 893 9332",
    "sg:postcode":"48708",
    "sg:province":"MI",
    "wof:name":"Stock'Pot Catering",
    "wof:placetype":"venue"
},
  "geometry": {"coordinates":[-83.887432,43.601014],"type":"Point"}
}