{
  "type": "Feature",
  "properties": {
    "iso:country":"US",
    "sg:address":"21671 Shadybrook Dr",
    "sg:city":"Novi",
    "sg:classifiers":[
        {
            "category":"Professional",
            "subcategory":"Business Services",
            "type":"Services"
        }
    ],
    "sg:phone":"+1 248 348 0311",
    "sg:postcode":"48375",
    "sg:province":"MI",
    "wof:name":"Elfring Family Ltd Partnership",
    "wof:placetype":"venue"
},
  "geometry": {"coordinates":[-83.445661,42.446183],"type":"Point"}
}