{
  "type": "Feature",
  "properties": {
    "iso:country":"US",
    "sg:address":"7414 E Atherton Rd",
    "sg:city":"Flushing",
    "sg:classifiers":[
        {
            "category":"Banks & Credit Unions",
            "subcategory":"Financial Services",
            "type":"Services"
        }
    ],
    "sg:phone":"+1 810 653 6531",
    "sg:postcode":"48423",
    "sg:province":"MI",
    "sg:tags":[
        "investor"
    ],
    "wof:name":"Cornerstone Investors",
    "wof:placetype":"venue"
},
  "geometry": {"coordinates":[-83.56442300000001,42.990483],"type":"Point"}
}