{
  "type": "Feature",
  "properties": {
    "iso:country":"US",
    "sg:address":"397 Capital Ave NE",
    "sg:city":"Battle Creek",
    "sg:classifiers":[
        {
            "category":"Personal",
            "subcategory":"Beauty Salon",
            "type":"Services"
        }
    ],
    "sg:phone":"+1 269 969 9551",
    "sg:postcode":"49017",
    "sg:province":"MI",
    "wof:name":"Sandy's Salon",
    "wof:placetype":"venue"
},
  "geometry": {"coordinates":[-85.16665,42.323748],"type":"Point"}
}