{
  "type": "Feature",
  "properties": {
    "iso:country":"US",
    "sg:address":"1106 W Dill Rd",
    "sg:city":"Dewitt",
    "sg:classifiers":[
        {
            "category":"Building & Trades",
            "subcategory":"Construction",
            "type":"Services"
        }
    ],
    "sg:phone":"+1 517 669 9224",
    "sg:postcode":"48820",
    "sg:province":"MI",
    "sg:tags":[
        "house"
    ],
    "wof:name":"Jaynes Construction Co",
    "wof:placetype":"venue"
},
  "geometry": {"coordinates":[-84.553146,42.839389],"type":"Point"}
}