{
  "type": "Feature",
  "properties": {
    "iso:country":"US",
    "sg:address":"18660 Mack Ave",
    "sg:city":"Grosse Pointe",
    "sg:classifiers":[
        {
            "category":"Restaurant",
            "type":"Food & Drink"
        }
    ],
    "sg:phone":"+1 313 881 7392",
    "sg:postcode":"48236",
    "sg:province":"MI",
    "sg:tags":[
        "pizza"
    ],
    "wof:name":"Mr C's Deli of Grosse Pointe Farms",
    "wof:placetype":"venue"
},
  "geometry": {"coordinates":[-82.911697,42.413601],"type":"Point"}
}