{
  "type": "Feature",
  "properties": {
    "iso:country":"US",
    "sg:address":"904 Blackbird Rd",
    "sg:city":"Petoskey",
    "sg:classifiers":[
        {
            "category":"Restaurant",
            "type":"Food & Drink"
        }
    ],
    "sg:phone":"+1 231 348 3044",
    "sg:postcode":"49770",
    "sg:province":"MI",
    "sg:tags":[
        "caterer"
    ],
    "wof:name":"Real Food Dream Kitchen",
    "wof:placetype":"venue"
},
  "geometry": {"coordinates":[-85.00584600000001,45.363253],"type":"Point"}
}