{
  "type": "Feature",
  "properties": {
    "iso:country":"US",
    "sg:address":"23700 Goddard",
    "sg:city":"Detroit",
    "sg:classifiers":[
        {
            "category":"Banks & Credit Unions",
            "subcategory":"Bank",
            "type":"Services"
        }
    ],
    "sg:phone":"+1 313 291 3900",
    "sg:postcode":"48201",
    "sg:province":"MI",
    "wof:name":"Standard Federal Bank",
    "wof:placetype":"venue"
},
  "geometry": {"coordinates":[-83.058899,42.3489],"type":"Point"}
}