{
  "type": "Feature",
  "properties": {
    "iso:country":"US",
    "sg:address":"5011 Port Sheldon St",
    "sg:city":"Hudsonville",
    "sg:classifiers":[
        {
            "category":"Building & Trades",
            "subcategory":"Construction",
            "type":"Services"
        }
    ],
    "sg:phone":"+1 616 662 8800",
    "sg:postcode":"49426",
    "sg:province":"MI",
    "wof:name":"Gold Coast Homes",
    "wof:placetype":"venue"
},
  "geometry": {"coordinates":[-85.906189,42.885277],"type":"Point"}
}