{
  "type": "Feature",
  "properties": {
    "iso:country":"US",
    "sg:address":"14375 Torrey Rd",
    "sg:city":"Fenton",
    "sg:classifiers":[
        {
            "category":"Shopping",
            "subcategory":"Used Merchandise",
            "type":"Retail Goods"
        }
    ],
    "sg:phone":"+1 810 714 3666",
    "sg:postcode":"48430",
    "sg:province":"MI",
    "sg:tags":[
        "antique"
    ],
    "wof:name":"Peacock Antiques & Auction Hse",
    "wof:placetype":"venue"
},
  "geometry": {"coordinates":[-83.726867,42.819238],"type":"Point"}
}