{
  "type": "Feature",
  "properties": {
    "iso:country":"US",
    "sg:address":"113 E State St",
    "sg:city":"Cheboygan",
    "sg:classifiers":[
        {
            "category":"Recreation",
            "subcategory":"Marina",
            "type":"Entertainment"
        }
    ],
    "sg:phone":"+1 231 627 7105",
    "sg:postcode":"49721",
    "sg:province":"MI",
    "sg:website":"www.walstrom.com",
    "wof:name":"Walstrom Marine-Cheboygan Inc",
    "wof:placetype":"venue"
},
  "geometry": {"coordinates":[-84.47247900000001,45.645895],"type":"Point"}
}