{
  "type": "Feature",
  "properties": {
    "iso:country":"US",
    "sg:address":"22100 W Warren Ave",
    "sg:city":"Redford",
    "sg:classifiers":[
        {
            "category":"Bars & Pubs",
            "type":"Food & Drink"
        }
    ],
    "sg:menulink":"http://www.allmenus.com/mi/detroit/246834-halligans-bar/menu/",
    "sg:phone":"+1 313 792 8399",
    "sg:postcode":"48239",
    "sg:province":"MI",
    "sg:tags":[
        "burger",
        "american"
    ],
    "wof:name":"Halligan's Bar",
    "wof:placetype":"venue"
},
  "geometry": {"coordinates":[-83.255122,42.342103],"type":"Point"}
}