{
  "type": "Feature",
  "properties": {
    "iso:country":"US",
    "sg:address":"1000 Brush St",
    "sg:city":"Detroit",
    "sg:classifiers":[
        {
            "category":"Banks & Credit Unions",
            "subcategory":"Bank",
            "type":"Services"
        }
    ],
    "sg:phone":"+1 313 962 2420",
    "sg:postcode":"48226",
    "sg:province":"MI",
    "wof:name":"First Independent Bank",
    "wof:placetype":"venue"
},
  "geometry": {"coordinates":[-83.043395,42.334213],"type":"Point"}
}