{
  "type": "Feature",
  "properties": {
    "iso:country":"US",
    "sg:address":"15700 W 10 Mile Rd",
    "sg:city":"Southfield",
    "sg:classifiers":[
        {
            "category":"Banks & Credit Unions",
            "subcategory":"Bank",
            "type":"Services"
        }
    ],
    "sg:phone":"+1 248 443 7462",
    "sg:postcode":"48075",
    "sg:province":"MI",
    "sg:tags":[
        "loan",
        "broker",
        "mortgage"
    ],
    "wof:name":"Millennium Loans",
    "wof:placetype":"venue"
},
  "geometry": {"coordinates":[-83.203295,42.473937],"type":"Point"}
}