{
  "type": "Feature",
  "properties": {
    "iso:country":"US",
    "sg:address":"515 N Monroe St",
    "sg:city":"Traverse City",
    "sg:classifiers":[
        {
            "category":"Professional",
            "subcategory":"Business Services",
            "type":"Services"
        }
    ],
    "sg:phone":"+1 231 929 1973",
    "sg:postcode":"49684",
    "sg:province":"MI",
    "wof:name":"Upnorth Stuff",
    "wof:placetype":"venue"
},
  "geometry": {"coordinates":[-85.641161,44.770398],"type":"Point"}
}