{
  "type": "Feature",
  "properties": {
    "iso:country":"US",
    "sg:address":"4906 Charing Cross Rd",
    "sg:city":"Bloomfield Hills",
    "sg:classifiers":[
        {
            "category":"Professional",
            "subcategory":"Business Services",
            "type":"Services"
        }
    ],
    "sg:phone":"+1 248 258 1645",
    "sg:postcode":"48304",
    "sg:province":"MI",
    "wof:name":"Jmp Associates Ltd Partnership",
    "wof:placetype":"venue"
},
  "geometry": {"coordinates":[-83.22496599999999,42.568306],"type":"Point"}
}