{
  "type": "Feature",
  "properties": {
    "iso:country":"US",
    "sg:address":"701 W Main St",
    "sg:city":"Fremont",
    "sg:classifiers":[
        {
            "category":"Social Services",
            "type":"Services"
        }
    ],
    "sg:phone":"+1 231 924 3901",
    "sg:postcode":"49412",
    "sg:province":"MI",
    "sg:tags":[
        "counseling"
    ],
    "wof:name":"Empowerment Network",
    "wof:placetype":"venue"
},
  "geometry": {"coordinates":[-85.95842399999999,43.467174],"type":"Point"}
}