{
  "type": "Feature",
  "properties": {
    "iso:country":"US",
    "sg:address":"15670 W 10 Mile Rd",
    "sg:city":"Southfield",
    "sg:classifiers":[
        {
            "category":"Real Estate",
            "subcategory":"Real Estate Agent",
            "type":"Services"
        }
    ],
    "sg:phone":"+1 248 443 1423",
    "sg:postcode":"48075",
    "sg:province":"MI",
    "wof:name":"Metro Detroit Properties",
    "wof:placetype":"venue"
},
  "geometry": {"coordinates":[-83.204329,42.473861],"type":"Point"}
}