{
  "type": "Feature",
  "properties": {
    "iso:country":"US",
    "sg:address":"202 US Hwy 41",
    "sg:city":"Stephenson",
    "sg:classifiers":[
        {
            "category":"Building & Trades",
            "subcategory":"Plumbing",
            "type":"Services"
        }
    ],
    "sg:phone":"+1 906 753 6335",
    "sg:postcode":"49887",
    "sg:province":"MI",
    "sg:tags":[
        "contractor"
    ],
    "wof:name":"Unlimited Services",
    "wof:placetype":"venue"
},
  "geometry": {"coordinates":[-87.605707,45.417028],"type":"Point"}
}