{
  "type": "Feature",
  "properties": {
    "iso:country":"US",
    "sg:address":"6314 Dixie Hwy",
    "sg:city":"Bridgeport",
    "sg:classifiers":[
        {
            "category":"Shopping",
            "subcategory":"Computers & Home Electronics",
            "type":"Retail Goods"
        }
    ],
    "sg:phone":"+1 989 777 7670",
    "sg:postcode":"48722",
    "sg:province":"MI",
    "sg:tags":[
        "equipment",
        "electronic",
        "supply"
    ],
    "wof:name":"Radio Shack",
    "wof:placetype":"venue"
},
  "geometry": {"coordinates":[-83.87234599999999,43.354313],"type":"Point"}
}