{
  "type": "Feature",
  "properties": {
    "iso:country":"US",
    "sg:address":"2171 Decker Rd",
    "sg:city":"Walled Lake",
    "sg:classifiers":[
        {
            "category":"Real Estate",
            "subcategory":"Real Estate Operator",
            "type":"Services"
        }
    ],
    "sg:phone":"+1 248 669 1960",
    "sg:postcode":"48390",
    "sg:province":"MI",
    "sg:tags":[
        "apartment"
    ],
    "wof:name":"Walnut Ridge Apartments",
    "wof:placetype":"venue"
},
  "geometry": {"coordinates":[-83.47215,42.555239],"type":"Point"}
}