{
  "type": "Feature",
  "properties": {
    "iso:country":"US",
    "sg:address":"3418 Plainfield Ave NE",
    "sg:city":"Grand Rapids",
    "sg:classifiers":[
        {
            "category":"Food & Beverages",
            "subcategory":"Liquor & Beverages",
            "type":"Retail Goods"
        }
    ],
    "sg:phone":"+1 616 361 2203",
    "sg:postcode":"49525",
    "sg:province":"MI",
    "sg:tags":[
        "beer",
        "ale"
    ],
    "wof:name":"Dudley's Party Store",
    "wof:placetype":"venue"
},
  "geometry": {"coordinates":[-85.632582,43.025038],"type":"Point"}
}