{
  "type": "Feature",
  "properties": {
    "iso:country":"US",
    "sg:address":"60825 Walnut St",
    "sg:city":"Vandalia",
    "sg:classifiers":[
        {
            "category":"Organizations",
            "subcategory":"Religious Organization",
            "type":"Services"
        }
    ],
    "sg:phone":"+1 269 476 9674",
    "sg:postcode":"49095",
    "sg:province":"MI",
    "wof:name":"Vandalia Church Of God",
    "wof:placetype":"venue"
},
  "geometry": {"coordinates":[-85.909353,41.914559],"type":"Point"}
}