{
  "type": "Feature",
  "properties": {
    "iso:country":"US",
    "sg:address":"1100 S Baldwin Rd",
    "sg:city":"Oxford",
    "sg:classifiers":[
        {
            "category":"Education",
            "subcategory":"School",
            "type":"Public Place"
        }
    ],
    "sg:phone":"+1 248 628 3198",
    "sg:postcode":"48371",
    "sg:province":"MI",
    "wof:name":"Indianwood Cmnty Baptst Church",
    "wof:placetype":"venue"
},
  "geometry": {"coordinates":[-83.333579,42.807689],"type":"Point"}
}