{
  "type": "Feature",
  "properties": {
    "iso:country":"US",
    "sg:address":"8861 Santosa Lane No 22",
    "sg:city":"Stephenson",
    "sg:classifiers":[
        {
            "category":"Building & Trades",
            "subcategory":"Construction",
            "type":"Services"
        }
    ],
    "sg:phone":"+1 906 863 4093",
    "sg:postcode":"49887",
    "sg:province":"MI",
    "sg:tags":[
        "house"
    ],
    "wof:name":"Molle Wood Design",
    "wof:placetype":"venue"
},
  "geometry": {"coordinates":[-87.858183,45.435662],"type":"Point"}
}