{
  "type": "Feature",
  "properties": {
    "iso:country":"US",
    "sg:address":"881 Hannah Ave",
    "sg:city":"Traverse City",
    "sg:classifiers":[
        {
            "category":"Banks & Credit Unions",
            "subcategory":"Bank",
            "type":"Services"
        }
    ],
    "sg:phone":"+1 231 922 0627",
    "sg:postcode":"49686",
    "sg:province":"MI",
    "wof:name":"Traverse City State Bank",
    "wof:placetype":"venue"
},
  "geometry": {"coordinates":[-85.601506,44.755312],"type":"Point"}
}