{
  "type": "Feature",
  "properties": {
    "iso:country":"US",
    "sg:address":"35531 Utica Rd",
    "sg:city":"Clinton Twp",
    "sg:classifiers":[
        {
            "category":"Organizations",
            "subcategory":"Religious Organization",
            "type":"Services"
        }
    ],
    "sg:phone":"+1 586 792 5251",
    "sg:postcode":"48035",
    "sg:province":"MI",
    "sg:tags":[
        "church"
    ],
    "wof:name":"Joy Community Church Inc",
    "wof:placetype":"venue"
},
  "geometry": {"coordinates":[-82.963464,42.557112],"type":"Point"}
}