{
  "type": "Feature",
  "properties": {
    "iso:country":"US",
    "sg:address":"30598 Southfield Rd",
    "sg:city":"Southfield",
    "sg:classifiers":[
        {
            "category":"Personal",
            "subcategory":"Nail Salon",
            "type":"Services"
        }
    ],
    "sg:phone":"+1 248 642 6622",
    "sg:postcode":"48076",
    "sg:province":"MI",
    "wof:name":"Bruno Hair Salon",
    "wof:placetype":"venue"
},
  "geometry": {"coordinates":[-83.223198,42.5145],"type":"Point"}
}