{
  "type": "Feature",
  "properties": {
    "iso:country":"US",
    "sg:address":"5414 Perry Rd",
    "sg:city":"Grand Blanc",
    "sg:classifiers":[
        {
            "category":"Professional",
            "type":"Services"
        },
        {
            "category":"Restaurant",
            "type":"Food & Drink"
        }
    ],
    "sg:phone":"+1 810 603 9999",
    "sg:postcode":"48439",
    "sg:province":"MI",
    "sg:tags":[
        "pizza",
        "caterer"
    ],
    "wof:name":"Pizza Mia",
    "wof:placetype":"venue"
},
  "geometry": {"coordinates":[-83.59945500000001,42.930698],"type":"Point"}
}