{
  "type": "Feature",
  "properties": {
    "iso:country":"US",
    "sg:address":"4343 State Hwy 32",
    "sg:city":"Alpena",
    "sg:classifiers":[
        {
            "category":"Government",
            "subcategory":"Office",
            "type":"Public Place"
        }
    ],
    "sg:phone":"+1 989 354 2209",
    "sg:postcode":"49707",
    "sg:province":"MI",
    "sg:tags":[
        "state"
    ],
    "wof:name":"Natural Resources Dept",
    "wof:placetype":"venue"
},
  "geometry": {"coordinates":[-83.537762,45.061043],"type":"Point"}
}