{
  "type": "Feature",
  "properties": {
    "iso:country":"US",
    "sg:address":"800 N Washington Ave",
    "sg:city":"Ludington",
    "sg:classifiers":[
        {
            "category":"Manufacturing",
            "subcategory":"Metals",
            "type":"Manufacturing & Wholesale Goods"
        }
    ],
    "sg:phone":"+1 231 843 2501",
    "sg:postcode":"49431",
    "sg:province":"MI",
    "sg:tags":[
        "foundry",
        "iron"
    ],
    "sg:website":"www.glccadv.com",
    "wof:name":"Great Lakes Castings Corp",
    "wof:placetype":"venue"
},
  "geometry": {"coordinates":[-86.439295,43.965726],"type":"Point"}
}