{
  "type": "Feature",
  "properties": {
    "iso:country":"US",
    "sg:address":"275 E Henderson Rd",
    "sg:city":"Lake Odessa",
    "sg:phone":"+1 616 374 7393",
    "sg:postcode":"48849",
    "sg:province":"MI",
    "sg:tags":[
        "farm",
        "corn",
        "wheat",
        "soybean"
    ],
    "wof:name":"Don Possehn",
    "wof:placetype":"venue"
},
  "geometry": {"coordinates":[-85.07055200000001,42.828642],"type":"Point"}
}