{
  "type": "Feature",
  "properties": {
    "iso:country":"US",
    "sg:address":"760 S Van Dyke Rd",
    "sg:city":"Bad Axe",
    "sg:classifiers":[
        {
            "category":"Education",
            "subcategory":"School",
            "type":"Public Place"
        }
    ],
    "sg:phone":"+1 989 269 9938",
    "sg:postcode":"48413",
    "sg:province":"MI",
    "wof:name":"Bad Axe Board Of Education",
    "wof:placetype":"venue"
},
  "geometry": {"coordinates":[-83.01580800000001,43.801828],"type":"Point"}
}