{
  "type": "Feature",
  "properties": {
    "iso:country":"US",
    "sg:address":"970 Maryland Ave NE",
    "sg:city":"Grand Rapids",
    "sg:classifiers":[
        {
            "category":"Building & Trades",
            "subcategory":"Cleaning & Sanitation",
            "type":"Services"
        }
    ],
    "sg:phone":"+1 616 774 0027",
    "sg:postcode":"49505",
    "sg:province":"MI",
    "sg:tags":[
        "maintenance",
        "contractor"
    ],
    "wof:name":"B & B Chimney Sweeps",
    "wof:placetype":"venue"
},
  "geometry": {"coordinates":[-85.610398,42.979326],"type":"Point"}
}