{
  "type": "Feature",
  "properties": {
    "iso:country":"US",
    "sg:address":"20133 Marlowe St",
    "sg:city":"Detroit",
    "sg:classifiers":[
        {
            "category":"Building & Trades",
            "subcategory":"Construction",
            "type":"Services"
        }
    ],
    "sg:phone":"+1 313 863 5970",
    "sg:postcode":"48235",
    "sg:province":"MI",
    "sg:tags":[
        "house"
    ],
    "wof:name":"Diverse King Cnstr Group",
    "wof:placetype":"venue"
},
  "geometry": {"coordinates":[-83.19185899999999,42.441362],"type":"Point"}
}