{
  "type": "Feature",
  "properties": {
    "iso:country":"US",
    "sg:address":"828 E Washington St",
    "sg:city":"Greenville",
    "sg:classifiers":[
        {
            "category":"Health Services",
            "subcategory":"Nursing And Care Facility",
            "type":"Services"
        }
    ],
    "sg:phone":"+1 616 754 7186",
    "sg:postcode":"48838",
    "sg:province":"MI",
    "sg:tags":[
        "home",
        "convalescent"
    ],
    "wof:name":"Metron Integraged Health Syst",
    "wof:placetype":"venue"
},
  "geometry": {"coordinates":[-85.241445,43.177295],"type":"Point"}
}