{
  "type": "Feature",
  "properties": {
    "iso:country":"US",
    "sg:address":"28700 Hayes Rd",
    "sg:city":"Roseville",
    "sg:classifiers":[
        {
            "category":"Wholesale",
            "subcategory":"Machinery & Supplies",
            "type":"Manufacturing & Wholesale Goods"
        }
    ],
    "sg:phone":"+1 586 774 3045",
    "sg:postcode":"48066",
    "sg:province":"MI",
    "sg:tags":[
        "printer",
        "cartridge"
    ],
    "wof:name":"Flint Ink Corp",
    "wof:placetype":"venue"
},
  "geometry": {"coordinates":[-82.968119,42.50739],"type":"Point"}
}