{
  "type": "Feature",
  "properties": {
    "iso:country":"US",
    "sg:address":"2126 Lakeshore Dr",
    "sg:city":"Fennville",
    "sg:classifiers":[
        {
            "category":"Travel",
            "subcategory":"Campground",
            "type":"Entertainment"
        }
    ],
    "sg:phone":"+1 269 543 3751",
    "sg:postcode":"49408",
    "sg:province":"MI",
    "wof:name":"Lake Park Trailer Resort",
    "wof:placetype":"venue"
},
  "geometry": {"coordinates":[-86.22901400000001,42.571952],"type":"Point"}
}