{
  "type": "Feature",
  "properties": {
    "iso:country":"US",
    "sg:address":"14891 Cross Ln",
    "sg:city":"Spring Lake",
    "sg:classifiers":[
        {
            "category":"Health Services",
            "subcategory":"Health Practitioner",
            "type":"Services"
        }
    ],
    "sg:phone":"+1 616 842 3807",
    "sg:postcode":"49456",
    "sg:province":"MI",
    "wof:name":"M Scherpenisse Dr",
    "wof:placetype":"venue"
},
  "geometry": {"coordinates":[-86.15778400000001,43.088646],"type":"Point"}
}