{
  "type": "Feature",
  "properties": {
    "iso:country":"US",
    "sg:address":"45602 Bristol Cir",
    "sg:city":"Novi",
    "sg:classifiers":[
        {
            "category":"Professional",
            "subcategory":"Management & Consulting",
            "type":"Services"
        }
    ],
    "sg:phone":"+1 248 669 5201",
    "sg:postcode":"48377",
    "sg:province":"MI",
    "sg:tags":[
        "communications",
        "consultant"
    ],
    "wof:name":"Digital Messaging Solutions",
    "wof:placetype":"venue"
},
  "geometry": {"coordinates":[-83.50087499999999,42.519063],"type":"Point"}
}