{
  "type": "Feature",
  "properties": {
    "iso:country":"US",
    "sg:address":"4030 E Bluewater Hwy",
    "sg:city":"Ionia",
    "sg:classifiers":[
        {
            "category":"Retail",
            "subcategory":"Repair Shop",
            "type":"Services"
        }
    ],
    "sg:phone":"+1 989 855 2022",
    "sg:postcode":"48846",
    "sg:province":"MI",
    "sg:tags":[
        "jewelry"
    ],
    "wof:name":"Ginger Goose LTD",
    "wof:placetype":"venue"
},
  "geometry": {"coordinates":[-84.98038200000001,43.001688],"type":"Point"}
}