{
  "type": "Feature",
  "properties": {
    "iso:country":"US",
    "sg:address":"5009 Hegel Rd",
    "sg:city":"Goodrich",
    "sg:classifiers":[
        {
            "category":"Building & Trades",
            "subcategory":"Construction",
            "type":"Services"
        }
    ],
    "sg:phone":"+1 810 797 5582",
    "sg:postcode":"48438",
    "sg:province":"MI",
    "sg:tags":[
        "concrete",
        "contractor"
    ],
    "wof:name":"Craig Gulledge",
    "wof:placetype":"venue"
},
  "geometry": {"coordinates":[-83.42496800000001,42.917321],"type":"Point"}
}