{
  "type": "Feature",
  "properties": {
    "iso:country":"US",
    "sg:address":"1133 W Long Lake Rd",
    "sg:city":"Bloomfield Hills",
    "sg:classifiers":[
        {
            "category":"Real Estate",
            "subcategory":"Real Estate Agent",
            "type":"Services"
        }
    ],
    "sg:phone":"+1 248 646 1400",
    "sg:postcode":"48302",
    "sg:province":"MI",
    "sg:tags":[
        "agency"
    ],
    "wof:name":"Max Broock Realtors Inc",
    "wof:placetype":"venue"
},
  "geometry": {"coordinates":[-83.283753,42.581174],"type":"Point"}
}