{
  "type": "Feature",
  "properties": {
    "iso:country":"US",
    "sg:address":"5099 Division Ave S",
    "sg:city":"Grand Rapids",
    "sg:classifiers":[
        {
            "category":"Banks & Credit Unions",
            "subcategory":"Investment Brokerage",
            "type":"Services"
        }
    ],
    "sg:phone":"+1 616 531 9191",
    "sg:postcode":"49548",
    "sg:province":"MI",
    "sg:tags":[
        "security"
    ],
    "wof:name":"Centennial Securities Co",
    "wof:placetype":"venue"
},
  "geometry": {"coordinates":[-85.66428500000001,42.871452],"type":"Point"}
}