{
  "type": "Feature",
  "properties": {
    "iso:country":"US",
    "sg:address":"6555 Balsam Dr",
    "sg:city":"Hudsonville",
    "sg:classifiers":[
        {
            "category":"Real Estate",
            "subcategory":"Real Estate Operator",
            "type":"Services"
        }
    ],
    "sg:phone":"+1 616 669 2697",
    "sg:postcode":"49426",
    "sg:province":"MI",
    "sg:tags":[
        "building",
        "apartment"
    ],
    "wof:name":"Oaktree Apartments",
    "wof:placetype":"venue"
},
  "geometry": {"coordinates":[-85.851961,42.88598],"type":"Point"}
}