{
  "type": "Feature",
  "properties": {
    "iso:country":"US",
    "sg:address":"25495 Co Rd 653",
    "sg:city":"Gobles",
    "sg:classifiers":[
        {
            "category":"Professional",
            "subcategory":"Accounting & Tax Preparation",
            "type":"Services"
        }
    ],
    "sg:phone":"+1 269 628 5050",
    "sg:postcode":"49055",
    "sg:province":"MI",
    "sg:tags":[
        "accountant"
    ],
    "wof:name":"Frederick J Cramer CPA",
    "wof:placetype":"venue"
},
  "geometry": {"coordinates":[-85.804298,42.326261],"type":"Point"}
}