{
  "type": "Feature",
  "properties": {
    "iso:country":"US",
    "sg:address":"604 Laurel Ave",
    "sg:city":"Sturgis",
    "sg:classifiers":[
        {
            "category":"Social Services",
            "subcategory":"Child Care",
            "type":"Services"
        }
    ],
    "sg:phone":"+1 269 659 8281",
    "sg:postcode":"49091",
    "sg:province":"MI",
    "sg:tags":[
        "day"
    ],
    "wof:name":"Nancy Flowers",
    "wof:placetype":"venue"
},
  "geometry": {"coordinates":[-85.41200000000001,41.794841],"type":"Point"}
}