{
  "type": "Feature",
  "properties": {
    "iso:country":"US",
    "sg:address":"11101 Wilshire Dr",
    "sg:city":"Detroit",
    "sg:classifiers":[
        {
            "category":"Shopping",
            "subcategory":"Clothing, Apparel, & Fashions",
            "type":"Retail Goods"
        }
    ],
    "sg:phone":"+1 313 839 3496",
    "sg:postcode":"48213",
    "sg:province":"MI",
    "wof:name":"DAnn Originals",
    "wof:placetype":"venue"
},
  "geometry": {"coordinates":[-82.99299999999999,42.405075],"type":"Point"}
}