{
  "type": "Feature",
  "properties": {
    "iso:country":"US",
    "sg:address":"111 Summit St",
    "sg:city":"Brighton",
    "sg:classifiers":[
        {
            "category":"Manufacturing",
            "subcategory":"Electronics",
            "type":"Manufacturing & Wholesale Goods"
        }
    ],
    "sg:phone":"+1 810 229 5751",
    "sg:postcode":"48116",
    "sg:province":"MI",
    "sg:tags":[
        "electronic",
        "capacitor"
    ],
    "wof:name":"Versatex Industries",
    "wof:placetype":"venue"
},
  "geometry": {"coordinates":[-83.77319199999999,42.517566],"type":"Point"}
}