{
  "type": "Feature",
  "properties": {
    "iso:country":"US",
    "sg:address":"2906 Cass Ave",
    "sg:city":"Detroit",
    "sg:classifiers":[
        {
            "category":"Bars & Pubs",
            "subcategory":"Nightclub",
            "type":"Food & Drink"
        }
    ],
    "sg:phone":"+1 313 832 2822",
    "sg:postcode":"48201",
    "sg:province":"MI",
    "sg:tags":[
        "nightlife"
    ],
    "wof:name":"Temple Bar",
    "wof:placetype":"venue"
},
  "geometry": {"coordinates":[-83.058899,42.342098],"type":"Point"}
}