{
  "type": "Feature",
  "properties": {
    "iso:country":"US",
    "sg:address":"4365 Galbraith Line Rd",
    "sg:city":"Croswell",
    "sg:classifiers":[
        {
            "category":"Social Services",
            "subcategory":"Child Care",
            "type":"Services"
        }
    ],
    "sg:phone":"+1 810 679 3205",
    "sg:postcode":"48422",
    "sg:province":"MI",
    "sg:tags":[
        "day"
    ],
    "wof:name":"Working Families Day Care",
    "wof:placetype":"venue"
},
  "geometry": {"coordinates":[-82.630403,43.193411],"type":"Point"}
}