{
  "type": "Feature",
  "properties": {
    "iso:country":"US",
    "sg:address":"2195 S Parma Rd",
    "sg:city":"Parma",
    "sg:classifiers":[
        {
            "category":"Building & Trades",
            "subcategory":"Construction",
            "type":"Services"
        }
    ],
    "sg:phone":"+1 517 531 4417",
    "sg:postcode":"49269",
    "sg:province":"MI",
    "sg:tags":[
        "masonry",
        "contractor"
    ],
    "wof:name":"Wellman Masonry",
    "wof:placetype":"venue"
},
  "geometry": {"coordinates":[-84.598153,42.221227],"type":"Point"}
}