{
  "type": "Feature",
  "properties": {
    "iso:country":"US",
    "sg:address":"3320 Bardaville St",
    "sg:city":"Lansing",
    "sg:classifiers":[
        {
            "category":"Social Services",
            "subcategory":"Child Care",
            "type":"Services"
        }
    ],
    "sg:phone":"+1 517 886 3195",
    "sg:postcode":"48906",
    "sg:province":"MI",
    "wof:name":"Genesis Child Development Ctr",
    "wof:placetype":"venue"
},
  "geometry": {"coordinates":[-84.59881799999999,42.766952],"type":"Point"}
}