{
  "type": "Feature",
  "properties": {
    "iso:country":"US",
    "sg:address":"4655 Canal Ave SW",
    "sg:city":"Grandville",
    "sg:classifiers":[
        {
            "category":"Shopping",
            "subcategory":"Bicycles & Sporting Goods",
            "type":"Retail Goods"
        }
    ],
    "sg:phone":"+1 616 249 0400",
    "sg:postcode":"49418",
    "sg:province":"MI",
    "sg:website":"www.gandermountain.com",
    "wof:name":"Gander Mountain",
    "wof:placetype":"venue"
},
  "geometry": {"coordinates":[-85.772434,42.878683],"type":"Point"}
}