{
  "type": "Feature",
  "properties": {
    "iso:country":"US",
    "sg:address":"2206 Oak Shade Dr",
    "sg:city":"Davison",
    "sg:classifiers":[
        {
            "category":"Food & Beverages",
            "subcategory":"Groceries & Convenience Stores",
            "type":"Retail Goods"
        }
    ],
    "sg:phone":"+1 810 658 4952",
    "sg:postcode":"48423",
    "sg:province":"MI",
    "wof:name":"Sarah's Market",
    "wof:placetype":"venue"
},
  "geometry": {"coordinates":[-83.540674,43.040903],"type":"Point"}
}