{
  "type": "Feature",
  "properties": {
    "iso:country":"US",
    "sg:address":"42080 Garfield Rd",
    "sg:city":"Clinton Township",
    "sg:classifiers":[
        {
            "category":"Personal",
            "subcategory":"Beauty Salon",
            "type":"Services"
        },
        {
            "category":"Personal",
            "type":"Services"
        }
    ],
    "sg:phone":"+1 586 263 7777",
    "sg:postcode":"48038",
    "sg:province":"MI",
    "sg:tags":[
        "spa",
        "day"
    ],
    "wof:name":"Gina's Salon & Spa",
    "wof:placetype":"venue"
},
  "geometry": {"coordinates":[-82.952499,42.606499],"type":"Point"}
}