{
  "type": "Feature",
  "properties": {
    "iso:country":"US",
    "sg:address":"1519 N Gordon Rd",
    "sg:city":"Scottville",
    "sg:classifiers":[
        {
            "category":"Retail",
            "subcategory":"Repair Shop",
            "type":"Services"
        }
    ],
    "sg:phone":"+1 231 757 2313",
    "sg:postcode":"49454",
    "sg:province":"MI",
    "wof:name":"Louies Mower Repair",
    "wof:placetype":"venue"
},
  "geometry": {"coordinates":[-86.310193,43.981858],"type":"Point"}
}