{
  "type": "Feature",
  "properties": {
    "iso:country":"US",
    "sg:address":"19658 Mack Ave",
    "sg:city":"Grosse Pointe",
    "sg:classifiers":[
        {
            "category":"Professional",
            "subcategory":"Lawyer & Legal Services",
            "type":"Services"
        }
    ],
    "sg:phone":"+1 313 885 5500",
    "sg:postcode":"48236",
    "sg:province":"MI",
    "wof:name":"Hughs & Hughes PC",
    "wof:placetype":"venue"
},
  "geometry": {"coordinates":[-82.909302,42.426201],"type":"Point"}
}