{
  "type": "Feature",
  "properties": {
    "iso:country":"US",
    "sg:address":"725 S Adams Rd",
    "sg:city":"Birmingham",
    "sg:classifiers":[
        {
            "category":"Professional",
            "subcategory":"Research",
            "type":"Services"
        }
    ],
    "sg:phone":"+1 248 540 8437",
    "sg:postcode":"48009",
    "sg:province":"MI",
    "sg:tags":[
        "environmental",
        "ecological"
    ],
    "wof:name":"Consolidated Environmental Svc",
    "wof:placetype":"venue"
},
  "geometry": {"coordinates":[-83.205423,42.541771],"type":"Point"}
}