{
  "type": "Feature",
  "properties": {
    "iso:country":"US",
    "sg:address":"2492 84th Ave",
    "sg:city":"Zeeland",
    "sg:classifiers":[
        {
            "category":"Professional",
            "type":"Services"
        }
    ],
    "sg:phone":"+1 616 748 1955",
    "sg:postcode":"49464",
    "sg:province":"MI",
    "sg:tags":[
        "establishment"
    ],
    "wof:name":"Arrowaste Inc",
    "wof:placetype":"venue"
},
  "geometry": {"coordinates":[-85.989683,42.815741],"type":"Point"}
}