{
  "type": "Feature",
  "properties": {
    "iso:country":"US",
    "sg:address":"324 E Front St",
    "sg:city":"Traverse City",
    "sg:classifiers":[
        {
            "category":"Professional",
            "subcategory":"Computer Services",
            "type":"Services"
        }
    ],
    "sg:phone":"+1 231 932 1591",
    "sg:postcode":"49684",
    "sg:province":"MI",
    "sg:tags":[
        "hardware",
        "provider",
        "internet",
        "software"
    ],
    "wof:name":"Interwoven Inc",
    "wof:placetype":"venue"
},
  "geometry": {"coordinates":[-85.616257,44.763983],"type":"Point"}
}