{
  "type": "Feature",
  "properties": {
    "iso:country":"US",
    "sg:address":"81961 Co Rd 687",
    "sg:city":"Hartford",
    "sg:classifiers":[
        {
            "category":"Shopping",
            "subcategory":"Hobbies, Toys, & Games",
            "type":"Retail Goods"
        }
    ],
    "sg:phone":"+1 269 621 2040",
    "sg:postcode":"49057",
    "sg:province":"MI",
    "wof:name":"Guaranteed Distributors",
    "wof:placetype":"venue"
},
  "geometry": {"coordinates":[-86.166174,42.121955],"type":"Point"}
}