{
  "type": "Feature",
  "properties": {
    "iso:country":"US",
    "sg:address":"415 S Chipman St",
    "sg:city":"Owosso",
    "sg:classifiers":[
        {
            "category":"Manufacturing",
            "subcategory":"Printing",
            "type":"Manufacturing & Wholesale Goods"
        }
    ],
    "sg:phone":"+1 989 723 1211",
    "sg:postcode":"48867",
    "sg:province":"MI",
    "sg:tags":[
        "printer"
    ],
    "wof:name":"Smith Printing",
    "wof:placetype":"venue"
},
  "geometry": {"coordinates":[-84.186446,42.995169],"type":"Point"}
}