{
  "type": "Feature",
  "properties": {
    "iso:country":"US",
    "sg:address":"501 Main St",
    "sg:city":"St Joseph",
    "sg:classifiers":[
        {
            "category":"Insurance",
            "subcategory":"Insurance Agent",
            "type":"Services"
        }
    ],
    "sg:phone":"+1 269 983 7101",
    "sg:postcode":"49085",
    "sg:province":"MI",
    "sg:website":"www.ims-myagency.com",
    "wof:name":"Insurance Management Svc",
    "wof:placetype":"venue"
},
  "geometry": {"coordinates":[-86.482609,42.106612],"type":"Point"}
}