{
  "type": "Feature",
  "properties": {
    "iso:country":"US",
    "sg:address":"41238 N Central Dr",
    "sg:city":"Sterling Heights",
    "sg:classifiers":[
        {
            "category":"Building & Trades",
            "subcategory":"Cleaning & Sanitation",
            "type":"Services"
        }
    ],
    "sg:phone":"+1 586 247 8501",
    "sg:postcode":"48313",
    "sg:province":"MI",
    "sg:tags":[
        "maintenance"
    ],
    "wof:name":"Red Star Cleaning Co",
    "wof:placetype":"venue"
},
  "geometry": {"coordinates":[-82.989142,42.598901],"type":"Point"}
}