{
  "type": "Feature",
  "properties": {
    "iso:country":"US",
    "sg:address":"22509 Statler St",
    "sg:city":"Saint Clair Shores",
    "sg:classifiers":[
        {
            "category":"Professional",
            "subcategory":"Art Services",
            "type":"Services"
        }
    ],
    "sg:phone":"+1 586 778 6343",
    "sg:postcode":"48081",
    "sg:province":"MI",
    "sg:tags":[
        "photo",
        "photography",
        "commercial",
        "studio",
        "portrait"
    ],
    "wof:name":"Al Salter Photography Inc",
    "wof:placetype":"venue"
},
  "geometry": {"coordinates":[-82.880304,42.479188],"type":"Point"}
}