{
  "type": "Feature",
  "properties": {
    "iso:country":"US",
    "sg:address":"52095 Van Dyke Ave",
    "sg:city":"Shelby Twp",
    "sg:classifiers":[
        {
            "category":"Shopping",
            "subcategory":"Clothing, Apparel, & Fashions",
            "type":"Retail Goods"
        }
    ],
    "sg:phone":"+1 586 323 4482",
    "sg:postcode":"48316",
    "sg:province":"MI",
    "sg:tags":[
        "shop",
        "bridal"
    ],
    "sg:website":"www.arenabridal.com",
    "wof:name":"Arena Bridal & Formal",
    "wof:placetype":"venue"
},
  "geometry": {"coordinates":[-83.03430299999999,42.678113],"type":"Point"}
}