{
  "type": "Feature",
  "properties": {
    "iso:country":"US",
    "sg:address":"69283 N Main St",
    "sg:city":"Richmond",
    "sg:classifiers":[
        {
            "category":"Insurance",
            "subcategory":"Insurance Agent",
            "type":"Services"
        }
    ],
    "sg:phone":"+1 586 727 3495",
    "sg:postcode":"48062",
    "sg:province":"MI",
    "wof:name":"Penwarden Simmons Agency Inc",
    "wof:placetype":"venue"
},
  "geometry": {"coordinates":[-82.757372,42.811243],"type":"Point"}
}