{
  "type": "Feature",
  "properties": {
    "iso:country":"US",
    "sg:address":"2216 E Kasson Rd",
    "sg:city":"Cedar",
    "sg:classifiers":[
        {
            "category":"Shopping",
            "subcategory":"Hobbies, Toys, & Games",
            "type":"Retail Goods"
        }
    ],
    "sg:phone":"+1 231 228 5129",
    "sg:postcode":"49621",
    "sg:province":"MI",
    "wof:name":"Make It Beautiful",
    "wof:placetype":"venue"
},
  "geometry": {"coordinates":[-85.813025,44.803603],"type":"Point"}
}