{
  "type": "Feature",
  "properties": {
    "iso:country":"US",
    "sg:address":"2644 Auburn Rd",
    "sg:city":"Shelby Twp",
    "sg:classifiers":[
        {
            "category":"Wholesale",
            "subcategory":"Machinery & Supplies",
            "type":"Manufacturing & Wholesale Goods"
        }
    ],
    "sg:phone":"+1 586 726 9690",
    "sg:postcode":"48317",
    "sg:province":"MI",
    "sg:tags":[
        "equipment",
        "construction",
        "contractor"
    ],
    "wof:name":"Contractors Connection Inc",
    "wof:placetype":"venue"
},
  "geometry": {"coordinates":[-83.08530399999999,42.638853],"type":"Point"}
}