{
  "type": "Feature",
  "properties": {
    "iso:country":"US",
    "sg:address":"2929 Haines Rd",
    "sg:city":"Lapeer",
    "sg:classifiers":[
        {
            "category":"Professional",
            "subcategory":"Computer Services",
            "type":"Services"
        }
    ],
    "sg:phone":"+1 810 667 3602",
    "sg:postcode":"48446",
    "sg:province":"MI",
    "sg:tags":[
        "school",
        "datum"
    ],
    "wof:name":"Gregs Universe",
    "wof:placetype":"venue"
},
  "geometry": {"coordinates":[-83.230268,43.075287],"type":"Point"}
}