{
  "type": "Feature",
  "properties": {
    "iso:country":"US",
    "sg:address":"6765 Courtland Dr NE",
    "sg:city":"Rockford",
    "sg:classifiers":[
        {
            "category":"Social Services",
            "subcategory":"Child Care",
            "type":"Services"
        },
        {
            "category":"Education",
            "subcategory":"Preschool",
            "type":"Public Place"
        },
        {
            "category":"Education",
            "subcategory":"School",
            "type":"Public Place"
        }
    ],
    "sg:phone":"+1 616 874 5437",
    "sg:postcode":"49341",
    "sg:province":"MI",
    "sg:tags":[
        "elementary",
        "day"
    ],
    "wof:name":"Appletree Christian Learning Center",
    "wof:placetype":"venue"
},
  "geometry": {"coordinates":[-85.551074,43.085596],"type":"Point"}
}