{
  "type": "Feature",
  "properties": {
    "iso:country":"US",
    "sg:address":"1026 Adams Rd",
    "sg:city":"Burton",
    "sg:classifiers":[
        {
            "category":"Shopping",
            "subcategory":"Used Merchandise",
            "type":"Retail Goods"
        }
    ],
    "sg:phone":"+1 810 744 3298",
    "sg:postcode":"48509",
    "sg:province":"MI",
    "wof:name":"Hunt Treasure Antiques",
    "wof:placetype":"venue"
},
  "geometry": {"coordinates":[-83.59045999999999,43.017858],"type":"Point"}
}