{
  "type": "Feature",
  "properties": {
    "iso:country":"US",
    "sg:address":"442 Lakeshore Dr N",
    "sg:city":"Holland",
    "sg:classifiers":[
        {
            "category":"Professional",
            "subcategory":"Business Services",
            "type":"Services"
        }
    ],
    "sg:phone":"+1 616 994 7408",
    "sg:postcode":"49424",
    "sg:province":"MI",
    "sg:tags":[
        "program",
        "incentive"
    ],
    "wof:name":"Keeter Marketing Svc",
    "wof:placetype":"venue"
},
  "geometry": {"coordinates":[-86.207292,42.809542],"type":"Point"}
}