{
  "type": "Feature",
  "properties": {
    "iso:country":"US",
    "sg:address":"831 Monroe St",
    "sg:city":"Dearborn",
    "sg:classifiers":[
        {
            "category":"Real Estate",
            "subcategory":"Real Estate Agent",
            "type":"Services"
        }
    ],
    "sg:phone":"+1 313 565 1000",
    "sg:postcode":"48124",
    "sg:province":"MI",
    "sg:tags":[
        "agency"
    ],
    "wof:name":"Century 21 Curran Christie RE",
    "wof:placetype":"venue"
},
  "geometry": {"coordinates":[-83.24452599999999,42.30766],"type":"Point"}
}