{
  "type": "Feature",
  "properties": {
    "iso:country":"US",
    "sg:address":"2275 W Main St SE",
    "sg:city":"Lowell",
    "sg:classifiers":[
        {
            "category":"Organizations",
            "subcategory":"Religious Organization",
            "type":"Services"
        }
    ],
    "sg:phone":"+1 616 897 7168",
    "sg:postcode":"49331",
    "sg:province":"MI",
    "sg:tags":[
        "church"
    ],
    "sg:website":"www.fbclowell.org",
    "wof:name":"First Baptist Church Of Lowell",
    "wof:placetype":"venue"
},
  "geometry": {"coordinates":[-85.363675,42.931187],"type":"Point"}
}