{
  "type": "Feature",
  "properties": {
    "iso:country":"US",
    "sg:address":"2956 Northlawn St",
    "sg:city":"Ypsilanti",
    "sg:classifiers":[
        {
            "category":"Social Services",
            "subcategory":"Child Care",
            "type":"Services"
        }
    ],
    "sg:phone":"+1 734 434 6608",
    "sg:postcode":"48197",
    "sg:province":"MI",
    "sg:tags":[
        "day"
    ],
    "wof:name":"Janet Bell",
    "wof:placetype":"venue"
},
  "geometry": {"coordinates":[-83.658554,42.248181],"type":"Point"}
}