{
  "type": "Feature",
  "properties": {
    "iso:country":"US",
    "sg:address":"43436 Devin Dr",
    "sg:city":"Clinton Twp",
    "sg:classifiers":[
        {
            "category":"Retail",
            "subcategory":"Funeral Services",
            "type":"Services"
        }
    ],
    "sg:phone":"+1 586 307 3765",
    "sg:postcode":"48038",
    "sg:province":"MI",
    "sg:tags":[
        "plan"
    ],
    "wof:name":"Exclusive Transportation",
    "wof:placetype":"venue"
},
  "geometry": {"coordinates":[-82.911022,42.617425],"type":"Point"}
}