{
  "type": "Feature",
  "properties": {
    "iso:country":"US",
    "sg:address":"2763 58th St",
    "sg:city":"Fennville",
    "sg:classifiers":[
        {
            "category":"Building & Trades",
            "subcategory":"Construction",
            "type":"Services"
        }
    ],
    "sg:phone":"+1 269 561 5239",
    "sg:postcode":"49408",
    "sg:province":"MI",
    "sg:tags":[
        "contractor"
    ],
    "wof:name":"Fernandez Builders",
    "wof:placetype":"venue"
},
  "geometry": {"coordinates":[-86.11448,42.621119],"type":"Point"}
}