{
  "type": "Feature",
  "properties": {
    "iso:country":"US",
    "sg:address":"4338 S Lapeer Rd",
    "sg:city":"Metamora",
    "sg:classifiers":[
        {
            "category":"Professional",
            "subcategory":"Accounting & Tax Preparation",
            "type":"Services"
        }
    ],
    "sg:phone":"+1 810 678 3753",
    "sg:postcode":"48455",
    "sg:province":"MI",
    "sg:tags":[
        "accountant"
    ],
    "wof:name":"Metamora Accounting & Tax Svc",
    "wof:placetype":"venue"
},
  "geometry": {"coordinates":[-83.31326199999999,42.933513],"type":"Point"}
}