{
  "type": "Feature",
  "properties": {
    "iso:country":"US",
    "sg:address":"23005 Katzman St",
    "sg:city":"Clinton Twp",
    "sg:classifiers":[
        {
            "category":"Freight",
            "type":"Transportation"
        }
    ],
    "sg:phone":"+1 313 361 6363",
    "sg:postcode":"48035",
    "sg:province":"MI",
    "sg:tags":[
        "hauling",
        "trucking"
    ],
    "wof:name":"Amicone Transfer",
    "wof:placetype":"venue"
},
  "geometry": {"coordinates":[-82.88277100000001,42.567627],"type":"Point"}
}