{
  "type": "Feature",
  "properties": {
    "iso:country":"US",
    "sg:address":"1125 E.14 Mile Rd.",
    "sg:city":"Troy",
    "sg:classifiers":[
        {
            "category":"Autos & Motor Vehicles",
            "subcategory":"Auto Supplies",
            "type":"Retail Goods"
        }
    ],
    "sg:phone":"+1 248 588 5100",
    "sg:postcode":"48083",
    "sg:province":"MI",
    "sg:tags":[
        "tire"
    ],
    "sg:website":"www.discounttire.com/makeappt",
    "wof:name":"Discount Tire",
    "wof:placetype":"venue"
},
  "geometry": {"coordinates":[-83.12085500000001,42.533904],"type":"Point"}
}