{
  "type": "Feature",
  "properties": {
    "iso:country":"US",
    "sg:address":"43351 Commons Dr",
    "sg:city":"Clinton Township",
    "sg:classifiers":[
        {
            "category":"Health Services",
            "subcategory":"Doctor",
            "type":"Services"
        }
    ],
    "sg:phone":"+1 586 228 8606",
    "sg:postcode":"48038",
    "sg:province":"MI",
    "sg:tags":[
        "physician",
        "surgeon",
        "medical"
    ],
    "wof:name":"Dimson Rudyard L MD",
    "wof:placetype":"venue"
},
  "geometry": {"coordinates":[-82.957802,42.6138],"type":"Point"}
}