{
  "type": "Feature",
  "properties": {
    "iso:country":"US",
    "sg:address":"2120 E 10 Mile Rd",
    "sg:city":"Warren",
    "sg:classifiers":[
        {
            "category":"Autos & Motor Vehicles",
            "subcategory":"Motorcycle Sales",
            "type":"Retail Goods"
        }
    ],
    "sg:phone":"+1 586 427 2700",
    "sg:postcode":"48091",
    "sg:province":"MI",
    "wof:name":"Cycleville USA",
    "wof:placetype":"venue"
},
  "geometry": {"coordinates":[-83.08145,42.476291],"type":"Point"}
}