{
  "type": "Feature",
  "properties": {
    "iso:country":"US",
    "sg:address":"10044 Pelham Rd",
    "sg:city":"Taylor",
    "sg:classifiers":[
        {
            "category":"Building & Trades",
            "subcategory":"Construction",
            "type":"Services"
        }
    ],
    "sg:phone":"+1 313 291 3357",
    "sg:postcode":"48180",
    "sg:province":"MI",
    "sg:tags":[
        "house"
    ],
    "wof:name":"Pamula Construction",
    "wof:placetype":"venue"
},
  "geometry": {"coordinates":[-83.23020200000001,42.233748],"type":"Point"}
}