{
  "type": "Feature",
  "properties": {
    "iso:country":"US",
    "sg:address":"3280 Boyes Rd",
    "sg:city":"Delton",
    "sg:classifiers":[
        {
            "category":"Retail",
            "subcategory":"Repair Shop",
            "type":"Services"
        }
    ],
    "sg:phone":"+1 269 671 5825",
    "sg:postcode":"49046",
    "sg:province":"MI",
    "wof:name":"JFS Enterprises",
    "wof:placetype":"venue"
},
  "geometry": {"coordinates":[-85.36268099999999,42.448827],"type":"Point"}
}