{
  "type": "Feature",
  "properties": {
    "iso:country":"US",
    "sg:address":"11885 N Division Ave",
    "sg:city":"Sparta",
    "sg:classifiers":[
        {
            "category":"Building & Trades",
            "subcategory":"Construction",
            "type":"Services"
        }
    ],
    "sg:phone":"+1 616 887 2222",
    "sg:postcode":"49345",
    "sg:province":"MI",
    "sg:tags":[
        "excavation",
        "contractor"
    ],
    "wof:name":"ABC Recycleing",
    "wof:placetype":"venue"
},
  "geometry": {"coordinates":[-85.671088,43.178731],"type":"Point"}
}