{
  "type": "Feature",
  "properties": {
    "iso:country":"US",
    "sg:address":"835 W State St",
    "sg:city":"Hastings",
    "sg:classifiers":[
        {
            "category":"Restaurant",
            "type":"Food & Drink"
        }
    ],
    "sg:menulink":"http://www.allmenus.com/mi/hastings/142412-subway/menu/",
    "sg:phone":"+1 269 948 2422",
    "sg:postcode":"49058",
    "sg:province":"MI",
    "sg:tags":[
        "american",
        "sandwich"
    ],
    "wof:name":"Subway",
    "wof:placetype":"venue"
},
  "geometry": {"coordinates":[-85.298106,42.648618],"type":"Point"}
}