{
  "type": "Feature",
  "properties": {
    "iso:country":"US",
    "sg:address":"6129 N Dort Hwy",
    "sg:city":"Flint",
    "sg:classifiers":[
        {
            "category":"Wholesale",
            "subcategory":"Groceries",
            "type":"Manufacturing & Wholesale Goods"
        }
    ],
    "sg:phone":"+1 810 789 5444",
    "sg:postcode":"48505",
    "sg:province":"MI",
    "sg:tags":[
        "food",
        "product"
    ],
    "wof:name":"Bivins Inc",
    "wof:placetype":"venue"
},
  "geometry": {"coordinates":[-83.67406200000001,43.065021],"type":"Point"}
}