{
  "type": "Feature",
  "properties": {
    "iso:country":"US",
    "sg:address":"4555 Dowling St",
    "sg:city":"Montague",
    "sg:classifiers":[
        {
            "category":"Banks & Credit Unions",
            "subcategory":"Bank",
            "type":"Services"
        }
    ],
    "sg:phone":"+1 231 893 1495",
    "sg:postcode":"49437",
    "sg:province":"MI",
    "wof:name":"Comerica Bank",
    "wof:placetype":"venue"
},
  "geometry": {"coordinates":[-86.355684,43.416657],"type":"Point"}
}