{
  "type": "Feature",
  "properties": {
    "iso:country":"US",
    "sg:address":"1203 W 14 Mile Rd",
    "sg:city":"Clawson",
    "sg:classifiers":[
        {
            "category":"Shopping",
            "subcategory":"Bicycles & Sporting Goods",
            "type":"Retail Goods"
        }
    ],
    "sg:phone":"+1 248 435 7240",
    "sg:postcode":"48017",
    "sg:province":"MI",
    "wof:name":"Play It Again Sports",
    "wof:placetype":"venue"
},
  "geometry": {"coordinates":[-83.162492,42.533044],"type":"Point"}
}