{
  "type": "Feature",
  "properties": {
    "iso:country":"US",
    "sg:address":"1255 E Grand River Ave",
    "sg:city":"Howell",
    "sg:classifiers":[
        {
            "category":"Government",
            "subcategory":"Office",
            "type":"Public Place"
        }
    ],
    "sg:phone":"+1 517 546 7450",
    "sg:postcode":"48843",
    "sg:province":"MI",
    "sg:tags":[
        "job",
        "program",
        "training"
    ],
    "wof:name":"Job Training Program",
    "wof:placetype":"venue"
},
  "geometry": {"coordinates":[-83.916645,42.60225],"type":"Point"}
}