{
  "type": "Feature",
  "properties": {
    "iso:country":"US",
    "sg:address":"146 E Main Ave",
    "sg:city":"Zeeland",
    "sg:classifiers":[
        {
            "category":"Banks & Credit Unions",
            "subcategory":"Bank",
            "type":"Services"
        }
    ],
    "sg:phone":"+1 616 772 2191",
    "sg:postcode":"49464",
    "sg:province":"MI",
    "sg:tags":[
        "state",
        "commercial"
    ],
    "wof:name":"Fifth Third Bank",
    "wof:placetype":"venue"
},
  "geometry": {"coordinates":[-86.015657,42.812244],"type":"Point"}
}