{
  "type": "Feature",
  "properties": {
    "iso:country":"US",
    "sg:address":"9355 Stark Rd",
    "sg:city":"Livonia",
    "sg:classifiers":[
        {
            "category":"Organizations",
            "subcategory":"Religious Organization",
            "type":"Services"
        }
    ],
    "sg:phone":"+1 734 261 6180",
    "sg:postcode":"48150",
    "sg:province":"MI",
    "wof:name":"Parkview Baptist Church Inc",
    "wof:placetype":"venue"
},
  "geometry": {"coordinates":[-83.381693,42.358997],"type":"Point"}
}