{
  "type": "Feature",
  "properties": {
    "iso:country":"US",
    "sg:address":"3619 Jasmine Ave NE",
    "sg:city":"Grand Rapids",
    "sg:classifiers":[
        {
            "category":"Professional",
            "subcategory":"Management & Consulting",
            "type":"Services"
        }
    ],
    "sg:phone":"+1 616 361 2021",
    "sg:postcode":"49525",
    "sg:province":"MI",
    "wof:name":"Ruths",
    "wof:placetype":"venue"
},
  "geometry": {"coordinates":[-85.598939,43.030174],"type":"Point"}
}