{
  "type": "Feature",
  "properties": {
    "iso:country":"US",
    "sg:address":"305 W Main St",
    "sg:city":"Hudson",
    "sg:classifiers":[
        {
            "category":"Insurance",
            "subcategory":"Insurance Agent",
            "type":"Services"
        }
    ],
    "sg:phone":"+1 517 448 2911",
    "sg:postcode":"49247",
    "sg:province":"MI",
    "wof:name":"T J Decker & Assoc Inc",
    "wof:placetype":"venue"
},
  "geometry": {"coordinates":[-84.35602299999999,41.854815],"type":"Point"}
}