{
  "type": "Feature",
  "properties": {
    "iso:country":"US",
    "sg:address":"11443 E 13 Mile Rd",
    "sg:city":"Warren",
    "sg:classifiers":[
        {
            "category":"Professional",
            "subcategory":"Accounting & Tax Preparation",
            "type":"Services"
        }
    ],
    "sg:phone":"+1 586 979 7575",
    "sg:postcode":"48093",
    "sg:province":"MI",
    "sg:tags":[
        "return",
        "filing"
    ],
    "wof:name":"Martin Wicker",
    "wof:placetype":"venue"
},
  "geometry": {"coordinates":[-83.009856,42.521441],"type":"Point"}
}