{
  "type": "Feature",
  "properties": {
    "iso:country":"US",
    "sg:address":"542 Townsend St",
    "sg:city":"Birmingham",
    "sg:classifiers":[
        {
            "category":"Professional",
            "type":"Services"
        }
    ],
    "sg:phone":"+1 248 988 9318",
    "sg:postcode":"48009",
    "sg:province":"MI",
    "sg:tags":[
        "establishment"
    ],
    "wof:name":"Dakota Birmingham",
    "wof:placetype":"venue"
},
  "geometry": {"coordinates":[-83.220209,42.54443],"type":"Point"}
}