{
  "type": "Feature",
  "properties": {
    "iso:country":"US",
    "sg:address":"5350 Emmett Rd",
    "sg:city":"Emmett",
    "sg:classifiers":[
        {
            "category":"Shopping",
            "subcategory":"Hobbies, Toys, & Games",
            "type":"Retail Goods"
        }
    ],
    "sg:phone":"+1 810 387 3269",
    "sg:postcode":"48022",
    "sg:province":"MI",
    "sg:tags":[
        "craft"
    ],
    "wof:name":"Kathy's Country Crafts",
    "wof:placetype":"venue"
},
  "geometry": {"coordinates":[-82.764077,43.055484],"type":"Point"}
}