{
  "type": "Feature",
  "properties": {
    "iso:country":"US",
    "sg:address":"5500 Northland Dr NE",
    "sg:city":"Grand Rapids",
    "sg:classifiers":[
        {
            "category":"Real Estate",
            "subcategory":"Real Estate Agent",
            "type":"Services"
        }
    ],
    "sg:phone":"+1 616 364 6622",
    "sg:postcode":"49525",
    "sg:province":"MI",
    "sg:tags":[
        "appraiser"
    ],
    "wof:name":"Ltm Incorporated",
    "wof:placetype":"venue"
},
  "geometry": {"coordinates":[-85.579911,43.063117],"type":"Point"}
}