{
  "type": "Feature",
  "properties": {
    "iso:country":"US",
    "sg:address":"1045 Baldwin Ave",
    "sg:city":"Pontiac",
    "sg:classifiers":[
        {
            "category":"Restaurant",
            "type":"Food & Drink"
        }
    ],
    "sg:phone":"+1 248 335 8840",
    "sg:postcode":"48340",
    "sg:province":"MI",
    "sg:tags":[
        "eating"
    ],
    "wof:name":"Wing Hing Chinese Restaurant",
    "wof:placetype":"venue"
},
  "geometry": {"coordinates":[-83.300338,42.665801],"type":"Point"}
}