{
  "type": "Feature",
  "properties": {
    "iso:country":"US",
    "sg:address":"7384 Cheboygan St",
    "sg:city":"Alanson",
    "sg:classifiers":[
        {
            "category":"Travel",
            "subcategory":"Campground",
            "type":"Entertainment"
        }
    ],
    "sg:phone":"+1 231 548 5534",
    "sg:postcode":"49706",
    "sg:province":"MI",
    "wof:name":"Crooked River Rv Park",
    "wof:placetype":"venue"
},
  "geometry": {"coordinates":[-84.782714,45.442483],"type":"Point"}
}