{
  "type": "Feature",
  "properties": {
    "iso:country":"US",
    "sg:address":"18105 Cross Dr",
    "sg:city":"Fraser",
    "sg:classifiers":[
        {
            "category":"Manufacturing",
            "subcategory":"Tools & Machinery",
            "type":"Manufacturing & Wholesale Goods"
        }
    ],
    "sg:phone":"+1 586 296 5597",
    "sg:postcode":"48026",
    "sg:province":"MI",
    "sg:tags":[
        "pattern",
        "industrial"
    ],
    "wof:name":"Odyssey",
    "wof:placetype":"venue"
},
  "geometry": {"coordinates":[-82.937466,42.543546],"type":"Point"}
}