{
  "type": "Feature",
  "properties": {
    "iso:country":"US",
    "sg:address":"8580 W Grand River Ave",
    "sg:city":"Brighton",
    "sg:classifiers":[
        {
            "category":"Health Services",
            "subcategory":"Doctor",
            "type":"Services"
        }
    ],
    "sg:phone":"+1 517 545 6618",
    "sg:postcode":"48116",
    "sg:province":"MI",
    "sg:tags":[
        "physician",
        "surgeon"
    ],
    "wof:name":"Mcauley-Mcpherson Obsterics",
    "wof:placetype":"venue"
},
  "geometry": {"coordinates":[-83.786619,42.540749],"type":"Point"}
}