{
  "type": "Feature",
  "properties": {
    "iso:country":"US",
    "sg:address":"653 S Madison St",
    "sg:city":"Adrian",
    "sg:classifiers":[
        {
            "category":"Building & Trades",
            "subcategory":"Cleaning & Sanitation",
            "type":"Services"
        }
    ],
    "sg:phone":"+1 517 266 8379",
    "sg:postcode":"49221",
    "sg:province":"MI",
    "sg:tags":[
        "janitor"
    ],
    "wof:name":"Cindy's Home Cleaning",
    "wof:placetype":"venue"
},
  "geometry": {"coordinates":[-84.058036,41.889836],"type":"Point"}
}