{
  "type": "Feature",
  "properties": {
    "iso:country":"US",
    "sg:address":"3800 Lake Harbor Rd",
    "sg:city":"Muskegon",
    "sg:classifiers":[
        {
            "category":"Organizations",
            "subcategory":"Religious Organization",
            "type":"Services"
        }
    ],
    "sg:phone":"+1 231 780 2476",
    "sg:postcode":"49441",
    "sg:province":"MI",
    "wof:name":"Mona Shores Baptist Church",
    "wof:placetype":"venue"
},
  "geometry": {"coordinates":[-86.28854800000001,43.183681],"type":"Point"}
}