{
  "type": "Feature",
  "properties": {
    "iso:country":"US",
    "sg:address":"565 S Tipsico Lake Rd",
    "sg:city":"Milford",
    "sg:classifiers":[
        {
            "category":"Building & Trades",
            "subcategory":"Plumbing",
            "type":"Services"
        }
    ],
    "sg:phone":"+1 248 887 2900",
    "sg:postcode":"48380",
    "sg:province":"MI",
    "sg:tags":[
        "contractor"
    ],
    "wof:name":"Mechanical Concepts",
    "wof:placetype":"venue"
},
  "geometry": {"coordinates":[-83.678707,42.629888],"type":"Point"}
}