{
  "type": "Feature",
  "properties": {
    "iso:country":"US",
    "sg:address":"205 Quincy St",
    "sg:city":"Kingsford",
    "sg:classifiers":[
        {
            "category":"Wholesale",
            "subcategory":"Hardware",
            "type":"Manufacturing & Wholesale Goods"
        }
    ],
    "sg:phone":"+1 906 771 2649",
    "sg:postcode":"49802",
    "sg:province":"MI",
    "sg:tags":[
        "refrigerating"
    ],
    "wof:name":"Helmer's Refrigeration",
    "wof:placetype":"venue"
},
  "geometry": {"coordinates":[-88.07409699999999,45.794987],"type":"Point"}
}