{
  "type": "Feature",
  "properties": {
    "iso:country":"US",
    "sg:address":"91 S Hancock St",
    "sg:city":"Pentwater",
    "sg:classifiers":[
        {
            "category":"Government",
            "subcategory":"Post Office",
            "type":"Public Place"
        }
    ],
    "sg:phone":"+1 231 000 1111",
    "sg:postcode":"49449",
    "sg:province":"MI",
    "wof:name":"US Post Office",
    "wof:placetype":"venue"
},
  "geometry": {"coordinates":[-86.433226,43.781054],"type":"Point"}
}