{
  "type": "Feature",
  "properties": {
    "iso:country":"US",
    "sg:address":"1313 60th St SE",
    "sg:city":"Grand Rapids",
    "sg:classifiers":[
        {
            "category":"Shopping",
            "subcategory":"Clothing, Apparel, & Fashions",
            "type":"Retail Goods"
        }
    ],
    "sg:phone":"+1 616 827 9447",
    "sg:postcode":"49508",
    "sg:province":"MI",
    "sg:tags":[
        "family"
    ],
    "wof:name":"Jodeneas",
    "wof:placetype":"venue"
},
  "geometry": {"coordinates":[-85.63783100000001,42.854849],"type":"Point"}
}