{
  "type": "Feature",
  "properties": {
    "iso:country":"US",
    "sg:address":"23640 Hoover Rd",
    "sg:city":"Warren",
    "sg:classifiers":[
        {
            "category":"Manufacturing",
            "subcategory":"Tools & Machinery",
            "type":"Manufacturing & Wholesale Goods"
        }
    ],
    "sg:phone":"+1 586 759 4401",
    "sg:postcode":"48089",
    "sg:province":"MI",
    "sg:tags":[
        "machine",
        "shop"
    ],
    "wof:name":"L & M Machining & Manufacture",
    "wof:placetype":"venue"
},
  "geometry": {"coordinates":[-83.005785,42.467439],"type":"Point"}
}