{
  "type": "Feature",
  "properties": {
    "iso:country":"US",
    "sg:address":"20550 Haggerty Rd",
    "sg:city":"Northville",
    "sg:classifiers":[
        {
            "category":"Banks & Credit Unions",
            "subcategory":"Bank",
            "type":"Services"
        }
    ],
    "sg:phone":"+1 248 324 8650",
    "sg:postcode":"48167",
    "sg:province":"MI",
    "wof:name":"Citizens Bank",
    "wof:placetype":"venue"
},
  "geometry": {"coordinates":[-83.436077,42.437621],"type":"Point"}
}