{
  "type": "Feature",
  "properties": {
    "iso:country":"US",
    "sg:address":"1581 Oak Dr",
    "sg:city":"Allegan",
    "sg:classifiers":[
        {
            "category":"Utilities",
            "subcategory":"Telephone",
            "type":"Services"
        }
    ],
    "sg:phone":"+1 269 673 0009",
    "sg:postcode":"49010",
    "sg:province":"MI",
    "sg:tags":[
        "distance",
        "long"
    ],
    "wof:name":"Alliance Group Svc Inc",
    "wof:placetype":"venue"
},
  "geometry": {"coordinates":[-85.869214,42.533494],"type":"Point"}
}