{
  "type": "Feature",
  "properties": {
    "iso:country":"US",
    "sg:address":"1854 Industrial Blvd",
    "sg:city":"Muskegon",
    "sg:classifiers":[
        {
            "category":"Manufacturing",
            "subcategory":"Metals",
            "type":"Manufacturing & Wholesale Goods"
        }
    ],
    "sg:phone":"+1 231 767 9799",
    "sg:postcode":"49442",
    "sg:province":"MI",
    "sg:tags":[
        "coating"
    ],
    "wof:name":"Prp Industries",
    "wof:placetype":"venue"
},
  "geometry": {"coordinates":[-86.204437,43.216592],"type":"Point"}
}