{
  "type": "Feature",
  "properties": {
    "iso:country":"US",
    "sg:address":"1259 Estey Rd",
    "sg:city":"Beaverton",
    "sg:classifiers":[
        {
            "category":"Freight",
            "type":"Transportation"
        }
    ],
    "sg:phone":"+1 989 435 7954",
    "sg:postcode":"48612",
    "sg:province":"MI",
    "sg:tags":[
        "commercial",
        "storage"
    ],
    "wof:name":"Lakeside Mini Storage",
    "wof:placetype":"venue"
},
  "geometry": {"coordinates":[-84.31993199999999,43.871685],"type":"Point"}
}