{
  "type": "Feature",
  "properties": {
    "iso:country":"US",
    "sg:address":"3384 E Jefferson Ave",
    "sg:city":"Detroit",
    "sg:classifiers":[
        {
            "category":"Insurance",
            "subcategory":"Insurance Agent",
            "type":"Services"
        }
    ],
    "sg:phone":"+1 313 568 0919",
    "sg:postcode":"48207",
    "sg:province":"MI",
    "wof:name":"Ellis Hayes",
    "wof:placetype":"venue"
},
  "geometry": {"coordinates":[-83.012963,42.342283],"type":"Point"}
}