{
  "type": "Feature",
  "properties": {
    "iso:country":"US",
    "sg:address":"9161 Arlington Dr",
    "sg:city":"Ypsilanti",
    "sg:classifiers":[
        {
            "category":"Personal",
            "type":"Services"
        }
    ],
    "sg:phone":"+1 734 483 0305",
    "sg:postcode":"48198",
    "sg:province":"MI",
    "sg:tags":[
        "towing"
    ],
    "wof:name":"Decker's Towing Service",
    "wof:placetype":"venue"
},
  "geometry": {"coordinates":[-83.57973800000001,42.275537],"type":"Point"}
}