{
  "type": "Feature",
  "properties": {
    "iso:country":"US",
    "sg:address":"30100 Mound Rd",
    "sg:city":"Warren",
    "sg:classifiers":[
        {
            "category":"Professional",
            "subcategory":"Computer Services",
            "type":"Services"
        }
    ],
    "sg:phone":"+1 586 986 4246",
    "sg:postcode":"48092",
    "sg:province":"MI",
    "sg:tags":[
        "processing",
        "datum"
    ],
    "wof:name":"Electronic Data Systems Corp",
    "wof:placetype":"venue"
},
  "geometry": {"coordinates":[-83.046503,42.514137],"type":"Point"}
}