{
  "type": "Feature",
  "properties": {
    "iso:country":"US",
    "sg:address":"405 Marion Ave",
    "sg:city":"Big Rapids",
    "sg:classifiers":[
        {
            "category":"Professional",
            "subcategory":"Research",
            "type":"Services"
        }
    ],
    "sg:phone":"+1 231 796 0903",
    "sg:postcode":"49307",
    "sg:province":"MI",
    "sg:tags":[
        "environmental",
        "ecological"
    ],
    "wof:name":"Vande Water Natural Resources",
    "wof:placetype":"venue"
},
  "geometry": {"coordinates":[-85.48560500000001,43.703315],"type":"Point"}
}