{
  "type": "Feature",
  "properties": {
    "iso:country":"US",
    "sg:address":"118 E Grand River Ave",
    "sg:city":"Fowlerville",
    "sg:classifiers":[
        {
            "category":"Banks & Credit Unions",
            "subcategory":"Bank",
            "type":"Services"
        }
    ],
    "sg:phone":"+1 517 223 3713",
    "sg:postcode":"48836",
    "sg:province":"MI",
    "sg:website":"www.bankone.com",
    "wof:name":"Bank One",
    "wof:placetype":"venue"
},
  "geometry": {"coordinates":[-84.073035,42.660595],"type":"Point"}
}