{
  "type": "Feature",
  "properties": {
    "iso:country":"US",
    "sg:address":"3079 30th St SW",
    "sg:city":"Grandville",
    "sg:classifiers":[
        {
            "category":"Shopping",
            "subcategory":"Department Store",
            "type":"Retail Goods"
        }
    ],
    "sg:phone":"+1 616 261 1517",
    "sg:postcode":"49418",
    "sg:province":"MI",
    "sg:tags":[
        "shop"
    ],
    "wof:name":"Dollar General",
    "wof:placetype":"venue"
},
  "geometry": {"coordinates":[-85.742014,42.910358],"type":"Point"}
}