{
  "type": "Feature",
  "properties": {
    "iso:country":"US",
    "sg:address":"5780 S Ubly Rd",
    "sg:city":"Ubly",
    "sg:classifiers":[
        {
            "category":"Farming",
            "subcategory":"Farm",
            "type":"Manufacturing & Wholesale Goods"
        }
    ],
    "sg:phone":"+1 989 658 8188",
    "sg:postcode":"48475",
    "sg:province":"MI",
    "sg:tags":[
        "crop",
        "general"
    ],
    "wof:name":"Dan Kubacki",
    "wof:placetype":"venue"
},
  "geometry": {"coordinates":[-82.936744,43.592247],"type":"Point"}
}