{
  "type": "Feature",
  "properties": {
    "iso:country":"US",
    "sg:address":"1600 Washington Ave",
    "sg:city":"Port Huron",
    "sg:classifiers":[
        {
            "category":"Manufacturing",
            "subcategory":"Petroleum Products",
            "type":"Manufacturing & Wholesale Goods"
        }
    ],
    "sg:phone":"+1 810 984 5581",
    "sg:postcode":"48060",
    "sg:province":"MI",
    "sg:tags":[
        "lubricant"
    ],
    "wof:name":"Acheson Industries Inc",
    "wof:placetype":"venue"
},
  "geometry": {"coordinates":[-82.436139,42.988494],"type":"Point"}
}