{
  "type": "Feature",
  "properties": {
    "iso:country":"US",
    "sg:address":"2971 Acorn Rd",
    "sg:city":"Bloomfield Hills",
    "sg:classifiers":[
        {
            "category":"Building & Trades",
            "subcategory":"Landscaping Services",
            "type":"Services"
        }
    ],
    "sg:phone":"+1 248 332 3378",
    "sg:postcode":"48302",
    "sg:province":"MI",
    "sg:tags":[
        "lawn",
        "maintenance",
        "grounds"
    ],
    "wof:name":"Springer Lawn Svc",
    "wof:placetype":"venue"
},
  "geometry": {"coordinates":[-83.28411699999999,42.597104],"type":"Point"}
}