{
  "type": "Feature",
  "properties": {
    "iso:country":"US",
    "sg:address":"1020 S Mears Ave",
    "sg:city":"Whitehall",
    "sg:classifiers":[
        {
            "category":"Health Services",
            "subcategory":"Chiropractor",
            "type":"Services"
        }
    ],
    "sg:phone":"+1 231 893 1755",
    "sg:postcode":"49461",
    "sg:province":"MI",
    "wof:name":"White Lake Chiropractic",
    "wof:placetype":"venue"
},
  "geometry": {"coordinates":[-86.347889,43.397978],"type":"Point"}
}