{
  "type": "Feature",
  "properties": {
    "iso:country":"US",
    "sg:address":"12933 Gurd Rd",
    "sg:city":"Delton",
    "sg:classifiers":[
        {
            "category":"Manufacturing",
            "subcategory":"Retail Goods",
            "type":"Manufacturing & Wholesale Goods"
        }
    ],
    "sg:phone":"+1 269 760 9629",
    "sg:postcode":"49046",
    "sg:province":"MI",
    "sg:tags":[
        "product",
        "mfg"
    ],
    "wof:name":"Scentsational Candles",
    "wof:placetype":"venue"
},
  "geometry": {"coordinates":[-85.327535,42.466196],"type":"Point"}
}