{
  "type": "Feature",
  "properties": {
    "iso:country":"US",
    "sg:address":"592 Springview Dr",
    "sg:city":"Rochester",
    "sg:classifiers":[
        {
            "category":"Professional",
            "subcategory":"Computer Services",
            "type":"Services"
        }
    ],
    "sg:phone":"+1 248 601 7300",
    "sg:postcode":"48307",
    "sg:province":"MI",
    "sg:tags":[
        "consultant",
        "designer"
    ],
    "wof:name":"Linder Technology Group",
    "wof:placetype":"venue"
},
  "geometry": {"coordinates":[-83.10798699999999,42.695472],"type":"Point"}
}