{
  "type": "Feature",
  "properties": {
    "iso:country":"US",
    "sg:address":"5198 N Samuelson Rd",
    "sg:city":"Chatham",
    "sg:classifiers":[
        {
            "category":"Professional",
            "subcategory":"Business Services",
            "type":"Services"
        }
    ],
    "sg:phone":"+1 906 439 5843",
    "sg:postcode":"49816",
    "sg:province":"MI",
    "wof:name":"Bill Rantz Home Inspectio",
    "wof:placetype":"venue"
},
  "geometry": {"coordinates":[-86.887097,46.354582],"type":"Point"}
}