{
  "type": "Feature",
  "properties": {
    "iso:country":"US",
    "sg:address":"170 W Soper Rd",
    "sg:city":"Bad Axe",
    "sg:classifiers":[
        {
            "category":"Recreation",
            "type":"Entertainment"
        }
    ],
    "sg:phone":"+1 989 269 2720",
    "sg:postcode":"48413",
    "sg:province":"MI",
    "wof:name":"Huron County Expo",
    "wof:placetype":"venue"
},
  "geometry": {"coordinates":[-83.003518,43.794716],"type":"Point"}
}