{
  "type": "Feature",
  "properties": {
    "iso:country":"US",
    "sg:address":"4114 Watson Rd",
    "sg:city":"Marlette",
    "sg:classifiers":[
        {
            "category":"Freight",
            "type":"Transportation"
        }
    ],
    "sg:phone":"+1 989 635 2756",
    "sg:postcode":"48453",
    "sg:province":"MI",
    "sg:tags":[
        "trucking"
    ],
    "wof:name":"Dye Trucking Inc",
    "wof:placetype":"venue"
},
  "geometry": {"coordinates":[-83.099693,43.299241],"type":"Point"}
}