{
  "type": "Feature",
  "properties": {
    "iso:country":"US",
    "sg:address":"39900 W 14 Mile Rd",
    "sg:city":"Commerce Twp",
    "sg:classifiers":[
        {
            "category":"Shopping",
            "subcategory":"Bicycles & Sporting Goods",
            "type":"Retail Goods"
        }
    ],
    "sg:phone":"+1 248 960 1371",
    "sg:postcode":"48390",
    "sg:province":"MI",
    "sg:tags":[
        "equipment",
        "exercise"
    ],
    "wof:name":"American Cycle & Fitness",
    "wof:placetype":"venue"
},
  "geometry": {"coordinates":[-83.445279,42.527006],"type":"Point"}
}