{
  "type": "Feature",
  "properties": {
    "iso:country":"US",
    "sg:address":"2450 Austin Dr",
    "sg:city":"Troy",
    "sg:classifiers":[
        {
            "category":"Wholesale",
            "subcategory":"Metals & Minerals",
            "type":"Manufacturing & Wholesale Goods"
        }
    ],
    "sg:phone":"+1 248 528 3200",
    "sg:postcode":"48083",
    "sg:province":"MI",
    "sg:tags":[
        "steel",
        "warehouse"
    ],
    "sg:website":"www.peerlesssteel.com",
    "wof:name":"Peerless Steel Co",
    "wof:placetype":"venue"
},
  "geometry": {"coordinates":[-83.115071,42.553978],"type":"Point"}
}