{
  "type": "Feature",
  "properties": {
    "iso:country":"US",
    "sg:address":"523 N Marias Ave",
    "sg:city":"Clawson",
    "sg:classifiers":[
        {
            "category":"Professional",
            "type":"Services"
        }
    ],
    "sg:phone":"+1 248 288 3307",
    "sg:postcode":"48017",
    "sg:province":"MI",
    "sg:tags":[
        "establishment"
    ],
    "wof:name":"Neighborhood Residential",
    "wof:placetype":"venue"
},
  "geometry": {"coordinates":[-83.158362,42.535],"type":"Point"}
}