{
  "type": "Feature",
  "properties": {
    "iso:country":"US",
    "sg:address":"9581 Burnette St",
    "sg:city":"Detroit",
    "sg:classifiers":[
        {
            "category":"Personal",
            "subcategory":"Barber",
            "type":"Services"
        }
    ],
    "sg:phone":"+1 313 279 2193",
    "sg:postcode":"48204",
    "sg:province":"MI",
    "wof:name":"Barber Shop 2",
    "wof:placetype":"venue"
},
  "geometry": {"coordinates":[-83.14247,42.367166],"type":"Point"}
}