{
  "type": "Feature",
  "properties": {
    "iso:country":"US",
    "sg:address":"2044 Gooding St",
    "sg:city":"Conklin",
    "sg:classifiers":[
        {
            "category":"Organizations",
            "subcategory":"Religious Organization",
            "type":"Services"
        }
    ],
    "sg:phone":"+1 616 899 2471",
    "sg:postcode":"49403",
    "sg:province":"MI",
    "wof:name":"St Francis Xavier Church",
    "wof:placetype":"venue"
},
  "geometry": {"coordinates":[-85.840628,43.161872],"type":"Point"}
}