{
  "type": "Feature",
  "properties": {
    "iso:country":"US",
    "sg:address":"19332 E 10 Mile Rd",
    "sg:city":"Eastpointe",
    "sg:classifiers":[
        {
            "category":"Shopping",
            "subcategory":"Pharmacy",
            "type":"Retail Goods"
        }
    ],
    "sg:phone":"+1 586 771 0030",
    "sg:postcode":"48021",
    "sg:province":"MI",
    "sg:tags":[
        "drugstore"
    ],
    "wof:name":"Fairway Sav-Mor Drugs",
    "wof:placetype":"venue"
},
  "geometry": {"coordinates":[-82.920303,42.480301],"type":"Point"}
}