{
  "type": "Feature",
  "properties": {
    "iso:country":"US",
    "sg:address":"1401 Farrow St",
    "sg:city":"Ferndale",
    "sg:classifiers":[
        {
            "category":"Social Services",
            "subcategory":"Job Training",
            "type":"Services"
        }
    ],
    "sg:phone":"+1 248 541 2740",
    "sg:postcode":"48220",
    "sg:province":"MI",
    "wof:name":"Detroit Carpenters Jatc Inc",
    "wof:placetype":"venue"
},
  "geometry": {"coordinates":[-83.118197,42.459663],"type":"Point"}
}