{
  "type": "Feature",
  "properties": {
    "iso:country":"US",
    "sg:address":"727 Vassar Dr",
    "sg:city":"Fenton",
    "sg:classifiers":[
        {
            "category":"Professional",
            "subcategory":"Art Services",
            "type":"Services"
        }
    ],
    "sg:phone":"+1 810 750 9936",
    "sg:postcode":"48430",
    "sg:province":"MI",
    "sg:tags":[
        "commercial",
        "design"
    ],
    "wof:name":"Whitener Company",
    "wof:placetype":"venue"
},
  "geometry": {"coordinates":[-83.71512199999999,42.787401],"type":"Point"}
}