{
  "type": "Feature",
  "properties": {
    "iso:country":"US",
    "sg:address":"275 Elizabeth St",
    "sg:city":"Niles",
    "sg:classifiers":[
        {
            "category":"Building & Trades",
            "subcategory":"Plumbing",
            "type":"Services"
        }
    ],
    "sg:phone":"+1 269 683 4913",
    "sg:postcode":"49120",
    "sg:province":"MI",
    "sg:tags":[
        "plumbing",
        "contractor"
    ],
    "wof:name":"Hood's Plumbing",
    "wof:placetype":"venue"
},
  "geometry": {"coordinates":[-86.214472,41.773021],"type":"Point"}
}