{
  "type": "Feature",
  "properties": {
    "iso:country":"US",
    "sg:address":"10367 Van Buren St",
    "sg:city":"Zeeland",
    "sg:classifiers":[
        {
            "category":"Travel",
            "subcategory":"Campground",
            "type":"Entertainment"
        }
    ],
    "sg:phone":"+1 616 669 1600",
    "sg:postcode":"49464",
    "sg:province":"MI",
    "sg:tags":[
        "trailer"
    ],
    "wof:name":"Baldwin Oaks Campground",
    "wof:placetype":"venue"
},
  "geometry": {"coordinates":[-86.037133,42.870562],"type":"Point"}
}