{
  "type": "Feature",
  "properties": {
    "iso:country":"US",
    "sg:address":"3478 N Skookum Rd",
    "sg:city":"Luther",
    "sg:classifiers":[
        {
            "category":"Manufacturing",
            "subcategory":"Tools & Machinery",
            "type":"Manufacturing & Wholesale Goods"
        }
    ],
    "sg:phone":"+1 231 797 5013",
    "sg:postcode":"49656",
    "sg:province":"MI",
    "sg:tags":[
        "mfg"
    ],
    "wof:name":"Mold & Craft Inc",
    "wof:placetype":"venue"
},
  "geometry": {"coordinates":[-85.64254699999999,44.033031],"type":"Point"}
}