{
  "type": "Feature",
  "properties": {
    "iso:country":"US",
    "sg:address":"2380 Central Rd",
    "sg:city":"Muskegon",
    "sg:classifiers":[
        {
            "category":"Organizations",
            "subcategory":"Membership Organization",
            "type":"Services"
        }
    ],
    "sg:phone":"+1 231 766 3447",
    "sg:postcode":"49445",
    "sg:province":"MI",
    "sg:tags":[
        "athletic"
    ],
    "wof:name":"Muskegon Bowmen Inc",
    "wof:placetype":"venue"
},
  "geometry": {"coordinates":[-86.24700199999999,43.298076],"type":"Point"}
}