{
  "type": "Feature",
  "properties": {
    "iso:country":"US",
    "sg:address":"38787 Byriver St",
    "sg:city":"Clinton Twp",
    "sg:classifiers":[
        {
            "category":"Health Services",
            "subcategory":"Health Practitioner",
            "type":"Services"
        }
    ],
    "sg:phone":"+1 586 469 1872",
    "sg:postcode":"48036",
    "sg:province":"MI",
    "sg:tags":[
        "psychologist"
    ],
    "wof:name":"Psychological Svc Human Growth",
    "wof:placetype":"venue"
},
  "geometry": {"coordinates":[-82.926846,42.58568],"type":"Point"}
}