{
  "type": "Feature",
  "properties": {
    "iso:country":"US",
    "sg:address":"4774 Mack Rd",
    "sg:city":"Howell",
    "sg:classifiers":[
        {
            "category":"Freight",
            "type":"Transportation"
        }
    ],
    "sg:phone":"+1 810 599 1337",
    "sg:postcode":"48855",
    "sg:province":"MI",
    "sg:tags":[
        "trucking"
    ],
    "wof:name":"Lin's Transport & Delivery",
    "wof:placetype":"venue"
},
  "geometry": {"coordinates":[-83.857563,42.672372],"type":"Point"}
}