{
  "type": "Feature",
  "properties": {
    "iso:country":"US",
    "sg:address":"11648 Yellowstone St",
    "sg:city":"Detroit",
    "sg:classifiers":[
        {
            "category":"Building & Trades",
            "subcategory":"Cleaning & Sanitation",
            "type":"Services"
        }
    ],
    "sg:phone":"+1 313 834 6201",
    "sg:postcode":"48204",
    "sg:province":"MI",
    "sg:tags":[
        "janitorial"
    ],
    "wof:name":"Ram Services",
    "wof:placetype":"venue"
},
  "geometry": {"coordinates":[-83.134918,42.376845],"type":"Point"}
}