{
  "type": "Feature",
  "properties": {
    "iso:country":"US",
    "sg:address":"2927 Dixon Rd",
    "sg:city":"Caro",
    "sg:phone":"+1 989 673 3238",
    "sg:postcode":"48723",
    "sg:province":"MI",
    "sg:tags":[
        "farm",
        "corn"
    ],
    "wof:name":"Nick Stoick",
    "wof:placetype":"venue"
},
  "geometry": {"coordinates":[-83.453737,43.466012],"type":"Point"}
}