{
  "type": "Feature",
  "properties": {
    "iso:country":"US",
    "sg:address":"304 E Bellevue St",
    "sg:city":"Leslie",
    "sg:classifiers":[
        {
            "category":"Wholesale",
            "subcategory":"Farm Supplies",
            "type":"Manufacturing & Wholesale Goods"
        }
    ],
    "sg:phone":"+1 517 589 8248",
    "sg:postcode":"49251",
    "sg:province":"MI",
    "sg:tags":[
        "feed"
    ],
    "wof:name":"Leslie Farm Ctr",
    "wof:placetype":"venue"
},
  "geometry": {"coordinates":[-84.428315,42.451136],"type":"Point"}
}