{
  "type": "Feature",
  "properties": {
    "iso:country":"US",
    "sg:address":"3600 Capital Ave SW",
    "sg:city":"Battle Creek",
    "sg:classifiers":[
        {
            "category":"Health Services",
            "subcategory":"Doctor",
            "type":"Services"
        }
    ],
    "sg:phone":"+1 269 979 6383",
    "sg:postcode":"49015",
    "sg:province":"MI",
    "sg:tags":[
        "medical"
    ],
    "wof:name":"John M Nassif MD",
    "wof:placetype":"venue"
},
  "geometry": {"coordinates":[-85.198593,42.253101],"type":"Point"}
}