{
  "type": "Feature",
  "properties": {
    "iso:country":"US",
    "sg:address":"6702 Parkbelt Dr",
    "sg:city":"Flint",
    "sg:classifiers":[
        {
            "category":"Professional",
            "type":"Services"
        }
    ],
    "sg:phone":"+1 810 789 3728",
    "sg:postcode":"48505",
    "sg:province":"MI",
    "wof:name":"McKelry & Associates",
    "wof:placetype":"venue"
},
  "geometry": {"coordinates":[-83.722403,43.074374],"type":"Point"}
}