{
  "type": "Feature",
  "properties": {
    "iso:country":"US",
    "sg:address":"4949 S Harvey St",
    "sg:city":"Muskegon",
    "sg:classifiers":[
        {
            "category":"Shopping",
            "type":"Retail Goods"
        }
    ],
    "sg:phone":"+1 231 722 2146",
    "sg:postcode":"49444",
    "sg:province":"MI",
    "sg:tags":[
        "church",
        "supply"
    ],
    "sg:website":"www.abc2z.com",
    "wof:name":"Hage's Christian Supplies",
    "wof:placetype":"venue"
},
  "geometry": {"coordinates":[-86.205623,43.167854],"type":"Point"}
}