{
  "type": "Feature",
  "properties": {
    "iso:country":"US",
    "sg:address":"12974 Croftshire Dr",
    "sg:city":"Grand Blanc",
    "sg:classifiers":[
        {
            "category":"Insurance",
            "subcategory":"Insurance Agent",
            "type":"Services"
        }
    ],
    "sg:phone":"+1 810 694 3826",
    "sg:postcode":"48439",
    "sg:province":"MI",
    "wof:name":"Primerica Financial Svc",
    "wof:placetype":"venue"
},
  "geometry": {"coordinates":[-83.61045799999999,42.917574],"type":"Point"}
}