{
  "type": "Feature",
  "properties": {
    "iso:country":"US",
    "sg:address":"1687 Plymouth Rd",
    "sg:city":"Ann Arbor",
    "sg:classifiers":[
        {
            "category":"Sports & Exercise",
            "subcategory":"Gym",
            "type":"Entertainment"
        }
    ],
    "sg:phone":"+1 734 668 0710",
    "sg:postcode":"48105",
    "sg:province":"MI",
    "sg:tags":[
        "fitness",
        "physical",
        "facility"
    ],
    "wof:name":"Callanetics Studio Ann Arbor",
    "wof:placetype":"venue"
},
  "geometry": {"coordinates":[-83.72754399999999,42.298287],"type":"Point"}
}