{
  "type": "Feature",
  "properties": {
    "iso:country":"US",
    "sg:address":"4585 Canal Ave SW",
    "sg:city":"Grandville",
    "sg:classifiers":[
        {
            "category":"Shopping",
            "subcategory":"Department Store",
            "type":"Retail Goods"
        }
    ],
    "sg:phone":"+1 616 531 9504",
    "sg:postcode":"49418",
    "sg:province":"MI",
    "sg:tags":[
        "shop"
    ],
    "wof:name":"Dollar Express",
    "wof:placetype":"venue"
},
  "geometry": {"coordinates":[-85.772413,42.882016],"type":"Point"}
}