{
  "type": "Feature",
  "properties": {
    "iso:country":"US",
    "sg:address":"27633 Little Mack Ave",
    "sg:city":"St Clair Shores",
    "sg:classifiers":[
        {
            "category":"Food & Beverages",
            "subcategory":"Groceries & Convenience Stores",
            "type":"Retail Goods"
        }
    ],
    "sg:phone":"+1 586 552 4639",
    "sg:postcode":"48081",
    "sg:province":"MI",
    "wof:name":"Marvins Mini Market",
    "wof:placetype":"venue"
},
  "geometry": {"coordinates":[-82.907754,42.495092],"type":"Point"}
}