{
  "type": "Feature",
  "properties": {
    "iso:country":"US",
    "sg:address":"1113 Ausable Rd",
    "sg:city":"Oscoda",
    "sg:classifiers":[
        {
            "category":"Building & Trades",
            "subcategory":"Electrical",
            "type":"Services"
        }
    ],
    "sg:phone":"+1 517 739 7333",
    "sg:postcode":"48750",
    "sg:province":"MI",
    "sg:tags":[
        "electrical",
        "electric",
        "contractor"
    ],
    "wof:name":"Al's Electric",
    "wof:placetype":"venue"
},
  "geometry": {"coordinates":[-83.348179,44.409989],"type":"Point"}
}