{
  "type": "Feature",
  "properties": {
    "iso:country":"US",
    "sg:address":"415 S Cedar St",
    "sg:city":"Mason",
    "sg:classifiers":[
        {
            "category":"Insurance",
            "subcategory":"Insurance Agent",
            "type":"Services"
        }
    ],
    "sg:phone":"+1 517 676 5534",
    "sg:postcode":"48854",
    "sg:province":"MI",
    "wof:name":"Mason Insurance Inc",
    "wof:placetype":"venue"
},
  "geometry": {"coordinates":[-84.45276800000001,42.578322],"type":"Point"}
}