{
  "type": "Feature",
  "properties": {
    "iso:country":"US",
    "sg:address":"1051 E Long Lake Rd",
    "sg:city":"Troy",
    "sg:classifiers":[
        {
            "category":"Personal",
            "subcategory":"Beauty Salon",
            "type":"Services"
        }
    ],
    "sg:phone":"+1 248 689 0402",
    "sg:postcode":"48085",
    "sg:province":"MI",
    "sg:tags":[
        "a",
        "hygiene",
        "cosmetology"
    ],
    "wof:name":"Merle Norman Cosmetics",
    "wof:placetype":"venue"
},
  "geometry": {"coordinates":[-83.12560499999999,42.592213],"type":"Point"}
}