{
  "type": "Feature",
  "properties": {
    "iso:country":"US",
    "sg:address":"52787 Hayes Rd",
    "sg:city":"Shelby Twp",
    "sg:classifiers":[
        {
            "category":"Restaurant",
            "type":"Food & Drink"
        }
    ],
    "sg:phone":"+1 586 566 6080",
    "sg:postcode":"48315",
    "sg:province":"MI",
    "sg:tags":[
        "eating"
    ],
    "wof:name":"Chinese Express",
    "wof:placetype":"venue"
},
  "geometry": {"coordinates":[-82.975656,42.68444],"type":"Point"}
}