{
  "type": "Feature",
  "properties": {
    "iso:country":"US",
    "sg:address":"136 W Huron Ave",
    "sg:city":"Bad Axe",
    "sg:phone":"+1 989 269 6481",
    "sg:postcode":"48413",
    "sg:province":"MI",
    "sg:tags":[
        "oil"
    ],
    "wof:name":"Neeb Corp",
    "wof:placetype":"venue"
},
  "geometry": {"coordinates":[-83.001424,43.801955],"type":"Point"}
}