{
  "type": "Feature",
  "properties": {
    "iso:country":"US",
    "sg:address":"1999 Maple Grove Rd",
    "sg:city":"Deckerville",
    "sg:classifiers":[
        {
            "category":"Retail",
            "subcategory":"Auto Repair",
            "type":"Services"
        }
    ],
    "sg:phone":"+1 810 376 8223",
    "sg:postcode":"48427",
    "sg:province":"MI",
    "sg:tags":[
        "automotive",
        "industrial",
        "general",
        "machinery",
        "mfg"
    ],
    "wof:name":"Maple Grove Auto Repair",
    "wof:placetype":"venue"
},
  "geometry": {"coordinates":[-82.673632,43.482547],"type":"Point"}
}