{
  "type": "Feature",
  "properties": {
    "iso:country":"US",
    "sg:address":"142 N State St",
    "sg:city":"Caro",
    "sg:classifiers":[
        {
            "category":"Restaurant",
            "type":"Food & Drink"
        }
    ],
    "sg:phone":"+1 989 672 3332",
    "sg:postcode":"48723",
    "sg:province":"MI",
    "sg:tags":[
        "shop",
        "coffee"
    ],
    "wof:name":"Thecaro Clique",
    "wof:placetype":"venue"
},
  "geometry": {"coordinates":[-83.395662,43.48934],"type":"Point"}
}