{
  "type": "Feature",
  "properties": {
    "iso:country":"US",
    "sg:address":"2004 Griswold St",
    "sg:city":"Port Huron",
    "sg:classifiers":[
        {
            "category":"Autos & Motor Vehicles",
            "subcategory":"Auto Supplies",
            "type":"Retail Goods"
        }
    ],
    "sg:phone":"+1 810 364 6329",
    "sg:postcode":"48060",
    "sg:province":"MI",
    "sg:tags":[
        "equipment",
        "racing",
        "car",
        "automobile"
    ],
    "wof:name":"Bad Bob's Mini Rods & Customs",
    "wof:placetype":"venue"
},
  "geometry": {"coordinates":[-82.44746600000001,42.966744],"type":"Point"}
}