{
  "type": "Feature",
  "properties": {
    "iso:country":"US",
    "sg:address":"2651 Westbrook Dr NW",
    "sg:city":"Grand Rapids",
    "sg:classifiers":[
        {
            "category":"Education",
            "subcategory":"Vocational School",
            "type":"Public Place"
        }
    ],
    "sg:phone":"+1 616 791 1111",
    "sg:postcode":"49504",
    "sg:province":"MI",
    "sg:tags":[
        "secretarial"
    ],
    "wof:name":"West Michigan PDI",
    "wof:placetype":"venue"
},
  "geometry": {"coordinates":[-85.734467,43.003494],"type":"Point"}
}