{
  "type": "Feature",
  "properties": {
    "iso:country":"US",
    "sg:address":"514 Lincoln Ave",
    "sg:city":"Holland",
    "sg:classifiers":[
        {
            "category":"Social Services",
            "type":"Services"
        }
    ],
    "sg:phone":"+1 616 395 2508",
    "sg:postcode":"49423",
    "sg:province":"MI",
    "sg:tags":[
        "youth",
        "organization",
        "center"
    ],
    "wof:name":"Urban Youth Ministry Inc",
    "wof:placetype":"venue"
},
  "geometry": {"coordinates":[-86.09733300000001,42.778259],"type":"Point"}
}