{
  "type": "Feature",
  "properties": {
    "iso:country":"US",
    "sg:address":"4843 Gilbo Ave",
    "sg:city":"Waterford",
    "sg:classifiers":[
        {
            "category":"Professional",
            "subcategory":"Art Services",
            "type":"Services"
        }
    ],
    "sg:phone":"+1 248 736 7627",
    "sg:postcode":"48328",
    "sg:province":"MI",
    "sg:tags":[
        "event",
        "portrait",
        "freelance",
        "photography",
        "specialist"
    ],
    "wof:name":"Maximum Exposure Inc",
    "wof:placetype":"venue"
},
  "geometry": {"coordinates":[-83.381006,42.64472],"type":"Point"}
}