{
  "type": "Feature",
  "properties": {
    "iso:country":"US",
    "sg:address":"101 S Beacon Blvd",
    "sg:city":"Grand Haven",
    "sg:classifiers":[
        {
            "category":"Real Estate",
            "subcategory":"Real Estate Agent",
            "type":"Services"
        }
    ],
    "sg:phone":"+1 616 935 1175",
    "sg:postcode":"49417",
    "sg:province":"MI",
    "wof:name":"Teitsma Team",
    "wof:placetype":"venue"
},
  "geometry": {"coordinates":[-86.220894,43.058974],"type":"Point"}
}