{
  "type": "Feature",
  "properties": {
    "iso:country":"US",
    "sg:address":"19610 Tanglewood Cir",
    "sg:city":"Clinton Township",
    "sg:classifiers":[
        {
            "category":"Arts & Performance",
            "subcategory":"Theater",
            "type":"Entertainment"
        }
    ],
    "sg:phone":"+1 586 412 3354",
    "sg:postcode":"48038",
    "sg:province":"MI",
    "sg:tags":[
        "group"
    ],
    "wof:name":"Power Entertainment Inc",
    "wof:placetype":"venue"
},
  "geometry": {"coordinates":[-82.922532,42.602028],"type":"Point"}
}