{
  "type": "Feature",
  "properties": {
    "iso:country":"US",
    "sg:address":"117 Division Ave S",
    "sg:city":"Grand Rapids",
    "sg:classifiers":[
        {
            "category":"Shopping",
            "subcategory":"Used Merchandise",
            "type":"Retail Goods"
        }
    ],
    "sg:phone":"+1 616 454 1033",
    "sg:postcode":"49503",
    "sg:province":"MI",
    "sg:tags":[
        "vintage",
        "clothing",
        "store"
    ],
    "wof:name":"Scavenger's Hunt",
    "wof:placetype":"venue"
},
  "geometry": {"coordinates":[-85.667772,42.959703],"type":"Point"}
}