{
  "type": "Feature",
  "properties": {
    "iso:country":"US",
    "sg:address":"5155 US Hwy 23",
    "sg:city":"Oscoda",
    "sg:classifiers":[
        {
            "category":"Food & Beverages",
            "subcategory":"Liquor & Beverages",
            "type":"Retail Goods"
        }
    ],
    "sg:phone":"+1 989 739 5846",
    "sg:postcode":"48750",
    "sg:province":"MI",
    "wof:name":"Block & Bottle",
    "wof:placetype":"venue"
},
  "geometry": {"coordinates":[-83.33027300000001,44.4276],"type":"Point"}
}