{
  "type": "Feature",
  "properties": {
    "iso:country":"US",
    "sg:address":"5282 Oakhill Dr",
    "sg:city":"Swartz Creek",
    "sg:classifiers":[
        {
            "category":"Communications",
            "subcategory":"Film & Video Production",
            "type":"Services"
        }
    ],
    "sg:phone":"+1 810 635 2324",
    "sg:postcode":"48473",
    "sg:province":"MI",
    "sg:tags":[
        "motion",
        "taping"
    ],
    "wof:name":"Roll'Em Productions",
    "wof:placetype":"venue"
},
  "geometry": {"coordinates":[-83.865696,42.947469],"type":"Point"}
}