{
  "type": "Feature",
  "properties": {
    "iso:country":"US",
    "sg:address":"8475 Farnum Ave",
    "sg:city":"Warren",
    "sg:classifiers":[
        {
            "category":"Professional",
            "subcategory":"Computer Services",
            "type":"Services"
        }
    ],
    "sg:phone":"+1 248 302 5174",
    "sg:postcode":"48093",
    "sg:province":"MI",
    "sg:tags":[
        "programing",
        "custom"
    ],
    "wof:name":"Computer Consultants",
    "wof:placetype":"venue"
},
  "geometry": {"coordinates":[-83.021728,42.496639],"type":"Point"}
}