{
  "type": "Feature",
  "properties": {
    "iso:country":"US",
    "sg:address":"4438 Oakbridge Dr",
    "sg:city":"Flint",
    "sg:classifiers":[
        {
            "category":"Professional",
            "subcategory":"Employment Agencies",
            "type":"Services"
        }
    ],
    "sg:phone":"+1 810 720 0022",
    "sg:postcode":"48532",
    "sg:province":"MI",
    "sg:tags":[
        "temporary"
    ],
    "wof:name":"Onsite Commercial Staffing",
    "wof:placetype":"venue"
},
  "geometry": {"coordinates":[-83.771123,42.997651],"type":"Point"}
}