{
  "type": "Feature",
  "properties": {
    "iso:country":"US",
    "sg:address":"121 E Michigan Ave",
    "sg:city":"Ypsilanti",
    "sg:classifiers":[
        {
            "category":"Personal",
            "subcategory":"Beauty Salon",
            "type":"Services"
        }
    ],
    "sg:phone":"+1 734 484 4100",
    "sg:postcode":"48198",
    "sg:province":"MI",
    "sg:tags":[
        "shop"
    ],
    "wof:name":"Avedas Hair Fashion",
    "wof:placetype":"venue"
},
  "geometry": {"coordinates":[-83.607202,42.241091],"type":"Point"}
}