{
  "type": "Feature",
  "properties": {
    "iso:country":"US",
    "sg:address":"9140 Highland Rd",
    "sg:city":"White Lake",
    "sg:classifiers":[
        {
            "category":"Cinema",
            "subcategory":"Movie Rental",
            "type":"Entertainment"
        }
    ],
    "sg:phone":"+1 248 698 9177",
    "sg:postcode":"48386",
    "sg:province":"MI",
    "sg:tags":[
        "leasing",
        "video",
        "disc",
        "tape"
    ],
    "wof:name":"Blockbuster Video",
    "wof:placetype":"venue"
},
  "geometry": {"coordinates":[-83.463843,42.657533],"type":"Point"}
}