{
  "type": "Feature",
  "properties": {
    "iso:country":"US",
    "sg:address":"3109 W Thompson Rd",
    "sg:city":"Fenton",
    "sg:classifiers":[
        {
            "category":"Retail",
            "subcategory":"Repair Shop",
            "type":"Services"
        }
    ],
    "sg:phone":"+1 810 750 9119",
    "sg:postcode":"48430",
    "sg:province":"MI",
    "sg:tags":[
        "hospital",
        "refinishing"
    ],
    "wof:name":"Flint Bio-Medical",
    "wof:placetype":"venue"
},
  "geometry": {"coordinates":[-83.732945,42.862889],"type":"Point"}
}