{
  "type": "Feature",
  "properties": {
    "iso:country":"US",
    "sg:address":"2870 Industrial Row Dr",
    "sg:city":"Troy",
    "sg:classifiers":[
        {
            "category":"Wholesale",
            "subcategory":"Machinery & Supplies",
            "type":"Manufacturing & Wholesale Goods"
        }
    ],
    "sg:phone":"+1 248 280 0030",
    "sg:postcode":"48084",
    "sg:province":"MI",
    "sg:tags":[
        "tubing",
        "hose"
    ],
    "wof:name":"Detroit Flexible Metal Prods",
    "wof:placetype":"venue"
},
  "geometry": {"coordinates":[-83.18378800000001,42.540553],"type":"Point"}
}