{
  "type": "Feature",
  "properties": {
    "iso:country":"US",
    "sg:address":"680 Pinckney Ct",
    "sg:city":"Comstock Park",
    "sg:classifiers":[
        {
            "category":"Real Estate",
            "subcategory":"Real Estate Operator",
            "type":"Services"
        }
    ],
    "sg:phone":"+1 616 784 0990",
    "sg:postcode":"49321",
    "sg:province":"MI",
    "sg:tags":[
        "building",
        "apartment"
    ],
    "wof:name":"Westgate Village Townhomes",
    "wof:placetype":"venue"
},
  "geometry": {"coordinates":[-85.68786,43.046329],"type":"Point"}
}