{
  "type": "Feature",
  "properties": {
    "iso:country":"US",
    "sg:address":"3201 Mill St",
    "sg:city":"Arcadia",
    "sg:classifiers":[
        {
            "category":"Professional",
            "type":"Services"
        }
    ],
    "sg:phone":"+1 231 889 4830",
    "sg:postcode":"49613",
    "sg:province":"MI",
    "wof:name":"Third Coast Architecture",
    "wof:placetype":"venue"
},
  "geometry": {"coordinates":[-86.23827799999999,44.492128],"type":"Point"}
}