{
  "type": "Feature",
  "properties": {
    "iso:country":"US",
    "sg:address":"305 Oakland Dr",
    "sg:city":"Kalamazoo",
    "sg:classifiers":[
        {
            "category":"Real Estate",
            "subcategory":"Real Estate Agent",
            "type":"Services"
        }
    ],
    "sg:phone":"+1 269 381 9258",
    "sg:postcode":"49007",
    "sg:province":"MI",
    "wof:name":"C David Howard Realtor",
    "wof:placetype":"venue"
},
  "geometry": {"coordinates":[-85.59692200000001,42.28916],"type":"Point"}
}