{
  "type": "Feature",
  "properties": {
    "iso:country":"US",
    "sg:address":"515 S Henry St",
    "sg:city":"Bay City",
    "sg:classifiers":[
        {
            "category":"Retail",
            "subcategory":"Repair Shop",
            "type":"Services"
        }
    ],
    "sg:phone":"+1 989 631 9111",
    "sg:postcode":"48706",
    "sg:province":"MI",
    "sg:tags":[
        "plumbing",
        "drain",
        "cleaning",
        "sewer"
    ],
    "wof:name":"Dependable Sewer Cleaning",
    "wof:placetype":"venue"
},
  "geometry": {"coordinates":[-83.900195,43.596276],"type":"Point"}
}