{
  "type": "Feature",
  "properties": {
    "iso:country":"US",
    "sg:address":"302 S Tecumseh St",
    "sg:city":"Adrian",
    "sg:classifiers":[
        {
            "category":"Social Services",
            "type":"Services"
        }
    ],
    "sg:phone":"+1 517 266 0937",
    "sg:postcode":"49221",
    "sg:province":"MI",
    "wof:name":"Daily Bread of Lenawee Inc",
    "wof:placetype":"venue"
},
  "geometry": {"coordinates":[-84.026849,41.895287],"type":"Point"}
}