{
  "type": "Feature",
  "properties": {
    "iso:country":"US",
    "sg:address":"1179 Chicago Rd",
    "sg:city":"Troy",
    "sg:classifiers":[
        {
            "category":"Education",
            "subcategory":"Vocational School",
            "type":"Public Place"
        }
    ],
    "sg:phone":"+1 248 597 0945",
    "sg:postcode":"48083",
    "sg:province":"MI",
    "sg:tags":[
        "training",
        "computer"
    ],
    "wof:name":"Technoventures",
    "wof:placetype":"venue"
},
  "geometry": {"coordinates":[-83.113843,42.547639],"type":"Point"}
}