{
  "type": "Feature",
  "properties": {
    "iso:country":"US",
    "sg:address":"4209 Park Ln",
    "sg:city":"Dorr",
    "sg:classifiers":[
        {
            "category":"Retail",
            "subcategory":"Auto Repair",
            "type":"Services"
        }
    ],
    "sg:phone":"+1 616 681 9776",
    "sg:postcode":"49323",
    "sg:province":"MI",
    "sg:tags":[
        "body",
        "automobile",
        "painting"
    ],
    "wof:name":"Dorr Village Auto Body",
    "wof:placetype":"venue"
},
  "geometry": {"coordinates":[-85.72600799999999,42.726306],"type":"Point"}
}