{
  "type": "Feature",
  "properties": {
    "iso:country":"US",
    "sg:address":"1 Water St",
    "sg:city":"Boyne City",
    "sg:classifiers":[
        {
            "category":"Restaurant",
            "type":"Food & Drink"
        }
    ],
    "sg:phone":"+1 231 582 1111",
    "sg:postcode":"49712",
    "sg:province":"MI",
    "wof:name":"Garrett's On Water Street",
    "wof:placetype":"venue"
},
  "geometry": {"coordinates":[-85.015315,45.213682],"type":"Point"}
}