{
  "type": "Feature",
  "properties": {
    "iso:country":"US",
    "sg:address":"2021 16th St",
    "sg:city":"Port Huron",
    "sg:classifiers":[
        {
            "category":"Wholesale",
            "subcategory":"Beer",
            "type":"Manufacturing & Wholesale Goods"
        }
    ],
    "sg:phone":"+1 810 987 7575",
    "sg:postcode":"48060",
    "sg:province":"MI",
    "sg:tags":[
        "ale"
    ],
    "wof:name":"Gerry's Distributing Co",
    "wof:placetype":"venue"
},
  "geometry": {"coordinates":[-82.442385,42.963006],"type":"Point"}
}