{
  "type": "Feature",
  "properties": {
    "iso:country":"US",
    "sg:address":"11209 Bellwood Dr",
    "sg:city":"Plymouth",
    "sg:classifiers":[
        {
            "category":"Professional",
            "subcategory":"Management & Consulting",
            "type":"Services"
        }
    ],
    "sg:phone":"+1 734 453 1743",
    "sg:postcode":"48170",
    "sg:province":"MI",
    "sg:tags":[
        "business"
    ],
    "wof:name":"Cornerstone Care Consultants",
    "wof:placetype":"venue"
},
  "geometry": {"coordinates":[-83.494924,42.363149],"type":"Point"}
}