{
  "type": "Feature",
  "properties": {
    "iso:country":"US",
    "sg:address":"20200 Cornillie Dr",
    "sg:city":"Roseville",
    "sg:classifiers":[
        {
            "category":"Manufacturing",
            "subcategory":"Tools & Machinery",
            "type":"Manufacturing & Wholesale Goods"
        }
    ],
    "sg:phone":"+1 586 294 2020",
    "sg:postcode":"48066",
    "sg:province":"MI",
    "sg:tags":[
        "power",
        "mfg"
    ],
    "wof:name":"Belt Grinding Accessories Inc",
    "wof:placetype":"venue"
},
  "geometry": {"coordinates":[-82.91204999999999,42.521079],"type":"Point"}
}