{
  "type": "Feature",
  "properties": {
    "iso:country":"US",
    "sg:address":"109 S Lincoln Ave",
    "sg:city":"Niles",
    "sg:classifiers":[
        {
            "category":"Health Services",
            "subcategory":"Doctor",
            "type":"Services"
        }
    ],
    "sg:phone":"+1 269 684 3580",
    "sg:postcode":"49120",
    "sg:province":"MI",
    "wof:name":"F Thomas Armstrong DDS",
    "wof:placetype":"venue"
},
  "geometry": {"coordinates":[-86.26362899999999,41.826134],"type":"Point"}
}