{
  "type": "Feature",
  "properties": {
    "iso:country":"US",
    "sg:address":"20333 Conant St",
    "sg:city":"Detroit",
    "sg:classifiers":[
        {
            "category":"Banks & Credit Unions",
            "subcategory":"Bank",
            "type":"Services"
        }
    ],
    "sg:phone":"+1 313 893 8255",
    "sg:postcode":"48234",
    "sg:province":"MI",
    "sg:tags":[
        "national",
        "commercial"
    ],
    "sg:website":"www.charteronebank.com",
    "wof:name":"Charter One Bank",
    "wof:placetype":"venue"
},
  "geometry": {"coordinates":[-83.082199,42.444599],"type":"Point"}
}