{
  "type": "Feature",
  "properties": {
    "iso:country":"US",
    "sg:address":"120 College Ave",
    "sg:city":"Britton",
    "sg:classifiers":[
        {
            "category":"Education",
            "subcategory":"Library",
            "type":"Public Place"
        }
    ],
    "sg:phone":"+1 517 451 2860",
    "sg:postcode":"49229",
    "sg:province":"MI",
    "wof:name":"Britton Library",
    "wof:placetype":"venue"
},
  "geometry": {"coordinates":[-83.83252400000001,41.985977],"type":"Point"}
}