{
  "type": "Feature",
  "properties": {
    "iso:country":"US",
    "sg:address":"3598 E Grand River Ave",
    "sg:city":"Howell",
    "sg:classifiers":[
        {
            "category":"Autos & Motor Vehicles",
            "subcategory":"Fuel & Gas Station",
            "type":"Retail Goods"
        }
    ],
    "sg:phone":"+1 517 545 8944",
    "sg:postcode":"48843",
    "sg:province":"MI",
    "sg:tags":[
        "oil"
    ],
    "wof:name":"Speedway",
    "wof:placetype":"venue"
},
  "geometry": {"coordinates":[-83.882262,42.589597],"type":"Point"}
}