{
  "type": "Feature",
  "properties": {
    "iso:country":"US",
    "sg:address":"1704 E Michigan Ave",
    "sg:city":"Lansing",
    "sg:classifiers":[
        {
            "category":"Personal",
            "type":"Services"
        }
    ],
    "sg:phone":"+1 517 367 7866",
    "sg:postcode":"48912",
    "sg:province":"MI",
    "wof:name":"Sunn City Inc",
    "wof:placetype":"venue"
},
  "geometry": {"coordinates":[-84.524908,42.733571],"type":"Point"}
}