{
  "type": "Feature",
  "properties": {
    "iso:country":"US",
    "sg:address":"859 Forest Ave",
    "sg:city":"Birmingham",
    "sg:classifiers":[
        {
            "category":"Real Estate",
            "subcategory":"Real Estate Agent",
            "type":"Services"
        }
    ],
    "sg:phone":"+1 248 258 1117",
    "sg:postcode":"48009",
    "sg:province":"MI",
    "sg:tags":[
        "appraiser"
    ],
    "wof:name":"Metro Appraisal Svc",
    "wof:placetype":"venue"
},
  "geometry": {"coordinates":[-83.206191,42.545657],"type":"Point"}
}