{
  "type": "Feature",
  "properties": {
    "iso:country":"US",
    "sg:address":"467 E Lakewood Blvd",
    "sg:city":"Holland",
    "sg:classifiers":[
        {
            "category":"Manufacturing",
            "subcategory":"Metals",
            "type":"Manufacturing & Wholesale Goods"
        }
    ],
    "sg:phone":"+1 616 392 3394",
    "sg:postcode":"49424",
    "sg:province":"MI",
    "sg:tags":[
        "fabricator",
        "sheet"
    ],
    "sg:website":"www.hollandsheetmtl.com",
    "wof:name":"Holland Sheet Metal Products",
    "wof:placetype":"venue"
},
  "geometry": {"coordinates":[-86.08919,42.804844],"type":"Point"}
}