{
  "type": "Feature",
  "properties": {
    "iso:country":"US",
    "sg:address":"40 W Howard St",
    "sg:city":"Pontiac",
    "sg:classifiers":[
        {
            "category":"Professional",
            "subcategory":"Art Services",
            "type":"Services"
        }
    ],
    "sg:phone":"+1 248 332 2579",
    "sg:postcode":"48342",
    "sg:province":"MI",
    "sg:tags":[
        "artist"
    ],
    "wof:name":"Robert Anthony Design",
    "wof:placetype":"venue"
},
  "geometry": {"coordinates":[-83.296468,42.646833],"type":"Point"}
}