{
  "type": "Feature",
  "properties": {
    "iso:country":"US",
    "sg:address":"29943 8 Mile Rd",
    "sg:city":"Livonia",
    "sg:classifiers":[
        {
            "category":"Retail",
            "subcategory":"Auto Repair",
            "type":"Services"
        }
    ],
    "sg:phone":"+1 248 477 6538",
    "sg:postcode":"48152",
    "sg:province":"MI",
    "sg:tags":[
        "body",
        "shop"
    ],
    "wof:name":"Daves Custom Collision",
    "wof:placetype":"venue"
},
  "geometry": {"coordinates":[-83.342499,42.441299],"type":"Point"}
}