{
  "type": "Feature",
  "properties": {
    "iso:country":"US",
    "sg:address":"7240 Saginaw Dr",
    "sg:city":"Kalamazoo",
    "sg:classifiers":[
        {
            "category":"Freight",
            "type":"Transportation"
        }
    ],
    "sg:phone":"+1 269 383 0111",
    "sg:postcode":"49048",
    "sg:province":"MI",
    "sg:tags":[
        "operator",
        "trucking"
    ],
    "wof:name":"Mrd Enterprises",
    "wof:placetype":"venue"
},
  "geometry": {"coordinates":[-85.48488399999999,42.290518],"type":"Point"}
}