{
  "type": "Feature",
  "properties": {
    "iso:country":"US",
    "sg:address":"52 E Goldengate",
    "sg:city":"Detroit",
    "sg:classifiers":[
        {
            "category":"Building & Trades",
            "subcategory":"Plumbing",
            "type":"Services"
        }
    ],
    "sg:phone":"+1 313 368 7867",
    "sg:postcode":"48203",
    "sg:province":"MI",
    "sg:tags":[
        "contractor"
    ],
    "wof:name":"Rons All Star Plumbing",
    "wof:placetype":"venue"
},
  "geometry": {"coordinates":[-83.100264,42.429035],"type":"Point"}
}