{
  "type": "Feature",
  "properties": {
    "iso:country":"US",
    "sg:address":"3345 Century Center St SW",
    "sg:city":"Grandville",
    "sg:classifiers":[
        {
            "category":"Shopping",
            "subcategory":"Shoes",
            "type":"Retail Goods"
        }
    ],
    "sg:phone":"+1 616 257 0510",
    "sg:postcode":"49418",
    "sg:province":"MI",
    "wof:name":"Birkenstock Place",
    "wof:placetype":"venue"
},
  "geometry": {"coordinates":[-85.74957499999999,42.881082],"type":"Point"}
}