{
  "type": "Feature",
  "properties": {
    "iso:country":"US",
    "sg:address":"39300 W 12 Mile Rd",
    "sg:city":"Farmington Hills",
    "sg:classifiers":[
        {
            "category":"Banks & Credit Unions",
            "subcategory":"Investment Brokerage",
            "type":"Services"
        }
    ],
    "sg:phone":"+1 248 536 6200",
    "sg:postcode":"48331",
    "sg:province":"MI",
    "sg:tags":[
        "consultant",
        "planning",
        "financial"
    ],
    "wof:name":"Msw Capital Management LLC",
    "wof:placetype":"venue"
},
  "geometry": {"coordinates":[-83.433735,42.497203],"type":"Point"}
}