{
  "type": "Feature",
  "properties": {
    "iso:country":"US",
    "sg:address":"401 S Jackson St",
    "sg:city":"Jackson",
    "sg:classifiers":[
        {
            "category":"Insurance",
            "subcategory":"Insurance Agent",
            "type":"Services"
        }
    ],
    "sg:phone":"+1 517 783 6600",
    "sg:postcode":"49203",
    "sg:province":"MI",
    "sg:tags":[
        "distributor",
        "enforcement",
        "law",
        "surety",
        "bond"
    ],
    "wof:name":"ID Card Service",
    "wof:placetype":"venue"
},
  "geometry": {"coordinates":[-84.40879099999999,42.243793],"type":"Point"}
}