{
  "type": "Feature",
  "properties": {
    "iso:country":"US",
    "sg:address":"129 Leona Ave",
    "sg:city":"Kalamazoo",
    "sg:classifiers":[
        {
            "category":"Shopping",
            "type":"Retail Goods"
        }
    ],
    "sg:phone":"+1 269 345 9375",
    "sg:postcode":"49001",
    "sg:province":"MI",
    "sg:tags":[
        "trophy",
        "medal",
        "award"
    ],
    "wof:name":"Quality Awards",
    "wof:placetype":"venue"
},
  "geometry": {"coordinates":[-85.57720399999999,42.254472],"type":"Point"}
}