{
  "type": "Feature",
  "properties": {
    "iso:country":"US",
    "sg:address":"3654 Campbell Rd",
    "sg:city":"Fort Gratiot",
    "sg:classifiers":[
        {
            "category":"Social Services",
            "subcategory":"Child Care",
            "type":"Services"
        }
    ],
    "sg:phone":"+1 810 987 4172",
    "sg:postcode":"48059",
    "sg:province":"MI",
    "sg:tags":[
        "day"
    ],
    "wof:name":"Aaron Lisa",
    "wof:placetype":"venue"
},
  "geometry": {"coordinates":[-82.51458700000001,43.012801],"type":"Point"}
}