{
  "type": "Feature",
  "properties": {
    "iso:country":"US",
    "sg:address":"27101 Beverly Rd",
    "sg:city":"Taylor",
    "sg:classifiers":[
        {
            "category":"Education",
            "subcategory":"School",
            "type":"Public Place"
        }
    ],
    "sg:phone":"+1 313 295 5775",
    "sg:postcode":"48180",
    "sg:province":"MI",
    "sg:tags":[
        "high",
        "middle",
        "elementary"
    ],
    "wof:name":"Taylor School District",
    "wof:placetype":"venue"
},
  "geometry": {"coordinates":[-83.305108,42.261062],"type":"Point"}
}