{
  "type": "Feature",
  "properties": {
    "iso:country":"US",
    "sg:address":"415 S Beacon Blvd",
    "sg:city":"Grand Haven",
    "sg:classifiers":[
        {
            "category":"Real Estate",
            "subcategory":"Real Estate Agent",
            "type":"Services"
        }
    ],
    "sg:phone":"+1 616 842 5970",
    "sg:postcode":"49417",
    "sg:province":"MI",
    "sg:tags":[
        "broker"
    ],
    "wof:name":"Prudential Clyd Hndrck Realtrs",
    "wof:placetype":"venue"
},
  "geometry": {"coordinates":[-86.220901,43.056386],"type":"Point"}
}