{
  "type": "Feature",
  "properties": {
    "iso:country":"US",
    "sg:address":"1918 Poplar St",
    "sg:city":"Holland",
    "sg:classifiers":[
        {
            "category":"Travel",
            "subcategory":"Hotels & Motels",
            "type":"Entertainment"
        }
    ],
    "sg:phone":"+1 616 399 9626",
    "sg:postcode":"49424",
    "sg:province":"MI",
    "sg:tags":[
        "operation"
    ],
    "wof:name":"Sunset Harbor Cottages",
    "wof:placetype":"venue"
},
  "geometry": {"coordinates":[-86.18843699999999,42.787358],"type":"Point"}
}