{
  "type": "Feature",
  "properties": {
    "iso:country":"US",
    "sg:address":"1245 S 11th St",
    "sg:city":"Niles",
    "sg:classifiers":[
        {
            "category":"Restaurant",
            "type":"Food & Drink"
        }
    ],
    "sg:menulink":"http://www.allmenus.com/mi/niles/4170-millennium-steak-house/menu/",
    "sg:phone":"+1 269 687 3000",
    "sg:postcode":"49120",
    "sg:province":"MI",
    "sg:tags":[
        "american",
        "steakhouse"
    ],
    "wof:name":"Millennium Steak House",
    "wof:placetype":"venue"
},
  "geometry": {"coordinates":[-86.24802800000001,41.814208],"type":"Point"}
}