{
  "type": "Feature",
  "properties": {
    "iso:country":"US",
    "sg:address":"322 Bay St",
    "sg:city":"Petoskey",
    "sg:classifiers":[
        {
            "category":"Professional",
            "type":"Services"
        }
    ],
    "sg:phone":"+1 231 487 9333",
    "sg:postcode":"49770",
    "sg:province":"MI",
    "sg:tags":[
        "establishment"
    ],
    "wof:name":"C J Designs",
    "wof:placetype":"venue"
},
  "geometry": {"coordinates":[-84.955703,45.375825],"type":"Point"}
}