{
  "type": "Feature",
  "properties": {
    "iso:country":"US",
    "sg:address":"43347 Ryer Ct",
    "sg:city":"Sterling Heights",
    "sg:classifiers":[
        {
            "category":"Professional",
            "subcategory":"Management & Consulting",
            "type":"Services"
        }
    ],
    "sg:phone":"+1 586 731 0442",
    "sg:postcode":"48313",
    "sg:province":"MI",
    "wof:name":"C A Malewicz",
    "wof:placetype":"venue"
},
  "geometry": {"coordinates":[-83.008262,42.612827],"type":"Point"}
}