{
  "type": "Feature",
  "properties": {
    "iso:country":"US",
    "sg:address":"362 State Park Dr",
    "sg:city":"Bay City",
    "sg:classifiers":[
        {
            "category":"Shopping",
            "subcategory":"Pharmacy",
            "type":"Retail Goods"
        }
    ],
    "sg:phone":"+1 989 684 8251",
    "sg:postcode":"48706",
    "sg:province":"MI",
    "wof:name":"Country Drugs",
    "wof:placetype":"venue"
},
  "geometry": {"coordinates":[-83.897525,43.653231],"type":"Point"}
}