{
  "type": "Feature",
  "properties": {
    "iso:country":"US",
    "sg:address":"11523 N Straits Hwy",
    "sg:city":"Cheboygan",
    "sg:classifiers":[
        {
            "category":"Shopping",
            "subcategory":"Stationery & Office Supplies",
            "type":"Retail Goods"
        }
    ],
    "sg:phone":"+1 231 627 9347",
    "sg:postcode":"49721",
    "sg:province":"MI",
    "sg:tags":[
        "album",
        "scrapbook"
    ],
    "wof:name":"Scrappin' Memories",
    "wof:placetype":"venue"
},
  "geometry": {"coordinates":[-84.477722,45.625884],"type":"Point"}
}