{
  "type": "Feature",
  "properties": {
    "iso:country":"US",
    "sg:address":"18575 San Quentin Dr",
    "sg:city":"Southfield",
    "sg:classifiers":[
        {
            "category":"Professional",
            "subcategory":"Business Services",
            "type":"Services"
        }
    ],
    "sg:phone":"+1 248 424 8843",
    "sg:postcode":"48076",
    "sg:province":"MI",
    "wof:name":"Jts & Assoc",
    "wof:placetype":"venue"
},
  "geometry": {"coordinates":[-83.227478,42.492832],"type":"Point"}
}