{
  "type": "Feature",
  "properties": {
    "iso:country":"US",
    "sg:address":"22722 N Nottingham Dr",
    "sg:city":"Franklin",
    "sg:classifiers":[
        {
            "category":"Professional",
            "subcategory":"Computer Services",
            "type":"Services"
        }
    ],
    "sg:phone":"+1 248 723 5850",
    "sg:postcode":"48025",
    "sg:province":"MI",
    "sg:tags":[
        "related"
    ],
    "wof:name":"Jackson Design",
    "wof:placetype":"venue"
},
  "geometry": {"coordinates":[-83.268602,42.525082],"type":"Point"}
}