{
  "type": "Feature",
  "properties": {
    "iso:country":"US",
    "sg:address":"35980 Woodward Ave",
    "sg:city":"Bloomfield Hills",
    "sg:classifiers":[
        {
            "category":"Professional",
            "subcategory":"Lawyer & Legal Services",
            "type":"Services"
        }
    ],
    "sg:phone":"+1 248 594 0353",
    "sg:postcode":"48304",
    "sg:province":"MI",
    "sg:tags":[
        "attorney"
    ],
    "wof:name":"Thomas J Manganello",
    "wof:placetype":"venue"
},
  "geometry": {"coordinates":[-83.218985,42.554456],"type":"Point"}
}