{
  "type": "Feature",
  "properties": {
    "iso:country":"US",
    "sg:address":"4210 Edgeland Ave",
    "sg:city":"Royal Oak",
    "sg:classifiers":[
        {
            "category":"Retail",
            "subcategory":"Repair Shop",
            "type":"Services"
        }
    ],
    "sg:phone":"+1 248 549 9338",
    "sg:postcode":"48073",
    "sg:province":"MI",
    "sg:tags":[
        "print",
        "electrical",
        "s",
        "lithographic",
        "typesetting"
    ],
    "wof:name":"Savers Printing",
    "wof:placetype":"venue"
},
  "geometry": {"coordinates":[-83.18104,42.526967],"type":"Point"}
}