{
  "type": "Feature",
  "properties": {
    "iso:country":"US",
    "sg:address":"13677 Westbrook Rd",
    "sg:city":"Plymouth",
    "sg:classifiers":[
        {
            "category":"Professional",
            "subcategory":"Lawyer & Legal Services",
            "type":"Services"
        }
    ],
    "sg:phone":"+1 734 451 9410",
    "sg:postcode":"48170",
    "sg:province":"MI",
    "wof:name":"Carol G Vlachos & Associates",
    "wof:placetype":"venue"
},
  "geometry": {"coordinates":[-83.49154900000001,42.378373],"type":"Point"}
}