{
  "type": "Feature",
  "properties": {
    "iso:country":"US",
    "sg:address":"2117 Bishop Cir E",
    "sg:city":"Dexter",
    "sg:classifiers":[
        {
            "category":"Professional",
            "subcategory":"Engineering",
            "type":"Services"
        }
    ],
    "sg:phone":"+1 734 424 2789",
    "sg:postcode":"48130",
    "sg:province":"MI",
    "sg:tags":[
        "control",
        "electronic",
        "manufacturing",
        "design"
    ],
    "wof:name":"Complete Dsign Automtn Systems",
    "wof:placetype":"venue"
},
  "geometry": {"coordinates":[-83.87738899999999,42.323078],"type":"Point"}
}