{
  "type": "Feature",
  "properties": {
    "iso:country":"US",
    "sg:address":"1055 136th Ave",
    "sg:city":"Holland",
    "sg:classifiers":[
        {
            "category":"Organizations",
            "subcategory":"Religious Organization",
            "type":"Services"
        }
    ],
    "sg:phone":"+1 616 786 0110",
    "sg:postcode":"49424",
    "sg:province":"MI",
    "sg:tags":[
        "church"
    ],
    "wof:name":"Harvestime Fellowship Church",
    "wof:placetype":"venue"
},
  "geometry": {"coordinates":[-86.117514,42.827099],"type":"Point"}
}