{
  "type": "Feature",
  "properties": {
    "iso:country":"US",
    "sg:address":"48925 West Rd",
    "sg:city":"Wixom",
    "sg:classifiers":[
        {
            "category":"Food & Beverages",
            "subcategory":"Specialty",
            "type":"Retail Goods"
        }
    ],
    "sg:phone":"+1 248 344 0030",
    "sg:postcode":"48393",
    "sg:province":"MI",
    "sg:tags":[
        "vitamin"
    ],
    "sg:website":"www.thebetterhealthstore.com",
    "wof:name":"Vitamin Outlet",
    "wof:placetype":"venue"
},
  "geometry": {"coordinates":[-83.534836,42.508165],"type":"Point"}
}