{
  "type": "Feature",
  "properties": {
    "iso:country":"US",
    "sg:address":"3235 Beecher Rd",
    "sg:city":"Flint",
    "sg:classifiers":[
        {
            "category":"Health Services",
            "subcategory":"Nursing And Care Facility",
            "type":"Services"
        }
    ],
    "sg:phone":"+1 810 342 1402",
    "sg:postcode":"48503",
    "sg:province":"MI",
    "wof:name":"Mclaren Health Care Corp",
    "wof:placetype":"venue"
},
  "geometry": {"coordinates":[-83.72752800000001,43.007363],"type":"Point"}
}