{
  "type": "Feature",
  "properties": {
    "iso:country":"US",
    "sg:address":"818 Pyle Dr",
    "sg:city":"Iron Mountain",
    "sg:classifiers":[
        {
            "category":"Government",
            "subcategory":"Office",
            "type":"Public Place"
        }
    ],
    "sg:phone":"+1 906 774 1868",
    "sg:postcode":"49802",
    "sg:province":"MI",
    "sg:tags":[
        "administrative",
        "program",
        "health"
    ],
    "wof:name":"Dickinson Iron Dst Hlth Dept",
    "wof:placetype":"venue"
},
  "geometry": {"coordinates":[-88.080201,45.804191],"type":"Point"}
}