{
  "type": "Feature",
  "properties": {
    "iso:country":"US",
    "sg:address":"824 Tittabawassee Rd",
    "sg:city":"Saginaw",
    "sg:classifiers":[
        {
            "category":"Shopping",
            "type":"Retail Goods"
        }
    ],
    "sg:phone":"+1 989 752 5459",
    "sg:postcode":"48604",
    "sg:province":"MI",
    "sg:tags":[
        "aquarium"
    ],
    "wof:name":"Aquatic Gardens",
    "wof:placetype":"venue"
},
  "geometry": {"coordinates":[-83.930187,43.479562],"type":"Point"}
}