{
  "type": "Feature",
  "properties": {
    "iso:country":"US",
    "sg:address":"2045 Austin Dr",
    "sg:city":"Troy",
    "sg:classifiers":[
        {
            "category":"Retail",
            "subcategory":"Auto Rental",
            "type":"Services"
        }
    ],
    "sg:phone":"+1 248 524 0198",
    "sg:postcode":"48083",
    "sg:province":"MI",
    "sg:tags":[
        "truck",
        "vehicle"
    ],
    "wof:name":"Rush Equipment Center",
    "wof:placetype":"venue"
},
  "geometry": {"coordinates":[-83.11527,42.555788],"type":"Point"}
}