{
  "type": "Feature",
  "properties": {
    "iso:country":"US",
    "sg:address":"2150 Pless Dr",
    "sg:city":"Brighton",
    "sg:classifiers":[
        {
            "category":"Manufacturing",
            "subcategory":"Signs",
            "type":"Manufacturing & Wholesale Goods"
        }
    ],
    "sg:phone":"+1 810 225 7446",
    "sg:postcode":"48114",
    "sg:province":"MI",
    "wof:name":"Signs By Tomorrow",
    "wof:placetype":"venue"
},
  "geometry": {"coordinates":[-83.812832,42.5695],"type":"Point"}
}