{
  "type": "Feature",
  "properties": {
    "iso:country":"US",
    "sg:address":"8540 Indian Hill Rd",
    "sg:city":"Honor",
    "sg:classifiers":[
        {
            "category":"Wholesale",
            "subcategory":"Construction Materials",
            "type":"Manufacturing & Wholesale Goods"
        }
    ],
    "sg:phone":"+1 231 325 5583",
    "sg:postcode":"49640",
    "sg:province":"MI",
    "sg:tags":[
        "sand",
        "gravel"
    ],
    "wof:name":"Bradley Sand & Gravel Inc",
    "wof:placetype":"venue"
},
  "geometry": {"coordinates":[-86.03922300000001,44.75589],"type":"Point"}
}