{
  "type": "Feature",
  "properties": {
    "iso:country":"US",
    "sg:address":"13707 Sterling Oaks Dr",
    "sg:city":"Sterling Heights",
    "sg:classifiers":[
        {
            "category":"Social Services",
            "subcategory":"Adult Care",
            "type":"Services"
        }
    ],
    "sg:phone":"+1 586 247 8181",
    "sg:postcode":"48313",
    "sg:province":"MI",
    "sg:tags":[
        "home",
        "aged",
        "for"
    ],
    "wof:name":"Polish Army Veterans Home",
    "wof:placetype":"venue"
},
  "geometry": {"coordinates":[-82.990813,42.597929],"type":"Point"}
}