{
  "type": "Feature",
  "properties": {
    "iso:country":"US",
    "sg:address":"1132 E Coggins Rd",
    "sg:city":"Pinconning",
    "sg:classifiers":[
        {
            "category":"Farming",
            "subcategory":"Farm",
            "type":"Manufacturing & Wholesale Goods"
        }
    ],
    "sg:phone":"+1 989 879 2248",
    "sg:postcode":"48650",
    "sg:province":"MI",
    "wof:name":"Johnson's Farm Co",
    "wof:placetype":"venue"
},
  "geometry": {"coordinates":[-84.002661,43.803627],"type":"Point"}
}