{
  "type": "Feature",
  "properties": {
    "iso:country":"US",
    "sg:address":"24630 Scotia Rd",
    "sg:city":"Oak Park",
    "sg:classifiers":[
        {
            "category":"Education",
            "subcategory":"Vocational School",
            "type":"Public Place"
        }
    ],
    "sg:phone":"+1 248 398 6438",
    "sg:postcode":"48237",
    "sg:province":"MI",
    "sg:tags":[
        "on",
        "line",
        "software",
        "senior",
        "citizen"
    ],
    "wof:name":"Madeline Maria Project Inc",
    "wof:placetype":"venue"
},
  "geometry": {"coordinates":[-83.172617,42.472402],"type":"Point"}
}