{
  "type": "Feature",
  "properties": {
    "iso:country":"US",
    "sg:address":"2007 Virginia Park St",
    "sg:city":"Detroit",
    "sg:classifiers":[
        {
            "category":"Retail",
            "subcategory":"Portrait Studio",
            "type":"Services"
        }
    ],
    "sg:phone":"+1 313 895 6243",
    "sg:postcode":"48206",
    "sg:province":"MI",
    "sg:tags":[
        "photo"
    ],
    "wof:name":"Frozen Moment Photos",
    "wof:placetype":"venue"
},
  "geometry": {"coordinates":[-83.097621,42.368951],"type":"Point"}
}