{
  "type": "Feature",
  "properties": {
    "iso:country":"US",
    "sg:address":"8261 E Michigan Ave",
    "sg:city":"Jackson",
    "sg:classifiers":[
        {
            "category":"Professional",
            "subcategory":"Business Services",
            "type":"Services"
        }
    ],
    "sg:phone":"+1 517 522 3139",
    "sg:postcode":"49201",
    "sg:province":"MI",
    "wof:name":"Cushard Design Assoc",
    "wof:placetype":"venue"
},
  "geometry": {"coordinates":[-84.278409,42.246977],"type":"Point"}
}