{
  "type": "Feature",
  "properties": {
    "iso:country":"US",
    "sg:address":"1005 Willis Ave",
    "sg:city":"Kalamazoo",
    "sg:classifiers":[
        {
            "category":"Building & Trades",
            "subcategory":"Construction",
            "type":"Services"
        }
    ],
    "sg:phone":"+1 269 552 9840",
    "sg:postcode":"49048",
    "sg:province":"MI",
    "sg:tags":[
        "concrete",
        "contractor"
    ],
    "wof:name":"Deleeuw Concrete",
    "wof:placetype":"venue"
},
  "geometry": {"coordinates":[-85.547196,42.281314],"type":"Point"}
}