{
  "type": "Feature",
  "properties": {
    "iso:country":"US",
    "sg:address":"4036 S Baldwin Rd",
    "sg:city":"Lake Orion",
    "sg:classifiers":[
        {
            "category":"Retail",
            "subcategory":"Car Wash",
            "type":"Services"
        }
    ],
    "sg:phone":"+1 248 393 3388",
    "sg:postcode":"48359",
    "sg:province":"MI",
    "sg:tags":[
        "polishing",
        "washing"
    ],
    "wof:name":"Town Auto Wash On Baldwin",
    "wof:placetype":"venue"
},
  "geometry": {"coordinates":[-83.307333,42.720757],"type":"Point"}
}