{
  "type": "Feature",
  "properties": {
    "iso:country":"US",
    "sg:address":"1075 Roseberry Ln",
    "sg:city":"Clio",
    "sg:classifiers":[
        {
            "category":"Arts & Performance",
            "subcategory":"Theater",
            "type":"Entertainment"
        }
    ],
    "sg:phone":"+1 810 686 0189",
    "sg:postcode":"48420",
    "sg:province":"MI",
    "sg:tags":[
        "musician"
    ],
    "wof:name":"Forest Green Family Inc",
    "wof:placetype":"venue"
},
  "geometry": {"coordinates":[-83.69856299999999,43.174522],"type":"Point"}
}