{
  "type": "Feature",
  "properties": {
    "iso:country":"US",
    "sg:address":"3494 Capital Ave SW",
    "sg:city":"Battle Creek",
    "sg:classifiers":[
        {
            "category":"Health Services",
            "subcategory":"Health Practitioner",
            "type":"Services"
        }
    ],
    "sg:phone":"+1 269 979 3881",
    "sg:postcode":"49015",
    "sg:province":"MI",
    "sg:tags":[
        "psychologist"
    ],
    "wof:name":"Lynn Lupini PHD",
    "wof:placetype":"venue"
},
  "geometry": {"coordinates":[-85.198667,42.253941],"type":"Point"}
}