{
  "type": "Feature",
  "properties": {
    "iso:country":"US",
    "sg:address":"5931 N Branch Rd",
    "sg:city":"North Branch",
    "sg:classifiers":[
        {
            "category":"Retail",
            "subcategory":"Car Wash",
            "type":"Services"
        }
    ],
    "sg:phone":"+1 810 793 1509",
    "sg:postcode":"48461",
    "sg:province":"MI",
    "sg:tags":[
        "polishing",
        "washing"
    ],
    "wof:name":"M & N Car Wash",
    "wof:placetype":"venue"
},
  "geometry": {"coordinates":[-83.124275,43.231239],"type":"Point"}
}