{
  "type": "Feature",
  "properties": {
    "iso:country":"US",
    "sg:address":"1001 Woodward Ave",
    "sg:city":"Detroit",
    "sg:classifiers":[
        {
            "category":"Organizations",
            "subcategory":"Professional Association",
            "type":"Services"
        }
    ],
    "sg:phone":"+1 313 309 2000",
    "sg:postcode":"48226",
    "sg:province":"MI",
    "sg:tags":[
        "business"
    ],
    "wof:name":"Great Lakes Fabricators/Erecto",
    "wof:placetype":"venue"
},
  "geometry": {"coordinates":[-83.04741199999999,42.33237],"type":"Point"}
}