{
  "type": "Feature",
  "properties": {
    "iso:country":"US",
    "sg:address":"4085 S Center Rd",
    "sg:city":"Burton",
    "sg:classifiers":[
        {
            "category":"Health Services",
            "subcategory":"Chiropractor",
            "type":"Services"
        }
    ],
    "sg:phone":"+1 810 744 4251",
    "sg:postcode":"48519",
    "sg:province":"MI",
    "wof:name":"Diagnostic Chiropractic",
    "wof:placetype":"venue"
},
  "geometry": {"coordinates":[-83.633003,42.971401],"type":"Point"}
}