{
  "type": "Feature",
  "properties": {
    "iso:country":"US",
    "sg:address":"30160 Orchard Lake Rd",
    "sg:city":"Farmington",
    "sg:classifiers":[
        {
            "category":"Communications",
            "subcategory":"Film & Video Production",
            "type":"Services"
        }
    ],
    "sg:phone":"+1 248 539 0800",
    "sg:postcode":"48334",
    "sg:province":"MI",
    "sg:tags":[
        "tape"
    ],
    "wof:name":"Newman Video Inc",
    "wof:placetype":"venue"
},
  "geometry": {"coordinates":[-83.359651,42.520483],"type":"Point"}
}