{
  "type": "Feature",
  "properties": {
    "iso:country":"US",
    "sg:address":"1735 Huron Springs Ln",
    "sg:city":"Commerce Township",
    "sg:classifiers":[
        {
            "category":"Professional",
            "subcategory":"Business Services",
            "type":"Services"
        }
    ],
    "sg:phone":"+1 248 366 1104",
    "sg:postcode":"48382",
    "sg:province":"MI",
    "wof:name":"Michigan Sales & Marketing",
    "wof:placetype":"venue"
},
  "geometry": {"coordinates":[-83.50544600000001,42.598354],"type":"Point"}
}