{
  "type": "Feature",
  "properties": {
    "iso:country":"US",
    "sg:address":"422 E South St",
    "sg:city":"Kalamazoo",
    "sg:classifiers":[
        {
            "category":"Education",
            "subcategory":"School",
            "type":"Public Place"
        }
    ],
    "sg:phone":"+1 269 488 9601",
    "sg:postcode":"49007",
    "sg:province":"MI",
    "sg:website":"www.remc12.k12.mi.us",
    "wof:name":"Young Adult Program",
    "wof:placetype":"venue"
},
  "geometry": {"coordinates":[-85.578328,42.291752],"type":"Point"}
}