{
  "type": "Feature",
  "properties": {
    "iso:country":"US",
    "sg:address":"598 Joy Rd",
    "sg:city":"Battle Creek",
    "sg:classifiers":[
        {
            "category":"Building & Trades",
            "subcategory":"Construction",
            "type":"Services"
        }
    ],
    "sg:phone":"+1 269 964 6361",
    "sg:postcode":"49014",
    "sg:province":"MI",
    "sg:tags":[
        "excavating",
        "contractor"
    ],
    "wof:name":"B & B Engineering",
    "wof:placetype":"venue"
},
  "geometry": {"coordinates":[-85.11502400000001,42.338927],"type":"Point"}
}