{
  "type": "Feature",
  "properties": {
    "iso:country":"US",
    "sg:address":"318 N Simon St",
    "sg:city":"Cadillac",
    "sg:classifiers":[
        {
            "category":"Education",
            "subcategory":"Special Training",
            "type":"Public Place"
        }
    ],
    "sg:phone":"+1 231 775 3972",
    "sg:postcode":"49601",
    "sg:province":"MI",
    "wof:name":"Studio One",
    "wof:placetype":"venue"
},
  "geometry": {"coordinates":[-85.398943,44.253998],"type":"Point"}
}