{
  "type": "Feature",
  "properties": {
    "iso:country":"US",
    "sg:address":"8845 Vergennes St SE",
    "sg:city":"Ada",
    "sg:classifiers":[
        {
            "category":"Wholesale",
            "subcategory":"Electrical",
            "type":"Manufacturing & Wholesale Goods"
        }
    ],
    "sg:phone":"+1 616 676 1460",
    "sg:postcode":"49301",
    "sg:province":"MI",
    "sg:tags":[
        "light",
        "tube",
        "bulb"
    ],
    "wof:name":"C & J Lighting",
    "wof:placetype":"venue"
},
  "geometry": {"coordinates":[-85.45038700000001,42.95795],"type":"Point"}
}