{
  "type": "Feature",
  "properties": {
    "iso:country":"US",
    "sg:address":"2920 Fuller Ave NE",
    "sg:city":"Grand Rapids",
    "sg:classifiers":[
        {
            "category":"Real Estate",
            "subcategory":"Real Estate Operator",
            "type":"Services"
        }
    ],
    "sg:phone":"+1 616 363 9064",
    "sg:postcode":"49505",
    "sg:province":"MI",
    "sg:tags":[
        "building",
        "parks"
    ],
    "wof:name":"Northbrook Office Park",
    "wof:placetype":"venue"
},
  "geometry": {"coordinates":[-85.639652,43.015487],"type":"Point"}
}