{
  "type": "Feature",
  "properties": {
    "iso:country":"US",
    "sg:address":"12700 W Chicago St",
    "sg:city":"Detroit",
    "sg:classifiers":[
        {
            "category":"Retail",
            "subcategory":"Auto Repair",
            "type":"Services"
        }
    ],
    "sg:phone":"+1 313 934 3881",
    "sg:postcode":"48228",
    "sg:province":"MI",
    "wof:name":"Chicago & Meyers Service",
    "wof:placetype":"venue"
},
  "geometry": {"coordinates":[-83.168701,42.3661],"type":"Point"}
}