{
  "type": "Feature",
  "properties": {
    "iso:country":"US",
    "sg:address":"8675 Breton Ave SE",
    "sg:city":"Caledonia",
    "sg:classifiers":[
        {
            "category":"Building & Trades",
            "subcategory":"Construction",
            "type":"Services"
        }
    ],
    "sg:phone":"+1 616 698 8399",
    "sg:postcode":"49316",
    "sg:province":"MI",
    "sg:tags":[
        "contractor"
    ],
    "wof:name":"Breton Builders",
    "wof:placetype":"venue"
},
  "geometry": {"coordinates":[-85.604927,42.806805],"type":"Point"}
}