{
  "type": "Feature",
  "properties": {
    "iso:country":"US",
    "sg:address":"3438 W Lennon Rd",
    "sg:city":"Flint",
    "sg:classifiers":[
        {
            "category":"Professional",
            "subcategory":"Accounting & Tax Preparation",
            "type":"Services"
        }
    ],
    "sg:phone":"+1 810 733 1100",
    "sg:postcode":"48507",
    "sg:province":"MI",
    "sg:tags":[
        "accountant"
    ],
    "sg:website":"www.rptcpas.com",
    "wof:name":"Rachor Purman & Tucker",
    "wof:placetype":"venue"
},
  "geometry": {"coordinates":[-83.750434,42.987541],"type":"Point"}
}