{
  "type": "Feature",
  "properties": {
    "iso:country":"US",
    "sg:address":"5276 N Branch Rd",
    "sg:city":"North Branch",
    "sg:classifiers":[
        {
            "category":"Building & Trades",
            "subcategory":"Cleaning & Sanitation",
            "type":"Services"
        }
    ],
    "sg:phone":"+1 810 688 1111",
    "sg:postcode":"48461",
    "sg:province":"MI",
    "sg:tags":[
        "janitor"
    ],
    "wof:name":"Jensen Cleaning Svc",
    "wof:placetype":"venue"
},
  "geometry": {"coordinates":[-83.13784099999999,43.230797],"type":"Point"}
}