{
  "type": "Feature",
  "properties": {
    "iso:country":"US",
    "sg:address":"321 N 7th St",
    "sg:city":"Grand Haven",
    "sg:classifiers":[
        {
            "category":"Retail",
            "subcategory":"Auto Repair",
            "type":"Services"
        }
    ],
    "sg:phone":"+1 616 842 4880",
    "sg:postcode":"49417",
    "sg:province":"MI",
    "sg:tags":[
        "towing",
        "wrecker"
    ],
    "wof:name":"Dicks Towing & Recovery Svc",
    "wof:placetype":"venue"
},
  "geometry": {"coordinates":[-86.221553,43.064295],"type":"Point"}
}