{
  "type": "Feature",
  "properties": {
    "iso:country":"US",
    "sg:address":"3645 E Cork St",
    "sg:city":"Kalamazoo",
    "sg:classifiers":[
        {
            "category":"Retail",
            "subcategory":"Repair Shop",
            "type":"Services"
        }
    ],
    "sg:phone":"+1 269 349 4780",
    "sg:postcode":"49001",
    "sg:province":"MI",
    "sg:tags":[
        "television",
        "radio",
        "facility"
    ],
    "wof:name":"Sears Roebuck and Co Inc",
    "wof:placetype":"venue"
},
  "geometry": {"coordinates":[-85.533462,42.261727],"type":"Point"}
}