{
  "type": "Feature",
  "properties": {
    "iso:country":"US",
    "sg:address":"1797 S Iroquois Row",
    "sg:city":"Brimley",
    "sg:classifiers":[
        {
            "category":"Travel",
            "subcategory":"Hotels & Motels",
            "type":"Entertainment"
        }
    ],
    "sg:phone":"+1 906 437 5300",
    "sg:postcode":"49715",
    "sg:province":"MI",
    "wof:name":"Iroquois Inn",
    "wof:placetype":"venue"
},
  "geometry": {"coordinates":[-84.689931,46.476448],"type":"Point"}
}