{
  "type": "Feature",
  "properties": {
    "iso:country":"US",
    "sg:address":"536 Elmwood Rd",
    "sg:city":"Lansing",
    "sg:classifiers":[
        {
            "category":"Coffee & Tea",
            "type":"Food & Drink"
        }
    ],
    "sg:menulink":"http://www.allmenus.com/mi/delta/248952-beaners-gourmet-coffee/menu/",
    "sg:phone":"+1 517 321 4146",
    "sg:postcode":"48917",
    "sg:province":"MI",
    "sg:tags":[
        "american"
    ],
    "wof:name":"Beaner's Gourmet Coffee",
    "wof:placetype":"venue"
},
  "geometry": {"coordinates":[-84.62127700000001,42.739723],"type":"Point"}
}