{
  "type": "Feature",
  "properties": {
    "iso:country":"US",
    "sg:address":"3028 Harborview St",
    "sg:city":"Monroe",
    "sg:classifiers":[
        {
            "category":"Recreation",
            "type":"Entertainment"
        }
    ],
    "sg:phone":"+1 734 289 3222",
    "sg:postcode":"48162",
    "sg:province":"MI",
    "sg:tags":[
        "club",
        "membership"
    ],
    "sg:website":"www.detroitbeachboatclub.com",
    "wof:name":"Detroit Beach Boat Club",
    "wof:placetype":"venue"
},
  "geometry": {"coordinates":[-83.33082,41.927338],"type":"Point"}
}