{
  "type": "Feature",
  "properties": {
    "iso:country":"US",
    "sg:address":"1950 N Opdyke Rd",
    "sg:city":"Auburn Hills",
    "sg:classifiers":[
        {
            "category":"Manufacturing",
            "subcategory":"Printing",
            "type":"Manufacturing & Wholesale Goods"
        }
    ],
    "sg:phone":"+1 248 377 4060",
    "sg:postcode":"48326",
    "sg:province":"MI",
    "sg:tags":[
        "printer"
    ],
    "wof:name":"American Speedy Printing Ctr",
    "wof:placetype":"venue"
},
  "geometry": {"coordinates":[-83.24576500000001,42.669703],"type":"Point"}
}