{
  "type": "Feature",
  "properties": {
    "iso:country":"US",
    "sg:address":"30710 Leroy St",
    "sg:city":"Romulus",
    "sg:classifiers":[
        {
            "category":"Restaurant",
            "type":"Food & Drink"
        }
    ],
    "sg:phone":"+1 734 941 2964",
    "sg:postcode":"48174",
    "sg:province":"MI",
    "sg:tags":[
        "eating"
    ],
    "wof:name":"Glenda Hodge Catering",
    "wof:placetype":"venue"
},
  "geometry": {"coordinates":[-83.33873800000001,42.187548],"type":"Point"}
}