{
  "type": "Feature",
  "properties": {
    "iso:country":"US",
    "sg:address":"7921 Normile St",
    "sg:city":"Dearborn",
    "sg:classifiers":[
        {
            "category":"Building & Trades",
            "subcategory":"Construction",
            "type":"Services"
        }
    ],
    "sg:phone":"+1 313 934 3099",
    "sg:postcode":"48126",
    "sg:province":"MI",
    "sg:tags":[
        "contractor"
    ],
    "wof:name":"Quality One Construction & Development Inc",
    "wof:placetype":"venue"
},
  "geometry": {"coordinates":[-83.158804,42.350983],"type":"Point"}
}