{
  "type": "Feature",
  "properties": {
    "iso:country":"US",
    "sg:address":"2321 E Grand River Ave",
    "sg:city":"Howell",
    "sg:classifiers":[
        {
            "category":"Real Estate",
            "subcategory":"Real Estate Agent",
            "type":"Services"
        }
    ],
    "sg:phone":"+1 517 546 9033",
    "sg:postcode":"48843",
    "sg:province":"MI",
    "wof:name":"Rafferty & Franchi Realty",
    "wof:placetype":"venue"
},
  "geometry": {"coordinates":[-83.90794,42.599214],"type":"Point"}
}