{
  "type": "Feature",
  "properties": {
    "iso:country":"US",
    "sg:address":"13675 Plymouth Rd",
    "sg:city":"Detroit",
    "sg:classifiers":[
        {
            "category":"Real Estate",
            "subcategory":"Real Estate Operator",
            "type":"Services"
        }
    ],
    "sg:phone":"+1 313 933 8755",
    "sg:postcode":"48227",
    "sg:province":"MI",
    "sg:tags":[
        "building",
        "nonresidential"
    ],
    "wof:name":"Cabillac Sons and Supply Co",
    "wof:placetype":"venue"
},
  "geometry": {"coordinates":[-83.181543,42.372897],"type":"Point"}
}