{
  "type": "Feature",
  "properties": {
    "iso:country":"US",
    "sg:address":"3205 Island Hwy",
    "sg:city":"Charlotte",
    "sg:classifiers":[
        {
            "category":"Professional",
            "subcategory":"Management & Consulting",
            "type":"Services"
        }
    ],
    "sg:phone":"+1 517 543 4796",
    "sg:postcode":"48813",
    "sg:province":"MI",
    "sg:tags":[
        "business"
    ],
    "wof:name":"Vib-Tech Maintenance Systems",
    "wof:placetype":"venue"
},
  "geometry": {"coordinates":[-84.77517,42.567678],"type":"Point"}
}