{
  "type": "Feature",
  "properties": {
    "iso:country":"US",
    "sg:address":"15315 State Hwy 46",
    "sg:city":"Casnovia",
    "sg:classifiers":[
        {
            "category":"Shopping",
            "subcategory":"Bicycles & Sporting Goods",
            "type":"Retail Goods"
        }
    ],
    "sg:phone":"+1 616 675 5894",
    "sg:postcode":"49318",
    "sg:province":"MI",
    "wof:name":"Rod W Cattanach Company",
    "wof:placetype":"venue"
},
  "geometry": {"coordinates":[-85.868255,43.23501],"type":"Point"}
}