{
  "type": "Feature",
  "properties": {
    "iso:country":"US",
    "sg:address":"10141 N Finley Lake Ave",
    "sg:city":"Harrison",
    "sg:classifiers":[
        {
            "category":"Bars & Pubs",
            "type":"Food & Drink"
        }
    ],
    "sg:phone":"+1 989 539 9644",
    "sg:postcode":"48625",
    "sg:province":"MI",
    "wof:name":"Riverside Bar",
    "wof:placetype":"venue"
},
  "geometry": {"coordinates":[-84.888711,44.135087],"type":"Point"}
}