{
  "type": "Feature",
  "properties": {
    "iso:country":"US",
    "sg:address":"1045 S Garfield Ave",
    "sg:city":"Traverse City",
    "sg:classifiers":[
        {
            "category":"Shopping",
            "subcategory":"Computers & Home Electronics",
            "type":"Retail Goods"
        }
    ],
    "sg:phone":"+1 231 933 7225",
    "sg:postcode":"49686",
    "sg:province":"MI",
    "sg:tags":[
        "audio"
    ],
    "wof:name":"A Better Sound",
    "wof:placetype":"venue"
},
  "geometry": {"coordinates":[-85.59526200000001,44.748853],"type":"Point"}
}