{
  "type": "Feature",
  "properties": {
    "iso:country":"US",
    "sg:address":"251 Cass St",
    "sg:city":"Niles",
    "sg:classifiers":[
        {
            "category":"Government",
            "subcategory":"Office",
            "type":"Public Place"
        }
    ],
    "sg:phone":"+1 269 683 2783",
    "sg:postcode":"49120",
    "sg:province":"MI",
    "sg:tags":[
        "executive"
    ],
    "wof:name":"Niles Housing Commission",
    "wof:placetype":"venue"
},
  "geometry": {"coordinates":[-86.256602,41.832774],"type":"Point"}
}