{
  "type": "Feature",
  "properties": {
    "iso:country":"US",
    "sg:address":"720 Shoppers Ln",
    "sg:city":"Kalamazoo",
    "sg:classifiers":[
        {
            "category":"Personal",
            "subcategory":"Beauty Salon",
            "type":"Services"
        }
    ],
    "sg:phone":"+1 269 349 8015",
    "sg:postcode":"49004",
    "sg:province":"MI",
    "sg:tags":[
        "shop"
    ],
    "wof:name":"Profiles Hair Design Center",
    "wof:placetype":"venue"
},
  "geometry": {"coordinates":[-85.57125600000001,42.320299],"type":"Point"}
}