{
  "type": "Feature",
  "properties": {
    "iso:country":"US",
    "sg:address":"21 E Burdick St",
    "sg:city":"Oxford",
    "sg:classifiers":[
        {
            "category":"Organizations",
            "subcategory":"Religious Organization",
            "type":"Services"
        }
    ],
    "sg:phone":"+1 248 628 1289",
    "sg:postcode":"48371",
    "sg:province":"MI",
    "sg:tags":[
        "church"
    ],
    "sg:website":"www.oumc.homestead.com",
    "wof:name":"Oxford United Methodist Church",
    "wof:placetype":"venue"
},
  "geometry": {"coordinates":[-83.262944,42.824883],"type":"Point"}
}