{
  "type": "Feature",
  "properties": {
    "iso:country":"US",
    "sg:address":"6436 N Burkhart Rd",
    "sg:city":"Howell",
    "sg:phone":"+1 517 546 2588",
    "sg:postcode":"48855",
    "sg:province":"MI",
    "sg:tags":[
        "farm",
        "corn"
    ],
    "wof:name":"Andrew Jackson",
    "wof:placetype":"venue"
},
  "geometry": {"coordinates":[-83.99644000000001,42.690943],"type":"Point"}
}