{
  "type": "Feature",
  "properties": {
    "iso:country":"US",
    "sg:address":"12753 Grafton Rd",
    "sg:city":"Carleton",
    "sg:classifiers":[
        {
            "category":"Retail",
            "subcategory":"Portrait Studio",
            "type":"Services"
        }
    ],
    "sg:phone":"+1 734 654 4500",
    "sg:postcode":"48117",
    "sg:province":"MI",
    "sg:tags":[
        "photo"
    ],
    "wof:name":"Cobblestone Studio",
    "wof:placetype":"venue"
},
  "geometry": {"coordinates":[-83.380297,42.059992],"type":"Point"}
}