{
  "type": "Feature",
  "properties": {
    "iso:country":"US",
    "sg:address":"817 Clinton Ave",
    "sg:city":"St Clair",
    "sg:classifiers":[
        {
            "category":"Professional",
            "subcategory":"Accounting & Tax Preparation",
            "type":"Services"
        }
    ],
    "sg:phone":"+1 810 329 8884",
    "sg:postcode":"48079",
    "sg:province":"MI",
    "sg:tags":[
        "bookkeeping",
        "general"
    ],
    "wof:name":"Meredith Financial Research",
    "wof:placetype":"venue"
},
  "geometry": {"coordinates":[-82.493655,42.821599],"type":"Point"}
}