{
  "type": "Feature",
  "properties": {
    "iso:country":"US",
    "sg:address":"6634 Roger Dr",
    "sg:city":"Jenison",
    "sg:classifiers":[
        {
            "category":"Wholesale",
            "subcategory":"Machinery & Supplies",
            "type":"Manufacturing & Wholesale Goods"
        }
    ],
    "sg:phone":"+1 616 669 2210",
    "sg:postcode":"49428",
    "sg:province":"MI",
    "sg:tags":[
        "equipment",
        "irrigation",
        "system"
    ],
    "sg:website":"www.schepers.com",
    "wof:name":"Schepers Lawn Sprinkling Inc",
    "wof:placetype":"venue"
},
  "geometry": {"coordinates":[-85.83910299999999,42.889998],"type":"Point"}
}