{
  "type": "Feature",
  "properties": {
    "iso:country":"US",
    "sg:address":"815 Lake George Trl",
    "sg:city":"Traverse City",
    "sg:classifiers":[
        {
            "category":"Building & Trades",
            "subcategory":"Construction",
            "type":"Services"
        }
    ],
    "sg:phone":"+1 231 947 5272",
    "sg:postcode":"49686",
    "sg:province":"MI",
    "sg:tags":[
        "contractor"
    ],
    "wof:name":"Dan Tile Man",
    "wof:placetype":"venue"
},
  "geometry": {"coordinates":[-85.5013,44.672343],"type":"Point"}
}