{
  "type": "Feature",
  "properties": {
    "iso:country":"US",
    "sg:address":"15570 Joy Rd",
    "sg:city":"Detroit",
    "sg:classifiers":[
        {
            "category":"Real Estate",
            "subcategory":"Real Estate Services",
            "type":"Services"
        },
        {
            "category":"Banks & Credit Unions",
            "subcategory":"Bank",
            "type":"Services"
        }
    ],
    "sg:phone":"+1 313 581 8778",
    "sg:postcode":"48228",
    "sg:province":"MI",
    "sg:tags":[
        "commercial",
        "loan",
        "saving"
    ],
    "sg:website":"http://www.charteronebank.com",
    "wof:name":"Charter One Bank",
    "wof:placetype":"venue"
},
  "geometry": {"coordinates":[-83.197857,42.358132],"type":"Point"}
}