{
  "type": "Feature",
  "properties": {
    "iso:country":"US",
    "sg:address":"17888 Farmington Rd",
    "sg:city":"Livonia",
    "sg:classifiers":[
        {
            "category":"Health Services",
            "subcategory":"Doctor",
            "type":"Services"
        }
    ],
    "sg:phone":"+1 734 458 4778",
    "sg:postcode":"48152",
    "sg:province":"MI",
    "sg:tags":[
        "medical"
    ],
    "wof:name":"Tata Zakari Physician",
    "wof:placetype":"venue"
},
  "geometry": {"coordinates":[-83.374495,42.417487],"type":"Point"}
}