{
  "type": "Feature",
  "properties": {
    "iso:country":"US",
    "sg:address":"18900 Michigan Ave Ste H304",
    "sg:city":"Dearborn",
    "sg:classifiers":[
        {
            "category":"Personal",
            "subcategory":"Tattoo Parlor",
            "type":"Services"
        }
    ],
    "sg:phone":"+1 313 271 4966",
    "sg:postcode":"48126",
    "sg:province":"MI",
    "sg:website":"www.hottopic.com",
    "wof:name":"Hot Topic Inc",
    "wof:placetype":"venue"
},
  "geometry": {"coordinates":[-83.221987,42.30981],"type":"Point"}
}