{
  "type": "Feature",
  "properties": {
    "iso:country":"US",
    "sg:address":"516 Western Ave",
    "sg:city":"Benton Harbor",
    "sg:classifiers":[
        {
            "category":"Local Transit",
            "type":"Transportation"
        }
    ],
    "sg:phone":"+1 269 925 8444",
    "sg:postcode":"49022",
    "sg:province":"MI",
    "sg:tags":[
        "limousine"
    ],
    "wof:name":"S & S Royale Limousine Svc",
    "wof:placetype":"venue"
},
  "geometry": {"coordinates":[-86.467676,42.091744],"type":"Point"}
}