{
  "type": "Feature",
  "properties": {
    "iso:country":"US",
    "sg:address":"1254 Woodbridge St",
    "sg:city":"St Clair Shores",
    "sg:classifiers":[
        {
            "category":"Real Estate",
            "subcategory":"Real Estate Agent",
            "type":"Services"
        }
    ],
    "sg:phone":"+1 586 777 3327",
    "sg:postcode":"48080",
    "sg:province":"MI",
    "wof:name":"Cape Cod Realty",
    "wof:placetype":"venue"
},
  "geometry": {"coordinates":[-82.92478199999999,42.455045],"type":"Point"}
}