{
  "type": "Feature",
  "properties": {
    "iso:country":"US",
    "sg:address":"2435 Pipestone Rd",
    "sg:city":"Benton Harbor",
    "sg:classifiers":[
        {
            "category":"Shopping",
            "subcategory":"Gifts & Souvenirs",
            "type":"Retail Goods"
        }
    ],
    "sg:phone":"+1 269 927 0076",
    "sg:postcode":"49022",
    "sg:province":"MI",
    "sg:tags":[
        "party",
        "supply"
    ],
    "wof:name":"Gordon Food Svc",
    "wof:placetype":"venue"
},
  "geometry": {"coordinates":[-86.416982,42.077729],"type":"Point"}
}