{
  "type": "Feature",
  "properties": {
    "iso:country":"US",
    "sg:address":"14450 Hall Rd",
    "sg:city":"Sterling Heights",
    "sg:classifiers":[
        {
            "category":"Community Center",
            "type":"Public Place"
        }
    ],
    "sg:phone":"+1 586 247 6918",
    "sg:postcode":"48313",
    "sg:province":"MI",
    "sg:tags":[
        "medical"
    ],
    "wof:name":"Henry Ford Medical Centers",
    "wof:placetype":"venue"
},
  "geometry": {"coordinates":[-82.982597,42.626801],"type":"Point"}
}