{
  "type": "Feature",
  "properties": {
    "iso:country":"US",
    "sg:address":"4968 N Otter Creek Rd",
    "sg:city":"La Salle",
    "sg:classifiers":[
        {
            "category":"Retail",
            "subcategory":"Repair Shop",
            "type":"Services"
        }
    ],
    "sg:phone":"+1 734 242 2930",
    "sg:postcode":"48145",
    "sg:province":"MI",
    "sg:tags":[
        "taxicab"
    ],
    "wof:name":"Matthews Taxidermy",
    "wof:placetype":"venue"
},
  "geometry": {"coordinates":[-83.41866899999999,41.846824],"type":"Point"}
}