{
  "type": "Feature",
  "properties": {
    "iso:country":"US",
    "sg:address":"31 W Meyers Ave",
    "sg:city":"Hazel Park",
    "sg:classifiers":[
        {
            "category":"Freight",
            "type":"Transportation"
        }
    ],
    "sg:phone":"+1 248 548 0125",
    "sg:postcode":"48030",
    "sg:province":"MI",
    "sg:tags":[
        "mover"
    ],
    "wof:name":"Independent Moving & Storage",
    "wof:placetype":"venue"
},
  "geometry": {"coordinates":[-83.10658100000001,42.454463],"type":"Point"}
}