{
  "type": "Feature",
  "properties": {
    "iso:country":"US",
    "sg:address":"10991 Robbins Rd",
    "sg:city":"Springport",
    "sg:classifiers":[
        {
            "category":"Freight",
            "type":"Transportation"
        }
    ],
    "sg:phone":"+1 517 857 3551",
    "sg:postcode":"49284",
    "sg:province":"MI",
    "sg:tags":[
        "delivery"
    ],
    "wof:name":"First Class Delivery",
    "wof:placetype":"venue"
},
  "geometry": {"coordinates":[-84.634918,42.388242],"type":"Point"}
}