{
  "type": "Feature",
  "properties": {
    "iso:country":"US",
    "sg:address":"5589 US Hwy 23",
    "sg:city":"Oscoda",
    "sg:classifiers":[
        {
            "category":"Organizations",
            "subcategory":"Religious Organization",
            "type":"Services"
        }
    ],
    "sg:phone":"+1 989 739 5441",
    "sg:postcode":"48750",
    "sg:province":"MI",
    "wof:name":"Oscoda Baptist Church",
    "wof:placetype":"venue"
},
  "geometry": {"coordinates":[-83.330179,44.443075],"type":"Point"}
}