{
  "type": "Feature",
  "properties": {
    "iso:country":"US",
    "sg:address":"3347 Beecher Rd",
    "sg:city":"Flint",
    "sg:classifiers":[
        {
            "category":"Real Estate",
            "subcategory":"Real Estate Operator",
            "type":"Services"
        }
    ],
    "sg:phone":"+1 810 733 6352",
    "sg:postcode":"48532",
    "sg:province":"MI",
    "sg:tags":[
        "condominium"
    ],
    "sg:website":"www.cummingsmanagement.com",
    "wof:name":"Cummings Realty",
    "wof:placetype":"venue"
},
  "geometry": {"coordinates":[-83.74433999999999,43.016114],"type":"Point"}
}