{
  "type": "Feature",
  "properties": {
    "iso:country":"US",
    "sg:address":"3585 64th Ave",
    "sg:city":"Zeeland",
    "sg:classifiers":[
        {
            "category":"Farming",
            "subcategory":"Livestock Farm",
            "type":"Manufacturing & Wholesale Goods"
        }
    ],
    "sg:phone":"+1 616 772 4795",
    "sg:postcode":"49464",
    "sg:province":"MI",
    "sg:tags":[
        "beef",
        "feedlot",
        "cattle"
    ],
    "wof:name":"Cal Verbeek",
    "wof:placetype":"venue"
},
  "geometry": {"coordinates":[-85.940101,42.83673],"type":"Point"}
}