{
  "type": "Feature",
  "properties": {
    "iso:country":"US",
    "sg:address":"169 E Division St",
    "sg:city":"Sparta",
    "sg:classifiers":[
        {
            "category":"Professional",
            "subcategory":"Secretarial Services",
            "type":"Services"
        }
    ],
    "sg:phone":"+1 616 887 1111",
    "sg:postcode":"49345",
    "sg:province":"MI",
    "sg:tags":[
        "reporting",
        "court"
    ],
    "wof:name":"Potes Secretarial & Word",
    "wof:placetype":"venue"
},
  "geometry": {"coordinates":[-85.705962,43.160739],"type":"Point"}
}