{
  "type": "Feature",
  "properties": {
    "iso:country":"US",
    "sg:address":"1254 Northover Dr",
    "sg:city":"Bloomfield Hills",
    "sg:classifiers":[
        {
            "category":"Professional",
            "subcategory":"Lawyer & Legal Services",
            "type":"Services"
        }
    ],
    "sg:phone":"+1 248 644 3793",
    "sg:postcode":"48304",
    "sg:province":"MI",
    "sg:tags":[
        "attorney"
    ],
    "wof:name":"William Soloy",
    "wof:placetype":"venue"
},
  "geometry": {"coordinates":[-83.208703,42.594436],"type":"Point"}
}