{
  "type": "Feature",
  "properties": {
    "iso:country":"US",
    "sg:address":"11010 Whittier St",
    "sg:city":"Detroit",
    "sg:classifiers":[
        {
            "category":"Home & Garden",
            "subcategory":"Home Furnishings",
            "type":"Retail Goods"
        },
        {
            "category":"Manufacturing",
            "subcategory":"Glass & Minerals",
            "type":"Manufacturing & Wholesale Goods"
        },
        {
            "category":"Manufacturing",
            "subcategory":"Apparel",
            "type":"Manufacturing & Wholesale Goods"
        },
        {
            "category":"Building & Trades",
            "subcategory":"Construction",
            "type":"Services"
        }
    ],
    "sg:phone":"+1 313 371 0049",
    "sg:postcode":"48224",
    "sg:province":"MI",
    "sg:tags":[
        "plate",
        "installation",
        "repair",
        "windows-repair",
        "glass-auto",
        "window",
        "mirror",
        "glass-broken",
        "replacement"
    ],
    "wof:name":"D & S Glass & Doors",
    "wof:placetype":"venue"
},
  "geometry": {"coordinates":[-82.956028,42.41817],"type":"Point"}
}