{
  "type": "Feature",
  "properties": {
    "iso:country":"US",
    "sg:address":"4900 Stanton Blvd",
    "sg:city":"Montague",
    "sg:classifiers":[
        {
            "category":"Education",
            "subcategory":"School",
            "type":"Public Place"
        }
    ],
    "sg:phone":"+1 231 893 1515",
    "sg:postcode":"49437",
    "sg:province":"MI",
    "wof:name":"Montague Area Public Schl Sys",
    "wof:placetype":"venue"
},
  "geometry": {"coordinates":[-86.365993,43.422343],"type":"Point"}
}