{
  "type": "Feature",
  "properties": {
    "iso:country":"US",
    "sg:address":"9210 E 13th St",
    "sg:city":"Cadillac",
    "sg:classifiers":[
        {
            "category":"Freight",
            "type":"Transportation"
        }
    ],
    "sg:phone":"+1 231 775 7840",
    "sg:postcode":"49601",
    "sg:province":"MI",
    "sg:tags":[
        "commercial",
        "storage"
    ],
    "wof:name":"Cadillac Climate Controlled",
    "wof:placetype":"venue"
},
  "geometry": {"coordinates":[-85.392447,44.266878],"type":"Point"}
}