{
  "type": "Feature",
  "properties": {
    "iso:country":"US",
    "sg:address":"5466 E Saint Charles Rd",
    "sg:city":"Ithaca",
    "sg:classifiers":[
        {
            "category":"Building & Trades",
            "subcategory":"Pest Control",
            "type":"Services"
        }
    ],
    "sg:phone":"+1 989 875 6848",
    "sg:postcode":"48847",
    "sg:province":"MI",
    "wof:name":"Diamond Pest Control",
    "wof:placetype":"venue"
},
  "geometry": {"coordinates":[-84.498876,43.306139],"type":"Point"}
}