{
  "type": "Feature",
  "properties": {
    "iso:country":"US",
    "sg:address":"2174 Winding Way Dr",
    "sg:city":"Davison",
    "sg:classifiers":[
        {
            "category":"Retail",
            "subcategory":"Veterinary Services",
            "type":"Services"
        }
    ],
    "sg:phone":"+1 810 653 5386",
    "sg:postcode":"48423",
    "sg:province":"MI",
    "sg:tags":[
        "veterinarian"
    ],
    "wof:name":"Borg Larry A DVM",
    "wof:placetype":"venue"
},
  "geometry": {"coordinates":[-83.545068,43.03847],"type":"Point"}
}