{
  "type": "Feature",
  "properties": {
    "iso:country":"US",
    "sg:address":"152 E Front St",
    "sg:city":"Adrian",
    "sg:classifiers":[
        {
            "category":"Professional",
            "subcategory":"Lawyer & Legal Services",
            "type":"Services"
        }
    ],
    "sg:phone":"+1 517 265 6363",
    "sg:postcode":"49221",
    "sg:province":"MI",
    "wof:name":"James W Daly Attorney",
    "wof:placetype":"venue"
},
  "geometry": {"coordinates":[-84.033918,41.901055],"type":"Point"}
}