{
  "type": "Feature",
  "properties": {
    "iso:country":"US",
    "sg:address":"27286 Novi Rd",
    "sg:city":"Novi",
    "sg:classifiers":[
        {
            "category":"Restaurant",
            "type":"Food & Drink"
        }
    ],
    "sg:menulink":"http://www.allmenus.com/mi/novi/236281-surf-city-squeeze/menu/",
    "sg:phone":"+1 248 735 8866",
    "sg:postcode":"48377",
    "sg:province":"MI",
    "sg:tags":[
        "smoothy",
        "juice",
        "american"
    ],
    "wof:name":"Surf City Squeeze",
    "wof:placetype":"venue"
},
  "geometry": {"coordinates":[-83.475953,42.489415],"type":"Point"}
}