{
  "type": "Feature",
  "properties": {
    "iso:country":"US",
    "sg:address":"4102 S Westnedge Ave",
    "sg:city":"Kalamazoo",
    "sg:classifiers":[
        {
            "category":"Insurance",
            "subcategory":"Insurance Agent",
            "type":"Services"
        }
    ],
    "sg:phone":"+1 269 384 5779",
    "sg:postcode":"49008",
    "sg:province":"MI",
    "wof:name":"A AA Royer Agency",
    "wof:placetype":"venue"
},
  "geometry": {"coordinates":[-85.589743,42.249583],"type":"Point"}
}