{
  "type": "Feature",
  "properties": {
    "iso:country":"US",
    "sg:address":"42200 Grand River Ave",
    "sg:city":"Novi",
    "sg:classifiers":[
        {
            "category":"Shopping",
            "subcategory":"Jewelry",
            "type":"Retail Goods"
        }
    ],
    "sg:phone":"+1 248 344 2551",
    "sg:postcode":"48375",
    "sg:province":"MI",
    "sg:tags":[
        "clocks"
    ],
    "wof:name":"Thomasville Home Furnishings",
    "wof:placetype":"venue"
},
  "geometry": {"coordinates":[-83.459102,42.476933],"type":"Point"}
}