{
  "type": "Feature",
  "properties": {
    "iso:country":"US",
    "sg:address":"8110 56th Ave",
    "sg:city":"Hudsonville",
    "sg:classifiers":[
        {
            "category":"Professional",
            "subcategory":"Art Services",
            "type":"Services"
        }
    ],
    "sg:phone":"+1 616 669 5069",
    "sg:postcode":"49426",
    "sg:province":"MI",
    "sg:tags":[
        "commercial",
        "design"
    ],
    "wof:name":"Collectibles Signs & Dezigns",
    "wof:placetype":"venue"
},
  "geometry": {"coordinates":[-85.922174,42.916653],"type":"Point"}
}