{
  "type": "Feature",
  "properties": {
    "iso:country":"US",
    "sg:address":"6223 Bluff Ave",
    "sg:city":"Ludington",
    "sg:classifiers":[
        {
            "category":"Building & Trades",
            "subcategory":"Construction",
            "type":"Services"
        }
    ],
    "sg:phone":"+1 231 843 8441",
    "sg:postcode":"49431",
    "sg:province":"MI",
    "sg:tags":[
        "house"
    ],
    "wof:name":"T C B Builders",
    "wof:placetype":"venue"
},
  "geometry": {"coordinates":[-86.439263,44.067433],"type":"Point"}
}