{
  "type": "Feature",
  "properties": {
    "iso:country":"US",
    "sg:address":"9003 90th Ave",
    "sg:city":"Mecosta",
    "sg:classifiers":[
        {
            "category":"Travel",
            "subcategory":"Campground",
            "type":"Entertainment"
        }
    ],
    "sg:phone":"+1 231 972 7450",
    "sg:postcode":"49332",
    "sg:province":"MI",
    "wof:name":"Mecosta County School Section",
    "wof:placetype":"venue"
},
  "geometry": {"coordinates":[-85.264948,43.599868],"type":"Point"}
}