{
  "type": "Feature",
  "properties": {
    "iso:country":"US",
    "sg:address":"2317 E Caro Rd",
    "sg:city":"Caro",
    "sg:classifiers":[
        {
            "category":"Social Services",
            "subcategory":"Child Care",
            "type":"Services"
        }
    ],
    "sg:phone":"+1 989 673 5774",
    "sg:postcode":"48723",
    "sg:province":"MI",
    "sg:tags":[
        "day"
    ],
    "wof:name":"Kristie Lee Hutchison",
    "wof:placetype":"venue"
},
  "geometry": {"coordinates":[-83.3359,43.542381],"type":"Point"}
}