{
  "type": "Feature",
  "properties": {
    "iso:country":"US",
    "sg:address":"209 E Grand River Ave",
    "sg:city":"Howell",
    "sg:classifiers":[
        {
            "category":"Restaurant",
            "type":"Food & Drink"
        }
    ],
    "sg:phone":"+1 517 548 7500",
    "sg:postcode":"48843",
    "sg:province":"MI",
    "wof:name":"Diamond's Taverns",
    "wof:placetype":"venue"
},
  "geometry": {"coordinates":[-83.928933,42.606825],"type":"Point"}
}