{
  "type": "Feature",
  "properties": {
    "iso:country":"US",
    "sg:address":"6400 Main St",
    "sg:city":"Cass City",
    "sg:classifiers":[
        {
            "category":"Retail",
            "subcategory":"Laundry & Dry Cleaning",
            "type":"Services"
        }
    ],
    "sg:phone":"+1 989 872 9903",
    "sg:postcode":"48726",
    "sg:province":"MI",
    "sg:tags":[
        "commercial",
        "power",
        "family"
    ],
    "wof:name":"Wash King Laundry",
    "wof:placetype":"venue"
},
  "geometry": {"coordinates":[-83.17586300000001,43.600859],"type":"Point"}
}