{
  "type": "Feature",
  "properties": {
    "iso:country":"US",
    "sg:address":"28595 Orchard Lake Rd",
    "sg:city":"Farmington Hills",
    "sg:classifiers":[
        {
            "category":"Health Services",
            "subcategory":"Health Practitioner",
            "type":"Services"
        }
    ],
    "sg:phone":"+1 248 324 0777",
    "sg:postcode":"48334",
    "sg:province":"MI",
    "sg:tags":[
        "acupuncture"
    ],
    "wof:name":"Center For Complimentary Med",
    "wof:placetype":"venue"
},
  "geometry": {"coordinates":[-83.359094,42.507041],"type":"Point"}
}