{
  "type": "Feature",
  "properties": {
    "iso:country":"US",
    "sg:address":"1500 Union Ave SE",
    "sg:city":"Grand Rapids",
    "sg:classifiers":[
        {
            "category":"Manufacturing",
            "subcategory":"Tools & Machinery",
            "type":"Manufacturing & Wholesale Goods"
        }
    ],
    "sg:phone":"+1 616 243 3633",
    "sg:postcode":"49507",
    "sg:province":"MI",
    "sg:tags":[
        "machine",
        "vending"
    ],
    "sg:website":"www.roweinternational.com",
    "wof:name":"Rowe International Corp",
    "wof:placetype":"venue"
},
  "geometry": {"coordinates":[-85.65366899999999,42.935527],"type":"Point"}
}