{
  "type": "Feature",
  "properties": {
    "iso:country":"US",
    "sg:address":"22465 S O J Miller Rd",
    "sg:city":"Trout Lake",
    "sg:classifiers":[
        {
            "category":"Travel",
            "subcategory":"Hotels & Motels",
            "type":"Entertainment"
        }
    ],
    "sg:phone":"+1 906 569 3810",
    "sg:postcode":"49793",
    "sg:province":"MI",
    "sg:tags":[
        "resort"
    ],
    "wof:name":"Trout Lake Resort",
    "wof:placetype":"venue"
},
  "geometry": {"coordinates":[-85.055109,46.183804],"type":"Point"}
}