{
  "type": "Feature",
  "properties": {
    "iso:country":"US",
    "sg:address":"3320 Hickory Dr",
    "sg:city":"Lake Orion",
    "sg:classifiers":[
        {
            "category":"Organizations",
            "subcategory":"Community Association",
            "type":"Services"
        }
    ],
    "sg:phone":"+1 248 393 2888",
    "sg:postcode":"48359",
    "sg:province":"MI",
    "wof:name":"Motown Muscle Inc",
    "wof:placetype":"venue"
},
  "geometry": {"coordinates":[-83.290842,42.730255],"type":"Point"}
}