{
  "type": "Feature",
  "properties": {
    "iso:country":"US",
    "sg:address":"11221 Pickerel Lake Rd",
    "sg:city":"Petoskey",
    "sg:classifiers":[
        {
            "category":"Building & Trades",
            "subcategory":"Construction",
            "type":"Services"
        }
    ],
    "sg:phone":"+1 231 348 8208",
    "sg:postcode":"49770",
    "sg:province":"MI",
    "sg:tags":[
        "contractor"
    ],
    "wof:name":"Robert K Brill",
    "wof:placetype":"venue"
},
  "geometry": {"coordinates":[-84.75490499999999,45.376651],"type":"Point"}
}