{
  "type": "Feature",
  "properties": {
    "iso:country":"US",
    "sg:address":"222 S Norton St",
    "sg:city":"Corunna",
    "sg:classifiers":[
        {
            "category":"Wholesale",
            "subcategory":"Non-durable Goods",
            "type":"Manufacturing & Wholesale Goods"
        }
    ],
    "sg:phone":"+1 989 743 5513",
    "sg:postcode":"48817",
    "sg:province":"MI",
    "sg:tags":[
        "retail",
        "novelty"
    ],
    "wof:name":"Deans Treasures",
    "wof:placetype":"venue"
},
  "geometry": {"coordinates":[-84.12342599999999,42.978616],"type":"Point"}
}