{
  "type": "Feature",
  "properties": {
    "iso:country":"US",
    "sg:address":"7650 Chrysler Dr",
    "sg:city":"Detroit",
    "sg:classifiers":[
        {
            "category":"Professional",
            "subcategory":"Advertising",
            "type":"Services"
        }
    ],
    "sg:phone":"+1 313 872 2020",
    "sg:postcode":"48211",
    "sg:province":"MI",
    "sg:tags":[
        "mail",
        "direct"
    ],
    "wof:name":"Mail Shop",
    "wof:placetype":"venue"
},
  "geometry": {"coordinates":[-83.0608,42.376031],"type":"Point"}
}