{
  "type": "Feature",
  "properties": {
    "iso:country":"US",
    "sg:address":"13109 W 8 Mile Rd",
    "sg:city":"Detroit",
    "sg:classifiers":[
        {
            "category":"Bars & Pubs",
            "subcategory":"Nightclub",
            "type":"Food & Drink"
        }
    ],
    "sg:phone":"+1 313 863 3444",
    "sg:postcode":"48235",
    "sg:province":"MI",
    "sg:tags":[
        "nightlife"
    ],
    "wof:name":"Hot Tamales Inc",
    "wof:placetype":"venue"
},
  "geometry": {"coordinates":[-83.175797,42.445202],"type":"Point"}
}