{
  "type": "Feature",
  "properties": {
    "iso:country":"US",
    "sg:address":"1032 S Kalamazoo Ave",
    "sg:city":"Marshall",
    "sg:classifiers":[
        {
            "category":"Building & Trades",
            "subcategory":"Construction",
            "type":"Services"
        }
    ],
    "sg:phone":"+1 269 781 8326",
    "sg:postcode":"49068",
    "sg:province":"MI",
    "sg:tags":[
        "house"
    ],
    "wof:name":"Pierce & Co",
    "wof:placetype":"venue"
},
  "geometry": {"coordinates":[-84.964022,42.259845],"type":"Point"}
}