{
  "type": "Feature",
  "properties": {
    "iso:country":"US",
    "sg:address":"10346 N Whitefish Point Rd",
    "sg:city":"Paradise",
    "sg:classifiers":[
        {
            "category":"Travel",
            "subcategory":"Hotels & Motels",
            "type":"Entertainment"
        }
    ],
    "sg:phone":"+1 906 492 3266",
    "sg:postcode":"49768",
    "sg:province":"MI",
    "sg:tags":[
        "operation"
    ],
    "wof:name":"Freighters View On Bay",
    "wof:placetype":"venue"
},
  "geometry": {"coordinates":[-85.03144899999999,46.656746],"type":"Point"}
}