{
  "type": "Feature",
  "properties": {
    "iso:country":"US",
    "sg:address":"18000 Vernier Rd Ste 765",
    "sg:city":"Detroit",
    "sg:classifiers":[
        {
            "category":"Shopping",
            "subcategory":"Optician",
            "type":"Retail Goods"
        }
    ],
    "sg:phone":"+1 313 371 6930",
    "sg:postcode":"48225",
    "sg:province":"MI",
    "sg:tags":[
        "eyewear"
    ],
    "sg:website":"www.lenscrafters.com",
    "wof:name":"Lenscrafters",
    "wof:placetype":"venue"
},
  "geometry": {"coordinates":[-82.934197,42.449746],"type":"Point"}
}