{
  "type": "Feature",
  "properties": {
    "iso:country":"US",
    "sg:address":"3497 W Auburn Rd",
    "sg:city":"Rochester Hills",
    "sg:classifiers":[
        {
            "category":"Banks & Credit Unions",
            "subcategory":"Investment Brokerage",
            "type":"Services"
        }
    ],
    "sg:phone":"+1 248 299 4100",
    "sg:postcode":"48309",
    "sg:province":"MI",
    "sg:tags":[
        "retirement",
        "planning"
    ],
    "wof:name":"Benefit Advantage",
    "wof:placetype":"venue"
},
  "geometry": {"coordinates":[-83.20010600000001,42.634216],"type":"Point"}
}