{
  "type": "Feature",
  "properties": {
    "iso:country":"US",
    "sg:address":"2431 Pontiac Rd",
    "sg:city":"Auburn Hills",
    "sg:classifiers":[
        {
            "category":"Manufacturing",
            "subcategory":"Chemicals & Compounds",
            "type":"Manufacturing & Wholesale Goods"
        }
    ],
    "sg:phone":"+1 248 475 9256",
    "sg:postcode":"48326",
    "sg:province":"MI",
    "sg:tags":[
        "plastic"
    ],
    "wof:name":"Guardian Sales",
    "wof:placetype":"venue"
},
  "geometry": {"coordinates":[-83.241079,42.670947],"type":"Point"}
}