{
  "type": "Feature",
  "properties": {
    "iso:country":"US",
    "sg:address":"5721 Jeanne Marie Dr",
    "sg:city":"White Lake",
    "sg:classifiers":[
        {
            "category":"Professional",
            "subcategory":"Management & Consulting",
            "type":"Services"
        }
    ],
    "sg:phone":"+1 248 889 8748",
    "sg:postcode":"48383",
    "sg:province":"MI",
    "wof:name":"Cast International",
    "wof:placetype":"venue"
},
  "geometry": {"coordinates":[-83.54321400000001,42.69013],"type":"Point"}
}