{
  "type": "Feature",
  "properties": {
    "iso:country":"US",
    "sg:address":"14 S Church St",
    "sg:city":"Zeeland",
    "sg:classifiers":[
        {
            "category":"Professional",
            "subcategory":"Business Services",
            "type":"Services"
        },
        {
            "category":"Personal",
            "type":"Services"
        }
    ],
    "sg:phone":"+1 616 772 0879",
    "sg:postcode":"49464",
    "sg:province":"MI",
    "sg:tags":[
        "conference",
        "center"
    ],
    "wof:name":"Howard Miller Community Center",
    "wof:placetype":"venue"
},
  "geometry": {"coordinates":[-86.014093,42.812035],"type":"Point"}
}