{
  "type": "Feature",
  "properties": {
    "iso:country":"US",
    "sg:address":"1433 43rd St SW",
    "sg:city":"Grand Rapids",
    "sg:classifiers":[
        {
            "category":"Professional",
            "subcategory":"Business Services",
            "type":"Services"
        }
    ],
    "sg:phone":"+1 616 617 2764",
    "sg:postcode":"49509",
    "sg:province":"MI",
    "wof:name":"Sales Support Group LLC",
    "wof:placetype":"venue"
},
  "geometry": {"coordinates":[-85.704444,42.885802],"type":"Point"}
}