{
  "type": "Feature",
  "properties": {
    "iso:country":"US",
    "sg:address":"1175 W Kinsel Hwy",
    "sg:city":"Charlotte",
    "sg:classifiers":[
        {
            "category":"Building & Trades",
            "subcategory":"Construction",
            "type":"Services"
        }
    ],
    "sg:phone":"+1 517 543 9055",
    "sg:postcode":"48813",
    "sg:province":"MI",
    "sg:tags":[
        "home",
        "carpentry",
        "improvement",
        "contractor"
    ],
    "wof:name":"K & M Carpentry Inc",
    "wof:placetype":"venue"
},
  "geometry": {"coordinates":[-84.85950099999999,42.596977],"type":"Point"}
}