{
  "type": "Feature",
  "properties": {
    "iso:country":"US",
    "sg:address":"3975 Linden Ave SE",
    "sg:city":"Grand Rapids",
    "sg:classifiers":[
        {
            "category":"Retail",
            "subcategory":"Repair Shop",
            "type":"Services"
        }
    ],
    "sg:phone":"+1 616 534 2774",
    "sg:postcode":"49548",
    "sg:province":"MI",
    "sg:tags":[
        "welding"
    ],
    "wof:name":"Yonker Welding Svc",
    "wof:placetype":"venue"
},
  "geometry": {"coordinates":[-85.648618,42.893987],"type":"Point"}
}