{
  "type": "Feature",
  "properties": {
    "iso:country":"US",
    "sg:address":"31500 Telegraph Rd",
    "sg:city":"Bingham Farms",
    "sg:classifiers":[
        {
            "category":"Health Services",
            "subcategory":"Doctor",
            "type":"Services"
        }
    ],
    "sg:phone":"+1 248 723 5880",
    "sg:postcode":"48025",
    "sg:province":"MI",
    "wof:name":"Rubin Steve MD",
    "wof:placetype":"venue"
},
  "geometry": {"coordinates":[-83.285454,42.518765],"type":"Point"}
}