{
  "type": "Feature",
  "properties": {
    "iso:country":"US",
    "sg:address":"2710 Pineridge Dr NW",
    "sg:city":"Grand Rapids",
    "sg:classifiers":[
        {
            "category":"Professional",
            "subcategory":"Art Services",
            "type":"Services"
        }
    ],
    "sg:phone":"+1 616 791 4393",
    "sg:postcode":"49534",
    "sg:province":"MI",
    "sg:tags":[
        "wood",
        "reproduction"
    ],
    "wof:name":"Ftr & Associates",
    "wof:placetype":"venue"
},
  "geometry": {"coordinates":[-85.777508,43.013493],"type":"Point"}
}