{
  "type": "Feature",
  "properties": {
    "iso:country":"US",
    "sg:address":"19322 Wyoming St",
    "sg:city":"Detroit",
    "sg:classifiers":[
        {
            "category":"Social Services",
            "subcategory":"Child Care",
            "type":"Services"
        }
    ],
    "sg:phone":"+1 313 862 1331",
    "sg:postcode":"48221",
    "sg:province":"MI",
    "sg:tags":[
        "day"
    ],
    "wof:name":"Little Village Day Care Center",
    "wof:placetype":"venue"
},
  "geometry": {"coordinates":[-83.16089599999999,42.4333],"type":"Point"}
}