{
  "type": "Feature",
  "properties": {
    "iso:country":"US",
    "sg:address":"1710 Dorn Dr",
    "sg:city":"Leonard",
    "sg:classifiers":[
        {
            "category":"Education",
            "subcategory":"Special Training",
            "type":"Public Place"
        }
    ],
    "sg:phone":"+1 248 628 6879",
    "sg:postcode":"48367",
    "sg:province":"MI",
    "wof:name":"Educate ME",
    "wof:placetype":"venue"
},
  "geometry": {"coordinates":[-83.1058,42.849061],"type":"Point"}
}