{
  "type": "Feature",
  "properties": {
    "iso:country":"US",
    "sg:address":"4910 Eastern Ave SE",
    "sg:city":"Grand Rapids",
    "sg:classifiers":[
        {
            "category":"Sports & Exercise",
            "subcategory":"Race Track",
            "type":"Entertainment"
        }
    ],
    "sg:phone":"+1 616 530 2902",
    "sg:postcode":"49508",
    "sg:province":"MI",
    "sg:tags":[
        "operation",
        "racing",
        "or"
    ],
    "wof:name":"Piersma Racing",
    "wof:placetype":"venue"
},
  "geometry": {"coordinates":[-85.645185,42.873474],"type":"Point"}
}