{
  "type": "Feature",
  "properties": {
    "iso:country":"US",
    "sg:address":"8600 Dixie Hwy",
    "sg:city":"Clarkston",
    "sg:classifiers":[
        {
            "category":"Home & Garden",
            "subcategory":"Garden Supply",
            "type":"Retail Goods"
        }
    ],
    "sg:phone":"+1 248 625 9100",
    "sg:postcode":"48348",
    "sg:province":"MI",
    "sg:tags":[
        "nurseryman"
    ],
    "sg:website":"www.bordines.com",
    "wof:name":"Bordine Nursery",
    "wof:placetype":"venue"
},
  "geometry": {"coordinates":[-83.459165,42.743257],"type":"Point"}
}