{
  "type": "Feature",
  "properties": {
    "iso:country":"US",
    "sg:address":"6750 Orchard Lake Rd",
    "sg:city":"West Bloomfield",
    "sg:classifiers":[
        {
            "category":"Sports & Exercise",
            "subcategory":"Gym",
            "type":"Entertainment"
        }
    ],
    "sg:phone":"+1 248 539 0444",
    "sg:postcode":"48322",
    "sg:province":"MI",
    "wof:name":"Powerhouse Gym Salon",
    "wof:placetype":"venue"
},
  "geometry": {"coordinates":[-83.360703,42.538399],"type":"Point"}
}