{
  "type": "Feature",
  "properties": {
    "iso:country":"US",
    "sg:address":"5900 N Canton Center Rd",
    "sg:city":"Canton",
    "sg:classifiers":[
        {
            "category":"Retail",
            "subcategory":"Veterinary Services",
            "type":"Services"
        }
    ],
    "sg:phone":"+1 734 459 1400",
    "sg:postcode":"48187",
    "sg:province":"MI",
    "sg:tags":[
        "veterinarian"
    ],
    "sg:website":"www.cantoncenteranimalhospital.com/",
    "wof:name":"Canton Center Animal Hospital",
    "wof:placetype":"venue"
},
  "geometry": {"coordinates":[-83.4879,42.325199],"type":"Point"}
}