{
  "type": "Feature",
  "properties": {
    "iso:country":"US",
    "sg:address":"10597 Lewis Ave",
    "sg:city":"Temperance",
    "sg:classifiers":[
        {
            "category":"Home & Garden",
            "subcategory":"Home Furnishings",
            "type":"Retail Goods"
        }
    ],
    "sg:phone":"+1 734 856 2973",
    "sg:postcode":"48182",
    "sg:province":"MI",
    "sg:tags":[
        "curtain",
        "made",
        "drapery"
    ],
    "wof:name":"Accents Draperies & More",
    "wof:placetype":"venue"
},
  "geometry": {"coordinates":[-83.569557,41.808203],"type":"Point"}
}