{
  "type": "Feature",
  "properties": {
    "iso:country":"US",
    "sg:address":"26330 Eastgate Blvd",
    "sg:city":"Roseville",
    "sg:classifiers":[
        {
            "category":"Shopping",
            "subcategory":"Clothing, Apparel, & Fashions",
            "type":"Retail Goods"
        }
    ],
    "sg:phone":"+1 586 771 5560",
    "sg:postcode":"48066",
    "sg:province":"MI",
    "wof:name":"Fashion Cents",
    "wof:placetype":"venue"
},
  "geometry": {"coordinates":[-82.941785,42.488504],"type":"Point"}
}