{
  "type": "Feature",
  "properties": {
    "iso:country":"US",
    "sg:address":"2001 Dallavo Dr",
    "sg:city":"Commerce Twp",
    "sg:classifiers":[
        {
            "category":"Building & Trades",
            "subcategory":"Cleaning & Sanitation",
            "type":"Services"
        }
    ],
    "sg:phone":"+1 248 669 6120",
    "sg:postcode":"48390",
    "sg:province":"MI",
    "sg:tags":[
        "butler",
        "maid"
    ],
    "wof:name":"Maid Service Suburban Pro",
    "wof:placetype":"venue"
},
  "geometry": {"coordinates":[-83.451376,42.568857],"type":"Point"}
}