{
  "type": "Feature",
  "properties": {
    "iso:country":"US",
    "sg:address":"2370 Hudson Rd",
    "sg:city":"Hillsdale",
    "sg:classifiers":[
        {
            "category":"Professional",
            "subcategory":"Engineering",
            "type":"Services"
        }
    ],
    "sg:phone":"+1 517 437 6998",
    "sg:postcode":"49242",
    "sg:province":"MI",
    "sg:tags":[
        "engineer"
    ],
    "wof:name":"Mechanical Design Svc",
    "wof:placetype":"venue"
},
  "geometry": {"coordinates":[-84.60181,41.888277],"type":"Point"}
}