{
  "type": "Feature",
  "properties": {
    "iso:country":"US",
    "sg:address":"5885 S Main St",
    "sg:city":"Clarkston",
    "sg:classifiers":[
        {
            "category":"Organizations",
            "subcategory":"Religious Organization",
            "type":"Services"
        }
    ],
    "sg:phone":"+1 248 625 5815",
    "sg:postcode":"48346",
    "sg:province":"MI",
    "wof:name":"Liberating Word Ministries",
    "wof:placetype":"venue"
},
  "geometry": {"coordinates":[-83.41871500000001,42.72339],"type":"Point"}
}