{
  "type": "Feature",
  "properties": {
    "iso:country":"US",
    "sg:address":"3650 Fernwood Dr",
    "sg:city":"Monroe",
    "sg:classifiers":[
        {
            "category":"Personal",
            "type":"Services"
        }
    ],
    "sg:phone":"+1 734 289 2586",
    "sg:postcode":"48162",
    "sg:province":"MI",
    "sg:tags":[
        "consulting",
        "management",
        "b"
    ],
    "wof:name":"Creative Inspirations",
    "wof:placetype":"venue"
},
  "geometry": {"coordinates":[-83.307385,41.942119],"type":"Point"}
}