{
  "type": "Feature",
  "properties": {
    "iso:country":"US",
    "sg:address":"330 E Maple Rd Ste 236",
    "sg:city":"Birmingham",
    "sg:classifiers":[
        {
            "category":"Building & Trades",
            "subcategory":"Construction",
            "type":"Services"
        }
    ],
    "sg:phone":"+1 248 761 5520",
    "sg:postcode":"48009",
    "sg:province":"MI",
    "sg:tags":[
        "painter"
    ],
    "wof:name":"ProTect Painters of Birmingham & Bloomfield",
    "wof:placetype":"venue"
},
  "geometry": {"coordinates":[-83.212621,42.54673],"type":"Point"}
}