{
  "type": "Feature",
  "properties": {
    "iso:country":"US",
    "sg:address":"15670 W 10 Mile Rd",
    "sg:city":"Southfield",
    "sg:classifiers":[
        {
            "category":"Retail",
            "subcategory":"Laundry & Dry Cleaning",
            "type":"Services"
        }
    ],
    "sg:phone":"+1 248 557 6324",
    "sg:postcode":"48075",
    "sg:province":"MI",
    "sg:tags":[
        "cleaners",
        "rug",
        "carpet"
    ],
    "wof:name":"A L Panos Carpet Cleaning",
    "wof:placetype":"venue"
},
  "geometry": {"coordinates":[-83.204329,42.473861],"type":"Point"}
}