{
  "type": "Feature",
  "properties": {
    "iso:country":"US",
    "sg:address":"21745 Kelly Rd",
    "sg:city":"Eastpointe",
    "sg:classifiers":[
        {
            "category":"Shopping",
            "subcategory":"Party Supplies",
            "type":"Retail Goods"
        },
        {
            "category":"Personal",
            "type":"Services"
        }
    ],
    "sg:phone":"+1 586 772 7022",
    "sg:postcode":"48021",
    "sg:province":"MI",
    "sg:tags":[
        "planning",
        "event"
    ],
    "wof:name":"Jo-Jo's Party Shoppe",
    "wof:placetype":"venue"
},
  "geometry": {"coordinates":[-82.933601,42.458401],"type":"Point"}
}