{
  "type": "Feature",
  "properties": {
    "iso:country":"US",
    "sg:address":"1320 E Grand River Ave",
    "sg:city":"Portland",
    "sg:classifiers":[
        {
            "category":"Home & Garden",
            "subcategory":"Household Appliances",
            "type":"Retail Goods"
        }
    ],
    "sg:phone":"+1 517 647 6700",
    "sg:postcode":"48875",
    "sg:province":"MI",
    "sg:tags":[
        "repair"
    ],
    "wof:name":"Platte Appliance & Home Center",
    "wof:placetype":"venue"
},
  "geometry": {"coordinates":[-84.889129,42.86414],"type":"Point"}
}