{
  "type": "Feature",
  "properties": {
    "iso:country":"US",
    "sg:address":"19511 Maple St",
    "sg:city":"Lake Ann",
    "sg:classifiers":[
        {
            "category":"Travel",
            "subcategory":"Hotels & Motels",
            "type":"Entertainment"
        }
    ],
    "sg:phone":"+1 231 275 7701",
    "sg:postcode":"49650",
    "sg:province":"MI",
    "sg:tags":[
        "resort"
    ],
    "wof:name":"Dreamland Resort",
    "wof:placetype":"venue"
},
  "geometry": {"coordinates":[-85.845726,44.723769],"type":"Point"}
}