{
  "type": "Feature",
  "properties": {
    "iso:country":"US",
    "sg:address":"1601 Galbraith Ave SE",
    "sg:city":"Grand Rapids",
    "sg:classifiers":[
        {
            "category":"Insurance",
            "subcategory":"Insurance Agent",
            "type":"Services"
        }
    ],
    "sg:phone":"+1 616 957 0098",
    "sg:postcode":"49546",
    "sg:province":"MI",
    "sg:tags":[
        "audit"
    ],
    "wof:name":"Chlystek & White Svc",
    "wof:placetype":"venue"
},
  "geometry": {"coordinates":[-85.53566499999999,42.934363],"type":"Point"}
}