{
  "type": "Feature",
  "properties": {
    "iso:country":"US",
    "sg:address":"121 W Long Lake Rd Ste 300",
    "sg:city":"Bloomfield Hills",
    "sg:classifiers":[
        {
            "category":"Real Estate",
            "subcategory":"Real Estate Services",
            "type":"Services"
        },
        {
            "category":"Building & Trades",
            "subcategory":"Construction",
            "type":"Services"
        }
    ],
    "sg:phone":"+1 248 646 3529",
    "sg:postcode":"48304",
    "sg:province":"MI",
    "sg:tags":[
        "management",
        "property",
        "contractor"
    ],
    "wof:name":"Milford Singer & Company",
    "wof:placetype":"venue"
},
  "geometry": {"coordinates":[-83.248694,42.583174],"type":"Point"}
}