{
  "type": "Feature",
  "properties": {
    "iso:country":"US",
    "sg:address":"49936 Fuller Ct",
    "sg:city":"Plymouth",
    "sg:classifiers":[
        {
            "category":"Building & Trades",
            "subcategory":"Electrical",
            "type":"Services"
        }
    ],
    "sg:phone":"+1 734 354 9035",
    "sg:postcode":"48170",
    "sg:province":"MI",
    "sg:tags":[
        "electrical",
        "contractor"
    ],
    "wof:name":"James Heileman Electric",
    "wof:placetype":"venue"
},
  "geometry": {"coordinates":[-83.53438300000001,42.369016],"type":"Point"}
}