{
  "type": "Feature",
  "properties": {
    "iso:country":"US",
    "sg:address":"10680 Davisburg Rd",
    "sg:city":"Davisburg",
    "sg:classifiers":[
        {
            "category":"Education",
            "subcategory":"Special Training",
            "type":"Public Place"
        }
    ],
    "sg:phone":"+1 248 625 4161",
    "sg:postcode":"48350",
    "sg:province":"MI",
    "wof:name":"Best Medicine Co Inc",
    "wof:placetype":"venue"
},
  "geometry": {"coordinates":[-83.500764,42.758734],"type":"Point"}
}