{
  "type": "Feature",
  "properties": {
    "iso:country":"US",
    "sg:address":"27054 Yale St",
    "sg:city":"Inkster",
    "sg:classifiers":[
        {
            "category":"Professional",
            "subcategory":"Business Services",
            "type":"Services"
        }
    ],
    "sg:phone":"+1 313 561 0276",
    "sg:postcode":"48141",
    "sg:province":"MI",
    "wof:name":"Faithway Enterprises Inc",
    "wof:placetype":"venue"
},
  "geometry": {"coordinates":[-83.306826,42.288297],"type":"Point"}
}