{
  "type": "Feature",
  "properties": {
    "iso:country":"US",
    "sg:address":"39555 Orchard Hill Pl",
    "sg:city":"Novi",
    "sg:classifiers":[
        {
            "category":"Insurance",
            "subcategory":"Insurance Agent",
            "type":"Services"
        }
    ],
    "sg:phone":"+1 248 380 6190",
    "sg:postcode":"48375",
    "sg:province":"MI",
    "sg:website":"www.nustar-ins.com",
    "wof:name":"Nustar Insurance Agency Inc",
    "wof:placetype":"venue"
},
  "geometry": {"coordinates":[-83.438554,42.441209],"type":"Point"}
}