{
  "type": "Feature",
  "properties": {
    "iso:country":"US",
    "sg:address":"211 Jipson St",
    "sg:city":"Blissfield",
    "sg:classifiers":[
        {
            "category":"Retail",
            "subcategory":"Auto Repair",
            "type":"Services"
        }
    ],
    "sg:phone":"+1 517 486 4324",
    "sg:postcode":"49228",
    "sg:province":"MI",
    "sg:tags":[
        "fuel",
        "equipment",
        "injection",
        "system"
    ],
    "wof:name":"Northwest Fuel Injection Svc",
    "wof:placetype":"venue"
},
  "geometry": {"coordinates":[-83.85526400000001,41.828661],"type":"Point"}
}