{
  "type": "Feature",
  "properties": {
    "iso:country":"US",
    "sg:address":"224 N Main St",
    "sg:city":"Cheboygan",
    "sg:classifiers":[
        {
            "category":"Social Services",
            "type":"Services"
        }
    ],
    "sg:phone":"+1 231 627 9077",
    "sg:postcode":"49721",
    "sg:province":"MI",
    "sg:tags":[
        "crisis",
        "intervention"
    ],
    "wof:name":"Rainbow Services-Youth & Fmly",
    "wof:placetype":"venue"
},
  "geometry": {"coordinates":[-84.473902,45.647769],"type":"Point"}
}