{
  "type": "Feature",
  "properties": {
    "iso:country":"US",
    "sg:address":"936 Abbey Ln",
    "sg:city":"Milford",
    "sg:classifiers":[
        {
            "category":"Insurance",
            "subcategory":"Insurance Agent",
            "type":"Services"
        }
    ],
    "sg:phone":"+1 248 684 5939",
    "sg:postcode":"48381",
    "sg:province":"MI",
    "sg:tags":[
        "agency"
    ],
    "wof:name":"Farmers Insurance",
    "wof:placetype":"venue"
},
  "geometry": {"coordinates":[-83.615003,42.598495],"type":"Point"}
}