{
  "type": "Feature",
  "properties": {
    "iso:country":"US",
    "sg:address":"6795 US Hwy 31 N",
    "sg:city":"Charlevoix",
    "sg:classifiers":[
        {
            "category":"Freight",
            "type":"Transportation"
        }
    ],
    "sg:phone":"+1 231 547 5838",
    "sg:postcode":"49720",
    "sg:province":"MI",
    "sg:tags":[
        "commercial",
        "storage"
    ],
    "wof:name":"Charlevoix Mini Storage",
    "wof:placetype":"venue"
},
  "geometry": {"coordinates":[-85.111273,45.360162],"type":"Point"}
}