{
  "type": "Feature",
  "properties": {
    "iso:country":"US",
    "sg:address":"24474 Goddard Rd",
    "sg:city":"Taylor",
    "sg:classifiers":[
        {
            "category":"Personal",
            "subcategory":"Hair Removal",
            "type":"Services"
        }
    ],
    "sg:phone":"+1 313 291 2411",
    "sg:postcode":"48180",
    "sg:province":"MI",
    "sg:tags":[
        "laser"
    ],
    "sg:website":"www.laserskinandhairclinics.com",
    "wof:name":"Laser Skin & Hair Clinics",
    "wof:placetype":"venue"
},
  "geometry": {"coordinates":[-83.27335600000001,42.226491],"type":"Point"}
}