{
  "type": "Feature",
  "properties": {
    "iso:country":"US",
    "sg:address":"2328 E Genesee Ave",
    "sg:city":"Saginaw",
    "sg:classifiers":[
        {
            "category":"Manufacturing",
            "subcategory":"Motor Vehicles & Parts",
            "type":"Manufacturing & Wholesale Goods"
        }
    ],
    "sg:phone":"+1 989 757 5000",
    "sg:postcode":"48601",
    "sg:province":"MI",
    "sg:tags":[
        "automobile",
        "supply"
    ],
    "wof:name":"Delphi Energy & Chassis",
    "wof:placetype":"venue"
},
  "geometry": {"coordinates":[-83.91858000000001,43.410311],"type":"Point"}
}