{
  "type": "Feature",
  "properties": {
    "iso:country":"US",
    "sg:address":"6460 Yorkshire Ln",
    "sg:city":"Eaton Rapids",
    "sg:classifiers":[
        {
            "category":"Building & Trades",
            "subcategory":"Construction",
            "type":"Services"
        }
    ],
    "sg:phone":"+1 517 663 4521",
    "sg:postcode":"48827",
    "sg:province":"MI",
    "sg:tags":[
        "home",
        "builder"
    ],
    "wof:name":"Woodstone Builders",
    "wof:placetype":"venue"
},
  "geometry": {"coordinates":[-84.632976,42.478233],"type":"Point"}
}