{
  "type": "Feature",
  "properties": {
    "iso:country":"US",
    "sg:address":"524 W Grand River Ave",
    "sg:city":"Fowlerville",
    "sg:classifiers":[
        {
            "category":"Banks & Credit Unions",
            "subcategory":"Bank",
            "type":"Services"
        }
    ],
    "sg:phone":"+1 517 223 9163",
    "sg:postcode":"48836",
    "sg:province":"MI",
    "wof:name":"Republic Bank",
    "wof:placetype":"venue"
},
  "geometry": {"coordinates":[-84.0795,42.660744],"type":"Point"}
}