{
  "type": "Feature",
  "properties": {
    "iso:country":"US",
    "sg:address":"304 S Water St",
    "sg:city":"Saginaw",
    "sg:classifiers":[
        {
            "category":"Organizations",
            "subcategory":"Professional Association",
            "type":"Services"
        }
    ],
    "sg:phone":"+1 989 459 4331",
    "sg:postcode":"48607",
    "sg:province":"MI",
    "wof:name":"Muscular Dystrophy Assn",
    "wof:placetype":"venue"
},
  "geometry": {"coordinates":[-83.941261,43.430024],"type":"Point"}
}