{
  "type": "Feature",
  "properties": {
    "iso:country":"US",
    "sg:address":"1219 Turner St",
    "sg:city":"Lansing",
    "sg:classifiers":[
        {
            "category":"Shopping",
            "subcategory":"Clothing, Apparel, & Fashions",
            "type":"Retail Goods"
        }
    ],
    "sg:phone":"+1 517 267 9741",
    "sg:postcode":"48906",
    "sg:province":"MI",
    "sg:tags":[
        "infant",
        "wear"
    ],
    "wof:name":"Ja'Mesha' Ruffles & Lace",
    "wof:placetype":"venue"
},
  "geometry": {"coordinates":[-84.549638,42.748752],"type":"Point"}
}