{
  "type": "Feature",
  "properties": {
    "iso:country":"US",
    "sg:address":"422 E 32nd St",
    "sg:city":"Holland",
    "sg:classifiers":[
        {
            "category":"Travel",
            "subcategory":"Hotels & Motels",
            "type":"Entertainment"
        }
    ],
    "sg:phone":"+1 616 392 1000",
    "sg:postcode":"49423",
    "sg:province":"MI",
    "sg:tags":[
        "operation"
    ],
    "sg:website":"www.comfortinn.com",
    "wof:name":"Comfort Inn",
    "wof:placetype":"venue"
},
  "geometry": {"coordinates":[-86.08752800000001,42.768563],"type":"Point"}
}