{
  "type": "Feature",
  "properties": {
    "iso:country":"US",
    "sg:address":"6714 W 72nd St",
    "sg:city":"Fremont",
    "sg:classifiers":[
        {
            "category":"Retail",
            "subcategory":"Repair Shop",
            "type":"Services"
        }
    ],
    "sg:phone":"+1 231 924 8597",
    "sg:postcode":"49412",
    "sg:province":"MI",
    "sg:tags":[
        "lock",
        "locksmith"
    ],
    "wof:name":"N C Lock Svc",
    "wof:placetype":"venue"
},
  "geometry": {"coordinates":[-85.97163,43.42379],"type":"Point"}
}