{
  "type": "Feature",
  "properties": {
    "iso:country":"US",
    "sg:address":"20345 Maplewood St",
    "sg:city":"Livonia",
    "sg:classifiers":[
        {
            "category":"Building & Trades",
            "subcategory":"Construction",
            "type":"Services"
        }
    ],
    "sg:phone":"+1 248 476 4078",
    "sg:postcode":"48152",
    "sg:province":"MI",
    "sg:tags":[
        "carpentry",
        "contractor"
    ],
    "wof:name":"Ronald Ludwig Co",
    "wof:placetype":"venue"
},
  "geometry": {"coordinates":[-83.33102,42.437641],"type":"Point"}
}