{
  "type": "Feature",
  "properties": {
    "iso:country":"US",
    "sg:address":"109 Water St",
    "sg:city":"Boyne City",
    "sg:classifiers":[
        {
            "category":"Professional",
            "subcategory":"Art Services",
            "type":"Services"
        }
    ],
    "sg:phone":"+1 231 582 9299",
    "sg:postcode":"49712",
    "sg:province":"MI",
    "sg:tags":[
        "graphic",
        "designer"
    ],
    "wof:name":"Michele Nickel Graphic Dsgnr",
    "wof:placetype":"venue"
},
  "geometry": {"coordinates":[-85.014757,45.213732],"type":"Point"}
}