{
  "type": "Feature",
  "properties": {
    "iso:country":"US",
    "sg:address":"7320 Highland Rd",
    "sg:city":"Waterford",
    "sg:classifiers":[
        {
            "category":"Restaurant",
            "type":"Food & Drink"
        }
    ],
    "sg:menulink":"http://www.allmenus.com/mi/waterford/196779-burger-king/menu/",
    "sg:phone":"+1 248 666 1275",
    "sg:postcode":"48327",
    "sg:province":"MI",
    "sg:tags":[
        "burger",
        "american"
    ],
    "wof:name":"Burger King",
    "wof:placetype":"venue"
},
  "geometry": {"coordinates":[-83.430987,42.660449],"type":"Point"}
}