{
  "type": "Feature",
  "properties": {
    "iso:country":"US",
    "sg:address":"519 Mason St",
    "sg:city":"Mason",
    "sg:classifiers":[
        {
            "category":"Manufacturing",
            "subcategory":"Tools & Machinery",
            "type":"Manufacturing & Wholesale Goods"
        }
    ],
    "sg:phone":"+1 517 676 0350",
    "sg:postcode":"48854",
    "sg:province":"MI",
    "sg:tags":[
        "die",
        "maker"
    ],
    "wof:name":"Mason Header Die",
    "wof:placetype":"venue"
},
  "geometry": {"coordinates":[-84.452516,42.591251],"type":"Point"}
}