{
  "type": "Feature",
  "properties": {
    "iso:country":"US",
    "sg:address":"2194 W Ristow Hwy",
    "sg:city":"Rogers City",
    "sg:classifiers":[
        {
            "category":"Building & Trades",
            "subcategory":"Construction",
            "type":"Services"
        }
    ],
    "sg:phone":"+1 989 734 2095",
    "sg:postcode":"49779",
    "sg:province":"MI",
    "sg:tags":[
        "excavating",
        "contractor"
    ],
    "wof:name":"Gary Wirgau Excavating",
    "wof:placetype":"venue"
},
  "geometry": {"coordinates":[-83.84730500000001,45.360773],"type":"Point"}
}