{
  "type": "Feature",
  "properties": {
    "iso:country":"US",
    "sg:address":"611 W Ottawa St",
    "sg:city":"Lansing",
    "sg:classifiers":[
        {
            "category":"Manufacturing",
            "subcategory":"Printing",
            "type":"Manufacturing & Wholesale Goods"
        }
    ],
    "sg:phone":"+1 517 373 9279",
    "sg:postcode":"48915",
    "sg:province":"MI",
    "sg:tags":[
        "litigation"
    ],
    "wof:name":"Litigation Dept",
    "wof:placetype":"venue"
},
  "geometry": {"coordinates":[-84.56144,42.734645],"type":"Point"}
}