{
  "type": "Feature",
  "properties": {
    "iso:country":"US",
    "sg:address":"2010 S Huron Rd",
    "sg:city":"Kawkawlin",
    "sg:classifiers":[
        {
            "category":"Autos & Motor Vehicles",
            "subcategory":"Recreational Vehicle Sales",
            "type":"Retail Goods"
        }
    ],
    "sg:phone":"+1 989 684 5707",
    "sg:postcode":"48631",
    "sg:province":"MI",
    "sg:tags":[
        "body"
    ],
    "wof:name":"Pines Truck Accessories",
    "wof:placetype":"venue"
},
  "geometry": {"coordinates":[-83.963691,43.688405],"type":"Point"}
}