{
  "type": "Feature",
  "properties": {
    "iso:country":"US",
    "sg:address":"101 E 5th St",
    "sg:city":"Royal Oak",
    "sg:classifiers":[
        {
            "category":"Real Estate",
            "subcategory":"Architect",
            "type":"Services"
        }
    ],
    "sg:phone":"+1 248 336 8175",
    "sg:postcode":"48067",
    "sg:province":"MI",
    "wof:name":"Hf Architecture",
    "wof:placetype":"venue"
},
  "geometry": {"coordinates":[-83.14295799999999,42.486458],"type":"Point"}
}