{
  "type": "Feature",
  "properties": {
    "iso:country":"US",
    "sg:address":"8881 Fenton",
    "sg:city":"Redford",
    "sg:classifiers":[
        {
            "category":"Retail",
            "subcategory":"Laundry & Dry Cleaning",
            "type":"Services"
        }
    ],
    "sg:phone":"+1 313 874 5720",
    "sg:postcode":"48239",
    "sg:province":"MI",
    "wof:name":"Hangers Supply",
    "wof:placetype":"venue"
},
  "geometry": {"coordinates":[-83.280011,42.357711],"type":"Point"}
}