{
  "type": "Feature",
  "properties": {
    "iso:country":"US",
    "sg:address":"20848 Cedar Run Rd",
    "sg:city":"Traverse City",
    "sg:classifiers":[
        {
            "category":"Wholesale",
            "subcategory":"Durable Goods & Equipment",
            "type":"Manufacturing & Wholesale Goods"
        }
    ],
    "sg:phone":"+1 231 275 7471",
    "sg:postcode":"49684",
    "sg:province":"MI",
    "sg:tags":[
        "antique",
        "shop"
    ],
    "wof:name":"Grey Wolf Antiques",
    "wof:placetype":"venue"
},
  "geometry": {"coordinates":[-85.816005,44.763054],"type":"Point"}
}