{
  "type": "Feature",
  "properties": {
    "iso:country":"US",
    "sg:address":"474 N Telegraph Rd",
    "sg:city":"Monroe",
    "sg:classifiers":[
        {
            "category":"Shopping",
            "type":"Retail Goods"
        }
    ],
    "sg:phone":"+1 734 241 7875",
    "sg:postcode":"48162",
    "sg:province":"MI",
    "sg:tags":[
        "durable",
        "medical",
        "supply"
    ],
    "wof:name":"Monroe Home Care Shoppe",
    "wof:placetype":"venue"
},
  "geometry": {"coordinates":[-83.409629,41.93288],"type":"Point"}
}