{
  "type": "Feature",
  "properties": {
    "iso:country":"US",
    "sg:address":"9167 Apple Orchard Dr",
    "sg:city":"Fenton",
    "sg:classifiers":[
        {
            "category":"Retail",
            "subcategory":"Repair Shop",
            "type":"Services"
        }
    ],
    "sg:phone":"+1 810 750 8131",
    "sg:postcode":"48430",
    "sg:province":"MI",
    "wof:name":"Diem Septic Tank Installations",
    "wof:placetype":"venue"
},
  "geometry": {"coordinates":[-83.78183,42.779207],"type":"Point"}
}