{
  "type": "Feature",
  "properties": {
    "iso:country":"US",
    "sg:address":"236 N Portage Rd",
    "sg:city":"Jackson",
    "sg:classifiers":[
        {
            "category":"Professional",
            "subcategory":"Management & Consulting",
            "type":"Services"
        }
    ],
    "sg:phone":"+1 517 522 4093",
    "sg:postcode":"49201",
    "sg:province":"MI",
    "sg:tags":[
        "help",
        "supply"
    ],
    "wof:name":"Fisher Freight Haulers",
    "wof:placetype":"venue"
},
  "geometry": {"coordinates":[-84.269531,42.246041],"type":"Point"}
}