{
  "type": "Feature",
  "properties": {
    "iso:country":"US",
    "sg:address":"7110 E Coldwater Rd",
    "sg:city":"Davison",
    "sg:classifiers":[
        {
            "category":"Retail",
            "subcategory":"Animal Services",
            "type":"Services"
        }
    ],
    "sg:phone":"+1 810 653 5906",
    "sg:postcode":"48423",
    "sg:province":"MI",
    "wof:name":"Morgan Ancan",
    "wof:placetype":"venue"
},
  "geometry": {"coordinates":[-83.575644,43.091757],"type":"Point"}
}