{
  "type": "Feature",
  "properties": {
    "iso:country":"US",
    "sg:address":"1730 E Main St",
    "sg:city":"Owosso",
    "sg:classifiers":[
        {
            "category":"Travel",
            "subcategory":"Hotels & Motels",
            "type":"Entertainment"
        }
    ],
    "sg:phone":"+1 989 723 9000",
    "sg:postcode":"48867",
    "sg:province":"MI",
    "wof:name":"Pines Country Inn",
    "wof:placetype":"venue"
},
  "geometry": {"coordinates":[-84.136235,42.997855],"type":"Point"}
}