{
  "type": "Feature",
  "properties": {
    "iso:country":"US",
    "sg:address":"433 Lake Ave",
    "sg:city":"Ironwood",
    "sg:classifiers":[
        {
            "category":"Organizations",
            "subcategory":"Religious Organization",
            "type":"Services"
        }
    ],
    "sg:phone":"+1 906 932 3853",
    "sg:postcode":"49938",
    "sg:province":"MI",
    "wof:name":"Grace Community Fellowship",
    "wof:placetype":"venue"
},
  "geometry": {"coordinates":[-90.166045,46.46133],"type":"Point"}
}