{
  "type": "Feature",
  "properties": {
    "iso:country":"US",
    "sg:address":"36655 Jefferson Ave",
    "sg:city":"Harrison Township",
    "sg:classifiers":[
        {
            "category":"Retail",
            "subcategory":"Auto Repair",
            "type":"Services"
        }
    ],
    "sg:phone":"+1 586 469 9544",
    "sg:postcode":"48045",
    "sg:province":"MI",
    "sg:tags":[
        "repairing",
        "automobile"
    ],
    "wof:name":"Select Motor Care",
    "wof:placetype":"venue"
},
  "geometry": {"coordinates":[-82.839873,42.568873],"type":"Point"}
}