{
  "type": "Feature",
  "properties": {
    "iso:country":"US",
    "sg:address":"3055 Henry St",
    "sg:city":"Muskegon",
    "sg:classifiers":[
        {
            "category":"Restaurant",
            "type":"Food & Drink"
        }
    ],
    "sg:menulink":"http://www.allmenus.com/mi/roosevelt-park/200514-long-john-silvers/menu/",
    "sg:phone":"+1 616 733 1760",
    "sg:postcode":"49441",
    "sg:province":"MI",
    "sg:tags":[
        "seafood",
        "american"
    ],
    "wof:name":"Long John Silver's",
    "wof:placetype":"venue"
},
  "geometry": {"coordinates":[-86.26329699999999,43.197155],"type":"Point"}
}