{
  "type": "Feature",
  "properties": {
    "iso:country":"US",
    "sg:address":"13953 Dixie",
    "sg:city":"Redford",
    "sg:classifiers":[
        {
            "category":"Banks & Credit Unions",
            "subcategory":"Financial Services",
            "type":"Services"
        }
    ],
    "sg:phone":"+1 313 850 6713",
    "sg:postcode":"48239",
    "sg:province":"MI",
    "sg:tags":[
        "investor"
    ],
    "wof:name":"A1 Investments Cstm Carpentry",
    "wof:placetype":"venue"
},
  "geometry": {"coordinates":[-83.283379,42.386403],"type":"Point"}
}