{
  "type": "Feature",
  "properties": {
    "iso:country":"US",
    "sg:address":"100 W Michigan Ave",
    "sg:city":"Jackson",
    "sg:classifiers":[
        {
            "category":"Restaurant",
            "type":"Food & Drink"
        }
    ],
    "sg:phone":"+1 517 522 9975",
    "sg:postcode":"49201",
    "sg:province":"MI",
    "wof:name":"Kugler Dairy",
    "wof:placetype":"venue"
},
  "geometry": {"coordinates":[-84.40881299999999,42.247461],"type":"Point"}
}