{
  "type": "Feature",
  "properties": {
    "iso:country":"US",
    "sg:address":"23225 Brandywynne St",
    "sg:city":"Southfield",
    "sg:classifiers":[
        {
            "category":"Professional",
            "subcategory":"Business Services",
            "type":"Services"
        }
    ],
    "sg:phone":"+1 248 356 3661",
    "sg:postcode":"48033",
    "sg:province":"MI",
    "sg:tags":[
        "embroidery"
    ],
    "wof:name":"Merry Diverse Designs",
    "wof:placetype":"venue"
},
  "geometry": {"coordinates":[-83.290486,42.45732],"type":"Point"}
}