{
  "type": "Feature",
  "properties": {
    "iso:country":"US",
    "sg:address":"4126 48th St",
    "sg:city":"Holland",
    "sg:classifiers":[
        {
            "category":"Building & Trades",
            "subcategory":"Construction",
            "type":"Services"
        }
    ],
    "sg:phone":"+1 269 751 8091",
    "sg:postcode":"49423",
    "sg:province":"MI",
    "sg:tags":[
        "roofing",
        "contractor"
    ],
    "wof:name":"Conklin Roofing Systems",
    "wof:placetype":"venue"
},
  "geometry": {"coordinates":[-86.015705,42.714816],"type":"Point"}
}