{
  "type": "Feature",
  "properties": {
    "iso:country":"US",
    "sg:address":"21137 Walton St",
    "sg:city":"Saint Clair Shores",
    "sg:classifiers":[
        {
            "category":"Professional",
            "subcategory":"Employment Agencies",
            "type":"Services"
        }
    ],
    "sg:phone":"+1 586 773 3799",
    "sg:postcode":"48081",
    "sg:province":"MI",
    "sg:tags":[
        "help",
        "supply"
    ],
    "wof:name":"Direct Hire Staffing Inc",
    "wof:placetype":"venue"
},
  "geometry": {"coordinates":[-82.905438,42.490978],"type":"Point"}
}