{
  "type": "Feature",
  "properties": {
    "iso:country":"US",
    "sg:address":"16625 W Ridge Rd",
    "sg:city":"Oakley",
    "sg:classifiers":[
        {
            "category":"Farming",
            "subcategory":"Farm",
            "type":"Manufacturing & Wholesale Goods"
        }
    ],
    "sg:phone":"+1 989 661 2747",
    "sg:postcode":"48649",
    "sg:province":"MI",
    "sg:tags":[
        "crop",
        "general"
    ],
    "wof:name":"Drafty Barn Farm",
    "wof:placetype":"venue"
},
  "geometry": {"coordinates":[-84.242367,43.143032],"type":"Point"}
}