{
  "type": "Feature",
  "properties": {
    "iso:country":"US",
    "sg:address":"3300 S Waverly Rd",
    "sg:city":"Lansing",
    "sg:classifiers":[
        {
            "category":"Personal",
            "subcategory":"Beauty Salon",
            "type":"Services"
        }
    ],
    "sg:phone":"+1 517 882 3000",
    "sg:postcode":"48911",
    "sg:province":"MI",
    "wof:name":"Ramon's House Of Style",
    "wof:placetype":"venue"
},
  "geometry": {"coordinates":[-84.603145,42.69989],"type":"Point"}
}