{
  "type": "Feature",
  "properties": {
    "iso:country":"US",
    "sg:address":"43700 Woodward Ave Ste 301",
    "sg:city":"Bloomfield Hills",
    "sg:classifiers":[
        {
            "category":"Health Services",
            "subcategory":"Doctor",
            "type":"Services"
        }
    ],
    "sg:phone":"+1 248 454 7650",
    "sg:postcode":"48302",
    "sg:province":"MI",
    "wof:name":"Bloomfield Endocrinology",
    "wof:placetype":"venue"
},
  "geometry": {"coordinates":[-83.26950100000001,42.6096],"type":"Point"}
}