{
  "type": "Feature",
  "properties": {
    "iso:country":"US",
    "sg:address":"55 N Mission Trl W",
    "sg:city":"Cedarville",
    "sg:classifiers":[
        {
            "category":"Real Estate",
            "subcategory":"Real Estate Agent",
            "type":"Services"
        }
    ],
    "sg:phone":"+1 906 484 6860",
    "sg:postcode":"49719",
    "sg:province":"MI",
    "sg:tags":[
        "authorities",
        "housing"
    ],
    "wof:name":"Hillcrest Properties",
    "wof:placetype":"venue"
},
  "geometry": {"coordinates":[-84.332196,46.003168],"type":"Point"}
}