{
  "type": "Feature",
  "properties": {
    "iso:country":"US",
    "sg:address":"1773 Main St",
    "sg:city":"Minden City",
    "sg:classifiers":[
        {
            "category":"Travel",
            "subcategory":"Hotels & Motels",
            "type":"Entertainment"
        }
    ],
    "sg:phone":"+1 989 864 3535",
    "sg:postcode":"48456",
    "sg:province":"MI",
    "wof:name":"Gillis Hotel",
    "wof:placetype":"venue"
},
  "geometry": {"coordinates":[-82.76828399999999,43.671811],"type":"Point"}
}