{
  "type": "Feature",
  "properties": {
    "iso:country":"US",
    "sg:address":"3331 Fort Street",
    "sg:city":"Wyandotte",
    "sg:classifiers":[
        {
            "category":"Shopping",
            "subcategory":"Computers & Home Electronics",
            "type":"Retail Goods"
        }
    ],
    "sg:phone":"+1 313 458 6418",
    "sg:postcode":"48192",
    "sg:province":"MI",
    "sg:tags":[
        "hardware",
        "supply"
    ],
    "sg:website":"http://www.wyandottecomputers.net",
    "wof:name":"Wyandotte Computers 48192",
    "wof:placetype":"venue"
},
  "geometry": {"coordinates":[-83.180019,42.198968],"type":"Point"}
}