{
  "type": "Feature",
  "properties": {
    "iso:country":"US",
    "sg:address":"3670 E Grand River Ave",
    "sg:city":"Howell",
    "sg:classifiers":[
        {
            "category":"Autos & Motor Vehicles",
            "subcategory":"Auto Supplies",
            "type":"Retail Goods"
        }
    ],
    "sg:phone":"+1 517 545 7715",
    "sg:postcode":"48843",
    "sg:province":"MI",
    "sg:tags":[
        "tire"
    ],
    "wof:name":"Belle Tire",
    "wof:placetype":"venue"
},
  "geometry": {"coordinates":[-83.88118799999999,42.589071],"type":"Point"}
}