{
  "type": "Feature",
  "properties": {
    "iso:country":"US",
    "sg:address":"3100 Division Ave S",
    "sg:city":"Grand Rapids",
    "sg:classifiers":[
        {
            "category":"Shopping",
            "subcategory":"Bicycles & Sporting Goods",
            "type":"Retail Goods"
        }
    ],
    "sg:phone":"+1 616 245 9156",
    "sg:postcode":"49548",
    "sg:province":"MI",
    "wof:name":"Al & Bob's Sporting Goods",
    "wof:placetype":"venue"
},
  "geometry": {"coordinates":[-85.665696,42.906962],"type":"Point"}
}