{
  "type": "Feature",
  "properties": {
    "iso:country":"US",
    "sg:address":"29273 Dequindre Rd",
    "sg:city":"Warren",
    "sg:classifiers":[
        {
            "category":"Health Services",
            "subcategory":"Chiropractor",
            "type":"Services"
        }
    ],
    "sg:phone":"+1 248 579 4971",
    "sg:postcode":"48092",
    "sg:province":"MI",
    "sg:website":"www.healthsourceofmadison.com",
    "wof:name":"HealthSource of Madison Hts",
    "wof:placetype":"venue"
},
  "geometry": {"coordinates":[-83.08573199999999,42.507356],"type":"Point"}
}