{
  "type": "Feature",
  "properties": {
    "iso:country":"US",
    "sg:address":"9787 Battle Creek Hwy",
    "sg:city":"Bellevue",
    "sg:classifiers":[
        {
            "category":"Restaurant",
            "type":"Food & Drink"
        }
    ],
    "sg:phone":"+1 269 763 0094",
    "sg:postcode":"49021",
    "sg:province":"MI",
    "wof:name":"Bellevue Drive-In",
    "wof:placetype":"venue"
},
  "geometry": {"coordinates":[-85.03282,42.443557],"type":"Point"}
}