{
  "type": "Feature",
  "properties": {
    "iso:country":"US",
    "sg:address":"440 2nd St",
    "sg:city":"South Lyon",
    "sg:classifiers":[
        {
            "category":"Banks & Credit Unions",
            "subcategory":"Bank",
            "type":"Services"
        }
    ],
    "sg:phone":"+1 248 446 9231",
    "sg:postcode":"48178",
    "sg:province":"MI",
    "sg:tags":[
        "mortgage"
    ],
    "wof:name":"Creative Mortgage Financing",
    "wof:placetype":"venue"
},
  "geometry": {"coordinates":[-83.65540799999999,42.462415],"type":"Point"}
}