{
  "type": "Feature",
  "properties": {
    "iso:country":"US",
    "sg:address":"14154 Telegraph Rd",
    "sg:city":"Redford",
    "sg:classifiers":[
        {
            "category":"Professional",
            "subcategory":"Lawyer & Legal Services",
            "type":"Services"
        }
    ],
    "sg:phone":"+1 313 362 0400",
    "sg:postcode":"48239",
    "sg:province":"MI",
    "sg:tags":[
        "clown"
    ],
    "sg:website":"http://jokers4fun.com",
    "wof:name":"Jokers Entertainment",
    "wof:placetype":"venue"
},
  "geometry": {"coordinates":[-83.276031,42.3887],"type":"Point"}
}