{
  "type": "Feature",
  "properties": {
    "iso:country":"US",
    "sg:address":"811 Oakwood Dr",
    "sg:city":"Rochester",
    "sg:classifiers":[
        {
            "category":"Health Services",
            "subcategory":"Health Practitioner",
            "type":"Services"
        }
    ],
    "sg:phone":"+1 248 656 1985",
    "sg:postcode":"48307",
    "sg:province":"MI",
    "sg:tags":[
        "therapist",
        "physical"
    ],
    "wof:name":"Total Physcl Thrapy Rhbltation",
    "wof:placetype":"venue"
},
  "geometry": {"coordinates":[-83.145537,42.683369],"type":"Point"}
}