{
  "type": "Feature",
  "properties": {
    "iso:country":"US",
    "sg:address":"2858 Buick St",
    "sg:city":"Waterford",
    "sg:classifiers":[
        {
            "category":"Professional",
            "type":"Services"
        }
    ],
    "sg:phone":"+1 248 738 8272",
    "sg:postcode":"48328",
    "sg:province":"MI",
    "wof:name":"Yeti Computer & Network Svc",
    "wof:placetype":"venue"
},
  "geometry": {"coordinates":[-83.34644400000001,42.657719],"type":"Point"}
}