{
  "type": "Feature",
  "properties": {
    "iso:country":"US",
    "sg:address":"58310 Van Dyke Rd",
    "sg:city":"Washington",
    "sg:classifiers":[
        {
            "category":"Personal",
            "subcategory":"Beauty Salon",
            "type":"Services"
        }
    ],
    "sg:phone":"+1 586 781 9844",
    "sg:postcode":"48094",
    "sg:province":"MI",
    "sg:tags":[
        "shop"
    ],
    "wof:name":"Izzi's Hair Salon",
    "wof:placetype":"venue"
},
  "geometry": {"coordinates":[-83.035826,42.724494],"type":"Point"}
}