{
  "type": "Feature",
  "properties": {
    "iso:country":"US",
    "sg:address":"27216 Lenox Ave",
    "sg:city":"Madison Heights",
    "sg:classifiers":[
        {
            "category":"Retail",
            "subcategory":"Repair Shop",
            "type":"Services"
        }
    ],
    "sg:phone":"+1 248 545 8847",
    "sg:postcode":"48071",
    "sg:province":"MI",
    "wof:name":"Dependable Sewer Cleaners",
    "wof:placetype":"venue"
},
  "geometry": {"coordinates":[-83.1147,42.49267],"type":"Point"}
}