{
  "type": "Feature",
  "properties": {
    "iso:country":"US",
    "sg:address":"7957 N Wayne Rd",
    "sg:city":"Westland",
    "sg:classifiers":[
        {
            "category":"Banks & Credit Unions",
            "subcategory":"Bank",
            "type":"Services"
        }
    ],
    "sg:phone":"+1 734 261 5450",
    "sg:postcode":"48185",
    "sg:province":"MI",
    "sg:tags":[
        "national",
        "commercial"
    ],
    "wof:name":"Standard Federal Bank",
    "wof:placetype":"venue"
},
  "geometry": {"coordinates":[-83.385597,42.346401],"type":"Point"}
}