{
  "type": "Feature",
  "properties": {
    "iso:country":"US",
    "sg:address":"1935 Southwood Dr",
    "sg:city":"Ishpeming",
    "sg:classifiers":[
        {
            "category":"Government",
            "subcategory":"Office",
            "type":"Public Place"
        }
    ],
    "sg:phone":"+1 906 485 1437",
    "sg:postcode":"49849",
    "sg:province":"MI",
    "wof:name":"State Of Michigan",
    "wof:placetype":"venue"
},
  "geometry": {"coordinates":[-87.724912,46.478332],"type":"Point"}
}