{
  "type": "Feature",
  "properties": {
    "addr:city":"Farmington",
    "addr:housenumber":"33305",
    "addr:street":"Grand River Ave.",
    "iso:country":"US",
    "name:eng_x_preferred":[
        "Neu Kombucha"
    ],
    "wof:name":"Neu Kombucha",
    "wof:placetype":"venue"
},
  "geometry": {"coordinates":[-83.375654,42.464201],"type":"Point"}
}