{
  "type": "Feature",
  "properties": {
    "iso:country":"US",
    "sg:address":"790 Kline Rd",
    "sg:city":"Oakland",
    "sg:classifiers":[
        {
            "category":"Social Services",
            "subcategory":"Adult Care",
            "type":"Services"
        }
    ],
    "sg:phone":"+1 248 814 9016",
    "sg:postcode":"48363",
    "sg:province":"MI",
    "sg:tags":[
        "home",
        "group"
    ],
    "wof:name":"Progressive Lifestyles",
    "wof:placetype":"venue"
},
  "geometry": {"coordinates":[-83.169032,42.79623],"type":"Point"}
}