{
  "type": "Feature",
  "properties": {
    "iso:country":"US",
    "sg:address":"246 S Division St",
    "sg:city":"Hesperia",
    "sg:classifiers":[
        {
            "category":"Shopping",
            "subcategory":"Florist",
            "type":"Retail Goods"
        }
    ],
    "sg:phone":"+1 231 854 6675",
    "sg:postcode":"49421",
    "sg:province":"MI",
    "wof:name":"Sunset Floral & Greenhouse",
    "wof:placetype":"venue"
},
  "geometry": {"coordinates":[-86.039768,43.564191],"type":"Point"}
}