{
  "type": "Feature",
  "properties": {
    "iso:country":"US",
    "sg:address":"325 N 2nd Ave",
    "sg:city":"Alpena",
    "sg:classifiers":[
        {
            "category":"Home & Garden",
            "subcategory":"Furniture",
            "type":"Retail Goods"
        }
    ],
    "sg:phone":"+1 989 356 9002",
    "sg:postcode":"49707",
    "sg:province":"MI",
    "wof:name":"Alpena Furniture & Flooring",
    "wof:placetype":"venue"
},
  "geometry": {"coordinates":[-83.429711,45.064518],"type":"Point"}
}