{
  "type": "Feature",
  "properties": {
    "iso:country":"US",
    "sg:address":"1460 Eureka Rd",
    "sg:city":"Wyandotte",
    "sg:classifiers":[
        {
            "category":"Retail",
            "subcategory":"Auto Repair",
            "type":"Services"
        }
    ],
    "sg:phone":"+1 734 283 1347",
    "sg:postcode":"48192",
    "sg:province":"MI",
    "sg:tags":[
        "body"
    ],
    "wof:name":"Clr Recon",
    "wof:placetype":"venue"
},
  "geometry": {"coordinates":[-83.170474,42.199704],"type":"Point"}
}