{
  "type": "Feature",
  "properties": {
    "iso:country":"US",
    "sg:address":"1024 I- 75 Bus",
    "sg:city":"Grayling",
    "sg:classifiers":[
        {
            "category":"Travel",
            "subcategory":"Hotels & Motels",
            "type":"Entertainment"
        }
    ],
    "sg:phone":"+1 989 348 5950",
    "sg:postcode":"49738",
    "sg:province":"MI",
    "sg:tags":[
        "operation"
    ],
    "wof:name":"Pointe North Grayling Motels",
    "wof:placetype":"venue"
},
  "geometry": {"coordinates":[-84.713644,44.70768],"type":"Point"}
}