{
  "type": "Feature",
  "properties": {
    "iso:country":"US",
    "sg:address":"1832 Springwells St",
    "sg:city":"Detroit",
    "sg:classifiers":[
        {
            "category":"Shopping",
            "subcategory":"Department Store",
            "type":"Retail Goods"
        }
    ],
    "sg:phone":"+1 313 297 7721",
    "sg:postcode":"48209",
    "sg:province":"MI",
    "wof:name":"Spring Dollar Store",
    "wof:placetype":"venue"
},
  "geometry": {"coordinates":[-83.12509900000001,42.308701],"type":"Point"}
}