{
  "type": "Feature",
  "properties": {
    "iso:country":"US",
    "sg:address":"1424 W Dansville Rd",
    "sg:city":"Mason",
    "sg:classifiers":[
        {
            "category":"Professional",
            "subcategory":"Employment Agencies",
            "type":"Services"
        }
    ],
    "sg:phone":"+1 517 244 9570",
    "sg:postcode":"48854",
    "sg:province":"MI",
    "sg:tags":[
        "opportunity"
    ],
    "wof:name":"Cascade Disabilty",
    "wof:placetype":"venue"
},
  "geometry": {"coordinates":[-84.40001700000001,42.567124],"type":"Point"}
}