{
  "type": "Feature",
  "properties": {
    "iso:country":"US",
    "sg:address":"27801 Rosebriar St",
    "sg:city":"Saint Clair Shores",
    "sg:classifiers":[
        {
            "category":"Professional",
            "subcategory":"Accounting & Tax Preparation",
            "type":"Services"
        }
    ],
    "sg:phone":"+1 586 776 1570",
    "sg:postcode":"48081",
    "sg:province":"MI",
    "wof:name":"Eric Vossberg",
    "wof:placetype":"venue"
},
  "geometry": {"coordinates":[-82.900301,42.498075],"type":"Point"}
}