{
  "type": "Feature",
  "properties": {
    "iso:country":"US",
    "sg:address":"1611 Webb St",
    "sg:city":"Detroit",
    "sg:classifiers":[
        {
            "category":"Communications",
            "type":"Services"
        }
    ],
    "sg:phone":"+1 313 867 7874",
    "sg:postcode":"48206",
    "sg:province":"MI",
    "sg:tags":[
        "recording",
        "rehearsal",
        "studio"
    ],
    "wof:name":"Masterpiece Sound",
    "wof:placetype":"venue"
},
  "geometry": {"coordinates":[-83.10430100000001,42.386902],"type":"Point"}
}