{
  "type": "Feature",
  "properties": {
    "iso:country":"US",
    "sg:address":"757 W Isabella Rd",
    "sg:city":"Midland",
    "sg:classifiers":[
        {
            "category":"Home & Garden",
            "subcategory":"Building Materials",
            "type":"Retail Goods"
        }
    ],
    "sg:phone":"+1 989 633 0000",
    "sg:postcode":"48640",
    "sg:province":"MI",
    "sg:tags":[
        "windows"
    ],
    "wof:name":"Clear Vision Windows & Siding",
    "wof:placetype":"venue"
},
  "geometry": {"coordinates":[-84.398585,43.61091],"type":"Point"}
}