{
  "type": "Feature",
  "properties": {
    "iso:country":"US",
    "sg:address":"20745 State Hwy 60",
    "sg:city":"Cassopolis",
    "sg:classifiers":[
        {
            "category":"Manufacturing",
            "subcategory":"Tools & Machinery",
            "type":"Manufacturing & Wholesale Goods"
        }
    ],
    "sg:phone":"+1 269 445 2495",
    "sg:postcode":"49031",
    "sg:province":"MI",
    "sg:tags":[
        "machine",
        "shop"
    ],
    "sg:website":"www.k-mm.com",
    "wof:name":"K & M Fabricating Inc",
    "wof:placetype":"venue"
},
  "geometry": {"coordinates":[-85.967159,41.918054],"type":"Point"}
}