{
  "type": "Feature",
  "properties": {
    "iso:country":"US",
    "sg:address":"7581 Secor Rd",
    "sg:city":"Lambertville",
    "sg:classifiers":[
        {
            "category":"Social Services",
            "subcategory":"Job Training",
            "type":"Services"
        }
    ],
    "sg:phone":"+1 734 856 6737",
    "sg:postcode":"48144",
    "sg:province":"MI",
    "sg:tags":[
        "rehabilitation"
    ],
    "wof:name":"Hartland Rehabilitation Svc",
    "wof:placetype":"venue"
},
  "geometry": {"coordinates":[-83.625844,41.752006],"type":"Point"}
}