{
  "type": "Feature",
  "properties": {
    "iso:country":"US",
    "sg:address":"355 E Broadway Ave",
    "sg:city":"Muskegon",
    "sg:classifiers":[
        {
            "category":"Organizations",
            "subcategory":"Community Association",
            "type":"Services"
        }
    ],
    "sg:phone":"+1 231 830 8700",
    "sg:postcode":"49444",
    "sg:province":"MI",
    "sg:tags":[
        "club"
    ],
    "wof:name":"Muskegon Heights Boxing Club",
    "wof:placetype":"venue"
},
  "geometry": {"coordinates":[-86.23485599999999,43.20083],"type":"Point"}
}