{
  "type": "Feature",
  "properties": {
    "iso:country":"US",
    "sg:address":"31293 Mally Dr",
    "sg:city":"Madison Heights",
    "sg:classifiers":[
        {
            "category":"Manufacturing",
            "subcategory":"Tools & Machinery",
            "type":"Manufacturing & Wholesale Goods"
        }
    ],
    "sg:phone":"+1 248 589 0990",
    "sg:postcode":"48071",
    "sg:province":"MI",
    "wof:name":"Paulson Boring Co",
    "wof:placetype":"venue"
},
  "geometry": {"coordinates":[-83.11625600000001,42.522255],"type":"Point"}
}