{
  "type": "Feature",
  "properties": {
    "iso:country":"US",
    "sg:address":"4407 Center St",
    "sg:city":"Saginaw",
    "sg:classifiers":[
        {
            "category":"Professional",
            "type":"Services"
        }
    ],
    "sg:phone":"+1 989 771 9252",
    "sg:postcode":"48604",
    "sg:province":"MI",
    "wof:name":"B & W Commercial Svc",
    "wof:placetype":"venue"
},
  "geometry": {"coordinates":[-83.920141,43.465113],"type":"Point"}
}