{
  "type": "Feature",
  "properties": {
    "iso:country":"US",
    "sg:address":"26425 Grand River Ave",
    "sg:city":"Redford",
    "sg:classifiers":[
        {
            "category":"Retail",
            "subcategory":"Auto Repair",
            "type":"Services"
        }
    ],
    "sg:phone":"+1 313 592 1788",
    "sg:postcode":"48240",
    "sg:province":"MI",
    "sg:tags":[
        "body"
    ],
    "wof:name":"Mid-West Truck Accessories",
    "wof:placetype":"venue"
},
  "geometry": {"coordinates":[-83.305127,42.435232],"type":"Point"}
}