{
  "type": "Feature",
  "properties": {
    "iso:country":"US",
    "sg:address":"24712 Michigan Ave Ste 6",
    "sg:city":"Dearborn",
    "sg:classifiers":[
        {
            "category":"Professional",
            "subcategory":"Accounting & Tax Preparation",
            "type":"Services"
        }
    ],
    "sg:phone":"+1 313 277 8251",
    "sg:postcode":"48124",
    "sg:province":"MI",
    "sg:tags":[
        "accountant"
    ],
    "wof:name":"Koss Financial Services",
    "wof:placetype":"venue"
},
  "geometry": {"coordinates":[-83.27829699999999,42.298698],"type":"Point"}
}