{
  "type": "Feature",
  "properties": {
    "iso:country":"US",
    "sg:address":"1553 Alpine Ave NW",
    "sg:city":"Grand Rapids",
    "sg:classifiers":[
        {
            "category":"Health Services",
            "subcategory":"Chiropractor",
            "type":"Services"
        }
    ],
    "sg:phone":"+1 616 364 9485",
    "sg:postcode":"49504",
    "sg:province":"MI",
    "wof:name":"James M Elliott DC",
    "wof:placetype":"venue"
},
  "geometry": {"coordinates":[-85.688321,42.992132],"type":"Point"}
}