{
  "type": "Feature",
  "properties": {
    "iso:country":"US",
    "sg:address":"37400 Garfield Rd",
    "sg:city":"Clinton Twp",
    "sg:classifiers":[
        {
            "category":"Professional",
            "subcategory":"Management & Consulting",
            "type":"Services"
        }
    ],
    "sg:phone":"+1 586 226 9640",
    "sg:postcode":"48036",
    "sg:province":"MI",
    "sg:tags":[
        "personnel",
        "consultant"
    ],
    "wof:name":"Advantage Staffing",
    "wof:placetype":"venue"
},
  "geometry": {"coordinates":[-82.95108500000001,42.573835],"type":"Point"}
}