{
  "type": "Feature",
  "properties": {
    "iso:country":"US",
    "sg:address":"104 E Upton Ave",
    "sg:city":"Reed City",
    "sg:classifiers":[
        {
            "category":"Wholesale",
            "subcategory":"Machinery & Supplies",
            "type":"Manufacturing & Wholesale Goods"
        }
    ],
    "sg:phone":"+1 231 832 2111",
    "sg:postcode":"49677",
    "sg:province":"MI",
    "sg:tags":[
        "pump"
    ],
    "wof:name":"D & E Supply Co",
    "wof:placetype":"venue"
},
  "geometry": {"coordinates":[-85.509152,43.876059],"type":"Point"}
}