{
  "type": "Feature",
  "properties": {
    "iso:country":"US",
    "sg:address":"6104 S 36th St",
    "sg:city":"Climax",
    "sg:classifiers":[
        {
            "category":"Real Estate",
            "subcategory":"Architect",
            "type":"Services"
        }
    ],
    "sg:phone":"+1 269 626 0199",
    "sg:postcode":"49034",
    "sg:province":"MI",
    "sg:tags":[
        "home",
        "planning",
        "design"
    ],
    "wof:name":"SGK Architecture",
    "wof:placetype":"venue"
},
  "geometry": {"coordinates":[-85.41337799999999,42.229785],"type":"Point"}
}