{
  "type": "Feature",
  "properties": {
    "iso:country":"US",
    "sg:address":"116 E Allegan St",
    "sg:city":"Otsego",
    "sg:classifiers":[
        {
            "category":"Building & Trades",
            "subcategory":"Plumbing",
            "type":"Services"
        }
    ],
    "sg:phone":"+1 269 694 9660",
    "sg:postcode":"49078",
    "sg:province":"MI",
    "sg:tags":[
        "conditioning",
        "air",
        "system",
        "contractor"
    ],
    "wof:name":"A J Heating & Cooling Supplies",
    "wof:placetype":"venue"
},
  "geometry": {"coordinates":[-85.69669,42.460418],"type":"Point"}
}