{
  "type": "Feature",
  "properties": {
    "iso:country":"US",
    "sg:address":"103 Carey St",
    "sg:city":"Deerfield",
    "sg:classifiers":[
        {
            "category":"Professional",
            "subcategory":"Business Services",
            "type":"Services"
        }
    ],
    "sg:phone":"+1 517 447 3370",
    "sg:postcode":"49238",
    "sg:province":"MI",
    "wof:name":"Atc Embroidery",
    "wof:placetype":"venue"
},
  "geometry": {"coordinates":[-83.779203,41.889705],"type":"Point"}
}