{
  "type": "Feature",
  "properties": {
    "iso:country":"US",
    "sg:address":"36400 Woodward Ave Ste 122",
    "sg:city":"Bloomfield",
    "sg:classifiers":[
        {
            "category":"Banks & Credit Unions",
            "subcategory":"Financial Services",
            "type":"Services"
        }
    ],
    "sg:phone":"+1 248 642 4744",
    "sg:postcode":"48304",
    "sg:province":"MI",
    "sg:tags":[
        "broker",
        "mortgage"
    ],
    "wof:name":"Oxford Financial Corp",
    "wof:placetype":"venue"
},
  "geometry": {"coordinates":[-83.22185399999999,42.557131],"type":"Point"}
}