{
  "type": "Feature",
  "properties": {
    "iso:country":"US",
    "sg:address":"710 Seminole Rd",
    "sg:city":"Muskegon",
    "sg:classifiers":[
        {
            "category":"Banks & Credit Unions",
            "subcategory":"Bank",
            "type":"Services"
        }
    ],
    "sg:phone":"+1 231 739 9333",
    "sg:postcode":"49441",
    "sg:province":"MI",
    "sg:tags":[
        "state",
        "commercial"
    ],
    "sg:website":"www.53.com",
    "wof:name":"Fifth Third Bank",
    "wof:placetype":"venue"
},
  "geometry": {"coordinates":[-86.263098,43.187221],"type":"Point"}
}