{
  "type": "Feature",
  "properties": {
    "iso:country":"US",
    "sg:address":"5035 W Main St",
    "sg:city":"Kalamazoo",
    "sg:classifiers":[
        {
            "category":"Banks & Credit Unions",
            "subcategory":"Bank",
            "type":"Services"
        }
    ],
    "sg:phone":"+1 269 553 9966",
    "sg:postcode":"49009",
    "sg:province":"MI",
    "sg:tags":[
        "cashing",
        "check"
    ],
    "wof:name":"Check 'n Go",
    "wof:placetype":"venue"
},
  "geometry": {"coordinates":[-85.648459,42.296217],"type":"Point"}
}