{
  "type": "Feature",
  "properties": {
    "iso:country":"US",
    "sg:address":"16358 Paint Creek Cir",
    "sg:city":"Macomb",
    "sg:classifiers":[
        {
            "category":"Professional",
            "type":"Services"
        }
    ],
    "sg:phone":"+1 586 677 7069",
    "sg:postcode":"48042",
    "sg:province":"MI",
    "sg:tags":[
        "establishment"
    ],
    "wof:name":"Renaissance Enterprises",
    "wof:placetype":"venue"
},
  "geometry": {"coordinates":[-82.96151999999999,42.685498],"type":"Point"}
}