{
  "type": "Feature",
  "properties": {
    "iso:country":"US",
    "sg:address":"25621 Lois Ln",
    "sg:city":"Southfield",
    "sg:classifiers":[
        {
            "category":"Retail",
            "subcategory":"Repair Shop",
            "type":"Services"
        }
    ],
    "sg:phone":"+1 248 355 0708",
    "sg:postcode":"48075",
    "sg:province":"MI",
    "wof:name":"Reasonable Drain Opening",
    "wof:placetype":"venue"
},
  "geometry": {"coordinates":[-83.257806,42.475599],"type":"Point"}
}