{
  "type": "Feature",
  "properties": {
    "iso:country":"US",
    "sg:address":"300 N Richardson St",
    "sg:city":"Vicksburg",
    "sg:classifiers":[
        {
            "category":"Museum",
            "type":"Entertainment"
        }
    ],
    "sg:phone":"+1 269 649 1733",
    "sg:postcode":"49097",
    "sg:province":"MI",
    "wof:name":"Vicksburg Museum",
    "wof:placetype":"venue"
},
  "geometry": {"coordinates":[-85.529905,42.122696],"type":"Point"}
}