{
  "type": "Feature",
  "properties": {
    "iso:country":"US",
    "sg:address":"608 Chrysler St",
    "sg:city":"Kalamazoo",
    "sg:classifiers":[
        {
            "category":"Building & Trades",
            "subcategory":"Landscaping Services",
            "type":"Services"
        }
    ],
    "sg:phone":"+1 269 341 4312",
    "sg:postcode":"49048",
    "sg:province":"MI",
    "wof:name":"A&R Classic Lawncare",
    "wof:placetype":"venue"
},
  "geometry": {"coordinates":[-85.53893100000001,42.299426],"type":"Point"}
}