{
  "type": "Feature",
  "properties": {
    "iso:country":"US",
    "sg:address":"166 E Lakewood Blvd",
    "sg:city":"Holland",
    "sg:classifiers":[
        {
            "category":"Coffee & Tea",
            "type":"Food & Drink"
        },
        {
            "category":"Restaurant",
            "type":"Food & Drink"
        }
    ],
    "sg:menulink":"http://www.allmenus.com/mi/holland/47766-joe-2-go/menu/",
    "sg:phone":"+1 616 395 5950",
    "sg:postcode":"49424",
    "sg:province":"MI",
    "sg:tags":[
        "tea",
        "coffee",
        "american"
    ],
    "wof:name":"Joe 2 Go",
    "wof:placetype":"venue"
},
  "geometry": {"coordinates":[-86.10086800000001,42.805515],"type":"Point"}
}