{
  "type": "Feature",
  "properties": {
    "iso:country":"US",
    "sg:address":"4301 Derry Rd",
    "sg:city":"Bloomfield Hills",
    "sg:classifiers":[
        {
            "category":"Building & Trades",
            "subcategory":"Construction",
            "type":"Services"
        }
    ],
    "sg:phone":"+1 248 851 2877",
    "sg:postcode":"48302",
    "sg:province":"MI",
    "sg:tags":[
        "home",
        "builder"
    ],
    "wof:name":"Expo Homes Inc",
    "wof:placetype":"venue"
},
  "geometry": {"coordinates":[-83.301783,42.574585],"type":"Point"}
}