{
  "type": "Feature",
  "properties": {
    "iso:country":"US",
    "sg:address":"373 N Willowbrook Rd",
    "sg:city":"Coldwater",
    "sg:classifiers":[
        {
            "category":"Restaurant",
            "type":"Food & Drink"
        }
    ],
    "sg:menulink":"http://www.allmenus.com/mi/coldwater/57496-neptunes-cavern/menu/",
    "sg:phone":"+1 517 278 6500",
    "sg:postcode":"49036",
    "sg:province":"MI",
    "sg:tags":[
        "seafood",
        "american"
    ],
    "wof:name":"Neptune's Cavern",
    "wof:placetype":"venue"
},
  "geometry": {"coordinates":[-84.97129099999999,41.950839],"type":"Point"}
}