{
  "type": "Feature",
  "properties": {
    "iso:country":"US",
    "sg:address":"6991 Wilson Ave SW",
    "sg:city":"Byron Center",
    "sg:classifiers":[
        {
            "category":"Professional",
            "subcategory":"Business Services",
            "type":"Services"
        }
    ],
    "sg:phone":"+1 616 878 3150",
    "sg:postcode":"49315",
    "sg:province":"MI",
    "wof:name":"Dynamite Marketing",
    "wof:placetype":"venue"
},
  "geometry": {"coordinates":[-85.762659,42.826718],"type":"Point"}
}