{
  "type": "Feature",
  "properties": {
    "iso:country":"US",
    "sg:address":"979 S Saginaw Rd",
    "sg:city":"Midland",
    "sg:classifiers":[
        {
            "category":"Restaurant",
            "type":"Food & Drink"
        }
    ],
    "sg:phone":"+1 989 633 9888",
    "sg:postcode":"48640",
    "sg:province":"MI",
    "wof:name":"Golden Buffet",
    "wof:placetype":"venue"
},
  "geometry": {"coordinates":[-84.2204,43.619638],"type":"Point"}
}