{
  "type": "Feature",
  "properties": {
    "iso:country":"US",
    "sg:address":"4294 58th St",
    "sg:city":"Holland",
    "sg:classifiers":[
        {
            "category":"Retail",
            "subcategory":"Auto Repair",
            "type":"Services"
        }
    ],
    "sg:phone":"+1 616 393 8480",
    "sg:postcode":"49423",
    "sg:province":"MI",
    "sg:tags":[
        "automobile",
        "lubrication",
        "general"
    ],
    "wof:name":"G & M Express LLC",
    "wof:placetype":"venue"
},
  "geometry": {"coordinates":[-86.115554,42.725568],"type":"Point"}
}