{
  "type": "Feature",
  "properties": {
    "iso:country":"US",
    "sg:address":"5414 N Henderson Rd",
    "sg:city":"Davison",
    "sg:classifiers":[
        {
            "category":"Building & Trades",
            "subcategory":"Construction",
            "type":"Services"
        }
    ],
    "sg:phone":"+1 810 658 2333",
    "sg:postcode":"48423",
    "sg:province":"MI",
    "sg:tags":[
        "water",
        "well",
        "drilling"
    ],
    "wof:name":"Walker Well Drilling",
    "wof:placetype":"venue"
},
  "geometry": {"coordinates":[-83.47932299999999,43.08787],"type":"Point"}
}