{
  "type": "Feature",
  "properties": {
    "iso:country":"US",
    "sg:address":"14651 Mercury Dr",
    "sg:city":"Grand Haven",
    "sg:classifiers":[
        {
            "category":"Building & Trades",
            "subcategory":"Construction",
            "type":"Services"
        }
    ],
    "sg:phone":"+1 616 846 9354",
    "sg:postcode":"49417",
    "sg:province":"MI",
    "sg:tags":[
        "home",
        "improvement"
    ],
    "wof:name":"Polak Builders",
    "wof:placetype":"venue"
},
  "geometry": {"coordinates":[-86.150604,43.023185],"type":"Point"}
}