{
  "type": "Feature",
  "properties": {
    "iso:country":"US",
    "sg:address":"7520 Allen Rd",
    "sg:city":"Clarkston",
    "sg:classifiers":[
        {
            "category":"Professional",
            "type":"Services"
        }
    ],
    "sg:phone":"+1 248 625 0835",
    "sg:postcode":"48348",
    "sg:province":"MI",
    "sg:tags":[
        "architectural"
    ],
    "wof:name":"Mark Postal & Assoc",
    "wof:placetype":"venue"
},
  "geometry": {"coordinates":[-83.429647,42.747575],"type":"Point"}
}