{
  "type": "Feature",
  "properties": {
    "iso:country":"US",
    "sg:address":"650 S Rochester Rd",
    "sg:city":"Rochester",
    "sg:classifiers":[
        {
            "category":"Restaurant",
            "type":"Food & Drink"
        }
    ],
    "sg:menulink":"http://www.allmenus.com/mi/rochester-hills/58042-gold-star-family-restauant/menu/",
    "sg:phone":"+1 248 652 2478",
    "sg:postcode":"48307",
    "sg:province":"MI",
    "sg:tags":[
        "american",
        "diner"
    ],
    "wof:name":"Gold Star Family Restauant",
    "wof:placetype":"venue"
},
  "geometry": {"coordinates":[-83.13400900000001,42.671501],"type":"Point"}
}