{
  "type": "Feature",
  "properties": {
    "iso:country":"US",
    "sg:address":"23200 W 14 Mile Rd",
    "sg:city":"Bloomfield Hills",
    "sg:classifiers":[
        {
            "category":"Professional",
            "subcategory":"Art Services",
            "type":"Services"
        }
    ],
    "sg:phone":"+1 248 647 0011",
    "sg:postcode":"48301",
    "sg:province":"MI",
    "sg:tags":[
        "graphic",
        "designer"
    ],
    "wof:name":"Graphic House Inc",
    "wof:placetype":"venue"
},
  "geometry": {"coordinates":[-83.274187,42.530428],"type":"Point"}
}