{
  "type": "Feature",
  "properties": {
    "iso:country":"US",
    "sg:address":"6040 W Columbia Rd",
    "sg:city":"Mason",
    "sg:classifiers":[
        {
            "category":"Farming",
            "subcategory":"Livestock Farm",
            "type":"Manufacturing & Wholesale Goods"
        }
    ],
    "sg:phone":"+1 517 663 5549",
    "sg:postcode":"48854",
    "sg:province":"MI",
    "sg:tags":[
        "equine"
    ],
    "wof:name":"Crestview Farm",
    "wof:placetype":"venue"
},
  "geometry": {"coordinates":[-84.584349,42.582186],"type":"Point"}
}