{
  "type": "Feature",
  "properties": {
    "iso:country":"US",
    "sg:address":"3394 Sashabaw Rd",
    "sg:city":"Waterford",
    "sg:classifiers":[
        {
            "category":"Personal",
            "subcategory":"Beauty Salon",
            "type":"Services"
        }
    ],
    "sg:phone":"+1 248 673 2700",
    "sg:postcode":"48329",
    "sg:province":"MI",
    "sg:tags":[
        "shop"
    ],
    "wof:name":"Kathy's Hair Fashions",
    "wof:placetype":"venue"
},
  "geometry": {"coordinates":[-83.373057,42.687348],"type":"Point"}
}