{
  "type": "Feature",
  "properties": {
    "iso:country":"US",
    "sg:address":"211 S Main St",
    "sg:city":"Milford",
    "sg:classifiers":[
        {
            "category":"Autos & Motor Vehicles",
            "subcategory":"Automobile Sales",
            "type":"Retail Goods"
        }
    ],
    "sg:phone":"+1 248 684 6020",
    "sg:postcode":"48381",
    "sg:province":"MI",
    "sg:tags":[
        "car",
        "dealer"
    ],
    "wof:name":"Colonial Motors LTD",
    "wof:placetype":"venue"
},
  "geometry": {"coordinates":[-83.600341,42.585498],"type":"Point"}
}