{
  "type": "Feature",
  "properties": {
    "iso:country":"US",
    "sg:address":"17177 N Laurel Park Dr Ste 164",
    "sg:city":"Livonia",
    "sg:classifiers":[
        {
            "category":"Insurance",
            "subcategory":"Hazard Insurance",
            "type":"Services"
        }
    ],
    "sg:phone":"+1 734 591 0290",
    "sg:postcode":"48152",
    "sg:province":"MI",
    "sg:website":"www.laurelparkinsurance.com",
    "wof:name":"Laurel Park Insurance Agency Allstate",
    "wof:placetype":"venue"
},
  "geometry": {"coordinates":[-83.420536,42.413335],"type":"Point"}
}