{
  "type": "Feature",
  "properties": {
    "iso:country":"US",
    "sg:address":"409 W Midland St",
    "sg:city":"Bay City",
    "sg:classifiers":[
        {
            "category":"Professional",
            "subcategory":"Management & Consulting",
            "type":"Services"
        }
    ],
    "sg:phone":"+1 989 892 4011",
    "sg:postcode":"48706",
    "sg:province":"MI",
    "sg:tags":[
        "selling",
        "establishment",
        "direct"
    ],
    "wof:name":"Shaklee Distributor",
    "wof:placetype":"venue"
},
  "geometry": {"coordinates":[-83.908248,43.602019],"type":"Point"}
}