{
  "type": "Feature",
  "properties": {
    "iso:country":"US",
    "sg:address":"2449 Rockhill Dr NE",
    "sg:city":"Grand Rapids",
    "sg:classifiers":[
        {
            "category":"Professional",
            "subcategory":"Business Services",
            "type":"Services"
        }
    ],
    "sg:phone":"+1 616 361 6671",
    "sg:postcode":"49525",
    "sg:province":"MI",
    "wof:name":"Walenta Design",
    "wof:placetype":"venue"
},
  "geometry": {"coordinates":[-85.607844,43.05521],"type":"Point"}
}