{
  "type": "Feature",
  "properties": {
    "iso:country":"US",
    "sg:address":"115 White Pigeon St",
    "sg:city":"Constantine",
    "sg:classifiers":[
        {
            "category":"Government",
            "subcategory":"Police Station",
            "type":"Public Place"
        }
    ],
    "sg:phone":"+1 269 435 4355",
    "sg:postcode":"49042",
    "sg:province":"MI",
    "sg:tags":[
        "protection"
    ],
    "wof:name":"Constantine Police Department",
    "wof:placetype":"venue"
},
  "geometry": {"coordinates":[-85.667517,41.842495],"type":"Point"}
}