{
  "type": "Feature",
  "properties": {
    "iso:country":"US",
    "sg:address":"3477 N Tipsico Lake Rd",
    "sg:city":"Hartland",
    "sg:classifiers":[
        {
            "category":"Building & Trades",
            "subcategory":"Plumbing",
            "type":"Services"
        }
    ],
    "sg:phone":"+1 248 887 5141",
    "sg:postcode":"48353",
    "sg:province":"MI",
    "sg:tags":[
        "refrigeration",
        "contractor"
    ],
    "wof:name":"Hartland Refrigeration Svc NC",
    "wof:placetype":"venue"
},
  "geometry": {"coordinates":[-83.68063600000001,42.658378],"type":"Point"}
}