{
  "type": "Feature",
  "properties": {
    "iso:country":"US",
    "sg:address":"16010 Beaver Lake Pk Rd",
    "sg:city":"Lachine",
    "sg:classifiers":[
        {
            "category":"Real Estate",
            "subcategory":"Real Estate Agent",
            "type":"Services"
        }
    ],
    "sg:phone":"+1 989 379 9911",
    "sg:postcode":"49753",
    "sg:province":"MI",
    "wof:name":"Independence Real Estate Svc",
    "wof:placetype":"venue"
},
  "geometry": {"coordinates":[-83.78728599999999,44.929619],"type":"Point"}
}