{
  "type": "Feature",
  "properties": {
    "iso:country":"US",
    "sg:address":"3933 Fort St",
    "sg:city":"Lincoln Park",
    "sg:classifiers":[
        {
            "category":"Personal",
            "subcategory":"Beauty Salon",
            "type":"Services"
        }
    ],
    "sg:phone":"+1 313 928 6999",
    "sg:postcode":"48146",
    "sg:province":"MI",
    "sg:tags":[
        "shop"
    ],
    "wof:name":"Fantastic Sams",
    "wof:placetype":"venue"
},
  "geometry": {"coordinates":[-83.180711,42.227411],"type":"Point"}
}