{
  "type": "Feature",
  "properties": {
    "iso:country":"US",
    "sg:address":"1211 Woodside Ave",
    "sg:city":"Essexville",
    "sg:classifiers":[
        {
            "category":"Manufacturing",
            "subcategory":"Food",
            "type":"Manufacturing & Wholesale Goods"
        }
    ],
    "sg:phone":"+1 989 892 4856",
    "sg:postcode":"48732",
    "sg:province":"MI",
    "sg:tags":[
        "preparation"
    ],
    "sg:website":"www.americangourmetpretzel.com",
    "wof:name":"American Gourmet Of Snacks Inc",
    "wof:placetype":"venue"
},
  "geometry": {"coordinates":[-83.845107,43.613923],"type":"Point"}
}