{
  "type": "Feature",
  "properties": {
    "iso:country":"US",
    "sg:address":"1810 4th St",
    "sg:city":"Bay City",
    "sg:classifiers":[
        {
            "category":"Shopping",
            "type":"Retail Goods"
        }
    ],
    "sg:phone":"+1 989 893 9050",
    "sg:postcode":"48708",
    "sg:province":"MI",
    "sg:tags":[
        "craft",
        "gallery",
        "dealer"
    ],
    "wof:name":"Dock Of The Bay",
    "wof:placetype":"venue"
},
  "geometry": {"coordinates":[-83.870323,43.598648],"type":"Point"}
}