{
  "type": "Feature",
  "properties": {
    "iso:country":"US",
    "sg:address":"2184 S Homer Rd",
    "sg:city":"Midland",
    "sg:classifiers":[
        {
            "category":"Organizations",
            "subcategory":"Religious Organization",
            "type":"Services"
        }
    ],
    "sg:phone":"+1 989 832 3570",
    "sg:postcode":"48640",
    "sg:province":"MI",
    "wof:name":"Mt Haley Church Of God",
    "wof:placetype":"venue"
},
  "geometry": {"coordinates":[-84.330516,43.548977],"type":"Point"}
}