{
  "type": "Feature",
  "properties": {
    "iso:country":"US",
    "sg:address":"103 Commercial St",
    "sg:city":"Dowagiac",
    "sg:classifiers":[
        {
            "category":"Shopping",
            "subcategory":"Jewelry",
            "type":"Retail Goods"
        }
    ],
    "sg:phone":"+1 269 782 3383",
    "sg:postcode":"49047",
    "sg:province":"MI",
    "wof:name":"Rasmussen Goldsmith",
    "wof:placetype":"venue"
},
  "geometry": {"coordinates":[-86.10978799999999,41.982827],"type":"Point"}
}