{
  "type": "Feature",
  "properties": {
    "iso:country":"US",
    "sg:address":"23967 West Rd",
    "sg:city":"Brownstown",
    "sg:classifiers":[
        {
            "category":"Shopping",
            "subcategory":"Mobile Phones",
            "type":"Retail Goods"
        }
    ],
    "sg:phone":"+1 734 362 7200",
    "sg:postcode":"48134",
    "sg:province":"MI",
    "sg:website":"www.cellularadvantage.com",
    "wof:name":"Cellular Advantage",
    "wof:placetype":"venue"
},
  "geometry": {"coordinates":[-83.267403,42.138],"type":"Point"}
}