{
  "type": "Feature",
  "properties": {
    "iso:country":"US",
    "sg:address":"901 47th St SW",
    "sg:city":"Wyoming",
    "sg:classifiers":[
        {
            "category":"Manufacturing",
            "subcategory":"Tools & Machinery",
            "type":"Manufacturing & Wholesale Goods"
        }
    ],
    "sg:phone":"+1 616 531 1257",
    "sg:postcode":"49509",
    "sg:province":"MI",
    "sg:tags":[
        "mold"
    ],
    "wof:name":"General Die & Engineering",
    "wof:placetype":"venue"
},
  "geometry": {"coordinates":[-85.68619,42.879002],"type":"Point"}
}