{
  "type": "Feature",
  "properties": {
    "iso:country":"US",
    "sg:address":"3366 Johnson Ave",
    "sg:city":"Newaygo",
    "sg:classifiers":[
        {
            "category":"Building & Trades",
            "subcategory":"Construction",
            "type":"Services"
        }
    ],
    "sg:phone":"+1 231 856 4539",
    "sg:postcode":"49337",
    "sg:province":"MI",
    "sg:tags":[
        "contractor"
    ],
    "wof:name":"Rock Solid Construction",
    "wof:placetype":"venue"
},
  "geometry": {"coordinates":[-85.597734,43.494285],"type":"Point"}
}