{
  "type": "Feature",
  "properties": {
    "iso:country":"US",
    "sg:address":"20 3rd St",
    "sg:city":"Pentwater",
    "sg:classifiers":[
        {
            "category":"Restaurant",
            "type":"Food & Drink"
        }
    ],
    "sg:phone":"+1 231 869 6664",
    "sg:postcode":"49449",
    "sg:province":"MI",
    "sg:tags":[
        "pizza"
    ],
    "wof:name":"Pentwater Pizza's & Grinders",
    "wof:placetype":"venue"
},
  "geometry": {"coordinates":[-86.432637,43.779149],"type":"Point"}
}