{
  "type": "Feature",
  "properties": {
    "iso:country":"US",
    "sg:address":"7643 Division Ave S",
    "sg:city":"Grand Rapids",
    "sg:classifiers":[
        {
            "category":"Retail",
            "subcategory":"Auto Repair",
            "type":"Services"
        }
    ],
    "sg:phone":"+1 616 827 0860",
    "sg:postcode":"49548",
    "sg:province":"MI",
    "sg:tags":[
        "repairing",
        "automobile"
    ],
    "wof:name":"Auto AID",
    "wof:placetype":"venue"
},
  "geometry": {"coordinates":[-85.663646,42.826028],"type":"Point"}
}