{
  "type": "Feature",
  "properties": {
    "iso:country":"US",
    "sg:address":"18646 70th Ave",
    "sg:city":"Marion",
    "sg:classifiers":[
        {
            "category":"Manufacturing",
            "subcategory":"Wood Products",
            "type":"Manufacturing & Wholesale Goods"
        }
    ],
    "sg:phone":"+1 231 743 2171",
    "sg:postcode":"49665",
    "sg:province":"MI",
    "sg:tags":[
        "mfg"
    ],
    "wof:name":"North Country Woodworking",
    "wof:placetype":"venue"
},
  "geometry": {"coordinates":[-85.226358,44.074086],"type":"Point"}
}