{
  "type": "Feature",
  "properties": {
    "iso:country":"US",
    "sg:address":"838 N Mitchell St",
    "sg:city":"Cadillac",
    "sg:classifiers":[
        {
            "category":"Food & Beverages",
            "subcategory":"Bakery",
            "type":"Retail Goods"
        }
    ],
    "sg:phone":"+1 231 775 4629",
    "sg:postcode":"49601",
    "sg:province":"MI",
    "sg:tags":[
        "baker"
    ],
    "wof:name":"Wonder Hostess",
    "wof:placetype":"venue"
},
  "geometry": {"coordinates":[-85.40473900000001,44.256952],"type":"Point"}
}