{
  "type": "Feature",
  "properties": {
    "iso:country":"US",
    "sg:address":"10450 Camp Rd",
    "sg:city":"Central Lake",
    "sg:classifiers":[
        {
            "category":"Building & Trades",
            "subcategory":"Construction",
            "type":"Services"
        }
    ],
    "sg:phone":"+1 231 544 6040",
    "sg:postcode":"49622",
    "sg:province":"MI",
    "sg:tags":[
        "contractor"
    ],
    "wof:name":"Priemer Design & Construction",
    "wof:placetype":"venue"
},
  "geometry": {"coordinates":[-85.310971,45.053707],"type":"Point"}
}