{
  "type": "Feature",
  "properties": {
    "iso:country":"US",
    "sg:address":"38 E Elm Ave",
    "sg:city":"Monroe",
    "sg:classifiers":[
        {
            "category":"Professional",
            "type":"Services"
        }
    ],
    "sg:phone":"+1 734 243 6347",
    "sg:postcode":"48162",
    "sg:province":"MI",
    "wof:name":"Loomis Battery of Michigan",
    "wof:placetype":"venue"
},
  "geometry": {"coordinates":[-83.39577,41.917963],"type":"Point"}
}