{
  "type": "Feature",
  "properties": {
    "iso:country":"US",
    "sg:address":"1145 W Huron St",
    "sg:city":"Waterford",
    "sg:classifiers":[
        {
            "category":"Real Estate",
            "subcategory":"Real Estate Agent",
            "type":"Services"
        }
    ],
    "sg:phone":"+1 248 681 6449",
    "sg:postcode":"48328",
    "sg:province":"MI",
    "wof:name":"City Sales Co",
    "wof:placetype":"venue"
},
  "geometry": {"coordinates":[-83.333578,42.634897],"type":"Point"}
}