{
  "type": "Feature",
  "properties": {
    "iso:country":"US",
    "sg:address":"6785 Myers Lake Ave NE",
    "sg:city":"Rockford",
    "sg:classifiers":[
        {
            "category":"Health Services",
            "subcategory":"Podiatrist",
            "type":"Services"
        }
    ],
    "sg:phone":"+1 616 874 8772",
    "sg:postcode":"49341",
    "sg:province":"MI",
    "wof:name":"Kelley Michael J DPM",
    "wof:placetype":"venue"
},
  "geometry": {"coordinates":[-85.500298,43.085999],"type":"Point"}
}