{
  "type": "Feature",
  "properties": {
    "iso:country":"US",
    "sg:address":"1505 N Woodbridge St",
    "sg:city":"Saginaw",
    "sg:classifiers":[
        {
            "category":"Autos & Motor Vehicles",
            "subcategory":"Fuel & Gas Station",
            "type":"Retail Goods"
        }
    ],
    "sg:phone":"+1 989 752 6208",
    "sg:postcode":"48602",
    "sg:province":"MI",
    "sg:tags":[
        "oil"
    ],
    "wof:name":"Marathon Gas Station",
    "wof:placetype":"venue"
},
  "geometry": {"coordinates":[-83.96195,43.42995],"type":"Point"}
}