{
  "type": "Feature",
  "properties": {
    "iso:country":"US",
    "sg:address":"11205 Lawrence Hwy",
    "sg:city":"Nashville",
    "sg:classifiers":[
        {
            "category":"Building & Trades",
            "subcategory":"Construction",
            "type":"Services"
        }
    ],
    "sg:phone":"+1 517 852 1536",
    "sg:postcode":"49073",
    "sg:province":"MI",
    "sg:tags":[
        "excavating",
        "contractor"
    ],
    "wof:name":"Nashville Construction Co",
    "wof:placetype":"venue"
},
  "geometry": {"coordinates":[-85.057739,42.567147],"type":"Point"}
}