{
  "type": "Feature",
  "properties": {
    "iso:country":"US",
    "sg:address":"6930 Walker St",
    "sg:city":"Benzonia",
    "sg:classifiers":[
        {
            "category":"Manufacturing",
            "subcategory":"Printing",
            "type":"Manufacturing & Wholesale Goods"
        }
    ],
    "sg:phone":"+1 231 882 5000",
    "sg:postcode":"49616",
    "sg:province":"MI",
    "sg:tags":[
        "engraver",
        "wood"
    ],
    "wof:name":"Eclectic Engraving & Designs",
    "wof:placetype":"venue"
},
  "geometry": {"coordinates":[-86.099341,44.619543],"type":"Point"}
}