{
  "type": "Feature",
  "properties": {
    "iso:country":"US",
    "sg:address":"3645 Glenn Dr SE",
    "sg:city":"Grand Rapids",
    "sg:classifiers":[
        {
            "category":"Personal",
            "subcategory":"Beauty Salon",
            "type":"Services"
        }
    ],
    "sg:phone":"+1 616 940 1039",
    "sg:postcode":"49546",
    "sg:province":"MI",
    "sg:tags":[
        "shop"
    ],
    "wof:name":"J D Designs",
    "wof:placetype":"venue"
},
  "geometry": {"coordinates":[-85.58255699999999,42.954781],"type":"Point"}
}