{
  "type": "Feature",
  "properties": {
    "iso:country":"US",
    "sg:address":"23600 Van Dyke Ave",
    "sg:city":"Warren",
    "sg:classifiers":[
        {
            "category":"Autos & Motor Vehicles",
            "subcategory":"Auto Supplies",
            "type":"Retail Goods"
        }
    ],
    "sg:phone":"+1 586 757 6326",
    "sg:postcode":"48089",
    "sg:province":"MI",
    "sg:tags":[
        "repair",
        "r",
        "tire",
        "automotive"
    ],
    "wof:name":"Regal Tire Co",
    "wof:placetype":"venue"
},
  "geometry": {"coordinates":[-83.026703,42.467899],"type":"Point"}
}