{
  "type": "Feature",
  "properties": {
    "iso:country":"US",
    "sg:address":"174 E Pike St",
    "sg:city":"Pontiac",
    "sg:classifiers":[
        {
            "category":"Real Estate",
            "subcategory":"Real Estate Operator",
            "type":"Services"
        }
    ],
    "sg:phone":"+1 248 335 7148",
    "sg:postcode":"48342",
    "sg:province":"MI",
    "sg:tags":[
        "apartment"
    ],
    "wof:name":"Pontiac Townhouse Co-Op",
    "wof:placetype":"venue"
},
  "geometry": {"coordinates":[-83.28829399999999,42.637316],"type":"Point"}
}