{
  "type": "Feature",
  "properties": {
    "iso:country":"US",
    "sg:address":"143 W Chicago St",
    "sg:city":"Coldwater",
    "sg:classifiers":[
        {
            "category":"Shopping",
            "subcategory":"Florist",
            "type":"Retail Goods"
        }
    ],
    "sg:phone":"+1 517 279 7760",
    "sg:postcode":"49036",
    "sg:province":"MI",
    "wof:name":"Chicago Pike Florist",
    "wof:placetype":"venue"
},
  "geometry": {"coordinates":[-85.007524,41.941655],"type":"Point"}
}