{
  "type": "Feature",
  "properties": {
    "iso:country":"US",
    "sg:address":"1660 Inverness",
    "sg:city":"Keego Harbor",
    "sg:classifiers":[
        {
            "category":"Sports & Exercise",
            "subcategory":"Gym",
            "type":"Entertainment"
        }
    ],
    "sg:phone":"+1 248 623 4896",
    "sg:postcode":"48320",
    "sg:province":"MI",
    "sg:tags":[
        "fitness",
        "physical",
        "facility"
    ],
    "wof:name":"Leka Health & Fitness",
    "wof:placetype":"venue"
},
  "geometry": {"coordinates":[-83.33029399999999,42.614546],"type":"Point"}
}