{
  "type": "Feature",
  "properties": {
    "iso:country":"US",
    "sg:address":"1029 S Madison Ave",
    "sg:city":"Bay City",
    "sg:classifiers":[
        {
            "category":"Insurance",
            "subcategory":"Insurance Agent",
            "type":"Services"
        }
    ],
    "sg:phone":"+1 989 891 0337",
    "sg:postcode":"48708",
    "sg:province":"MI",
    "wof:name":"Schupback Assurance Group",
    "wof:placetype":"venue"
},
  "geometry": {"coordinates":[-83.885633,43.58013],"type":"Point"}
}