{
  "type": "Feature",
  "properties": {
    "iso:country":"US",
    "sg:address":"12521 James St",
    "sg:city":"Holland",
    "sg:classifiers":[
        {
            "category":"Insurance",
            "subcategory":"Insurance Agent",
            "type":"Services"
        }
    ],
    "sg:phone":"+1 616 738 8100",
    "sg:postcode":"49424",
    "sg:province":"MI",
    "wof:name":"LA Insurance",
    "wof:placetype":"venue"
},
  "geometry": {"coordinates":[-86.090722,42.812081],"type":"Point"}
}