{
  "type": "Feature",
  "properties": {
    "iso:country":"US",
    "sg:address":"6606 Roger Dr",
    "sg:city":"Jenison",
    "sg:classifiers":[
        {
            "category":"Arts & Performance",
            "subcategory":"Theater",
            "type":"Entertainment"
        }
    ],
    "sg:phone":"+1 616 662 7469",
    "sg:postcode":"49428",
    "sg:province":"MI",
    "sg:tags":[
        "entertainer",
        "business"
    ],
    "wof:name":"A Amazing Magic By PJ Weber",
    "wof:placetype":"venue"
},
  "geometry": {"coordinates":[-85.839095,42.889269],"type":"Point"}
}