{
  "type": "Feature",
  "properties": {
    "iso:country":"US",
    "sg:address":"183 E Beech St NE",
    "sg:city":"Cedar Springs",
    "sg:classifiers":[
        {
            "category":"Building & Trades",
            "subcategory":"Construction",
            "type":"Services"
        }
    ],
    "sg:phone":"+1 616 696 0842",
    "sg:postcode":"49319",
    "sg:province":"MI",
    "sg:tags":[
        "dry wall",
        "contractor"
    ],
    "wof:name":"Durst Drywall",
    "wof:placetype":"venue"
},
  "geometry": {"coordinates":[-85.54649000000001,43.221925],"type":"Point"}
}