{
  "type": "Feature",
  "properties": {
    "iso:country":"US",
    "sg:address":"2615 Wolcott St",
    "sg:city":"Ferndale",
    "sg:classifiers":[
        {
            "category":"Wholesale",
            "subcategory":"Auto Parts",
            "type":"Manufacturing & Wholesale Goods"
        }
    ],
    "sg:phone":"+1 248 543 1325",
    "sg:postcode":"48220",
    "sg:province":"MI",
    "sg:tags":[
        "automobile",
        "supply"
    ],
    "wof:name":"Nodelco",
    "wof:placetype":"venue"
},
  "geometry": {"coordinates":[-83.12727599999999,42.467884],"type":"Point"}
}