{
  "type": "Feature",
  "properties": {
    "iso:country":"US",
    "sg:address":"29840 Telegraph Rd",
    "sg:city":"Southfield",
    "sg:classifiers":[
        {
            "category":"Health Services",
            "subcategory":"Clinic",
            "type":"Services"
        }
    ],
    "sg:phone":"+1 248 356 6800",
    "sg:postcode":"48034",
    "sg:province":"MI",
    "wof:name":"Gentiva Health Services",
    "wof:placetype":"venue"
},
  "geometry": {"coordinates":[-83.285124,42.507114],"type":"Point"}
}