{
  "type": "Feature",
  "properties": {
    "iso:country":"US",
    "sg:address":"611 de Villen Ave",
    "sg:city":"Royal Oak",
    "sg:classifiers":[
        {
            "category":"Building & Trades",
            "subcategory":"Plumbing",
            "type":"Services"
        }
    ],
    "sg:phone":"+1 248 583 0648",
    "sg:postcode":"48073",
    "sg:province":"MI",
    "sg:tags":[
        "plumbing",
        "contractor"
    ],
    "wof:name":"Larry D Plumbing Co Inc",
    "wof:placetype":"venue"
},
  "geometry": {"coordinates":[-83.137927,42.515499],"type":"Point"}
}