{
  "type": "Feature",
  "properties": {
    "iso:country":"US",
    "sg:address":"208 W Ferry St",
    "sg:city":"Berrien Springs",
    "sg:classifiers":[
        {
            "category":"Insurance",
            "subcategory":"Insurance Agent",
            "type":"Services"
        }
    ],
    "sg:phone":"+1 269 473 3737",
    "sg:postcode":"49103",
    "sg:province":"MI",
    "wof:name":"Beall John CLU Chfc",
    "wof:placetype":"venue"
},
  "geometry": {"coordinates":[-86.33864800000001,41.946326],"type":"Point"}
}