{
  "type": "Feature",
  "properties": {
    "iso:country":"US",
    "sg:address":"6035 State Hwy 25",
    "sg:city":"Akron",
    "sg:classifiers":[
        {
            "category":"Recreation",
            "subcategory":"Marina",
            "type":"Entertainment"
        }
    ],
    "sg:phone":"+1 989 691 5241",
    "sg:postcode":"48701",
    "sg:province":"MI",
    "sg:tags":[
        "operation",
        "boat"
    ],
    "wof:name":"Sunset Bay Marina Inc",
    "wof:placetype":"venue"
},
  "geometry": {"coordinates":[-83.584673,43.615967],"type":"Point"}
}