{
  "type": "Feature",
  "properties": {
    "iso:country":"US",
    "sg:address":"9304 Oakland St",
    "sg:city":"Detroit",
    "sg:classifiers":[
        {
            "category":"Organizations",
            "subcategory":"Religious Organization",
            "type":"Services"
        }
    ],
    "sg:phone":"+1 313 867 3889",
    "sg:postcode":"48211",
    "sg:province":"MI",
    "wof:name":"Greater Ephesian Baptst Church",
    "wof:placetype":"venue"
},
  "geometry": {"coordinates":[-83.073723,42.387663],"type":"Point"}
}