{
  "type": "Feature",
  "properties": {
    "iso:country":"US",
    "sg:address":"7364 Adams St",
    "sg:city":"Zeeland",
    "sg:classifiers":[
        {
            "category":"Farming",
            "subcategory":"Nursery",
            "type":"Manufacturing & Wholesale Goods"
        }
    ],
    "sg:phone":"+1 616 688 5209",
    "sg:postcode":"49464",
    "sg:province":"MI",
    "sg:tags":[
        "greenhouse"
    ],
    "wof:name":"Windridge Greenhouse",
    "wof:placetype":"venue"
},
  "geometry": {"coordinates":[-85.963983,42.783139],"type":"Point"}
}