{
  "type": "Feature",
  "properties": {
    "iso:country":"US",
    "sg:address":"1120 E Oakland Ave",
    "sg:city":"Lansing",
    "sg:classifiers":[
        {
            "category":"Organizations",
            "subcategory":"Professional Association",
            "type":"Services"
        }
    ],
    "sg:phone":"+1 517 484 0016",
    "sg:postcode":"48906",
    "sg:province":"MI",
    "wof:name":"Michigan Interfaith Council",
    "wof:placetype":"venue"
},
  "geometry": {"coordinates":[-84.53489,42.743512],"type":"Point"}
}