{
  "type": "Feature",
  "properties": {
    "iso:country":"US",
    "sg:address":"8389 S 39 Rd",
    "sg:city":"Cadillac",
    "sg:classifiers":[
        {
            "category":"Organizations",
            "subcategory":"Religious Organization",
            "type":"Services"
        }
    ],
    "sg:phone":"+1 231 775 4585",
    "sg:postcode":"49601",
    "sg:province":"MI",
    "sg:tags":[
        "church"
    ],
    "wof:name":"Church Of Jesus Christ Of Lds",
    "wof:placetype":"venue"
},
  "geometry": {"coordinates":[-85.43617,44.217965],"type":"Point"}
}