{
  "type": "Feature",
  "properties": {
    "iso:country":"US",
    "sg:address":"401 S Euclid Ave",
    "sg:city":"Bay City",
    "sg:classifiers":[
        {
            "category":"Health Services",
            "subcategory":"Doctor",
            "type":"Services"
        }
    ],
    "sg:phone":"+1 989 667 0491",
    "sg:postcode":"48706",
    "sg:province":"MI",
    "sg:tags":[
        "clinic"
    ],
    "wof:name":"Redi Med",
    "wof:placetype":"venue"
},
  "geometry": {"coordinates":[-83.915357,43.597463],"type":"Point"}
}