{
  "type": "Feature",
  "properties": {
    "iso:country":"US",
    "sg:address":"1702 E M-43 Hwy",
    "sg:city":"Freeport",
    "sg:classifiers":[
        {
            "category":"Farming",
            "subcategory":"Farm",
            "type":"Manufacturing & Wholesale Goods"
        }
    ],
    "sg:phone":"+1 269 945 4830",
    "sg:postcode":"49325",
    "sg:province":"MI",
    "sg:tags":[
        "bean",
        "crop",
        "general"
    ],
    "wof:name":"Riverside Grain Co",
    "wof:placetype":"venue"
},
  "geometry": {"coordinates":[-85.25830499999999,42.726511],"type":"Point"}
}