{
  "type": "Feature",
  "properties": {
    "iso:country":"US",
    "sg:address":"230 E Front St",
    "sg:city":"Traverse City",
    "sg:classifiers":[
        {
            "category":"Food & Beverages",
            "subcategory":"Specialty",
            "type":"Retail Goods"
        }
    ],
    "sg:phone":"+1 231 935 4480",
    "sg:postcode":"49684",
    "sg:province":"MI",
    "sg:tags":[
        "gourmet",
        "shop"
    ],
    "wof:name":"American Spoon Foods",
    "wof:placetype":"venue"
},
  "geometry": {"coordinates":[-85.620403,44.763989],"type":"Point"}
}