{
  "type": "Feature",
  "properties": {
    "iso:country":"US",
    "sg:address":"2574 S Benedict Rd",
    "sg:city":"Ludington",
    "sg:classifiers":[
        {
            "category":"Wholesale",
            "subcategory":"Plants",
            "type":"Manufacturing & Wholesale Goods"
        }
    ],
    "sg:phone":"+1 231 843 4111",
    "sg:postcode":"49431",
    "sg:province":"MI",
    "sg:tags":[
        "supply"
    ],
    "wof:name":"Stanley Peterson Tree Orders",
    "wof:placetype":"venue"
},
  "geometry": {"coordinates":[-86.389579,43.911517],"type":"Point"}
}