{
  "type": "Feature",
  "properties": {
    "iso:country":"US",
    "sg:address":"204 E Grand River Ave",
    "sg:city":"Williamston",
    "sg:classifiers":[
        {
            "category":"Ice Cream",
            "type":"Food & Drink"
        }
    ],
    "sg:menulink":"http://www.allmenus.com/mi/williamston/168192-dairy-queen/menu/",
    "sg:phone":"+1 517 655 1739",
    "sg:postcode":"48895",
    "sg:province":"MI",
    "sg:tags":[
        "burger",
        "american"
    ],
    "wof:name":"Dairy Queen",
    "wof:placetype":"venue"
},
  "geometry": {"coordinates":[-84.280956,42.688777],"type":"Point"}
}