{
  "type": "Feature",
  "properties": {
    "iso:country":"US",
    "sg:address":"5626 Woodstock Dr",
    "sg:city":"Lansing",
    "sg:classifiers":[
        {
            "category":"Professional",
            "type":"Services"
        }
    ],
    "sg:phone":"+1 517 321 9783",
    "sg:postcode":"48917",
    "sg:province":"MI",
    "wof:name":"Crafty Creations",
    "wof:placetype":"venue"
},
  "geometry": {"coordinates":[-84.629109,42.748899],"type":"Point"}
}