{
  "type": "Feature",
  "properties": {
    "iso:country":"US",
    "sg:address":"34165 Autry St",
    "sg:city":"Livonia",
    "sg:classifiers":[
        {
            "category":"Manufacturing",
            "subcategory":"Motor Vehicles & Parts",
            "type":"Manufacturing & Wholesale Goods"
        }
    ],
    "sg:phone":"+1 734 261 9474",
    "sg:postcode":"48150",
    "sg:province":"MI",
    "sg:tags":[
        "body",
        "auto",
        "mfg"
    ],
    "wof:name":"American Sun Roof",
    "wof:placetype":"venue"
},
  "geometry": {"coordinates":[-83.379392,42.38019],"type":"Point"}
}