{
  "type": "Feature",
  "properties": {
    "iso:country":"US",
    "sg:address":"1694 E White Lake Dr",
    "sg:city":"Twin Lake",
    "sg:classifiers":[
        {
            "category":"Building & Trades",
            "subcategory":"Cleaning & Sanitation",
            "type":"Services"
        }
    ],
    "sg:phone":"+1 231 828 4039",
    "sg:postcode":"49457",
    "sg:province":"MI",
    "sg:tags":[
        "fireplace",
        "chimney"
    ],
    "wof:name":"Ye Old Chimney Svc LTD",
    "wof:placetype":"venue"
},
  "geometry": {"coordinates":[-86.200035,43.382855],"type":"Point"}
}