{
  "type": "Feature",
  "properties": {
    "iso:country":"US",
    "sg:address":"5110 Anthony Wayne Dr",
    "sg:city":"Detroit",
    "sg:classifiers":[
        {
            "category":"Food & Beverages",
            "subcategory":"Bakery",
            "type":"Retail Goods"
        }
    ],
    "sg:phone":"+1 313 832 7614",
    "sg:postcode":"48202",
    "sg:province":"MI",
    "sg:tags":[
        "sandwich"
    ],
    "wof:name":"Jimmy John's Gourmet Sandwich Shop",
    "wof:placetype":"venue"
},
  "geometry": {"coordinates":[-83.07168,42.355935],"type":"Point"}
}