{
  "type": "Feature",
  "properties": {
    "iso:country":"US",
    "sg:address":"908 W Silver Lake Rd S",
    "sg:city":"Traverse City",
    "sg:classifiers":[
        {
            "category":"Freight",
            "type":"Transportation"
        }
    ],
    "sg:phone":"+1 231 943 9219",
    "sg:postcode":"49684",
    "sg:province":"MI",
    "sg:tags":[
        "operator",
        "trucking"
    ],
    "wof:name":"William Moyer",
    "wof:placetype":"venue"
},
  "geometry": {"coordinates":[-85.68994499999999,44.674159],"type":"Point"}
}