{
  "type": "Feature",
  "properties": {
    "iso:country":"US",
    "sg:address":"496 Marion St",
    "sg:city":"Ypsilanti",
    "sg:classifiers":[
        {
            "category":"Professional",
            "subcategory":"Business Services",
            "type":"Services"
        }
    ],
    "sg:phone":"+1 734 547 0527",
    "sg:postcode":"48197",
    "sg:province":"MI",
    "wof:name":"Nancy Harvey Designs",
    "wof:placetype":"venue"
},
  "geometry": {"coordinates":[-83.639546,42.246449],"type":"Point"}
}