{
  "type": "Feature",
  "properties": {
    "iso:country":"US",
    "sg:address":"4700 N Ainger Rd",
    "sg:city":"Charlotte",
    "sg:classifiers":[
        {
            "category":"Professional",
            "subcategory":"Accounting & Tax Preparation",
            "type":"Services"
        }
    ],
    "sg:phone":"+1 517 726 1127",
    "sg:postcode":"48813",
    "sg:province":"MI",
    "wof:name":"Organizing For You",
    "wof:placetype":"venue"
},
  "geometry": {"coordinates":[-84.93454300000001,42.639796],"type":"Point"}
}