{
  "type": "Feature",
  "properties": {
    "iso:country":"US",
    "sg:address":"31701 Sikon St",
    "sg:city":"Chesterfield",
    "sg:classifiers":[
        {
            "category":"Wholesale",
            "subcategory":"Machinery & Supplies",
            "type":"Manufacturing & Wholesale Goods"
        }
    ],
    "sg:phone":"+1 586 948 5000",
    "sg:postcode":"48047",
    "sg:province":"MI",
    "sg:tags":[
        "equipment",
        "plastic"
    ],
    "sg:website":"www.water-assist.com",
    "wof:name":"Alliance Gas Systems",
    "wof:placetype":"venue"
},
  "geometry": {"coordinates":[-82.788357,42.669564],"type":"Point"}
}