{
  "type": "Feature",
  "properties": {
    "iso:country":"US",
    "sg:address":"3181 Bradford St NE",
    "sg:city":"Grand Rapids",
    "sg:classifiers":[
        {
            "category":"Organizations",
            "subcategory":"Religious Organization",
            "type":"Services"
        }
    ],
    "sg:phone":"+1 616 940 0554",
    "sg:postcode":"49525",
    "sg:province":"MI",
    "sg:tags":[
        "church"
    ],
    "sg:website":"www.vor.org/truth",
    "wof:name":"Reformed Baptist Church",
    "wof:placetype":"venue"
},
  "geometry": {"coordinates":[-85.592231,42.97721],"type":"Point"}
}