{
  "type": "Feature",
  "properties": {
    "iso:country":"US",
    "sg:address":"4294 Saint Antoine St",
    "sg:city":"Detroit",
    "sg:classifiers":[
        {
            "category":"Professional",
            "subcategory":"Business Services",
            "type":"Services"
        }
    ],
    "sg:phone":"+1 313 831 5470",
    "sg:postcode":"48201",
    "sg:province":"MI",
    "wof:name":"V Blessing",
    "wof:placetype":"venue"
},
  "geometry": {"coordinates":[-83.05297299999999,42.350499],"type":"Point"}
}