{
  "type": "Feature",
  "properties": {
    "iso:country":"US",
    "sg:address":"2700 N Peshabestown Rd",
    "sg:city":"Suttons Bay",
    "sg:classifiers":[
        {
            "category":"Professional",
            "subcategory":"Lawyer & Legal Services",
            "type":"Services"
        }
    ],
    "sg:phone":"+1 231 271 6550",
    "sg:postcode":"49682",
    "sg:province":"MI",
    "sg:tags":[
        "attorney"
    ],
    "wof:name":"William Gregory",
    "wof:placetype":"venue"
},
  "geometry": {"coordinates":[-85.628276,45.021607],"type":"Point"}
}