{
  "type": "Feature",
  "properties": {
    "iso:country":"US",
    "sg:address":"28035 Southfield Rd",
    "sg:city":"Southfield",
    "sg:classifiers":[
        {
            "category":"Professional",
            "subcategory":"Business Services",
            "type":"Services"
        }
    ],
    "sg:phone":"+1 248 443 8073",
    "sg:postcode":"48076",
    "sg:province":"MI",
    "sg:tags":[
        "print",
        "screen",
        "silk",
        "embossing",
        "embroidery"
    ],
    "wof:name":"Bam Wearables Inc",
    "wof:placetype":"venue"
},
  "geometry": {"coordinates":[-83.22234400000001,42.496091],"type":"Point"}
}