{
  "type": "Feature",
  "properties": {
    "iso:country":"US",
    "sg:address":"11901 Longsdorf St",
    "sg:city":"Wyandotte",
    "sg:classifiers":[
        {
            "category":"Freight",
            "type":"Transportation"
        }
    ],
    "sg:phone":"+1 734 281 2588",
    "sg:postcode":"48193",
    "sg:province":"MI",
    "sg:tags":[
        "warehouse"
    ],
    "wof:name":"Milltech Inc",
    "wof:placetype":"venue"
},
  "geometry": {"coordinates":[-83.170901,42.177811],"type":"Point"}
}