{
  "type": "Feature",
  "properties": {
    "iso:country":"US",
    "sg:address":"1460 E Pierson Rd",
    "sg:city":"Flushing",
    "sg:classifiers":[
        {
            "category":"Organizations",
            "subcategory":"Community Association",
            "type":"Services"
        }
    ],
    "sg:phone":"+1 810 659 5896",
    "sg:postcode":"48433",
    "sg:province":"MI",
    "wof:name":"Spruced Moose",
    "wof:placetype":"venue"
},
  "geometry": {"coordinates":[-83.81989,43.060092],"type":"Point"}
}