{
  "type": "Feature",
  "properties": {
    "iso:country":"US",
    "sg:address":"2976 Okemos Rd",
    "sg:city":"Mason",
    "sg:classifiers":[
        {
            "category":"Building & Trades",
            "subcategory":"Construction",
            "type":"Services"
        }
    ],
    "sg:phone":"+1 517 349 1177",
    "sg:postcode":"48854",
    "sg:province":"MI",
    "sg:tags":[
        "roofing",
        "contractor"
    ],
    "wof:name":"Peaks & Valleys Roofing Co",
    "wof:placetype":"venue"
},
  "geometry": {"coordinates":[-84.43281,42.665388],"type":"Point"}
}