{
  "type": "Feature",
  "properties": {
    "iso:country":"US",
    "sg:address":"2910 Churchill Rd",
    "sg:city":"Leslie",
    "sg:classifiers":[
        {
            "category":"Manufacturing",
            "subcategory":"Paper Products",
            "type":"Manufacturing & Wholesale Goods"
        }
    ],
    "sg:phone":"+1 517 589 9066",
    "sg:postcode":"49251",
    "sg:province":"MI",
    "sg:tags":[
        "stationery",
        "mfg"
    ],
    "wof:name":"Life Plus Legacy",
    "wof:placetype":"venue"
},
  "geometry": {"coordinates":[-84.444272,42.498857],"type":"Point"}
}