{
  "type": "Feature",
  "properties": {
    "iso:country":"US",
    "sg:address":"29244 York St",
    "sg:city":"Inkster",
    "sg:classifiers":[
        {
            "category":"Social Services",
            "type":"Services"
        }
    ],
    "sg:phone":"+1 734 723 7713",
    "sg:postcode":"48141",
    "sg:province":"MI",
    "sg:tags":[
        "outreach"
    ],
    "wof:name":"Helping Hands of Inkster",
    "wof:placetype":"venue"
},
  "geometry": {"coordinates":[-83.328011,42.276025],"type":"Point"}
}