{
  "type": "Feature",
  "properties": {
    "iso:country":"US",
    "sg:address":"9949 McGregor Rd",
    "sg:city":"Pinckney",
    "sg:classifiers":[
        {
            "category":"Organizations",
            "subcategory":"Religious Organization",
            "type":"Services"
        }
    ],
    "sg:phone":"+1 734 426 0933",
    "sg:postcode":"48169",
    "sg:province":"MI",
    "sg:tags":[
        "church"
    ],
    "wof:name":"Christian House Of Prayer",
    "wof:placetype":"venue"
},
  "geometry": {"coordinates":[-83.909847,42.414471],"type":"Point"}
}