{
  "type": "Feature",
  "properties": {
    "iso:country":"US",
    "sg:address":"2605 N Branch Rd",
    "sg:city":"North Branch",
    "sg:classifiers":[
        {
            "category":"Building & Trades",
            "subcategory":"Construction",
            "type":"Services"
        }
    ],
    "sg:phone":"+1 810 688 2905",
    "sg:postcode":"48461",
    "sg:province":"MI",
    "sg:tags":[
        "contractor"
    ],
    "wof:name":"James A Grant Builders",
    "wof:placetype":"venue"
},
  "geometry": {"coordinates":[-83.248,43.228429],"type":"Point"}
}