{
  "type": "Feature",
  "properties": {
    "iso:country":"US",
    "sg:address":"1180 Matt Urban Dr",
    "sg:city":"Holland",
    "sg:classifiers":[
        {
            "category":"Real Estate",
            "subcategory":"Real Estate Operator",
            "type":"Services"
        }
    ],
    "sg:phone":"+1 616 393 2030",
    "sg:postcode":"49423",
    "sg:province":"MI",
    "sg:tags":[
        "building",
        "apartment"
    ],
    "sg:website":"www.theapartment4u.com",
    "wof:name":"Crown Pointe Apartments",
    "wof:placetype":"venue"
},
  "geometry": {"coordinates":[-86.118765,42.754373],"type":"Point"}
}