{
  "type": "Feature",
  "properties": {
    "iso:country":"US",
    "sg:address":"69306 N Main St",
    "sg:city":"Richmond",
    "sg:classifiers":[
        {
            "category":"Banks & Credit Unions",
            "subcategory":"Bank",
            "type":"Services"
        }
    ],
    "sg:phone":"+1 586 727 7581",
    "sg:postcode":"48062",
    "sg:province":"MI",
    "wof:name":"National City Bank",
    "wof:placetype":"venue"
},
  "geometry": {"coordinates":[-82.757471,42.811494],"type":"Point"}
}