{
  "type": "Feature",
  "properties": {
    "iso:country":"US",
    "sg:address":"4566 W US Hwy 10",
    "sg:city":"Ludington",
    "sg:classifiers":[
        {
            "category":"Banks & Credit Unions",
            "subcategory":"Bank",
            "type":"Services"
        }
    ],
    "sg:phone":"+1 231 843 2601",
    "sg:postcode":"49431",
    "sg:province":"MI",
    "wof:name":"National City Bank",
    "wof:placetype":"venue"
},
  "geometry": {"coordinates":[-86.394363,43.955599],"type":"Point"}
}