{
  "type": "Feature",
  "properties": {
    "iso:country":"US",
    "sg:address":"2907 Tipton Hwy",
    "sg:city":"Adrian",
    "sg:classifiers":[
        {
            "category":"Government",
            "subcategory":"Office",
            "type":"Public Place"
        }
    ],
    "sg:phone":"+1 517 263 7920",
    "sg:postcode":"49221",
    "sg:province":"MI",
    "sg:tags":[
        "village"
    ],
    "wof:name":"Adrian Township Hall",
    "wof:placetype":"venue"
},
  "geometry": {"coordinates":[-84.064898,41.92569],"type":"Point"}
}