{
  "type": "Feature",
  "properties": {
    "iso:country":"US",
    "sg:address":"3117 W Brocker Rd",
    "sg:city":"Metamora",
    "sg:classifiers":[
        {
            "category":"Farming",
            "subcategory":"Farm",
            "type":"Manufacturing & Wholesale Goods"
        }
    ],
    "sg:phone":"+1 810 797 4695",
    "sg:postcode":"48455",
    "sg:province":"MI",
    "sg:tags":[
        "crop",
        "general"
    ],
    "wof:name":"Ella June Clark",
    "wof:placetype":"venue"
},
  "geometry": {"coordinates":[-83.342191,42.911703],"type":"Point"}
}