{
  "type": "Feature",
  "properties": {
    "iso:country":"US",
    "sg:address":"1830 W Square Lake Rd",
    "sg:city":"Bloomfield Hills",
    "sg:classifiers":[
        {
            "category":"Social Services",
            "subcategory":"Child Care",
            "type":"Services"
        },
        {
            "category":"Education",
            "subcategory":"Preschool",
            "type":"Public Place"
        },
        {
            "category":"Education",
            "subcategory":"School",
            "type":"Public Place"
        }
    ],
    "sg:phone":"+1 248 338 8383",
    "sg:postcode":"48302",
    "sg:province":"MI",
    "sg:tags":[
        "elementary",
        "day"
    ],
    "wof:name":"Unity Montessori & Day Care",
    "wof:placetype":"venue"
},
  "geometry": {"coordinates":[-83.315201,42.604698],"type":"Point"}
}