{
  "type": "Feature",
  "properties": {
    "iso:country":"US",
    "sg:address":"1224 Jenks St",
    "sg:city":"Port Huron",
    "sg:classifiers":[
        {
            "category":"Taxi",
            "type":"Transportation"
        }
    ],
    "sg:phone":"+1 810 984 1515",
    "sg:postcode":"48060",
    "sg:province":"MI",
    "sg:tags":[
        "taxicab"
    ],
    "wof:name":"Acme Cab Co",
    "wof:placetype":"venue"
},
  "geometry": {"coordinates":[-82.436869,42.976076],"type":"Point"}
}