{
  "type": "Feature",
  "properties": {
    "iso:country":"US",
    "sg:address":"28650 W 11 Mile Rd",
    "sg:city":"Farmington Hills",
    "sg:classifiers":[
        {
            "category":"Education",
            "subcategory":"School",
            "type":"Public Place"
        }
    ],
    "sg:phone":"+1 248 427 1906",
    "sg:postcode":"48336",
    "sg:province":"MI",
    "wof:name":"Oakland International Academy",
    "wof:placetype":"venue"
},
  "geometry": {"coordinates":[-83.331226,42.485404],"type":"Point"}
}