{
  "type": "Feature",
  "properties": {
    "iso:country":"US",
    "sg:address":"2422 N 5th St",
    "sg:city":"Kalamazoo",
    "sg:classifiers":[
        {
            "category":"Building & Trades",
            "subcategory":"Construction",
            "type":"Services"
        }
    ],
    "sg:phone":"+1 269 217 4534",
    "sg:postcode":"49009",
    "sg:province":"MI",
    "sg:tags":[
        "house"
    ],
    "wof:name":"Dennis King Contracting",
    "wof:placetype":"venue"
},
  "geometry": {"coordinates":[-85.720834,42.313732],"type":"Point"}
}