{
  "type": "Feature",
  "properties": {
    "iso:country":"US",
    "sg:address":"22320 Goddard Rd",
    "sg:city":"Taylor",
    "sg:classifiers":[
        {
            "category":"Shopping",
            "subcategory":"Optical Goods",
            "type":"Retail Goods"
        },
        {
            "category":"Health Services",
            "subcategory":"Optometrist",
            "type":"Services"
        },
        {
            "category":"Shopping",
            "subcategory":"Optician",
            "type":"Retail Goods"
        }
    ],
    "sg:phone":"+1 313 299 8870",
    "sg:postcode":"48180",
    "sg:province":"MI",
    "sg:tags":[
        "lens",
        "eyeglass",
        "contact",
        "eyewear",
        "ophthalmologist"
    ],
    "sg:website":"www.svsvision.com",
    "wof:name":"Svs Vision",
    "wof:placetype":"venue"
},
  "geometry": {"coordinates":[-83.253159,42.227093],"type":"Point"}
}