{
  "type": "Feature",
  "properties": {
    "iso:country":"US",
    "sg:address":"130 E Main St",
    "sg:city":"Homer",
    "sg:classifiers":[
        {
            "category":"Government",
            "subcategory":"Office",
            "type":"Public Place"
        }
    ],
    "sg:phone":"+1 517 568 4321",
    "sg:postcode":"49245",
    "sg:province":"MI",
    "sg:tags":[
        "village"
    ],
    "wof:name":"Homer Clerk's Office",
    "wof:placetype":"venue"
},
  "geometry": {"coordinates":[-84.80674399999999,42.145708],"type":"Point"}
}