{
  "type": "Feature",
  "properties": {
    "iso:country":"US",
    "sg:address":"5316 Clyde Park Ave SW",
    "sg:city":"Wyoming",
    "sg:classifiers":[
        {
            "category":"Shopping",
            "subcategory":"Department Store",
            "type":"Retail Goods"
        }
    ],
    "sg:phone":"+1 616 261 4362",
    "sg:postcode":"49509",
    "sg:province":"MI",
    "sg:tags":[
        "shop"
    ],
    "wof:name":"Dollar Stretcher",
    "wof:placetype":"venue"
},
  "geometry": {"coordinates":[-85.68388,42.86823],"type":"Point"}
}