{
  "type": "Feature",
  "properties": {
    "iso:country":"US",
    "sg:address":"1026 Sheridan Dr",
    "sg:city":"Kalamazoo",
    "sg:classifiers":[
        {
            "category":"Social Services",
            "subcategory":"Adult Care",
            "type":"Services"
        }
    ],
    "sg:phone":"+1 269 226 9363",
    "sg:postcode":"49001",
    "sg:province":"MI",
    "sg:tags":[
        "home",
        "residential"
    ],
    "wof:name":"Pomeroy House",
    "wof:placetype":"venue"
},
  "geometry": {"coordinates":[-85.56552499999999,42.261314],"type":"Point"}
}