{
  "type": "Feature",
  "properties": {
    "iso:country":"US",
    "sg:address":"32581 Northwestern Hwy",
    "sg:city":"Farmington Hills",
    "sg:classifiers":[
        {
            "category":"Retail",
            "subcategory":"Auto Repair",
            "type":"Services"
        }
    ],
    "sg:phone":"+1 248 737 7122",
    "sg:postcode":"48334",
    "sg:province":"MI",
    "sg:tags":[
        "body",
        "shop"
    ],
    "wof:name":"Maxie Collision Inc",
    "wof:placetype":"venue"
},
  "geometry": {"coordinates":[-83.35271,42.52578],"type":"Point"}
}