{
  "type": "Feature",
  "properties": {
    "iso:country":"US",
    "sg:address":"3303 Remembrance Rd NW",
    "sg:city":"Grand Rapids",
    "sg:classifiers":[
        {
            "category":"Shopping",
            "subcategory":"Bicycles & Sporting Goods",
            "type":"Retail Goods"
        }
    ],
    "sg:phone":"+1 616 791 2311",
    "sg:postcode":"49534",
    "sg:province":"MI",
    "wof:name":"Stream & Lake Tackle",
    "wof:placetype":"venue"
},
  "geometry": {"coordinates":[-85.74975499999999,42.987832],"type":"Point"}
}