{
  "type": "Feature",
  "properties": {
    "iso:country":"US",
    "sg:address":"610 Charbon Eau Ln",
    "sg:city":"Gaylord",
    "sg:classifiers":[
        {
            "category":"Social Services",
            "subcategory":"Adult Care",
            "type":"Services"
        }
    ],
    "sg:phone":"+1 989 732 4749",
    "sg:postcode":"49735",
    "sg:province":"MI",
    "sg:tags":[
        "foster"
    ],
    "wof:name":"Kucharek Adult Foster Care",
    "wof:placetype":"venue"
},
  "geometry": {"coordinates":[-84.67913799999999,44.998548],"type":"Point"}
}