{
  "type": "Feature",
  "properties": {
    "iso:country":"US",
    "sg:address":"8900 E Jefferson Ave Ste 2",
    "sg:city":"Detroit",
    "sg:classifiers":[
        {
            "category":"Food & Beverages",
            "subcategory":"Groceries & Convenience Stores",
            "type":"Retail Goods"
        }
    ],
    "sg:phone":"+1 313 823 1010",
    "sg:postcode":"48214",
    "sg:province":"MI",
    "wof:name":"River Front House Market",
    "wof:placetype":"venue"
},
  "geometry": {"coordinates":[-82.984568,42.35455],"type":"Point"}
}