{
  "type": "Feature",
  "properties": {
    "iso:country":"US",
    "sg:address":"1416 Hill St",
    "sg:city":"Ann Arbor",
    "sg:classifiers":[
        {
            "category":"Real Estate",
            "subcategory":"Real Estate Agent",
            "type":"Services"
        }
    ],
    "sg:phone":"+1 734 761 7435",
    "sg:postcode":"48104",
    "sg:province":"MI",
    "sg:tags":[
        "organization",
        "religious"
    ],
    "wof:name":"Friends Meeting House Inc",
    "wof:placetype":"venue"
},
  "geometry": {"coordinates":[-83.73003,42.272263],"type":"Point"}
}