{
  "type": "Feature",
  "properties": {
    "iso:country":"US",
    "sg:address":"625 Quincy St",
    "sg:city":"Hancock",
    "sg:classifiers":[
        {
            "category":"Autos & Motor Vehicles",
            "subcategory":"Automobile Sales",
            "type":"Retail Goods"
        }
    ],
    "sg:phone":"+1 906 482 0620",
    "sg:postcode":"49930",
    "sg:province":"MI",
    "sg:tags":[
        "car",
        "dealer"
    ],
    "wof:name":"Northern Auto Inc",
    "wof:placetype":"venue"
},
  "geometry": {"coordinates":[-88.59106,47.126618],"type":"Point"}
}