{
  "type": "Feature",
  "properties": {
    "iso:country":"US",
    "sg:address":"12377 Linden Ave",
    "sg:city":"Sawyer",
    "sg:classifiers":[
        {
            "category":"Building & Trades",
            "subcategory":"Cleaning & Sanitation",
            "type":"Services"
        }
    ],
    "sg:phone":"+1 269 426 8528",
    "sg:postcode":"49125",
    "sg:province":"MI",
    "sg:tags":[
        "janitor"
    ],
    "wof:name":"Sabrina's The Cleaning Svc",
    "wof:placetype":"venue"
},
  "geometry": {"coordinates":[-86.600747,41.896255],"type":"Point"}
}