{
  "type": "Feature",
  "properties": {
    "iso:country":"US",
    "sg:address":"5206 Carpenter Rd",
    "sg:city":"Kinde",
    "sg:classifiers":[
        {
            "category":"Real Estate",
            "subcategory":"Real Estate Operator",
            "type":"Services"
        }
    ],
    "sg:phone":"+1 989 874 4784",
    "sg:postcode":"48445",
    "sg:province":"MI",
    "sg:tags":[
        "property",
        "lessor"
    ],
    "wof:name":"Sylvester Polega",
    "wof:placetype":"venue"
},
  "geometry": {"coordinates":[-82.945553,43.948853],"type":"Point"}
}