{
  "type": "Feature",
  "properties": {
    "iso:country":"US",
    "sg:address":"630 S Ortonville Rd",
    "sg:city":"Ortonville",
    "sg:classifiers":[
        {
            "category":"Banks & Credit Unions",
            "subcategory":"Investment Brokerage",
            "type":"Services"
        }
    ],
    "sg:phone":"+1 248 627 7170",
    "sg:postcode":"48462",
    "sg:province":"MI",
    "sg:tags":[
        "advisory",
        "financial"
    ],
    "wof:name":"Sure Financial",
    "wof:placetype":"venue"
},
  "geometry": {"coordinates":[-83.447838,42.841905],"type":"Point"}
}