{
  "type": "Feature",
  "properties": {
    "iso:country":"US",
    "sg:address":"1275 W Broadway Hwy",
    "sg:city":"Charlotte",
    "sg:phone":"+1 517 543 1548",
    "sg:postcode":"48813",
    "sg:province":"MI",
    "sg:tags":[
        "farm",
        "corn",
        "soybean"
    ],
    "wof:name":"Scott Hansen",
    "wof:placetype":"venue"
},
  "geometry": {"coordinates":[-84.84326799999999,42.524136],"type":"Point"}
}