{
  "type": "Feature",
  "properties": {
    "iso:country":"US",
    "sg:address":"25153 W 7 Mile Rd",
    "sg:city":"Redford",
    "sg:classifiers":[
        {
            "category":"Retail",
            "subcategory":"Auto Repair",
            "type":"Services"
        }
    ],
    "sg:phone":"+1 313 581 0499",
    "sg:postcode":"48240",
    "sg:province":"MI",
    "sg:tags":[
        "automotive"
    ],
    "wof:name":"Hill Auto Electric Inc",
    "wof:placetype":"venue"
},
  "geometry": {"coordinates":[-83.289294,42.428458],"type":"Point"}
}