{
  "type": "Feature",
  "properties": {
    "iso:country":"US",
    "sg:address":"9644 Joseph Campau St",
    "sg:city":"Hamtramck",
    "sg:classifiers":[
        {
            "category":"Shopping",
            "subcategory":"Clothing, Apparel, & Fashions",
            "type":"Retail Goods"
        }
    ],
    "sg:phone":"+1 313 873 2807",
    "sg:postcode":"48212",
    "sg:province":"MI",
    "sg:tags":[
        "children's",
        "clothing"
    ],
    "wof:name":"Rainbow",
    "wof:placetype":"venue"
},
  "geometry": {"coordinates":[-83.05740400000001,42.396301],"type":"Point"}
}