{
  "type": "Feature",
  "properties": {
    "iso:country":"US",
    "sg:address":"2200 Island Hwy",
    "sg:city":"Charlotte",
    "sg:classifiers":[
        {
            "category":"Sports & Exercise",
            "subcategory":"Golf",
            "type":"Entertainment"
        }
    ],
    "sg:phone":"+1 517 543 0570",
    "sg:postcode":"48813",
    "sg:province":"MI",
    "sg:tags":[
        "course",
        "public"
    ],
    "wof:name":"Twin Brook Golf Club LLC",
    "wof:placetype":"venue"
},
  "geometry": {"coordinates":[-84.79421600000001,42.567439],"type":"Point"}
}