{
  "type": "Feature",
  "properties": {
    "iso:country":"US",
    "sg:address":"111 E Edgewood Blvd",
    "sg:city":"Lansing",
    "sg:classifiers":[
        {
            "category":"Government",
            "subcategory":"Office",
            "type":"Public Place"
        }
    ],
    "sg:phone":"+1 517 272 2500",
    "sg:postcode":"48911",
    "sg:province":"MI",
    "sg:tags":[
        "federal",
        "program",
        "adm"
    ],
    "wof:name":"US Census Bureau",
    "wof:placetype":"venue"
},
  "geometry": {"coordinates":[-84.55600200000001,42.660632],"type":"Point"}
}