{
  "type": "Feature",
  "properties": {
    "iso:country":"US",
    "sg:address":"2370 E Hammond Lake Dr",
    "sg:city":"Bloomfield Hills",
    "sg:classifiers":[
        {
            "category":"Professional",
            "type":"Services"
        }
    ],
    "sg:phone":"+1 248 334 8642",
    "sg:postcode":"48302",
    "sg:province":"MI",
    "wof:name":"Dorothy M Doig",
    "wof:placetype":"venue"
},
  "geometry": {"coordinates":[-83.319785,42.604331],"type":"Point"}
}