{
  "type": "Feature",
  "properties": {
    "iso:country":"US",
    "sg:address":"1735 Peck St",
    "sg:city":"Muskegon",
    "sg:classifiers":[
        {
            "category":"Health Services",
            "subcategory":"Health Practitioner",
            "type":"Services"
        }
    ],
    "sg:phone":"+1 231 726 3196",
    "sg:postcode":"49441",
    "sg:province":"MI",
    "sg:tags":[
        "psychologist"
    ],
    "wof:name":"Cedarbrook Psychological Svcs",
    "wof:placetype":"venue"
},
  "geometry": {"coordinates":[-86.244394,43.221705],"type":"Point"}
}