{
  "type": "Feature",
  "properties": {
    "iso:country":"US",
    "sg:address":"4270 Shance Hwy",
    "sg:city":"Charlotte",
    "sg:classifiers":[
        {
            "category":"Wholesale",
            "subcategory":"Construction Materials",
            "type":"Manufacturing & Wholesale Goods"
        }
    ],
    "sg:phone":"+1 517 712 0651",
    "sg:postcode":"48813",
    "sg:province":"MI",
    "sg:tags":[
        "pallet",
        "skid"
    ],
    "wof:name":"Kamps",
    "wof:placetype":"venue"
},
  "geometry": {"coordinates":[-84.75277800000001,42.611078],"type":"Point"}
}