{
  "type": "Feature",
  "properties": {
    "iso:country":"US",
    "sg:address":"684 Tanview Dr",
    "sg:city":"Oxford",
    "sg:classifiers":[
        {
            "category":"Real Estate",
            "subcategory":"Real Estate Operator",
            "type":"Services"
        }
    ],
    "sg:phone":"+1 248 628 7229",
    "sg:postcode":"48371",
    "sg:province":"MI",
    "sg:tags":[
        "building",
        "nonresidential"
    ],
    "wof:name":"Jcn Properties LLC",
    "wof:placetype":"venue"
},
  "geometry": {"coordinates":[-83.284188,42.815679],"type":"Point"}
}