{
  "type": "Feature",
  "properties": {
    "iso:country":"US",
    "sg:address":"14461 S Telegraph Rd",
    "sg:city":"Monroe",
    "sg:classifiers":[
        {
            "category":"Shopping",
            "subcategory":"Bicycles & Sporting Goods",
            "type":"Retail Goods"
        }
    ],
    "sg:phone":"+1 734 242 1223",
    "sg:postcode":"48161",
    "sg:province":"MI",
    "wof:name":"Cook's Sports II",
    "wof:placetype":"venue"
},
  "geometry": {"coordinates":[-83.448482,41.876078],"type":"Point"}
}