{
  "type": "Feature",
  "properties": {
    "iso:country":"US",
    "sg:address":"9955 Wiggins Rd",
    "sg:city":"Howell",
    "sg:classifiers":[
        {
            "category":"Building & Trades",
            "subcategory":"Construction",
            "type":"Services"
        }
    ],
    "sg:phone":"+1 517 546 0684",
    "sg:postcode":"48855",
    "sg:province":"MI",
    "sg:tags":[
        "home",
        "builder",
        "contractor"
    ],
    "wof:name":"Unique Style Home Builders Inc",
    "wof:placetype":"venue"
},
  "geometry": {"coordinates":[-83.901951,42.739739],"type":"Point"}
}