{
  "type": "Feature",
  "properties": {
    "iso:country":"US",
    "sg:address":"3087 30th St SW",
    "sg:city":"Grandville",
    "sg:classifiers":[
        {
            "category":"Shopping",
            "subcategory":"Used Merchandise",
            "type":"Retail Goods"
        }
    ],
    "sg:phone":"+1 616 534 0209",
    "sg:postcode":"49418",
    "sg:province":"MI",
    "wof:name":"The Carousel Collections",
    "wof:placetype":"venue"
},
  "geometry": {"coordinates":[-85.742108,42.910355],"type":"Point"}
}