{
  "type": "Feature",
  "properties": {
    "iso:country":"US",
    "sg:address":"249 W Lakewood Blvd",
    "sg:city":"Holland",
    "sg:classifiers":[
        {
            "category":"Freight",
            "type":"Transportation"
        }
    ],
    "sg:phone":"+1 616 392 9898",
    "sg:postcode":"49424",
    "sg:province":"MI",
    "sg:tags":[
        "commercial",
        "storage"
    ],
    "wof:name":"Lakewood Self Storage Ctr",
    "wof:placetype":"venue"
},
  "geometry": {"coordinates":[-86.119184,42.804943],"type":"Point"}
}