{
  "type": "Feature",
  "properties": {
    "iso:country":"US",
    "sg:address":"620 Vulcan St",
    "sg:city":"Iron Mountain",
    "sg:classifiers":[
        {
            "category":"Shopping",
            "subcategory":"Clothing, Apparel, & Fashions",
            "type":"Retail Goods"
        }
    ],
    "sg:phone":"+1 906 776 9467",
    "sg:postcode":"49801",
    "sg:province":"MI",
    "sg:tags":[
        "automobile",
        "screen",
        "printing",
        "painting",
        "custom"
    ],
    "wof:name":"All American Design",
    "wof:placetype":"venue"
},
  "geometry": {"coordinates":[-88.05755600000001,45.8299],"type":"Point"}
}