{
  "type": "Feature",
  "properties": {
    "iso:country":"US",
    "sg:address":"2800 N East St",
    "sg:city":"Lansing",
    "sg:classifiers":[
        {
            "category":"Health Services",
            "subcategory":"Clinic",
            "type":"Services"
        }
    ],
    "sg:phone":"+1 517 372 3922",
    "sg:postcode":"48906",
    "sg:province":"MI",
    "sg:tags":[
        "alternative"
    ],
    "wof:name":"Alternative Hlth Imprv Ctr PC",
    "wof:placetype":"venue"
},
  "geometry": {"coordinates":[-84.542767,42.762761],"type":"Point"}
}