{
  "type": "Feature",
  "properties": {
    "iso:country":"US",
    "sg:address":"9 Bonita Dr",
    "sg:city":"Battle Creek",
    "sg:classifiers":[
        {
            "category":"Professional",
            "subcategory":"Secretarial Services",
            "type":"Services"
        }
    ],
    "sg:phone":"+1 269 964 6355",
    "sg:postcode":"49014",
    "sg:province":"MI",
    "sg:tags":[
        "reporting",
        "computer",
        "related"
    ],
    "wof:name":"Data Tamer Resume Service",
    "wof:placetype":"venue"
},
  "geometry": {"coordinates":[-85.17333000000001,42.302238],"type":"Point"}
}