{
  "type": "Feature",
  "properties": {
    "iso:country":"US",
    "sg:address":"89 E Mount Forest Rd",
    "sg:city":"Pinconning",
    "sg:classifiers":[
        {
            "category":"Farming",
            "subcategory":"Fish & Marine Products",
            "type":"Manufacturing & Wholesale Goods"
        }
    ],
    "sg:phone":"+1 989 879 3546",
    "sg:postcode":"48650",
    "sg:province":"MI",
    "sg:tags":[
        "management"
    ],
    "wof:name":"Pipeline Rngncks Gmbird Prsrve",
    "wof:placetype":"venue"
},
  "geometry": {"coordinates":[-84.04331000000001,43.882839],"type":"Point"}
}