{
  "type": "Feature",
  "properties": {
    "iso:country":"US",
    "sg:address":"4946 Berl Dr",
    "sg:city":"Saginaw",
    "sg:classifiers":[
        {
            "category":"Home & Garden",
            "subcategory":"Furniture",
            "type":"Retail Goods"
        }
    ],
    "sg:phone":"+1 989 790 3856",
    "sg:postcode":"48604",
    "sg:province":"MI",
    "wof:name":"Feige's Interiors",
    "wof:placetype":"venue"
},
  "geometry": {"coordinates":[-83.96750400000001,43.478151],"type":"Point"}
}