{
  "type": "Feature",
  "properties": {
    "iso:country":"US",
    "sg:address":"6785 Myers Lake Ave NE Ste A",
    "sg:city":"Rockford",
    "sg:classifiers":[
        {
            "category":"Health Services",
            "subcategory":"Dentist",
            "type":"Services"
        }
    ],
    "sg:phone":"+1 616 874 6040",
    "sg:postcode":"49341",
    "sg:province":"MI",
    "wof:name":"Cannon Family Dentistry",
    "wof:placetype":"venue"
},
  "geometry": {"coordinates":[-85.500298,43.085899],"type":"Point"}
}