{
  "type": "Feature",
  "properties": {
    "iso:country":"US",
    "sg:address":"11110 Co Rd 633",
    "sg:city":"Buckley",
    "sg:classifiers":[
        {
            "category":"Farming",
            "subcategory":"Farm",
            "type":"Manufacturing & Wholesale Goods"
        }
    ],
    "sg:phone":"+1 231 269 3458",
    "sg:postcode":"49620",
    "sg:province":"MI",
    "wof:name":"Patchwork Farms",
    "wof:placetype":"venue"
},
  "geometry": {"coordinates":[-85.696369,44.524796],"type":"Point"}
}