{
  "type": "Feature",
  "properties": {
    "iso:country":"US",
    "sg:address":"221 N Main St",
    "sg:city":"Brooklyn",
    "sg:classifiers":[
        {
            "category":"Organizations",
            "subcategory":"Professional Association",
            "type":"Services"
        }
    ],
    "sg:phone":"+1 517 592 8907",
    "sg:postcode":"49230",
    "sg:province":"MI",
    "sg:tags":[
        "chambers",
        "commerce"
    ],
    "wof:name":"Brooklyn Irish Hills Chamber",
    "wof:placetype":"venue"
},
  "geometry": {"coordinates":[-84.247923,42.107847],"type":"Point"}
}