{
  "type": "Feature",
  "properties": {
    "iso:country":"US",
    "sg:address":"935 W Pine River Rd",
    "sg:city":"Breckenridge",
    "sg:classifiers":[
        {
            "category":"Farming",
            "subcategory":"Livestock Farm",
            "type":"Manufacturing & Wholesale Goods"
        }
    ],
    "sg:phone":"+1 989 832 7596",
    "sg:postcode":"48615",
    "sg:province":"MI",
    "sg:tags":[
        "feedlot",
        "field",
        "crop",
        "beef",
        "cattle"
    ],
    "wof:name":"Donald Anger",
    "wof:placetype":"venue"
},
  "geometry": {"coordinates":[-84.407006,43.548303],"type":"Point"}
}