{
  "type": "Feature",
  "properties": {
    "iso:country":"US",
    "sg:address":"6626 Summerhill Dr SE",
    "sg:city":"Alto",
    "sg:classifiers":[
        {
            "category":"Social Services",
            "subcategory":"Adult Care",
            "type":"Services"
        }
    ],
    "sg:phone":"+1 616 868 0762",
    "sg:postcode":"49302",
    "sg:province":"MI",
    "sg:tags":[
        "residential",
        "architectural"
    ],
    "wof:name":"Residential Care Consultants",
    "wof:placetype":"venue"
},
  "geometry": {"coordinates":[-85.42068,42.845435],"type":"Point"}
}