{
  "type": "Feature",
  "properties": {
    "iso:country":"US",
    "sg:address":"27760 Novi Rd",
    "sg:city":"Novi",
    "sg:classifiers":[
        {
            "category":"Fast Food",
            "type":"Food & Drink"
        },
        {
            "category":"Restaurant",
            "type":"Food & Drink"
        }
    ],
    "sg:phone":"+1 248 349 8470",
    "sg:postcode":"48377",
    "sg:province":"MI",
    "sg:tags":[
        "american",
        "style",
        "seafood",
        "family",
        "take"
    ],
    "sg:website":"http://www.redlobster.com",
    "wof:name":"Red Lobster",
    "wof:placetype":"venue"
},
  "geometry": {"coordinates":[-83.476028,42.491044],"type":"Point"}
}