{
  "type": "Feature",
  "properties": {
    "iso:country":"US",
    "sg:address":"1960 N Osseo Rd",
    "sg:city":"Hillsdale",
    "sg:classifiers":[
        {
            "category":"Retail",
            "subcategory":"Repair Shop",
            "type":"Services"
        }
    ],
    "sg:phone":"+1 517 523 2056",
    "sg:postcode":"49242",
    "sg:province":"MI",
    "sg:tags":[
        "related"
    ],
    "wof:name":"L & R Sales & Svc",
    "wof:placetype":"venue"
},
  "geometry": {"coordinates":[-84.534875,41.913597],"type":"Point"}
}