{
  "type": "Feature",
  "properties": {
    "iso:country":"US",
    "sg:address":"3378 E Shaughniss Rd",
    "sg:city":"Angola",
    "sg:phone":"+1 260 665 3385",
    "sg:postcode":"46703",
    "sg:province":"MI",
    "sg:tags":[
        "farm",
        "field",
        "crop"
    ],
    "wof:name":"Walt Bidlack",
    "wof:placetype":"venue"
},
  "geometry": {"coordinates":[-84.927803,41.594905],"type":"Point"}
}