{
  "type": "Feature",
  "properties": {
    "iso:country":"US",
    "sg:address":"8853 E 10 Mile Rd",
    "sg:city":"Center Line",
    "sg:classifiers":[
        {
            "category":"Retail",
            "subcategory":"Repair Shop",
            "type":"Services"
        }
    ],
    "sg:phone":"+1 313 842 1331",
    "sg:postcode":"48015",
    "sg:province":"MI",
    "sg:tags":[
        "automotive",
        "stampings",
        "metal",
        "welding",
        "mfg"
    ],
    "wof:name":"Jeford Industries Inc",
    "wof:placetype":"venue"
},
  "geometry": {"coordinates":[-83.016897,42.477561],"type":"Point"}
}