{
  "type": "Feature",
  "properties": {
    "iso:country":"US",
    "sg:address":"999 W Silver Lake Rd",
    "sg:city":"Fenton",
    "sg:classifiers":[
        {
            "category":"Freight",
            "type":"Transportation"
        }
    ],
    "sg:phone":"+1 810 629 3878",
    "sg:postcode":"48430",
    "sg:province":"MI",
    "sg:tags":[
        "commercial",
        "storage"
    ],
    "wof:name":"Silver Lake Storage",
    "wof:placetype":"venue"
},
  "geometry": {"coordinates":[-83.719876,42.800388],"type":"Point"}
}