{
  "type": "Feature",
  "properties": {
    "iso:country":"US",
    "sg:address":"615 N Main St",
    "sg:city":"Ovid",
    "sg:classifiers":[
        {
            "category":"Education",
            "subcategory":"School",
            "type":"Public Place"
        }
    ],
    "sg:phone":"+1 989 834 5022",
    "sg:postcode":"48866",
    "sg:province":"MI",
    "wof:name":"North Community Ctr",
    "wof:placetype":"venue"
},
  "geometry": {"coordinates":[-84.37186800000001,43.011098],"type":"Point"}
}