{
  "type": "Feature",
  "properties": {
    "iso:country":"US",
    "sg:address":"4290 Peck Rd",
    "sg:city":"North Branch",
    "sg:classifiers":[
        {
            "category":"Social Services",
            "subcategory":"Child Care",
            "type":"Services"
        }
    ],
    "sg:phone":"+1 810 688 7263",
    "sg:postcode":"48461",
    "sg:province":"MI",
    "sg:tags":[
        "day"
    ],
    "wof:name":"Home Day Care",
    "wof:placetype":"venue"
},
  "geometry": {"coordinates":[-83.190431,43.252738],"type":"Point"}
}