{
  "type": "Feature",
  "properties": {
    "iso:country":"US",
    "sg:address":"1256 Lincoln Rd",
    "sg:city":"Allegan",
    "sg:classifiers":[
        {
            "category":"Restaurant",
            "type":"Food & Drink"
        }
    ],
    "sg:phone":"+1 269 686 8207",
    "sg:postcode":"49010",
    "sg:province":"MI",
    "wof:name":"Rib House",
    "wof:placetype":"venue"
},
  "geometry": {"coordinates":[-85.812719,42.508043],"type":"Point"}
}