{
  "type": "Feature",
  "properties": {
    "iso:country":"US",
    "sg:address":"4572 State St",
    "sg:city":"Saginaw",
    "sg:classifiers":[
        {
            "category":"Shopping",
            "subcategory":"Department Store",
            "type":"Retail Goods"
        }
    ],
    "sg:phone":"+1 989 249 4137",
    "sg:postcode":"48603",
    "sg:province":"MI",
    "wof:name":"A J Wright",
    "wof:placetype":"venue"
},
  "geometry": {"coordinates":[-84.005909,43.436827],"type":"Point"}
}