{
  "type": "Feature",
  "properties": {
    "iso:country":"US",
    "sg:address":"150 Hemlock St",
    "sg:city":"Baraga",
    "sg:classifiers":[
        {
            "category":"Real Estate",
            "subcategory":"Real Estate Operator",
            "type":"Services"
        }
    ],
    "sg:phone":"+1 906 353 4000",
    "sg:postcode":"49935",
    "sg:province":"MI",
    "sg:tags":[
        "mobile",
        "home",
        "site"
    ],
    "wof:name":"Hi Park Industries",
    "wof:placetype":"venue"
},
  "geometry": {"coordinates":[-88.633636,46.087769],"type":"Point"}
}