{
  "type": "Feature",
  "properties": {
    "iso:country":"US",
    "sg:address":"7056 Peckins Rd",
    "sg:city":"Lyons",
    "sg:classifiers":[
        {
            "category":"Farming",
            "subcategory":"Dairy Farm",
            "type":"Manufacturing & Wholesale Goods"
        }
    ],
    "sg:phone":"+1 989 855 3843",
    "sg:postcode":"48851",
    "sg:province":"MI",
    "wof:name":"Peckens Dairy Farms",
    "wof:placetype":"venue"
},
  "geometry": {"coordinates":[-84.936808,42.958159],"type":"Point"}
}