{
  "type": "Feature",
  "properties": {
    "iso:country":"US",
    "sg:address":"72 Tammy Dr",
    "sg:city":"Battle Creek",
    "sg:classifiers":[
        {
            "category":"Retail",
            "subcategory":"Auto Repair",
            "type":"Services"
        }
    ],
    "sg:phone":"+1 269 788 1231",
    "sg:postcode":"49037",
    "sg:province":"MI",
    "sg:tags":[
        "electronic",
        "wiring"
    ],
    "wof:name":"Joshua Chafe",
    "wof:placetype":"venue"
},
  "geometry": {"coordinates":[-85.789463,43.455527],"type":"Point"}
}