{
  "type": "Feature",
  "properties": {
    "iso:country":"US",
    "sg:address":"1230 N Portsmouth Rd",
    "sg:city":"Saginaw",
    "sg:phone":"+1 989 752 2791",
    "sg:postcode":"48601",
    "sg:province":"MI",
    "sg:tags":[
        "farm",
        "grain",
        "cash"
    ],
    "wof:name":"Tom Schaeff",
    "wof:placetype":"venue"
},
  "geometry": {"coordinates":[-83.83686,43.421543],"type":"Point"}
}