{
  "type": "Feature",
  "properties": {
    "iso:country":"US",
    "sg:address":"95 Hilltop Dr",
    "sg:city":"Hart",
    "sg:classifiers":[
        {
            "category":"Travel",
            "subcategory":"Campground",
            "type":"Entertainment"
        }
    ],
    "sg:phone":"+1 231 873 3458",
    "sg:postcode":"49420",
    "sg:province":"MI",
    "sg:tags":[
        "trailer"
    ],
    "wof:name":"Silver City Campgrounds 2",
    "wof:placetype":"venue"
},
  "geometry": {"coordinates":[-86.364734,43.707482],"type":"Point"}
}