{
  "type": "Feature",
  "properties": {
    "iso:country":"US",
    "sg:address":"7119 Assyria Rd",
    "sg:city":"Nashville",
    "sg:classifiers":[
        {
            "category":"Restaurant",
            "type":"Food & Drink"
        }
    ],
    "sg:phone":"+1 517 852 0364",
    "sg:postcode":"49073",
    "sg:province":"MI",
    "sg:tags":[
        "eating"
    ],
    "wof:name":"Ktc Restaurant Equip Svc",
    "wof:placetype":"venue"
},
  "geometry": {"coordinates":[-85.13287099999999,42.550541],"type":"Point"}
}