{
  "type": "Feature",
  "properties": {
    "iso:country":"US",
    "sg:address":"1660 Cass Lake Rd Ste 101",
    "sg:city":"Keego Harbor",
    "sg:classifiers":[
        {
            "category":"Real Estate",
            "subcategory":"Architect",
            "type":"Services"
        }
    ],
    "sg:phone":"+1 248 683 3934",
    "sg:postcode":"48320",
    "sg:province":"MI",
    "wof:name":"Larry Michael Rockind Associates",
    "wof:placetype":"venue"
},
  "geometry": {"coordinates":[-83.346802,42.614399],"type":"Point"}
}