{
  "type": "Feature",
  "properties": {
    "iso:country":"US",
    "sg:address":"2095 Hunters Park W",
    "sg:city":"St Clair",
    "sg:classifiers":[
        {
            "category":"Recreation",
            "type":"Entertainment"
        }
    ],
    "sg:phone":"+1 810 329 3391",
    "sg:postcode":"48079",
    "sg:province":"MI",
    "sg:tags":[
        "instruction",
        "gymnastic"
    ],
    "wof:name":"Tumblebus Fit N Fun",
    "wof:placetype":"venue"
},
  "geometry": {"coordinates":[-82.514537,42.843006],"type":"Point"}
}