{
  "type": "Feature",
  "properties": {
    "iso:country":"US",
    "sg:address":"3851 N Huron Rd",
    "sg:city":"Pinconning",
    "sg:classifiers":[
        {
            "category":"Shopping",
            "subcategory":"Discount & Variety Stores",
            "type":"Retail Goods"
        }
    ],
    "sg:phone":"+1 989 879 1014",
    "sg:postcode":"48650",
    "sg:province":"MI",
    "wof:name":"Family Dollar Store",
    "wof:placetype":"venue"
},
  "geometry": {"coordinates":[-83.96616899999999,43.848878],"type":"Point"}
}