{
  "type": "Feature",
  "properties": {
    "iso:country":"US",
    "sg:address":"4900 40th Ave",
    "sg:city":"Hudsonville",
    "sg:classifiers":[
        {
            "category":"Education",
            "subcategory":"School",
            "type":"Public Place"
        }
    ],
    "sg:phone":"+1 616 669 1773",
    "sg:postcode":"49426",
    "sg:province":"MI",
    "wof:name":"Heritage Chrstn Schl",
    "wof:placetype":"venue"
},
  "geometry": {"coordinates":[-85.880737,42.856627],"type":"Point"}
}