{
  "type": "Feature",
  "properties": {
    "iso:country":"US",
    "sg:address":"877 E Mc Gregor Rd",
    "sg:city":"St Louis",
    "sg:classifiers":[
        {
            "category":"Retail",
            "subcategory":"Animal Services",
            "type":"Services"
        }
    ],
    "sg:phone":"+1 989 681 2028",
    "sg:postcode":"48880",
    "sg:province":"MI",
    "sg:tags":[
        "cat",
        "dog",
        "kennel"
    ],
    "wof:name":"Have A Heart Kennels",
    "wof:placetype":"venue"
},
  "geometry": {"coordinates":[-84.593974,43.429649],"type":"Point"}
}