{
  "type": "Feature",
  "properties": {
    "iso:country":"US",
    "sg:address":"5772 Smiths Creek Rd",
    "sg:city":"Kimball",
    "sg:classifiers":[
        {
            "category":"Social Services",
            "subcategory":"Adult Care",
            "type":"Services"
        }
    ],
    "sg:phone":"+1 810 367 6482",
    "sg:postcode":"48074",
    "sg:province":"MI",
    "sg:tags":[
        "home",
        "group"
    ],
    "wof:name":"Roehl Group Home",
    "wof:placetype":"venue"
},
  "geometry": {"coordinates":[-82.552463,42.91884],"type":"Point"}
}