{
  "type": "Feature",
  "properties": {
    "iso:country":"US",
    "sg:address":"628 7th St",
    "sg:city":"Traverse City",
    "sg:classifiers":[
        {
            "category":"Real Estate",
            "subcategory":"Architect",
            "type":"Services"
        }
    ],
    "sg:phone":"+1 231 929 2962",
    "sg:postcode":"49684",
    "sg:province":"MI",
    "sg:tags":[
        "architectural"
    ],
    "wof:name":"Byrdhouses Etc",
    "wof:placetype":"venue"
},
  "geometry": {"coordinates":[-85.63323699999999,44.760542],"type":"Point"}
}