{
  "type": "Feature",
  "properties": {
    "iso:country":"US",
    "sg:address":"25225 Middlebelt Rd",
    "sg:city":"Farmington",
    "sg:classifiers":[
        {
            "category":"Organizations",
            "subcategory":"Religious Organization",
            "type":"Services"
        }
    ],
    "sg:phone":"+1 248 477 1677",
    "sg:postcode":"48336",
    "sg:province":"MI",
    "wof:name":"Holy Cross Greek Orthdox Chrch",
    "wof:placetype":"venue"
},
  "geometry": {"coordinates":[-83.338139,42.477584],"type":"Point"}
}