{
  "type": "Feature",
  "properties": {
    "iso:country":"US",
    "sg:address":"111 E June St",
    "sg:city":"Gladwin",
    "sg:classifiers":[
        {
            "category":"Social Services",
            "subcategory":"Child Care",
            "type":"Services"
        }
    ],
    "sg:phone":"+1 989 426 3091",
    "sg:postcode":"48624",
    "sg:province":"MI",
    "sg:tags":[
        "home",
        "day"
    ],
    "wof:name":"Schalk Alana",
    "wof:placetype":"venue"
},
  "geometry": {"coordinates":[-84.486639,43.976961],"type":"Point"}
}