{
  "type": "Feature",
  "properties": {
    "iso:country":"US",
    "sg:address":"2743 Henry St",
    "sg:city":"Muskegon",
    "sg:classifiers":[
        {
            "category":"Freight",
            "type":"Transportation"
        }
    ],
    "sg:phone":"+1 231 755 5551",
    "sg:postcode":"49441",
    "sg:province":"MI",
    "sg:tags":[
        "shipping",
        "rental",
        "duplicating",
        "agent",
        "mailbox"
    ],
    "wof:name":"UPS Store",
    "wof:placetype":"venue"
},
  "geometry": {"coordinates":[-86.26323499999999,43.201431],"type":"Point"}
}