{
  "type": "Feature",
  "properties": {
    "iso:country":"US",
    "sg:address":"100 E Superior St",
    "sg:city":"Munising",
    "sg:classifiers":[
        {
            "category":"Government",
            "subcategory":"Office",
            "type":"Public Place"
        }
    ],
    "sg:phone":"+1 906 387 2023",
    "sg:postcode":"49862",
    "sg:province":"MI",
    "sg:tags":[
        "city"
    ],
    "wof:name":"Munising Tourist Park",
    "wof:placetype":"venue"
},
  "geometry": {"coordinates":[-86.655743,46.410661],"type":"Point"}
}