{
  "type": "Feature",
  "properties": {
    "iso:country":"US",
    "sg:address":"31350 Telegraph Rd",
    "sg:city":"Bingham Farms",
    "sg:classifiers":[
        {
            "category":"Health Services",
            "subcategory":"Doctor",
            "type":"Services"
        }
    ],
    "sg:phone":"+1 248 646 0064",
    "sg:postcode":"48025",
    "sg:province":"MI",
    "sg:tags":[
        "dentist"
    ],
    "wof:name":"David Belokonny DDS",
    "wof:placetype":"venue"
},
  "geometry": {"coordinates":[-83.285585,42.517967],"type":"Point"}
}