{
  "type": "Feature",
  "properties": {
    "iso:country":"US",
    "sg:address":"515 Myrtle St NW",
    "sg:city":"Grand Rapids",
    "sg:classifiers":[
        {
            "category":"Organizations",
            "subcategory":"Religious Organization",
            "type":"Services"
        }
    ],
    "sg:phone":"+1 616 454 6948",
    "sg:postcode":"49504",
    "sg:province":"MI",
    "sg:tags":[
        "church"
    ],
    "wof:name":"St Peter & Paul Church Clthng",
    "wof:placetype":"venue"
},
  "geometry": {"coordinates":[-85.68123199999999,42.98824],"type":"Point"}
}