{
  "type": "Feature",
  "properties": {
    "iso:country":"US",
    "sg:address":"50666 Magician Lake Rd",
    "sg:city":"Dowagiac",
    "sg:classifiers":[
        {
            "category":"Freight",
            "type":"Transportation"
        }
    ],
    "sg:phone":"+1 269 424 7224",
    "sg:postcode":"49047",
    "sg:province":"MI",
    "sg:tags":[
        "without",
        "storage"
    ],
    "wof:name":"E E T Trucking Inc",
    "wof:placetype":"venue"
},
  "geometry": {"coordinates":[-86.141593,42.061152],"type":"Point"}
}