{
  "type": "Feature",
  "properties": {
    "iso:country":"US",
    "sg:address":"2800 E Michigan Ave",
    "sg:city":"Ypsilanti",
    "sg:classifiers":[
        {
            "category":"Home & Garden",
            "subcategory":"Building Materials",
            "type":"Retail Goods"
        }
    ],
    "sg:phone":"+1 734 484 3923",
    "sg:postcode":"48198",
    "sg:province":"MI",
    "sg:tags":[
        "supply"
    ],
    "sg:website":"www.carterlumber.com",
    "wof:name":"Carter Lumber",
    "wof:placetype":"venue"
},
  "geometry": {"coordinates":[-83.556297,42.252399],"type":"Point"}
}