{
  "type": "Feature",
  "properties": {
    "iso:country":"US",
    "sg:address":"21519 Harper Ave",
    "sg:city":"Saint Clair Shores",
    "sg:classifiers":[
        {
            "category":"Health Services",
            "subcategory":"Doctor",
            "type":"Services"
        }
    ],
    "sg:phone":"+1 586 445 3706",
    "sg:postcode":"48080",
    "sg:province":"MI",
    "sg:tags":[
        "medicine",
        "internal"
    ],
    "wof:name":"Datla Shilaja MD",
    "wof:placetype":"venue"
},
  "geometry": {"coordinates":[-82.91330000000001,42.454102],"type":"Point"}
}