{
  "type": "Feature",
  "properties": {
    "iso:country":"US",
    "sg:address":"18425 Adrian St",
    "sg:city":"Southfield",
    "sg:classifiers":[
        {
            "category":"Retail",
            "subcategory":"Laundry & Dry Cleaning",
            "type":"Services"
        },
        {
            "category":"Building & Trades",
            "subcategory":"Cleaning & Sanitation",
            "type":"Services"
        }
    ],
    "sg:phone":"+1 248 559 5570",
    "sg:postcode":"48075",
    "sg:province":"MI",
    "sg:tags":[
        "cleaner",
        "house"
    ],
    "wof:name":"Cleaning Out The Closet",
    "wof:placetype":"venue"
},
  "geometry": {"coordinates":[-83.225362,42.47963],"type":"Point"}
}