{
  "type": "Feature",
  "properties": {
    "iso:country":"US",
    "sg:address":"32031 Townley St",
    "sg:city":"Madison Heights",
    "sg:classifiers":[
        {
            "category":"Manufacturing",
            "subcategory":"Printing",
            "type":"Manufacturing & Wholesale Goods"
        }
    ],
    "sg:phone":"+1 248 583 2500",
    "sg:postcode":"48071",
    "sg:province":"MI",
    "sg:tags":[
        "printer"
    ],
    "sg:website":"www.egtgo.com",
    "wof:name":"EGT Group",
    "wof:placetype":"venue"
},
  "geometry": {"coordinates":[-83.10433999999999,42.527712],"type":"Point"}
}