{
  "type": "Feature",
  "properties": {
    "iso:country":"US",
    "sg:address":"2716 34th St",
    "sg:city":"Allegan",
    "sg:classifiers":[
        {
            "category":"Building & Trades",
            "subcategory":"Cleaning & Sanitation",
            "type":"Services"
        }
    ],
    "sg:phone":"+1 269 686 7107",
    "sg:postcode":"49010",
    "sg:province":"MI",
    "sg:tags":[
        "janitor"
    ],
    "wof:name":"Bright Side Janitorial & Wndw",
    "wof:placetype":"venue"
},
  "geometry": {"coordinates":[-85.879954,42.62301],"type":"Point"}
}