{
  "type": "Feature",
  "properties": {
    "iso:country":"US",
    "sg:address":"105 5th St",
    "sg:city":"Manton",
    "sg:classifiers":[
        {
            "category":"Education",
            "subcategory":"School",
            "type":"Public Place"
        }
    ],
    "sg:phone":"+1 231 824 6411",
    "sg:postcode":"49663",
    "sg:province":"MI",
    "sg:tags":[
        "educational",
        "administrative"
    ],
    "wof:name":"Manton Consolidated Dst Schl",
    "wof:placetype":"venue"
},
  "geometry": {"coordinates":[-85.397659,44.405814],"type":"Point"}
}