{
  "type": "Feature",
  "properties": {
    "iso:country":"US",
    "sg:address":"13151 W McNichols Rd",
    "sg:city":"Detroit",
    "sg:classifiers":[
        {
            "category":"Retail",
            "subcategory":"Auto Repair",
            "type":"Services"
        }
    ],
    "sg:phone":"+1 313 345 2400",
    "sg:postcode":"48235",
    "sg:province":"MI",
    "wof:name":"Z & R Auto Service",
    "wof:placetype":"venue"
},
  "geometry": {"coordinates":[-83.175301,42.4165],"type":"Point"}
}