{
  "type": "Feature",
  "properties": {
    "iso:country":"US",
    "sg:address":"1565 S Opdyke Rd",
    "sg:city":"Bloomfield Hills",
    "sg:classifiers":[
        {
            "category":"Shopping",
            "type":"Retail Goods"
        }
    ],
    "sg:phone":"+1 248 874 3474",
    "sg:postcode":"48304",
    "sg:province":"MI",
    "sg:tags":[
        "pet",
        "shop"
    ],
    "sg:website":"www.aquaexotics.com",
    "wof:name":"Aqua Exotics Inc",
    "wof:placetype":"venue"
},
  "geometry": {"coordinates":[-83.24843300000001,42.618719],"type":"Point"}
}