{
  "type": "Feature",
  "properties": {
    "iso:country":"US",
    "sg:address":"1136 N Leroy St",
    "sg:city":"Fenton",
    "sg:classifiers":[
        {
            "category":"Home & Garden",
            "subcategory":"Furniture",
            "type":"Retail Goods"
        }
    ],
    "sg:phone":"+1 810 629 0650",
    "sg:postcode":"48430",
    "sg:province":"MI",
    "sg:website":"www.fentonhomefurnishings.com",
    "wof:name":"Fenton Home Furnishings House",
    "wof:placetype":"venue"
},
  "geometry": {"coordinates":[-83.70720799999999,42.809523],"type":"Point"}
}