{
  "type": "Feature",
  "properties": {
    "iso:country":"US",
    "sg:address":"28480 Little Mack Ave",
    "sg:city":"Saint Clair Shores",
    "sg:classifiers":[
        {
            "category":"Food & Beverages",
            "subcategory":"Liquor & Beverages",
            "type":"Retail Goods"
        }
    ],
    "sg:phone":"+1 586 771 5556",
    "sg:postcode":"48081",
    "sg:province":"MI",
    "sg:tags":[
        "beer",
        "spirit",
        "wine"
    ],
    "wof:name":"Little Mack Beer & Wine",
    "wof:placetype":"venue"
},
  "geometry": {"coordinates":[-82.907799,42.502701],"type":"Point"}
}