{
  "type": "Feature",
  "properties": {
    "iso:country":"US",
    "sg:address":"625 Hancock St",
    "sg:city":"Hancock",
    "sg:classifiers":[
        {
            "category":"Retail",
            "subcategory":"Repair Shop",
            "type":"Services"
        }
    ],
    "sg:phone":"+1 906 483 3700",
    "sg:postcode":"49930",
    "sg:province":"MI",
    "sg:tags":[
        "repairing",
        "equipment",
        "electric"
    ],
    "wof:name":"Erickson Electronics",
    "wof:placetype":"venue"
},
  "geometry": {"coordinates":[-88.59070800000001,47.125789],"type":"Point"}
}