{
  "type": "Feature",
  "properties": {
    "iso:country":"US",
    "sg:address":"136 N Ruggles St",
    "sg:city":"Bronson",
    "sg:classifiers":[
        {
            "category":"Professional",
            "subcategory":"Business Services",
            "type":"Services"
        }
    ],
    "sg:phone":"+1 517 369 3955",
    "sg:postcode":"49028",
    "sg:province":"MI",
    "sg:tags":[
        "auctioneer"
    ],
    "wof:name":"Myers Wilber & Wilson",
    "wof:placetype":"venue"
},
  "geometry": {"coordinates":[-85.199392,41.872013],"type":"Point"}
}