{
  "type": "Feature",
  "properties": {
    "iso:country":"US",
    "sg:address":"225 S 600 W",
    "sg:city":"Angola",
    "sg:classifiers":[
        {
            "category":"Wholesale",
            "subcategory":"Construction Materials",
            "type":"Manufacturing & Wholesale Goods"
        }
    ],
    "sg:phone":"+1 260 665 3683",
    "sg:postcode":"46703",
    "sg:province":"MI",
    "sg:tags":[
        "sand",
        "gravel"
    ],
    "wof:name":"Irvin Gravel Co Inc",
    "wof:placetype":"venue"
},
  "geometry": {"coordinates":[-85.102081,41.638054],"type":"Point"}
}