{
  "type": "Feature",
  "properties": {
    "iso:country":"US",
    "sg:address":"82 N Adams Rd",
    "sg:city":"Rochester Hills",
    "sg:classifiers":[
        {
            "category":"Real Estate",
            "subcategory":"Real Estate Operator",
            "type":"Services"
        }
    ],
    "sg:phone":"+1 248 375 9451",
    "sg:postcode":"48309",
    "sg:province":"MI",
    "sg:tags":[
        "mall",
        "shopping",
        "center"
    ],
    "sg:website":"www.villageofrochesterhills.com",
    "wof:name":"Village Of Rochester Hills",
    "wof:placetype":"venue"
},
  "geometry": {"coordinates":[-83.19407099999999,42.682686],"type":"Point"}
}