{
  "type": "Feature",
  "properties": {
    "iso:country":"US",
    "sg:address":"2939 Wilson Ave SW",
    "sg:city":"Grandville",
    "sg:classifiers":[
        {
            "category":"Shopping",
            "type":"Retail Goods"
        }
    ],
    "sg:phone":"+1 616 724 1888",
    "sg:postcode":"49418",
    "sg:province":"MI",
    "sg:tags":[
        "candle"
    ],
    "wof:name":"Candle Experience",
    "wof:placetype":"venue"
},
  "geometry": {"coordinates":[-85.763278,42.911724],"type":"Point"}
}