{
  "type": "Feature",
  "properties": {
    "iso:country":"US",
    "sg:address":"13217 Wacousta Rd",
    "sg:city":"Grand Ledge",
    "sg:classifiers":[
        {
            "category":"Building & Trades",
            "subcategory":"Construction",
            "type":"Services"
        }
    ],
    "sg:phone":"+1 517 626 6103",
    "sg:postcode":"48837",
    "sg:province":"MI",
    "sg:tags":[
        "house",
        "nonresidential"
    ],
    "wof:name":"Freund Construction",
    "wof:placetype":"venue"
},
  "geometry": {"coordinates":[-84.70080400000001,42.827131],"type":"Point"}
}