{
  "type": "Feature",
  "properties": {
    "iso:country":"US",
    "sg:address":"4727 Barnum Rd",
    "sg:city":"Hastings",
    "sg:classifiers":[
        {
            "category":"Farming",
            "subcategory":"Farm",
            "type":"Manufacturing & Wholesale Goods"
        }
    ],
    "sg:phone":"+1 269 367 4631",
    "sg:postcode":"49058",
    "sg:province":"MI",
    "sg:tags":[
        "crop",
        "general"
    ],
    "wof:name":"Oliver Boulter",
    "wof:placetype":"venue"
},
  "geometry": {"coordinates":[-85.202349,42.712108],"type":"Point"}
}