{
  "type": "Feature",
  "properties": {
    "iso:country":"US",
    "sg:address":"1028 S Van Dyke Rd",
    "sg:city":"Bad Axe",
    "sg:classifiers":[
        {
            "category":"Real Estate",
            "subcategory":"Real Estate Services",
            "type":"Services"
        }
    ],
    "sg:phone":"+1 989 269 9126",
    "sg:postcode":"48413",
    "sg:province":"MI",
    "wof:name":"Sally's Abstract Svc",
    "wof:placetype":"venue"
},
  "geometry": {"coordinates":[-83.041842,43.800617],"type":"Point"}
}