{
  "type": "Feature",
  "properties": {
    "iso:country":"US",
    "sg:address":"120 S Mercantile St",
    "sg:city":"Carson City",
    "sg:classifiers":[
        {
            "category":"Personal",
            "subcategory":"Beauty Salon",
            "type":"Services"
        }
    ],
    "sg:phone":"+1 989 584 0302",
    "sg:postcode":"48811",
    "sg:province":"MI",
    "sg:tags":[
        "manicuring"
    ],
    "wof:name":"Just Nails",
    "wof:placetype":"venue"
},
  "geometry": {"coordinates":[-84.847725,43.177009],"type":"Point"}
}