{
  "type": "Feature",
  "properties": {
    "iso:country":"US",
    "sg:address":"960 E Commerce Dr",
    "sg:city":"Traverse City",
    "sg:classifiers":[
        {
            "category":"Food & Beverages",
            "subcategory":"Candy",
            "type":"Retail Goods"
        }
    ],
    "sg:phone":"+1 231 943 9200",
    "sg:postcode":"49684",
    "sg:province":"MI",
    "sg:tags":[
        "popcorn",
        "supply"
    ],
    "wof:name":"Jay's Snack Foods",
    "wof:placetype":"venue"
},
  "geometry": {"coordinates":[-85.663954,44.672446],"type":"Point"}
}