{
  "type": "Feature",
  "properties": {
    "iso:country":"US",
    "sg:address":"24525 Southfield Rd Ste 201",
    "sg:city":"Southfield",
    "sg:classifiers":[
        {
            "category":"Banks & Credit Unions",
            "subcategory":"Financial Services",
            "type":"Services"
        }
    ],
    "sg:phone":"+1 248 569 9660",
    "sg:postcode":"48075",
    "sg:province":"MI",
    "sg:tags":[
        "broker",
        "mortgage"
    ],
    "wof:name":"Alternative Processing Services",
    "wof:placetype":"venue"
},
  "geometry": {"coordinates":[-83.221001,42.470001],"type":"Point"}
}