{
  "type": "Feature",
  "properties": {
    "iso:country":"US",
    "sg:address":"38970 Michigan Ave",
    "sg:city":"Wayne",
    "sg:classifiers":[
        {
            "category":"Retail",
            "subcategory":"Auto Repair",
            "type":"Services"
        }
    ],
    "sg:phone":"+1 734 326 8400",
    "sg:postcode":"48184",
    "sg:province":"MI",
    "sg:website":"www.collexcollision.com",
    "wof:name":"Collex Collision Experts",
    "wof:placetype":"venue"
},
  "geometry": {"coordinates":[-83.422875,42.27924],"type":"Point"}
}