{
  "type": "Feature",
  "properties": {
    "iso:country":"US",
    "sg:address":"344 Hamilton Row",
    "sg:city":"Birmingham",
    "sg:classifiers":[
        {
            "category":"Personal",
            "subcategory":"Nail Salon",
            "type":"Services"
        }
    ],
    "sg:phone":"+1 248 219 1171",
    "sg:postcode":"48009",
    "sg:province":"MI",
    "wof:name":"Nails By Lyudmila",
    "wof:placetype":"venue"
},
  "geometry": {"coordinates":[-83.212965,42.547555],"type":"Point"}
}