{
  "type": "Feature",
  "properties": {
    "iso:country":"US",
    "sg:address":"3915 W Auburn Rd",
    "sg:city":"Rochester Hills",
    "sg:classifiers":[
        {
            "category":"Retail",
            "subcategory":"Veterinary Services",
            "type":"Services"
        }
    ],
    "sg:phone":"+1 248 852 5580",
    "sg:postcode":"48309",
    "sg:province":"MI",
    "sg:tags":[
        "veterinarian"
    ],
    "wof:name":"Avon Animal Clinic",
    "wof:placetype":"venue"
},
  "geometry": {"coordinates":[-83.208504,42.6339],"type":"Point"}
}