{
  "type": "Feature",
  "properties": {
    "iso:country":"US",
    "sg:address":"6452 Millennium Dr",
    "sg:city":"Lansing",
    "sg:classifiers":[
        {
            "category":"Education",
            "subcategory":"Special Training",
            "type":"Public Place"
        }
    ],
    "sg:phone":"+1 517 323 2008",
    "sg:postcode":"48917",
    "sg:province":"MI",
    "sg:tags":[
        "tutoring"
    ],
    "wof:name":"Sylvan Learning Ctr",
    "wof:placetype":"venue"
},
  "geometry": {"coordinates":[-84.643838,42.726279],"type":"Point"}
}