{
  "type": "Feature",
  "properties": {
    "iso:country":"US",
    "sg:address":"8949 Bluewater Hwy",
    "sg:city":"Saranac",
    "sg:classifiers":[
        {
            "category":"Professional",
            "subcategory":"Computer Services",
            "type":"Services"
        }
    ],
    "sg:phone":"+1 616 336 1726",
    "sg:postcode":"48881",
    "sg:province":"MI",
    "sg:tags":[
        "software"
    ],
    "wof:name":"Writexchange",
    "wof:placetype":"venue"
},
  "geometry": {"coordinates":[-85.260228,42.933334],"type":"Point"}
}