{
  "type": "Feature",
  "properties": {
    "iso:country":"US",
    "sg:address":"4655 Shoreview Ln",
    "sg:city":"Indian River",
    "sg:classifiers":[
        {
            "category":"Building & Trades",
            "subcategory":"Construction",
            "type":"Services"
        }
    ],
    "sg:phone":"+1 231 238 0978",
    "sg:postcode":"49749",
    "sg:province":"MI",
    "sg:tags":[
        "house"
    ],
    "wof:name":"Complete Wood Care Specialists",
    "wof:placetype":"venue"
},
  "geometry": {"coordinates":[-84.55590100000001,45.452498],"type":"Point"}
}