{
  "type": "Feature",
  "properties": {
    "iso:country":"US",
    "sg:address":"2463 Hunt Club Dr",
    "sg:city":"Bloomfield Hills",
    "sg:classifiers":[
        {
            "category":"Building & Trades",
            "subcategory":"Construction",
            "type":"Services"
        }
    ],
    "sg:phone":"+1 248 594 8770",
    "sg:postcode":"48304",
    "sg:province":"MI",
    "sg:tags":[
        "home",
        "builder"
    ],
    "wof:name":"Home Shapers Inc",
    "wof:placetype":"venue"
},
  "geometry": {"coordinates":[-83.23274499999999,42.594342],"type":"Point"}
}