{
  "type": "Feature",
  "properties": {
    "iso:country":"US",
    "sg:address":"777 Washington Ave",
    "sg:city":"Holland",
    "sg:classifiers":[
        {
            "category":"Restaurant",
            "type":"Food & Drink"
        }
    ],
    "sg:menulink":"http://www.allmenus.com/mi/holland/47761-china-kitchen/menu/",
    "sg:phone":"+1 616 393 6888",
    "sg:postcode":"49423",
    "sg:province":"MI",
    "sg:tags":[
        "asian",
        "chinese"
    ],
    "wof:name":"China Kitchen",
    "wof:placetype":"venue"
},
  "geometry": {"coordinates":[-86.1168,42.767784],"type":"Point"}
}