{
  "type": "Feature",
  "properties": {
    "iso:country":"US",
    "sg:address":"55801 Grand River Ave",
    "sg:city":"New Hudson",
    "sg:classifiers":[
        {
            "category":"Home & Garden",
            "subcategory":"Building Materials",
            "type":"Retail Goods"
        }
    ],
    "sg:phone":"+1 248 437 6044",
    "sg:postcode":"48165",
    "sg:province":"MI",
    "sg:tags":[
        "windows"
    ],
    "wof:name":"Lee Wholesale Supply Inc",
    "wof:placetype":"venue"
},
  "geometry": {"coordinates":[-83.60701899999999,42.509789],"type":"Point"}
}