{
  "type": "Feature",
  "properties": {
    "iso:country":"US",
    "sg:address":"2759 Ashmun St",
    "sg:city":"Sault Ste Marie",
    "sg:classifiers":[
        {
            "category":"Building & Trades",
            "subcategory":"Plumbing",
            "type":"Services"
        }
    ],
    "sg:phone":"+1 906 632 8253",
    "sg:postcode":"49783",
    "sg:province":"MI",
    "sg:tags":[
        "plumbing",
        "contractor"
    ],
    "wof:name":"Baril Plumbing Heating & Cool",
    "wof:placetype":"venue"
},
  "geometry": {"coordinates":[-84.353798,46.474371],"type":"Point"}
}