{
  "type": "Feature",
  "properties": {
    "iso:country":"US",
    "sg:address":"1400 Townsend Dr",
    "sg:city":"Houghton",
    "sg:classifiers":[
        {
            "category":"Government",
            "subcategory":"Office",
            "type":"Public Place"
        }
    ],
    "sg:phone":"+1 906 482 4481",
    "sg:postcode":"49931",
    "sg:province":"MI",
    "sg:tags":[
        "federal",
        "security"
    ],
    "wof:name":"Us Army Rotc",
    "wof:placetype":"venue"
},
  "geometry": {"coordinates":[-88.53358299999999,47.112463],"type":"Point"}
}