{
  "type": "Feature",
  "properties": {
    "iso:country":"US",
    "sg:address":"32 Moyers St",
    "sg:city":"Oxford",
    "sg:classifiers":[
        {
            "category":"Building & Trades",
            "subcategory":"Construction",
            "type":"Services"
        }
    ],
    "sg:phone":"+1 248 969 2610",
    "sg:postcode":"48371",
    "sg:province":"MI",
    "sg:tags":[
        "house"
    ],
    "wof:name":"C&J Homes of Oxford LLC",
    "wof:placetype":"venue"
},
  "geometry": {"coordinates":[-83.265806,42.820439],"type":"Point"}
}