{
  "type": "Feature",
  "properties": {
    "iso:country":"US",
    "sg:address":"430 E Buffalo St",
    "sg:city":"New Buffalo",
    "sg:classifiers":[
        {
            "category":"Building & Trades",
            "subcategory":"Plumbing",
            "type":"Services"
        }
    ],
    "sg:phone":"+1 269 469 6388",
    "sg:postcode":"49117",
    "sg:province":"MI",
    "sg:tags":[
        "heating",
        "contractor"
    ],
    "wof:name":"Shafer Heating & Air Cond",
    "wof:placetype":"venue"
},
  "geometry": {"coordinates":[-86.738533,41.796324],"type":"Point"}
}