{
  "type": "Feature",
  "properties": {
    "iso:country":"US",
    "sg:address":"7445 Sleepy Hollow Dr",
    "sg:city":"Hudsonville",
    "sg:classifiers":[
        {
            "category":"Real Estate",
            "subcategory":"Real Estate Agent",
            "type":"Services"
        }
    ],
    "sg:phone":"+1 616 334 3113",
    "sg:postcode":"49426",
    "sg:province":"MI",
    "wof:name":"Homes & Loans Of West Michigan",
    "wof:placetype":"venue"
},
  "geometry": {"coordinates":[-85.89317200000001,42.905155],"type":"Point"}
}