{
  "type": "Feature",
  "properties": {
    "iso:country":"US",
    "sg:address":"24573 Hampton Ct",
    "sg:city":"Novi",
    "sg:classifiers":[
        {
            "category":"Professional",
            "subcategory":"Business Services",
            "type":"Services"
        }
    ],
    "sg:phone":"+1 248 912 6679",
    "sg:postcode":"48375",
    "sg:province":"MI",
    "wof:name":"BEI Solutions",
    "wof:placetype":"venue"
},
  "geometry": {"coordinates":[-83.461911,42.47071],"type":"Point"}
}