{
  "type": "Feature",
  "properties": {
    "iso:country":"US",
    "sg:address":"3228 N East St",
    "sg:city":"Lansing",
    "sg:classifiers":[
        {
            "category":"Manufacturing",
            "subcategory":"Tools & Machinery",
            "type":"Manufacturing & Wholesale Goods"
        }
    ],
    "sg:phone":"+1 517 371 4405",
    "sg:postcode":"48906",
    "sg:province":"MI",
    "sg:tags":[
        "electrical",
        "apparatus"
    ],
    "wof:name":"Tom Martin Electric",
    "wof:placetype":"venue"
},
  "geometry": {"coordinates":[-84.542672,42.766451],"type":"Point"}
}