{
  "type": "Feature",
  "properties": {
    "iso:country":"US",
    "sg:address":"5900 W Dunbar Rd",
    "sg:city":"Monroe",
    "sg:classifiers":[
        {
            "category":"Insurance",
            "subcategory":"Insurance Agent",
            "type":"Services"
        }
    ],
    "sg:phone":"+1 734 243 2281",
    "sg:postcode":"48161",
    "sg:province":"MI",
    "wof:name":"State Farm Insurance",
    "wof:placetype":"venue"
},
  "geometry": {"coordinates":[-83.52445899999999,41.917678],"type":"Point"}
}