{
  "type": "Feature",
  "properties": {
    "iso:country":"US",
    "sg:address":"336 US Hwy 31 S",
    "sg:city":"Traverse City",
    "sg:classifiers":[
        {
            "category":"Autos & Motor Vehicles",
            "subcategory":"Motorcycle Sales",
            "type":"Retail Goods"
        }
    ],
    "sg:phone":"+1 231 943 4645",
    "sg:postcode":"49684",
    "sg:province":"MI",
    "sg:tags":[
        "car",
        "golf",
        "cart"
    ],
    "wof:name":"Caddy Shack Golf Car Sales Inc",
    "wof:placetype":"venue"
},
  "geometry": {"coordinates":[-85.65631,44.681749],"type":"Point"}
}