{
  "type": "Feature",
  "properties": {
    "iso:country":"US",
    "sg:address":"6004 W Pierson Rd",
    "sg:city":"Flushing",
    "sg:classifiers":[
        {
            "category":"Retail",
            "subcategory":"Repair Shop",
            "type":"Services"
        }
    ],
    "sg:phone":"+1 810 732 7768",
    "sg:postcode":"48433",
    "sg:province":"MI",
    "sg:tags":[
        "cleaners",
        "household",
        "appliance",
        "parts",
        "electrical",
        "vacuum"
    ],
    "wof:name":"Kirby Co",
    "wof:placetype":"venue"
},
  "geometry": {"coordinates":[-83.793384,43.060439],"type":"Point"}
}