{
  "type": "Feature",
  "properties": {
    "iso:country":"US",
    "sg:address":"1961 Base Ave",
    "sg:city":"Springfield",
    "sg:classifiers":[
        {
            "category":"Professional",
            "subcategory":"Business Services",
            "type":"Services"
        }
    ],
    "sg:phone":"+1 269 964 8185",
    "sg:postcode":"49037",
    "sg:province":"MI",
    "sg:tags":[
        "record",
        "document"
    ],
    "wof:name":"Archives One",
    "wof:placetype":"venue"
},
  "geometry": {"coordinates":[-83.49357500000001,42.567425],"type":"Point"}
}