{
  "type": "Feature",
  "properties": {
    "iso:country":"US",
    "sg:address":"81 E Applegate Rd",
    "sg:city":"Sandusky",
    "sg:classifiers":[
        {
            "category":"Professional",
            "subcategory":"Art Services",
            "type":"Services"
        }
    ],
    "sg:phone":"+1 810 648 1909",
    "sg:postcode":"48471",
    "sg:province":"MI",
    "sg:tags":[
        "artist"
    ],
    "wof:name":"Wagner Illustration & Design",
    "wof:placetype":"venue"
},
  "geometry": {"coordinates":[-82.81825600000001,43.348557],"type":"Point"}
}