{
  "type": "Feature",
  "properties": {
    "iso:country":"US",
    "sg:address":"4327 Delemere Ct",
    "sg:city":"Royal Oak",
    "sg:classifiers":[
        {
            "category":"Building & Trades",
            "subcategory":"Construction",
            "type":"Services"
        }
    ],
    "sg:phone":"+1 248 549 1800",
    "sg:postcode":"48073",
    "sg:province":"MI",
    "sg:tags":[
        "contractor"
    ],
    "sg:website":"www.ronnisch.com",
    "wof:name":"Ronnisch Construction Group",
    "wof:placetype":"venue"
},
  "geometry": {"coordinates":[-83.17809699999999,42.527463],"type":"Point"}
}