{
  "type": "Feature",
  "properties": {
    "iso:country":"US",
    "sg:address":"8811 Lakeshore Rd",
    "sg:city":"Lexington",
    "sg:classifiers":[
        {
            "category":"Health Services",
            "subcategory":"Doctor",
            "type":"Services"
        }
    ],
    "sg:phone":"+1 810 327 0504",
    "sg:postcode":"48450",
    "sg:province":"MI",
    "sg:tags":[
        "medical"
    ],
    "wof:name":"John Ensley MD",
    "wof:placetype":"venue"
},
  "geometry": {"coordinates":[-82.506483,43.173727],"type":"Point"}
}