{
  "type": "Feature",
  "properties": {
    "iso:country":"US",
    "sg:address":"44900 Ford Rd",
    "sg:city":"Canton",
    "sg:classifiers":[
        {
            "category":"Restaurant",
            "type":"Food & Drink"
        }
    ],
    "sg:phone":"+1 734 459 3313",
    "sg:postcode":"48187",
    "sg:province":"MI",
    "wof:name":"McDonald's of Canton Twp Inc",
    "wof:placetype":"venue"
},
  "geometry": {"coordinates":[-83.48400100000001,42.322102],"type":"Point"}
}