{
  "type": "Feature",
  "properties": {
    "iso:country":"US",
    "sg:address":"729 W Washington St",
    "sg:city":"Marquette",
    "sg:classifiers":[
        {
            "category":"Autos & Motor Vehicles",
            "subcategory":"Automobile Sales",
            "type":"Retail Goods"
        }
    ],
    "sg:phone":"+1 906 225 6767",
    "sg:postcode":"49855",
    "sg:province":"MI",
    "sg:tags":[
        "repair",
        "used"
    ],
    "wof:name":"Indian Motorcycle Marquette",
    "wof:placetype":"venue"
},
  "geometry": {"coordinates":[-87.408706,46.545452],"type":"Point"}
}