{
  "type": "Feature",
  "properties": {
    "iso:country":"US",
    "sg:address":"260 E Prosper Rd",
    "sg:city":"Falmouth",
    "sg:classifiers":[
        {
            "category":"Manufacturing",
            "subcategory":"Pet Food",
            "type":"Manufacturing & Wholesale Goods"
        }
    ],
    "sg:phone":"+1 231 826 3301",
    "sg:postcode":"49632",
    "sg:province":"MI",
    "sg:tags":[
        "feed"
    ],
    "wof:name":"Falmouth Co-Operative Co",
    "wof:placetype":"venue"
},
  "geometry": {"coordinates":[-85.08869799999999,44.24368],"type":"Point"}
}