{
  "type": "Feature",
  "properties": {
    "iso:country":"US",
    "sg:address":"3361 23rd St",
    "sg:city":"Detroit",
    "sg:classifiers":[
        {
            "category":"Education",
            "subcategory":"School",
            "type":"Public Place"
        }
    ],
    "sg:phone":"+1 313 894 0880",
    "sg:postcode":"48208",
    "sg:province":"MI",
    "wof:name":"St Casimir School",
    "wof:placetype":"venue"
},
  "geometry": {"coordinates":[-83.092922,42.334839],"type":"Point"}
}