{
  "type": "Feature",
  "properties": {
    "iso:country":"US",
    "sg:address":"1480 Glenwood",
    "sg:city":"Keego Harbor",
    "sg:classifiers":[
        {
            "category":"Building & Trades",
            "subcategory":"Construction",
            "type":"Services"
        }
    ],
    "sg:phone":"+1 248 738 6089",
    "sg:postcode":"48320",
    "sg:province":"MI",
    "sg:tags":[
        "house"
    ],
    "wof:name":"Awl Wood Products",
    "wof:placetype":"venue"
},
  "geometry": {"coordinates":[-83.326983,42.620223],"type":"Point"}
}