{
  "type": "Feature",
  "properties": {
    "iso:country":"US",
    "sg:address":"9045 US Hwy 31",
    "sg:city":"Berrien Springs",
    "sg:classifiers":[
        {
            "category":"Health Services",
            "subcategory":"Clinic",
            "type":"Services"
        },
        {
            "category":"Social Services",
            "subcategory":"Job Training",
            "type":"Services"
        }
    ],
    "sg:phone":"+1 269 471 7621",
    "sg:postcode":"49103",
    "sg:province":"MI",
    "sg:tags":[
        "rehabilitation",
        "outpatient",
        "specialty"
    ],
    "wof:name":"Lakeland Rehabilitation Center",
    "wof:placetype":"venue"
},
  "geometry": {"coordinates":[-86.362173,41.958064],"type":"Point"}
}