{
  "type": "Feature",
  "properties": {
    "iso:country":"US",
    "sg:address":"4138 Corunna Rd",
    "sg:city":"Flint",
    "sg:classifiers":[
        {
            "category":"Organizations",
            "subcategory":"Community Association",
            "type":"Services"
        }
    ],
    "sg:phone":"+1 810 230 8410",
    "sg:postcode":"48532",
    "sg:province":"MI",
    "sg:tags":[
        "military"
    ],
    "wof:name":"Vfw Post Local 3087",
    "wof:placetype":"venue"
},
  "geometry": {"coordinates":[-83.757964,43.001999],"type":"Point"}
}