{
  "type": "Feature",
  "properties": {
    "iso:country":"US",
    "sg:address":"4700 Trailwood Cir N",
    "sg:city":"Midland",
    "sg:classifiers":[
        {
            "category":"Professional",
            "subcategory":"Computer Services",
            "type":"Services"
        }
    ],
    "sg:phone":"+1 989 832 0438",
    "sg:postcode":"48642",
    "sg:province":"MI",
    "sg:tags":[
        "home",
        "consulting",
        "page",
        "dev",
        "internet"
    ],
    "wof:name":"Despac",
    "wof:placetype":"venue"
},
  "geometry": {"coordinates":[-84.20434,43.638858],"type":"Point"}
}