{
  "type": "Feature",
  "properties": {
    "iso:country":"US",
    "sg:address":"2800 Snover Rd",
    "sg:city":"Carsonville",
    "sg:classifiers":[
        {
            "category":"Professional",
            "subcategory":"Business Services",
            "type":"Services"
        }
    ],
    "sg:phone":"+1 810 648 4900",
    "sg:postcode":"48419",
    "sg:province":"MI",
    "sg:tags":[
        "notary",
        "public"
    ],
    "wof:name":"James Bowerman",
    "wof:placetype":"venue"
},
  "geometry": {"coordinates":[-82.714489,43.468903],"type":"Point"}
}