{
  "type": "Feature",
  "properties": {
    "iso:country":"US",
    "sg:address":"301 Crowley St",
    "sg:city":"Scottville",
    "sg:classifiers":[
        {
            "category":"Insurance",
            "subcategory":"Health Insurance",
            "type":"Services"
        }
    ],
    "sg:phone":"+1 231 794 9692",
    "sg:postcode":"49454",
    "sg:province":"MI",
    "sg:tags":[
        "organization",
        "preferred",
        "provider"
    ],
    "wof:name":"Bear Necessities Daycare",
    "wof:placetype":"venue"
},
  "geometry": {"coordinates":[-86.280805,43.950886],"type":"Point"}
}