{
  "type": "Feature",
  "properties": {
    "iso:country":"US",
    "sg:address":"10767 E Traverse Hwy",
    "sg:city":"Traverse City",
    "sg:classifiers":[
        {
            "category":"Health Services",
            "subcategory":"Clinic",
            "type":"Services"
        },
        {
            "category":"Health Services",
            "subcategory":"Doctor",
            "type":"Services"
        }
    ],
    "sg:phone":"+1 231 947 1112",
    "sg:postcode":"49684",
    "sg:province":"MI",
    "sg:tags":[
        "worker",
        "provides",
        "for",
        "migrant"
    ],
    "wof:name":"Northwest Michigan Health Svcs",
    "wof:placetype":"venue"
},
  "geometry": {"coordinates":[-85.645152,44.775193],"type":"Point"}
}