{
  "type": "Feature",
  "properties": {
    "iso:country":"US",
    "sg:address":"1949 E Jefferson Ave",
    "sg:city":"Detroit",
    "sg:classifiers":[
        {
            "category":"Retail",
            "subcategory":"Auto Rental",
            "type":"Services"
        }
    ],
    "sg:phone":"+1 313 259 1543",
    "sg:postcode":"48207",
    "sg:province":"MI",
    "sg:tags":[
        "car"
    ],
    "sg:website":"www.hertz.com",
    "wof:name":"Hertz Rent A Car and Hertz Local Edition",
    "wof:placetype":"venue"
},
  "geometry": {"coordinates":[-83.026965,42.336534],"type":"Point"}
}