{
  "type": "Feature",
  "properties": {
    "iso:country":"US",
    "sg:address":"2516 Emogene St",
    "sg:city":"Melvindale",
    "sg:classifiers":[
        {
            "category":"Manufacturing",
            "subcategory":"Rubber & Plastics",
            "type":"Manufacturing & Wholesale Goods"
        }
    ],
    "sg:phone":"+1 313 928 0867",
    "sg:postcode":"48122",
    "sg:province":"MI",
    "sg:tags":[
        "product",
        "mfg"
    ],
    "wof:name":"Nationwide Plastics",
    "wof:placetype":"venue"
},
  "geometry": {"coordinates":[-83.17972399999999,42.271175],"type":"Point"}
}