{
  "type": "Feature",
  "properties": {
    "iso:country":"US",
    "sg:address":"106 Airport Dr",
    "sg:city":"Kimball",
    "sg:classifiers":[
        {
            "category":"Autos & Motor Vehicles",
            "subcategory":"Automobile Sales",
            "type":"Retail Goods"
        },
        {
            "category":"Airport",
            "type":"Transportation"
        }
    ],
    "sg:phone":"+1 810 364 5885",
    "sg:postcode":"48079",
    "sg:province":"MI",
    "sg:tags":[
        "mfg",
        "support",
        "air",
        "equipment",
        "aircraft",
        "ground"
    ],
    "wof:name":"Action Air Parts Inc",
    "wof:placetype":"venue"
},
  "geometry": {"coordinates":[-82.52321600000001,42.903218],"type":"Point"}
}