{
  "type": "Feature",
  "properties": {
    "iso:country":"US",
    "sg:address":"45700 W 12 Mile Rd",
    "sg:city":"Novi",
    "sg:classifiers":[
        {
            "category":"Professional",
            "type":"Services"
        }
    ],
    "sg:phone":"+1 248 735 4158",
    "sg:postcode":"48377",
    "sg:province":"MI",
    "sg:tags":[
        "establishment"
    ],
    "wof:name":"Tele Scan Technology Inc",
    "wof:placetype":"venue"
},
  "geometry": {"coordinates":[-83.501974,42.494938],"type":"Point"}
}