{
  "type": "Feature",
  "properties": {
    "iso:country":"US",
    "sg:address":"3575 Prospect Rd",
    "sg:city":"Indian River",
    "sg:classifiers":[
        {
            "category":"Building & Trades",
            "subcategory":"Construction",
            "type":"Services"
        }
    ],
    "sg:phone":"+1 231 238 9607",
    "sg:postcode":"49749",
    "sg:province":"MI",
    "sg:tags":[
        "house"
    ],
    "wof:name":"Emmet Construction Co",
    "wof:placetype":"venue"
},
  "geometry": {"coordinates":[-84.61159499999999,45.414114],"type":"Point"}
}