{
  "type": "Feature",
  "properties": {
    "iso:country":"US",
    "sg:address":"8181 Contingo Ter",
    "sg:city":"Kalamazoo",
    "sg:classifiers":[
        {
            "category":"Retail",
            "subcategory":"Laundry & Dry Cleaning",
            "type":"Services"
        }
    ],
    "sg:phone":"+1 269 349 3996",
    "sg:postcode":"49009",
    "sg:province":"MI",
    "wof:name":"Superior Cleaning Soultions",
    "wof:placetype":"venue"
},
  "geometry": {"coordinates":[-85.709828,42.214931],"type":"Point"}
}