{
  "type": "Feature",
  "properties": {
    "iso:country":"US",
    "sg:address":"6020 W Pierson Rd",
    "sg:city":"Flushing",
    "sg:classifiers":[
        {
            "category":"Insurance",
            "subcategory":"Hazard Insurance",
            "type":"Services"
        }
    ],
    "sg:phone":"+1 810 732 7560",
    "sg:postcode":"48433",
    "sg:province":"MI",
    "sg:tags":[
        "property",
        "casualty"
    ],
    "wof:name":"Farm Bureau Mutual Life Insur",
    "wof:placetype":"venue"
},
  "geometry": {"coordinates":[-83.792355,43.060448],"type":"Point"}
}