{
  "type": "Feature",
  "properties": {
    "iso:country":"US",
    "sg:address":"18066 Henry St",
    "sg:city":"Melvindale",
    "sg:classifiers":[
        {
            "category":"Building & Trades",
            "subcategory":"Construction",
            "type":"Services"
        }
    ],
    "sg:phone":"+1 313 386 6120",
    "sg:postcode":"48122",
    "sg:province":"MI",
    "sg:tags":[
        "house"
    ],
    "wof:name":"Raines Remodeling & Maint",
    "wof:placetype":"venue"
},
  "geometry": {"coordinates":[-83.186111,42.28561],"type":"Point"}
}