{
  "type": "Feature",
  "properties": {
    "iso:country":"US",
    "sg:address":"610 Highland St",
    "sg:city":"Wyandotte",
    "sg:classifiers":[
        {
            "category":"Shopping",
            "subcategory":"Used Merchandise",
            "type":"Retail Goods"
        }
    ],
    "sg:phone":"+1 734 282 7182",
    "sg:postcode":"48192",
    "sg:province":"MI",
    "sg:tags":[
        "vintage",
        "consignment"
    ],
    "wof:name":"Ekko",
    "wof:placetype":"venue"
},
  "geometry": {"coordinates":[-83.159302,42.231201],"type":"Point"}
}