{
  "type": "Feature",
  "properties": {
    "iso:country":"US",
    "sg:address":"3465 Charing Cross Rd",
    "sg:city":"Ann Arbor",
    "sg:classifiers":[
        {
            "category":"Retail",
            "subcategory":"Auto Rental",
            "type":"Services"
        }
    ],
    "sg:phone":"+1 734 368 7568",
    "sg:postcode":"48108",
    "sg:province":"MI",
    "sg:tags":[
        "taxicab",
        "leasing"
    ],
    "wof:name":"Ann Arbor Leasing Company",
    "wof:placetype":"venue"
},
  "geometry": {"coordinates":[-83.689352,42.244768],"type":"Point"}
}