{
  "type": "Feature",
  "properties": {
    "iso:country":"US",
    "sg:address":"238 E Michigan Ave",
    "sg:city":"Paw Paw",
    "sg:classifiers":[
        {
            "category":"Organizations",
            "subcategory":"Professional Association",
            "type":"Services"
        }
    ],
    "sg:phone":"+1 269 657 4281",
    "sg:postcode":"49079",
    "sg:province":"MI",
    "wof:name":"Masonic Lodge",
    "wof:placetype":"venue"
},
  "geometry": {"coordinates":[-85.89043599999999,42.217547],"type":"Point"}
}