{
  "type": "Feature",
  "properties": {
    "iso:country":"US",
    "sg:address":"5115 N Smith Rd",
    "sg:city":"Owosso",
    "sg:classifiers":[
        {
            "category":"Real Estate",
            "subcategory":"Real Estate Agent",
            "type":"Services"
        }
    ],
    "sg:phone":"+1 989 723 2239",
    "sg:postcode":"48867",
    "sg:province":"MI",
    "wof:name":"Michigan State Realty",
    "wof:placetype":"venue"
},
  "geometry": {"coordinates":[-84.226176,43.076496],"type":"Point"}
}