{
  "type": "Feature",
  "properties": {
    "iso:country":"US",
    "sg:address":"7066 E River Rd",
    "sg:city":"Flushing",
    "sg:classifiers":[
        {
            "category":"Autos & Motor Vehicles",
            "subcategory":"Boat Sales",
            "type":"Retail Goods"
        },
        {
            "category":"Wholesale",
            "subcategory":"Sporting Goods",
            "type":"Manufacturing & Wholesale Goods"
        }
    ],
    "sg:phone":"+1 810 659 6562",
    "sg:postcode":"48433",
    "sg:province":"MI",
    "sg:tags":[
        "equipment",
        "gasoline",
        "supply"
    ],
    "wof:name":"Bob's Boathouse",
    "wof:placetype":"venue"
},
  "geometry": {"coordinates":[-83.814165,43.049079],"type":"Point"}
}