{
  "type": "Feature",
  "properties": {
    "iso:country":"US",
    "sg:address":"4014 S Saginaw St",
    "sg:city":"Burton",
    "sg:classifiers":[
        {
            "category":"Shopping",
            "subcategory":"Bicycles & Sporting Goods",
            "type":"Retail Goods"
        }
    ],
    "sg:phone":"+1 810 742 5420",
    "sg:postcode":"48529",
    "sg:province":"MI",
    "sg:website":"www.rockysonline.com",
    "wof:name":"Rocky's Great Outdoors",
    "wof:placetype":"venue"
},
  "geometry": {"coordinates":[-83.67254800000001,42.973101],"type":"Point"}
}