{
  "type": "Feature",
  "properties": {
    "iso:country":"US",
    "sg:address":"925 Grand Rapids St",
    "sg:city":"Middleville",
    "sg:classifiers":[
        {
            "category":"Wholesale",
            "subcategory":"Construction Materials",
            "type":"Manufacturing & Wholesale Goods"
        }
    ],
    "sg:phone":"+1 269 795 0002",
    "sg:postcode":"49333",
    "sg:province":"MI",
    "sg:tags":[
        "granite"
    ],
    "wof:name":"Advanced Stone & Tile Fbrctns",
    "wof:placetype":"venue"
},
  "geometry": {"coordinates":[-85.461699,42.718247],"type":"Point"}
}