{
  "type": "Feature",
  "properties": {
    "iso:country":"US",
    "sg:address":"5323 N Saginaw Rd",
    "sg:city":"Midland",
    "sg:classifiers":[
        {
            "category":"Wholesale",
            "subcategory":"Auto Parts",
            "type":"Manufacturing & Wholesale Goods"
        }
    ],
    "sg:phone":"+1 989 835 3391",
    "sg:postcode":"48642",
    "sg:province":"MI",
    "sg:tags":[
        "rental",
        "glass",
        "without",
        "truck",
        "residential"
    ],
    "wof:name":"Henderson Brothers Glass Inc",
    "wof:placetype":"venue"
},
  "geometry": {"coordinates":[-84.298717,43.644056],"type":"Point"}
}