{
  "type": "Feature",
  "properties": {
    "iso:country":"US",
    "sg:address":"5835 Mowerson Rd",
    "sg:city":"Brown City",
    "sg:classifiers":[
        {
            "category":"Farming",
            "subcategory":"Dairy Farm",
            "type":"Manufacturing & Wholesale Goods"
        }
    ],
    "sg:phone":"+1 810 378 5958",
    "sg:postcode":"48416",
    "sg:province":"MI",
    "wof:name":"Steve Bader",
    "wof:placetype":"venue"
},
  "geometry": {"coordinates":[-82.88301800000001,43.247544],"type":"Point"}
}