{
  "type": "Feature",
  "properties": {
    "iso:country":"US",
    "sg:address":"207 N 7th St",
    "sg:city":"Grand Haven",
    "sg:classifiers":[
        {
            "category":"Restaurant",
            "type":"Food & Drink"
        }
    ],
    "sg:phone":"+1 616 847 9008",
    "sg:postcode":"49417",
    "sg:province":"MI",
    "wof:name":"Charlie Mac's",
    "wof:placetype":"venue"
},
  "geometry": {"coordinates":[-86.222122,43.063359],"type":"Point"}
}