{
  "type": "Feature",
  "properties": {
    "iso:country":"US",
    "sg:address":"964 E 10 Mile Rd",
    "sg:city":"Hazel Park",
    "sg:classifiers":[
        {
            "category":"Home & Garden",
            "subcategory":"Garden Supply",
            "type":"Retail Goods"
        }
    ],
    "sg:phone":"+1 248 398 1551",
    "sg:postcode":"48030",
    "sg:province":"MI",
    "sg:tags":[
        "engine"
    ],
    "wof:name":"Booth Automotive Engine Kits",
    "wof:placetype":"venue"
},
  "geometry": {"coordinates":[-83.09529499999999,42.476143],"type":"Point"}
}