{
  "type": "Feature",
  "properties": {
    "iso:country":"US",
    "sg:address":"8435 Davison Rd",
    "sg:city":"Davison",
    "sg:classifiers":[
        {
            "category":"Restaurant",
            "type":"Food & Drink"
        }
    ],
    "sg:phone":"+1 810 658 9333",
    "sg:postcode":"48423",
    "sg:province":"MI",
    "sg:tags":[
        "pizza"
    ],
    "sg:website":"www.thepizzaco.net",
    "wof:name":"Pizza Company the",
    "wof:placetype":"venue"
},
  "geometry": {"coordinates":[-83.541,43.034302],"type":"Point"}
}