{
  "type": "Feature",
  "properties": {
    "iso:country":"US",
    "sg:address":"1375 Odanah Rd",
    "sg:city":"Hurley",
    "sg:classifiers":[
        {
            "category":"Building & Trades",
            "subcategory":"Construction",
            "type":"Services"
        }
    ],
    "sg:phone":"+1 715 561 2569",
    "sg:postcode":"54534",
    "sg:province":"WI",
    "sg:tags":[
        "road",
        "contractor"
    ],
    "wof:name":"Ross Peterson Construction",
    "wof:placetype":"venue"
},
  "geometry": {"coordinates":[-90.201337,46.436356],"type":"Point"}
}