{
  "type": "Feature",
  "properties": {
    "iso:country":"US",
    "sg:address":"171 E Jefferson St",
    "sg:city":"Frankenmuth",
    "sg:classifiers":[
        {
            "category":"Manufacturing",
            "subcategory":"Signs",
            "type":"Manufacturing & Wholesale Goods"
        }
    ],
    "sg:phone":"+1 989 652 3888",
    "sg:postcode":"48734",
    "sg:province":"MI",
    "sg:tags":[
        "body",
        "auto",
        "specialty",
        "mfg"
    ],
    "wof:name":"Autograph Cstm Signs & Design",
    "wof:placetype":"venue"
},
  "geometry": {"coordinates":[-83.73836900000001,43.321572],"type":"Point"}
}