{
  "type": "Feature",
  "properties": {
    "iso:country":"US",
    "sg:address":"2002 Wildwood Harbor Rd",
    "sg:city":"Boyne City",
    "sg:classifiers":[
        {
            "category":"Utilities",
            "subcategory":"Mobile Phone",
            "type":"Services"
        }
    ],
    "sg:phone":"+1 231 582 9679",
    "sg:postcode":"49712",
    "sg:province":"MI",
    "sg:tags":[
        "telephone",
        "cellular"
    ],
    "wof:name":"Century Tel",
    "wof:placetype":"venue"
},
  "geometry": {"coordinates":[-85.00737700000001,45.23036],"type":"Point"}
}