{
  "type": "Feature",
  "properties": {
    "iso:country":"US",
    "sg:address":"1918 E Kalamazoo St",
    "sg:city":"Lansing",
    "sg:classifiers":[
        {
            "category":"Shopping",
            "type":"Retail Goods"
        }
    ],
    "sg:phone":"+1 517 492 1918",
    "sg:postcode":"48912",
    "sg:province":"MI",
    "sg:tags":[
        "cosmetic",
        "perfume"
    ],
    "wof:name":"King World Beauty Supply",
    "wof:placetype":"venue"
},
  "geometry": {"coordinates":[-84.52267999999999,42.729903],"type":"Point"}
}