{
  "type": "Feature",
  "properties": {
    "iso:country":"US",
    "sg:address":"3067 Loon Lake Shores Rd",
    "sg:city":"Waterford",
    "sg:classifiers":[
        {
            "category":"Wholesale",
            "subcategory":"Machinery & Supplies",
            "type":"Manufacturing & Wholesale Goods"
        }
    ],
    "sg:phone":"+1 248 673 6042",
    "sg:postcode":"48329",
    "sg:province":"MI",
    "sg:tags":[
        "equipment",
        "hydraulic"
    ],
    "wof:name":"SPX-Power Team",
    "wof:placetype":"venue"
},
  "geometry": {"coordinates":[-83.36223099999999,42.686067],"type":"Point"}
}