{
  "type": "Feature",
  "properties": {
    "iso:country":"US",
    "sg:address":"2401 Partridge Rd",
    "sg:city":"Port Huron",
    "sg:classifiers":[
        {
            "category":"Retail",
            "subcategory":"Repair Shop",
            "type":"Services"
        }
    ],
    "sg:phone":"+1 810 982 0992",
    "sg:postcode":"48060",
    "sg:province":"MI",
    "sg:tags":[
        "wa",
        "contractor"
    ],
    "wof:name":"Modern Sewer & Drain Cleaning",
    "wof:placetype":"venue"
},
  "geometry": {"coordinates":[-82.49325899999999,42.979946],"type":"Point"}
}