{
  "type": "Feature",
  "properties": {
    "iso:country":"US",
    "sg:address":"6377 Marina Dr",
    "sg:city":"Clay",
    "sg:classifiers":[
        {
            "category":"Building & Trades",
            "subcategory":"Construction",
            "type":"Services"
        }
    ],
    "sg:phone":"+1 810 794 4410",
    "sg:postcode":"48001",
    "sg:province":"MI",
    "sg:tags":[
        "carpenter"
    ],
    "wof:name":"Mark Trombly Co",
    "wof:placetype":"venue"
},
  "geometry": {"coordinates":[-82.60865699999999,42.627539],"type":"Point"}
}