{
  "type": "Feature",
  "properties": {
    "iso:country":"US",
    "sg:address":"415 Cherry Blossom Ln",
    "sg:city":"Rochester Hills",
    "sg:classifiers":[
        {
            "category":"Education",
            "subcategory":"School",
            "type":"Public Place"
        }
    ],
    "sg:phone":"+1 248 651 4179",
    "sg:postcode":"48306",
    "sg:province":"MI",
    "wof:name":"Fishers Academy Inc",
    "wof:placetype":"venue"
},
  "geometry": {"coordinates":[-83.144824,42.705134],"type":"Point"}
}