{
  "type": "Feature",
  "properties": {
    "iso:country":"US",
    "sg:address":"28612 Harper Ave",
    "sg:city":"Saint Clair Shores",
    "sg:classifiers":[
        {
            "category":"Shopping",
            "subcategory":"Bicycles & Sporting Goods",
            "type":"Retail Goods"
        }
    ],
    "sg:phone":"+1 586 772 7676",
    "sg:postcode":"48081",
    "sg:province":"MI",
    "wof:name":"Sea-Side Diving",
    "wof:placetype":"venue"
},
  "geometry": {"coordinates":[-82.898017,42.504512],"type":"Point"}
}