{
  "type": "Feature",
  "properties": {
    "iso:country":"US",
    "sg:address":"32747 Mound Rd",
    "sg:city":"Warren",
    "sg:classifiers":[
        {
            "category":"Restaurant",
            "type":"Food & Drink"
        }
    ],
    "sg:menulink":"http://www.allmenus.com/mi/warren/89335-bronx-burgers--restaurant/menu/",
    "sg:phone":"+1 586 939 7800",
    "sg:postcode":"48092",
    "sg:province":"MI",
    "sg:tags":[
        "burger",
        "american"
    ],
    "wof:name":"Bronx Burgers & Restaurant",
    "wof:placetype":"venue"
},
  "geometry": {"coordinates":[-83.048129,42.534984],"type":"Point"}
}