{
  "type": "Feature",
  "properties": {
    "iso:country":"US",
    "sg:address":"13609 Grace Dr",
    "sg:city":"Eagle",
    "sg:phone":"+1 517 626 6958",
    "sg:postcode":"48822",
    "sg:province":"MI",
    "sg:tags":[
        "farm",
        "grain",
        "cash"
    ],
    "wof:name":"Schafer Petrolum",
    "wof:placetype":"venue"
},
  "geometry": {"coordinates":[-84.757302,42.82154],"type":"Point"}
}