{
  "type": "Feature",
  "properties": {
    "iso:country":"US",
    "sg:address":"675 Cotts Way",
    "sg:city":"Oxford",
    "sg:classifiers":[
        {
            "category":"Shopping",
            "subcategory":"Clothing, Apparel, & Fashions",
            "type":"Retail Goods"
        }
    ],
    "sg:phone":"+1 248 236 9428",
    "sg:postcode":"48371",
    "sg:province":"MI",
    "sg:tags":[
        "infant",
        "wear"
    ],
    "wof:name":"Aller-Tees",
    "wof:placetype":"venue"
},
  "geometry": {"coordinates":[-83.26845,42.812587],"type":"Point"}
}