{
  "type": "Feature",
  "properties": {
    "iso:country":"US",
    "sg:address":"17117 W 9 Mile Rd",
    "sg:city":"Southfield",
    "sg:classifiers":[
        {
            "category":"Banks & Credit Unions",
            "subcategory":"Bank",
            "type":"Services"
        }
    ],
    "sg:phone":"+1 248 557 4477",
    "sg:postcode":"48075",
    "sg:province":"MI",
    "wof:name":"Fidelity Bank",
    "wof:placetype":"venue"
},
  "geometry": {"coordinates":[-83.214558,42.458838],"type":"Point"}
}