{
  "type": "Feature",
  "properties": {
    "iso:country":"US",
    "sg:address":"1917 Clark Rd",
    "sg:city":"Central Lake",
    "sg:classifiers":[
        {
            "category":"Manufacturing",
            "subcategory":"Tools & Machinery",
            "type":"Manufacturing & Wholesale Goods"
        }
    ],
    "sg:phone":"+1 231 544 3703",
    "sg:postcode":"49622",
    "sg:province":"MI",
    "sg:tags":[
        "industrial",
        "mfg"
    ],
    "wof:name":"Greens Fabrication Repair",
    "wof:placetype":"venue"
},
  "geometry": {"coordinates":[-85.28223800000001,45.055459],"type":"Point"}
}