{
  "type": "Feature",
  "properties": {
    "iso:country":"US",
    "sg:address":"600 E 9 Mile Rd",
    "sg:city":"Ferndale",
    "sg:classifiers":[
        {
            "category":"Sports & Exercise",
            "subcategory":"Bowling",
            "type":"Entertainment"
        }
    ],
    "sg:phone":"+1 248 544 0530",
    "sg:postcode":"48220",
    "sg:province":"MI",
    "wof:name":"Luxury Lanes & Lounge",
    "wof:placetype":"venue"
},
  "geometry": {"coordinates":[-83.125801,42.460701],"type":"Point"}
}