{
  "type": "Feature",
  "properties": {
    "iso:country":"US",
    "sg:address":"2797 Kimmel St",
    "sg:city":"Stevensville",
    "sg:classifiers":[
        {
            "category":"Home & Garden",
            "subcategory":"Home Furnishings",
            "type":"Retail Goods"
        }
    ],
    "sg:phone":"+1 269 556 2552",
    "sg:postcode":"49127",
    "sg:province":"MI",
    "sg:tags":[
        "blanket"
    ],
    "wof:name":"Accomplish Quilting Inc",
    "wof:placetype":"venue"
},
  "geometry": {"coordinates":[-86.521134,42.013596],"type":"Point"}
}