{
  "type": "Feature",
  "properties": {
    "iso:country":"US",
    "sg:address":"748 Starkweather St",
    "sg:city":"Plymouth",
    "sg:classifiers":[
        {
            "category":"Shopping",
            "subcategory":"Used Merchandise",
            "type":"Retail Goods"
        }
    ],
    "sg:phone":"+1 734 207 9565",
    "sg:postcode":"48170",
    "sg:province":"MI",
    "wof:name":"Doloress Antiques",
    "wof:placetype":"venue"
},
  "geometry": {"coordinates":[-83.461944,42.380222],"type":"Point"}
}