{
  "type": "Feature",
  "properties": {
    "iso:country":"US",
    "sg:address":"58335 County Line Rd",
    "sg:city":"Three Rivers",
    "sg:classifiers":[
        {
            "category":"Building & Trades",
            "subcategory":"Landscaping Services",
            "type":"Services"
        }
    ],
    "sg:phone":"+1 269 244 8524",
    "sg:postcode":"49093",
    "sg:province":"MI",
    "wof:name":"American Arbor Tree Service",
    "wof:placetype":"venue"
},
  "geometry": {"coordinates":[-85.760761,41.949455],"type":"Point"}
}