{
  "type": "Feature",
  "properties": {
    "iso:country":"US",
    "sg:address":"4812 Willow Ln",
    "sg:city":"West Bloomfield",
    "sg:classifiers":[
        {
            "category":"Banks & Credit Unions",
            "subcategory":"Financial Services",
            "type":"Services"
        }
    ],
    "sg:phone":"+1 248 681 2475",
    "sg:postcode":"48324",
    "sg:province":"MI",
    "sg:tags":[
        "trust",
        "management"
    ],
    "wof:name":"Tuktawa Foundation",
    "wof:placetype":"venue"
},
  "geometry": {"coordinates":[-83.377875,42.582495],"type":"Point"}
}