{
  "type": "Feature",
  "properties": {
    "iso:country":"US",
    "sg:address":"967 Oakwood Dr",
    "sg:city":"Rochester",
    "sg:classifiers":[
        {
            "category":"Banks & Credit Unions",
            "subcategory":"Bank",
            "type":"Services"
        }
    ],
    "sg:phone":"+1 248 650 4303",
    "sg:postcode":"48307",
    "sg:province":"MI",
    "sg:tags":[
        "loan",
        "real estate"
    ],
    "wof:name":"Strategic Capital Mortgage Co",
    "wof:placetype":"venue"
},
  "geometry": {"coordinates":[-83.14743799999999,42.683325],"type":"Point"}
}