{
  "type": "Feature",
  "properties": {
    "iso:country":"US",
    "sg:address":"1096 S Belsay Rd",
    "sg:city":"Burton",
    "sg:classifiers":[
        {
            "category":"Health Services",
            "subcategory":"Doctor",
            "type":"Services"
        }
    ],
    "sg:phone":"+1 810 743 3880",
    "sg:postcode":"48509",
    "sg:province":"MI",
    "sg:tags":[
        "medical"
    ],
    "wof:name":"Family Medicine PC",
    "wof:placetype":"venue"
},
  "geometry": {"coordinates":[-83.595411,43.018817],"type":"Point"}
}