{
  "type": "Feature",
  "properties": {
    "iso:country":"US",
    "sg:address":"169 E Division St",
    "sg:city":"Sparta",
    "sg:classifiers":[
        {
            "category":"Retail",
            "subcategory":"Repair Shop",
            "type":"Services"
        }
    ],
    "sg:phone":"+1 616 887 8425",
    "sg:postcode":"49345",
    "sg:province":"MI",
    "sg:tags":[
        "jewelry"
    ],
    "wof:name":"Paul-Lawrence Jewelry",
    "wof:placetype":"venue"
},
  "geometry": {"coordinates":[-85.705962,43.160739],"type":"Point"}
}