{
  "type": "Feature",
  "properties": {
    "iso:country":"US",
    "sg:address":"7881 Golf Point Dr SE",
    "sg:city":"Caledonia",
    "sg:classifiers":[
        {
            "category":"Professional",
            "subcategory":"Employment Agencies",
            "type":"Services"
        }
    ],
    "sg:phone":"+1 616 536 2555",
    "sg:postcode":"49316",
    "sg:province":"MI",
    "wof:name":"Opalstaff",
    "wof:placetype":"venue"
},
  "geometry": {"coordinates":[-85.540948,42.821143],"type":"Point"}
}