{
  "type": "Feature",
  "properties": {
    "iso:country":"US",
    "sg:address":"467 Forest Ave",
    "sg:city":"Plymouth",
    "sg:classifiers":[
        {
            "category":"Food & Beverages",
            "subcategory":"Specialty",
            "type":"Retail Goods"
        }
    ],
    "sg:phone":"+1 734 667 2755",
    "sg:postcode":"48170",
    "sg:province":"MI",
    "sg:website":"oldworldolivepress.com",
    "wof:name":"Old World Olive Press",
    "wof:placetype":"venue"
},
  "geometry": {"coordinates":[-83.470454,42.369155],"type":"Point"}
}