{
  "type": "Feature",
  "properties": {
    "iso:country":"US",
    "sg:address":"14432 Northline Rd",
    "sg:city":"Southgate",
    "sg:classifiers":[
        {
            "category":"Shopping",
            "subcategory":"Music",
            "type":"Retail Goods"
        }
    ],
    "sg:phone":"+1 734 246 2440",
    "sg:postcode":"48195",
    "sg:province":"MI",
    "wof:name":"Rock Box",
    "wof:placetype":"venue"
},
  "geometry": {"coordinates":[-83.199879,42.213673],"type":"Point"}
}