{
  "type": "Feature",
  "properties": {
    "iso:country":"US",
    "sg:address":"14800 Farmington Rd",
    "sg:city":"Livonia",
    "sg:classifiers":[
        {
            "category":"Banks & Credit Unions",
            "subcategory":"Bank",
            "type":"Services"
        }
    ],
    "sg:phone":"+1 734 422 2003",
    "sg:postcode":"48154",
    "sg:province":"MI",
    "sg:tags":[
        "banker",
        "mortgage"
    ],
    "wof:name":"Plymouth Exchange Mrtg Corp",
    "wof:placetype":"venue"
},
  "geometry": {"coordinates":[-83.373463,42.392287],"type":"Point"}
}