{
  "type": "Feature",
  "properties": {
    "iso:country":"US",
    "sg:address":"32088 Gratiot Ave",
    "sg:city":"Roseville",
    "sg:classifiers":[
        {
            "category":"Restaurant",
            "type":"Food & Drink"
        }
    ],
    "sg:menulink":"http://www.allmenus.com/mi/roseville/10572-la-shish/menu/",
    "sg:phone":"+1 586 415 0500",
    "sg:postcode":"48066",
    "sg:province":"MI",
    "sg:tags":[
        "mediterranean"
    ],
    "wof:name":"La Shish",
    "wof:placetype":"venue"
},
  "geometry": {"coordinates":[-82.91473499999999,42.530547],"type":"Point"}
}