{
  "type": "Feature",
  "properties": {
    "iso:country":"US",
    "sg:address":"450 W Michigan Ave",
    "sg:city":"Parma",
    "sg:classifiers":[
        {
            "category":"Utilities",
            "subcategory":"Natural Gas",
            "type":"Services"
        }
    ],
    "sg:phone":"+1 517 531 3426",
    "sg:postcode":"49269",
    "sg:province":"MI",
    "sg:tags":[
        "transmission",
        "distribution"
    ],
    "wof:name":"Ameri Gas Inc",
    "wof:placetype":"venue"
},
  "geometry": {"coordinates":[-84.605324,42.26039],"type":"Point"}
}