{
  "type": "Feature",
  "properties": {
    "iso:country":"US",
    "sg:address":"7625 Davis Rd",
    "sg:city":"Buckley",
    "sg:classifiers":[
        {
            "category":"Farming",
            "subcategory":"Farm",
            "type":"Manufacturing & Wholesale Goods"
        }
    ],
    "sg:phone":"+1 231 263 7239",
    "sg:postcode":"49620",
    "sg:province":"MI",
    "wof:name":"Werp Farms",
    "wof:placetype":"venue"
},
  "geometry": {"coordinates":[-85.733052,44.556097],"type":"Point"}
}