{
  "type": "Feature",
  "properties": {
    "iso:country":"US",
    "sg:address":"20779 Washington St",
    "sg:city":"Roseville",
    "sg:classifiers":[
        {
            "category":"Personal",
            "type":"Services"
        }
    ],
    "sg:phone":"+1 586 772 3249",
    "sg:postcode":"48066",
    "sg:province":"MI",
    "sg:tags":[
        "information"
    ],
    "wof:name":"Global Exchange Services Inc",
    "wof:placetype":"venue"
},
  "geometry": {"coordinates":[-82.907447,42.513909],"type":"Point"}
}