{
  "type": "Feature",
  "properties": {
    "iso:country":"US",
    "sg:address":"713 W University Dr",
    "sg:city":"Rochester",
    "sg:classifiers":[
        {
            "category":"Professional",
            "type":"Services"
        }
    ],
    "sg:phone":"+1 248 656 7934",
    "sg:postcode":"48307",
    "sg:province":"MI",
    "wof:name":"Welcome Service Rochester",
    "wof:placetype":"venue"
},
  "geometry": {"coordinates":[-83.142078,42.681837],"type":"Point"}
}