{
  "type": "Feature",
  "properties": {
    "iso:country":"US",
    "sg:address":"23405 Plymouth Rd",
    "sg:city":"Redford",
    "sg:classifiers":[
        {
            "category":"Community Center",
            "type":"Public Place"
        }
    ],
    "sg:phone":"+1 313 535 7880",
    "sg:postcode":"48239",
    "sg:province":"MI",
    "sg:tags":[
        "medical"
    ],
    "wof:name":"Redford Urgent Care Medical Center",
    "wof:placetype":"venue"
},
  "geometry": {"coordinates":[-83.268196,42.371302],"type":"Point"}
}