{
  "type": "Feature",
  "properties": {
    "iso:country":"US",
    "sg:address":"7460 Ore Lake Rd",
    "sg:city":"Brighton",
    "sg:classifiers":[
        {
            "category":"Building & Trades",
            "subcategory":"Construction",
            "type":"Services"
        }
    ],
    "sg:phone":"+1 810 231 0084",
    "sg:postcode":"48116",
    "sg:province":"MI",
    "sg:tags":[
        "contractor"
    ],
    "wof:name":"M & M Bg Construction Inc",
    "wof:placetype":"venue"
},
  "geometry": {"coordinates":[-83.799204,42.471869],"type":"Point"}
}