{
  "type": "Feature",
  "properties": {
    "iso:country":"US",
    "sg:address":"601 Jackson St",
    "sg:city":"Ironwood",
    "sg:classifiers":[
        {
            "category":"Government",
            "subcategory":"Office",
            "type":"Public Place"
        }
    ],
    "sg:phone":"+1 906 932 0399",
    "sg:postcode":"49938",
    "sg:province":"MI",
    "sg:tags":[
        "armed",
        "force",
        "recruiting"
    ],
    "wof:name":"US Army Recruiting",
    "wof:placetype":"venue"
},
  "geometry": {"coordinates":[-90.14582900000001,46.465071],"type":"Point"}
}