{
  "type": "Feature",
  "properties": {
    "iso:country":"US",
    "sg:address":"3999 Bald Mountain Rd",
    "sg:city":"Lake Orion",
    "sg:classifiers":[
        {
            "category":"Professional",
            "subcategory":"Business Services",
            "type":"Services"
        }
    ],
    "sg:phone":"+1 248 475 9175",
    "sg:postcode":"48360",
    "sg:province":"MI",
    "wof:name":"Blatant Lines Inc",
    "wof:placetype":"venue"
},
  "geometry": {"coordinates":[-83.234821,42.724219],"type":"Point"}
}