{
  "type": "Feature",
  "properties": {
    "iso:country":"US",
    "sg:address":"1120 Middlebelt Rd",
    "sg:city":"Inkster",
    "sg:classifiers":[
        {
            "category":"Retail",
            "subcategory":"Laundry & Dry Cleaning",
            "type":"Services"
        }
    ],
    "sg:phone":"+1 734 722 4747",
    "sg:postcode":"48141",
    "sg:province":"MI",
    "wof:name":"Det Expert Forty Minute Cleaners",
    "wof:placetype":"venue"
},
  "geometry": {"coordinates":[-83.3302,42.302799],"type":"Point"}
}