{
  "type": "Feature",
  "properties": {
    "iso:country":"US",
    "sg:address":"30506 Hennepin St",
    "sg:city":"Garden City",
    "sg:classifiers":[
        {
            "category":"Professional",
            "subcategory":"Business Services",
            "type":"Services"
        }
    ],
    "sg:phone":"+1 734 425 0865",
    "sg:postcode":"48135",
    "sg:province":"MI",
    "wof:name":"Right Choice Home Inspections",
    "wof:placetype":"venue"
},
  "geometry": {"coordinates":[-83.342797,42.320006],"type":"Point"}
}