{
  "type": "Feature",
  "properties": {
    "iso:country":"US",
    "sg:address":"4085 S Saginaw St",
    "sg:city":"Burton",
    "sg:classifiers":[
        {
            "category":"Banks & Credit Unions",
            "subcategory":"Bank",
            "type":"Services"
        }
    ],
    "sg:phone":"+1 810 234 3557",
    "sg:postcode":"48529",
    "sg:province":"MI",
    "sg:website":"www.bankone.com",
    "wof:name":"Bank One",
    "wof:placetype":"venue"
},
  "geometry": {"coordinates":[-83.672264,42.972084],"type":"Point"}
}