{
  "type": "Feature",
  "properties": {
    "iso:country":"US",
    "sg:address":"2694 Garfield Rd S",
    "sg:city":"Traverse City",
    "sg:classifiers":[
        {
            "category":"Personal",
            "type":"Services"
        }
    ],
    "sg:phone":"+1 231 946 0752",
    "sg:postcode":"49686",
    "sg:province":"MI",
    "sg:tags":[
        "therapist",
        "massage"
    ],
    "wof:name":"Therapy Great Lakes Massage",
    "wof:placetype":"venue"
},
  "geometry": {"coordinates":[-85.531019,44.648231],"type":"Point"}
}