{
  "type": "Feature",
  "properties": {
    "iso:country":"US",
    "sg:address":"3270 Newport Rd",
    "sg:city":"Newport",
    "sg:classifiers":[
        {
            "category":"Food & Beverages",
            "subcategory":"Groceries & Convenience Stores",
            "type":"Retail Goods"
        }
    ],
    "sg:phone":"+1 734 586 3394",
    "sg:postcode":"48166",
    "sg:province":"MI",
    "wof:name":"Newport Travel Ctr",
    "wof:placetype":"venue"
},
  "geometry": {"coordinates":[-83.319181,42.007603],"type":"Point"}
}