{
  "type": "Feature",
  "properties": {
    "iso:country":"US",
    "sg:address":"8157 W P Q Ave",
    "sg:city":"Kalamazoo",
    "sg:classifiers":[
        {
            "category":"Manufacturing",
            "subcategory":"Glass & Minerals",
            "type":"Manufacturing & Wholesale Goods"
        }
    ],
    "sg:phone":"+1 269 372 9620",
    "sg:postcode":"49009",
    "sg:province":"MI",
    "sg:tags":[
        "product",
        "mfg"
    ],
    "wof:name":"Enhanced Glass",
    "wof:placetype":"venue"
},
  "geometry": {"coordinates":[-85.70611100000001,42.211728],"type":"Point"}
}