{
  "type": "Feature",
  "properties": {
    "iso:country":"US",
    "sg:address":"2251 N Squirrel Rd",
    "sg:city":"Auburn Hills",
    "sg:classifiers":[
        {
            "category":"Health Services",
            "subcategory":"Doctor",
            "type":"Services"
        }
    ],
    "sg:phone":"+1 248 364 0500",
    "sg:postcode":"48326",
    "sg:province":"MI",
    "sg:tags":[
        "physician",
        "surgeon"
    ],
    "wof:name":"Robert Cornfield",
    "wof:placetype":"venue"
},
  "geometry": {"coordinates":[-83.220771,42.674029],"type":"Point"}
}