{
  "type": "Feature",
  "properties": {
    "iso:country":"US",
    "sg:address":"1204 N Leroy St",
    "sg:city":"Fenton",
    "sg:classifiers":[
        {
            "category":"Restaurant",
            "type":"Food & Drink"
        }
    ],
    "sg:phone":"+1 810 629 4133",
    "sg:postcode":"48430",
    "sg:province":"MI",
    "wof:name":"Great Lake",
    "wof:placetype":"venue"
},
  "geometry": {"coordinates":[-83.707247,42.811002],"type":"Point"}
}