{
  "type": "Feature",
  "properties": {
    "iso:country":"US",
    "sg:address":"20545 W 7 Mile Rd",
    "sg:city":"Detroit",
    "sg:classifiers":[
        {
            "category":"Autos & Motor Vehicles",
            "subcategory":"Fuel & Gas Station",
            "type":"Retail Goods"
        }
    ],
    "sg:phone":"+1 313 535 2915",
    "sg:postcode":"48219",
    "sg:province":"MI",
    "wof:name":"Marathon",
    "wof:placetype":"venue"
},
  "geometry": {"coordinates":[-83.24506599999999,42.429285],"type":"Point"}
}