{
  "type": "Feature",
  "properties": {
    "iso:country":"US",
    "sg:address":"3818 Grant Ave",
    "sg:city":"Fort Gratiot",
    "sg:classifiers":[
        {
            "category":"Organizations",
            "subcategory":"Religious Organization",
            "type":"Services"
        }
    ],
    "sg:phone":"+1 810 982 6973",
    "sg:postcode":"48059",
    "sg:province":"MI",
    "wof:name":"Thomas J Seppo Rev",
    "wof:placetype":"venue"
},
  "geometry": {"coordinates":[-82.49045700000001,43.012715],"type":"Point"}
}