{
  "type": "Feature",
  "properties": {
    "iso:country":"US",
    "sg:address":"3700 Mill Creek Ave NE",
    "sg:city":"Comstock Park",
    "sg:classifiers":[
        {
            "category":"Freight",
            "type":"Transportation"
        }
    ],
    "sg:phone":"+1 616 784 5214",
    "sg:postcode":"49321",
    "sg:province":"MI",
    "sg:tags":[
        "self"
    ],
    "wof:name":"Michigan Moving and Storage Co",
    "wof:placetype":"venue"
},
  "geometry": {"coordinates":[-85.66764999999999,43.03228],"type":"Point"}
}