{
  "type": "Feature",
  "properties": {
    "iso:country":"US",
    "sg:address":"324 N Grand Traverse St",
    "sg:city":"Flint",
    "sg:classifiers":[
        {
            "category":"Shopping",
            "subcategory":"Used Merchandise",
            "type":"Retail Goods"
        }
    ],
    "sg:phone":"+1 810 237 3224",
    "sg:postcode":"48503",
    "sg:province":"MI",
    "wof:name":"Empire Antiques and Decorative",
    "wof:placetype":"venue"
},
  "geometry": {"coordinates":[-83.69784799999999,43.016832],"type":"Point"}
}