{
  "type": "Feature",
  "properties": {
    "iso:country":"US",
    "sg:address":"6200 S Pennsylvania Ave",
    "sg:city":"Lansing",
    "sg:classifiers":[
        {
            "category":"Professional",
            "subcategory":"Accounting & Tax Preparation",
            "type":"Services"
        }
    ],
    "sg:phone":"+1 517 394 3748",
    "sg:postcode":"48911",
    "sg:province":"MI",
    "sg:tags":[
        "return",
        "filing"
    ],
    "wof:name":"J & H Tax Svc",
    "wof:placetype":"venue"
},
  "geometry": {"coordinates":[-84.538206,42.666132],"type":"Point"}
}