{
  "type": "Feature",
  "properties": {
    "iso:country":"US",
    "sg:address":"2256 Riverside Dr",
    "sg:city":"Trenton",
    "sg:classifiers":[
        {
            "category":"Freight",
            "type":"Transportation"
        }
    ],
    "sg:phone":"+1 734 675 7997",
    "sg:postcode":"48183",
    "sg:province":"MI",
    "sg:tags":[
        "arrangement"
    ],
    "wof:name":"Great Lakes Maritime Transport",
    "wof:placetype":"venue"
},
  "geometry": {"coordinates":[-83.17506400000001,42.147969],"type":"Point"}
}