{
  "type": "Feature",
  "properties": {
    "iso:country":"US",
    "sg:address":"5185 144th Ave",
    "sg:city":"Holland",
    "sg:classifiers":[
        {
            "category":"Retail",
            "subcategory":"Repair Shop",
            "type":"Services"
        }
    ],
    "sg:phone":"+1 616 399 3711",
    "sg:postcode":"49424",
    "sg:province":"MI",
    "wof:name":"J L H Marine Repair Inc",
    "wof:placetype":"venue"
},
  "geometry": {"coordinates":[-86.138381,42.856296],"type":"Point"}
}