{
  "type": "Feature",
  "properties": {
    "iso:country":"US",
    "sg:address":"8296 E US Hwy 10",
    "sg:city":"Chase",
    "sg:classifiers":[
        {
            "category":"Government",
            "subcategory":"Office",
            "type":"Public Place"
        }
    ],
    "sg:phone":"+1 231 832 3018",
    "sg:postcode":"49623",
    "sg:province":"MI",
    "sg:tags":[
        "village"
    ],
    "wof:name":"Chase Twp Hall",
    "wof:placetype":"venue"
},
  "geometry": {"coordinates":[-85.635981,43.887745],"type":"Point"}
}