{
  "type": "Feature",
  "properties": {
    "iso:country":"US",
    "sg:address":"4438 Westshire Dr NW",
    "sg:city":"Comstock Park",
    "sg:classifiers":[
        {
            "category":"Restaurant",
            "type":"Food & Drink"
        }
    ],
    "sg:phone":"+1 616 784 3620",
    "sg:postcode":"49321",
    "sg:province":"MI",
    "sg:tags":[
        "pizza"
    ],
    "wof:name":"J T's Pizza Depot",
    "wof:placetype":"venue"
},
  "geometry": {"coordinates":[-85.68821800000001,43.047748],"type":"Point"}
}