{
  "type": "Feature",
  "properties": {
    "iso:country":"US",
    "sg:address":"2337 Lorriana Ln",
    "sg:city":"Hartland",
    "sg:classifiers":[
        {
            "category":"Building & Trades",
            "subcategory":"Construction",
            "type":"Services"
        }
    ],
    "sg:phone":"+1 810 632 7804",
    "sg:postcode":"48353",
    "sg:province":"MI",
    "sg:tags":[
        "hanging",
        "contractor"
    ],
    "wof:name":"Rileys Custom Painting",
    "wof:placetype":"venue"
},
  "geometry": {"coordinates":[-83.737915,42.639554],"type":"Point"}
}