{
  "type": "Feature",
  "properties": {
    "iso:country":"US",
    "sg:address":"207 Lake Linden Ave",
    "sg:city":"Calumet",
    "sg:classifiers":[
        {
            "category":"Insurance",
            "subcategory":"Insurance Agent",
            "type":"Services"
        }
    ],
    "sg:phone":"+1 906 337 4400",
    "sg:postcode":"49913",
    "sg:province":"MI",
    "wof:name":"Peter A Wesa",
    "wof:placetype":"venue"
},
  "geometry": {"coordinates":[-88.445622,47.233644],"type":"Point"}
}