{
  "type": "Feature",
  "properties": {
    "iso:country":"US",
    "sg:address":"24483 W 10 Mile Rd",
    "sg:city":"Southfield",
    "sg:classifiers":[
        {
            "category":"Wholesale",
            "subcategory":"Furniture",
            "type":"Manufacturing & Wholesale Goods"
        }
    ],
    "sg:phone":"+1 248 357 7211",
    "sg:postcode":"48034",
    "sg:province":"MI",
    "sg:tags":[
        "equipment"
    ],
    "wof:name":"Global Industries Inc",
    "wof:placetype":"venue"
},
  "geometry": {"coordinates":[-83.285301,42.471699],"type":"Point"}
}