{
  "type": "Feature",
  "properties": {
    "iso:country":"US",
    "sg:address":"1424 Ivanhoe Rd",
    "sg:city":"Ludington",
    "sg:classifiers":[
        {
            "category":"Real Estate",
            "subcategory":"Real Estate Agent",
            "type":"Services"
        }
    ],
    "sg:phone":"+1 231 845 1343",
    "sg:postcode":"49431",
    "sg:province":"MI",
    "wof:name":"Sherman Oaks Apartments",
    "wof:placetype":"venue"
},
  "geometry": {"coordinates":[-86.431759,43.974553],"type":"Point"}
}