{
  "type": "Feature",
  "properties": {
    "iso:country":"US",
    "sg:address":"117 Railroad Ave",
    "sg:city":"Daggett",
    "sg:classifiers":[
        {
            "category":"Bars & Pubs",
            "type":"Food & Drink"
        }
    ],
    "sg:phone":"+1 906 753 6381",
    "sg:postcode":"49821",
    "sg:province":"MI",
    "wof:name":"J R's Place",
    "wof:placetype":"venue"
},
  "geometry": {"coordinates":[-87.604662,45.46334],"type":"Point"}
}