{
  "type": "Feature",
  "properties": {
    "iso:country":"US",
    "sg:address":"20731 Robinson St",
    "sg:city":"Farmington Hills",
    "sg:classifiers":[
        {
            "category":"Building & Trades",
            "subcategory":"Construction",
            "type":"Services"
        }
    ],
    "sg:phone":"+1 248 626 6355",
    "sg:postcode":"48336",
    "sg:province":"MI",
    "sg:tags":[
        "designer",
        "dealer",
        "pool",
        "swimming"
    ],
    "wof:name":"Superior Pools",
    "wof:placetype":"venue"
},
  "geometry": {"coordinates":[-83.362038,42.442477],"type":"Point"}
}