{
  "type": "Feature",
  "properties": {
    "iso:country":"US",
    "sg:address":"400 Maynard St",
    "sg:city":"Ann Arbor",
    "sg:classifiers":[
        {
            "category":"Health Services",
            "subcategory":"Health Practitioner",
            "type":"Services"
        }
    ],
    "sg:phone":"+1 734 662 2255",
    "sg:postcode":"48104",
    "sg:province":"MI",
    "wof:name":"Arthur S Brickman",
    "wof:placetype":"venue"
},
  "geometry": {"coordinates":[-83.74200999999999,42.276208],"type":"Point"}
}