{
  "type": "Feature",
  "properties": {
    "iso:country":"US",
    "sg:address":"106 W 7th St",
    "sg:city":"Clare",
    "sg:classifiers":[
        {
            "category":"Social Services",
            "type":"Services"
        }
    ],
    "sg:phone":"+1 989 386 6015",
    "sg:postcode":"48617",
    "sg:province":"MI",
    "sg:tags":[
        "organization",
        "welfare"
    ],
    "sg:website":"www.unitedwayclare.org",
    "wof:name":"United Way",
    "wof:placetype":"venue"
},
  "geometry": {"coordinates":[-84.770307,43.821564],"type":"Point"}
}