{
  "type": "Feature",
  "properties": {
    "iso:country":"US",
    "sg:address":"14120 Northland Dr",
    "sg:city":"Big Rapids",
    "sg:classifiers":[
        {
            "category":"Autos & Motor Vehicles",
            "subcategory":"Automobile Sales",
            "type":"Retail Goods"
        }
    ],
    "sg:phone":"+1 231 796 7617",
    "sg:postcode":"49307",
    "sg:province":"MI",
    "sg:tags":[
        "car",
        "dealer"
    ],
    "sg:website":"www.allamericanflm.com",
    "wof:name":"All American Ford",
    "wof:placetype":"venue"
},
  "geometry": {"coordinates":[-85.4833,43.670312],"type":"Point"}
}