{
  "type": "Feature",
  "properties": {
    "iso:country":"US",
    "sg:address":"1117 E Mount Garfield Rd",
    "sg:city":"Muskegon",
    "sg:classifiers":[
        {
            "category":"Manufacturing",
            "subcategory":"Printing",
            "type":"Manufacturing & Wholesale Goods"
        }
    ],
    "sg:phone":"+1 231 798 7931",
    "sg:postcode":"49441",
    "sg:province":"MI",
    "sg:tags":[
        "printer"
    ],
    "sg:website":"www.glpsi.com",
    "wof:name":"Great Lakes Printing Solutions",
    "wof:placetype":"venue"
},
  "geometry": {"coordinates":[-86.21555600000001,43.147052],"type":"Point"}
}