{
  "type": "Feature",
  "properties": {
    "iso:country":"US",
    "sg:address":"1316 Woodland Ave NW",
    "sg:city":"Grand Rapids",
    "sg:classifiers":[
        {
            "category":"Shopping",
            "subcategory":"Photographic Equipment",
            "type":"Retail Goods"
        }
    ],
    "sg:phone":"+1 616 453 8413",
    "sg:postcode":"49504",
    "sg:province":"MI",
    "sg:tags":[
        "supply"
    ],
    "wof:name":"Mary Dagley",
    "wof:placetype":"venue"
},
  "geometry": {"coordinates":[-85.732438,42.988764],"type":"Point"}
}