{
  "type": "Feature",
  "properties": {
    "iso:country":"US",
    "sg:address":"132 N Wattles Rd",
    "sg:city":"Battle Creek",
    "sg:classifiers":[
        {
            "category":"Education",
            "subcategory":"School",
            "type":"Public Place"
        }
    ],
    "sg:phone":"+1 269 966 1657",
    "sg:postcode":"49014",
    "sg:province":"MI",
    "wof:name":"Harper Creek Comm Schools",
    "wof:placetype":"venue"
},
  "geometry": {"coordinates":[-85.111147,42.309222],"type":"Point"}
}