{
  "type": "Feature",
  "properties": {
    "iso:country":"US",
    "sg:address":"1204 Chicago Dr SW",
    "sg:city":"Wyoming",
    "sg:classifiers":[
        {
            "category":"Building & Trades",
            "subcategory":"Plumbing",
            "type":"Services"
        }
    ],
    "sg:phone":"+1 616 243 6345",
    "sg:postcode":"49509",
    "sg:province":"MI",
    "sg:tags":[
        "plumbing",
        "contractor"
    ],
    "wof:name":"John Penning & Son Plumbing",
    "wof:placetype":"venue"
},
  "geometry": {"coordinates":[-85.697307,42.935399],"type":"Point"}
}