{
  "type": "Feature",
  "properties": {
    "iso:country":"US",
    "sg:address":"51450 Schoenherr Rd",
    "sg:city":"Shelby Twp",
    "sg:classifiers":[
        {
            "category":"Autos & Motor Vehicles",
            "subcategory":"Automobile Sales",
            "type":"Retail Goods"
        }
    ],
    "sg:phone":"+1 586 566 4333",
    "sg:postcode":"48315",
    "sg:province":"MI",
    "sg:tags":[
        "classic"
    ],
    "wof:name":"Classic Corbette Investment",
    "wof:placetype":"venue"
},
  "geometry": {"coordinates":[-82.99472799999999,42.673169],"type":"Point"}
}