{
  "type": "Feature",
  "properties": {
    "iso:country":"US",
    "sg:address":"300 S Riverside Ave",
    "sg:city":"St Clair",
    "sg:classifiers":[
        {
            "category":"Banks & Credit Unions",
            "subcategory":"Bank",
            "type":"Services"
        }
    ],
    "sg:phone":"+1 810 326 5626",
    "sg:postcode":"48079",
    "sg:province":"MI",
    "sg:tags":[
        "loan",
        "real estate"
    ],
    "wof:name":"American Home Loans",
    "wof:placetype":"venue"
},
  "geometry": {"coordinates":[-82.486011,42.822929],"type":"Point"}
}