{
  "type": "Feature",
  "properties": {
    "iso:country":"US",
    "sg:address":"220 Lyon St NW",
    "sg:city":"Grand Rapids",
    "sg:classifiers":[
        {
            "category":"Professional",
            "subcategory":"Management & Consulting",
            "type":"Services"
        }
    ],
    "sg:phone":"+1 616 458 9200",
    "sg:postcode":"49503",
    "sg:province":"MI",
    "sg:tags":[
        "training",
        "sales"
    ],
    "wof:name":"Tempest Inc",
    "wof:placetype":"venue"
},
  "geometry": {"coordinates":[-85.673327,42.96715],"type":"Point"}
}