{
  "type": "Feature",
  "properties": {
    "iso:country":"US",
    "sg:address":"3271 E Rattalee Lake Rd",
    "sg:city":"Holly",
    "sg:classifiers":[
        {
            "category":"Building & Trades",
            "subcategory":"Construction",
            "type":"Services"
        }
    ],
    "sg:phone":"+1 248 634 8720",
    "sg:postcode":"48442",
    "sg:province":"MI",
    "sg:tags":[
        "roofing",
        "contractor"
    ],
    "wof:name":"Peck Construction",
    "wof:placetype":"venue"
},
  "geometry": {"coordinates":[-83.569374,42.77222],"type":"Point"}
}