{
  "type": "Feature",
  "properties": {
    "iso:country":"US",
    "sg:address":"1965 Muer Dr",
    "sg:city":"Troy",
    "sg:classifiers":[
        {
            "category":"Retail",
            "subcategory":"Repair Shop",
            "type":"Services"
        }
    ],
    "sg:phone":"+1 248 643 0782",
    "sg:postcode":"48084",
    "sg:province":"MI",
    "sg:tags":[
        "door"
    ],
    "wof:name":"Ronald A Gross",
    "wof:placetype":"venue"
},
  "geometry": {"coordinates":[-83.175006,42.567888],"type":"Point"}
}