{
  "type": "Feature",
  "properties": {
    "iso:country":"US",
    "sg:address":"1537 Honey Dew",
    "sg:city":"Gaylord",
    "sg:classifiers":[
        {
            "category":"Banks & Credit Unions",
            "subcategory":"Financial Services",
            "type":"Services"
        }
    ],
    "sg:phone":"+1 989 731 3357",
    "sg:postcode":"49735",
    "sg:province":"MI",
    "sg:tags":[
        "trust",
        "management"
    ],
    "wof:name":"White Tail Investment Group",
    "wof:placetype":"venue"
},
  "geometry": {"coordinates":[-84.706317,45.040359],"type":"Point"}
}