{
  "type": "Feature",
  "properties": {
    "iso:country":"US",
    "sg:address":"8023 Summerfield Rd",
    "sg:city":"Lambertville",
    "sg:classifiers":[
        {
            "category":"Shopping",
            "subcategory":"Clothing, Apparel, & Fashions",
            "type":"Retail Goods"
        }
    ],
    "sg:phone":"+1 734 854 4641",
    "sg:postcode":"48144",
    "sg:province":"MI",
    "sg:tags":[
        "infant",
        "wear"
    ],
    "wof:name":"Kidz Kloset",
    "wof:placetype":"venue"
},
  "geometry": {"coordinates":[-83.626547,41.760915],"type":"Point"}
}