{
  "type": "Feature",
  "properties": {
    "iso:country":"US",
    "sg:address":"1030 Devere Dr",
    "sg:city":"Alpena",
    "sg:classifiers":[
        {
            "category":"Building & Trades",
            "subcategory":"Construction",
            "type":"Services"
        }
    ],
    "sg:phone":"+1 989 356 4411",
    "sg:postcode":"49707",
    "sg:province":"MI",
    "sg:tags":[
        "general",
        "contractor"
    ],
    "sg:website":"www.devereconstruction.com",
    "wof:name":"De Vere Construction Co",
    "wof:placetype":"venue"
},
  "geometry": {"coordinates":[-83.490606,45.063326],"type":"Point"}
}