{
  "type": "Feature",
  "properties": {
    "iso:country":"US",
    "sg:address":"757 Dover St",
    "sg:city":"Dearborn Heights",
    "sg:classifiers":[
        {
            "category":"Personal",
            "subcategory":"Beauty Salon",
            "type":"Services"
        }
    ],
    "sg:phone":"+1 313 277 2088",
    "sg:postcode":"48127",
    "sg:province":"MI",
    "sg:tags":[
        "shop"
    ],
    "wof:name":"Allure Tanning & Spa Inc",
    "wof:placetype":"venue"
},
  "geometry": {"coordinates":[-83.297043,42.316039],"type":"Point"}
}