{
  "type": "Feature",
  "properties": {
    "iso:country":"US",
    "sg:address":"17689 174th Ave",
    "sg:city":"Spring Lake",
    "sg:classifiers":[
        {
            "category":"Personal",
            "subcategory":"Beauty Salon",
            "type":"Services"
        }
    ],
    "sg:phone":"+1 616 846 9520",
    "sg:postcode":"49456",
    "sg:province":"MI",
    "sg:tags":[
        "shop"
    ],
    "wof:name":"Joseph's Hair Studio",
    "wof:placetype":"venue"
},
  "geometry": {"coordinates":[-86.220771,43.090484],"type":"Point"}
}