{
  "type": "Feature",
  "properties": {
    "iso:country":"US",
    "sg:address":"24826 Joseph Dr",
    "sg:city":"Novi",
    "sg:classifiers":[
        {
            "category":"Retail",
            "subcategory":"Laundry & Dry Cleaning",
            "type":"Services"
        }
    ],
    "sg:phone":"+1 248 477 2397",
    "sg:postcode":"48375",
    "sg:province":"MI",
    "sg:tags":[
        "drycleaning",
        "plant"
    ],
    "wof:name":"Your Valet",
    "wof:placetype":"venue"
},
  "geometry": {"coordinates":[-83.44704,42.473046],"type":"Point"}
}