{
  "type": "Feature",
  "properties": {
    "iso:country":"US",
    "sg:address":"210 Jordan",
    "sg:city":"East Jordan",
    "sg:classifiers":[
        {
            "category":"Organizations",
            "subcategory":"Religious Organization",
            "type":"Services"
        }
    ],
    "sg:phone":"+1 231 536 2870",
    "sg:postcode":"49727",
    "sg:province":"MI",
    "sg:tags":[
        "church"
    ],
    "wof:name":"Harvest Barn Word Of Live Chr",
    "wof:placetype":"venue"
},
  "geometry": {"coordinates":[-85.134771,45.152063],"type":"Point"}
}