{
  "type": "Feature",
  "properties": {
    "iso:country":"US",
    "sg:address":"653 N Jefferson St",
    "sg:city":"Ionia",
    "sg:classifiers":[
        {
            "category":"Social Services",
            "subcategory":"Adult Care",
            "type":"Services"
        }
    ],
    "sg:phone":"+1 616 527 4097",
    "sg:postcode":"48846",
    "sg:province":"MI",
    "sg:tags":[
        "foster",
        "provider"
    ],
    "wof:name":"Arthur & Cynthia Wiles",
    "wof:placetype":"venue"
},
  "geometry": {"coordinates":[-85.054616,42.989013],"type":"Point"}
}