{
  "type": "Feature",
  "properties": {
    "iso:country":"US",
    "sg:address":"2974 Palmer Pl",
    "sg:city":"Grayling",
    "sg:classifiers":[
        {
            "category":"Building & Trades",
            "subcategory":"Construction",
            "type":"Services"
        }
    ],
    "sg:phone":"+1 989 348 8527",
    "sg:postcode":"49738",
    "sg:province":"MI",
    "sg:tags":[
        "house"
    ],
    "wof:name":"J T Cochrane Construction",
    "wof:placetype":"venue"
},
  "geometry": {"coordinates":[-84.664858,44.708745],"type":"Point"}
}