{
  "type": "Feature",
  "properties": {
    "iso:country":"US",
    "sg:address":"408 S Stephenson Ave",
    "sg:city":"Iron Mountain",
    "sg:classifiers":[
        {
            "category":"Manufacturing",
            "subcategory":"Printing",
            "type":"Manufacturing & Wholesale Goods"
        }
    ],
    "sg:phone":"+1 906 774 3370",
    "sg:postcode":"49801",
    "sg:province":"MI",
    "sg:tags":[
        "screen"
    ],
    "wof:name":"Shirt Tails",
    "wof:placetype":"venue"
},
  "geometry": {"coordinates":[-88.065788,45.819308],"type":"Point"}
}