{
  "type": "Feature",
  "properties": {
    "iso:country":"US",
    "sg:address":"403 W Main St",
    "sg:city":"Middleville",
    "sg:classifiers":[
        {
            "category":"Insurance",
            "subcategory":"Insurance Agent",
            "type":"Services"
        }
    ],
    "sg:phone":"+1 269 795 7925",
    "sg:postcode":"49333",
    "sg:province":"MI",
    "wof:name":"Lon Lefanty Insurance",
    "wof:placetype":"venue"
},
  "geometry": {"coordinates":[-85.47145500000001,42.710936],"type":"Point"}
}