{
  "type": "Feature",
  "properties": {
    "iso:country":"US",
    "sg:address":"2711 N Lincoln Rd",
    "sg:city":"Escanaba",
    "sg:classifiers":[
        {
            "category":"Personal",
            "subcategory":"Beauty Salon",
            "type":"Services"
        }
    ],
    "sg:phone":"+1 906 786 9919",
    "sg:postcode":"49829",
    "sg:province":"MI",
    "wof:name":"Studio 2711",
    "wof:placetype":"venue"
},
  "geometry": {"coordinates":[-87.083393,45.782449],"type":"Point"}
}