{
  "type": "Feature",
  "properties": {
    "iso:country":"US",
    "sg:address":"4860 Miller Rd",
    "sg:city":"Ann Arbor",
    "sg:classifiers":[
        {
            "category":"Professional",
            "subcategory":"Business Services",
            "type":"Services"
        }
    ],
    "sg:phone":"+1 734 994 5608",
    "sg:postcode":"48103",
    "sg:province":"MI",
    "wof:name":"Cyber Growth Solutions Inc",
    "wof:placetype":"venue"
},
  "geometry": {"coordinates":[-83.82294400000001,42.309757],"type":"Point"}
}