{
  "type": "Feature",
  "properties": {
    "iso:country":"US",
    "sg:address":"4955 Bay Rd",
    "sg:city":"Saginaw",
    "sg:classifiers":[
        {
            "category":"Banks & Credit Unions",
            "subcategory":"Bank",
            "type":"Services"
        }
    ],
    "sg:phone":"+1 989 790 1202",
    "sg:postcode":"48604",
    "sg:province":"MI",
    "sg:tags":[
        "state",
        "commercial"
    ],
    "wof:name":"Chemical Bank & Trust Co",
    "wof:placetype":"venue"
},
  "geometry": {"coordinates":[-83.975568,43.478054],"type":"Point"}
}