{
  "type": "Feature",
  "properties": {
    "iso:country":"US",
    "sg:address":"3680 Airline Rd",
    "sg:city":"Muskegon",
    "sg:classifiers":[
        {
            "category":"Bars & Pubs",
            "type":"Food & Drink"
        }
    ],
    "sg:phone":"+1 231 739 7210",
    "sg:postcode":"49444",
    "sg:province":"MI",
    "wof:name":"N C's Inc",
    "wof:placetype":"venue"
},
  "geometry": {"coordinates":[-86.22756200000001,43.187344],"type":"Point"}
}