{
  "type": "Feature",
  "properties": {
    "iso:country":"US",
    "sg:address":"3545 S Lakeshore Dr",
    "sg:city":"St Joseph",
    "sg:classifiers":[
        {
            "category":"Manufacturing",
            "subcategory":"Building Materials",
            "type":"Manufacturing & Wholesale Goods"
        }
    ],
    "sg:phone":"+1 269 556 1873",
    "sg:postcode":"49085",
    "sg:province":"MI",
    "sg:website":"www.monarchdeck.com",
    "wof:name":"Green Tree Composites",
    "wof:placetype":"venue"
},
  "geometry": {"coordinates":[-86.51414699999999,42.055109],"type":"Point"}
}