{
  "type": "Feature",
  "properties": {
    "iso:country":"US",
    "sg:address":"10109 Mckinney St",
    "sg:city":"Detroit",
    "sg:classifiers":[
        {
            "category":"Building & Trades",
            "subcategory":"Cleaning & Sanitation",
            "type":"Services"
        }
    ],
    "sg:phone":"+1 313 316 2113",
    "sg:postcode":"48224",
    "sg:province":"MI",
    "sg:tags":[
        "house"
    ],
    "wof:name":"Johnny On The Spot Carpet Cleaning",
    "wof:placetype":"venue"
},
  "geometry": {"coordinates":[-82.94642899999999,42.41601],"type":"Point"}
}