{
  "type": "Feature",
  "properties": {
    "iso:country":"US",
    "sg:address":"5723 E 8 Mile Rd",
    "sg:city":"Warren",
    "sg:classifiers":[
        {
            "category":"Utilities",
            "subcategory":"Electric",
            "type":"Services"
        }
    ],
    "sg:phone":"+1 586 754 6576",
    "sg:postcode":"48234",
    "sg:province":"MI",
    "sg:tags":[
        "company"
    ],
    "wof:name":"Caldwell's Electric",
    "wof:placetype":"venue"
},
  "geometry": {"coordinates":[-83.04566800000001,42.44764],"type":"Point"}
}