{
  "type": "Feature",
  "properties": {
    "iso:country":"US",
    "sg:address":"1015 Hill St",
    "sg:city":"Petoskey",
    "sg:classifiers":[
        {
            "category":"Building & Trades",
            "subcategory":"Construction",
            "type":"Services"
        }
    ],
    "sg:phone":"+1 231 347 6090",
    "sg:postcode":"49770",
    "sg:province":"MI",
    "wof:name":"Panelized Pre-Cut Custom Homes",
    "wof:placetype":"venue"
},
  "geometry": {"coordinates":[-84.93736199999999,45.372054],"type":"Point"}
}