{
  "type": "Feature",
  "properties": {
    "iso:country":"US",
    "sg:address":"2120 Oak Industrial Dr NE",
    "sg:city":"Grand Rapids",
    "sg:classifiers":[
        {
            "category":"Home & Garden",
            "subcategory":"Building Materials",
            "type":"Retail Goods"
        }
    ],
    "sg:phone":"+1 616 235 3600",
    "sg:postcode":"49505",
    "sg:province":"MI",
    "sg:tags":[
        "windows"
    ],
    "wof:name":"Horne Building Specialties",
    "wof:placetype":"venue"
},
  "geometry": {"coordinates":[-85.614971,42.975091],"type":"Point"}
}