{
  "type": "Feature",
  "properties": {
    "iso:country":"US",
    "sg:address":"316 S Linden St",
    "sg:city":"Marshall",
    "sg:classifiers":[
        {
            "category":"Building & Trades",
            "subcategory":"Plumbing",
            "type":"Services"
        }
    ],
    "sg:phone":"+1 269 789 2350",
    "sg:postcode":"49068",
    "sg:province":"MI",
    "sg:tags":[
        "tank",
        "septic"
    ],
    "wof:name":"Jeff & Son Excavating",
    "wof:placetype":"venue"
},
  "geometry": {"coordinates":[-84.969217,42.26908],"type":"Point"}
}