{
  "type": "Feature",
  "properties": {
    "iso:country":"US",
    "sg:address":"617 Lyon St NE",
    "sg:city":"Grand Rapids",
    "sg:classifiers":[
        {
            "category":"Professional",
            "type":"Services"
        }
    ],
    "sg:phone":"+1 616 458 3734",
    "sg:postcode":"49503",
    "sg:province":"MI",
    "sg:tags":[
        "arts",
        "artist"
    ],
    "wof:name":"Richard Cooper Art Studio",
    "wof:placetype":"venue"
},
  "geometry": {"coordinates":[-85.65228999999999,42.967396],"type":"Point"}
}