{
  "type": "Feature",
  "properties": {
    "iso:country":"US",
    "sg:address":"4859 Haggerty Rd",
    "sg:city":"West Bloomfield",
    "sg:classifiers":[
        {
            "category":"Restaurant",
            "type":"Food & Drink"
        }
    ],
    "sg:menulink":"http://www.allmenus.com/mi/west-bloomfield/84454-papa-johns-pizza/menu/",
    "sg:phone":"+1 248 960 7373",
    "sg:postcode":"48323",
    "sg:province":"MI",
    "sg:tags":[
        "american",
        "pizza"
    ],
    "wof:name":"Papa John's Pizza",
    "wof:placetype":"venue"
},
  "geometry": {"coordinates":[-83.439482,42.564155],"type":"Point"}
}