{
  "type": "Feature",
  "properties": {
    "iso:country":"US",
    "sg:address":"25595 Statler St",
    "sg:city":"Taylor",
    "sg:classifiers":[
        {
            "category":"Banks & Credit Unions",
            "subcategory":"Financial Services",
            "type":"Services"
        }
    ],
    "sg:phone":"+1 313 295 2021",
    "sg:postcode":"48180",
    "sg:province":"MI",
    "sg:tags":[
        "company",
        "bank",
        "holding"
    ],
    "wof:name":"Paulianna Inc",
    "wof:placetype":"venue"
},
  "geometry": {"coordinates":[-83.286387,42.234163],"type":"Point"}
}