{
  "type": "Feature",
  "properties": {
    "iso:country":"US",
    "sg:address":"23922 Cherry Hill St",
    "sg:city":"Dearborn",
    "sg:classifiers":[
        {
            "category":"Restaurant",
            "type":"Food & Drink"
        }
    ],
    "sg:phone":"+1 313 274 6116",
    "sg:postcode":"48124",
    "sg:province":"MI",
    "sg:tags":[
        "pizza"
    ],
    "wof:name":"Karl's Pizza & Rib Shack",
    "wof:placetype":"venue"
},
  "geometry": {"coordinates":[-83.2715,42.312698],"type":"Point"}
}