{
  "type": "Feature",
  "properties": {
    "iso:country":"US",
    "sg:address":"3125 W Michigan Ave",
    "sg:city":"Kalamazoo",
    "sg:classifiers":[
        {
            "category":"Organizations",
            "subcategory":"Community Association",
            "type":"Services"
        }
    ],
    "sg:phone":"+1 269 383 0741",
    "sg:postcode":"49006",
    "sg:province":"MI",
    "sg:tags":[
        "sorority",
        "fraternity"
    ],
    "wof:name":"Sigma Kappa",
    "wof:placetype":"venue"
},
  "geometry": {"coordinates":[-85.626903,42.280137],"type":"Point"}
}