{
  "type": "Feature",
  "properties": {
    "iso:country":"US",
    "sg:address":"11700 Killen Rd",
    "sg:city":"Howell",
    "sg:classifiers":[
        {
            "category":"Building & Trades",
            "subcategory":"Construction",
            "type":"Services"
        }
    ],
    "sg:phone":"+1 517 548 7583",
    "sg:postcode":"48855",
    "sg:province":"MI",
    "sg:tags":[
        "excavating",
        "contractor"
    ],
    "wof:name":"R L Curvin & Sons Excavating",
    "wof:placetype":"venue"
},
  "geometry": {"coordinates":[-83.922516,42.78082],"type":"Point"}
}