{
  "type": "Feature",
  "properties": {
    "iso:country":"US",
    "sg:address":"3550 Shattuck Rd",
    "sg:city":"Saginaw",
    "sg:classifiers":[
        {
            "category":"Personal",
            "subcategory":"Beauty Salon",
            "type":"Services"
        }
    ],
    "sg:phone":"+1 989 793 2486",
    "sg:postcode":"48603",
    "sg:province":"MI",
    "wof:name":"Looks Hair Designs-Men & Women",
    "wof:placetype":"venue"
},
  "geometry": {"coordinates":[-83.986653,43.451075],"type":"Point"}
}