{
  "type": "Feature",
  "properties": {
    "iso:country":"US",
    "sg:address":"21710 E 9 Mile Rd",
    "sg:city":"St Clair Shores",
    "sg:classifiers":[
        {
            "category":"Professional",
            "subcategory":"Lawyer & Legal Services",
            "type":"Services"
        }
    ],
    "sg:phone":"+1 586 774 7210",
    "sg:postcode":"48080",
    "sg:province":"MI",
    "sg:tags":[
        "attorney"
    ],
    "wof:name":"Thomas Wininger",
    "wof:placetype":"venue"
},
  "geometry": {"coordinates":[-82.89966699999999,42.466326],"type":"Point"}
}