{
  "type": "Feature",
  "properties": {
    "iso:country":"US",
    "sg:address":"18424 W McNichols Rd",
    "sg:city":"Detroit",
    "sg:classifiers":[
        {
            "category":"Health Services",
            "subcategory":"Dentist",
            "type":"Services"
        }
    ],
    "sg:phone":"+1 313 537 3800",
    "sg:postcode":"48219",
    "sg:province":"MI",
    "wof:name":"McAdoo Dental Bldg",
    "wof:placetype":"venue"
},
  "geometry": {"coordinates":[-83.2239,42.4156],"type":"Point"}
}