{
  "type": "Feature",
  "properties": {
    "iso:country":"US",
    "sg:address":"8784 E Traverse Hwy",
    "sg:city":"Traverse City",
    "sg:classifiers":[
        {
            "category":"Health Services",
            "subcategory":"Doctor",
            "type":"Services"
        }
    ],
    "sg:phone":"+1 231 947 2265",
    "sg:postcode":"49684",
    "sg:province":"MI",
    "sg:tags":[
        "medical"
    ],
    "wof:name":"Karin E Olson MD",
    "wof:placetype":"venue"
},
  "geometry": {"coordinates":[-85.70135500000001,44.775261],"type":"Point"}
}