{
  "type": "Feature",
  "properties": {
    "iso:country":"US",
    "sg:address":"9118 Joseph Campau St",
    "sg:city":"Detroit",
    "sg:classifiers":[
        {
            "category":"Food & Beverages",
            "subcategory":"Groceries & Convenience Stores",
            "type":"Retail Goods"
        }
    ],
    "sg:phone":"+1 313 872 5710",
    "sg:postcode":"48212",
    "sg:province":"MI",
    "sg:tags":[
        "ticket",
        "lottery",
        "liquor"
    ],
    "wof:name":"Lance Food Shop Inc",
    "wof:placetype":"venue"
},
  "geometry": {"coordinates":[-83.05512400000001,42.392758],"type":"Point"}
}