{
  "type": "Feature",
  "properties": {
    "iso:country":"US",
    "sg:address":"23013 Gratiot Ave",
    "sg:city":"Eastpointe",
    "sg:classifiers":[
        {
            "category":"Shopping",
            "subcategory":"Music",
            "type":"Retail Goods"
        }
    ],
    "sg:phone":"+1 586 774 8480",
    "sg:postcode":"48021",
    "sg:province":"MI",
    "sg:tags":[
        "compact",
        "record",
        "disc",
        "tape"
    ],
    "wof:name":"Melodies & Memories",
    "wof:placetype":"venue"
},
  "geometry": {"coordinates":[-82.95639,42.467586],"type":"Point"}
}