{
  "type": "Feature",
  "properties": {
    "iso:country":"US",
    "sg:address":"20034 Stahelin Ave",
    "sg:city":"Detroit",
    "sg:classifiers":[
        {
            "category":"Banks & Credit Unions",
            "subcategory":"Financial Services",
            "type":"Services"
        }
    ],
    "sg:phone":"+1 313 535 4610",
    "sg:postcode":"48219",
    "sg:province":"MI",
    "sg:tags":[
        "investor",
        "real estate"
    ],
    "wof:name":"Favored Estates Inc",
    "wof:placetype":"venue"
},
  "geometry": {"coordinates":[-83.228207,42.440252],"type":"Point"}
}