{
  "type": "Feature",
  "properties": {
    "iso:country":"US",
    "sg:address":"8501 Midland Rd",
    "sg:city":"Freeland",
    "sg:classifiers":[
        {
            "category":"Building & Trades",
            "subcategory":"Construction",
            "type":"Services"
        }
    ],
    "sg:phone":"+1 989 695 9402",
    "sg:postcode":"48623",
    "sg:province":"MI",
    "sg:tags":[
        "tile",
        "dealer"
    ],
    "wof:name":"J E Ceramic TILE Co LLC",
    "wof:placetype":"venue"
},
  "geometry": {"coordinates":[-84.132846,43.533168],"type":"Point"}
}