{
  "type": "Feature",
  "properties": {
    "iso:country":"US",
    "sg:address":"2305 Coolidge Hwy",
    "sg:city":"Berkley",
    "sg:classifiers":[
        {
            "category":"Building & Trades",
            "subcategory":"Cleaning & Sanitation",
            "type":"Services"
        }
    ],
    "sg:phone":"+1 248 545 5121",
    "sg:postcode":"48072",
    "sg:province":"MI",
    "sg:tags":[
        "home"
    ],
    "wof:name":"Merry Maids Inc",
    "wof:placetype":"venue"
},
  "geometry": {"coordinates":[-83.183998,42.500702],"type":"Point"}
}