{
  "type": "Feature",
  "properties": {
    "iso:country":"US",
    "sg:address":"649 Kinney Ave NW",
    "sg:city":"Grand Rapids",
    "sg:classifiers":[
        {
            "category":"Professional",
            "subcategory":"Art Services",
            "type":"Services"
        }
    ],
    "sg:phone":"+1 616 791 9784",
    "sg:postcode":"49534",
    "sg:province":"MI",
    "sg:tags":[
        "commercial",
        "design"
    ],
    "wof:name":"Nissi Network",
    "wof:placetype":"venue"
},
  "geometry": {"coordinates":[-85.766638,42.976515],"type":"Point"}
}