{
  "type": "Feature",
  "properties": {
    "iso:country":"US",
    "sg:address":"3661 Poinsettia Ave SE",
    "sg:city":"Grand Rapids",
    "sg:classifiers":[
        {
            "category":"Organizations",
            "subcategory":"Religious Organization",
            "type":"Services"
        }
    ],
    "sg:phone":"+1 616 243 2829",
    "sg:postcode":"49508",
    "sg:province":"MI",
    "wof:name":"Millbrook Christian Ref Church",
    "wof:placetype":"venue"
},
  "geometry": {"coordinates":[-85.635344,42.897754],"type":"Point"}
}