{
  "type": "Feature",
  "properties": {
    "iso:country":"US",
    "sg:address":"1046 E Sternberg Rd",
    "sg:city":"Muskegon",
    "sg:classifiers":[
        {
            "category":"Shopping",
            "subcategory":"Gifts & Souvenirs",
            "type":"Retail Goods"
        }
    ],
    "sg:phone":"+1 231 798 3882",
    "sg:postcode":"49444",
    "sg:province":"MI",
    "wof:name":"Purple Moon",
    "wof:placetype":"venue"
},
  "geometry": {"coordinates":[-86.216326,43.154387],"type":"Point"}
}