{
  "type": "Feature",
  "properties": {
    "iso:country":"US",
    "sg:address":"22605 Van Dyke Ave",
    "sg:city":"Warren",
    "sg:classifiers":[
        {
            "category":"Health Services",
            "subcategory":"Doctor",
            "type":"Services"
        }
    ],
    "sg:phone":"+1 586 759 1100",
    "sg:postcode":"48089",
    "sg:province":"MI",
    "sg:tags":[
        "practice",
        "family"
    ],
    "wof:name":"Primecare Medical Centers",
    "wof:placetype":"venue"
},
  "geometry": {"coordinates":[-83.02419999999999,42.459499],"type":"Point"}
}