{
  "type": "Feature",
  "properties": {
    "iso:country":"US",
    "sg:address":"7153 N 12th St",
    "sg:city":"Kalamazoo",
    "sg:classifiers":[
        {
            "category":"Professional",
            "type":"Services"
        }
    ],
    "sg:phone":"+1 269 349 3768",
    "sg:postcode":"49009",
    "sg:province":"MI",
    "wof:name":"Safe Energy",
    "wof:placetype":"venue"
},
  "geometry": {"coordinates":[-85.64892500000001,42.363441],"type":"Point"}
}