{
  "type": "Feature",
  "properties": {
    "iso:country":"US",
    "sg:address":"3828 Patterson Rd",
    "sg:city":"Bay City",
    "sg:classifiers":[
        {
            "category":"Professional",
            "subcategory":"Employment Agencies",
            "type":"Services"
        }
    ],
    "sg:phone":"+1 989 753 8201",
    "sg:postcode":"48706",
    "sg:province":"MI",
    "sg:tags":[
        "trucking"
    ],
    "wof:name":"J C J Enterprises Ltd",
    "wof:placetype":"venue"
},
  "geometry": {"coordinates":[-83.873768,43.631814],"type":"Point"}
}