{
  "type": "Feature",
  "properties": {
    "iso:country":"US",
    "sg:address":"3525 Plainfield Ave NE",
    "sg:city":"Grand Rapids",
    "sg:classifiers":[
        {
            "category":"Shopping",
            "type":"Retail Goods"
        }
    ],
    "sg:phone":"+1 616 365 7696",
    "sg:postcode":"49525",
    "sg:province":"MI",
    "sg:tags":[
        "cosmetic",
        "perfume"
    ],
    "wof:name":"Hair Mart Beauty Supply",
    "wof:placetype":"venue"
},
  "geometry": {"coordinates":[-85.631773,43.027862],"type":"Point"}
}