{
  "type": "Feature",
  "properties": {
    "iso:country":"US",
    "sg:address":"2020 Munford Rd",
    "sg:city":"Ubly",
    "sg:classifiers":[
        {
            "category":"Shopping",
            "subcategory":"Gifts & Souvenirs",
            "type":"Retail Goods"
        }
    ],
    "sg:phone":"+1 989 658 2336",
    "sg:postcode":"48475",
    "sg:province":"MI",
    "wof:name":"Bgs Gifts & Distributing",
    "wof:placetype":"venue"
},
  "geometry": {"coordinates":[-82.93599500000001,43.69546],"type":"Point"}
}