{
  "type": "Feature",
  "properties": {
    "iso:country":"US",
    "sg:address":"13 Mill Rd",
    "sg:city":"Marshall",
    "sg:phone":"+1 269 781 0637",
    "sg:postcode":"49014",
    "sg:province":"MI",
    "sg:tags":[
        "farm",
        "corn",
        "wheat",
        "soybean"
    ],
    "wof:name":"Gregory Karns",
    "wof:placetype":"venue"
},
  "geometry": {"coordinates":[-85.14959399999999,42.33256],"type":"Point"}
}