{
  "type": "Feature",
  "properties": {
    "iso:country":"US",
    "sg:address":"317 W Houghton Ave",
    "sg:city":"West Branch",
    "sg:classifiers":[
        {
            "category":"Professional",
            "subcategory":"Accounting & Tax Preparation",
            "type":"Services"
        }
    ],
    "sg:phone":"+1 989 345 0850",
    "sg:postcode":"48661",
    "sg:province":"MI",
    "sg:tags":[
        "accountant"
    ],
    "wof:name":"Stephenson Gracik & Co",
    "wof:placetype":"venue"
},
  "geometry": {"coordinates":[-84.23969,44.276328],"type":"Point"}
}