{
  "type": "Feature",
  "properties": {
    "iso:country":"US",
    "sg:address":"705 Garland St",
    "sg:city":"Flint",
    "sg:classifiers":[
        {
            "category":"Organizations",
            "subcategory":"Religious Organization",
            "type":"Services"
        },
        {
            "category":"Social Services",
            "type":"Services"
        }
    ],
    "sg:phone":"+1 810 238 6827",
    "sg:postcode":"48503",
    "sg:province":"MI",
    "sg:tags":[
        "welfare"
    ],
    "wof:name":"Carriage Town Family Center",
    "wof:placetype":"venue"
},
  "geometry": {"coordinates":[-83.697743,43.022323],"type":"Point"}
}