{
  "type": "Feature",
  "properties": {
    "iso:country":"US",
    "sg:address":"4324 W Saginaw Hwy",
    "sg:city":"Lansing",
    "sg:classifiers":[
        {
            "category":"Personal",
            "subcategory":"Beauty Salon",
            "type":"Services"
        }
    ],
    "sg:phone":"+1 517 886 6666",
    "sg:postcode":"48917",
    "sg:province":"MI",
    "wof:name":"African Braiding Gallery",
    "wof:placetype":"venue"
},
  "geometry": {"coordinates":[-84.610057,42.74119],"type":"Point"}
}