{
  "type": "Feature",
  "properties": {
    "iso:country":"US",
    "sg:address":"6717 Westpoint",
    "sg:city":"Taylor",
    "sg:classifiers":[
        {
            "category":"Home & Garden",
            "subcategory":"Furniture",
            "type":"Retail Goods"
        }
    ],
    "sg:phone":"+1 313 291 0223",
    "sg:postcode":"48180",
    "sg:province":"MI",
    "wof:name":"Sharons Furniture Cleaning",
    "wof:placetype":"venue"
},
  "geometry": {"coordinates":[-83.26895,42.259328],"type":"Point"}
}