{
  "type": "Feature",
  "properties": {
    "iso:country":"US",
    "sg:address":"6705 Ryan Hwy",
    "sg:city":"Tipton",
    "sg:classifiers":[
        {
            "category":"Professional",
            "subcategory":"Computer Services",
            "type":"Services"
        }
    ],
    "sg:phone":"+1 517 431 2880",
    "sg:postcode":"49287",
    "sg:province":"MI",
    "sg:tags":[
        "home",
        "consulting",
        "page",
        "dev",
        "internet"
    ],
    "wof:name":"Hoffman Historical Press",
    "wof:placetype":"venue"
},
  "geometry": {"coordinates":[-84.099311,41.97521],"type":"Point"}
}