{
  "type": "Feature",
  "properties": {
    "iso:country":"US",
    "sg:address":"253 N Milford Rd",
    "sg:city":"Highland",
    "sg:classifiers":[
        {
            "category":"Building & Trades",
            "subcategory":"Construction",
            "type":"Services"
        }
    ],
    "sg:phone":"+1 248 887 0123",
    "sg:postcode":"48357",
    "sg:province":"MI",
    "sg:tags":[
        "siding",
        "contractor"
    ],
    "wof:name":"TEK Siding Inc",
    "wof:placetype":"venue"
},
  "geometry": {"coordinates":[-83.617774,42.639827],"type":"Point"}
}