{
  "type": "Feature",
  "properties": {
    "iso:country":"US",
    "sg:address":"506 4th St",
    "sg:city":"Houghton",
    "sg:classifiers":[
        {
            "category":"Professional",
            "subcategory":"Computer Services",
            "type":"Services"
        }
    ],
    "sg:phone":"+1 906 487 9349",
    "sg:postcode":"49931",
    "sg:province":"MI",
    "sg:tags":[
        "prepackaged",
        "software"
    ],
    "wof:name":"Windak Co",
    "wof:placetype":"venue"
},
  "geometry": {"coordinates":[-88.57853900000001,47.118283],"type":"Point"}
}