{
  "type": "Feature",
  "properties": {
    "iso:country":"US",
    "sg:address":"4900 Montrose Ave",
    "sg:city":"Okemos",
    "sg:classifiers":[
        {
            "category":"Professional",
            "subcategory":"Accounting & Tax Preparation",
            "type":"Services"
        }
    ],
    "sg:phone":"+1 517 347 7750",
    "sg:postcode":"48864",
    "sg:province":"MI",
    "sg:tags":[
        "payroll"
    ],
    "wof:name":"Cbs Payroll Solutions LLC",
    "wof:placetype":"venue"
},
  "geometry": {"coordinates":[-84.435401,42.722194],"type":"Point"}
}