{
  "type": "Feature",
  "properties": {
    "iso:country":"US",
    "sg:address":"14455 Neff Rd",
    "sg:city":"Clio",
    "sg:classifiers":[
        {
            "category":"Building & Trades",
            "subcategory":"Equipment Rental",
            "type":"Services"
        }
    ],
    "sg:phone":"+1 810 686 3883",
    "sg:postcode":"48420",
    "sg:province":"MI",
    "wof:name":"Dale Roth Rental Hou",
    "wof:placetype":"venue"
},
  "geometry": {"coordinates":[-83.715104,43.214705],"type":"Point"}
}