{
  "type": "Feature",
  "properties": {
    "iso:country":"US",
    "sg:address":"510 Iroquois Dr",
    "sg:city":"Fremont",
    "sg:classifiers":[
        {
            "category":"Organizations",
            "subcategory":"Religious Organization",
            "type":"Services"
        }
    ],
    "sg:phone":"+1 231 924 0160",
    "sg:postcode":"49412",
    "sg:province":"MI",
    "sg:tags":[
        "church"
    ],
    "wof:name":"All Saints Catholic Church",
    "wof:placetype":"venue"
},
  "geometry": {"coordinates":[-85.929056,43.46332],"type":"Point"}
}