{
  "type": "Feature",
  "properties": {
    "iso:country":"US",
    "sg:address":"7330 Bush Dr NE",
    "sg:city":"Rockford",
    "sg:classifiers":[
        {
            "category":"Wholesale",
            "subcategory":"Stationery",
            "type":"Manufacturing & Wholesale Goods"
        },
        {
            "category":"Manufacturing",
            "subcategory":"Rubber & Plastics",
            "type":"Manufacturing & Wholesale Goods"
        }
    ],
    "sg:phone":"+1 616 874 1215",
    "sg:postcode":"49341",
    "sg:province":"MI",
    "sg:tags":[
        "packaging",
        "product",
        "material",
        "mfg"
    ],
    "wof:name":"E Bubble Wrap",
    "wof:placetype":"venue"
},
  "geometry": {"coordinates":[-85.477001,43.108287],"type":"Point"}
}