{
  "type": "Feature",
  "properties": {
    "iso:country":"US",
    "sg:address":"6560 Dixie Hwy",
    "sg:city":"Bridgeport",
    "sg:classifiers":[
        {
            "category":"Deli",
            "type":"Food & Drink"
        }
    ],
    "sg:menulink":"http://www.allmenus.com/mi/bridgeport/127383-blimpie-subs--sandwiches/menu/",
    "sg:phone":"+1 989 777 8730",
    "sg:postcode":"48722",
    "sg:province":"MI",
    "sg:tags":[
        "wrap",
        "american",
        "sandwich"
    ],
    "wof:name":"Blimpie Subs & Sandwiches",
    "wof:placetype":"venue"
},
  "geometry": {"coordinates":[-83.86045799999999,43.348676],"type":"Point"}
}