{
  "type": "Feature",
  "properties": {
    "iso:country":"US",
    "sg:address":"2 Hurley Plz Ste 212",
    "sg:city":"Flint",
    "sg:classifiers":[
        {
            "category":"Health Services",
            "subcategory":"Doctor",
            "type":"Services"
        }
    ],
    "sg:phone":"+1 810 762 7300",
    "sg:postcode":"48503",
    "sg:province":"MI",
    "wof:name":"Campbell Peter Bruce MD",
    "wof:placetype":"venue"
},
  "geometry": {"coordinates":[-83.69409899999999,43.0089],"type":"Point"}
}