{
  "type": "Feature",
  "properties": {
    "iso:country":"US",
    "sg:address":"5370 E Hill Rd",
    "sg:city":"Grand Blanc",
    "sg:classifiers":[
        {
            "category":"Shopping",
            "subcategory":"Pharmacy",
            "type":"Retail Goods"
        }
    ],
    "sg:phone":"+1 810 694 4775",
    "sg:postcode":"48439",
    "sg:province":"MI",
    "sg:tags":[
        "drugstore"
    ],
    "sg:website":"www.riteaid.com",
    "wof:name":"Rite Aid Pharmacies",
    "wof:placetype":"venue"
},
  "geometry": {"coordinates":[-83.60028699999999,42.945136],"type":"Point"}
}