{
  "type": "Feature",
  "properties": {
    "iso:country":"US",
    "sg:address":"99 S 35th St",
    "sg:city":"Galesburg",
    "sg:classifiers":[
        {
            "category":"Building & Trades",
            "subcategory":"Cleaning & Sanitation",
            "type":"Services"
        }
    ],
    "sg:phone":"+1 269 665 9173",
    "sg:postcode":"49053",
    "sg:province":"MI",
    "sg:tags":[
        "maintenance"
    ],
    "wof:name":"Nca Services",
    "wof:placetype":"venue"
},
  "geometry": {"coordinates":[-85.428843,42.2874],"type":"Point"}
}