{
  "type": "Feature",
  "properties": {
    "iso:country":"US",
    "sg:address":"230 Stephens Rd",
    "sg:city":"Grosse Pointe",
    "sg:classifiers":[
        {
            "category":"Health Services",
            "subcategory":"Doctor",
            "type":"Services"
        }
    ],
    "sg:phone":"+1 313 886 9746",
    "sg:postcode":"48236",
    "sg:province":"MI",
    "sg:tags":[
        "medical"
    ],
    "wof:name":"Dr M Khalidi",
    "wof:placetype":"venue"
},
  "geometry": {"coordinates":[-82.899367,42.403901],"type":"Point"}
}