{
  "type": "Feature",
  "properties": {
    "iso:country":"US",
    "sg:address":"622 E High St",
    "sg:city":"Benton Harbor",
    "sg:classifiers":[
        {
            "category":"Organizations",
            "subcategory":"Membership Organization",
            "type":"Services"
        }
    ],
    "sg:phone":"+1 269 927 1658",
    "sg:postcode":"49022",
    "sg:province":"MI",
    "wof:name":"Habitat For Humanity",
    "wof:placetype":"venue"
},
  "geometry": {"coordinates":[-86.44348100000001,42.113657],"type":"Point"}
}