{
  "type": "Feature",
  "properties": {
    "iso:country":"US",
    "sg:address":"25718 Schoolcraft",
    "sg:city":"Redford",
    "sg:classifiers":[
        {
            "category":"Organizations",
            "subcategory":"Professional Association",
            "type":"Services"
        }
    ],
    "sg:phone":"+1 313 534 6000",
    "sg:postcode":"48239",
    "sg:province":"MI",
    "sg:tags":[
        "business"
    ],
    "wof:name":"Empowerment Together",
    "wof:placetype":"venue"
},
  "geometry": {"coordinates":[-83.295288,42.385478],"type":"Point"}
}