{
  "type": "Feature",
  "properties": {
    "iso:country":"US",
    "sg:address":"10440 Highland Rd",
    "sg:city":"Hartland",
    "sg:classifiers":[
        {
            "category":"Restaurant",
            "type":"Food & Drink"
        }
    ],
    "sg:menulink":"http://www.allmenus.com/mi/hartland/207720-taco-bell/menu/",
    "sg:phone":"+1 810 632 4341",
    "sg:postcode":"48353",
    "sg:province":"MI",
    "sg:tags":[
        "mexican"
    ],
    "wof:name":"Taco Bell",
    "wof:placetype":"venue"
},
  "geometry": {"coordinates":[-83.74529099999999,42.633792],"type":"Point"}
}