{
  "type": "Feature",
  "properties": {
    "iso:country":"US",
    "sg:address":"1283 W Dansville Rd",
    "sg:city":"Mason",
    "sg:phone":"+1 517 676 4469",
    "sg:postcode":"48854",
    "sg:province":"MI",
    "sg:tags":[
        "farm",
        "corn",
        "beef",
        "feedlot",
        "cattle"
    ],
    "wof:name":"Charles Goeke",
    "wof:placetype":"venue"
},
  "geometry": {"coordinates":[-84.388695,42.563821],"type":"Point"}
}