{
  "type": "Feature",
  "properties": {
    "iso:country":"US",
    "sg:address":"1200 E Columbia Ave",
    "sg:city":"Battle Creek",
    "sg:classifiers":[
        {
            "category":"Retail",
            "subcategory":"Auto Repair",
            "type":"Services"
        }
    ],
    "sg:phone":"+1 269 964 9131",
    "sg:postcode":"49014",
    "sg:province":"MI",
    "sg:tags":[
        "automotive"
    ],
    "wof:name":"R&R Complete Car Care",
    "wof:placetype":"venue"
},
  "geometry": {"coordinates":[-85.164137,42.301631],"type":"Point"}
}