{
  "type": "Feature",
  "properties": {
    "iso:country":"US",
    "sg:address":"11356 McDougall St",
    "sg:city":"Hamtramck",
    "sg:classifiers":[
        {
            "category":"Building & Trades",
            "subcategory":"Construction",
            "type":"Services"
        }
    ],
    "sg:phone":"+1 313 891 0369",
    "sg:postcode":"48212",
    "sg:province":"MI",
    "sg:tags":[
        "painter"
    ],
    "wof:name":"Norman's Painting Co",
    "wof:placetype":"venue"
},
  "geometry": {"coordinates":[-83.05819700000001,42.401001],"type":"Point"}
}