{
  "type": "Feature",
  "properties": {
    "iso:country":"US",
    "sg:address":"19900 E 10 Mile Rd Ste 102",
    "sg:city":"Saint Clair Shores",
    "sg:classifiers":[
        {
            "category":"Professional",
            "subcategory":"Lawyer & Legal Services",
            "type":"Services"
        }
    ],
    "sg:phone":"+1 586 774 0071",
    "sg:postcode":"48080",
    "sg:province":"MI",
    "wof:name":"Johnson Stuart",
    "wof:placetype":"venue"
},
  "geometry": {"coordinates":[-82.9151,42.480499],"type":"Point"}
}