{
  "type": "Feature",
  "properties": {
    "iso:country":"US",
    "sg:address":"691 Melrose St",
    "sg:city":"Pontiac",
    "sg:classifiers":[
        {
            "category":"Travel",
            "subcategory":"Travel Agent",
            "type":"Entertainment"
        }
    ],
    "sg:phone":"+1 248 409 9806",
    "sg:postcode":"48340",
    "sg:province":"MI",
    "sg:tags":[
        "tours",
        "promoter"
    ],
    "wof:name":"Angel Tours",
    "wof:placetype":"venue"
},
  "geometry": {"coordinates":[-83.26567900000001,42.657848],"type":"Point"}
}