{
  "type": "Feature",
  "properties": {
    "iso:country":"US",
    "sg:address":"71451 S Centerville Rd",
    "sg:city":"Sturgis",
    "sg:classifiers":[
        {
            "category":"Travel",
            "subcategory":"Hotels & Motels",
            "type":"Entertainment"
        }
    ],
    "sg:phone":"+1 269 651 4210",
    "sg:postcode":"49091",
    "sg:province":"MI",
    "sg:tags":[
        "building",
        "operator",
        "operation",
        "apartment"
    ],
    "sg:website":"http://www.sturgis.hamptoninn.com",
    "wof:name":"Hampton Inn",
    "wof:placetype":"venue"
},
  "geometry": {"coordinates":[-85.427757,41.760059],"type":"Point"}
}