{
  "type": "Feature",
  "properties": {
    "iso:country":"US",
    "sg:address":"176 Mc Kinley Ave",
    "sg:city":"Grosse Pointe",
    "sg:classifiers":[
        {
            "category":"Education",
            "subcategory":"School",
            "type":"Public Place"
        }
    ],
    "sg:phone":"+1 313 343 2281",
    "sg:postcode":"48236",
    "sg:province":"MI",
    "sg:tags":[
        "elementary"
    ],
    "wof:name":"Richard Elementary School",
    "wof:placetype":"venue"
},
  "geometry": {"coordinates":[-82.90568,42.394993],"type":"Point"}
}