{
  "type": "Feature",
  "properties": {
    "iso:country":"US",
    "sg:address":"61380 Pinehurst",
    "sg:city":"Washington",
    "sg:classifiers":[
        {
            "category":"Professional",
            "subcategory":"Management & Consulting",
            "type":"Services"
        }
    ],
    "sg:phone":"+1 586 992 3421",
    "sg:postcode":"48094",
    "sg:province":"MI",
    "sg:tags":[
        "business"
    ],
    "wof:name":"EZ Business Solutions & Cons",
    "wof:placetype":"venue"
},
  "geometry": {"coordinates":[-83.032307,42.743729],"type":"Point"}
}