{
  "type": "Feature",
  "properties": {
    "iso:country":"US",
    "sg:address":"6740 Cascade Rd SE",
    "sg:city":"Grand Rapids",
    "sg:classifiers":[
        {
            "category":"Insurance",
            "subcategory":"Insurance Agent",
            "type":"Services"
        }
    ],
    "sg:phone":"+1 616 940 7039",
    "sg:postcode":"49546",
    "sg:province":"MI",
    "wof:name":"Farm Bureau Insurance",
    "wof:placetype":"venue"
},
  "geometry": {"coordinates":[-85.499573,42.913591],"type":"Point"}
}