{
  "type": "Feature",
  "properties": {
    "iso:country":"US",
    "sg:address":"825 S Main St",
    "sg:city":"Lapeer",
    "sg:classifiers":[
        {
            "category":"Restaurant",
            "type":"Food & Drink"
        }
    ],
    "sg:menulink":"http://www.allmenus.com/mi/lapeer/251461-e-g-nicks/menu/",
    "sg:phone":"+1 810 664 6200",
    "sg:postcode":"48446",
    "sg:province":"MI",
    "sg:tags":[
        "american"
    ],
    "wof:name":"E. G. Nick's",
    "wof:placetype":"venue"
},
  "geometry": {"coordinates":[-83.32105300000001,43.040554],"type":"Point"}
}