{
  "type": "Feature",
  "properties": {
    "iso:country":"US",
    "sg:address":"4181 W Vienna Rd",
    "sg:city":"Clio",
    "sg:classifiers":[
        {
            "category":"Personal",
            "subcategory":"Beauty Salon",
            "type":"Services"
        }
    ],
    "sg:phone":"+1 810 564 9563",
    "sg:postcode":"48420",
    "sg:province":"MI",
    "wof:name":"Grondin's Hair Ctr",
    "wof:placetype":"venue"
},
  "geometry": {"coordinates":[-83.758906,43.177384],"type":"Point"}
}