{
  "type": "Feature",
  "properties": {
    "iso:country":"US",
    "sg:address":"4470 128th Ave",
    "sg:city":"Holland",
    "sg:classifiers":[
        {
            "category":"Manufacturing",
            "subcategory":"Metals",
            "type":"Manufacturing & Wholesale Goods"
        }
    ],
    "sg:phone":"+1 616 786 4300",
    "sg:postcode":"49424",
    "sg:province":"MI",
    "sg:tags":[
        "machine",
        "screw",
        "product"
    ],
    "wof:name":"Atcon International",
    "wof:placetype":"venue"
},
  "geometry": {"coordinates":[-86.098794,42.854378],"type":"Point"}
}