{
  "type": "Feature",
  "properties": {
    "iso:country":"US",
    "sg:address":"201 Park Ave",
    "sg:city":"Jackson",
    "sg:classifiers":[
        {
            "category":"Food & Beverages",
            "subcategory":"Groceries & Convenience Stores",
            "type":"Retail Goods"
        }
    ],
    "sg:phone":"+1 517 783 4226",
    "sg:postcode":"49203",
    "sg:province":"MI",
    "wof:name":"Pollys Food Service Inc",
    "wof:placetype":"venue"
},
  "geometry": {"coordinates":[-84.400362,42.195857],"type":"Point"}
}