{
  "type": "Feature",
  "properties": {
    "iso:country":"US",
    "sg:address":"575 E 40th St",
    "sg:city":"White Cloud",
    "sg:classifiers":[
        {
            "category":"Health Services",
            "subcategory":"Clinic",
            "type":"Services"
        }
    ],
    "sg:phone":"+1 231 689 2025",
    "sg:postcode":"49349",
    "sg:province":"MI",
    "sg:tags":[
        "medical",
        "group"
    ],
    "wof:name":"Pine Medical Group",
    "wof:placetype":"venue"
},
  "geometry": {"coordinates":[-85.798704,43.481439],"type":"Point"}
}