{
  "type": "Feature",
  "properties": {
    "iso:country":"US",
    "sg:address":"5955 Becht Rd",
    "sg:city":"Coloma",
    "sg:classifiers":[
        {
            "category":"Building & Trades",
            "subcategory":"Construction",
            "type":"Services"
        }
    ],
    "sg:phone":"+1 269 876 2595",
    "sg:postcode":"49038",
    "sg:province":"MI",
    "sg:tags":[
        "repairing",
        "remodeling",
        "contractor"
    ],
    "wof:name":"Larry Nelson Construction",
    "wof:placetype":"venue"
},
  "geometry": {"coordinates":[-86.320635,42.218726],"type":"Point"}
}