{
  "type": "Feature",
  "properties": {
    "iso:country":"US",
    "sg:address":"5919 Sigler Rd",
    "sg:city":"South Rockwood",
    "sg:classifiers":[
        {
            "category":"Building & Trades",
            "subcategory":"Equipment Rental",
            "type":"Services"
        }
    ],
    "sg:phone":"+1 734 586 3445",
    "sg:postcode":"48179",
    "sg:province":"MI",
    "wof:name":"Elite Party Tent Rental",
    "wof:placetype":"venue"
},
  "geometry": {"coordinates":[-83.266166,42.037561],"type":"Point"}
}