{
  "type": "Feature",
  "properties": {
    "iso:country":"US",
    "sg:address":"13161 Thistlewood Ln",
    "sg:city":"Holland",
    "sg:classifiers":[
        {
            "category":"Building & Trades",
            "subcategory":"Construction",
            "type":"Services"
        }
    ],
    "sg:phone":"+1 616 786 9322",
    "sg:postcode":"49424",
    "sg:province":"MI",
    "sg:tags":[
        "painter"
    ],
    "wof:name":"Painting Cutting Edge",
    "wof:placetype":"venue"
},
  "geometry": {"coordinates":[-86.10664199999999,42.824407],"type":"Point"}
}