{
  "type": "Feature",
  "properties": {
    "iso:country":"US",
    "sg:address":"210 S 1st St",
    "sg:city":"Shepherd",
    "sg:classifiers":[
        {
            "category":"Wholesale",
            "subcategory":"Vending Machines",
            "type":"Manufacturing & Wholesale Goods"
        }
    ],
    "sg:phone":"+1 989 772 0586",
    "sg:postcode":"48883",
    "sg:province":"MI",
    "wof:name":"Mid-Michigan Vending Co",
    "wof:placetype":"venue"
},
  "geometry": {"coordinates":[-84.697132,43.523706],"type":"Point"}
}