{
  "type": "Feature",
  "properties": {
    "iso:country":"US",
    "sg:address":"425 S Main St",
    "sg:city":"Pigeon",
    "sg:classifiers":[
        {
            "category":"Manufacturing",
            "subcategory":"Tools & Machinery",
            "type":"Manufacturing & Wholesale Goods"
        }
    ],
    "sg:phone":"+1 989 453 2120",
    "sg:postcode":"48755",
    "sg:province":"MI",
    "sg:tags":[
        "farm",
        "equipment"
    ],
    "wof:name":"Osentoski Equipment Inc",
    "wof:placetype":"venue"
},
  "geometry": {"coordinates":[-83.27014800000001,43.824431],"type":"Point"}
}