{
  "type": "Feature",
  "properties": {
    "iso:country":"US",
    "sg:address":"851 Madison Ave SE",
    "sg:city":"Grand Rapids",
    "sg:classifiers":[
        {
            "category":"Education",
            "subcategory":"School",
            "type":"Public Place"
        }
    ],
    "sg:phone":"+1 616 819 2785",
    "sg:postcode":"49507",
    "sg:province":"MI",
    "sg:website":"www.grps.k12.mi.us",
    "wof:name":"Madison Park Elementary School",
    "wof:placetype":"venue"
},
  "geometry": {"coordinates":[-85.659127,42.947549],"type":"Point"}
}