{
  "type": "Feature",
  "properties": {
    "iso:country":"US",
    "sg:address":"1488 Waverly Dr",
    "sg:city":"Troy",
    "sg:classifiers":[
        {
            "category":"Banks & Credit Unions",
            "subcategory":"Investment Brokerage",
            "type":"Services"
        }
    ],
    "sg:phone":"+1 248 641 0737",
    "sg:postcode":"48098",
    "sg:province":"MI",
    "sg:tags":[
        "advisory"
    ],
    "wof:name":"William Shamoun",
    "wof:placetype":"venue"
},
  "geometry": {"coordinates":[-83.175319,42.59964],"type":"Point"}
}