{
  "type": "Feature",
  "properties": {
    "iso:country":"US",
    "sg:address":"12057 Westwood St",
    "sg:city":"Detroit",
    "sg:classifiers":[
        {
            "category":"Social Services",
            "subcategory":"Child Care",
            "type":"Services"
        }
    ],
    "sg:phone":"+1 313 838 2019",
    "sg:postcode":"48228",
    "sg:province":"MI",
    "sg:tags":[
        "day"
    ],
    "wof:name":"Starr Babys Child Care Center",
    "wof:placetype":"venue"
},
  "geometry": {"coordinates":[-83.231582,42.374589],"type":"Point"}
}