{
  "type": "Feature",
  "properties": {
    "iso:country":"US",
    "sg:address":"1816 Sinclair St",
    "sg:city":"Saint Clair",
    "sg:classifiers":[
        {
            "category":"Real Estate",
            "subcategory":"Real Estate Services",
            "type":"Services"
        }
    ],
    "sg:phone":"+1 810 326 1241",
    "sg:postcode":"48079",
    "sg:province":"MI",
    "sg:tags":[
        "abstract",
        "title"
    ],
    "wof:name":"Stewart Title",
    "wof:placetype":"venue"
},
  "geometry": {"coordinates":[-82.50873900000001,42.819247],"type":"Point"}
}