{
  "type": "Feature",
  "properties": {
    "iso:country":"US",
    "sg:address":"11280 Ozga St",
    "sg:city":"Romulus",
    "sg:classifiers":[
        {
            "category":"Organizations",
            "subcategory":"Religious Organization",
            "type":"Services"
        }
    ],
    "sg:phone":"+1 734 941 5056",
    "sg:postcode":"48174",
    "sg:province":"MI",
    "wof:name":"St Aloysius Catholic Church",
    "wof:placetype":"venue"
},
  "geometry": {"coordinates":[-83.405192,42.220699],"type":"Point"}
}