{
  "type": "Feature",
  "properties": {
    "iso:country":"US",
    "sg:address":"1121 N 2nd St",
    "sg:city":"Ishpeming",
    "sg:classifiers":[
        {
            "category":"Government",
            "subcategory":"Office",
            "type":"Public Place"
        }
    ],
    "sg:phone":"+1 906 486 6101",
    "sg:postcode":"49849",
    "sg:province":"MI",
    "sg:tags":[
        "village"
    ],
    "wof:name":"Ishpeming City Little League",
    "wof:placetype":"venue"
},
  "geometry": {"coordinates":[-87.66585600000001,46.4991],"type":"Point"}
}