{
  "type": "Feature",
  "properties": {
    "iso:country":"US",
    "sg:address":"6268 Woodbine St",
    "sg:city":"Caseville",
    "sg:classifiers":[
        {
            "category":"Professional",
            "subcategory":"Detective & Security Services",
            "type":"Services"
        }
    ],
    "sg:phone":"+1 989 856 7427",
    "sg:postcode":"48725",
    "sg:province":"MI",
    "sg:tags":[
        "system"
    ],
    "wof:name":"Vr Klein Inc",
    "wof:placetype":"venue"
},
  "geometry": {"coordinates":[-83.26584099999999,43.947616],"type":"Point"}
}