{
  "type": "Feature",
  "properties": {
    "iso:country":"US",
    "sg:address":"58134 Circle Dr",
    "sg:city":"Three Rivers",
    "sg:classifiers":[
        {
            "category":"Real Estate",
            "subcategory":"Real Estate Agent",
            "type":"Services"
        }
    ],
    "sg:phone":"+1 269 279 5447",
    "sg:postcode":"49093",
    "sg:province":"MI",
    "wof:name":"Landmark Realty",
    "wof:placetype":"venue"
},
  "geometry": {"coordinates":[-85.650183,41.951034],"type":"Point"}
}