{
  "type": "Feature",
  "properties": {
    "iso:country":"US",
    "sg:address":"2225 E Hill Rd",
    "sg:city":"Grand Blanc",
    "sg:classifiers":[
        {
            "category":"Restaurant",
            "type":"Food & Drink"
        }
    ],
    "sg:phone":"+1 810 694 4139",
    "sg:postcode":"48439",
    "sg:province":"MI",
    "sg:website":"www.subway.com",
    "wof:name":"Subway",
    "wof:placetype":"venue"
},
  "geometry": {"coordinates":[-83.664299,42.9445],"type":"Point"}
}