{
  "type": "Feature",
  "properties": {
    "iso:country":"US",
    "sg:address":"9997 S Big School Lot Lake Rd",
    "sg:city":"Holly",
    "sg:classifiers":[
        {
            "category":"Professional",
            "subcategory":"Computer Services",
            "type":"Services"
        }
    ],
    "sg:phone":"+1 248 634 7295",
    "sg:postcode":"48442",
    "sg:province":"MI",
    "sg:tags":[
        "programing",
        "custom"
    ],
    "wof:name":"Slingerland Creative Solutions",
    "wof:placetype":"venue"
},
  "geometry": {"coordinates":[-83.626453,42.741096],"type":"Point"}
}