{
  "type": "Feature",
  "properties": {
    "iso:country":"US",
    "sg:address":"2814 Terrehaven Dr",
    "sg:city":"Adrian",
    "sg:classifiers":[
        {
            "category":"Real Estate",
            "subcategory":"Real Estate Agent",
            "type":"Services"
        }
    ],
    "sg:phone":"+1 517 263 5740",
    "sg:postcode":"49221",
    "sg:province":"MI",
    "wof:name":"N & D Properties",
    "wof:placetype":"venue"
},
  "geometry": {"coordinates":[-84.10078300000001,41.925712],"type":"Point"}
}