{
  "type": "Feature",
  "properties": {
    "iso:country":"US",
    "sg:address":"46698 Lake Ct",
    "sg:city":"Decatur",
    "sg:classifiers":[
        {
            "category":"Retail",
            "subcategory":"Repair Shop",
            "type":"Services"
        }
    ],
    "sg:phone":"+1 269 423 6336",
    "sg:postcode":"49045",
    "sg:province":"MI",
    "wof:name":"T & G Taxidermy",
    "wof:placetype":"venue"
},
  "geometry": {"coordinates":[-86.000246,42.10635],"type":"Point"}
}