{
  "type": "Feature",
  "properties": {
    "iso:country":"US",
    "sg:address":"99 W Lovell Dr",
    "sg:city":"Troy",
    "sg:classifiers":[
        {
            "category":"Professional",
            "subcategory":"Business Services",
            "type":"Services"
        }
    ],
    "sg:phone":"+1 248 879 9840",
    "sg:postcode":"48098",
    "sg:province":"MI",
    "sg:tags":[
        "repossessing"
    ],
    "wof:name":"Oakland Auto Recovery",
    "wof:placetype":"venue"
},
  "geometry": {"coordinates":[-83.150295,42.617946],"type":"Point"}
}