{
  "type": "Feature",
  "properties": {
    "iso:country":"US",
    "sg:address":"8871 Unionville Rd",
    "sg:city":"Sebewaing",
    "sg:classifiers":[
        {
            "category":"Real Estate",
            "subcategory":"Real Estate Agent",
            "type":"Services"
        }
    ],
    "sg:phone":"+1 989 883 2248",
    "sg:postcode":"48759",
    "sg:province":"MI",
    "wof:name":"Kelly & Co Realty & Auctioneer",
    "wof:placetype":"venue"
},
  "geometry": {"coordinates":[-83.44705399999999,43.719669],"type":"Point"}
}