{
  "type": "Feature",
  "properties": {
    "iso:country":"US",
    "sg:address":"2726 Pasadena St",
    "sg:city":"Detroit",
    "sg:classifiers":[
        {
            "category":"Wholesale",
            "subcategory":"Vending Machines",
            "type":"Manufacturing & Wholesale Goods"
        }
    ],
    "sg:phone":"+1 313 865 4253",
    "sg:postcode":"48238",
    "sg:province":"MI",
    "sg:tags":[
        "operator"
    ],
    "wof:name":"Clever Vending",
    "wof:placetype":"venue"
},
  "geometry": {"coordinates":[-83.125495,42.394829],"type":"Point"}
}