{
  "type": "Feature",
  "properties": {
    "iso:country":"US",
    "sg:address":"9880 Klais Ct",
    "sg:city":"Clarkston",
    "sg:classifiers":[
        {
            "category":"Professional",
            "subcategory":"Business Services",
            "type":"Services"
        }
    ],
    "sg:phone":"+1 248 969 5803",
    "sg:postcode":"48348",
    "sg:province":"MI",
    "wof:name":"Common Sense Technology",
    "wof:placetype":"venue"
},
  "geometry": {"coordinates":[-83.334352,42.78414],"type":"Point"}
}