{
  "type": "Feature",
  "properties": {
    "iso:country":"US",
    "sg:address":"2150 E Coon Lake Rd",
    "sg:city":"Howell",
    "sg:classifiers":[
        {
            "category":"Professional",
            "subcategory":"Accounting & Tax Preparation",
            "type":"Services"
        }
    ],
    "sg:phone":"+1 517 552 0943",
    "sg:postcode":"48843",
    "sg:province":"MI",
    "wof:name":"Crm Electric Med Billing",
    "wof:placetype":"venue"
},
  "geometry": {"coordinates":[-83.912847,42.539766],"type":"Point"}
}