{
  "type": "Feature",
  "properties": {
    "iso:country":"US",
    "sg:address":"600 N Main St",
    "sg:city":"Rochester",
    "sg:classifiers":[
        {
            "category":"Home & Garden",
            "subcategory":"Hardware",
            "type":"Retail Goods"
        }
    ],
    "sg:phone":"+1 248 608 5095",
    "sg:postcode":"48307",
    "sg:province":"MI",
    "wof:name":"True Value Hdwr Of Rochester",
    "wof:placetype":"venue"
},
  "geometry": {"coordinates":[-83.133865,42.683567],"type":"Point"}
}