{
  "type": "Feature",
  "properties": {
    "iso:country":"US",
    "sg:address":"48719 Fairchild Rd",
    "sg:city":"Macomb",
    "sg:classifiers":[
        {
            "category":"Building & Trades",
            "subcategory":"Plumbing",
            "type":"Services"
        }
    ],
    "sg:phone":"+1 586 598 7878",
    "sg:postcode":"48042",
    "sg:province":"MI",
    "sg:tags":[
        "plumbing",
        "contractor"
    ],
    "wof:name":"Bill Vought Plumbing Inc",
    "wof:placetype":"venue"
},
  "geometry": {"coordinates":[-82.86227100000001,42.657367],"type":"Point"}
}