{
  "type": "Feature",
  "properties": {
    "iso:country":"US",
    "sg:address":"307 S Sheridan Ave",
    "sg:city":"Remus",
    "sg:classifiers":[
        {
            "category":"Organizations",
            "subcategory":"Religious Organization",
            "type":"Services"
        }
    ],
    "sg:phone":"+1 989 967 8553",
    "sg:postcode":"49340",
    "sg:province":"MI",
    "sg:tags":[
        "church"
    ],
    "wof:name":"Chippewa Hills Assembly-God",
    "wof:placetype":"venue"
},
  "geometry": {"coordinates":[-85.145421,43.594682],"type":"Point"}
}