{
  "type": "Feature",
  "properties": {
    "iso:country":"US",
    "sg:address":"1860 E Hile Rd",
    "sg:city":"Muskegon",
    "sg:classifiers":[
        {
            "category":"Social Services",
            "subcategory":"Child Care",
            "type":"Services"
        }
    ],
    "sg:phone":"+1 231 737 1179",
    "sg:postcode":"49444",
    "sg:province":"MI",
    "sg:tags":[
        "kindergarten",
        "academic",
        "school"
    ],
    "wof:name":"Creative Child Preschool",
    "wof:placetype":"venue"
},
  "geometry": {"coordinates":[-86.200839,43.168877],"type":"Point"}
}