{
  "type": "Feature",
  "properties": {
    "iso:country":"US",
    "sg:address":"2462 S Getty St",
    "sg:city":"Muskegon",
    "sg:classifiers":[
        {
            "category":"Retail",
            "subcategory":"Auto Repair",
            "type":"Services"
        }
    ],
    "sg:phone":"+1 231 739 7240",
    "sg:postcode":"49444",
    "sg:province":"MI",
    "sg:tags":[
        "body"
    ],
    "wof:name":"Ramos & Sons Body Shop",
    "wof:placetype":"venue"
},
  "geometry": {"coordinates":[-86.224538,43.208398],"type":"Point"}
}