{
  "type": "Feature",
  "properties": {
    "iso:country":"US",
    "sg:address":"3955 Meridian Rd",
    "sg:city":"Okemos",
    "sg:classifiers":[
        {
            "category":"Professional",
            "subcategory":"Business Services",
            "type":"Services"
        }
    ],
    "sg:phone":"+1 517 347 2949",
    "sg:postcode":"48864",
    "sg:province":"MI",
    "wof:name":"M & M Enterprises Ingham Cnty",
    "wof:placetype":"venue"
},
  "geometry": {"coordinates":[-84.363615,42.696573],"type":"Point"}
}