{
  "type": "Feature",
  "properties": {
    "iso:country":"US",
    "sg:address":"1007 Lansing Ave",
    "sg:city":"Jackson",
    "sg:classifiers":[
        {
            "category":"Personal",
            "subcategory":"Beauty Salon",
            "type":"Services"
        }
    ],
    "sg:phone":"+1 517 789 8840",
    "sg:postcode":"49202",
    "sg:province":"MI",
    "wof:name":"Erma Ragland Beauty Salon",
    "wof:placetype":"venue"
},
  "geometry": {"coordinates":[-84.417288,42.261184],"type":"Point"}
}