{
  "type": "Feature",
  "properties": {
    "iso:country":"US",
    "sg:address":"12430 E 13 Mile Rd",
    "sg:city":"Warren",
    "sg:classifiers":[
        {
            "category":"Professional",
            "type":"Services"
        }
    ],
    "sg:phone":"+1 586 751 2462",
    "sg:postcode":"48093",
    "sg:province":"MI",
    "wof:name":"Facility Systems & Services",
    "wof:placetype":"venue"
},
  "geometry": {"coordinates":[-82.998757,42.521487],"type":"Point"}
}