{
  "type": "Feature",
  "properties": {
    "iso:country":"US",
    "sg:address":"1854 Winthrop Ln",
    "sg:city":"Birmingham",
    "sg:classifiers":[
        {
            "category":"Health Services",
            "subcategory":"Doctor",
            "type":"Services"
        }
    ],
    "sg:phone":"+1 248 647 3645",
    "sg:postcode":"48009",
    "sg:province":"MI",
    "sg:tags":[
        "medical"
    ],
    "wof:name":"Kthryn J Wimbish MD Foundation",
    "wof:placetype":"venue"
},
  "geometry": {"coordinates":[-83.236357,42.549074],"type":"Point"}
}