{
  "type": "Feature",
  "properties": {
    "iso:country":"US",
    "sg:address":"208 S Sophie St",
    "sg:city":"Bessemer",
    "sg:classifiers":[
        {
            "category":"Bars & Pubs",
            "type":"Food & Drink"
        }
    ],
    "sg:phone":"+1 906 663 6903",
    "sg:postcode":"49911",
    "sg:province":"MI",
    "wof:name":"Gin Mill Bar",
    "wof:placetype":"venue"
},
  "geometry": {"coordinates":[-90.05042899999999,46.48007],"type":"Point"}
}