{
  "type": "Feature",
  "properties": {
    "iso:country":"US",
    "sg:address":"632 W Hanover St",
    "sg:city":"Marshall",
    "sg:classifiers":[
        {
            "category":"Retail",
            "subcategory":"Portrait Studio",
            "type":"Services"
        }
    ],
    "sg:phone":"+1 269 781 2736",
    "sg:postcode":"49068",
    "sg:province":"MI",
    "sg:tags":[
        "photo"
    ],
    "wof:name":"Creative Photo Services",
    "wof:placetype":"venue"
},
  "geometry": {"coordinates":[-84.96905099999999,42.270015],"type":"Point"}
}