{
  "type": "Feature",
  "properties": {
    "iso:country":"US",
    "sg:address":"31936 Mound Rd",
    "sg:city":"Warren",
    "sg:classifiers":[
        {
            "category":"Shopping",
            "subcategory":"Pets & Pet Supplies",
            "type":"Retail Goods"
        }
    ],
    "sg:phone":"+1 586 939 5960",
    "sg:postcode":"48092",
    "sg:province":"MI",
    "sg:tags":[
        "store"
    ],
    "wof:name":"K-9 Specialties Obedience & Show Supplies",
    "wof:placetype":"venue"
},
  "geometry": {"coordinates":[-83.047302,42.528099],"type":"Point"}
}