{
  "type": "Feature",
  "properties": {
    "iso:country":"US",
    "sg:address":"1613 W Lawrence Hwy",
    "sg:city":"Charlotte",
    "sg:classifiers":[
        {
            "category":"Communications",
            "subcategory":"Radio Station",
            "type":"Services"
        }
    ],
    "sg:phone":"+1 517 543 8200",
    "sg:postcode":"48813",
    "sg:province":"MI",
    "sg:tags":[
        "company",
        "broadcasting"
    ],
    "wof:name":"WLCM",
    "wof:placetype":"venue"
},
  "geometry": {"coordinates":[-84.873701,42.568004],"type":"Point"}
}