{
  "type": "Feature",
  "properties": {
    "iso:country":"US",
    "sg:address":"12384 Percy Rd",
    "sg:city":"Shingleton",
    "sg:classifiers":[
        {
            "category":"Professional",
            "subcategory":"Employment Agencies",
            "type":"Services"
        }
    ],
    "sg:phone":"+1 906 452 6477",
    "sg:postcode":"49884",
    "sg:province":"MI",
    "sg:tags":[
        "picking",
        "cone",
        "pine"
    ],
    "wof:name":"Kim Robinson",
    "wof:placetype":"venue"
},
  "geometry": {"coordinates":[-86.48981999999999,46.390392],"type":"Point"}
}