{
  "type": "Feature",
  "properties": {
    "iso:country":"US",
    "sg:address":"133 W Cedar St",
    "sg:city":"Kalamazoo",
    "sg:classifiers":[
        {
            "category":"Professional",
            "subcategory":"Lawyer & Legal Services",
            "type":"Services"
        }
    ],
    "sg:phone":"+1 269 344 1855",
    "sg:postcode":"49007",
    "sg:province":"MI",
    "sg:tags":[
        "divorce",
        "attorney",
        "criminal",
        "family",
        "law"
    ],
    "sg:website":"http://www.dughielawoffice.com",
    "wof:name":"Dughie Law Office",
    "wof:placetype":"venue"
},
  "geometry": {"coordinates":[-85.58408,42.287444],"type":"Point"}
}