{
  "type": "Feature",
  "properties": {
    "iso:country":"US",
    "sg:address":"45557 Mound Rd",
    "sg:city":"Shelby Twp",
    "sg:classifiers":[
        {
            "category":"Building & Trades",
            "subcategory":"Construction",
            "type":"Services"
        }
    ],
    "sg:phone":"+1 586 731 5445",
    "sg:postcode":"48317",
    "sg:province":"MI",
    "sg:tags":[
        "planning",
        "remodeling",
        "kitchen"
    ],
    "wof:name":"Raywal Kitchen Inc",
    "wof:placetype":"venue"
},
  "geometry": {"coordinates":[-83.052577,42.628963],"type":"Point"}
}