{
  "type": "Feature",
  "properties": {
    "iso:country":"US",
    "sg:address":"49150 Schoenherr Rd",
    "sg:city":"Shelby Twp",
    "sg:classifiers":[
        {
            "category":"Retail",
            "subcategory":"Funeral Services",
            "type":"Services"
        }
    ],
    "sg:phone":"+1 586 532 8600",
    "sg:postcode":"48315",
    "sg:province":"MI",
    "sg:tags":[
        "director"
    ],
    "wof:name":"Wasik Funeral Home Inc",
    "wof:placetype":"venue"
},
  "geometry": {"coordinates":[-82.994124,42.657236],"type":"Point"}
}