{
  "type": "Feature",
  "properties": {
    "iso:country":"US",
    "sg:address":"31724 Schoenherr Rd",
    "sg:city":"Warren",
    "sg:classifiers":[
        {
            "category":"Professional",
            "subcategory":"Computer Services",
            "type":"Services"
        }
    ],
    "sg:phone":"+1 586 693 0540",
    "sg:postcode":"48088",
    "sg:province":"MI",
    "sg:tags":[
        "programming",
        "age",
        "employment",
        "custom"
    ],
    "wof:name":"US Infotech",
    "wof:placetype":"venue"
},
  "geometry": {"coordinates":[-82.988392,42.52667],"type":"Point"}
}