{
  "type": "Feature",
  "properties": {
    "iso:country":"US",
    "sg:address":"13740 Lincoln St",
    "sg:city":"Oak Park",
    "sg:classifiers":[
        {
            "category":"Building & Trades",
            "subcategory":"Plumbing",
            "type":"Services"
        }
    ],
    "sg:phone":"+1 248 548 0989",
    "sg:postcode":"48237",
    "sg:province":"MI",
    "sg:tags":[
        "heating",
        "contractor"
    ],
    "wof:name":"M Orr & Co",
    "wof:placetype":"venue"
},
  "geometry": {"coordinates":[-83.18529700000001,42.48154],"type":"Point"}
}