{
  "type": "Feature",
  "properties": {
    "iso:country":"US",
    "sg:address":"705 US Hwy 31 S",
    "sg:city":"Traverse City",
    "sg:classifiers":[
        {
            "category":"Autos & Motor Vehicles",
            "subcategory":"Recreational Vehicle Sales",
            "type":"Retail Goods"
        }
    ],
    "sg:phone":"+1 231 943 4050",
    "sg:postcode":"49684",
    "sg:province":"MI",
    "wof:name":"Tc-Rv Inc",
    "wof:placetype":"venue"
},
  "geometry": {"coordinates":[-85.656176,44.676238],"type":"Point"}
}