{
  "type": "Feature",
  "properties": {
    "iso:country":"US",
    "sg:address":"2820 W Maple Rd Ste 126",
    "sg:city":"Troy",
    "sg:classifiers":[
        {
            "category":"Building & Trades",
            "subcategory":"Construction",
            "type":"Services"
        }
    ],
    "sg:phone":"+1 248 643 9590",
    "sg:postcode":"48084",
    "sg:province":"MI",
    "sg:tags":[
        "contractor"
    ],
    "wof:name":"Woodlake Construction",
    "wof:placetype":"venue"
},
  "geometry": {"coordinates":[-83.183701,42.547501],"type":"Point"}
}