{
  "type": "Feature",
  "properties": {
    "iso:country":"US",
    "sg:address":"410 E Dowland St",
    "sg:city":"Ludington",
    "sg:classifiers":[
        {
            "category":"Local Transit",
            "type":"Transportation"
        }
    ],
    "sg:phone":"+1 231 845 6218",
    "sg:postcode":"49431",
    "sg:province":"MI",
    "sg:tags":[
        "bus",
        "line"
    ],
    "wof:name":"Dial-A-Ride",
    "wof:placetype":"venue"
},
  "geometry": {"coordinates":[-86.440819,43.949429],"type":"Point"}
}