{
  "type": "Feature",
  "properties": {
    "iso:country":"US",
    "sg:address":"2645 Auburn Rd",
    "sg:city":"Auburn Hills",
    "sg:classifiers":[
        {
            "category":"Wholesale",
            "subcategory":"Motor Vehicles",
            "type":"Manufacturing & Wholesale Goods"
        }
    ],
    "sg:phone":"+1 248 852 8300",
    "sg:postcode":"48326",
    "sg:province":"MI",
    "sg:tags":[
        "trailer"
    ],
    "sg:website":"www.reeferpeterbilt.com",
    "wof:name":"Reefer Peterbilt",
    "wof:placetype":"venue"
},
  "geometry": {"coordinates":[-83.236626,42.634382],"type":"Point"}
}