{
  "type": "Feature",
  "properties": {
    "iso:country":"US",
    "sg:address":"18415 W McNichols Rd",
    "sg:city":"Detroit",
    "sg:classifiers":[
        {
            "category":"Education",
            "subcategory":"Preschool",
            "type":"Public Place"
        },
        {
            "category":"Education",
            "subcategory":"School",
            "type":"Public Place"
        }
    ],
    "sg:phone":"+1 313 794 7430",
    "sg:postcode":"48219",
    "sg:province":"MI",
    "sg:tags":[
        "elementary"
    ],
    "wof:name":"Children's Learning Center",
    "wof:placetype":"venue"
},
  "geometry": {"coordinates":[-83.223297,42.415298],"type":"Point"}
}