{
  "type": "Feature",
  "properties": {
    "iso:country":"US",
    "sg:address":"27205 Dequindre Rd",
    "sg:city":"Madison Heights",
    "sg:classifiers":[
        {
            "category":"Organizations",
            "subcategory":"Religious Organization",
            "type":"Services"
        }
    ],
    "sg:phone":"+1 248 584 4100",
    "sg:postcode":"48071",
    "sg:province":"MI",
    "wof:name":"American Islamic Community",
    "wof:placetype":"venue"
},
  "geometry": {"coordinates":[-83.085341,42.492611],"type":"Point"}
}