{
  "type": "Feature",
  "properties": {
    "iso:country":"US",
    "sg:address":"277 W Montcalm St",
    "sg:city":"Pontiac",
    "sg:classifiers":[
        {
            "category":"Autos & Motor Vehicles",
            "subcategory":"Automobile Sales",
            "type":"Retail Goods"
        }
    ],
    "sg:phone":"+1 248 334 7161",
    "sg:postcode":"48342",
    "sg:province":"MI",
    "sg:tags":[
        "car",
        "used",
        "dealer"
    ],
    "wof:name":"Mc Farlane Inc",
    "wof:placetype":"venue"
},
  "geometry": {"coordinates":[-83.30632,42.656238],"type":"Point"}
}