{
  "type": "Feature",
  "properties": {
    "iso:country":"US",
    "sg:address":"613 Oak St",
    "sg:city":"Calumet",
    "sg:classifiers":[
        {
            "category":"Professional",
            "subcategory":"Business Services",
            "type":"Services"
        }
    ],
    "sg:phone":"+1 906 337 2552",
    "sg:postcode":"49913",
    "sg:province":"MI",
    "sg:tags":[
        "operation"
    ],
    "wof:name":"Oak Street Interiors",
    "wof:placetype":"venue"
},
  "geometry": {"coordinates":[-88.45497400000001,47.246358],"type":"Point"}
}