{
  "type": "Feature",
  "properties": {
    "iso:country":"US",
    "sg:address":"600 Wilshire Dr",
    "sg:city":"Troy",
    "sg:classifiers":[
        {
            "category":"Wholesale",
            "subcategory":"Auto Parts",
            "type":"Manufacturing & Wholesale Goods"
        }
    ],
    "sg:phone":"+1 248 729 2450",
    "sg:postcode":"48084",
    "sg:province":"MI",
    "sg:tags":[
        "automobile"
    ],
    "wof:name":"Mimco",
    "wof:placetype":"venue"
},
  "geometry": {"coordinates":[-83.162268,42.564769],"type":"Point"}
}