{
  "type": "Feature",
  "properties": {
    "iso:country":"US",
    "sg:address":"7105 Old Lantern Dr SE",
    "sg:city":"Caledonia",
    "sg:classifiers":[
        {
            "category":"Recreation",
            "subcategory":"Arcade",
            "type":"Entertainment"
        }
    ],
    "sg:phone":"+1 616 698 6495",
    "sg:postcode":"49316",
    "sg:province":"MI",
    "wof:name":"A A Amusement Co",
    "wof:placetype":"venue"
},
  "geometry": {"coordinates":[-85.6339,42.833791],"type":"Point"}
}