{
  "type": "Feature",
  "properties": {
    "iso:country":"US",
    "sg:address":"6550 Bostonhill Ln",
    "sg:city":"Canton",
    "sg:classifiers":[
        {
            "category":"Professional",
            "subcategory":"Employment Agencies",
            "type":"Services"
        }
    ],
    "sg:phone":"+1 734 416 9275",
    "sg:postcode":"48187",
    "sg:province":"MI",
    "sg:tags":[
        "home",
        "cleaning",
        "help",
        "supply"
    ],
    "wof:name":"Maid Spotless",
    "wof:placetype":"venue"
},
  "geometry": {"coordinates":[-83.482697,42.330601],"type":"Point"}
}