{
  "type": "Feature",
  "properties": {
    "iso:country":"US",
    "sg:address":"5911 S Westnedge Ave",
    "sg:city":"Portage",
    "sg:classifiers":[
        {
            "category":"Shopping",
            "subcategory":"Books",
            "type":"Retail Goods"
        }
    ],
    "sg:phone":"+1 269 552 1500",
    "sg:postcode":"49002",
    "sg:province":"MI",
    "sg:tags":[
        "dealer"
    ],
    "wof:name":"Talking Book World",
    "wof:placetype":"venue"
},
  "geometry": {"coordinates":[-85.58941299999999,42.231812],"type":"Point"}
}