{
  "type": "Feature",
  "properties": {
    "iso:country":"US",
    "sg:address":"10015 Bergin Rd",
    "sg:city":"Howell",
    "sg:classifiers":[
        {
            "category":"Building & Trades",
            "subcategory":"Construction",
            "type":"Services"
        }
    ],
    "sg:phone":"+1 810 632 6070",
    "sg:postcode":"48843",
    "sg:province":"MI",
    "sg:tags":[
        "general",
        "contractor"
    ],
    "wof:name":"Matthew Homes",
    "wof:placetype":"venue"
},
  "geometry": {"coordinates":[-83.762529,42.617842],"type":"Point"}
}