{
  "type": "Feature",
  "properties": {
    "iso:country":"US",
    "sg:address":"31850 Ford Rd",
    "sg:city":"Garden City",
    "sg:classifiers":[
        {
            "category":"Autos & Motor Vehicles",
            "subcategory":"Automobile Sales",
            "type":"Retail Goods"
        }
    ],
    "sg:phone":"+1 734 427 6200",
    "sg:postcode":"48135",
    "sg:province":"MI",
    "sg:tags":[
        "body",
        "repair",
        "general"
    ],
    "wof:name":"Gordon Chevrolet Inc",
    "wof:placetype":"venue"
},
  "geometry": {"coordinates":[-83.35580400000001,42.325129],"type":"Point"}
}