{
  "type": "Feature",
  "properties": {
    "iso:country":"US",
    "sg:address":"53 E White Lake Dr",
    "sg:city":"Twin Lake",
    "sg:classifiers":[
        {
            "category":"Building & Trades",
            "subcategory":"Construction",
            "type":"Services"
        }
    ],
    "sg:phone":"+1 231 893 0969",
    "sg:postcode":"49457",
    "sg:province":"MI",
    "sg:tags":[
        "house"
    ],
    "wof:name":"J Wright Construction",
    "wof:placetype":"venue"
},
  "geometry": {"coordinates":[-86.236175,43.383237],"type":"Point"}
}