{
  "type": "Feature",
  "properties": {
    "iso:country":"US",
    "sg:address":"4639 W River Dr NE",
    "sg:city":"Comstock Park",
    "sg:classifiers":[
        {
            "category":"Professional",
            "subcategory":"Accounting & Tax Preparation",
            "type":"Services"
        }
    ],
    "sg:phone":"+1 616 784 4445",
    "sg:postcode":"49321",
    "sg:province":"MI",
    "sg:tags":[
        "accountant"
    ],
    "wof:name":"Mierendorf & Co",
    "wof:placetype":"venue"
},
  "geometry": {"coordinates":[-85.654892,43.048728],"type":"Point"}
}