{
  "type": "Feature",
  "properties": {
    "iso:country":"US",
    "sg:address":"5591 Wild Ridge Ln",
    "sg:city":"West Bloomfield",
    "sg:classifiers":[
        {
            "category":"Social Services",
            "subcategory":"Child Care",
            "type":"Services"
        }
    ],
    "sg:phone":"+1 248 855 3669",
    "sg:postcode":"48322",
    "sg:province":"MI",
    "sg:tags":[
        "day"
    ],
    "wof:name":"Children Choice",
    "wof:placetype":"venue"
},
  "geometry": {"coordinates":[-83.332481,42.539905],"type":"Point"}
}