{
  "type": "Feature",
  "properties": {
    "iso:country":"US",
    "sg:address":"9230 Shaver Rd",
    "sg:city":"Portage",
    "sg:classifiers":[
        {
            "category":"Retail",
            "subcategory":"Repair Shop",
            "type":"Services"
        }
    ],
    "sg:phone":"+1 269 329 2084",
    "sg:postcode":"49024",
    "sg:province":"MI",
    "wof:name":"Sew & Sew Upholstery",
    "wof:placetype":"venue"
},
  "geometry": {"coordinates":[-85.613833,42.172036],"type":"Point"}
}