{
  "type": "Feature",
  "properties": {
    "iso:country":"US",
    "sg:address":"2786 E Highland Rd",
    "sg:city":"Highland",
    "sg:classifiers":[
        {
            "category":"Restaurant",
            "type":"Food & Drink"
        }
    ],
    "sg:phone":"+1 248 887 5001",
    "sg:postcode":"48356",
    "sg:province":"MI",
    "sg:tags":[
        "pizza"
    ],
    "wof:name":"Grove's Highland Pizza",
    "wof:placetype":"venue"
},
  "geometry": {"coordinates":[-83.583083,42.653478],"type":"Point"}
}