{
  "type": "Feature",
  "properties": {
    "iso:country":"US",
    "sg:address":"627 28th St SW",
    "sg:city":"Wyoming",
    "sg:classifiers":[
        {
            "category":"Restaurant",
            "type":"Food & Drink"
        }
    ],
    "sg:menulink":"http://www.allmenus.com/mi/wyoming/59251-golden-28-restaurant/menu/",
    "sg:phone":"+1 616 531 2800",
    "sg:postcode":"49509",
    "sg:province":"MI",
    "sg:tags":[
        "asian",
        "chinese"
    ],
    "wof:name":"Golden 28 Restaurant",
    "wof:placetype":"venue"
},
  "geometry": {"coordinates":[-85.68217,42.913293],"type":"Point"}
}