{
  "type": "Feature",
  "properties": {
    "iso:country":"US",
    "sg:address":"1121 Burr St",
    "sg:city":"Jackson",
    "sg:classifiers":[
        {
            "category":"Social Services",
            "subcategory":"Child Care",
            "type":"Services"
        }
    ],
    "sg:phone":"+1 517 787 3968",
    "sg:postcode":"49201",
    "sg:province":"MI",
    "sg:tags":[
        "day"
    ],
    "wof:name":"Laiers Day Care",
    "wof:placetype":"venue"
},
  "geometry": {"coordinates":[-84.391852,42.25377],"type":"Point"}
}