{
  "type": "Feature",
  "properties": {
    "iso:country":"US",
    "sg:address":"24000 Research Dr",
    "sg:city":"Farmington Hills",
    "sg:classifiers":[
        {
            "category":"Manufacturing",
            "subcategory":"Printing",
            "type":"Manufacturing & Wholesale Goods"
        }
    ],
    "sg:phone":"+1 248 478 9200",
    "sg:postcode":"48335",
    "sg:province":"MI",
    "sg:tags":[
        "publisher"
    ],
    "wof:name":"Rex Publishing Co Inc",
    "wof:placetype":"venue"
},
  "geometry": {"coordinates":[-83.427243,42.467992],"type":"Point"}
}