{
  "type": "Feature",
  "properties": {
    "iso:country":"US",
    "sg:address":"27701 Aberdeen St",
    "sg:city":"Southfield",
    "sg:classifiers":[
        {
            "category":"Professional",
            "subcategory":"Secretarial Services",
            "type":"Services"
        }
    ],
    "sg:phone":"+1 248 569 1784",
    "sg:postcode":"48076",
    "sg:province":"MI",
    "sg:tags":[
        "reporting",
        "court"
    ],
    "wof:name":"Direct Express",
    "wof:placetype":"venue"
},
  "geometry": {"coordinates":[-83.209451,42.494871],"type":"Point"}
}