{
  "type": "Feature",
  "properties": {
    "iso:country":"US",
    "sg:address":"2345 Jarco Dr",
    "sg:city":"Holt",
    "sg:classifiers":[
        {
            "category":"Building & Trades",
            "subcategory":"Electrical",
            "type":"Services"
        }
    ],
    "sg:phone":"+1 517 694 8700",
    "sg:postcode":"48842",
    "sg:province":"MI",
    "sg:tags":[
        "electric",
        "contractor"
    ],
    "wof:name":"Quality Electric Inc",
    "wof:placetype":"venue"
},
  "geometry": {"coordinates":[-84.51176700000001,42.648874],"type":"Point"}
}