{
  "type": "Feature",
  "properties": {
    "iso:country":"US",
    "sg:address":"1763 Weber Rd",
    "sg:city":"Gladwin",
    "sg:classifiers":[
        {
            "category":"Wholesale",
            "subcategory":"Meat",
            "type":"Manufacturing & Wholesale Goods"
        }
    ],
    "sg:phone":"+1 989 426 7754",
    "sg:postcode":"48624",
    "sg:province":"MI",
    "sg:tags":[
        "butchering"
    ],
    "wof:name":"Kenny's Kustom Kuts",
    "wof:placetype":"venue"
},
  "geometry": {"coordinates":[-84.435726,43.987196],"type":"Point"}
}