{
  "type": "Feature",
  "properties": {
    "iso:country":"US",
    "sg:address":"35034 Automation Dr",
    "sg:city":"Clinton Twp",
    "sg:classifiers":[
        {
            "category":"Manufacturing",
            "subcategory":"Tools & Machinery",
            "type":"Manufacturing & Wholesale Goods"
        }
    ],
    "sg:phone":"+1 586 792 1266",
    "sg:postcode":"48035",
    "sg:province":"MI",
    "sg:tags":[
        "machine",
        "shop"
    ],
    "wof:name":"K & M Tool Inc",
    "wof:placetype":"venue"
},
  "geometry": {"coordinates":[-82.883855,42.558385],"type":"Point"}
}