{
  "type": "Feature",
  "properties": {
    "iso:country":"US",
    "sg:address":"305 E Midland St",
    "sg:city":"Bay City",
    "sg:classifiers":[
        {
            "category":"Wholesale",
            "subcategory":"Office Equipment",
            "type":"Manufacturing & Wholesale Goods"
        },
        {
            "category":"Shopping",
            "type":"Retail Goods"
        }
    ],
    "sg:phone":"+1 989 895 8662",
    "sg:postcode":"48706",
    "sg:province":"MI",
    "sg:tags":[
        "machine",
        "register",
        "cash",
        "supply"
    ],
    "wof:name":"Northern Business Machines Co",
    "wof:placetype":"venue"
},
  "geometry": {"coordinates":[-83.903409,43.602183],"type":"Point"}
}