{
  "type": "Feature",
  "properties": {
    "iso:country":"US",
    "sg:address":"4501 Camden Ave",
    "sg:city":"Flint",
    "sg:classifiers":[
        {
            "category":"Education",
            "subcategory":"School",
            "type":"Public Place"
        }
    ],
    "sg:phone":"+1 810 760 1610",
    "sg:postcode":"48507",
    "sg:province":"MI",
    "sg:tags":[
        "middle"
    ],
    "wof:name":"Mc Kinley Middle School",
    "wof:placetype":"venue"
},
  "geometry": {"coordinates":[-83.687977,42.982986],"type":"Point"}
}