{
  "type": "Feature",
  "properties": {
    "iso:country":"US",
    "sg:address":"83904 Co Rd 687",
    "sg:city":"Hartford",
    "sg:classifiers":[
        {
            "category":"Professional",
            "subcategory":"Management & Consulting",
            "type":"Services"
        }
    ],
    "sg:phone":"+1 269 621 4746",
    "sg:postcode":"49057",
    "sg:province":"MI",
    "sg:tags":[
        "business"
    ],
    "wof:name":"Hartford Driver Testing",
    "wof:placetype":"venue"
},
  "geometry": {"coordinates":[-86.166375,42.114898],"type":"Point"}
}