{
  "type": "Feature",
  "properties": {
    "iso:country":"US",
    "sg:address":"41486 Tompkins St",
    "sg:city":"Belleville",
    "sg:classifiers":[
        {
            "category":"Professional",
            "type":"Services"
        }
    ],
    "sg:phone":"+1 734 699 7065",
    "sg:postcode":"48111",
    "sg:province":"MI",
    "wof:name":"Country Time",
    "wof:placetype":"venue"
},
  "geometry": {"coordinates":[-83.448145,42.228663],"type":"Point"}
}