{
  "type": "Feature",
  "properties": {
    "iso:country":"US",
    "sg:address":"1645 E Avis Dr",
    "sg:city":"Madison Heights",
    "sg:classifiers":[
        {
            "category":"Retail",
            "subcategory":"Repair Shop",
            "type":"Services"
        }
    ],
    "sg:phone":"+1 248 589 4700",
    "sg:postcode":"48071",
    "sg:province":"MI",
    "sg:tags":[
        "technology",
        "sales"
    ],
    "sg:website":"www.metropolitanoffice.com",
    "wof:name":"Metro Imaging Systems",
    "wof:placetype":"venue"
},
  "geometry": {"coordinates":[-83.086917,42.528408],"type":"Point"}
}