{
  "type": "Feature",
  "properties": {
    "iso:country":"US",
    "sg:address":"28897 Augusta",
    "sg:city":"Farmington",
    "sg:classifiers":[
        {
            "category":"Professional",
            "subcategory":"Management & Consulting",
            "type":"Services"
        }
    ],
    "sg:phone":"+1 248 553 9358",
    "sg:postcode":"48331",
    "sg:province":"MI",
    "sg:tags":[
        "business"
    ],
    "wof:name":"Cricklewood Associates LLC",
    "wof:placetype":"venue"
},
  "geometry": {"coordinates":[-83.419871,42.50744],"type":"Point"}
}