{
  "type": "Feature",
  "properties": {
    "iso:country":"US",
    "sg:address":"423 S 4th Ave",
    "sg:city":"Saginaw",
    "sg:classifiers":[
        {
            "category":"Professional",
            "subcategory":"Computer Services",
            "type":"Services"
        }
    ],
    "sg:phone":"+1 989 754 9034",
    "sg:postcode":"48601",
    "sg:province":"MI",
    "sg:tags":[
        "datum"
    ],
    "wof:name":"Genisys Graphics",
    "wof:placetype":"venue"
},
  "geometry": {"coordinates":[-83.927528,43.425679],"type":"Point"}
}