{
  "type": "Feature",
  "properties": {
    "iso:country":"US",
    "sg:address":"3931 Eastern Ave SE",
    "sg:city":"Grand Rapids",
    "sg:classifiers":[
        {
            "category":"Retail",
            "subcategory":"Auto Repair",
            "type":"Services"
        }
    ],
    "sg:phone":"+1 616 247 4611",
    "sg:postcode":"49508",
    "sg:province":"MI",
    "sg:tags":[
        "repairing",
        "automobile"
    ],
    "wof:name":"A J's Auto",
    "wof:placetype":"venue"
},
  "geometry": {"coordinates":[-85.645985,42.891725],"type":"Point"}
}