{
  "type": "Feature",
  "properties": {
    "iso:country":"US",
    "sg:address":"1119 Vos St",
    "sg:city":"Jenison",
    "sg:classifiers":[
        {
            "category":"Social Services",
            "subcategory":"Child Care",
            "type":"Services"
        }
    ],
    "sg:phone":"+1 616 667 1795",
    "sg:postcode":"49428",
    "sg:province":"MI",
    "sg:tags":[
        "day"
    ],
    "wof:name":"Jody Grabill",
    "wof:placetype":"venue"
},
  "geometry": {"coordinates":[-85.80918800000001,42.899433],"type":"Point"}
}