{
  "type": "Feature",
  "properties": {
    "iso:country":"US",
    "sg:address":"1875 West Rd",
    "sg:city":"Trenton",
    "sg:classifiers":[
        {
            "category":"Autos & Motor Vehicles",
            "subcategory":"Fuel & Gas Station",
            "type":"Retail Goods"
        }
    ],
    "sg:phone":"+1 734 675 1750",
    "sg:postcode":"48183",
    "sg:province":"MI",
    "wof:name":"King's Mobil Mart",
    "wof:placetype":"venue"
},
  "geometry": {"coordinates":[-83.190804,42.141399],"type":"Point"}
}