{
  "type": "Feature",
  "properties": {
    "iso:country":"US",
    "sg:address":"601 Ditmar Ave",
    "sg:city":"Pontiac",
    "sg:classifiers":[
        {
            "category":"Social Services",
            "subcategory":"Child Care",
            "type":"Services"
        }
    ],
    "sg:phone":"+1 248 454 9589",
    "sg:postcode":"48341",
    "sg:province":"MI",
    "sg:tags":[
        "day"
    ],
    "wof:name":"Mona Baylor Gretel",
    "wof:placetype":"venue"
},
  "geometry": {"coordinates":[-83.295491,42.612355],"type":"Point"}
}