{
  "type": "Feature",
  "properties": {
    "iso:country":"US",
    "sg:address":"2215 44th St SW",
    "sg:city":"Wyoming",
    "sg:classifiers":[
        {
            "category":"Health Services",
            "subcategory":"Doctor",
            "type":"Services"
        }
    ],
    "sg:phone":"+1 616 252 8300",
    "sg:postcode":"49519",
    "sg:province":"MI",
    "sg:tags":[
        "physician",
        "surgeon"
    ],
    "wof:name":"Metro Health Pediatrics",
    "wof:placetype":"venue"
},
  "geometry": {"coordinates":[-85.72179,42.884759],"type":"Point"}
}