{
  "type": "Feature",
  "properties": {
    "iso:country":"US",
    "sg:address":"500 Andre St",
    "sg:city":"Bay City",
    "sg:classifiers":[
        {
            "category":"Bus Charters",
            "type":"Transportation"
        }
    ],
    "sg:phone":"+1 989 684 2400",
    "sg:postcode":"48706",
    "sg:province":"MI",
    "sg:tags":[
        "rental"
    ],
    "wof:name":"Mitchell Motorcoach LTD",
    "wof:placetype":"venue"
},
  "geometry": {"coordinates":[-83.86939,43.619423],"type":"Point"}
}