{
  "type": "Feature",
  "properties": {
    "iso:country":"US",
    "sg:address":"7843 N Unionville Rd",
    "sg:city":"Unionville",
    "sg:classifiers":[
        {
            "category":"Food & Beverages",
            "subcategory":"Meat & Fish",
            "type":"Retail Goods"
        }
    ],
    "sg:phone":"+1 989 883 3356",
    "sg:postcode":"48767",
    "sg:province":"MI",
    "sg:tags":[
        "seafood"
    ],
    "wof:name":"Jahrs Fish Co",
    "wof:placetype":"venue"
},
  "geometry": {"coordinates":[-83.46616400000001,43.684092],"type":"Point"}
}