{
  "type": "Feature",
  "properties": {
    "iso:country":"US",
    "sg:address":"15490 Oak Ridge Dr",
    "sg:city":"Spring Lake",
    "sg:classifiers":[
        {
            "category":"Professional",
            "subcategory":"Management & Consulting",
            "type":"Services"
        }
    ],
    "sg:phone":"+1 616 296 0770",
    "sg:postcode":"49456",
    "sg:province":"MI",
    "wof:name":"Renaissance Spirit Consulting",
    "wof:placetype":"venue"
},
  "geometry": {"coordinates":[-86.17058900000001,43.071763],"type":"Point"}
}