{
  "type": "Feature",
  "properties": {
    "iso:country":"US",
    "sg:address":"11057 N Shore Dr",
    "sg:city":"Lake",
    "sg:classifiers":[
        {
            "category":"Banks & Credit Unions",
            "subcategory":"Investment Brokerage",
            "type":"Services"
        }
    ],
    "sg:phone":"+1 989 544 2759",
    "sg:postcode":"48622",
    "sg:province":"MI",
    "wof:name":"HFP Investments",
    "wof:placetype":"venue"
},
  "geometry": {"coordinates":[-85.06871599999999,43.847477],"type":"Point"}
}