{
  "type": "Feature",
  "properties": {
    "iso:country":"US",
    "sg:address":"923 Smith St",
    "sg:city":"Algonac",
    "sg:classifiers":[
        {
            "category":"Building & Trades",
            "subcategory":"Construction",
            "type":"Services"
        }
    ],
    "sg:phone":"+1 810 794 4161",
    "sg:postcode":"48001",
    "sg:province":"MI",
    "sg:tags":[
        "house"
    ],
    "wof:name":"Polar Insulation & Cnstr",
    "wof:placetype":"venue"
},
  "geometry": {"coordinates":[-82.53821499999999,42.62412],"type":"Point"}
}