{
  "type": "Feature",
  "properties": {
    "iso:country":"US",
    "sg:address":"3011 E Empire Ave",
    "sg:city":"Benton Harbor",
    "sg:classifiers":[
        {
            "category":"Building & Trades",
            "subcategory":"Landscaping Services",
            "type":"Services"
        }
    ],
    "sg:phone":"+1 269 925 8375",
    "sg:postcode":"49022",
    "sg:province":"MI",
    "wof:name":"Scotts Lawn Service",
    "wof:placetype":"venue"
},
  "geometry": {"coordinates":[-86.379783,42.101502],"type":"Point"}
}