{
  "type": "Feature",
  "properties": {
    "iso:country":"US",
    "sg:address":"1427 Robinson Rd SE",
    "sg:city":"Grand Rapids",
    "sg:classifiers":[
        {
            "category":"Personal",
            "subcategory":"Beauty Salon",
            "type":"Services"
        }
    ],
    "sg:phone":"+1 616 458 2740",
    "sg:postcode":"49506",
    "sg:province":"MI",
    "sg:tags":[
        "shop"
    ],
    "wof:name":"Eastowne Salon",
    "wof:placetype":"venue"
},
  "geometry": {"coordinates":[-85.633431,42.957775],"type":"Point"}
}