{
  "type": "Feature",
  "properties": {
    "iso:country":"US",
    "sg:address":"163 Potter Dr",
    "sg:city":"Belleville",
    "sg:classifiers":[
        {
            "category":"Autos & Motor Vehicles",
            "subcategory":"Automobile Sales",
            "type":"Retail Goods"
        }
    ],
    "sg:phone":"+1 734 697 7218",
    "sg:postcode":"48111",
    "sg:province":"MI",
    "sg:tags":[
        "new",
        "car"
    ],
    "wof:name":"V T Automotive",
    "wof:placetype":"venue"
},
  "geometry": {"coordinates":[-83.47563,42.21277],"type":"Point"}
}