{
  "type": "Feature",
  "properties": {
    "iso:country":"US",
    "sg:address":"40 44th St SW",
    "sg:city":"Grand Rapids",
    "sg:classifiers":[
        {
            "category":"Retail",
            "subcategory":"Auto Repair",
            "type":"Services"
        }
    ],
    "sg:phone":"+1 616 532 8300",
    "sg:postcode":"49548",
    "sg:province":"MI",
    "sg:tags":[
        "engine"
    ],
    "wof:name":"Superior Engine Rebuilders",
    "wof:placetype":"venue"
},
  "geometry": {"coordinates":[-85.66661000000001,42.883946],"type":"Point"}
}