{
  "type": "Feature",
  "properties": {
    "iso:country":"US",
    "sg:address":"2506 Woodward Ave",
    "sg:city":"Bloomfield Hills",
    "sg:classifiers":[
        {
            "category":"Retail",
            "subcategory":"Laundry & Dry Cleaning",
            "type":"Services"
        }
    ],
    "sg:phone":"+1 248 338 9858",
    "sg:postcode":"48301",
    "sg:province":"MI",
    "wof:name":"Two Eighty Nine Cleaners",
    "wof:placetype":"venue"
},
  "geometry": {"coordinates":[-83.285202,42.5448],"type":"Point"}
}