{
  "type": "Feature",
  "properties": {
    "iso:country":"US",
    "sg:address":"341 Beaux Rivages Dr",
    "sg:city":"Harbor Springs",
    "sg:classifiers":[
        {
            "category":"Building & Trades",
            "subcategory":"Construction",
            "type":"Services"
        }
    ],
    "sg:phone":"+1 231 526 9629",
    "sg:postcode":"49740",
    "sg:province":"MI",
    "sg:tags":[
        "house"
    ],
    "wof:name":"Mann Construction",
    "wof:placetype":"venue"
},
  "geometry": {"coordinates":[-84.901856,45.490325],"type":"Point"}
}