{
  "type": "Feature",
  "properties": {
    "iso:country":"US",
    "sg:address":"5792 Lewis Ave",
    "sg:city":"Ida",
    "sg:classifiers":[
        {
            "category":"Food & Beverages",
            "subcategory":"Liquor & Beverages",
            "type":"Retail Goods"
        },
        {
            "category":"Restaurant",
            "type":"Food & Drink"
        }
    ],
    "sg:phone":"+1 734 269 6789",
    "sg:postcode":"48140",
    "sg:province":"MI",
    "wof:name":"Lewis Pizza & Mawsallys Liquor",
    "wof:placetype":"venue"
},
  "geometry": {"coordinates":[-83.571776,41.870825],"type":"Point"}
}