{
  "type": "Feature",
  "properties": {
    "iso:country":"US",
    "sg:address":"421 Arlington Street",
    "sg:city":"Birmingham",
    "sg:classifiers":[
        {
            "category":"Personal",
            "type":"Services"
        }
    ],
    "sg:phone":"+1 248 723 1589",
    "sg:postcode":"48009",
    "sg:province":"MI",
    "sg:tags":[
        "local"
    ],
    "sg:website":"simplycandids.com",
    "wof:name":"Simply Candids Photography",
    "wof:placetype":"venue"
},
  "geometry": {"coordinates":[-83.230431,42.543458],"type":"Point"}
}