{
  "type": "Feature",
  "properties": {
    "iso:country":"US",
    "sg:address":"341 E Huron St",
    "sg:city":"Ann Arbor",
    "sg:classifiers":[
        {
            "category":"Deli",
            "type":"Food & Drink"
        }
    ],
    "sg:menulink":"http://www.allmenus.com/mi/ann-arbor/17559-ahmos-gyros--deli/menu/",
    "sg:phone":"+1 734 662 4445",
    "sg:postcode":"48104",
    "sg:province":"MI",
    "sg:tags":[
        "pita",
        "american",
        "sandwich"
    ],
    "wof:name":"Ahmo's Gyros & Deli",
    "wof:placetype":"venue"
},
  "geometry": {"coordinates":[-83.744963,42.281348],"type":"Point"}
}