{
  "type": "Feature",
  "properties": {
    "iso:country":"US",
    "sg:address":"1335 S University Ave",
    "sg:city":"Ann Arbor",
    "sg:classifiers":[
        {
            "category":"Real Estate",
            "subcategory":"Real Estate Operator",
            "type":"Services"
        }
    ],
    "sg:phone":"+1 734 665 8825",
    "sg:postcode":"48104",
    "sg:province":"MI",
    "sg:tags":[
        "building",
        "ope",
        "apartment",
        "nonresidential"
    ],
    "wof:name":"Campus Rentals",
    "wof:placetype":"venue"
},
  "geometry": {"coordinates":[-83.73139999999999,42.275122],"type":"Point"}
}