{
  "type": "Feature",
  "properties": {
    "iso:country":"US",
    "sg:address":"6950 Anna Dr",
    "sg:city":"Belleville",
    "sg:classifiers":[
        {
            "category":"Wholesale",
            "subcategory":"Auto Parts",
            "type":"Manufacturing & Wholesale Goods"
        }
    ],
    "sg:phone":"+1 734 397 4891",
    "sg:postcode":"48111",
    "sg:province":"MI",
    "sg:tags":[
        "distributor"
    ],
    "wof:name":"Springs International",
    "wof:placetype":"venue"
},
  "geometry": {"coordinates":[-83.463386,42.251689],"type":"Point"}
}