{
  "type": "Feature",
  "properties": {
    "iso:country":"US",
    "sg:address":"502 Randolph St",
    "sg:city":"Detroit",
    "sg:classifiers":[
        {
            "category":"Personal",
            "subcategory":"Day Spa",
            "type":"Services"
        }
    ],
    "sg:phone":"+1 313 965 3004",
    "sg:postcode":"48226",
    "sg:province":"MI",
    "wof:name":"De'spa Elite",
    "wof:placetype":"venue"
},
  "geometry": {"coordinates":[-83.04235199999999,42.330697],"type":"Point"}
}