{
  "type": "Feature",
  "properties": {
    "iso:country":"US",
    "sg:address":"37640 W 12 Mile Rd",
    "sg:city":"Farmington Hills",
    "sg:classifiers":[
        {
            "category":"Personal",
            "subcategory":"Beauty Salon",
            "type":"Services"
        }
    ],
    "sg:phone":"+1 248 489 9510",
    "sg:postcode":"48331",
    "sg:province":"MI",
    "sg:tags":[
        "hair"
    ],
    "sg:website":"numbersixsalon.com/",
    "wof:name":"Number Six Salon",
    "wof:placetype":"venue"
},
  "geometry": {"coordinates":[-83.41939600000001,42.497761],"type":"Point"}
}