{
  "type": "Feature",
  "properties": {
    "iso:country":"US",
    "sg:address":"17950 E 14 Mile Rd",
    "sg:city":"Fraser",
    "sg:classifiers":[
        {
            "category":"Home & Garden",
            "subcategory":"Building Materials",
            "type":"Retail Goods"
        }
    ],
    "sg:phone":"+1 586 294 8300",
    "sg:postcode":"48026",
    "sg:province":"MI",
    "sg:tags":[
        "equipment",
        "fixture",
        "lighting"
    ],
    "sg:website":"www.madisonelectric.com",
    "wof:name":"Madison Electronics Div",
    "wof:placetype":"venue"
},
  "geometry": {"coordinates":[-82.93707999999999,42.539168],"type":"Point"}
}