{
  "type": "Feature",
  "properties": {
    "iso:country":"US",
    "sg:address":"1218 9th St",
    "sg:city":"Port Huron",
    "sg:classifiers":[
        {
            "category":"Professional",
            "subcategory":"Business Services",
            "type":"Services"
        }
    ],
    "sg:phone":"+1 810 985 4283",
    "sg:postcode":"48060",
    "sg:province":"MI",
    "sg:tags":[
        "appraiser"
    ],
    "wof:name":"KANE Appraisal",
    "wof:placetype":"venue"
},
  "geometry": {"coordinates":[-82.43086700000001,42.971393],"type":"Point"}
}