{
  "type": "Feature",
  "properties": {
    "iso:country":"US",
    "sg:address":"9827 S M 43 Hwy",
    "sg:city":"Delton",
    "sg:classifiers":[
        {
            "category":"Personal",
            "subcategory":"Beauty Salon",
            "type":"Services"
        }
    ],
    "sg:phone":"+1 269 623 2152",
    "sg:postcode":"49046",
    "sg:province":"MI",
    "wof:name":"Be Original Hair Salon",
    "wof:placetype":"venue"
},
  "geometry": {"coordinates":[-85.408452,42.511876],"type":"Point"}
}