{
  "type": "Feature",
  "properties": {
    "iso:country":"US",
    "sg:address":"1047 Oakdale St SE",
    "sg:city":"Grand Rapids",
    "sg:classifiers":[
        {
            "category":"Building & Trades",
            "subcategory":"Construction",
            "type":"Services"
        }
    ],
    "sg:phone":"+1 616 245 0182",
    "sg:postcode":"49507",
    "sg:province":"MI",
    "sg:tags":[
        "hanging",
        "contractor"
    ],
    "wof:name":"Falcon Painting & Decorator",
    "wof:placetype":"venue"
},
  "geometry": {"coordinates":[-85.641593,42.937261],"type":"Point"}
}