{
  "type": "Feature",
  "properties": {
    "iso:country":"US",
    "sg:address":"9375 N Territorial Rd",
    "sg:city":"Dexter",
    "sg:classifiers":[
        {
            "category":"Retail",
            "subcategory":"Auto Repair",
            "type":"Services"
        }
    ],
    "sg:phone":"+1 734 424 0579",
    "sg:postcode":"48130",
    "sg:province":"MI",
    "sg:tags":[
        "general"
    ],
    "wof:name":"DC Automotive Specialists",
    "wof:placetype":"venue"
},
  "geometry": {"coordinates":[-83.917314,42.387426],"type":"Point"}
}