{
  "type": "Feature",
  "properties": {
    "iso:country":"US",
    "sg:address":"760 E Michigan Ave",
    "sg:city":"Saline",
    "sg:classifiers":[
        {
            "category":"Restaurant",
            "type":"Food & Drink"
        }
    ],
    "sg:menulink":"http://www.allmenus.com/mi/saline/182566-wendys/menu/",
    "sg:phone":"+1 734 944 0044",
    "sg:postcode":"48176",
    "sg:province":"MI",
    "sg:tags":[
        "burger",
        "american",
        "soup"
    ],
    "wof:name":"Wendy's",
    "wof:placetype":"venue"
},
  "geometry": {"coordinates":[-83.76621900000001,42.173299],"type":"Point"}
}