{
  "type": "Feature",
  "properties": {
    "iso:country":"US",
    "sg:address":"1414 Industrial St",
    "sg:city":"Dearborn",
    "sg:classifiers":[
        {
            "category":"Retail",
            "subcategory":"Auto Repair",
            "type":"Services"
        }
    ],
    "sg:phone":"+1 313 841 3457",
    "sg:postcode":"48120",
    "sg:province":"MI",
    "sg:tags":[
        "rack",
        "torque",
        "converter",
        "pinion"
    ],
    "wof:name":"PHD Convertors Inc",
    "wof:placetype":"venue"
},
  "geometry": {"coordinates":[-83.14534,42.297524],"type":"Point"}
}