{
  "type": "Feature",
  "properties": {
    "iso:country":"US",
    "sg:address":"305 E Northport St",
    "sg:city":"Walled Lake",
    "sg:classifiers":[
        {
            "category":"Insurance",
            "subcategory":"Insurance Agent",
            "type":"Services"
        }
    ],
    "sg:phone":"+1 248 446 3300",
    "sg:postcode":"48390",
    "sg:province":"MI",
    "wof:name":"KMA Inc",
    "wof:placetype":"venue"
},
  "geometry": {"coordinates":[-83.482384,42.533088],"type":"Point"}
}