{
  "type": "Feature",
  "properties": {
    "iso:country":"US",
    "sg:address":"30960 Ford Rd",
    "sg:city":"Garden City",
    "sg:classifiers":[
        {
            "category":"Personal",
            "subcategory":"Tattoo Parlor",
            "type":"Services"
        },
        {
            "category":"Personal",
            "subcategory":"Piercing",
            "type":"Services"
        }
    ],
    "sg:phone":"+1 734 261 7944",
    "sg:postcode":"48135",
    "sg:province":"MI",
    "sg:website":"www.myspace.com/inkaddictiontattoos",
    "wof:name":"Ink Addiction",
    "wof:placetype":"venue"
},
  "geometry": {"coordinates":[-83.346728,42.325347],"type":"Point"}
}