{
  "type": "Feature",
  "properties": {
    "iso:country":"US",
    "sg:address":"1754 W Norton Ave",
    "sg:city":"Muskegon",
    "sg:classifiers":[
        {
            "category":"Building & Trades",
            "subcategory":"Electrical",
            "type":"Services"
        }
    ],
    "sg:phone":"+1 231 759 4119",
    "sg:postcode":"49441",
    "sg:province":"MI",
    "sg:tags":[
        "electric",
        "contractor"
    ],
    "wof:name":"Jerrys Electric",
    "wof:placetype":"venue"
},
  "geometry": {"coordinates":[-86.286783,43.190967],"type":"Point"}
}