{
  "type": "Feature",
  "properties": {
    "iso:country":"US",
    "sg:address":"2100 O'Connor Dr",
    "sg:city":"Mount Pleasant",
    "sg:classifiers":[
        {
            "category":"Building & Trades",
            "subcategory":"Construction",
            "type":"Services"
        }
    ],
    "sg:phone":"+1 989 773 5557",
    "sg:postcode":"48858",
    "sg:province":"MI",
    "sg:tags":[
        "house"
    ],
    "wof:name":"Terry Lyon Builder",
    "wof:placetype":"venue"
},
  "geometry": {"coordinates":[-84.951967,43.625029],"type":"Point"}
}