{
  "type": "Feature",
  "properties": {
    "iso:country":"US",
    "sg:address":"514 Huron St",
    "sg:city":"South Haven",
    "sg:classifiers":[
        {
            "category":"Coffee & Tea",
            "type":"Food & Drink"
        }
    ],
    "sg:menulink":"http://www.allmenus.com/mi/south-haven/121520-the-coffee-beanery/menu/",
    "sg:phone":"+1 269 637 8655",
    "sg:postcode":"49090",
    "sg:province":"MI",
    "sg:tags":[
        "american",
        "diner"
    ],
    "wof:name":"The Coffee Beanery",
    "wof:placetype":"venue"
},
  "geometry": {"coordinates":[-86.272621,42.401923],"type":"Point"}
}