{
  "type": "Feature",
  "properties": {
    "iso:country":"US",
    "sg:address":"3800 Grand River Ave",
    "sg:city":"Detroit",
    "sg:classifiers":[
        {
            "category":"Retail",
            "subcategory":"Veterinary Services",
            "type":"Services"
        },
        {
            "category":"Retail",
            "subcategory":"Pet Boarding",
            "type":"Services"
        }
    ],
    "sg:phone":"+1 313 832 7282",
    "sg:postcode":"48208",
    "sg:province":"MI",
    "sg:tags":[
        "veterinarian",
        "boarding/pet",
        "sitting"
    ],
    "wof:name":"Patterson Dog and Cat Hospital Inc",
    "wof:placetype":"venue"
},
  "geometry": {"coordinates":[-83.074997,42.342999],"type":"Point"}
}