{
  "type": "Feature",
  "properties": {
    "iso:country":"US",
    "sg:address":"106 S Cochran Ave",
    "sg:city":"Charlotte",
    "sg:classifiers":[
        {
            "category":"Shopping",
            "subcategory":"Jewelry",
            "type":"Retail Goods"
        }
    ],
    "sg:phone":"+1 517 543 6531",
    "sg:postcode":"48813",
    "sg:province":"MI",
    "sg:tags":[
        "jeweler"
    ],
    "wof:name":"Carl V Reck Jewelers",
    "wof:placetype":"venue"
},
  "geometry": {"coordinates":[-84.83595699999999,42.563869],"type":"Point"}
}