{
  "type": "Feature",
  "properties": {
    "iso:country":"US",
    "sg:address":"762 W Main St",
    "sg:city":"Kalamazoo",
    "sg:classifiers":[
        {
            "category":"Restaurant",
            "type":"Food & Drink"
        }
    ],
    "sg:menulink":"http://www.allmenus.com/mi/kalamazoo/272654-pasta-pasta/menu/",
    "sg:phone":"+1 269 345 6755",
    "sg:postcode":"49006",
    "sg:province":"MI",
    "sg:tags":[
        "italian"
    ],
    "wof:name":"Pasta Pasta",
    "wof:placetype":"venue"
},
  "geometry": {"coordinates":[-85.594087,42.291603],"type":"Point"}
}