{
  "type": "Feature",
  "properties": {
    "iso:country":"US",
    "sg:address":"2215 S 124th Ave",
    "sg:city":"Shelby",
    "sg:phone":"+1 231 861 4717",
    "sg:postcode":"49455",
    "sg:province":"MI",
    "sg:tags":[
        "farm",
        "field",
        "crop"
    ],
    "wof:name":"Don Baron",
    "wof:placetype":"venue"
},
  "geometry": {"coordinates":[-86.248288,43.603108],"type":"Point"}
}