{
  "type": "Feature",
  "properties": {
    "iso:country":"US",
    "sg:address":"1374 Thorn Ridge Dr",
    "sg:city":"Howell",
    "sg:classifiers":[
        {
            "category":"Home & Garden",
            "subcategory":"Carpets & Floor Coverings",
            "type":"Retail Goods"
        }
    ],
    "sg:phone":"+1 517 552 6200",
    "sg:postcode":"48843",
    "sg:province":"MI",
    "sg:tags":[
        "material"
    ],
    "wof:name":"P M Commercial Flooring Inc",
    "wof:placetype":"venue"
},
  "geometry": {"coordinates":[-83.780512,42.624514],"type":"Point"}
}