{
  "type": "Feature",
  "properties": {
    "iso:country":"US",
    "sg:address":"27083 Woodward Ave",
    "sg:city":"Berkley",
    "sg:classifiers":[
        {
            "category":"Wholesale",
            "subcategory":"Construction Materials",
            "type":"Manufacturing & Wholesale Goods"
        }
    ],
    "sg:phone":"+1 248 539 2272",
    "sg:postcode":"48072",
    "sg:province":"MI",
    "sg:tags":[
        "fence"
    ],
    "wof:name":"Action Fence Of Michigan",
    "wof:placetype":"venue"
},
  "geometry": {"coordinates":[-83.15975,42.490266],"type":"Point"}
}