{
  "type": "Feature",
  "properties": {
    "iso:country":"US",
    "sg:address":"525 Judd Rd",
    "sg:city":"Saline",
    "sg:classifiers":[
        {
            "category":"Professional",
            "subcategory":"Management & Consulting",
            "type":"Services"
        }
    ],
    "sg:phone":"+1 734 944 6643",
    "sg:postcode":"48176",
    "sg:province":"MI",
    "sg:tags":[
        "business"
    ],
    "wof:name":"Goyarts Consulting Svcs",
    "wof:placetype":"venue"
},
  "geometry": {"coordinates":[-83.73064599999999,42.141263],"type":"Point"}
}