{
  "type": "Feature",
  "properties": {
    "iso:country":"US",
    "sg:address":"3575 Francis St",
    "sg:city":"Jackson",
    "sg:classifiers":[
        {
            "category":"Restaurant",
            "type":"Food & Drink"
        }
    ],
    "sg:phone":"+1 517 783 0898",
    "sg:postcode":"49203",
    "sg:province":"MI",
    "sg:tags":[
        "banquet",
        "rooms"
    ],
    "sg:website":"www.genedavisandsons.com",
    "wof:name":"Gene Davis & Sons Catering",
    "wof:placetype":"venue"
},
  "geometry": {"coordinates":[-84.398107,42.211649],"type":"Point"}
}