{
  "type": "Feature",
  "properties": {
    "iso:country":"US",
    "sg:address":"8716 Van Dyke St",
    "sg:city":"Detroit",
    "sg:classifiers":[
        {
            "category":"Food & Beverages",
            "subcategory":"Liquor & Beverages",
            "type":"Retail Goods"
        }
    ],
    "sg:phone":"+1 313 922 2230",
    "sg:postcode":"48213",
    "sg:province":"MI",
    "sg:tags":[
        "beer",
        "spirit",
        "wine"
    ],
    "wof:name":"Super Star Party Shop",
    "wof:placetype":"venue"
},
  "geometry": {"coordinates":[-83.022499,42.392601],"type":"Point"}
}