{
  "type": "Feature",
  "properties": {
    "iso:country":"US",
    "sg:address":"2450 Old Novi Rd",
    "sg:city":"Novi",
    "sg:classifiers":[
        {
            "category":"Insurance",
            "subcategory":"Insurance Agent",
            "type":"Services"
        }
    ],
    "sg:phone":"+1 248 926 8940",
    "sg:postcode":"48377",
    "sg:province":"MI",
    "wof:name":"Maynes Services",
    "wof:placetype":"venue"
},
  "geometry": {"coordinates":[-83.47683000000001,42.506208],"type":"Point"}
}