{
  "type": "Feature",
  "properties": {
    "iso:country":"US",
    "sg:address":"3025 Bass Lake Rd",
    "sg:city":"Iron Mountain",
    "sg:classifiers":[
        {
            "category":"Building & Trades",
            "subcategory":"Construction",
            "type":"Services"
        }
    ],
    "sg:phone":"+1 906 774 7809",
    "sg:postcode":"49801",
    "sg:province":"MI",
    "sg:tags":[
        "home",
        "builder"
    ],
    "wof:name":"Bass Lake Home",
    "wof:placetype":"venue"
},
  "geometry": {"coordinates":[-88.068721,45.857086],"type":"Point"}
}