{
  "type": "Feature",
  "properties": {
    "iso:country":"US",
    "sg:address":"314 E Center St",
    "sg:city":"Alma",
    "sg:classifiers":[
        {
            "category":"Wholesale",
            "subcategory":"Toys & Hobbies",
            "type":"Manufacturing & Wholesale Goods"
        }
    ],
    "sg:phone":"+1 989 466 2606",
    "sg:postcode":"48801",
    "sg:province":"MI",
    "sg:tags":[
        "wholesaler"
    ],
    "wof:name":"Don's Wholesale LLC",
    "wof:placetype":"venue"
},
  "geometry": {"coordinates":[-84.65725399999999,43.377582],"type":"Point"}
}