{
  "type": "Feature",
  "properties": {
    "iso:country":"US",
    "sg:address":"3050 Fruit Ridge Ave NW",
    "sg:city":"Grand Rapids",
    "sg:classifiers":[
        {
            "category":"Autos & Motor Vehicles",
            "subcategory":"Fuel & Gas Station",
            "type":"Retail Goods"
        }
    ],
    "sg:phone":"+1 616 784 5881",
    "sg:postcode":"49544",
    "sg:province":"MI",
    "sg:tags":[
        "oil"
    ],
    "wof:name":"Fruit Ridge Citgo",
    "wof:placetype":"venue"
},
  "geometry": {"coordinates":[-85.763302,43.020659],"type":"Point"}
}