{
  "type": "Feature",
  "properties": {
    "iso:country":"US",
    "sg:address":"9946 Cherry Valley Ave SE",
    "sg:city":"Caledonia",
    "sg:classifiers":[
        {
            "category":"Arts & Performance",
            "subcategory":"Theater",
            "type":"Entertainment"
        }
    ],
    "sg:phone":"+1 616 891 6069",
    "sg:postcode":"49316",
    "sg:province":"MI",
    "sg:tags":[
        "entertainer",
        "business"
    ],
    "wof:name":"J & J Entertainment",
    "wof:placetype":"venue"
},
  "geometry": {"coordinates":[-85.5067,42.783715],"type":"Point"}
}