{
  "type": "Feature",
  "properties": {
    "iso:country":"US",
    "sg:address":"415 3rd St",
    "sg:city":"Manistee",
    "sg:classifiers":[
        {
            "category":"Government",
            "subcategory":"Office",
            "type":"Public Place"
        }
    ],
    "sg:phone":"+1 231 723 2146",
    "sg:postcode":"49660",
    "sg:province":"MI",
    "wof:name":"Manistee County Register-Deeds",
    "wof:placetype":"venue"
},
  "geometry": {"coordinates":[-86.324776,44.244055],"type":"Point"}
}