{
  "type": "Feature",
  "properties": {
    "iso:country":"US",
    "sg:address":"360 Wilshire Dr",
    "sg:city":"Bloomfield Hills",
    "sg:classifiers":[
        {
            "category":"Real Estate",
            "subcategory":"Real Estate Agent",
            "type":"Services"
        }
    ],
    "sg:phone":"+1 248 334 7971",
    "sg:postcode":"48302",
    "sg:province":"MI",
    "wof:name":"Dame La Enterprises",
    "wof:placetype":"venue"
},
  "geometry": {"coordinates":[-83.275086,42.601316],"type":"Point"}
}