{
  "type": "Feature",
  "properties": {
    "iso:country":"US",
    "sg:address":"11299 Brooklyn Rd",
    "sg:city":"Brooklyn",
    "sg:classifiers":[
        {
            "category":"Restaurant",
            "type":"Food & Drink"
        }
    ],
    "sg:menulink":"http://www.allmenus.com/mi/columbia/196904-burger-king/menu/",
    "sg:phone":"+1 517 592 4076",
    "sg:postcode":"49230",
    "sg:province":"MI",
    "sg:tags":[
        "burger",
        "american"
    ],
    "wof:name":"Burger King",
    "wof:placetype":"venue"
},
  "geometry": {"coordinates":[-84.24811699999999,42.113842],"type":"Point"}
}