{
  "type": "Feature",
  "properties": {
    "iso:country":"US",
    "sg:address":"4236 Baldwin Rd",
    "sg:city":"Auburn Hills",
    "sg:classifiers":[
        {
            "category":"Shopping",
            "type":"Retail Goods"
        }
    ],
    "sg:phone":"+1 248 454 8861",
    "sg:postcode":"48326",
    "sg:province":"MI",
    "sg:tags":[
        "miscellaneous",
        "store"
    ],
    "wof:name":"Asset Management & Sales",
    "wof:placetype":"venue"
},
  "geometry": {"coordinates":[-83.306724,42.700787],"type":"Point"}
}