{
  "type": "Feature",
  "properties": {
    "iso:country":"US",
    "sg:address":"46825 Garfield Rd",
    "sg:city":"Macomb",
    "sg:classifiers":[
        {
            "category":"Banks & Credit Unions",
            "subcategory":"Bank",
            "type":"Services"
        }
    ],
    "sg:phone":"+1 586 532 0264",
    "sg:postcode":"48044",
    "sg:province":"MI",
    "sg:tags":[
        "lender",
        "mortgage"
    ],
    "wof:name":"First Standard Mortgage Co",
    "wof:placetype":"venue"
},
  "geometry": {"coordinates":[-82.956327,42.64035],"type":"Point"}
}