{
  "type": "Feature",
  "properties": {
    "iso:country":"US",
    "sg:address":"18700 E 10 Mile Rd",
    "sg:city":"Eastpointe",
    "sg:classifiers":[
        {
            "category":"Autos & Motor Vehicles",
            "subcategory":"Fuel & Gas Station",
            "type":"Retail Goods"
        }
    ],
    "sg:phone":"+1 586 772 1950",
    "sg:postcode":"48021",
    "sg:province":"MI",
    "sg:tags":[
        "oil"
    ],
    "wof:name":"Ten Mile & Kelly Mobil",
    "wof:placetype":"venue"
},
  "geometry": {"coordinates":[-82.92600299999999,42.480202],"type":"Point"}
}