{
  "type": "Feature",
  "properties": {
    "iso:country":"US",
    "sg:address":"6717 White Oak Ct",
    "sg:city":"Hudsonville",
    "sg:classifiers":[
        {
            "category":"Building & Trades",
            "subcategory":"Landscaping Services",
            "type":"Services"
        }
    ],
    "sg:phone":"+1 616 662 0752",
    "sg:postcode":"49426",
    "sg:province":"MI",
    "sg:tags":[
        "tree"
    ],
    "wof:name":"Advantage Tree Svc",
    "wof:placetype":"venue"
},
  "geometry": {"coordinates":[-85.88816,42.890833],"type":"Point"}
}