{
  "type": "Feature",
  "properties": {
    "iso:country":"US",
    "sg:address":"23334 Schoenherr Rd",
    "sg:city":"Warren",
    "sg:classifiers":[
        {
            "category":"Manufacturing",
            "subcategory":"Metals",
            "type":"Manufacturing & Wholesale Goods"
        }
    ],
    "sg:phone":"+1 586 445 9530",
    "sg:postcode":"48089",
    "sg:province":"MI",
    "sg:tags":[
        "fabricator",
        "sheet"
    ],
    "wof:name":"J & L Mfg Co",
    "wof:placetype":"venue"
},
  "geometry": {"coordinates":[-82.986163,42.464382],"type":"Point"}
}