{
  "type": "Feature",
  "properties": {
    "iso:country":"US",
    "sg:address":"17555 Ida West Rd",
    "sg:city":"Petersburg",
    "sg:classifiers":[
        {
            "category":"Education",
            "subcategory":"School",
            "type":"Public Place"
        }
    ],
    "sg:phone":"+1 734 279 1035",
    "sg:postcode":"49270",
    "sg:province":"MI",
    "sg:website":"www.summerfield.k12.mi.us",
    "wof:name":"Summerfield Schools",
    "wof:placetype":"venue"
},
  "geometry": {"coordinates":[-83.699538,41.907358],"type":"Point"}
}