{
  "type": "Feature",
  "properties": {
    "iso:country":"US",
    "sg:address":"2307 Concord Rd",
    "sg:city":"Lansing",
    "sg:classifiers":[
        {
            "category":"Manufacturing",
            "subcategory":"Printing",
            "type":"Manufacturing & Wholesale Goods"
        }
    ],
    "sg:phone":"+1 517 374 7544",
    "sg:postcode":"48910",
    "sg:province":"MI",
    "sg:tags":[
        "publisher"
    ],
    "sg:website":"www.spartaninternet.com",
    "wof:name":"Spartan",
    "wof:placetype":"venue"
},
  "geometry": {"coordinates":[-84.578902,42.706676],"type":"Point"}
}