{
  "type": "Feature",
  "properties": {
    "iso:country":"US",
    "sg:address":"2709 Polk Ct",
    "sg:city":"Hudsonville",
    "sg:classifiers":[
        {
            "category":"Professional",
            "subcategory":"Secretarial Services",
            "type":"Services"
        }
    ],
    "sg:phone":"+1 616 662 3868",
    "sg:postcode":"49426",
    "sg:province":"MI",
    "sg:tags":[
        "transcription",
        "medical"
    ],
    "wof:name":"Victorian Health Care Svc",
    "wof:placetype":"venue"
},
  "geometry": {"coordinates":[-85.848952,42.861937],"type":"Point"}
}