{
  "type": "Feature",
  "properties": {
    "iso:country":"US",
    "sg:address":"3080 Ivywood Ln",
    "sg:city":"Lansing",
    "sg:classifiers":[
        {
            "category":"Organizations",
            "subcategory":"Religious Organization",
            "type":"Services"
        }
    ],
    "sg:phone":"+1 517 393 5052",
    "sg:postcode":"48911",
    "sg:province":"MI",
    "wof:name":"Lonnie Crowe Ministries",
    "wof:placetype":"venue"
},
  "geometry": {"coordinates":[-84.499268,42.670607],"type":"Point"}
}