{
  "type": "Feature",
  "properties": {
    "iso:country":"US",
    "sg:address":"804 N Cherry St",
    "sg:city":"Greenville",
    "sg:classifiers":[
        {
            "category":"Organizations",
            "subcategory":"Community Association",
            "type":"Services"
        }
    ],
    "sg:phone":"+1 616 754 4823",
    "sg:postcode":"48838",
    "sg:province":"MI",
    "wof:name":"Independent Order Oddfellows",
    "wof:placetype":"venue"
},
  "geometry": {"coordinates":[-85.240016,43.189416],"type":"Point"}
}