{
  "type": "Feature",
  "properties": {
    "iso:country":"US",
    "sg:address":"10241 Conant St",
    "sg:city":"Hamtramck",
    "sg:classifiers":[
        {
            "category":"Retail",
            "subcategory":"Auto Repair",
            "type":"Services"
        }
    ],
    "sg:phone":"+1 313 873 8315",
    "sg:postcode":"48212",
    "sg:province":"MI",
    "wof:name":"Stan and Stan Sales and Service",
    "wof:placetype":"venue"
},
  "geometry": {"coordinates":[-83.049599,42.397598],"type":"Point"}
}