{
  "type": "Feature",
  "properties": {
    "iso:country":"US",
    "sg:address":"660 Woodward Ave",
    "sg:city":"Detroit",
    "sg:classifiers":[
        {
            "category":"Restaurant",
            "type":"Food & Drink"
        }
    ],
    "sg:phone":"+1 313 962 2077",
    "sg:postcode":"48226",
    "sg:province":"MI",
    "sg:tags":[
        "new",
        "american"
    ],
    "sg:website":"www.zipweb.com/?businessname=zef...",
    "wof:name":"Zef's Coney Restaurant",
    "wof:placetype":"venue"
},
  "geometry": {"coordinates":[-83.045805,42.330822],"type":"Point"}
}