{
  "type": "Feature",
  "properties": {
    "iso:country":"US",
    "sg:address":"11777 Horning Rd",
    "sg:city":"Brooklyn",
    "sg:classifiers":[
        {
            "category":"Building & Trades",
            "subcategory":"Construction",
            "type":"Services"
        }
    ],
    "sg:phone":"+1 517 592 5054",
    "sg:postcode":"49230",
    "sg:province":"MI",
    "sg:tags":[
        "house"
    ],
    "wof:name":"Steve Grodi Construction",
    "wof:placetype":"venue"
},
  "geometry": {"coordinates":[-84.19860199999999,42.116456],"type":"Point"}
}