{
  "type": "Feature",
  "properties": {
    "iso:country":"US",
    "sg:address":"29303 Southfield Rd",
    "sg:city":"Southfield",
    "sg:classifiers":[
        {
            "category":"Restaurant",
            "type":"Food & Drink"
        }
    ],
    "sg:phone":"+1 248 552 1078",
    "sg:postcode":"48076",
    "sg:province":"MI",
    "sg:tags":[
        "caterer"
    ],
    "wof:name":"Abes Deli",
    "wof:placetype":"venue"
},
  "geometry": {"coordinates":[-83.222826,42.506032],"type":"Point"}
}