{
  "type": "Feature",
  "properties": {
    "iso:country":"US",
    "sg:address":"21728 Harper Ave",
    "sg:city":"Saint Clair Shores",
    "sg:classifiers":[
        {
            "category":"Professional",
            "type":"Services"
        },
        {
            "category":"Retail",
            "subcategory":"Event Space",
            "type":"Services"
        }
    ],
    "sg:phone":"+1 586 773 3400",
    "sg:postcode":"48080",
    "sg:province":"MI",
    "sg:tags":[
        "venue",
        "caterer"
    ],
    "wof:name":"Elk's Lodge No 34-St Nick's Catering",
    "wof:placetype":"venue"
},
  "geometry": {"coordinates":[-82.91179700000001,42.4566],"type":"Point"}
}