{
  "type": "Feature",
  "properties": {
    "iso:country":"US",
    "sg:address":"675 E Big Beaver Rd",
    "sg:city":"Troy",
    "sg:classifiers":[
        {
            "category":"Shopping",
            "subcategory":"Optician",
            "type":"Retail Goods"
        }
    ],
    "sg:phone":"+1 248 619 9362",
    "sg:postcode":"48083",
    "sg:province":"MI",
    "sg:tags":[
        "eyewear"
    ],
    "wof:name":"Senior Vision Care",
    "wof:placetype":"venue"
},
  "geometry": {"coordinates":[-83.134625,42.563099],"type":"Point"}
}