{
  "type": "Feature",
  "properties": {
    "iso:country":"US",
    "sg:address":"4464 Breton Rd SE",
    "sg:city":"Grand Rapids",
    "sg:classifiers":[
        {
            "category":"Manufacturing",
            "subcategory":"Printing",
            "type":"Manufacturing & Wholesale Goods"
        }
    ],
    "sg:phone":"+1 616 281 8837",
    "sg:postcode":"49508",
    "sg:province":"MI",
    "sg:tags":[
        "printer"
    ],
    "wof:name":"International Minute Press",
    "wof:placetype":"venue"
},
  "geometry": {"coordinates":[-85.606261,42.882733],"type":"Point"}
}