{
  "type": "Feature",
  "properties": {
    "iso:country":"US",
    "sg:address":"2320 S Rose St",
    "sg:city":"Kalamazoo",
    "sg:classifiers":[
        {
            "category":"Professional",
            "subcategory":"Management & Consulting",
            "type":"Services"
        }
    ],
    "sg:phone":"+1 269 345 7472",
    "sg:postcode":"49001",
    "sg:province":"MI",
    "sg:tags":[
        "consultant",
        "business"
    ],
    "wof:name":"KAMACO Inc",
    "wof:placetype":"venue"
},
  "geometry": {"coordinates":[-85.584838,42.268266],"type":"Point"}
}