{
  "type": "Feature",
  "properties": {
    "iso:country":"US",
    "sg:address":"11425 Baseline Rd",
    "sg:city":"Otsego",
    "sg:classifiers":[
        {
            "category":"Manufacturing",
            "subcategory":"Paper Products",
            "type":"Manufacturing & Wholesale Goods"
        }
    ],
    "sg:phone":"+1 269 692 6510",
    "sg:postcode":"49078",
    "sg:province":"MI",
    "sg:tags":[
        "label"
    ],
    "wof:name":"Budget Label Co",
    "wof:placetype":"venue"
},
  "geometry": {"coordinates":[-85.77811,42.420657],"type":"Point"}
}