{
  "type": "Feature",
  "properties": {
    "iso:country":"US",
    "sg:address":"34378 Harper Ave",
    "sg:city":"Clinton Twp",
    "sg:classifiers":[
        {
            "category":"Manufacturing",
            "subcategory":"Signs",
            "type":"Manufacturing & Wholesale Goods"
        }
    ],
    "sg:phone":"+1 586 792 7446",
    "sg:postcode":"48035",
    "sg:province":"MI",
    "wof:name":"Sign-A-Rama",
    "wof:placetype":"venue"
},
  "geometry": {"coordinates":[-82.874916,42.548481],"type":"Point"}
}