{
  "type": "Feature",
  "properties": {
    "iso:country":"US",
    "sg:address":"3284 Chambourne St",
    "sg:city":"Commerce Twp",
    "sg:classifiers":[
        {
            "category":"Building & Trades",
            "subcategory":"Cleaning & Sanitation",
            "type":"Services"
        },
        {
            "category":"Professional",
            "subcategory":"Employment Agencies",
            "type":"Services"
        }
    ],
    "sg:phone":"+1 248 360 1124",
    "sg:postcode":"48382",
    "sg:province":"MI",
    "sg:tags":[
        "house",
        "help",
        "supply"
    ],
    "wof:name":"Country Maids",
    "wof:placetype":"venue"
},
  "geometry": {"coordinates":[-83.44325600000001,42.588235],"type":"Point"}
}