{
  "type": "Feature",
  "properties": {
    "iso:country":"US",
    "sg:address":"82 E Main St",
    "sg:city":"Breedsville",
    "sg:classifiers":[
        {
            "category":"Government",
            "subcategory":"Office",
            "type":"Public Place"
        }
    ],
    "sg:phone":"+1 269 427 9029",
    "sg:postcode":"49027",
    "sg:province":"MI",
    "sg:tags":[
        "village"
    ],
    "wof:name":"Breedsville Village Offices",
    "wof:placetype":"venue"
},
  "geometry": {"coordinates":[-86.07043,42.346468],"type":"Point"}
}