{
  "type": "Feature",
  "properties": {
    "iso:country":"US",
    "sg:address":"The Millennium Centre 15600 J L Hudson Dr",
    "sg:city":"Southfield",
    "sg:classifiers":[
        {
            "category":"Food & Beverages",
            "subcategory":"Farmers Market",
            "type":"Retail Goods"
        }
    ],
    "sg:postcode":"48075",
    "sg:province":"MI",
    "sg:website":"www.southfieldfarmersmarket.net",
    "wof:name":"Southfield Farmers Market",
    "wof:placetype":"venue"
},
  "geometry": {"coordinates":[-83.210094,42.45502],"type":"Point"}
}