{
  "type": "Feature",
  "properties": {
    "iso:country":"US",
    "sg:address":"1948 E 9 Mile Rd",
    "sg:city":"Warren",
    "sg:classifiers":[
        {
            "category":"Retail",
            "subcategory":"Auto Repair",
            "type":"Services"
        }
    ],
    "sg:phone":"+1 586 755 4500",
    "sg:postcode":"48091",
    "sg:province":"MI",
    "sg:tags":[
        "automotive",
        "lubrication"
    ],
    "wof:name":"Jiffy Lube",
    "wof:placetype":"venue"
},
  "geometry": {"coordinates":[-83.08195499999999,42.461796],"type":"Point"}
}