{
  "type": "Feature",
  "properties": {
    "iso:country":"US",
    "sg:address":"2040 Airport Rd",
    "sg:city":"Waterford",
    "sg:classifiers":[
        {
            "category":"Manufacturing",
            "subcategory":"Signs",
            "type":"Manufacturing & Wholesale Goods"
        }
    ],
    "sg:phone":"+1 248 618 0000",
    "sg:postcode":"48327",
    "sg:province":"MI",
    "wof:name":"Eagle Graphics & Design Inc",
    "wof:placetype":"venue"
},
  "geometry": {"coordinates":[-83.406335,42.669982],"type":"Point"}
}