{
  "type": "Feature",
  "properties": {
    "iso:country":"US",
    "sg:address":"3743 Pueblo Ct SW",
    "sg:city":"Grandville",
    "sg:classifiers":[
        {
            "category":"Professional",
            "subcategory":"Business Services",
            "type":"Services"
        }
    ],
    "sg:phone":"+1 616 538 1544",
    "sg:postcode":"49418",
    "sg:province":"MI",
    "wof:name":"DHS Assoc",
    "wof:placetype":"venue"
},
  "geometry": {"coordinates":[-85.7513,42.896382],"type":"Point"}
}