{
  "type": "Feature",
  "properties": {
    "iso:country":"US",
    "sg:address":"5326 W Main St",
    "sg:city":"Kalamazoo",
    "sg:classifiers":[
        {
            "category":"Health Services",
            "subcategory":"Health Practitioner",
            "type":"Services"
        }
    ],
    "sg:phone":"+1 269 349 1713",
    "sg:postcode":"49009",
    "sg:province":"MI",
    "sg:tags":[
        "nutritionist"
    ],
    "wof:name":"GNC",
    "wof:placetype":"venue"
},
  "geometry": {"coordinates":[-85.652461,42.296292],"type":"Point"}
}