{
  "type": "Feature",
  "properties": {
    "iso:country":"US",
    "sg:address":"27432 Groesbeck Hwy",
    "sg:city":"Roseville",
    "sg:classifiers":[
        {
            "category":"Professional",
            "type":"Services"
        }
    ],
    "sg:phone":"+1 586 497 7916",
    "sg:postcode":"48066",
    "sg:province":"MI",
    "wof:name":"Comcast Customer Svc",
    "wof:placetype":"venue"
},
  "geometry": {"coordinates":[-82.964308,42.499852],"type":"Point"}
}