{
  "type": "Feature",
  "properties": {
    "iso:country":"US",
    "sg:address":"15300 N Commerce Dr",
    "sg:city":"Dearborn",
    "sg:classifiers":[
        {
            "category":"Banks & Credit Unions",
            "subcategory":"Investment Brokerage",
            "type":"Services"
        }
    ],
    "sg:phone":"+1 313 982 1518",
    "sg:postcode":"48120",
    "sg:province":"MI",
    "sg:tags":[
        "investing"
    ],
    "wof:name":"Es Investments",
    "wof:placetype":"venue"
},
  "geometry": {"coordinates":[-83.1875,42.311798],"type":"Point"}
}