{
  "type": "Feature",
  "properties": {
    "iso:country":"US",
    "sg:address":"50496 Schoenherr Rd",
    "sg:city":"Utica",
    "sg:classifiers":[
        {
            "category":"Restaurant",
            "type":"Food & Drink"
        },
        {
            "category":"Ice Cream",
            "type":"Food & Drink"
        }
    ],
    "sg:menulink":"http://www.allmenus.com/mi/shelby/40491-cold-stone-creamery/menu/",
    "sg:phone":"+1 586 685 2663",
    "sg:postcode":"48315",
    "sg:province":"MI",
    "sg:tags":[
        "smoothy",
        "juice",
        "american",
        "ice",
        "cream"
    ],
    "wof:name":"Cold Stone Creamery",
    "wof:placetype":"venue"
},
  "geometry": {"coordinates":[-82.99453699999999,42.666611],"type":"Point"}
}