{
  "type": "Feature",
  "properties": {
    "iso:country":"US",
    "sg:address":"23630 Civic Center Dr",
    "sg:city":"Southfield",
    "sg:classifiers":[
        {
            "category":"Professional",
            "subcategory":"Business Services",
            "type":"Services"
        }
    ],
    "sg:phone":"+1 248 827 3004",
    "sg:postcode":"48033",
    "sg:province":"MI",
    "wof:name":"Silverhook Studios",
    "wof:placetype":"venue"
},
  "geometry": {"coordinates":[-83.276169,42.479172],"type":"Point"}
}