{
  "type": "Feature",
  "properties": {
    "iso:country":"US",
    "sg:address":"3745 Cass Ave",
    "sg:city":"Detroit",
    "sg:classifiers":[
        {
            "category":"Organizations",
            "subcategory":"Community Association",
            "type":"Services"
        }
    ],
    "sg:phone":"+1 313 833 7751",
    "sg:postcode":"48201",
    "sg:province":"MI",
    "wof:name":"Project Scout",
    "wof:placetype":"venue"
},
  "geometry": {"coordinates":[-83.062156,42.347901],"type":"Point"}
}