{
  "type": "Feature",
  "properties": {
    "iso:country":"US",
    "sg:address":"51 Summit St",
    "sg:city":"Brighton",
    "sg:classifiers":[
        {
            "category":"Wholesale",
            "subcategory":"Metals & Minerals",
            "type":"Manufacturing & Wholesale Goods"
        }
    ],
    "sg:phone":"+1 810 225 9000",
    "sg:postcode":"48116",
    "sg:province":"MI",
    "sg:tags":[
        "steel",
        "warehouse"
    ],
    "sg:website":"www.quadsteel.com",
    "wof:name":"Quad Steel Corp",
    "wof:placetype":"venue"
},
  "geometry": {"coordinates":[-83.772463,42.51765],"type":"Point"}
}