{
  "type": "Feature",
  "properties": {
    "iso:country":"US",
    "sg:address":"1100 W Huron St",
    "sg:city":"Ann Arbor",
    "sg:classifiers":[
        {
            "category":"Health Services",
            "subcategory":"Doctor",
            "type":"Services"
        }
    ],
    "sg:phone":"+1 734 761 2165",
    "sg:postcode":"48103",
    "sg:province":"MI",
    "sg:tags":[
        "medical"
    ],
    "wof:name":"Melvin L Edwards MD",
    "wof:placetype":"venue"
},
  "geometry": {"coordinates":[-83.761854,42.281921],"type":"Point"}
}