{
  "type": "Feature",
  "properties": {
    "iso:country":"US",
    "sg:address":"598 Dayburg Rd",
    "sg:city":"Coldwater",
    "sg:classifiers":[
        {
            "category":"Building & Trades",
            "subcategory":"Landscaping Services",
            "type":"Services"
        }
    ],
    "sg:phone":"+1 517 279 2464",
    "sg:postcode":"49036",
    "sg:province":"MI",
    "sg:tags":[
        "tree"
    ],
    "wof:name":"Connors & Sons Complete Stump",
    "wof:placetype":"venue"
},
  "geometry": {"coordinates":[-84.96419899999999,42.014626],"type":"Point"}
}