{
  "type": "Feature",
  "properties": {
    "iso:country":"US",
    "sg:address":"40 W Square Lake Rd",
    "sg:city":"Troy",
    "sg:classifiers":[
        {
            "category":"Personal",
            "subcategory":"Tanning Parlor",
            "type":"Services"
        }
    ],
    "sg:phone":"+1 248 828 7676",
    "sg:postcode":"48098",
    "sg:province":"MI",
    "wof:name":"Vip Tanning",
    "wof:placetype":"venue"
},
  "geometry": {"coordinates":[-83.150497,42.606499],"type":"Point"}
}