{
  "type": "Feature",
  "properties": {
    "iso:country":"US",
    "sg:address":"3000 W Miller Rd",
    "sg:city":"Lansing",
    "sg:classifiers":[
        {
            "category":"Organizations",
            "subcategory":"Religious Organization",
            "type":"Services"
        }
    ],
    "sg:phone":"+1 517 393 9860",
    "sg:postcode":"48911",
    "sg:province":"MI",
    "wof:name":"Christian Life Changers Center",
    "wof:placetype":"venue"
},
  "geometry": {"coordinates":[-84.589405,42.669329],"type":"Point"}
}