{
  "type": "Feature",
  "properties": {
    "iso:country":"US",
    "sg:address":"821 Sunset Ln",
    "sg:city":"East Lansing",
    "sg:classifiers":[
        {
            "category":"Organizations",
            "subcategory":"Professional Association",
            "type":"Services"
        }
    ],
    "sg:phone":"+1 517 351 4634",
    "sg:postcode":"48823",
    "sg:province":"MI",
    "wof:name":"Lee B Reimann Treasurer",
    "wof:placetype":"venue"
},
  "geometry": {"coordinates":[-84.48694,42.74231],"type":"Point"}
}