{
  "type": "Feature",
  "properties": {
    "iso:country":"US",
    "sg:address":"22405 Glenwood St",
    "sg:city":"Clinton Twp",
    "sg:classifiers":[
        {
            "category":"Organizations",
            "subcategory":"Religious Organization",
            "type":"Services"
        }
    ],
    "sg:phone":"+1 586 791 4739",
    "sg:postcode":"48035",
    "sg:province":"MI",
    "sg:tags":[
        "church"
    ],
    "wof:name":"Sam J Woodard Ministry",
    "wof:placetype":"venue"
},
  "geometry": {"coordinates":[-82.88271,42.560632],"type":"Point"}
}