{
  "type": "Feature",
  "properties": {
    "iso:country":"US",
    "sg:address":"4044 Oak Bank Ct",
    "sg:city":"Orchard Lake",
    "sg:classifiers":[
        {
            "category":"Banks & Credit Unions",
            "subcategory":"Investment Brokerage",
            "type":"Services"
        }
    ],
    "sg:phone":"+1 248 661 9531",
    "sg:postcode":"48323",
    "sg:province":"MI",
    "wof:name":"Omni Investment Group LLC",
    "wof:placetype":"venue"
},
  "geometry": {"coordinates":[-83.36429099999999,42.579116],"type":"Point"}
}