{
  "type": "Feature",
  "properties": {
    "iso:country":"US",
    "sg:address":"233 High Lake Rd",
    "sg:city":"Traverse City",
    "sg:classifiers":[
        {
            "category":"Travel",
            "subcategory":"Hotels & Motels",
            "type":"Entertainment"
        }
    ],
    "sg:phone":"+1 231 947 8945",
    "sg:postcode":"49686",
    "sg:province":"MI",
    "sg:tags":[
        "resort"
    ],
    "sg:website":"www.courtades.com",
    "wof:name":"Courtade's Trading Ctr",
    "wof:placetype":"venue"
},
  "geometry": {"coordinates":[-85.511777,44.687834],"type":"Point"}
}