{
  "type": "Feature",
  "properties": {
    "iso:country":"US",
    "sg:address":"5948 Willis Rd",
    "sg:city":"Ypsilanti",
    "sg:classifiers":[
        {
            "category":"Building & Trades",
            "subcategory":"Landscaping Services",
            "type":"Services"
        }
    ],
    "sg:phone":"+1 734 487 8482",
    "sg:postcode":"48197",
    "sg:province":"MI",
    "wof:name":"Brians Lawn Maintenance",
    "wof:placetype":"venue"
},
  "geometry": {"coordinates":[-83.65301599999999,42.156068],"type":"Point"}
}