{
  "type": "Feature",
  "properties": {
    "iso:country":"US",
    "sg:address":"4366 E 9 Mile Rd",
    "sg:city":"Warren",
    "sg:classifiers":[
        {
            "category":"Health Services",
            "subcategory":"Dentist",
            "type":"Services"
        }
    ],
    "sg:phone":"+1 586 758 4949",
    "sg:postcode":"48091",
    "sg:province":"MI",
    "wof:name":"Zobl Robert J & Associates",
    "wof:placetype":"venue"
},
  "geometry": {"coordinates":[-83.0616,42.462101],"type":"Point"}
}