{
  "type": "Feature",
  "properties": {
    "iso:country":"US",
    "sg:address":"814 Palmer Ave",
    "sg:city":"Kalamazoo",
    "sg:classifiers":[
        {
            "category":"Wholesale",
            "subcategory":"Auto Parts",
            "type":"Manufacturing & Wholesale Goods"
        }
    ],
    "sg:phone":"+1 269 344 2930",
    "sg:postcode":"49001",
    "sg:province":"MI",
    "sg:tags":[
        "automobile",
        "supply"
    ],
    "wof:name":"Wholesale Autoparts Inc",
    "wof:placetype":"venue"
},
  "geometry": {"coordinates":[-85.56899199999999,42.269864],"type":"Point"}
}