{
  "type": "Feature",
  "properties": {
    "iso:country":"US",
    "sg:address":"6520 Maidens Rd",
    "sg:city":"Bear Lake",
    "sg:classifiers":[
        {
            "category":"Building & Trades",
            "subcategory":"Construction",
            "type":"Services"
        }
    ],
    "sg:phone":"+1 231 864 2295",
    "sg:postcode":"49614",
    "sg:province":"MI",
    "sg:tags":[
        "floor",
        "laying",
        "contractor"
    ],
    "wof:name":"Ward Flooring Installation LLC",
    "wof:placetype":"venue"
},
  "geometry": {"coordinates":[-86.173647,44.388899],"type":"Point"}
}