{
  "type": "Feature",
  "properties": {
    "iso:country":"US",
    "sg:address":"1785 E Hamlin Rd",
    "sg:city":"Rochester Hills",
    "sg:classifiers":[
        {
            "category":"Professional",
            "type":"Services"
        },
        {
            "category":"Manufacturing",
            "subcategory":"Tools & Machinery",
            "type":"Manufacturing & Wholesale Goods"
        }
    ],
    "sg:phone":"+1 248 652 0029",
    "sg:postcode":"48307",
    "sg:province":"MI",
    "sg:tags":[
        "furnace",
        "works",
        "mfg",
        "accessory",
        "machine",
        "blast",
        "establishment"
    ],
    "wof:name":"Road Runner Machine",
    "wof:placetype":"venue"
},
  "geometry": {"coordinates":[-83.098747,42.653277],"type":"Point"}
}