{
  "type": "Feature",
  "properties": {
    "iso:country":"US",
    "sg:address":"8410 Pokagon Rd",
    "sg:city":"Berrien Center",
    "sg:classifiers":[
        {
            "category":"Building & Trades",
            "subcategory":"Construction",
            "type":"Services"
        }
    ],
    "sg:phone":"+1 269 683 8263",
    "sg:postcode":"49102",
    "sg:province":"MI",
    "sg:tags":[
        "hanging",
        "contractor"
    ],
    "wof:name":"Hartlein Painting",
    "wof:placetype":"venue"
},
  "geometry": {"coordinates":[-86.25129699999999,41.927915],"type":"Point"}
}