{
  "type": "Feature",
  "properties": {
    "iso:country":"US",
    "sg:address":"2987 Blue Star Hwy",
    "sg:city":"Fennville",
    "sg:classifiers":[
        {
            "category":"Wholesale",
            "subcategory":"Machinery & Supplies",
            "type":"Manufacturing & Wholesale Goods"
        }
    ],
    "sg:phone":"+1 269 857 8887",
    "sg:postcode":"49408",
    "sg:province":"MI",
    "sg:tags":[
        "equipment",
        "material",
        "handling"
    ],
    "wof:name":"D R Storage Systems",
    "wof:placetype":"venue"
},
  "geometry": {"coordinates":[-86.21191399999999,42.632062],"type":"Point"}
}