{
  "type": "Feature",
  "properties": {
    "iso:country":"US",
    "sg:address":"4316 Buckingham Rd",
    "sg:city":"Royal Oak",
    "sg:classifiers":[
        {
            "category":"Professional",
            "type":"Services"
        }
    ],
    "sg:phone":"+1 248 549 9559",
    "sg:postcode":"48073",
    "sg:province":"MI",
    "sg:tags":[
        "establishment"
    ],
    "wof:name":"M G Remus Inc",
    "wof:placetype":"venue"
},
  "geometry": {"coordinates":[-83.198572,42.529544],"type":"Point"}
}