{
  "type": "Feature",
  "properties": {
    "iso:country":"US",
    "sg:address":"1477 Walli Strasse Dr",
    "sg:city":"Burton",
    "sg:classifiers":[
        {
            "category":"Professional",
            "subcategory":"Employment Agencies",
            "type":"Services"
        }
    ],
    "sg:phone":"+1 810 742 8500",
    "sg:postcode":"48509",
    "sg:province":"MI",
    "wof:name":"Trialon Corp",
    "wof:placetype":"venue"
},
  "geometry": {"coordinates":[-83.6315,43.005798],"type":"Point"}
}