{
  "type": "Feature",
  "properties": {
    "iso:country":"US",
    "sg:address":"435 E Superior St",
    "sg:city":"Wayland",
    "sg:classifiers":[
        {
            "category":"Education",
            "subcategory":"School",
            "type":"Public Place"
        }
    ],
    "sg:phone":"+1 269 792 1100",
    "sg:postcode":"49348",
    "sg:province":"MI",
    "wof:name":"Wayland Union Schools",
    "wof:placetype":"venue"
},
  "geometry": {"coordinates":[-85.637021,42.673889],"type":"Point"}
}