{
  "type": "Feature",
  "properties": {
    "iso:country":"US",
    "sg:address":"29500 Van Dyke Ave",
    "sg:city":"Warren",
    "sg:classifiers":[
        {
            "category":"Government",
            "subcategory":"Office",
            "type":"Public Place"
        }
    ],
    "sg:phone":"+1 586 751 6833",
    "sg:postcode":"48093",
    "sg:province":"MI",
    "wof:name":"Warren Employee's Retirement",
    "wof:placetype":"venue"
},
  "geometry": {"coordinates":[-83.028407,42.509924],"type":"Point"}
}