{
  "type": "Feature",
  "properties": {
    "iso:country":"US",
    "sg:address":"2000 Boston Blvd",
    "sg:city":"Lansing",
    "sg:classifiers":[
        {
            "category":"Building & Trades",
            "subcategory":"Construction",
            "type":"Services"
        }
    ],
    "sg:phone":"+1 517 853 1597",
    "sg:postcode":"48910",
    "sg:province":"MI",
    "sg:tags":[
        "hanging",
        "contractor"
    ],
    "wof:name":"Host With Most Painting",
    "wof:placetype":"venue"
},
  "geometry": {"coordinates":[-84.57602300000001,42.711982],"type":"Point"}
}