{
  "type": "Feature",
  "properties": {
    "iso:country":"US",
    "sg:address":"9040 Miller Rd",
    "sg:city":"Alanson",
    "sg:classifiers":[
        {
            "category":"Retail",
            "subcategory":"Auto Repair",
            "type":"Services"
        }
    ],
    "sg:phone":"+1 231 548 3038",
    "sg:postcode":"49706",
    "sg:province":"MI",
    "sg:tags":[
        "automotive"
    ],
    "wof:name":"Htn Machine",
    "wof:placetype":"venue"
},
  "geometry": {"coordinates":[-84.7299,45.420232],"type":"Point"}
}