{
  "type": "Feature",
  "properties": {
    "iso:country":"US",
    "sg:address":"6758 Southpointe Ct SW",
    "sg:city":"Byron Center",
    "sg:classifiers":[
        {
            "category":"Travel",
            "subcategory":"Travel Agent",
            "type":"Entertainment"
        }
    ],
    "sg:phone":"+1 616 532 5804",
    "sg:postcode":"49315",
    "sg:province":"MI",
    "sg:tags":[
        "cruise"
    ],
    "wof:name":"All One Travel",
    "wof:placetype":"venue"
},
  "geometry": {"coordinates":[-85.68503800000001,42.842531],"type":"Point"}
}