{
  "type": "Feature",
  "properties": {
    "iso:country":"US",
    "sg:address":"3012 Village Ln",
    "sg:city":"Brooklyn",
    "sg:classifiers":[
        {
            "category":"Shopping",
            "subcategory":"Computers & Home Electronics",
            "type":"Retail Goods"
        }
    ],
    "sg:phone":"+1 517 592 2363",
    "sg:postcode":"49230",
    "sg:province":"MI",
    "wof:name":"Micronet",
    "wof:placetype":"venue"
},
  "geometry": {"coordinates":[-84.19727899999999,42.08992],"type":"Point"}
}