{
  "type": "Feature",
  "properties": {
    "iso:country":"US",
    "sg:address":"5713 Venture Park Dr",
    "sg:city":"Kalamazoo",
    "sg:classifiers":[
        {
            "category":"Banks & Credit Unions",
            "subcategory":"Bank",
            "type":"Services"
        }
    ],
    "sg:phone":"+1 269 372 4455",
    "sg:postcode":"49009",
    "sg:province":"MI",
    "wof:name":"Allegis Credit Union",
    "wof:placetype":"venue"
},
  "geometry": {"coordinates":[-85.66266,42.267289],"type":"Point"}
}