{
  "type": "Feature",
  "properties": {
    "iso:country":"US",
    "sg:address":"285 River St",
    "sg:city":"Manistee",
    "sg:classifiers":[
        {
            "category":"Retail",
            "subcategory":"Laundry & Dry Cleaning",
            "type":"Services"
        }
    ],
    "sg:phone":"+1 231 723 4633",
    "sg:postcode":"49660",
    "sg:province":"MI",
    "sg:tags":[
        "cleaners"
    ],
    "wof:name":"American Cleaners",
    "wof:placetype":"venue"
},
  "geometry": {"coordinates":[-86.318056,44.249268],"type":"Point"}
}