{
  "type": "Feature",
  "properties": {
    "iso:country":"US",
    "sg:address":"7015 Hall Rd",
    "sg:city":"Bellevue",
    "sg:classifiers":[
        {
            "category":"Personal",
            "subcategory":"Beauty Salon",
            "type":"Services"
        }
    ],
    "sg:phone":"+1 269 763 3167",
    "sg:postcode":"49021",
    "sg:province":"MI",
    "sg:tags":[
        "shop"
    ],
    "wof:name":"Sherrys Hair Care",
    "wof:placetype":"venue"
},
  "geometry": {"coordinates":[-84.97409399999999,42.458213],"type":"Point"}
}