{
  "type": "Feature",
  "properties": {
    "iso:country":"US",
    "sg:address":"30885 Groesbeck Hwy",
    "sg:city":"Roseville",
    "sg:classifiers":[
        {
            "category":"Retail",
            "subcategory":"Auto Repair",
            "type":"Services"
        }
    ],
    "sg:phone":"+1 586 772 0063",
    "sg:postcode":"48066",
    "sg:province":"MI",
    "sg:tags":[
        "general"
    ],
    "wof:name":"J & H Automotive",
    "wof:placetype":"venue"
},
  "geometry": {"coordinates":[-82.947112,42.523201],"type":"Point"}
}