{
  "type": "Feature",
  "properties": {
    "iso:country":"US",
    "sg:address":"3663 Clay Ave SW",
    "sg:city":"Grand Rapids",
    "sg:classifiers":[
        {
            "category":"Retail",
            "subcategory":"Auto Rental",
            "type":"Services"
        }
    ],
    "sg:phone":"+1 770 569 6000",
    "sg:postcode":"49548",
    "sg:province":"MI",
    "sg:tags":[
        "truck",
        "rent",
        "lease"
    ],
    "sg:website":"www.ryder.com",
    "wof:name":"Ryder",
    "wof:placetype":"venue"
},
  "geometry": {"coordinates":[-85.67646000000001,42.895168],"type":"Point"}
}