{
  "type": "Feature",
  "properties": {
    "iso:country":"US",
    "sg:address":"3830 W Pillar Rd",
    "sg:city":"Whitmore Lake",
    "sg:classifiers":[
        {
            "category":"Organizations",
            "subcategory":"Religious Organization",
            "type":"Services"
        }
    ],
    "sg:phone":"+1 734 426 0679",
    "sg:postcode":"48189",
    "sg:province":"MI",
    "wof:name":"Hope Christian Fellowship",
    "wof:placetype":"venue"
},
  "geometry": {"coordinates":[-83.80872100000001,42.387846],"type":"Point"}
}