{
  "type": "Feature",
  "properties": {
    "iso:country":"US",
    "sg:address":"5 Holland Ct",
    "sg:city":"Saginaw",
    "sg:classifiers":[
        {
            "category":"Health Services",
            "subcategory":"Medical Lab",
            "type":"Services"
        }
    ],
    "sg:phone":"+1 989 714 7887",
    "sg:postcode":"48601",
    "sg:province":"MI",
    "sg:tags":[
        "testing",
        "pulse"
    ],
    "wof:name":"RCP Consulting Inc",
    "wof:placetype":"venue"
},
  "geometry": {"coordinates":[-83.937562,43.416003],"type":"Point"}
}