{
  "type": "Feature",
  "properties": {
    "iso:country":"US",
    "sg:address":"16440 Dusklight Dr",
    "sg:city":"Fenton",
    "sg:classifiers":[
        {
            "category":"Organizations",
            "subcategory":"Community Association",
            "type":"Services"
        }
    ],
    "sg:phone":"+1 810 750 0997",
    "sg:postcode":"48430",
    "sg:province":"MI",
    "wof:name":"Coachlight Pines Property",
    "wof:placetype":"venue"
},
  "geometry": {"coordinates":[-83.772006,42.785181],"type":"Point"}
}