{
  "type": "Feature",
  "properties": {
    "iso:country":"US",
    "sg:address":"8101 S 49 Rd",
    "sg:city":"Cadillac",
    "sg:classifiers":[
        {
            "category":"Retail",
            "subcategory":"Repair Shop",
            "type":"Services"
        }
    ],
    "sg:phone":"+1 231 775 3904",
    "sg:postcode":"49601",
    "sg:province":"MI",
    "wof:name":"Georges Repair Service",
    "wof:placetype":"venue"
},
  "geometry": {"coordinates":[-85.33578199999999,44.222927],"type":"Point"}
}