{
  "type": "Feature",
  "properties": {
    "iso:country":"US",
    "sg:address":"9874 Mevis Dr",
    "sg:city":"Brighton",
    "sg:classifiers":[
        {
            "category":"Manufacturing",
            "subcategory":"Toys & Sporting Goods",
            "type":"Manufacturing & Wholesale Goods"
        }
    ],
    "sg:phone":"+1 248 886 0012",
    "sg:postcode":"48114",
    "sg:province":"MI",
    "sg:tags":[
        "mfg"
    ],
    "wof:name":"Reynolds Aviation Consulting",
    "wof:placetype":"venue"
},
  "geometry": {"coordinates":[-83.755652,42.578444],"type":"Point"}
}