{
  "type": "Feature",
  "properties": {
    "iso:country":"US",
    "sg:address":"1343 Hawkcrest Ln",
    "sg:city":"Pontiac",
    "sg:classifiers":[
        {
            "category":"Building & Trades",
            "subcategory":"Construction",
            "type":"Services"
        }
    ],
    "sg:phone":"+1 248 370 9615",
    "sg:postcode":"48340",
    "sg:province":"MI",
    "sg:tags":[
        "hanging",
        "contractor"
    ],
    "wof:name":"Cepeda Painting Co",
    "wof:placetype":"venue"
},
  "geometry": {"coordinates":[-83.264302,42.67301],"type":"Point"}
}