{
  "type": "Feature",
  "properties": {
    "iso:country":"US",
    "sg:address":"804 Fix Rd",
    "sg:city":"Monroe",
    "sg:classifiers":[
        {
            "category":"Professional",
            "subcategory":"Accounting & Tax Preparation",
            "type":"Services"
        }
    ],
    "sg:phone":"+1 734 241 1154",
    "sg:postcode":"48162",
    "sg:province":"MI",
    "sg:tags":[
        "consultant"
    ],
    "wof:name":"American Tax System",
    "wof:placetype":"venue"
},
  "geometry": {"coordinates":[-83.366246,41.949532],"type":"Point"}
}