{
  "type": "Feature",
  "properties": {
    "iso:country":"US",
    "sg:address":"1053 S Lapeer Rd",
    "sg:city":"Lapeer",
    "sg:classifiers":[
        {
            "category":"Professional",
            "subcategory":"Accounting & Tax Preparation",
            "type":"Services"
        }
    ],
    "sg:phone":"+1 810 667 6906",
    "sg:postcode":"48446",
    "sg:province":"MI",
    "sg:tags":[
        "return"
    ],
    "wof:name":"Nassar Tax & Accounting",
    "wof:placetype":"venue"
},
  "geometry": {"coordinates":[-83.322999,43.034326],"type":"Point"}
}