{
  "type": "Feature",
  "properties": {
    "iso:country":"US",
    "sg:address":"220 Park St",
    "sg:city":"Birmingham",
    "sg:classifiers":[
        {
            "category":"Wholesale",
            "subcategory":"Durable Goods & Equipment",
            "type":"Manufacturing & Wholesale Goods"
        }
    ],
    "sg:phone":"+1 248 203 1971",
    "sg:postcode":"48009",
    "sg:province":"MI",
    "sg:tags":[
        "representative",
        "manufacturer"
    ],
    "wof:name":"Tapeponents Co Inc",
    "wof:placetype":"venue"
},
  "geometry": {"coordinates":[-83.212238,42.547012],"type":"Point"}
}