{
  "type": "Feature",
  "properties": {
    "iso:country":"US",
    "sg:address":"62511 State Hwy 43",
    "sg:city":"Bangor",
    "sg:classifiers":[
        {
            "category":"Building & Trades",
            "subcategory":"Landscaping Services",
            "type":"Services"
        }
    ],
    "sg:phone":"+1 269 639 7924",
    "sg:postcode":"49013",
    "sg:province":"MI",
    "sg:tags":[
        "landscape",
        "contractor"
    ],
    "wof:name":"Lawn Boys Inc",
    "wof:placetype":"venue"
},
  "geometry": {"coordinates":[-86.152973,42.32987],"type":"Point"}
}