{
  "type": "Feature",
  "properties": {
    "iso:country":"US",
    "sg:address":"200 S East Ave",
    "sg:city":"Jackson",
    "sg:classifiers":[
        {
            "category":"Health Services",
            "subcategory":"Doctor",
            "type":"Services"
        }
    ],
    "sg:phone":"+1 517 788 8727",
    "sg:postcode":"49201",
    "sg:province":"MI",
    "sg:tags":[
        "physician",
        "surgeon"
    ],
    "wof:name":"Gambro Healthcare",
    "wof:placetype":"venue"
},
  "geometry": {"coordinates":[-84.39267100000001,42.247508],"type":"Point"}
}