{
  "type": "Feature",
  "properties": {
    "iso:country":"US",
    "sg:address":"3822 W Centre Ave",
    "sg:city":"Portage",
    "sg:classifiers":[
        {
            "category":"Restaurant",
            "type":"Food & Drink"
        }
    ],
    "sg:phone":"+1 269 321 8990",
    "sg:postcode":"49024",
    "sg:province":"MI",
    "wof:name":"Subway Sandwiches & Salads",
    "wof:placetype":"venue"
},
  "geometry": {"coordinates":[-85.642371,42.1983],"type":"Point"}
}