{
  "type": "Feature",
  "properties": {
    "iso:country":"US",
    "sg:address":"3088 Sheffield St",
    "sg:city":"Muskegon",
    "sg:classifiers":[
        {
            "category":"Shopping",
            "subcategory":"Computers & Home Electronics",
            "type":"Retail Goods"
        }
    ],
    "sg:phone":"+1 231 733 8299",
    "sg:postcode":"49441",
    "sg:province":"MI",
    "sg:tags":[
        "equipment",
        "dealer"
    ],
    "wof:name":"Mouse House",
    "wof:placetype":"venue"
},
  "geometry": {"coordinates":[-86.26197000000001,43.197965],"type":"Point"}
}