{
  "type": "Feature",
  "properties": {
    "iso:country":"US",
    "sg:address":"6856 E K Ave",
    "sg:city":"Kalamazoo",
    "sg:classifiers":[
        {
            "category":"Manufacturing",
            "subcategory":"Tools & Machinery",
            "type":"Manufacturing & Wholesale Goods"
        }
    ],
    "sg:phone":"+1 269 382 2050",
    "sg:postcode":"49048",
    "sg:province":"MI",
    "sg:tags":[
        "cutting"
    ],
    "sg:website":"www.kalamazooindustries.com",
    "wof:name":"Kalamazoo Industries Inc",
    "wof:placetype":"venue"
},
  "geometry": {"coordinates":[-85.495983,42.290284],"type":"Point"}
}