{
  "type": "Feature",
  "properties": {
    "iso:country":"US",
    "sg:address":"4952 Bunker Rd",
    "sg:city":"Mason",
    "sg:classifiers":[
        {
            "category":"Retail",
            "subcategory":"Repair Shop",
            "type":"Services"
        }
    ],
    "sg:phone":"+1 517 628 2285",
    "sg:postcode":"48854",
    "sg:province":"MI",
    "sg:tags":[
        "related"
    ],
    "wof:name":"Ken's Repair Svc",
    "wof:placetype":"venue"
},
  "geometry": {"coordinates":[-84.541788,42.553157],"type":"Point"}
}