{
  "type": "Feature",
  "properties": {
    "iso:country":"US",
    "sg:address":"3711 138th Ave",
    "sg:city":"Hamilton",
    "sg:classifiers":[
        {
            "category":"Building & Trades",
            "subcategory":"Construction",
            "type":"Services"
        }
    ],
    "sg:phone":"+1 269 751 7230",
    "sg:postcode":"49419",
    "sg:province":"MI",
    "sg:tags":[
        "concrete",
        "contractor"
    ],
    "wof:name":"Staat Poured Walls Inc",
    "wof:placetype":"venue"
},
  "geometry": {"coordinates":[-85.91139,42.695194],"type":"Point"}
}