{
  "type": "Feature",
  "properties": {
    "iso:country":"US",
    "sg:address":"5011 Bath Rd",
    "sg:city":"Bancroft",
    "sg:classifiers":[
        {
            "category":"Farming",
            "subcategory":"Farm",
            "type":"Manufacturing & Wholesale Goods"
        }
    ],
    "sg:phone":"+1 989 634 9710",
    "sg:postcode":"48414",
    "sg:province":"MI",
    "sg:tags":[
        "crop",
        "general"
    ],
    "wof:name":"Richard Hurrell",
    "wof:placetype":"venue"
},
  "geometry": {"coordinates":[-84.062074,42.821737],"type":"Point"}
}