{
  "type": "Feature",
  "properties": {
    "iso:country":"US",
    "sg:address":"640 W Chicago Rd",
    "sg:city":"Niles",
    "sg:classifiers":[
        {
            "category":"Autos & Motor Vehicles",
            "subcategory":"Fuel & Gas Station",
            "type":"Retail Goods"
        }
    ],
    "sg:phone":"+1 269 683 0561",
    "sg:postcode":"49120",
    "sg:province":"MI",
    "sg:tags":[
        "oil"
    ],
    "wof:name":"Admiral",
    "wof:placetype":"venue"
},
  "geometry": {"coordinates":[-86.26406799999999,41.823209],"type":"Point"}
}