{
  "type": "Feature",
  "properties": {
    "iso:country":"US",
    "sg:address":"1908 10th St",
    "sg:city":"Port Huron",
    "sg:classifiers":[
        {
            "category":"Shopping",
            "subcategory":"Catalog Store",
            "type":"Retail Goods"
        }
    ],
    "sg:phone":"+1 810 987 0855",
    "sg:postcode":"48060",
    "sg:province":"MI",
    "sg:tags":[
        "showroom"
    ],
    "wof:name":"John's Collectibles",
    "wof:placetype":"venue"
},
  "geometry": {"coordinates":[-82.432275,42.964419],"type":"Point"}
}