{
  "type": "Feature",
  "properties": {
    "iso:country":"US",
    "sg:address":"168 S Old Woodward Ave",
    "sg:city":"Birmingham",
    "sg:classifiers":[
        {
            "category":"Shopping",
            "subcategory":"Clothing, Apparel, & Fashions",
            "type":"Retail Goods"
        }
    ],
    "sg:phone":"+1 248 644 0300",
    "sg:postcode":"48009",
    "sg:province":"MI",
    "sg:tags":[
        "accessory"
    ],
    "wof:name":"Ariada & Co",
    "wof:placetype":"venue"
},
  "geometry": {"coordinates":[-83.21379899999999,42.546001],"type":"Point"}
}