{
  "type": "Feature",
  "properties": {
    "iso:country":"US",
    "sg:address":"11360 Powderhorn Rd",
    "sg:city":"Bessemer",
    "sg:classifiers":[
        {
            "category":"Travel",
            "subcategory":"Hotels & Motels",
            "type":"Entertainment"
        }
    ],
    "sg:phone":"+1 906 932 3100",
    "sg:postcode":"49911",
    "sg:province":"MI",
    "sg:tags":[
        "organization",
        "lodging",
        "center",
        "resort",
        "skiing"
    ],
    "sg:website":"www.bpla.com",
    "wof:name":"Big Powderhorn Lodging Assoc",
    "wof:placetype":"venue"
},
  "geometry": {"coordinates":[-90.09034200000001,46.509398],"type":"Point"}
}