{
  "type": "Feature",
  "properties": {
    "iso:country":"US",
    "sg:address":"8887 Gull Rd",
    "sg:city":"Richland",
    "sg:classifiers":[
        {
            "category":"Banks & Credit Unions",
            "subcategory":"Bank",
            "type":"Services"
        }
    ],
    "sg:phone":"+1 269 629 4806",
    "sg:postcode":"49083",
    "sg:province":"MI",
    "sg:tags":[
        "loan",
        "real estate"
    ],
    "wof:name":"Premier Mortgage Funding Inc",
    "wof:placetype":"venue"
},
  "geometry": {"coordinates":[-85.461473,42.370812],"type":"Point"}
}