{
  "type": "Feature",
  "properties": {
    "iso:country":"US",
    "sg:address":"625 Church St",
    "sg:city":"Ann Arbor",
    "sg:classifiers":[
        {
            "category":"Real Estate",
            "subcategory":"Real Estate Agent",
            "type":"Services"
        }
    ],
    "sg:phone":"+1 734 663 3641",
    "sg:postcode":"48104",
    "sg:province":"MI",
    "wof:name":"Zwas Realty",
    "wof:placetype":"venue"
},
  "geometry": {"coordinates":[-83.734478,42.274066],"type":"Point"}
}