{
  "type": "Feature",
  "properties": {
    "iso:country":"US",
    "sg:address":"798 Beachway Dr",
    "sg:city":"White Lake",
    "sg:classifiers":[
        {
            "category":"Retail",
            "subcategory":"Portrait Studio",
            "type":"Services"
        }
    ],
    "sg:phone":"+1 248 698 9858",
    "sg:postcode":"48383",
    "sg:province":"MI",
    "sg:tags":[
        "photographer"
    ],
    "wof:name":"Sports Section",
    "wof:placetype":"venue"
},
  "geometry": {"coordinates":[-83.510058,42.637252],"type":"Point"}
}