{
  "type": "Feature",
  "properties": {
    "iso:country":"US",
    "sg:address":"936 N Telegraph Rd",
    "sg:city":"Dearborn",
    "sg:classifiers":[
        {
            "category":"Insurance",
            "subcategory":"Hazard Insurance",
            "type":"Services"
        }
    ],
    "sg:phone":"+1 313 562 4062",
    "sg:postcode":"48128",
    "sg:province":"MI",
    "sg:website":"www.bobzakar.com/",
    "wof:name":"Bob Zakar - State Farm Insurance",
    "wof:placetype":"venue"
},
  "geometry": {"coordinates":[-83.271727,42.318647],"type":"Point"}
}