{
  "type": "Feature",
  "properties": {
    "iso:country":"US",
    "sg:address":"8228 23rd Ln",
    "sg:city":"Rapid River",
    "sg:classifiers":[
        {
            "category":"Professional",
            "subcategory":"Management & Consulting",
            "type":"Services"
        }
    ],
    "sg:phone":"+1 906 474 6477",
    "sg:postcode":"49878",
    "sg:province":"MI",
    "sg:tags":[
        "consultant",
        "business"
    ],
    "wof:name":"Hardwick Management Inc",
    "wof:placetype":"venue"
},
  "geometry": {"coordinates":[-86.952251,45.868315],"type":"Point"}
}