{
  "type": "Feature",
  "properties": {
    "iso:country":"US",
    "sg:address":"178 Lothrop Rd",
    "sg:city":"Grosse Pointe",
    "sg:classifiers":[
        {
            "category":"Farming",
            "subcategory":"Farm",
            "type":"Manufacturing & Wholesale Goods"
        }
    ],
    "sg:phone":"+1 313 640 0123",
    "sg:postcode":"48236",
    "sg:province":"MI",
    "sg:tags":[
        "crop",
        "general"
    ],
    "wof:name":"Huron City Co",
    "wof:placetype":"venue"
},
  "geometry": {"coordinates":[-82.899168,42.402146],"type":"Point"}
}