{
  "type": "Feature",
  "properties": {
    "iso:country":"US",
    "sg:address":"2431 Eastern Ave SE",
    "sg:city":"Grand Rapids",
    "sg:classifiers":[
        {
            "category":"Cinema",
            "subcategory":"Movie Rental",
            "type":"Entertainment"
        }
    ],
    "sg:phone":"+1 616 245 9813",
    "sg:postcode":"49507",
    "sg:province":"MI",
    "sg:tags":[
        "video",
        "tape"
    ],
    "wof:name":"Video Master",
    "wof:placetype":"venue"
},
  "geometry": {"coordinates":[-85.647519,42.918688],"type":"Point"}
}