{
  "type": "Feature",
  "properties": {
    "iso:country":"US",
    "sg:address":"14708 Young St",
    "sg:city":"Detroit",
    "sg:classifiers":[
        {
            "category":"Personal",
            "subcategory":"Barber",
            "type":"Services"
        }
    ],
    "sg:phone":"+1 313 521 1169",
    "sg:postcode":"48205",
    "sg:province":"MI",
    "wof:name":"G-Ru's Barber Shop",
    "wof:placetype":"venue"
},
  "geometry": {"coordinates":[-82.97114999999999,42.42377],"type":"Point"}
}