{
  "type": "Feature",
  "properties": {
    "iso:country":"US",
    "sg:address":"2750 Cook Rd",
    "sg:city":"West Branch",
    "sg:classifiers":[
        {
            "category":"Retail",
            "subcategory":"Portrait Studio",
            "type":"Services"
        }
    ],
    "sg:phone":"+1 989 343 0122",
    "sg:postcode":"48661",
    "sg:province":"MI",
    "sg:tags":[
        "photographer"
    ],
    "wof:name":"Wal-Mart Portrait Studio",
    "wof:placetype":"venue"
},
  "geometry": {"coordinates":[-84.224998,44.25465],"type":"Point"}
}