{
  "type": "Feature",
  "properties": {
    "iso:country":"US",
    "sg:address":"401 Washington Ave",
    "sg:city":"Bay City",
    "sg:classifiers":[
        {
            "category":"Insurance",
            "subcategory":"Insurance Agent",
            "type":"Services"
        }
    ],
    "sg:phone":"+1 989 894 4748",
    "sg:postcode":"48708",
    "sg:province":"MI",
    "wof:name":"Martin Bauer Insurance Agency",
    "wof:placetype":"venue"
},
  "geometry": {"coordinates":[-83.888261,43.595031],"type":"Point"}
}