{
  "type": "Feature",
  "properties": {
    "iso:country":"US",
    "sg:address":"6145 Marsh Rd",
    "sg:city":"Cottrellville",
    "sg:classifiers":[
        {
            "category":"Home & Garden",
            "subcategory":"Building Materials",
            "type":"Retail Goods"
        }
    ],
    "sg:phone":"+1 810 765 3085",
    "sg:postcode":"48039",
    "sg:province":"MI",
    "sg:tags":[
        "cement"
    ],
    "wof:name":"Connin Cement",
    "wof:placetype":"venue"
},
  "geometry": {"coordinates":[-82.536818,42.722266],"type":"Point"}
}