{
  "type": "Feature",
  "properties": {
    "iso:country":"US",
    "sg:address":"32355 Mally Dr",
    "sg:city":"Madison Heights",
    "sg:classifiers":[
        {
            "category":"Professional",
            "subcategory":"Computer Services",
            "type":"Services"
        }
    ],
    "sg:phone":"+1 248 280 2530",
    "sg:postcode":"48071",
    "sg:province":"MI",
    "sg:tags":[
        "repair"
    ],
    "sg:website":"www.sectormi.com",
    "wof:name":"Sector Computer Systems Inc",
    "wof:placetype":"venue"
},
  "geometry": {"coordinates":[-83.116563,42.528224],"type":"Point"}
}