{
  "type": "Feature",
  "properties": {
    "iso:country":"US",
    "sg:address":"307 W Michigan Ave",
    "sg:city":"Marshall",
    "sg:classifiers":[
        {
            "category":"Professional",
            "subcategory":"Accounting & Tax Preparation",
            "type":"Services"
        }
    ],
    "sg:phone":"+1 269 781 2206",
    "sg:postcode":"49068",
    "sg:province":"MI",
    "sg:tags":[
        "program",
        "computer",
        "custom"
    ],
    "wof:name":"Stanley M Wolk CPA",
    "wof:placetype":"venue"
},
  "geometry": {"coordinates":[-84.963368,42.271966],"type":"Point"}
}