{
  "type": "Feature",
  "properties": {
    "iso:country":"US",
    "sg:address":"6415 S Westnedge Ave",
    "sg:city":"Portage",
    "sg:classifiers":[
        {
            "category":"Restaurant",
            "type":"Food & Drink"
        }
    ],
    "sg:menulink":"http://www.allmenus.com/mi/portage/196867-burger-king/menu/",
    "sg:phone":"+1 616 323 2739",
    "sg:postcode":"49002",
    "sg:province":"MI",
    "sg:tags":[
        "burger",
        "american"
    ],
    "wof:name":"Burger King",
    "wof:placetype":"venue"
},
  "geometry": {"coordinates":[-85.58943499999999,42.224261],"type":"Point"}
}