{
  "type": "Feature",
  "properties": {
    "iso:country":"US",
    "sg:address":"8117 Macomb St",
    "sg:city":"Grosse Ile",
    "sg:classifiers":[
        {
            "category":"Personal",
            "type":"Services"
        }
    ],
    "sg:phone":"+1 734 671 6978",
    "sg:postcode":"48138",
    "sg:province":"MI",
    "sg:tags":[
        "therapist",
        "massage"
    ],
    "wof:name":"Grosse Ile Therapy",
    "wof:placetype":"venue"
},
  "geometry": {"coordinates":[-83.14633000000001,42.130203],"type":"Point"}
}