{
  "type": "Feature",
  "properties": {
    "iso:country":"US",
    "sg:address":"6497 Highland Rd",
    "sg:city":"Waterford",
    "sg:classifiers":[
        {
            "category":"Retail",
            "subcategory":"Auto Repair",
            "type":"Services"
        }
    ],
    "sg:phone":"+1 248 666 3006",
    "sg:postcode":"48327",
    "sg:province":"MI",
    "sg:tags":[
        "body"
    ],
    "wof:name":"Town & Country Collision Inc",
    "wof:placetype":"venue"
},
  "geometry": {"coordinates":[-83.416786,42.659657],"type":"Point"}
}