{
  "type": "Feature",
  "properties": {
    "iso:country":"US",
    "sg:address":"830 S Monroe St",
    "sg:city":"Monroe",
    "sg:classifiers":[
        {
            "category":"Food & Beverages",
            "subcategory":"Groceries & Convenience Stores",
            "type":"Retail Goods"
        }
    ],
    "sg:phone":"+1 734 240 2673",
    "sg:postcode":"48161",
    "sg:province":"MI",
    "sg:tags":[
        "grocer"
    ],
    "wof:name":"Elamigo",
    "wof:placetype":"venue"
},
  "geometry": {"coordinates":[-83.40458700000001,41.90821],"type":"Point"}
}