{
  "type": "Feature",
  "properties": {
    "iso:country":"US",
    "sg:address":"5424 E Grand River Ave",
    "sg:city":"Howell",
    "sg:classifiers":[
        {
            "category":"Health Services",
            "subcategory":"Chiropractor",
            "type":"Services"
        }
    ],
    "sg:phone":"+1 517 546 0603",
    "sg:postcode":"48843",
    "sg:province":"MI",
    "wof:name":"Wellness Chiropractic",
    "wof:placetype":"venue"
},
  "geometry": {"coordinates":[-83.846349,42.57726],"type":"Point"}
}