{
  "type": "Feature",
  "properties": {
    "iso:country":"US",
    "sg:address":"2420 Westbrook Dr NW",
    "sg:city":"Grand Rapids",
    "sg:classifiers":[
        {
            "category":"Professional",
            "subcategory":"Business Services",
            "type":"Services"
        }
    ],
    "sg:phone":"+1 616 735 0678",
    "sg:postcode":"49504",
    "sg:province":"MI",
    "wof:name":"Jl Enterprises",
    "wof:placetype":"venue"
},
  "geometry": {"coordinates":[-85.729589,43.004214],"type":"Point"}
}