{
  "type": "Feature",
  "properties": {
    "iso:country":"US",
    "sg:address":"14440 Tireman St",
    "sg:city":"Detroit",
    "sg:classifiers":[
        {
            "category":"Retail",
            "subcategory":"Auto Repair",
            "type":"Services"
        }
    ],
    "sg:phone":"+1 313 584 8551",
    "sg:postcode":"48228",
    "sg:province":"MI",
    "wof:name":"Sam's Auto Repair",
    "wof:placetype":"venue"
},
  "geometry": {"coordinates":[-83.185303,42.3512],"type":"Point"}
}