{
  "type": "Feature",
  "properties": {
    "iso:country":"US",
    "sg:address":"2422 Jolly Rd",
    "sg:city":"Okemos",
    "sg:classifiers":[
        {
            "category":"Health Services",
            "subcategory":"Hospital",
            "type":"Services"
        }
    ],
    "sg:phone":"+1 517 347 6944",
    "sg:postcode":"48864",
    "sg:province":"MI",
    "sg:tags":[
        "mental"
    ],
    "wof:name":"Human Systems Alignment",
    "wof:placetype":"venue"
},
  "geometry": {"coordinates":[-84.43662399999999,42.682919],"type":"Point"}
}