{
  "type": "Feature",
  "properties": {
    "iso:country":"US",
    "sg:address":"6776 Plymouth Rd",
    "sg:city":"Ann Arbor",
    "sg:classifiers":[
        {
            "category":"Professional",
            "subcategory":"Business Services",
            "type":"Services"
        }
    ],
    "sg:phone":"+1 734 741 0660",
    "sg:postcode":"48105",
    "sg:province":"MI",
    "wof:name":"A&D Sales",
    "wof:placetype":"venue"
},
  "geometry": {"coordinates":[-83.63169499999999,42.322592],"type":"Point"}
}