{
  "type": "Feature",
  "properties": {
    "iso:country":"US",
    "sg:address":"4505 Morey Hwy",
    "sg:city":"Clayton",
    "sg:classifiers":[
        {
            "category":"Personal",
            "subcategory":"Beauty Salon",
            "type":"Services"
        }
    ],
    "sg:phone":"+1 517 445 2236",
    "sg:postcode":"49235",
    "sg:province":"MI",
    "sg:tags":[
        "shop"
    ],
    "wof:name":"Velma's Beauty Shop",
    "wof:placetype":"venue"
},
  "geometry": {"coordinates":[-84.23629800000001,41.857089],"type":"Point"}
}