{
  "type": "Feature",
  "properties": {
    "iso:country":"US",
    "sg:address":"233 S County Line Rd",
    "sg:city":"Union City",
    "sg:classifiers":[
        {
            "category":"Farming",
            "subcategory":"Farm",
            "type":"Manufacturing & Wholesale Goods"
        }
    ],
    "sg:phone":"+1 517 741 3156",
    "sg:postcode":"49094",
    "sg:province":"MI",
    "sg:tags":[
        "crop",
        "general"
    ],
    "wof:name":"Brubaker John",
    "wof:placetype":"venue"
},
  "geometry": {"coordinates":[-85.13855,42.072477],"type":"Point"}
}