{
  "type": "Feature",
  "properties": {
    "iso:country":"US",
    "sg:address":"10792 Creighton Rd SW",
    "sg:city":"Fife Lake",
    "sg:classifiers":[
        {
            "category":"Manufacturing",
            "subcategory":"Tools & Machinery",
            "type":"Manufacturing & Wholesale Goods"
        }
    ],
    "sg:phone":"+1 231 879 4406",
    "sg:postcode":"49633",
    "sg:province":"MI",
    "sg:tags":[
        "machine",
        "shop"
    ],
    "wof:name":"Recon Equipment Inc",
    "wof:placetype":"venue"
},
  "geometry": {"coordinates":[-85.252956,44.558055],"type":"Point"}
}