{
  "type": "Feature",
  "properties": {
    "iso:country":"US",
    "sg:address":"1300 Robin Rd",
    "sg:city":"Muskegon",
    "sg:classifiers":[
        {
            "category":"Wholesale",
            "subcategory":"Computers",
            "type":"Manufacturing & Wholesale Goods"
        }
    ],
    "sg:phone":"+1 231 744 1015",
    "sg:postcode":"49445",
    "sg:province":"MI",
    "sg:tags":[
        "added",
        "value",
        "reseller"
    ],
    "wof:name":"Alternate Computer Supply",
    "wof:placetype":"venue"
},
  "geometry": {"coordinates":[-86.21125600000001,43.288808],"type":"Point"}
}