{
  "type": "Feature",
  "properties": {
    "iso:country":"US",
    "sg:address":"1505 E Lansing Dr",
    "sg:city":"East Lansing",
    "sg:classifiers":[
        {
            "category":"Building & Trades",
            "subcategory":"Cleaning & Sanitation",
            "type":"Services"
        }
    ],
    "sg:phone":"+1 517 332 2485",
    "sg:postcode":"48823",
    "sg:province":"MI",
    "sg:tags":[
        "maintenance"
    ],
    "wof:name":"Care In Devaults Cleaning",
    "wof:placetype":"venue"
},
  "geometry": {"coordinates":[-84.452394,42.748601],"type":"Point"}
}