{
  "type": "Feature",
  "properties": {
    "iso:country":"US",
    "sg:address":"15354 Vaughan St",
    "sg:city":"Detroit",
    "sg:classifiers":[
        {
            "category":"Real Estate",
            "subcategory":"Real Estate Operator",
            "type":"Services"
        }
    ],
    "sg:phone":"+1 313 592 0018",
    "sg:postcode":"48223",
    "sg:province":"MI",
    "sg:tags":[
        "property",
        "lessor"
    ],
    "wof:name":"Jbl Property Mgmt & Investment",
    "wof:placetype":"venue"
},
  "geometry": {"coordinates":[-83.23846399999999,42.401469],"type":"Point"}
}