{
  "type": "Feature",
  "properties": {
    "iso:country":"US",
    "sg:address":"1770 Fort St",
    "sg:city":"Lincoln Park",
    "sg:classifiers":[
        {
            "category":"Insurance",
            "subcategory":"Insurance Agent",
            "type":"Services"
        }
    ],
    "sg:phone":"+1 313 388 7782",
    "sg:postcode":"48146",
    "sg:province":"MI",
    "wof:name":"Associated Group Underwriters",
    "wof:placetype":"venue"
},
  "geometry": {"coordinates":[-83.17714700000001,42.250545],"type":"Point"}
}