{
  "type": "Feature",
  "properties": {
    "iso:country":"US",
    "sg:address":"6025 N Dort Hwy",
    "sg:city":"Flint",
    "sg:classifiers":[
        {
            "category":"Autos & Motor Vehicles",
            "subcategory":"Automobile Sales",
            "type":"Retail Goods"
        },
        {
            "category":"Autos & Motor Vehicles",
            "subcategory":"Auto Supplies",
            "type":"Retail Goods"
        },
        {
            "category":"Wholesale",
            "subcategory":"Auto Parts",
            "type":"Manufacturing & Wholesale Goods"
        }
    ],
    "sg:phone":"+1 810 787 0142",
    "sg:postcode":"48505",
    "sg:province":"MI",
    "sg:tags":[
        "body",
        "used",
        "car",
        "equipment",
        "rebuilt-wholesale",
        "supplies-used",
        "truck",
        "rebuilt",
        "salvage",
        "manufacturer"
    ],
    "sg:website":"http://www.rpmcarparts.com",
    "wof:name":"RPM Wholesale Auto & Parts & Auto Salvage",
    "wof:placetype":"venue"
},
  "geometry": {"coordinates":[-83.674027,43.067011],"type":"Point"}
}