{
  "type": "Feature",
  "properties": {
    "iso:country":"US",
    "sg:address":"20045 Mack Ave",
    "sg:city":"Grosse Pointe",
    "sg:classifiers":[
        {
            "category":"Health Services",
            "subcategory":"Doctor",
            "type":"Services"
        },
        {
            "category":"Personal",
            "subcategory":"Hair Removal",
            "type":"Services"
        }
    ],
    "sg:phone":"+1 313 884 5100",
    "sg:postcode":"48236",
    "sg:province":"MI",
    "sg:tags":[
        "laser",
        "dermatologist"
    ],
    "wof:name":"Ferrara Richard J Sr MD",
    "wof:placetype":"venue"
},
  "geometry": {"coordinates":[-82.908798,42.4333],"type":"Point"}
}