{
  "type": "Feature",
  "properties": {
    "iso:country":"US",
    "sg:address":"506 N State Rd",
    "sg:city":"Owosso",
    "sg:classifiers":[
        {
            "category":"Shopping",
            "subcategory":"Gifts & Souvenirs",
            "type":"Retail Goods"
        }
    ],
    "sg:phone":"+1 989 743 6030",
    "sg:postcode":"48867",
    "sg:province":"MI",
    "wof:name":"D & L Gifts",
    "wof:placetype":"venue"
},
  "geometry": {"coordinates":[-84.118932,43.003919],"type":"Point"}
}