{
  "type": "Feature",
  "properties": {
    "iso:country":"US",
    "sg:address":"10447 Argentine Rd",
    "sg:city":"Linden",
    "sg:classifiers":[
        {
            "category":"Manufacturing",
            "subcategory":"Tools & Machinery",
            "type":"Manufacturing & Wholesale Goods"
        }
    ],
    "sg:phone":"+1 810 735 9170",
    "sg:postcode":"48451",
    "sg:province":"MI",
    "sg:tags":[
        "hose",
        "reel",
        "rack"
    ],
    "wof:name":"Rokan Corp",
    "wof:placetype":"venue"
},
  "geometry": {"coordinates":[-83.84364600000001,42.749812],"type":"Point"}
}