{
  "type": "Feature",
  "properties": {
    "iso:country":"US",
    "sg:address":"19395 Keystone St",
    "sg:city":"Detroit",
    "sg:classifiers":[
        {
            "category":"Freight",
            "type":"Transportation"
        }
    ],
    "sg:phone":"+1 313 366 8259",
    "sg:postcode":"48234",
    "sg:province":"MI",
    "sg:tags":[
        "operator",
        "local",
        "trucking"
    ],
    "wof:name":"Hudgins Trucking Inc",
    "wof:placetype":"venue"
},
  "geometry": {"coordinates":[-83.05170099999999,42.437545],"type":"Point"}
}