{
  "type": "Feature",
  "properties": {
    "iso:country":"US",
    "sg:address":"26151 Gratiot Ave",
    "sg:city":"Roseville",
    "sg:classifiers":[
        {
            "category":"Home & Garden",
            "subcategory":"Furniture",
            "type":"Retail Goods"
        }
    ],
    "sg:phone":"+1 586 777 3973",
    "sg:postcode":"48066",
    "sg:province":"MI",
    "sg:tags":[
        "store"
    ],
    "wof:name":"Mattress Superstore",
    "wof:placetype":"venue"
},
  "geometry": {"coordinates":[-82.942511,42.488875],"type":"Point"}
}