{
  "type": "Feature",
  "properties": {
    "iso:country":"US",
    "sg:address":"1623 Colwood Rd",
    "sg:city":"Caro",
    "sg:classifiers":[
        {
            "category":"Building & Trades",
            "subcategory":"Landscaping Services",
            "type":"Services"
        }
    ],
    "sg:phone":"+1 989 673 7109",
    "sg:postcode":"48723",
    "sg:province":"MI",
    "wof:name":"Lajoies Lawn Service",
    "wof:placetype":"venue"
},
  "geometry": {"coordinates":[-83.348179,43.510597],"type":"Point"}
}