{
  "type": "Feature",
  "properties": {
    "iso:country":"US",
    "sg:address":"380 Eastlawn Dr",
    "sg:city":"Rochester Hills",
    "sg:classifiers":[
        {
            "category":"Professional",
            "subcategory":"Accounting & Tax Preparation",
            "type":"Services"
        },
        {
            "category":"Shopping",
            "subcategory":"Computers & Home Electronics",
            "type":"Retail Goods"
        }
    ],
    "sg:phone":"+1 248 852 6596",
    "sg:postcode":"48307",
    "sg:province":"MI",
    "sg:tags":[
        "return",
        "software"
    ],
    "sg:website":"www.acctware.com",
    "wof:name":"Acctware Business Systems",
    "wof:placetype":"venue"
},
  "geometry": {"coordinates":[-83.128474,42.62445],"type":"Point"}
}