{
  "type": "Feature",
  "properties": {
    "iso:country":"US",
    "sg:address":"18640 S Tilson Rd",
    "sg:city":"Rudyard",
    "sg:classifiers":[
        {
            "category":"Organizations",
            "subcategory":"Community Association",
            "type":"Services"
        }
    ],
    "sg:phone":"+1 906 478 5281",
    "sg:postcode":"49780",
    "sg:province":"MI",
    "wof:name":"International Assoc of LI",
    "wof:placetype":"venue"
},
  "geometry": {"coordinates":[-84.592555,46.236433],"type":"Point"}
}