{
  "type": "Feature",
  "properties": {
    "iso:country":"US",
    "sg:address":"3629 Duke St",
    "sg:city":"Kalamazoo",
    "sg:classifiers":[
        {
            "category":"Real Estate",
            "subcategory":"Real Estate Operator",
            "type":"Services"
        }
    ],
    "sg:phone":"+1 269 345 7938",
    "sg:postcode":"49008",
    "sg:province":"MI",
    "sg:tags":[
        "building",
        "apartment"
    ],
    "wof:name":"Carroll Panse Properties Inc",
    "wof:placetype":"venue"
},
  "geometry": {"coordinates":[-85.594454,42.254721],"type":"Point"}
}