{
  "type": "Feature",
  "properties": {
    "iso:country":"US",
    "sg:address":"1310 W 14 Mile Rd",
    "sg:city":"Clawson",
    "sg:classifiers":[
        {
            "category":"Recreation",
            "type":"Entertainment"
        }
    ],
    "sg:phone":"+1 248 616 0960",
    "sg:postcode":"48017",
    "sg:province":"MI",
    "sg:tags":[
        "amusement"
    ],
    "wof:name":"Renaissance Fencing Club",
    "wof:placetype":"venue"
},
  "geometry": {"coordinates":[-83.16161700000001,42.533219],"type":"Point"}
}