{
  "type": "Feature",
  "properties": {
    "iso:country":"US",
    "sg:address":"15381 Hallmark Dr",
    "sg:city":"Macomb",
    "sg:classifiers":[
        {
            "category":"Manufacturing",
            "subcategory":"Tools & Machinery",
            "type":"Manufacturing & Wholesale Goods"
        }
    ],
    "sg:phone":"+1 586 786 0080",
    "sg:postcode":"48042",
    "sg:province":"MI",
    "sg:tags":[
        "machine"
    ],
    "sg:website":"www.jointproduction.net",
    "wof:name":"JPT Joint Production Tech",
    "wof:placetype":"venue"
},
  "geometry": {"coordinates":[-82.97457300000001,42.675033],"type":"Point"}
}