{
  "type": "Feature",
  "properties": {
    "iso:country":"US",
    "sg:address":"3814 Leslie St",
    "sg:city":"Detroit",
    "sg:classifiers":[
        {
            "category":"Retail",
            "subcategory":"Portrait Studio",
            "type":"Services"
        }
    ],
    "sg:phone":"+1 313 491 3916",
    "sg:postcode":"48238",
    "sg:province":"MI",
    "sg:tags":[
        "photo"
    ],
    "wof:name":"Fgs Photography",
    "wof:placetype":"venue"
},
  "geometry": {"coordinates":[-83.130313,42.385513],"type":"Point"}
}