{
  "type": "Feature",
  "properties": {
    "iso:country":"US",
    "sg:address":"14695 16th Ave",
    "sg:city":"Marne",
    "sg:classifiers":[
        {
            "category":"Banks & Credit Unions",
            "subcategory":"Bank",
            "type":"Services"
        }
    ],
    "sg:phone":"+1 616 677 1264",
    "sg:postcode":"49435",
    "sg:province":"MI",
    "wof:name":"Comerica Bank",
    "wof:placetype":"venue"
},
  "geometry": {"coordinates":[-85.827703,43.037319],"type":"Point"}
}