{
  "type": "Feature",
  "properties": {
    "iso:country":"US",
    "sg:address":"1684 Rochester Rd",
    "sg:city":"Troy",
    "sg:classifiers":[
        {
            "category":"Manufacturing",
            "subcategory":"Signs",
            "type":"Manufacturing & Wholesale Goods"
        }
    ],
    "sg:phone":"+1 248 689 2158",
    "sg:postcode":"48083",
    "sg:province":"MI",
    "sg:tags":[
        "mfg",
        "assembles",
        "show",
        "trade",
        "item",
        "custom",
        "display"
    ],
    "sg:website":"www.displaymanufacturing.com",
    "wof:name":"Display Manufacturing Inc",
    "wof:placetype":"venue"
},
  "geometry": {"coordinates":[-83.131837,42.549715],"type":"Point"}
}