{
  "type": "Feature",
  "properties": {
    "iso:country":"US",
    "sg:address":"44491 N Groesbeck Hwy",
    "sg:city":"Clinton Twp",
    "sg:classifiers":[
        {
            "category":"Organizations",
            "subcategory":"Membership Organization",
            "type":"Services"
        }
    ],
    "sg:phone":"+1 586 469 2582",
    "sg:postcode":"48036",
    "sg:province":"MI",
    "sg:tags":[
        "athletic"
    ],
    "wof:name":"Cutting Edge Athletics",
    "wof:placetype":"venue"
},
  "geometry": {"coordinates":[-82.876285,42.627688],"type":"Point"}
}