{
  "type": "Feature",
  "properties": {
    "iso:country":"US",
    "sg:address":"1496 Treanor St",
    "sg:city":"Saginaw",
    "sg:classifiers":[
        {
            "category":"Manufacturing",
            "subcategory":"Metals",
            "type":"Manufacturing & Wholesale Goods"
        }
    ],
    "sg:phone":"+1 989 754 8877",
    "sg:postcode":"48601",
    "sg:province":"MI",
    "sg:tags":[
        "steel"
    ],
    "wof:name":"T & K Steel Inc",
    "wof:placetype":"venue"
},
  "geometry": {"coordinates":[-83.927801,43.393164],"type":"Point"}
}