{
  "type": "Feature",
  "properties": {
    "iso:country":"US",
    "sg:address":"30150 Telegraph Rd",
    "sg:city":"Bingham Farms",
    "sg:classifiers":[
        {
            "category":"Recreation",
            "type":"Entertainment"
        }
    ],
    "sg:phone":"+1 248 593 1100",
    "sg:postcode":"48025",
    "sg:province":"MI",
    "sg:tags":[
        "ticket"
    ],
    "wof:name":"Ticketmaster",
    "wof:placetype":"venue"
},
  "geometry": {"coordinates":[-83.28525,42.510376],"type":"Point"}
}