{
  "type": "Feature",
  "properties": {
    "iso:country":"US",
    "sg:address":"2724 Emmons Ave",
    "sg:city":"Rochester Hills",
    "sg:classifiers":[
        {
            "category":"Building & Trades",
            "subcategory":"Construction",
            "type":"Services"
        }
    ],
    "sg:phone":"+1 248 299 7995",
    "sg:postcode":"48307",
    "sg:province":"MI",
    "sg:tags":[
        "masonry",
        "contractor"
    ],
    "wof:name":"Dunn Masonry",
    "wof:placetype":"venue"
},
  "geometry": {"coordinates":[-83.100883,42.640437],"type":"Point"}
}