{
  "type": "Feature",
  "properties": {
    "iso:country":"US",
    "sg:address":"5895 John R Rd",
    "sg:city":"Troy",
    "sg:classifiers":[
        {
            "category":"Health Services",
            "subcategory":"Doctor",
            "type":"Services"
        }
    ],
    "sg:phone":"+1 248 879 5885",
    "sg:postcode":"48085",
    "sg:province":"MI",
    "wof:name":"Emerald Lake Dental",
    "wof:placetype":"venue"
},
  "geometry": {"coordinates":[-83.11012700000001,42.604993],"type":"Point"}
}