{
  "type": "Feature",
  "properties": {
    "iso:country":"US",
    "sg:address":"9540 Gratiot Rd",
    "sg:city":"Saginaw",
    "sg:classifiers":[
        {
            "category":"Recreation",
            "type":"Entertainment"
        }
    ],
    "sg:phone":"+1 989 781 2260",
    "sg:postcode":"48609",
    "sg:province":"MI",
    "sg:tags":[
        "club",
        "membership"
    ],
    "wof:name":"Saginaw Gun Club Inc",
    "wof:placetype":"venue"
},
  "geometry": {"coordinates":[-84.10192000000001,43.416254],"type":"Point"}
}