{
  "type": "Feature",
  "properties": {
    "iso:country":"US",
    "sg:address":"721 W Blue Star Dr",
    "sg:city":"Traverse City",
    "sg:classifiers":[
        {
            "category":"Shopping",
            "type":"Retail Goods"
        }
    ],
    "sg:phone":"+1 231 943 3156",
    "sg:postcode":"49684",
    "sg:province":"MI",
    "sg:tags":[
        "plastic"
    ],
    "wof:name":"Plastic Center",
    "wof:placetype":"venue"
},
  "geometry": {"coordinates":[-85.655162,44.697308],"type":"Point"}
}