{
  "type": "Feature",
  "properties": {
    "iso:country":"US",
    "sg:address":"19350 Flamingo Blvd",
    "sg:city":"Livonia",
    "sg:classifiers":[
        {
            "category":"Professional",
            "subcategory":"Business Services",
            "type":"Services"
        }
    ],
    "sg:phone":"+1 248 477 1889",
    "sg:postcode":"48152",
    "sg:province":"MI",
    "wof:name":"Teeters Enterprises Inc",
    "wof:placetype":"venue"
},
  "geometry": {"coordinates":[-83.348145,42.429923],"type":"Point"}
}