{
  "type": "Feature",
  "properties": {
    "iso:country":"US",
    "sg:address":"9185 Cherry Valley Ave SE",
    "sg:city":"Caledonia",
    "sg:classifiers":[
        {
            "category":"Shopping",
            "subcategory":"Computers & Home Electronics",
            "type":"Retail Goods"
        }
    ],
    "sg:phone":"+1 616 891 5800",
    "sg:postcode":"49316",
    "sg:province":"MI",
    "sg:tags":[
        "software"
    ],
    "wof:name":"Solid Works",
    "wof:placetype":"venue"
},
  "geometry": {"coordinates":[-85.50708400000001,42.799183],"type":"Point"}
}