{
  "type": "Feature",
  "properties": {
    "iso:country":"US",
    "sg:address":"6352 Fulton St E",
    "sg:city":"Ada",
    "sg:classifiers":[
        {
            "category":"Building & Trades",
            "subcategory":"Construction",
            "type":"Services"
        }
    ],
    "sg:phone":"+1 616 676 8189",
    "sg:postcode":"49301",
    "sg:province":"MI",
    "sg:tags":[
        "masonry",
        "contractor"
    ],
    "wof:name":"Staytrue Construction Inc",
    "wof:placetype":"venue"
},
  "geometry": {"coordinates":[-85.51666299999999,42.962565],"type":"Point"}
}