{
  "type": "Feature",
  "properties": {
    "iso:country":"US",
    "sg:address":"202 Chinkapin Rill",
    "sg:city":"Fenton",
    "sg:classifiers":[
        {
            "category":"Professional",
            "subcategory":"Computer Services",
            "type":"Services"
        }
    ],
    "sg:phone":"+1 810 629 9239",
    "sg:postcode":"48430",
    "sg:province":"MI",
    "sg:tags":[
        "design",
        "system"
    ],
    "wof:name":"Modern Tech Web Design",
    "wof:placetype":"venue"
},
  "geometry": {"coordinates":[-83.74371600000001,42.785443],"type":"Point"}
}