{
  "type": "Feature",
  "properties": {
    "iso:country":"US",
    "sg:address":"3234 Greenbriar",
    "sg:city":"Harbor Springs",
    "sg:classifiers":[
        {
            "category":"Professional",
            "type":"Services"
        }
    ],
    "sg:phone":"+1 231 526 4211",
    "sg:postcode":"49740",
    "sg:province":"MI",
    "wof:name":"Up North Svc",
    "wof:placetype":"venue"
},
  "geometry": {"coordinates":[-85.035312,45.473694],"type":"Point"}
}