{
  "type": "Feature",
  "properties": {
    "iso:country":"US",
    "sg:address":"6522 Willow Bend Dr",
    "sg:city":"Lansing",
    "sg:classifiers":[
        {
            "category":"Retail",
            "subcategory":"Repair Shop",
            "type":"Services"
        }
    ],
    "sg:phone":"+1 517 323 3459",
    "sg:postcode":"48917",
    "sg:province":"MI",
    "wof:name":"Wayne B Castle",
    "wof:placetype":"venue"
},
  "geometry": {"coordinates":[-84.646244,42.757984],"type":"Point"}
}