{
  "type": "Feature",
  "properties": {
    "iso:country":"US",
    "sg:address":"31995 Northwestern Hwy",
    "sg:city":"Farmington",
    "sg:classifiers":[
        {
            "category":"Health Services",
            "subcategory":"Doctor",
            "type":"Services"
        }
    ],
    "sg:phone":"+1 248 538 1000",
    "sg:postcode":"48334",
    "sg:province":"MI",
    "sg:tags":[
        "medical"
    ],
    "wof:name":"Clinical Oncology Associates",
    "wof:placetype":"venue"
},
  "geometry": {"coordinates":[-83.34534499999999,42.522291],"type":"Point"}
}