{
  "type": "Feature",
  "properties": {
    "iso:country":"US",
    "sg:address":"5187 Mattawa Dr",
    "sg:city":"Clarkston",
    "sg:classifiers":[
        {
            "category":"Education",
            "subcategory":"Special Training",
            "type":"Public Place"
        }
    ],
    "sg:phone":"+1 248 969 8992",
    "sg:postcode":"48348",
    "sg:province":"MI",
    "wof:name":"Multiverse Knowledge",
    "wof:placetype":"venue"
},
  "geometry": {"coordinates":[-83.36082399999999,42.784372],"type":"Point"}
}