{
  "type": "Feature",
  "properties": {
    "iso:country":"US",
    "sg:address":"34312 Manor Run Cir",
    "sg:city":"Sterling Heights",
    "sg:classifiers":[
        {
            "category":"Building & Trades",
            "subcategory":"Locksmith",
            "type":"Services"
        }
    ],
    "sg:phone":"+1 586 819 0907",
    "sg:postcode":"48312",
    "sg:province":"MI",
    "sg:tags":[
        "key"
    ],
    "wof:name":"Locksmith",
    "wof:placetype":"venue"
},
  "geometry": {"coordinates":[-82.991235,42.547806],"type":"Point"}
}