{
  "type": "Feature",
  "properties": {
    "iso:country":"US",
    "sg:address":"67529 S Main St",
    "sg:city":"Richmond",
    "sg:classifiers":[
        {
            "category":"Health Services",
            "subcategory":"Doctor",
            "type":"Services"
        }
    ],
    "sg:phone":"+1 586 727 0898",
    "sg:postcode":"48062",
    "sg:province":"MI",
    "sg:tags":[
        "medical"
    ],
    "wof:name":"Childrens Health Care",
    "wof:placetype":"venue"
},
  "geometry": {"coordinates":[-82.739104,42.798203],"type":"Point"}
}