{
  "type": "Feature",
  "properties": {
    "iso:country":"US",
    "sg:address":"18879 Gill Rd",
    "sg:city":"Livonia",
    "sg:classifiers":[
        {
            "category":"Shopping",
            "subcategory":"Crafts & Fabrics",
            "type":"Retail Goods"
        }
    ],
    "sg:phone":"+1 248 474 6785",
    "sg:postcode":"48152",
    "sg:province":"MI",
    "sg:tags":[
        "sewing"
    ],
    "wof:name":"Accent Stitchery",
    "wof:placetype":"venue"
},
  "geometry": {"coordinates":[-83.384664,42.422704],"type":"Point"}
}