{
  "type": "Feature",
  "properties": {
    "iso:country":"US",
    "sg:address":"1000 Yale Ave",
    "sg:city":"Bessemer",
    "sg:classifiers":[
        {
            "category":"Home & Garden",
            "subcategory":"Building Materials",
            "type":"Retail Goods"
        }
    ],
    "sg:phone":"+1 906 667 0277",
    "sg:postcode":"49911",
    "sg:province":"MI",
    "sg:tags":[
        "plywood",
        "veneer"
    ],
    "wof:name":"Bessemer Plywood Corp",
    "wof:placetype":"venue"
},
  "geometry": {"coordinates":[-90.06761299999999,46.468099],"type":"Point"}
}