{
  "type": "Feature",
  "properties": {
    "iso:country":"US",
    "sg:address":"4401 N Campus Ridge Dr",
    "sg:city":"Midland",
    "sg:classifiers":[
        {
            "category":"Health Services",
            "subcategory":"Health Practitioner",
            "type":"Services"
        }
    ],
    "sg:phone":"+1 989 837 9400",
    "sg:postcode":"48640",
    "sg:province":"MI",
    "sg:tags":[
        "medical"
    ],
    "wof:name":"Sundstrom Renee Do",
    "wof:placetype":"venue"
},
  "geometry": {"coordinates":[-84.261285,43.639762],"type":"Point"}
}