{
  "type": "Feature",
  "properties": {
    "iso:country":"US",
    "sg:address":"1217 E Center St",
    "sg:city":"Ithaca",
    "sg:classifiers":[
        {
            "category":"Retail",
            "subcategory":"Auto Repair",
            "type":"Services"
        }
    ],
    "sg:phone":"+1 989 875 7705",
    "sg:postcode":"48847",
    "sg:province":"MI",
    "sg:tags":[
        "automotive"
    ],
    "wof:name":"Gratiot Oil & Lube LLC",
    "wof:placetype":"venue"
},
  "geometry": {"coordinates":[-84.591472,43.291727],"type":"Point"}
}