{
  "type": "Feature",
  "properties": {
    "iso:country":"US",
    "sg:address":"150 Cass Ave",
    "sg:city":"Mt Clemens",
    "sg:classifiers":[
        {
            "category":"Education",
            "subcategory":"Library",
            "type":"Public Place"
        }
    ],
    "sg:phone":"+1 586 469 6200",
    "sg:postcode":"48043",
    "sg:province":"MI",
    "sg:tags":[
        "executive"
    ],
    "sg:website":"www.libcoop.net/mountclemens",
    "wof:name":"Mount Clemens Public Library",
    "wof:placetype":"venue"
},
  "geometry": {"coordinates":[-82.884642,42.597493],"type":"Point"}
}