{
  "type": "Feature",
  "properties": {
    "iso:country":"US",
    "sg:address":"119 W Bridge St",
    "sg:city":"Plainwell",
    "sg:classifiers":[
        {
            "category":"Wholesale",
            "subcategory":"Farm Supplies",
            "type":"Manufacturing & Wholesale Goods"
        },
        {
            "category":"Train Station",
            "subcategory":"Rail",
            "type":"Transportation"
        }
    ],
    "sg:phone":"+1 269 685 8571",
    "sg:postcode":"49080",
    "sg:province":"MI",
    "sg:tags":[
        "equipment",
        "part",
        "tractor"
    ],
    "wof:name":"A H Warnement Sons",
    "wof:placetype":"venue"
},
  "geometry": {"coordinates":[-85.642123,42.442789],"type":"Point"}
}