{
  "type": "Feature",
  "properties": {
    "iso:country":"US",
    "sg:address":"3851 Auburn Rd",
    "sg:city":"Auburn Hills",
    "sg:classifiers":[
        {
            "category":"Home & Garden",
            "subcategory":"Building Materials",
            "type":"Retail Goods"
        }
    ],
    "sg:phone":"+1 248 852 7050",
    "sg:postcode":"48326",
    "sg:province":"MI",
    "sg:tags":[
        "door"
    ],
    "wof:name":"Gamalski Building Specialties",
    "wof:placetype":"venue"
},
  "geometry": {"coordinates":[-83.21253400000001,42.633997],"type":"Point"}
}