{
  "type": "Feature",
  "properties": {
    "iso:country":"US",
    "sg:address":"1699 Dutcher Rd",
    "sg:city":"Howell",
    "sg:classifiers":[
        {
            "category":"Professional",
            "subcategory":"Business Services",
            "type":"Services"
        }
    ],
    "sg:phone":"+1 517 546 8389",
    "sg:postcode":"48843",
    "sg:province":"MI",
    "sg:tags":[
        "paper",
        "lamination"
    ],
    "wof:name":"Larry's Lamination & Trim",
    "wof:placetype":"venue"
},
  "geometry": {"coordinates":[-84.03029600000001,42.572202],"type":"Point"}
}