{
  "type": "Feature",
  "properties": {
    "iso:country":"US",
    "sg:address":"1811 N Mason St",
    "sg:city":"Saginaw",
    "sg:classifiers":[
        {
            "category":"Shopping",
            "subcategory":"Gifts & Souvenirs",
            "type":"Retail Goods"
        }
    ],
    "sg:phone":"+1 989 921 6209",
    "sg:postcode":"48602",
    "sg:province":"MI",
    "sg:tags":[
        "party",
        "supply"
    ],
    "wof:name":"Party Lite",
    "wof:placetype":"venue"
},
  "geometry": {"coordinates":[-83.960796,43.434007],"type":"Point"}
}