{
  "type": "Feature",
  "properties": {
    "iso:country":"US",
    "sg:address":"2903 Bent Oak Hwy",
    "sg:city":"Adrian",
    "sg:classifiers":[
        {
            "category":"Organizations",
            "subcategory":"Religious Organization",
            "type":"Services"
        }
    ],
    "sg:phone":"+1 517 265 5285",
    "sg:postcode":"49221",
    "sg:province":"MI",
    "sg:tags":[
        "church"
    ],
    "sg:website":"www.proclaimliberty.com",
    "wof:name":"Church-Lord Jesus Christ",
    "wof:placetype":"venue"
},
  "geometry": {"coordinates":[-84.03516399999999,41.920947],"type":"Point"}
}