{
  "type": "Feature",
  "properties": {
    "iso:country":"US",
    "sg:address":"2249 Rosemary Ave",
    "sg:city":"Waterford",
    "sg:classifiers":[
        {
            "category":"Home & Garden",
            "subcategory":"Garden Supply",
            "type":"Retail Goods"
        }
    ],
    "sg:phone":"+1 248 674 9002",
    "sg:postcode":"48328",
    "sg:province":"MI",
    "sg:tags":[
        "sprinkler"
    ],
    "wof:name":"Aqua Master Sprinklers",
    "wof:placetype":"venue"
},
  "geometry": {"coordinates":[-83.33817500000001,42.67306],"type":"Point"}
}