{
  "type": "Feature",
  "properties": {
    "iso:country":"US",
    "sg:address":"844 W Michigan Ave",
    "sg:city":"Marshall",
    "sg:classifiers":[
        {
            "category":"Restaurant",
            "type":"Food & Drink"
        }
    ],
    "sg:phone":"+1 269 781 9178",
    "sg:postcode":"49068",
    "sg:province":"MI",
    "sg:tags":[
        "banquet",
        "rooms"
    ],
    "wof:name":"Boardwalk Banquet Ctr",
    "wof:placetype":"venue"
},
  "geometry": {"coordinates":[-84.971968,42.272104],"type":"Point"}
}