{
  "type": "Feature",
  "properties": {
    "iso:country":"US",
    "sg:address":"1044 Runway Dr SW",
    "sg:city":"Byron Center",
    "sg:classifiers":[
        {
            "category":"Home & Garden",
            "subcategory":"Garden Supply",
            "type":"Retail Goods"
        }
    ],
    "sg:phone":"+1 616 530 5555",
    "sg:postcode":"49315",
    "sg:province":"MI",
    "sg:tags":[
        "sprinkler"
    ],
    "wof:name":"Superior Lawn Sprinkling",
    "wof:placetype":"venue"
},
  "geometry": {"coordinates":[-85.68966500000001,42.843468],"type":"Point"}
}