{
  "type": "Feature",
  "properties": {
    "iso:country":"US",
    "sg:address":"2614 E Grand River Ave",
    "sg:city":"Howell",
    "sg:classifiers":[
        {
            "category":"Personal",
            "subcategory":"Beauty Salon",
            "type":"Services"
        }
    ],
    "sg:phone":"+1 517 545 1883",
    "sg:postcode":"48843",
    "sg:province":"MI",
    "sg:tags":[
        "shop"
    ],
    "wof:name":"Look Hair Salon",
    "wof:placetype":"venue"
},
  "geometry": {"coordinates":[-83.901675,42.596735],"type":"Point"}
}