{
  "type": "Feature",
  "properties": {
    "iso:country":"US",
    "sg:address":"413 Bard St",
    "sg:city":"Port Huron",
    "sg:classifiers":[
        {
            "category":"Real Estate",
            "subcategory":"Architect",
            "type":"Services"
        }
    ],
    "sg:phone":"+1 810 985 3511",
    "sg:postcode":"48060",
    "sg:province":"MI",
    "wof:name":"William Vogan Architects",
    "wof:placetype":"venue"
},
  "geometry": {"coordinates":[-82.42431000000001,42.980431],"type":"Point"}
}