{
  "type": "Feature",
  "properties": {
    "iso:country":"US",
    "sg:address":"43861 N Gratiot Ave",
    "sg:city":"Clinton Township",
    "sg:classifiers":[
        {
            "category":"Personal",
            "type":"Services"
        },
        {
            "category":"Retail",
            "subcategory":"Storage",
            "type":"Services"
        }
    ],
    "sg:phone":"+1 586 228 8480",
    "sg:postcode":"48036",
    "sg:province":"MI",
    "sg:tags":[
        "mover",
        "self"
    ],
    "wof:name":"Budget Rent A Car System Inc",
    "wof:placetype":"venue"
},
  "geometry": {"coordinates":[-82.866997,42.618301],"type":"Point"}
}