{
  "type": "Feature",
  "properties": {
    "iso:country":"US",
    "sg:address":"1343 US Hwy 41",
    "sg:city":"Bark River",
    "sg:classifiers":[
        {
            "category":"Insurance",
            "subcategory":"Insurance Agent",
            "type":"Services"
        }
    ],
    "sg:phone":"+1 906 466 9927",
    "sg:postcode":"49807",
    "sg:province":"MI",
    "wof:name":"Bergman Insurance",
    "wof:placetype":"venue"
},
  "geometry": {"coordinates":[-87.303051,45.710772],"type":"Point"}
}