{
  "type": "Feature",
  "properties": {
    "iso:country":"US",
    "sg:address":"15851 W McNichols At Prevost",
    "sg:city":"Detroit",
    "sg:classifiers":[
        {
            "category":"Retail",
            "subcategory":"Auto Repair",
            "type":"Services"
        }
    ],
    "sg:phone":"+1 313 270 2663",
    "sg:postcode":"48201",
    "sg:province":"MI",
    "wof:name":"National Auto Center Inc",
    "wof:placetype":"venue"
},
  "geometry": {"coordinates":[-83.202904,42.415758],"type":"Point"}
}