{
  "type": "Feature",
  "properties": {
    "iso:country":"US",
    "sg:address":"5601 N Saginaw St",
    "sg:city":"Flint",
    "sg:classifiers":[
        {
            "category":"Organizations",
            "subcategory":"Religious Organization",
            "type":"Services"
        }
    ],
    "sg:phone":"+1 810 785 9730",
    "sg:postcode":"48505",
    "sg:province":"MI",
    "wof:name":"Liberty Christian Church",
    "wof:placetype":"venue"
},
  "geometry": {"coordinates":[-83.693901,43.065127],"type":"Point"}
}