{
  "type": "Feature",
  "properties": {
    "iso:country":"US",
    "sg:address":"305 N Zeeb Rd",
    "sg:city":"Ann Arbor",
    "sg:classifiers":[
        {
            "category":"Restaurant",
            "type":"Food & Drink"
        }
    ],
    "sg:menulink":"http://www.allmenus.com/mi/scio/247731-metzgers/menu/",
    "sg:phone":"+1 734 668 8987",
    "sg:postcode":"48103",
    "sg:province":"MI",
    "sg:tags":[
        "german"
    ],
    "wof:name":"Metzger's",
    "wof:placetype":"venue"
},
  "geometry": {"coordinates":[-83.838688,42.293375],"type":"Point"}
}