{
  "type": "Feature",
  "properties": {
    "iso:country":"US",
    "sg:address":"47037 Gratiot Ave",
    "sg:city":"New Baltimore",
    "sg:classifiers":[
        {
            "category":"Restaurant",
            "type":"Food & Drink"
        }
    ],
    "sg:menulink":"http://www.allmenus.com/mi/chesterfield/43011-yes-china-king/menu/",
    "sg:phone":"+1 586 948 3388",
    "sg:postcode":"48051",
    "sg:province":"MI",
    "sg:tags":[
        "asian",
        "chinese"
    ],
    "wof:name":"Ye's China King",
    "wof:placetype":"venue"
},
  "geometry": {"coordinates":[-82.852344,42.646562],"type":"Point"}
}