{
  "type": "Feature",
  "properties": {
    "iso:country":"US",
    "sg:address":"1924 24th St",
    "sg:city":"Port Huron",
    "sg:classifiers":[
        {
            "category":"Retail",
            "subcategory":"Repair Shop",
            "type":"Services"
        }
    ],
    "sg:phone":"+1 810 989 9349",
    "sg:postcode":"48060",
    "sg:province":"MI",
    "sg:tags":[
        "refinishing",
        "furniture"
    ],
    "wof:name":"Summit Finishing",
    "wof:placetype":"venue"
},
  "geometry": {"coordinates":[-82.452197,42.963672],"type":"Point"}
}