{
  "type": "Feature",
  "properties": {
    "iso:country":"US",
    "sg:address":"13337 Michigan Ave",
    "sg:city":"Dearborn",
    "sg:classifiers":[
        {
            "category":"Restaurant",
            "type":"Food & Drink"
        }
    ],
    "sg:phone":"+1 313 581 5576",
    "sg:postcode":"48126",
    "sg:province":"MI",
    "sg:tags":[
        "asian",
        "chinese",
        "pan"
    ],
    "wof:name":"Kong Kow Restaurant",
    "wof:placetype":"venue"
},
  "geometry": {"coordinates":[-83.17420199999999,42.322601],"type":"Point"}
}