{
  "type": "Feature",
  "properties": {
    "iso:country":"US",
    "sg:address":"4471 Mauck Rd",
    "sg:city":"Hillsdale",
    "sg:phone":"+1 517 437 7994",
    "sg:postcode":"49242",
    "sg:province":"MI",
    "sg:tags":[
        "farm",
        "corn",
        "grain",
        "cash"
    ],
    "wof:name":"Lewis Stoll",
    "wof:placetype":"venue"
},
  "geometry": {"coordinates":[-84.57235799999999,41.941777],"type":"Point"}
}