{
  "type": "Feature",
  "properties": {
    "iso:country":"US",
    "sg:address":"4749 W Stoney Corners Rd",
    "sg:city":"Mc Bain",
    "sg:classifiers":[
        {
            "category":"Real Estate",
            "subcategory":"Real Estate Operator",
            "type":"Services"
        }
    ],
    "sg:phone":"+1 231 825 2339",
    "sg:postcode":"49657",
    "sg:province":"MI",
    "sg:tags":[
        "property",
        "lessor"
    ],
    "wof:name":"Lewis Sweet",
    "wof:placetype":"venue"
},
  "geometry": {"coordinates":[-85.191643,44.193636],"type":"Point"}
}