{
  "type": "Feature",
  "properties": {
    "iso:country":"US",
    "sg:address":"66021 Van Dyke Rd",
    "sg:city":"Washington",
    "sg:classifiers":[
        {
            "category":"Restaurant",
            "type":"Food & Drink"
        }
    ],
    "sg:menulink":"http://www.allmenus.com/mi/washington/210688-arbys/menu/",
    "sg:phone":"+1 586 336 4800",
    "sg:postcode":"48095",
    "sg:province":"MI",
    "sg:tags":[
        "burger",
        "american"
    ],
    "wof:name":"Arby's",
    "wof:placetype":"venue"
},
  "geometry": {"coordinates":[-83.01376999999999,42.780247],"type":"Point"}
}