{
  "type": "Feature",
  "properties": {
    "iso:country":"US",
    "sg:address":"3215 Hallmark Ct",
    "sg:city":"Saginaw",
    "sg:classifiers":[
        {
            "category":"Health Services",
            "subcategory":"Doctor",
            "type":"Services"
        }
    ],
    "sg:phone":"+1 989 799 1160",
    "sg:postcode":"48603",
    "sg:province":"MI",
    "sg:tags":[
        "physician",
        "surgeon"
    ],
    "wof:name":"Covenant Healthcare",
    "wof:placetype":"venue"
},
  "geometry": {"coordinates":[-83.983199,43.451633],"type":"Point"}
}