{
  "type": "Feature",
  "properties": {
    "iso:country":"US",
    "sg:address":"1195 Woiderski Rd",
    "sg:city":"Cheboygan",
    "sg:classifiers":[
        {
            "category":"Government",
            "subcategory":"Fire Station",
            "type":"Public Place"
        }
    ],
    "sg:phone":"+1 231 627 3301",
    "sg:postcode":"49721",
    "sg:province":"MI",
    "sg:tags":[
        "department"
    ],
    "wof:name":"Inverness Fire Dept",
    "wof:placetype":"venue"
},
  "geometry": {"coordinates":[-84.521529,45.634304],"type":"Point"}
}