{
  "type": "Feature",
  "properties": {
    "iso:country":"US",
    "sg:address":"4300 Hogback Rd",
    "sg:city":"Fowlerville",
    "sg:classifiers":[
        {
            "category":"Social Services",
            "subcategory":"Adult Care",
            "type":"Services"
        }
    ],
    "sg:phone":"+1 517 223 8761",
    "sg:postcode":"48836",
    "sg:province":"MI",
    "sg:tags":[
        "home",
        "residential"
    ],
    "wof:name":"Autumn View Assisted Living",
    "wof:placetype":"venue"
},
  "geometry": {"coordinates":[-84.044149,42.668023],"type":"Point"}
}