{
  "type": "Feature",
  "properties": {
    "iso:country":"US",
    "sg:address":"641 Albany St",
    "sg:city":"Ferndale",
    "sg:classifiers":[
        {
            "category":"Arts & Performance",
            "subcategory":"Theater",
            "type":"Entertainment"
        }
    ],
    "sg:phone":"+1 248 544 4328",
    "sg:postcode":"48220",
    "sg:province":"MI",
    "sg:tags":[
        "bureau"
    ],
    "wof:name":"Calico Entertainment",
    "wof:placetype":"venue"
},
  "geometry": {"coordinates":[-83.139387,42.458027],"type":"Point"}
}