{
  "type": "Feature",
  "properties": {
    "iso:country":"US",
    "sg:address":"2572 Carpenter Rd",
    "sg:city":"Ann Arbor",
    "sg:classifiers":[
        {
            "category":"Real Estate",
            "subcategory":"Real Estate Operator",
            "type":"Services"
        }
    ],
    "sg:phone":"+1 734 971 4939",
    "sg:postcode":"48108",
    "sg:province":"MI",
    "sg:tags":[
        "building",
        "apartment"
    ],
    "wof:name":"Town & Country Apartments",
    "wof:placetype":"venue"
},
  "geometry": {"coordinates":[-83.680584,42.249323],"type":"Point"}
}