{
  "type": "Feature",
  "properties": {
    "iso:country":"US",
    "sg:address":"16250 Northland Dr Ste 207",
    "sg:city":"Southfield",
    "sg:classifiers":[
        {
            "category":"Professional",
            "subcategory":"Employment Agencies",
            "type":"Services"
        }
    ],
    "sg:phone":"+1 248 424 7374",
    "sg:postcode":"48075",
    "sg:province":"MI",
    "wof:name":"Knowledge Brokers",
    "wof:placetype":"venue"
},
  "geometry": {"coordinates":[-83.209889,42.445981],"type":"Point"}
}