{
  "type": "Feature",
  "properties": {
    "iso:country":"US",
    "sg:address":"5411 Dixie Hwy",
    "sg:city":"Saginaw",
    "sg:classifiers":[
        {
            "category":"Mining & Drilling",
            "type":"Manufacturing & Wholesale Goods"
        }
    ],
    "sg:phone":"+1 989 777 7009",
    "sg:postcode":"48601",
    "sg:province":"MI",
    "sg:tags":[
        "stone"
    ],
    "wof:name":"MTI Stone & Marble",
    "wof:placetype":"venue"
},
  "geometry": {"coordinates":[-83.89877,43.382838],"type":"Point"}
}