{
  "type": "Feature",
  "properties": {
    "iso:country":"US",
    "sg:address":"169 E Broadway Ave",
    "sg:city":"Muskegon",
    "sg:classifiers":[
        {
            "category":"Restaurant",
            "type":"Food & Drink"
        }
    ],
    "sg:phone":"+1 231 739 9577",
    "sg:postcode":"49444",
    "sg:province":"MI",
    "wof:name":"E J's Famous Fried Fish",
    "wof:placetype":"venue"
},
  "geometry": {"coordinates":[-86.24011400000001,43.2009],"type":"Point"}
}