{
  "type": "Feature",
  "properties": {
    "iso:country":"US",
    "sg:address":"32502 M 62 W",
    "sg:city":"Dowagiac",
    "sg:classifiers":[
        {
            "category":"Real Estate",
            "subcategory":"Real Estate Agent",
            "type":"Services"
        }
    ],
    "sg:phone":"+1 269 782 4000",
    "sg:postcode":"49047",
    "sg:province":"MI",
    "wof:name":"Jerdon Realestate Inc",
    "wof:placetype":"venue"
},
  "geometry": {"coordinates":[-86.201482,41.983785],"type":"Point"}
}