{
  "type": "Feature",
  "properties": {
    "iso:country":"US",
    "sg:address":"4256 Post Dr",
    "sg:city":"Flint",
    "sg:classifiers":[
        {
            "category":"Building & Trades",
            "subcategory":"Construction",
            "type":"Services"
        }
    ],
    "sg:phone":"+1 810 230 6117",
    "sg:postcode":"48532",
    "sg:province":"MI",
    "sg:tags":[
        "home",
        "improvement"
    ],
    "wof:name":"Driesen Home Detailing Inc",
    "wof:placetype":"venue"
},
  "geometry": {"coordinates":[-83.765075,43.023126],"type":"Point"}
}