{
  "type": "Feature",
  "properties": {
    "iso:country":"US",
    "sg:address":"7990 Garfield Rd",
    "sg:city":"Standish",
    "sg:classifiers":[
        {
            "category":"Home & Garden",
            "subcategory":"Garden Supply",
            "type":"Retail Goods"
        }
    ],
    "sg:phone":"+1 989 846 4477",
    "sg:postcode":"48658",
    "sg:province":"MI",
    "wof:name":"Bay Farm Service",
    "wof:placetype":"venue"
},
  "geometry": {"coordinates":[-84.084835,43.966188],"type":"Point"}
}