{
  "type": "Feature",
  "properties": {
    "iso:country":"US",
    "sg:address":"6705 Division Ave S",
    "sg:city":"Grand Rapids",
    "sg:classifiers":[
        {
            "category":"Personal",
            "subcategory":"Beauty Salon",
            "type":"Services"
        }
    ],
    "sg:phone":"+1 616 281 6540",
    "sg:postcode":"49548",
    "sg:province":"MI",
    "sg:tags":[
        "manicuring"
    ],
    "wof:name":"#1 Nails",
    "wof:placetype":"venue"
},
  "geometry": {"coordinates":[-85.663769,42.842452],"type":"Point"}
}