{
  "type": "Feature",
  "properties": {
    "iso:country":"US",
    "sg:address":"5018 Ridgetop Dr",
    "sg:city":"Waterford",
    "sg:classifiers":[
        {
            "category":"Banks & Credit Unions",
            "subcategory":"Investment Brokerage",
            "type":"Services"
        }
    ],
    "sg:phone":"+1 248 673 9310",
    "sg:postcode":"48327",
    "sg:province":"MI",
    "sg:tags":[
        "advisory"
    ],
    "wof:name":"Thrifty Financial Svcs",
    "wof:placetype":"venue"
},
  "geometry": {"coordinates":[-83.387215,42.665122],"type":"Point"}
}