{
  "type": "Feature",
  "properties": {
    "iso:country":"US",
    "sg:address":"24627 N River Rd",
    "sg:city":"Mount Clemens",
    "sg:classifiers":[
        {
            "category":"Restaurant",
            "type":"Food & Drink"
        }
    ],
    "sg:menulink":"http://www.allmenus.com/mi/mount-clemens/185873-mcdonalds/menu/",
    "sg:postcode":"48043",
    "sg:province":"MI",
    "sg:tags":[
        "burger",
        "american"
    ],
    "wof:name":"McDonald's",
    "wof:placetype":"venue"
},
  "geometry": {"coordinates":[-82.860562,42.594573],"type":"Point"}
}