{
  "type": "Feature",
  "properties": {
    "iso:country":"US",
    "sg:address":"1426 Pacific Dr",
    "sg:city":"Auburn Hills",
    "sg:classifiers":[
        {
            "category":"Professional",
            "subcategory":"Management & Consulting",
            "type":"Services"
        }
    ],
    "sg:phone":"+1 248 377 1600",
    "sg:postcode":"48326",
    "sg:province":"MI",
    "sg:tags":[
        "marketing",
        "program"
    ],
    "sg:website":"www.msxi.com",
    "wof:name":"MSX Intl",
    "wof:placetype":"venue"
},
  "geometry": {"coordinates":[-83.27106499999999,42.6952],"type":"Point"}
}