{
  "type": "Feature",
  "properties": {
    "iso:country":"US",
    "sg:address":"31166 Orchard Lake Rd",
    "sg:city":"Farmington Hills",
    "sg:classifiers":[
        {
            "category":"Retail",
            "subcategory":"Repair Shop",
            "type":"Services"
        },
        {
            "category":"Shopping",
            "type":"Retail Goods"
        }
    ],
    "sg:phone":"+1 248 626 2855",
    "sg:postcode":"48334",
    "sg:province":"MI",
    "sg:tags":[
        "picture",
        "frame"
    ],
    "wof:name":"Aardvark Custom Framing LLC",
    "wof:placetype":"venue"
},
  "geometry": {"coordinates":[-83.359953,42.526377],"type":"Point"}
}