{
  "type": "Feature",
  "properties": {
    "iso:country":"US",
    "sg:address":"155 E Apple Ave",
    "sg:city":"Muskegon",
    "sg:classifiers":[
        {
            "category":"Social Services",
            "subcategory":"Adult Care",
            "type":"Services"
        }
    ],
    "sg:phone":"+1 231 724 6040",
    "sg:postcode":"49442",
    "sg:province":"MI",
    "sg:tags":[
        "residential"
    ],
    "wof:name":"County of Muskegon",
    "wof:placetype":"venue"
},
  "geometry": {"coordinates":[-86.240067,43.234177],"type":"Point"}
}