{
  "type": "Feature",
  "properties": {
    "iso:country":"US",
    "sg:address":"307 Kenway Dr",
    "sg:city":"Lansing",
    "sg:classifiers":[
        {
            "category":"Professional",
            "subcategory":"Management & Consulting",
            "type":"Services"
        }
    ],
    "sg:phone":"+1 517 323 9112",
    "sg:postcode":"48917",
    "sg:province":"MI",
    "wof:name":"Gerald Thiede",
    "wof:placetype":"venue"
},
  "geometry": {"coordinates":[-84.63168,42.731369],"type":"Point"}
}