{
  "type": "Feature",
  "properties": {
    "iso:country":"US",
    "sg:address":"220 S Main St",
    "sg:city":"Ann Arbor",
    "sg:classifiers":[
        {
            "category":"Personal",
            "subcategory":"Beauty Salon",
            "type":"Services"
        }
    ],
    "sg:phone":"+1 734 995 1747",
    "sg:postcode":"48104",
    "sg:province":"MI",
    "sg:tags":[
        "shop",
        "dance"
    ],
    "wof:name":"Studio 1 School Of Dance",
    "wof:placetype":"venue"
},
  "geometry": {"coordinates":[-83.748632,42.279777],"type":"Point"}
}