{
  "type": "Feature",
  "properties": {
    "iso:country":"US",
    "sg:address":"1605 Benner Hwy",
    "sg:city":"Clayton",
    "sg:classifiers":[
        {
            "category":"Social Services",
            "subcategory":"Child Care",
            "type":"Services"
        }
    ],
    "sg:phone":"+1 517 263 0007",
    "sg:postcode":"49235",
    "sg:province":"MI",
    "sg:tags":[
        "day"
    ],
    "wof:name":"Play N Learn Day Care",
    "wof:placetype":"venue"
},
  "geometry": {"coordinates":[-84.16065399999999,41.89082],"type":"Point"}
}