{
  "type": "Feature",
  "properties": {
    "iso:country":"US",
    "sg:address":"1675 E Maple Rd",
    "sg:city":"Troy",
    "sg:classifiers":[
        {
            "category":"Wholesale",
            "subcategory":"Machinery & Supplies",
            "type":"Manufacturing & Wholesale Goods"
        }
    ],
    "sg:phone":"+1 248 689 2400",
    "sg:postcode":"48083",
    "sg:province":"MI",
    "sg:tags":[
        "equipment",
        "hydraulic"
    ],
    "sg:website":"www.birmingham-hydraulics.com",
    "wof:name":"Birmingham Hydraulics Inc",
    "wof:placetype":"venue"
},
  "geometry": {"coordinates":[-83.114148,42.549127],"type":"Point"}
}