{
  "type": "Feature",
  "properties": {
    "iso:country":"US",
    "sg:address":"48929 Hayes Rd",
    "sg:city":"Utica",
    "sg:classifiers":[
        {
            "category":"Bars & Pubs",
            "type":"Food & Drink"
        }
    ],
    "sg:menulink":"http://www.allmenus.com/mi/macomb/58067-hamlin-pub/menu/",
    "sg:phone":"+1 586 247 4100",
    "sg:postcode":"48315",
    "sg:province":"MI",
    "sg:tags":[
        "burger",
        "american"
    ],
    "wof:name":"Hamlin Pub",
    "wof:placetype":"venue"
},
  "geometry": {"coordinates":[-82.974397,42.655856],"type":"Point"}
}