{
  "type": "Feature",
  "properties": {
    "iso:country":"US",
    "sg:address":"902 Delta Ave",
    "sg:city":"Gladstone",
    "sg:classifiers":[
        {
            "category":"Restaurant",
            "type":"Food & Drink"
        }
    ],
    "sg:phone":"+1 906 428 9190",
    "sg:postcode":"49837",
    "sg:province":"MI",
    "sg:tags":[
        "pizza"
    ],
    "wof:name":"Delta Pub",
    "wof:placetype":"venue"
},
  "geometry": {"coordinates":[-87.02072200000001,45.84763],"type":"Point"}
}