{
  "type": "Feature",
  "properties": {
    "iso:country":"US",
    "sg:address":"2958 E Long Lake Rd",
    "sg:city":"Troy",
    "sg:classifiers":[
        {
            "category":"Health Services",
            "subcategory":"Doctor",
            "type":"Services"
        }
    ],
    "sg:phone":"+1 248 689 6080",
    "sg:postcode":"48085",
    "sg:province":"MI",
    "wof:name":"Richard K Faughn DDS PC",
    "wof:placetype":"venue"
},
  "geometry": {"coordinates":[-83.093304,42.592855],"type":"Point"}
}