{
  "type": "Feature",
  "properties": {
    "iso:country":"US",
    "sg:address":"16732 E Uv Ave",
    "sg:city":"Fulton",
    "sg:classifiers":[
        {
            "category":"Organizations",
            "subcategory":"Religious Organization",
            "type":"Services"
        }
    ],
    "sg:phone":"+1 269 729 5431",
    "sg:postcode":"49052",
    "sg:province":"MI",
    "wof:name":"Wakeshma Community Church",
    "wof:placetype":"venue"
},
  "geometry": {"coordinates":[-85.301269,42.136856],"type":"Point"}
}