{
  "type": "Feature",
  "properties": {
    "iso:country":"US",
    "sg:address":"30535 W 14 Mile Rd",
    "sg:city":"Farmington",
    "sg:classifiers":[
        {
            "category":"Professional",
            "subcategory":"Management & Consulting",
            "type":"Services"
        }
    ],
    "sg:phone":"+1 248 932 5274",
    "sg:postcode":"48334",
    "sg:province":"MI",
    "sg:tags":[
        "business"
    ],
    "wof:name":"Alan M Green",
    "wof:placetype":"venue"
},
  "geometry": {"coordinates":[-83.347917,42.528677],"type":"Point"}
}