{
  "type": "Feature",
  "properties": {
    "iso:country":"US",
    "sg:address":"2300 Griswold St",
    "sg:city":"Port Huron",
    "sg:classifiers":[
        {
            "category":"Banks & Credit Unions",
            "subcategory":"Bank",
            "type":"Services"
        }
    ],
    "sg:phone":"+1 810 984 2035",
    "sg:postcode":"48060",
    "sg:province":"MI",
    "sg:tags":[
        "national",
        "commercial"
    ],
    "wof:name":"Standard Federal Bank N A",
    "wof:placetype":"venue"
},
  "geometry": {"coordinates":[-82.452393,42.966685],"type":"Point"}
}