{
  "type": "Feature",
  "properties": {
    "iso:country":"US",
    "sg:address":"28254 Riverbridge Dr",
    "sg:city":"Romulus",
    "sg:classifiers":[
        {
            "category":"Social Services",
            "subcategory":"Adult Care",
            "type":"Services"
        }
    ],
    "sg:phone":"+1 734 942 7163",
    "sg:postcode":"48174",
    "sg:province":"MI",
    "sg:tags":[
        "foster"
    ],
    "wof:name":"Twilley Richard & Delois",
    "wof:placetype":"venue"
},
  "geometry": {"coordinates":[-83.314471,42.187205],"type":"Point"}
}