{
  "type": "Feature",
  "properties": {
    "iso:country":"US",
    "sg:address":"352 W Houghton Ave",
    "sg:city":"West Branch",
    "sg:classifiers":[
        {
            "category":"Health Services",
            "subcategory":"Clinic",
            "type":"Services"
        }
    ],
    "sg:phone":"+1 989 345 3138",
    "sg:postcode":"48661",
    "sg:province":"MI",
    "sg:tags":[
        "home"
    ],
    "wof:name":"Leelin Home Health Care I",
    "wof:placetype":"venue"
},
  "geometry": {"coordinates":[-84.239344,44.276186],"type":"Point"}
}