{
  "type": "Feature",
  "properties": {
    "iso:country":"US",
    "sg:address":"13265 Crane Ridge Ct",
    "sg:city":"Fenton",
    "sg:classifiers":[
        {
            "category":"Building & Trades",
            "subcategory":"Construction",
            "type":"Services"
        }
    ],
    "sg:phone":"+1 810 750 4564",
    "sg:postcode":"48430",
    "sg:province":"MI",
    "sg:tags":[
        "house"
    ],
    "wof:name":"Recommended Builders",
    "wof:placetype":"venue"
},
  "geometry": {"coordinates":[-83.719523,42.833617],"type":"Point"}
}