{
  "type": "Feature",
  "properties": {
    "iso:country":"US",
    "sg:address":"33300 Ryan Rd",
    "sg:city":"Sterling Heights",
    "sg:classifiers":[
        {
            "category":"Social Services",
            "subcategory":"Child Care",
            "type":"Services"
        },
        {
            "category":"Education",
            "subcategory":"Preschool",
            "type":"Public Place"
        },
        {
            "category":"Education",
            "subcategory":"School",
            "type":"Public Place"
        }
    ],
    "sg:phone":"+1 586 978 8099",
    "sg:postcode":"48310",
    "sg:province":"MI",
    "sg:tags":[
        "elementary",
        "day"
    ],
    "wof:name":"Kindercare Learning Centers",
    "wof:placetype":"venue"
},
  "geometry": {"coordinates":[-83.06849699999999,42.537899],"type":"Point"}
}