{
  "type": "Feature",
  "properties": {
    "iso:country":"US",
    "sg:address":"914 Charlevoix St",
    "sg:city":"Grand Ledge",
    "sg:classifiers":[
        {
            "category":"Banks & Credit Unions",
            "subcategory":"Bank",
            "type":"Services"
        }
    ],
    "sg:phone":"+1 517 622 4321",
    "sg:postcode":"48837",
    "sg:province":"MI",
    "sg:website":"www.flagstar.com",
    "wof:name":"Flagstar Bank",
    "wof:placetype":"venue"
},
  "geometry": {"coordinates":[-84.733244,42.741888],"type":"Point"}
}