{
  "type": "Feature",
  "properties": {
    "iso:country":"US",
    "sg:address":"1805 W Court St",
    "sg:city":"Flint",
    "sg:classifiers":[
        {
            "category":"Social Services",
            "subcategory":"Child Care",
            "type":"Services"
        }
    ],
    "sg:phone":"+1 810 238 7022",
    "sg:postcode":"48503",
    "sg:province":"MI",
    "sg:tags":[
        "day"
    ],
    "wof:name":"Montessori Children's House",
    "wof:placetype":"venue"
},
  "geometry": {"coordinates":[-83.71078300000001,43.006797],"type":"Point"}
}