{
  "type": "Feature",
  "properties": {
    "iso:country":"US",
    "sg:address":"29244 Northwestern Hwy",
    "sg:city":"Southfield",
    "sg:classifiers":[
        {
            "category":"Restaurant",
            "type":"Food & Drink"
        }
    ],
    "sg:phone":"+1 248 351 2925",
    "sg:postcode":"48034",
    "sg:province":"MI",
    "sg:tags":[
        "seafood",
        "cajun/creole"
    ],
    "sg:website":"www.fishbonesusa.com",
    "wof:name":"Fishbone's Rhythm Kitchen Cafe",
    "wof:placetype":"venue"
},
  "geometry": {"coordinates":[-83.311401,42.5028],"type":"Point"}
}