{
  "type": "Feature",
  "properties": {
    "iso:country":"US",
    "sg:address":"13602 Streamside Ct",
    "sg:city":"Grand Haven",
    "sg:classifiers":[
        {
            "category":"Shopping",
            "subcategory":"Used Merchandise",
            "type":"Retail Goods"
        }
    ],
    "sg:phone":"+1 616 844 7490",
    "sg:postcode":"49417",
    "sg:province":"MI",
    "wof:name":"Timeless Expressions",
    "wof:placetype":"venue"
},
  "geometry": {"coordinates":[-86.16043500000001,43.014865],"type":"Point"}
}