{
  "type": "Feature",
  "properties": {
    "iso:country":"US",
    "sg:address":"35600 Central City Pkwy Ste 106",
    "sg:city":"Westland",
    "sg:classifiers":[
        {
            "category":"Health Services",
            "subcategory":"Doctor",
            "type":"Services"
        }
    ],
    "sg:phone":"+1 734 525 0350",
    "sg:postcode":"48185",
    "sg:province":"MI",
    "wof:name":"Morrison John H Jr DO",
    "wof:placetype":"venue"
},
  "geometry": {"coordinates":[-83.3943,42.341932],"type":"Point"}
}