{
  "type": "Feature",
  "properties": {
    "iso:country":"US",
    "sg:address":"23030 Tuck Rd",
    "sg:city":"Farmington Hills",
    "sg:classifiers":[
        {
            "category":"Building & Trades",
            "subcategory":"Construction",
            "type":"Services"
        }
    ],
    "sg:phone":"+1 248 476 6875",
    "sg:postcode":"48336",
    "sg:province":"MI",
    "sg:tags":[
        "contractor"
    ],
    "wof:name":"J & C Decks",
    "wof:placetype":"venue"
},
  "geometry": {"coordinates":[-83.347026,42.462712],"type":"Point"}
}