{
  "type": "Feature",
  "properties": {
    "iso:country":"US",
    "sg:address":"460 Shaw Ct",
    "sg:city":"Milford",
    "sg:classifiers":[
        {
            "category":"Professional",
            "type":"Services"
        }
    ],
    "sg:phone":"+1 248 685 9599",
    "sg:postcode":"48380",
    "sg:province":"MI",
    "wof:name":"Bobs It Svc",
    "wof:placetype":"venue"
},
  "geometry": {"coordinates":[-83.655008,42.598275],"type":"Point"}
}