{
  "type": "Feature",
  "properties": {
    "iso:country":"US",
    "sg:address":"6229 King Rd",
    "sg:city":"Spring Arbor",
    "sg:classifiers":[
        {
            "category":"Education",
            "subcategory":"Special Training",
            "type":"Public Place"
        }
    ],
    "sg:phone":"+1 517 750 4952",
    "sg:postcode":"49283",
    "sg:province":"MI",
    "wof:name":"Jerry Glassel Guitar School",
    "wof:placetype":"venue"
},
  "geometry": {"coordinates":[-84.519732,42.218337],"type":"Point"}
}