{
  "type": "Feature",
  "properties": {
    "iso:country":"US",
    "sg:address":"1160 Welch Rd",
    "sg:city":"Commerce Twp",
    "sg:classifiers":[
        {
            "category":"Manufacturing",
            "subcategory":"Apparel",
            "type":"Manufacturing & Wholesale Goods"
        }
    ],
    "sg:phone":"+1 248 669 9696",
    "sg:postcode":"48390",
    "sg:province":"MI",
    "sg:tags":[
        "drapery",
        "contractor"
    ],
    "wof:name":"Designs Designs LTD",
    "wof:placetype":"venue"
},
  "geometry": {"coordinates":[-83.45809199999999,42.541101],"type":"Point"}
}