{
  "type": "Feature",
  "properties": {
    "iso:country":"US",
    "sg:address":"7870 Sprinkle Rd",
    "sg:city":"Portage",
    "sg:classifiers":[
        {
            "category":"Wholesale",
            "subcategory":"Electrical",
            "type":"Manufacturing & Wholesale Goods"
        }
    ],
    "sg:phone":"+1 269 321 0070",
    "sg:postcode":"49002",
    "sg:province":"MI",
    "sg:tags":[
        "electric",
        "motor"
    ],
    "wof:name":"J P Motors & Drives Inc",
    "wof:placetype":"venue"
},
  "geometry": {"coordinates":[-85.5406,42.205687],"type":"Point"}
}