{
  "type": "Feature",
  "properties": {
    "iso:country":"US",
    "sg:address":"2433 Gertrude St",
    "sg:city":"Kalamazoo",
    "sg:classifiers":[
        {
            "category":"Education",
            "subcategory":"School",
            "type":"Public Place"
        }
    ],
    "sg:phone":"+1 269 337 0690",
    "sg:postcode":"49048",
    "sg:province":"MI",
    "wof:name":"Northeastern Elementary School",
    "wof:placetype":"venue"
},
  "geometry": {"coordinates":[-85.55027800000001,42.306868],"type":"Point"}
}