{
  "type": "Feature",
  "properties": {
    "iso:country":"US",
    "sg:address":"8087 Davison Rd",
    "sg:city":"Davison",
    "sg:classifiers":[
        {
            "category":"Wholesale",
            "subcategory":"Hardware",
            "type":"Manufacturing & Wholesale Goods"
        }
    ],
    "sg:phone":"+1 810 653 1146",
    "sg:postcode":"48423",
    "sg:province":"MI",
    "sg:tags":[
        "used",
        "boiler"
    ],
    "wof:name":"Mechanical Specialties",
    "wof:placetype":"venue"
},
  "geometry": {"coordinates":[-83.55141999999999,43.034179],"type":"Point"}
}