{
  "type": "Feature",
  "properties": {
    "iso:country":"US",
    "sg:address":"1 N Center St",
    "sg:city":"Sebewaing",
    "sg:classifiers":[
        {
            "category":"Health Services",
            "subcategory":"Chiropractor",
            "type":"Services"
        }
    ],
    "sg:phone":"+1 989 883 9090",
    "sg:postcode":"48759",
    "sg:province":"MI",
    "wof:name":"Sebewaing Chiropractic Center",
    "wof:placetype":"venue"
},
  "geometry": {"coordinates":[-83.451255,43.733165],"type":"Point"}
}