{
  "type": "Feature",
  "properties": {
    "iso:country":"US",
    "sg:address":"33699 5 Mile Rd",
    "sg:city":"Livonia",
    "sg:classifiers":[
        {
            "category":"Restaurant",
            "type":"Food & Drink"
        }
    ],
    "sg:phone":"+1 734 427 5050",
    "sg:postcode":"48154",
    "sg:province":"MI",
    "sg:tags":[
        "pizza"
    ],
    "wof:name":"Hungry Howie's No 17",
    "wof:placetype":"venue"
},
  "geometry": {"coordinates":[-83.376503,42.3969],"type":"Point"}
}