{
  "type": "Feature",
  "properties": {
    "iso:country":"US",
    "sg:address":"14221 M 89",
    "sg:city":"Augusta",
    "sg:classifiers":[
        {
            "category":"Health Services",
            "subcategory":"Nursing And Care Facility",
            "type":"Services"
        }
    ],
    "sg:phone":"+1 269 731 3426",
    "sg:postcode":"49012",
    "sg:province":"MI",
    "sg:tags":[
        "adult"
    ],
    "wof:name":"Stoney Oaks",
    "wof:placetype":"venue"
},
  "geometry": {"coordinates":[-85.348719,42.373771],"type":"Point"}
}