{
  "type": "Feature",
  "properties": {
    "iso:country":"US",
    "sg:address":"370 Gumwood Rd",
    "sg:city":"Niles",
    "sg:classifiers":[
        {
            "category":"Home & Garden",
            "subcategory":"Home Furnishings",
            "type":"Retail Goods"
        }
    ],
    "sg:phone":"+1 269 687 8520",
    "sg:postcode":"49120",
    "sg:province":"MI",
    "sg:tags":[
        "window",
        "covering"
    ],
    "wof:name":"V2k Window Fashions",
    "wof:placetype":"venue"
},
  "geometry": {"coordinates":[-86.18634900000001,41.781576],"type":"Point"}
}