{
  "type": "Feature",
  "properties": {
    "iso:country":"US",
    "sg:address":"18400 Lesure St",
    "sg:city":"Detroit",
    "sg:classifiers":[
        {
            "category":"Education",
            "subcategory":"Special Training",
            "type":"Public Place"
        }
    ],
    "sg:phone":"+1 313 345 8415",
    "sg:postcode":"48235",
    "sg:province":"MI",
    "wof:name":"Skill Builders & Association",
    "wof:placetype":"venue"
},
  "geometry": {"coordinates":[-83.18237000000001,42.426553],"type":"Point"}
}