{
  "type": "Feature",
  "properties": {
    "iso:country":"US",
    "sg:address":"305 Fitz Rd",
    "sg:city":"Wales",
    "sg:classifiers":[
        {
            "category":"Building & Trades",
            "subcategory":"Construction",
            "type":"Services"
        }
    ],
    "sg:phone":"+1 810 392 3127",
    "sg:postcode":"48027",
    "sg:province":"MI",
    "sg:tags":[
        "carpenter"
    ],
    "wof:name":"Gudme Construction",
    "wof:placetype":"venue"
},
  "geometry": {"coordinates":[-82.696167,42.908394],"type":"Point"}
}