{
  "type": "Feature",
  "properties": {
    "iso:country":"US",
    "sg:address":"8956 Church Dr",
    "sg:city":"Vassar",
    "sg:classifiers":[
        {
            "category":"Organizations",
            "subcategory":"Religious Organization",
            "type":"Services"
        }
    ],
    "sg:phone":"+1 989 871 3788",
    "sg:postcode":"48768",
    "sg:province":"MI",
    "sg:tags":[
        "church"
    ],
    "wof:name":"Tuscola Community Church",
    "wof:placetype":"venue"
},
  "geometry": {"coordinates":[-83.65799699999999,43.328208],"type":"Point"}
}