{
  "type": "Feature",
  "properties": {
    "iso:country":"US",
    "sg:address":"7699 Markel Rd",
    "sg:city":"Ira",
    "sg:classifiers":[
        {
            "category":"Farming",
            "subcategory":"Farm",
            "type":"Manufacturing & Wholesale Goods"
        }
    ],
    "sg:phone":"+1 586 725 3218",
    "sg:postcode":"48023",
    "sg:province":"MI",
    "wof:name":"S & T Farms",
    "wof:placetype":"venue"
},
  "geometry": {"coordinates":[-82.61997100000001,42.70218],"type":"Point"}
}