{
  "type": "Feature",
  "properties": {
    "iso:country":"US",
    "sg:address":"3239 Turnberry Ln",
    "sg:city":"Port Huron",
    "sg:classifiers":[
        {
            "category":"Shopping",
            "subcategory":"Hobbies, Toys, & Games",
            "type":"Retail Goods"
        }
    ],
    "sg:phone":"+1 810 984 8764",
    "sg:postcode":"48060",
    "sg:province":"MI",
    "sg:tags":[
        "model",
        "supply"
    ],
    "wof:name":"Blue Water Hobbies",
    "wof:placetype":"venue"
},
  "geometry": {"coordinates":[-82.466478,43.003624],"type":"Point"}
}