{
  "type": "Feature",
  "properties": {
    "iso:country":"US",
    "sg:address":"10682 Pine St",
    "sg:city":"Taylor",
    "sg:classifiers":[
        {
            "category":"Education",
            "subcategory":"Special Training",
            "type":"Public Place"
        }
    ],
    "sg:phone":"+1 313 291 2345",
    "sg:postcode":"48180",
    "sg:province":"MI",
    "sg:tags":[
        "school",
        "specialty"
    ],
    "wof:name":"Elements Floral Art School",
    "wof:placetype":"venue"
},
  "geometry": {"coordinates":[-83.26440599999999,42.229054],"type":"Point"}
}