{
  "type": "Feature",
  "properties": {
    "iso:country":"US",
    "sg:address":"9605 Sterling",
    "sg:city":"Richland",
    "sg:classifiers":[
        {
            "category":"Autos & Motor Vehicles",
            "subcategory":"Auto Supplies",
            "type":"Retail Goods"
        }
    ],
    "sg:phone":"+1 269 629 4488",
    "sg:postcode":"49083",
    "sg:province":"MI",
    "sg:tags":[
        "equipment",
        "racing",
        "car",
        "automobile"
    ],
    "wof:name":"Ripley Racing",
    "wof:placetype":"venue"
},
  "geometry": {"coordinates":[-85.44292,42.413835],"type":"Point"}
}