{
  "type": "Feature",
  "properties": {
    "iso:country":"US",
    "sg:address":"720 S 11th St",
    "sg:city":"Niles",
    "sg:classifiers":[
        {
            "category":"Coffee & Tea",
            "type":"Food & Drink"
        }
    ],
    "sg:menulink":"http://www.allmenus.com/mi/niles/125642-starbucks-coffee/menu/",
    "sg:phone":"+1 616 684 2722",
    "sg:postcode":"49120",
    "sg:province":"MI",
    "sg:tags":[
        "american"
    ],
    "wof:name":"Starbucks Coffee",
    "wof:placetype":"venue"
},
  "geometry": {"coordinates":[-86.247157,41.821035],"type":"Point"}
}