{
  "type": "Feature",
  "properties": {
    "iso:country":"US",
    "sg:address":"9723 N Straits Hwy",
    "sg:city":"Cheboygan",
    "sg:classifiers":[
        {
            "category":"Wholesale",
            "subcategory":"Electrical",
            "type":"Manufacturing & Wholesale Goods"
        }
    ],
    "sg:phone":"+1 231 627 6636",
    "sg:postcode":"49721",
    "sg:province":"MI",
    "sg:tags":[
        "control",
        "security",
        "system"
    ],
    "wof:name":"Northern Sound & Security Syst",
    "wof:placetype":"venue"
},
  "geometry": {"coordinates":[-84.475821,45.599261],"type":"Point"}
}