{
  "type": "Feature",
  "properties": {
    "iso:country":"US",
    "sg:address":"514 Longfellow Dr",
    "sg:city":"Troy",
    "sg:classifiers":[
        {
            "category":"Manufacturing",
            "subcategory":"Tools & Machinery",
            "type":"Manufacturing & Wholesale Goods"
        }
    ],
    "sg:phone":"+1 586 285 1995",
    "sg:postcode":"48085",
    "sg:province":"MI",
    "sg:tags":[
        "chiller"
    ],
    "wof:name":"Microtemp Systems Inc",
    "wof:placetype":"venue"
},
  "geometry": {"coordinates":[-83.13511200000001,42.582893],"type":"Point"}
}