{
  "type": "Feature",
  "properties": {
    "iso:country":"US",
    "sg:address":"5037 32nd Ave",
    "sg:city":"Hudsonville",
    "sg:classifiers":[
        {
            "category":"Education",
            "subcategory":"School",
            "type":"Public Place"
        }
    ],
    "sg:phone":"+1 616 669 1500",
    "sg:postcode":"49426",
    "sg:province":"MI",
    "sg:tags":[
        "high"
    ],
    "sg:website":"www.hudsonville.k12.mi.us",
    "wof:name":"Hudsonville High School",
    "wof:placetype":"venue"
},
  "geometry": {"coordinates":[-85.861243,42.86336],"type":"Point"}
}