{
  "type": "Feature",
  "properties": {
    "iso:country":"US",
    "sg:address":"315 W Green St",
    "sg:city":"Marshall",
    "sg:classifiers":[
        {
            "category":"Government",
            "subcategory":"Office",
            "type":"Public Place"
        }
    ],
    "sg:phone":"+1 269 781 0980",
    "sg:postcode":"49068",
    "sg:province":"MI",
    "wof:name":"Calhoun County Human Resources",
    "wof:placetype":"venue"
},
  "geometry": {"coordinates":[-84.963416,42.27106],"type":"Point"}
}