{
  "type": "Feature",
  "properties": {
    "iso:country":"US",
    "sg:address":"2115 N Wixom Rd",
    "sg:city":"Wixom",
    "sg:classifiers":[
        {
            "category":"Restaurant",
            "type":"Food & Drink"
        }
    ],
    "sg:phone":"+1 248 960 0005",
    "sg:postcode":"48393",
    "sg:province":"MI",
    "wof:name":"Paparooni's Pizzeria",
    "wof:placetype":"venue"
},
  "geometry": {"coordinates":[-83.537757,42.549969],"type":"Point"}
}