{
  "type": "Feature",
  "properties": {
    "iso:country":"US",
    "sg:address":"6359 Euclid St",
    "sg:city":"Marlette",
    "sg:classifiers":[
        {
            "category":"Wholesale",
            "subcategory":"Machinery & Supplies",
            "type":"Manufacturing & Wholesale Goods"
        }
    ],
    "sg:phone":"+1 989 635 5644",
    "sg:postcode":"48453",
    "sg:province":"MI",
    "sg:tags":[
        "industrial"
    ],
    "wof:name":"General Fasteners Company",
    "wof:placetype":"venue"
},
  "geometry": {"coordinates":[-83.075666,43.320566],"type":"Point"}
}