{
  "type": "Feature",
  "properties": {
    "iso:country":"US",
    "sg:address":"9029 Raisin St",
    "sg:city":"Maybee",
    "sg:classifiers":[
        {
            "category":"Insurance",
            "subcategory":"Insurance Agent",
            "type":"Services"
        }
    ],
    "sg:phone":"+1 734 587 8345",
    "sg:postcode":"48159",
    "sg:province":"MI",
    "wof:name":"Schafer Agencys' Inc",
    "wof:placetype":"venue"
},
  "geometry": {"coordinates":[-83.51573999999999,42.004046],"type":"Point"}
}