{
  "type": "Feature",
  "properties": {
    "iso:country":"US",
    "sg:address":"5678 Whitmore Lake Rd",
    "sg:city":"Brighton",
    "sg:classifiers":[
        {
            "category":"Banks & Credit Unions",
            "subcategory":"Bank",
            "type":"Services"
        }
    ],
    "sg:phone":"+1 313 277 0862",
    "sg:postcode":"48116",
    "sg:province":"MI",
    "sg:tags":[
        "state"
    ],
    "wof:name":"Comerica",
    "wof:placetype":"venue"
},
  "geometry": {"coordinates":[-83.75932899999999,42.519827],"type":"Point"}
}