{
  "type": "Feature",
  "properties": {
    "iso:country":"US",
    "sg:address":"24555 Hallwood Ct",
    "sg:city":"Farmington",
    "sg:classifiers":[
        {
            "category":"Professional",
            "subcategory":"Management & Consulting",
            "type":"Services"
        }
    ],
    "sg:phone":"+1 248 926 9900",
    "sg:postcode":"48335",
    "sg:province":"MI",
    "sg:tags":[
        "wholesale",
        "company",
        "medical"
    ],
    "wof:name":"American Laser Centers",
    "wof:placetype":"venue"
},
  "geometry": {"coordinates":[-83.419102,42.47383],"type":"Point"}
}