{
  "type": "Feature",
  "properties": {
    "iso:country":"US",
    "sg:address":"6333 Summit St",
    "sg:city":"Erie",
    "sg:classifiers":[
        {
            "category":"Government",
            "subcategory":"Fire Station",
            "type":"Public Place"
        }
    ],
    "sg:phone":"+1 734 848 8942",
    "sg:postcode":"48133",
    "sg:province":"MI",
    "sg:tags":[
        "dept",
        "volunteer"
    ],
    "wof:name":"Morin Point Fire Dept",
    "wof:placetype":"venue"
},
  "geometry": {"coordinates":[-83.479859,41.733419],"type":"Point"}
}