{
  "type": "Feature",
  "properties": {
    "iso:country":"US",
    "sg:address":"520 S Main St",
    "sg:city":"Lapeer",
    "sg:classifiers":[
        {
            "category":"Shopping",
            "subcategory":"Jewelry",
            "type":"Retail Goods"
        }
    ],
    "sg:phone":"+1 810 664 4971",
    "sg:postcode":"48446",
    "sg:province":"MI",
    "sg:tags":[
        "designer"
    ],
    "wof:name":"Dimensions In Gold",
    "wof:placetype":"venue"
},
  "geometry": {"coordinates":[-83.31974200000001,43.044326],"type":"Point"}
}