{
  "type": "Feature",
  "properties": {
    "iso:country":"US",
    "sg:address":"5454 S Old US Highway 23",
    "sg:city":"Brighton",
    "sg:classifiers":[
        {
            "category":"Local Transit",
            "type":"Transportation"
        }
    ],
    "sg:phone":"+1 810 225 9463",
    "sg:postcode":"48116",
    "sg:province":"MI",
    "sg:tags":[
        "limousine"
    ],
    "wof:name":"Service Ultimate Limousine",
    "wof:placetype":"venue"
},
  "geometry": {"coordinates":[-83.75961100000001,42.523156],"type":"Point"}
}