{
  "type": "Feature",
  "properties": {
    "iso:country":"US",
    "sg:address":"521 S Meade St",
    "sg:city":"Flint",
    "sg:classifiers":[
        {
            "category":"Real Estate",
            "subcategory":"Real Estate Operator",
            "type":"Services"
        }
    ],
    "sg:phone":"+1 810 232 7728",
    "sg:postcode":"48503",
    "sg:province":"MI",
    "sg:tags":[
        "apartment"
    ],
    "wof:name":"Woodlawn Apartments",
    "wof:placetype":"venue"
},
  "geometry": {"coordinates":[-83.65583100000001,43.021818],"type":"Point"}
}