{
  "type": "Feature",
  "properties": {
    "iso:country":"US",
    "sg:address":"6541 Plaza Dr",
    "sg:city":"Marlette",
    "sg:classifiers":[
        {
            "category":"Food & Beverages",
            "subcategory":"Groceries & Convenience Stores",
            "type":"Retail Goods"
        }
    ],
    "sg:phone":"+1 989 635 7505",
    "sg:postcode":"48420",
    "sg:province":"MI",
    "sg:tags":[
        "grocer"
    ],
    "wof:name":"Adams Iga",
    "wof:placetype":"venue"
},
  "geometry": {"coordinates":[-83.719898,43.176798],"type":"Point"}
}