{
  "type": "Feature",
  "properties": {
    "iso:country":"US",
    "sg:address":"20705 E 9 Mile Rd",
    "sg:city":"St Clair Shores",
    "sg:classifiers":[
        {
            "category":"Wholesale",
            "subcategory":"Durable Goods & Equipment",
            "type":"Manufacturing & Wholesale Goods"
        }
    ],
    "sg:phone":"+1 586 771 1369",
    "sg:postcode":"48080",
    "sg:province":"MI",
    "sg:tags":[
        "importer"
    ],
    "wof:name":"Stoukas Imports",
    "wof:placetype":"venue"
},
  "geometry": {"coordinates":[-82.907982,42.466217],"type":"Point"}
}