{
  "type": "Feature",
  "properties": {
    "iso:country":"US",
    "sg:address":"8706 Cooley Beach Dr",
    "sg:city":"White Lake",
    "sg:classifiers":[
        {
            "category":"Professional",
            "subcategory":"Management & Consulting",
            "type":"Services"
        }
    ],
    "sg:phone":"+1 248 360 9560",
    "sg:postcode":"48386",
    "sg:province":"MI",
    "sg:tags":[
        "business"
    ],
    "wof:name":"Solutions Rock Group",
    "wof:placetype":"venue"
},
  "geometry": {"coordinates":[-83.45577900000001,42.620742],"type":"Point"}
}