{
  "type": "Feature",
  "properties": {
    "iso:country":"US",
    "sg:address":"2365 Woodlake Dr",
    "sg:city":"Okemos",
    "sg:classifiers":[
        {
            "category":"Real Estate",
            "subcategory":"Architect",
            "type":"Services"
        }
    ],
    "sg:phone":"+1 517 349 3619",
    "sg:postcode":"48864",
    "sg:province":"MI",
    "wof:name":"Studio Intrigue",
    "wof:placetype":"venue"
},
  "geometry": {"coordinates":[-84.43839199999999,42.681142],"type":"Point"}
}