{
  "type": "Feature",
  "properties": {
    "iso:country":"US",
    "sg:address":"12345 Stark Rd",
    "sg:city":"Livonia",
    "sg:classifiers":[
        {
            "category":"Professional",
            "subcategory":"Computer Services",
            "type":"Services"
        }
    ],
    "sg:phone":"+1 734 466 9101",
    "sg:postcode":"48150",
    "sg:province":"MI",
    "sg:tags":[
        "information",
        "retrieval"
    ],
    "wof:name":"Accufilm Inc",
    "wof:placetype":"venue"
},
  "geometry": {"coordinates":[-83.38036200000001,42.374556],"type":"Point"}
}