{
  "type": "Feature",
  "properties": {
    "iso:country":"US",
    "sg:address":"2409 Lakeshore Dr",
    "sg:city":"St Joseph",
    "sg:classifiers":[
        {
            "category":"Real Estate",
            "subcategory":"Real Estate Agent",
            "type":"Services"
        }
    ],
    "sg:phone":"+1 269 983 0011",
    "sg:postcode":"49085",
    "sg:province":"MI",
    "sg:website":"www.cbanchor.com",
    "wof:name":"Coldwell Banker",
    "wof:placetype":"venue"
},
  "geometry": {"coordinates":[-86.49516,42.09057],"type":"Point"}
}