{
  "type": "Feature",
  "properties": {
    "iso:country":"US",
    "sg:address":"1835 Imperial Dr",
    "sg:city":"Highland",
    "sg:classifiers":[
        {
            "category":"Organizations",
            "subcategory":"Membership Organization",
            "type":"Services"
        }
    ],
    "sg:phone":"+1 248 889 2926",
    "sg:postcode":"48356",
    "sg:province":"MI",
    "wof:name":"Gregg Gooch",
    "wof:placetype":"venue"
},
  "geometry": {"coordinates":[-83.592153,42.678796],"type":"Point"}
}