{
  "type": "Feature",
  "properties": {
    "iso:country":"US",
    "sg:address":"22332 Garrison St",
    "sg:city":"Dearborn",
    "sg:classifiers":[
        {
            "category":"Banks & Credit Unions",
            "subcategory":"Bank",
            "type":"Services"
        }
    ],
    "sg:phone":"+1 313 278 8499",
    "sg:postcode":"48124",
    "sg:province":"MI",
    "sg:website":"statefarm.com",
    "wof:name":"Murrell Leah",
    "wof:placetype":"venue"
},
  "geometry": {"coordinates":[-83.250801,42.305901],"type":"Point"}
}