{
  "type": "Feature",
  "properties": {
    "iso:country":"US",
    "sg:address":"678 Front Ave NW",
    "sg:city":"Grand Rapids",
    "sg:classifiers":[
        {
            "category":"Professional",
            "subcategory":"Research",
            "type":"Services"
        }
    ],
    "sg:phone":"+1 616 454 7979",
    "sg:postcode":"49504",
    "sg:province":"MI",
    "sg:tags":[
        "foundation",
        "philanthropic"
    ],
    "wof:name":"Epilepsy Foundation Of Mi",
    "wof:placetype":"venue"
},
  "geometry": {"coordinates":[-85.67629100000001,42.974836],"type":"Point"}
}