{
  "type": "Feature",
  "properties": {
    "iso:country":"US",
    "sg:address":"22118 Coolidge Hwy",
    "sg:city":"Oak Park",
    "sg:classifiers":[
        {
            "category":"Shopping",
            "subcategory":"Mobile Phones",
            "type":"Retail Goods"
        }
    ],
    "sg:phone":"+1 248 544 0266",
    "sg:postcode":"48237",
    "sg:province":"MI",
    "wof:name":"Oak Park Metro Pcs",
    "wof:placetype":"venue"
},
  "geometry": {"coordinates":[-83.18167,42.458538],"type":"Point"}
}