{
  "type": "Feature",
  "properties": {
    "iso:country":"US",
    "sg:address":"10154 US Hwy 2",
    "sg:city":"Rapid River",
    "sg:classifiers":[
        {
            "category":"Travel",
            "subcategory":"Hotels & Motels",
            "type":"Entertainment"
        }
    ],
    "sg:phone":"+1 906 474 6696",
    "sg:postcode":"49878",
    "sg:province":"MI",
    "wof:name":"Hill Crest Motel",
    "wof:placetype":"venue"
},
  "geometry": {"coordinates":[-86.84837899999999,45.89757],"type":"Point"}
}