{
  "type": "Feature",
  "properties": {
    "iso:country":"US",
    "sg:address":"3060 S Commerce Rd",
    "sg:city":"Walled Lake",
    "sg:classifiers":[
        {
            "category":"Insurance",
            "subcategory":"Insurance Agent",
            "type":"Services"
        }
    ],
    "sg:phone":"+1 248 926 1300",
    "sg:postcode":"48390",
    "sg:province":"MI",
    "sg:tags":[
        "specializing",
        "property",
        "agency",
        "casualty"
    ],
    "wof:name":"Insureyourbizcom",
    "wof:placetype":"venue"
},
  "geometry": {"coordinates":[-83.474335,42.566856],"type":"Point"}
}