{
  "type": "Feature",
  "properties": {
    "iso:country":"US",
    "sg:address":"311 Main St",
    "sg:city":"Twining",
    "sg:classifiers":[
        {
            "category":"Government",
            "subcategory":"Fire Station",
            "type":"Public Place"
        }
    ],
    "sg:phone":"+1 989 867 4665",
    "sg:postcode":"48766",
    "sg:province":"MI",
    "sg:tags":[
        "department"
    ],
    "wof:name":"Mason Twining Fire Dept",
    "wof:placetype":"venue"
},
  "geometry": {"coordinates":[-83.81211399999999,44.112886],"type":"Point"}
}