{
  "type": "Feature",
  "properties": {
    "iso:country":"US",
    "sg:address":"520 S Creyts Rd",
    "sg:city":"Lansing",
    "sg:classifiers":[
        {
            "category":"Professional",
            "subcategory":"Engineering",
            "type":"Services"
        }
    ],
    "sg:phone":"+1 517 321 6900",
    "sg:postcode":"48917",
    "sg:province":"MI",
    "sg:tags":[
        "consulting",
        "engineer"
    ],
    "wof:name":"Neyer Tiseo & Hindo Ltd",
    "wof:placetype":"venue"
},
  "geometry": {"coordinates":[-84.64237300000001,42.729333],"type":"Point"}
}