{
  "type": "Feature",
  "properties": {
    "iso:country":"US",
    "sg:address":"8110 Farley Rd",
    "sg:city":"Pinckney",
    "sg:classifiers":[
        {
            "category":"Education",
            "subcategory":"School",
            "type":"Public Place"
        }
    ],
    "sg:phone":"+1 810 225 6400",
    "sg:postcode":"48169",
    "sg:province":"MI",
    "sg:website":"www.pcs.k12.mi.us",
    "wof:name":"Farley Hill Elementary School",
    "wof:placetype":"venue"
},
  "geometry": {"coordinates":[-83.914348,42.479202],"type":"Point"}
}