{
  "type": "Feature",
  "properties": {
    "iso:country":"US",
    "sg:address":"19221 Mitchell St",
    "sg:city":"Detroit",
    "sg:classifiers":[
        {
            "category":"Social Services",
            "subcategory":"Child Care",
            "type":"Services"
        }
    ],
    "sg:phone":"+1 313 891 0998",
    "sg:postcode":"48234",
    "sg:province":"MI",
    "sg:tags":[
        "day"
    ],
    "wof:name":"Randall Occeletta",
    "wof:placetype":"venue"
},
  "geometry": {"coordinates":[-83.07236399999999,42.433962],"type":"Point"}
}