{
  "type": "Feature",
  "properties": {
    "iso:country":"US",
    "sg:address":"4177 Ranchero Dr",
    "sg:city":"Dorr",
    "sg:classifiers":[
        {
            "category":"Professional",
            "subcategory":"Accounting & Tax Preparation",
            "type":"Services"
        }
    ],
    "sg:phone":"+1 616 681 2947",
    "sg:postcode":"49323",
    "sg:province":"MI",
    "sg:tags":[
        "accountant"
    ],
    "wof:name":"Kas Co",
    "wof:placetype":"venue"
},
  "geometry": {"coordinates":[-85.712673,42.723227],"type":"Point"}
}