{
  "type": "Feature",
  "properties": {
    "iso:country":"US",
    "sg:address":"1744 Keats Ave",
    "sg:city":"Madison Heights",
    "sg:classifiers":[
        {
            "category":"Building & Trades",
            "subcategory":"Construction",
            "type":"Services"
        }
    ],
    "sg:phone":"+1 248 583 5529",
    "sg:postcode":"48071",
    "sg:province":"MI",
    "sg:tags":[
        "house"
    ],
    "wof:name":"Excel Home Repair Inc",
    "wof:placetype":"venue"
},
  "geometry": {"coordinates":[-83.124262,42.516772],"type":"Point"}
}