{
  "type": "Feature",
  "properties": {
    "iso:country":"US",
    "sg:address":"736 S Michigan Ave",
    "sg:city":"Howell",
    "sg:classifiers":[
        {
            "category":"Professional",
            "subcategory":"Accounting & Tax Preparation",
            "type":"Services"
        }
    ],
    "sg:phone":"+1 517 548 0505",
    "sg:postcode":"48843",
    "sg:province":"MI",
    "sg:tags":[
        "accountant"
    ],
    "wof:name":"C & J Accounting Svc",
    "wof:placetype":"venue"
},
  "geometry": {"coordinates":[-83.93368100000001,42.601107],"type":"Point"}
}