{
  "type": "Feature",
  "properties": {
    "iso:country":"US",
    "sg:address":"217 Ann Arbor Rd W Ste 302",
    "sg:city":"Plymouth",
    "sg:classifiers":[
        {
            "category":"Professional",
            "subcategory":"Lawyer & Legal Services",
            "type":"Services"
        }
    ],
    "sg:phone":"+1 734 455 4250",
    "sg:postcode":"48170",
    "sg:province":"MI",
    "wof:name":"Vos John F III Jd-Ply Legal",
    "wof:placetype":"venue"
},
  "geometry": {"coordinates":[-83.461135,42.35879],"type":"Point"}
}