{
  "type": "Feature",
  "properties": {
    "iso:country":"US",
    "sg:address":"216 Maple St",
    "sg:city":"Muir",
    "sg:classifiers":[
        {
            "category":"Government",
            "subcategory":"Office",
            "type":"Public Place"
        }
    ],
    "sg:phone":"+1 989 855 3546",
    "sg:postcode":"48860",
    "sg:province":"MI",
    "sg:tags":[
        "village"
    ],
    "wof:name":"Maintenance Garage",
    "wof:placetype":"venue"
},
  "geometry": {"coordinates":[-84.942812,43.001803],"type":"Point"}
}