{
  "type": "Feature",
  "properties": {
    "iso:country":"US",
    "sg:address":"420 N 5th St",
    "sg:city":"Burr Oak",
    "sg:classifiers":[
        {
            "category":"Building & Trades",
            "subcategory":"Construction",
            "type":"Services"
        }
    ],
    "sg:phone":"+1 269 489 0200",
    "sg:postcode":"49030",
    "sg:province":"MI",
    "sg:tags":[
        "carpentry",
        "contractor"
    ],
    "wof:name":"Burr Oak Overhead Doors",
    "wof:placetype":"venue"
},
  "geometry": {"coordinates":[-85.322357,41.852268],"type":"Point"}
}