{
  "type": "Feature",
  "properties": {
    "iso:country":"US",
    "sg:address":"760 W Wattles Rd",
    "sg:city":"Troy",
    "sg:classifiers":[
        {
            "category":"Organizations",
            "subcategory":"Religious Organization",
            "type":"Services"
        }
    ],
    "sg:phone":"+1 248 362 9575",
    "sg:postcode":"48098",
    "sg:province":"MI",
    "sg:tags":[
        "greek",
        "orthodox",
        "church"
    ],
    "wof:name":"Saint Nchls Grk Orthdx Chrch",
    "wof:placetype":"venue"
},
  "geometry": {"coordinates":[-83.162902,42.576979],"type":"Point"}
}