{
  "type": "Feature",
  "properties": {
    "iso:country":"US",
    "sg:address":"902 Razorback Dr",
    "sg:city":"Houghton",
    "sg:classifiers":[
        {
            "category":"Government",
            "subcategory":"Office",
            "type":"Public Place"
        }
    ],
    "sg:phone":"+1 906 482 6916",
    "sg:postcode":"49931",
    "sg:province":"MI",
    "wof:name":"Western Up Michigan Works",
    "wof:placetype":"venue"
},
  "geometry": {"coordinates":[-88.586032,47.109531],"type":"Point"}
}