{
  "type": "Feature",
  "properties": {
    "iso:country":"US",
    "sg:address":"3570 Shattuck Rd",
    "sg:city":"Saginaw",
    "sg:classifiers":[
        {
            "category":"Health Services",
            "subcategory":"Doctor",
            "type":"Services"
        }
    ],
    "sg:phone":"+1 989 792 5353",
    "sg:postcode":"48603",
    "sg:province":"MI",
    "sg:tags":[
        "physician",
        "surgeon"
    ],
    "wof:name":"Heritage Family Physicians",
    "wof:placetype":"venue"
},
  "geometry": {"coordinates":[-83.986452,43.451073],"type":"Point"}
}