{
  "type": "Feature",
  "properties": {
    "iso:country":"US",
    "sg:address":"449 S Main St",
    "sg:city":"Milford",
    "sg:classifiers":[
        {
            "category":"Bars & Pubs",
            "type":"Food & Drink"
        }
    ],
    "sg:phone":"+1 248 685 2800",
    "sg:postcode":"48381",
    "sg:province":"MI",
    "wof:name":"O'Callaghan's Irish Pub",
    "wof:placetype":"venue"
},
  "geometry": {"coordinates":[-83.60021399999999,42.583837],"type":"Point"}
}