{
  "type": "Feature",
  "properties": {
    "iso:country":"US",
    "sg:address":"4220 Livernois Ave",
    "sg:city":"Detroit",
    "sg:classifiers":[
        {
            "category":"Restaurant",
            "type":"Food & Drink"
        }
    ],
    "sg:phone":"+1 313 894 1111",
    "sg:postcode":"48210",
    "sg:province":"MI",
    "sg:tags":[
        "pizza"
    ],
    "wof:name":"Happy's Pizza Corp",
    "wof:placetype":"venue"
},
  "geometry": {"coordinates":[-83.12053899999999,42.331654],"type":"Point"}
}