{
  "type": "Feature",
  "properties": {
    "iso:country":"US",
    "sg:address":"778 W Columbia Ave",
    "sg:city":"Battle Creek",
    "sg:classifiers":[
        {
            "category":"Organizations",
            "subcategory":"Membership Organization",
            "type":"Services"
        },
        {
            "category":"Insurance",
            "subcategory":"Insurance Agent",
            "type":"Services"
        }
    ],
    "sg:phone":"+1 269 962 2500",
    "sg:postcode":"49015",
    "sg:province":"MI",
    "sg:tags":[
        "automobile"
    ],
    "wof:name":"AAA Michigan",
    "wof:placetype":"venue"
},
  "geometry": {"coordinates":[-85.211618,42.298606],"type":"Point"}
}