{
  "type": "Feature",
  "properties": {
    "iso:country":"US",
    "sg:address":"17753 Northrop St",
    "sg:city":"Detroit",
    "sg:classifiers":[
        {
            "category":"Retail",
            "subcategory":"Laundry & Dry Cleaning",
            "type":"Services"
        }
    ],
    "sg:phone":"+1 313 531 2023",
    "sg:postcode":"48219",
    "sg:province":"MI",
    "wof:name":"Sunrise Carpet Cleaning",
    "wof:placetype":"venue"
},
  "geometry": {"coordinates":[-83.26156400000001,42.421726],"type":"Point"}
}