{
  "type": "Feature",
  "properties": {
    "iso:country":"US",
    "sg:address":"342 Park St",
    "sg:city":"Deerfield",
    "sg:classifiers":[
        {
            "category":"Building & Trades",
            "subcategory":"Cleaning & Sanitation",
            "type":"Services"
        }
    ],
    "sg:phone":"+1 517 447 4014",
    "sg:postcode":"49238",
    "sg:province":"MI",
    "sg:tags":[
        "ventilating",
        "system"
    ],
    "wof:name":"Indoor Air Specialist",
    "wof:placetype":"venue"
},
  "geometry": {"coordinates":[-83.77630499999999,41.891744],"type":"Point"}
}