{
  "type": "Feature",
  "properties": {
    "iso:country":"US",
    "sg:address":"20924 Robinson St",
    "sg:city":"Farmington Hills",
    "sg:classifiers":[
        {
            "category":"Building & Trades",
            "subcategory":"Construction",
            "type":"Services"
        }
    ],
    "sg:phone":"+1 248 471 1605",
    "sg:postcode":"48336",
    "sg:province":"MI",
    "sg:tags":[
        "roofing",
        "contractor"
    ],
    "wof:name":"Horizon Construction",
    "wof:placetype":"venue"
},
  "geometry": {"coordinates":[-83.361981,42.444359],"type":"Point"}
}