{
  "type": "Feature",
  "properties": {
    "iso:country":"US",
    "sg:address":"1361 W Silver Lake Rd N",
    "sg:city":"Traverse City",
    "sg:classifiers":[
        {
            "category":"Building & Trades",
            "subcategory":"Landscaping Services",
            "type":"Services"
        }
    ],
    "sg:phone":"+1 231 947 7366",
    "sg:postcode":"49684",
    "sg:province":"MI",
    "sg:tags":[
        "lawn",
        "maintenance",
        "grounds"
    ],
    "wof:name":"Clearbrook OR LLC",
    "wof:placetype":"venue"
},
  "geometry": {"coordinates":[-85.69239399999999,44.707979],"type":"Point"}
}