{
  "type": "Feature",
  "properties": {
    "iso:country":"US",
    "sg:address":"2611 Olthoff Dr",
    "sg:city":"Muskegon",
    "sg:classifiers":[
        {
            "category":"Professional",
            "type":"Services"
        }
    ],
    "sg:phone":"+1 231 767 3213",
    "sg:postcode":"49444",
    "sg:province":"MI",
    "wof:name":"Sunset Waste Systems",
    "wof:placetype":"venue"
},
  "geometry": {"coordinates":[-86.173523,43.207524],"type":"Point"}
}