{
  "type": "Feature",
  "properties": {
    "iso:country":"US",
    "sg:address":"822 W Main St",
    "sg:city":"Owosso",
    "sg:classifiers":[
        {
            "category":"Shopping",
            "subcategory":"Music",
            "type":"Retail Goods"
        }
    ],
    "sg:phone":"+1 989 723 6448",
    "sg:postcode":"48867",
    "sg:province":"MI",
    "sg:tags":[
        "record"
    ],
    "wof:name":"Round Midnight Records",
    "wof:placetype":"venue"
},
  "geometry": {"coordinates":[-84.18053399999999,42.997698],"type":"Point"}
}