{
  "type": "Feature",
  "properties": {
    "iso:country":"US",
    "sg:address":"8295 Pine Knob Rd",
    "sg:city":"Clarkston",
    "sg:classifiers":[
        {
            "category":"Retail",
            "subcategory":"Auto Repair",
            "type":"Services"
        }
    ],
    "sg:phone":"+1 248 394 0535",
    "sg:postcode":"48348",
    "sg:province":"MI",
    "sg:tags":[
        "general"
    ],
    "wof:name":"Independence Truck & Eqp Repr",
    "wof:placetype":"venue"
},
  "geometry": {"coordinates":[-83.37089,42.760048],"type":"Point"}
}