{
  "type": "Feature",
  "properties": {
    "iso:country":"US",
    "sg:address":"2515 Parkview St SW",
    "sg:city":"Grand Rapids",
    "sg:classifiers":[
        {
            "category":"Building & Trades",
            "subcategory":"Construction",
            "type":"Services"
        }
    ],
    "sg:phone":"+1 616 534 5548",
    "sg:postcode":"49519",
    "sg:province":"MI",
    "sg:tags":[
        "house"
    ],
    "wof:name":"Todd Barker Construction",
    "wof:placetype":"venue"
},
  "geometry": {"coordinates":[-85.727628,42.877959],"type":"Point"}
}