{
  "type": "Feature",
  "properties": {
    "iso:country":"US",
    "sg:address":"2820 W Maple Rd",
    "sg:city":"Troy",
    "sg:classifiers":[
        {
            "category":"Social Services",
            "type":"Services"
        }
    ],
    "sg:phone":"+1 248 643 8340",
    "sg:postcode":"48084",
    "sg:province":"MI",
    "sg:tags":[
        "professional",
        "counselor"
    ],
    "wof:name":"Counseling Services",
    "wof:placetype":"venue"
},
  "geometry": {"coordinates":[-83.18612299999999,42.547519],"type":"Point"}
}