{
  "type": "Feature",
  "properties": {
    "iso:country":"US",
    "sg:address":"15212 Chadwick Rd",
    "sg:city":"Portland",
    "sg:classifiers":[
        {
            "category":"Building & Trades",
            "subcategory":"Construction",
            "type":"Services"
        }
    ],
    "sg:phone":"+1 517 647 7255",
    "sg:postcode":"48875",
    "sg:province":"MI",
    "sg:tags":[
        "excavating",
        "contractor"
    ],
    "wof:name":"Martin Excavating",
    "wof:placetype":"venue"
},
  "geometry": {"coordinates":[-84.81996599999999,42.871617],"type":"Point"}
}