{
  "type": "Feature",
  "properties": {
    "iso:country":"US",
    "sg:address":"5405 W Saginaw Hwy",
    "sg:city":"Lansing",
    "sg:classifiers":[
        {
            "category":"Restaurant",
            "type":"Food & Drink"
        }
    ],
    "sg:phone":"+1 517 321 8808",
    "sg:postcode":"48917",
    "sg:province":"MI",
    "wof:name":"Dok Sing Restaurant",
    "wof:placetype":"venue"
},
  "geometry": {"coordinates":[-84.62232899999999,42.74111],"type":"Point"}
}