{
  "type": "Feature",
  "properties": {
    "iso:country":"US",
    "sg:address":"35844 Jefferson Ave",
    "sg:city":"Harrison Township",
    "sg:classifiers":[
        {
            "category":"Real Estate",
            "subcategory":"Real Estate Operator",
            "type":"Services"
        },
        {
            "category":"Real Estate",
            "subcategory":"Real Estate Agent",
            "type":"Services"
        }
    ],
    "sg:phone":"+1 586 791 3093",
    "sg:postcode":"48045",
    "sg:province":"MI",
    "sg:tags":[
        "apartment"
    ],
    "wof:name":"Village Green On Lake St Clair",
    "wof:placetype":"venue"
},
  "geometry": {"coordinates":[-82.849701,42.559299],"type":"Point"}
}