{
  "type": "Feature",
  "properties": {
    "iso:country":"US",
    "sg:address":"1709 Short Rd",
    "sg:city":"Saginaw",
    "sg:classifiers":[
        {
            "category":"Building & Trades",
            "subcategory":"Electrical",
            "type":"Services"
        }
    ],
    "sg:phone":"+1 989 781 2563",
    "sg:postcode":"48609",
    "sg:province":"MI",
    "sg:tags":[
        "electric",
        "contractor"
    ],
    "wof:name":"Curtis Electric",
    "wof:placetype":"venue"
},
  "geometry": {"coordinates":[-84.066858,43.431458],"type":"Point"}
}