{
  "type": "Feature",
  "properties": {
    "iso:country":"US",
    "sg:address":"870 Sturdevant Rd",
    "sg:city":"Kimball",
    "sg:classifiers":[
        {
            "category":"Retail",
            "subcategory":"Repair Shop",
            "type":"Services"
        }
    ],
    "sg:phone":"+1 810 367 3802",
    "sg:postcode":"48074",
    "sg:province":"MI",
    "sg:tags":[
        "radio",
        "television",
        "electrical"
    ],
    "wof:name":"Fix It Shop",
    "wof:placetype":"venue"
},
  "geometry": {"coordinates":[-82.581451,42.929111],"type":"Point"}
}