{
  "type": "Feature",
  "properties": {
    "iso:country":"US",
    "sg:address":"3420 Casey Rd",
    "sg:city":"Metamora",
    "sg:classifiers":[
        {
            "category":"Professional",
            "subcategory":"Testing Lab",
            "type":"Services"
        }
    ],
    "sg:phone":"+1 810 796 3892",
    "sg:postcode":"48455",
    "sg:province":"MI",
    "sg:tags":[
        "facility"
    ],
    "wof:name":"Bio Energetic Testing Svcs LLC",
    "wof:placetype":"venue"
},
  "geometry": {"coordinates":[-83.213111,42.921542],"type":"Point"}
}