{
  "type": "Feature",
  "properties": {
    "iso:country":"US",
    "sg:address":"2027 S Telegraph Rd",
    "sg:city":"Dearborn",
    "sg:classifiers":[
        {
            "category":"Autos & Motor Vehicles",
            "subcategory":"Automobile Sales",
            "type":"Retail Goods"
        }
    ],
    "sg:phone":"+1 313 730 2100",
    "sg:postcode":"48124",
    "sg:province":"MI",
    "sg:tags":[
        "car"
    ],
    "wof:name":"Lafontaine Import Motors Inc",
    "wof:placetype":"venue"
},
  "geometry": {"coordinates":[-83.271103,42.296799],"type":"Point"}
}