{
  "type": "Feature",
  "properties": {
    "iso:country":"US",
    "sg:address":"2640 Thornwood St SW",
    "sg:city":"Wyoming",
    "sg:classifiers":[
        {
            "category":"Building & Trades",
            "subcategory":"Landscaping Services",
            "type":"Services"
        }
    ],
    "sg:phone":"+1 616 530 9775",
    "sg:postcode":"49519",
    "sg:province":"MI",
    "sg:tags":[
        "lawn",
        "maintenance",
        "grounds"
    ],
    "wof:name":"Witte Lawn Maintenance Inc",
    "wof:placetype":"venue"
},
  "geometry": {"coordinates":[-85.729632,42.917421],"type":"Point"}
}