{
  "type": "Feature",
  "properties": {
    "iso:country":"US",
    "sg:address":"4118 Baldwin Rd",
    "sg:city":"Auburn Hills",
    "sg:classifiers":[
        {
            "category":"Shopping",
            "subcategory":"Clothing, Apparel, & Fashions",
            "type":"Retail Goods"
        }
    ],
    "sg:phone":"+1 248 332 4769",
    "sg:postcode":"48326",
    "sg:province":"MI",
    "sg:tags":[
        "lingerie"
    ],
    "wof:name":"Maidenform",
    "wof:placetype":"venue"
},
  "geometry": {"coordinates":[-83.30676099999999,42.701358],"type":"Point"}
}