{
  "type": "Feature",
  "properties": {
    "iso:country":"US",
    "sg:address":"20400 E 9 Mile Rd",
    "sg:city":"St Clair Shores",
    "sg:classifiers":[
        {
            "category":"Wholesale",
            "subcategory":"Durable Goods & Equipment",
            "type":"Manufacturing & Wholesale Goods"
        }
    ],
    "sg:phone":"+1 586 774 6600",
    "sg:postcode":"48080",
    "sg:province":"MI",
    "sg:tags":[
        "representative",
        "manufacturer"
    ],
    "wof:name":"Jorgenson & Co",
    "wof:placetype":"venue"
},
  "geometry": {"coordinates":[-82.912002,42.465884],"type":"Point"}
}