{
  "type": "Feature",
  "properties": {
    "iso:country":"US",
    "sg:address":"20071 James Couzens Fwy",
    "sg:city":"Detroit",
    "sg:classifiers":[
        {
            "category":"Professional",
            "subcategory":"Art Services",
            "type":"Services"
        }
    ],
    "sg:phone":"+1 313 862 6112",
    "sg:postcode":"48235",
    "sg:province":"MI",
    "sg:tags":[
        "commercial",
        "design"
    ],
    "wof:name":"Sportswear Ltd",
    "wof:placetype":"venue"
},
  "geometry": {"coordinates":[-83.197452,42.439815],"type":"Point"}
}