{
  "type": "Feature",
  "properties": {
    "iso:country":"US",
    "sg:address":"8103 Holly Rd",
    "sg:city":"Grand Blanc",
    "sg:classifiers":[
        {
            "category":"Health Services",
            "subcategory":"Doctor",
            "type":"Services"
        }
    ],
    "sg:phone":"+1 810 695 2580",
    "sg:postcode":"48439",
    "sg:province":"MI",
    "sg:tags":[
        "dentist"
    ],
    "wof:name":"Lakeside Dental Assoc",
    "wof:placetype":"venue"
},
  "geometry": {"coordinates":[-83.621877,42.915203],"type":"Point"}
}