{
  "type": "Feature",
  "properties": {
    "iso:country":"US",
    "sg:address":"6350 King Rd",
    "sg:city":"Cottrellville",
    "sg:classifiers":[
        {
            "category":"Retail",
            "subcategory":"Auto Repair",
            "type":"Services"
        }
    ],
    "sg:phone":"+1 810 765 9790",
    "sg:postcode":"48039",
    "sg:province":"MI",
    "sg:tags":[
        "body",
        "automobile",
        "painting"
    ],
    "wof:name":"J D's Auto & Auto Body",
    "wof:placetype":"venue"
},
  "geometry": {"coordinates":[-82.509626,42.716494],"type":"Point"}
}