{
  "type": "Feature",
  "properties": {
    "iso:country":"US",
    "sg:address":"148 S Saginaw St",
    "sg:city":"Saginaw",
    "sg:classifiers":[
        {
            "category":"Organizations",
            "subcategory":"Community Association",
            "type":"Services"
        }
    ],
    "sg:phone":"+1 989 865 8568",
    "sg:postcode":"48655",
    "sg:province":"MI",
    "sg:tags":[
        "club"
    ],
    "wof:name":"Masonic Lodge",
    "wof:placetype":"venue"
},
  "geometry": {"coordinates":[-84.140317,43.296591],"type":"Point"}
}