{
  "type": "Feature",
  "properties": {
    "iso:country":"US",
    "sg:address":"2801 S Dort Hwy",
    "sg:city":"Flint",
    "sg:classifiers":[
        {
            "category":"Real Estate",
            "subcategory":"Real Estate Operator",
            "type":"Services"
        }
    ],
    "sg:phone":"+1 810 743 2111",
    "sg:postcode":"48507",
    "sg:province":"MI",
    "sg:tags":[
        "mobile",
        "home",
        "community"
    ],
    "wof:name":"Elms Mobile Home Park",
    "wof:placetype":"venue"
},
  "geometry": {"coordinates":[-83.65364700000001,42.996067],"type":"Point"}
}