{
  "type": "Feature",
  "properties": {
    "iso:country":"US",
    "sg:address":"16 Burton St SW",
    "sg:city":"Grand Rapids",
    "sg:classifiers":[
        {
            "category":"Food & Beverages",
            "subcategory":"Groceries & Convenience Stores",
            "type":"Retail Goods"
        }
    ],
    "sg:phone":"+1 616 243 0217",
    "sg:postcode":"49507",
    "sg:province":"MI",
    "sg:tags":[
        "grocer"
    ],
    "wof:name":"Burton Heights Foodland",
    "wof:placetype":"venue"
},
  "geometry": {"coordinates":[-85.669346,42.92752],"type":"Point"}
}