{
  "type": "Feature",
  "properties": {
    "iso:country":"US",
    "sg:address":"2730 Charnwood Dr",
    "sg:city":"Troy",
    "sg:classifiers":[
        {
            "category":"Professional",
            "subcategory":"Management & Consulting",
            "type":"Services"
        }
    ],
    "sg:phone":"+1 248 616 0694",
    "sg:postcode":"48098",
    "sg:province":"MI",
    "wof:name":"Omp Studios",
    "wof:placetype":"venue"
},
  "geometry": {"coordinates":[-83.200211,42.608176],"type":"Point"}
}