{
  "type": "Feature",
  "properties": {
    "iso:country":"US",
    "sg:address":"1174 W Michigan Ave",
    "sg:city":"Marshall",
    "sg:classifiers":[
        {
            "category":"Health Services",
            "subcategory":"Doctor",
            "type":"Services"
        }
    ],
    "sg:phone":"+1 269 781 9867",
    "sg:postcode":"49068",
    "sg:province":"MI",
    "wof:name":"Albion Medical Asssociates",
    "wof:placetype":"venue"
},
  "geometry": {"coordinates":[-84.977706,42.272033],"type":"Point"}
}