{
  "type": "Feature",
  "properties": {
    "iso:country":"US",
    "sg:address":"15944 W 12 Mile Rd",
    "sg:city":"Southfield",
    "sg:classifiers":[
        {
            "category":"Wholesale",
            "subcategory":"Hardware",
            "type":"Manufacturing & Wholesale Goods"
        }
    ],
    "sg:phone":"+1 248 569 3340",
    "sg:postcode":"48076",
    "sg:province":"MI",
    "sg:tags":[
        "used",
        "boiler"
    ],
    "wof:name":"Car-Bee Inc",
    "wof:placetype":"venue"
},
  "geometry": {"coordinates":[-83.207033,42.502907],"type":"Point"}
}