{
  "type": "Feature",
  "properties": {
    "iso:country":"US",
    "sg:address":"3136 Francis St",
    "sg:city":"Jackson",
    "sg:classifiers":[
        {
            "category":"Manufacturing",
            "subcategory":"Printing",
            "type":"Manufacturing & Wholesale Goods"
        }
    ],
    "sg:phone":"+1 517 783 2705",
    "sg:postcode":"49203",
    "sg:province":"MI",
    "sg:tags":[
        "commercial"
    ],
    "sg:website":"www.jacksonprinting.com",
    "wof:name":"Jackson Printing Co Inc",
    "wof:placetype":"venue"
},
  "geometry": {"coordinates":[-84.39862100000001,42.214495],"type":"Point"}
}