{
  "type": "Feature",
  "properties": {
    "iso:country":"US",
    "sg:address":"7650 Caterpillar Ct SW",
    "sg:city":"Grand Rapids",
    "sg:classifiers":[
        {
            "category":"Professional",
            "subcategory":"Business Services",
            "type":"Services"
        }
    ],
    "sg:phone":"+1 616 827 8525",
    "sg:postcode":"49548",
    "sg:province":"MI",
    "sg:tags":[
        "packaging"
    ],
    "wof:name":"Praxis Packaging Solutions LLC",
    "wof:placetype":"venue"
},
  "geometry": {"coordinates":[-85.669236,42.822466],"type":"Point"}
}