{
  "type": "Feature",
  "properties": {
    "iso:country":"US",
    "sg:address":"338 W State St",
    "sg:city":"Sterling",
    "sg:classifiers":[
        {
            "category":"Education",
            "subcategory":"School",
            "type":"Public Place"
        }
    ],
    "sg:phone":"+1 989 654 2367",
    "sg:postcode":"48659",
    "sg:province":"MI",
    "sg:website":"www.standish-sterling.org",
    "wof:name":"Sterling Elementary School",
    "wof:placetype":"venue"
},
  "geometry": {"coordinates":[-84.026471,44.033369],"type":"Point"}
}