{
  "type": "Feature",
  "properties": {
    "iso:country":"US",
    "sg:address":"309 W Saginaw Rd",
    "sg:city":"Sanford",
    "sg:classifiers":[
        {
            "category":"Personal",
            "subcategory":"Beauty Salon",
            "type":"Services"
        }
    ],
    "sg:phone":"+1 989 687 7666",
    "sg:postcode":"48657",
    "sg:province":"MI",
    "wof:name":"C J's Hairstyling",
    "wof:placetype":"venue"
},
  "geometry": {"coordinates":[-84.380805,43.671885],"type":"Point"}
}