{
  "type": "Feature",
  "properties": {
    "iso:country":"US",
    "sg:address":"3070 Country Club Dr",
    "sg:city":"Muskegon",
    "sg:classifiers":[
        {
            "category":"Arts & Performance",
            "subcategory":"Theater",
            "type":"Entertainment"
        }
    ],
    "sg:phone":"+1 231 755 7300",
    "sg:postcode":"49441",
    "sg:province":"MI",
    "sg:tags":[
        "group"
    ],
    "wof:name":"A Sound Encounter",
    "wof:placetype":"venue"
},
  "geometry": {"coordinates":[-86.31927399999999,43.212317],"type":"Point"}
}