{
  "type": "Feature",
  "properties": {
    "iso:country":"US",
    "sg:address":"44947 W Red Arrow Hwy",
    "sg:city":"Paw Paw",
    "sg:classifiers":[
        {
            "category":"Food & Beverages",
            "subcategory":"Groceries & Convenience Stores",
            "type":"Retail Goods"
        }
    ],
    "sg:phone":"+1 269 657 6777",
    "sg:postcode":"49079",
    "sg:province":"MI",
    "wof:name":"Lakeside Convenience Store",
    "wof:placetype":"venue"
},
  "geometry": {"coordinates":[-85.989637,42.211128],"type":"Point"}
}