{
  "type": "Feature",
  "properties": {
    "iso:country":"US",
    "sg:address":"400 Silver St",
    "sg:city":"Ironwood",
    "sg:classifiers":[
        {
            "category":"Restaurant",
            "type":"Food & Drink"
        }
    ],
    "sg:phone":"+1 906 932 0989",
    "sg:postcode":"49938",
    "sg:province":"MI",
    "wof:name":"Pizza King Joe",
    "wof:placetype":"venue"
},
  "geometry": {"coordinates":[-90.177317,46.449911],"type":"Point"}
}