{
  "type": "Feature",
  "properties": {
    "iso:country":"US",
    "sg:address":"22217 Michigan Ave",
    "sg:city":"Dearborn",
    "sg:classifiers":[
        {
            "category":"Bars & Pubs",
            "type":"Food & Drink"
        }
    ],
    "sg:phone":"+1 313 730 1630",
    "sg:postcode":"48124",
    "sg:province":"MI",
    "sg:website":"www.moosesmartinipub.com/",
    "wof:name":"Moose's Martini Pub",
    "wof:placetype":"venue"
},
  "geometry": {"coordinates":[-83.248583,42.30515],"type":"Point"}
}