{
  "type": "Feature",
  "properties": {
    "iso:country":"US",
    "sg:address":"63395 Lakeshore Dr",
    "sg:city":"Dowagiac",
    "sg:classifiers":[
        {
            "category":"Autos & Motor Vehicles",
            "subcategory":"Boat Sales",
            "type":"Retail Goods"
        }
    ],
    "sg:phone":"+1 269 424 5960",
    "sg:postcode":"49047",
    "sg:province":"MI",
    "sg:tags":[
        "dealer",
        "sales"
    ],
    "wof:name":"Blue Fin Marina",
    "wof:placetype":"venue"
},
  "geometry": {"coordinates":[-86.159667,42.072258],"type":"Point"}
}