{
  "type": "Feature",
  "properties": {
    "iso:country":"US",
    "sg:address":"412 Stanwood St",
    "sg:city":"Kalamazoo",
    "sg:classifiers":[
        {
            "category":"Professional",
            "type":"Services"
        }
    ],
    "sg:phone":"+1 269 567 4335",
    "sg:postcode":"49006",
    "sg:province":"MI",
    "sg:tags":[
        "establishment"
    ],
    "wof:name":"Geek Group",
    "wof:placetype":"venue"
},
  "geometry": {"coordinates":[-85.60237499999999,42.287295],"type":"Point"}
}