{
  "type": "Feature",
  "properties": {
    "iso:country":"US",
    "sg:address":"525 E Garfield Rd",
    "sg:city":"Ashley",
    "sg:classifiers":[
        {
            "category":"Freight",
            "type":"Transportation"
        }
    ],
    "sg:phone":"+1 989 838 4147",
    "sg:postcode":"48806",
    "sg:province":"MI",
    "sg:tags":[
        "trucking"
    ],
    "wof:name":"P J's Trucking Inc",
    "wof:placetype":"venue"
},
  "geometry": {"coordinates":[-84.594275,43.190561],"type":"Point"}
}