{
  "type": "Feature",
  "properties": {
    "iso:country":"US",
    "sg:address":"18226 Pine Meadows Dr",
    "sg:city":"Thompsonville",
    "sg:classifiers":[
        {
            "category":"Building & Trades",
            "subcategory":"Plumbing",
            "type":"Services"
        }
    ],
    "sg:phone":"+1 231 378 4412",
    "sg:postcode":"49683",
    "sg:province":"MI",
    "sg:tags":[
        "contractor"
    ],
    "wof:name":"Rons Heating Co LLC",
    "wof:placetype":"venue"
},
  "geometry": {"coordinates":[-85.97318199999999,44.502066],"type":"Point"}
}