{
  "type": "Feature",
  "properties": {
    "iso:country":"US",
    "sg:address":"415 W Main St",
    "sg:city":"Hartford",
    "sg:classifiers":[
        {
            "category":"Professional",
            "subcategory":"Business Services",
            "type":"Services"
        }
    ],
    "sg:phone":"+1 269 621 6681",
    "sg:postcode":"49057",
    "sg:province":"MI",
    "sg:tags":[
        "auctioneer"
    ],
    "wof:name":"D & J Auction",
    "wof:placetype":"venue"
},
  "geometry": {"coordinates":[-86.17322900000001,42.20661],"type":"Point"}
}