{
  "type": "Feature",
  "properties": {
    "iso:country":"US",
    "sg:address":"105 W Sheridan St",
    "sg:city":"Fremont",
    "sg:classifiers":[
        {
            "category":"Organizations",
            "subcategory":"Religious Organization",
            "type":"Services"
        }
    ],
    "sg:phone":"+1 231 924 7047",
    "sg:postcode":"49412",
    "sg:province":"MI",
    "wof:name":"Grace Community Church",
    "wof:placetype":"venue"
},
  "geometry": {"coordinates":[-85.94908,43.46629],"type":"Point"}
}