{
  "type": "Feature",
  "properties": {
    "iso:country":"US",
    "sg:address":"149 S Main St",
    "sg:city":"Leslie",
    "sg:classifiers":[
        {
            "category":"Shopping",
            "subcategory":"Clothing, Apparel, & Fashions",
            "type":"Retail Goods"
        }
    ],
    "sg:phone":"+1 517 589 5097",
    "sg:postcode":"49251",
    "sg:province":"MI",
    "sg:tags":[
        "shop",
        "bridal"
    ],
    "wof:name":"Tropical Bridal",
    "wof:placetype":"venue"
},
  "geometry": {"coordinates":[-84.431849,42.450328],"type":"Point"}
}