{
  "type": "Feature",
  "properties": {
    "iso:country":"US",
    "sg:address":"8642 E Main St",
    "sg:city":"Galesburg",
    "sg:classifiers":[
        {
            "category":"Building & Trades",
            "subcategory":"Cleaning & Sanitation",
            "type":"Services"
        }
    ],
    "sg:phone":"+1 269 381 1852",
    "sg:postcode":"49053",
    "sg:province":"MI",
    "sg:tags":[
        "janitor"
    ],
    "wof:name":"Shadwick's Custom Cleaning",
    "wof:placetype":"venue"
},
  "geometry": {"coordinates":[-85.462369,42.302912],"type":"Point"}
}