{
  "type": "Feature",
  "properties": {
    "iso:country":"US",
    "sg:address":"12011 Brooklyn Rd",
    "sg:city":"Brooklyn",
    "sg:classifiers":[
        {
            "category":"Freight",
            "type":"Transportation"
        }
    ],
    "sg:phone":"+1 517 592 3989",
    "sg:postcode":"49230",
    "sg:province":"MI",
    "sg:tags":[
        "commercial",
        "storage"
    ],
    "wof:name":"Affordable Storage Of Brooklyn",
    "wof:placetype":"venue"
},
  "geometry": {"coordinates":[-84.247744,42.090554],"type":"Point"}
}