{
  "type": "Feature",
  "properties": {
    "iso:country":"US",
    "sg:address":"201 Culver St",
    "sg:city":"Saugatuck",
    "sg:classifiers":[
        {
            "category":"Shopping",
            "subcategory":"Gifts & Souvenirs",
            "type":"Retail Goods"
        }
    ],
    "sg:phone":"+1 269 857 4400",
    "sg:postcode":"49453",
    "sg:province":"MI",
    "wof:name":"Touches",
    "wof:placetype":"venue"
},
  "geometry": {"coordinates":[-86.20284100000001,42.654793],"type":"Point"}
}