{
  "type": "Feature",
  "properties": {
    "iso:country":"US",
    "sg:address":"10481 W 17 Mile Rd",
    "sg:city":"Rudyard",
    "sg:classifiers":[
        {
            "category":"Farming",
            "subcategory":"Farm",
            "type":"Manufacturing & Wholesale Goods"
        }
    ],
    "sg:phone":"+1 906 478 3808",
    "sg:postcode":"49780",
    "sg:province":"MI",
    "sg:tags":[
        "crop",
        "general"
    ],
    "wof:name":"Chippewa County Farm Bureau",
    "wof:placetype":"venue"
},
  "geometry": {"coordinates":[-84.57866199999999,46.259511],"type":"Point"}
}