{
  "type": "Feature",
  "properties": {
    "iso:country":"US",
    "sg:address":"772 McPherson Park Dr",
    "sg:city":"Howell",
    "sg:classifiers":[
        {
            "category":"Wholesale",
            "subcategory":"Hardware",
            "type":"Manufacturing & Wholesale Goods"
        }
    ],
    "sg:phone":"+1 517 548 2114",
    "sg:postcode":"48843",
    "sg:province":"MI",
    "sg:tags":[
        "furnace"
    ],
    "sg:website":"www.pyro-heating.com",
    "wof:name":"Pyro Heating & Cooling Inc",
    "wof:placetype":"venue"
},
  "geometry": {"coordinates":[-83.944164,42.603244],"type":"Point"}
}