{
  "type": "Feature",
  "properties": {
    "iso:country":"US",
    "sg:address":"9042 Red Arrow Hwy",
    "sg:city":"Bridgman",
    "sg:classifiers":[
        {
            "category":"Building & Trades",
            "subcategory":"Construction",
            "type":"Services"
        }
    ],
    "sg:phone":"+1 269 465 4399",
    "sg:postcode":"49106",
    "sg:province":"MI",
    "sg:tags":[
        "general",
        "contractor"
    ],
    "wof:name":"Berger Construction",
    "wof:placetype":"venue"
},
  "geometry": {"coordinates":[-86.554823,41.951716],"type":"Point"}
}