{
  "type": "Feature",
  "properties": {
    "iso:country":"US",
    "sg:address":"641 Diamond Ave NE",
    "sg:city":"Grand Rapids",
    "sg:classifiers":[
        {
            "category":"Shopping",
            "type":"Retail Goods"
        }
    ],
    "sg:phone":"+1 616 776 0450",
    "sg:postcode":"49503",
    "sg:province":"MI",
    "sg:tags":[
        "religious"
    ],
    "wof:name":"Angelus Religious Goods",
    "wof:placetype":"venue"
},
  "geometry": {"coordinates":[-85.64477100000001,42.974553],"type":"Point"}
}