{
  "type": "Feature",
  "properties": {
    "iso:country":"US",
    "sg:address":"1197 S Carney Dr",
    "sg:city":"St Clair",
    "sg:classifiers":[
        {
            "category":"Shopping",
            "subcategory":"Tobacco",
            "type":"Retail Goods"
        }
    ],
    "sg:phone":"+1 810 329 9010",
    "sg:postcode":"48079",
    "sg:province":"MI",
    "sg:tags":[
        "cigarette",
        "cigar",
        "dealer"
    ],
    "wof:name":"Smokers Planet II",
    "wof:placetype":"venue"
},
  "geometry": {"coordinates":[-82.50504100000001,42.818166],"type":"Point"}
}