{
  "type": "Feature",
  "properties": {
    "iso:country":"US",
    "sg:address":"1200 S Williams Lake Rd",
    "sg:city":"White Lake",
    "sg:classifiers":[
        {
            "category":"Building & Trades",
            "subcategory":"Construction",
            "type":"Services"
        }
    ],
    "sg:phone":"+1 248 363 5511",
    "sg:postcode":"48386",
    "sg:province":"MI",
    "sg:tags":[
        "insulation",
        "heat",
        "contractor"
    ],
    "wof:name":"Industrial Insulation Co",
    "wof:placetype":"venue"
},
  "geometry": {"coordinates":[-83.442241,42.620901],"type":"Point"}
}