{
  "type": "Feature",
  "properties": {
    "iso:country":"US",
    "sg:address":"68 Kibbee St",
    "sg:city":"Mount Clemens",
    "sg:classifiers":[
        {
            "category":"Organizations",
            "subcategory":"Religious Organization",
            "type":"Services"
        }
    ],
    "sg:phone":"+1 586 465 1441",
    "sg:postcode":"48043",
    "sg:province":"MI",
    "sg:tags":[
        "church"
    ],
    "sg:website":"www.stephentemple.com",
    "wof:name":"Stephen Temple",
    "wof:placetype":"venue"
},
  "geometry": {"coordinates":[-82.87799800000001,42.5867],"type":"Point"}
}