{
  "type": "Feature",
  "properties": {
    "iso:country":"US",
    "sg:address":"47564 Pontiac Trl",
    "sg:city":"Wixom",
    "sg:classifiers":[
        {
            "category":"Retail",
            "subcategory":"Auto Repair",
            "type":"Services"
        }
    ],
    "sg:phone":"+1 248 624 2939",
    "sg:postcode":"48393",
    "sg:province":"MI",
    "sg:tags":[
        "truck",
        "general"
    ],
    "wof:name":"Johnnies Garage",
    "wof:placetype":"venue"
},
  "geometry": {"coordinates":[-83.51909000000001,42.524812],"type":"Point"}
}