{
  "type": "Feature",
  "properties": {
    "iso:country":"US",
    "sg:address":"23111 Lahser Rd",
    "sg:city":"Southfield",
    "sg:classifiers":[
        {
            "category":"Shopping",
            "subcategory":"Pharmacy",
            "type":"Retail Goods"
        }
    ],
    "sg:phone":"+1 248 945 9216",
    "sg:postcode":"48033",
    "sg:province":"MI",
    "sg:tags":[
        "drugstore"
    ],
    "sg:website":"www.walgreens.com",
    "wof:name":"Walgreen Drug Stores",
    "wof:placetype":"venue"
},
  "geometry": {"coordinates":[-83.260288,42.458738],"type":"Point"}
}