{
  "type": "Feature",
  "properties": {
    "iso:country":"US",
    "sg:address":"1015 N Hickory St",
    "sg:city":"Owosso",
    "sg:classifiers":[
        {
            "category":"Retail",
            "subcategory":"Repair Shop",
            "type":"Services"
        }
    ],
    "sg:phone":"+1 989 725 6941",
    "sg:postcode":"48867",
    "sg:province":"MI",
    "sg:tags":[
        "upholsterer"
    ],
    "wof:name":"Jan's Upholstery & Interiors",
    "wof:placetype":"venue"
},
  "geometry": {"coordinates":[-84.167168,43.008553],"type":"Point"}
}