{
  "type": "Feature",
  "properties": {
    "iso:country":"US",
    "sg:address":"26300 Northwestern Hwy",
    "sg:city":"Southfield",
    "sg:classifiers":[
        {
            "category":"Professional",
            "subcategory":"Management & Consulting",
            "type":"Services"
        }
    ],
    "sg:phone":"+1 248 356 5488",
    "sg:postcode":"48076",
    "sg:province":"MI",
    "sg:tags":[
        "consultant",
        "business"
    ],
    "wof:name":"Southfield Oxford Assoc",
    "wof:placetype":"venue"
},
  "geometry": {"coordinates":[-83.26121500000001,42.483781],"type":"Point"}
}