{
  "type": "Feature",
  "properties": {
    "iso:country":"US",
    "sg:address":"1955 Hasler Lake Rd",
    "sg:city":"Lapeer",
    "sg:classifiers":[
        {
            "category":"Building & Trades",
            "subcategory":"Construction",
            "type":"Services"
        }
    ],
    "sg:phone":"+1 810 653 9502",
    "sg:postcode":"48446",
    "sg:province":"MI",
    "sg:tags":[
        "contractor"
    ],
    "wof:name":"Wades Roofing",
    "wof:placetype":"venue"
},
  "geometry": {"coordinates":[-83.448279,43.000041],"type":"Point"}
}