{
  "type": "Feature",
  "properties": {
    "iso:country":"US",
    "sg:address":"3413 10th St",
    "sg:city":"Menominee",
    "sg:classifiers":[
        {
            "category":"Retail",
            "subcategory":"Car Wash",
            "type":"Services"
        }
    ],
    "sg:phone":"+1 906 863 4656",
    "sg:postcode":"49858",
    "sg:province":"MI",
    "sg:tags":[
        "carwash"
    ],
    "wof:name":"Magic Wand Laser Wash",
    "wof:placetype":"venue"
},
  "geometry": {"coordinates":[-87.612842,45.129894],"type":"Point"}
}