{
  "type": "Feature",
  "properties": {
    "iso:country":"US",
    "sg:address":"2325 Indian Lakes Rd NE",
    "sg:city":"Cedar Springs",
    "sg:classifiers":[
        {
            "category":"Retail",
            "subcategory":"Auto Repair",
            "type":"Services"
        }
    ],
    "sg:phone":"+1 616 696 0467",
    "sg:postcode":"49319",
    "sg:province":"MI",
    "sg:tags":[
        "body",
        "automobile",
        "painting"
    ],
    "wof:name":"Ed's Auto Body Inc",
    "wof:placetype":"venue"
},
  "geometry": {"coordinates":[-85.614321,43.197313],"type":"Point"}
}