{
  "type": "Feature",
  "properties": {
    "iso:country":"US",
    "sg:address":"10994 N Straits Hwy",
    "sg:city":"Cheboygan",
    "sg:classifiers":[
        {
            "category":"Home & Garden",
            "subcategory":"Building Materials",
            "type":"Retail Goods"
        }
    ],
    "sg:phone":"+1 231 627 4426",
    "sg:postcode":"49721",
    "sg:province":"MI",
    "sg:tags":[
        "glass",
        "window",
        "plate"
    ],
    "wof:name":"Straits Area Glass Co",
    "wof:placetype":"venue"
},
  "geometry": {"coordinates":[-84.47862499999999,45.620759],"type":"Point"}
}