{
  "type": "Feature",
  "properties": {
    "iso:country":"US",
    "sg:address":"1270 E Columbia Ave",
    "sg:city":"Battle Creek",
    "sg:classifiers":[
        {
            "category":"Wholesale",
            "subcategory":"Machinery & Supplies",
            "type":"Manufacturing & Wholesale Goods"
        }
    ],
    "sg:phone":"+1 269 565 0425",
    "sg:postcode":"49014",
    "sg:province":"MI",
    "sg:tags":[
        "industrial",
        "consulting",
        "management"
    ],
    "wof:name":"Motion Industries Inc",
    "wof:placetype":"venue"
},
  "geometry": {"coordinates":[-85.164783,42.301273],"type":"Point"}
}