{
  "type": "Feature",
  "properties": {
    "iso:country":"US",
    "sg:address":"25300 Groesbeck Hwy",
    "sg:city":"Warren",
    "sg:classifiers":[
        {
            "category":"Manufacturing",
            "subcategory":"Tools & Machinery",
            "type":"Manufacturing & Wholesale Goods"
        }
    ],
    "sg:phone":"+1 586 777 0410",
    "sg:postcode":"48089",
    "sg:province":"MI",
    "sg:tags":[
        "cutting"
    ],
    "wof:name":"Acar Broach & Machine",
    "wof:placetype":"venue"
},
  "geometry": {"coordinates":[-82.97811900000001,42.481416],"type":"Point"}
}