{
  "type": "Feature",
  "properties": {
    "iso:country":"US",
    "sg:address":"5837 Colf Rd",
    "sg:city":"Carleton",
    "sg:classifiers":[
        {
            "category":"Professional",
            "subcategory":"Business Services",
            "type":"Services"
        }
    ],
    "sg:phone":"+1 734 587 2328",
    "sg:postcode":"48117",
    "sg:province":"MI",
    "sg:tags":[
        "recording",
        "studio"
    ],
    "wof:name":"Tear Drop Record Co",
    "wof:placetype":"venue"
},
  "geometry": {"coordinates":[-83.47430199999999,42.07245],"type":"Point"}
}