{
  "type": "Feature",
  "properties": {
    "iso:country":"US",
    "sg:address":"43021 Heron Ct",
    "sg:city":"Sterling Heights",
    "sg:classifiers":[
        {
            "category":"Professional",
            "subcategory":"Business Services",
            "type":"Services"
        }
    ],
    "sg:phone":"+1 586 247 8319",
    "sg:postcode":"48313",
    "sg:province":"MI",
    "wof:name":"Epoxy Systems Solutions",
    "wof:placetype":"venue"
},
  "geometry": {"coordinates":[-82.98627,42.611199],"type":"Point"}
}