{
  "type": "Feature",
  "properties": {
    "iso:country":"US",
    "sg:address":"525 Water St",
    "sg:city":"Port Huron",
    "sg:classifiers":[
        {
            "category":"Government",
            "subcategory":"Office",
            "type":"Public Place"
        }
    ],
    "sg:phone":"+1 810 985 7404",
    "sg:postcode":"48060",
    "sg:province":"MI",
    "sg:tags":[
        "county"
    ],
    "wof:name":"New Horizons Of Oakland County",
    "wof:placetype":"venue"
},
  "geometry": {"coordinates":[-82.425192,42.975257],"type":"Point"}
}