{
  "type": "Feature",
  "properties": {
    "iso:country":"US",
    "sg:address":"352 W Columbia St",
    "sg:city":"Mason",
    "sg:classifiers":[
        {
            "category":"Shopping",
            "subcategory":"Gifts & Souvenirs",
            "type":"Retail Goods"
        }
    ],
    "sg:phone":"+1 517 676 4044",
    "sg:postcode":"48854",
    "sg:province":"MI",
    "sg:tags":[
        "shop"
    ],
    "wof:name":"Poppy Creek Station",
    "wof:placetype":"venue"
},
  "geometry": {"coordinates":[-84.44739800000001,42.582278],"type":"Point"}
}