{
  "type": "Feature",
  "properties": {
    "iso:country":"US",
    "sg:address":"22751 Dequindre Rd",
    "sg:city":"Hazel Park",
    "sg:classifiers":[
        {
            "category":"Professional",
            "subcategory":"Computer Services",
            "type":"Services"
        }
    ],
    "sg:phone":"+1 586 484 9266",
    "sg:postcode":"48030",
    "sg:province":"MI",
    "sg:tags":[
        "management",
        "chain",
        "assist",
        "supply"
    ],
    "wof:name":"Acsm Inc",
    "wof:placetype":"venue"
},
  "geometry": {"coordinates":[-83.08395899999999,42.459812],"type":"Point"}
}