{
  "type": "Feature",
  "properties": {
    "iso:country":"US",
    "sg:address":"36222 Glenwood Rd",
    "sg:city":"Westland",
    "sg:classifiers":[
        {
            "category":"Building & Trades",
            "subcategory":"Landscaping Services",
            "type":"Services"
        }
    ],
    "sg:phone":"+1 734 728 1346",
    "sg:postcode":"48186",
    "sg:province":"MI",
    "sg:tags":[
        "tree",
        "landscape",
        "contractor"
    ],
    "sg:website":"http://www.agrolawn.com/agroscapes/treeshrub.htm",
    "wof:name":"Dearborn Tree Service",
    "wof:placetype":"venue"
},
  "geometry": {"coordinates":[-83.396181,42.288119],"type":"Point"}
}