{
  "type": "Feature",
  "properties": {
    "iso:country":"US",
    "sg:address":"30160 Southfield Rd",
    "sg:city":"Southfield",
    "sg:classifiers":[
        {
            "category":"Utilities",
            "subcategory":"Mobile Phone",
            "type":"Services"
        },
        {
            "category":"Coffee & Tea",
            "type":"Food & Drink"
        }
    ],
    "sg:phone":"+1 248 203 2025",
    "sg:postcode":"48076",
    "sg:province":"MI",
    "sg:tags":[
        "shop",
        "wi-fi",
        "espresso",
        "hotspot",
        "restaurant"
    ],
    "sg:website":"http://www.starbuckscoffee.com",
    "wof:name":"Starbucks Coffee",
    "wof:placetype":"venue"
},
  "geometry": {"coordinates":[-83.22302500000001,42.51112],"type":"Point"}
}