{
  "type": "Feature",
  "properties": {
    "iso:country":"US",
    "sg:address":"11764 S Enzian Rd",
    "sg:city":"Plainwell",
    "sg:classifiers":[
        {
            "category":"Building & Trades",
            "subcategory":"Construction",
            "type":"Services"
        }
    ],
    "sg:phone":"+1 269 664 6401",
    "sg:postcode":"49080",
    "sg:province":"MI",
    "sg:tags":[
        "house"
    ],
    "wof:name":"Brinkhuis Construction",
    "wof:placetype":"venue"
},
  "geometry": {"coordinates":[-85.493956,42.486334],"type":"Point"}
}