{
  "type": "Feature",
  "properties": {
    "iso:country":"US",
    "sg:address":"3593 Whitehall Rd",
    "sg:city":"Muskegon",
    "sg:classifiers":[
        {
            "category":"Organizations",
            "subcategory":"Religious Organization",
            "type":"Services"
        }
    ],
    "sg:phone":"+1 231 766 3539",
    "sg:postcode":"49445",
    "sg:province":"MI",
    "sg:tags":[
        "church"
    ],
    "wof:name":"Faith Baptist Church Muskegon",
    "wof:placetype":"venue"
},
  "geometry": {"coordinates":[-86.263245,43.322288],"type":"Point"}
}