{
  "type": "Feature",
  "properties": {
    "iso:country":"US",
    "sg:address":"10621 Twin Lakes Rd",
    "sg:city":"Cheboygan",
    "sg:classifiers":[
        {
            "category":"Restaurant",
            "type":"Food & Drink"
        }
    ],
    "sg:phone":"+1 231 625 9322",
    "sg:postcode":"49721",
    "sg:province":"MI",
    "wof:name":"Chateau Lodge",
    "wof:placetype":"venue"
},
  "geometry": {"coordinates":[-84.264977,45.53118],"type":"Point"}
}