{
  "type": "Feature",
  "properties": {
    "iso:country":"US",
    "sg:address":"305 2nd St",
    "sg:city":"Cassopolis",
    "sg:classifiers":[
        {
            "category":"Organizations",
            "subcategory":"Religious Organization",
            "type":"Services"
        }
    ],
    "sg:phone":"+1 269 445 3498",
    "sg:postcode":"49031",
    "sg:province":"MI",
    "wof:name":"Christ Temple Church",
    "wof:placetype":"venue"
},
  "geometry": {"coordinates":[-86.00357700000001,41.916871],"type":"Point"}
}