{
  "type": "Feature",
  "properties": {
    "iso:country":"US",
    "sg:address":"2171 Lodge Rd",
    "sg:city":"Flint",
    "sg:classifiers":[
        {
            "category":"Manufacturing",
            "subcategory":"Printing",
            "type":"Manufacturing & Wholesale Goods"
        }
    ],
    "sg:phone":"+1 810 736 6770",
    "sg:postcode":"48532",
    "sg:province":"MI",
    "sg:tags":[
        "printer"
    ],
    "wof:name":"Addressing & Printing Svc",
    "wof:placetype":"venue"
},
  "geometry": {"coordinates":[-83.750389,42.997706],"type":"Point"}
}