{
  "type": "Feature",
  "properties": {
    "iso:country":"US",
    "sg:address":"26734 Michigan Ave",
    "sg:city":"Inkster",
    "sg:classifiers":[
        {
            "category":"Professional",
            "type":"Services"
        }
    ],
    "sg:phone":"+1 313 359 0900",
    "sg:postcode":"48141",
    "sg:province":"MI",
    "sg:tags":[
        "caterer"
    ],
    "wof:name":"Gracie See Pastaria",
    "wof:placetype":"venue"
},
  "geometry": {"coordinates":[-83.30166699999999,42.295708],"type":"Point"}
}