{
  "type": "Feature",
  "properties": {
    "iso:country":"US",
    "sg:address":"1256 E McDevitt Ave",
    "sg:city":"Jackson",
    "sg:classifiers":[
        {
            "category":"Bars & Pubs",
            "type":"Food & Drink"
        }
    ],
    "sg:phone":"+1 517 782 3626",
    "sg:postcode":"49203",
    "sg:province":"MI",
    "wof:name":"Gypsey's",
    "wof:placetype":"venue"
},
  "geometry": {"coordinates":[-84.378613,42.196936],"type":"Point"}
}