{
  "type": "Feature",
  "properties": {
    "iso:country":"US",
    "sg:address":"1821 Horton Rd",
    "sg:city":"Jackson",
    "sg:classifiers":[
        {
            "category":"Food & Beverages",
            "subcategory":"Specialty",
            "type":"Retail Goods"
        }
    ],
    "sg:phone":"+1 517 788 8840",
    "sg:postcode":"49203",
    "sg:province":"MI",
    "sg:tags":[
        "gourmet",
        "shop"
    ],
    "wof:name":"Culinary Secrets",
    "wof:placetype":"venue"
},
  "geometry": {"coordinates":[-84.435698,42.202639],"type":"Point"}
}