{
  "type": "Feature",
  "properties": {
    "iso:country":"US",
    "sg:address":"256 Fairfax Ct",
    "sg:city":"Erie",
    "sg:classifiers":[
        {
            "category":"Social Services",
            "subcategory":"Child Care",
            "type":"Services"
        }
    ],
    "sg:phone":"+1 734 848 2260",
    "sg:postcode":"48133",
    "sg:province":"MI",
    "sg:tags":[
        "instruction",
        "preschool"
    ],
    "wof:name":"Home Away From Home",
    "wof:placetype":"venue"
},
  "geometry": {"coordinates":[-83.518384,41.735538],"type":"Point"}
}