{
  "type": "Feature",
  "properties": {
    "iso:country":"US",
    "sg:address":"1165 Harvard Rd",
    "sg:city":"Grosse Pointe",
    "sg:classifiers":[
        {
            "category":"Building & Trades",
            "subcategory":"Cleaning & Sanitation",
            "type":"Services"
        }
    ],
    "sg:phone":"+1 313 882 5169",
    "sg:postcode":"48230",
    "sg:province":"MI",
    "sg:tags":[
        "maintenance"
    ],
    "wof:name":"Safe Flue Chimney Service",
    "wof:placetype":"venue"
},
  "geometry": {"coordinates":[-82.919177,42.387409],"type":"Point"}
}