{
  "type": "Feature",
  "properties": {
    "iso:country":"US",
    "sg:address":"12352 Antrim Dr",
    "sg:city":"Ellsworth",
    "sg:classifiers":[
        {
            "category":"Sports & Exercise",
            "subcategory":"Golf",
            "type":"Entertainment"
        }
    ],
    "sg:phone":"+1 231 599 2679",
    "sg:postcode":"49729",
    "sg:province":"MI",
    "sg:tags":[
        "course",
        "public"
    ],
    "wof:name":"Antrim Dell Golf & Tennis Club",
    "wof:placetype":"venue"
},
  "geometry": {"coordinates":[-85.357044,45.164919],"type":"Point"}
}