{
  "type": "Feature",
  "properties": {
    "iso:country":"US",
    "sg:address":"296 South Blvd W",
    "sg:city":"Pontiac",
    "sg:classifiers":[
        {
            "category":"Organizations",
            "subcategory":"Religious Organization",
            "type":"Services"
        }
    ],
    "sg:phone":"+1 248 338 9369",
    "sg:postcode":"48341",
    "sg:province":"MI",
    "sg:tags":[
        "church"
    ],
    "wof:name":"Church Of God",
    "wof:placetype":"venue"
},
  "geometry": {"coordinates":[-83.291132,42.619321],"type":"Point"}
}