{
  "type": "Feature",
  "properties": {
    "iso:country":"US",
    "sg:address":"31690 Madison Ave",
    "sg:city":"Madison Heights",
    "sg:classifiers":[
        {
            "category":"Manufacturing",
            "subcategory":"Metals",
            "type":"Manufacturing & Wholesale Goods"
        }
    ],
    "sg:phone":"+1 248 589 3701",
    "sg:postcode":"48071",
    "sg:province":"MI",
    "sg:tags":[
        "machine",
        "screw",
        "product"
    ],
    "wof:name":"Lane Sales",
    "wof:placetype":"venue"
},
  "geometry": {"coordinates":[-83.124729,42.525757],"type":"Point"}
}