{
  "type": "Feature",
  "properties": {
    "iso:country":"US",
    "sg:address":"7662 Claus Rd",
    "sg:city":"Hawks",
    "sg:classifiers":[
        {
            "category":"Restaurant",
            "type":"Food & Drink"
        }
    ],
    "sg:phone":"+1 989 734 8256",
    "sg:postcode":"49743",
    "sg:province":"MI",
    "sg:tags":[
        "banquet",
        "rooms"
    ],
    "wof:name":"Bismark Township Hall",
    "wof:placetype":"venue"
},
  "geometry": {"coordinates":[-83.886021,45.307701],"type":"Point"}
}