{
  "type": "Feature",
  "properties": {
    "iso:country":"US",
    "sg:address":"3495 40th St",
    "sg:city":"Newaygo",
    "sg:classifiers":[
        {
            "category":"Social Services",
            "subcategory":"Child Care",
            "type":"Services"
        }
    ],
    "sg:phone":"+1 231 652 9477",
    "sg:postcode":"49337",
    "sg:province":"MI",
    "sg:tags":[
        "day"
    ],
    "wof:name":"Aunt Loiss Daycare",
    "wof:placetype":"venue"
},
  "geometry": {"coordinates":[-85.72283899999999,43.482323],"type":"Point"}
}