{
  "type": "Feature",
  "properties": {
    "iso:country":"US",
    "sg:address":"1820 N Telegraph Rd",
    "sg:city":"Dearborn",
    "sg:classifiers":[
        {
            "category":"Education",
            "subcategory":"Dance Studio",
            "type":"Public Place"
        }
    ],
    "sg:phone":"+1 313 563 8707",
    "sg:postcode":"48128",
    "sg:province":"MI",
    "sg:tags":[
        "instruction",
        "dancing"
    ],
    "wof:name":"Dancers' Studio",
    "wof:placetype":"venue"
},
  "geometry": {"coordinates":[-83.27222399999999,42.324511],"type":"Point"}
}