{
  "type": "Feature",
  "properties": {
    "iso:country":"US",
    "sg:address":"3921 W M 42",
    "sg:city":"Mesick",
    "sg:classifiers":[
        {
            "category":"Social Services",
            "subcategory":"Adult Care",
            "type":"Services"
        }
    ],
    "sg:phone":"+1 231 885 1127",
    "sg:postcode":"49668",
    "sg:province":"MI",
    "sg:tags":[
        "foster"
    ],
    "wof:name":"Elaine Zinger Home",
    "wof:placetype":"venue"
},
  "geometry": {"coordinates":[-85.656825,44.409904],"type":"Point"}
}