{
  "type": "Feature",
  "properties": {
    "iso:country":"US",
    "sg:address":"8357 Churchill Rd",
    "sg:city":"Jackson",
    "sg:phone":"+1 517 569 3592",
    "sg:postcode":"49201",
    "sg:province":"MI",
    "sg:tags":[
        "wheat",
        "beef",
        "farm",
        "corn",
        "soybean",
        "cattle"
    ],
    "wof:name":"Ted Sluder",
    "wof:placetype":"venue"
},
  "geometry": {"coordinates":[-84.438226,42.351369],"type":"Point"}
}