{
  "type": "Feature",
  "properties": {
    "iso:country":"US",
    "sg:address":"9871 E Grand River Ave",
    "sg:city":"Brighton",
    "sg:classifiers":[
        {
            "category":"Sports & Exercise",
            "subcategory":"Bowling",
            "type":"Entertainment"
        }
    ],
    "sg:phone":"+1 810 227 3341",
    "sg:postcode":"48116",
    "sg:province":"MI",
    "sg:tags":[
        "center"
    ],
    "wof:name":"Brighton Bowl",
    "wof:placetype":"venue"
},
  "geometry": {"coordinates":[-83.761867,42.521624],"type":"Point"}
}