{
  "type": "Feature",
  "properties": {
    "iso:country":"US",
    "sg:address":"14307 Alpena Dr",
    "sg:city":"Sterling Heights",
    "sg:classifiers":[
        {
            "category":"Building & Trades",
            "subcategory":"Construction",
            "type":"Services"
        }
    ],
    "sg:phone":"+1 586 566 7457",
    "sg:postcode":"48313",
    "sg:province":"MI",
    "sg:tags":[
        "residential"
    ],
    "wof:name":"Kc Construction",
    "wof:placetype":"venue"
},
  "geometry": {"coordinates":[-82.982354,42.598452],"type":"Point"}
}