{
  "type": "Feature",
  "properties": {
    "iso:country":"US",
    "sg:address":"32100 Grand River Ave",
    "sg:city":"Farmington",
    "sg:classifiers":[
        {
            "category":"Professional",
            "subcategory":"Management & Consulting",
            "type":"Services"
        }
    ],
    "sg:phone":"+1 248 477 8197",
    "sg:postcode":"48336",
    "sg:province":"MI",
    "sg:tags":[
        "consultant",
        "educational",
        "business"
    ],
    "wof:name":"Jo El Educational Consulting",
    "wof:placetype":"venue"
},
  "geometry": {"coordinates":[-83.364492,42.459857],"type":"Point"}
}