{
  "type": "Feature",
  "properties": {
    "iso:country":"US",
    "sg:address":"25759 Pineview Ave",
    "sg:city":"Warren",
    "sg:classifiers":[
        {
            "category":"Building & Trades",
            "subcategory":"Construction",
            "type":"Services"
        }
    ],
    "sg:phone":"+1 586 759 5512",
    "sg:postcode":"48091",
    "sg:province":"MI",
    "sg:tags":[
        "carpentry",
        "contractor"
    ],
    "wof:name":"Chinoski Carpentry",
    "wof:placetype":"venue"
},
  "geometry": {"coordinates":[-83.050161,42.483424],"type":"Point"}
}