{
  "type": "Feature",
  "properties": {
    "iso:country":"US",
    "sg:address":"5052 Highland Rd",
    "sg:city":"Waterford",
    "sg:classifiers":[
        {
            "category":"Shopping",
            "type":"Retail Goods"
        }
    ],
    "sg:phone":"+1 248 673 3033",
    "sg:postcode":"48327",
    "sg:province":"MI",
    "sg:tags":[
        "picture",
        "frame"
    ],
    "wof:name":"Jo-John Gallery",
    "wof:placetype":"venue"
},
  "geometry": {"coordinates":[-83.389195,42.660402],"type":"Point"}
}