{
  "type": "Feature",
  "properties": {
    "iso:country":"US",
    "sg:address":"7215 Sulier Dr",
    "sg:city":"Temperance",
    "sg:classifiers":[
        {
            "category":"Professional",
            "subcategory":"Business Services",
            "type":"Services"
        }
    ],
    "sg:phone":"+1 734 847 1250",
    "sg:postcode":"48182",
    "sg:province":"MI",
    "sg:tags":[
        "paper"
    ],
    "wof:name":"Metro Secure Shred",
    "wof:placetype":"venue"
},
  "geometry": {"coordinates":[-83.55275,41.748207],"type":"Point"}
}