{
  "type": "Feature",
  "properties": {
    "iso:country":"US",
    "sg:address":"12024 N Bray Rd",
    "sg:city":"Clio",
    "sg:classifiers":[
        {
            "category":"Building & Trades",
            "subcategory":"Construction",
            "type":"Services"
        }
    ],
    "sg:phone":"+1 810 686 6168",
    "sg:postcode":"48420",
    "sg:province":"MI",
    "sg:tags":[
        "demolition",
        "contractor"
    ],
    "wof:name":"Jerry's Manufactured Home",
    "wof:placetype":"venue"
},
  "geometry": {"coordinates":[-83.66022700000001,43.184371],"type":"Point"}
}