{
  "type": "Feature",
  "properties": {
    "iso:country":"US",
    "sg:address":"4802 Richmond St",
    "sg:city":"Lansing",
    "sg:classifiers":[
        {
            "category":"Social Services",
            "subcategory":"Child Care",
            "type":"Services"
        }
    ],
    "sg:phone":"+1 517 887 0809",
    "sg:postcode":"48911",
    "sg:province":"MI",
    "sg:tags":[
        "day"
    ],
    "wof:name":"Kime Christine",
    "wof:placetype":"venue"
},
  "geometry": {"coordinates":[-84.583787,42.684001],"type":"Point"}
}