{
  "type": "Feature",
  "properties": {
    "iso:country":"US",
    "sg:address":"309 S 3rd St",
    "sg:city":"Escanaba",
    "sg:classifiers":[
        {
            "category":"Organizations",
            "subcategory":"Non-profit Organization",
            "type":"Services"
        }
    ],
    "sg:phone":"+1 906 786 7623",
    "sg:postcode":"49829",
    "sg:province":"MI",
    "sg:tags":[
        "fund",
        "counselor",
        "raising"
    ],
    "wof:name":"Escanaba Wrestling Take Down",
    "wof:placetype":"venue"
},
  "geometry": {"coordinates":[-87.050206,45.743433],"type":"Point"}
}