{
  "type": "Feature",
  "properties": {
    "iso:country":"US",
    "sg:address":"24450 Evergreen Rd",
    "sg:city":"Southfield",
    "sg:classifiers":[
        {
            "category":"Insurance",
            "subcategory":"Hazard Insurance",
            "type":"Services"
        }
    ],
    "sg:phone":"+1 248 357 1151",
    "sg:postcode":"48075",
    "sg:province":"MI",
    "sg:tags":[
        "carrier"
    ],
    "wof:name":"Horace Mann Insurance Co",
    "wof:placetype":"venue"
},
  "geometry": {"coordinates":[-83.24042300000001,42.471109],"type":"Point"}
}