{
  "type": "Feature",
  "properties": {
    "iso:country":"US",
    "sg:address":"433 Seminole Rd",
    "sg:city":"Muskegon",
    "sg:classifiers":[
        {
            "category":"Health Services",
            "subcategory":"Health Practitioner",
            "type":"Services"
        }
    ],
    "sg:phone":"+1 231 726 6969",
    "sg:postcode":"49444",
    "sg:province":"MI",
    "sg:tags":[
        "psychologist"
    ],
    "wof:name":"Patricia J Dauser",
    "wof:placetype":"venue"
},
  "geometry": {"coordinates":[-86.25430299999999,43.187488],"type":"Point"}
}