{
  "type": "Feature",
  "properties": {
    "iso:country":"US",
    "sg:address":"710 W Conway Rd",
    "sg:city":"Harbor Springs",
    "sg:classifiers":[
        {
            "category":"Home & Garden",
            "subcategory":"Building Materials",
            "type":"Retail Goods"
        }
    ],
    "sg:phone":"+1 231 439 9200",
    "sg:postcode":"49740",
    "sg:province":"MI",
    "sg:tags":[
        "mixed",
        "concrete"
    ],
    "wof:name":"Cornillie Concrete",
    "wof:placetype":"venue"
},
  "geometry": {"coordinates":[-84.89943100000001,45.427883],"type":"Point"}
}