{
  "type": "Feature",
  "properties": {
    "iso:country":"US",
    "sg:address":"7536 E 7 Mile Rd",
    "sg:city":"Detroit",
    "sg:classifiers":[
        {
            "category":"Organizations",
            "subcategory":"Religious Organization",
            "type":"Services"
        }
    ],
    "sg:phone":"+1 313 892 1777",
    "sg:postcode":"48234",
    "sg:province":"MI",
    "wof:name":"Ephesus Mssonary Baptst Church",
    "wof:placetype":"venue"
},
  "geometry": {"coordinates":[-83.026332,42.43385],"type":"Point"}
}