{
  "type": "Feature",
  "properties": {
    "iso:country":"US",
    "sg:address":"1101 Industrial Blvd",
    "sg:city":"Albion",
    "sg:classifiers":[
        {
            "category":"Manufacturing",
            "subcategory":"Rubber & Plastics",
            "type":"Manufacturing & Wholesale Goods"
        }
    ],
    "sg:phone":"+1 517 629 2170",
    "sg:postcode":"49224",
    "sg:province":"MI",
    "sg:website":"www.maxslate.com",
    "wof:name":"Max Manufacturing",
    "wof:placetype":"venue"
},
  "geometry": {"coordinates":[-84.775941,42.256302],"type":"Point"}
}