{
  "type": "Feature",
  "properties": {
    "iso:country":"US",
    "sg:address":"3477 Military St",
    "sg:city":"Detroit",
    "sg:classifiers":[
        {
            "category":"Building & Trades",
            "subcategory":"Landscaping Services",
            "type":"Services"
        }
    ],
    "sg:phone":"+1 313 898 7512",
    "sg:postcode":"48210",
    "sg:province":"MI",
    "sg:tags":[
        "landscape"
    ],
    "wof:name":"San Jose Landscaping Inc",
    "wof:placetype":"venue"
},
  "geometry": {"coordinates":[-83.116175,42.327084],"type":"Point"}
}