{
  "type": "Feature",
  "properties": {
    "iso:country":"US",
    "sg:address":"301 Maplewood St",
    "sg:city":"Greenville",
    "sg:classifiers":[
        {
            "category":"Shopping",
            "subcategory":"Gifts & Souvenirs",
            "type":"Retail Goods"
        }
    ],
    "sg:phone":"+1 616 754 9955",
    "sg:postcode":"48838",
    "sg:province":"MI",
    "sg:tags":[
        "shop"
    ],
    "wof:name":"Cathy's Hallmark",
    "wof:placetype":"venue"
},
  "geometry": {"coordinates":[-85.275729,43.179804],"type":"Point"}
}