{
  "type": "Feature",
  "properties": {
    "iso:country":"US",
    "sg:address":"2535 N Grand River Ave",
    "sg:city":"Lansing",
    "sg:classifiers":[
        {
            "category":"Autos & Motor Vehicles",
            "subcategory":"Automobile Sales",
            "type":"Retail Goods"
        }
    ],
    "sg:phone":"+1 517 327 1949",
    "sg:postcode":"48906",
    "sg:province":"MI",
    "sg:tags":[
        "car",
        "dealer"
    ],
    "wof:name":"D & J Auto Sales",
    "wof:placetype":"venue"
},
  "geometry": {"coordinates":[-84.56679699999999,42.759645],"type":"Point"}
}