{
  "type": "Feature",
  "properties": {
    "iso:country":"US",
    "sg:address":"5408 E Cutler Rd",
    "sg:city":"Bath",
    "sg:classifiers":[
        {
            "category":"Social Services",
            "subcategory":"Child Care",
            "type":"Services"
        }
    ],
    "sg:phone":"+1 517 641 6883",
    "sg:postcode":"48808",
    "sg:province":"MI",
    "sg:tags":[
        "day"
    ],
    "wof:name":"Dianes Daycare",
    "wof:placetype":"venue"
},
  "geometry": {"coordinates":[-84.455448,42.852948],"type":"Point"}
}