{
  "type": "Feature",
  "properties": {
    "iso:country":"US",
    "sg:address":"13115 Florentine Dr",
    "sg:city":"Utica",
    "sg:classifiers":[
        {
            "category":"Building & Trades",
            "subcategory":"Construction",
            "type":"Services"
        }
    ],
    "sg:phone":"+1 586 731 7369",
    "sg:postcode":"48315",
    "sg:province":"MI",
    "sg:tags":[
        "hanging",
        "contractor"
    ],
    "wof:name":"Extreme Painting",
    "wof:placetype":"venue"
},
  "geometry": {"coordinates":[-82.99773500000001,42.653121],"type":"Point"}
}