{
  "type": "Feature",
  "properties": {
    "iso:country":"US",
    "sg:address":"7506 S Westnedge Ave",
    "sg:city":"Portage",
    "sg:classifiers":[
        {
            "category":"Shopping",
            "subcategory":"Clothing, Apparel, & Fashions",
            "type":"Retail Goods"
        }
    ],
    "sg:phone":"+1 269 327 3598",
    "sg:postcode":"49002",
    "sg:province":"MI",
    "wof:name":"Max 10",
    "wof:placetype":"venue"
},
  "geometry": {"coordinates":[-85.589455,42.206403],"type":"Point"}
}