{
  "type": "Feature",
  "properties": {
    "iso:country":"US",
    "sg:address":"447 E Front St",
    "sg:city":"Traverse City",
    "sg:classifiers":[
        {
            "category":"Professional",
            "subcategory":"Lawyer & Legal Services",
            "type":"Services"
        }
    ],
    "sg:phone":"+1 231 947 2540",
    "sg:postcode":"49686",
    "sg:province":"MI",
    "sg:tags":[
        "attorney"
    ],
    "wof:name":"Graff & Hunt",
    "wof:placetype":"venue"
},
  "geometry": {"coordinates":[-85.61506,44.764143],"type":"Point"}
}