{
  "type": "Feature",
  "properties": {
    "iso:country":"US",
    "sg:address":"940 Venture Ln",
    "sg:city":"Williamston",
    "sg:classifiers":[
        {
            "category":"Government",
            "subcategory":"Office",
            "type":"Public Place"
        }
    ],
    "sg:phone":"+1 517 655 8202",
    "sg:postcode":"48895",
    "sg:province":"MI",
    "sg:tags":[
        "state",
        "program",
        "lab"
    ],
    "wof:name":"Agriculture Michigan Dept",
    "wof:placetype":"venue"
},
  "geometry": {"coordinates":[-84.277176,42.674067],"type":"Point"}
}