{
  "type": "Feature",
  "properties": {
    "iso:country":"US",
    "sg:address":"6580 Peckins Rd",
    "sg:city":"Manchester",
    "sg:classifiers":[
        {
            "category":"Professional",
            "subcategory":"Computer Services",
            "type":"Services"
        }
    ],
    "sg:phone":"+1 734 433 0315",
    "sg:postcode":"48158",
    "sg:province":"MI",
    "sg:tags":[
        "prepackaged",
        "software"
    ],
    "wof:name":"Modular Software Systems",
    "wof:placetype":"venue"
},
  "geometry": {"coordinates":[-84.01975899999999,42.225572],"type":"Point"}
}