{
  "type": "Feature",
  "properties": {
    "iso:country":"US",
    "sg:address":"6363 Burton Rd",
    "sg:city":"Adrian",
    "sg:classifiers":[
        {
            "category":"Sports & Exercise",
            "subcategory":"Golf",
            "type":"Entertainment"
        }
    ],
    "sg:phone":"+1 517 265 3944",
    "sg:postcode":"49221",
    "sg:province":"MI",
    "sg:tags":[
        "course",
        "public"
    ],
    "wof:name":"Wolf Creek Golf Club Inc",
    "wof:placetype":"venue"
},
  "geometry": {"coordinates":[-84.10900100000001,41.927483],"type":"Point"}
}