{
  "type": "Feature",
  "properties": {
    "iso:country":"US",
    "sg:address":"25272 Farmington Rd",
    "sg:city":"Farmington",
    "sg:classifiers":[
        {
            "category":"Building & Trades",
            "subcategory":"Construction",
            "type":"Services"
        }
    ],
    "sg:phone":"+1 248 476 7402",
    "sg:postcode":"48336",
    "sg:province":"MI",
    "sg:tags":[
        "house"
    ],
    "wof:name":"Seflic Builders",
    "wof:placetype":"venue"
},
  "geometry": {"coordinates":[-83.377116,42.4786],"type":"Point"}
}