{
  "type": "Feature",
  "properties": {
    "iso:country":"US",
    "sg:address":"526 Division St",
    "sg:city":"Stephenson",
    "sg:classifiers":[
        {
            "category":"Education",
            "subcategory":"School",
            "type":"Public Place"
        }
    ],
    "sg:phone":"+1 906 753 2222",
    "sg:postcode":"49887",
    "sg:province":"MI",
    "wof:name":"Stephenson High School",
    "wof:placetype":"venue"
},
  "geometry": {"coordinates":[-87.611378,45.41725],"type":"Point"}
}