{
  "type": "Feature",
  "properties": {
    "iso:country":"US",
    "sg:address":"39724 Wolo Ct",
    "sg:city":"Clinton Twp",
    "sg:classifiers":[
        {
            "category":"Building & Trades",
            "subcategory":"Electrical",
            "type":"Services"
        }
    ],
    "sg:phone":"+1 586 412 5932",
    "sg:postcode":"48038",
    "sg:province":"MI",
    "sg:tags":[
        "electric",
        "contractor"
    ],
    "wof:name":"General Electric",
    "wof:placetype":"venue"
},
  "geometry": {"coordinates":[-82.92656599999999,42.590169],"type":"Point"}
}