{
  "type": "Feature",
  "properties": {
    "iso:country":"US",
    "sg:address":"1719 Crooks Rd",
    "sg:city":"Royal Oak",
    "sg:classifiers":[
        {
            "category":"Insurance",
            "subcategory":"Insurance Agent",
            "type":"Services"
        }
    ],
    "sg:phone":"+1 248 541 7624",
    "sg:postcode":"48067",
    "sg:province":"MI",
    "wof:name":"Andrezejak Insurance",
    "wof:placetype":"venue"
},
  "geometry": {"coordinates":[-83.15075299999999,42.503828],"type":"Point"}
}