{
  "type": "Feature",
  "properties": {
    "iso:country":"US",
    "sg:address":"3331 E Dodge Rd",
    "sg:city":"Clio",
    "sg:classifiers":[
        {
            "category":"Organizations",
            "subcategory":"Professional Association",
            "type":"Services"
        }
    ],
    "sg:phone":"+1 810 686 1168",
    "sg:postcode":"48420",
    "sg:province":"MI",
    "wof:name":"American Guild of Organists",
    "wof:placetype":"venue"
},
  "geometry": {"coordinates":[-83.65141,43.149819],"type":"Point"}
}