{
  "type": "Feature",
  "properties": {
    "iso:country":"US",
    "sg:address":"5123 Highland Rd",
    "sg:city":"Waterford",
    "sg:classifiers":[
        {
            "category":"Food & Beverages",
            "subcategory":"Specialty",
            "type":"Retail Goods"
        }
    ],
    "sg:phone":"+1 248 673 5440",
    "sg:postcode":"48327",
    "sg:province":"MI",
    "sg:tags":[
        "health",
        "diet"
    ],
    "wof:name":"GNC",
    "wof:placetype":"venue"
},
  "geometry": {"coordinates":[-83.387843,42.660202],"type":"Point"}
}