{
  "type": "Feature",
  "properties": {
    "iso:country":"US",
    "sg:address":"8020 W Mcnichols Rd",
    "sg:city":"Detroit",
    "sg:classifiers":[
        {
            "category":"Professional",
            "type":"Services"
        },
        {
            "category":"Restaurant",
            "type":"Food & Drink"
        }
    ],
    "sg:phone":"+1 313 861 0710",
    "sg:postcode":"48221",
    "sg:province":"MI",
    "sg:tags":[
        "caterer"
    ],
    "wof:name":"Grandfather's Place",
    "wof:placetype":"venue"
},
  "geometry": {"coordinates":[-83.150282,42.41712],"type":"Point"}
}