{
  "type": "Feature",
  "properties": {
    "iso:country":"US",
    "sg:address":"2729 W Clark Rd",
    "sg:city":"Lansing",
    "sg:classifiers":[
        {
            "category":"Professional",
            "subcategory":"Management & Consulting",
            "type":"Services"
        }
    ],
    "sg:phone":"+1 517 669 5231",
    "sg:postcode":"48906",
    "sg:province":"MI",
    "sg:tags":[
        "consultant",
        "business"
    ],
    "wof:name":"Jca",
    "wof:placetype":"venue"
},
  "geometry": {"coordinates":[-84.578588,42.813177],"type":"Point"}
}