{
  "type": "Feature",
  "properties": {
    "iso:country":"US",
    "sg:address":"401 Main St",
    "sg:city":"East Tawas",
    "sg:classifiers":[
        {
            "category":"Organizations",
            "subcategory":"Religious Organization",
            "type":"Services"
        }
    ],
    "sg:phone":"+1 989 362 5371",
    "sg:postcode":"48730",
    "sg:province":"MI",
    "wof:name":"Grace Lutheran Church",
    "wof:placetype":"venue"
},
  "geometry": {"coordinates":[-83.49054599999999,44.284475],"type":"Point"}
}