{
  "type": "Feature",
  "properties": {
    "iso:country":"US",
    "sg:address":"624 S Cedar St",
    "sg:city":"Mason",
    "sg:classifiers":[
        {
            "category":"Building & Trades",
            "subcategory":"Landscaping Services",
            "type":"Services"
        }
    ],
    "sg:phone":"+1 517 676 5522",
    "sg:postcode":"48854",
    "sg:province":"MI",
    "sg:tags":[
        "landscape",
        "contractor"
    ],
    "wof:name":"Anderson-Fischer & Assoc Inc",
    "wof:placetype":"venue"
},
  "geometry": {"coordinates":[-84.452915,42.575127],"type":"Point"}
}