{
  "type": "Feature",
  "properties": {
    "iso:country":"US",
    "sg:address":"7220 N Begole Rd",
    "sg:city":"Alma",
    "sg:classifiers":[
        {
            "category":"Building & Trades",
            "subcategory":"Plumbing",
            "type":"Services"
        }
    ],
    "sg:phone":"+1 989 463 8767",
    "sg:postcode":"48801",
    "sg:province":"MI",
    "sg:tags":[
        "conditioning",
        "air",
        "system",
        "contractor"
    ],
    "wof:name":"Moline Heating & Cooling",
    "wof:placetype":"venue"
},
  "geometry": {"coordinates":[-84.646734,43.396492],"type":"Point"}
}