{
  "type": "Feature",
  "properties": {
    "iso:country":"US",
    "sg:address":"1108 3rd St",
    "sg:city":"Three Rivers",
    "sg:classifiers":[
        {
            "category":"Personal",
            "type":"Services"
        }
    ],
    "sg:phone":"+1 269 278 8234",
    "sg:postcode":"49093",
    "sg:province":"MI",
    "wof:name":"Golden Touch",
    "wof:placetype":"venue"
},
  "geometry": {"coordinates":[-85.63093000000001,41.932066],"type":"Point"}
}