{
  "type": "Feature",
  "properties": {
    "iso:country":"US",
    "sg:address":"28850 Utica Rd",
    "sg:city":"Roseville",
    "sg:classifiers":[
        {
            "category":"Home & Garden",
            "subcategory":"Building Materials",
            "type":"Retail Goods"
        }
    ],
    "sg:phone":"+1 586 777 9599",
    "sg:postcode":"48066",
    "sg:province":"MI",
    "sg:tags":[
        "glass",
        "window",
        "plate"
    ],
    "wof:name":"True View Auto Glass",
    "wof:placetype":"venue"
},
  "geometry": {"coordinates":[-82.935475,42.508595],"type":"Point"}
}