{
  "type": "Feature",
  "properties": {
    "iso:country":"US",
    "sg:address":"24825 Winona St",
    "sg:city":"Dearborn",
    "sg:classifiers":[
        {
            "category":"Education",
            "subcategory":"Special Training",
            "type":"Public Place"
        }
    ],
    "sg:phone":"+1 313 562 8169",
    "sg:postcode":"48124",
    "sg:province":"MI",
    "sg:tags":[
        "school",
        "language"
    ],
    "wof:name":"Friendly Faces Llc",
    "wof:placetype":"venue"
},
  "geometry": {"coordinates":[-83.279297,42.3055],"type":"Point"}
}