{
  "type": "Feature",
  "properties": {
    "iso:country":"US",
    "sg:address":"847 Harrington St",
    "sg:city":"Mount Clemens",
    "sg:classifiers":[
        {
            "category":"Building & Trades",
            "subcategory":"Construction",
            "type":"Services"
        }
    ],
    "sg:phone":"+1 586 463 2877",
    "sg:postcode":"48043",
    "sg:province":"MI",
    "sg:tags":[
        "carpentry",
        "contractor"
    ],
    "wof:name":"Corona Carpentry",
    "wof:placetype":"venue"
},
  "geometry": {"coordinates":[-82.89377399999999,42.586043],"type":"Point"}
}