{
  "type": "Feature",
  "properties": {
    "iso:country":"US",
    "sg:address":"14393 Pine Creek Ct",
    "sg:city":"Holland",
    "sg:classifiers":[
        {
            "category":"Professional",
            "subcategory":"Computer Services",
            "type":"Services"
        }
    ],
    "sg:phone":"+1 616 738 0731",
    "sg:postcode":"49424",
    "sg:province":"MI",
    "sg:tags":[
        "repair",
        "sales"
    ],
    "wof:name":"Westside Computers",
    "wof:placetype":"venue"
},
  "geometry": {"coordinates":[-86.13777899999999,42.829648],"type":"Point"}
}