{
  "type": "Feature",
  "properties": {
    "iso:country":"US",
    "sg:address":"1436 Berwyck Dr",
    "sg:city":"Milford",
    "sg:classifiers":[
        {
            "category":"Professional",
            "subcategory":"Engineering",
            "type":"Services"
        }
    ],
    "sg:phone":"+1 248 685 2381",
    "sg:postcode":"48381",
    "sg:province":"MI",
    "wof:name":"Priority Design",
    "wof:placetype":"venue"
},
  "geometry": {"coordinates":[-83.61616100000001,42.570126],"type":"Point"}
}