{
  "type": "Feature",
  "properties": {
    "iso:country":"US",
    "sg:address":"3167 Baldwin Ave",
    "sg:city":"Fremont",
    "sg:classifiers":[
        {
            "category":"Real Estate",
            "subcategory":"Real Estate Operator",
            "type":"Services"
        }
    ],
    "sg:phone":"+1 231 924 0205",
    "sg:postcode":"49412",
    "sg:province":"MI",
    "sg:tags":[
        "mobile",
        "home",
        "site"
    ],
    "wof:name":"Rob-Ann Mobile Home Park",
    "wof:placetype":"venue"
},
  "geometry": {"coordinates":[-85.880731,43.496108],"type":"Point"}
}