{
  "type": "Feature",
  "properties": {
    "iso:country":"US",
    "sg:address":"407 E Woodworth St",
    "sg:city":"Bad Axe",
    "sg:classifiers":[
        {
            "category":"Education",
            "subcategory":"School",
            "type":"Public Place"
        }
    ],
    "sg:phone":"+1 989 269 7117",
    "sg:postcode":"48413",
    "sg:province":"MI",
    "wof:name":"Bad Axe Junior High School",
    "wof:placetype":"venue"
},
  "geometry": {"coordinates":[-82.995965,43.803415],"type":"Point"}
}