{
  "type": "Feature",
  "properties": {
    "iso:country":"US",
    "sg:address":"32917 Ryan Rd",
    "sg:city":"Warren",
    "sg:classifiers":[
        {
            "category":"Health Services",
            "subcategory":"Dentist",
            "type":"Services"
        }
    ],
    "sg:phone":"+1 586 698 2234",
    "sg:postcode":"48092",
    "sg:province":"MI",
    "wof:name":"Ashtar Dentistry",
    "wof:placetype":"venue"
},
  "geometry": {"coordinates":[-83.06867200000001,42.534758],"type":"Point"}
}