{
  "type": "Feature",
  "properties": {
    "iso:country":"US",
    "sg:address":"325 S Waverly Rd",
    "sg:city":"Lansing",
    "sg:classifiers":[
        {
            "category":"Building & Trades",
            "subcategory":"Construction",
            "type":"Services"
        }
    ],
    "sg:phone":"+1 517 327 9572",
    "sg:postcode":"48917",
    "sg:province":"MI",
    "sg:tags":[
        "bathroom",
        "remodeling"
    ],
    "wof:name":"Luxury Bath & Custom Closets",
    "wof:placetype":"venue"
},
  "geometry": {"coordinates":[-84.60301699999999,42.730139],"type":"Point"}
}