{
  "type": "Feature",
  "properties": {
    "iso:country":"US",
    "sg:address":"4970 Mackinaw Rd",
    "sg:city":"Saginaw",
    "sg:classifiers":[
        {
            "category":"Organizations",
            "subcategory":"Religious Organization",
            "type":"Services"
        }
    ],
    "sg:phone":"+1 989 793 8822",
    "sg:postcode":"48603",
    "sg:province":"MI",
    "wof:name":"St Demetrios Greek Orthodox",
    "wof:placetype":"venue"
},
  "geometry": {"coordinates":[-83.99512199999999,43.47615],"type":"Point"}
}