{
  "type": "Feature",
  "properties": {
    "iso:country":"US",
    "sg:address":"60281 Lamplighter Dr",
    "sg:city":"New Hudson",
    "sg:classifiers":[
        {
            "category":"Restaurant",
            "type":"Food & Drink"
        }
    ],
    "sg:phone":"+1 248 446 1597",
    "sg:postcode":"48165",
    "sg:province":"MI",
    "sg:tags":[
        "eating"
    ],
    "wof:name":"Johnny Os Catering Inc",
    "wof:placetype":"venue"
},
  "geometry": {"coordinates":[-83.64955500000001,42.510809],"type":"Point"}
}