{
  "type": "Feature",
  "properties": {
    "iso:country":"US",
    "sg:address":"713 W University Dr",
    "sg:city":"Rochester",
    "sg:classifiers":[
        {
            "category":"Home & Garden",
            "subcategory":"Household Appliances",
            "type":"Retail Goods"
        }
    ],
    "sg:phone":"+1 248 456 8661",
    "sg:postcode":"48307",
    "sg:province":"MI",
    "wof:name":"Appliance Discharge & Air",
    "wof:placetype":"venue"
},
  "geometry": {"coordinates":[-83.142078,42.681837],"type":"Point"}
}