{
  "type": "Feature",
  "properties": {
    "iso:country":"US",
    "sg:address":"100 Maple St",
    "sg:city":"Grayling",
    "sg:classifiers":[
        {
            "category":"Recreation",
            "type":"Entertainment"
        }
    ],
    "sg:phone":"+1 989 348 2910",
    "sg:postcode":"49738",
    "sg:province":"MI",
    "sg:tags":[
        "charter",
        "canoe"
    ],
    "wof:name":"Penrod's Au Sable Paddlesports",
    "wof:placetype":"venue"
},
  "geometry": {"coordinates":[-84.708173,44.661817],"type":"Point"}
}