{
  "type": "Feature",
  "properties": {
    "iso:country":"US",
    "sg:address":"2396 Hillside Dr NW",
    "sg:city":"Grand Rapids",
    "sg:classifiers":[
        {
            "category":"Education",
            "subcategory":"School",
            "type":"Public Place"
        }
    ],
    "sg:phone":"+1 616 363 3879",
    "sg:postcode":"49544",
    "sg:province":"MI",
    "wof:name":"Fairview Elementary School",
    "wof:placetype":"venue"
},
  "geometry": {"coordinates":[-85.68628099999999,43.00751],"type":"Point"}
}