{
  "type": "Feature",
  "properties": {
    "iso:country":"US",
    "sg:address":"6650 E Townline Lake Rd",
    "sg:city":"Harrison",
    "sg:classifiers":[
        {
            "category":"Professional",
            "subcategory":"Business Services",
            "type":"Services"
        }
    ],
    "sg:phone":"+1 989 539 1967",
    "sg:postcode":"48625",
    "sg:province":"MI",
    "sg:tags":[
        "auctioneer"
    ],
    "wof:name":"MLR Auctions",
    "wof:placetype":"venue"
},
  "geometry": {"coordinates":[-84.71566,44.031939],"type":"Point"}
}