{
  "type": "Feature",
  "properties": {
    "iso:country":"US",
    "sg:address":"2369 Marlene Dr",
    "sg:city":"Swartz Creek",
    "sg:classifiers":[
        {
            "category":"Building & Trades",
            "subcategory":"Construction",
            "type":"Services"
        }
    ],
    "sg:phone":"+1 810 630 1154",
    "sg:postcode":"48473",
    "sg:province":"MI",
    "sg:tags":[
        "hanging",
        "contractor"
    ],
    "wof:name":"Jeff Leet",
    "wof:placetype":"venue"
},
  "geometry": {"coordinates":[-83.787862,42.992836],"type":"Point"}
}