{
  "type": "Feature",
  "properties": {
    "iso:country":"US",
    "sg:address":"402 W 14 Mile Rd",
    "sg:city":"Troy",
    "sg:classifiers":[
        {
            "category":"Restaurant",
            "type":"Food & Drink"
        }
    ],
    "sg:menulink":"http://www.allmenus.com/mi/troy/43562-chilis/menu/",
    "sg:phone":"+1 248 589 2119",
    "sg:postcode":"48083",
    "sg:province":"MI",
    "sg:tags":[
        "burger",
        "american",
        "sandwich",
        "tex-mex",
        "soup"
    ],
    "wof:name":"Chili's",
    "wof:placetype":"venue"
},
  "geometry": {"coordinates":[-83.110192,42.534393],"type":"Point"}
}