{
  "type": "Feature",
  "properties": {
    "iso:country":"US",
    "sg:address":"627 W Division St",
    "sg:city":"Boyne City",
    "sg:classifiers":[
        {
            "category":"Retail",
            "subcategory":"Repair Shop",
            "type":"Services"
        }
    ],
    "sg:phone":"+1 231 582 6870",
    "sg:postcode":"49712",
    "sg:province":"MI",
    "sg:tags":[
        "house",
        "construction"
    ],
    "wof:name":"M & J Enterprise",
    "wof:placetype":"venue"
},
  "geometry": {"coordinates":[-85.024106,45.204861],"type":"Point"}
}