{
  "type": "Feature",
  "properties": {
    "iso:country":"US",
    "sg:address":"34115 W 12 Mile Rd",
    "sg:city":"Farmington",
    "sg:classifiers":[
        {
            "category":"Professional",
            "subcategory":"Management & Consulting",
            "type":"Services"
        }
    ],
    "sg:phone":"+1 248 553 8355",
    "sg:postcode":"48331",
    "sg:province":"MI",
    "sg:tags":[
        "marketing"
    ],
    "wof:name":"Phoenix Group",
    "wof:placetype":"venue"
},
  "geometry": {"coordinates":[-83.38558500000001,42.498339],"type":"Point"}
}