{
  "type": "Feature",
  "properties": {
    "iso:country":"US",
    "sg:address":"200 W Wall St",
    "sg:city":"Benton Harbor",
    "sg:classifiers":[
        {
            "category":"Manufacturing",
            "subcategory":"Metals",
            "type":"Manufacturing & Wholesale Goods"
        }
    ],
    "sg:phone":"+1 269 926 6366",
    "sg:postcode":"49022",
    "sg:province":"MI",
    "sg:tags":[
        "foundry"
    ],
    "wof:name":"G-M Brass & Aluminum Foundry",
    "wof:placetype":"venue"
},
  "geometry": {"coordinates":[-86.458692,42.114159],"type":"Point"}
}