{
  "type": "Feature",
  "properties": {
    "iso:country":"US",
    "sg:address":"109 N Riverview Dr",
    "sg:city":"Parchment",
    "sg:classifiers":[
        {
            "category":"Retail",
            "subcategory":"Repair Shop",
            "type":"Services"
        }
    ],
    "sg:phone":"+1 269 381 3674",
    "sg:postcode":"49004",
    "sg:province":"MI",
    "sg:tags":[
        "upholsterer"
    ],
    "wof:name":"Vanderberg Co",
    "wof:placetype":"venue"
},
  "geometry": {"coordinates":[-85.569586,42.328356],"type":"Point"}
}