{
  "type": "Feature",
  "properties": {
    "iso:country":"US",
    "sg:address":"1977 Burning Woods Ct SE",
    "sg:city":"Grand Rapids",
    "sg:classifiers":[
        {
            "category":"Professional",
            "subcategory":"Management & Consulting",
            "type":"Services"
        }
    ],
    "sg:phone":"+1 616 940 2961",
    "sg:postcode":"49546",
    "sg:province":"MI",
    "sg:tags":[
        "consultant",
        "educational"
    ],
    "wof:name":"Integrasource",
    "wof:placetype":"venue"
},
  "geometry": {"coordinates":[-85.563332,42.927779],"type":"Point"}
}