{
  "type": "Feature",
  "properties": {
    "iso:country":"US",
    "sg:address":"30135 Woodgate Dr",
    "sg:city":"Southfield",
    "sg:classifiers":[
        {
            "category":"Professional",
            "subcategory":"Business Services",
            "type":"Services"
        }
    ],
    "sg:phone":"+1 248 642 2437",
    "sg:postcode":"48076",
    "sg:province":"MI",
    "wof:name":"Mary Elizabeth Shea Interiors",
    "wof:placetype":"venue"
},
  "geometry": {"coordinates":[-83.23956099999999,42.510602],"type":"Point"}
}