{
  "type": "Feature",
  "properties": {
    "iso:country":"US",
    "sg:address":"45209 Helm St",
    "sg:city":"Plymouth",
    "sg:classifiers":[
        {
            "category":"Professional",
            "subcategory":"Computer Services",
            "type":"Services"
        }
    ],
    "sg:phone":"+1 734 455 1311",
    "sg:postcode":"48170",
    "sg:province":"MI",
    "sg:tags":[
        "integrated",
        "software",
        "design",
        "d",
        "system"
    ],
    "wof:name":"Freese Enterprises Inc",
    "wof:placetype":"venue"
},
  "geometry": {"coordinates":[-83.490151,42.391607],"type":"Point"}
}