{
  "type": "Feature",
  "properties": {
    "iso:country":"US",
    "sg:address":"109 E Randolph St",
    "sg:city":"Lansing",
    "sg:classifiers":[
        {
            "category":"Organizations",
            "subcategory":"Religious Organization",
            "type":"Services"
        }
    ],
    "sg:phone":"+1 517 372 5849",
    "sg:postcode":"48906",
    "sg:province":"MI",
    "wof:name":"Passionist Sisters",
    "wof:placetype":"venue"
},
  "geometry": {"coordinates":[-84.551858,42.7601],"type":"Point"}
}