{
  "type": "Feature",
  "properties": {
    "iso:country":"US",
    "sg:address":"4360 Curtice Rd",
    "sg:city":"Mason",
    "sg:classifiers":[
        {
            "category":"Professional",
            "subcategory":"Computer Services",
            "type":"Services"
        }
    ],
    "sg:phone":"+1 517 676 6633",
    "sg:postcode":"48854",
    "sg:province":"MI",
    "sg:tags":[
        "consultant",
        "designer"
    ],
    "sg:website":"www.appl-spec.com",
    "wof:name":"Application Specialists",
    "wof:placetype":"venue"
},
  "geometry": {"coordinates":[-84.50856400000001,42.567306],"type":"Point"}
}