{
  "type": "Feature",
  "properties": {
    "iso:country":"US",
    "sg:address":"23530 Reynolds Ct",
    "sg:city":"Clinton Twp",
    "sg:classifiers":[
        {
            "category":"Manufacturing",
            "subcategory":"Tools & Machinery",
            "type":"Manufacturing & Wholesale Goods"
        }
    ],
    "sg:phone":"+1 586 783 7135",
    "sg:postcode":"48036",
    "sg:province":"MI",
    "sg:tags":[
        "machine",
        "shop"
    ],
    "wof:name":"Sterling Thread Products",
    "wof:placetype":"venue"
},
  "geometry": {"coordinates":[-82.870284,42.622696],"type":"Point"}
}