{
  "type": "Feature",
  "properties": {
    "iso:country":"US",
    "sg:address":"1385 Decker Rd",
    "sg:city":"Walled Lake",
    "sg:classifiers":[
        {
            "category":"Wholesale",
            "subcategory":"Machinery & Supplies",
            "type":"Manufacturing & Wholesale Goods"
        }
    ],
    "sg:phone":"+1 248 960 5891",
    "sg:postcode":"48390",
    "sg:province":"MI",
    "sg:tags":[
        "tool"
    ],
    "wof:name":"T C Tapsaver Inc",
    "wof:placetype":"venue"
},
  "geometry": {"coordinates":[-83.46825699999999,42.543818],"type":"Point"}
}