{
  "type": "Feature",
  "properties": {
    "iso:country":"US",
    "sg:address":"506 W Michigan Ave",
    "sg:city":"Jackson",
    "sg:classifiers":[
        {
            "category":"Professional",
            "subcategory":"Accounting & Tax Preparation",
            "type":"Services"
        }
    ],
    "sg:phone":"+1 517 784 0533",
    "sg:postcode":"49201",
    "sg:province":"MI",
    "sg:tags":[
        "accountant"
    ],
    "wof:name":"S & W Business Svc Inc",
    "wof:placetype":"venue"
},
  "geometry": {"coordinates":[-84.417266,42.247495],"type":"Point"}
}