{
  "type": "Feature",
  "properties": {
    "iso:country":"US",
    "sg:address":"1020 Royal Oak St SW",
    "sg:city":"Wyoming",
    "sg:classifiers":[
        {
            "category":"Freight",
            "type":"Transportation"
        }
    ],
    "sg:phone":"+1 616 530 0263",
    "sg:postcode":"49509",
    "sg:province":"MI",
    "sg:tags":[
        "trucking"
    ],
    "wof:name":"Universal Brush & Stump Svc",
    "wof:placetype":"venue"
},
  "geometry": {"coordinates":[-85.69032199999999,42.905131],"type":"Point"}
}