{
  "type": "Feature",
  "properties": {
    "iso:country":"US",
    "sg:address":"8103 Fawn Valley Dr",
    "sg:city":"Clarkston",
    "sg:classifiers":[
        {
            "category":"Professional",
            "subcategory":"Computer Services",
            "type":"Services"
        }
    ],
    "sg:phone":"+1 248 625 7389",
    "sg:postcode":"48348",
    "sg:province":"MI",
    "sg:tags":[
        "consultant",
        "designer",
        "datum",
        "system"
    ],
    "wof:name":"Forestro LLC",
    "wof:placetype":"venue"
},
  "geometry": {"coordinates":[-83.409434,42.757641],"type":"Point"}
}