{
  "type": "Feature",
  "properties": {
    "iso:country":"US",
    "sg:address":"1936 Holland Ave",
    "sg:city":"Port Huron",
    "sg:classifiers":[
        {
            "category":"Health Services",
            "subcategory":"Doctor",
            "type":"Services"
        }
    ],
    "sg:phone":"+1 810 987 8310",
    "sg:postcode":"48060",
    "sg:province":"MI",
    "wof:name":"Anthony Szyndlar DDS",
    "wof:placetype":"venue"
},
  "geometry": {"coordinates":[-82.449967,43.015424],"type":"Point"}
}