{
  "type": "Feature",
  "properties": {
    "iso:country":"US",
    "sg:address":"118 E Lawrence Ave",
    "sg:city":"Charlotte",
    "sg:classifiers":[
        {
            "category":"Education",
            "subcategory":"Dance Studio",
            "type":"Public Place"
        }
    ],
    "sg:phone":"+1 517 543 8800",
    "sg:postcode":"48813",
    "sg:province":"MI",
    "sg:tags":[
        "instruction",
        "dancing"
    ],
    "wof:name":"Brenda's Dance Academy",
    "wof:placetype":"venue"
},
  "geometry": {"coordinates":[-84.835711,42.563892],"type":"Point"}
}