{
  "type": "Feature",
  "properties": {
    "iso:country":"US",
    "sg:address":"450 E State St",
    "sg:city":"Belding",
    "sg:classifiers":[
        {
            "category":"Restaurant",
            "type":"Food & Drink"
        }
    ],
    "sg:phone":"+1 616 794 9897",
    "sg:postcode":"48809",
    "sg:province":"MI",
    "wof:name":"Belding Saloon",
    "wof:placetype":"venue"
},
  "geometry": {"coordinates":[-85.223995,43.089044],"type":"Point"}
}