{
  "type": "Feature",
  "properties": {
    "iso:country":"US",
    "sg:address":"13516 Mark St",
    "sg:city":"Southgate",
    "sg:classifiers":[
        {
            "category":"Professional",
            "subcategory":"Business Services",
            "type":"Services"
        }
    ],
    "sg:phone":"+1 734 285 3649",
    "sg:postcode":"48195",
    "sg:province":"MI",
    "wof:name":"Fastway Express",
    "wof:placetype":"venue"
},
  "geometry": {"coordinates":[-83.206129,42.210638],"type":"Point"}
}