{
  "type": "Feature",
  "properties": {
    "iso:country":"US",
    "sg:address":"1600 Chester Rd",
    "sg:city":"Gaylord",
    "sg:classifiers":[
        {
            "category":"Building & Trades",
            "subcategory":"Construction",
            "type":"Services"
        }
    ],
    "sg:phone":"+1 989 732 3324",
    "sg:postcode":"49735",
    "sg:province":"MI",
    "sg:tags":[
        "excavation",
        "contractor"
    ],
    "wof:name":"Bk Excavating Inc",
    "wof:placetype":"venue"
},
  "geometry": {"coordinates":[-84.60658100000001,45.007733],"type":"Point"}
}