{
  "type": "Feature",
  "properties": {
    "iso:country":"US",
    "sg:address":"2177 W Columbia Ave",
    "sg:city":"Battle Creek",
    "sg:classifiers":[
        {
            "category":"Shopping",
            "type":"Retail Goods"
        }
    ],
    "sg:phone":"+1 269 963 7461",
    "sg:postcode":"49015",
    "sg:province":"MI",
    "sg:tags":[
        "hearing",
        "equipment",
        "supply",
        "impaired"
    ],
    "wof:name":"National Hearing Ctr",
    "wof:placetype":"venue"
},
  "geometry": {"coordinates":[-85.237077,42.297279],"type":"Point"}
}