{
  "type": "Feature",
  "properties": {
    "iso:country":"US",
    "sg:address":"878 Camellia Ln",
    "sg:city":"Moline",
    "sg:classifiers":[
        {
            "category":"Building & Trades",
            "subcategory":"Construction",
            "type":"Services"
        }
    ],
    "sg:phone":"+1 616 877 0204",
    "sg:postcode":"49348",
    "sg:province":"MI",
    "sg:tags":[
        "water",
        "restoration",
        "damage"
    ],
    "wof:name":"Service Master Co",
    "wof:placetype":"venue"
},
  "geometry": {"coordinates":[-85.632357,42.743573],"type":"Point"}
}