{
  "type": "Feature",
  "properties": {
    "iso:country":"US",
    "sg:address":"1269 S Bunn Rd",
    "sg:city":"Hillsdale",
    "sg:classifiers":[
        {
            "category":"Retail",
            "subcategory":"Auto Repair",
            "type":"Services"
        }
    ],
    "sg:phone":"+1 517 437 4400",
    "sg:postcode":"49242",
    "sg:province":"MI",
    "sg:tags":[
        "shop",
        "automotive",
        "general"
    ],
    "wof:name":"McLain Auto Service Inc",
    "wof:placetype":"venue"
},
  "geometry": {"coordinates":[-84.687427,41.909946],"type":"Point"}
}