{
  "type": "Feature",
  "properties": {
    "iso:country":"US",
    "sg:address":"1552 Pine Valley Blvd",
    "sg:city":"Ann Arbor",
    "sg:classifiers":[
        {
            "category":"Professional",
            "subcategory":"Management & Consulting",
            "type":"Services"
        }
    ],
    "sg:phone":"+1 734 260 0517",
    "sg:postcode":"48104",
    "sg:province":"MI",
    "sg:tags":[
        "assistance",
        "certification"
    ],
    "wof:name":"AMS",
    "wof:placetype":"venue"
},
  "geometry": {"coordinates":[-83.723286,42.251719],"type":"Point"}
}