{
  "type": "Feature",
  "properties": {
    "iso:country":"US",
    "sg:address":"2689 Gullmont Dr SW",
    "sg:city":"Wyoming",
    "sg:classifiers":[
        {
            "category":"Retail",
            "subcategory":"Repair Shop",
            "type":"Services"
        }
    ],
    "sg:phone":"+1 616 534 6686",
    "sg:postcode":"49418",
    "sg:province":"MI",
    "sg:tags":[
        "related"
    ],
    "wof:name":"LTK Small Tool Repair",
    "wof:placetype":"venue"
},
  "geometry": {"coordinates":[-85.730357,42.867334],"type":"Point"}
}