{
  "type": "Feature",
  "properties": {
    "iso:country":"US",
    "sg:address":"7949 Livernois Ave",
    "sg:city":"Detroit",
    "sg:classifiers":[
        {
            "category":"Autos & Motor Vehicles",
            "subcategory":"Automobile Sales",
            "type":"Retail Goods"
        }
    ],
    "sg:phone":"+1 313 834 2111",
    "sg:postcode":"48210",
    "sg:province":"MI",
    "sg:tags":[
        "used"
    ],
    "wof:name":"Roys Super Auto Sales",
    "wof:placetype":"venue"
},
  "geometry": {"coordinates":[-83.135414,42.351378],"type":"Point"}
}