{
  "type": "Feature",
  "properties": {
    "iso:country":"US",
    "sg:address":"5814 Thornaby Dr",
    "sg:city":"Waterford",
    "sg:classifiers":[
        {
            "category":"Organizations",
            "subcategory":"Religious Organization",
            "type":"Services"
        }
    ],
    "sg:phone":"+1 248 673 4053",
    "sg:postcode":"48329",
    "sg:province":"MI",
    "wof:name":"Gods House of Worship",
    "wof:placetype":"venue"
},
  "geometry": {"coordinates":[-83.403796,42.680852],"type":"Point"}
}