{
  "type": "Feature",
  "properties": {
    "iso:country":"US",
    "sg:address":"28641 Elbamar Dr",
    "sg:city":"Grosse Ile",
    "sg:classifiers":[
        {
            "category":"Education",
            "subcategory":"Vocational School",
            "type":"Public Place"
        }
    ],
    "sg:phone":"+1 734 675 6247",
    "sg:postcode":"48138",
    "sg:province":"MI",
    "wof:name":"Positive Support Seminars",
    "wof:placetype":"venue"
},
  "geometry": {"coordinates":[-83.16866400000001,42.097139],"type":"Point"}
}