{
  "type": "Feature",
  "properties": {
    "iso:country":"US",
    "sg:address":"37651 6 Mile Rd",
    "sg:city":"Livonia",
    "sg:classifiers":[
        {
            "category":"Fast Food",
            "type":"Food & Drink"
        },
        {
            "category":"Restaurant",
            "type":"Food & Drink"
        }
    ],
    "sg:phone":"+1 734 469 4400",
    "sg:postcode":"48152",
    "sg:province":"MI",
    "sg:tags":[
        "chicken",
        "style",
        "american",
        "family",
        "take"
    ],
    "sg:website":"http://www.buffalowildwings.com/",
    "wof:name":"Buffalo Wild Wings",
    "wof:placetype":"venue"
},
  "geometry": {"coordinates":[-83.41664400000001,42.410659],"type":"Point"}
}