{
  "type": "Feature",
  "properties": {
    "iso:country":"US",
    "sg:address":"1802 Wood St",
    "sg:city":"Saginaw",
    "sg:classifiers":[
        {
            "category":"Real Estate",
            "subcategory":"Real Estate Agent",
            "type":"Services"
        }
    ],
    "sg:phone":"+1 989 792 7586",
    "sg:postcode":"48602",
    "sg:province":"MI",
    "wof:name":"Federico Navarrete",
    "wof:placetype":"venue"
},
  "geometry": {"coordinates":[-83.99144099999999,43.402619],"type":"Point"}
}