{
  "type": "Feature",
  "properties": {
    "iso:country":"US",
    "sg:address":"13160 Sparta Ave",
    "sg:city":"Kent City",
    "sg:classifiers":[
        {
            "category":"Building & Trades",
            "subcategory":"Construction",
            "type":"Services"
        }
    ],
    "sg:phone":"+1 616 887 6338",
    "sg:postcode":"49330",
    "sg:province":"MI",
    "sg:tags":[
        "contractor"
    ],
    "wof:name":"Mullen Builders LLC",
    "wof:placetype":"venue"
},
  "geometry": {"coordinates":[-85.710866,43.197966],"type":"Point"}
}