{
  "type": "Feature",
  "properties": {
    "iso:country":"US",
    "sg:address":"201 Brookley Ave",
    "sg:city":"Jackson",
    "sg:classifiers":[
        {
            "category":"Manufacturing",
            "subcategory":"Printing",
            "type":"Manufacturing & Wholesale Goods"
        }
    ],
    "sg:phone":"+1 517 787 4130",
    "sg:postcode":"49202",
    "sg:province":"MI",
    "sg:tags":[
        "commercial"
    ],
    "wof:name":"Ray Printing & Mailing Co Inc",
    "wof:placetype":"venue"
},
  "geometry": {"coordinates":[-84.39920499999999,42.270994],"type":"Point"}
}