{
  "type": "Feature",
  "properties": {
    "iso:country":"US",
    "sg:address":"11594 Boyce Rd",
    "sg:city":"Stockbridge",
    "sg:classifiers":[
        {
            "category":"Building & Trades",
            "subcategory":"Construction",
            "type":"Services"
        }
    ],
    "sg:phone":"+1 517 851 4651",
    "sg:postcode":"49285",
    "sg:province":"MI",
    "sg:tags":[
        "house"
    ],
    "wof:name":"Mj Builders",
    "wof:placetype":"venue"
},
  "geometry": {"coordinates":[-84.097842,42.405378],"type":"Point"}
}