{
  "type": "Feature",
  "properties": {
    "iso:country":"US",
    "sg:address":"4512 Pontiac Lake Rd",
    "sg:city":"Waterford",
    "sg:classifiers":[
        {
            "category":"Personal",
            "type":"Services"
        }
    ],
    "sg:phone":"+1 248 673 2583",
    "sg:postcode":"48328",
    "sg:province":"MI",
    "wof:name":"Sun Country Tanning",
    "wof:placetype":"venue"
},
  "geometry": {"coordinates":[-83.375822,42.654159],"type":"Point"}
}