{
  "type": "Feature",
  "properties": {
    "iso:country":"US",
    "sg:address":"4704 S Washington Rd",
    "sg:city":"Saginaw",
    "sg:classifiers":[
        {
            "category":"Freight",
            "type":"Transportation"
        }
    ],
    "sg:phone":"+1 989 777 7218",
    "sg:postcode":"48601",
    "sg:province":"MI",
    "sg:tags":[
        "trucking"
    ],
    "wof:name":"Dexter Trucking",
    "wof:placetype":"venue"
},
  "geometry": {"coordinates":[-83.921122,43.371994],"type":"Point"}
}