{
  "type": "Feature",
  "properties": {
    "iso:country":"US",
    "sg:address":"5119 Highland Rd",
    "sg:city":"Waterford",
    "sg:classifiers":[
        {
            "category":"Professional",
            "subcategory":"Advertising",
            "type":"Services"
        }
    ],
    "sg:phone":"+1 248 618 0667",
    "sg:postcode":"48327",
    "sg:province":"MI",
    "sg:tags":[
        "mailing",
        "shipping"
    ],
    "wof:name":"ETC Mailboxes",
    "wof:placetype":"venue"
},
  "geometry": {"coordinates":[-83.387902,42.660209],"type":"Point"}
}