{
  "type": "Feature",
  "properties": {
    "iso:country":"US",
    "sg:address":"1901 Breton Rd SE",
    "sg:city":"Grand Rapids",
    "sg:classifiers":[
        {
            "category":"Banks & Credit Unions",
            "subcategory":"Bank",
            "type":"Services"
        }
    ],
    "sg:phone":"+1 616 771 6327",
    "sg:postcode":"49506",
    "sg:province":"MI",
    "sg:tags":[
        "national",
        "commercial"
    ],
    "sg:website":"www.huntington.com",
    "wof:name":"Huntington National Bank",
    "wof:placetype":"venue"
},
  "geometry": {"coordinates":[-85.609241,42.927666],"type":"Point"}
}