{
  "type": "Feature",
  "properties": {
    "iso:country":"US",
    "sg:address":"3487 76th St SE",
    "sg:city":"Caledonia",
    "sg:classifiers":[
        {
            "category":"Building & Trades",
            "subcategory":"Construction",
            "type":"Services"
        }
    ],
    "sg:phone":"+1 616 656 9781",
    "sg:postcode":"49316",
    "sg:province":"MI",
    "sg:tags":[
        "mobile",
        "home"
    ],
    "wof:name":"South Kent Mobile Home Repair",
    "wof:placetype":"venue"
},
  "geometry": {"coordinates":[-85.580956,42.826651],"type":"Point"}
}