{
  "type": "Feature",
  "properties": {
    "iso:country":"US",
    "sg:address":"6807 Cascade Rd SE",
    "sg:city":"Grand Rapids",
    "sg:classifiers":[
        {
            "category":"Shopping",
            "type":"Retail Goods"
        }
    ],
    "sg:phone":"+1 616 954 6598",
    "sg:postcode":"49331",
    "sg:province":"MI",
    "sg:tags":[
        "equipment",
        "care",
        "health",
        "home"
    ],
    "sg:website":"www.wmmedicalsupply.com",
    "wof:name":"West Michigan Medical Supply",
    "wof:placetype":"venue"
},
  "geometry": {"coordinates":[-85.498688,42.91295],"type":"Point"}
}