{
  "type": "Feature",
  "properties": {
    "iso:country":"US",
    "sg:address":"1715 Glendale Blvd",
    "sg:city":"Kalamazoo",
    "sg:classifiers":[
        {
            "category":"Professional",
            "subcategory":"Art Services",
            "type":"Services"
        },
        {
            "category":"Shopping",
            "subcategory":"Computers & Home Electronics",
            "type":"Retail Goods"
        }
    ],
    "sg:phone":"+1 269 382 2561",
    "sg:postcode":"49004",
    "sg:province":"MI",
    "sg:tags":[
        "commercial",
        "design",
        "publishing"
    ],
    "wof:name":"Sand Hill Marketing",
    "wof:placetype":"venue"
},
  "geometry": {"coordinates":[-85.55919400000001,42.326536],"type":"Point"}
}