{
  "type": "Feature",
  "properties": {
    "iso:country":"US",
    "sg:address":"11250 E 13 Mile Rd",
    "sg:city":"Warren",
    "sg:classifiers":[
        {
            "category":"Health Services",
            "subcategory":"Doctor",
            "type":"Services"
        }
    ],
    "sg:phone":"+1 586 574 9500",
    "sg:postcode":"48093",
    "sg:province":"MI",
    "sg:tags":[
        "surgeon",
        "oral"
    ],
    "wof:name":"Tuck Ronald L DDS",
    "wof:placetype":"venue"
},
  "geometry": {"coordinates":[-83.007896,42.5214],"type":"Point"}
}