{
  "type": "Feature",
  "properties": {
    "iso:country":"US",
    "sg:address":"309 Shellbourne Dr",
    "sg:city":"Rochester Hills",
    "sg:classifiers":[
        {
            "category":"Professional",
            "subcategory":"Art Services",
            "type":"Services"
        }
    ],
    "sg:phone":"+1 248 370 8930",
    "sg:postcode":"48309",
    "sg:province":"MI",
    "sg:tags":[
        "photographer"
    ],
    "wof:name":"Allstates Photo",
    "wof:placetype":"venue"
},
  "geometry": {"coordinates":[-83.2054,42.684623],"type":"Point"}
}