{
  "type": "Feature",
  "properties": {
    "iso:country":"US",
    "sg:address":"10200 Cooper Rd",
    "sg:city":"Pleasant Lake",
    "sg:classifiers":[
        {
            "category":"Building & Trades",
            "subcategory":"Construction",
            "type":"Services"
        }
    ],
    "sg:phone":"+1 517 769 2353",
    "sg:postcode":"49272",
    "sg:province":"MI",
    "sg:tags":[
        "home",
        "improvement"
    ],
    "wof:name":"New Generation Construction",
    "wof:placetype":"venue"
},
  "geometry": {"coordinates":[-84.374576,42.391951],"type":"Point"}
}