{
  "type": "Feature",
  "properties": {
    "iso:country":"US",
    "sg:address":"4488 Jackson Rd",
    "sg:city":"Ann Arbor",
    "sg:classifiers":[
        {
            "category":"Insurance",
            "subcategory":"Insurance Agent",
            "type":"Services"
        }
    ],
    "sg:phone":"+1 734 827 2822",
    "sg:postcode":"48103",
    "sg:province":"MI",
    "wof:name":"Jim Pietila Agency",
    "wof:placetype":"venue"
},
  "geometry": {"coordinates":[-83.82074,42.286364],"type":"Point"}
}