{
  "type": "Feature",
  "properties": {
    "iso:country":"US",
    "sg:address":"32801 John R Rd",
    "sg:city":"Madison Heights",
    "sg:classifiers":[
        {
            "category":"Restaurant",
            "type":"Food & Drink"
        }
    ],
    "sg:phone":"+1 248 588 9088",
    "sg:postcode":"48071",
    "sg:province":"MI",
    "wof:name":"Taco Bell",
    "wof:placetype":"venue"
},
  "geometry": {"coordinates":[-83.10705900000001,42.533386],"type":"Point"}
}