{
  "type": "Feature",
  "properties": {
    "iso:country":"US",
    "sg:address":"4270 N Adrian Hwy",
    "sg:city":"Adrian",
    "sg:classifiers":[
        {
            "category":"Autos & Motor Vehicles",
            "subcategory":"Motorcycle Sales",
            "type":"Retail Goods"
        }
    ],
    "sg:phone":"+1 517 266 8839",
    "sg:postcode":"49221",
    "sg:province":"MI",
    "sg:tags":[
        "car",
        "golf",
        "cart"
    ],
    "wof:name":"Wilson Sales",
    "wof:placetype":"venue"
},
  "geometry": {"coordinates":[-84.004678,41.944809],"type":"Point"}
}