{
  "type": "Feature",
  "properties": {
    "iso:country":"US",
    "sg:address":"115 N 4th St",
    "sg:city":"Coleman",
    "sg:classifiers":[
        {
            "category":"Restaurant",
            "type":"Food & Drink"
        }
    ],
    "sg:phone":"+1 989 465 1142",
    "sg:postcode":"48618",
    "sg:province":"MI",
    "wof:name":"Pizza Man",
    "wof:placetype":"venue"
},
  "geometry": {"coordinates":[-84.585848,43.756973],"type":"Point"}
}