{
  "type": "Feature",
  "properties": {
    "iso:country":"US",
    "sg:address":"15411 W Warren Ave",
    "sg:city":"Dearborn",
    "sg:classifiers":[
        {
            "category":"Restaurant",
            "type":"Food & Drink"
        }
    ],
    "sg:menulink":"http://www.allmenus.com/mi/dearborn/247101-amanis-restaurant/menu/",
    "sg:phone":"+1 313 584 1888",
    "sg:postcode":"48126",
    "sg:province":"MI",
    "sg:tags":[
        "middle",
        "eastern"
    ],
    "wof:name":"Amani's Restaurant",
    "wof:placetype":"venue"
},
  "geometry": {"coordinates":[-83.19527600000001,42.343676],"type":"Point"}
}