{
  "type": "Feature",
  "properties": {
    "iso:country":"US",
    "sg:address":"6709 Blake Dr",
    "sg:city":"Caseville",
    "sg:classifiers":[
        {
            "category":"Food & Beverages",
            "subcategory":"Groceries & Convenience Stores",
            "type":"Retail Goods"
        }
    ],
    "sg:phone":"+1 989 738 7511",
    "sg:postcode":"48725",
    "sg:province":"MI",
    "wof:name":"Colas Coolers",
    "wof:placetype":"venue"
},
  "geometry": {"coordinates":[-83.16178499999999,43.983428],"type":"Point"}
}