{
  "type": "Feature",
  "properties": {
    "iso:country":"US",
    "sg:address":"39650 Orchard Hill Pl",
    "sg:city":"Novi",
    "sg:classifiers":[
        {
            "category":"Health Services",
            "subcategory":"Doctor",
            "type":"Services"
        }
    ],
    "sg:phone":"+1 248 471 2800",
    "sg:postcode":"48375",
    "sg:province":"MI",
    "sg:tags":[
        "physician",
        "surgeon"
    ],
    "wof:name":"Pulmonary & Critical Care Spec",
    "wof:placetype":"venue"
},
  "geometry": {"coordinates":[-83.437219,42.444587],"type":"Point"}
}