{
  "type": "Feature",
  "properties": {
    "iso:country":"US",
    "sg:address":"177 Catalpa Ave",
    "sg:city":"Benton Harbor",
    "sg:classifiers":[
        {
            "category":"Social Services",
            "subcategory":"Child Care",
            "type":"Services"
        }
    ],
    "sg:phone":"+1 269 934 8220",
    "sg:postcode":"49022",
    "sg:province":"MI",
    "wof:name":"New Beginning Day Care",
    "wof:placetype":"venue"
},
  "geometry": {"coordinates":[-86.45607099999999,42.106738],"type":"Point"}
}