{
  "type": "Feature",
  "properties": {
    "iso:country":"US",
    "sg:address":"1650 Fort St",
    "sg:city":"Trenton",
    "sg:classifiers":[
        {
            "category":"Health Services",
            "subcategory":"Health Practitioner",
            "type":"Services"
        }
    ],
    "sg:phone":"+1 734 675 6755",
    "sg:postcode":"48183",
    "sg:province":"MI",
    "wof:name":"Sportsmedic Med Rehabilitation",
    "wof:placetype":"venue"
},
  "geometry": {"coordinates":[-83.188695,42.151495],"type":"Point"}
}