{
  "type": "Feature",
  "properties": {
    "iso:country":"US",
    "sg:address":"2223 Avon Industrial Dr",
    "sg:city":"Rochester Hills",
    "sg:classifiers":[
        {
            "category":"Home & Garden",
            "subcategory":"Building Materials",
            "type":"Retail Goods"
        }
    ],
    "sg:phone":"+1 248 258 1979",
    "sg:postcode":"48309",
    "sg:province":"MI",
    "sg:tags":[
        "glass",
        "window",
        "plate"
    ],
    "wof:name":"Visions Glass Inc",
    "wof:placetype":"venue"
},
  "geometry": {"coordinates":[-83.17177100000001,42.648331],"type":"Point"}
}