{
  "type": "Feature",
  "properties": {
    "iso:country":"US",
    "sg:address":"5211 Claremont St",
    "sg:city":"Midland",
    "sg:classifiers":[
        {
            "category":"Real Estate",
            "subcategory":"Real Estate Agent",
            "type":"Services"
        }
    ],
    "sg:phone":"+1 989 832 6045",
    "sg:postcode":"48642",
    "sg:province":"MI",
    "wof:name":"Cendant Mobility Services Corp",
    "wof:placetype":"venue"
},
  "geometry": {"coordinates":[-84.211322,43.644237],"type":"Point"}
}