{
  "type": "Feature",
  "properties": {
    "iso:country":"US",
    "sg:address":"2930 Michael Ave SW",
    "sg:city":"Wyoming",
    "sg:classifiers":[
        {
            "category":"Building & Trades",
            "subcategory":"Cleaning & Sanitation",
            "type":"Services"
        }
    ],
    "sg:phone":"+1 616 291 8928",
    "sg:postcode":"49509",
    "sg:province":"MI",
    "sg:tags":[
        "house"
    ],
    "wof:name":"Doctor MD Cleaning",
    "wof:placetype":"venue"
},
  "geometry": {"coordinates":[-85.69530399999999,42.909557],"type":"Point"}
}