{
  "type": "Feature",
  "properties": {
    "iso:country":"US",
    "sg:address":"259 Bertrand St",
    "sg:city":"St Ignace",
    "sg:classifiers":[
        {
            "category":"Shopping",
            "subcategory":"Florist",
            "type":"Retail Goods"
        }
    ],
    "sg:phone":"+1 906 643 9480",
    "sg:postcode":"49781",
    "sg:province":"MI",
    "wof:name":"St Ignace Greenhouse & Flower",
    "wof:placetype":"venue"
},
  "geometry": {"coordinates":[-84.712763,45.857683],"type":"Point"}
}