{
  "type": "Feature",
  "properties": {
    "iso:country":"US",
    "sg:address":"6111 Bunker Rd",
    "sg:city":"Eaton Rapids",
    "sg:classifiers":[
        {
            "category":"Building & Trades",
            "subcategory":"Construction",
            "type":"Services"
        }
    ],
    "sg:phone":"+1 517 663 8360",
    "sg:postcode":"48827",
    "sg:province":"MI",
    "sg:tags":[
        "home",
        "builder"
    ],
    "wof:name":"Stoneybrook Homes",
    "wof:placetype":"venue"
},
  "geometry": {"coordinates":[-84.598685,42.552931],"type":"Point"}
}