{
  "type": "Feature",
  "properties": {
    "iso:country":"US",
    "sg:address":"1606 King St",
    "sg:city":"Saginaw",
    "sg:classifiers":[
        {
            "category":"Banks & Credit Unions",
            "subcategory":"Bank",
            "type":"Services"
        }
    ],
    "sg:phone":"+1 989 799 4391",
    "sg:postcode":"48602",
    "sg:province":"MI",
    "sg:tags":[
        "state",
        "loan",
        "broker"
    ],
    "wof:name":"Amalgamated Credit Union",
    "wof:placetype":"venue"
},
  "geometry": {"coordinates":[-83.97424100000001,43.405727],"type":"Point"}
}