{
  "type": "Feature",
  "properties": {
    "iso:country":"US",
    "sg:address":"911 Village Green Ln",
    "sg:city":"Waterford",
    "sg:classifiers":[
        {
            "category":"Real Estate",
            "subcategory":"Real Estate Operator",
            "type":"Services"
        }
    ],
    "sg:phone":"+1 248 683 2525",
    "sg:postcode":"48328",
    "sg:province":"MI",
    "sg:tags":[
        "apartment"
    ],
    "wof:name":"Village Green Apartments",
    "wof:placetype":"venue"
},
  "geometry": {"coordinates":[-83.354328,42.652375],"type":"Point"}
}