{
  "type": "Feature",
  "properties": {
    "iso:country":"US",
    "sg:address":"20 Mill Rd",
    "sg:city":"Marshall",
    "sg:classifiers":[
        {
            "category":"Health Services",
            "subcategory":"Clinic",
            "type":"Services"
        }
    ],
    "sg:phone":"+1 269 789 9770",
    "sg:postcode":"49014",
    "sg:province":"MI",
    "sg:tags":[
        "personal"
    ],
    "wof:name":"Nutritnal Blnce Wigh Managment",
    "wof:placetype":"venue"
},
  "geometry": {"coordinates":[-85.149433,42.332109],"type":"Point"}
}