{
  "type": "Feature",
  "properties": {
    "iso:country":"US",
    "sg:address":"1817 W G Ave",
    "sg:city":"Kalamazoo",
    "sg:classifiers":[
        {
            "category":"Professional",
            "subcategory":"Management & Consulting",
            "type":"Services"
        }
    ],
    "sg:phone":"+1 269 349 4227",
    "sg:postcode":"49009",
    "sg:province":"MI",
    "wof:name":"Changeworks",
    "wof:placetype":"venue"
},
  "geometry": {"coordinates":[-85.615284,42.332823],"type":"Point"}
}