{
  "type": "Feature",
  "properties": {
    "iso:country":"US",
    "sg:address":"11310 Prairie Ave",
    "sg:city":"Allendale",
    "sg:classifiers":[
        {
            "category":"Shopping",
            "subcategory":"Hobbies, Toys, & Games",
            "type":"Retail Goods"
        }
    ],
    "sg:phone":"+1 616 895 6378",
    "sg:postcode":"49401",
    "sg:province":"MI",
    "sg:tags":[
        "mfg",
        "craft",
        "supply"
    ],
    "wof:name":"Tomorrow's Heirlooms",
    "wof:placetype":"venue"
},
  "geometry": {"coordinates":[-85.930955,42.973891],"type":"Point"}
}