{
  "type": "Feature",
  "properties": {
    "iso:country":"US",
    "sg:address":"6491 Sashabaw Rd",
    "sg:city":"Clarkston",
    "sg:classifiers":[
        {
            "category":"Banks & Credit Unions",
            "subcategory":"Bank",
            "type":"Services"
        }
    ],
    "sg:phone":"+1 248 922 9168",
    "sg:postcode":"48346",
    "sg:province":"MI",
    "sg:tags":[
        "loan",
        "real estate"
    ],
    "wof:name":"Countrywide Home Loans",
    "wof:placetype":"venue"
},
  "geometry": {"coordinates":[-83.37927999999999,42.72879],"type":"Point"}
}