{
  "type": "Feature",
  "properties": {
    "iso:country":"US",
    "sg:address":"15949 Front",
    "sg:city":"Powers",
    "sg:classifiers":[
        {
            "category":"Railroad",
            "type":"Transportation"
        }
    ],
    "sg:phone":"+1 906 497 5712",
    "sg:postcode":"49874",
    "sg:province":"MI",
    "wof:name":"Wisconsin Central LTD",
    "wof:placetype":"venue"
},
  "geometry": {"coordinates":[-87.526679,45.688834],"type":"Point"}
}