{
  "type": "Feature",
  "properties": {
    "iso:country":"US",
    "sg:address":"16311 Cloverbrook Dr",
    "sg:city":"Hemlock",
    "sg:classifiers":[
        {
            "category":"Building & Trades",
            "subcategory":"Construction",
            "type":"Services"
        }
    ],
    "sg:phone":"+1 989 642 4156",
    "sg:postcode":"48626",
    "sg:province":"MI",
    "sg:tags":[
        "painter"
    ],
    "wof:name":"Pollick's Painting",
    "wof:placetype":"venue"
},
  "geometry": {"coordinates":[-84.23617,43.406504],"type":"Point"}
}