{
  "type": "Feature",
  "properties": {
    "iso:country":"US",
    "sg:address":"26315 Scotia Rd",
    "sg:city":"Huntington Wd",
    "sg:classifiers":[
        {
            "category":"Education",
            "subcategory":"School",
            "type":"Public Place"
        }
    ],
    "sg:phone":"+1 248 837 8600",
    "sg:postcode":"48070",
    "sg:province":"MI",
    "sg:tags":[
        "high",
        "middle",
        "elementary"
    ],
    "wof:name":"Berkley School District",
    "wof:placetype":"venue"
},
  "geometry": {"coordinates":[-83.1735,42.4842],"type":"Point"}
}