{
  "type": "Feature",
  "properties": {
    "iso:country":"US",
    "sg:address":"2491 Cedar Park Blvd",
    "sg:city":"Holt",
    "sg:classifiers":[
        {
            "category":"Professional",
            "subcategory":"Employment Agencies",
            "type":"Services"
        }
    ],
    "sg:phone":"+1 517 694 1153",
    "sg:postcode":"48842",
    "sg:province":"MI",
    "sg:tags":[
        "executive",
        "placement",
        "help",
        "contractor"
    ],
    "wof:name":"Management Recruiters Intl",
    "wof:placetype":"venue"
},
  "geometry": {"coordinates":[-84.536734,42.654337],"type":"Point"}
}