{
  "type": "Feature",
  "properties": {
    "iso:country":"US",
    "sg:address":"472 N State Rd",
    "sg:city":"Otisville",
    "sg:classifiers":[
        {
            "category":"Retail",
            "subcategory":"Car Wash",
            "type":"Services"
        }
    ],
    "sg:phone":"+1 810 631 4229",
    "sg:postcode":"48463",
    "sg:province":"MI",
    "sg:tags":[
        "carwash"
    ],
    "wof:name":"Teachout Yard Cleanup",
    "wof:placetype":"venue"
},
  "geometry": {"coordinates":[-83.52400799999999,43.171985],"type":"Point"}
}