{
  "type": "Feature",
  "properties": {
    "iso:country":"US",
    "sg:address":"4129 Boulder Mdw NE",
    "sg:city":"Belmont",
    "sg:classifiers":[
        {
            "category":"Professional",
            "subcategory":"Accounting & Tax Preparation",
            "type":"Services"
        }
    ],
    "sg:phone":"+1 616 874 2119",
    "sg:postcode":"49306",
    "sg:province":"MI",
    "sg:tags":[
        "accountant"
    ],
    "wof:name":"Thomas & Company Cpa's",
    "wof:placetype":"venue"
},
  "geometry": {"coordinates":[-85.566101,43.072601],"type":"Point"}
}