{
  "type": "Feature",
  "properties": {
    "iso:country":"US",
    "sg:address":"9260 Warwick St",
    "sg:city":"Detroit",
    "sg:classifiers":[
        {
            "category":"Building & Trades",
            "subcategory":"Equipment Rental",
            "type":"Services"
        }
    ],
    "sg:phone":"+1 313 493 6426",
    "sg:postcode":"48228",
    "sg:province":"MI",
    "sg:tags":[
        "home",
        "maintenance",
        "repair"
    ],
    "wof:name":"Ronalds Maintenance",
    "wof:placetype":"venue"
},
  "geometry": {"coordinates":[-83.227414,42.36199],"type":"Point"}
}