{
  "type": "Feature",
  "properties": {
    "iso:country":"US",
    "sg:address":"331 N Alice Ave",
    "sg:city":"Rochester",
    "sg:classifiers":[
        {
            "category":"Building & Trades",
            "subcategory":"Construction",
            "type":"Services"
        }
    ],
    "sg:phone":"+1 248 652 4063",
    "sg:postcode":"48307",
    "sg:province":"MI",
    "sg:tags":[
        "contractor"
    ],
    "wof:name":"Garret Dennis Construction",
    "wof:placetype":"venue"
},
  "geometry": {"coordinates":[-83.14694900000001,42.680647],"type":"Point"}
}