{
  "type": "Feature",
  "properties": {
    "iso:country":"US",
    "sg:address":"27901 Woodward Ave Ste 220",
    "sg:city":"Berkley",
    "sg:classifiers":[
        {
            "category":"Health Services",
            "subcategory":"Doctor",
            "type":"Services"
        }
    ],
    "sg:phone":"+1 248 399 5492",
    "sg:postcode":"48072",
    "sg:province":"MI",
    "wof:name":"Kakos Norman J MD",
    "wof:placetype":"venue"
},
  "geometry": {"coordinates":[-83.165463,42.495974],"type":"Point"}
}