{
  "type": "Feature",
  "properties": {
    "iso:country":"US",
    "sg:address":"3364 Quincy St",
    "sg:city":"Hudsonville",
    "sg:classifiers":[
        {
            "category":"Retail",
            "subcategory":"Auto Repair",
            "type":"Services"
        }
    ],
    "sg:phone":"+1 616 669 8777",
    "sg:postcode":"49426",
    "sg:province":"MI",
    "sg:tags":[
        "general"
    ],
    "wof:name":"Speed Wrench Inc",
    "wof:placetype":"venue"
},
  "geometry": {"coordinates":[-85.865613,42.840256],"type":"Point"}
}