{
  "type": "Feature",
  "properties": {
    "iso:country":"US",
    "sg:address":"3950 Hendershot Ave NW",
    "sg:city":"Grand Rapids",
    "sg:classifiers":[
        {
            "category":"Education",
            "subcategory":"School",
            "type":"Public Place"
        }
    ],
    "sg:phone":"+1 616 785 3225",
    "sg:postcode":"49544",
    "sg:province":"MI",
    "sg:website":"www.khps.org",
    "wof:name":"Kenowa Hills Middle School",
    "wof:placetype":"venue"
},
  "geometry": {"coordinates":[-85.756828,43.042297],"type":"Point"}
}