{
  "type": "Feature",
  "properties": {
    "iso:country":"US",
    "sg:address":"708 Ogemaw St",
    "sg:city":"Grayling",
    "sg:classifiers":[
        {
            "category":"Shopping",
            "subcategory":"Stationery & Office Supplies",
            "type":"Retail Goods"
        }
    ],
    "sg:phone":"+1 989 348 1348",
    "sg:postcode":"49738",
    "sg:province":"MI",
    "wof:name":"Ausable Cash Registers",
    "wof:placetype":"venue"
},
  "geometry": {"coordinates":[-84.711969,44.666766],"type":"Point"}
}