{
  "type": "Feature",
  "properties": {
    "iso:country":"US",
    "sg:address":"4150 Grand River Ave",
    "sg:city":"Detroit",
    "sg:classifiers":[
        {
            "category":"Real Estate",
            "subcategory":"Real Estate Agent",
            "type":"Services"
        }
    ],
    "sg:phone":"+1 313 831 2855",
    "sg:postcode":"48208",
    "sg:province":"MI",
    "sg:tags":[
        "manager",
        "property"
    ],
    "wof:name":"Golden Oaks Limited Dividend H",
    "wof:placetype":"venue"
},
  "geometry": {"coordinates":[-83.079263,42.344679],"type":"Point"}
}