{
  "type": "Feature",
  "properties": {
    "iso:country":"US",
    "sg:address":"516 North St",
    "sg:city":"Yale",
    "sg:classifiers":[
        {
            "category":"Professional",
            "type":"Services"
        },
        {
            "category":"Health Services",
            "subcategory":"Hospital",
            "type":"Services"
        }
    ],
    "sg:phone":"+1 810 387 3232",
    "sg:postcode":"48097",
    "sg:province":"MI",
    "sg:tags":[
        "mental"
    ],
    "wof:name":"Touchstone Services Inc",
    "wof:placetype":"venue"
},
  "geometry": {"coordinates":[-82.788625,43.130127],"type":"Point"}
}