{
  "type": "Feature",
  "properties": {
    "iso:country":"US",
    "sg:address":"2025 Franklin Rd",
    "sg:city":"Bloomfield Hills",
    "sg:classifiers":[
        {
            "category":"Banks & Credit Unions",
            "subcategory":"Investment Brokerage",
            "type":"Services"
        }
    ],
    "sg:phone":"+1 248 451 0046",
    "sg:postcode":"48302",
    "sg:province":"MI",
    "sg:tags":[
        "investing"
    ],
    "wof:name":"Munder Capitol Mgmnt",
    "wof:placetype":"venue"
},
  "geometry": {"coordinates":[-83.287498,42.608501],"type":"Point"}
}