{
  "type": "Feature",
  "properties": {
    "iso:country":"US",
    "sg:address":"29321 8 Mile Rd",
    "sg:city":"Livonia",
    "sg:classifiers":[
        {
            "category":"Autos & Motor Vehicles",
            "subcategory":"Fuel & Gas Station",
            "type":"Retail Goods"
        }
    ],
    "sg:phone":"+1 248 476 5451",
    "sg:postcode":"48152",
    "sg:province":"MI",
    "wof:name":"Michigan Fuels",
    "wof:placetype":"venue"
},
  "geometry": {"coordinates":[-83.33580499999999,42.441449],"type":"Point"}
}