{
  "type": "Feature",
  "properties": {
    "iso:country":"US",
    "sg:address":"50475 Metzen",
    "sg:city":"Chesterfield",
    "sg:classifiers":[
        {
            "category":"Building & Trades",
            "subcategory":"Electrical",
            "type":"Services"
        }
    ],
    "sg:phone":"+1 586 598 1474",
    "sg:postcode":"48051",
    "sg:province":"MI",
    "sg:tags":[
        "electric",
        "contractor"
    ],
    "wof:name":"Target Electric LLC",
    "wof:placetype":"venue"
},
  "geometry": {"coordinates":[-82.825624,42.672151],"type":"Point"}
}