{
  "type": "Feature",
  "properties": {
    "iso:country":"US",
    "sg:address":"7460 E River Rd",
    "sg:city":"Flushing",
    "sg:classifiers":[
        {
            "category":"Social Services",
            "subcategory":"Adult Care",
            "type":"Services"
        }
    ],
    "sg:phone":"+1 810 659 3787",
    "sg:postcode":"48433",
    "sg:province":"MI",
    "sg:tags":[
        "home",
        "residential"
    ],
    "wof:name":"Hyde Park Assisted Living",
    "wof:placetype":"venue"
},
  "geometry": {"coordinates":[-83.824645,43.055057],"type":"Point"}
}