{
  "type": "Feature",
  "properties": {
    "iso:country":"US",
    "sg:address":"1036 Washington Ave",
    "sg:city":"Holland",
    "sg:classifiers":[
        {
            "category":"Building & Trades",
            "subcategory":"Construction",
            "type":"Services"
        }
    ],
    "sg:phone":"+1 616 546 2839",
    "sg:postcode":"49423",
    "sg:province":"MI",
    "sg:tags":[
        "front",
        "store"
    ],
    "wof:name":"Just-A-Buck",
    "wof:placetype":"venue"
},
  "geometry": {"coordinates":[-86.116612,42.760106],"type":"Point"}
}