{
  "type": "Feature",
  "properties": {
    "iso:country":"US",
    "sg:address":"6966 Killarney Dr",
    "sg:city":"Troy",
    "sg:classifiers":[
        {
            "category":"Professional",
            "subcategory":"Management & Consulting",
            "type":"Services"
        }
    ],
    "sg:phone":"+1 248 813 8737",
    "sg:postcode":"48098",
    "sg:province":"MI",
    "sg:tags":[
        "consultant",
        "resource",
        "human"
    ],
    "wof:name":"Human Asset Strategies",
    "wof:placetype":"venue"
},
  "geometry": {"coordinates":[-83.203503,42.617403],"type":"Point"}
}