{
  "type": "Feature",
  "properties": {
    "iso:country":"US",
    "sg:address":"2 Leonore Ave",
    "sg:city":"Mount Clemens",
    "sg:classifiers":[
        {
            "category":"Personal",
            "subcategory":"Beauty Salon",
            "type":"Services"
        }
    ],
    "sg:phone":"+1 586 463 6631",
    "sg:postcode":"48043",
    "sg:province":"MI",
    "sg:tags":[
        "shop"
    ],
    "wof:name":"Beauty Bell Salon",
    "wof:placetype":"venue"
},
  "geometry": {"coordinates":[-82.88051900000001,42.609913],"type":"Point"}
}