{
  "type": "Feature",
  "properties": {
    "iso:country":"US",
    "sg:address":"122 Main St",
    "sg:city":"East Jordan",
    "sg:classifiers":[
        {
            "category":"Shopping",
            "subcategory":"Clothing, Apparel, & Fashions",
            "type":"Retail Goods"
        }
    ],
    "sg:phone":"+1 231 536 2348",
    "sg:postcode":"49727",
    "sg:province":"MI",
    "sg:tags":[
        "sportswear"
    ],
    "wof:name":"E J Shop Brand Name Sportswear",
    "wof:placetype":"venue"
},
  "geometry": {"coordinates":[-85.127521,45.155115],"type":"Point"}
}