{
  "type": "Feature",
  "properties": {
    "iso:country":"US",
    "sg:address":"7830 Jackson Rd",
    "sg:city":"Ann Arbor",
    "sg:classifiers":[
        {
            "category":"Freight",
            "type":"Transportation"
        }
    ],
    "sg:phone":"+1 734 424 0802",
    "sg:postcode":"48103",
    "sg:province":"MI",
    "sg:tags":[
        "mover"
    ],
    "wof:name":"Frisbie Moving & Storage Co",
    "wof:placetype":"venue"
},
  "geometry": {"coordinates":[-83.882428,42.29413],"type":"Point"}
}