{
  "type": "Feature",
  "properties": {
    "iso:country":"US",
    "sg:address":"3762 Washington St",
    "sg:city":"Snover",
    "sg:phone":"+1 810 672 8907",
    "sg:postcode":"48472",
    "sg:province":"MI",
    "sg:tags":[
        "farm",
        "corn",
        "soybean"
    ],
    "wof:name":"John R Gillig",
    "wof:placetype":"venue"
},
  "geometry": {"coordinates":[-82.980181,43.461009],"type":"Point"}
}