{
  "type": "Feature",
  "properties": {
    "iso:country":"US",
    "sg:address":"45525 Grand River Ave",
    "sg:city":"Novi",
    "sg:classifiers":[
        {
            "category":"Manufacturing",
            "subcategory":"Printing",
            "type":"Manufacturing & Wholesale Goods"
        }
    ],
    "sg:phone":"+1 248 735 7600",
    "sg:postcode":"48374",
    "sg:province":"MI",
    "sg:tags":[
        "printer"
    ],
    "sg:website":"www.jpscolor.com",
    "wof:name":"Johnson's Printing & Mailing",
    "wof:placetype":"venue"
},
  "geometry": {"coordinates":[-83.504516,42.487194],"type":"Point"}
}