{
  "type": "Feature",
  "properties": {
    "iso:country":"US",
    "sg:address":"1013 Lions Park Dr",
    "sg:city":"St Joseph",
    "sg:classifiers":[
        {
            "category":"Professional",
            "subcategory":"Management & Consulting",
            "type":"Services"
        }
    ],
    "sg:phone":"+1 269 985 0134",
    "sg:postcode":"49085",
    "sg:province":"MI",
    "sg:tags":[
        "consultant",
        "business"
    ],
    "wof:name":"Jean Johnson & Assoc",
    "wof:placetype":"venue"
},
  "geometry": {"coordinates":[-86.490008,42.104156],"type":"Point"}
}