{
  "type": "Feature",
  "properties": {
    "iso:country":"US",
    "sg:address":"1100 E Michigan Ave",
    "sg:city":"Grayling",
    "sg:classifiers":[
        {
            "category":"Health Services",
            "subcategory":"Clinic",
            "type":"Services"
        }
    ],
    "sg:phone":"+1 989 348 0560",
    "sg:postcode":"49738",
    "sg:province":"MI",
    "wof:name":"Mercy Occupational Health Svc",
    "wof:placetype":"venue"
},
  "geometry": {"coordinates":[-84.707925,44.668271],"type":"Point"}
}