{
  "type": "Feature",
  "properties": {
    "iso:country":"US",
    "sg:address":"38800 Country Club Dr",
    "sg:city":"Farmington Hills",
    "sg:classifiers":[
        {
            "category":"Professional",
            "type":"Services"
        }
    ],
    "sg:phone":"+1 248 848 3700",
    "sg:postcode":"48331",
    "sg:province":"MI",
    "sg:tags":[
        "establishment"
    ],
    "wof:name":"ACI Intl",
    "wof:placetype":"venue"
},
  "geometry": {"coordinates":[-83.434865,42.494729],"type":"Point"}
}