{
  "type": "Feature",
  "properties": {
    "iso:country":"US",
    "sg:address":"1110 Carpenter Ave",
    "sg:city":"Iron Mountain",
    "sg:classifiers":[
        {
            "category":"Professional",
            "subcategory":"Computer Services",
            "type":"Services"
        }
    ],
    "sg:phone":"+1 906 774 4530",
    "sg:postcode":"49801",
    "sg:province":"MI",
    "sg:tags":[
        "repair"
    ],
    "wof:name":"JDL Computer Svc",
    "wof:placetype":"venue"
},
  "geometry": {"coordinates":[-88.068612,45.812427],"type":"Point"}
}