{
  "type": "Feature",
  "properties": {
    "iso:country":"US",
    "sg:address":"9472 Revere Dr",
    "sg:city":"Belleville",
    "sg:classifiers":[
        {
            "category":"Professional",
            "subcategory":"Computer Services",
            "type":"Services"
        }
    ],
    "sg:phone":"+1 734 697 4646",
    "sg:postcode":"48111",
    "sg:province":"MI",
    "sg:tags":[
        "design",
        "system"
    ],
    "wof:name":"Cadd-Mate",
    "wof:placetype":"venue"
},
  "geometry": {"coordinates":[-83.470544,42.231929],"type":"Point"}
}