{
  "type": "Feature",
  "properties": {
    "iso:country":"US",
    "sg:address":"5471 Mount Elliott St",
    "sg:city":"Detroit",
    "sg:classifiers":[
        {
            "category":"Shopping",
            "subcategory":"Party Supplies",
            "type":"Retail Goods"
        }
    ],
    "sg:phone":"+1 313 921 7000",
    "sg:postcode":"48211",
    "sg:province":"MI",
    "wof:name":"Motor City Party Store",
    "wof:placetype":"venue"
},
  "geometry": {"coordinates":[-83.030342,42.374285],"type":"Point"}
}