{
  "type": "Feature",
  "properties": {
    "iso:country":"US",
    "sg:address":"2596 Detroit Rd",
    "sg:city":"Niles",
    "sg:classifiers":[
        {
            "category":"Manufacturing",
            "subcategory":"Glass & Minerals",
            "type":"Manufacturing & Wholesale Goods"
        }
    ],
    "sg:phone":"+1 269 684 5960",
    "sg:postcode":"49120",
    "sg:province":"MI",
    "sg:tags":[
        "slag"
    ],
    "wof:name":"Kenneth Smith Inc",
    "wof:placetype":"venue"
},
  "geometry": {"coordinates":[-86.190789,41.829821],"type":"Point"}
}