{
  "type": "Feature",
  "properties": {
    "iso:country":"US",
    "sg:address":"319 Oak St",
    "sg:city":"Freeport",
    "sg:classifiers":[
        {
            "category":"Retail",
            "subcategory":"Auto Repair",
            "type":"Services"
        }
    ],
    "sg:phone":"+1 616 765 3179",
    "sg:postcode":"49325",
    "sg:province":"MI",
    "sg:tags":[
        "truck"
    ],
    "wof:name":"B J & Sons Trucking",
    "wof:placetype":"venue"
},
  "geometry": {"coordinates":[-85.311126,42.766998],"type":"Point"}
}