{
  "type": "Feature",
  "properties": {
    "iso:country":"US",
    "sg:address":"5300 Gateway Blvd",
    "sg:city":"Flint",
    "sg:classifiers":[
        {
            "category":"Personal",
            "subcategory":"Beauty Salon",
            "type":"Services"
        }
    ],
    "sg:phone":"+1 810 232 1772",
    "sg:postcode":"48507",
    "sg:province":"MI",
    "wof:name":"Gateway Center Spa",
    "wof:placetype":"venue"
},
  "geometry": {"coordinates":[-83.72042,42.946108],"type":"Point"}
}