{
  "type": "Feature",
  "properties": {
    "iso:country":"US",
    "sg:address":"3695 Delta Dr",
    "sg:city":"Traverse City",
    "sg:classifiers":[
        {
            "category":"Professional",
            "subcategory":"Accounting & Tax Preparation",
            "type":"Services"
        }
    ],
    "sg:phone":"+1 231 943 4720",
    "sg:postcode":"49684",
    "sg:province":"MI",
    "sg:tags":[
        "accountant"
    ],
    "wof:name":"Reliable Accounting & Tax Svc",
    "wof:placetype":"venue"
},
  "geometry": {"coordinates":[-85.65181699999999,44.680406],"type":"Point"}
}