{
  "type": "Feature",
  "properties": {
    "iso:country":"US",
    "sg:address":"217 W E St",
    "sg:city":"Iron Mountain",
    "sg:classifiers":[
        {
            "category":"Real Estate",
            "subcategory":"Real Estate Agent",
            "type":"Services"
        }
    ],
    "sg:phone":"+1 906 774 5766",
    "sg:postcode":"49801",
    "sg:province":"MI",
    "wof:name":"Wild River Land Management",
    "wof:placetype":"venue"
},
  "geometry": {"coordinates":[-88.06971299999999,45.814595],"type":"Point"}
}