{
  "type": "Feature",
  "properties": {
    "iso:country":"US",
    "sg:address":"8998 1st St",
    "sg:city":"Baroda",
    "sg:classifiers":[
        {
            "category":"Retail",
            "subcategory":"Auto Repair",
            "type":"Services"
        }
    ],
    "sg:phone":"+1 269 422 5051",
    "sg:postcode":"49101",
    "sg:province":"MI",
    "sg:tags":[
        "body",
        "automobile",
        "painting"
    ],
    "wof:name":"Touch Of Class Auto Body",
    "wof:placetype":"venue"
},
  "geometry": {"coordinates":[-86.485732,41.953627],"type":"Point"}
}