{
  "type": "Feature",
  "properties": {
    "iso:country":"US",
    "sg:address":"155 Laurin Ct",
    "sg:city":"Ann Arbor",
    "sg:classifiers":[
        {
            "category":"Professional",
            "subcategory":"Management & Consulting",
            "type":"Services"
        }
    ],
    "sg:phone":"+1 734 665 5996",
    "sg:postcode":"48105",
    "sg:province":"MI",
    "sg:tags":[
        "business"
    ],
    "wof:name":"Raymond R Reilly",
    "wof:placetype":"venue"
},
  "geometry": {"coordinates":[-83.687933,42.274166],"type":"Point"}
}