{
  "type": "Feature",
  "properties": {
    "iso:country":"US",
    "sg:address":"3959 W Oregon Rd",
    "sg:city":"Lapeer",
    "sg:classifiers":[
        {
            "category":"Shopping",
            "subcategory":"Hobbies, Toys, & Games",
            "type":"Retail Goods"
        }
    ],
    "sg:phone":"+1 810 664 3975",
    "sg:postcode":"48446",
    "sg:province":"MI",
    "wof:name":"Creative Memories",
    "wof:placetype":"venue"
},
  "geometry": {"coordinates":[-83.379104,43.056236],"type":"Point"}
}