{
  "type": "Feature",
  "properties": {
    "iso:country":"US",
    "sg:address":"645 Hughes Pt",
    "sg:city":"Harrison",
    "sg:classifiers":[
        {
            "category":"Building & Trades",
            "subcategory":"Construction",
            "type":"Services"
        }
    ],
    "sg:phone":"+1 989 539 7625",
    "sg:postcode":"48625",
    "sg:province":"MI",
    "sg:tags":[
        "concrete",
        "contractor"
    ],
    "wof:name":"Crown Concrete & Construction",
    "wof:placetype":"venue"
},
  "geometry": {"coordinates":[-84.79405300000001,44.023181],"type":"Point"}
}