{
  "type": "Feature",
  "properties": {
    "iso:country":"US",
    "sg:address":"9958 Miller Dr",
    "sg:city":"Galesburg",
    "sg:classifiers":[
        {
            "category":"Building & Trades",
            "subcategory":"Construction",
            "type":"Services"
        }
    ],
    "sg:phone":"+1 269 329 4829",
    "sg:postcode":"49053",
    "sg:province":"MI",
    "sg:tags":[
        "layer",
        "carpet"
    ],
    "wof:name":"Waldorf's Floor Covering Svc",
    "wof:placetype":"venue"
},
  "geometry": {"coordinates":[-85.440528,42.272674],"type":"Point"}
}