{
  "type": "Feature",
  "properties": {
    "iso:country":"US",
    "sg:address":"1780 E Lansing Dr",
    "sg:city":"East Lansing",
    "sg:classifiers":[
        {
            "category":"Health Services",
            "subcategory":"Chiropractor",
            "type":"Services"
        }
    ],
    "sg:phone":"+1 517 316 1277",
    "sg:postcode":"48823",
    "sg:province":"MI",
    "wof:name":"Backbone Chrprtic Hlth Wllness",
    "wof:placetype":"venue"
},
  "geometry": {"coordinates":[-84.45216499999999,42.747892],"type":"Point"}
}