{
  "type": "Feature",
  "properties": {
    "iso:country":"US",
    "sg:address":"1250 Larch Dr",
    "sg:city":"Waterford",
    "sg:classifiers":[
        {
            "category":"Professional",
            "type":"Services"
        }
    ],
    "sg:phone":"+1 248 683 9337",
    "sg:postcode":"48328",
    "sg:province":"MI",
    "wof:name":"Sunshine Surface Care",
    "wof:placetype":"venue"
},
  "geometry": {"coordinates":[-83.34429,42.620956],"type":"Point"}
}