{
  "type": "Feature",
  "properties": {
    "iso:country":"US",
    "sg:address":"32125 Block St",
    "sg:city":"Garden City",
    "sg:classifiers":[
        {
            "category":"Building & Trades",
            "subcategory":"Construction",
            "type":"Services"
        }
    ],
    "sg:phone":"+1 734 422 6400",
    "sg:postcode":"48135",
    "sg:province":"MI",
    "sg:tags":[
        "contractor"
    ],
    "wof:name":"Sheridan Construction Inc",
    "wof:placetype":"venue"
},
  "geometry": {"coordinates":[-83.358299,42.329399],"type":"Point"}
}