{
  "type": "Feature",
  "properties": {
    "iso:country":"US",
    "sg:address":"20909 Whitlock St",
    "sg:city":"Farmington Hills",
    "sg:classifiers":[
        {
            "category":"Organizations",
            "subcategory":"Religious Organization",
            "type":"Services"
        }
    ],
    "sg:phone":"+1 248 477 8188",
    "sg:postcode":"48336",
    "sg:province":"MI",
    "sg:tags":[
        "church"
    ],
    "wof:name":"Good Shepherd Baptist Church",
    "wof:placetype":"venue"
},
  "geometry": {"coordinates":[-83.366907,42.441896],"type":"Point"}
}