{
  "type": "Feature",
  "properties": {
    "iso:country":"US",
    "sg:address":"19311 Augusta Dr",
    "sg:city":"Livonia",
    "sg:classifiers":[
        {
            "category":"Building & Trades",
            "subcategory":"Construction",
            "type":"Services"
        }
    ],
    "sg:phone":"+1 734 462 3985",
    "sg:postcode":"48152",
    "sg:province":"MI",
    "sg:tags":[
        "contractor"
    ],
    "wof:name":"T A Ceramic Tile & Marble Co",
    "wof:placetype":"venue"
},
  "geometry": {"coordinates":[-83.41247300000001,42.427279],"type":"Point"}
}