{
  "type": "Feature",
  "properties": {
    "iso:country":"US",
    "sg:address":"7208 Grand River Rd",
    "sg:city":"Brighton",
    "sg:classifiers":[
        {
            "category":"Retail",
            "subcategory":"Auto Rental",
            "type":"Services"
        }
    ],
    "sg:phone":"+1 810 227 3530",
    "sg:postcode":"48114",
    "sg:province":"MI",
    "sg:tags":[
        "automobile"
    ],
    "wof:name":"Conely Rent-A-Car",
    "wof:placetype":"venue"
},
  "geometry": {"coordinates":[-83.80915,42.567557],"type":"Point"}
}