{
  "type": "Feature",
  "properties": {
    "iso:country":"US",
    "sg:address":"217 S Monroe St",
    "sg:city":"Bay City",
    "sg:classifiers":[
        {
            "category":"Education",
            "subcategory":"School",
            "type":"Public Place"
        }
    ],
    "sg:phone":"+1 989 892 2533",
    "sg:postcode":"48708",
    "sg:province":"MI",
    "sg:tags":[
        "organization",
        "religious"
    ],
    "wof:name":"All Saints Central High School",
    "wof:placetype":"venue"
},
  "geometry": {"coordinates":[-83.884585,43.587852],"type":"Point"}
}