{
  "type": "Feature",
  "properties": {
    "iso:country":"US",
    "sg:address":"22001 Allen Rd",
    "sg:city":"Woodhaven",
    "sg:classifiers":[
        {
            "category":"Health Services",
            "subcategory":"Dentist",
            "type":"Services"
        }
    ],
    "sg:phone":"+1 734 692 1920",
    "sg:postcode":"48183",
    "sg:province":"MI",
    "sg:tags":[
        "orthodontist"
    ],
    "sg:website":"www.greatexpressions.com",
    "wof:name":"Great Expressions Dental Centers",
    "wof:placetype":"venue"
},
  "geometry": {"coordinates":[-83.22626,42.148099],"type":"Point"}
}