{
  "type": "Feature",
  "properties": {
    "iso:country":"US",
    "sg:address":"23965 Novi Rd",
    "sg:city":"Novi",
    "sg:classifiers":[
        {
            "category":"Personal",
            "subcategory":"Beauty Salon",
            "type":"Services"
        }
    ],
    "sg:phone":"+1 248 349 9925",
    "sg:postcode":"48375",
    "sg:province":"MI",
    "sg:tags":[
        "shop"
    ],
    "wof:name":"Pamela's Salon",
    "wof:placetype":"venue"
},
  "geometry": {"coordinates":[-83.474752,42.465248],"type":"Point"}
}