{
  "type": "Feature",
  "properties": {
    "iso:country":"US",
    "sg:address":"5197 Klug Rd",
    "sg:city":"Ruth",
    "sg:classifiers":[
        {
            "category":"Farming",
            "subcategory":"Livestock Farm",
            "type":"Manufacturing & Wholesale Goods"
        }
    ],
    "sg:phone":"+1 989 864 3295",
    "sg:postcode":"48470",
    "sg:province":"MI",
    "sg:tags":[
        "beef",
        "feedlot",
        "cattle"
    ],
    "wof:name":"Douglas Messing",
    "wof:placetype":"venue"
},
  "geometry": {"coordinates":[-82.679588,43.694863],"type":"Point"}
}