{
  "type": "Feature",
  "properties": {
    "iso:country":"US",
    "sg:address":"15902 Venice Ave",
    "sg:city":"Clinton Township",
    "sg:classifiers":[
        {
            "category":"Freight",
            "type":"Transportation"
        }
    ],
    "sg:phone":"+1 586 791 1579",
    "sg:postcode":"48035",
    "sg:province":"MI",
    "sg:tags":[
        "operator",
        "local",
        "trucking"
    ],
    "wof:name":"Ylli Trucking Corp",
    "wof:placetype":"venue"
},
  "geometry": {"coordinates":[-82.96159900000001,42.559892],"type":"Point"}
}