{
  "type": "Feature",
  "properties": {
    "iso:country":"US",
    "sg:address":"30850 Telegraph Rd",
    "sg:city":"Bingham Farms",
    "sg:classifiers":[
        {
            "category":"Professional",
            "subcategory":"Lawyer & Legal Services",
            "type":"Services"
        }
    ],
    "sg:phone":"+1 248 593 0395",
    "sg:postcode":"48025",
    "sg:province":"MI",
    "sg:tags":[
        "attorney"
    ],
    "wof:name":"Herman Richard A PC",
    "wof:placetype":"venue"
},
  "geometry": {"coordinates":[-83.2854,42.514599],"type":"Point"}
}