{
  "type": "Feature",
  "properties": {
    "iso:country":"US",
    "sg:address":"17708 W 13 Mile Rd",
    "sg:city":"Beverly Hills",
    "sg:classifiers":[
        {
            "category":"Shopping",
            "subcategory":"Hobbies, Toys, & Games",
            "type":"Retail Goods"
        }
    ],
    "sg:phone":"+1 248 258 1510",
    "sg:postcode":"48025",
    "sg:province":"MI",
    "sg:tags":[
        "shop",
        "hobby"
    ],
    "sg:website":"www.gamestop.com",
    "wof:name":"Gamestop",
    "wof:placetype":"venue"
},
  "geometry": {"coordinates":[-83.222281,42.517233],"type":"Point"}
}