{
  "type": "Feature",
  "properties": {
    "iso:country":"US",
    "sg:address":"110 N Main St",
    "sg:city":"Mount Pleasant",
    "sg:classifiers":[
        {
            "category":"Restaurant",
            "type":"Food & Drink"
        }
    ],
    "sg:menulink":"http://www.allmenus.com/mi/mount-pleasant/236059-pisanellos-pizza/menu/",
    "sg:phone":"+1 989 773 9906",
    "sg:postcode":"48858",
    "sg:province":"MI",
    "sg:tags":[
        "american",
        "pizza"
    ],
    "wof:name":"Pisanello's Pizza",
    "wof:placetype":"venue"
},
  "geometry": {"coordinates":[-84.776601,43.604525],"type":"Point"}
}