{
  "type": "Feature",
  "properties": {
    "iso:country":"US",
    "sg:address":"6551 Main St",
    "sg:city":"Caseville",
    "sg:classifiers":[
        {
            "category":"Freight",
            "type":"Transportation"
        }
    ],
    "sg:phone":"+1 989 856 7010",
    "sg:postcode":"48725",
    "sg:province":"MI",
    "sg:tags":[
        "dock"
    ],
    "wof:name":"Fisherman's Wharf",
    "wof:placetype":"venue"
},
  "geometry": {"coordinates":[-83.27281000000001,43.943577],"type":"Point"}
}