{
  "type": "Feature",
  "properties": {
    "iso:country":"US",
    "sg:address":"41690 Ford Rd",
    "sg:city":"Canton",
    "sg:classifiers":[
        {
            "category":"Home & Garden",
            "subcategory":"Household Appliances",
            "type":"Retail Goods"
        }
    ],
    "sg:phone":"+1 734 981 7780",
    "sg:postcode":"48187",
    "sg:province":"MI",
    "sg:tags":[
        "repair"
    ],
    "wof:name":"A B C Appliance Warehouse",
    "wof:placetype":"venue"
},
  "geometry": {"coordinates":[-83.451599,42.323002],"type":"Point"}
}