{
  "type": "Feature",
  "properties": {
    "iso:country":"US",
    "sg:address":"23009 E Main St",
    "sg:city":"Armada",
    "sg:classifiers":[
        {
            "category":"Restaurant",
            "type":"Food & Drink"
        }
    ],
    "sg:menulink":"http://www.allmenus.com/mi/armada/146212-subway/menu/",
    "sg:phone":"+1 586 784 3006",
    "sg:postcode":"48005",
    "sg:province":"MI",
    "sg:tags":[
        "american",
        "sandwich"
    ],
    "wof:name":"Subway",
    "wof:placetype":"venue"
},
  "geometry": {"coordinates":[-82.88466699999999,42.844028],"type":"Point"}
}