{
  "type": "Feature",
  "properties": {
    "iso:country":"US",
    "sg:address":"1928 Colgrove Ave",
    "sg:city":"Kalamazoo",
    "sg:classifiers":[
        {
            "category":"Real Estate",
            "subcategory":"Real Estate Operator",
            "type":"Services"
        }
    ],
    "sg:phone":"+1 269 343 9745",
    "sg:postcode":"49048",
    "sg:province":"MI",
    "sg:tags":[
        "building",
        "apartment"
    ],
    "wof:name":"Spring Lake Apartments",
    "wof:placetype":"venue"
},
  "geometry": {"coordinates":[-85.555114,42.308721],"type":"Point"}
}