{
  "type": "Feature",
  "properties": {
    "iso:country":"US",
    "sg:address":"22800 Kelly Rd",
    "sg:city":"Eastpointe",
    "sg:classifiers":[
        {
            "category":"Real Estate",
            "subcategory":"Real Estate Agent",
            "type":"Services"
        }
    ],
    "sg:phone":"+1 586 774 0702",
    "sg:postcode":"48021",
    "sg:province":"MI",
    "sg:tags":[
        "management"
    ],
    "wof:name":"Oliver Management & Leasing Co",
    "wof:placetype":"venue"
},
  "geometry": {"coordinates":[-82.926557,42.467048],"type":"Point"}
}