{
  "type": "Feature",
  "properties": {
    "iso:country":"US",
    "sg:address":"144 S 29 Rd",
    "sg:city":"Cadillac",
    "sg:classifiers":[
        {
            "category":"Building & Trades",
            "subcategory":"Construction",
            "type":"Services"
        }
    ],
    "sg:phone":"+1 231 779 0556",
    "sg:postcode":"49601",
    "sg:province":"MI",
    "sg:tags":[
        "general",
        "contractor"
    ],
    "wof:name":"Greeley Construction",
    "wof:placetype":"venue"
},
  "geometry": {"coordinates":[-85.539918,44.337905],"type":"Point"}
}