{
  "type": "Feature",
  "properties": {
    "iso:country":"US",
    "sg:address":"6421 Lucas Rd",
    "sg:city":"Flint",
    "sg:classifiers":[
        {
            "category":"Professional",
            "subcategory":"Employment Agencies",
            "type":"Services"
        }
    ],
    "sg:phone":"+1 810 736 7376",
    "sg:postcode":"48506",
    "sg:province":"MI",
    "sg:tags":[
        "medical",
        "help"
    ],
    "wof:name":"Prn Nurse Staffing LLC",
    "wof:placetype":"venue"
},
  "geometry": {"coordinates":[-83.58004699999999,43.098896],"type":"Point"}
}