{
  "type": "Feature",
  "properties": {
    "iso:country":"US",
    "sg:address":"2036 Hyde Park Rd",
    "sg:city":"Detroit",
    "sg:classifiers":[
        {
            "category":"Real Estate",
            "subcategory":"Real Estate Operator",
            "type":"Services"
        }
    ],
    "sg:phone":"+1 313 259 6642",
    "sg:postcode":"48207",
    "sg:province":"MI",
    "sg:tags":[
        "apartment"
    ],
    "wof:name":"Hyde Park Townhouses",
    "wof:placetype":"venue"
},
  "geometry": {"coordinates":[-83.030502,42.344299],"type":"Point"}
}