{
  "type": "Feature",
  "properties": {
    "iso:country":"US",
    "sg:address":"21700 Greenfield Rd",
    "sg:city":"Oak Park",
    "sg:classifiers":[
        {
            "category":"Building & Trades",
            "subcategory":"Landscaping Services",
            "type":"Services"
        }
    ],
    "sg:phone":"+1 313 865 0190",
    "sg:postcode":"48237",
    "sg:province":"MI",
    "sg:tags":[
        "lawn",
        "maintenance",
        "grounds"
    ],
    "wof:name":"Benjamin Brothers",
    "wof:placetype":"venue"
},
  "geometry": {"coordinates":[-83.20080799999999,42.452886],"type":"Point"}
}