{
  "type": "Feature",
  "properties": {
    "iso:country":"US",
    "sg:address":"9111 Summit Ave NE",
    "sg:city":"Rockford",
    "sg:classifiers":[
        {
            "category":"Professional",
            "subcategory":"Business Services",
            "type":"Services"
        }
    ],
    "sg:phone":"+1 616 866 3416",
    "sg:postcode":"49341",
    "sg:province":"MI",
    "sg:tags":[
        "water",
        "treatment"
    ],
    "sg:website":"www.hartwater.com",
    "wof:name":"Hart Water Co",
    "wof:placetype":"venue"
},
  "geometry": {"coordinates":[-85.565909,43.129844],"type":"Point"}
}