{
  "type": "Feature",
  "properties": {
    "iso:country":"US",
    "sg:address":"35651 Briar Ridge Ln",
    "sg:city":"Farmington",
    "sg:classifiers":[
        {
            "category":"Professional",
            "subcategory":"Business Services",
            "type":"Services"
        }
    ],
    "sg:phone":"+1 248 476 4242",
    "sg:postcode":"48335",
    "sg:province":"MI",
    "sg:tags":[
        "notary",
        "public"
    ],
    "wof:name":"Ronald J Briggs",
    "wof:placetype":"venue"
},
  "geometry": {"coordinates":[-83.39974599999999,42.468296],"type":"Point"}
}