{
  "type": "Feature",
  "properties": {
    "iso:country":"US",
    "sg:address":"10315 Grand River Rd",
    "sg:city":"Brighton",
    "sg:classifiers":[
        {
            "category":"Real Estate",
            "subcategory":"Real Estate Services",
            "type":"Services"
        }
    ],
    "sg:phone":"+1 810 227 1733",
    "sg:postcode":"48116",
    "sg:province":"MI",
    "sg:tags":[
        "abstract",
        "title"
    ],
    "wof:name":"Landmark Title Services",
    "wof:placetype":"venue"
},
  "geometry": {"coordinates":[-83.751531,42.519378],"type":"Point"}
}