{
  "type": "Feature",
  "properties": {
    "iso:country":"US",
    "sg:address":"1130 Cole Rd",
    "sg:city":"Monroe",
    "sg:classifiers":[
        {
            "category":"Wholesale",
            "subcategory":"Photographic Equipment",
            "type":"Manufacturing & Wholesale Goods"
        }
    ],
    "sg:phone":"+1 734 242 2614",
    "sg:postcode":"48162",
    "sg:province":"MI",
    "sg:tags":[
        "identification"
    ],
    "wof:name":"PALS Across America",
    "wof:placetype":"venue"
},
  "geometry": {"coordinates":[-83.36649,41.939063],"type":"Point"}
}