{
  "type": "Feature",
  "properties": {
    "iso:country":"US",
    "sg:address":"8 W Walton Ave",
    "sg:city":"Muskegon",
    "sg:classifiers":[
        {
            "category":"Real Estate",
            "subcategory":"Real Estate Services",
            "type":"Services"
        }
    ],
    "sg:phone":"+1 231 722 6021",
    "sg:postcode":"49440",
    "sg:province":"MI",
    "sg:tags":[
        "company",
        "title"
    ],
    "wof:name":"Land America Transnation Title",
    "wof:placetype":"venue"
},
  "geometry": {"coordinates":[-86.244741,43.235255],"type":"Point"}
}