{
  "type": "Feature",
  "properties": {
    "iso:country":"US",
    "sg:address":"311 Morenci Ave",
    "sg:city":"Mio",
    "sg:classifiers":[
        {
            "category":"Government",
            "subcategory":"Office",
            "type":"Public Place"
        }
    ],
    "sg:phone":"+1 989 826 1109",
    "sg:postcode":"48647",
    "sg:province":"MI",
    "sg:tags":[
        "county"
    ],
    "wof:name":"Oscoda County Clerk",
    "wof:placetype":"venue"
},
  "geometry": {"coordinates":[-84.12992,44.650625],"type":"Point"}
}