{
  "type": "Feature",
  "properties": {
    "iso:country":"US",
    "sg:address":"1139 US Hwy 41",
    "sg:city":"Bark River",
    "sg:classifiers":[
        {
            "category":"Shopping",
            "subcategory":"Gifts & Souvenirs",
            "type":"Retail Goods"
        }
    ],
    "sg:phone":"+1 906 466 7673",
    "sg:postcode":"49807",
    "sg:province":"MI",
    "sg:tags":[
        "shop"
    ],
    "wof:name":"Rose Floral & Gifts",
    "wof:placetype":"venue"
},
  "geometry": {"coordinates":[-87.32237000000001,45.704761],"type":"Point"}
}