{
  "type": "Feature",
  "properties": {
    "iso:country":"US",
    "sg:address":"1725 Bunting Rd",
    "sg:city":"Jackson",
    "sg:classifiers":[
        {
            "category":"Social Services",
            "subcategory":"Adult Care",
            "type":"Services"
        }
    ],
    "sg:phone":"+1 517 750 3769",
    "sg:postcode":"49201",
    "sg:province":"MI",
    "sg:tags":[
        "residential"
    ],
    "wof:name":"Renaissance Community Homes",
    "wof:placetype":"venue"
},
  "geometry": {"coordinates":[-84.49741299999999,42.235765],"type":"Point"}
}