{
  "type": "Feature",
  "properties": {
    "iso:country":"US",
    "sg:address":"2316 Lawndale St",
    "sg:city":"Detroit",
    "sg:classifiers":[
        {
            "category":"Government",
            "subcategory":"Office",
            "type":"Public Place"
        }
    ],
    "sg:phone":"+1 313 849 4105",
    "sg:postcode":"48209",
    "sg:province":"MI",
    "sg:tags":[
        "government-united",
        "state"
    ],
    "wof:name":"Southwest Housing Corp",
    "wof:placetype":"venue"
},
  "geometry": {"coordinates":[-83.13281000000001,42.309343],"type":"Point"}
}