{
  "type": "Feature",
  "properties": {
    "iso:country":"US",
    "sg:address":"4261 Park Rd",
    "sg:city":"Ann Arbor",
    "sg:classifiers":[
        {
            "category":"Banks & Credit Unions",
            "subcategory":"Investment Brokerage",
            "type":"Services"
        }
    ],
    "sg:phone":"+1 734 663 1611",
    "sg:postcode":"48103",
    "sg:province":"MI",
    "sg:tags":[
        "security"
    ],
    "wof:name":"Sigma Finacial",
    "wof:placetype":"venue"
},
  "geometry": {"coordinates":[-83.81455200000001,42.28468],"type":"Point"}
}