{
  "type": "Feature",
  "properties": {
    "iso:country":"US",
    "sg:address":"27343 Cherry Hill Rd",
    "sg:city":"Inkster",
    "sg:classifiers":[
        {
            "category":"Shopping",
            "subcategory":"Department Store",
            "type":"Retail Goods"
        }
    ],
    "sg:phone":"+1 313 274 8001",
    "sg:postcode":"48141",
    "sg:province":"MI",
    "sg:website":"www.familydollar.com",
    "wof:name":"Family Dollar Store Inc",
    "wof:placetype":"venue"
},
  "geometry": {"coordinates":[-83.308449,42.311737],"type":"Point"}
}