{
  "type": "Feature",
  "properties": {
    "iso:country":"US",
    "sg:address":"16901 Michigan Ave",
    "sg:city":"Dearborn",
    "sg:classifiers":[
        {
            "category":"Professional",
            "subcategory":"Computer Services",
            "type":"Services"
        }
    ],
    "sg:phone":"+1 313 336 7700",
    "sg:postcode":"48126",
    "sg:province":"MI",
    "sg:tags":[
        "datum"
    ],
    "wof:name":"ADP",
    "wof:placetype":"venue"
},
  "geometry": {"coordinates":[-83.2132,42.311062],"type":"Point"}
}