{
  "type": "Feature",
  "properties": {
    "iso:country":"US",
    "sg:address":"8623 Schultz Rd",
    "sg:city":"Hubbard Lake",
    "sg:classifiers":[
        {
            "category":"Building & Trades",
            "subcategory":"Construction",
            "type":"Services"
        }
    ],
    "sg:phone":"+1 989 727 4094",
    "sg:postcode":"49747",
    "sg:province":"MI",
    "sg:tags":[
        "excavating",
        "contractor"
    ],
    "wof:name":"A & W Excavating",
    "wof:placetype":"venue"
},
  "geometry": {"coordinates":[-83.624487,44.946114],"type":"Point"}
}