{
  "type": "Feature",
  "properties": {
    "iso:country":"US",
    "sg:address":"618 Unionville Rd",
    "sg:city":"Sebewaing",
    "sg:classifiers":[
        {
            "category":"Personal",
            "subcategory":"Beauty Salon",
            "type":"Services"
        }
    ],
    "sg:phone":"+1 989 883 2250",
    "sg:postcode":"48759",
    "sg:province":"MI",
    "sg:tags":[
        "shop"
    ],
    "wof:name":"Salon 25",
    "wof:placetype":"venue"
},
  "geometry": {"coordinates":[-83.445759,43.726],"type":"Point"}
}