{
  "type": "Feature",
  "properties": {
    "iso:country":"US",
    "sg:address":"1074 Fairfax St",
    "sg:city":"Flint",
    "sg:classifiers":[
        {
            "category":"Personal",
            "subcategory":"Barber",
            "type":"Services"
        }
    ],
    "sg:phone":"+1 810 789 8007",
    "sg:postcode":"48505",
    "sg:province":"MI",
    "sg:tags":[
        "shop"
    ],
    "wof:name":"J W Barber Q A Barber Tr",
    "wof:placetype":"venue"
},
  "geometry": {"coordinates":[-83.68613499999999,43.061852],"type":"Point"}
}