{
  "type": "Feature",
  "properties": {
    "iso:country":"US",
    "sg:address":"220 E Washington St",
    "sg:city":"St Louis",
    "sg:classifiers":[
        {
            "category":"Retail",
            "subcategory":"Car Wash",
            "type":"Services"
        }
    ],
    "sg:phone":"+1 989 681 0771",
    "sg:postcode":"48880",
    "sg:province":"MI",
    "sg:tags":[
        "automobile",
        "detail",
        "clean"
    ],
    "wof:name":"Brandon's Auto Detailing",
    "wof:placetype":"venue"
},
  "geometry": {"coordinates":[-84.60534699999999,43.407796],"type":"Point"}
}