{
  "type": "Feature",
  "properties": {
    "iso:country":"US",
    "sg:address":"23611 Lauren Ave",
    "sg:city":"Warren",
    "sg:classifiers":[
        {
            "category":"Arts & Performance",
            "subcategory":"Theater",
            "type":"Entertainment"
        }
    ],
    "sg:phone":"+1 586 775 3472",
    "sg:postcode":"48089",
    "sg:province":"MI",
    "sg:tags":[
        "music",
        "live",
        "bureau"
    ],
    "wof:name":"Triple AAA Entertainment",
    "wof:placetype":"venue"
},
  "geometry": {"coordinates":[-82.97544499999999,42.469244],"type":"Point"}
}