{
  "type": "Feature",
  "properties": {
    "iso:country":"US",
    "sg:address":"1071 N Ballenger Hwy",
    "sg:city":"Flint",
    "sg:classifiers":[
        {
            "category":"Real Estate",
            "subcategory":"Real Estate Operator",
            "type":"Services"
        }
    ],
    "sg:phone":"+1 810 232 9821",
    "sg:postcode":"48504",
    "sg:province":"MI",
    "sg:tags":[
        "building",
        "parks"
    ],
    "wof:name":"Park Plaza Medical Building",
    "wof:placetype":"venue"
},
  "geometry": {"coordinates":[-83.734865,43.018323],"type":"Point"}
}