{
  "type": "Feature",
  "properties": {
    "iso:country":"US",
    "sg:address":"26777 Central Park Blvd",
    "sg:city":"Southfield",
    "sg:classifiers":[
        {
            "category":"Professional",
            "subcategory":"Lawyer & Legal Services",
            "type":"Services"
        }
    ],
    "sg:phone":"+1 248 799 8260",
    "sg:postcode":"48076",
    "sg:province":"MI",
    "wof:name":"Perry C Kenneth Jr Atty",
    "wof:placetype":"venue"
},
  "geometry": {"coordinates":[-83.244698,42.486198],"type":"Point"}
}