{
  "type": "Feature",
  "properties": {
    "iso:country":"US",
    "sg:address":"520 Union St",
    "sg:city":"Saginaw",
    "sg:classifiers":[
        {
            "category":"Retail",
            "subcategory":"Car Wash",
            "type":"Services"
        }
    ],
    "sg:phone":"+1 989 755 7002",
    "sg:postcode":"48602",
    "sg:province":"MI",
    "sg:tags":[
        "automobile",
        "detail",
        "clean"
    ],
    "wof:name":"Miracle Wash & Detail",
    "wof:placetype":"venue"
},
  "geometry": {"coordinates":[-83.950169,43.434182],"type":"Point"}
}