{
  "type": "Feature",
  "properties": {
    "iso:country":"US",
    "sg:address":"672 Baldwin St",
    "sg:city":"Jenison",
    "sg:classifiers":[
        {
            "category":"Food & Beverages",
            "subcategory":"Bakery",
            "type":"Retail Goods"
        }
    ],
    "sg:phone":"+1 616 457 5070",
    "sg:postcode":"49428",
    "sg:province":"MI",
    "wof:name":"Jenison Donut & Coffee Shop",
    "wof:placetype":"venue"
},
  "geometry": {"coordinates":[-85.797978,42.907112],"type":"Point"}
}