{
  "type": "Feature",
  "properties": {
    "iso:country":"US",
    "sg:address":"34346 Utica Rd",
    "sg:city":"Fraser",
    "sg:classifiers":[
        {
            "category":"Shopping",
            "subcategory":"Used Merchandise",
            "type":"Retail Goods"
        }
    ],
    "sg:phone":"+1 586 415 4495",
    "sg:postcode":"48026",
    "sg:province":"MI",
    "sg:tags":[
        "shop",
        "consignment"
    ],
    "wof:name":"Clothes Exchange",
    "wof:placetype":"venue"
},
  "geometry": {"coordinates":[-82.957397,42.546204],"type":"Point"}
}