{
  "type": "Feature",
  "properties": {
    "iso:country":"US",
    "sg:address":"2328 US Hwy 12",
    "sg:city":"Niles",
    "sg:classifiers":[
        {
            "category":"Restaurant",
            "type":"Food & Drink"
        }
    ],
    "sg:phone":"+1 269 687 6665",
    "sg:postcode":"49120",
    "sg:province":"MI",
    "wof:name":"Country Cafe",
    "wof:placetype":"venue"
},
  "geometry": {"coordinates":[-86.193298,41.782703],"type":"Point"}
}