{
  "type": "Feature",
  "properties": {
    "iso:country":"US",
    "sg:address":"4707 River Rd",
    "sg:city":"Manistee",
    "sg:classifiers":[
        {
            "category":"Farming",
            "subcategory":"Livestock Farm",
            "type":"Manufacturing & Wholesale Goods"
        }
    ],
    "sg:phone":"+1 231 723 6842",
    "sg:postcode":"49660",
    "sg:province":"MI",
    "sg:tags":[
        "beef",
        "feedlot",
        "cattle"
    ],
    "wof:name":"Todd Carter Farm",
    "wof:placetype":"venue"
},
  "geometry": {"coordinates":[-86.211264,44.274144],"type":"Point"}
}