{
  "type": "Feature",
  "properties": {
    "iso:country":"US",
    "sg:address":"130 S Main St",
    "sg:city":"Brooklyn",
    "sg:classifiers":[
        {
            "category":"Personal",
            "type":"Services"
        }
    ],
    "sg:phone":"+1 517 592 2989",
    "sg:postcode":"49230",
    "sg:province":"MI",
    "sg:tags":[
        "therapist",
        "massage"
    ],
    "wof:name":"Natural Touch",
    "wof:placetype":"venue"
},
  "geometry": {"coordinates":[-84.247986,42.105675],"type":"Point"}
}