{
  "type": "Feature",
  "properties": {
    "iso:country":"US",
    "sg:address":"640 Clement Rd",
    "sg:city":"Lansing",
    "sg:classifiers":[
        {
            "category":"Professional",
            "subcategory":"Business Services",
            "type":"Services"
        }
    ],
    "sg:phone":"+1 517 484 9449",
    "sg:postcode":"48917",
    "sg:province":"MI",
    "sg:tags":[
        "embroidery"
    ],
    "wof:name":"Patches Plus Inc",
    "wof:placetype":"venue"
},
  "geometry": {"coordinates":[-84.60059699999999,42.729354],"type":"Point"}
}