{
  "type": "Feature",
  "properties": {
    "iso:country":"US",
    "sg:address":"7107 Dixie Hwy",
    "sg:city":"Clarkston",
    "sg:classifiers":[
        {
            "category":"Insurance",
            "subcategory":"Insurance Agent",
            "type":"Services"
        }
    ],
    "sg:phone":"+1 248 620 5225",
    "sg:postcode":"48346",
    "sg:province":"MI",
    "wof:name":"Pat Toohey Agency",
    "wof:placetype":"venue"
},
  "geometry": {"coordinates":[-83.427438,42.72416],"type":"Point"}
}