{
  "type": "Feature",
  "properties": {
    "iso:country":"US",
    "sg:address":"5819 Joshua St",
    "sg:city":"Lansing",
    "sg:classifiers":[
        {
            "category":"Building & Trades",
            "subcategory":"Construction",
            "type":"Services"
        }
    ],
    "sg:phone":"+1 517 394 6986",
    "sg:postcode":"48911",
    "sg:province":"MI",
    "sg:tags":[
        "floor",
        "installation",
        "covering"
    ],
    "wof:name":"Central Floor Covering",
    "wof:placetype":"venue"
},
  "geometry": {"coordinates":[-84.54289199999999,42.673852],"type":"Point"}
}