{
  "type": "Feature",
  "properties": {
    "iso:country":"US",
    "sg:address":"5510 Jordan St",
    "sg:city":"Allendale",
    "sg:classifiers":[
        {
            "category":"Professional",
            "subcategory":"Management & Consulting",
            "type":"Services"
        }
    ],
    "sg:phone":"+1 616 892 4565",
    "sg:postcode":"49401",
    "sg:province":"MI",
    "sg:tags":[
        "business"
    ],
    "wof:name":"Hoover Consulting Inc",
    "wof:placetype":"venue"
},
  "geometry": {"coordinates":[-85.921204,42.969113],"type":"Point"}
}