{
  "type": "Feature",
  "properties": {
    "iso:country":"US",
    "sg:address":"13161 Dix Toledo Rd",
    "sg:city":"Southgate",
    "sg:classifiers":[
        {
            "category":"Bakery",
            "type":"Food & Drink"
        }
    ],
    "sg:phone":"+1 734 285 8095",
    "sg:postcode":"48195",
    "sg:province":"MI",
    "wof:name":"C P J's Bakery",
    "wof:placetype":"venue"
},
  "geometry": {"coordinates":[-83.19499999999999,42.212299],"type":"Point"}
}