{
  "type": "Feature",
  "properties": {
    "iso:country":"US",
    "sg:address":"131 S Mechanic St",
    "sg:city":"Jackson",
    "sg:classifiers":[
        {
            "category":"Personal",
            "type":"Services"
        }
    ],
    "sg:phone":"+1 517 784 3488",
    "sg:postcode":"49201",
    "sg:province":"MI",
    "sg:tags":[
        "program",
        "physical",
        "exercise",
        "fitness"
    ],
    "wof:name":"Body Fitness Exp 30 Minute",
    "wof:placetype":"venue"
},
  "geometry": {"coordinates":[-84.405806,42.245619],"type":"Point"}
}