{
  "type": "Feature",
  "properties": {
    "iso:country":"US",
    "sg:address":"5300 Heron Cove",
    "sg:city":"Beaverton",
    "sg:classifiers":[
        {
            "category":"Building & Trades",
            "subcategory":"Cleaning & Sanitation",
            "type":"Services"
        }
    ],
    "sg:phone":"+1 989 435 7666",
    "sg:postcode":"48612",
    "sg:province":"MI",
    "sg:tags":[
        "window"
    ],
    "wof:name":"Mid Michigan Win Clg Pwr Wshg",
    "wof:placetype":"venue"
},
  "geometry": {"coordinates":[-84.36470300000001,43.833877],"type":"Point"}
}