{
  "type": "Feature",
  "properties": {
    "iso:country":"US",
    "sg:address":"11554 Ware Rd",
    "sg:city":"Lowell",
    "sg:classifiers":[
        {
            "category":"Retail",
            "subcategory":"Auto Repair",
            "type":"Services"
        }
    ],
    "sg:phone":"+1 616 897 6018",
    "sg:postcode":"49331",
    "sg:province":"MI",
    "sg:tags":[
        "small",
        "engine"
    ],
    "wof:name":"B E S Small Engine Repair",
    "wof:placetype":"venue"
},
  "geometry": {"coordinates":[-85.30371,42.914929],"type":"Point"}
}