{
  "type": "Feature",
  "properties": {
    "iso:country":"US",
    "sg:address":"15256 Levan Rd",
    "sg:city":"Livonia",
    "sg:classifiers":[
        {
            "category":"Health Services",
            "subcategory":"Doctor",
            "type":"Services"
        }
    ],
    "sg:phone":"+1 734 542 9300",
    "sg:postcode":"48154",
    "sg:province":"MI",
    "sg:tags":[
        "medical"
    ],
    "wof:name":"Colleen D O Hartwig",
    "wof:placetype":"venue"
},
  "geometry": {"coordinates":[-83.402817,42.395146],"type":"Point"}
}