{
  "type": "Feature",
  "properties": {
    "iso:country":"US",
    "sg:address":"627 E Maple Rd",
    "sg:city":"Troy",
    "sg:classifiers":[
        {
            "category":"Shopping",
            "subcategory":"Computers & Home Electronics",
            "type":"Retail Goods"
        }
    ],
    "sg:phone":"+1 248 524 2702",
    "sg:postcode":"48083",
    "sg:province":"MI",
    "sg:tags":[
        "equipment",
        "electronic",
        "supply"
    ],
    "wof:name":"Sala-Burgess Electronics",
    "wof:placetype":"venue"
},
  "geometry": {"coordinates":[-83.13464399999999,42.54866],"type":"Point"}
}