{
  "type": "Feature",
  "properties": {
    "iso:country":"US",
    "sg:address":"7810 Michigan Ave",
    "sg:city":"Detroit",
    "sg:classifiers":[
        {
            "category":"Retail",
            "subcategory":"Self-service Laundry",
            "type":"Services"
        }
    ],
    "sg:phone":"+1 313 846 6665",
    "sg:postcode":"48210",
    "sg:province":"MI",
    "sg:tags":[
        "coin"
    ],
    "wof:name":"Sunshine Laundry",
    "wof:placetype":"venue"
},
  "geometry": {"coordinates":[-83.13996899999999,42.331171],"type":"Point"}
}