{
  "type": "Feature",
  "properties": {
    "iso:country":"US",
    "sg:address":"304 W Main St",
    "sg:city":"Durand",
    "sg:classifiers":[
        {
            "category":"Retail",
            "subcategory":"Auto Repair",
            "type":"Services"
        }
    ],
    "sg:phone":"+1 989 288 5100",
    "sg:postcode":"48429",
    "sg:province":"MI",
    "sg:tags":[
        "transmission"
    ],
    "wof:name":"Durand Transmission",
    "wof:placetype":"venue"
},
  "geometry": {"coordinates":[-83.987802,42.91083],"type":"Point"}
}