{
  "type": "Feature",
  "properties": {
    "iso:country":"US",
    "sg:address":"125 N Coldwater Rd",
    "sg:city":"Weidman",
    "sg:classifiers":[
        {
            "category":"Building & Trades",
            "subcategory":"Construction",
            "type":"Services"
        }
    ],
    "sg:phone":"+1 989 644 6763",
    "sg:postcode":"48893",
    "sg:province":"MI",
    "sg:tags":[
        "general",
        "contractor"
    ],
    "wof:name":"Shimunek Custom Builders",
    "wof:placetype":"venue"
},
  "geometry": {"coordinates":[-84.987741,43.642192],"type":"Point"}
}