{
  "type": "Feature",
  "properties": {
    "iso:country":"US",
    "sg:address":"1827 N Squirrel Rd",
    "sg:city":"Auburn Hills",
    "sg:classifiers":[
        {
            "category":"Professional",
            "subcategory":"Computer Services",
            "type":"Services"
        }
    ],
    "sg:phone":"+1 248 370 9400",
    "sg:postcode":"48326",
    "sg:province":"MI",
    "wof:name":"EDS",
    "wof:placetype":"venue"
},
  "geometry": {"coordinates":[-83.22062200000001,42.672406],"type":"Point"}
}