{
  "type": "Feature",
  "properties": {
    "iso:country":"US",
    "sg:address":"45441 Heydenreich Rd",
    "sg:city":"Macomb",
    "sg:classifiers":[
        {
            "category":"Health Services",
            "subcategory":"Doctor",
            "type":"Services"
        }
    ],
    "sg:phone":"+1 586 416 1300",
    "sg:postcode":"48044",
    "sg:province":"MI",
    "sg:tags":[
        "physician",
        "surgeon"
    ],
    "wof:name":"St Clair Orthopaedics & Sports",
    "wof:placetype":"venue"
},
  "geometry": {"coordinates":[-82.916065,42.630071],"type":"Point"}
}