{
  "type": "Feature",
  "properties": {
    "iso:country":"US",
    "sg:address":"17780 Wallin Rd",
    "sg:city":"Thompsonville",
    "sg:classifiers":[
        {
            "category":"Building & Trades",
            "subcategory":"Construction",
            "type":"Services"
        }
    ],
    "sg:phone":"+1 231 378 2584",
    "sg:postcode":"49683",
    "sg:province":"MI",
    "sg:tags":[
        "project"
    ],
    "wof:name":"Bill Woodward Construction",
    "wof:placetype":"venue"
},
  "geometry": {"coordinates":[-85.88319,44.570678],"type":"Point"}
}