{
  "type": "Feature",
  "properties": {
    "iso:country":"US",
    "sg:address":"323 Le Grand Blvd",
    "sg:city":"White Lake",
    "sg:classifiers":[
        {
            "category":"Real Estate",
            "subcategory":"Developer",
            "type":"Services"
        },
        {
            "category":"Real Estate",
            "subcategory":"Real Estate Operator",
            "type":"Services"
        }
    ],
    "sg:phone":"+1 248 887 4131",
    "sg:postcode":"48383",
    "sg:province":"MI",
    "sg:tags":[
        "mobile",
        "home",
        "site"
    ],
    "wof:name":"Cedarbrook Estates Ltd",
    "wof:placetype":"venue"
},
  "geometry": {"coordinates":[-83.536796,42.644553],"type":"Point"}
}