{
  "type": "Feature",
  "properties": {
    "iso:country":"US",
    "sg:address":"360 Capital Ave NE",
    "sg:city":"Battle Creek",
    "sg:classifiers":[
        {
            "category":"Organizations",
            "subcategory":"Religious Organization",
            "type":"Services"
        }
    ],
    "sg:phone":"+1 269 565 0839",
    "sg:postcode":"49017",
    "sg:province":"MI",
    "sg:tags":[
        "church"
    ],
    "wof:name":"New Birth Bible Church",
    "wof:placetype":"venue"
},
  "geometry": {"coordinates":[-85.167833,42.32339],"type":"Point"}
}