{
  "type": "Feature",
  "properties": {
    "iso:country":"US",
    "sg:address":"22851 Lexington Ave",
    "sg:city":"Eastpointe",
    "sg:classifiers":[
        {
            "category":"Organizations",
            "subcategory":"Religious Organization",
            "type":"Services"
        }
    ],
    "sg:phone":"+1 586 776 4685",
    "sg:postcode":"48021",
    "sg:province":"MI",
    "wof:name":"Adrian Dominican Sister Development Office",
    "wof:placetype":"venue"
},
  "geometry": {"coordinates":[-82.934529,42.467047],"type":"Point"}
}