{
  "type": "Feature",
  "properties": {
    "iso:country":"US",
    "sg:address":"5967 Maple Island Rd",
    "sg:city":"Nunica",
    "sg:classifiers":[
        {
            "category":"Manufacturing",
            "subcategory":"Metals",
            "type":"Manufacturing & Wholesale Goods"
        }
    ],
    "sg:phone":"+1 231 865 6856",
    "sg:postcode":"49448",
    "sg:province":"MI",
    "sg:tags":[
        "steel"
    ],
    "wof:name":"Varney's Fab & Weld",
    "wof:placetype":"venue"
},
  "geometry": {"coordinates":[-86.066564,43.144048],"type":"Point"}
}