{
  "type": "Feature",
  "properties": {
    "iso:country":"US",
    "sg:address":"2161 N Meridian Rd",
    "sg:city":"Sanford",
    "sg:classifiers":[
        {
            "category":"Organizations",
            "subcategory":"Religious Organization",
            "type":"Services"
        }
    ],
    "sg:phone":"+1 989 687 6388",
    "sg:postcode":"48657",
    "sg:province":"MI",
    "wof:name":"Church At Sanford Inc",
    "wof:placetype":"venue"
},
  "geometry": {"coordinates":[-84.36854,43.674516],"type":"Point"}
}