{
  "type": "Feature",
  "properties": {
    "iso:country":"US",
    "sg:address":"5329 Greenview Dr",
    "sg:city":"Clarkston",
    "sg:classifiers":[
        {
            "category":"Shopping",
            "subcategory":"Catalog Store",
            "type":"Retail Goods"
        }
    ],
    "sg:phone":"+1 248 321 0325",
    "sg:postcode":"48348",
    "sg:province":"MI",
    "sg:tags":[
        "mail",
        "house"
    ],
    "wof:name":"G4k Ltd",
    "wof:placetype":"venue"
},
  "geometry": {"coordinates":[-83.361265,42.757001],"type":"Point"}
}