{
  "type": "Feature",
  "properties": {
    "iso:country":"US",
    "sg:address":"22720 Nancy Ave",
    "sg:city":"Southfield",
    "sg:classifiers":[
        {
            "category":"Recreation",
            "type":"Entertainment"
        }
    ],
    "sg:phone":"+1 248 356 1274",
    "sg:postcode":"48033",
    "sg:province":"MI",
    "sg:tags":[
        "piano",
        "instruction"
    ],
    "wof:name":"Diana Munch",
    "wof:placetype":"venue"
},
  "geometry": {"coordinates":[-83.289277,42.452506],"type":"Point"}
}