{
  "type": "Feature",
  "properties": {
    "iso:country":"US",
    "sg:address":"30201 Orchard Lake Rd",
    "sg:city":"Farmington Hills",
    "sg:classifiers":[
        {
            "category":"Professional",
            "subcategory":"Accounting & Tax Preparation",
            "type":"Services"
        }
    ],
    "sg:phone":"+1 248 932 2556",
    "sg:postcode":"48334",
    "sg:province":"MI",
    "sg:tags":[
        "accountant"
    ],
    "wof:name":"Michael J Franco & Assoc",
    "wof:placetype":"venue"
},
  "geometry": {"coordinates":[-83.359792,42.520165],"type":"Point"}
}