{
  "type": "Feature",
  "properties": {
    "iso:country":"US",
    "sg:address":"29700 Van Dyke Ave",
    "sg:city":"Warren",
    "sg:classifiers":[
        {
            "category":"Banks & Credit Unions",
            "subcategory":"Bank",
            "type":"Services"
        }
    ],
    "sg:phone":"+1 586 558 0212",
    "sg:postcode":"48093",
    "sg:province":"MI",
    "wof:name":"Chase",
    "wof:placetype":"venue"
},
  "geometry": {"coordinates":[-83.028384,42.512047],"type":"Point"}
}