{
  "type": "Feature",
  "properties": {
    "iso:country":"US",
    "sg:address":"4963 Eastman Ave",
    "sg:city":"Midland",
    "sg:classifiers":[
        {
            "category":"Food & Beverages",
            "subcategory":"Bakery",
            "type":"Retail Goods"
        }
    ],
    "sg:phone":"+1 989 631 0081",
    "sg:postcode":"48640",
    "sg:province":"MI",
    "sg:tags":[
        "baker"
    ],
    "wof:name":"North Country Grains Bakery",
    "wof:placetype":"venue"
},
  "geometry": {"coordinates":[-84.24688399999999,43.643665],"type":"Point"}
}