{
  "type": "Feature",
  "properties": {
    "iso:country":"US",
    "sg:address":"611 Vis del Sol",
    "sg:city":"Lapeer",
    "sg:classifiers":[
        {
            "category":"Manufacturing",
            "subcategory":"Textiles",
            "type":"Manufacturing & Wholesale Goods"
        },
        {
            "category":"Home & Garden",
            "subcategory":"Home Furnishings",
            "type":"Retail Goods"
        }
    ],
    "sg:phone":"+1 810 664 9452",
    "sg:postcode":"48446",
    "sg:province":"MI",
    "sg:tags":[
        "mill",
        "fabric",
        "quilting"
    ],
    "wof:name":"Piece Full Quilting",
    "wof:placetype":"venue"
},
  "geometry": {"coordinates":[-83.33604,43.112073],"type":"Point"}
}