{
  "type": "Feature",
  "properties": {
    "iso:country":"US",
    "sg:address":"6898 Close Dr",
    "sg:city":"Tecumseh",
    "sg:classifiers":[
        {
            "category":"Social Services",
            "subcategory":"Child Care",
            "type":"Services"
        }
    ],
    "sg:phone":"+1 517 423 1200",
    "sg:postcode":"49286",
    "sg:province":"MI",
    "sg:tags":[
        "day"
    ],
    "wof:name":"Best Friends Day Care",
    "wof:placetype":"venue"
},
  "geometry": {"coordinates":[-83.951684,41.990723],"type":"Point"}
}