{
  "type": "Feature",
  "properties": {
    "iso:country":"US",
    "sg:address":"4386 Pine Grove Ave",
    "sg:city":"Fort Gratiot",
    "sg:classifiers":[
        {
            "category":"Shopping",
            "subcategory":"Florist",
            "type":"Retail Goods"
        }
    ],
    "sg:phone":"+1 810 385 7565",
    "sg:postcode":"48059",
    "sg:province":"MI",
    "wof:name":"Balloons By Betty",
    "wof:placetype":"venue"
},
  "geometry": {"coordinates":[-82.481486,43.036549],"type":"Point"}
}