{
  "type": "Feature",
  "properties": {
    "iso:country":"US",
    "sg:address":"48264 Manchester",
    "sg:city":"Macomb",
    "sg:classifiers":[
        {
            "category":"Professional",
            "subcategory":"Engineering",
            "type":"Services"
        },
        {
            "category":"Real Estate",
            "subcategory":"Surveying",
            "type":"Services"
        }
    ],
    "sg:phone":"+1 586 216 1043",
    "sg:postcode":"48044",
    "sg:province":"MI",
    "sg:tags":[
        "consulting",
        "land",
        "civil",
        "geotechnical",
        "surveyor",
        "engineer"
    ],
    "sg:website":"http://www.sesengineeringgroup.vpweb.com",
    "wof:name":"SES Engineering Group, LLC",
    "wof:placetype":"venue"
},
  "geometry": {"coordinates":[-82.924893,42.652292],"type":"Point"}
}