{
  "type": "Feature",
  "properties": {
    "iso:country":"US",
    "sg:address":"3144 Dixie Hwy",
    "sg:city":"Waterford",
    "sg:classifiers":[
        {
            "category":"Manufacturing",
            "subcategory":"Metals",
            "type":"Manufacturing & Wholesale Goods"
        }
    ],
    "sg:phone":"+1 248 673 2250",
    "sg:postcode":"48328",
    "sg:province":"MI",
    "sg:tags":[
        "steel"
    ],
    "wof:name":"Martin Structural Sales Inc",
    "wof:placetype":"venue"
},
  "geometry": {"coordinates":[-83.34898200000001,42.675395],"type":"Point"}
}