{
  "type": "Feature",
  "properties": {
    "iso:country":"US",
    "sg:address":"28015 Gratiot Ave",
    "sg:city":"Roseville",
    "sg:classifiers":[
        {
            "category":"Personal",
            "subcategory":"Beauty Salon",
            "type":"Services"
        }
    ],
    "sg:phone":"+1 586 772 7722",
    "sg:postcode":"48066",
    "sg:province":"MI",
    "sg:tags":[
        "shop"
    ],
    "wof:name":"Rebels Hair Studio Inc",
    "wof:placetype":"venue"
},
  "geometry": {"coordinates":[-82.93288,42.503487],"type":"Point"}
}