{
  "type": "Feature",
  "properties": {
    "iso:country":"US",
    "sg:address":"1034 Lapeer Ave",
    "sg:city":"Port Huron",
    "sg:classifiers":[
        {
            "category":"Local Transit",
            "type":"Transportation"
        }
    ],
    "sg:phone":"+1 810 985 9166",
    "sg:postcode":"48060",
    "sg:province":"MI",
    "sg:tags":[
        "airport"
    ],
    "wof:name":"All Around Shuttle",
    "wof:placetype":"venue"
},
  "geometry": {"coordinates":[-82.434562,42.97625],"type":"Point"}
}