{
  "type": "Feature",
  "properties": {
    "iso:country":"US",
    "sg:address":"2286 US Hwy 23 N",
    "sg:city":"Alpena",
    "sg:classifiers":[
        {
            "category":"Personal",
            "subcategory":"Beauty Salon",
            "type":"Services"
        }
    ],
    "sg:phone":"+1 989 356 6767",
    "sg:postcode":"49707",
    "sg:province":"MI",
    "sg:tags":[
        "shop"
    ],
    "wof:name":"Regis Salons",
    "wof:placetype":"venue"
},
  "geometry": {"coordinates":[-83.45645399999999,45.095693],"type":"Point"}
}