{
  "type": "Feature",
  "properties": {
    "iso:country":"US",
    "sg:address":"6191 Sheridan Rd",
    "sg:city":"Saginaw",
    "sg:classifiers":[
        {
            "category":"Freight",
            "type":"Transportation"
        }
    ],
    "sg:phone":"+1 989 777 0637",
    "sg:postcode":"48601",
    "sg:province":"MI",
    "sg:tags":[
        "operator",
        "local",
        "trucking"
    ],
    "wof:name":"Sages Hauling",
    "wof:placetype":"venue"
},
  "geometry": {"coordinates":[-83.934026,43.335632],"type":"Point"}
}