{
  "type": "Feature",
  "properties": {
    "iso:country":"US",
    "sg:address":"2454 W Monroe Rd",
    "sg:city":"Alma",
    "sg:classifiers":[
        {
            "category":"Travel",
            "subcategory":"Hotels & Motels",
            "type":"Entertainment"
        }
    ],
    "sg:phone":"+1 989 681 5728",
    "sg:postcode":"48801",
    "sg:province":"MI",
    "wof:name":"Petticoat Motel",
    "wof:placetype":"venue"
},
  "geometry": {"coordinates":[-84.654149,43.407992],"type":"Point"}
}