{
  "type": "Feature",
  "properties": {
    "iso:country":"US",
    "sg:address":"116 Terry Ave",
    "sg:city":"Rochester",
    "sg:classifiers":[
        {
            "category":"Travel",
            "subcategory":"Hotels & Motels",
            "type":"Entertainment"
        }
    ],
    "sg:phone":"+1 248 651 8090",
    "sg:postcode":"48307",
    "sg:province":"MI",
    "sg:tags":[
        "building",
        "operator",
        "apartment",
        "house"
    ],
    "wof:name":"The Spartan Motel",
    "wof:placetype":"venue"
},
  "geometry": {"coordinates":[-83.131698,42.68859],"type":"Point"}
}