{
  "type": "Feature",
  "properties": {
    "iso:country":"US",
    "sg:address":"498 Ashton Ct SE",
    "sg:city":"Grand Rapids",
    "sg:classifiers":[
        {
            "category":"Professional",
            "subcategory":"Business Services",
            "type":"Services"
        }
    ],
    "sg:phone":"+1 616 942 7604",
    "sg:postcode":"49546",
    "sg:province":"MI",
    "sg:tags":[
        "notary",
        "public"
    ],
    "wof:name":"Shirley D Jeter",
    "wof:placetype":"venue"
},
  "geometry": {"coordinates":[-85.58649,42.9547],"type":"Point"}
}