{
  "type": "Feature",
  "properties": {
    "iso:country":"US",
    "sg:address":"1733 Century Ave SW",
    "sg:city":"Grand Rapids",
    "sg:classifiers":[
        {
            "category":"Building & Trades",
            "subcategory":"Construction",
            "type":"Services"
        }
    ],
    "sg:phone":"+1 616 530 1700",
    "sg:postcode":"49503",
    "sg:province":"MI",
    "sg:tags":[
        "bathroom",
        "remodeling"
    ],
    "wof:name":"Complete Remodeling Of Mi",
    "wof:placetype":"venue"
},
  "geometry": {"coordinates":[-85.681449,42.931902],"type":"Point"}
}