{
  "type": "Feature",
  "properties": {
    "iso:country":"US",
    "sg:address":"1520 S Dow Rd",
    "sg:city":"West Branch",
    "sg:classifiers":[
        {
            "category":"Recreation",
            "type":"Entertainment"
        }
    ],
    "sg:phone":"+1 989 345 1283",
    "sg:postcode":"48661",
    "sg:province":"MI",
    "wof:name":"Cedar Brook Driving Range",
    "wof:placetype":"venue"
},
  "geometry": {"coordinates":[-84.24683899999999,44.294596],"type":"Point"}
}