{
  "type": "Feature",
  "properties": {
    "iso:country":"US",
    "sg:address":"2100 Raybrook Ave SE",
    "sg:city":"Grand Rapids",
    "sg:classifiers":[
        {
            "category":"Professional",
            "type":"Services"
        },
        {
            "category":"Insurance",
            "subcategory":"Health Insurance",
            "type":"Services"
        }
    ],
    "sg:phone":"+1 616 957 2395",
    "sg:postcode":"49546",
    "sg:province":"MI",
    "sg:tags":[
        "establishment",
        "plan"
    ],
    "wof:name":"Community Care Plan",
    "wof:placetype":"venue"
},
  "geometry": {"coordinates":[-85.58787,42.923818],"type":"Point"}
}