{
  "type": "Feature",
  "properties": {
    "iso:country":"US",
    "sg:address":"25185 Carmel",
    "sg:city":"Trenton",
    "sg:classifiers":[
        {
            "category":"Wholesale",
            "subcategory":"Machinery & Supplies",
            "type":"Manufacturing & Wholesale Goods"
        }
    ],
    "sg:phone":"+1 734 782 3341",
    "sg:postcode":"48183",
    "sg:province":"MI",
    "sg:tags":[
        "equipment",
        "establishment"
    ],
    "wof:name":"RB Unique Caroeting",
    "wof:placetype":"venue"
},
  "geometry": {"coordinates":[-83.259636,42.121582],"type":"Point"}
}