{
  "type": "Feature",
  "properties": {
    "iso:country":"US",
    "sg:address":"31080 Harper Ave",
    "sg:city":"Saint Clair Shores",
    "sg:classifiers":[
        {
            "category":"Retail",
            "subcategory":"Auto Repair",
            "type":"Services"
        }
    ],
    "sg:phone":"+1 586 293 1965",
    "sg:postcode":"48082",
    "sg:province":"MI",
    "sg:tags":[
        "repairing",
        "automobile"
    ],
    "wof:name":"Shores Car Care",
    "wof:placetype":"venue"
},
  "geometry": {"coordinates":[-82.898399,42.523602],"type":"Point"}
}