{
  "type": "Feature",
  "properties": {
    "iso:country":"US",
    "sg:address":"6247 Cooper Rd",
    "sg:city":"Lansing",
    "sg:classifiers":[
        {
            "category":"Social Services",
            "type":"Services"
        }
    ],
    "sg:phone":"+1 517 272 9831",
    "sg:postcode":"48911",
    "sg:province":"MI",
    "sg:tags":[
        "referral"
    ],
    "wof:name":"No BS Referral",
    "wof:placetype":"venue"
},
  "geometry": {"coordinates":[-84.560863,42.6642],"type":"Point"}
}