{
  "type": "Feature",
  "properties": {
    "iso:country":"US",
    "sg:address":"3024 S Airport Rd W",
    "sg:city":"Traverse City",
    "sg:classifiers":[
        {
            "category":"Shopping",
            "subcategory":"Gifts & Souvenirs",
            "type":"Retail Goods"
        }
    ],
    "sg:phone":"+1 231 883 4438",
    "sg:postcode":"49684",
    "sg:province":"MI",
    "sg:tags":[
        "glass",
        "art",
        "blown"
    ],
    "wof:name":"Traverse Artglass",
    "wof:placetype":"venue"
},
  "geometry": {"coordinates":[-85.635952,44.729086],"type":"Point"}
}