{
  "type": "Feature",
  "properties": {
    "iso:country":"US",
    "sg:address":"20300 Civic Center Dr # 100",
    "sg:city":"Southfield",
    "sg:classifiers":[
        {
            "category":"Professional",
            "subcategory":"Business Services",
            "type":"Services"
        }
    ],
    "sg:phone":"+1 248 304 0143",
    "sg:postcode":"48076",
    "sg:province":"MI",
    "sg:tags":[
        "medical",
        "administration"
    ],
    "sg:website":"http://www.co.oakland.mi.us",
    "wof:name":"Health Dept",
    "wof:placetype":"venue"
},
  "geometry": {"coordinates":[-83.243942,42.480019],"type":"Point"}
}