{
  "type": "Feature",
  "properties": {
    "iso:country":"US",
    "sg:address":"216 E 10th Ave",
    "sg:city":"Sault Sainte Marie",
    "sg:classifiers":[
        {
            "category":"Social Services",
            "subcategory":"Adult Care",
            "type":"Services"
        }
    ],
    "sg:phone":"+1 906 632 2515",
    "sg:postcode":"49783",
    "sg:province":"MI",
    "sg:tags":[
        "day",
        "provider"
    ],
    "wof:name":"Bumstead Day Care",
    "wof:placetype":"venue"
},
  "geometry": {"coordinates":[-84.351732,46.482705],"type":"Point"}
}