{
  "type": "Feature",
  "properties": {
    "iso:country":"US",
    "sg:address":"10310 Kress Rd",
    "sg:city":"Pinckney",
    "sg:classifiers":[
        {
            "category":"Building & Trades",
            "subcategory":"Construction",
            "type":"Services"
        }
    ],
    "sg:phone":"+1 810 231 1360",
    "sg:postcode":"48169",
    "sg:province":"MI",
    "sg:tags":[
        "residential",
        "contractor"
    ],
    "wof:name":"Lakeland Building Company Inc",
    "wof:placetype":"venue"
},
  "geometry": {"coordinates":[-83.85498699999999,42.451315],"type":"Point"}
}