{
  "type": "Feature",
  "properties": {
    "iso:country":"US",
    "sg:address":"31501 Madison Ave",
    "sg:city":"Madison Heights",
    "sg:classifiers":[
        {
            "category":"Professional",
            "subcategory":"Engineering",
            "type":"Services"
        },
        {
            "category":"Professional",
            "subcategory":"Computer Services",
            "type":"Services"
        }
    ],
    "sg:phone":"+1 248 585 1450",
    "sg:postcode":"48071",
    "sg:province":"MI",
    "sg:tags":[
        "design",
        "system",
        "engineer"
    ],
    "wof:name":"Diverse Technologies Inc",
    "wof:placetype":"venue"
},
  "geometry": {"coordinates":[-83.124833,42.523789],"type":"Point"}
}