{
  "type": "Feature",
  "properties": {
    "iso:country":"US",
    "sg:address":"3972 Laplaya Ln",
    "sg:city":"Orchard Lake",
    "sg:classifiers":[
        {
            "category":"Professional",
            "subcategory":"Employment Agencies",
            "type":"Services"
        }
    ],
    "sg:phone":"+1 248 706 3521",
    "sg:postcode":"48324",
    "sg:province":"MI",
    "sg:tags":[
        "consultant",
        "search",
        "executive"
    ],
    "wof:name":"Engineering Partnership",
    "wof:placetype":"venue"
},
  "geometry": {"coordinates":[-83.39876099999999,42.581027],"type":"Point"}
}