{
  "type": "Feature",
  "properties": {
    "iso:country":"US",
    "sg:address":"2411 N Squirrel Rd",
    "sg:city":"Auburn Hills",
    "sg:classifiers":[
        {
            "category":"Social Services",
            "subcategory":"Child Care",
            "type":"Services"
        }
    ],
    "sg:phone":"+1 248 373 5999",
    "sg:postcode":"48326",
    "sg:province":"MI",
    "wof:name":"Rainbow Child Development",
    "wof:placetype":"venue"
},
  "geometry": {"coordinates":[-83.221215,42.678457],"type":"Point"}
}