{
  "type": "Feature",
  "properties": {
    "iso:country":"US",
    "sg:address":"2697 Aubrey Dr",
    "sg:city":"Lake Orion",
    "sg:classifiers":[
        {
            "category":"Professional",
            "type":"Services"
        }
    ],
    "sg:phone":"+1 248 391 2522",
    "sg:postcode":"48360",
    "sg:province":"MI",
    "sg:tags":[
        "inventor"
    ],
    "wof:name":"Phipes Inc",
    "wof:placetype":"venue"
},
  "geometry": {"coordinates":[-83.322879,42.741126],"type":"Point"}
}