{
  "type": "Feature",
  "properties": {
    "iso:country":"US",
    "sg:address":"28723 Dequindre Rd",
    "sg:city":"Madison Heights",
    "sg:classifiers":[
        {
            "category":"Sports & Exercise",
            "subcategory":"Bicycle Rental",
            "type":"Entertainment"
        }
    ],
    "sg:phone":"+1 248 398 2626",
    "sg:postcode":"48071",
    "sg:province":"MI",
    "sg:tags":[
        "bike"
    ],
    "wof:name":"One Stop Scooter Shop",
    "wof:placetype":"venue"
},
  "geometry": {"coordinates":[-83.08571600000001,42.503495],"type":"Point"}
}