{
  "type": "Feature",
  "properties": {
    "iso:country":"US",
    "sg:address":"3501 Lake Eastbrook Blvd SE",
    "sg:city":"Grand Rapids",
    "sg:classifiers":[
        {
            "category":"Professional",
            "subcategory":"Credit Reporting & Collection",
            "type":"Services"
        }
    ],
    "sg:phone":"+1 616 956 5139",
    "sg:postcode":"49546",
    "sg:province":"MI",
    "sg:tags":[
        "agency"
    ],
    "wof:name":"Premier Credit Corp",
    "wof:placetype":"venue"
},
  "geometry": {"coordinates":[-85.58004,42.917736],"type":"Point"}
}