{
  "type": "Feature",
  "properties": {
    "iso:country":"US",
    "sg:address":"38165 Utica Rd",
    "sg:city":"Sterling Heights",
    "sg:classifiers":[
        {
            "category":"Health Services",
            "subcategory":"Chiropractor",
            "type":"Services"
        }
    ],
    "sg:phone":"+1 586 939 2040",
    "sg:postcode":"48312",
    "sg:province":"MI",
    "wof:name":"Back To Health Chiropractic",
    "wof:placetype":"venue"
},
  "geometry": {"coordinates":[-82.988899,42.576801],"type":"Point"}
}