{
  "type": "Feature",
  "properties": {
    "iso:country":"US",
    "sg:address":"433 N Washington Ave",
    "sg:city":"Royal Oak",
    "sg:classifiers":[
        {
            "category":"Professional",
            "subcategory":"Employment Agencies",
            "type":"Services"
        }
    ],
    "sg:phone":"+1 248 544 0008",
    "sg:postcode":"48067",
    "sg:province":"MI",
    "sg:tags":[
        "modeling"
    ],
    "wof:name":"Ledzed's Modeling Agency",
    "wof:placetype":"venue"
},
  "geometry": {"coordinates":[-83.14687000000001,42.492668],"type":"Point"}
}