{
  "type": "Feature",
  "properties": {
    "iso:country":"US",
    "sg:address":"24625 Cottage Ln",
    "sg:city":"Warren",
    "sg:classifiers":[
        {
            "category":"Building & Trades",
            "subcategory":"Cleaning & Sanitation",
            "type":"Services"
        }
    ],
    "sg:phone":"+1 586 778 9474",
    "sg:postcode":"48089",
    "sg:province":"MI",
    "sg:tags":[
        "house"
    ],
    "wof:name":"I Maid It Clean",
    "wof:placetype":"venue"
},
  "geometry": {"coordinates":[-82.978886,42.476267],"type":"Point"}
}