{
  "type": "Feature",
  "properties": {
    "iso:country":"US",
    "sg:address":"4016 N Irish Rd",
    "sg:city":"Davison",
    "sg:classifiers":[
        {
            "category":"Personal",
            "subcategory":"Beauty Salon",
            "type":"Services"
        }
    ],
    "sg:phone":"+1 810 658 8322",
    "sg:postcode":"48423",
    "sg:province":"MI",
    "sg:tags":[
        "shop"
    ],
    "wof:name":"Salon Gabella",
    "wof:placetype":"venue"
},
  "geometry": {"coordinates":[-83.55752699999999,43.072076],"type":"Point"}
}