{
  "type": "Feature",
  "properties": {
    "iso:country":"US",
    "sg:address":"37319 Little Mack Ave",
    "sg:city":"Clinton Township",
    "sg:classifiers":[
        {
            "category":"Personal",
            "type":"Services"
        }
    ],
    "sg:phone":"+1 586 463 3343",
    "sg:postcode":"48036",
    "sg:province":"MI",
    "sg:tags":[
        "towing"
    ],
    "sg:website":"www.bingesltd.com",
    "wof:name":"Binge's Ltd",
    "wof:placetype":"venue"
},
  "geometry": {"coordinates":[-82.899101,42.573101],"type":"Point"}
}