{
  "type": "Feature",
  "properties": {
    "iso:country":"US",
    "sg:address":"233 Moss Rd",
    "sg:city":"Wellston",
    "sg:classifiers":[
        {
            "category":"Travel",
            "subcategory":"Campground",
            "type":"Entertainment"
        }
    ],
    "sg:phone":"+1 231 848 4124",
    "sg:postcode":"49689",
    "sg:province":"MI",
    "wof:name":"Twin Oaks Campground",
    "wof:placetype":"venue"
},
  "geometry": {"coordinates":[-85.891192,44.23441],"type":"Point"}
}