{
  "type": "Feature",
  "properties": {
    "iso:country":"US",
    "sg:address":"3314 Linden St",
    "sg:city":"Dearborn",
    "sg:classifiers":[
        {
            "category":"Building & Trades",
            "subcategory":"Construction",
            "type":"Services"
        }
    ],
    "sg:phone":"+1 313 563 6249",
    "sg:postcode":"48124",
    "sg:province":"MI",
    "sg:tags":[
        "hanging",
        "contractor"
    ],
    "wof:name":"Craft Painting",
    "wof:placetype":"venue"
},
  "geometry": {"coordinates":[-83.21659200000001,42.282226],"type":"Point"}
}