{
  "type": "Feature",
  "properties": {
    "iso:country":"US",
    "sg:address":"881 Burke Ave NE",
    "sg:city":"Grand Rapids",
    "sg:classifiers":[
        {
            "category":"Professional",
            "subcategory":"Management & Consulting",
            "type":"Services"
        }
    ],
    "sg:phone":"+1 616 774 2832",
    "sg:postcode":"49503",
    "sg:province":"MI",
    "wof:name":"Sea Coast Management",
    "wof:placetype":"venue"
},
  "geometry": {"coordinates":[-85.64152199999999,42.978223],"type":"Point"}
}