{
  "type": "Feature",
  "properties": {
    "iso:country":"US",
    "sg:address":"1885 Osseo Rd S",
    "sg:city":"Osseo",
    "sg:classifiers":[
        {
            "category":"Social Services",
            "subcategory":"Adult Care",
            "type":"Services"
        }
    ],
    "sg:phone":"+1 517 523 2100",
    "sg:postcode":"49266",
    "sg:province":"MI",
    "sg:tags":[
        "home",
        "foster"
    ],
    "wof:name":"Golden Years Foster Care Inc",
    "wof:placetype":"venue"
},
  "geometry": {"coordinates":[-84.534656,41.899814],"type":"Point"}
}