{
  "type": "Feature",
  "properties": {
    "iso:country":"US",
    "sg:address":"2267 Heilman St",
    "sg:city":"Burton",
    "sg:classifiers":[
        {
            "category":"Retail",
            "subcategory":"Auto Repair",
            "type":"Services"
        }
    ],
    "sg:phone":"+1 810 742 8379",
    "sg:postcode":"48529",
    "sg:province":"MI",
    "sg:tags":[
        "glass",
        "replacement"
    ],
    "wof:name":"Burton Auto Glass",
    "wof:placetype":"venue"
},
  "geometry": {"coordinates":[-83.662662,42.960912],"type":"Point"}
}