{
  "type": "Feature",
  "properties": {
    "iso:country":"US",
    "sg:address":"8491 Secor Rd",
    "sg:city":"Lambertville",
    "sg:classifiers":[
        {
            "category":"Manufacturing",
            "subcategory":"Printing",
            "type":"Manufacturing & Wholesale Goods"
        }
    ],
    "sg:phone":"+1 734 856 4333",
    "sg:postcode":"48144",
    "sg:province":"MI",
    "sg:tags":[
        "commercial"
    ],
    "wof:name":"L & J Printing Inc",
    "wof:placetype":"venue"
},
  "geometry": {"coordinates":[-83.626548,41.769422],"type":"Point"}
}