{
  "type": "Feature",
  "properties": {
    "iso:country":"US",
    "sg:address":"46065 Royal Dr",
    "sg:city":"New Baltimore",
    "sg:classifiers":[
        {
            "category":"Real Estate",
            "subcategory":"Architect",
            "type":"Services"
        }
    ],
    "sg:phone":"+1 586 949 5033",
    "sg:postcode":"48051",
    "sg:province":"MI",
    "sg:tags":[
        "architectural"
    ],
    "wof:name":"Studio 3 Design LLC",
    "wof:placetype":"venue"
},
  "geometry": {"coordinates":[-82.85343399999999,42.637742],"type":"Point"}
}