{
  "type": "Feature",
  "properties": {
    "iso:country":"US",
    "sg:address":"2730 Trillium Ln",
    "sg:city":"Ann Arbor",
    "sg:classifiers":[
        {
            "category":"Manufacturing",
            "subcategory":"Retail Goods",
            "type":"Manufacturing & Wholesale Goods"
        }
    ],
    "sg:phone":"+1 734 623 7611",
    "sg:postcode":"48103",
    "sg:province":"MI",
    "sg:tags":[
        "product",
        "mfg"
    ],
    "wof:name":"Trillium Pottery",
    "wof:placetype":"venue"
},
  "geometry": {"coordinates":[-83.80441500000001,42.244192],"type":"Point"}
}