{
  "type": "Feature",
  "properties": {
    "iso:country":"US",
    "sg:address":"24101 Novi Rd",
    "sg:city":"Novi",
    "sg:classifiers":[
        {
            "category":"Professional",
            "subcategory":"Lawyer & Legal Services",
            "type":"Services"
        }
    ],
    "sg:phone":"+1 248 347 9620",
    "sg:postcode":"48375",
    "sg:province":"MI",
    "sg:tags":[
        "attorney"
    ],
    "wof:name":"Harrington Law Offices",
    "wof:placetype":"venue"
},
  "geometry": {"coordinates":[-83.474683,42.464424],"type":"Point"}
}