{
  "type": "Feature",
  "properties": {
    "iso:country":"US",
    "sg:address":"1324 Southfield Rd",
    "sg:city":"Lincoln Park",
    "sg:classifiers":[
        {
            "category":"Retail",
            "subcategory":"Funeral Services",
            "type":"Services"
        }
    ],
    "sg:phone":"+1 313 382 7878",
    "sg:postcode":"48146",
    "sg:province":"MI",
    "sg:tags":[
        "cemetery"
    ],
    "wof:name":"Aleks R C & Son Funeral Home Inc",
    "wof:placetype":"venue"
},
  "geometry": {"coordinates":[-83.177696,42.250702],"type":"Point"}
}