{
  "type": "Feature",
  "properties": {
    "iso:country":"US",
    "sg:address":"8191 Moorsbridge Rd",
    "sg:city":"Portage",
    "sg:classifiers":[
        {
            "category":"Insurance",
            "subcategory":"Insurance Agent",
            "type":"Services"
        }
    ],
    "sg:phone":"+1 269 323 2600",
    "sg:postcode":"49024",
    "sg:province":"MI",
    "wof:name":"Sackett Insurance Group Inc",
    "wof:placetype":"venue"
},
  "geometry": {"coordinates":[-85.632053,42.202346],"type":"Point"}
}