{
  "type": "Feature",
  "properties": {
    "iso:country":"US",
    "sg:address":"16170 Red Arrow Hwy",
    "sg:city":"Union Pier",
    "sg:classifiers":[
        {
            "category":"Professional",
            "subcategory":"Business Services",
            "type":"Services"
        }
    ],
    "sg:phone":"+1 269 469 0077",
    "sg:postcode":"49129",
    "sg:province":"MI",
    "wof:name":"Sensational Spas",
    "wof:placetype":"venue"
},
  "geometry": {"coordinates":[-86.693583,41.826853],"type":"Point"}
}