{
  "type": "Feature",
  "properties": {
    "iso:country":"US",
    "sg:address":"18734 Woodward Ave",
    "sg:city":"Detroit",
    "sg:classifiers":[
        {
            "category":"Manufacturing",
            "subcategory":"Buildings",
            "type":"Manufacturing & Wholesale Goods"
        },
        {
            "category":"Structure",
            "subcategory":"Warehouse",
            "type":"Public Place"
        },
        {
            "category":"Building & Trades",
            "subcategory":"Construction",
            "type":"Services"
        }
    ],
    "sg:phone":"+1 313 366 2970",
    "sg:postcode":"48203",
    "sg:province":"MI",
    "sg:tags":[
        "warehouses-merchandise",
        "warehouses-public-commercial",
        "builder",
        "contractor",
        "home",
        "estimate"
    ],
    "wof:name":"D & A Construction Services",
    "wof:placetype":"venue"
},
  "geometry": {"coordinates":[-83.113039,42.429248],"type":"Point"}
}