{
  "type": "Feature",
  "properties": {
    "iso:country":"US",
    "sg:address":"24240 Veterans Memorial Hwy",
    "sg:city":"Hillman",
    "sg:classifiers":[
        {
            "category":"Retail",
            "subcategory":"Funeral Services",
            "type":"Services"
        }
    ],
    "sg:phone":"+1 989 742 4814",
    "sg:postcode":"49746",
    "sg:province":"MI",
    "sg:tags":[
        "merchandise"
    ],
    "wof:name":"Green Funeral Home Inc",
    "wof:placetype":"venue"
},
  "geometry": {"coordinates":[-83.895957,45.059283],"type":"Point"}
}