{
  "type": "Feature",
  "properties": {
    "iso:country":"US",
    "sg:address":"7334 Forrister Rd",
    "sg:city":"Adrian",
    "sg:classifiers":[
        {
            "category":"Personal",
            "type":"Services"
        }
    ],
    "sg:phone":"+1 517 264 1854",
    "sg:postcode":"49221",
    "sg:province":"MI",
    "wof:name":"J & JS Home Improvement Inc",
    "wof:placetype":"venue"
},
  "geometry": {"coordinates":[-84.132295,41.915286],"type":"Point"}
}