{
  "type": "Feature",
  "properties": {
    "iso:country":"US",
    "sg:address":"560 Oak St",
    "sg:city":"Lapeer",
    "sg:classifiers":[
        {
            "category":"Manufacturing",
            "subcategory":"Signs",
            "type":"Manufacturing & Wholesale Goods"
        },
        {
            "category":"Professional",
            "subcategory":"Art Services",
            "type":"Services"
        }
    ],
    "sg:phone":"+1 810 664 3812",
    "sg:postcode":"48446",
    "sg:province":"MI",
    "sg:tags":[
        "arts",
        "graphic",
        "design",
        "related"
    ],
    "wof:name":"Vision Graphics & Signs Inc",
    "wof:placetype":"venue"
},
  "geometry": {"coordinates":[-83.31811500000001,43.045175],"type":"Point"}
}