{
  "type": "Feature",
  "properties": {
    "iso:country":"US",
    "sg:address":"2551 Appleton Dr NE",
    "sg:city":"Grand Rapids",
    "sg:classifiers":[
        {
            "category":"Travel",
            "subcategory":"Travel Agent",
            "type":"Entertainment"
        }
    ],
    "sg:phone":"+1 616 363 7117",
    "sg:postcode":"49525",
    "sg:province":"MI",
    "sg:tags":[
        "agency",
        "bureau"
    ],
    "wof:name":"Ripmaster Travel",
    "wof:placetype":"venue"
},
  "geometry": {"coordinates":[-85.594885,43.008498],"type":"Point"}
}