{
  "type": "Feature",
  "properties": {
    "iso:country":"US",
    "sg:address":"900 Ethel Ave",
    "sg:city":"Hancock",
    "sg:classifiers":[
        {
            "category":"Government",
            "subcategory":"Fire Station",
            "type":"Public Place"
        }
    ],
    "sg:phone":"+1 906 482 1118",
    "sg:postcode":"49930",
    "sg:province":"MI",
    "sg:tags":[
        "protection"
    ],
    "wof:name":"Hancock Fire Station",
    "wof:placetype":"venue"
},
  "geometry": {"coordinates":[-88.599795,47.131501],"type":"Point"}
}