{
  "type": "Feature",
  "properties": {
    "iso:country":"US",
    "sg:address":"425 Boardman Ave",
    "sg:city":"Traverse City",
    "sg:classifiers":[
        {
            "category":"Recreation",
            "type":"Entertainment"
        }
    ],
    "sg:phone":"+1 231 274 0319",
    "sg:postcode":"49684",
    "sg:province":"MI",
    "sg:tags":[
        "martial",
        "arts",
        "instruction"
    ],
    "wof:name":"Murayama Martial Arts",
    "wof:placetype":"venue"
},
  "geometry": {"coordinates":[-85.615748,44.760254],"type":"Point"}
}