{
  "type": "Feature",
  "properties": {
    "iso:country":"US",
    "sg:address":"198 N State St",
    "sg:city":"St Ignace",
    "sg:classifiers":[
        {
            "category":"Shopping",
            "subcategory":"Gifts & Souvenirs",
            "type":"Retail Goods"
        }
    ],
    "sg:phone":"+1 906 643 7825",
    "sg:postcode":"49781",
    "sg:province":"MI",
    "sg:tags":[
        "shop"
    ],
    "wof:name":"Show Gifts",
    "wof:placetype":"venue"
},
  "geometry": {"coordinates":[-84.7243,45.867728],"type":"Point"}
}