{
  "type": "Feature",
  "properties": {
    "iso:country":"US",
    "sg:address":"480 Abbey Wood Dr",
    "sg:city":"Rochester",
    "sg:classifiers":[
        {
            "category":"Manufacturing",
            "subcategory":"Soap",
            "type":"Manufacturing & Wholesale Goods"
        }
    ],
    "sg:phone":"+1 248 601 4395",
    "sg:postcode":"48306",
    "sg:province":"MI",
    "sg:tags":[
        "detergent"
    ],
    "wof:name":"Procter & Gamble Co",
    "wof:placetype":"venue"
},
  "geometry": {"coordinates":[-83.143412,42.71603],"type":"Point"}
}