{
  "type": "Feature",
  "properties": {
    "iso:country":"US",
    "sg:address":"14763 Indian Trails Dr",
    "sg:city":"Grand Haven",
    "sg:classifiers":[
        {
            "category":"Wholesale",
            "subcategory":"Jewelry",
            "type":"Manufacturing & Wholesale Goods"
        }
    ],
    "sg:phone":"+1 616 844 0083",
    "sg:postcode":"49417",
    "sg:province":"MI",
    "sg:tags":[
        "equipment"
    ],
    "wof:name":"Carter Holdings",
    "wof:placetype":"venue"
},
  "geometry": {"coordinates":[-86.179378,43.037576],"type":"Point"}
}