{
  "type": "Feature",
  "properties": {
    "iso:country":"US",
    "sg:address":"3216 W Main St",
    "sg:city":"Lansing",
    "sg:classifiers":[
        {
            "category":"Travel",
            "subcategory":"Hotels & Motels",
            "type":"Entertainment"
        }
    ],
    "sg:phone":"+1 517 487 9119",
    "sg:postcode":"48917",
    "sg:province":"MI",
    "sg:tags":[
        "operation"
    ],
    "wof:name":"Burkewood Inn",
    "wof:placetype":"venue"
},
  "geometry": {"coordinates":[-84.597331,42.720262],"type":"Point"}
}