{
  "type": "Feature",
  "properties": {
    "iso:country":"US",
    "sg:address":"204 Albers Rd",
    "sg:city":"Bronson",
    "sg:classifiers":[
        {
            "category":"Education",
            "subcategory":"School",
            "type":"Public Place"
        }
    ],
    "sg:phone":"+1 517 369 4625",
    "sg:postcode":"49028",
    "sg:province":"MI",
    "wof:name":"St Mary's School",
    "wof:placetype":"venue"
},
  "geometry": {"coordinates":[-85.204222,41.875963],"type":"Point"}
}