{
  "type": "Feature",
  "properties": {
    "iso:country":"US",
    "sg:address":"16250 Northland Dr",
    "sg:city":"Southfield",
    "sg:classifiers":[
        {
            "category":"Banks & Credit Unions",
            "subcategory":"Bank",
            "type":"Services"
        }
    ],
    "sg:phone":"+1 248 423 0732",
    "sg:postcode":"48075",
    "sg:province":"MI",
    "sg:tags":[
        "loan",
        "real estate"
    ],
    "wof:name":"RYM Technology Holdings",
    "wof:placetype":"venue"
},
  "geometry": {"coordinates":[-83.210686,42.44497],"type":"Point"}
}