{
  "type": "Feature",
  "properties": {
    "iso:country":"US",
    "sg:address":"7672 Phelan Dr",
    "sg:city":"Clarkston",
    "sg:classifiers":[
        {
            "category":"Professional",
            "subcategory":"Business Services",
            "type":"Services"
        }
    ],
    "sg:phone":"+1 248 625 6866",
    "sg:postcode":"48346",
    "sg:province":"MI",
    "sg:tags":[
        "water",
        "treatment"
    ],
    "wof:name":"Aquatrol",
    "wof:placetype":"venue"
},
  "geometry": {"coordinates":[-83.436606,42.731693],"type":"Point"}
}