{
  "type": "Feature",
  "properties": {
    "iso:country":"US",
    "sg:address":"43956 24th Ave",
    "sg:city":"Bloomingdale",
    "sg:classifiers":[
        {
            "category":"Building & Trades",
            "subcategory":"Plumbing",
            "type":"Services"
        }
    ],
    "sg:phone":"+1 269 521 4327",
    "sg:postcode":"49026",
    "sg:province":"MI",
    "sg:tags":[
        "boiler",
        "cleaning"
    ],
    "wof:name":"Power Mechanical Svc",
    "wof:placetype":"venue"
},
  "geometry": {"coordinates":[-85.9593,42.3323],"type":"Point"}
}