{
  "type": "Feature",
  "properties": {
    "iso:country":"US",
    "sg:address":"4675 S 39 Rd",
    "sg:city":"Cadillac",
    "sg:classifiers":[
        {
            "category":"Retail",
            "subcategory":"Auto Repair",
            "type":"Services"
        }
    ],
    "sg:phone":"+1 231 775 8471",
    "sg:postcode":"49601",
    "sg:province":"MI",
    "sg:tags":[
        "truck"
    ],
    "wof:name":"Cadillac Truck Svc",
    "wof:placetype":"venue"
},
  "geometry": {"coordinates":[-85.436485,44.227897],"type":"Point"}
}