{
  "type": "Feature",
  "properties": {
    "iso:country":"US",
    "sg:address":"2291 Major Cir",
    "sg:city":"Davison",
    "sg:classifiers":[
        {
            "category":"Shopping",
            "subcategory":"Hobbies, Toys, & Games",
            "type":"Retail Goods"
        }
    ],
    "sg:phone":"+1 810 653 1201",
    "sg:postcode":"48423",
    "sg:province":"MI",
    "sg:tags":[
        "model",
        "supply"
    ],
    "wof:name":"Dusty Dungeon Hobbies Inc",
    "wof:placetype":"venue"
},
  "geometry": {"coordinates":[-83.544573,43.039653],"type":"Point"}
}