{
  "type": "Feature",
  "properties": {
    "iso:country":"US",
    "sg:address":"843 Riverside Dr",
    "sg:city":"Battle Creek",
    "sg:classifiers":[
        {
            "category":"Manufacturing",
            "subcategory":"Retail Goods",
            "type":"Manufacturing & Wholesale Goods"
        }
    ],
    "sg:phone":"+1 269 968 2442",
    "sg:postcode":"49015",
    "sg:province":"MI",
    "sg:tags":[
        "product",
        "mfg"
    ],
    "wof:name":"Webster Displays",
    "wof:placetype":"venue"
},
  "geometry": {"coordinates":[-85.188917,42.277855],"type":"Point"}
}