{
  "type": "Feature",
  "properties": {
    "iso:country":"US",
    "sg:address":"32400 Edward Ave",
    "sg:city":"Madison Heights",
    "sg:classifiers":[
        {
            "category":"Manufacturing",
            "subcategory":"Printing",
            "type":"Manufacturing & Wholesale Goods"
        }
    ],
    "sg:phone":"+1 248 588 4444",
    "sg:postcode":"48071",
    "sg:province":"MI",
    "sg:tags":[
        "printer"
    ],
    "wof:name":"Popcorn Press",
    "wof:placetype":"venue"
},
  "geometry": {"coordinates":[-83.10177400000001,42.528529],"type":"Point"}
}