{
  "type": "Feature",
  "properties": {
    "iso:country":"US",
    "sg:address":"5423 Sunnyside",
    "sg:city":"Clarkston",
    "sg:classifiers":[
        {
            "category":"Retail",
            "subcategory":"Laundry & Dry Cleaning",
            "type":"Services"
        }
    ],
    "sg:phone":"+1 248 673 2095",
    "sg:postcode":"48346",
    "sg:province":"MI",
    "sg:tags":[
        "cleaners",
        "rug",
        "carpet"
    ],
    "wof:name":"Kurt's Carpet & Upholstery Svc",
    "wof:placetype":"venue"
},
  "geometry": {"coordinates":[-83.366084,42.714685],"type":"Point"}
}