{
  "type": "Feature",
  "properties": {
    "iso:country":"US",
    "sg:address":"1407 Chicago Dr SW",
    "sg:city":"Wyoming",
    "sg:classifiers":[
        {
            "category":"Building & Trades",
            "subcategory":"Construction",
            "type":"Services"
        }
    ],
    "sg:phone":"+1 616 452 7611",
    "sg:postcode":"49509",
    "sg:province":"MI",
    "sg:tags":[
        "painter"
    ],
    "sg:website":"www.eckhoffdevries.com",
    "wof:name":"Eckhoff & De Vries Painting",
    "wof:placetype":"venue"
},
  "geometry": {"coordinates":[-85.703332,42.935547],"type":"Point"}
}