{
  "type": "Feature",
  "properties": {
    "iso:country":"US",
    "sg:address":"1039 Washington St",
    "sg:city":"Dearborn",
    "sg:classifiers":[
        {
            "category":"Health Services",
            "subcategory":"Doctor",
            "type":"Services"
        }
    ],
    "sg:phone":"+1 313 563 1033",
    "sg:postcode":"48124",
    "sg:province":"MI",
    "sg:tags":[
        "medicine",
        "internal"
    ],
    "wof:name":"Angeles D S MD",
    "wof:placetype":"venue"
},
  "geometry": {"coordinates":[-83.257301,42.3027],"type":"Point"}
}