{
  "type": "Feature",
  "properties": {
    "iso:country":"US",
    "sg:address":"14508 Valusek Dr",
    "sg:city":"Sterling Heights",
    "sg:classifiers":[
        {
            "category":"Cinema",
            "subcategory":"Movie Rental",
            "type":"Entertainment"
        }
    ],
    "sg:phone":"+1 586 268 3912",
    "sg:postcode":"48312",
    "sg:province":"MI",
    "sg:tags":[
        "video",
        "tape"
    ],
    "wof:name":"Heath Video Services Ltd",
    "wof:placetype":"venue"
},
  "geometry": {"coordinates":[-82.97739900000001,42.541325],"type":"Point"}
}