{
  "type": "Feature",
  "properties": {
    "iso:country":"US",
    "sg:address":"15090 Beck Road Suite 300",
    "sg:city":"Plymouth",
    "sg:classifiers":[
        {
            "category":"Professional",
            "subcategory":"Computer Services",
            "type":"Services"
        }
    ],
    "sg:postcode":"48170",
    "sg:province":"MI",
    "sg:tags":[
        "microsoft",
        "windows",
        "online",
        "reporting"
    ],
    "sg:website":"http://www.neowin.net",
    "wof:name":"Neowin",
    "wof:placetype":"venue"
},
  "geometry": {"coordinates":[-83.51004,42.39093],"type":"Point"}
}