{
  "type": "Feature",
  "properties": {
    "iso:country":"US",
    "sg:address":"420 E Main St",
    "sg:city":"Gaylord",
    "sg:classifiers":[
        {
            "category":"Health Services",
            "subcategory":"Doctor",
            "type":"Services"
        }
    ],
    "sg:phone":"+1 989 732 0813",
    "sg:postcode":"49735",
    "sg:province":"MI",
    "wof:name":"Robert L Darnell DDS",
    "wof:placetype":"venue"
},
  "geometry": {"coordinates":[-84.668657,45.027309],"type":"Point"}
}