{
  "type": "Feature",
  "properties": {
    "iso:country":"US",
    "sg:address":"93 N Pine St",
    "sg:city":"Gwinn",
    "sg:classifiers":[
        {
            "category":"Autos & Motor Vehicles",
            "subcategory":"Fuel & Gas Station",
            "type":"Retail Goods"
        }
    ],
    "sg:phone":"+1 906 346 5341",
    "sg:postcode":"49841",
    "sg:province":"MI",
    "sg:tags":[
        "a",
        "repair",
        "used",
        "gasoline",
        "general",
        "station"
    ],
    "wof:name":"Joes Auto Sales",
    "wof:placetype":"venue"
},
  "geometry": {"coordinates":[-87.438332,46.278484],"type":"Point"}
}