{
  "type": "Feature",
  "properties": {
    "iso:country":"US",
    "sg:address":"14568 Penrod St",
    "sg:city":"Detroit",
    "sg:classifiers":[
        {
            "category":"Professional",
            "subcategory":"Employment Agencies",
            "type":"Services"
        }
    ],
    "sg:phone":"+1 313 835 9259",
    "sg:postcode":"48223",
    "sg:province":"MI",
    "wof:name":"Bradley Personnel Contracting",
    "wof:placetype":"venue"
},
  "geometry": {"coordinates":[-83.22139300000001,42.395599],"type":"Point"}
}