{
  "type": "Feature",
  "properties": {
    "iso:country":"US",
    "sg:address":"7650 Mayfair St",
    "sg:city":"Taylor",
    "sg:classifiers":[
        {
            "category":"Building & Trades",
            "subcategory":"Plumbing",
            "type":"Services"
        }
    ],
    "sg:phone":"+1 313 388 5021",
    "sg:postcode":"48180",
    "sg:province":"MI",
    "sg:tags":[
        "contractor"
    ],
    "wof:name":"Anaconda",
    "wof:placetype":"venue"
},
  "geometry": {"coordinates":[-83.235924,42.254154],"type":"Point"}
}