{
  "type": "Feature",
  "properties": {
    "iso:country":"US",
    "sg:address":"326 W Huron Rd",
    "sg:city":"Au Gres",
    "sg:classifiers":[
        {
            "category":"Restaurant",
            "type":"Food & Drink"
        }
    ],
    "sg:phone":"+1 989 876 2900",
    "sg:postcode":"48703",
    "sg:province":"MI",
    "sg:tags":[
        "eating"
    ],
    "wof:name":"McDonalds",
    "wof:placetype":"venue"
},
  "geometry": {"coordinates":[-83.705507,44.048327],"type":"Point"}
}