{
  "type": "Feature",
  "properties": {
    "iso:country":"US",
    "sg:address":"4830 Georgia Dr",
    "sg:city":"Lake Orion",
    "sg:classifiers":[
        {
            "category":"Personal",
            "type":"Services"
        }
    ],
    "sg:phone":"+1 248 391 6932",
    "sg:postcode":"48359",
    "sg:province":"MI",
    "wof:name":"Miss Dees Home Inc",
    "wof:placetype":"venue"
},
  "geometry": {"coordinates":[-83.30546099999999,42.708906],"type":"Point"}
}