{
  "type": "Feature",
  "properties": {
    "iso:country":"US",
    "sg:address":"3180 N Adrian Hwy",
    "sg:city":"Adrian",
    "sg:classifiers":[
        {
            "category":"Building & Trades",
            "subcategory":"Construction",
            "type":"Services"
        }
    ],
    "sg:phone":"+1 517 266 9442",
    "sg:postcode":"49221",
    "sg:province":"MI",
    "sg:tags":[
        "contractor"
    ],
    "wof:name":"Midwest Custom Builders",
    "wof:placetype":"venue"
},
  "geometry": {"coordinates":[-84.00947499999999,41.928822],"type":"Point"}
}