{
  "type": "Feature",
  "properties": {
    "iso:country":"US",
    "sg:address":"23466 Barfield St",
    "sg:city":"Farmington",
    "sg:classifiers":[
        {
            "category":"Restaurant",
            "type":"Food & Drink"
        }
    ],
    "sg:phone":"+1 248 477 3665",
    "sg:postcode":"48336",
    "sg:province":"MI",
    "sg:tags":[
        "eating"
    ],
    "wof:name":"Laura J Musick",
    "wof:placetype":"venue"
},
  "geometry": {"coordinates":[-83.342912,42.466057],"type":"Point"}
}