{
  "type": "Feature",
  "properties": {
    "iso:country":"US",
    "sg:address":"1015 Gull Rd",
    "sg:city":"Kalamazoo",
    "sg:classifiers":[
        {
            "category":"Real Estate",
            "subcategory":"Developer",
            "type":"Services"
        }
    ],
    "sg:phone":"+1 269 337 8227",
    "sg:postcode":"49048",
    "sg:province":"MI",
    "sg:tags":[
        "cemetery"
    ],
    "wof:name":"Riverside Cemetery",
    "wof:placetype":"venue"
},
  "geometry": {"coordinates":[-85.56835700000001,42.301613],"type":"Point"}
}