{
  "type": "Feature",
  "properties": {
    "iso:country":"US",
    "sg:address":"3190 E Midland Rd",
    "sg:city":"Bay City",
    "sg:classifiers":[
        {
            "category":"Health Services",
            "subcategory":"Doctor",
            "type":"Services"
        }
    ],
    "sg:phone":"+1 517 667 6650",
    "sg:postcode":"48706",
    "sg:province":"MI",
    "sg:tags":[
        "medical"
    ],
    "wof:name":"Don Ko MD",
    "wof:placetype":"venue"
},
  "geometry": {"coordinates":[-83.92627299999999,43.602126],"type":"Point"}
}