{
  "type": "Feature",
  "properties": {
    "iso:country":"US",
    "sg:address":"2127 Spring Arbor Rd",
    "sg:city":"Jackson",
    "sg:classifiers":[
        {
            "category":"Professional",
            "subcategory":"Lawyer & Legal Services",
            "type":"Services"
        }
    ],
    "sg:phone":"+1 517 787 7600",
    "sg:postcode":"49203",
    "sg:province":"MI",
    "sg:tags":[
        "attorney"
    ],
    "wof:name":"Chalgian & Tripp Law Offs Pllc",
    "wof:placetype":"venue"
},
  "geometry": {"coordinates":[-84.439207,42.237337],"type":"Point"}
}