{
  "type": "Feature",
  "properties": {
    "iso:country":"US",
    "sg:address":"205 Mine St",
    "sg:city":"Norway",
    "sg:classifiers":[
        {
            "category":"Building & Trades",
            "subcategory":"Construction",
            "type":"Services"
        }
    ],
    "sg:phone":"+1 906 563 9257",
    "sg:postcode":"49870",
    "sg:province":"MI",
    "sg:tags":[
        "hanging",
        "contractor"
    ],
    "wof:name":"Eden Wallcovering",
    "wof:placetype":"venue"
},
  "geometry": {"coordinates":[-87.90506600000001,45.782374],"type":"Point"}
}