{
  "type": "Feature",
  "properties": {
    "iso:country":"US",
    "sg:address":"801 Monroe Ave NW",
    "sg:city":"Grand Rapids",
    "sg:classifiers":[
        {
            "category":"Organizations",
            "subcategory":"Community Association",
            "type":"Services"
        }
    ],
    "sg:phone":"+1 616 534 0440",
    "sg:postcode":"49503",
    "sg:province":"MI",
    "sg:tags":[
        "fraternal"
    ],
    "sg:website":"www.foresters.biz",
    "wof:name":"Independent Order Of Foresters",
    "wof:placetype":"venue"
},
  "geometry": {"coordinates":[-85.67249700000001,42.978204],"type":"Point"}
}