{
  "type": "Feature",
  "properties": {
    "iso:country":"US",
    "sg:address":"365 Meadow Bridge Dr",
    "sg:city":"Rochester",
    "sg:classifiers":[
        {
            "category":"Personal",
            "subcategory":"Beauty Salon",
            "type":"Services"
        }
    ],
    "sg:phone":"+1 248 650 9320",
    "sg:postcode":"48307",
    "sg:province":"MI",
    "sg:tags":[
        "shop"
    ],
    "wof:name":"Picassos Artistic Hair Design",
    "wof:placetype":"venue"
},
  "geometry": {"coordinates":[-83.13936,42.661151],"type":"Point"}
}