{
  "type": "Feature",
  "properties": {
    "iso:country":"US",
    "sg:address":"235 S Homer St",
    "sg:city":"Lansing",
    "sg:classifiers":[
        {
            "category":"Retail",
            "subcategory":"Auto Repair",
            "type":"Services"
        }
    ],
    "sg:phone":"+1 517 664 1755",
    "sg:postcode":"48912",
    "sg:province":"MI",
    "sg:tags":[
        "repairing",
        "automobile"
    ],
    "wof:name":"A & J Transmissions & Auto Rpr",
    "wof:placetype":"venue"
},
  "geometry": {"coordinates":[-84.509653,42.732628],"type":"Point"}
}