{
  "type": "Feature",
  "properties": {
    "iso:country":"US",
    "sg:address":"2113 W Vienna Rd",
    "sg:city":"Clio",
    "sg:classifiers":[
        {
            "category":"Farming",
            "subcategory":"Farm",
            "type":"Manufacturing & Wholesale Goods"
        }
    ],
    "sg:phone":"+1 810 686 3733",
    "sg:postcode":"48420",
    "sg:province":"MI",
    "wof:name":"Dennis Farms LLC",
    "wof:placetype":"venue"
},
  "geometry": {"coordinates":[-83.717051,43.177581],"type":"Point"}
}