{
  "type": "Feature",
  "properties": {
    "iso:country":"US",
    "sg:address":"1097 Union Lake Rd",
    "sg:city":"White Lake",
    "sg:classifiers":[
        {
            "category":"Insurance",
            "subcategory":"Insurance Agent",
            "type":"Services"
        }
    ],
    "sg:phone":"+1 248 366 3222",
    "sg:postcode":"48386",
    "sg:province":"MI",
    "wof:name":"Farm Bur Insurance Group",
    "wof:placetype":"venue"
},
  "geometry": {"coordinates":[-83.45814900000001,42.626597],"type":"Point"}
}