{
  "type": "Feature",
  "properties": {
    "iso:country":"US",
    "sg:address":"12850 Fountain Sq",
    "sg:city":"Davisburg",
    "sg:classifiers":[
        {
            "category":"Personal",
            "subcategory":"Beauty Salon",
            "type":"Services"
        }
    ],
    "sg:phone":"+1 248 882 3180",
    "sg:postcode":"48350",
    "sg:province":"MI",
    "wof:name":"Fountain Salon",
    "wof:placetype":"venue"
},
  "geometry": {"coordinates":[-83.546795,42.74732],"type":"Point"}
}