{
  "type": "Feature",
  "properties": {
    "iso:country":"US",
    "sg:address":"4897 Rochester Rd",
    "sg:city":"Troy",
    "sg:classifiers":[
        {
            "category":"Restaurant",
            "type":"Food & Drink"
        }
    ],
    "sg:phone":"+1 248 528 2860",
    "sg:postcode":"48085",
    "sg:province":"MI",
    "wof:name":"Michigan Multi-King Corp",
    "wof:placetype":"venue"
},
  "geometry": {"coordinates":[-83.129107,42.590671],"type":"Point"}
}