{
  "type": "Feature",
  "properties": {
    "iso:country":"US",
    "sg:address":"9380 Bray Rd",
    "sg:city":"Millington",
    "sg:classifiers":[
        {
            "category":"Shopping",
            "subcategory":"Used Merchandise",
            "type":"Retail Goods"
        }
    ],
    "sg:phone":"+1 989 871 9901",
    "sg:postcode":"48746",
    "sg:province":"MI",
    "sg:tags":[
        "second",
        "store",
        "hand"
    ],
    "wof:name":"Hidden Treasures",
    "wof:placetype":"venue"
},
  "geometry": {"coordinates":[-83.66161,43.254285],"type":"Point"}
}