{
  "type": "Feature",
  "properties": {
    "iso:country":"US",
    "sg:address":"5591 Sashabaw Rd",
    "sg:city":"Clarkston",
    "sg:classifiers":[
        {
            "category":"Home & Garden",
            "subcategory":"Hardware",
            "type":"Retail Goods"
        }
    ],
    "sg:phone":"+1 248 625 5377",
    "sg:postcode":"48346",
    "sg:province":"MI",
    "wof:name":"ACO Hardware",
    "wof:placetype":"venue"
},
  "geometry": {"coordinates":[-83.379138,42.722071],"type":"Point"}
}