{
  "type": "Feature",
  "properties": {
    "iso:country":"US",
    "sg:address":"3903 Hollywood Rd",
    "sg:city":"St Joseph",
    "sg:classifiers":[
        {
            "category":"Health Services",
            "subcategory":"Doctor",
            "type":"Services"
        }
    ],
    "sg:phone":"+1 269 408 1100",
    "sg:postcode":"49085",
    "sg:province":"MI",
    "sg:tags":[
        "physician",
        "surgeon"
    ],
    "wof:name":"Great Lakes Gastroenterology",
    "wof:placetype":"venue"
},
  "geometry": {"coordinates":[-86.45574000000001,42.046155],"type":"Point"}
}