{
  "type": "Feature",
  "properties": {
    "iso:country":"US",
    "sg:address":"2018 Rambling Rd",
    "sg:city":"Kalamazoo",
    "sg:classifiers":[
        {
            "category":"Education",
            "subcategory":"Dance Studio",
            "type":"Public Place"
        }
    ],
    "sg:phone":"+1 269 345 3433",
    "sg:postcode":"49008",
    "sg:province":"MI",
    "wof:name":"Ballet Arts",
    "wof:placetype":"venue"
},
  "geometry": {"coordinates":[-85.625456,42.270599],"type":"Point"}
}