{
  "type": "Feature",
  "properties": {
    "iso:country":"US",
    "sg:address":"8481 Eaton Rd",
    "sg:city":"Davisburg",
    "sg:classifiers":[
        {
            "category":"Retail",
            "subcategory":"Repair Shop",
            "type":"Services"
        }
    ],
    "sg:phone":"+1 248 634 3844",
    "sg:postcode":"48350",
    "sg:province":"MI",
    "wof:name":"Parsons Locksmithing",
    "wof:placetype":"venue"
},
  "geometry": {"coordinates":[-83.541196,42.756933],"type":"Point"}
}