{
  "type": "Feature",
  "properties": {
    "iso:country":"US",
    "sg:address":"5693 Filion Rd",
    "sg:city":"Pigeon",
    "sg:classifiers":[
        {
            "category":"Retail",
            "subcategory":"Repair Shop",
            "type":"Services"
        }
    ],
    "sg:phone":"+1 989 375 4350",
    "sg:postcode":"48755",
    "sg:province":"MI",
    "sg:tags":[
        "related"
    ],
    "wof:name":"S & I Inc",
    "wof:placetype":"venue"
},
  "geometry": {"coordinates":[-83.20969700000001,43.889392],"type":"Point"}
}