{
  "type": "Feature",
  "properties": {
    "iso:country":"US",
    "sg:address":"7170 Tuscarora Cir",
    "sg:city":"Indian River",
    "sg:classifiers":[
        {
            "category":"Recreation",
            "subcategory":"Marina",
            "type":"Entertainment"
        }
    ],
    "sg:phone":"+1 231 238 8570",
    "sg:postcode":"49749",
    "sg:province":"MI",
    "sg:tags":[
        "repairing",
        "boat"
    ],
    "wof:name":"Gearcase & Sterndrive Specs",
    "wof:placetype":"venue"
},
  "geometry": {"coordinates":[-84.631229,45.38009],"type":"Point"}
}