{
  "type": "Feature",
  "properties": {
    "iso:country":"US",
    "sg:address":"505 W Kalamazoo Ave",
    "sg:city":"Kalamazoo",
    "sg:classifiers":[
        {
            "category":"Shopping",
            "type":"Retail Goods"
        }
    ],
    "sg:phone":"+1 269 342 4131",
    "sg:postcode":"49007",
    "sg:province":"MI",
    "sg:tags":[
        "wedding",
        "supply"
    ],
    "wof:name":"Party Creations By Shirley",
    "wof:placetype":"venue"
},
  "geometry": {"coordinates":[-85.590632,42.294308],"type":"Point"}
}