{
  "type": "Feature",
  "properties": {
    "iso:country":"US",
    "sg:address":"5990 Springport Rd",
    "sg:city":"Jackson",
    "sg:classifiers":[
        {
            "category":"Organizations",
            "subcategory":"Religious Organization",
            "type":"Services"
        }
    ],
    "sg:phone":"+1 517 782 9550",
    "sg:postcode":"49201",
    "sg:province":"MI",
    "wof:name":"Bennett Community Church",
    "wof:placetype":"venue"
},
  "geometry": {"coordinates":[-84.48487900000001,42.294055],"type":"Point"}
}