{
  "type": "Feature",
  "properties": {
    "iso:country":"US",
    "sg:address":"180 Works Ave",
    "sg:city":"Cadillac",
    "sg:classifiers":[
        {
            "category":"Retail",
            "subcategory":"Auto Rental",
            "type":"Services"
        }
    ],
    "sg:phone":"+1 231 775 7104",
    "sg:postcode":"49601",
    "sg:province":"MI",
    "sg:tags":[
        "renting",
        "truck",
        "leasing"
    ],
    "wof:name":"U-Haul Co",
    "wof:placetype":"venue"
},
  "geometry": {"coordinates":[-85.404884,44.277684],"type":"Point"}
}