{
  "type": "Feature",
  "properties": {
    "iso:country":"US",
    "sg:address":"28231 Ford Rd",
    "sg:city":"Garden City",
    "sg:classifiers":[
        {
            "category":"Shopping",
            "subcategory":"Jewelry",
            "type":"Retail Goods"
        }
    ],
    "sg:phone":"+1 734 422 6810",
    "sg:postcode":"48135",
    "sg:province":"MI",
    "sg:website":"www.highglow.com",
    "wof:name":"Highglow Jewlers",
    "wof:placetype":"venue"
},
  "geometry": {"coordinates":[-83.316597,42.325901],"type":"Point"}
}