{
  "type": "Feature",
  "properties": {
    "iso:country":"US",
    "sg:address":"54738 Sherwood Ln",
    "sg:city":"Utica",
    "sg:classifiers":[
        {
            "category":"Real Estate",
            "subcategory":"Real Estate Operator",
            "type":"Services"
        }
    ],
    "sg:phone":"+1 586 739 1349",
    "sg:postcode":"48315",
    "sg:province":"MI",
    "sg:tags":[
        "building",
        "nonresidential"
    ],
    "wof:name":"Kenline Properties 2 LLC",
    "wof:placetype":"venue"
},
  "geometry": {"coordinates":[-82.981635,42.698242],"type":"Point"}
}