{
  "type": "Feature",
  "properties": {
    "iso:country":"US",
    "sg:address":"39359 Rivercrest Ave",
    "sg:city":"Harrison Twp",
    "sg:classifiers":[
        {
            "category":"Wholesale",
            "subcategory":"Electrical",
            "type":"Manufacturing & Wholesale Goods"
        }
    ],
    "sg:phone":"+1 586 954 3222",
    "sg:postcode":"48045",
    "sg:province":"MI",
    "sg:tags":[
        "equipment",
        "alarm",
        "burglar",
        "system"
    ],
    "wof:name":"Alarm Service Center Corp",
    "wof:placetype":"venue"
},
  "geometry": {"coordinates":[-82.819931,42.589422],"type":"Point"}
}