{
  "type": "Feature",
  "properties": {
    "iso:country":"US",
    "sg:address":"3305 Remembrance Rd NW",
    "sg:city":"Grand Rapids",
    "sg:classifiers":[
        {
            "category":"Food & Beverages",
            "subcategory":"Specialty",
            "type":"Retail Goods"
        }
    ],
    "sg:phone":"+1 616 453 5005",
    "sg:postcode":"49534",
    "sg:province":"MI",
    "sg:tags":[
        "equipment",
        "coffee",
        "handling",
        "roasting"
    ],
    "wof:name":"Rush Coffee Svc",
    "wof:placetype":"venue"
},
  "geometry": {"coordinates":[-85.749658,42.987834],"type":"Point"}
}