{
  "type": "Feature",
  "properties": {
    "iso:country":"US",
    "sg:address":"15100 Northline Rd",
    "sg:city":"Southgate",
    "sg:classifiers":[
        {
            "category":"Professional",
            "subcategory":"Employment Agencies",
            "type":"Services"
        }
    ],
    "sg:phone":"+1 734 281 2470",
    "sg:postcode":"48195",
    "sg:province":"MI",
    "wof:name":"A A R P Foundation Senior Employment",
    "wof:placetype":"venue"
},
  "geometry": {"coordinates":[-83.207802,42.2136],"type":"Point"}
}