{
  "type": "Feature",
  "properties": {
    "iso:country":"US",
    "sg:address":"260 Turner Rd",
    "sg:city":"Williamston",
    "sg:classifiers":[
        {
            "category":"Retail",
            "subcategory":"Animal Services",
            "type":"Services"
        }
    ],
    "sg:phone":"+1 517 655 2584",
    "sg:postcode":"48895",
    "sg:province":"MI",
    "sg:tags":[
        "horse",
        "training"
    ],
    "wof:name":"Horse Scape Farm",
    "wof:placetype":"venue"
},
  "geometry": {"coordinates":[-84.349795,42.700773],"type":"Point"}
}