{
  "type": "Feature",
  "properties": {
    "iso:country":"US",
    "sg:address":"113 W Broadway St",
    "sg:city":"Mount Pleasant",
    "sg:classifiers":[
        {
            "category":"Health Services",
            "subcategory":"Health Practitioner",
            "type":"Services"
        }
    ],
    "sg:phone":"+1 517 775 8240",
    "sg:postcode":"48858",
    "sg:province":"MI",
    "wof:name":"Saginaw Psychological",
    "wof:placetype":"venue"
},
  "geometry": {"coordinates":[-84.777582,43.604372],"type":"Point"}
}