{
  "type": "Feature",
  "properties": {
    "iso:country":"US",
    "sg:address":"20195 Mack Ave",
    "sg:city":"Grosse Pointe",
    "sg:classifiers":[
        {
            "category":"Restaurant",
            "type":"Food & Drink"
        }
    ],
    "sg:phone":"+1 313 885 6480",
    "sg:postcode":"48236",
    "sg:province":"MI",
    "sg:website":"www.bostonmarket.com",
    "wof:name":"Boston Market",
    "wof:placetype":"venue"
},
  "geometry": {"coordinates":[-82.908501,42.435398],"type":"Point"}
}