{
  "type": "Feature",
  "properties": {
    "iso:country":"US",
    "sg:address":"10080 E Potter Rd",
    "sg:city":"Davison",
    "sg:classifiers":[
        {
            "category":"Real Estate",
            "subcategory":"Developer",
            "type":"Services"
        }
    ],
    "sg:phone":"+1 810 653 8300",
    "sg:postcode":"48423",
    "sg:province":"MI",
    "sg:tags":[
        "cemetery"
    ],
    "wof:name":"Davison Cemetery",
    "wof:placetype":"venue"
},
  "geometry": {"coordinates":[-83.49950699999999,43.049312],"type":"Point"}
}