{
  "type": "Feature",
  "properties": {
    "iso:country":"US",
    "sg:address":"2695 Elmridge Dr NW",
    "sg:city":"Grand Rapids",
    "sg:classifiers":[
        {
            "category":"Utilities",
            "subcategory":"Refuse",
            "type":"Services"
        }
    ],
    "sg:phone":"+1 616 454 9405",
    "sg:postcode":"49534",
    "sg:province":"MI",
    "sg:tags":[
        "waste",
        "removal"
    ],
    "sg:website":"www.stericycle.com",
    "wof:name":"Stericycle Inc",
    "wof:placetype":"venue"
},
  "geometry": {"coordinates":[-85.743363,43.013133],"type":"Point"}
}