{
  "type": "Feature",
  "properties": {
    "iso:country":"US",
    "sg:address":"23503 S Dryburg Rd",
    "sg:city":"Rudyard",
    "sg:classifiers":[
        {
            "category":"Retail",
            "subcategory":"Auto Repair",
            "type":"Services"
        }
    ],
    "sg:phone":"+1 906 478 4004",
    "sg:postcode":"49780",
    "sg:province":"MI",
    "sg:tags":[
        "repairing",
        "automobile"
    ],
    "wof:name":"Ellison's Garage Inc",
    "wof:placetype":"venue"
},
  "geometry": {"coordinates":[-84.687793,46.165231],"type":"Point"}
}