{
  "type": "Feature",
  "properties": {
    "iso:country":"US",
    "sg:address":"8256 Chapp Ave",
    "sg:city":"Warren",
    "sg:classifiers":[
        {
            "category":"Professional",
            "type":"Services"
        }
    ],
    "sg:phone":"+1 586 759 1805",
    "sg:postcode":"48089",
    "sg:province":"MI",
    "sg:tags":[
        "establishment"
    ],
    "wof:name":"RMS",
    "wof:placetype":"venue"
},
  "geometry": {"coordinates":[-83.021918,42.469408],"type":"Point"}
}