{
  "type": "Feature",
  "properties": {
    "iso:country":"US",
    "sg:address":"3300 Dutcher Rd",
    "sg:city":"Howell",
    "sg:classifiers":[
        {
            "category":"Manufacturing",
            "subcategory":"Signs",
            "type":"Manufacturing & Wholesale Goods"
        }
    ],
    "sg:phone":"+1 517 546 0582",
    "sg:postcode":"48843",
    "sg:province":"MI",
    "sg:tags":[
        "specialty",
        "mfg"
    ],
    "wof:name":"Interactive Media Solution",
    "wof:placetype":"venue"
},
  "geometry": {"coordinates":[-84.02964299999999,42.549437],"type":"Point"}
}