{
  "type": "Feature",
  "properties": {
    "iso:country":"US",
    "sg:address":"599 W Brooks St",
    "sg:city":"Newaygo",
    "sg:classifiers":[
        {
            "category":"Organizations",
            "subcategory":"Religious Organization",
            "type":"Services"
        }
    ],
    "sg:phone":"+1 231 652 1286",
    "sg:postcode":"49337",
    "sg:province":"MI",
    "sg:tags":[
        "church"
    ],
    "wof:name":"Saint Bartholomew",
    "wof:placetype":"venue"
},
  "geometry": {"coordinates":[-85.80752099999999,43.410659],"type":"Point"}
}