{
  "type": "Feature",
  "properties": {
    "iso:country":"US",
    "sg:address":"4203 Highland Rd",
    "sg:city":"Waterford",
    "sg:classifiers":[
        {
            "category":"Personal",
            "type":"Services"
        }
    ],
    "sg:phone":"+1 248 683 9600",
    "sg:postcode":"48328",
    "sg:province":"MI",
    "wof:name":"Medical Weight Loss Clinic",
    "wof:placetype":"venue"
},
  "geometry": {"coordinates":[-83.367368,42.649964],"type":"Point"}
}