{
  "type": "Feature",
  "properties": {
    "iso:country":"US",
    "sg:address":"1376 S Main St",
    "sg:city":"Plymouth",
    "sg:classifiers":[
        {
            "category":"Building & Trades",
            "subcategory":"Construction",
            "type":"Services"
        }
    ],
    "sg:phone":"+1 734 453 0350",
    "sg:postcode":"48170",
    "sg:province":"MI",
    "sg:tags":[
        "hanging",
        "contractor"
    ],
    "wof:name":"Preferred Painting",
    "wof:placetype":"venue"
},
  "geometry": {"coordinates":[-83.469673,42.360527],"type":"Point"}
}