{
  "type": "Feature",
  "properties": {
    "iso:country":"US",
    "sg:address":"19040 John R St",
    "sg:city":"Highland Park",
    "sg:classifiers":[
        {
            "category":"Food & Beverages",
            "subcategory":"Groceries & Convenience Stores",
            "type":"Retail Goods"
        }
    ],
    "sg:phone":"+1 313 366 0440",
    "sg:postcode":"48203",
    "sg:province":"MI",
    "wof:name":"John R Food Market",
    "wof:placetype":"venue"
},
  "geometry": {"coordinates":[-83.102203,42.431599],"type":"Point"}
}