{
  "type": "Feature",
  "properties": {
    "iso:country":"US",
    "sg:address":"4777 Holton Rd",
    "sg:city":"Twin Lake",
    "sg:classifiers":[
        {
            "category":"Building & Trades",
            "subcategory":"Landscaping Services",
            "type":"Services"
        }
    ],
    "sg:phone":"+1 231 744 0008",
    "sg:postcode":"49457",
    "sg:province":"MI",
    "sg:tags":[
        "landscape",
        "contractor"
    ],
    "wof:name":"Dreamscape Inc",
    "wof:placetype":"venue"
},
  "geometry": {"coordinates":[-86.167827,43.339688],"type":"Point"}
}