{
  "type": "Feature",
  "properties": {
    "iso:country":"US",
    "sg:address":"31150 5 Mile Rd",
    "sg:city":"Livonia",
    "sg:classifiers":[
        {
            "category":"Restaurant",
            "type":"Food & Drink"
        }
    ],
    "sg:menulink":"http://www.allmenus.com/mi/livonia/182367-wendys/menu/",
    "sg:phone":"+1 734 522 9283",
    "sg:postcode":"48154",
    "sg:province":"MI",
    "sg:tags":[
        "burger",
        "american",
        "soup"
    ],
    "wof:name":"Wendy's",
    "wof:placetype":"venue"
},
  "geometry": {"coordinates":[-83.352507,42.397694],"type":"Point"}
}