{
  "type": "Feature",
  "properties": {
    "iso:country":"US",
    "sg:address":"3303 Breton Rd SE",
    "sg:city":"Grand Rapids",
    "sg:classifiers":[
        {
            "category":"Education",
            "subcategory":"School",
            "type":"Public Place"
        }
    ],
    "sg:phone":"+1 616 245 2203",
    "sg:postcode":"49512",
    "sg:province":"MI",
    "sg:tags":[
        "elementary"
    ],
    "wof:name":"Alexander Hamilton School",
    "wof:placetype":"venue"
},
  "geometry": {"coordinates":[-85.60756499999999,42.903417],"type":"Point"}
}