{
  "type": "Feature",
  "properties": {
    "iso:country":"US",
    "sg:address":"217 Romence Rd",
    "sg:city":"Portage",
    "sg:classifiers":[
        {
            "category":"Ice Cream",
            "type":"Food & Drink"
        }
    ],
    "sg:menulink":"http://www.allmenus.com/mi/portage/60201-ritters/menu/",
    "sg:phone":"+1 269 321 8800",
    "sg:postcode":"49024",
    "sg:province":"MI",
    "sg:tags":[
        "american"
    ],
    "wof:name":"Ritters",
    "wof:placetype":"venue"
},
  "geometry": {"coordinates":[-85.59353,42.215522],"type":"Point"}
}