{
  "type": "Feature",
  "properties": {
    "iso:country":"US",
    "sg:address":"7966 Perry Lake Rd",
    "sg:city":"Clarkston",
    "sg:classifiers":[
        {
            "category":"Building & Trades",
            "subcategory":"Pest Control",
            "type":"Services"
        }
    ],
    "sg:phone":"+1 248 620 5252",
    "sg:postcode":"48348",
    "sg:province":"MI",
    "wof:name":"Time Tested Pest Control Inc",
    "wof:placetype":"venue"
},
  "geometry": {"coordinates":[-83.404866,42.754761],"type":"Point"}
}