{
  "type": "Feature",
  "properties": {
    "iso:country":"US",
    "sg:address":"18401 Champaign Rd",
    "sg:city":"Allen Park",
    "sg:classifiers":[
        {
            "category":"Education",
            "subcategory":"School",
            "type":"Public Place"
        }
    ],
    "sg:phone":"+1 313 386 3699",
    "sg:postcode":"48101",
    "sg:province":"MI",
    "wof:name":"Allen Park Public Schools",
    "wof:placetype":"venue"
},
  "geometry": {"coordinates":[-83.225098,42.249199],"type":"Point"}
}