{
  "type": "Feature",
  "properties": {
    "iso:country":"US",
    "sg:address":"75 Oak St",
    "sg:city":"Manistee",
    "sg:classifiers":[
        {
            "category":"Shopping",
            "subcategory":"Gifts & Souvenirs",
            "type":"Retail Goods"
        }
    ],
    "sg:phone":"+1 231 723 7883",
    "sg:postcode":"49660",
    "sg:province":"MI",
    "wof:name":"Bear North",
    "wof:placetype":"venue"
},
  "geometry": {"coordinates":[-86.325379,44.246901],"type":"Point"}
}