{
  "type": "Feature",
  "properties": {
    "iso:country":"US",
    "sg:address":"10281 E San Remo Blvd",
    "sg:city":"Traverse City",
    "sg:classifiers":[
        {
            "category":"Real Estate",
            "subcategory":"Real Estate Agent",
            "type":"Services"
        }
    ],
    "sg:phone":"+1 231 946 2021",
    "sg:postcode":"49684",
    "sg:province":"MI",
    "wof:name":"J M Mc Cafferty & Assoc",
    "wof:placetype":"venue"
},
  "geometry": {"coordinates":[-85.649636,44.825848],"type":"Point"}
}