{
  "type": "Feature",
  "properties": {
    "iso:country":"US",
    "sg:address":"135 N Caseville Rd",
    "sg:city":"Pigeon",
    "sg:classifiers":[
        {
            "category":"Health Services",
            "subcategory":"Doctor",
            "type":"Services"
        }
    ],
    "sg:phone":"+1 989 453 3798",
    "sg:postcode":"48755",
    "sg:province":"MI",
    "sg:tags":[
        "physician",
        "surgeon"
    ],
    "wof:name":"Scheurer Professional Ctr",
    "wof:placetype":"venue"
},
  "geometry": {"coordinates":[-83.279501,43.831345],"type":"Point"}
}