{
  "type": "Feature",
  "properties": {
    "iso:country":"US",
    "sg:address":"159 W Pearl St",
    "sg:city":"Jackson",
    "sg:classifiers":[
        {
            "category":"Building & Trades",
            "subcategory":"Landscaping Services",
            "type":"Services"
        }
    ],
    "sg:phone":"+1 517 789 7961",
    "sg:postcode":"49201",
    "sg:province":"MI",
    "sg:tags":[
        "lawn",
        "maintenance",
        "grounds"
    ],
    "wof:name":"Right Touch Lawn Svc",
    "wof:placetype":"venue"
},
  "geometry": {"coordinates":[-84.407358,42.248362],"type":"Point"}
}