{
  "type": "Feature",
  "properties": {
    "iso:country":"US",
    "sg:address":"5301 Comstock Ave",
    "sg:city":"Kalamazoo",
    "sg:classifiers":[
        {
            "category":"Restaurant",
            "type":"Food & Drink"
        }
    ],
    "sg:phone":"+1 269 345 0511",
    "sg:postcode":"49048",
    "sg:province":"MI",
    "sg:tags":[
        "banquet",
        "rooms"
    ],
    "wof:name":"Lamplighter Inn",
    "wof:placetype":"venue"
},
  "geometry": {"coordinates":[-85.52968300000001,42.283405],"type":"Point"}
}