{
  "type": "Feature",
  "properties": {
    "iso:country":"US",
    "sg:address":"12300 Linnhurst St",
    "sg:city":"Detroit",
    "sg:classifiers":[
        {
            "category":"Education",
            "subcategory":"School",
            "type":"Public Place"
        }
    ],
    "sg:phone":"+1 313 866 2200",
    "sg:postcode":"48205",
    "sg:province":"MI",
    "wof:name":"Detroit Public Schools",
    "wof:placetype":"venue"
},
  "geometry": {"coordinates":[-82.999577,42.430823],"type":"Point"}
}