{
  "type": "Feature",
  "properties": {
    "iso:country":"US",
    "sg:address":"1605 N Finkle Rd",
    "sg:city":"Harbor Beach",
    "sg:phone":"+1 989 479 6727",
    "sg:postcode":"48441",
    "sg:province":"MI",
    "sg:tags":[
        "farm",
        "field",
        "corn",
        "wheat",
        "crop"
    ],
    "wof:name":"Daniel Geiger",
    "wof:placetype":"venue"
},
  "geometry": {"coordinates":[-82.762458,43.845567],"type":"Point"}
}