{
  "type": "Feature",
  "properties": {
    "iso:country":"US",
    "sg:address":"30520 Groesbeck Hwy",
    "sg:city":"Roseville",
    "sg:classifiers":[
        {
            "category":"Autos & Motor Vehicles",
            "subcategory":"Auto Supplies",
            "type":"Retail Goods"
        }
    ],
    "sg:phone":"+1 586 777 7777",
    "sg:postcode":"48066",
    "sg:province":"MI",
    "sg:tags":[
        "automobile",
        "parts"
    ],
    "wof:name":"S & G Imported Car Parts",
    "wof:placetype":"venue"
},
  "geometry": {"coordinates":[-82.947676,42.522407],"type":"Point"}
}