{
  "type": "Feature",
  "properties": {
    "iso:country":"US",
    "sg:address":"45855 Co Rd 653",
    "sg:city":"Paw Paw",
    "sg:classifiers":[
        {
            "category":"Professional",
            "subcategory":"Management & Consulting",
            "type":"Services"
        }
    ],
    "sg:phone":"+1 269 657 5400",
    "sg:postcode":"49079",
    "sg:province":"MI",
    "sg:tags":[
        "consultant"
    ],
    "wof:name":"Perspectives Consulting Group",
    "wof:placetype":"venue"
},
  "geometry": {"coordinates":[-85.85996900000001,42.251923],"type":"Point"}
}