{
  "type": "Feature",
  "properties": {
    "iso:country":"US",
    "sg:address":"18495 Birch Dr",
    "sg:city":"Macomb",
    "sg:classifiers":[
        {
            "category":"Professional",
            "subcategory":"Business Services",
            "type":"Services"
        }
    ],
    "sg:phone":"+1 586 228 1282",
    "sg:postcode":"48044",
    "sg:province":"MI",
    "wof:name":"Creative Asset Solutions LLC",
    "wof:placetype":"venue"
},
  "geometry": {"coordinates":[-82.93795799999999,42.634166],"type":"Point"}
}