{
  "type": "Feature",
  "properties": {
    "iso:country":"US",
    "sg:address":"12305 Beech Daly Rd",
    "sg:city":"Taylor",
    "sg:classifiers":[
        {
            "category":"Retail",
            "subcategory":"Event Space",
            "type":"Services"
        }
    ],
    "sg:phone":"+1 734 946 5727",
    "sg:postcode":"48180",
    "sg:province":"MI",
    "sg:tags":[
        "venue"
    ],
    "wof:name":"Local 26M-S E I U",
    "wof:placetype":"venue"
},
  "geometry": {"coordinates":[-83.288101,42.215401],"type":"Point"}
}