{
  "type": "Feature",
  "properties": {
    "iso:country":"US",
    "sg:address":"1218 Struble Rd",
    "sg:city":"Muir",
    "sg:phone":"+1 989 855 3878",
    "sg:postcode":"48860",
    "sg:province":"MI",
    "sg:tags":[
        "farm",
        "field",
        "crop"
    ],
    "wof:name":"Mark Fletcher",
    "wof:placetype":"venue"
},
  "geometry": {"coordinates":[-84.916804,43.008943],"type":"Point"}
}