{
  "type": "Feature",
  "properties": {
    "iso:country":"US",
    "sg:address":"28630 Southfield Rd",
    "sg:city":"Lathrup Village",
    "sg:classifiers":[
        {
            "category":"Personal",
            "subcategory":"Nail Salon",
            "type":"Services"
        }
    ],
    "sg:phone":"+1 248 559 1245",
    "sg:postcode":"48076",
    "sg:province":"MI",
    "wof:name":"Nail Room the",
    "wof:placetype":"venue"
},
  "geometry": {"coordinates":[-83.222397,42.4995],"type":"Point"}
}