{
  "type": "Feature",
  "properties": {
    "iso:country":"US",
    "sg:address":"1274 Library St",
    "sg:city":"Detroit",
    "sg:classifiers":[
        {
            "category":"Organizations",
            "subcategory":"Professional Association",
            "type":"Services"
        }
    ],
    "sg:phone":"+1 313 965 5077",
    "sg:postcode":"48226",
    "sg:province":"MI",
    "sg:tags":[
        "business"
    ],
    "wof:name":"Black Women Contracting Assn",
    "wof:placetype":"venue"
},
  "geometry": {"coordinates":[-83.047223,42.334417],"type":"Point"}
}