{
  "type": "Feature",
  "properties": {
    "iso:country":"US",
    "sg:address":"8747 Harris Rd",
    "sg:city":"Dexter",
    "sg:classifiers":[
        {
            "category":"Social Services",
            "subcategory":"Child Care",
            "type":"Services"
        }
    ],
    "sg:phone":"+1 734 426 2155",
    "sg:postcode":"48130",
    "sg:province":"MI",
    "sg:tags":[
        "day"
    ],
    "wof:name":"Leapsnbounds",
    "wof:placetype":"venue"
},
  "geometry": {"coordinates":[-83.906381,42.349397],"type":"Point"}
}