{
  "type": "Feature",
  "properties": {
    "iso:country":"US",
    "sg:address":"7203 Hudson Ave",
    "sg:city":"Warren",
    "sg:classifiers":[
        {
            "category":"Building & Trades",
            "subcategory":"Cleaning & Sanitation",
            "type":"Services"
        }
    ],
    "sg:phone":"+1 586 755 9428",
    "sg:postcode":"48091",
    "sg:province":"MI",
    "sg:tags":[
        "maintenance"
    ],
    "wof:name":"D & KS Cleaning Co",
    "wof:placetype":"venue"
},
  "geometry": {"coordinates":[-83.02931,42.457935],"type":"Point"}
}