{
  "type": "Feature",
  "properties": {
    "iso:country":"US",
    "sg:address":"5640 Underwood St",
    "sg:city":"Detroit",
    "sg:classifiers":[
        {
            "category":"Social Services",
            "subcategory":"Child Care",
            "type":"Services"
        }
    ],
    "sg:phone":"+1 313 931 5679",
    "sg:postcode":"48204",
    "sg:province":"MI",
    "sg:tags":[
        "day"
    ],
    "wof:name":"Nikkis Kids",
    "wof:placetype":"venue"
},
  "geometry": {"coordinates":[-83.136489,42.36117],"type":"Point"}
}