{
  "type": "Feature",
  "properties": {
    "iso:country":"US",
    "sg:address":"4944 Lakeshore Rd",
    "sg:city":"Lexington",
    "sg:classifiers":[
        {
            "category":"Health Services",
            "subcategory":"Medical Lab",
            "type":"Services"
        }
    ],
    "sg:phone":"+1 810 359 8827",
    "sg:postcode":"48450",
    "sg:province":"MI",
    "sg:tags":[
        "laboratory",
        "dental"
    ],
    "wof:name":"Vans Dental Laboratory",
    "wof:placetype":"venue"
},
  "geometry": {"coordinates":[-82.53202400000001,43.284561],"type":"Point"}
}