{
  "type": "Feature",
  "properties": {
    "iso:country":"US",
    "sg:address":"1118 N Leroy St",
    "sg:city":"Fenton",
    "sg:classifiers":[
        {
            "category":"Personal",
            "subcategory":"Barber",
            "type":"Services"
        }
    ],
    "sg:phone":"+1 810 750 0873",
    "sg:postcode":"48430",
    "sg:province":"MI",
    "sg:tags":[
        "shop"
    ],
    "wof:name":"Judy's Barber Shop",
    "wof:placetype":"venue"
},
  "geometry": {"coordinates":[-83.707331,42.809314],"type":"Point"}
}