{
  "type": "Feature",
  "properties": {
    "iso:country":"US",
    "sg:address":"170 North Ave",
    "sg:city":"Battle Creek",
    "sg:classifiers":[
        {
            "category":"Health Services",
            "subcategory":"Chiropractor",
            "type":"Services"
        }
    ],
    "sg:phone":"+1 269 963 8249",
    "sg:postcode":"49017",
    "sg:province":"MI",
    "wof:name":"James R Fausey Office",
    "wof:placetype":"venue"
},
  "geometry": {"coordinates":[-85.18022000000001,42.326715],"type":"Point"}
}