{
  "type": "Feature",
  "properties": {
    "iso:country":"US",
    "sg:address":"114 E Main St",
    "sg:city":"Boyne City",
    "sg:classifiers":[
        {
            "category":"Shopping",
            "type":"Retail Goods"
        }
    ],
    "sg:phone":"+1 231 582 2620",
    "sg:postcode":"49712",
    "sg:province":"MI",
    "sg:tags":[
        "picture",
        "frame"
    ],
    "wof:name":"Sweetgrass",
    "wof:placetype":"venue"
},
  "geometry": {"coordinates":[-85.01476700000001,45.211809],"type":"Point"}
}