{
  "type": "Feature",
  "properties": {
    "iso:country":"US",
    "sg:address":"1815 Comfort St",
    "sg:city":"Lansing",
    "sg:classifiers":[
        {
            "category":"Professional",
            "subcategory":"Business Services",
            "type":"Services"
        }
    ],
    "sg:phone":"+1 517 487 3120",
    "sg:postcode":"48915",
    "sg:province":"MI",
    "wof:name":"V I P Household Support Svcs",
    "wof:placetype":"venue"
},
  "geometry": {"coordinates":[-84.57463,42.75536],"type":"Point"}
}