{
  "type": "Feature",
  "properties": {
    "iso:country":"US",
    "sg:address":"12826 Georgia Ave",
    "sg:city":"Grand Ledge",
    "sg:classifiers":[
        {
            "category":"Retail",
            "subcategory":"Repair Shop",
            "type":"Services"
        }
    ],
    "sg:phone":"+1 517 622 4640",
    "sg:postcode":"48837",
    "sg:province":"MI",
    "wof:name":"J D Hydraulics",
    "wof:placetype":"venue"
},
  "geometry": {"coordinates":[-84.765423,42.753113],"type":"Point"}
}