{
  "type": "Feature",
  "properties": {
    "iso:country":"US",
    "sg:address":"6765 Bloomfield Ln",
    "sg:city":"West Bloomfield",
    "sg:classifiers":[
        {
            "category":"Health Services",
            "subcategory":"Doctor",
            "type":"Services"
        }
    ],
    "sg:phone":"+1 248 478 1232",
    "sg:postcode":"48322",
    "sg:province":"MI",
    "sg:tags":[
        "gynecologist"
    ],
    "wof:name":"East Gyn Center",
    "wof:placetype":"venue"
},
  "geometry": {"coordinates":[-83.33282800000001,42.543228],"type":"Point"}
}