{
  "type": "Feature",
  "properties": {
    "iso:country":"US",
    "sg:address":"415 W Hackley Ave",
    "sg:city":"Muskegon",
    "sg:classifiers":[
        {
            "category":"Manufacturing",
            "subcategory":"Tools & Machinery",
            "type":"Manufacturing & Wholesale Goods"
        }
    ],
    "sg:phone":"+1 231 737 2189",
    "sg:postcode":"49444",
    "sg:province":"MI",
    "sg:tags":[
        "machine",
        "shop"
    ],
    "wof:name":"JFK Machine",
    "wof:placetype":"venue"
},
  "geometry": {"coordinates":[-86.255441,43.212417],"type":"Point"}
}