{
  "type": "Feature",
  "properties": {
    "iso:country":"US",
    "sg:address":"121 W Superior St",
    "sg:city":"Ishpeming",
    "sg:classifiers":[
        {
            "category":"Real Estate",
            "subcategory":"Real Estate Agent",
            "type":"Services"
        }
    ],
    "sg:phone":"+1 906 486 6614",
    "sg:postcode":"49849",
    "sg:province":"MI",
    "wof:name":"Kenneth M Dymond",
    "wof:placetype":"venue"
},
  "geometry": {"coordinates":[-87.674442,46.488365],"type":"Point"}
}