{
  "type": "Feature",
  "properties": {
    "iso:country":"US",
    "sg:address":"801 Water St",
    "sg:city":"East Jordan",
    "sg:classifiers":[
        {
            "category":"Shopping",
            "subcategory":"Bicycles & Sporting Goods",
            "type":"Retail Goods"
        }
    ],
    "sg:phone":"+1 231 536 3521",
    "sg:postcode":"49727",
    "sg:province":"MI",
    "sg:tags":[
        "bait",
        "fishing"
    ],
    "wof:name":"Tom's Bait & Tackle",
    "wof:placetype":"venue"
},
  "geometry": {"coordinates":[-85.14138699999999,45.154122],"type":"Point"}
}