{
  "type": "Feature",
  "properties": {
    "iso:country":"US",
    "sg:address":"2681 Ashmun St",
    "sg:city":"Sault Ste Marie",
    "sg:classifiers":[
        {
            "category":"Retail",
            "subcategory":"Car Wash",
            "type":"Services"
        }
    ],
    "sg:phone":"+1 906 632 9722",
    "sg:postcode":"49783",
    "sg:province":"MI",
    "sg:tags":[
        "polishing",
        "washing"
    ],
    "wof:name":"Reno's Car Care",
    "wof:placetype":"venue"
},
  "geometry": {"coordinates":[-84.353785,46.474888],"type":"Point"}
}