{
  "type": "Feature",
  "properties": {
    "iso:country":"US",
    "sg:address":"3999 Alpenhorn Dr NW",
    "sg:city":"Comstock Park",
    "sg:classifiers":[
        {
            "category":"Social Services",
            "subcategory":"Child Care",
            "type":"Services"
        }
    ],
    "sg:phone":"+1 616 785 2772",
    "sg:postcode":"49321",
    "sg:province":"MI",
    "wof:name":"Family & Friends Childcare",
    "wof:placetype":"venue"
},
  "geometry": {"coordinates":[-85.688197,43.035471],"type":"Point"}
}