{
  "type": "Feature",
  "properties": {
    "iso:country":"US",
    "sg:address":"1701 E Front St",
    "sg:city":"Traverse City",
    "sg:classifiers":[
        {
            "category":"Communications",
            "subcategory":"Radio Station",
            "type":"Services"
        }
    ],
    "sg:phone":"+1 231 995 1090",
    "sg:postcode":"49686",
    "sg:province":"MI",
    "sg:tags":[
        "company",
        "broadcasting"
    ],
    "wof:name":"WNMC",
    "wof:placetype":"venue"
},
  "geometry": {"coordinates":[-85.58428600000001,44.764161],"type":"Point"}
}