{
  "type": "Feature",
  "properties": {
    "iso:country":"US",
    "sg:address":"7421 Windsor Woods Dr",
    "sg:city":"Canton",
    "sg:classifiers":[
        {
            "category":"Retail",
            "subcategory":"Car Wash",
            "type":"Services"
        }
    ],
    "sg:phone":"+1 734 454 5496",
    "sg:postcode":"48187",
    "sg:province":"MI",
    "sg:tags":[
        "carwash"
    ],
    "wof:name":"Picture Perfect Detailing",
    "wof:placetype":"venue"
},
  "geometry": {"coordinates":[-83.470252,42.338367],"type":"Point"}
}