{
  "type": "Feature",
  "properties": {
    "iso:country":"US",
    "sg:address":"13245 E State Fair St",
    "sg:city":"Detroit",
    "sg:classifiers":[
        {
            "category":"Professional",
            "subcategory":"Art Services",
            "type":"Services"
        }
    ],
    "sg:phone":"+1 313 839 4781",
    "sg:postcode":"48205",
    "sg:province":"MI",
    "sg:tags":[
        "graphic",
        "designer"
    ],
    "wof:name":"Dame Design LLC",
    "wof:placetype":"venue"
},
  "geometry": {"coordinates":[-82.98944899999999,42.44216],"type":"Point"}
}