{
  "type": "Feature",
  "properties": {
    "iso:country":"US",
    "sg:address":"1393 Wheaton Dr",
    "sg:city":"Troy",
    "sg:classifiers":[
        {
            "category":"Wholesale",
            "subcategory":"Machinery & Supplies",
            "type":"Manufacturing & Wholesale Goods"
        }
    ],
    "sg:phone":"+1 248 619 0142",
    "sg:postcode":"48083",
    "sg:province":"MI",
    "sg:tags":[
        "equipment",
        "material",
        "handling"
    ],
    "wof:name":"Linpac Materials Handling",
    "wof:placetype":"venue"
},
  "geometry": {"coordinates":[-83.12810899999999,42.557227],"type":"Point"}
}