{
  "type": "Feature",
  "properties": {
    "iso:country":"US",
    "sg:address":"3765 N Mill Rd",
    "sg:city":"Dryden",
    "sg:classifiers":[
        {
            "category":"Retail",
            "subcategory":"Auto Repair",
            "type":"Services"
        }
    ],
    "sg:phone":"+1 810 796 3223",
    "sg:postcode":"48428",
    "sg:province":"MI",
    "sg:tags":[
        "repairing",
        "automobile",
        "general"
    ],
    "wof:name":"Master's Automotive",
    "wof:placetype":"venue"
},
  "geometry": {"coordinates":[-83.125398,42.951672],"type":"Point"}
}