{
  "type": "Feature",
  "properties": {
    "iso:country":"US",
    "sg:address":"20500 Lahser Rd",
    "sg:city":"Detroit",
    "sg:classifiers":[
        {
            "category":"Food & Beverages",
            "subcategory":"Meat & Fish",
            "type":"Retail Goods"
        }
    ],
    "sg:phone":"+1 313 794 1000",
    "sg:postcode":"48219",
    "sg:province":"MI",
    "sg:tags":[
        "shop",
        "market"
    ],
    "wof:name":"Meat Town",
    "wof:placetype":"venue"
},
  "geometry": {"coordinates":[-83.258698,42.442101],"type":"Point"}
}