{
  "type": "Feature",
  "properties": {
    "iso:country":"US",
    "sg:address":"3190 Lake Michigan Dr NW",
    "sg:city":"Grand Rapids",
    "sg:classifiers":[
        {
            "category":"Organizations",
            "subcategory":"Religious Organization",
            "type":"Services"
        }
    ],
    "sg:phone":"+1 616 677 3223",
    "sg:postcode":"49544",
    "sg:province":"MI",
    "wof:name":"Voice Of Pentecost",
    "wof:placetype":"venue"
},
  "geometry": {"coordinates":[-85.86716199999999,42.972094],"type":"Point"}
}