{
  "type": "Feature",
  "properties": {
    "iso:country":"US",
    "sg:address":"23411 Jefferson Ave",
    "sg:city":"St Clair Shores",
    "sg:classifiers":[
        {
            "category":"Professional",
            "subcategory":"Lawyer & Legal Services",
            "type":"Services"
        }
    ],
    "sg:phone":"+1 586 779 5539",
    "sg:postcode":"48080",
    "sg:province":"MI",
    "sg:tags":[
        "planning",
        "estate"
    ],
    "wof:name":"Estate Information Law Ctr",
    "wof:placetype":"venue"
},
  "geometry": {"coordinates":[-82.88235,42.460549],"type":"Point"}
}