{
  "type": "Feature",
  "properties": {
    "iso:country":"US",
    "sg:address":"185 W 8th St",
    "sg:city":"Holland",
    "sg:classifiers":[
        {
            "category":"Manufacturing",
            "subcategory":"Tools & Machinery",
            "type":"Manufacturing & Wholesale Goods"
        }
    ],
    "sg:phone":"+1 616 392 9803",
    "sg:postcode":"49423",
    "sg:province":"MI",
    "sg:tags":[
        "machine",
        "shop"
    ],
    "sg:website":"www.ixlmachine.com",
    "wof:name":"IXL Machine Shop",
    "wof:placetype":"venue"
},
  "geometry": {"coordinates":[-86.115658,42.790324],"type":"Point"}
}