{
  "type": "Feature",
  "properties": {
    "iso:country":"US",
    "sg:address":"28418 Telegraph Rd",
    "sg:city":"Flat Rock",
    "sg:classifiers":[
        {
            "category":"Professional",
            "type":"Services"
        }
    ],
    "sg:phone":"+1 734 782 1855",
    "sg:postcode":"48134",
    "sg:province":"MI",
    "sg:tags":[
        "caterer"
    ],
    "wof:name":"Jim's Butcher Shop & Catering",
    "wof:placetype":"venue"
},
  "geometry": {"coordinates":[-83.292413,42.099665],"type":"Point"}
}