{
  "type": "Feature",
  "properties": {
    "iso:country":"US",
    "sg:address":"32440 Dequindre Rd",
    "sg:city":"Warren",
    "sg:classifiers":[
        {
            "category":"Professional",
            "type":"Services"
        }
    ],
    "sg:phone":"+1 586 979 2278",
    "sg:postcode":"48071",
    "sg:province":"MI",
    "sg:tags":[
        "establishment"
    ],
    "wof:name":"Tandem Marketing",
    "wof:placetype":"venue"
},
  "geometry": {"coordinates":[-83.086713,42.529099],"type":"Point"}
}