{
  "type": "Feature",
  "properties": {
    "iso:country":"US",
    "sg:address":"42500 Hayes Rd Ste 800",
    "sg:city":"Clinton Township",
    "sg:classifiers":[
        {
            "category":"Health Services",
            "subcategory":"Doctor",
            "type":"Services"
        }
    ],
    "sg:phone":"+1 586 228 0200",
    "sg:postcode":"48038",
    "sg:province":"MI",
    "wof:name":"Shelby Macomb Family Practice",
    "wof:placetype":"venue"
},
  "geometry": {"coordinates":[-82.972397,42.608601],"type":"Point"}
}