{
  "type": "Feature",
  "properties": {
    "iso:country":"US",
    "sg:address":"5448 Townline Rd",
    "sg:city":"Birch Run",
    "sg:classifiers":[
        {
            "category":"Building & Trades",
            "subcategory":"Construction",
            "type":"Services"
        }
    ],
    "sg:phone":"+1 989 777 0822",
    "sg:postcode":"48415",
    "sg:province":"MI",
    "sg:tags":[
        "excavating",
        "contractor"
    ],
    "wof:name":"Musselman Excavating",
    "wof:placetype":"venue"
},
  "geometry": {"coordinates":[-83.850735,43.307368],"type":"Point"}
}