{
  "type": "Feature",
  "properties": {
    "iso:country":"US",
    "sg:address":"1806 Magnolia Blvd",
    "sg:city":"Monroe",
    "sg:classifiers":[
        {
            "category":"Professional",
            "subcategory":"Computer Services",
            "type":"Services"
        }
    ],
    "sg:phone":"+1 734 457 5026",
    "sg:postcode":"48161",
    "sg:province":"MI",
    "sg:tags":[
        "website",
        "design"
    ],
    "wof:name":"East Side Hosting",
    "wof:placetype":"venue"
},
  "geometry": {"coordinates":[-83.427002,41.914762],"type":"Point"}
}