{
  "type": "Feature",
  "properties": {
    "iso:country":"US",
    "sg:address":"1242 28th St SW",
    "sg:city":"Wyoming",
    "sg:classifiers":[
        {
            "category":"Shopping",
            "subcategory":"Department Store",
            "type":"Retail Goods"
        }
    ],
    "sg:phone":"+1 616 530 8888",
    "sg:postcode":"49509",
    "sg:province":"MI",
    "sg:tags":[
        "shop"
    ],
    "wof:name":"Dollar Tree",
    "wof:placetype":"venue"
},
  "geometry": {"coordinates":[-85.698363,42.913339],"type":"Point"}
}