{
  "type": "Feature",
  "properties": {
    "iso:country":"US",
    "sg:address":"7735 Boardwalk",
    "sg:city":"Brighton",
    "sg:classifiers":[
        {
            "category":"Professional",
            "type":"Services"
        }
    ],
    "sg:phone":"+1 248 437 3010",
    "sg:postcode":"48116",
    "sg:province":"MI",
    "sg:tags":[
        "establishment"
    ],
    "wof:name":"Triple J Enterprises",
    "wof:placetype":"venue"
},
  "geometry": {"coordinates":[-83.693237,42.492719],"type":"Point"}
}