{
  "type": "Feature",
  "properties": {
    "iso:country":"US",
    "sg:address":"3285 Lapeer Rd",
    "sg:city":"Auburn Hills",
    "sg:classifiers":[
        {
            "category":"Professional",
            "subcategory":"Engineering",
            "type":"Services"
        }
    ],
    "sg:phone":"+1 248 754 1900",
    "sg:postcode":"48326",
    "sg:province":"MI",
    "sg:tags":[
        "engineer"
    ],
    "wof:name":"Esys Corporation",
    "wof:placetype":"venue"
},
  "geometry": {"coordinates":[-83.241263,42.687001],"type":"Point"}
}