{
  "type": "Feature",
  "properties": {
    "iso:country":"US",
    "sg:address":"9200 Gratiot Ave Ste 103",
    "sg:city":"Detroit",
    "sg:classifiers":[
        {
            "category":"Organizations",
            "subcategory":"Religious Organization",
            "type":"Services"
        }
    ],
    "sg:phone":"+1 313 579 9071",
    "sg:postcode":"48213",
    "sg:province":"MI",
    "wof:name":"Michigan Coalition For Human Rights",
    "wof:placetype":"venue"
},
  "geometry": {"coordinates":[-83.007527,42.389333],"type":"Point"}
}