{
  "type": "Feature",
  "properties": {
    "iso:country":"US",
    "sg:address":"1324 W Bristol Rd",
    "sg:city":"Detroit",
    "sg:classifiers":[
        {
            "category":"Banks & Credit Unions",
            "subcategory":"Atm",
            "type":"Services"
        }
    ],
    "sg:phone":"+1 313 406 8870",
    "sg:postcode":"48201",
    "sg:province":"MI",
    "sg:tags":[
        "bankruptcy"
    ],
    "sg:website":"www.fregobrodsky.com",
    "wof:name":"Frego & Brodsky Attorneys At Law",
    "wof:placetype":"venue"
},
  "geometry": {"coordinates":[-83.080977,42.322832],"type":"Point"}
}