{
  "type": "Feature",
  "properties": {
    "iso:country":"US",
    "sg:address":"6665 Vernmoor",
    "sg:city":"Troy",
    "sg:classifiers":[
        {
            "category":"Professional",
            "subcategory":"Computer Services",
            "type":"Services"
        }
    ],
    "sg:phone":"+1 248 436 8037",
    "sg:postcode":"48098",
    "sg:province":"MI",
    "sg:tags":[
        "banner",
        "banner-maker",
        "banner-creator",
        "flash",
        "flash-banner",
        "flash-banners",
        "free",
        "ads",
        "ad",
        "banner-ads",
        "banner-ad",
        "free-banners",
        "banner-advertising",
        "create-banner",
        "flash-animations",
        "make-a-banner",
        "create-a-banner",
        "flash-banner-maker",
        "banner-ad-software",
        "free"
    ],
    "sg:website":"http://www.bannersnack.com",
    "wof:name":"BannerSnack",
    "wof:placetype":"venue"
},
  "geometry": {"coordinates":[-83.15731599999999,42.612908],"type":"Point"}
}