{
  "type": "Feature",
  "properties": {
    "iso:country":"US",
    "sg:address":"2662 Seidlers Rd",
    "sg:city":"Midland",
    "sg:classifiers":[
        {
            "category":"Health Services",
            "subcategory":"Health Practitioner",
            "type":"Services"
        }
    ],
    "sg:phone":"+1 989 631 7773",
    "sg:postcode":"48642",
    "sg:province":"MI",
    "wof:name":"New Life Midwifery Svc",
    "wof:placetype":"venue"
},
  "geometry": {"coordinates":[-84.162448,43.683469],"type":"Point"}
}