{
  "type": "Feature",
  "properties": {
    "iso:country":"US",
    "sg:address":"101 S Franklin St",
    "sg:city":"Greenville",
    "sg:classifiers":[
        {
            "category":"Organizations",
            "subcategory":"Religious Organization",
            "type":"Services"
        }
    ],
    "sg:phone":"+1 616 754 3187",
    "sg:postcode":"48838",
    "sg:province":"MI",
    "sg:tags":[
        "church"
    ],
    "wof:name":"Church Of God First",
    "wof:placetype":"venue"
},
  "geometry": {"coordinates":[-85.254795,43.180682],"type":"Point"}
}