{
  "type": "Feature",
  "properties": {
    "iso:country":"US",
    "sg:address":"555 S Old Woodward Ave",
    "sg:city":"Birmingham",
    "sg:classifiers":[
        {
            "category":"Shopping",
            "subcategory":"Books",
            "type":"Retail Goods"
        }
    ],
    "sg:phone":"+1 248 645 6443",
    "sg:postcode":"48009",
    "sg:province":"MI",
    "sg:tags":[
        "dealer"
    ],
    "sg:website":"www.physicianspress.com",
    "wof:name":"Physicians' Press",
    "wof:placetype":"venue"
},
  "geometry": {"coordinates":[-83.212019,42.544576],"type":"Point"}
}