{
  "type": "Feature",
  "properties": {
    "iso:country":"US",
    "sg:address":"108 E Broad St",
    "sg:city":"Chesaning",
    "sg:classifiers":[
        {
            "category":"Real Estate",
            "subcategory":"Real Estate Agent",
            "type":"Services"
        }
    ],
    "sg:phone":"+1 989 845 4800",
    "sg:postcode":"48616",
    "sg:province":"MI",
    "sg:tags":[
        "policy",
        "vocation"
    ],
    "wof:name":"Century 21",
    "wof:placetype":"venue"
},
  "geometry": {"coordinates":[-84.11533,43.184566],"type":"Point"}
}