{
  "type": "Feature",
  "properties": {
    "iso:country":"US",
    "sg:address":"2200 Salzburg Rd",
    "sg:city":"Midland",
    "sg:classifiers":[
        {
            "category":"Manufacturing",
            "subcategory":"Metals",
            "type":"Manufacturing & Wholesale Goods"
        }
    ],
    "sg:phone":"+1 989 496 4000",
    "sg:postcode":"48640",
    "sg:province":"MI",
    "sg:tags":[
        "coating"
    ],
    "sg:website":"www.ziameter.com",
    "wof:name":"Dow Corning Corp",
    "wof:placetype":"venue"
},
  "geometry": {"coordinates":[-84.200929,43.583343],"type":"Point"}
}