{
  "type": "Feature",
  "properties": {
    "iso:country":"US",
    "sg:address":"30825 John R Rd",
    "sg:city":"Madison Heights",
    "sg:classifiers":[
        {
            "category":"Health Services",
            "subcategory":"Dentist",
            "type":"Services"
        }
    ],
    "sg:phone":"+1 248 588 8966",
    "sg:postcode":"48071",
    "sg:province":"MI",
    "wof:name":"Grace Dental Care",
    "wof:placetype":"venue"
},
  "geometry": {"coordinates":[-83.106579,42.519592],"type":"Point"}
}