{
  "type": "Feature",
  "properties": {
    "iso:country":"US",
    "sg:address":"27628 Avondale St",
    "sg:city":"Inkster",
    "sg:classifiers":[
        {
            "category":"Organizations",
            "subcategory":"Religious Organization",
            "type":"Services"
        }
    ],
    "sg:phone":"+1 313 563 1705",
    "sg:postcode":"48141",
    "sg:province":"MI",
    "wof:name":"New Birth Baptist Church",
    "wof:placetype":"venue"
},
  "geometry": {"coordinates":[-83.31383700000001,42.304461],"type":"Point"}
}