{
  "type": "Feature",
  "properties": {
    "iso:country":"US",
    "sg:address":"12820 Eureka Rd",
    "sg:city":"Southgate",
    "sg:classifiers":[
        {
            "category":"Restaurant",
            "type":"Food & Drink"
        }
    ],
    "sg:phone":"+1 734 283 3711",
    "sg:postcode":"48195",
    "sg:province":"MI",
    "wof:name":"A & W Root Beer Drive In",
    "wof:placetype":"venue"
},
  "geometry": {"coordinates":[-83.181099,42.199501],"type":"Point"}
}