{
  "type": "Feature",
  "properties": {
    "iso:country":"US",
    "sg:address":"50390 Utica Dr",
    "sg:city":"Shelby Twp",
    "sg:classifiers":[
        {
            "category":"Wholesale",
            "subcategory":"Metals & Minerals",
            "type":"Manufacturing & Wholesale Goods"
        }
    ],
    "sg:phone":"+1 586 532 2135",
    "sg:postcode":"48315",
    "sg:province":"MI",
    "sg:tags":[
        "steel",
        "warehouse"
    ],
    "sg:website":"www.horizonsteel.com",
    "wof:name":"Horizon Steel",
    "wof:placetype":"venue"
},
  "geometry": {"coordinates":[-82.977051,42.669554],"type":"Point"}
}