{
  "type": "Feature",
  "properties": {
    "iso:country":"US",
    "sg:address":"10699 S Barnard Rd",
    "sg:city":"Saint Louis",
    "sg:classifiers":[
        {
            "category":"Building & Trades",
            "subcategory":"Construction",
            "type":"Services"
        }
    ],
    "sg:phone":"+1 989 681 2565",
    "sg:postcode":"48883",
    "sg:province":"MI",
    "sg:tags":[
        "excavation",
        "contractor"
    ],
    "wof:name":"Bills Custom Backhoe",
    "wof:placetype":"venue"
},
  "geometry": {"coordinates":[-84.63728999999999,43.486491],"type":"Point"}
}