{
  "type": "Feature",
  "properties": {
    "iso:country":"US",
    "sg:address":"10 S Main St Ste 104",
    "sg:city":"Mount Clemens",
    "sg:classifiers":[
        {
            "category":"Banks & Credit Unions",
            "subcategory":"Financial Services",
            "type":"Services"
        }
    ],
    "sg:phone":"+1 586 493 9400",
    "sg:postcode":"48043",
    "sg:province":"MI",
    "sg:tags":[
        "broker",
        "mortgage"
    ],
    "wof:name":"Southwest Funding Lp",
    "wof:placetype":"venue"
},
  "geometry": {"coordinates":[-82.878641,42.596568],"type":"Point"}
}