{
  "type": "Feature",
  "properties": {
    "iso:country":"US",
    "sg:address":"4150 Dove Rd",
    "sg:city":"Port Huron",
    "sg:classifiers":[
        {
            "category":"Recreation",
            "type":"Entertainment"
        }
    ],
    "sg:phone":"+1 810 364 4850",
    "sg:postcode":"48060",
    "sg:province":"MI",
    "sg:tags":[
        "club",
        "hockey"
    ],
    "wof:name":"Blue Water Hockey League",
    "wof:placetype":"venue"
},
  "geometry": {"coordinates":[-82.483853,42.951181],"type":"Point"}
}