{
  "type": "Feature",
  "properties": {
    "iso:country":"US",
    "sg:address":"2365 S State Rd",
    "sg:city":"Ionia",
    "sg:classifiers":[
        {
            "category":"Restaurant",
            "type":"Food & Drink"
        }
    ],
    "sg:menulink":"http://www.allmenus.com/mi/ionia/146231-subway/menu/",
    "sg:phone":"+1 616 527 2577",
    "sg:postcode":"48846",
    "sg:province":"MI",
    "sg:tags":[
        "american",
        "sandwich"
    ],
    "wof:name":"Subway",
    "wof:placetype":"venue"
},
  "geometry": {"coordinates":[-85.074732,42.948894],"type":"Point"}
}