{
  "type": "Feature",
  "properties": {
    "iso:country":"US",
    "sg:address":"11946 Lakeway St",
    "sg:city":"Plainwell",
    "sg:classifiers":[
        {
            "category":"Retail",
            "subcategory":"Repair Shop",
            "type":"Services"
        }
    ],
    "sg:phone":"+1 269 664 4923",
    "sg:postcode":"49080",
    "sg:province":"MI",
    "sg:tags":[
        "upholsterer"
    ],
    "wof:name":"Pine Lake Lady Boat Upholstery",
    "wof:placetype":"venue"
},
  "geometry": {"coordinates":[-85.52057499999999,42.490314],"type":"Point"}
}