{
  "type": "Feature",
  "properties": {
    "iso:country":"US",
    "sg:address":"2627 W Michigan Ave",
    "sg:city":"Kalamazoo",
    "sg:classifiers":[
        {
            "category":"Food & Beverages",
            "subcategory":"Groceries & Convenience Stores",
            "type":"Retail Goods"
        }
    ],
    "sg:phone":"+1 269 343 8688",
    "sg:postcode":"49006",
    "sg:province":"MI",
    "sg:website":"www.littlegrocerystore.com",
    "wof:name":"7-Eleven",
    "wof:placetype":"venue"
},
  "geometry": {"coordinates":[-85.6224,42.281327],"type":"Point"}
}