{
  "type": "Feature",
  "properties": {
    "iso:country":"US",
    "sg:address":"315 S Front St",
    "sg:city":"Marquette",
    "sg:classifiers":[
        {
            "category":"Shopping",
            "subcategory":"Computers & Home Electronics",
            "type":"Retail Goods"
        },
        {
            "category":"Professional",
            "subcategory":"Computer Services",
            "type":"Services"
        }
    ],
    "sg:phone":"+1 906 226 3266",
    "sg:postcode":"49855",
    "sg:province":"MI",
    "sg:tags":[
        "equipment",
        "dealer"
    ],
    "sg:website":"www.ironbay.net",
    "wof:name":"Iron Bay Computer & Design Inc",
    "wof:placetype":"venue"
},
  "geometry": {"coordinates":[-87.39329600000001,46.541448],"type":"Point"}
}