{
  "type": "Feature",
  "properties": {
    "iso:country":"US",
    "sg:address":"414 S Lehman Rd",
    "sg:city":"Twining",
    "sg:classifiers":[
        {
            "category":"Building & Trades",
            "subcategory":"Landscaping Services",
            "type":"Services"
        }
    ],
    "sg:phone":"+1 989 653 2971",
    "sg:postcode":"48766",
    "sg:province":"MI",
    "wof:name":"Home Services",
    "wof:placetype":"venue"
},
  "geometry": {"coordinates":[-83.82737,44.075449],"type":"Point"}
}