{
  "type": "Feature",
  "properties": {
    "iso:country":"US",
    "sg:address":"3520 Duce Rd",
    "sg:city":"Avoca",
    "sg:classifiers":[
        {
            "category":"Building & Trades",
            "subcategory":"Construction",
            "type":"Services"
        }
    ],
    "sg:phone":"+1 810 325 1629",
    "sg:postcode":"48006",
    "sg:province":"MI",
    "sg:tags":[
        "excavation",
        "contractor"
    ],
    "wof:name":"Bruce Johnson Excavating",
    "wof:placetype":"venue"
},
  "geometry": {"coordinates":[-82.671874,43.004772],"type":"Point"}
}