{
  "type": "Feature",
  "properties": {
    "iso:country":"US",
    "sg:address":"1152 Roberts Dr",
    "sg:city":"Metamora",
    "sg:classifiers":[
        {
            "category":"Building & Trades",
            "subcategory":"Construction",
            "type":"Services"
        }
    ],
    "sg:phone":"+1 248 789 2797",
    "sg:postcode":"48455",
    "sg:province":"MI",
    "sg:tags":[
        "restoration",
        "cleaning",
        "patio",
        "deck"
    ],
    "wof:name":"Four Seasons Powerwashing",
    "wof:placetype":"venue"
},
  "geometry": {"coordinates":[-83.313241,42.918673],"type":"Point"}
}