{
  "type": "Feature",
  "properties": {
    "iso:country":"US",
    "sg:address":"437 W Saint Joseph St",
    "sg:city":"Lawrence",
    "sg:classifiers":[
        {
            "category":"Autos & Motor Vehicles",
            "subcategory":"Fuel & Gas Station",
            "type":"Retail Goods"
        }
    ],
    "sg:phone":"+1 269 674 3326",
    "sg:postcode":"49064",
    "sg:province":"MI",
    "sg:tags":[
        "oil"
    ],
    "wof:name":"Village Marathon",
    "wof:placetype":"venue"
},
  "geometry": {"coordinates":[-86.055543,42.219173],"type":"Point"}
}