{
  "type": "Feature",
  "properties": {
    "iso:country":"US",
    "sg:address":"42115 Irwin Dr",
    "sg:city":"Harrison Twp",
    "sg:classifiers":[
        {
            "category":"Professional",
            "subcategory":"Business Services",
            "type":"Services"
        }
    ],
    "sg:phone":"+1 586 954 3390",
    "sg:postcode":"48045",
    "sg:province":"MI",
    "sg:tags":[
        "inspection"
    ],
    "wof:name":"Accurate Quality Sorting Co",
    "wof:placetype":"venue"
},
  "geometry": {"coordinates":[-82.852086,42.597252],"type":"Point"}
}