{
  "type": "Feature",
  "properties": {
    "iso:country":"US",
    "sg:address":"6130 Highland Rd",
    "sg:city":"Waterford",
    "sg:classifiers":[
        {
            "category":"Professional",
            "type":"Services"
        }
    ],
    "sg:phone":"+1 248 886 0337",
    "sg:postcode":"48327",
    "sg:province":"MI",
    "sg:tags":[
        "establishment"
    ],
    "wof:name":"WRJ Inc",
    "wof:placetype":"venue"
},
  "geometry": {"coordinates":[-83.410325,42.659838],"type":"Point"}
}