{
  "type": "Feature",
  "properties": {
    "iso:country":"US",
    "sg:address":"9700 Riley Rd",
    "sg:city":"Interlochen",
    "sg:classifiers":[
        {
            "category":"Education",
            "subcategory":"Library",
            "type":"Public Place"
        }
    ],
    "sg:phone":"+1 231 276 6767",
    "sg:postcode":"49643",
    "sg:province":"MI",
    "wof:name":"Interlochen Public Library",
    "wof:placetype":"venue"
},
  "geometry": {"coordinates":[-85.77189,44.644031],"type":"Point"}
}