{
  "type": "Feature",
  "properties": {
    "iso:country":"US",
    "sg:address":"3424 E Jefferson Ave",
    "sg:city":"Detroit",
    "sg:classifiers":[
        {
            "category":"Restaurant",
            "type":"Food & Drink"
        }
    ],
    "sg:phone":"+1 313 877 9192",
    "sg:postcode":"48207",
    "sg:province":"MI",
    "sg:website":"www.subway.com",
    "wof:name":"Subway Sandwiches",
    "wof:placetype":"venue"
},
  "geometry": {"coordinates":[-83.012199,42.342602],"type":"Point"}
}