{
  "type": "Feature",
  "properties": {
    "iso:country":"US",
    "sg:address":"122 N Main St",
    "sg:city":"Camden",
    "sg:classifiers":[
        {
            "category":"Shopping",
            "subcategory":"Used Merchandise",
            "type":"Retail Goods"
        }
    ],
    "sg:phone":"+1 517 368 5644",
    "sg:postcode":"49232",
    "sg:province":"MI",
    "sg:tags":[
        "shop",
        "consignment"
    ],
    "wof:name":"Village Mini Mall",
    "wof:placetype":"venue"
},
  "geometry": {"coordinates":[-84.757655,41.7571],"type":"Point"}
}