{
  "type": "Feature",
  "properties": {
    "iso:country":"US",
    "sg:address":"529 N Sand Lake Rd",
    "sg:city":"National City",
    "sg:classifiers":[
        {
            "category":"Building & Trades",
            "subcategory":"Construction",
            "type":"Services"
        }
    ],
    "sg:phone":"+1 989 362 8343",
    "sg:postcode":"48748",
    "sg:province":"MI",
    "sg:tags":[
        "hanging",
        "contractor"
    ],
    "wof:name":"Schaffer Painting",
    "wof:placetype":"venue"
},
  "geometry": {"coordinates":[-83.68365300000001,44.28451],"type":"Point"}
}