{
  "type": "Feature",
  "properties": {
    "iso:country":"US",
    "sg:address":"3113 S 11th St",
    "sg:city":"Niles",
    "sg:classifiers":[
        {
            "category":"Travel",
            "subcategory":"Hotels & Motels",
            "type":"Entertainment"
        }
    ],
    "sg:phone":"+1 269 683 3275",
    "sg:postcode":"49120",
    "sg:province":"MI",
    "wof:name":"Stephens Motel",
    "wof:placetype":"venue"
},
  "geometry": {"coordinates":[-86.250795,41.764679],"type":"Point"}
}