{
  "type": "Feature",
  "properties": {
    "iso:country":"US",
    "sg:address":"33401 Woodward Ave",
    "sg:city":"Birmingham",
    "sg:classifiers":[
        {
            "category":"Health Services",
            "subcategory":"Health Practitioner",
            "type":"Services"
        }
    ],
    "sg:phone":"+1 866 454 8346",
    "sg:postcode":"48009",
    "sg:province":"MI",
    "sg:tags":[
        "home",
        "care"
    ],
    "sg:website":"www.homecareassistance.com",
    "wof:name":"Home Care Assistance",
    "wof:placetype":"venue"
},
  "geometry": {"coordinates":[-83.20261000000001,42.535126],"type":"Point"}
}