{
  "type": "Feature",
  "properties": {
    "iso:country":"US",
    "sg:address":"23300 Greenfield Rd",
    "sg:city":"Oak Park",
    "sg:classifiers":[
        {
            "category":"Personal",
            "subcategory":"Beauty Salon",
            "type":"Services"
        }
    ],
    "sg:phone":"+1 248 967 8998",
    "sg:postcode":"48237",
    "sg:province":"MI",
    "sg:tags":[
        "manicuring"
    ],
    "wof:name":"Nail It Inc",
    "wof:placetype":"venue"
},
  "geometry": {"coordinates":[-83.201087,42.459475],"type":"Point"}
}