{
  "type": "Feature",
  "properties": {
    "iso:country":"US",
    "sg:address":"41400 Executive Dr",
    "sg:city":"Harrison Township",
    "sg:classifiers":[
        {
            "category":"Manufacturing",
            "subcategory":"Tools & Machinery",
            "type":"Manufacturing & Wholesale Goods"
        }
    ],
    "sg:phone":"+1 586 466 3400",
    "sg:postcode":"48045",
    "sg:province":"MI",
    "sg:tags":[
        "die",
        "engineering"
    ],
    "wof:name":"Image Machine & Tool Inc",
    "wof:placetype":"venue"
},
  "geometry": {"coordinates":[-82.855557,42.596307],"type":"Point"}
}