{
  "type": "Feature",
  "properties": {
    "iso:country":"US",
    "sg:address":"900 W Avon Rd",
    "sg:city":"Rochester Hills",
    "sg:classifiers":[
        {
            "category":"Personal",
            "type":"Services"
        },
        {
            "category":"Restaurant",
            "type":"Food & Drink"
        }
    ],
    "sg:phone":"+1 248 652 6706",
    "sg:postcode":"48307",
    "sg:province":"MI",
    "sg:tags":[
        "eating",
        "caterer"
    ],
    "wof:name":"River Crest Catering",
    "wof:placetype":"venue"
},
  "geometry": {"coordinates":[-83.15269499999999,42.665931],"type":"Point"}
}