{
  "type": "Feature",
  "properties": {
    "iso:country":"US",
    "sg:address":"8955 Robbins Rd",
    "sg:city":"Clarksville",
    "sg:classifiers":[
        {
            "category":"Real Estate",
            "subcategory":"Real Estate Operator",
            "type":"Services"
        }
    ],
    "sg:phone":"+1 616 693 2515",
    "sg:postcode":"48815",
    "sg:province":"MI",
    "sg:tags":[
        "property",
        "lessor"
    ],
    "wof:name":"Joan Mc Connon",
    "wof:placetype":"venue"
},
  "geometry": {"coordinates":[-85.247947,42.834845],"type":"Point"}
}