{
  "type": "Feature",
  "properties": {
    "iso:country":"US",
    "sg:address":"8740 Heritage Pl",
    "sg:city":"Detroit",
    "sg:classifiers":[
        {
            "category":"Professional",
            "subcategory":"Management & Consulting",
            "type":"Services"
        }
    ],
    "sg:phone":"+1 313 361 3192",
    "sg:postcode":"48204",
    "sg:province":"MI",
    "wof:name":"Endurance Unlimited",
    "wof:placetype":"venue"
},
  "geometry": {"coordinates":[-83.122428,42.362055],"type":"Point"}
}