{
  "type": "Feature",
  "properties": {
    "iso:country":"US",
    "sg:address":"2335 S Commerce Rd",
    "sg:city":"Walled Lake",
    "sg:classifiers":[
        {
            "category":"Health Services",
            "subcategory":"Doctor",
            "type":"Services"
        }
    ],
    "sg:phone":"+1 248 624 1526",
    "sg:postcode":"48390",
    "sg:province":"MI",
    "sg:tags":[
        "practice",
        "family"
    ],
    "wof:name":"Walled Lake Medical Center PC",
    "wof:placetype":"venue"
},
  "geometry": {"coordinates":[-83.47389699999999,42.555928],"type":"Point"}
}