{
  "type": "Feature",
  "properties": {
    "iso:country":"US",
    "sg:address":"318 N 5th St",
    "sg:city":"Niles",
    "sg:classifiers":[
        {
            "category":"Shopping",
            "subcategory":"Bicycles & Sporting Goods",
            "type":"Retail Goods"
        }
    ],
    "sg:phone":"+1 269 684 6390",
    "sg:postcode":"49120",
    "sg:province":"MI",
    "sg:tags":[
        "gun",
        "gunsmith"
    ],
    "wof:name":"Firing Pin Inc",
    "wof:placetype":"venue"
},
  "geometry": {"coordinates":[-86.254058,41.831037],"type":"Point"}
}