{
  "type": "Feature",
  "properties": {
    "iso:country":"US",
    "sg:address":"433 E Highland Rd",
    "sg:city":"Howell",
    "sg:classifiers":[
        {
            "category":"Restaurant",
            "type":"Food & Drink"
        }
    ],
    "sg:phone":"+1 517 552 1311",
    "sg:postcode":"48843",
    "sg:province":"MI",
    "wof:name":"Pizza Hut",
    "wof:placetype":"venue"
},
  "geometry": {"coordinates":[-83.92312699999999,42.622679],"type":"Point"}
}