{
  "type": "Feature",
  "properties": {
    "iso:country":"US",
    "sg:address":"20490 Maple St",
    "sg:city":"Lake Ann",
    "sg:classifiers":[
        {
            "category":"Home & Garden",
            "subcategory":"Building Materials",
            "type":"Retail Goods"
        }
    ],
    "sg:phone":"+1 231 275 5370",
    "sg:postcode":"49650",
    "sg:province":"MI",
    "wof:name":"Glassworks",
    "wof:placetype":"venue"
},
  "geometry": {"coordinates":[-85.827189,44.725375],"type":"Point"}
}