{
  "type": "Feature",
  "properties": {
    "iso:country":"US",
    "sg:address":"123 Quick Rd",
    "sg:city":"Harbor Springs",
    "sg:classifiers":[
        {
            "category":"Building & Trades",
            "subcategory":"Construction",
            "type":"Services"
        }
    ],
    "sg:phone":"+1 231 526 2164",
    "sg:postcode":"49740",
    "sg:province":"MI",
    "sg:tags":[
        "water",
        "well",
        "drilling"
    ],
    "wof:name":"Luttrell Well Drilling Inc",
    "wof:placetype":"venue"
},
  "geometry": {"coordinates":[-84.916366,45.449624],"type":"Point"}
}