{
  "type": "Feature",
  "properties": {
    "iso:country":"US",
    "sg:address":"1335 Lake Lansing Rd",
    "sg:city":"Lansing",
    "sg:classifiers":[
        {
            "category":"Wholesale",
            "subcategory":"Durable Goods & Equipment",
            "type":"Manufacturing & Wholesale Goods"
        }
    ],
    "sg:phone":"+1 517 372 4442",
    "sg:postcode":"48912",
    "sg:province":"MI",
    "sg:tags":[
        "fire",
        "extinguisher"
    ],
    "wof:name":"Lansing Fire & Safety",
    "wof:placetype":"venue"
},
  "geometry": {"coordinates":[-84.532551,42.759269],"type":"Point"}
}