{
  "type": "Feature",
  "properties": {
    "iso:country":"US",
    "sg:address":"2750 Selden St",
    "sg:city":"Detroit",
    "sg:classifiers":[
        {
            "category":"Education",
            "subcategory":"School",
            "type":"Public Place"
        }
    ],
    "sg:phone":"+1 313 494 2621",
    "sg:postcode":"48208",
    "sg:province":"MI",
    "sg:tags":[
        "vocational"
    ],
    "wof:name":"Booth Cntning Edcatn For Girls",
    "wof:placetype":"venue"
},
  "geometry": {"coordinates":[-83.089951,42.339974],"type":"Point"}
}