{
  "type": "Feature",
  "properties": {
    "iso:country":"US",
    "sg:address":"5295 State Hwy 30",
    "sg:city":"Beaverton",
    "sg:classifiers":[
        {
            "category":"Professional",
            "subcategory":"Business Services",
            "type":"Services"
        }
    ],
    "sg:phone":"+1 989 435 8655",
    "sg:postcode":"48612",
    "sg:province":"MI",
    "wof:name":"Peace Mind Home Insptn Svc LLC",
    "wof:placetype":"venue"
},
  "geometry": {"coordinates":[-84.367509,43.834898],"type":"Point"}
}