{
  "type": "Feature",
  "properties": {
    "iso:country":"US",
    "sg:address":"640 Hickory St",
    "sg:city":"Milford",
    "sg:classifiers":[
        {
            "category":"Professional",
            "type":"Services"
        }
    ],
    "sg:phone":"+1 248 685 9148",
    "sg:postcode":"48381",
    "sg:province":"MI",
    "wof:name":"Kathy Taylor Handy Dandy",
    "wof:placetype":"venue"
},
  "geometry": {"coordinates":[-83.597994,42.59416],"type":"Point"}
}