{
  "type": "Feature",
  "properties": {
    "iso:country":"US",
    "sg:address":"9419 Dexter Ave",
    "sg:city":"Detroit",
    "sg:classifiers":[
        {
            "category":"Retail",
            "subcategory":"Funeral Services",
            "type":"Services"
        }
    ],
    "sg:phone":"+1 313 895 8900",
    "sg:postcode":"48206",
    "sg:province":"MI",
    "wof:name":"Mc Fall Brothers Inc",
    "wof:placetype":"venue"
},
  "geometry": {"coordinates":[-83.11896,42.371944],"type":"Point"}
}