{
  "type": "Feature",
  "properties": {
    "iso:country":"US",
    "sg:address":"1796 E Monroe Rd",
    "sg:city":"Tecumseh",
    "sg:classifiers":[
        {
            "category":"Professional",
            "subcategory":"Computer Services",
            "type":"Services"
        }
    ],
    "sg:phone":"+1 517 423 9683",
    "sg:postcode":"49286",
    "sg:province":"MI",
    "sg:tags":[
        "datum"
    ],
    "wof:name":"Raisin River Distributors",
    "wof:placetype":"venue"
},
  "geometry": {"coordinates":[-84.003958,42.009523],"type":"Point"}
}