{
  "type": "Feature",
  "properties": {
    "iso:country":"US",
    "sg:address":"931 Coolidge Ave",
    "sg:city":"Clawson",
    "sg:classifiers":[
        {
            "category":"Professional",
            "type":"Services"
        }
    ],
    "sg:phone":"+1 248 577 2630",
    "sg:postcode":"48017",
    "sg:province":"MI",
    "wof:name":"Unlimited Ink",
    "wof:placetype":"venue"
},
  "geometry": {"coordinates":[-83.132414,42.535061],"type":"Point"}
}