{
  "type": "Feature",
  "properties": {
    "iso:country":"US",
    "sg:address":"27701 Jefferson Ave",
    "sg:city":"St Clair Shores",
    "sg:classifiers":[
        {
            "category":"Government",
            "subcategory":"Office",
            "type":"Public Place"
        },
        {
            "category":"Government",
            "subcategory":"Court House",
            "type":"Public Place"
        }
    ],
    "sg:phone":"+1 586 445 5282",
    "sg:postcode":"48081",
    "sg:province":"MI",
    "sg:tags":[
        "village"
    ],
    "wof:name":"St Clair Shores Dist CT-Civil",
    "wof:placetype":"venue"
},
  "geometry": {"coordinates":[-82.887891,42.497251],"type":"Point"}
}