{
  "type": "Feature",
  "properties": {
    "iso:country":"US",
    "sg:address":"4008 Seaway Dr",
    "sg:city":"Saginaw",
    "sg:classifiers":[
        {
            "category":"Home & Garden",
            "subcategory":"Building Materials",
            "type":"Retail Goods"
        }
    ],
    "sg:phone":"+1 989 759 7625",
    "sg:postcode":"48604",
    "sg:province":"MI",
    "sg:tags":[
        "stone"
    ],
    "wof:name":"BMT Stone Sales",
    "wof:placetype":"venue"
},
  "geometry": {"coordinates":[-83.919372,43.463613],"type":"Point"}
}