{
  "type": "Feature",
  "properties": {
    "iso:country":"US",
    "sg:address":"46638 Houghton Dr",
    "sg:city":"Shelby Twp",
    "sg:classifiers":[
        {
            "category":"Wholesale",
            "subcategory":"Groceries",
            "type":"Manufacturing & Wholesale Goods"
        }
    ],
    "sg:phone":"+1 586 731 3922",
    "sg:postcode":"48315",
    "sg:province":"MI",
    "sg:tags":[
        "food",
        "broker"
    ],
    "wof:name":"George F Howard Food Brokers",
    "wof:placetype":"venue"
},
  "geometry": {"coordinates":[-82.99902400000001,42.640205],"type":"Point"}
}