{
  "type": "Feature",
  "properties": {
    "iso:country":"US",
    "sg:address":"53075 Pimpernil",
    "sg:city":"New Baltimore",
    "sg:classifiers":[
        {
            "category":"Professional",
            "type":"Services"
        }
    ],
    "sg:phone":"+1 586 749 2866",
    "sg:postcode":"48051",
    "sg:province":"MI",
    "wof:name":"New Beginnings Nutritional Svc",
    "wof:placetype":"venue"
},
  "geometry": {"coordinates":[-82.79989399999999,42.690091],"type":"Point"}
}