{
  "type": "Feature",
  "properties": {
    "iso:country":"US",
    "sg:address":"151 Saint Marys Dr",
    "sg:city":"Hemlock",
    "sg:classifiers":[
        {
            "category":"Organizations",
            "subcategory":"Religious Organization",
            "type":"Services"
        }
    ],
    "sg:phone":"+1 989 642 5606",
    "sg:postcode":"48626",
    "sg:province":"MI",
    "wof:name":"St Marys Church",
    "wof:placetype":"venue"
},
  "geometry": {"coordinates":[-84.23968600000001,43.418716],"type":"Point"}
}