{
  "type": "Feature",
  "properties": {
    "iso:country":"US",
    "sg:address":"22671 Red Arrow Hwy",
    "sg:city":"Mattawan",
    "sg:classifiers":[
        {
            "category":"Retail",
            "subcategory":"Auto Repair",
            "type":"Services"
        }
    ],
    "sg:phone":"+1 269 668 2379",
    "sg:postcode":"49071",
    "sg:province":"MI",
    "sg:tags":[
        "body"
    ],
    "wof:name":"Car Connection",
    "wof:placetype":"venue"
},
  "geometry": {"coordinates":[-85.773158,42.239914],"type":"Point"}
}