{
  "type": "Feature",
  "properties": {
    "iso:country":"US",
    "sg:address":"40 New St Ste 203",
    "sg:city":"Mount Clemens",
    "sg:classifiers":[
        {
            "category":"Professional",
            "subcategory":"Lawyer & Legal Services",
            "type":"Services"
        }
    ],
    "sg:phone":"+1 586 469 1111",
    "sg:postcode":"48043",
    "sg:province":"MI",
    "wof:name":"Bieglecki & Baratta PC",
    "wof:placetype":"venue"
},
  "geometry": {"coordinates":[-82.877403,42.598701],"type":"Point"}
}