{
  "type": "Feature",
  "properties": {
    "iso:country":"US",
    "sg:address":"35046 Woodward Ave Ste 200",
    "sg:city":"Birmingham",
    "sg:classifiers":[
        {
            "category":"Health Services",
            "subcategory":"Dentist",
            "type":"Services"
        }
    ],
    "sg:phone":"+1 248 644 5400",
    "sg:postcode":"48009",
    "sg:province":"MI",
    "sg:tags":[
        "orthodontist"
    ],
    "sg:website":"www.orthodonticassociates.com",
    "wof:name":"Orthodontic Associates PC",
    "wof:placetype":"venue"
},
  "geometry": {"coordinates":[-83.210921,42.547738],"type":"Point"}
}