{
  "type": "Feature",
  "properties": {
    "iso:country":"US",
    "sg:address":"2402 S Ely Hwy",
    "sg:city":"Ithaca",
    "sg:phone":"+1 989 875 4586",
    "sg:postcode":"48847",
    "sg:province":"MI",
    "sg:tags":[
        "farm",
        "corn",
        "soybean"
    ],
    "wof:name":"Wood Family Farms",
    "wof:placetype":"venue"
},
  "geometry": {"coordinates":[-84.7097,43.255909],"type":"Point"}
}