{
  "type": "Feature",
  "properties": {
    "iso:country":"US",
    "sg:address":"606 W Front St",
    "sg:city":"Traverse City",
    "sg:classifiers":[
        {
            "category":"Retail",
            "subcategory":"Animal Services",
            "type":"Services"
        }
    ],
    "sg:phone":"+1 231 264 5855",
    "sg:postcode":"49684",
    "sg:province":"MI",
    "sg:tags":[
        "pet",
        "boarding",
        "sitting"
    ],
    "wof:name":"Bokhara Pet Care Ctr",
    "wof:placetype":"venue"
},
  "geometry": {"coordinates":[-85.63299499999999,44.764102],"type":"Point"}
}