{
  "type": "Feature",
  "properties": {
    "iso:country":"US",
    "sg:address":"1992 N Eastman Rd",
    "sg:city":"Midland",
    "sg:classifiers":[
        {
            "category":"Home & Garden",
            "subcategory":"Building Materials",
            "type":"Retail Goods"
        }
    ],
    "sg:phone":"+1 989 631 3191",
    "sg:postcode":"48642",
    "sg:province":"MI",
    "sg:tags":[
        "paint"
    ],
    "wof:name":"Northeastern Paint & Floor",
    "wof:placetype":"venue"
},
  "geometry": {"coordinates":[-84.24714899999999,43.671487],"type":"Point"}
}