{
  "type": "Feature",
  "properties": {
    "iso:country":"US",
    "sg:address":"3584 Fairlanes Ave SW",
    "sg:city":"Grandville",
    "sg:classifiers":[
        {
            "category":"Health Services",
            "subcategory":"Health Practitioner",
            "type":"Services"
        }
    ],
    "sg:phone":"+1 616 531 5025",
    "sg:postcode":"49418",
    "sg:province":"MI",
    "sg:tags":[
        "clinic",
        "therapist",
        "therapy",
        "physical"
    ],
    "wof:name":"Physiotherapy Associates Inc",
    "wof:placetype":"venue"
},
  "geometry": {"coordinates":[-85.77578200000001,42.902894],"type":"Point"}
}