{
  "type": "Feature",
  "properties": {
    "iso:country":"US",
    "sg:address":"12843 S 10th St",
    "sg:city":"Schoolcraft",
    "sg:classifiers":[
        {
            "category":"Building & Trades",
            "subcategory":"Electrical",
            "type":"Services"
        }
    ],
    "sg:phone":"+1 269 679 2142",
    "sg:postcode":"49087",
    "sg:province":"MI",
    "sg:tags":[
        "telecommunication",
        "contractor"
    ],
    "wof:name":"Encore Communications Inc",
    "wof:placetype":"venue"
},
  "geometry": {"coordinates":[-85.66668799999999,42.136815],"type":"Point"}
}