{
  "type": "Feature",
  "properties": {
    "iso:country":"US",
    "sg:address":"13545 Ohio St",
    "sg:city":"Detroit",
    "sg:classifiers":[
        {
            "category":"Professional",
            "subcategory":"Business Services",
            "type":"Services"
        }
    ],
    "sg:phone":"+1 313 834 3065",
    "sg:postcode":"48238",
    "sg:province":"MI",
    "wof:name":"Ashtone Enterprises",
    "wof:placetype":"venue"
},
  "geometry": {"coordinates":[-83.155175,42.388314],"type":"Point"}
}