{
  "type": "Feature",
  "properties": {
    "iso:country":"US",
    "sg:address":"24155 Drake Rd",
    "sg:city":"Farmington Hills",
    "sg:classifiers":[
        {
            "category":"Government",
            "subcategory":"Office",
            "type":"Public Place"
        }
    ],
    "sg:phone":"+1 248 888 8700",
    "sg:postcode":"48335",
    "sg:province":"MI",
    "sg:tags":[
        "state",
        "inspection"
    ],
    "sg:website":"www.michigan.gov",
    "wof:name":"Liquor Control Commission",
    "wof:placetype":"venue"
},
  "geometry": {"coordinates":[-83.396191,42.467532],"type":"Point"}
}