{
  "type": "Feature",
  "properties": {
    "iso:country":"US",
    "sg:address":"8581 Marr Hwy",
    "sg:city":"Manitou Beach",
    "sg:classifiers":[
        {
            "category":"Professional",
            "subcategory":"Lawyer & Legal Services",
            "type":"Services"
        }
    ],
    "sg:phone":"+1 517 467 7820",
    "sg:postcode":"49253",
    "sg:province":"MI",
    "wof:name":"Coons & Assoc",
    "wof:placetype":"venue"
},
  "geometry": {"coordinates":[-84.24679999999999,42.00922],"type":"Point"}
}