{
  "type": "Feature",
  "properties": {
    "iso:country":"US",
    "sg:address":"1337 N Telegraph Rd",
    "sg:city":"Monroe",
    "sg:classifiers":[
        {
            "category":"Travel",
            "subcategory":"Travel Agent",
            "type":"Entertainment"
        }
    ],
    "sg:phone":"+1 734 457 0511",
    "sg:postcode":"48162",
    "sg:province":"MI",
    "sg:tags":[
        "agency",
        "bureau"
    ],
    "wof:name":"Atlas World Travel",
    "wof:placetype":"venue"
},
  "geometry": {"coordinates":[-83.405636,41.940109],"type":"Point"}
}