{
  "type": "Feature",
  "properties": {
    "iso:country":"US",
    "sg:address":"6447 Eastbrooke",
    "sg:city":"West Bloomfield",
    "sg:classifiers":[
        {
            "category":"Health Services",
            "subcategory":"Doctor",
            "type":"Services"
        }
    ],
    "sg:phone":"+1 248 668 1840",
    "sg:postcode":"48322",
    "sg:province":"MI",
    "wof:name":"Hamtramck Dental Center",
    "wof:placetype":"venue"
},
  "geometry": {"coordinates":[-83.43137,42.547092],"type":"Point"}
}