{
  "type": "Feature",
  "properties": {
    "iso:country":"US",
    "sg:address":"1303 W Commerce Rd",
    "sg:city":"Milford",
    "sg:classifiers":[
        {
            "category":"Professional",
            "subcategory":"Management & Consulting",
            "type":"Services"
        }
    ],
    "sg:phone":"+1 248 684 0066",
    "sg:postcode":"48380",
    "sg:province":"MI",
    "sg:tags":[
        "course",
        "consultant",
        "golf",
        "developer"
    ],
    "wof:name":"Total Golf Inc",
    "wof:placetype":"venue"
},
  "geometry": {"coordinates":[-83.628136,42.593736],"type":"Point"}
}