{
  "type": "Feature",
  "properties": {
    "iso:country":"US",
    "sg:address":"13537 24th Ave",
    "sg:city":"Marne",
    "sg:classifiers":[
        {
            "category":"Retail",
            "subcategory":"Repair Shop",
            "type":"Services"
        }
    ],
    "sg:phone":"+1 616 677 3067",
    "sg:postcode":"49435",
    "sg:province":"MI",
    "sg:tags":[
        "taxidermist"
    ],
    "wof:name":"Gone Wild Taxidermy",
    "wof:placetype":"venue"
},
  "geometry": {"coordinates":[-85.847325,43.015184],"type":"Point"}
}