{
  "type": "Feature",
  "properties": {
    "iso:country":"US",
    "sg:address":"1115 3rd St",
    "sg:city":"Muskegon",
    "sg:classifiers":[
        {
            "category":"Organizations",
            "subcategory":"Non-profit Organization",
            "type":"Services"
        }
    ],
    "sg:phone":"+1 231 727 0809",
    "sg:postcode":"49441",
    "sg:province":"MI",
    "sg:tags":[
        "human"
    ],
    "wof:name":"Neighborhood Investment Corp",
    "wof:placetype":"venue"
},
  "geometry": {"coordinates":[-86.24929299999999,43.231743],"type":"Point"}
}