{
  "type": "Feature",
  "properties": {
    "iso:country":"US",
    "sg:address":"5010 Division Ave S",
    "sg:city":"Grand Rapids",
    "sg:classifiers":[
        {
            "category":"Organizations",
            "subcategory":"Religious Organization",
            "type":"Services"
        }
    ],
    "sg:phone":"+1 616 257 7042",
    "sg:postcode":"49548",
    "sg:province":"MI",
    "sg:tags":[
        "christian",
        "ministry"
    ],
    "wof:name":"Roadbed Ministries Inc",
    "wof:placetype":"venue"
},
  "geometry": {"coordinates":[-85.664215,42.871651],"type":"Point"}
}