{
  "type": "Feature",
  "properties": {
    "iso:country":"US",
    "sg:address":"11403 Denne St",
    "sg:city":"Livonia",
    "sg:classifiers":[
        {
            "category":"Building & Trades",
            "subcategory":"Locksmith",
            "type":"Services"
        }
    ],
    "sg:phone":"+1 734 402 8860",
    "sg:postcode":"48150",
    "sg:province":"MI",
    "sg:tags":[
        "key"
    ],
    "wof:name":"MI Lockshop Solutions",
    "wof:placetype":"venue"
},
  "geometry": {"coordinates":[-83.350449,42.367435],"type":"Point"}
}