{
  "type": "Feature",
  "properties": {
    "iso:country":"US",
    "sg:address":"1186 M 89",
    "sg:city":"Plainwell",
    "sg:classifiers":[
        {
            "category":"Autos & Motor Vehicles",
            "subcategory":"Automobile Sales",
            "type":"Retail Goods"
        }
    ],
    "sg:phone":"+1 269 685 1568",
    "sg:postcode":"49080",
    "sg:province":"MI",
    "sg:tags":[
        "car",
        "dealer"
    ],
    "wof:name":"Allegan Chrysler Plymouth",
    "wof:placetype":"venue"
},
  "geometry": {"coordinates":[-85.65884,42.449826],"type":"Point"}
}