{
  "type": "Feature",
  "properties": {
    "iso:country":"US",
    "sg:address":"1211 Boulder Dr",
    "sg:city":"Burton",
    "sg:classifiers":[
        {
            "category":"Building & Trades",
            "subcategory":"Construction",
            "type":"Services"
        }
    ],
    "sg:phone":"+1 810 234 7181",
    "sg:postcode":"48529",
    "sg:province":"MI",
    "sg:tags":[
        "hanging",
        "contractor"
    ],
    "wof:name":"Cherokee Custom Painting",
    "wof:placetype":"venue"
},
  "geometry": {"coordinates":[-83.684512,42.961456],"type":"Point"}
}