{
  "type": "Feature",
  "properties": {
    "iso:country":"US",
    "sg:address":"1785 Losey Rd",
    "sg:city":"Rives Junction",
    "sg:classifiers":[
        {
            "category":"Professional",
            "type":"Services"
        }
    ],
    "sg:phone":"+1 517 569 3469",
    "sg:postcode":"49277",
    "sg:province":"MI",
    "wof:name":"Integrated Co Inc",
    "wof:placetype":"venue"
},
  "geometry": {"coordinates":[-84.40528999999999,42.40024],"type":"Point"}
}