{
  "type": "Feature",
  "properties": {
    "iso:country":"US",
    "sg:address":"1905 Marlow Dr",
    "sg:city":"Warren",
    "sg:classifiers":[
        {
            "category":"Health Services",
            "subcategory":"Doctor",
            "type":"Services"
        }
    ],
    "sg:phone":"+1 586 751 7777",
    "sg:postcode":"48092",
    "sg:province":"MI",
    "sg:tags":[
        "surgeon",
        "oral"
    ],
    "wof:name":"Gorecki Christopher T DDS",
    "wof:placetype":"venue"
},
  "geometry": {"coordinates":[-83.08580000000001,42.509899],"type":"Point"}
}