{
  "type": "Feature",
  "properties": {
    "iso:country":"US",
    "sg:address":"409 N Main St",
    "sg:city":"Royal Oak",
    "sg:classifiers":[
        {
            "category":"Shopping",
            "subcategory":"Florist",
            "type":"Retail Goods"
        }
    ],
    "sg:phone":"+1 248 547 9980",
    "sg:postcode":"48067",
    "sg:province":"MI",
    "wof:name":"Main Street Florist By Deb",
    "wof:placetype":"venue"
},
  "geometry": {"coordinates":[-83.144505,42.492897],"type":"Point"}
}