{
  "type": "Feature",
  "properties": {
    "iso:country":"US",
    "sg:address":"3920 E Territorial Rd",
    "sg:city":"Camden",
    "sg:classifiers":[
        {
            "category":"Building & Trades",
            "subcategory":"Construction",
            "type":"Services"
        }
    ],
    "sg:phone":"+1 517 254 4170",
    "sg:postcode":"49232",
    "sg:province":"MI",
    "sg:tags":[
        "house"
    ],
    "wof:name":"Advanced Construction",
    "wof:placetype":"venue"
},
  "geometry": {"coordinates":[-84.57413,41.709253],"type":"Point"}
}