{
  "type": "Feature",
  "properties": {
    "iso:country":"US",
    "sg:address":"2851 Charlevoix Dr SE",
    "sg:city":"Grand Rapids",
    "sg:classifiers":[
        {
            "category":"Banks & Credit Unions",
            "subcategory":"Investment Brokerage",
            "type":"Services"
        }
    ],
    "sg:phone":"+1 616 285 3739",
    "sg:postcode":"49546",
    "sg:province":"MI",
    "sg:tags":[
        "planner",
        "financial"
    ],
    "wof:name":"American Express",
    "wof:placetype":"venue"
},
  "geometry": {"coordinates":[-85.52234799999999,42.912527],"type":"Point"}
}