{
  "type": "Feature",
  "properties": {
    "iso:country":"US",
    "sg:address":"2975 Narrow Lake Rd",
    "sg:city":"Charlotte",
    "sg:classifiers":[
        {
            "category":"Home & Garden",
            "subcategory":"Home Furnishings",
            "type":"Retail Goods"
        }
    ],
    "sg:phone":"+1 517 543 6011",
    "sg:postcode":"48813",
    "sg:province":"MI",
    "sg:tags":[
        "lighting"
    ],
    "wof:name":"Klaiss Stage Lighting",
    "wof:placetype":"venue"
},
  "geometry": {"coordinates":[-84.777846,42.524625],"type":"Point"}
}