{
  "type": "Feature",
  "properties": {
    "iso:country":"US",
    "sg:address":"2525 Beebe Rd NE",
    "sg:city":"Kalkaska",
    "sg:classifiers":[
        {
            "category":"Organizations",
            "subcategory":"Religious Organization",
            "type":"Services"
        }
    ],
    "sg:phone":"+1 231 258 2820",
    "sg:postcode":"49646",
    "sg:province":"MI",
    "wof:name":"Kalkaska United Methdst Church",
    "wof:placetype":"venue"
},
  "geometry": {"coordinates":[-85.174164,44.757102],"type":"Point"}
}