{
  "type": "Feature",
  "properties": {
    "iso:country":"US",
    "sg:address":"1755 Kensington Rd",
    "sg:city":"Bloomfield Hills",
    "sg:classifiers":[
        {
            "category":"Professional",
            "subcategory":"Accounting & Tax Preparation",
            "type":"Services"
        }
    ],
    "sg:phone":"+1 248 645 2095",
    "sg:postcode":"48304",
    "sg:province":"MI",
    "sg:tags":[
        "accountant"
    ],
    "wof:name":"Witulski CPA PC",
    "wof:placetype":"venue"
},
  "geometry": {"coordinates":[-83.236,42.586399],"type":"Point"}
}