{
  "type": "Feature",
  "properties": {
    "iso:country":"US",
    "sg:address":"2605 E Oakley Park Rd",
    "sg:city":"Commerce Twp",
    "sg:classifiers":[
        {
            "category":"Wholesale",
            "subcategory":"Durable Goods & Equipment",
            "type":"Manufacturing & Wholesale Goods"
        }
    ],
    "sg:phone":"+1 248 669 2800",
    "sg:postcode":"48390",
    "sg:province":"MI",
    "sg:tags":[
        "representative",
        "manufacturer"
    ],
    "sg:website":"www.burkeagency.com",
    "wof:name":"Burke Agency Inc",
    "wof:placetype":"venue"
},
  "geometry": {"coordinates":[-83.451532,42.57047],"type":"Point"}
}