{
  "type": "Feature",
  "properties": {
    "iso:country":"US",
    "sg:address":"328 E Aurora St",
    "sg:city":"Ironwood",
    "sg:classifiers":[
        {
            "category":"Retail",
            "subcategory":"Repair Shop",
            "type":"Services"
        }
    ],
    "sg:phone":"+1 906 932 4210",
    "sg:postcode":"49938",
    "sg:province":"MI",
    "wof:name":"Bens Snow Mobile Clinic",
    "wof:placetype":"venue"
},
  "geometry": {"coordinates":[-90.16636099999999,46.455779],"type":"Point"}
}