{
  "type": "Feature",
  "properties": {
    "iso:country":"US",
    "sg:address":"6149 Greenwycke Ln",
    "sg:city":"Monroe",
    "sg:classifiers":[
        {
            "category":"Shopping",
            "subcategory":"Catalog Store",
            "type":"Retail Goods"
        }
    ],
    "sg:phone":"+1 734 243 9763",
    "sg:postcode":"48161",
    "sg:province":"MI",
    "sg:tags":[
        "mail",
        "house"
    ],
    "wof:name":"Becky J Brooks",
    "wof:placetype":"venue"
},
  "geometry": {"coordinates":[-83.413051,41.893522],"type":"Point"}
}