{
  "type": "Feature",
  "properties": {
    "iso:country":"US",
    "sg:address":"29829 Greenfield Rd Ste 100",
    "sg:city":"Southfield",
    "sg:classifiers":[
        {
            "category":"Professional",
            "subcategory":"Lawyer & Legal Services",
            "type":"Services"
        }
    ],
    "sg:phone":"+1 248 569 9771",
    "sg:postcode":"48076",
    "sg:province":"MI",
    "wof:name":"Collis Stewart M Law Office",
    "wof:placetype":"venue"
},
  "geometry": {"coordinates":[-83.2034,42.509499],"type":"Point"}
}