{
  "type": "Feature",
  "properties": {
    "iso:country":"US",
    "sg:address":"2409 Jaquay Rd",
    "sg:city":"Boyne City",
    "sg:classifiers":[
        {
            "category":"Professional",
            "subcategory":"Business Services",
            "type":"Services"
        }
    ],
    "sg:phone":"+1 231 582 7628",
    "sg:postcode":"49712",
    "sg:province":"MI",
    "wof:name":"Behlings Crane Service",
    "wof:placetype":"venue"
},
  "geometry": {"coordinates":[-85.038838,45.172382],"type":"Point"}
}