{
  "type": "Feature",
  "properties": {
    "iso:country":"US",
    "sg:address":"226 E Michigan Ave",
    "sg:city":"Paw Paw",
    "sg:classifiers":[
        {
            "category":"Museum",
            "type":"Entertainment"
        }
    ],
    "sg:phone":"+1 269 655 8307",
    "sg:postcode":"49079",
    "sg:province":"MI",
    "wof:name":"Van Buren County Museum",
    "wof:placetype":"venue"
},
  "geometry": {"coordinates":[-85.890598,42.217563],"type":"Point"}
}