{
  "type": "Feature",
  "properties": {
    "iso:country":"US",
    "sg:address":"550 Kirtland St SW",
    "sg:city":"Grand Rapids",
    "sg:classifiers":[
        {
            "category":"Professional",
            "subcategory":"Business Services",
            "type":"Services"
        }
    ],
    "sg:phone":"+1 616 241 0440",
    "sg:postcode":"49507",
    "sg:province":"MI",
    "sg:tags":[
        "operator",
        "crane"
    ],
    "wof:name":"Pioneer Construction",
    "wof:placetype":"venue"
},
  "geometry": {"coordinates":[-85.679372,42.924516],"type":"Point"}
}