{
  "type": "Feature",
  "properties": {
    "iso:country":"US",
    "sg:address":"105 N Sophie St",
    "sg:city":"Bessemer",
    "sg:classifiers":[
        {
            "category":"Food & Beverages",
            "subcategory":"Bakery",
            "type":"Retail Goods"
        }
    ],
    "sg:phone":"+1 906 663 4005",
    "sg:postcode":"49911",
    "sg:province":"MI",
    "sg:tags":[
        "baker"
    ],
    "wof:name":"Bread Of Life Bakery & Cafe",
    "wof:placetype":"venue"
},
  "geometry": {"coordinates":[-90.050268,46.481887],"type":"Point"}
}