{
  "type": "Feature",
  "properties": {
    "iso:country":"US",
    "sg:address":"8023 Summerfield Rd",
    "sg:city":"Lambertville",
    "sg:classifiers":[
        {
            "category":"Government",
            "subcategory":"Post Office",
            "type":"Public Place"
        }
    ],
    "sg:phone":"+1 734 000 1111",
    "sg:postcode":"48144",
    "sg:province":"MI",
    "wof:name":"US Post Office",
    "wof:placetype":"venue"
},
  "geometry": {"coordinates":[-83.626547,41.760915],"type":"Point"}
}