{
  "type": "Feature",
  "properties": {
    "iso:country":"US",
    "sg:address":"114 Stimpson St",
    "sg:city":"Pellston",
    "sg:classifiers":[
        {
            "category":"Shopping",
            "subcategory":"Used Merchandise",
            "type":"Retail Goods"
        }
    ],
    "sg:phone":"+1 231 539 8030",
    "sg:postcode":"49769",
    "sg:province":"MI",
    "sg:tags":[
        "antique"
    ],
    "wof:name":"Antiques Art & Collectables",
    "wof:placetype":"venue"
},
  "geometry": {"coordinates":[-84.784449,45.552156],"type":"Point"}
}