{
  "type": "Feature",
  "properties": {
    "iso:country":"US",
    "sg:address":"118 W Washington St",
    "sg:city":"Marquette",
    "sg:classifiers":[
        {
            "category":"Professional",
            "type":"Services"
        },
        {
            "category":"Personal",
            "subcategory":"Beauty Salon",
            "type":"Services"
        }
    ],
    "sg:phone":"+1 906 226 9600",
    "sg:postcode":"49855",
    "sg:province":"MI",
    "wof:name":"Edge Hair Studio  The",
    "wof:placetype":"venue"
},
  "geometry": {"coordinates":[-87.395017,46.543588],"type":"Point"}
}