{
  "type": "Feature",
  "properties": {
    "iso:country":"US",
    "sg:address":"921 Brown Rd",
    "sg:city":"Lake Orion",
    "sg:classifiers":[
        {
            "category":"Retail",
            "subcategory":"Auto Repair",
            "type":"Services"
        }
    ],
    "sg:phone":"+1 248 393 8355",
    "sg:postcode":"48359",
    "sg:province":"MI",
    "sg:tags":[
        "body"
    ],
    "wof:name":"Great Lakes Collision Repair",
    "wof:placetype":"venue"
},
  "geometry": {"coordinates":[-83.265381,42.708289],"type":"Point"}
}