{
  "type": "Feature",
  "properties": {
    "iso:country":"US",
    "sg:address":"1655 Wright Ave",
    "sg:city":"Alma",
    "sg:classifiers":[
        {
            "category":"Health Services",
            "subcategory":"Hospital",
            "type":"Services"
        }
    ],
    "sg:phone":"+1 989 463 6656",
    "sg:postcode":"48801",
    "sg:province":"MI",
    "sg:tags":[
        "mental"
    ],
    "wof:name":"Ellen S Vandemark",
    "wof:placetype":"venue"
},
  "geometry": {"coordinates":[-84.666777,43.394012],"type":"Point"}
}