{
  "type": "Feature",
  "properties": {
    "iso:country":"US",
    "sg:address":"54128 Co Rd 388",
    "sg:city":"Grand Junction",
    "sg:classifiers":[
        {
            "category":"Education",
            "subcategory":"Library",
            "type":"Public Place"
        }
    ],
    "sg:phone":"+1 269 434 6510",
    "sg:postcode":"49056",
    "sg:province":"MI",
    "wof:name":"Book Station Library",
    "wof:placetype":"venue"
},
  "geometry": {"coordinates":[-86.072914,42.404482],"type":"Point"}
}