{
  "type": "Feature",
  "properties": {
    "iso:country":"US",
    "sg:address":"427 2nd St",
    "sg:city":"Menominee",
    "sg:classifiers":[
        {
            "category":"Building & Trades",
            "subcategory":"Plumbing",
            "type":"Services"
        }
    ],
    "sg:phone":"+1 906 863 3894",
    "sg:postcode":"49858",
    "sg:province":"MI",
    "sg:tags":[
        "heating",
        "contractor"
    ],
    "wof:name":"Goldstone Barley Hvac & Sheet",
    "wof:placetype":"venue"
},
  "geometry": {"coordinates":[-87.602813,45.102837],"type":"Point"}
}