{
  "type": "Feature",
  "properties": {
    "iso:country":"US",
    "sg:address":"28555 Orchard Lake Rd",
    "sg:city":"Farmington",
    "sg:classifiers":[
        {
            "category":"Professional",
            "subcategory":"Computer Services",
            "type":"Services"
        }
    ],
    "sg:phone":"+1 248 553 3003",
    "sg:postcode":"48334",
    "sg:province":"MI",
    "sg:tags":[
        "datum",
        "programing",
        "custom"
    ],
    "wof:name":"Realcomp II Ltd",
    "wof:placetype":"venue"
},
  "geometry": {"coordinates":[-83.359103,42.507261],"type":"Point"}
}