{
  "type": "Feature",
  "properties": {
    "iso:country":"US",
    "sg:address":"10728 Woodwind",
    "sg:city":"Interlochen",
    "sg:classifiers":[
        {
            "category":"Building & Trades",
            "subcategory":"Construction",
            "type":"Services"
        }
    ],
    "sg:phone":"+1 231 276 9204",
    "sg:postcode":"49643",
    "sg:province":"MI",
    "sg:tags":[
        "roofing",
        "contractor"
    ],
    "wof:name":"Rouch Roofing & Siding",
    "wof:placetype":"venue"
},
  "geometry": {"coordinates":[-85.79051,44.645509],"type":"Point"}
}