{
  "type": "Feature",
  "properties": {
    "iso:country":"US",
    "sg:address":"1080 Hager Dr",
    "sg:city":"Petoskey",
    "sg:classifiers":[
        {
            "category":"Health Services",
            "subcategory":"Doctor",
            "type":"Services"
        }
    ],
    "sg:phone":"+1 231 487 3980",
    "sg:postcode":"49770",
    "sg:province":"MI",
    "wof:name":"Adult Primary Care",
    "wof:placetype":"venue"
},
  "geometry": {"coordinates":[-84.963452,45.34889],"type":"Point"}
}