{
  "type": "Feature",
  "properties": {
    "iso:country":"US",
    "sg:address":"296 N Blind Line Rd",
    "sg:city":"Cedarville",
    "sg:classifiers":[
        {
            "category":"Building & Trades",
            "subcategory":"Construction",
            "type":"Services"
        }
    ],
    "sg:phone":"+1 906 484 2345",
    "sg:postcode":"49719",
    "sg:province":"MI",
    "sg:tags":[
        "general",
        "contractor"
    ],
    "wof:name":"Great Northern Construction Co",
    "wof:placetype":"venue"
},
  "geometry": {"coordinates":[-84.37324700000001,46.003433],"type":"Point"}
}