{
  "type": "Feature",
  "properties": {
    "iso:country":"US",
    "sg:address":"6520 Schaefer Rd",
    "sg:city":"Dearborn",
    "sg:classifiers":[
        {
            "category":"Travel",
            "subcategory":"Travel Agent",
            "type":"Entertainment"
        }
    ],
    "sg:phone":"+1 313 846 1600",
    "sg:postcode":"48126",
    "sg:province":"MI",
    "sg:tags":[
        "agency"
    ],
    "wof:name":"Five Star Travel",
    "wof:placetype":"venue"
},
  "geometry": {"coordinates":[-83.176603,42.338643],"type":"Point"}
}