{
  "type": "Feature",
  "properties": {
    "iso:country":"US",
    "sg:address":"1423 N Raisinville Rd",
    "sg:city":"Monroe",
    "sg:classifiers":[
        {
            "category":"Building & Trades",
            "subcategory":"Construction",
            "type":"Services"
        }
    ],
    "sg:phone":"+1 734 457 4329",
    "sg:postcode":"48162",
    "sg:province":"MI",
    "sg:tags":[
        "excavating",
        "contractor"
    ],
    "wof:name":"All Phase Excavation",
    "wof:placetype":"venue"
},
  "geometry": {"coordinates":[-83.454392,41.958061],"type":"Point"}
}