{
  "type": "Feature",
  "properties": {
    "iso:country":"US",
    "sg:address":"4125 E Court St",
    "sg:city":"Burton",
    "sg:classifiers":[
        {
            "category":"Restaurant",
            "type":"Food & Drink"
        }
    ],
    "sg:phone":"+1 810 742 2187",
    "sg:postcode":"48509",
    "sg:province":"MI",
    "sg:website":"www.bostonmarket.com",
    "wof:name":"Boston Market",
    "wof:placetype":"venue"
},
  "geometry": {"coordinates":[-83.61489899999999,43.018799],"type":"Point"}
}