{
  "type": "Feature",
  "properties": {
    "iso:country":"US",
    "sg:address":"14856 Atwater Dr",
    "sg:city":"Sterling Heights",
    "sg:classifiers":[
        {
            "category":"Real Estate",
            "subcategory":"Real Estate Operator",
            "type":"Services"
        }
    ],
    "sg:phone":"+1 586 566 4544",
    "sg:postcode":"48313",
    "sg:province":"MI",
    "sg:tags":[
        "apartment"
    ],
    "wof:name":"Lakeside Apartments",
    "wof:placetype":"venue"
},
  "geometry": {"coordinates":[-82.97806799999999,42.625515],"type":"Point"}
}