{
  "type": "Feature",
  "properties": {
    "iso:country":"US",
    "sg:address":"2173 Helmsford Dr",
    "sg:city":"Wolverine Lake",
    "sg:classifiers":[
        {
            "category":"Building & Trades",
            "subcategory":"Cleaning & Sanitation",
            "type":"Services"
        }
    ],
    "sg:phone":"+1 248 960 8766",
    "sg:postcode":"48390",
    "sg:province":"MI",
    "sg:tags":[
        "janitor"
    ],
    "wof:name":"Bloomfield Cleaning Svc",
    "wof:placetype":"venue"
},
  "geometry": {"coordinates":[-83.47895699999999,42.554298],"type":"Point"}
}