{
  "type": "Feature",
  "properties": {
    "iso:country":"US",
    "sg:address":"3797 Pleasant Ridge Dr",
    "sg:city":"Williamsburg",
    "sg:classifiers":[
        {
            "category":"Retail",
            "subcategory":"Repair Shop",
            "type":"Services"
        }
    ],
    "sg:phone":"+1 231 938 2347",
    "sg:postcode":"49690",
    "sg:province":"MI",
    "sg:tags":[
        "group"
    ],
    "wof:name":"David Chown",
    "wof:placetype":"venue"
},
  "geometry": {"coordinates":[-85.498159,44.760394],"type":"Point"}
}