{
  "type": "Feature",
  "properties": {
    "iso:country":"US",
    "sg:address":"31720 Gratiot Ave",
    "sg:city":"Roseville",
    "sg:classifiers":[
        {
            "category":"Wholesale",
            "subcategory":"Medical Equipment & Supplies",
            "type":"Manufacturing & Wholesale Goods"
        }
    ],
    "sg:phone":"+1 586 294 3332",
    "sg:postcode":"48066",
    "sg:province":"MI",
    "sg:tags":[
        "assistive",
        "aid",
        "device",
        "hearing"
    ],
    "wof:name":"GSM-Walker Products",
    "wof:placetype":"venue"
},
  "geometry": {"coordinates":[-82.91513,42.52999],"type":"Point"}
}