{
  "type": "Feature",
  "properties": {
    "iso:country":"US",
    "sg:address":"3229 Turner St",
    "sg:city":"Lansing",
    "sg:classifiers":[
        {
            "category":"Communications",
            "subcategory":"Film & Video Production",
            "type":"Services"
        }
    ],
    "sg:phone":"+1 517 484 3483",
    "sg:postcode":"48906",
    "sg:province":"MI",
    "wof:name":"Aguilar Tlvsion Rdo Cmmnctions",
    "wof:placetype":"venue"
},
  "geometry": {"coordinates":[-84.555834,42.766499],"type":"Point"}
}