{
  "type": "Feature",
  "properties": {
    "iso:country":"US",
    "sg:address":"2005 Riverside Ct",
    "sg:city":"Lansing",
    "sg:classifiers":[
        {
            "category":"Building & Trades",
            "subcategory":"Construction",
            "type":"Services"
        }
    ],
    "sg:phone":"+1 517 327 8260",
    "sg:postcode":"48906",
    "sg:province":"MI",
    "sg:tags":[
        "layer",
        "carpet"
    ],
    "wof:name":"Doering Group Inc",
    "wof:placetype":"venue"
},
  "geometry": {"coordinates":[-84.563046,42.757576],"type":"Point"}
}