{
  "type": "Feature",
  "properties": {
    "iso:country":"US",
    "sg:address":"1093 Stable Ln",
    "sg:city":"South Lyon",
    "sg:classifiers":[
        {
            "category":"Wholesale",
            "subcategory":"Machinery & Supplies",
            "type":"Manufacturing & Wholesale Goods"
        }
    ],
    "sg:phone":"+1 248 437 0414",
    "sg:postcode":"48178",
    "sg:province":"MI",
    "sg:tags":[
        "industrial"
    ],
    "wof:name":"Avk Industrial Products",
    "wof:placetype":"venue"
},
  "geometry": {"coordinates":[-83.65676000000001,42.47539],"type":"Point"}
}