{
  "type": "Feature",
  "properties": {
    "iso:country":"US",
    "sg:address":"32042 Beacon Ln",
    "sg:city":"Fraser",
    "sg:classifiers":[
        {
            "category":"Government",
            "subcategory":"Office",
            "type":"Public Place"
        }
    ],
    "sg:phone":"+1 586 294 3890",
    "sg:postcode":"48026",
    "sg:province":"MI",
    "sg:tags":[
        "village"
    ],
    "wof:name":"Fraser Dpw",
    "wof:placetype":"venue"
},
  "geometry": {"coordinates":[-82.933176,42.532362],"type":"Point"}
}