{
  "type": "Feature",
  "properties": {
    "iso:country":"US",
    "sg:address":"1483 US Hwy 31 S",
    "sg:city":"Petoskey",
    "sg:classifiers":[
        {
            "category":"Real Estate",
            "subcategory":"Real Estate Agent",
            "type":"Services"
        }
    ],
    "sg:phone":"+1 231 348 2765",
    "sg:postcode":"49770",
    "sg:province":"MI",
    "sg:tags":[
        "management"
    ],
    "wof:name":"Holiday Accommodations",
    "wof:placetype":"venue"
},
  "geometry": {"coordinates":[-84.98696200000001,45.367845],"type":"Point"}
}