{
  "type": "Feature",
  "properties": {
    "iso:country":"US",
    "sg:address":"45150 Utica Park Blvd",
    "sg:city":"Utica",
    "sg:classifiers":[
        {
            "category":"Home & Garden",
            "subcategory":"Furniture",
            "type":"Retail Goods"
        }
    ],
    "sg:phone":"+1 586 726 7600",
    "sg:postcode":"48315",
    "sg:province":"MI",
    "sg:website":"www.newtonfurn.com",
    "wof:name":"Newton Furniture Inc",
    "wof:placetype":"venue"
},
  "geometry": {"coordinates":[-83.007755,42.627039],"type":"Point"}
}