{
  "type": "Feature",
  "properties": {
    "iso:country":"US",
    "sg:address":"400 State St",
    "sg:city":"Lincoln",
    "sg:classifiers":[
        {
            "category":"Retail",
            "subcategory":"Car Wash",
            "type":"Services"
        }
    ],
    "sg:phone":"+1 989 736 3252",
    "sg:postcode":"48740",
    "sg:province":"MI",
    "sg:tags":[
        "carwash"
    ],
    "wof:name":"Water Works",
    "wof:placetype":"venue"
},
  "geometry": {"coordinates":[-83.303962,44.644978],"type":"Point"}
}