{
  "type": "Feature",
  "properties": {
    "iso:country":"US",
    "sg:address":"712 E Grand Blvd",
    "sg:city":"Ypsilanti",
    "sg:classifiers":[
        {
            "category":"Organizations",
            "subcategory":"Religious Organization",
            "type":"Services"
        }
    ],
    "sg:phone":"+1 734 484 0992",
    "sg:postcode":"48198",
    "sg:province":"MI",
    "wof:name":"New Hope Baptist Church",
    "wof:placetype":"venue"
},
  "geometry": {"coordinates":[-83.58192699999999,42.253508],"type":"Point"}
}