{
  "type": "Feature",
  "properties": {
    "iso:country":"US",
    "sg:address":"1953 Portage St",
    "sg:city":"Kalamazoo",
    "sg:classifiers":[
        {
            "category":"Shopping",
            "subcategory":"Music",
            "type":"Retail Goods"
        }
    ],
    "sg:phone":"+1 269 276 0044",
    "sg:postcode":"49001",
    "sg:province":"MI",
    "sg:tags":[
        "compact",
        "record",
        "disc",
        "tape"
    ],
    "wof:name":"Casa Of Musica Garcia",
    "wof:placetype":"venue"
},
  "geometry": {"coordinates":[-85.572582,42.2718],"type":"Point"}
}