{
  "type": "Feature",
  "properties": {
    "iso:country":"US",
    "sg:address":"3583 Westcott Dr SE",
    "sg:city":"Ada",
    "sg:classifiers":[
        {
            "category":"Professional",
            "subcategory":"Management & Consulting",
            "type":"Services"
        }
    ],
    "sg:phone":"+1 616 682 8350",
    "sg:postcode":"49301",
    "sg:province":"MI",
    "sg:tags":[
        "business"
    ],
    "wof:name":"Madison Consulting",
    "wof:placetype":"venue"
},
  "geometry": {"coordinates":[-85.47339599999999,42.901361],"type":"Point"}
}