{
  "type": "Feature",
  "properties": {
    "iso:country":"US",
    "sg:address":"1434 S 13th St",
    "sg:city":"Niles",
    "sg:classifiers":[
        {
            "category":"Autos & Motor Vehicles",
            "subcategory":"Auto Supplies",
            "type":"Retail Goods"
        }
    ],
    "sg:phone":"+1 269 683 0313",
    "sg:postcode":"49120",
    "sg:province":"MI",
    "sg:tags":[
        "tire"
    ],
    "wof:name":"Zolman Tire Inc",
    "wof:placetype":"venue"
},
  "geometry": {"coordinates":[-86.24582100000001,41.810805],"type":"Point"}
}