{
  "type": "Feature",
  "properties": {
    "iso:country":"US",
    "sg:address":"116 N Michigan Ave",
    "sg:city":"Saginaw",
    "sg:classifiers":[
        {
            "category":"Restaurant",
            "type":"Food & Drink"
        }
    ],
    "sg:phone":"+1 989 790 1000",
    "sg:postcode":"48602",
    "sg:province":"MI",
    "wof:name":"Guido's",
    "wof:placetype":"venue"
},
  "geometry": {"coordinates":[-83.963482,43.418086],"type":"Point"}
}