{
  "type": "Feature",
  "properties": {
    "iso:country":"US",
    "sg:address":"12296 White Creek Ave NE",
    "sg:city":"Cedar Springs",
    "sg:classifiers":[
        {
            "category":"Local Transit",
            "type":"Transportation"
        }
    ],
    "sg:phone":"+1 616 240 6053",
    "sg:postcode":"49319",
    "sg:province":"MI",
    "sg:tags":[
        "limousine",
        "rental"
    ],
    "wof:name":"Excluvive Limousine Service",
    "wof:placetype":"venue"
},
  "geometry": {"coordinates":[-85.57103600000001,43.193487],"type":"Point"}
}