{
  "type": "Feature",
  "properties": {
    "iso:country":"US",
    "sg:address":"3899 Grow Rd NW",
    "sg:city":"Stanton",
    "sg:classifiers":[
        {
            "category":"Organizations",
            "subcategory":"Religious Organization",
            "type":"Services"
        }
    ],
    "sg:phone":"+1 989 762 5487",
    "sg:postcode":"48888",
    "sg:province":"MI",
    "sg:tags":[
        "church"
    ],
    "wof:name":"Entrican Bible Church",
    "wof:placetype":"venue"
},
  "geometry": {"coordinates":[-85.15447,43.349082],"type":"Point"}
}