{
  "type": "Feature",
  "properties": {
    "iso:country":"US",
    "sg:address":"13501 E 12 Mile Rd",
    "sg:city":"Warren",
    "sg:classifiers":[
        {
            "category":"Food & Beverages",
            "subcategory":"Groceries & Convenience Stores",
            "type":"Retail Goods"
        }
    ],
    "sg:phone":"+1 586 576 0276",
    "sg:postcode":"48088",
    "sg:province":"MI",
    "sg:tags":[
        "grocer"
    ],
    "wof:name":"Beeblos Grocery Store",
    "wof:placetype":"venue"
},
  "geometry": {"coordinates":[-82.98781,42.507707],"type":"Point"}
}