{
  "type": "Feature",
  "properties": {
    "iso:country":"US",
    "sg:address":"1000 Blossom Heath Blvd",
    "sg:city":"St Clair Shores",
    "sg:classifiers":[
        {
            "category":"Government",
            "subcategory":"Office",
            "type":"Public Place"
        }
    ],
    "sg:phone":"+1 586 773 9200",
    "sg:postcode":"48080",
    "sg:province":"MI",
    "sg:tags":[
        "village"
    ],
    "wof:name":"St Clair Shores Leisure Manor",
    "wof:placetype":"venue"
},
  "geometry": {"coordinates":[-82.88716100000001,42.474209],"type":"Point"}
}