{
  "type": "Feature",
  "properties": {
    "iso:country":"US",
    "sg:address":"32049 Howard Ave",
    "sg:city":"Madison Heights",
    "sg:classifiers":[
        {
            "category":"Manufacturing",
            "subcategory":"Rubber & Plastics",
            "type":"Manufacturing & Wholesale Goods"
        },
        {
            "category":"Retail",
            "subcategory":"Auto Repair",
            "type":"Services"
        }
    ],
    "sg:phone":"+1 248 307 9088",
    "sg:postcode":"48071",
    "sg:province":"MI",
    "sg:tags":[
        "product",
        "for",
        "supply",
        "automotive",
        "supplier",
        "inspector",
        "quality"
    ],
    "wof:name":"Performance Enterprises Inc",
    "wof:placetype":"venue"
},
  "geometry": {"coordinates":[-83.09948799999999,42.530327],"type":"Point"}
}