{
  "type": "Feature",
  "properties": {
    "iso:country":"US",
    "sg:address":"1551 N Zimmerman Rd",
    "sg:city":"Honor",
    "sg:classifiers":[
        {
            "category":"Retail",
            "subcategory":"Repair Shop",
            "type":"Services"
        }
    ],
    "sg:phone":"+1 231 325 5532",
    "sg:postcode":"49640",
    "sg:province":"MI",
    "sg:tags":[
        "lock",
        "locksmith"
    ],
    "wof:name":"Mayo's Lock Shop",
    "wof:placetype":"venue"
},
  "geometry": {"coordinates":[-86.018714,44.646142],"type":"Point"}
}