{
  "type": "Feature",
  "properties": {
    "iso:country":"US",
    "sg:address":"800 W 13th St",
    "sg:city":"Cadillac",
    "sg:classifiers":[
        {
            "category":"Education",
            "subcategory":"School",
            "type":"Public Place"
        }
    ],
    "sg:phone":"+1 231 775 1301",
    "sg:postcode":"49601",
    "sg:province":"MI",
    "wof:name":"St Ann School",
    "wof:placetype":"venue"
},
  "geometry": {"coordinates":[-85.420052,44.26693],"type":"Point"}
}