{
  "type": "Feature",
  "properties": {
    "iso:country":"US",
    "sg:address":"70050 S Centerville Rd",
    "sg:city":"Sturgis",
    "sg:classifiers":[
        {
            "category":"Real Estate",
            "subcategory":"Real Estate Agent",
            "type":"Services"
        }
    ],
    "sg:phone":"+1 269 651 1451",
    "sg:postcode":"49091",
    "sg:province":"MI",
    "wof:name":"Century 21",
    "wof:placetype":"venue"
},
  "geometry": {"coordinates":[-85.428269,41.781108],"type":"Point"}
}