{
  "type": "Feature",
  "properties": {
    "iso:country":"US",
    "sg:address":"110 N Saginaw St",
    "sg:city":"Lapeer",
    "sg:classifiers":[
        {
            "category":"Professional",
            "subcategory":"Lawyer & Legal Services",
            "type":"Services"
        }
    ],
    "sg:phone":"+1 810 664 0750",
    "sg:postcode":"48446",
    "sg:province":"MI",
    "wof:name":"Rickard Higgins Denney & Assoc",
    "wof:placetype":"venue"
},
  "geometry": {"coordinates":[-83.30586099999999,43.052063],"type":"Point"}
}