{
  "type": "Feature",
  "properties": {
    "iso:country":"US",
    "sg:address":"167 W North St",
    "sg:city":"Jackson",
    "sg:classifiers":[
        {
            "category":"Home & Garden",
            "subcategory":"Building Materials",
            "type":"Retail Goods"
        }
    ],
    "sg:phone":"+1 517 784 6138",
    "sg:postcode":"49202",
    "sg:province":"MI",
    "sg:tags":[
        "paint"
    ],
    "wof:name":"Tingley's Paint & Wallpaper",
    "wof:placetype":"venue"
},
  "geometry": {"coordinates":[-84.408232,42.258892],"type":"Point"}
}