{
  "type": "Feature",
  "properties": {
    "iso:country":"US",
    "sg:address":"4571 W Stanley Rd",
    "sg:city":"Mount Morris",
    "sg:classifiers":[
        {
            "category":"Food & Beverages",
            "subcategory":"Specialty",
            "type":"Retail Goods"
        }
    ],
    "sg:phone":"+1 810 640 2606",
    "sg:postcode":"48458",
    "sg:province":"MI",
    "wof:name":"Mikatam Foods",
    "wof:placetype":"venue"
},
  "geometry": {"coordinates":[-83.77031700000001,43.104231],"type":"Point"}
}