{
  "type": "Feature",
  "properties": {
    "iso:country":"US",
    "sg:address":"111 Superior Ave",
    "sg:city":"Baraga",
    "sg:classifiers":[
        {
            "category":"Bars & Pubs",
            "type":"Food & Drink"
        }
    ],
    "sg:phone":"+1 906 353 6777",
    "sg:postcode":"49908",
    "sg:province":"MI",
    "wof:name":"Side Track Bar",
    "wof:placetype":"venue"
},
  "geometry": {"coordinates":[-88.483372,46.783926],"type":"Point"}
}