{
  "type": "Feature",
  "properties": {
    "iso:country":"US",
    "sg:address":"23031 Kenosha St",
    "sg:city":"Oak Park",
    "sg:classifiers":[
        {
            "category":"Shopping",
            "subcategory":"Department Store",
            "type":"Retail Goods"
        }
    ],
    "sg:phone":"+1 248 414 4467",
    "sg:postcode":"48237",
    "sg:province":"MI",
    "wof:name":"La Chez Apparel",
    "wof:placetype":"venue"
},
  "geometry": {"coordinates":[-83.19071599999999,42.460002],"type":"Point"}
}