{
  "type": "Feature",
  "properties": {
    "iso:country":"US",
    "sg:address":"11193 Honor Hwy",
    "sg:city":"Honor",
    "sg:classifiers":[
        {
            "category":"Autos & Motor Vehicles",
            "subcategory":"Automobile Sales",
            "type":"Retail Goods"
        }
    ],
    "sg:phone":"+1 231 275 3313",
    "sg:postcode":"49640",
    "sg:province":"MI",
    "sg:tags":[
        "car",
        "dealer"
    ],
    "wof:name":"K & J Auto",
    "wof:placetype":"venue"
},
  "geometry": {"coordinates":[-86.01485599999999,44.662902],"type":"Point"}
}