{
  "type": "Feature",
  "properties": {
    "iso:country":"US",
    "sg:address":"31065 Orchard Lake Rd",
    "sg:city":"Farmington Hills",
    "sg:classifiers":[
        {
            "category":"Shopping",
            "subcategory":"Clothing, Apparel, & Fashions",
            "type":"Retail Goods"
        }
    ],
    "sg:phone":"+1 248 737 9259",
    "sg:postcode":"48334",
    "sg:province":"MI",
    "sg:tags":[
        "accessory"
    ],
    "wof:name":"Christopher & Banks",
    "wof:placetype":"venue"
},
  "geometry": {"coordinates":[-83.36016499999999,42.525846],"type":"Point"}
}