{
  "type": "Feature",
  "properties": {
    "iso:country":"US",
    "sg:address":"21800 W 10 Mile Rd Ste 203A",
    "sg:city":"Southfield",
    "sg:classifiers":[
        {
            "category":"Professional",
            "subcategory":"Accounting & Tax Preparation",
            "type":"Services"
        }
    ],
    "sg:phone":"+1 248 354 3997",
    "sg:postcode":"48075",
    "sg:province":"MI",
    "sg:tags":[
        "accountant"
    ],
    "wof:name":"Bokolor Mark CPA",
    "wof:placetype":"venue"
},
  "geometry": {"coordinates":[-83.259399,42.4725],"type":"Point"}
}