{
  "type": "Feature",
  "properties": {
    "iso:country":"US",
    "sg:address":"2227 S Commerce Rd",
    "sg:city":"Wolverine Lake",
    "sg:classifiers":[
        {
            "category":"Professional",
            "subcategory":"Detective & Security Services",
            "type":"Services"
        }
    ],
    "sg:phone":"+1 248 669 3550",
    "sg:postcode":"48390",
    "sg:province":"MI",
    "sg:tags":[
        "guard",
        "patrol"
    ],
    "wof:name":"Master Security Co",
    "wof:placetype":"venue"
},
  "geometry": {"coordinates":[-83.478678,42.55474],"type":"Point"}
}