{
  "type": "Feature",
  "properties": {
    "iso:country":"US",
    "sg:address":"222 Park Ave",
    "sg:city":"Petoskey",
    "sg:classifiers":[
        {
            "category":"Personal",
            "subcategory":"Beauty Salon",
            "type":"Services"
        }
    ],
    "sg:phone":"+1 231 348 5956",
    "sg:postcode":"49770",
    "sg:province":"MI",
    "wof:name":"Tracy Lee Salon",
    "wof:placetype":"venue"
},
  "geometry": {"coordinates":[-84.954449,45.375658],"type":"Point"}
}