{
  "type": "Feature",
  "properties": {
    "iso:country":"US",
    "sg:address":"5656 Clyde Park Ave SW",
    "sg:city":"Grand Rapids",
    "sg:classifiers":[
        {
            "category":"Restaurant",
            "type":"Food & Drink"
        }
    ],
    "sg:phone":"+1 616 530 2400",
    "sg:postcode":"49509",
    "sg:province":"MI",
    "sg:tags":[
        "shop",
        "pro",
        "bar",
        "center",
        "bowling"
    ],
    "wof:name":"Woodys Pressbox",
    "wof:placetype":"venue"
},
  "geometry": {"coordinates":[-85.683566,42.859511],"type":"Point"}
}