{
  "type": "Feature",
  "properties": {
    "iso:country":"US",
    "sg:address":"7335 McGraw St",
    "sg:city":"Detroit",
    "sg:classifiers":[
        {
            "category":"Wholesale",
            "subcategory":"Fruits & Vegetables",
            "type":"Manufacturing & Wholesale Goods"
        }
    ],
    "sg:phone":"+1 313 895 4130",
    "sg:postcode":"48210",
    "sg:province":"MI",
    "sg:tags":[
        "veggie"
    ],
    "wof:name":"Big Apple Fruit Market Inc",
    "wof:placetype":"venue"
},
  "geometry": {"coordinates":[-83.13800000000001,42.336498],"type":"Point"}
}