{
  "type": "Feature",
  "properties": {
    "iso:country":"US",
    "sg:address":"851 N Canton Center Rd",
    "sg:city":"Canton",
    "sg:classifiers":[
        {
            "category":"Retail",
            "subcategory":"Funeral Services",
            "type":"Services"
        }
    ],
    "sg:phone":"+1 734 981 4530",
    "sg:postcode":"48187",
    "sg:province":"MI",
    "sg:tags":[
        "cemetery"
    ],
    "wof:name":"McCabe Funeral Home",
    "wof:placetype":"venue"
},
  "geometry": {"coordinates":[-83.48719800000001,42.310699],"type":"Point"}
}