{
  "type": "Feature",
  "properties": {
    "iso:country":"US",
    "sg:address":"110 Huron Blvd",
    "sg:city":"Marysville",
    "sg:classifiers":[
        {
            "category":"Professional",
            "type":"Services"
        }
    ],
    "sg:phone":"+1 810 364 4334",
    "sg:postcode":"48040",
    "sg:province":"MI",
    "sg:tags":[
        "establishment"
    ],
    "wof:name":"T & J Corp",
    "wof:placetype":"venue"
},
  "geometry": {"coordinates":[-82.48107400000001,42.910994],"type":"Point"}
}