{
  "type": "Feature",
  "properties": {
    "iso:country":"US",
    "sg:address":"27489 Schoolcraft Rd",
    "sg:city":"Livonia",
    "sg:classifiers":[
        {
            "category":"Home & Garden",
            "subcategory":"Hardware",
            "type":"Retail Goods"
        }
    ],
    "sg:phone":"+1 734 427 6991",
    "sg:postcode":"48150",
    "sg:province":"MI",
    "sg:tags":[
        "fire",
        "sprinklers-residential",
        "industrial",
        "commercial",
        "automatic"
    ],
    "wof:name":"Magnum Fire Protection",
    "wof:placetype":"venue"
},
  "geometry": {"coordinates":[-83.315904,42.38366],"type":"Point"}
}