{
  "type": "Feature",
  "properties": {
    "iso:country":"US",
    "sg:address":"22255 Hall Rd",
    "sg:city":"Macomb",
    "sg:classifiers":[
        {
            "category":"Building & Trades",
            "subcategory":"Construction",
            "type":"Services"
        }
    ],
    "sg:phone":"+1 586 598 7774",
    "sg:postcode":"48042",
    "sg:province":"MI",
    "sg:tags":[
        "carpenter"
    ],
    "wof:name":"A & E Contracting Inc",
    "wof:placetype":"venue"
},
  "geometry": {"coordinates":[-82.884992,42.629427],"type":"Point"}
}