{
  "type": "Feature",
  "properties": {
    "iso:country":"US",
    "sg:address":"4460 24th Ave",
    "sg:city":"Fort Gratiot",
    "sg:classifiers":[
        {
            "category":"Professional",
            "type":"Services"
        }
    ],
    "sg:phone":"+1 810 385 2010",
    "sg:postcode":"48059",
    "sg:province":"MI",
    "sg:tags":[
        "establishment"
    ],
    "wof:name":"Advantis",
    "wof:placetype":"venue"
},
  "geometry": {"coordinates":[-82.45662400000001,43.038054],"type":"Point"}
}