{
  "type": "Feature",
  "properties": {
    "iso:country":"US",
    "sg:address":"608 W Michigan Ave",
    "sg:city":"Jackson",
    "sg:classifiers":[
        {
            "category":"Health Services",
            "subcategory":"Doctor",
            "type":"Services"
        }
    ],
    "sg:phone":"+1 517 784 3009",
    "sg:postcode":"49201",
    "sg:province":"MI",
    "sg:tags":[
        "dentist"
    ],
    "wof:name":"Jeffery D Hurst DDS",
    "wof:placetype":"venue"
},
  "geometry": {"coordinates":[-84.41849499999999,42.247494],"type":"Point"}
}