{
  "type": "Feature",
  "properties": {
    "iso:country":"US",
    "sg:address":"35296 Mound Rd",
    "sg:city":"Sterling Heights",
    "sg:classifiers":[
        {
            "category":"Communications",
            "type":"Services"
        }
    ],
    "sg:phone":"+1 586 977 7087",
    "sg:postcode":"48310",
    "sg:province":"MI",
    "sg:tags":[
        "web",
        "design"
    ],
    "sg:website":"www.apexdigital.com",
    "wof:name":"Apex Digital Solutions",
    "wof:placetype":"venue"
},
  "geometry": {"coordinates":[-83.048103,42.5527],"type":"Point"}
}