{
  "type": "Feature",
  "properties": {
    "iso:country":"US",
    "sg:address":"512 Goddard St",
    "sg:city":"Wyandotte",
    "sg:classifiers":[
        {
            "category":"Retail",
            "subcategory":"Repair Shop",
            "type":"Services"
        }
    ],
    "sg:phone":"+1 734 281 1730",
    "sg:postcode":"48192",
    "sg:province":"MI",
    "sg:tags":[
        "propeller",
        "marine"
    ],
    "wof:name":"Marine Propeller Inc",
    "wof:placetype":"venue"
},
  "geometry": {"coordinates":[-83.15716500000001,42.223798],"type":"Point"}
}