{
  "type": "Feature",
  "properties": {
    "iso:country":"US",
    "sg:address":"58766 Ash Rd",
    "sg:city":"Three Rivers",
    "sg:classifiers":[
        {
            "category":"Building & Trades",
            "subcategory":"Plumbing",
            "type":"Services"
        }
    ],
    "sg:phone":"+1 269 273 7296",
    "sg:postcode":"49093",
    "sg:province":"MI",
    "sg:tags":[
        "contractor"
    ],
    "wof:name":"Micks Heating & A & Plbg Repr",
    "wof:placetype":"venue"
},
  "geometry": {"coordinates":[-85.592163,41.947576],"type":"Point"}
}