{
  "type": "Feature",
  "properties": {
    "iso:country":"US",
    "sg:address":"4519 Brightmore Rd",
    "sg:city":"Bloomfield Hills",
    "sg:classifiers":[
        {
            "category":"Professional",
            "subcategory":"Business Services",
            "type":"Services"
        }
    ],
    "sg:phone":"+1 248 642 2777",
    "sg:postcode":"48302",
    "sg:province":"MI",
    "sg:tags":[
        "interior",
        "decorator"
    ],
    "wof:name":"Liefeld Interiors",
    "wof:placetype":"venue"
},
  "geometry": {"coordinates":[-83.27188,42.575054],"type":"Point"}
}