{
  "type": "Feature",
  "properties": {
    "iso:country":"US",
    "sg:address":"313 E Mitchell St",
    "sg:city":"Petoskey",
    "sg:classifiers":[
        {
            "category":"Real Estate",
            "subcategory":"Real Estate Agent",
            "type":"Services"
        }
    ],
    "sg:phone":"+1 231 347 6410",
    "sg:postcode":"49770",
    "sg:province":"MI",
    "sg:tags":[
        "management"
    ],
    "wof:name":"Colwell Property Management",
    "wof:placetype":"venue"
},
  "geometry": {"coordinates":[-84.955713,45.374051],"type":"Point"}
}