{
  "type": "Feature",
  "properties": {
    "iso:country":"US",
    "sg:address":"6325 W Jefferson Ave",
    "sg:city":"Detroit",
    "sg:classifiers":[
        {
            "category":"Museum",
            "type":"Entertainment"
        }
    ],
    "sg:phone":"+1 313 297 8382",
    "sg:postcode":"48209",
    "sg:province":"MI",
    "sg:tags":[
        "gallery"
    ],
    "wof:name":"Collections Resource Center",
    "wof:placetype":"venue"
},
  "geometry": {"coordinates":[-83.09984900000001,42.299156],"type":"Point"}
}