{
  "type": "Feature",
  "properties": {
    "iso:country":"US",
    "sg:address":"168 E Wright Ave",
    "sg:city":"Shepherd",
    "sg:classifiers":[
        {
            "category":"Organizations",
            "subcategory":"Religious Organization",
            "type":"Services"
        }
    ],
    "sg:phone":"+1 989 828 5720",
    "sg:postcode":"48883",
    "sg:province":"MI",
    "wof:name":"St Vincent De Paul",
    "wof:placetype":"venue"
},
  "geometry": {"coordinates":[-84.68992799999999,43.524155],"type":"Point"}
}