{
  "type": "Feature",
  "properties": {
    "iso:country":"US",
    "sg:address":"6812 Old 28th St SE",
    "sg:city":"Grand Rapids",
    "sg:classifiers":[
        {
            "category":"Real Estate",
            "subcategory":"Real Estate Services",
            "type":"Services"
        }
    ],
    "sg:phone":"+1 616 301 1170",
    "sg:postcode":"49546",
    "sg:province":"MI",
    "sg:tags":[
        "company",
        "title"
    ],
    "wof:name":"Complete Title Svc-Southern",
    "wof:placetype":"venue"
},
  "geometry": {"coordinates":[-85.500236,42.913176],"type":"Point"}
}