{
  "type": "Feature",
  "properties": {
    "iso:country":"US",
    "sg:address":"1220 W Sanilac Rd",
    "sg:city":"Caro",
    "sg:classifiers":[
        {
            "category":"Health Services",
            "subcategory":"Clinic",
            "type":"Services"
        }
    ],
    "sg:phone":"+1 989 672 3103",
    "sg:postcode":"48723",
    "sg:province":"MI",
    "sg:tags":[
        "fire",
        "rake",
        "side",
        "parts",
        "manufacturing",
        "rack"
    ],
    "wof:name":"Cass Valley Enterprises Whse",
    "wof:placetype":"venue"
},
  "geometry": {"coordinates":[-83.400396,43.408868],"type":"Point"}
}