{
  "type": "Feature",
  "properties": {
    "iso:country":"US",
    "sg:address":"1674 Riva Ridge Dr SE",
    "sg:city":"Grand Rapids",
    "sg:classifiers":[
        {
            "category":"Professional",
            "subcategory":"Lawyer & Legal Services",
            "type":"Services"
        }
    ],
    "sg:phone":"+1 616 956 6969",
    "sg:postcode":"49546",
    "sg:province":"MI",
    "sg:tags":[
        "attorney"
    ],
    "wof:name":"Matthew J Missad",
    "wof:placetype":"venue"
},
  "geometry": {"coordinates":[-85.550811,42.933526],"type":"Point"}
}