{
  "type": "Feature",
  "properties": {
    "iso:country":"US",
    "sg:address":"401 N Demorest St",
    "sg:city":"Belding",
    "sg:classifiers":[
        {
            "category":"Building & Trades",
            "subcategory":"Construction",
            "type":"Services"
        }
    ],
    "sg:phone":"+1 616 794 0128",
    "sg:postcode":"48809",
    "sg:province":"MI",
    "sg:tags":[
        "general",
        "contractor"
    ],
    "wof:name":"JDL Installation",
    "wof:placetype":"venue"
},
  "geometry": {"coordinates":[-85.24276399999999,43.099153],"type":"Point"}
}