{
  "type": "Feature",
  "properties": {
    "iso:country":"US",
    "sg:address":"1330 W Washington St",
    "sg:city":"Greenville",
    "sg:classifiers":[
        {
            "category":"Health Services",
            "subcategory":"Health Practitioner",
            "type":"Services"
        }
    ],
    "sg:phone":"+1 616 754 7040",
    "sg:postcode":"48838",
    "sg:province":"MI",
    "sg:tags":[
        "therapist",
        "physical"
    ],
    "wof:name":"Kimberlee J ODonald Pt PC",
    "wof:placetype":"venue"
},
  "geometry": {"coordinates":[-85.272491,43.177335],"type":"Point"}
}