{
  "type": "Feature",
  "properties": {
    "iso:country":"US",
    "sg:address":"23720 Farmington Rd",
    "sg:city":"Farmington",
    "sg:classifiers":[
        {
            "category":"Retail",
            "subcategory":"Funeral Services",
            "type":"Services"
        }
    ],
    "sg:phone":"+1 248 474 5200",
    "sg:postcode":"48336",
    "sg:province":"MI",
    "sg:tags":[
        "home",
        "cemetery"
    ],
    "sg:website":"www.heeney-sundquist.com",
    "wof:name":"Heeney-Sundquist Funeral Home Inc",
    "wof:placetype":"venue"
},
  "geometry": {"coordinates":[-83.37629699999999,42.465401],"type":"Point"}
}