{
  "type": "Feature",
  "properties": {
    "iso:country":"US",
    "sg:address":"19015 Van Born Rd",
    "sg:city":"Allen Park",
    "sg:classifiers":[
        {
            "category":"Bakery",
            "type":"Food & Drink"
        }
    ],
    "sg:phone":"+1 313 563 7566",
    "sg:postcode":"48101",
    "sg:province":"MI",
    "wof:name":"Dough Boy Donuts & Cakes",
    "wof:placetype":"venue"
},
  "geometry": {"coordinates":[-83.22930100000001,42.269798],"type":"Point"}
}