{
  "type": "Feature",
  "properties": {
    "iso:country":"US",
    "sg:address":"25140 Lahser Rd",
    "sg:city":"Southfield",
    "sg:classifiers":[
        {
            "category":"Professional",
            "subcategory":"Lawyer & Legal Services",
            "type":"Services"
        }
    ],
    "sg:phone":"+1 248 353 5111",
    "sg:postcode":"48033",
    "sg:province":"MI",
    "wof:name":"DO It Yourself Divorce",
    "wof:placetype":"venue"
},
  "geometry": {"coordinates":[-83.260592,42.47392],"type":"Point"}
}