{
  "type": "Feature",
  "properties": {
    "iso:country":"US",
    "sg:address":"111 South St",
    "sg:city":"Belleville",
    "sg:classifiers":[
        {
            "category":"Social Services",
            "subcategory":"Child Care",
            "type":"Services"
        }
    ],
    "sg:phone":"+1 734 697 2985",
    "sg:postcode":"48111",
    "sg:province":"MI",
    "sg:tags":[
        "day"
    ],
    "wof:name":"Our Fathers Child",
    "wof:placetype":"venue"
},
  "geometry": {"coordinates":[-83.48508099999999,42.202934],"type":"Point"}
}