{
  "type": "Feature",
  "properties": {
    "iso:country":"US",
    "sg:address":"8028 W Vernor Hwy",
    "sg:city":"Detroit",
    "sg:classifiers":[
        {
            "category":"Health Services",
            "subcategory":"Doctor",
            "type":"Services"
        }
    ],
    "sg:phone":"+1 313 841 7700",
    "sg:postcode":"48209",
    "sg:province":"MI",
    "sg:tags":[
        "surgeon",
        "oral"
    ],
    "wof:name":"Balla Andrea E DDS",
    "wof:placetype":"venue"
},
  "geometry": {"coordinates":[-83.127701,42.311401],"type":"Point"}
}