{
  "type": "Feature",
  "properties": {
    "iso:country":"US",
    "sg:address":"303 Congress St",
    "sg:city":"Sheridan",
    "sg:classifiers":[
        {
            "category":"Health Services",
            "subcategory":"Doctor",
            "type":"Services"
        }
    ],
    "sg:phone":"+1 989 291 3242",
    "sg:postcode":"48884",
    "sg:province":"MI",
    "sg:tags":[
        "physician",
        "surgeon"
    ],
    "wof:name":"Anthony Kam MD",
    "wof:placetype":"venue"
},
  "geometry": {"coordinates":[-85.074831,43.217063],"type":"Point"}
}