{
  "type": "Feature",
  "properties": {
    "iso:country":"US",
    "sg:address":"103 Chocolay River Trl",
    "sg:city":"Marquette",
    "sg:classifiers":[
        {
            "category":"Professional",
            "subcategory":"Accounting & Tax Preparation",
            "type":"Services"
        }
    ],
    "sg:phone":"+1 906 249 1631",
    "sg:postcode":"49855",
    "sg:province":"MI",
    "sg:tags":[
        "return"
    ],
    "wof:name":"Bev Tax Service",
    "wof:placetype":"venue"
},
  "geometry": {"coordinates":[-87.34148399999999,46.491785],"type":"Point"}
}