{
  "type": "Feature",
  "properties": {
    "iso:country":"US",
    "sg:address":"300 S Capitol Ave",
    "sg:city":"Lansing",
    "sg:classifiers":[
        {
            "category":"Education",
            "subcategory":"College",
            "type":"Public Place"
        }
    ],
    "sg:phone":"+1 517 371 5140",
    "sg:postcode":"48933",
    "sg:province":"MI",
    "sg:tags":[
        "academic",
        "school"
    ],
    "sg:website":"www.cooley.edu",
    "wof:name":"Thomas M Cooley Law School",
    "wof:placetype":"venue"
},
  "geometry": {"coordinates":[-84.55392500000001,42.730019],"type":"Point"}
}