{
  "type": "Feature",
  "properties": {
    "iso:country":"US",
    "sg:address":"345 8th St",
    "sg:city":"Ann Arbor",
    "sg:classifiers":[
        {
            "category":"Shopping",
            "subcategory":"Crafts & Fabrics",
            "type":"Retail Goods"
        }
    ],
    "sg:phone":"+1 734 747 9596",
    "sg:postcode":"48103",
    "sg:province":"MI",
    "sg:tags":[
        "sewing"
    ],
    "wof:name":"The Looking Glass Quilt Shop",
    "wof:placetype":"venue"
},
  "geometry": {"coordinates":[-83.75973399999999,42.280799],"type":"Point"}
}