{
  "type": "Feature",
  "properties": {
    "iso:country":"US",
    "sg:address":"1361 Giddings Rd",
    "sg:city":"Pontiac",
    "sg:classifiers":[
        {
            "category":"Organizations",
            "subcategory":"Religious Organization",
            "type":"Services"
        }
    ],
    "sg:phone":"+1 248 373 0311",
    "sg:postcode":"48340",
    "sg:province":"MI",
    "wof:name":"Calvary Missionary Church",
    "wof:placetype":"venue"
},
  "geometry": {"coordinates":[-83.260946,42.672993],"type":"Point"}
}