{
  "type": "Feature",
  "properties": {
    "iso:country":"US",
    "sg:address":"2987 Rau Rd",
    "sg:city":"West Branch",
    "sg:classifiers":[
        {
            "category":"Building & Trades",
            "subcategory":"Construction",
            "type":"Services"
        }
    ],
    "sg:phone":"+1 989 345 0519",
    "sg:postcode":"48661",
    "sg:province":"MI",
    "sg:tags":[
        "excavating",
        "contractor"
    ],
    "wof:name":"Zettel Excavating",
    "wof:placetype":"venue"
},
  "geometry": {"coordinates":[-84.22781000000001,44.233207],"type":"Point"}
}