{
  "type": "Feature",
  "properties": {
    "iso:country":"US",
    "sg:address":"28021 Harper Ave",
    "sg:city":"St Clair Shores",
    "sg:classifiers":[
        {
            "category":"Home & Garden",
            "subcategory":"Building Materials",
            "type":"Retail Goods"
        }
    ],
    "sg:phone":"+1 586 777 5100",
    "sg:postcode":"48081",
    "sg:province":"MI",
    "sg:tags":[
        "door"
    ],
    "sg:website":"www.giganticonline.com",
    "wof:name":"Gigantic Garage Doors",
    "wof:placetype":"venue"
},
  "geometry": {"coordinates":[-82.89779900000001,42.496734],"type":"Point"}
}