{
  "type": "Feature",
  "properties": {
    "iso:country":"US",
    "sg:address":"33524 Kelly Rd",
    "sg:city":"Clinton Twp",
    "sg:classifiers":[
        {
            "category":"Wholesale",
            "subcategory":"Auto Parts",
            "type":"Manufacturing & Wholesale Goods"
        }
    ],
    "sg:phone":"+1 586 790 4074",
    "sg:postcode":"48035",
    "sg:province":"MI",
    "sg:tags":[
        "automobile",
        "supply"
    ],
    "wof:name":"Detroit Connection Inc",
    "wof:placetype":"venue"
},
  "geometry": {"coordinates":[-82.92975300000001,42.542188],"type":"Point"}
}