{
  "type": "Feature",
  "properties": {
    "iso:country":"US",
    "sg:address":"217 N Washington St",
    "sg:city":"Owosso",
    "sg:classifiers":[
        {
            "category":"Professional",
            "subcategory":"Accounting & Tax Preparation",
            "type":"Services"
        }
    ],
    "sg:phone":"+1 989 723 8227",
    "sg:postcode":"48867",
    "sg:province":"MI",
    "sg:tags":[
        "accountant"
    ],
    "wof:name":"Demis & Wenzlick",
    "wof:placetype":"venue"
},
  "geometry": {"coordinates":[-84.170692,42.99932],"type":"Point"}
}