{
  "type": "Feature",
  "properties": {
    "iso:country":"US",
    "sg:address":"5117 I Rd",
    "sg:city":"Bark River",
    "sg:classifiers":[
        {
            "category":"Social Services",
            "subcategory":"Child Care",
            "type":"Services"
        }
    ],
    "sg:phone":"+1 906 789 9648",
    "sg:postcode":"49807",
    "sg:province":"MI",
    "sg:tags":[
        "day"
    ],
    "wof:name":"Linda Laviolette",
    "wof:placetype":"venue"
},
  "geometry": {"coordinates":[-87.20253200000001,45.730599],"type":"Point"}
}