{
  "type": "Feature",
  "properties": {
    "iso:country":"US",
    "sg:address":"2333 E Colby Rd",
    "sg:city":"Stanton",
    "sg:classifiers":[
        {
            "category":"Personal",
            "type":"Services"
        }
    ],
    "sg:phone":"+1 989 831 0139",
    "sg:postcode":"48888",
    "sg:province":"MI",
    "wof:name":"Pampered Piggies-Stephanie Duk",
    "wof:placetype":"venue"
},
  "geometry": {"coordinates":[-85.018773,43.26412],"type":"Point"}
}