{
  "type": "Feature",
  "properties": {
    "iso:country":"US",
    "sg:address":"207 E Hughitt St",
    "sg:city":"Iron Mountain",
    "sg:classifiers":[
        {
            "category":"Shopping",
            "subcategory":"Discount & Variety Stores",
            "type":"Retail Goods"
        }
    ],
    "sg:phone":"+1 906 774 2697",
    "sg:postcode":"49801",
    "sg:province":"MI",
    "wof:name":"TNT Discounts",
    "wof:placetype":"venue"
},
  "geometry": {"coordinates":[-88.06563,45.819304],"type":"Point"}
}