{
  "type": "Feature",
  "properties": {
    "iso:country":"US",
    "sg:address":"9502 Rolling Greens Dr",
    "sg:city":"Pinckney",
    "sg:classifiers":[
        {
            "category":"Manufacturing",
            "subcategory":"Signs",
            "type":"Manufacturing & Wholesale Goods"
        }
    ],
    "sg:phone":"+1 734 878 0036",
    "sg:postcode":"48169",
    "sg:province":"MI",
    "sg:tags":[
        "specialty",
        "mfg"
    ],
    "wof:name":"Andrew Eckman",
    "wof:placetype":"venue"
},
  "geometry": {"coordinates":[-83.896486,42.460401],"type":"Point"}
}