{
  "type": "Feature",
  "properties": {
    "iso:country":"US",
    "sg:address":"4900 Montrose Ave",
    "sg:city":"Okemos",
    "sg:classifiers":[
        {
            "category":"Professional",
            "subcategory":"Lawyer & Legal Services",
            "type":"Services"
        }
    ],
    "sg:phone":"+1 517 347 4178",
    "sg:postcode":"48864",
    "sg:province":"MI",
    "sg:tags":[
        "attorney"
    ],
    "wof:name":"Miller & Shea Pllc",
    "wof:placetype":"venue"
},
  "geometry": {"coordinates":[-84.435401,42.722194],"type":"Point"}
}