{
  "type": "Feature",
  "properties": {
    "iso:country":"US",
    "sg:address":"213 E 10th St",
    "sg:city":"Traverse City",
    "sg:classifiers":[
        {
            "category":"Building & Trades",
            "subcategory":"Construction",
            "type":"Services"
        }
    ],
    "sg:phone":"+1 231 941 0836",
    "sg:postcode":"49684",
    "sg:province":"MI",
    "sg:tags":[
        "painter"
    ],
    "wof:name":"Norman Alexander",
    "wof:placetype":"venue"
},
  "geometry": {"coordinates":[-85.62061199999999,44.757135],"type":"Point"}
}