{
  "type": "Feature",
  "properties": {
    "iso:country":"US",
    "sg:address":"404 Spruce",
    "sg:city":"Elk Rapids",
    "sg:classifiers":[
        {
            "category":"Organizations",
            "subcategory":"Religious Organization",
            "type":"Services"
        }
    ],
    "sg:phone":"+1 231 264 8167",
    "sg:postcode":"49629",
    "sg:province":"MI",
    "wof:name":"First Presbt Church Elk Rapids",
    "wof:placetype":"venue"
},
  "geometry": {"coordinates":[-85.416206,44.894609],"type":"Point"}
}