{
  "type": "Feature",
  "properties": {
    "iso:country":"US",
    "sg:address":"310 Ludington St",
    "sg:city":"Escanaba",
    "sg:classifiers":[
        {
            "category":"Government",
            "subcategory":"Court House",
            "type":"Public Place"
        }
    ],
    "sg:phone":"+1 906 789 5112",
    "sg:postcode":"49829",
    "sg:province":"MI",
    "sg:tags":[
        "county"
    ],
    "wof:name":"Delta County Probate Court",
    "wof:placetype":"venue"
},
  "geometry": {"coordinates":[-87.05205100000001,45.745839],"type":"Point"}
}