{
  "type": "Feature",
  "properties": {
    "iso:country":"US",
    "sg:address":"6325 Quarry Vw",
    "sg:city":"Petoskey",
    "sg:classifiers":[
        {
            "category":"Banks & Credit Unions",
            "subcategory":"Bank",
            "type":"Services"
        }
    ],
    "sg:phone":"+1 231 348 7566",
    "sg:postcode":"49770",
    "sg:province":"MI",
    "sg:tags":[
        "federal",
        "agency"
    ],
    "wof:name":"Criterion International Ltd",
    "wof:placetype":"venue"
},
  "geometry": {"coordinates":[-85.068597,45.362623],"type":"Point"}
}