{
  "type": "Feature",
  "properties": {
    "iso:country":"US",
    "sg:address":"5030 W Pierson Rd",
    "sg:city":"Flint",
    "sg:classifiers":[
        {
            "category":"Retail",
            "subcategory":"Laundry & Dry Cleaning",
            "type":"Services"
        }
    ],
    "sg:phone":"+1 810 249 5880",
    "sg:postcode":"48504",
    "sg:province":"MI",
    "sg:tags":[
        "cleaners"
    ],
    "wof:name":"Pro Clean Laundry & Dry",
    "wof:placetype":"venue"
},
  "geometry": {"coordinates":[-83.777823,43.060574],"type":"Point"}
}