{
  "type": "Feature",
  "properties": {
    "iso:country":"US",
    "sg:address":"3985 Research Park Dr",
    "sg:city":"Ann Arbor",
    "sg:classifiers":[
        {
            "category":"Health Services",
            "subcategory":"Medical Lab",
            "type":"Services"
        }
    ],
    "sg:phone":"+1 734 930 9818",
    "sg:postcode":"48108",
    "sg:province":"MI",
    "sg:tags":[
        "laboratory"
    ],
    "wof:name":"Main Line Technology Inc",
    "wof:placetype":"venue"
},
  "geometry": {"coordinates":[-83.735491,42.23088],"type":"Point"}
}