{
  "type": "Feature",
  "properties": {
    "iso:country":"US",
    "sg:address":"9643 Gratiot Ave",
    "sg:city":"Detroit",
    "sg:classifiers":[
        {
            "category":"Shopping",
            "subcategory":"Mobile Phones",
            "type":"Retail Goods"
        }
    ],
    "sg:phone":"+1 313 267 1591",
    "sg:postcode":"48213",
    "sg:province":"MI",
    "sg:website":"www.t-mobile.com",
    "wof:name":"T Mobile Gratoit & Harper",
    "wof:placetype":"venue"
},
  "geometry": {"coordinates":[-83.00569299999999,42.39272],"type":"Point"}
}