{
  "type": "Feature",
  "properties": {
    "iso:country":"US",
    "sg:address":"1020 W Silver Lake Rd",
    "sg:city":"Fenton",
    "sg:classifiers":[
        {
            "category":"Building & Trades",
            "subcategory":"Plumbing",
            "type":"Services"
        }
    ],
    "sg:phone":"+1 810 750 8100",
    "sg:postcode":"48430",
    "sg:province":"MI",
    "sg:tags":[
        "heating",
        "contractor"
    ],
    "wof:name":"First Choice Htg & Cooling",
    "wof:placetype":"venue"
},
  "geometry": {"coordinates":[-83.72102099999999,42.800746],"type":"Point"}
}