{
  "type": "Feature",
  "properties": {
    "iso:country":"US",
    "sg:address":"29520 Hemlock Ave",
    "sg:city":"Farmington",
    "sg:classifiers":[
        {
            "category":"Building & Trades",
            "subcategory":"Construction",
            "type":"Services"
        }
    ],
    "sg:phone":"+1 248 476 0592",
    "sg:postcode":"48336",
    "sg:province":"MI",
    "sg:tags":[
        "contractor"
    ],
    "wof:name":"Craggs Construction Company",
    "wof:placetype":"venue"
},
  "geometry": {"coordinates":[-83.34215500000001,42.475914],"type":"Point"}
}