{
  "type": "Feature",
  "properties": {
    "iso:country":"US",
    "sg:address":"410 Petoskey St",
    "sg:city":"Petoskey",
    "sg:classifiers":[
        {
            "category":"Professional",
            "subcategory":"Lawyer & Legal Services",
            "type":"Services"
        }
    ],
    "sg:phone":"+1 231 347 4444",
    "sg:postcode":"49770",
    "sg:province":"MI",
    "sg:tags":[
        "attorney"
    ],
    "wof:name":"Daniel J Harris Law Office",
    "wof:placetype":"venue"
},
  "geometry": {"coordinates":[-84.95732599999999,45.373861],"type":"Point"}
}