{
  "type": "Feature",
  "properties": {
    "iso:country":"US",
    "sg:address":"2698 Leach Rd",
    "sg:city":"Rochester Hills",
    "sg:classifiers":[
        {
            "category":"Organizations",
            "subcategory":"Religious Organization",
            "type":"Services"
        }
    ],
    "sg:phone":"+1 248 852 5411",
    "sg:postcode":"48309",
    "sg:province":"MI",
    "sg:tags":[
        "church"
    ],
    "wof:name":"Leach Road Community Church",
    "wof:placetype":"venue"
},
  "geometry": {"coordinates":[-83.197497,42.636951],"type":"Point"}
}