{
  "type": "Feature",
  "properties": {
    "iso:country":"US",
    "sg:address":"43211 Dalcoma Dr",
    "sg:city":"Clinton Township",
    "sg:classifiers":[
        {
            "category":"Health Services",
            "subcategory":"Doctor",
            "type":"Services"
        }
    ],
    "sg:phone":"+1 586 286 7000",
    "sg:postcode":"48038",
    "sg:province":"MI",
    "sg:tags":[
        "dentist"
    ],
    "wof:name":"Goodman Daniel DDS Matsura",
    "wof:placetype":"venue"
},
  "geometry": {"coordinates":[-82.962864,42.613117],"type":"Point"}
}