{
  "type": "Feature",
  "properties": {
    "iso:country":"US",
    "sg:address":"4160 John R St",
    "sg:city":"Detroit",
    "sg:classifiers":[
        {
            "category":"Organizations",
            "subcategory":"Non-profit Organization",
            "type":"Services"
        }
    ],
    "sg:phone":"+1 313 671 3912",
    "sg:postcode":"48201",
    "sg:province":"MI",
    "sg:tags":[
        "social"
    ],
    "wof:name":"Integrated Counseling Svcs LLC",
    "wof:placetype":"venue"
},
  "geometry": {"coordinates":[-83.058181,42.351917],"type":"Point"}
}