{
  "type": "Feature",
  "properties": {
    "iso:country":"US",
    "sg:address":"3053 Evanston Ave",
    "sg:city":"Muskegon",
    "sg:classifiers":[
        {
            "category":"Organizations",
            "subcategory":"Religious Organization",
            "type":"Services"
        }
    ],
    "sg:phone":"+1 231 773 4897",
    "sg:postcode":"49442",
    "sg:province":"MI",
    "sg:tags":[
        "church"
    ],
    "wof:name":"Grace Bible Church",
    "wof:placetype":"venue"
},
  "geometry": {"coordinates":[-86.165757,43.212386],"type":"Point"}
}