{
  "type": "Feature",
  "properties": {
    "iso:country":"US",
    "sg:address":"22731 Newman St",
    "sg:city":"Dearborn",
    "sg:classifiers":[
        {
            "category":"Health Services",
            "subcategory":"Doctor",
            "type":"Services"
        }
    ],
    "sg:phone":"+1 313 561 4910",
    "sg:postcode":"48124",
    "sg:province":"MI",
    "wof:name":"Hand Surgery Associates PC",
    "wof:placetype":"venue"
},
  "geometry": {"coordinates":[-83.253998,42.2967],"type":"Point"}
}