{
  "type": "Feature",
  "properties": {
    "iso:country":"US",
    "sg:address":"5365 W Bachelor Rd",
    "sg:city":"Angola",
    "sg:classifiers":[
        {
            "category":"Professional",
            "subcategory":"Management & Consulting",
            "type":"Services"
        }
    ],
    "sg:phone":"+1 260 833 9023",
    "sg:postcode":"46703",
    "sg:province":"MI",
    "sg:tags":[
        "consultant",
        "livestock"
    ],
    "wof:name":"Pond View Emus",
    "wof:placetype":"venue"
},
  "geometry": {"coordinates":[-85.090024,41.724901],"type":"Point"}
}