{
  "type": "Feature",
  "properties": {
    "iso:country":"US",
    "sg:address":"1345 Merkle Rd",
    "sg:city":"Ortonville",
    "sg:classifiers":[
        {
            "category":"Wholesale",
            "subcategory":"Machinery & Supplies",
            "type":"Manufacturing & Wholesale Goods"
        }
    ],
    "sg:phone":"+1 248 627 4367",
    "sg:postcode":"48462",
    "sg:province":"MI",
    "sg:tags":[
        "industrial"
    ],
    "wof:name":"3d Composite Aircraft Parts",
    "wof:placetype":"venue"
},
  "geometry": {"coordinates":[-83.458917,42.829639],"type":"Point"}
}