{
  "type": "Feature",
  "properties": {
    "iso:country":"US",
    "sg:address":"2495 Burlingame Ave SW",
    "sg:city":"Wyoming",
    "sg:classifiers":[
        {
            "category":"Education",
            "subcategory":"Dance Studio",
            "type":"Public Place"
        }
    ],
    "sg:phone":"+1 616 532 8383",
    "sg:postcode":"49509",
    "sg:province":"MI",
    "sg:tags":[
        "instruction",
        "dancing"
    ],
    "wof:name":"T 3's Dance Elite",
    "wof:placetype":"venue"
},
  "geometry": {"coordinates":[-85.70559299999999,42.920595],"type":"Point"}
}