{
  "type": "Feature",
  "properties": {
    "iso:country":"US",
    "sg:address":"106 N 5th St",
    "sg:city":"Harrisville",
    "sg:classifiers":[
        {
            "category":"Government",
            "subcategory":"Office",
            "type":"Public Place"
        }
    ],
    "sg:phone":"+1 989 724 9440",
    "sg:postcode":"48740",
    "sg:province":"MI",
    "wof:name":"Alcona County Building Inspctr",
    "wof:placetype":"venue"
},
  "geometry": {"coordinates":[-83.296126,44.658531],"type":"Point"}
}