{
  "type": "Feature",
  "properties": {
    "iso:country":"US",
    "sg:address":"20411 W 12 Mile Rd",
    "sg:city":"Southfield",
    "sg:classifiers":[
        {
            "category":"Organizations",
            "subcategory":"Membership Organization",
            "type":"Services"
        },
        {
            "category":"Museum",
            "type":"Entertainment"
        }
    ],
    "sg:phone":"+1 248 223 9552",
    "sg:postcode":"48076",
    "sg:province":"MI",
    "sg:tags":[
        "information",
        "arts"
    ],
    "wof:name":"Omniarts In Education Inc",
    "wof:placetype":"venue"
},
  "geometry": {"coordinates":[-83.24390200000001,42.501856],"type":"Point"}
}