{
  "type": "Feature",
  "properties": {
    "iso:country":"US",
    "sg:address":"23640 Joseph St",
    "sg:city":"Warren",
    "sg:classifiers":[
        {
            "category":"Organizations",
            "subcategory":"Religious Organization",
            "type":"Services"
        }
    ],
    "sg:phone":"+1 586 757 8762",
    "sg:postcode":"48091",
    "sg:province":"MI",
    "wof:name":"Wounded Healer Ministries",
    "wof:placetype":"venue"
},
  "geometry": {"coordinates":[-83.074986,42.466343],"type":"Point"}
}