{
  "type": "Feature",
  "properties": {
    "iso:country":"US",
    "sg:address":"9442 W Vogt Rd",
    "sg:city":"Fowlerville",
    "sg:classifiers":[
        {
            "category":"Home & Garden",
            "subcategory":"Hardware",
            "type":"Retail Goods"
        }
    ],
    "sg:phone":"+1 517 468 1586",
    "sg:postcode":"48836",
    "sg:province":"MI",
    "wof:name":"Progressive Hardware Suppliers",
    "wof:placetype":"venue"
},
  "geometry": {"coordinates":[-84.105913,42.750814],"type":"Point"}
}