{
  "type": "Feature",
  "properties": {
    "iso:country":"US",
    "sg:address":"5604 Cleveland Ave",
    "sg:city":"Stevensville",
    "sg:classifiers":[
        {
            "category":"Insurance",
            "subcategory":"Insurance Agent",
            "type":"Services"
        }
    ],
    "sg:phone":"+1 269 429 5959",
    "sg:postcode":"49127",
    "sg:province":"MI",
    "wof:name":"Countryside Insurance Svc Inc",
    "wof:placetype":"venue"
},
  "geometry": {"coordinates":[-86.49495899999999,42.016361],"type":"Point"}
}