{
  "type": "Feature",
  "properties": {
    "iso:country":"US",
    "sg:address":"1032 E V W Ave",
    "sg:city":"Vicksburg",
    "sg:classifiers":[
        {
            "category":"Real Estate",
            "subcategory":"Real Estate Agent",
            "type":"Services"
        }
    ],
    "sg:phone":"+1 269 649 4656",
    "sg:postcode":"49097",
    "sg:province":"MI",
    "wof:name":"All Seasons Property Mtnnc",
    "wof:placetype":"venue"
},
  "geometry": {"coordinates":[-85.57650700000001,42.121371],"type":"Point"}
}