{
  "type": "Feature",
  "properties": {
    "iso:country":"US",
    "sg:address":"4580 Family Ln",
    "sg:city":"Kingston",
    "sg:classifiers":[
        {
            "category":"Professional",
            "subcategory":"Credit Reporting & Collection",
            "type":"Services"
        }
    ],
    "sg:phone":"+1 989 683 2888",
    "sg:postcode":"48741",
    "sg:province":"MI",
    "sg:tags":[
        "agency"
    ],
    "wof:name":"United Collection Svc",
    "wof:placetype":"venue"
},
  "geometry": {"coordinates":[-83.271627,43.382311],"type":"Point"}
}