{
  "type": "Feature",
  "properties": {
    "iso:country":"US",
    "sg:address":"1985 Rock Rd",
    "sg:city":"Commerce Twp",
    "sg:classifiers":[
        {
            "category":"Manufacturing",
            "subcategory":"Metals",
            "type":"Manufacturing & Wholesale Goods"
        }
    ],
    "sg:phone":"+1 248 624 9199",
    "sg:postcode":"48390",
    "sg:province":"MI",
    "sg:tags":[
        "steel"
    ],
    "wof:name":"Triple J Fab",
    "wof:placetype":"venue"
},
  "geometry": {"coordinates":[-83.44520900000001,42.555465],"type":"Point"}
}