{
  "type": "Feature",
  "properties": {
    "iso:country":"US",
    "sg:address":"1916 W Stadium Blvd",
    "sg:city":"Ann Arbor",
    "sg:classifiers":[
        {
            "category":"Restaurant",
            "type":"Food & Drink"
        }
    ],
    "sg:menulink":"http://www.allmenus.com/mi/ann-arbor/246246-happy-wok/menu/",
    "sg:phone":"+1 734 665 6888",
    "sg:postcode":"48103",
    "sg:province":"MI",
    "sg:tags":[
        "asian",
        "chinese"
    ],
    "wof:name":"Happy Wok",
    "wof:placetype":"venue"
},
  "geometry": {"coordinates":[-83.7722,42.268807],"type":"Point"}
}