{
  "type": "Feature",
  "properties": {
    "iso:country":"US",
    "sg:address":"129 State St",
    "sg:city":"Harbor Beach",
    "sg:classifiers":[
        {
            "category":"Restaurant",
            "type":"Food & Drink"
        }
    ],
    "sg:phone":"+1 989 479 9013",
    "sg:postcode":"48441",
    "sg:province":"MI",
    "sg:tags":[
        "eating"
    ],
    "wof:name":"Ernestos Pizzeria",
    "wof:placetype":"venue"
},
  "geometry": {"coordinates":[-82.651701,43.844668],"type":"Point"}
}