{
  "type": "Feature",
  "properties": {
    "iso:country":"US",
    "sg:address":"2436 9th St",
    "sg:city":"Muskegon",
    "sg:classifiers":[
        {
            "category":"Building & Trades",
            "subcategory":"Plumbing",
            "type":"Services"
        }
    ],
    "sg:phone":"+1 231 733 2466",
    "sg:postcode":"49444",
    "sg:province":"MI",
    "sg:tags":[
        "sheet",
        "work",
        "metal",
        "contractor"
    ],
    "wof:name":"Heights Sheet Metal Inc",
    "wof:placetype":"venue"
},
  "geometry": {"coordinates":[-86.253248,43.207644],"type":"Point"}
}