{
  "type": "Feature",
  "properties": {
    "iso:country":"US",
    "sg:address":"8739 N Scott Rd",
    "sg:city":"St Johns",
    "sg:classifiers":[
        {
            "category":"Building & Trades",
            "subcategory":"Construction",
            "type":"Services"
        }
    ],
    "sg:phone":"+1 989 224 4045",
    "sg:postcode":"48879",
    "sg:province":"MI",
    "sg:tags":[
        "drainage",
        "contractor"
    ],
    "wof:name":"Burnham Farm Tiling",
    "wof:placetype":"venue"
},
  "geometry": {"coordinates":[-84.543162,43.107379],"type":"Point"}
}