{
  "type": "Feature",
  "properties": {
    "iso:country":"US",
    "sg:address":"40808 Ryan Rd",
    "sg:city":"Sterling Heights",
    "sg:classifiers":[
        {
            "category":"Restaurant",
            "type":"Food & Drink"
        }
    ],
    "sg:menulink":"http://www.allmenus.com/mi/sterling-heights/24170-jets-pizza/menu/",
    "sg:phone":"+1 586 978 0888",
    "sg:postcode":"48310",
    "sg:province":"MI",
    "sg:tags":[
        "american",
        "pizza"
    ],
    "wof:name":"Jet's Pizza",
    "wof:placetype":"venue"
},
  "geometry": {"coordinates":[-83.070778,42.592221],"type":"Point"}
}