{
  "type": "Feature",
  "properties": {
    "iso:country":"US",
    "sg:address":"8293 Kier Rd",
    "sg:city":"Clarkston",
    "sg:classifiers":[
        {
            "category":"Social Services",
            "subcategory":"Adult Care",
            "type":"Services"
        }
    ],
    "sg:phone":"+1 248 674 2905",
    "sg:postcode":"48348",
    "sg:province":"MI",
    "sg:tags":[
        "home",
        "residential"
    ],
    "wof:name":"Liberty Manor",
    "wof:placetype":"venue"
},
  "geometry": {"coordinates":[-83.458823,42.789075],"type":"Point"}
}