{
  "type": "Feature",
  "properties": {
    "iso:country":"US",
    "sg:address":"9702 Portage Rd",
    "sg:city":"Portage",
    "sg:classifiers":[
        {
            "category":"Food & Beverages",
            "subcategory":"Bakery",
            "type":"Retail Goods"
        },
        {
            "category":"Bakery",
            "type":"Food & Drink"
        }
    ],
    "sg:phone":"+1 269 327 7480",
    "sg:postcode":"49002",
    "sg:province":"MI",
    "sg:tags":[
        "bakers-wholesale"
    ],
    "wof:name":"Nickles Bakery",
    "wof:placetype":"venue"
},
  "geometry": {"coordinates":[-85.567359,42.176926],"type":"Point"}
}