{
  "type": "Feature",
  "properties": {
    "iso:country":"US",
    "sg:address":"4512 Breton Rd SE",
    "sg:city":"Grand Rapids",
    "sg:classifiers":[
        {
            "category":"Restaurant",
            "type":"Food & Drink"
        }
    ],
    "sg:menulink":"http://www.allmenus.com/mi/kentwood/24124-jets-pizza/menu/",
    "sg:phone":"+1 616 281 5450",
    "sg:postcode":"49508",
    "sg:province":"MI",
    "sg:tags":[
        "american",
        "pizza"
    ],
    "wof:name":"Jet's Pizza",
    "wof:placetype":"venue"
},
  "geometry": {"coordinates":[-85.606257,42.881153],"type":"Point"}
}