{
  "type": "Feature",
  "properties": {
    "iso:country":"US",
    "sg:address":"12171 Indian Oak Dr",
    "sg:city":"Fenton",
    "sg:classifiers":[
        {
            "category":"Real Estate",
            "subcategory":"Developer",
            "type":"Services"
        }
    ],
    "sg:phone":"+1 810 750 3980",
    "sg:postcode":"48430",
    "sg:province":"MI",
    "wof:name":"Woods At River Ridge Assn",
    "wof:placetype":"venue"
},
  "geometry": {"coordinates":[-83.721171,42.754346],"type":"Point"}
}