{
  "type": "Feature",
  "properties": {
    "iso:country":"US",
    "sg:address":"834 Pine Tree St",
    "sg:city":"Lake Orion",
    "sg:classifiers":[
        {
            "category":"Professional",
            "subcategory":"Art Services",
            "type":"Services"
        }
    ],
    "sg:phone":"+1 248 693 1839",
    "sg:postcode":"48362",
    "sg:province":"MI",
    "sg:tags":[
        "graphic",
        "designer"
    ],
    "wof:name":"Graphic Concepts",
    "wof:placetype":"venue"
},
  "geometry": {"coordinates":[-83.26443999999999,42.768283],"type":"Point"}
}