{
  "type": "Feature",
  "properties": {
    "iso:country":"US",
    "sg:address":"600 E Main St",
    "sg:city":"Edmore",
    "sg:classifiers":[
        {
            "category":"Food & Beverages",
            "subcategory":"Specialty",
            "type":"Retail Goods"
        }
    ],
    "sg:phone":"+1 989 427 0014",
    "sg:postcode":"48829",
    "sg:province":"MI",
    "sg:tags":[
        "health",
        "diet"
    ],
    "wof:name":"Rogers Natural Foods",
    "wof:placetype":"venue"
},
  "geometry": {"coordinates":[-85.03809699999999,43.408068],"type":"Point"}
}