{
  "type": "Feature",
  "properties": {
    "iso:country":"US",
    "sg:address":"2266 S Jerome Rd",
    "sg:city":"Ithaca",
    "sg:classifiers":[
        {
            "category":"Wholesale",
            "subcategory":"Machinery & Supplies",
            "type":"Manufacturing & Wholesale Goods"
        }
    ],
    "sg:phone":"+1 989 235 3055",
    "sg:postcode":"48847",
    "sg:province":"MI",
    "sg:tags":[
        "gasket"
    ],
    "wof:name":"Secure Sales Inc",
    "wof:placetype":"venue"
},
  "geometry": {"coordinates":[-84.62072499999999,43.259492],"type":"Point"}
}