{
  "type": "Feature",
  "properties": {
    "iso:country":"US",
    "sg:address":"11351 Brooklyn Rd",
    "sg:city":"Brooklyn",
    "sg:classifiers":[
        {
            "category":"Banks & Credit Unions",
            "subcategory":"Bank",
            "type":"Services"
        }
    ],
    "sg:phone":"+1 517 592 2635",
    "sg:postcode":"49230",
    "sg:province":"MI",
    "wof:name":"Comerica Bank",
    "wof:placetype":"venue"
},
  "geometry": {"coordinates":[-84.25092600000001,42.118794],"type":"Point"}
}