{
  "type": "Feature",
  "properties": {
    "iso:country":"US",
    "sg:address":"3535 E 9 Mile Rd",
    "sg:city":"Warren",
    "sg:classifiers":[
        {
            "category":"Restaurant",
            "type":"Food & Drink"
        }
    ],
    "sg:phone":"+1 586 755 5055",
    "sg:postcode":"48091",
    "sg:province":"MI",
    "wof:name":"Shantie Food & Spirit",
    "wof:placetype":"venue"
},
  "geometry": {"coordinates":[-83.06909899999999,42.462299],"type":"Point"}
}