{
  "type": "Feature",
  "properties": {
    "iso:country":"US",
    "sg:address":"5468 S Saginaw Rd",
    "sg:city":"Flint",
    "sg:classifiers":[
        {
            "category":"Health Services",
            "subcategory":"Chiropractor",
            "type":"Services"
        }
    ],
    "sg:phone":"+1 810 953 0624",
    "sg:postcode":"48507",
    "sg:province":"MI",
    "wof:name":"Wildwood Clinic",
    "wof:placetype":"venue"
},
  "geometry": {"coordinates":[-83.65550500000001,42.949078],"type":"Point"}
}