{
  "type": "Feature",
  "properties": {
    "iso:country":"US",
    "sg:address":"1065 E Maple Rd",
    "sg:city":"Birmingham",
    "sg:classifiers":[
        {
            "category":"Autos & Motor Vehicles",
            "subcategory":"Fuel & Gas Station",
            "type":"Retail Goods"
        }
    ],
    "sg:phone":"+1 248 646 4774",
    "sg:postcode":"48009",
    "sg:province":"MI",
    "sg:tags":[
        "repair",
        "oil"
    ],
    "wof:name":"Adams-Maple Mobil",
    "wof:placetype":"venue"
},
  "geometry": {"coordinates":[-83.2062,42.547001],"type":"Point"}
}