{
  "type": "Feature",
  "properties": {
    "iso:country":"US",
    "sg:address":"1917 E Main St",
    "sg:city":"Niles",
    "sg:classifiers":[
        {
            "category":"Mining & Drilling",
            "type":"Manufacturing & Wholesale Goods"
        }
    ],
    "sg:phone":"+1 269 684 6289",
    "sg:postcode":"49120",
    "sg:province":"MI",
    "sg:tags":[
        "field"
    ],
    "wof:name":"Payne Bros Construction Inc",
    "wof:placetype":"venue"
},
  "geometry": {"coordinates":[-86.231373,41.816385],"type":"Point"}
}