{
  "type": "Feature",
  "properties": {
    "iso:country":"US",
    "sg:address":"1456 Catalina Dr",
    "sg:city":"Ann Arbor",
    "sg:classifiers":[
        {
            "category":"Home & Garden",
            "subcategory":"Home Furnishings",
            "type":"Retail Goods"
        }
    ],
    "sg:phone":"+1 734 995 8638",
    "sg:postcode":"48103",
    "sg:province":"MI",
    "wof:name":"Lesueur Claywork",
    "wof:placetype":"venue"
},
  "geometry": {"coordinates":[-83.768619,42.262689],"type":"Point"}
}