{
  "type": "Feature",
  "properties": {
    "iso:country":"US",
    "sg:address":"330 W Michigan Ave",
    "sg:city":"Jackson",
    "sg:classifiers":[
        {
            "category":"Social Services",
            "type":"Services"
        }
    ],
    "sg:phone":"+1 517 787 7920",
    "sg:postcode":"49201",
    "sg:province":"MI",
    "sg:tags":[
        "counselor",
        "marriage",
        "family"
    ],
    "sg:website":"www.strong-families.org",
    "wof:name":"Family Svc & Children's Aid",
    "wof:placetype":"venue"
},
  "geometry": {"coordinates":[-84.413121,42.247514],"type":"Point"}
}