{
  "type": "Feature",
  "properties": {
    "iso:country":"US",
    "sg:address":"1131 Columbus Ave",
    "sg:city":"Benton Harbor",
    "sg:classifiers":[
        {
            "category":"Education",
            "subcategory":"School",
            "type":"Public Place"
        }
    ],
    "sg:phone":"+1 269 927 0734",
    "sg:postcode":"49022",
    "sg:province":"MI",
    "wof:name":"Bhas Sterne Brunson Elementary",
    "wof:placetype":"venue"
},
  "geometry": {"coordinates":[-86.44881599999999,42.096746],"type":"Point"}
}