{
  "type": "Feature",
  "properties": {
    "iso:country":"US",
    "sg:address":"1850 E 12 Mile Rd",
    "sg:city":"Madison Heights",
    "sg:classifiers":[
        {
            "category":"Shopping",
            "subcategory":"Mobile Phones",
            "type":"Retail Goods"
        }
    ],
    "sg:phone":"+1 248 541 5000",
    "sg:postcode":"48071",
    "sg:province":"MI",
    "sg:website":"www.wirelesstoyz.com",
    "wof:name":"Wireless Toyz",
    "wof:placetype":"venue"
},
  "geometry": {"coordinates":[-83.086026,42.505043],"type":"Point"}
}