{
  "type": "Feature",
  "properties": {
    "iso:country":"US",
    "sg:address":"2032 Hunters Creek Dr",
    "sg:city":"Ypsilanti",
    "sg:classifiers":[
        {
            "category":"Retail",
            "subcategory":"Animal Services",
            "type":"Services"
        }
    ],
    "sg:phone":"+1 734 481 1215",
    "sg:postcode":"48198",
    "sg:province":"MI",
    "wof:name":"Stone Creek Arabians",
    "wof:placetype":"venue"
},
  "geometry": {"coordinates":[-83.609835,42.277844],"type":"Point"}
}