{
  "type": "Feature",
  "properties": {
    "iso:country":"US",
    "sg:address":"44401 W Ann Arbor Trl",
    "sg:city":"Plymouth",
    "sg:classifiers":[
        {
            "category":"Education",
            "subcategory":"School",
            "type":"Public Place"
        }
    ],
    "sg:phone":"+1 734 416 7550",
    "sg:postcode":"48170",
    "sg:province":"MI",
    "sg:tags":[
        "high",
        "middle",
        "elementary"
    ],
    "wof:name":"Plymouth-Canton Community School District",
    "wof:placetype":"venue"
},
  "geometry": {"coordinates":[-83.48022899999999,42.371385],"type":"Point"}
}