{
  "type": "Feature",
  "properties": {
    "iso:country":"US",
    "sg:address":"3070 S Baldwin Rd",
    "sg:city":"Orion",
    "sg:classifiers":[
        {
            "category":"Organizations",
            "subcategory":"Religious Organization",
            "type":"Services"
        }
    ],
    "sg:phone":"+1 248 391 9211",
    "sg:postcode":"48359",
    "sg:province":"MI",
    "sg:tags":[
        "church"
    ],
    "wof:name":"Unity North Church",
    "wof:placetype":"venue"
},
  "geometry": {"coordinates":[-83.30804500000001,42.734196],"type":"Point"}
}