{
  "type": "Feature",
  "properties": {
    "iso:country":"US",
    "sg:address":"98 Maple St",
    "sg:city":"Hulbert",
    "sg:classifiers":[
        {
            "category":"Professional",
            "subcategory":"Management & Consulting",
            "type":"Services"
        }
    ],
    "sg:phone":"+1 906 876 2509",
    "sg:postcode":"49748",
    "sg:province":"MI",
    "sg:tags":[
        "communications",
        "consultant"
    ],
    "wof:name":"Nationwide Communications Inc",
    "wof:placetype":"venue"
},
  "geometry": {"coordinates":[-85.15053899999999,46.356076],"type":"Point"}
}