{
  "type": "Feature",
  "properties": {
    "iso:country":"US",
    "sg:address":"15019 W Maple Rapids Rd",
    "sg:city":"Hubbardston",
    "sg:classifiers":[
        {
            "category":"Retail",
            "subcategory":"Animal Services",
            "type":"Services"
        }
    ],
    "sg:phone":"+1 989 981 6967",
    "sg:postcode":"48845",
    "sg:province":"MI",
    "sg:tags":[
        "cat",
        "dog",
        "kennel"
    ],
    "wof:name":"Chartrand Kennels",
    "wof:placetype":"venue"
},
  "geometry": {"coordinates":[-84.821023,43.105089],"type":"Point"}
}