{
  "type": "Feature",
  "properties": {
    "iso:country":"US",
    "sg:address":"109 N Fulton St",
    "sg:city":"Cassopolis",
    "sg:classifiers":[
        {
            "category":"Retail",
            "subcategory":"Animal Services",
            "type":"Services"
        }
    ],
    "sg:phone":"+1 269 445 3432",
    "sg:postcode":"49031",
    "sg:province":"MI",
    "sg:tags":[
        "pet",
        "grooming",
        "washing"
    ],
    "wof:name":"Clipper Creations Pet Salon",
    "wof:placetype":"venue"
},
  "geometry": {"coordinates":[-86.008882,41.91325],"type":"Point"}
}