{
  "type": "Feature",
  "properties": {
    "iso:country":"US",
    "sg:address":"313 N Cedar St",
    "sg:city":"Traverse City",
    "sg:classifiers":[
        {
            "category":"Retail",
            "subcategory":"Auto Repair",
            "type":"Services"
        }
    ],
    "sg:phone":"+1 231 941 1857",
    "sg:postcode":"49684",
    "sg:province":"MI",
    "sg:tags":[
        "automotive"
    ],
    "wof:name":"Jet Lube Mobile Oil Change",
    "wof:placetype":"venue"
},
  "geometry": {"coordinates":[-85.636459,44.767056],"type":"Point"}
}