{
  "type": "Feature",
  "properties": {
    "iso:country":"US",
    "sg:address":"15260 Eureka Rd",
    "sg:city":"Southgate",
    "sg:classifiers":[
        {
            "category":"Personal",
            "subcategory":"Beauty Salon",
            "type":"Services"
        }
    ],
    "sg:phone":"+1 734 282 6699",
    "sg:postcode":"48195",
    "sg:province":"MI",
    "sg:tags":[
        "shop"
    ],
    "wof:name":"Fantastic Sams",
    "wof:placetype":"venue"
},
  "geometry": {"coordinates":[-83.20869500000001,42.199095],"type":"Point"}
}