{
  "type": "Feature",
  "properties": {
    "iso:country":"US",
    "sg:address":"3519 Wayland Dr",
    "sg:city":"Jackson",
    "sg:classifiers":[
        {
            "category":"Professional",
            "subcategory":"Management & Consulting",
            "type":"Services"
        }
    ],
    "sg:phone":"+1 517 782 8300",
    "sg:postcode":"49202",
    "sg:province":"MI",
    "sg:tags":[
        "consultant",
        "industrial"
    ],
    "sg:website":"www.877gallant.com",
    "wof:name":"Gallant Industrial Svc",
    "wof:placetype":"venue"
},
  "geometry": {"coordinates":[-84.45926799999999,42.270906],"type":"Point"}
}