{
  "type": "Feature",
  "properties": {
    "iso:country":"US",
    "sg:address":"23697 Wendy Ln",
    "sg:city":"Southfield",
    "sg:classifiers":[
        {
            "category":"Professional",
            "subcategory":"Management & Consulting",
            "type":"Services"
        }
    ],
    "sg:phone":"+1 248 443 2781",
    "sg:postcode":"48075",
    "sg:province":"MI",
    "sg:tags":[
        "public",
        "relations"
    ],
    "wof:name":"Store House Distributor",
    "wof:placetype":"venue"
},
  "geometry": {"coordinates":[-83.212914,42.46473],"type":"Point"}
}