{
  "type": "Feature",
  "properties": {
    "iso:country":"US",
    "sg:address":"140 Tower St",
    "sg:city":"Oxford",
    "sg:classifiers":[
        {
            "category":"Retail",
            "subcategory":"Auto Rental",
            "type":"Services"
        }
    ],
    "sg:phone":"+1 248 391 8235",
    "sg:postcode":"48386",
    "sg:province":"MI",
    "sg:tags":[
        "renting",
        "truck",
        "leasing"
    ],
    "wof:name":"Budget Truck Rental",
    "wof:placetype":"venue"
},
  "geometry": {"coordinates":[-83.469584,42.635025],"type":"Point"}
}