{
  "type": "Feature",
  "properties": {
    "iso:country":"US",
    "sg:address":"4040 S Ainger Rd",
    "sg:city":"Charlotte",
    "sg:classifiers":[
        {
            "category":"Manufacturing",
            "subcategory":"Wood Products",
            "type":"Manufacturing & Wholesale Goods"
        }
    ],
    "sg:phone":"+1 517 541 3618",
    "sg:postcode":"48813",
    "sg:province":"MI",
    "sg:tags":[
        "mfg"
    ],
    "wof:name":"C & J Pallets",
    "wof:placetype":"venue"
},
  "geometry": {"coordinates":[-84.935051,42.50905],"type":"Point"}
}