{
  "type": "Feature",
  "properties": {
    "iso:country":"US",
    "sg:address":"3370 Warren Dr",
    "sg:city":"Waterford",
    "sg:classifiers":[
        {
            "category":"Manufacturing",
            "subcategory":"Metals",
            "type":"Manufacturing & Wholesale Goods"
        }
    ],
    "sg:phone":"+1 248 674 4333",
    "sg:postcode":"48329",
    "sg:province":"MI",
    "sg:tags":[
        "plating"
    ],
    "wof:name":"ABC Custom Chrome",
    "wof:placetype":"venue"
},
  "geometry": {"coordinates":[-83.385937,42.687515],"type":"Point"}
}