{
  "type": "Feature",
  "properties": {
    "iso:country":"US",
    "sg:address":"17665 Gary Rd",
    "sg:city":"Chesaning",
    "sg:classifiers":[
        {
            "category":"Professional",
            "subcategory":"Business Services",
            "type":"Services"
        },
        {
            "category":"Professional",
            "subcategory":"Management & Consulting",
            "type":"Services"
        }
    ],
    "sg:phone":"+1 989 845 6331",
    "sg:postcode":"48616",
    "sg:province":"MI",
    "sg:tags":[
        "party",
        "planning"
    ],
    "wof:name":"Creative Images All Occasion",
    "wof:placetype":"venue"
},
  "geometry": {"coordinates":[-84.26174399999999,43.215092],"type":"Point"}
}