{
  "type": "Feature",
  "properties": {
    "iso:country":"US",
    "sg:address":"18101 Oakwood Blvd",
    "sg:city":"Dearborn",
    "sg:classifiers":[
        {
            "category":"Health Services",
            "subcategory":"Doctor",
            "type":"Services"
        }
    ],
    "sg:phone":"+1 313 593 5810",
    "sg:postcode":"48124",
    "sg:province":"MI",
    "sg:tags":[
        "obstetrician",
        "gynecologist"
    ],
    "wof:name":"Fumia Fred MD",
    "wof:placetype":"venue"
},
  "geometry": {"coordinates":[-83.211502,42.291698],"type":"Point"}
}