{
  "type": "Feature",
  "properties": {
    "iso:country":"US",
    "sg:address":"508 S Washington Ave",
    "sg:city":"Royal Oak",
    "sg:classifiers":[
        {
            "category":"Shopping",
            "subcategory":"Clothing, Apparel, & Fashions",
            "type":"Retail Goods"
        },
        {
            "category":"Shopping",
            "subcategory":"Jewelry",
            "type":"Retail Goods"
        }
    ],
    "sg:phone":"+1 248 556 5741",
    "sg:postcode":"48068",
    "sg:province":"MI",
    "sg:tags":[
        "clothing",
        "women's"
    ],
    "wof:name":"The Pink Elephant",
    "wof:placetype":"venue"
},
  "geometry": {"coordinates":[-83.146556,42.486019],"type":"Point"}
}