{
  "type": "Feature",
  "properties": {
    "iso:country":"US",
    "sg:address":"1421 Washington St",
    "sg:city":"Midland",
    "sg:classifiers":[
        {
            "category":"Utilities",
            "subcategory":"Mobile Phone",
            "type":"Services"
        }
    ],
    "sg:phone":"+1 989 839 0807",
    "sg:postcode":"48642",
    "sg:province":"MI",
    "sg:tags":[
        "telephone",
        "cellular"
    ],
    "wof:name":"Wireless Plus",
    "wof:placetype":"venue"
},
  "geometry": {"coordinates":[-84.217361,43.615236],"type":"Point"}
}