{
  "type": "Feature",
  "properties": {
    "iso:country":"US",
    "sg:address":"24470 Telegraph Rd.",
    "sg:city":"Southfield",
    "sg:classifiers":[
        {
            "category":"Building & Trades",
            "subcategory":"Construction",
            "type":"Services"
        }
    ],
    "sg:phone":"+1 248 357 1240",
    "sg:postcode":"48033",
    "sg:province":"MI",
    "sg:tags":[
        "contractor"
    ],
    "sg:website":"bobsonconstruction.com",
    "wof:name":"Bobson Construction",
    "wof:placetype":"venue"
},
  "geometry": {"coordinates":[-83.27957000000001,42.46859],"type":"Point"}
}