{
  "type": "Feature",
  "properties": {
    "iso:country":"US",
    "sg:address":"2033 Bisby Dr",
    "sg:city":"Mount Morris",
    "sg:classifiers":[
        {
            "category":"Professional",
            "subcategory":"Computer Services",
            "type":"Services"
        }
    ],
    "sg:phone":"+1 810 670 1626",
    "sg:postcode":"48458",
    "sg:province":"MI",
    "wof:name":"PC Designers",
    "wof:placetype":"venue"
},
  "geometry": {"coordinates":[-83.673706,43.129115],"type":"Point"}
}