{
  "type": "Feature",
  "properties": {
    "iso:country":"US",
    "sg:address":"17195 W 12 Mile Rd",
    "sg:city":"Southfield",
    "sg:classifiers":[
        {
            "category":"Shopping",
            "subcategory":"Bicycles & Sporting Goods",
            "type":"Retail Goods"
        }
    ],
    "sg:phone":"+1 248 559 1630",
    "sg:postcode":"48076",
    "sg:province":"MI",
    "sg:tags":[
        "equipment",
        "golf",
        "supply"
    ],
    "wof:name":"International Golf Enterprises",
    "wof:placetype":"venue"
},
  "geometry": {"coordinates":[-83.214991,42.502601],"type":"Point"}
}