{
  "type": "Feature",
  "properties": {
    "iso:country":"US",
    "sg:address":"1024 Boston St",
    "sg:city":"Waterford",
    "sg:classifiers":[
        {
            "category":"Building & Trades",
            "subcategory":"Construction",
            "type":"Services"
        }
    ],
    "sg:phone":"+1 248 682 0819",
    "sg:postcode":"48328",
    "sg:province":"MI",
    "sg:tags":[
        "residential"
    ],
    "wof:name":"Rlr Construction",
    "wof:placetype":"venue"
},
  "geometry": {"coordinates":[-83.329857,42.637547],"type":"Point"}
}