{
  "type": "Feature",
  "properties": {
    "iso:country":"US",
    "sg:address":"1420 Madison St",
    "sg:city":"Muskegon",
    "sg:classifiers":[
        {
            "category":"Education",
            "subcategory":"School",
            "type":"Public Place"
        }
    ],
    "sg:phone":"+1 231 720 2450",
    "sg:postcode":"49442",
    "sg:province":"MI",
    "wof:name":"Oakview School",
    "wof:placetype":"venue"
},
  "geometry": {"coordinates":[-86.219252,43.226006],"type":"Point"}
}