{
  "type": "Feature",
  "properties": {
    "iso:country":"US",
    "sg:address":"11350 Southworth Ave",
    "sg:city":"Plymouth",
    "sg:classifiers":[
        {
            "category":"Professional",
            "subcategory":"Computer Services",
            "type":"Services"
        }
    ],
    "sg:phone":"+1 734 453 2157",
    "sg:postcode":"48170",
    "sg:province":"MI",
    "wof:name":"Cardinal Technology Inc",
    "wof:placetype":"venue"
},
  "geometry": {"coordinates":[-83.449735,42.365333],"type":"Point"}
}