{
  "type": "Feature",
  "properties": {
    "iso:country":"US",
    "sg:address":"46480 Springhill Dr",
    "sg:city":"Utica",
    "sg:classifiers":[
        {
            "category":"Manufacturing",
            "subcategory":"Apparel",
            "type":"Manufacturing & Wholesale Goods"
        }
    ],
    "sg:phone":"+1 586 739 8841",
    "sg:postcode":"48317",
    "sg:province":"MI",
    "sg:tags":[
        "mfg"
    ],
    "wof:name":"Bright Ideas of Shelby",
    "wof:placetype":"venue"
},
  "geometry": {"coordinates":[-83.0641,42.634974],"type":"Point"}
}