{
  "type": "Feature",
  "properties": {
    "iso:country":"US",
    "sg:address":"920 E 2nd St",
    "sg:city":"Royal Oak",
    "sg:classifiers":[
        {
            "category":"Real Estate",
            "subcategory":"Architect",
            "type":"Services"
        }
    ],
    "sg:phone":"+1 248 544 1644",
    "sg:postcode":"48067",
    "sg:province":"MI",
    "sg:tags":[
        "building",
        "construction"
    ],
    "wof:name":"R P Improvements",
    "wof:placetype":"venue"
},
  "geometry": {"coordinates":[-83.13230900000001,42.489218],"type":"Point"}
}