{
  "type": "Feature",
  "properties": {
    "iso:country":"US",
    "sg:address":"322 N State St",
    "sg:city":"Alma",
    "sg:classifiers":[
        {
            "category":"Health Services",
            "subcategory":"Optometrist",
            "type":"Services"
        }
    ],
    "sg:phone":"+1 989 463 2981",
    "sg:postcode":"48801",
    "sg:province":"MI",
    "wof:name":"Church Lynn Dr Od",
    "wof:placetype":"venue"
},
  "geometry": {"coordinates":[-84.661771,43.378687],"type":"Point"}
}