{
  "type": "Feature",
  "properties": {
    "iso:country":"US",
    "sg:address":"26085 John R Road",
    "sg:city":"Madison Heights",
    "sg:classifiers":[
        {
            "category":"Restaurant",
            "type":"Food & Drink"
        }
    ],
    "sg:phone":"+1 248 544 3418",
    "sg:postcode":"48071",
    "sg:province":"MI",
    "wof:name":"JJ's Grill",
    "wof:placetype":"venue"
},
  "geometry": {"coordinates":[-83.10506700000001,42.484141],"type":"Point"}
}