{
  "type": "Feature",
  "properties": {
    "iso:country":"US",
    "sg:address":"6123 King Rd",
    "sg:city":"Cottrellville",
    "sg:classifiers":[
        {
            "category":"Manufacturing",
            "subcategory":"Retail Goods",
            "type":"Manufacturing & Wholesale Goods"
        },
        {
            "category":"Professional",
            "subcategory":"Business Services",
            "type":"Services"
        }
    ],
    "sg:phone":"+1 810 765 6999",
    "sg:postcode":"48039",
    "sg:province":"MI",
    "sg:tags":[
        "manufacturer"
    ],
    "wof:name":"Richcraft Industries Inc",
    "wof:placetype":"venue"
},
  "geometry": {"coordinates":[-82.509739,42.724736],"type":"Point"}
}