{
  "type": "Feature",
  "properties": {
    "iso:country":"US",
    "sg:address":"2032 S Loomis Rd",
    "sg:city":"Mt Pleasant",
    "sg:classifiers":[
        {
            "category":"Organizations",
            "subcategory":"Religious Organization",
            "type":"Services"
        }
    ],
    "sg:phone":"+1 989 773 9736",
    "sg:postcode":"48858",
    "sg:province":"MI",
    "sg:tags":[
        "church"
    ],
    "wof:name":"Chippewa Baptist Church",
    "wof:placetype":"venue"
},
  "geometry": {"coordinates":[-84.668227,43.611327],"type":"Point"}
}