{
  "type": "Feature",
  "properties": {
    "iso:country":"US",
    "sg:address":"1470 Vera Dr",
    "sg:city":"Hillsdale",
    "sg:classifiers":[
        {
            "category":"Building & Trades",
            "subcategory":"Construction",
            "type":"Services"
        }
    ],
    "sg:phone":"+1 517 437 2300",
    "sg:postcode":"49242",
    "sg:province":"MI",
    "sg:tags":[
        "installs",
        "residential",
        "commercial",
        "auto",
        "glass"
    ],
    "wof:name":"G & G Glass Inc",
    "wof:placetype":"venue"
},
  "geometry": {"coordinates":[-84.62322899999999,41.905129],"type":"Point"}
}