{
  "type": "Feature",
  "properties": {
    "iso:country":"US",
    "sg:address":"9981 Telegraph Rd",
    "sg:city":"Taylor",
    "sg:classifiers":[
        {
            "category":"Organizations",
            "subcategory":"Community Association",
            "type":"Services"
        }
    ],
    "sg:phone":"+1 313 291 1398",
    "sg:postcode":"48180",
    "sg:province":"MI",
    "wof:name":"Moose Family Center 887",
    "wof:placetype":"venue"
},
  "geometry": {"coordinates":[-83.269228,42.236321],"type":"Point"}
}