{
  "type": "Feature",
  "properties": {
    "iso:country":"US",
    "sg:address":"402 3rd St",
    "sg:city":"Gwinn",
    "sg:classifiers":[
        {
            "category":"Government",
            "subcategory":"Office",
            "type":"Public Place"
        }
    ],
    "sg:phone":"+1 906 346 8767",
    "sg:postcode":"49858",
    "sg:province":"MI",
    "sg:tags":[
        "federal",
        "security"
    ],
    "wof:name":"Us Naval Reserve Facility",
    "wof:placetype":"venue"
},
  "geometry": {"coordinates":[-87.603533,45.102255],"type":"Point"}
}