{
  "type": "Feature",
  "properties": {
    "iso:country":"US",
    "sg:address":"22412 Gratiot Ave",
    "sg:city":"Eastpointe",
    "sg:classifiers":[
        {
            "category":"Restaurant",
            "type":"Food & Drink"
        }
    ],
    "sg:phone":"+1 586 772 3388",
    "sg:postcode":"48021",
    "sg:province":"MI",
    "sg:tags":[
        "chinese"
    ],
    "wof:name":"Happy Garden Restaurant",
    "wof:placetype":"venue"
},
  "geometry": {"coordinates":[-82.959503,42.4618],"type":"Point"}
}