{
  "type": "Feature",
  "properties": {
    "iso:country":"US",
    "sg:address":"19143 Harlow St",
    "sg:city":"Melvindale",
    "sg:classifiers":[
        {
            "category":"Building & Trades",
            "subcategory":"Landscaping Services",
            "type":"Services"
        }
    ],
    "sg:phone":"+1 313 381 3503",
    "sg:postcode":"48122",
    "sg:province":"MI",
    "wof:name":"Gino & Assoc Lawncare & Snow R",
    "wof:placetype":"venue"
},
  "geometry": {"coordinates":[-83.18571,42.271794],"type":"Point"}
}