{
  "type": "Feature",
  "properties": {
    "iso:country":"US",
    "sg:address":"8933 Mystic Ln",
    "sg:city":"Warren",
    "sg:classifiers":[
        {
            "category":"Building & Trades",
            "subcategory":"Plumbing",
            "type":"Services"
        }
    ],
    "sg:phone":"+1 586 977 9175",
    "sg:postcode":"48093",
    "sg:province":"MI",
    "sg:tags":[
        "contractor"
    ],
    "wof:name":"Veterans Heating & Cooling",
    "wof:placetype":"venue"
},
  "geometry": {"coordinates":[-83.01795199999999,42.529031],"type":"Point"}
}