{
  "type": "Feature",
  "properties": {
    "iso:country":"US",
    "sg:address":"1324 Harry St",
    "sg:city":"Ypsilanti",
    "sg:classifiers":[
        {
            "category":"Professional",
            "subcategory":"Accounting & Tax Preparation",
            "type":"Services"
        }
    ],
    "sg:phone":"+1 734 487 5884",
    "sg:postcode":"48198",
    "sg:province":"MI",
    "wof:name":"Sargent & Sons Tax Service",
    "wof:placetype":"venue"
},
  "geometry": {"coordinates":[-83.574489,42.226949],"type":"Point"}
}