{
  "type": "Feature",
  "properties": {
    "iso:country":"US",
    "sg:address":"10777 96th Ave",
    "sg:city":"Zeeland",
    "sg:classifiers":[
        {
            "category":"Retail",
            "subcategory":"Auto Repair",
            "type":"Services"
        }
    ],
    "sg:phone":"+1 616 895 9078",
    "sg:postcode":"49464",
    "sg:province":"MI",
    "sg:tags":[
        "truck"
    ],
    "wof:name":"Wagenmaker Truck & Trailer",
    "wof:placetype":"venue"
},
  "geometry": {"coordinates":[-86.02378,42.960571],"type":"Point"}
}