{
  "type": "Feature",
  "properties": {
    "iso:country":"US",
    "sg:address":"11829 US Hwy 23",
    "sg:city":"Ossineke",
    "sg:classifiers":[
        {
            "category":"Shopping",
            "subcategory":"Gifts & Souvenirs",
            "type":"Retail Goods"
        }
    ],
    "sg:phone":"+1 989 471 5345",
    "sg:postcode":"49766",
    "sg:province":"MI",
    "wof:name":"Secret Garden & Gifts",
    "wof:placetype":"venue"
},
  "geometry": {"coordinates":[-83.44312600000001,44.904856],"type":"Point"}
}