{
  "type": "Feature",
  "properties": {
    "iso:country":"US",
    "sg:address":"609 E Dill Dr",
    "sg:city":"Dewitt",
    "sg:classifiers":[
        {
            "category":"Personal",
            "subcategory":"Beauty Salon",
            "type":"Services"
        }
    ],
    "sg:phone":"+1 517 669 3434",
    "sg:postcode":"48820",
    "sg:province":"MI",
    "wof:name":"Cottage Hair Designs",
    "wof:placetype":"venue"
},
  "geometry": {"coordinates":[-84.563484,42.839411],"type":"Point"}
}