{
  "type": "Feature",
  "properties": {
    "iso:country":"US",
    "sg:address":"230 N Sycamore St",
    "sg:city":"Lansing",
    "sg:classifiers":[
        {
            "category":"Professional",
            "subcategory":"Lawyer & Legal Services",
            "type":"Services"
        }
    ],
    "sg:phone":"+1 517 702 1742",
    "sg:postcode":"48933",
    "sg:province":"MI",
    "sg:tags":[
        "attorney"
    ],
    "wof:name":"Mc Coy Law",
    "wof:placetype":"venue"
},
  "geometry": {"coordinates":[-84.561469,42.735624],"type":"Point"}
}