{
  "type": "Feature",
  "properties": {
    "iso:country":"US",
    "sg:address":"3412 Stoneyridge Dr",
    "sg:city":"Hudsonville",
    "sg:classifiers":[
        {
            "category":"Banks & Credit Unions",
            "subcategory":"Investment Brokerage",
            "type":"Services"
        }
    ],
    "sg:phone":"+1 616 669 6422",
    "sg:postcode":"49426",
    "sg:province":"MI",
    "sg:tags":[
        "advisory"
    ],
    "wof:name":"Firstmark Financial LLC",
    "wof:placetype":"venue"
},
  "geometry": {"coordinates":[-85.866986,42.890676],"type":"Point"}
}