{
  "type": "Feature",
  "properties": {
    "iso:country":"US",
    "sg:address":"2496 Meadow Dr",
    "sg:city":"Zeeland",
    "sg:classifiers":[
        {
            "category":"Banks & Credit Unions",
            "subcategory":"Financial Services",
            "type":"Services"
        }
    ],
    "sg:phone":"+1 616 772 0865",
    "sg:postcode":"49464",
    "sg:province":"MI",
    "sg:tags":[
        "company",
        "holding"
    ],
    "wof:name":"Betten Family Holding Co",
    "wof:placetype":"venue"
},
  "geometry": {"coordinates":[-86.044813,42.812433],"type":"Point"}
}