{
  "type": "Feature",
  "properties": {
    "iso:country":"US",
    "sg:address":"36950 Ryan Rd",
    "sg:city":"Sterling Heights",
    "sg:classifiers":[
        {
            "category":"Banks & Credit Unions",
            "subcategory":"Financial Services",
            "type":"Services"
        }
    ],
    "sg:phone":"+1 586 979 2300",
    "sg:postcode":"48310",
    "sg:province":"MI",
    "sg:tags":[
        "broker",
        "mortgage"
    ],
    "wof:name":"Home Credit Lending",
    "wof:placetype":"venue"
},
  "geometry": {"coordinates":[-83.06970200000001,42.564098],"type":"Point"}
}