{
  "type": "Feature",
  "properties": {
    "iso:country":"US",
    "sg:address":"105 W Michigan Ave",
    "sg:city":"Marshall",
    "sg:classifiers":[
        {
            "category":"Restaurant",
            "type":"Food & Drink"
        }
    ],
    "sg:phone":"+1 269 781 7935",
    "sg:postcode":"49068",
    "sg:province":"MI",
    "sg:tags":[
        "shop",
        "coffee"
    ],
    "wof:name":"Garden Theater Coffee Shop",
    "wof:placetype":"venue"
},
  "geometry": {"coordinates":[-84.95878399999999,42.27197],"type":"Point"}
}