{
  "type": "Feature",
  "properties": {
    "iso:country":"US",
    "sg:address":"163 N Huron Rd",
    "sg:city":"Linwood",
    "sg:classifiers":[
        {
            "category":"Home & Garden",
            "subcategory":"Home Furnishings",
            "type":"Retail Goods"
        }
    ],
    "sg:phone":"+1 989 697 4310",
    "sg:postcode":"48634",
    "sg:province":"MI",
    "sg:tags":[
        "curtain",
        "made",
        "drapery"
    ],
    "wof:name":"Lois Jean Interiors",
    "wof:placetype":"venue"
},
  "geometry": {"coordinates":[-83.976432,43.743716],"type":"Point"}
}