{
  "type": "Feature",
  "properties": {
    "iso:country":"US",
    "sg:address":"122 Monroe Center St NW",
    "sg:city":"Grand Rapids",
    "sg:classifiers":[
        {
            "category":"Restaurant",
            "type":"Food & Drink"
        }
    ],
    "sg:menulink":"http://www.allmenus.com/mi/grand-rapids/58292-tre-cugini/menu/",
    "sg:phone":"+1 616 235 9339",
    "sg:postcode":"49503",
    "sg:province":"MI",
    "sg:tags":[
        "italian"
    ],
    "wof:name":"Tre Cugini",
    "wof:placetype":"venue"
},
  "geometry": {"coordinates":[-85.67083599999999,42.965487],"type":"Point"}
}