{
  "type": "Feature",
  "properties": {
    "iso:country":"US",
    "sg:address":"12800 Cherry Ave",
    "sg:city":"Rapid City",
    "sg:classifiers":[
        {
            "category":"Travel",
            "subcategory":"Hotels & Motels",
            "type":"Entertainment"
        }
    ],
    "sg:phone":"+1 231 322 4444",
    "sg:postcode":"49676",
    "sg:province":"MI",
    "wof:name":"Torch River Resort LLC",
    "wof:placetype":"venue"
},
  "geometry": {"coordinates":[-85.330219,44.850186],"type":"Point"}
}