{
  "type": "Feature",
  "properties": {
    "iso:country":"US",
    "sg:address":"5580 State Hwy 140",
    "sg:city":"Eau Claire",
    "sg:classifiers":[
        {
            "category":"Professional",
            "subcategory":"Business Services",
            "type":"Services"
        }
    ],
    "sg:phone":"+1 269 461 6686",
    "sg:postcode":"49111",
    "sg:province":"MI",
    "sg:tags":[
        "auctioneer"
    ],
    "wof:name":"Glassman's Auction & Real Est",
    "wof:placetype":"venue"
},
  "geometry": {"coordinates":[-86.261532,42.016347],"type":"Point"}
}