{
  "type": "Feature",
  "properties": {
    "iso:country":"US",
    "sg:address":"32783 Middlebelt Rd",
    "sg:city":"Farmington Hills",
    "sg:classifiers":[
        {
            "category":"Professional",
            "subcategory":"Accounting & Tax Preparation",
            "type":"Services"
        }
    ],
    "sg:phone":"+1 248 626 3800",
    "sg:postcode":"48334",
    "sg:province":"MI",
    "sg:tags":[
        "accountant"
    ],
    "wof:name":"Tama Ely CPA",
    "wof:placetype":"venue"
},
  "geometry": {"coordinates":[-83.340599,42.527599],"type":"Point"}
}