{
  "type": "Feature",
  "properties": {
    "iso:country":"US",
    "sg:address":"934 E Keating Ave",
    "sg:city":"Muskegon",
    "sg:classifiers":[
        {
            "category":"Government",
            "subcategory":"Post Office",
            "type":"Public Place"
        }
    ],
    "sg:phone":"+1 231 725 8141",
    "sg:postcode":"49442",
    "sg:province":"MI",
    "wof:name":"US Post Office",
    "wof:placetype":"venue"
},
  "geometry": {"coordinates":[-86.221322,43.215944],"type":"Point"}
}