{
  "type": "Feature",
  "properties": {
    "iso:country":"US",
    "sg:address":"1449 Banbury Rd",
    "sg:city":"Kalamazoo",
    "sg:classifiers":[
        {
            "category":"Shopping",
            "subcategory":"Clothing, Apparel, & Fashions",
            "type":"Retail Goods"
        }
    ],
    "sg:phone":"+1 269 321 2103",
    "sg:postcode":"49001",
    "sg:province":"MI",
    "sg:tags":[
        "alteration"
    ],
    "wof:name":"And Sew On",
    "wof:placetype":"venue"
},
  "geometry": {"coordinates":[-85.560924,42.251028],"type":"Point"}
}