{
  "type": "Feature",
  "properties": {
    "iso:country":"US",
    "sg:address":"212 Bedlington Dr",
    "sg:city":"Rochester",
    "sg:classifiers":[
        {
            "category":"Building & Trades",
            "subcategory":"Construction",
            "type":"Services"
        }
    ],
    "sg:phone":"+1 248 651 6093",
    "sg:postcode":"48307",
    "sg:province":"MI",
    "sg:tags":[
        "hanging",
        "contractor"
    ],
    "wof:name":"Decor Painting Co",
    "wof:placetype":"venue"
},
  "geometry": {"coordinates":[-83.12931500000001,42.656574],"type":"Point"}
}