{
  "type": "Feature",
  "properties": {
    "iso:country":"US",
    "sg:address":"17163 Westphalia St",
    "sg:city":"Detroit",
    "sg:classifiers":[
        {
            "category":"Professional",
            "subcategory":"Business Services",
            "type":"Services"
        }
    ],
    "sg:phone":"+1 313 527 9142",
    "sg:postcode":"48205",
    "sg:province":"MI",
    "wof:name":"Big Daddy Grove Publishing",
    "wof:placetype":"venue"
},
  "geometry": {"coordinates":[-82.992378,42.427268],"type":"Point"}
}