{
  "type": "Feature",
  "properties": {
    "iso:country":"US",
    "sg:address":"154 E Chicago Blvd",
    "sg:city":"Tecumseh",
    "sg:classifiers":[
        {
            "category":"Shopping",
            "subcategory":"Gifts & Souvenirs",
            "type":"Retail Goods"
        }
    ],
    "sg:phone":"+1 517 270 0962",
    "sg:postcode":"49286",
    "sg:province":"MI",
    "sg:tags":[
        "basket",
        "parcel"
    ],
    "wof:name":"Gathered Gifts",
    "wof:placetype":"venue"
},
  "geometry": {"coordinates":[-83.94453900000001,42.003985],"type":"Point"}
}