{
  "type": "Feature",
  "properties": {
    "iso:country":"US",
    "sg:address":"1550 Middlebrook Dr",
    "sg:city":"Muskegon",
    "sg:classifiers":[
        {
            "category":"Real Estate",
            "subcategory":"Real Estate Agent",
            "type":"Services"
        }
    ],
    "sg:phone":"+1 231 780 4741",
    "sg:postcode":"49441",
    "sg:province":"MI",
    "wof:name":"Max L Green & Associates",
    "wof:placetype":"venue"
},
  "geometry": {"coordinates":[-86.280512,43.180241],"type":"Point"}
}