{
  "type": "Feature",
  "properties": {
    "iso:country":"US",
    "sg:address":"626 E Conrad Rd",
    "sg:city":"Scottville",
    "sg:phone":"+1 231 757 3880",
    "sg:postcode":"49454",
    "sg:province":"MI",
    "sg:tags":[
        "farm"
    ],
    "wof:name":"Alexis Bradow Farm",
    "wof:placetype":"venue"
},
  "geometry": {"coordinates":[-86.26361900000001,43.933314],"type":"Point"}
}