{
  "type": "Feature",
  "properties": {
    "iso:country":"US",
    "sg:address":"226 Perry Ave",
    "sg:city":"Big Rapids",
    "sg:classifiers":[
        {
            "category":"Restaurant",
            "type":"Food & Drink"
        }
    ],
    "sg:phone":"+1 231 592 4966",
    "sg:postcode":"49307",
    "sg:province":"MI",
    "wof:name":"Hot 'n Now Hamburgers",
    "wof:placetype":"venue"
},
  "geometry": {"coordinates":[-85.490334,43.687862],"type":"Point"}
}