{
  "type": "Feature",
  "properties": {
    "iso:country":"US",
    "sg:address":"13264 S Benzonia Trl",
    "sg:city":"Empire",
    "sg:classifiers":[
        {
            "category":"Airport",
            "type":"Transportation"
        }
    ],
    "sg:phone":"+1 231 326 5513",
    "sg:postcode":"49630",
    "sg:province":"MI",
    "wof:name":"Empire Airport",
    "wof:placetype":"venue"
},
  "geometry": {"coordinates":[-85.998682,44.78957],"type":"Point"}
}