{
  "type": "Feature",
  "properties": {
    "iso:country":"US",
    "sg:address":"3313 Chestnut Ave",
    "sg:city":"Coloma",
    "sg:classifiers":[
        {
            "category":"Travel",
            "subcategory":"Hotels & Motels",
            "type":"Entertainment"
        }
    ],
    "sg:phone":"+1 269 849 1233",
    "sg:postcode":"49038",
    "sg:province":"MI",
    "sg:tags":[
        "resort"
    ],
    "wof:name":"Sweet Cherry Resort",
    "wof:placetype":"venue"
},
  "geometry": {"coordinates":[-86.380207,42.214724],"type":"Point"}
}