{
  "type": "Feature",
  "properties": {
    "iso:country":"US",
    "sg:address":"3133 Union Lake Rd",
    "sg:city":"Commerce Township",
    "sg:classifiers":[
        {
            "category":"Professional",
            "subcategory":"Secretarial Services",
            "type":"Services"
        }
    ],
    "sg:phone":"+1 248 360 2145",
    "sg:postcode":"48382",
    "sg:province":"MI",
    "sg:tags":[
        "reporting"
    ],
    "wof:name":"Regency Transcriptions",
    "wof:placetype":"venue"
},
  "geometry": {"coordinates":[-83.445809,42.591397],"type":"Point"}
}