{
  "type": "Feature",
  "properties": {
    "iso:country":"US",
    "sg:address":"3162 S Loomis Rd",
    "sg:city":"Mt Pleasant",
    "sg:classifiers":[
        {
            "category":"Retail",
            "subcategory":"Animal Services",
            "type":"Services"
        }
    ],
    "sg:phone":"+1 989 779 1084",
    "sg:postcode":"48858",
    "sg:province":"MI",
    "sg:tags":[
        "pet",
        "boarding",
        "sitting"
    ],
    "wof:name":"K 9 Companions Club",
    "wof:placetype":"venue"
},
  "geometry": {"coordinates":[-84.6681,43.594913],"type":"Point"}
}