{
  "type": "Feature",
  "properties": {
    "iso:country":"US",
    "sg:address":"10698 Michigan Ave",
    "sg:city":"Posen",
    "sg:classifiers":[
        {
            "category":"Food & Beverages",
            "subcategory":"Groceries & Convenience Stores",
            "type":"Retail Goods"
        }
    ],
    "sg:phone":"+1 989 766 2548",
    "sg:postcode":"49776",
    "sg:province":"MI",
    "wof:name":"Val-U-Variety",
    "wof:placetype":"venue"
},
  "geometry": {"coordinates":[-83.698936,45.266669],"type":"Point"}
}