{
  "type": "Feature",
  "properties": {
    "iso:country":"US",
    "sg:address":"130 River Rd",
    "sg:city":"Sparta",
    "sg:classifiers":[
        {
            "category":"Social Services",
            "subcategory":"Child Care",
            "type":"Services"
        }
    ],
    "sg:phone":"+1 616 887 0507",
    "sg:postcode":"49345",
    "sg:province":"MI",
    "sg:tags":[
        "day"
    ],
    "wof:name":"Kathleen Helsel",
    "wof:placetype":"venue"
},
  "geometry": {"coordinates":[-85.700293,43.163801],"type":"Point"}
}