{
  "type": "Feature",
  "properties": {
    "iso:country":"US",
    "sg:address":"7040 Schaefer Rd",
    "sg:city":"Dearborn",
    "sg:classifiers":[
        {
            "category":"Restaurant",
            "type":"Food & Drink"
        }
    ],
    "sg:menulink":"http://www.allmenus.com/mi/dearborn/247157-cozi-grill-baguette/menu/",
    "sg:phone":"+1 313 584 2241",
    "sg:postcode":"48126",
    "sg:province":"MI",
    "sg:tags":[
        "wrap",
        "american",
        "sandwich"
    ],
    "wof:name":"Cozi Grill Baguette",
    "wof:placetype":"venue"
},
  "geometry": {"coordinates":[-83.17679800000001,42.342573],"type":"Point"}
}