{
  "type": "Feature",
  "properties": {
    "iso:country":"US",
    "sg:address":"1681 N 350 E",
    "sg:city":"Angola",
    "sg:classifiers":[
        {
            "category":"Building & Trades",
            "subcategory":"Construction",
            "type":"Services"
        }
    ],
    "sg:phone":"+1 260 665 9307",
    "sg:postcode":"46703",
    "sg:province":"MI",
    "sg:tags":[
        "concrete",
        "contractor"
    ],
    "wof:name":"Dave's Construction",
    "wof:placetype":"venue"
},
  "geometry": {"coordinates":[-84.926233,41.662603],"type":"Point"}
}