{
  "type": "Feature",
  "properties": {
    "iso:country":"US",
    "sg:address":"2071 Metropolitan Pkwy",
    "sg:city":"Sterling Heights",
    "sg:classifiers":[
        {
            "category":"Manufacturing",
            "subcategory":"Printing",
            "type":"Manufacturing & Wholesale Goods"
        }
    ],
    "sg:phone":"+1 586 264 5001",
    "sg:postcode":"48310",
    "sg:province":"MI",
    "sg:tags":[
        "printer"
    ],
    "wof:name":"Digital Harp",
    "wof:placetype":"venue"
},
  "geometry": {"coordinates":[-83.087653,42.564196],"type":"Point"}
}