{
  "type": "Feature",
  "properties": {
    "iso:country":"US",
    "sg:address":"1412 W River Rd",
    "sg:city":"Traverse City",
    "sg:classifiers":[
        {
            "category":"Building & Trades",
            "subcategory":"Landscaping Services",
            "type":"Services"
        }
    ],
    "sg:phone":"+1 231 947 9548",
    "sg:postcode":"49686",
    "sg:province":"MI",
    "sg:tags":[
        "landscape",
        "contractor"
    ],
    "wof:name":"Anderson Outdoor Svc",
    "wof:placetype":"venue"
},
  "geometry": {"coordinates":[-85.60647299999999,44.665383],"type":"Point"}
}