{
  "type": "Feature",
  "properties": {
    "iso:country":"US",
    "sg:address":"62 E State St",
    "sg:city":"Port Austin",
    "sg:classifiers":[
        {
            "category":"Banks & Credit Unions",
            "subcategory":"Bank",
            "type":"Services"
        }
    ],
    "sg:phone":"+1 989 738 5235",
    "sg:postcode":"48467",
    "sg:province":"MI",
    "wof:name":"Port Austin State Bank",
    "wof:placetype":"venue"
},
  "geometry": {"coordinates":[-82.99293,44.044763],"type":"Point"}
}