{
  "type": "Feature",
  "properties": {
    "iso:country":"US",
    "sg:address":"25119 Leach St",
    "sg:city":"Roseville",
    "sg:classifiers":[
        {
            "category":"Manufacturing",
            "subcategory":"Retail Goods",
            "type":"Manufacturing & Wholesale Goods"
        }
    ],
    "sg:phone":"+1 586 772 3905",
    "sg:postcode":"48066",
    "sg:province":"MI",
    "sg:tags":[
        "lead",
        "mfg"
    ],
    "wof:name":"Airtistic Airbrush",
    "wof:placetype":"venue"
},
  "geometry": {"coordinates":[-82.96427,42.483208],"type":"Point"}
}