{
  "type": "Feature",
  "properties": {
    "iso:country":"US",
    "sg:address":"3056 Bay Point Dr",
    "sg:city":"Rochester Hills",
    "sg:classifiers":[
        {
            "category":"Personal",
            "subcategory":"Hair Removal",
            "type":"Services"
        }
    ],
    "sg:phone":"+1 248 375 2911",
    "sg:postcode":"48309",
    "sg:province":"MI",
    "sg:tags":[
        "removing"
    ],
    "wof:name":"Electrolysis By Gordana",
    "wof:placetype":"venue"
},
  "geometry": {"coordinates":[-83.197204,42.690387],"type":"Point"}
}