{
  "type": "Feature",
  "properties": {
    "iso:country":"US",
    "sg:address":"5945 Sandhurst St",
    "sg:city":"Canton",
    "sg:classifiers":[
        {
            "category":"Real Estate",
            "subcategory":"Real Estate Services",
            "type":"Services"
        }
    ],
    "sg:phone":"+1 734 331 9160",
    "sg:postcode":"48187",
    "sg:province":"MI",
    "sg:tags":[
        "management",
        "property"
    ],
    "wof:name":"Perfect Property Maintenance",
    "wof:placetype":"venue"
},
  "geometry": {"coordinates":[-83.435425,42.325032],"type":"Point"}
}