{
  "type": "Feature",
  "properties": {
    "iso:country":"US",
    "sg:address":"7093 L Rd",
    "sg:city":"Escanaba",
    "sg:classifiers":[
        {
            "category":"Wholesale",
            "subcategory":"Construction Materials",
            "type":"Manufacturing & Wholesale Goods"
        }
    ],
    "sg:phone":"+1 906 786 2329",
    "sg:postcode":"49829",
    "sg:province":"MI",
    "sg:tags":[
        "fence"
    ],
    "wof:name":"V W Fence Co",
    "wof:placetype":"venue"
},
  "geometry": {"coordinates":[-87.142067,45.799801],"type":"Point"}
}