{
  "type": "Feature",
  "properties": {
    "iso:country":"US",
    "sg:address":"418 E Chestnut St",
    "sg:city":"Breckenridge",
    "sg:phone":"+1 989 842 5361",
    "sg:postcode":"48615",
    "sg:province":"MI",
    "sg:tags":[
        "farm",
        "field",
        "crop"
    ],
    "wof:name":"Triple M Seeds",
    "wof:placetype":"venue"
},
  "geometry": {"coordinates":[-84.47456699999999,43.406657],"type":"Point"}
}