{
  "type": "Feature",
  "properties": {
    "iso:country":"US",
    "sg:address":"32870 Robinhood Dr",
    "sg:city":"Beverly Hills",
    "sg:classifiers":[
        {
            "category":"Professional",
            "subcategory":"Management & Consulting",
            "type":"Services"
        }
    ],
    "sg:phone":"+1 248 433 3590",
    "sg:postcode":"48025",
    "sg:province":"MI",
    "sg:tags":[
        "construction"
    ],
    "wof:name":"John Higgins & Assoc Inc",
    "wof:placetype":"venue"
},
  "geometry": {"coordinates":[-83.271952,42.530292],"type":"Point"}
}