{
  "type": "Feature",
  "properties": {
    "iso:country":"US",
    "sg:address":"33752 Frost St",
    "sg:city":"Dowagiac",
    "sg:classifiers":[
        {
            "category":"Freight",
            "type":"Transportation"
        }
    ],
    "sg:phone":"+1 269 782 4142",
    "sg:postcode":"49047",
    "sg:province":"MI",
    "sg:tags":[
        "operator",
        "local",
        "trucking"
    ],
    "wof:name":"Bruce Bell Trucking",
    "wof:placetype":"venue"
},
  "geometry": {"coordinates":[-86.21812300000001,41.970966],"type":"Point"}
}