{
  "type": "Feature",
  "properties": {
    "iso:country":"US",
    "sg:address":"9366 Apple Ave",
    "sg:city":"Ravenna",
    "sg:classifiers":[
        {
            "category":"Government",
            "subcategory":"Office",
            "type":"Public Place"
        }
    ],
    "sg:phone":"+1 231 724 6001",
    "sg:postcode":"49451",
    "sg:province":"MI",
    "sg:tags":[
        "solid",
        "waste",
        "facility"
    ],
    "wof:name":"O Solid Waste",
    "wof:placetype":"venue"
},
  "geometry": {"coordinates":[-86.008244,43.235098],"type":"Point"}
}