{
  "type": "Feature",
  "properties": {
    "iso:country":"US",
    "sg:address":"220 W Congress St",
    "sg:city":"Detroit",
    "sg:classifiers":[
        {
            "category":"Professional",
            "subcategory":"Lawyer & Legal Services",
            "type":"Services"
        }
    ],
    "sg:phone":"+1 313 967 9666",
    "sg:postcode":"48226",
    "sg:province":"MI",
    "wof:name":"Justice Center the PC",
    "wof:placetype":"venue"
},
  "geometry": {"coordinates":[-83.048597,42.329256],"type":"Point"}
}