{
  "type": "Feature",
  "properties": {
    "iso:country":"US",
    "sg:address":"2692 Elton Cir",
    "sg:city":"Lambertville",
    "sg:classifiers":[
        {
            "category":"Professional",
            "subcategory":"Computer Services",
            "type":"Services"
        }
    ],
    "sg:phone":"+1 734 856 3504",
    "sg:postcode":"48144",
    "sg:province":"MI",
    "wof:name":"HP",
    "wof:placetype":"venue"
},
  "geometry": {"coordinates":[-83.612532,41.73672],"type":"Point"}
}