{
  "type": "Feature",
  "properties": {
    "iso:country":"US",
    "sg:address":"1116 W Ganson St",
    "sg:city":"Jackson",
    "sg:classifiers":[
        {
            "category":"Health Services",
            "subcategory":"Doctor",
            "type":"Services"
        }
    ],
    "sg:phone":"+1 517 782 9436",
    "sg:postcode":"49202",
    "sg:province":"MI",
    "sg:tags":[
        "physician",
        "surgeon"
    ],
    "wof:name":"Tlc Eye Care Of Michigan",
    "wof:placetype":"venue"
},
  "geometry": {"coordinates":[-84.428162,42.25477],"type":"Point"}
}