{
  "type": "Feature",
  "properties": {
    "iso:country":"US",
    "sg:address":"7667 Gordon Industrial Dr SW",
    "sg:city":"Byron Center",
    "sg:classifiers":[
        {
            "category":"Autos & Motor Vehicles",
            "subcategory":"Auto Supplies",
            "type":"Retail Goods"
        }
    ],
    "sg:phone":"+1 616 281 9800",
    "sg:postcode":"49315",
    "sg:province":"MI",
    "sg:tags":[
        "tire"
    ],
    "sg:website":"www.belletires.com",
    "wof:name":"Belle Tire Distributors",
    "wof:placetype":"venue"
},
  "geometry": {"coordinates":[-85.67596899999999,42.824448],"type":"Point"}
}