{
  "type": "Feature",
  "properties": {
    "iso:country":"US",
    "sg:address":"30912 Lund Ave",
    "sg:city":"Warren",
    "sg:classifiers":[
        {
            "category":"Professional",
            "subcategory":"Business Services",
            "type":"Services"
        }
    ],
    "sg:phone":"+1 586 751 7052",
    "sg:postcode":"48093",
    "sg:province":"MI",
    "wof:name":"Innovated Capital Solutions",
    "wof:placetype":"venue"
},
  "geometry": {"coordinates":[-83.019768,42.519414],"type":"Point"}
}