{
  "type": "Feature",
  "properties": {
    "iso:country":"US",
    "sg:address":"16880 Middlebelt Rd",
    "sg:city":"Livonia",
    "sg:classifiers":[
        {
            "category":"Professional",
            "subcategory":"Management & Consulting",
            "type":"Services"
        }
    ],
    "sg:phone":"+1 734 522 2212",
    "sg:postcode":"48154",
    "sg:province":"MI",
    "sg:tags":[
        "business"
    ],
    "wof:name":"I A Q Management Inc",
    "wof:placetype":"venue"
},
  "geometry": {"coordinates":[-83.33508500000001,42.41182],"type":"Point"}
}