{
  "type": "Feature",
  "properties": {
    "iso:country":"US",
    "sg:address":"1807 Martindale Ave SW",
    "sg:city":"Grand Rapids",
    "sg:classifiers":[
        {
            "category":"Communications",
            "subcategory":"Film & Video Production",
            "type":"Services"
        }
    ],
    "sg:phone":"+1 616 723 6352",
    "sg:postcode":"49509",
    "sg:province":"MI",
    "sg:tags":[
        "taping"
    ],
    "wof:name":"Evermore Studios",
    "wof:placetype":"venue"
},
  "geometry": {"coordinates":[-85.69926700000001,42.932032],"type":"Point"}
}