{
  "type": "Feature",
  "properties": {
    "iso:country":"US",
    "sg:address":"3626 Dunckel Rd",
    "sg:city":"Lansing",
    "sg:classifiers":[
        {
            "category":"Professional",
            "subcategory":"Lawyer & Legal Services",
            "type":"Services"
        }
    ],
    "sg:phone":"+1 517 332 3555",
    "sg:postcode":"48910",
    "sg:province":"MI",
    "sg:tags":[
        "attorney"
    ],
    "wof:name":"Rapaport Pollok Farrell",
    "wof:placetype":"venue"
},
  "geometry": {"coordinates":[-84.50003700000001,42.689421],"type":"Point"}
}