{
  "type": "Feature",
  "properties": {
    "iso:country":"US",
    "sg:address":"9271 W Outer Dr",
    "sg:city":"Detroit",
    "sg:classifiers":[
        {
            "category":"Recreation",
            "type":"Entertainment"
        }
    ],
    "sg:phone":"+1 313 533 2771",
    "sg:postcode":"48219",
    "sg:province":"MI",
    "sg:tags":[
        "club",
        "membership"
    ],
    "wof:name":"USA Track & Field Inc",
    "wof:placetype":"venue"
},
  "geometry": {"coordinates":[-83.231489,42.411251],"type":"Point"}
}