{
  "type": "Feature",
  "properties": {
    "iso:country":"US",
    "sg:address":"22789 Rosalind Ave",
    "sg:city":"Eastpointe",
    "sg:classifiers":[
        {
            "category":"Real Estate",
            "subcategory":"Real Estate Operator",
            "type":"Services"
        }
    ],
    "sg:phone":"+1 586 772 5624",
    "sg:postcode":"48021",
    "sg:province":"MI",
    "sg:tags":[
        "building",
        "nonresidential"
    ],
    "wof:name":"Commercial Property Claim Svc",
    "wof:placetype":"venue"
},
  "geometry": {"coordinates":[-82.933201,42.466955],"type":"Point"}
}