{
  "type": "Feature",
  "properties": {
    "iso:country":"US",
    "sg:address":"69020 N Main St",
    "sg:city":"Richmond",
    "sg:classifiers":[
        {
            "category":"Shopping",
            "type":"Retail Goods"
        }
    ],
    "sg:phone":"+1 586 727 8000",
    "sg:postcode":"48062",
    "sg:province":"MI",
    "sg:tags":[
        "art",
        "gallery",
        "dealer"
    ],
    "wof:name":"Main Street Gallery",
    "wof:placetype":"venue"
},
  "geometry": {"coordinates":[-82.75612599999999,42.809292],"type":"Point"}
}