{
  "type": "Feature",
  "properties": {
    "iso:country":"US",
    "sg:address":"100 W Main St",
    "sg:city":"Mecosta",
    "sg:classifiers":[
        {
            "category":"Home & Garden",
            "subcategory":"Hardware",
            "type":"Retail Goods"
        }
    ],
    "sg:phone":"+1 231 972 8710",
    "sg:postcode":"49332",
    "sg:province":"MI",
    "wof:name":"Bradley's Hardware",
    "wof:placetype":"venue"
},
  "geometry": {"coordinates":[-85.22741000000001,43.620892],"type":"Point"}
}