{
  "type": "Feature",
  "properties": {
    "iso:country":"US",
    "sg:address":"35543 S Gratiot Ave",
    "sg:city":"Clinton Twp",
    "sg:classifiers":[
        {
            "category":"Restaurant",
            "type":"Food & Drink"
        }
    ],
    "sg:phone":"+1 586 792 3190",
    "sg:postcode":"48035",
    "sg:province":"MI",
    "sg:website":"www.oldcountrybuffet.com",
    "wof:name":"Old Country Buffet",
    "wof:placetype":"venue"
},
  "geometry": {"coordinates":[-82.896779,42.560446],"type":"Point"}
}