{
  "type": "Feature",
  "properties": {
    "iso:country":"US",
    "sg:address":"602 Piccadilly Rd",
    "sg:city":"Kalamazoo",
    "sg:classifiers":[
        {
            "category":"Shopping",
            "type":"Retail Goods"
        }
    ],
    "sg:phone":"+1 269 343 3507",
    "sg:postcode":"49006",
    "sg:province":"MI",
    "sg:tags":[
        "cosmetic",
        "perfume"
    ],
    "wof:name":"Back & Neck Nook",
    "wof:placetype":"venue"
},
  "geometry": {"coordinates":[-85.64395399999999,42.298411],"type":"Point"}
}