{
  "type": "Feature",
  "properties": {
    "iso:country":"US",
    "sg:address":"1970 Nash Dr",
    "sg:city":"Saint Joseph",
    "sg:classifiers":[
        {
            "category":"Real Estate",
            "subcategory":"Real Estate Operator",
            "type":"Services"
        }
    ],
    "sg:phone":"+1 269 428 2823",
    "sg:postcode":"49085",
    "sg:province":"MI",
    "sg:tags":[
        "building",
        "apartment"
    ],
    "wof:name":"Orchard View Apartments",
    "wof:placetype":"venue"
},
  "geometry": {"coordinates":[-86.501627,42.052852],"type":"Point"}
}