{
  "type": "Feature",
  "properties": {
    "iso:country":"US",
    "sg:address":"8830 Fenkell St",
    "sg:city":"Detroit",
    "sg:classifiers":[
        {
            "category":"Bars & Pubs",
            "subcategory":"Sports Bar",
            "type":"Food & Drink"
        }
    ],
    "sg:phone":"+1 313 345 7665",
    "sg:postcode":"48238",
    "sg:province":"MI",
    "sg:tags":[
        "hall",
        "pool"
    ],
    "wof:name":"Long Green Billards",
    "wof:placetype":"venue"
},
  "geometry": {"coordinates":[-83.15759799999999,42.402667],"type":"Point"}
}