{
  "type": "Feature",
  "properties": {
    "iso:country":"US",
    "sg:address":"500 Cherry St",
    "sg:city":"Manistee",
    "sg:classifiers":[
        {
            "category":"Sports & Exercise",
            "subcategory":"Golf",
            "type":"Entertainment"
        },
        {
            "category":"Recreation",
            "type":"Entertainment"
        }
    ],
    "sg:phone":"+1 231 723 2500",
    "sg:postcode":"49660",
    "sg:province":"MI",
    "sg:tags":[
        "club",
        "course",
        "membership"
    ],
    "wof:name":"Mainstee Golf & Country Club",
    "wof:placetype":"venue"
},
  "geometry": {"coordinates":[-86.339209,44.242101],"type":"Point"}
}