{
  "type": "Feature",
  "properties": {
    "iso:country":"US",
    "sg:address":"24845 Van Dyke Ave",
    "sg:city":"Center Line",
    "sg:classifiers":[
        {
            "category":"Shopping",
            "subcategory":"Mobile Phones",
            "type":"Retail Goods"
        }
    ],
    "sg:phone":"+1 586 759 0000",
    "sg:postcode":"48015",
    "sg:province":"MI",
    "wof:name":"Boost Mobile",
    "wof:placetype":"venue"
},
  "geometry": {"coordinates":[-83.027379,42.476308],"type":"Point"}
}