{
  "type": "Feature",
  "properties": {
    "iso:country":"US",
    "sg:address":"314 Town Center Dr",
    "sg:city":"Troy",
    "sg:classifiers":[
        {
            "category":"Professional",
            "subcategory":"Lawyer & Legal Services",
            "type":"Services"
        }
    ],
    "sg:phone":"+1 248 619 2500",
    "sg:postcode":"48084",
    "sg:province":"MI",
    "wof:name":"Lange & Cholack PC",
    "wof:placetype":"venue"
},
  "geometry": {"coordinates":[-83.15660099999999,42.566799],"type":"Point"}
}