{
  "type": "Feature",
  "properties": {
    "iso:country":"US",
    "sg:address":"1700 E Center Rd",
    "sg:city":"Hastings",
    "sg:classifiers":[
        {
            "category":"Education",
            "subcategory":"Special Training",
            "type":"Public Place"
        }
    ],
    "sg:phone":"+1 269 948 8588",
    "sg:postcode":"49058",
    "sg:province":"MI",
    "wof:name":"Christian Music Lessons",
    "wof:placetype":"venue"
},
  "geometry": {"coordinates":[-85.25958799999999,42.639174],"type":"Point"}
}