{
  "type": "Feature",
  "properties": {
    "iso:country":"US",
    "sg:address":"1172 147th Ave",
    "sg:city":"Wayland",
    "sg:classifiers":[
        {
            "category":"Freight",
            "type":"Transportation"
        }
    ],
    "sg:phone":"+1 616 877 4412",
    "sg:postcode":"49348",
    "sg:province":"MI",
    "sg:tags":[
        "consultant"
    ],
    "wof:name":"TNT Logistics",
    "wof:placetype":"venue"
},
  "geometry": {"coordinates":[-85.655612,42.761095],"type":"Point"}
}