{
  "type": "Feature",
  "properties": {
    "iso:country":"US",
    "sg:address":"221 Michigan St NE",
    "sg:city":"Grand Rapids",
    "sg:classifiers":[
        {
            "category":"Health Services",
            "subcategory":"Doctor",
            "type":"Services"
        }
    ],
    "sg:phone":"+1 616 456 9601",
    "sg:postcode":"49503",
    "sg:province":"MI",
    "sg:tags":[
        "medical"
    ],
    "wof:name":"Ottenweller Steven E MD",
    "wof:placetype":"venue"
},
  "geometry": {"coordinates":[-85.663504,42.970407],"type":"Point"}
}