{
  "type": "Feature",
  "properties": {
    "iso:country":"US",
    "sg:address":"17369 E 12 Mile Rd",
    "sg:city":"Roseville",
    "sg:classifiers":[
        {
            "category":"Shopping",
            "subcategory":"Gifts & Souvenirs",
            "type":"Retail Goods"
        }
    ],
    "sg:phone":"+1 586 498 8308",
    "sg:postcode":"48066",
    "sg:province":"MI",
    "wof:name":"Gifts 4 Gamblers",
    "wof:placetype":"venue"
},
  "geometry": {"coordinates":[-82.94155600000001,42.509588],"type":"Point"}
}