{
  "type": "Feature",
  "properties": {
    "iso:country":"US",
    "sg:address":"3543 Alpine Ave NW",
    "sg:city":"Grand Rapids",
    "sg:classifiers":[
        {
            "category":"Banks & Credit Unions",
            "subcategory":"Bank",
            "type":"Services"
        }
    ],
    "sg:phone":"+1 616 647 9000",
    "sg:postcode":"49544",
    "sg:province":"MI",
    "sg:tags":[
        "depository",
        "banking",
        "check",
        "cashing"
    ],
    "wof:name":"Check 'n Go",
    "wof:placetype":"venue"
},
  "geometry": {"coordinates":[-85.689386,43.027558],"type":"Point"}
}