{
  "type": "Feature",
  "properties": {
    "iso:country":"US",
    "sg:address":"21000 Telegraph Rd",
    "sg:city":"Southfield",
    "sg:classifiers":[
        {
            "category":"Manufacturing",
            "subcategory":"Tools & Machinery",
            "type":"Manufacturing & Wholesale Goods"
        }
    ],
    "sg:phone":"+1 248 353 8888",
    "sg:postcode":"48033",
    "sg:province":"MI",
    "sg:tags":[
        "equipment",
        "system",
        "automation"
    ],
    "sg:website":"www.comaupico.com",
    "wof:name":"Comau Pico",
    "wof:placetype":"venue"
},
  "geometry": {"coordinates":[-83.27818000000001,42.454364],"type":"Point"}
}