{
  "type": "Feature",
  "properties": {
    "iso:country":"US",
    "sg:address":"5245 Braden Rd",
    "sg:city":"Byron",
    "sg:classifiers":[
        {
            "category":"Shopping",
            "type":"Retail Goods"
        }
    ],
    "sg:phone":"+1 989 634 9738",
    "sg:postcode":"48418",
    "sg:province":"MI",
    "wof:name":"Direct Brand Names Inc",
    "wof:placetype":"venue"
},
  "geometry": {"coordinates":[-84.05832100000001,42.792731],"type":"Point"}
}