{
  "type": "Feature",
  "properties": {
    "iso:country":"US",
    "sg:address":"465 Pleasant St",
    "sg:city":"Hubbardston",
    "sg:classifiers":[
        {
            "category":"Social Services",
            "subcategory":"Adult Care",
            "type":"Services"
        }
    ],
    "sg:phone":"+1 989 981 6488",
    "sg:postcode":"48845",
    "sg:province":"MI",
    "sg:tags":[
        "residential"
    ],
    "wof:name":"Swartz Afc",
    "wof:placetype":"venue"
},
  "geometry": {"coordinates":[-84.848266,43.09816],"type":"Point"}
}