{
  "type": "Feature",
  "properties": {
    "iso:country":"US",
    "sg:address":"7077 W Old Channel Trl",
    "sg:city":"Montague",
    "sg:classifiers":[
        {
            "category":"Building & Trades",
            "subcategory":"Construction",
            "type":"Services"
        }
    ],
    "sg:phone":"+1 231 788 4789",
    "sg:postcode":"49437",
    "sg:province":"MI",
    "sg:tags":[
        "house",
        "repair"
    ],
    "wof:name":"Fred R Hoeker Builder",
    "wof:placetype":"venue"
},
  "geometry": {"coordinates":[-86.41841599999999,43.38301],"type":"Point"}
}