{
  "type": "Feature",
  "properties": {
    "iso:country":"US",
    "sg:address":"16500 Ashton Ave",
    "sg:city":"Detroit",
    "sg:classifiers":[
        {
            "category":"Professional",
            "subcategory":"Management & Consulting",
            "type":"Services"
        }
    ],
    "sg:phone":"+1 313 532 1724",
    "sg:postcode":"48219",
    "sg:province":"MI",
    "wof:name":"Dac Marketing",
    "wof:placetype":"venue"
},
  "geometry": {"coordinates":[-83.21992400000001,42.411888],"type":"Point"}
}