{
  "type": "Feature",
  "properties": {
    "iso:country":"US",
    "sg:address":"7115 Old Mill Rd",
    "sg:city":"Bloomfield Hills",
    "sg:classifiers":[
        {
            "category":"Professional",
            "subcategory":"Business Services",
            "type":"Services"
        }
    ],
    "sg:phone":"+1 248 593 8118",
    "sg:postcode":"48301",
    "sg:province":"MI",
    "wof:name":"S E Y Productions",
    "wof:placetype":"venue"
},
  "geometry": {"coordinates":[-83.274689,42.535406],"type":"Point"}
}