{
  "type": "Feature",
  "properties": {
    "iso:country":"US",
    "sg:address":"3001 W Big Beaver Rd Ste 608",
    "sg:city":"Troy",
    "sg:classifiers":[
        {
            "category":"Communications",
            "subcategory":"Television Station",
            "type":"Services"
        }
    ],
    "sg:phone":"+1 248 643 8445",
    "sg:postcode":"48084",
    "sg:province":"MI",
    "sg:tags":[
        "broadcast",
        "representative"
    ],
    "wof:name":"N B C Television Network",
    "wof:placetype":"venue"
},
  "geometry": {"coordinates":[-83.187004,42.560913],"type":"Point"}
}