{
  "type": "Feature",
  "properties": {
    "iso:country":"US",
    "sg:address":"7743 N Upton Rd",
    "sg:city":"Elsie",
    "sg:classifiers":[
        {
            "category":"Organizations",
            "subcategory":"Religious Organization",
            "type":"Services"
        }
    ],
    "sg:phone":"+1 989 862 4246",
    "sg:postcode":"48831",
    "sg:province":"MI",
    "wof:name":"Ashley Banister United ME",
    "wof:placetype":"venue"
},
  "geometry": {"coordinates":[-84.407168,43.094845],"type":"Point"}
}