{
  "type": "Feature",
  "properties": {
    "iso:country":"US",
    "sg:address":"10810 N Straits Hwy",
    "sg:city":"Cheboygan",
    "sg:classifiers":[
        {
            "category":"Retail",
            "subcategory":"Auto Repair",
            "type":"Services"
        }
    ],
    "sg:phone":"+1 231 597 8125",
    "sg:postcode":"49721",
    "sg:province":"MI",
    "sg:tags":[
        "repairing",
        "automobile"
    ],
    "wof:name":"Casey's Auto Parts & Repair",
    "wof:placetype":"venue"
},
  "geometry": {"coordinates":[-84.477553,45.61793],"type":"Point"}
}