{
  "type": "Feature",
  "properties": {
    "iso:country":"US",
    "sg:address":"4861 Henry St",
    "sg:city":"Muskegon",
    "sg:classifiers":[
        {
            "category":"Organizations",
            "subcategory":"Religious Organization",
            "type":"Services"
        }
    ],
    "sg:phone":"+1 231 798 2181",
    "sg:postcode":"49441",
    "sg:province":"MI",
    "sg:tags":[
        "church"
    ],
    "sg:website":"www.lakeharborumc.org",
    "wof:name":"Lake Harbor United Methodist",
    "wof:placetype":"venue"
},
  "geometry": {"coordinates":[-86.264129,43.164862],"type":"Point"}
}