{
  "type": "Feature",
  "properties": {
    "iso:country":"US",
    "sg:address":"641 145th Ave",
    "sg:city":"Caledonia",
    "sg:classifiers":[
        {
            "category":"Retail",
            "subcategory":"Repair Shop",
            "type":"Services"
        }
    ],
    "sg:phone":"+1 616 455 4100",
    "sg:postcode":"49316",
    "sg:province":"MI",
    "wof:name":"Dekams TV",
    "wof:placetype":"venue"
},
  "geometry": {"coordinates":[-85.614284,42.747025],"type":"Point"}
}