{
  "type": "Feature",
  "properties": {
    "iso:country":"US",
    "sg:address":"1280 E Big Beaver Rd Ste A",
    "sg:city":"Troy",
    "sg:classifiers":[
        {
            "category":"Shopping",
            "subcategory":"Stationery & Office Supplies",
            "type":"Retail Goods"
        }
    ],
    "sg:phone":"+1 248 307 1850",
    "sg:postcode":"48083",
    "sg:province":"MI",
    "sg:tags":[
        "equipment"
    ],
    "sg:website":"www.officeexpressnow.com",
    "wof:name":"Office Express",
    "wof:placetype":"venue"
},
  "geometry": {"coordinates":[-83.122238,42.56289],"type":"Point"}
}