{
  "type": "Feature",
  "properties": {
    "iso:country":"US",
    "sg:address":"1095 Virginia Way",
    "sg:city":"Jackson",
    "sg:classifiers":[
        {
            "category":"Manufacturing",
            "subcategory":"Tools & Machinery",
            "type":"Manufacturing & Wholesale Goods"
        }
    ],
    "sg:phone":"+1 517 784 0090",
    "sg:postcode":"49201",
    "sg:province":"MI",
    "sg:tags":[
        "broaching"
    ],
    "wof:name":"Worldwide Broach & Tool Inc",
    "wof:placetype":"venue"
},
  "geometry": {"coordinates":[-84.41099199999999,42.312493],"type":"Point"}
}