{
  "type": "Feature",
  "properties": {
    "iso:country":"US",
    "sg:address":"111 S 4th Ave",
    "sg:city":"Ann Arbor",
    "sg:classifiers":[
        {
            "category":"Health Services",
            "subcategory":"Doctor",
            "type":"Services"
        }
    ],
    "sg:phone":"+1 734 994 5110",
    "sg:postcode":"48104",
    "sg:province":"MI",
    "sg:tags":[
        "medical"
    ],
    "wof:name":"Blos Peter Jr MD PC",
    "wof:placetype":"venue"
},
  "geometry": {"coordinates":[-83.747192,42.280542],"type":"Point"}
}