{
  "type": "Feature",
  "properties": {
    "iso:country":"US",
    "sg:address":"3070 Palms Rd",
    "sg:city":"Casco",
    "sg:classifiers":[
        {
            "category":"Wholesale",
            "subcategory":"Computers",
            "type":"Manufacturing & Wholesale Goods"
        }
    ],
    "sg:phone":"+1 810 326 9000",
    "sg:postcode":"48064",
    "sg:province":"MI",
    "sg:tags":[
        "comp",
        "peripheral",
        "retail"
    ],
    "wof:name":"Hi-Tech System Service Nic",
    "wof:placetype":"venue"
},
  "geometry": {"coordinates":[-82.634715,42.809166],"type":"Point"}
}