{
  "type": "Feature",
  "properties": {
    "iso:country":"US",
    "sg:address":"922 W River Center Dr NE",
    "sg:city":"Comstock Park",
    "sg:classifiers":[
        {
            "category":"Wholesale",
            "subcategory":"Machinery & Supplies",
            "type":"Manufacturing & Wholesale Goods"
        }
    ],
    "sg:phone":"+1 616 785 8534",
    "sg:postcode":"49321",
    "sg:province":"MI",
    "sg:tags":[
        "equipment",
        "hydraulic"
    ],
    "sg:website":"www.masondynamics.com",
    "wof:name":"Mason Dynamics",
    "wof:placetype":"venue"
},
  "geometry": {"coordinates":[-85.65066899999999,43.048868],"type":"Point"}
}