{
  "type": "Feature",
  "properties": {
    "iso:country":"US",
    "sg:address":"521 Michigan St",
    "sg:city":"Port Huron",
    "sg:classifiers":[
        {
            "category":"Professional",
            "subcategory":"Lawyer & Legal Services",
            "type":"Services"
        }
    ],
    "sg:phone":"+1 810 984 3030",
    "sg:postcode":"48060",
    "sg:province":"MI",
    "wof:name":"Ladd Robert P Attorney At Law",
    "wof:placetype":"venue"
},
  "geometry": {"coordinates":[-82.42342600000001,42.980169],"type":"Point"}
}