{
  "type": "Feature",
  "properties": {
    "iso:country":"US",
    "sg:address":"18980 Wyoming St",
    "sg:city":"Detroit",
    "sg:classifiers":[
        {
            "category":"Organizations",
            "subcategory":"Religious Organization",
            "type":"Services"
        }
    ],
    "sg:phone":"+1 313 340 1361",
    "sg:postcode":"48221",
    "sg:province":"MI",
    "sg:tags":[
        "church"
    ],
    "wof:name":"Free Reign Fellowship",
    "wof:placetype":"venue"
},
  "geometry": {"coordinates":[-83.160887,42.430632],"type":"Point"}
}