{
  "type": "Feature",
  "properties": {
    "iso:country":"US",
    "sg:address":"6386 Auburn Rd",
    "sg:city":"Utica",
    "sg:classifiers":[
        {
            "category":"Building & Trades",
            "subcategory":"Equipment Rental",
            "type":"Services"
        }
    ],
    "sg:phone":"+1 586 731 0150",
    "sg:postcode":"48317",
    "sg:province":"MI",
    "sg:tags":[
        "heavy",
        "construction"
    ],
    "wof:name":"Utica Equipment Company",
    "wof:placetype":"venue"
},
  "geometry": {"coordinates":[-83.049279,42.629717],"type":"Point"}
}