{
  "type": "Feature",
  "properties": {
    "iso:country":"US",
    "sg:address":"151 W Michigan Ave",
    "sg:city":"Jackson",
    "sg:classifiers":[
        {
            "category":"Restaurant",
            "type":"Food & Drink"
        }
    ],
    "sg:menulink":"http://www.allmenus.com/mi/jackson/280000-daryls-downtown/menu/",
    "sg:phone":"+1 517 782 1895",
    "sg:postcode":"49201",
    "sg:province":"MI",
    "sg:tags":[
        "american"
    ],
    "wof:name":"Daryl's Downtown",
    "wof:placetype":"venue"
},
  "geometry": {"coordinates":[-84.40733,42.247335],"type":"Point"}
}