{
  "type": "Feature",
  "properties": {
    "iso:country":"US",
    "sg:address":"3206 Eastern Ave SE",
    "sg:city":"Grand Rapids",
    "sg:classifiers":[
        {
            "category":"Health Services",
            "subcategory":"Doctor",
            "type":"Services"
        }
    ],
    "sg:phone":"+1 616 475 7922",
    "sg:postcode":"49508",
    "sg:province":"MI",
    "sg:tags":[
        "physician",
        "surgeon",
        "medical"
    ],
    "wof:name":"Behavioral Medicine Clinic",
    "wof:placetype":"venue"
},
  "geometry": {"coordinates":[-85.646542,42.903971],"type":"Point"}
}