{
  "type": "Feature",
  "properties": {
    "iso:country":"US",
    "sg:address":"4430 S Bay Dr",
    "sg:city":"Orchard Lake",
    "sg:classifiers":[
        {
            "category":"Professional",
            "subcategory":"Computer Services",
            "type":"Services"
        }
    ],
    "sg:phone":"+1 248 681 0085",
    "sg:postcode":"48323",
    "sg:province":"MI",
    "sg:tags":[
        "consultant",
        "designer"
    ],
    "wof:name":"R Levin Assoc",
    "wof:placetype":"venue"
},
  "geometry": {"coordinates":[-83.38045700000001,42.573635],"type":"Point"}
}