{
  "type": "Feature",
  "properties": {
    "iso:country":"US",
    "sg:address":"11581 E Prior Rd",
    "sg:city":"Gaines",
    "sg:classifiers":[
        {
            "category":"Farming",
            "subcategory":"Livestock Farm",
            "type":"Manufacturing & Wholesale Goods"
        }
    ],
    "sg:phone":"+1 989 271 9310",
    "sg:postcode":"48436",
    "sg:province":"MI",
    "sg:tags":[
        "beef",
        "equine",
        "feedlot",
        "cattle"
    ],
    "wof:name":"Harry Tinson",
    "wof:placetype":"venue"
},
  "geometry": {"coordinates":[-83.933059,42.882796],"type":"Point"}
}