{
  "type": "Feature",
  "properties": {
    "iso:country":"US",
    "sg:address":"2567 US Hwy 23 N",
    "sg:city":"Alpena",
    "sg:classifiers":[
        {
            "category":"Manufacturing",
            "subcategory":"Printing",
            "type":"Manufacturing & Wholesale Goods"
        }
    ],
    "sg:phone":"+1 989 356 6178",
    "sg:postcode":"49707",
    "sg:province":"MI",
    "sg:tags":[
        "printer"
    ],
    "wof:name":"Alpena Print Master",
    "wof:placetype":"venue"
},
  "geometry": {"coordinates":[-83.45662799999999,45.094413],"type":"Point"}
}