{
  "type": "Feature",
  "properties": {
    "iso:country":"US",
    "sg:address":"16609 Asbury Park",
    "sg:city":"Detroit",
    "sg:classifiers":[
        {
            "category":"Building & Trades",
            "subcategory":"Construction",
            "type":"Services"
        }
    ],
    "sg:phone":"+1 248 632 0054",
    "sg:postcode":"48235",
    "sg:province":"MI",
    "sg:tags":[
        "plastering",
        "contractor"
    ],
    "wof:name":"World's Best Plaster",
    "wof:placetype":"venue"
},
  "geometry": {"coordinates":[-83.208805,42.411316],"type":"Point"}
}