{
  "type": "Feature",
  "properties": {
    "iso:country":"US",
    "sg:address":"33335 Grand River Ave",
    "sg:city":"Farmington",
    "sg:classifiers":[
        {
            "category":"Shopping",
            "subcategory":"Clothing, Apparel, & Fashions",
            "type":"Retail Goods"
        }
    ],
    "sg:phone":"+1 248 888 0628",
    "sg:postcode":"48336",
    "sg:province":"MI",
    "sg:tags":[
        "accessory",
        "clothing",
        "women's"
    ],
    "wof:name":"Shanghai",
    "wof:placetype":"venue"
},
  "geometry": {"coordinates":[-83.375783,42.464481],"type":"Point"}
}