{
  "type": "Feature",
  "properties": {
    "iso:country":"US",
    "sg:address":"311 N Clinton Ave",
    "sg:city":"St Johns",
    "sg:classifiers":[
        {
            "category":"Bars & Pubs",
            "type":"Food & Drink"
        }
    ],
    "sg:phone":"+1 989 224 9443",
    "sg:postcode":"48879",
    "sg:province":"MI",
    "wof:name":"Alibi",
    "wof:placetype":"venue"
},
  "geometry": {"coordinates":[-84.558486,43.004342],"type":"Point"}
}