{
  "type": "Feature",
  "properties": {
    "iso:country":"US",
    "sg:address":"42645 Ford Rd",
    "sg:city":"Canton",
    "sg:classifiers":[
        {
            "category":"Cinema",
            "subcategory":"Movie Rental",
            "type":"Entertainment"
        }
    ],
    "sg:phone":"+1 734 981 1773",
    "sg:postcode":"48187",
    "sg:province":"MI",
    "sg:tags":[
        "game",
        "video"
    ],
    "sg:website":"www.gamestop.com",
    "wof:name":"Gamestop",
    "wof:placetype":"venue"
},
  "geometry": {"coordinates":[-83.46158800000001,42.322377],"type":"Point"}
}