{
  "type": "Feature",
  "properties": {
    "iso:country":"US",
    "sg:address":"45461 Brownell St",
    "sg:city":"Utica",
    "sg:classifiers":[
        {
            "category":"Education",
            "subcategory":"School",
            "type":"Public Place"
        }
    ],
    "sg:phone":"+1 586 797 2900",
    "sg:postcode":"48317",
    "sg:province":"MI",
    "sg:tags":[
        "high",
        "middle",
        "elementary"
    ],
    "wof:name":"Utica Community Schools",
    "wof:placetype":"venue"
},
  "geometry": {"coordinates":[-83.03589599999999,42.629299],"type":"Point"}
}