{
  "type": "Feature",
  "properties": {
    "iso:country":"US",
    "sg:address":"26270 N River Park Dr",
    "sg:city":"Inkster",
    "sg:classifiers":[
        {
            "category":"Recreation",
            "type":"Entertainment"
        }
    ],
    "sg:phone":"+1 313 561 4895",
    "sg:postcode":"48141",
    "sg:province":"MI",
    "sg:tags":[
        "house"
    ],
    "wof:name":"George D Swistock",
    "wof:placetype":"venue"
},
  "geometry": {"coordinates":[-83.297639,42.30215],"type":"Point"}
}