{
  "type": "Feature",
  "properties": {
    "iso:country":"US",
    "sg:address":"3489 N Eastman Rd",
    "sg:city":"Midland",
    "sg:classifiers":[
        {
            "category":"Organizations",
            "subcategory":"Religious Organization",
            "type":"Services"
        }
    ],
    "sg:phone":"+1 989 837 2856",
    "sg:postcode":"48642",
    "sg:province":"MI",
    "sg:tags":[
        "church"
    ],
    "wof:name":"Lord Of New Life Lutheran",
    "wof:placetype":"venue"
},
  "geometry": {"coordinates":[-84.24707600000001,43.705444],"type":"Point"}
}