{
  "type": "Feature",
  "properties": {
    "iso:country":"US",
    "sg:address":"1169 S Miller Rd",
    "sg:city":"Saginaw",
    "sg:classifiers":[
        {
            "category":"Manufacturing",
            "subcategory":"Metals",
            "type":"Manufacturing & Wholesale Goods"
        }
    ],
    "sg:phone":"+1 989 781 2931",
    "sg:postcode":"48609",
    "sg:province":"MI",
    "sg:tags":[
        "equipment",
        "heating",
        "mfg"
    ],
    "wof:name":"Advanced Biomass Systems Inc",
    "wof:placetype":"venue"
},
  "geometry": {"coordinates":[-84.071575,43.404007],"type":"Point"}
}