{
  "type": "Feature",
  "properties": {
    "iso:country":"US",
    "sg:address":"28 W Chicago St",
    "sg:city":"Coldwater",
    "sg:classifiers":[
        {
            "category":"Government",
            "subcategory":"Office",
            "type":"Public Place"
        }
    ],
    "sg:phone":"+1 517 278 8324",
    "sg:postcode":"49036",
    "sg:province":"MI",
    "sg:tags":[
        "village"
    ],
    "wof:name":"Downtown Development Authority",
    "wof:placetype":"venue"
},
  "geometry": {"coordinates":[-85.002008,41.940894],"type":"Point"}
}