{
  "type": "Feature",
  "properties": {
    "iso:country":"US",
    "sg:address":"224 Trowbridge St",
    "sg:city":"Allegan",
    "sg:classifiers":[
        {
            "category":"Manufacturing",
            "subcategory":"Wood Products",
            "type":"Manufacturing & Wholesale Goods"
        }
    ],
    "sg:phone":"+1 269 686 0001",
    "sg:postcode":"49010",
    "sg:province":"MI",
    "sg:tags":[
        "mfg"
    ],
    "wof:name":"Superior Frames",
    "wof:placetype":"venue"
},
  "geometry": {"coordinates":[-85.85253,42.528929],"type":"Point"}
}