{
  "type": "Feature",
  "properties": {
    "iso:country":"US",
    "sg:address":"3162 Cedar Creek Dr SW",
    "sg:city":"Grandville",
    "sg:classifiers":[
        {
            "category":"Retail",
            "subcategory":"Portrait Studio",
            "type":"Services"
        }
    ],
    "sg:phone":"+1 616 531 4514",
    "sg:postcode":"49418",
    "sg:province":"MI",
    "sg:tags":[
        "photo"
    ],
    "wof:name":"Lehmann Photography",
    "wof:placetype":"venue"
},
  "geometry": {"coordinates":[-85.743242,42.897895],"type":"Point"}
}