{
  "type": "Feature",
  "properties": {
    "iso:country":"US",
    "sg:address":"263 Walnut St",
    "sg:city":"Frankenmuth",
    "sg:classifiers":[
        {
            "category":"Organizations",
            "subcategory":"Community Association",
            "type":"Services"
        }
    ],
    "sg:phone":"+1 989 652 8063",
    "sg:postcode":"48734",
    "sg:province":"MI",
    "wof:name":"American Legion Aux",
    "wof:placetype":"venue"
},
  "geometry": {"coordinates":[-83.735945,43.320631],"type":"Point"}
}