{
  "type": "Feature",
  "properties": {
    "iso:country":"US",
    "sg:address":"8290 W C Ave",
    "sg:city":"Kalamazoo",
    "sg:classifiers":[
        {
            "category":"Health Services",
            "subcategory":"Nursing And Care Facility",
            "type":"Services"
        }
    ],
    "sg:phone":"+1 269 343 2587",
    "sg:postcode":"49009",
    "sg:province":"MI",
    "sg:tags":[
        "home"
    ],
    "wof:name":"Alamo Nursing Home Inc",
    "wof:placetype":"venue"
},
  "geometry": {"coordinates":[-85.71471,42.389661],"type":"Point"}
}