{
  "type": "Feature",
  "properties": {
    "iso:country":"US",
    "sg:address":"2540 Lapeer Rd",
    "sg:city":"Port Huron",
    "sg:classifiers":[
        {
            "category":"Manufacturing",
            "subcategory":"Printing",
            "type":"Manufacturing & Wholesale Goods"
        }
    ],
    "sg:phone":"+1 810 982 0360",
    "sg:postcode":"48060",
    "sg:province":"MI",
    "sg:tags":[
        "printer"
    ],
    "wof:name":"Precision Printing",
    "wof:placetype":"venue"
},
  "geometry": {"coordinates":[-82.45751,42.978231],"type":"Point"}
}