{
  "type": "Feature",
  "properties": {
    "iso:country":"US",
    "sg:address":"36568 Boyce Dr",
    "sg:city":"Clinton Twp",
    "sg:classifiers":[
        {
            "category":"Manufacturing",
            "subcategory":"Watercraft",
            "type":"Manufacturing & Wholesale Goods"
        }
    ],
    "sg:phone":"+1 586 790 2678",
    "sg:postcode":"48035",
    "sg:province":"MI",
    "sg:tags":[
        "rebuilt",
        "part",
        "boat"
    ],
    "wof:name":"Louis M Tisch Inc",
    "wof:placetype":"venue"
},
  "geometry": {"coordinates":[-82.9263,42.567444],"type":"Point"}
}