{
  "type": "Feature",
  "properties": {
    "iso:country":"US",
    "sg:address":"8950 Telegraph Rd",
    "sg:city":"Taylor",
    "sg:classifiers":[
        {
            "category":"Health Services",
            "subcategory":"Optometrist",
            "type":"Services"
        }
    ],
    "sg:phone":"+1 313 295 3937",
    "sg:postcode":"48180",
    "sg:province":"MI",
    "sg:tags":[
        "ophthalmologist"
    ],
    "wof:name":"Downriver Eye Center",
    "wof:placetype":"venue"
},
  "geometry": {"coordinates":[-83.264,42.243],"type":"Point"}
}