{
  "type": "Feature",
  "properties": {
    "iso:country":"US",
    "sg:address":"440 Beeline Rd",
    "sg:city":"Holland",
    "sg:classifiers":[
        {
            "category":"Retail",
            "subcategory":"Repair Shop",
            "type":"Services"
        }
    ],
    "sg:phone":"+1 616 396 7851",
    "sg:postcode":"49424",
    "sg:province":"MI",
    "sg:tags":[
        "upholsterer"
    ],
    "wof:name":"D J's Upholstery",
    "wof:placetype":"venue"
},
  "geometry": {"coordinates":[-86.10292699999999,42.811539],"type":"Point"}
}