{
  "type": "Feature",
  "properties": {
    "iso:country":"US",
    "sg:address":"1455 Forest Hill Ave SE",
    "sg:city":"Grand Rapids",
    "sg:classifiers":[
        {
            "category":"Professional",
            "subcategory":"Business Services",
            "type":"Services"
        }
    ],
    "sg:phone":"+1 616 942 5742",
    "sg:postcode":"49546",
    "sg:province":"MI",
    "sg:tags":[
        "translator",
        "interpreter"
    ],
    "wof:name":"Translations Unlimited",
    "wof:placetype":"venue"
},
  "geometry": {"coordinates":[-85.555612,42.938946],"type":"Point"}
}