{
  "type": "Feature",
  "properties": {
    "iso:country":"US",
    "sg:address":"340 E Lansing Rd",
    "sg:city":"East Lansing",
    "sg:classifiers":[
        {
            "category":"Education",
            "subcategory":"College",
            "type":"Public Place"
        }
    ],
    "sg:phone":"+1 517 355 5115",
    "sg:postcode":"48857",
    "sg:province":"MI",
    "sg:tags":[
        "university"
    ],
    "wof:name":"Office of Planning and Budget",
    "wof:placetype":"venue"
},
  "geometry": {"coordinates":[-84.157545,42.852078],"type":"Point"}
}