{
  "type": "Feature",
  "properties": {
    "iso:country":"US",
    "sg:address":"1034 N Homer St",
    "sg:city":"Lansing",
    "sg:classifiers":[
        {
            "category":"Social Services",
            "type":"Services"
        }
    ],
    "sg:phone":"+1 517 482 2085",
    "sg:postcode":"48912",
    "sg:province":"MI",
    "sg:tags":[
        "information",
        "abuse",
        "treatment",
        "center"
    ],
    "wof:name":"Sex Abuse Treatment Alliance",
    "wof:placetype":"venue"
},
  "geometry": {"coordinates":[-84.509435,42.74521],"type":"Point"}
}