{
  "type": "Feature",
  "properties": {
    "iso:country":"US",
    "sg:address":"14164 Poplar St",
    "sg:city":"Southgate",
    "sg:classifiers":[
        {
            "category":"Professional",
            "subcategory":"Management & Consulting",
            "type":"Services"
        }
    ],
    "sg:phone":"+1 734 284 2384",
    "sg:postcode":"48195",
    "sg:province":"MI",
    "wof:name":"Exhibit Management Inc",
    "wof:placetype":"venue"
},
  "geometry": {"coordinates":[-83.20109100000001,42.20434],"type":"Point"}
}