{
  "type": "Feature",
  "properties": {
    "iso:country":"US",
    "sg:address":"4729 Conner St",
    "sg:city":"Detroit",
    "sg:classifiers":[
        {
            "category":"Professional",
            "subcategory":"Employment Agencies",
            "type":"Services"
        }
    ],
    "sg:phone":"+1 313 822 9500",
    "sg:postcode":"48215",
    "sg:province":"MI",
    "wof:name":"Michigan Emplymnt Secrty Agncy",
    "wof:placetype":"venue"
},
  "geometry": {"coordinates":[-82.97281,42.387984],"type":"Point"}
}