{
  "type": "Feature",
  "properties": {
    "iso:country":"US",
    "sg:address":"423 Walbridge St",
    "sg:city":"Kalamazoo",
    "sg:classifiers":[
        {
            "category":"Manufacturing",
            "subcategory":"Metals",
            "type":"Manufacturing & Wholesale Goods"
        }
    ],
    "sg:phone":"+1 269 552 4999",
    "sg:postcode":"49007",
    "sg:province":"MI",
    "sg:tags":[
        "plating"
    ],
    "wof:name":"Lawrence Industries Inc",
    "wof:placetype":"venue"
},
  "geometry": {"coordinates":[-85.57664800000001,42.294985],"type":"Point"}
}