{
  "type": "Feature",
  "properties": {
    "iso:country":"US",
    "sg:address":"9188 Riverdale",
    "sg:city":"Redford",
    "sg:classifiers":[
        {
            "category":"Social Services",
            "subcategory":"Adult Care",
            "type":"Services"
        }
    ],
    "sg:phone":"+1 313 537 9058",
    "sg:postcode":"48239",
    "sg:province":"MI",
    "sg:tags":[
        "residential"
    ],
    "wof:name":"Home Lifestyle",
    "wof:placetype":"venue"
},
  "geometry": {"coordinates":[-83.268914,42.360156],"type":"Point"}
}