{
  "type": "Feature",
  "properties": {
    "iso:country":"US",
    "sg:address":"1408 8th Ave S",
    "sg:city":"Escanaba",
    "sg:classifiers":[
        {
            "category":"Food & Beverages",
            "subcategory":"Groceries & Convenience Stores",
            "type":"Retail Goods"
        }
    ],
    "sg:phone":"+1 906 786 2055",
    "sg:postcode":"49829",
    "sg:province":"MI",
    "sg:tags":[
        "grocer"
    ],
    "wof:name":"Gary's South Side",
    "wof:placetype":"venue"
},
  "geometry": {"coordinates":[-87.067194,45.736316],"type":"Point"}
}