{
  "type": "Feature",
  "properties": {
    "iso:country":"US",
    "sg:address":"1069 Novi Rd",
    "sg:city":"Northville",
    "sg:classifiers":[
        {
            "category":"Retail",
            "subcategory":"Self-service Laundry",
            "type":"Services"
        }
    ],
    "sg:phone":"+1 248 349 8120",
    "sg:postcode":"48167",
    "sg:province":"MI",
    "sg:tags":[
        "coin"
    ],
    "wof:name":"Novi Road Coin Laundry",
    "wof:placetype":"venue"
},
  "geometry": {"coordinates":[-83.474307,42.442031],"type":"Point"}
}