{
  "type": "Feature",
  "properties": {
    "iso:country":"US",
    "sg:address":"2295 Sower Blvd",
    "sg:city":"Okemos",
    "sg:classifiers":[
        {
            "category":"Professional",
            "subcategory":"Lawyer & Legal Services",
            "type":"Services"
        }
    ],
    "sg:phone":"+1 517 349 0000",
    "sg:postcode":"48864",
    "sg:province":"MI",
    "wof:name":"Pratt Paul C",
    "wof:placetype":"venue"
},
  "geometry": {"coordinates":[-84.434107,42.702454],"type":"Point"}
}