{
  "type": "Feature",
  "properties": {
    "iso:country":"US",
    "sg:address":"12663 S Marina Village Dr",
    "sg:city":"Traverse City",
    "sg:classifiers":[
        {
            "category":"Real Estate",
            "subcategory":"Real Estate Operator",
            "type":"Services"
        }
    ],
    "sg:phone":"+1 231 922 0069",
    "sg:postcode":"49684",
    "sg:province":"MI",
    "sg:tags":[
        "condominium"
    ],
    "wof:name":"Harbor West Marina Village",
    "wof:placetype":"venue"
},
  "geometry": {"coordinates":[-85.635272,44.792896],"type":"Point"}
}