{
  "type": "Feature",
  "properties": {
    "iso:country":"US",
    "sg:address":"5725 Delphi Dr",
    "sg:city":"Troy",
    "sg:classifiers":[
        {
            "category":"Professional",
            "subcategory":"Accounting & Tax Preparation",
            "type":"Services"
        }
    ],
    "sg:phone":"+1 248 879 2587",
    "sg:postcode":"48098",
    "sg:province":"MI",
    "sg:tags":[
        "accountant"
    ],
    "wof:name":"Deloitte",
    "wof:placetype":"venue"
},
  "geometry": {"coordinates":[-83.162958,42.606057],"type":"Point"}
}