{
  "type": "Feature",
  "properties": {
    "iso:country":"US",
    "sg:address":"2275 State Hwy 139",
    "sg:city":"Benton Harbor",
    "sg:classifiers":[
        {
            "category":"Manufacturing",
            "subcategory":"Apparel",
            "type":"Manufacturing & Wholesale Goods"
        }
    ],
    "sg:phone":"+1 269 925 2187",
    "sg:postcode":"49022",
    "sg:province":"MI",
    "sg:tags":[
        "canvas",
        "product",
        "related"
    ],
    "sg:website":"www.bhawning.com",
    "wof:name":"B H Awning & Tent Co",
    "wof:placetype":"venue"
},
  "geometry": {"coordinates":[-86.436494,42.079111],"type":"Point"}
}