{
  "type": "Feature",
  "properties": {
    "iso:country":"US",
    "sg:address":"41451 Irwin Dr",
    "sg:city":"Harrison Twp",
    "sg:classifiers":[
        {
            "category":"Retail",
            "subcategory":"Auto Repair",
            "type":"Services"
        }
    ],
    "sg:phone":"+1 586 463 5829",
    "sg:postcode":"48045",
    "sg:province":"MI",
    "sg:tags":[
        "repairing",
        "cylinder"
    ],
    "sg:website":"www.sarnsindustries.com",
    "wof:name":"Sarns Machine",
    "wof:placetype":"venue"
},
  "geometry": {"coordinates":[-82.85188599999999,42.601744],"type":"Point"}
}