{
  "type": "Feature",
  "properties": {
    "iso:country":"US",
    "sg:address":"1125 Bus Park Dr",
    "sg:city":"Traverse City",
    "sg:classifiers":[
        {
            "category":"Building & Trades",
            "subcategory":"Construction",
            "type":"Services"
        }
    ],
    "sg:phone":"+1 231 947 7951",
    "sg:postcode":"49686",
    "sg:province":"MI",
    "sg:tags":[
        "contractor"
    ],
    "wof:name":"Peninsula Construction & Supl",
    "wof:placetype":"venue"
},
  "geometry": {"coordinates":[-85.556794,44.743539],"type":"Point"}
}