{
  "type": "Feature",
  "properties": {
    "iso:country":"US",
    "sg:address":"665 136th Ave",
    "sg:city":"Holland",
    "sg:classifiers":[
        {
            "category":"Building & Trades",
            "subcategory":"Construction",
            "type":"Services"
        }
    ],
    "sg:phone":"+1 616 399 6863",
    "sg:postcode":"49424",
    "sg:province":"MI",
    "sg:tags":[
        "home",
        "builder"
    ],
    "sg:website":"www.pinecreekconstruction.com",
    "wof:name":"Pine Creek Construction Inc",
    "wof:placetype":"venue"
},
  "geometry": {"coordinates":[-86.117479,42.818833],"type":"Point"}
}