{
  "type": "Feature",
  "properties": {
    "iso:country":"US",
    "sg:address":"22101 Moross Rd",
    "sg:city":"Detroit",
    "sg:classifiers":[
        {
            "category":"Community Center",
            "type":"Public Place"
        }
    ],
    "sg:phone":"+1 313 417 2900",
    "sg:postcode":"48236",
    "sg:province":"MI",
    "sg:tags":[
        "medical"
    ],
    "wof:name":"Fresenius Medical Care East District",
    "wof:placetype":"venue"
},
  "geometry": {"coordinates":[-82.914948,42.419136],"type":"Point"}
}