{
  "type": "Feature",
  "properties": {
    "iso:country":"US",
    "sg:address":"1027 Owana Ave",
    "sg:city":"Royal Oak",
    "sg:classifiers":[
        {
            "category":"Personal",
            "subcategory":"Barber",
            "type":"Services"
        }
    ],
    "sg:phone":"+1 248 545 8015",
    "sg:postcode":"48067",
    "sg:province":"MI",
    "sg:tags":[
        "shop"
    ],
    "wof:name":"Assoc Master Barbers & Be",
    "wof:placetype":"venue"
},
  "geometry": {"coordinates":[-83.128332,42.48254],"type":"Point"}
}