{
  "type": "Feature",
  "properties": {
    "iso:country":"US",
    "sg:address":"843 S Telegraph Rd",
    "sg:city":"Monroe",
    "sg:classifiers":[
        {
            "category":"Shopping",
            "type":"Retail Goods"
        }
    ],
    "sg:phone":"+1 734 242 2033",
    "sg:postcode":"48161",
    "sg:province":"MI",
    "sg:tags":[
        "ice"
    ],
    "wof:name":"Arctic Ice & Refrigeration",
    "wof:placetype":"venue"
},
  "geometry": {"coordinates":[-83.42043099999999,41.912438],"type":"Point"}
}