{
  "type": "Feature",
  "properties": {
    "iso:country":"US",
    "sg:address":"322 N Orient St",
    "sg:city":"Kalamazoo",
    "sg:classifiers":[
        {
            "category":"Building & Trades",
            "subcategory":"Construction",
            "type":"Services"
        }
    ],
    "sg:phone":"+1 269 343 9097",
    "sg:postcode":"49004",
    "sg:province":"MI",
    "sg:tags":[
        "steel",
        "fabrication",
        "welding"
    ],
    "wof:name":"West Shore Fab & Precision",
    "wof:placetype":"venue"
},
  "geometry": {"coordinates":[-85.561055,42.33055],"type":"Point"}
}