{
  "type": "Feature",
  "properties": {
    "iso:country":"US",
    "sg:address":"2400 W Grand River Ave",
    "sg:city":"Howell",
    "sg:classifiers":[
        {
            "category":"Food & Beverages",
            "subcategory":"Groceries & Convenience Stores",
            "type":"Retail Goods"
        }
    ],
    "sg:phone":"+1 517 548 3065",
    "sg:postcode":"48843",
    "sg:province":"MI",
    "sg:tags":[
        "grocer"
    ],
    "wof:name":"V G's Food Ctr & Pharmacy",
    "wof:placetype":"venue"
},
  "geometry": {"coordinates":[-83.96162099999999,42.615178],"type":"Point"}
}