{
  "type": "Feature",
  "properties": {
    "iso:country":"US",
    "sg:address":"5605 Glenn Ave",
    "sg:city":"Flint",
    "sg:classifiers":[
        {
            "category":"Shopping",
            "subcategory":"Crafts & Fabrics",
            "type":"Retail Goods"
        }
    ],
    "sg:phone":"+1 810 785 6425",
    "sg:postcode":"48505",
    "sg:province":"MI",
    "sg:tags":[
        "sewing"
    ],
    "wof:name":"Sew N Go",
    "wof:placetype":"venue"
},
  "geometry": {"coordinates":[-83.71738000000001,43.067095],"type":"Point"}
}