{
  "type": "Feature",
  "properties": {
    "iso:country":"US",
    "sg:address":"620 S Lake St",
    "sg:city":"Marquette",
    "sg:classifiers":[
        {
            "category":"Insurance",
            "subcategory":"Insurance Agent",
            "type":"Services"
        }
    ],
    "sg:phone":"+1 906 228 6255",
    "sg:postcode":"49855",
    "sg:province":"MI",
    "wof:name":"Employee Benefits Agency Inc",
    "wof:placetype":"venue"
},
  "geometry": {"coordinates":[-87.390111,46.524564],"type":"Point"}
}