{
  "type": "Feature",
  "properties": {
    "iso:country":"US",
    "sg:address":"311 N Harrison St",
    "sg:city":"Ludington",
    "sg:classifiers":[
        {
            "category":"Building & Trades",
            "subcategory":"Construction",
            "type":"Services"
        }
    ],
    "sg:phone":"+1 231 845 0307",
    "sg:postcode":"49431",
    "sg:province":"MI",
    "sg:tags":[
        "carpentry",
        "contractor"
    ],
    "wof:name":"C W Vinyl Restoration",
    "wof:placetype":"venue"
},
  "geometry": {"coordinates":[-86.446556,43.959505],"type":"Point"}
}