{
  "type": "Feature",
  "properties": {
    "iso:country":"US",
    "sg:address":"1206 Ludington St",
    "sg:city":"Escanaba",
    "sg:classifiers":[
        {
            "category":"Shopping",
            "subcategory":"Clothing, Apparel, & Fashions",
            "type":"Retail Goods"
        }
    ],
    "sg:phone":"+1 906 789 9796",
    "sg:postcode":"49829",
    "sg:province":"MI",
    "sg:tags":[
        "shop",
        "bridal"
    ],
    "wof:name":"Beautiful Beginnings Bridal",
    "wof:placetype":"venue"
},
  "geometry": {"coordinates":[-87.065583,45.745835],"type":"Point"}
}