{
  "type": "Feature",
  "properties": {
    "iso:country":"US",
    "sg:address":"1818 Star-Batt Dr",
    "sg:city":"Rochester Hills",
    "sg:classifiers":[
        {
            "category":"Retail",
            "subcategory":"Auto Repair",
            "type":"Services"
        }
    ],
    "sg:phone":"+1 248 852 5755",
    "sg:postcode":"48309",
    "sg:province":"MI",
    "sg:tags":[
        "body",
        "automobile",
        "painting"
    ],
    "wof:name":"Gignac's Collision",
    "wof:placetype":"venue"
},
  "geometry": {"coordinates":[-83.166974,42.647621],"type":"Point"}
}