{
  "type": "Feature",
  "properties": {
    "iso:country":"US",
    "sg:address":"1921 25 Mile Rd",
    "sg:city":"Utica",
    "sg:classifiers":[
        {
            "category":"Restaurant",
            "type":"Food & Drink"
        }
    ],
    "sg:menulink":"http://www.allmenus.com/mi/shelby/58073-king-wok/menu/",
    "sg:phone":"+1 248 601 8989",
    "sg:postcode":"48316",
    "sg:province":"MI",
    "sg:tags":[
        "asian",
        "chinese"
    ],
    "wof:name":"King Wok",
    "wof:placetype":"venue"
},
  "geometry": {"coordinates":[-83.093546,42.697003],"type":"Point"}
}