{
  "type": "Feature",
  "properties": {
    "iso:country":"US",
    "sg:address":"529 E Cedar St",
    "sg:city":"Standish",
    "sg:classifiers":[
        {
            "category":"Health Services",
            "subcategory":"Doctor",
            "type":"Services"
        }
    ],
    "sg:phone":"+1 989 846 9533",
    "sg:postcode":"48658",
    "sg:province":"MI",
    "sg:tags":[
        "physician",
        "surgeon"
    ],
    "wof:name":"J V Bashir MD",
    "wof:placetype":"venue"
},
  "geometry": {"coordinates":[-83.954228,43.982742],"type":"Point"}
}