{
  "type": "Feature",
  "properties": {
    "iso:country":"US",
    "sg:address":"3350 Gratiot Blvd",
    "sg:city":"Marysville",
    "sg:classifiers":[
        {
            "category":"Health Services",
            "subcategory":"Doctor",
            "type":"Services"
        }
    ],
    "sg:phone":"+1 810 364 4000",
    "sg:postcode":"48040",
    "sg:province":"MI",
    "sg:tags":[
        "physician",
        "surgeon"
    ],
    "wof:name":"Physicians Health Care",
    "wof:placetype":"venue"
},
  "geometry": {"coordinates":[-82.497711,42.910669],"type":"Point"}
}