{
  "type": "Feature",
  "properties": {
    "iso:country":"US",
    "sg:address":"514 Adams St",
    "sg:city":"Bay City",
    "sg:classifiers":[
        {
            "category":"Professional",
            "subcategory":"Lawyer & Legal Services",
            "type":"Services"
        }
    ],
    "sg:phone":"+1 989 893 9678",
    "sg:postcode":"48708",
    "sg:province":"MI",
    "sg:tags":[
        "attorney"
    ],
    "wof:name":"Mc Donough & Mc Donough",
    "wof:placetype":"venue"
},
  "geometry": {"coordinates":[-83.886931,43.595772],"type":"Point"}
}