{
  "type": "Feature",
  "properties": {
    "iso:country":"US",
    "sg:address":"1151 Billings Ct",
    "sg:city":"Grand Rapids",
    "sg:classifiers":[
        {
            "category":"Shopping",
            "subcategory":"Catalog Store",
            "type":"Retail Goods"
        }
    ],
    "sg:phone":"+1 616 656 0768",
    "sg:postcode":"49508",
    "sg:province":"MI",
    "sg:tags":[
        "mail",
        "house"
    ],
    "wof:name":"Gb Ventures",
    "wof:placetype":"venue"
},
  "geometry": {"coordinates":[-85.637066,42.849609],"type":"Point"}
}