{
  "type": "Feature",
  "properties": {
    "iso:country":"US",
    "sg:address":"210 W Carleton Rd",
    "sg:city":"Hillsdale",
    "sg:classifiers":[
        {
            "category":"Utilities",
            "subcategory":"Mobile Phone",
            "type":"Services"
        }
    ],
    "sg:phone":"+1 517 437 7577",
    "sg:postcode":"49242",
    "sg:province":"MI",
    "sg:tags":[
        "telephone",
        "cellular"
    ],
    "wof:name":"Centennial Wireless",
    "wof:placetype":"venue"
},
  "geometry": {"coordinates":[-84.641504,41.933462],"type":"Point"}
}