{
  "type": "Feature",
  "properties": {
    "iso:country":"US",
    "sg:address":"7060 N 42nd St",
    "sg:city":"Augusta",
    "sg:classifiers":[
        {
            "category":"Professional",
            "subcategory":"Research",
            "type":"Services"
        }
    ],
    "sg:phone":"+1 269 731 4597",
    "sg:postcode":"49012",
    "sg:province":"MI",
    "wof:name":"W K Kellogg Exp Forest",
    "wof:placetype":"venue"
},
  "geometry": {"coordinates":[-85.35607299999999,42.365466],"type":"Point"}
}