{
  "type": "Feature",
  "properties": {
    "iso:country":"US",
    "sg:address":"6829 Longworth Dr",
    "sg:city":"Waterford",
    "sg:classifiers":[
        {
            "category":"Professional",
            "subcategory":"Accounting & Tax Preparation",
            "type":"Services"
        }
    ],
    "sg:phone":"+1 248 623 0009",
    "sg:postcode":"48329",
    "sg:province":"MI",
    "sg:tags":[
        "return"
    ],
    "wof:name":"Income Tax By ME",
    "wof:placetype":"venue"
},
  "geometry": {"coordinates":[-83.42319999999999,42.692031],"type":"Point"}
}