{
  "type": "Feature",
  "properties": {
    "iso:country":"US",
    "sg:address":"6345 Dixie Hwy",
    "sg:city":"Bridgeport",
    "sg:classifiers":[
        {
            "category":"Restaurant",
            "type":"Food & Drink"
        }
    ],
    "sg:menulink":"http://www.allmenus.com/mi/bridgeport/208717-taco-bell/menu/",
    "sg:phone":"+1 989 777 1511",
    "sg:postcode":"48722",
    "sg:province":"MI",
    "sg:tags":[
        "mexican"
    ],
    "wof:name":"Taco Bell",
    "wof:placetype":"venue"
},
  "geometry": {"coordinates":[-83.871764,43.354042],"type":"Point"}
}