{
  "type": "Feature",
  "properties": {
    "iso:country":"US",
    "sg:address":"228 N Main St",
    "sg:city":"Romeo",
    "sg:classifiers":[
        {
            "category":"Social Services",
            "type":"Services"
        }
    ],
    "sg:phone":"+1 586 336 0910",
    "sg:postcode":"48065",
    "sg:province":"MI",
    "sg:tags":[
        "professional",
        "counselor"
    ],
    "wof:name":"Orchard Hills Counseling Ctr",
    "wof:placetype":"venue"
},
  "geometry": {"coordinates":[-83.013301,42.803511],"type":"Point"}
}