{
  "type": "Feature",
  "properties": {
    "iso:country":"US",
    "sg:address":"8513 N Inkster Rd",
    "sg:city":"Westland",
    "sg:classifiers":[
        {
            "category":"Home & Garden",
            "subcategory":"Garden Supply",
            "type":"Retail Goods"
        }
    ],
    "sg:phone":"+1 734 427 6444",
    "sg:postcode":"48185",
    "sg:province":"MI",
    "sg:tags":[
        "nursery",
        "gardening"
    ],
    "wof:name":"Dave's Engine & Mower Shop",
    "wof:placetype":"venue"
},
  "geometry": {"coordinates":[-83.312798,42.3522],"type":"Point"}
}