{
  "type": "Feature",
  "properties": {
    "iso:country":"US",
    "sg:address":"844 Pyle Dr",
    "sg:city":"Kingsford",
    "sg:classifiers":[
        {
            "category":"Health Services",
            "subcategory":"Doctor",
            "type":"Services"
        }
    ],
    "sg:phone":"+1 906 774 6383",
    "sg:postcode":"49802",
    "sg:province":"MI",
    "sg:tags":[
        "clinic"
    ],
    "wof:name":"Family Practice Clinic",
    "wof:placetype":"venue"
},
  "geometry": {"coordinates":[-88.07976499999999,45.804192],"type":"Point"}
}