{
  "type": "Feature",
  "properties": {
    "iso:country":"US",
    "sg:address":"1253 Ramona St SE",
    "sg:city":"Grand Rapids",
    "sg:classifiers":[
        {
            "category":"Organizations",
            "subcategory":"Religious Organization",
            "type":"Services"
        }
    ],
    "sg:phone":"+1 616 245 2922",
    "sg:postcode":"49507",
    "sg:province":"MI",
    "sg:tags":[
        "church"
    ],
    "sg:website":"www.morningstarcogic.com",
    "wof:name":"Morningstar Church Of God",
    "wof:placetype":"venue"
},
  "geometry": {"coordinates":[-85.636162,42.935927],"type":"Point"}
}