{
  "type": "Feature",
  "properties": {
    "iso:country":"US",
    "sg:address":"6059 Red Arrow Hwy",
    "sg:city":"Stevensville",
    "sg:classifiers":[
        {
            "category":"Shopping",
            "subcategory":"Discount & Variety Stores",
            "type":"Retail Goods"
        }
    ],
    "sg:phone":"+1 269 408 1418",
    "sg:postcode":"49127",
    "sg:province":"MI",
    "sg:tags":[
        "merchandise",
        "general"
    ],
    "wof:name":"Hometown Dollar",
    "wof:placetype":"venue"
},
  "geometry": {"coordinates":[-86.530136,42.009113],"type":"Point"}
}