{
  "type": "Feature",
  "properties": {
    "iso:country":"US",
    "sg:address":"585 E North St",
    "sg:city":"Owosso",
    "sg:classifiers":[
        {
            "category":"Social Services",
            "subcategory":"Child Care",
            "type":"Services"
        },
        {
            "category":"Organizations",
            "subcategory":"Religious Organization",
            "type":"Services"
        }
    ],
    "sg:phone":"+1 989 725 5039",
    "sg:postcode":"48867",
    "sg:province":"MI",
    "sg:tags":[
        "kindergarten",
        "academic",
        "school"
    ],
    "wof:name":"First Church Of Christ Preschl",
    "wof:placetype":"venue"
},
  "geometry": {"coordinates":[-84.16387,43.01222],"type":"Point"}
}