{
  "type": "Feature",
  "properties": {
    "iso:country":"US",
    "sg:address":"6466 N Loomis Rd",
    "sg:city":"Coleman",
    "sg:phone":"+1 989 465 1425",
    "sg:postcode":"48618",
    "sg:province":"MI",
    "sg:tags":[
        "beef",
        "farm",
        "corn",
        "soybean",
        "cattle",
        "feedlot"
    ],
    "wof:name":"Wayne Callison",
    "wof:placetype":"venue"
},
  "geometry": {"coordinates":[-84.667216,43.730109],"type":"Point"}
}