{
  "type": "Feature",
  "properties": {
    "iso:country":"US",
    "sg:address":"8546 S Vandecar Rd",
    "sg:city":"Shepherd",
    "sg:classifiers":[
        {
            "category":"Building & Trades",
            "subcategory":"Construction",
            "type":"Services"
        }
    ],
    "sg:phone":"+1 989 866 8270",
    "sg:postcode":"48883",
    "sg:province":"MI",
    "sg:tags":[
        "builder",
        "deck"
    ],
    "wof:name":"Custom Deck & Fence",
    "wof:placetype":"venue"
},
  "geometry": {"coordinates":[-84.88583800000001,43.517152],"type":"Point"}
}