{
  "type": "Feature",
  "properties": {
    "iso:country":"US",
    "sg:address":"3715 S Williams Rd",
    "sg:city":"Leslie",
    "sg:classifiers":[
        {
            "category":"Government",
            "subcategory":"Office",
            "type":"Public Place"
        }
    ],
    "sg:phone":"+1 517 589 3418",
    "sg:postcode":"49251",
    "sg:province":"MI",
    "sg:tags":[
        "village"
    ],
    "wof:name":"Bunkerhill Twp Office",
    "wof:placetype":"venue"
},
  "geometry": {"coordinates":[-84.326697,42.477695],"type":"Point"}
}