{
  "type": "Feature",
  "properties": {
    "iso:country":"US",
    "sg:address":"365 E Edmund Ave",
    "sg:city":"Madison Heights",
    "sg:classifiers":[
        {
            "category":"Real Estate",
            "subcategory":"Real Estate Operator",
            "type":"Services"
        }
    ],
    "sg:phone":"+1 248 588 5558",
    "sg:postcode":"48071",
    "sg:province":"MI",
    "sg:tags":[
        "apartment"
    ],
    "wof:name":"Oakland Mall Apartments",
    "wof:placetype":"venue"
},
  "geometry": {"coordinates":[-83.103104,42.524799],"type":"Point"}
}