{
  "type": "Feature",
  "properties": {
    "iso:country":"US",
    "sg:address":"100 Sherman St",
    "sg:city":"Fennville",
    "sg:classifiers":[
        {
            "category":"Manufacturing",
            "subcategory":"Food",
            "type":"Manufacturing & Wholesale Goods"
        }
    ],
    "sg:phone":"+1 269 561 8211",
    "sg:postcode":"49408",
    "sg:province":"MI",
    "sg:tags":[
        "canning"
    ],
    "sg:website":"www.birdseyefoods.com",
    "wof:name":"Birds Eye Foods Inc",
    "wof:placetype":"venue"
},
  "geometry": {"coordinates":[-86.102036,42.593354],"type":"Point"}
}