{
  "type": "Feature",
  "properties": {
    "iso:country":"US",
    "sg:address":"180 Colony Dr S",
    "sg:city":"Saginaw",
    "sg:classifiers":[
        {
            "category":"Government",
            "subcategory":"Office",
            "type":"Public Place"
        }
    ],
    "sg:phone":"+1 989 790 3289",
    "sg:postcode":"48638",
    "sg:province":"MI",
    "wof:name":"Saginaw County Senior Ctr",
    "wof:placetype":"venue"
},
  "geometry": {"coordinates":[-84.01987,43.414109],"type":"Point"}
}