{
  "type": "Feature",
  "properties": {
    "iso:country":"US",
    "sg:address":"35 Warner Rd",
    "sg:city":"Grosse Pointe",
    "sg:classifiers":[
        {
            "category":"Real Estate",
            "subcategory":"Real Estate Agent",
            "type":"Services"
        }
    ],
    "sg:phone":"+1 313 882 2140",
    "sg:postcode":"48236",
    "sg:province":"MI",
    "wof:name":"Germack Family Partnership",
    "wof:placetype":"venue"
},
  "geometry": {"coordinates":[-82.89595,42.39097],"type":"Point"}
}