{
  "type": "Feature",
  "properties": {
    "iso:country":"US",
    "sg:address":"3611 Butternut Dr",
    "sg:city":"Holland",
    "sg:classifiers":[
        {
            "category":"Social Services",
            "subcategory":"Child Care",
            "type":"Services"
        }
    ],
    "sg:phone":"+1 616 786 9139",
    "sg:postcode":"49424",
    "sg:province":"MI",
    "sg:tags":[
        "day",
        "provider"
    ],
    "wof:name":"Skiver Sunnye",
    "wof:placetype":"venue"
},
  "geometry": {"coordinates":[-86.150181,42.834734],"type":"Point"}
}