{
  "type": "Feature",
  "properties": {
    "iso:country":"US",
    "sg:address":"23 N Delano Rd",
    "sg:city":"Au Gres",
    "sg:classifiers":[
        {
            "category":"Utilities",
            "subcategory":"Water",
            "type":"Services"
        }
    ],
    "sg:phone":"+1 989 876 8631",
    "sg:postcode":"48703",
    "sg:province":"MI",
    "sg:tags":[
        "company",
        "sewage"
    ],
    "wof:name":"Sims Township Water Dept",
    "wof:placetype":"venue"
},
  "geometry": {"coordinates":[-83.62587499999999,44.088835],"type":"Point"}
}