{
  "type": "Feature",
  "properties": {
    "iso:country":"US",
    "sg:address":"27559 Schoolcraft Rd",
    "sg:city":"Livonia",
    "sg:classifiers":[
        {
            "category":"Manufacturing",
            "subcategory":"Motor Vehicles & Parts",
            "type":"Manufacturing & Wholesale Goods"
        }
    ],
    "sg:phone":"+1 734 522 9440",
    "sg:postcode":"48150",
    "sg:province":"MI",
    "sg:tags":[
        "automotive",
        "rebuilds",
        "drive",
        "shaft"
    ],
    "wof:name":"Drives & Shafts Specialties",
    "wof:placetype":"venue"
},
  "geometry": {"coordinates":[-83.318617,42.38359],"type":"Point"}
}