{
  "type": "Feature",
  "properties": {
    "iso:country":"US",
    "sg:address":"20959 Elwell Rd",
    "sg:city":"Belleville",
    "sg:classifiers":[
        {
            "category":"Building & Trades",
            "subcategory":"Construction",
            "type":"Services"
        }
    ],
    "sg:phone":"+1 734 461 2558",
    "sg:postcode":"48111",
    "sg:province":"MI",
    "sg:tags":[
        "hanging",
        "contractor"
    ],
    "wof:name":"Hanson Painting Inc",
    "wof:placetype":"venue"
},
  "geometry": {"coordinates":[-83.50000199999999,42.149218],"type":"Point"}
}