{
  "type": "Feature",
  "properties": {
    "iso:country":"US",
    "sg:address":"7550 W 56th St",
    "sg:city":"Fremont",
    "sg:classifiers":[
        {
            "category":"Farming",
            "subcategory":"Dairy Farm",
            "type":"Manufacturing & Wholesale Goods"
        }
    ],
    "sg:phone":"+1 231 924 3945",
    "sg:postcode":"49412",
    "sg:province":"MI",
    "wof:name":"Klomp Farm",
    "wof:placetype":"venue"
},
  "geometry": {"coordinates":[-85.98839700000001,43.45279],"type":"Point"}
}