{
  "type": "Feature",
  "properties": {
    "iso:country":"US",
    "sg:address":"143 Ford St",
    "sg:city":"Carleton",
    "sg:classifiers":[
        {
            "category":"Arts & Performance",
            "subcategory":"Theater",
            "type":"Entertainment"
        }
    ],
    "sg:phone":"+1 734 654 6906",
    "sg:postcode":"48117",
    "sg:province":"MI",
    "sg:tags":[
        "live",
        "music"
    ],
    "wof:name":"Moon Lite Sounds",
    "wof:placetype":"venue"
},
  "geometry": {"coordinates":[-83.380353,42.053294],"type":"Point"}
}