{
  "type": "Feature",
  "properties": {
    "iso:country":"US",
    "sg:address":"5634 Patricia Ave",
    "sg:city":"Utica",
    "sg:classifiers":[
        {
            "category":"Building & Trades",
            "subcategory":"Landscaping Services",
            "type":"Services"
        }
    ],
    "sg:phone":"+1 586 323 0890",
    "sg:postcode":"48317",
    "sg:province":"MI",
    "sg:tags":[
        "landscape"
    ],
    "wof:name":"Shapes & Scapes Ldscp Maint",
    "wof:placetype":"venue"
},
  "geometry": {"coordinates":[-83.05384100000001,42.668304],"type":"Point"}
}