{
  "type": "Feature",
  "properties": {
    "iso:country":"US",
    "sg:address":"1567 N Straits Hwy",
    "sg:city":"Topinabee",
    "sg:classifiers":[
        {
            "category":"Shopping",
            "subcategory":"Used Merchandise",
            "type":"Retail Goods"
        }
    ],
    "sg:phone":"+1 231 238 1050",
    "sg:postcode":"49721",
    "sg:province":"MI",
    "sg:tags":[
        "antique"
    ],
    "wof:name":"Lakeview Cottage Antq & Trsrs",
    "wof:placetype":"venue"
},
  "geometry": {"coordinates":[-84.59299799999999,45.48397],"type":"Point"}
}