{
  "type": "Feature",
  "properties": {
    "iso:country":"US",
    "sg:address":"12684 Calhoun Rd",
    "sg:city":"Milan",
    "sg:phone":"+1 734 439 1106",
    "sg:postcode":"48160",
    "sg:province":"MI",
    "sg:tags":[
        "farm",
        "corn",
        "soybean"
    ],
    "wof:name":"Robert Ferencz",
    "wof:placetype":"venue"
},
  "geometry": {"coordinates":[-83.620788,42.052818],"type":"Point"}
}