{
  "type": "Feature",
  "properties": {
    "iso:country":"US",
    "sg:address":"3586 Charles St",
    "sg:city":"Fort Gratiot",
    "sg:classifiers":[
        {
            "category":"Professional",
            "subcategory":"Advertising",
            "type":"Services"
        }
    ],
    "sg:phone":"+1 810 385 3952",
    "sg:postcode":"48059",
    "sg:province":"MI",
    "sg:tags":[
        "mail",
        "direct"
    ],
    "wof:name":"Mail Management Service",
    "wof:placetype":"venue"
},
  "geometry": {"coordinates":[-82.487702,43.099075],"type":"Point"}
}