{
  "type": "Feature",
  "properties": {
    "iso:country":"US",
    "sg:address":"1336 Ravine Rd",
    "sg:city":"Kalamazoo",
    "sg:classifiers":[
        {
            "category":"Arts & Performance",
            "subcategory":"Theater",
            "type":"Entertainment"
        }
    ],
    "sg:phone":"+1 269 344 6015",
    "sg:postcode":"49004",
    "sg:province":"MI",
    "sg:tags":[
        "entertainer"
    ],
    "wof:name":"Mermaid Lounge",
    "wof:placetype":"venue"
},
  "geometry": {"coordinates":[-85.608824,42.307318],"type":"Point"}
}