{
  "type": "Feature",
  "properties": {
    "iso:country":"US",
    "sg:address":"980 S Telegraph Rd",
    "sg:city":"Monroe",
    "sg:classifiers":[
        {
            "category":"Insurance",
            "subcategory":"Insurance Agent",
            "type":"Services"
        }
    ],
    "sg:phone":"+1 734 241 1200",
    "sg:postcode":"48161",
    "sg:province":"MI",
    "wof:name":"Monroe Insurance",
    "wof:placetype":"venue"
},
  "geometry": {"coordinates":[-83.421325,41.910799],"type":"Point"}
}