{
  "type": "Feature",
  "properties": {
    "iso:country":"US",
    "sg:address":"105 W High St",
    "sg:city":"Union City",
    "sg:classifiers":[
        {
            "category":"Retail",
            "subcategory":"Repair Shop",
            "type":"Services"
        }
    ],
    "sg:phone":"+1 517 741 5642",
    "sg:postcode":"49094",
    "sg:province":"MI",
    "sg:tags":[
        "upholstery",
        "work",
        "carpet"
    ],
    "wof:name":"Carpet & Upholstery",
    "wof:placetype":"venue"
},
  "geometry": {"coordinates":[-85.13467,42.066407],"type":"Point"}
}