{
  "type": "Feature",
  "properties": {
    "iso:country":"US",
    "sg:address":"46956 Co Rd 215",
    "sg:city":"Lawrence",
    "sg:classifiers":[
        {
            "category":"Farming",
            "subcategory":"Orchard",
            "type":"Manufacturing & Wholesale Goods"
        }
    ],
    "sg:phone":"+1 269 674 3851",
    "sg:postcode":"49064",
    "sg:province":"MI",
    "sg:tags":[
        "fruit",
        "tree"
    ],
    "wof:name":"Tony Santos",
    "wof:placetype":"venue"
},
  "geometry": {"coordinates":[-86.07149099999999,42.245564],"type":"Point"}
}