{
  "type": "Feature",
  "properties": {
    "iso:country":"US",
    "sg:address":"26360 Huntington Rd",
    "sg:city":"Huntington Woods",
    "sg:classifiers":[
        {
            "category":"Shopping",
            "subcategory":"Used Merchandise",
            "type":"Retail Goods"
        }
    ],
    "sg:phone":"+1 248 543 6276",
    "sg:postcode":"48070",
    "sg:province":"MI",
    "wof:name":"Abbey Antiques",
    "wof:placetype":"venue"
},
  "geometry": {"coordinates":[-83.160894,42.486366],"type":"Point"}
}