{
  "type": "Feature",
  "properties": {
    "iso:country":"US",
    "sg:address":"407 E Chicago St",
    "sg:city":"Coldwater",
    "sg:classifiers":[
        {
            "category":"Shopping",
            "type":"Retail Goods"
        }
    ],
    "sg:phone":"+1 517 279 9999",
    "sg:postcode":"49036",
    "sg:province":"MI",
    "sg:tags":[
        "equipment",
        "care",
        "health",
        "home"
    ],
    "wof:name":"Carelinc Medical",
    "wof:placetype":"venue"
},
  "geometry": {"coordinates":[-84.983975,41.937892],"type":"Point"}
}