{
  "type": "Feature",
  "properties": {
    "iso:country":"US",
    "sg:address":"10470 Busch Rd",
    "sg:city":"Birch Run",
    "sg:classifiers":[
        {
            "category":"Building & Trades",
            "subcategory":"Landscaping Services",
            "type":"Services"
        }
    ],
    "sg:phone":"+1 989 652 9671",
    "sg:postcode":"48415",
    "sg:province":"MI",
    "sg:tags":[
        "landscape",
        "contractor"
    ],
    "wof:name":"Ken Worley Landscaping",
    "wof:placetype":"venue"
},
  "geometry": {"coordinates":[-83.74672700000001,43.293125],"type":"Point"}
}