{
  "type": "Feature",
  "properties": {
    "iso:country":"US",
    "sg:address":"1370 N Clinton Trl",
    "sg:city":"Charlotte",
    "sg:classifiers":[
        {
            "category":"Social Services",
            "subcategory":"Child Care",
            "type":"Services"
        }
    ],
    "sg:phone":"+1 517 543 2751",
    "sg:postcode":"48813",
    "sg:province":"MI",
    "sg:tags":[
        "kindergarten",
        "academic",
        "school"
    ],
    "wof:name":"Head Start",
    "wof:placetype":"venue"
},
  "geometry": {"coordinates":[-84.857168,42.620995],"type":"Point"}
}