{
  "type": "Feature",
  "properties": {
    "iso:country":"US",
    "sg:address":"465 South St",
    "sg:city":"Ortonville",
    "sg:classifiers":[
        {
            "category":"Food & Beverages",
            "subcategory":"Groceries & Convenience Stores",
            "type":"Retail Goods"
        }
    ],
    "sg:phone":"+1 248 627 3835",
    "sg:postcode":"48462",
    "sg:province":"MI",
    "sg:tags":[
        "grocer"
    ],
    "wof:name":"Tom's Super Market",
    "wof:placetype":"venue"
},
  "geometry": {"coordinates":[-83.44783,42.84514],"type":"Point"}
}