{
  "type": "Feature",
  "properties": {
    "iso:country":"US",
    "sg:address":"25734 Cambridge Ct",
    "sg:city":"Roseville",
    "sg:classifiers":[
        {
            "category":"Health Services",
            "subcategory":"Health Practitioner",
            "type":"Services"
        }
    ],
    "sg:phone":"+1 586 771 0965",
    "sg:postcode":"48066",
    "sg:province":"MI",
    "wof:name":"Silver Bc",
    "wof:placetype":"venue"
},
  "geometry": {"coordinates":[-82.93849899999999,42.484494],"type":"Point"}
}