{
  "type": "Feature",
  "properties": {
    "iso:country":"US",
    "sg:address":"119 S Larch St",
    "sg:city":"Lansing",
    "sg:classifiers":[
        {
            "category":"Retail",
            "subcategory":"Auto Repair",
            "type":"Services"
        }
    ],
    "sg:phone":"+1 517 484 2549",
    "sg:postcode":"48912",
    "sg:province":"MI",
    "sg:tags":[
        "repairing",
        "automobile",
        "brake",
        "suspension"
    ],
    "wof:name":"Liskeys Professional Wheel Svc",
    "wof:placetype":"venue"
},
  "geometry": {"coordinates":[-84.54459300000001,42.732241],"type":"Point"}
}