{
  "type": "Feature",
  "properties": {
    "iso:country":"US",
    "sg:address":"24127 Stanford St",
    "sg:city":"Dearborn Heights",
    "sg:classifiers":[
        {
            "category":"Professional",
            "subcategory":"Business Services",
            "type":"Services"
        }
    ],
    "sg:phone":"+1 313 274 2899",
    "sg:postcode":"48125",
    "sg:province":"MI",
    "wof:name":"Northwind Expediting",
    "wof:placetype":"venue"
},
  "geometry": {"coordinates":[-83.272671,42.278925],"type":"Point"}
}