{
  "type": "Feature",
  "properties": {
    "iso:country":"US",
    "sg:address":"45 S Rose St",
    "sg:city":"Mt Clemens",
    "sg:classifiers":[
        {
            "category":"Manufacturing",
            "subcategory":"Retail Goods",
            "type":"Manufacturing & Wholesale Goods"
        }
    ],
    "sg:phone":"+1 586 783 8070",
    "sg:postcode":"48043",
    "sg:province":"MI",
    "sg:tags":[
        "assembly",
        "fabricating"
    ],
    "wof:name":"Gen Tec Fabrication",
    "wof:placetype":"venue"
},
  "geometry": {"coordinates":[-82.895894,42.596699],"type":"Point"}
}