{
  "type": "Feature",
  "properties": {
    "iso:country":"US",
    "sg:address":"793 Lincoln Rd",
    "sg:city":"Otsego",
    "sg:classifiers":[
        {
            "category":"Shopping",
            "subcategory":"Used Merchandise",
            "type":"Retail Goods"
        }
    ],
    "sg:phone":"+1 269 692 2330",
    "sg:postcode":"49078",
    "sg:province":"MI",
    "sg:tags":[
        "antique"
    ],
    "wof:name":"Little Red Schoolhouse",
    "wof:placetype":"venue"
},
  "geometry": {"coordinates":[-85.748125,42.475712],"type":"Point"}
}