{
  "type": "Feature",
  "properties": {
    "iso:country":"US",
    "sg:address":"18728 Ecorse Rd",
    "sg:city":"Allen Park",
    "sg:classifiers":[
        {
            "category":"Personal",
            "subcategory":"Beauty Salon",
            "type":"Services"
        }
    ],
    "sg:phone":"+1 313 386 5557",
    "sg:postcode":"48101",
    "sg:province":"MI",
    "sg:tags":[
        "shop"
    ],
    "wof:name":"Pretty Lady Salon",
    "wof:placetype":"venue"
},
  "geometry": {"coordinates":[-83.225424,42.256611],"type":"Point"}
}