{
  "type": "Feature",
  "properties": {
    "iso:country":"US",
    "sg:address":"17776 Grand River Ave",
    "sg:city":"Detroit",
    "sg:classifiers":[
        {
            "category":"Autos & Motor Vehicles",
            "subcategory":"Fuel & Gas Station",
            "type":"Retail Goods"
        }
    ],
    "sg:phone":"+1 313 270 2071",
    "sg:postcode":"48227",
    "sg:province":"MI",
    "wof:name":"A & H Fill Up",
    "wof:placetype":"venue"
},
  "geometry": {"coordinates":[-83.21779600000001,42.4006],"type":"Point"}
}