{
  "type": "Feature",
  "properties": {
    "iso:country":"US",
    "sg:address":"2200 Ashmun St",
    "sg:city":"Sault Ste Marie",
    "sg:classifiers":[
        {
            "category":"Restaurant",
            "type":"Food & Drink"
        }
    ],
    "sg:phone":"+1 906 632 3353",
    "sg:postcode":"49783",
    "sg:province":"MI",
    "wof:name":"KFC",
    "wof:placetype":"venue"
},
  "geometry": {"coordinates":[-84.353747,46.479983],"type":"Point"}
}