{
  "type": "Feature",
  "properties": {
    "iso:country":"US",
    "sg:address":"3410 Corunna Rd",
    "sg:city":"Flint",
    "sg:classifiers":[
        {
            "category":"Restaurant",
            "type":"Food & Drink"
        }
    ],
    "sg:phone":"+1 810 767 0022",
    "sg:postcode":"48503",
    "sg:province":"MI",
    "wof:name":"Halo Burger",
    "wof:placetype":"venue"
},
  "geometry": {"coordinates":[-83.732163,43.002477],"type":"Point"}
}