{
  "type": "Feature",
  "properties": {
    "iso:country":"US",
    "sg:address":"4270 Van Atta Rd",
    "sg:city":"Okemos",
    "sg:classifiers":[
        {
            "category":"Professional",
            "subcategory":"Computer Services",
            "type":"Services"
        }
    ],
    "sg:phone":"+1 517 349 6383",
    "sg:postcode":"48864",
    "sg:province":"MI",
    "sg:tags":[
        "programing",
        "custom"
    ],
    "wof:name":"Psy Corp Internationale",
    "wof:placetype":"venue"
},
  "geometry": {"coordinates":[-84.37818300000001,42.709833],"type":"Point"}
}