{
  "type": "Feature",
  "properties": {
    "iso:country":"US",
    "sg:address":"215 S Hancock St",
    "sg:city":"Pentwater",
    "sg:classifiers":[
        {
            "category":"Professional",
            "subcategory":"Lawyer & Legal Services",
            "type":"Services"
        }
    ],
    "sg:phone":"+1 231 869 8621",
    "sg:postcode":"49449",
    "sg:province":"MI",
    "sg:tags":[
        "attorney"
    ],
    "wof:name":"Lawrence W Konopka",
    "wof:placetype":"venue"
},
  "geometry": {"coordinates":[-86.433134,43.779816],"type":"Point"}
}