{
  "type": "Feature",
  "properties": {
    "iso:country":"US",
    "sg:address":"1442 Brush St",
    "sg:city":"Detroit",
    "sg:classifiers":[
        {
            "category":"Professional",
            "subcategory":"Art Services",
            "type":"Services"
        }
    ],
    "sg:phone":"+1 313 964 5083",
    "sg:postcode":"48226",
    "sg:province":"MI",
    "sg:tags":[
        "graphic",
        "design"
    ],
    "wof:name":"Octane Design",
    "wof:placetype":"venue"
},
  "geometry": {"coordinates":[-83.045102,42.336478],"type":"Point"}
}