{
  "type": "Feature",
  "properties": {
    "iso:country":"US",
    "sg:address":"216 Dean Ln",
    "sg:city":"Grosse Pointe",
    "sg:classifiers":[
        {
            "category":"Professional",
            "subcategory":"Management & Consulting",
            "type":"Services"
        }
    ],
    "sg:phone":"+1 313 613 2822",
    "sg:postcode":"48236",
    "sg:province":"MI",
    "wof:name":"Jamie A Statham",
    "wof:placetype":"venue"
},
  "geometry": {"coordinates":[-82.905664,42.398703],"type":"Point"}
}