{
  "type": "Feature",
  "properties": {
    "iso:country":"US",
    "sg:address":"1765 Michigan Ave",
    "sg:city":"Marysville",
    "sg:classifiers":[
        {
            "category":"Recreation",
            "subcategory":"Marina",
            "type":"Entertainment"
        }
    ],
    "sg:phone":"+1 810 364 8875",
    "sg:postcode":"48040",
    "sg:province":"MI",
    "sg:tags":[
        "repairing",
        "boat"
    ],
    "wof:name":"Tiger Fiberglass & Marine Inc",
    "wof:placetype":"venue"
},
  "geometry": {"coordinates":[-82.479518,42.901728],"type":"Point"}
}