{
  "type": "Feature",
  "properties": {
    "iso:country":"US",
    "sg:address":"9774 68th Ave",
    "sg:city":"Allendale",
    "sg:classifiers":[
        {
            "category":"Building & Trades",
            "subcategory":"Construction",
            "type":"Services"
        }
    ],
    "sg:phone":"+1 616 892 5800",
    "sg:postcode":"49401",
    "sg:province":"MI",
    "sg:tags":[
        "house"
    ],
    "wof:name":"Scott Wondergem Bldgs",
    "wof:placetype":"venue"
},
  "geometry": {"coordinates":[-85.952872,42.946264],"type":"Point"}
}