{
  "type": "Feature",
  "properties": {
    "iso:country":"US",
    "sg:address":"24205 Telegraph Rd",
    "sg:city":"Southfield",
    "sg:classifiers":[
        {
            "category":"Manufacturing",
            "subcategory":"Electronics",
            "type":"Manufacturing & Wholesale Goods"
        }
    ],
    "sg:phone":"+1 248 356 2839",
    "sg:postcode":"48033",
    "sg:province":"MI",
    "sg:tags":[
        "equipment",
        "electronic",
        "supply"
    ],
    "sg:website":"www.syndevco.com",
    "wof:name":"Syndevco Inc",
    "wof:placetype":"venue"
},
  "geometry": {"coordinates":[-83.281942,42.4719],"type":"Point"}
}