{
  "type": "Feature",
  "properties": {
    "iso:country":"US",
    "sg:address":"3665 28th St SE",
    "sg:city":"Grand Rapids",
    "sg:classifiers":[
        {
            "category":"Shopping",
            "subcategory":"Clothing, Apparel, & Fashions",
            "type":"Retail Goods"
        }
    ],
    "sg:phone":"+1 616 464 1592",
    "sg:postcode":"49512",
    "sg:province":"MI",
    "sg:tags":[
        "leather"
    ],
    "wof:name":"Leather Lobby",
    "wof:placetype":"venue"
},
  "geometry": {"coordinates":[-85.577403,42.912596],"type":"Point"}
}