{
  "type": "Feature",
  "properties": {
    "iso:country":"US",
    "sg:address":"45636 Van Dyke Ave",
    "sg:city":"Utica",
    "sg:classifiers":[
        {
            "category":"Professional",
            "subcategory":"Employment Agencies",
            "type":"Services"
        }
    ],
    "sg:phone":"+1 586 739 9055",
    "sg:postcode":"48317",
    "sg:province":"MI",
    "sg:website":"www.laborready.com",
    "wof:name":"Labor Ready",
    "wof:placetype":"venue"
},
  "geometry": {"coordinates":[-83.032501,42.631802],"type":"Point"}
}