{
  "type": "Feature",
  "properties": {
    "iso:country":"US",
    "sg:address":"19875 State Hwy 205",
    "sg:city":"Edwardsburg",
    "sg:classifiers":[
        {
            "category":"Manufacturing",
            "subcategory":"Rubber & Plastics",
            "type":"Manufacturing & Wholesale Goods"
        }
    ],
    "sg:phone":"+1 269 641 5508",
    "sg:postcode":"49112",
    "sg:province":"MI",
    "wof:name":"LRT Plastics Inc",
    "wof:placetype":"venue"
},
  "geometry": {"coordinates":[-85.95213200000001,41.767879],"type":"Point"}
}