{
  "type": "Feature",
  "properties": {
    "iso:country":"US",
    "sg:address":"912 Industrial Dr",
    "sg:city":"Tecumseh",
    "sg:classifiers":[
        {
            "category":"Wholesale",
            "subcategory":"Machinery & Supplies",
            "type":"Manufacturing & Wholesale Goods"
        }
    ],
    "sg:phone":"+1 517 423 8356",
    "sg:postcode":"49286",
    "sg:province":"MI",
    "sg:tags":[
        "equipment",
        "plastic"
    ],
    "sg:website":"www.glycon.com",
    "wof:name":"Glycon",
    "wof:placetype":"venue"
},
  "geometry": {"coordinates":[-83.942638,41.991631],"type":"Point"}
}