{
  "type": "Feature",
  "properties": {
    "iso:country":"US",
    "sg:address":"1809 27th St",
    "sg:city":"Bay City",
    "sg:classifiers":[
        {
            "category":"Recreation",
            "subcategory":"Marina",
            "type":"Entertainment"
        }
    ],
    "sg:phone":"+1 989 895 7000",
    "sg:postcode":"48708",
    "sg:province":"MI",
    "sg:tags":[
        "repairing",
        "boat"
    ],
    "wof:name":"Mid Michigan Fiber Glass",
    "wof:placetype":"venue"
},
  "geometry": {"coordinates":[-83.85328199999999,43.575931],"type":"Point"}
}