{
  "type": "Feature",
  "properties": {
    "iso:country":"US",
    "sg:address":"521 Leonard St NW",
    "sg:city":"Grand Rapids",
    "sg:classifiers":[
        {
            "category":"Manufacturing",
            "subcategory":"Food",
            "type":"Manufacturing & Wholesale Goods"
        }
    ],
    "sg:phone":"+1 616 726 1259",
    "sg:postcode":"49504",
    "sg:province":"MI",
    "sg:tags":[
        "coffee",
        "mills"
    ],
    "wof:name":"Beadbin",
    "wof:placetype":"venue"
},
  "geometry": {"coordinates":[-85.681309,42.985006],"type":"Point"}
}