{
  "type": "Feature",
  "properties": {
    "iso:country":"US",
    "sg:address":"9860 Palmoor Ave",
    "sg:city":"White Lake",
    "sg:classifiers":[
        {
            "category":"Building & Trades",
            "subcategory":"Construction",
            "type":"Services"
        }
    ],
    "sg:phone":"+1 248 698 3284",
    "sg:postcode":"48386",
    "sg:province":"MI",
    "sg:tags":[
        "house",
        "general",
        "contractor"
    ],
    "wof:name":"Percival Construction",
    "wof:placetype":"venue"
},
  "geometry": {"coordinates":[-83.47966700000001,42.636692],"type":"Point"}
}