{
  "type": "Feature",
  "properties": {
    "iso:country":"US",
    "sg:address":"1184 Cleaver Rd",
    "sg:city":"Caro",
    "sg:classifiers":[
        {
            "category":"Health Services",
            "subcategory":"Doctor",
            "type":"Services"
        }
    ],
    "sg:phone":"+1 989 673 5488",
    "sg:postcode":"48723",
    "sg:province":"MI",
    "sg:tags":[
        "physician",
        "surgeon"
    ],
    "wof:name":"Sity Girgis MD",
    "wof:placetype":"venue"
},
  "geometry": {"coordinates":[-83.38760499999999,43.501919],"type":"Point"}
}