{
  "type": "Feature",
  "properties": {
    "iso:country":"US",
    "sg:address":"4148 E Cook Rd",
    "sg:city":"Grand Blanc",
    "sg:classifiers":[
        {
            "category":"Building & Trades",
            "subcategory":"Construction",
            "type":"Services"
        }
    ],
    "sg:phone":"+1 810 695 9266",
    "sg:postcode":"48439",
    "sg:province":"MI",
    "sg:tags":[
        "dry wall",
        "contractor"
    ],
    "wof:name":"Witnauer Drywall Co",
    "wof:placetype":"venue"
},
  "geometry": {"coordinates":[-83.62097,42.901684],"type":"Point"}
}