{
  "type": "Feature",
  "properties": {
    "iso:country":"US",
    "sg:address":"26311 Ursuline St",
    "sg:city":"Saint Clair Shores",
    "sg:classifiers":[
        {
            "category":"Arts & Performance",
            "subcategory":"Theater",
            "type":"Entertainment"
        }
    ],
    "sg:phone":"+1 586 773 5914",
    "sg:postcode":"48081",
    "sg:province":"MI",
    "sg:tags":[
        "theatrical"
    ],
    "wof:name":"Broadway Videostage Group Atte",
    "wof:placetype":"venue"
},
  "geometry": {"coordinates":[-82.913785,42.487246],"type":"Point"}
}