{
  "type": "Feature",
  "properties": {
    "iso:country":"US",
    "sg:address":"5720 Johnson Rd",
    "sg:city":"Greenville",
    "sg:classifiers":[
        {
            "category":"Building & Trades",
            "subcategory":"Cleaning & Sanitation",
            "type":"Services"
        }
    ],
    "sg:phone":"+1 616 225 2083",
    "sg:postcode":"48838",
    "sg:province":"MI",
    "wof:name":"Ace Power Wash & Wet Sandblstg",
    "wof:placetype":"venue"
},
  "geometry": {"coordinates":[-85.302322,43.210486],"type":"Point"}
}