{
  "type": "Feature",
  "properties": {
    "iso:country":"US",
    "sg:address":"8308 Lapeer Rd",
    "sg:city":"Davison",
    "sg:classifiers":[
        {
            "category":"Retail",
            "subcategory":"Auto Repair",
            "type":"Services"
        }
    ],
    "sg:phone":"+1 810 653 8767",
    "sg:postcode":"48423",
    "sg:province":"MI",
    "sg:tags":[
        "body",
        "shop"
    ],
    "wof:name":"Dar's Auto Body",
    "wof:placetype":"venue"
},
  "geometry": {"coordinates":[-83.549896,43.0117],"type":"Point"}
}