{
  "type": "Feature",
  "properties": {
    "iso:country":"US",
    "sg:address":"15626 S Telegraph Rd",
    "sg:city":"Monroe",
    "sg:classifiers":[
        {
            "category":"Retail",
            "subcategory":"Auto Repair",
            "type":"Services"
        }
    ],
    "sg:phone":"+1 734 242 7750",
    "sg:postcode":"48161",
    "sg:province":"MI",
    "sg:tags":[
        "body",
        "automobile",
        "painting"
    ],
    "wof:name":"Paul's Carstar Collision Rpr",
    "wof:placetype":"venue"
},
  "geometry": {"coordinates":[-83.425628,41.904669],"type":"Point"}
}