{
  "type": "Feature",
  "properties": {
    "iso:country":"US",
    "sg:address":"408 E State St",
    "sg:city":"Cassopolis",
    "sg:classifiers":[
        {
            "category":"Health Services",
            "subcategory":"Doctor",
            "type":"Services"
        }
    ],
    "sg:phone":"+1 269 445 8636",
    "sg:postcode":"49031",
    "sg:province":"MI",
    "sg:tags":[
        "dentist"
    ],
    "wof:name":"Cassopolis Dental",
    "wof:placetype":"venue"
},
  "geometry": {"coordinates":[-86.00765800000001,41.911485],"type":"Point"}
}