{
  "type": "Feature",
  "properties": {
    "iso:country":"US",
    "sg:address":"5836 N Branch Rd",
    "sg:city":"North Branch",
    "sg:classifiers":[
        {
            "category":"Health Services",
            "subcategory":"Health Practitioner",
            "type":"Services"
        }
    ],
    "sg:phone":"+1 810 793 5282",
    "sg:postcode":"48461",
    "sg:province":"MI",
    "sg:tags":[
        "therapist",
        "physical"
    ],
    "wof:name":"Full Circle Physical Therapy",
    "wof:placetype":"venue"
},
  "geometry": {"coordinates":[-83.120659,43.231159],"type":"Point"}
}