{
  "type": "Feature",
  "properties": {
    "iso:country":"US",
    "sg:address":"559 Cook Rd",
    "sg:city":"Grosse Pointe",
    "sg:classifiers":[
        {
            "category":"Professional",
            "subcategory":"Business Services",
            "type":"Services"
        }
    ],
    "sg:phone":"+1 313 884 2634",
    "sg:postcode":"48236",
    "sg:province":"MI",
    "wof:name":"Ozog Automotive Group LLC",
    "wof:placetype":"venue"
},
  "geometry": {"coordinates":[-82.890826,42.42037],"type":"Point"}
}