{
  "type": "Feature",
  "properties": {
    "iso:country":"US",
    "sg:address":"5164 Springborn Rd",
    "sg:city":"East China",
    "sg:classifiers":[
        {
            "category":"Social Services",
            "subcategory":"Adult Care",
            "type":"Services"
        }
    ],
    "sg:phone":"+1 810 765 9255",
    "sg:postcode":"48054",
    "sg:province":"MI",
    "sg:tags":[
        "residential"
    ],
    "wof:name":"Springborn Acres",
    "wof:placetype":"venue"
},
  "geometry": {"coordinates":[-82.516762,42.742917],"type":"Point"}
}