{
  "type": "Feature",
  "properties": {
    "iso:country":"US",
    "sg:address":"644 Meadow Rd",
    "sg:city":"Tawas City",
    "sg:classifiers":[
        {
            "category":"Retail",
            "subcategory":"Car Wash",
            "type":"Services"
        }
    ],
    "sg:phone":"+1 989 362 5663",
    "sg:postcode":"48763",
    "sg:province":"MI",
    "sg:tags":[
        "polishing",
        "washing"
    ],
    "wof:name":"Bay Shore Car Wash",
    "wof:placetype":"venue"
},
  "geometry": {"coordinates":[-83.539365,44.265309],"type":"Point"}
}