{
  "type": "Feature",
  "properties": {
    "iso:country":"US",
    "sg:address":"134 Spencer Ln",
    "sg:city":"Ypsilanti",
    "sg:classifiers":[
        {
            "category":"Organizations",
            "subcategory":"Religious Organization",
            "type":"Services"
        }
    ],
    "sg:phone":"+1 734 483 1110",
    "sg:postcode":"48198",
    "sg:province":"MI",
    "wof:name":"Strong Tower Ministry",
    "wof:placetype":"venue"
},
  "geometry": {"coordinates":[-83.568398,42.251202],"type":"Point"}
}