{
  "type": "Feature",
  "properties": {
    "iso:country":"US",
    "sg:address":"5466 Schaefer Rd",
    "sg:city":"Dearborn",
    "sg:classifiers":[
        {
            "category":"Shopping",
            "subcategory":"Computers & Home Electronics",
            "type":"Retail Goods"
        }
    ],
    "sg:phone":"+1 313 945 9945",
    "sg:postcode":"48126",
    "sg:province":"MI",
    "wof:name":"Smart Buy Electronics",
    "wof:placetype":"venue"
},
  "geometry": {"coordinates":[-83.17600299999999,42.328499],"type":"Point"}
}