{
  "type": "Feature",
  "properties": {
    "iso:country":"US",
    "sg:address":"42806 Garfield Rd",
    "sg:city":"Clinton Twp",
    "sg:classifiers":[
        {
            "category":"Personal",
            "subcategory":"Beauty Salon",
            "type":"Services"
        }
    ],
    "sg:phone":"+1 586 909 1763",
    "sg:postcode":"48038",
    "sg:province":"MI",
    "sg:tags":[
        "manicuring"
    ],
    "wof:name":"Nails By Chris In Calfornia",
    "wof:placetype":"venue"
},
  "geometry": {"coordinates":[-82.952805,42.611493],"type":"Point"}
}