{
  "type": "Feature",
  "properties": {
    "iso:country":"US",
    "sg:address":"5430 W Frances Rd",
    "sg:city":"Clio",
    "sg:classifiers":[
        {
            "category":"Building & Trades",
            "subcategory":"Construction",
            "type":"Services"
        }
    ],
    "sg:phone":"+1 810 687 7745",
    "sg:postcode":"48420",
    "sg:province":"MI",
    "sg:tags":[
        "house"
    ],
    "wof:name":"Matt Nelson Carpentry",
    "wof:placetype":"venue"
},
  "geometry": {"coordinates":[-83.79222799999999,43.133902],"type":"Point"}
}