{
  "type": "Feature",
  "properties": {
    "iso:country":"US",
    "sg:address":"626 Oak St",
    "sg:city":"Adrian",
    "sg:classifiers":[
        {
            "category":"Autos & Motor Vehicles",
            "subcategory":"Auto Supplies",
            "type":"Retail Goods"
        }
    ],
    "sg:phone":"+1 517 265 5101",
    "sg:postcode":"49221",
    "sg:province":"MI",
    "sg:tags":[
        "automobile",
        "parts"
    ],
    "wof:name":"NAPA Auto & Truck Parts",
    "wof:placetype":"venue"
},
  "geometry": {"coordinates":[-84.024593,41.890668],"type":"Point"}
}