{
  "type": "Feature",
  "properties": {
    "iso:country":"US",
    "sg:address":"2939 North Dr",
    "sg:city":"Traverse City",
    "sg:classifiers":[
        {
            "category":"Building & Trades",
            "subcategory":"Electrical",
            "type":"Services"
        }
    ],
    "sg:phone":"+1 231 943 8836",
    "sg:postcode":"49684",
    "sg:province":"MI",
    "sg:tags":[
        "electrical",
        "contractor"
    ],
    "wof:name":"Future Sound",
    "wof:placetype":"venue"
},
  "geometry": {"coordinates":[-85.659803,44.643806],"type":"Point"}
}