{
  "type": "Feature",
  "properties": {
    "iso:country":"US",
    "sg:address":"6565 Orchard Lake Rd",
    "sg:city":"West Bloomfield",
    "sg:classifiers":[
        {
            "category":"Food & Beverages",
            "subcategory":"Groceries & Convenience Stores",
            "type":"Retail Goods"
        }
    ],
    "sg:phone":"+1 248 851 3852",
    "sg:postcode":"48322",
    "sg:province":"MI",
    "wof:name":"Farmer Jack",
    "wof:placetype":"venue"
},
  "geometry": {"coordinates":[-83.36045,42.541502],"type":"Point"}
}