{
  "type": "Feature",
  "properties": {
    "iso:country":"US",
    "sg:address":"241 W South St",
    "sg:city":"Kalamazoo",
    "sg:classifiers":[
        {
            "category":"Government",
            "subcategory":"Court House",
            "type":"Public Place"
        }
    ],
    "sg:phone":"+1 269 337 8185",
    "sg:postcode":"49007",
    "sg:province":"MI",
    "sg:tags":[
        "city",
        "counsel"
    ],
    "wof:name":"Kalamazoo City Attorney",
    "wof:placetype":"venue"
},
  "geometry": {"coordinates":[-85.58559,42.289689],"type":"Point"}
}