{
  "type": "Feature",
  "properties": {
    "iso:country":"US",
    "sg:address":"9897 Howard City Edmore Rd",
    "sg:city":"Lakeview",
    "sg:classifiers":[
        {
            "category":"Communications",
            "type":"Services"
        }
    ],
    "sg:phone":"+1 989 352 7700",
    "sg:postcode":"48850",
    "sg:province":"MI",
    "wof:name":"Great Lakes Communications",
    "wof:placetype":"venue"
},
  "geometry": {"coordinates":[-85.279622,43.43132],"type":"Point"}
}