{
  "type": "Feature",
  "properties": {
    "iso:country":"US",
    "sg:address":"44784 Woodward Ave",
    "sg:city":"Pontiac",
    "sg:classifiers":[
        {
            "category":"Travel",
            "subcategory":"Hotels & Motels",
            "type":"Entertainment"
        }
    ],
    "sg:phone":"+1 248 334 2592",
    "sg:postcode":"48341",
    "sg:province":"MI",
    "wof:name":"Sagano Motel",
    "wof:placetype":"venue"
},
  "geometry": {"coordinates":[-83.277603,42.618198],"type":"Point"}
}