{
  "type": "Feature",
  "properties": {
    "iso:country":"US",
    "sg:address":"3657 S Bay Ridge Ln",
    "sg:city":"Suttons Bay",
    "sg:classifiers":[
        {
            "category":"Building & Trades",
            "subcategory":"Construction",
            "type":"Services"
        }
    ],
    "sg:phone":"+1 231 271 5440",
    "sg:postcode":"49682",
    "sg:province":"MI",
    "sg:tags":[
        "contractor"
    ],
    "wof:name":"Larry Shugart Builders",
    "wof:placetype":"venue"
},
  "geometry": {"coordinates":[-85.604636,44.927267],"type":"Point"}
}