{
  "type": "Feature",
  "properties": {
    "iso:country":"US",
    "sg:address":"1101 Myrtle Ave",
    "sg:city":"Sturgis",
    "sg:classifiers":[
        {
            "category":"Farming",
            "subcategory":"Farm",
            "type":"Manufacturing & Wholesale Goods"
        }
    ],
    "sg:phone":"+1 269 651 6966",
    "sg:postcode":"49091",
    "sg:province":"MI",
    "sg:tags":[
        "crop",
        "general"
    ],
    "wof:name":"Dawn Wallman",
    "wof:placetype":"venue"
},
  "geometry": {"coordinates":[-85.40504300000001,41.794229],"type":"Point"}
}