{
  "type": "Feature",
  "properties": {
    "iso:country":"US",
    "sg:address":"5562 Continental Rd",
    "sg:city":"Grand Blanc",
    "sg:classifiers":[
        {
            "category":"Real Estate",
            "subcategory":"Real Estate Operator",
            "type":"Services"
        }
    ],
    "sg:phone":"+1 810 694 4997",
    "sg:postcode":"48439",
    "sg:province":"MI",
    "sg:tags":[
        "building",
        "nonresidential"
    ],
    "wof:name":"State Properties",
    "wof:placetype":"venue"
},
  "geometry": {"coordinates":[-83.593951,42.953121],"type":"Point"}
}