{
  "type": "Feature",
  "properties": {
    "iso:country":"US",
    "sg:address":"3825 E Wellman Line Rd",
    "sg:city":"Yale",
    "sg:classifiers":[
        {
            "category":"Building & Trades",
            "subcategory":"Construction",
            "type":"Services"
        }
    ],
    "sg:phone":"+1 810 327 2430",
    "sg:postcode":"48097",
    "sg:province":"MI",
    "sg:tags":[
        "general",
        "contractor"
    ],
    "wof:name":"D & G Underground Construction",
    "wof:placetype":"venue"
},
  "geometry": {"coordinates":[-82.64980799999999,43.178308],"type":"Point"}
}