{
  "type": "Feature",
  "properties": {
    "iso:country":"US",
    "sg:address":"3552 Meridian Crossings Dr",
    "sg:city":"Okemos",
    "sg:classifiers":[
        {
            "category":"Personal",
            "subcategory":"Beauty Salon",
            "type":"Services"
        }
    ],
    "sg:phone":"+1 517 347 6668",
    "sg:postcode":"48864",
    "sg:province":"MI",
    "sg:tags":[
        "shop"
    ],
    "wof:name":"Enstyle Salon LLC",
    "wof:placetype":"venue"
},
  "geometry": {"coordinates":[-84.434967,42.68384],"type":"Point"}
}