{
  "type": "Feature",
  "properties": {
    "iso:country":"US",
    "sg:address":"1415 Fisk Rd",
    "sg:city":"White Lake",
    "sg:classifiers":[
        {
            "category":"Real Estate",
            "subcategory":"Real Estate Operator",
            "type":"Services"
        }
    ],
    "sg:phone":"+1 248 666 2070",
    "sg:postcode":"48386",
    "sg:province":"MI",
    "sg:tags":[
        "mobile",
        "home",
        "community"
    ],
    "wof:name":"White Lake Mfr Home Community",
    "wof:placetype":"venue"
},
  "geometry": {"coordinates":[-83.46998000000001,42.665063],"type":"Point"}
}