{
  "type": "Feature",
  "properties": {
    "iso:country":"US",
    "sg:address":"9600 Macon Hwy",
    "sg:city":"Tecumseh",
    "sg:phone":"+1 517 423 2663",
    "sg:postcode":"49286",
    "sg:province":"MI",
    "sg:tags":[
        "feed",
        "beef",
        "farm",
        "corn",
        "crop",
        "field",
        "soybean",
        "cattle"
    ],
    "wof:name":"Douglas Gruber",
    "wof:placetype":"venue"
},
  "geometry": {"coordinates":[-83.895962,42.035729],"type":"Point"}
}