{
  "type": "Feature",
  "properties": {
    "iso:country":"US",
    "sg:address":"24565 Hallwood Ct",
    "sg:city":"Farmington Hills",
    "sg:classifiers":[
        {
            "category":"Shopping",
            "subcategory":"Stationery & Office Supplies",
            "type":"Retail Goods"
        }
    ],
    "sg:phone":"+1 248 478 7700",
    "sg:postcode":"48335",
    "sg:province":"MI",
    "sg:tags":[
        "equipment"
    ],
    "wof:name":"Wilson Business Machines Inc",
    "wof:placetype":"venue"
},
  "geometry": {"coordinates":[-83.418701,42.472698],"type":"Point"}
}