{
  "type": "Feature",
  "properties": {
    "iso:country":"US",
    "sg:address":"201 Spring Arbor Rd",
    "sg:city":"Concord",
    "sg:classifiers":[
        {
            "category":"Retail",
            "subcategory":"Auto Repair",
            "type":"Services"
        }
    ],
    "sg:phone":"+1 517 524 6199",
    "sg:postcode":"49237",
    "sg:province":"MI",
    "sg:tags":[
        "general"
    ],
    "wof:name":"Pit Stop Automotive",
    "wof:placetype":"venue"
},
  "geometry": {"coordinates":[-84.64324000000001,42.182605],"type":"Point"}
}