{
  "type": "Feature",
  "properties": {
    "iso:country":"US",
    "sg:address":"9475 Cushing Rd",
    "sg:city":"Eau Claire",
    "sg:classifiers":[
        {
            "category":"Utilities",
            "subcategory":"Cable",
            "type":"Services"
        }
    ],
    "sg:phone":"+1 269 782 8582",
    "sg:postcode":"49111",
    "sg:province":"MI",
    "sg:tags":[
        "television"
    ],
    "wof:name":"Charter Communications",
    "wof:placetype":"venue"
},
  "geometry": {"coordinates":[-86.22871499999999,42.020798],"type":"Point"}
}