{
  "type": "Feature",
  "properties": {
    "iso:country":"US",
    "sg:address":"68705 M 103",
    "sg:city":"White Pigeon",
    "sg:classifiers":[
        {
            "category":"Personal",
            "subcategory":"Beauty Salon",
            "type":"Services"
        }
    ],
    "sg:phone":"+1 269 483 7111",
    "sg:postcode":"49099",
    "sg:province":"MI",
    "sg:tags":[
        "shop"
    ],
    "wof:name":"Flora Mays Beauty Salon",
    "wof:placetype":"venue"
},
  "geometry": {"coordinates":[-85.756857,41.798868],"type":"Point"}
}