{
  "type": "Feature",
  "properties": {
    "iso:country":"US",
    "sg:address":"19160 Toepfer Dr",
    "sg:city":"Eastpointe",
    "sg:classifiers":[
        {
            "category":"Organizations",
            "subcategory":"Religious Organization",
            "type":"Services"
        }
    ],
    "sg:phone":"+1 586 771 4420",
    "sg:postcode":"48021",
    "sg:province":"MI",
    "sg:tags":[
        "church"
    ],
    "wof:name":"Community Of Christ",
    "wof:placetype":"venue"
},
  "geometry": {"coordinates":[-82.928505,42.455306],"type":"Point"}
}