{
  "type": "Feature",
  "properties": {
    "iso:country":"US",
    "sg:address":"1250 S Huron Rd",
    "sg:city":"Kawkawlin",
    "sg:classifiers":[
        {
            "category":"Retail",
            "subcategory":"Auto Repair",
            "type":"Services"
        }
    ],
    "sg:phone":"+1 989 671 9006",
    "sg:postcode":"48631",
    "sg:province":"MI",
    "sg:tags":[
        "repairing",
        "electric",
        "supply",
        "automobile",
        "brake",
        "service-equipment"
    ],
    "wof:name":"Superior Automotive",
    "wof:placetype":"venue"
},
  "geometry": {"coordinates":[-83.96856699999999,43.70303],"type":"Point"}
}