{
  "type": "Feature",
  "properties": {
    "iso:country":"US",
    "sg:address":"16140 148th Ave",
    "sg:city":"Spring Lake",
    "sg:classifiers":[
        {
            "category":"Organizations",
            "subcategory":"Membership Organization",
            "type":"Services"
        }
    ],
    "sg:phone":"+1 616 846 5506",
    "sg:postcode":"49456",
    "sg:province":"MI",
    "wof:name":"Laker Athletic Foundation",
    "wof:placetype":"venue"
},
  "geometry": {"coordinates":[-86.15586500000001,43.069136],"type":"Point"}
}