{
  "type": "Feature",
  "properties": {
    "iso:country":"US",
    "sg:address":"43 S Howell St",
    "sg:city":"Hillsdale",
    "sg:classifiers":[
        {
            "category":"Health Services",
            "subcategory":"Optometrist",
            "type":"Services"
        }
    ],
    "sg:phone":"+1 517 437 3365",
    "sg:postcode":"49242",
    "sg:province":"MI",
    "wof:name":"Brichta & Brichta",
    "wof:placetype":"venue"
},
  "geometry": {"coordinates":[-84.631958,41.918249],"type":"Point"}
}