{
  "type": "Feature",
  "properties": {
    "iso:country":"US",
    "sg:address":"450 Morris Ave",
    "sg:city":"Muskegon",
    "sg:classifiers":[
        {
            "category":"Government",
            "subcategory":"Office",
            "type":"Public Place"
        }
    ],
    "sg:phone":"+1 231 726 3588",
    "sg:postcode":"49440",
    "sg:province":"MI",
    "sg:tags":[
        "federal",
        "social",
        "administration",
        "welfare"
    ],
    "wof:name":"Social Security Administration",
    "wof:placetype":"venue"
},
  "geometry": {"coordinates":[-86.25321599999999,43.236749],"type":"Point"}
}