{
  "type": "Feature",
  "properties": {
    "iso:country":"US",
    "sg:address":"1122 N Leroy St",
    "sg:city":"Fenton",
    "sg:classifiers":[
        {
            "category":"Retail",
            "subcategory":"Laundry & Dry Cleaning",
            "type":"Services"
        }
    ],
    "sg:phone":"+1 810 750 9160",
    "sg:postcode":"48430",
    "sg:province":"MI",
    "sg:tags":[
        "garment",
        "plant",
        "agent",
        "drycleaning"
    ],
    "wof:name":"Cotharins Cleaners",
    "wof:placetype":"venue"
},
  "geometry": {"coordinates":[-83.707206,42.809247],"type":"Point"}
}