{
  "type": "Feature",
  "properties": {
    "iso:country":"US",
    "sg:address":"2007 Edgemont Ct",
    "sg:city":"Rochester",
    "sg:classifiers":[
        {
            "category":"Social Services",
            "subcategory":"Adult Care",
            "type":"Services"
        }
    ],
    "sg:phone":"+1 248 650 0924",
    "sg:postcode":"48306",
    "sg:province":"MI",
    "sg:tags":[
        "foster",
        "provider"
    ],
    "wof:name":"Mazurek Leroy & Caryn",
    "wof:placetype":"venue"
},
  "geometry": {"coordinates":[-83.17312800000001,42.697933],"type":"Point"}
}