{
  "type": "Feature",
  "properties": {
    "iso:country":"US",
    "sg:address":"2030 W 5 Mile Rd",
    "sg:city":"Sault Sainte Marie",
    "sg:classifiers":[
        {
            "category":"Professional",
            "subcategory":"Accounting & Tax Preparation",
            "type":"Services"
        }
    ],
    "sg:phone":"+1 906 635 4221",
    "sg:postcode":"49783",
    "sg:province":"MI",
    "wof:name":"Cote Accounting",
    "wof:placetype":"venue"
},
  "geometry": {"coordinates":[-84.403864,46.433779],"type":"Point"}
}