{
  "type": "Feature",
  "properties": {
    "iso:country":"US",
    "sg:address":"2427 Tuscola Ave",
    "sg:city":"Flint",
    "sg:classifiers":[
        {
            "category":"Building & Trades",
            "subcategory":"Construction",
            "type":"Services"
        }
    ],
    "sg:phone":"+1 810 233 5792",
    "sg:postcode":"48503",
    "sg:province":"MI",
    "sg:tags":[
        "woodworker"
    ],
    "wof:name":"H & B Wood Crafts",
    "wof:placetype":"venue"
},
  "geometry": {"coordinates":[-83.658642,43.024856],"type":"Point"}
}