{
  "type": "Feature",
  "properties": {
    "iso:country":"US",
    "sg:address":"53 E Liberty St",
    "sg:city":"Quincy",
    "sg:classifiers":[
        {
            "category":"Education",
            "subcategory":"School",
            "type":"Public Place"
        }
    ],
    "sg:phone":"+1 517 639 8179",
    "sg:postcode":"49082",
    "sg:province":"MI",
    "wof:name":"Liberty School",
    "wof:placetype":"venue"
},
  "geometry": {"coordinates":[-84.879852,41.940155],"type":"Point"}
}