{
  "type": "Feature",
  "properties": {
    "iso:country":"US",
    "sg:address":"10467 Pincherry Rd",
    "sg:city":"Charlevoix",
    "sg:classifiers":[
        {
            "category":"Building & Trades",
            "subcategory":"Construction",
            "type":"Services"
        }
    ],
    "sg:phone":"+1 231 347 3032",
    "sg:postcode":"49720",
    "sg:province":"MI",
    "sg:tags":[
        "house"
    ],
    "wof:name":"C Price Construction",
    "wof:placetype":"venue"
},
  "geometry": {"coordinates":[-85.10643899999999,45.353314],"type":"Point"}
}