{
  "type": "Feature",
  "properties": {
    "iso:country":"US",
    "sg:address":"1587 State Hwy 32",
    "sg:city":"Alpena",
    "sg:classifiers":[
        {
            "category":"Building & Trades",
            "subcategory":"Plumbing",
            "type":"Services"
        }
    ],
    "sg:phone":"+1 989 354 7574",
    "sg:postcode":"49707",
    "sg:province":"MI",
    "sg:tags":[
        "heating",
        "contractor"
    ],
    "wof:name":"Lakeshore Plumbing & Heating",
    "wof:placetype":"venue"
},
  "geometry": {"coordinates":[-83.468418,45.0618],"type":"Point"}
}