{
  "type": "Feature",
  "properties": {
    "iso:country":"US",
    "sg:address":"9493 West Rd",
    "sg:city":"Whitmore Lake",
    "sg:classifiers":[
        {
            "category":"Building & Trades",
            "subcategory":"Construction",
            "type":"Services"
        }
    ],
    "sg:phone":"+1 734 449 2261",
    "sg:postcode":"48189",
    "sg:province":"MI",
    "sg:tags":[
        "painting",
        "contractor"
    ],
    "wof:name":"Josephson Thomas Painting Co",
    "wof:placetype":"venue"
},
  "geometry": {"coordinates":[-83.76406799999999,42.421796],"type":"Point"}
}