{
  "type": "Feature",
  "properties": {
    "iso:country":"US",
    "sg:address":"4763 E Margaret St",
    "sg:city":"Bridgeport",
    "sg:classifiers":[
        {
            "category":"Health Services",
            "subcategory":"Nursing And Care Facility",
            "type":"Services"
        }
    ],
    "sg:phone":"+1 989 777 2004",
    "sg:postcode":"48722",
    "sg:province":"MI",
    "wof:name":"Roseview Ais",
    "wof:placetype":"venue"
},
  "geometry": {"coordinates":[-83.87324099999999,43.353278],"type":"Point"}
}