{
  "type": "Feature",
  "properties": {
    "iso:country":"US",
    "sg:address":"7194 Kalkaska Dr",
    "sg:city":"Davison",
    "sg:classifiers":[
        {
            "category":"Building & Trades",
            "subcategory":"Plumbing",
            "type":"Services"
        }
    ],
    "sg:phone":"+1 810 742 8838",
    "sg:postcode":"48423",
    "sg:province":"MI",
    "sg:tags":[
        "contractor"
    ],
    "wof:name":"Austin Heating & Cooling",
    "wof:placetype":"venue"
},
  "geometry": {"coordinates":[-83.566198,43.004565],"type":"Point"}
}