{
  "type": "Feature",
  "properties": {
    "iso:country":"US",
    "sg:address":"14380 W 8 Mile Rd",
    "sg:city":"Oak Park",
    "sg:classifiers":[
        {
            "category":"Travel",
            "subcategory":"Hotels & Motels",
            "type":"Entertainment"
        }
    ],
    "sg:phone":"+1 248 967 1505",
    "sg:postcode":"48237",
    "sg:province":"MI",
    "sg:tags":[
        "operation"
    ],
    "wof:name":"Embassy Motel",
    "wof:placetype":"venue"
},
  "geometry": {"coordinates":[-83.18789700000001,42.4454],"type":"Point"}
}