{
  "type": "Feature",
  "properties": {
    "iso:country":"US",
    "sg:address":"710 W Wellman Line Rd",
    "sg:city":"Melvin",
    "sg:phone":"+1 810 387 3515",
    "sg:postcode":"48454",
    "sg:province":"MI",
    "sg:tags":[
        "farm",
        "corn",
        "soybean"
    ],
    "wof:name":"Robert Elston",
    "wof:placetype":"venue"
},
  "geometry": {"coordinates":[-82.832019,43.172871],"type":"Point"}
}