{
  "type": "Feature",
  "properties": {
    "iso:country":"US",
    "sg:address":"6631 Livernois Rd",
    "sg:city":"Troy",
    "sg:classifiers":[
        {
            "category":"Banks & Credit Unions",
            "subcategory":"Investment Brokerage",
            "type":"Services"
        }
    ],
    "sg:phone":"+1 248 828 3051",
    "sg:postcode":"48098",
    "sg:province":"MI",
    "sg:tags":[
        "advisory",
        "financial"
    ],
    "wof:name":"DAALLC",
    "wof:placetype":"venue"
},
  "geometry": {"coordinates":[-83.150239,42.614629],"type":"Point"}
}