{
  "type": "Feature",
  "properties": {
    "iso:country":"US",
    "sg:address":"4992 Lake Shore Dr",
    "sg:city":"Grawn",
    "sg:classifiers":[
        {
            "category":"Professional",
            "subcategory":"Lawyer & Legal Services",
            "type":"Services"
        }
    ],
    "sg:phone":"+1 231 276 5118",
    "sg:postcode":"49637",
    "sg:province":"MI",
    "sg:tags":[
        "attorney"
    ],
    "wof:name":"L Keith Borgerson",
    "wof:placetype":"venue"
},
  "geometry": {"coordinates":[-85.730845,44.615317],"type":"Point"}
}