{
  "type": "Feature",
  "properties": {
    "iso:country":"US",
    "sg:address":"6204 N Saginaw St",
    "sg:city":"Flint",
    "sg:classifiers":[
        {
            "category":"Autos & Motor Vehicles",
            "subcategory":"Auto Supplies",
            "type":"Retail Goods"
        }
    ],
    "sg:phone":"+1 810 789 8529",
    "sg:postcode":"48505",
    "sg:province":"MI",
    "sg:tags":[
        "automobile",
        "parts"
    ],
    "wof:name":"North Flint Automotive Supply",
    "wof:placetype":"venue"
},
  "geometry": {"coordinates":[-83.693859,43.069493],"type":"Point"}
}