{
  "type": "Feature",
  "properties": {
    "iso:country":"US",
    "sg:address":"9077 N Tottenham Dr",
    "sg:city":"Traverse City",
    "sg:classifiers":[
        {
            "category":"Home & Garden",
            "subcategory":"Home Furnishings",
            "type":"Retail Goods"
        }
    ],
    "sg:phone":"+1 231 943 8125",
    "sg:postcode":"49684",
    "sg:province":"MI",
    "sg:tags":[
        "business"
    ],
    "wof:name":"ACF Designs",
    "wof:placetype":"venue"
},
  "geometry": {"coordinates":[-85.762946,44.692781],"type":"Point"}
}