{
  "type": "Feature",
  "properties": {
    "iso:country":"US",
    "sg:address":"22526 Rausch Ave",
    "sg:city":"Eastpointe",
    "sg:classifiers":[
        {
            "category":"Utilities",
            "subcategory":"Telephone",
            "type":"Services"
        }
    ],
    "sg:phone":"+1 586 771 1156",
    "sg:postcode":"48021",
    "sg:province":"MI",
    "sg:tags":[
        "communications"
    ],
    "wof:name":"Charles Nutting III",
    "wof:placetype":"venue"
},
  "geometry": {"coordinates":[-82.94463399999999,42.463881],"type":"Point"}
}