{
  "type": "Feature",
  "properties": {
    "iso:country":"US",
    "sg:address":"609 Quarter St",
    "sg:city":"Rochester",
    "sg:classifiers":[
        {
            "category":"Professional",
            "subcategory":"Secretarial Services",
            "type":"Services"
        }
    ],
    "sg:phone":"+1 248 656 2269",
    "sg:postcode":"48307",
    "sg:province":"MI",
    "sg:tags":[
        "reporting"
    ],
    "wof:name":"Inkwell Works",
    "wof:placetype":"venue"
},
  "geometry": {"coordinates":[-83.141825,42.674442],"type":"Point"}
}