{
  "type": "Feature",
  "properties": {
    "iso:country":"US",
    "sg:address":"1156 Division Ave S",
    "sg:city":"Grand Rapids",
    "sg:classifiers":[
        {
            "category":"Restaurant",
            "type":"Food & Drink"
        }
    ],
    "sg:phone":"+1 616 245 8241",
    "sg:postcode":"49507",
    "sg:province":"MI",
    "wof:name":"Chicken Coop Inc",
    "wof:placetype":"venue"
},
  "geometry": {"coordinates":[-85.66727,42.941838],"type":"Point"}
}