{
  "type": "Feature",
  "properties": {
    "iso:country":"US",
    "sg:address":"9744 Chambray St",
    "sg:city":"Portage",
    "sg:classifiers":[
        {
            "category":"Professional",
            "type":"Services"
        }
    ],
    "sg:phone":"+1 269 327 4303",
    "sg:postcode":"49002",
    "sg:province":"MI",
    "sg:tags":[
        "establishment"
    ],
    "wof:name":"Let's Talk About It Community",
    "wof:placetype":"venue"
},
  "geometry": {"coordinates":[-85.585881,42.176921],"type":"Point"}
}