{
  "type": "Feature",
  "properties": {
    "iso:country":"US",
    "sg:address":"13725 215th Ave",
    "sg:city":"Big Rapids",
    "sg:classifiers":[
        {
            "category":"Building & Trades",
            "subcategory":"Construction",
            "type":"Services"
        }
    ],
    "sg:phone":"+1 231 796 6571",
    "sg:postcode":"49307",
    "sg:province":"MI",
    "sg:tags":[
        "excavating",
        "contractor"
    ],
    "wof:name":"MMC Golf Carts",
    "wof:placetype":"venue"
},
  "geometry": {"coordinates":[-85.513734,43.67317],"type":"Point"}
}