{
  "type": "Feature",
  "properties": {
    "iso:country":"US",
    "sg:address":"111 S Lake St",
    "sg:city":"Boyne City",
    "sg:classifiers":[
        {
            "category":"Banks & Credit Unions",
            "subcategory":"Bank",
            "type":"Services"
        }
    ],
    "sg:phone":"+1 231 582 6123",
    "sg:postcode":"49712",
    "sg:province":"MI",
    "sg:tags":[
        "loan",
        "real estate"
    ],
    "wof:name":"First Capitol Mortgage",
    "wof:placetype":"venue"
},
  "geometry": {"coordinates":[-85.014747,45.213576],"type":"Point"}
}