{
  "type": "Feature",
  "properties": {
    "iso:country":"US",
    "sg:address":"230 S Church St",
    "sg:city":"Tekonsha",
    "sg:classifiers":[
        {
            "category":"Education",
            "subcategory":"Library",
            "type":"Public Place"
        }
    ],
    "sg:phone":"+1 517 767 4769",
    "sg:postcode":"49092",
    "sg:province":"MI",
    "wof:name":"Tekonsha Township Library",
    "wof:placetype":"venue"
},
  "geometry": {"coordinates":[-84.98756400000001,42.091485],"type":"Point"}
}