{
  "type": "Feature",
  "properties": {
    "iso:country":"US",
    "sg:address":"1154 E Big Beaver Rd",
    "sg:city":"Troy",
    "sg:classifiers":[
        {
            "category":"Structure",
            "subcategory":"Warehouse",
            "type":"Public Place"
        }
    ],
    "sg:phone":"+1 248 688 9231",
    "sg:postcode":"48083",
    "sg:province":"MI",
    "sg:tags":[
        "warehouses-public-commercial"
    ],
    "wof:name":"Amtech Material Systems",
    "wof:placetype":"venue"
},
  "geometry": {"coordinates":[-83.12478400000001,42.562992],"type":"Point"}
}