{
  "type": "Feature",
  "properties": {
    "iso:country":"US",
    "sg:address":"5505 Michigan Ave",
    "sg:city":"Detroit",
    "sg:classifiers":[
        {
            "category":"Organizations",
            "subcategory":"Religious Organization",
            "type":"Services"
        }
    ],
    "sg:phone":"+1 313 898 5366",
    "sg:postcode":"48210",
    "sg:province":"MI",
    "wof:name":"United Pentecostal Church",
    "wof:placetype":"venue"
},
  "geometry": {"coordinates":[-83.111448,42.331095],"type":"Point"}
}