{
  "type": "Feature",
  "properties": {
    "iso:country":"US",
    "sg:address":"24943 Tompkins Dr",
    "sg:city":"Coldwater",
    "sg:classifiers":[
        {
            "category":"Real Estate",
            "subcategory":"Real Estate Agent",
            "type":"Services"
        }
    ],
    "sg:phone":"+1 517 238 5388",
    "sg:postcode":"49036",
    "sg:province":"MI",
    "wof:name":"Jones Property Management LLC",
    "wof:placetype":"venue"
},
  "geometry": {"coordinates":[-84.98924599999999,41.835819],"type":"Point"}
}