{
  "type": "Feature",
  "properties": {
    "iso:country":"US",
    "sg:address":"5362 Hopkins Rd",
    "sg:city":"Flint",
    "sg:classifiers":[
        {
            "category":"Retail",
            "subcategory":"Portrait Studio",
            "type":"Services"
        }
    ],
    "sg:phone":"+1 810 736 8918",
    "sg:postcode":"48506",
    "sg:province":"MI",
    "sg:tags":[
        "photographer"
    ],
    "wof:name":"Accurate Photography By Mark",
    "wof:placetype":"venue"
},
  "geometry": {"coordinates":[-83.597492,43.077055],"type":"Point"}
}