{
  "type": "Feature",
  "properties": {
    "iso:country":"US",
    "sg:address":"6000 Lansing Ave",
    "sg:city":"Jackson",
    "sg:classifiers":[
        {
            "category":"Building & Trades",
            "subcategory":"Construction",
            "type":"Services"
        }
    ],
    "sg:phone":"+1 517 787 5587",
    "sg:postcode":"49201",
    "sg:province":"MI",
    "sg:tags":[
        "heavy"
    ],
    "wof:name":"Blue Water Ponds & Service",
    "wof:placetype":"venue"
},
  "geometry": {"coordinates":[-84.41361999999999,42.333884],"type":"Point"}
}