{
  "type": "Feature",
  "properties": {
    "iso:country":"US",
    "sg:address":"3339 Luce Rd",
    "sg:city":"Flushing",
    "sg:classifiers":[
        {
            "category":"Manufacturing",
            "subcategory":"Tools & Machinery",
            "type":"Manufacturing & Wholesale Goods"
        }
    ],
    "sg:phone":"+1 248 625 9639",
    "sg:postcode":"48433",
    "sg:province":"MI",
    "sg:tags":[
        "mfg",
        "industrial",
        "general"
    ],
    "wof:name":"Applied System Technologi",
    "wof:placetype":"venue"
},
  "geometry": {"coordinates":[-83.802391,43.048218],"type":"Point"}
}