{
  "type": "Feature",
  "properties": {
    "iso:country":"US",
    "sg:address":"114 W Bellevue St",
    "sg:city":"Leslie",
    "sg:classifiers":[
        {
            "category":"Organizations",
            "subcategory":"Religious Organization",
            "type":"Services"
        }
    ],
    "sg:phone":"+1 517 589 5226",
    "sg:postcode":"49251",
    "sg:province":"MI",
    "sg:tags":[
        "church"
    ],
    "wof:name":"Congregational United Church",
    "wof:placetype":"venue"
},
  "geometry": {"coordinates":[-84.43311199999999,42.451211],"type":"Point"}
}