{
  "type": "Feature",
  "properties": {
    "iso:country":"US",
    "sg:address":"5145 Grimes Rd",
    "sg:city":"Sand Lake",
    "sg:classifiers":[
        {
            "category":"Social Services",
            "subcategory":"Child Care",
            "type":"Services"
        }
    ],
    "sg:phone":"+1 616 636 4291",
    "sg:postcode":"49343",
    "sg:province":"MI",
    "sg:tags":[
        "day",
        "provider"
    ],
    "wof:name":"Alice Kay Doan",
    "wof:placetype":"venue"
},
  "geometry": {"coordinates":[-85.54195,43.285552],"type":"Point"}
}