{
  "type": "Feature",
  "properties": {
    "iso:country":"US",
    "sg:address":"5656 W Maple Rd",
    "sg:city":"West Bloomfield",
    "sg:classifiers":[
        {
            "category":"Restaurant",
            "type":"Food & Drink"
        }
    ],
    "sg:phone":"+1 248 851 2185",
    "sg:postcode":"48322",
    "sg:province":"MI",
    "sg:tags":[
        "eating"
    ],
    "wof:name":"Joes Crab Shack",
    "wof:placetype":"venue"
},
  "geometry": {"coordinates":[-83.358176,42.54309],"type":"Point"}
}