{
  "type": "Feature",
  "properties": {
    "iso:country":"US",
    "sg:address":"2161 S Lake Shore Dr",
    "sg:city":"Lake Leelanau",
    "sg:classifiers":[
        {
            "category":"Wholesale",
            "subcategory":"Construction Materials",
            "type":"Manufacturing & Wholesale Goods"
        }
    ],
    "sg:phone":"+1 231 256 2895",
    "sg:postcode":"49653",
    "sg:province":"MI",
    "sg:tags":[
        "fence"
    ],
    "wof:name":"Dog Watch Nw Michigan",
    "wof:placetype":"venue"
},
  "geometry": {"coordinates":[-85.71981,44.949545],"type":"Point"}
}