{
  "type": "Feature",
  "properties": {
    "iso:country":"US",
    "sg:address":"15099 Northline Rd",
    "sg:city":"Southgate",
    "sg:classifiers":[
        {
            "category":"Restaurant",
            "type":"Food & Drink"
        }
    ],
    "sg:menulink":"http://www.allmenus.com/mi/southgate/34668-chicken-shack/menu/",
    "sg:phone":"+1 734 283 7300",
    "sg:postcode":"48195",
    "sg:province":"MI",
    "sg:tags":[
        "american",
        "wing",
        "soul"
    ],
    "wof:name":"Chicken Shack",
    "wof:placetype":"venue"
},
  "geometry": {"coordinates":[-83.207257,42.213479],"type":"Point"}
}