{
  "type": "Feature",
  "properties": {
    "iso:country":"US",
    "sg:address":"50513 W Lakeshore Dr",
    "sg:city":"Dowagiac",
    "sg:classifiers":[
        {
            "category":"Retail",
            "subcategory":"Car Wash",
            "type":"Services"
        }
    ],
    "sg:phone":"+1 269 424 3685",
    "sg:postcode":"49047",
    "sg:province":"MI",
    "sg:tags":[
        "coin"
    ],
    "wof:name":"M P W Services Inc",
    "wof:placetype":"venue"
},
  "geometry": {"coordinates":[-86.181653,42.063826],"type":"Point"}
}