{
  "type": "Feature",
  "properties": {
    "iso:country":"US",
    "sg:address":"115 3rd St",
    "sg:city":"Ferrysburg",
    "sg:classifiers":[
        {
            "category":"Personal",
            "subcategory":"Tanning Parlor",
            "type":"Services"
        }
    ],
    "sg:phone":"+1 616 842 7121",
    "sg:postcode":"49449",
    "sg:province":"MI",
    "sg:tags":[
        "salon"
    ],
    "wof:name":"Tan On The Grand",
    "wof:placetype":"venue"
},
  "geometry": {"coordinates":[-86.430623,43.77907],"type":"Point"}
}