{
  "type": "Feature",
  "properties": {
    "iso:country":"US",
    "sg:address":"12085 Dixie",
    "sg:city":"Redford",
    "sg:classifiers":[
        {
            "category":"Professional",
            "subcategory":"Art Services",
            "type":"Services"
        }
    ],
    "sg:phone":"+1 313 255 1153",
    "sg:postcode":"48239",
    "sg:province":"MI",
    "sg:tags":[
        "commercial",
        "design",
        "datum"
    ],
    "wof:name":"Pdxro Graphics LLC",
    "wof:placetype":"venue"
},
  "geometry": {"coordinates":[-83.282492,42.37514],"type":"Point"}
}