{
  "type": "Feature",
  "properties": {
    "iso:country":"US",
    "sg:address":"4395 Rohr Rd",
    "sg:city":"Lake Orion",
    "sg:classifiers":[
        {
            "category":"Building & Trades",
            "subcategory":"Landscaping Services",
            "type":"Services"
        }
    ],
    "sg:phone":"+1 248 391 1666",
    "sg:postcode":"48359",
    "sg:province":"MI",
    "wof:name":"Kmj Lawn Svs",
    "wof:placetype":"venue"
},
  "geometry": {"coordinates":[-83.327606,42.717754],"type":"Point"}
}