{
  "type": "Feature",
  "properties": {
    "iso:country":"US",
    "sg:address":"525 Madison Ave",
    "sg:city":"Rochester",
    "sg:classifiers":[
        {
            "category":"Health Services",
            "subcategory":"Health Practitioner",
            "type":"Services"
        }
    ],
    "sg:phone":"+1 248 656 2155",
    "sg:postcode":"48307",
    "sg:province":"MI",
    "wof:name":"Sharon Myers Rd",
    "wof:placetype":"venue"
},
  "geometry": {"coordinates":[-83.139461,42.682715],"type":"Point"}
}