{
  "type": "Feature",
  "properties": {
    "iso:country":"US",
    "sg:address":"30555 Northwestern Hwy",
    "sg:city":"Farmington Hills",
    "sg:classifiers":[
        {
            "category":"Restaurant",
            "type":"Food & Drink"
        }
    ],
    "sg:phone":"+1 248 865 8600",
    "sg:postcode":"48334",
    "sg:province":"MI",
    "wof:name":"JTRB Inc",
    "wof:placetype":"venue"
},
  "geometry": {"coordinates":[-83.330561,42.513466],"type":"Point"}
}