{
  "type": "Feature",
  "properties": {
    "iso:country":"US",
    "sg:address":"5836 Sunfish Lake Ave NE",
    "sg:city":"Rockford",
    "sg:classifiers":[
        {
            "category":"Building & Trades",
            "subcategory":"Construction",
            "type":"Services"
        }
    ],
    "sg:phone":"+1 616 874 3208",
    "sg:postcode":"49341",
    "sg:province":"MI",
    "sg:tags":[
        "house"
    ],
    "wof:name":"R Lawrence Home Improvement",
    "wof:placetype":"venue"
},
  "geometry": {"coordinates":[-85.480256,43.068106],"type":"Point"}
}