{
  "type": "Feature",
  "properties": {
    "iso:country":"US",
    "sg:address":"1939 Brandes Ln",
    "sg:city":"Pinckney",
    "sg:classifiers":[
        {
            "category":"Professional",
            "type":"Services"
        }
    ],
    "sg:phone":"+1 734 878 5733",
    "sg:postcode":"48169",
    "sg:province":"MI",
    "wof:name":"Hahn Escort Service",
    "wof:placetype":"venue"
},
  "geometry": {"coordinates":[-83.913467,42.489946],"type":"Point"}
}