{
  "type": "Feature",
  "properties": {
    "iso:country":"US",
    "sg:address":"710 S State St",
    "sg:city":"Hart",
    "sg:classifiers":[
        {
            "category":"Food & Beverages",
            "subcategory":"Groceries & Convenience Stores",
            "type":"Retail Goods"
        }
    ],
    "sg:phone":"+1 231 873 3333",
    "sg:postcode":"49420",
    "sg:province":"MI",
    "sg:tags":[
        "grocer"
    ],
    "wof:name":"Gales's IGA Super Market",
    "wof:placetype":"venue"
},
  "geometry": {"coordinates":[-86.363998,43.695131],"type":"Point"}
}