{
  "type": "Feature",
  "properties": {
    "iso:country":"US",
    "sg:address":"5700 Crooks Rd Ste 112",
    "sg:city":"Troy",
    "sg:classifiers":[
        {
            "category":"Banks & Credit Unions",
            "subcategory":"Investment Brokerage",
            "type":"Services"
        }
    ],
    "sg:phone":"+1 248 689 1550",
    "sg:postcode":"48098",
    "sg:province":"MI",
    "sg:tags":[
        "investing"
    ],
    "sg:website":"www.portfoliosolutions.com",
    "wof:name":"Portfolio Solutions",
    "wof:placetype":"venue"
},
  "geometry": {"coordinates":[-83.16875400000001,42.602184],"type":"Point"}
}