{
  "type": "Feature",
  "properties": {
    "iso:country":"US",
    "sg:address":"263 N Jebavy Dr",
    "sg:city":"Ludington",
    "sg:classifiers":[
        {
            "category":"Freight",
            "type":"Transportation"
        }
    ],
    "sg:phone":"+1 231 845 7242",
    "sg:postcode":"49431",
    "sg:province":"MI",
    "sg:tags":[
        "commercial",
        "storage"
    ],
    "wof:name":"Larson's Self Storage Inc",
    "wof:placetype":"venue"
},
  "geometry": {"coordinates":[-86.41924299999999,43.960524],"type":"Point"}
}