{
  "type": "Feature",
  "properties": {
    "iso:country":"US",
    "sg:address":"125 W Ontario St",
    "sg:city":"Rogers City",
    "sg:classifiers":[
        {
            "category":"Organizations",
            "subcategory":"Religious Organization",
            "type":"Services"
        }
    ],
    "sg:phone":"+1 989 734 3929",
    "sg:postcode":"49779",
    "sg:province":"MI",
    "sg:tags":[
        "church"
    ],
    "wof:name":"Westminster Presbyterian Chr",
    "wof:placetype":"venue"
},
  "geometry": {"coordinates":[-83.81438799999999,45.417991],"type":"Point"}
}