{
  "type": "Feature",
  "properties": {
    "iso:country":"US",
    "sg:address":"4109 Benjamin Ave",
    "sg:city":"Royal Oak",
    "sg:classifiers":[
        {
            "category":"Professional",
            "subcategory":"Management & Consulting",
            "type":"Services"
        }
    ],
    "sg:phone":"+1 248 549 1495",
    "sg:postcode":"48073",
    "sg:province":"MI",
    "sg:tags":[
        "business"
    ],
    "wof:name":"Capitol Group Consultants LLC",
    "wof:placetype":"venue"
},
  "geometry": {"coordinates":[-83.174937,42.523132],"type":"Point"}
}