{
  "type": "Feature",
  "properties": {
    "iso:country":"US",
    "sg:address":"56748 Orchard Ln",
    "sg:city":"Bangor",
    "sg:classifiers":[
        {
            "category":"Sports & Exercise",
            "subcategory":"Bowling",
            "type":"Entertainment"
        }
    ],
    "sg:phone":"+1 269 427 8366",
    "sg:postcode":"49013",
    "sg:province":"MI",
    "sg:tags":[
        "center"
    ],
    "wof:name":"Lariat Restaurant & Lounge",
    "wof:placetype":"venue"
},
  "geometry": {"coordinates":[-86.09845199999999,42.310102],"type":"Point"}
}