{
  "type": "Feature",
  "properties": {
    "iso:country":"US",
    "sg:address":"9220 Center Rd",
    "sg:city":"Fenton",
    "sg:classifiers":[
        {
            "category":"Building & Trades",
            "subcategory":"Construction",
            "type":"Services"
        }
    ],
    "sg:phone":"+1 810 750 3774",
    "sg:postcode":"48430",
    "sg:province":"MI",
    "sg:tags":[
        "house"
    ],
    "wof:name":"A Plus Home Improvement",
    "wof:placetype":"venue"
},
  "geometry": {"coordinates":[-83.77914800000001,42.736459],"type":"Point"}
}