{
  "type": "Feature",
  "properties": {
    "iso:country":"US",
    "sg:address":"4585 Shifman Rd",
    "sg:city":"Goodrich",
    "sg:classifiers":[
        {
            "category":"Building & Trades",
            "subcategory":"Construction",
            "type":"Services"
        }
    ],
    "sg:phone":"+1 810 797 4142",
    "sg:postcode":"48438",
    "sg:province":"MI",
    "sg:tags":[
        "hanging",
        "contractor"
    ],
    "wof:name":"Decore Custom Painting",
    "wof:placetype":"venue"
},
  "geometry": {"coordinates":[-83.403445,42.903193],"type":"Point"}
}