{
  "type": "Feature",
  "properties": {
    "iso:country":"US",
    "sg:address":"44199 Dequindre Rd",
    "sg:city":"Troy",
    "sg:classifiers":[
        {
            "category":"Health Services",
            "subcategory":"Doctor",
            "type":"Services"
        }
    ],
    "sg:phone":"+1 248 964 5880",
    "sg:postcode":"48085",
    "sg:province":"MI",
    "wof:name":"Alqasmi Mohammed MD",
    "wof:placetype":"venue"
},
  "geometry": {"coordinates":[-83.091329,42.617845],"type":"Point"}
}