{
  "type": "Feature",
  "properties": {
    "iso:country":"US",
    "sg:address":"19979 State Hwy 140",
    "sg:city":"South Haven",
    "sg:classifiers":[
        {
            "category":"Organizations",
            "subcategory":"Religious Organization",
            "type":"Services"
        }
    ],
    "sg:phone":"+1 269 637 8271",
    "sg:postcode":"49090",
    "sg:province":"MI",
    "sg:tags":[
        "church"
    ],
    "wof:name":"Lakeshore Church Of Christ",
    "wof:placetype":"venue"
},
  "geometry": {"coordinates":[-86.25997599999999,42.396156],"type":"Point"}
}