{
  "type": "Feature",
  "properties": {
    "iso:country":"US",
    "sg:address":"5165 Marlowe Dr SE",
    "sg:city":"Grand Rapids",
    "sg:classifiers":[
        {
            "category":"Social Services",
            "subcategory":"Child Care",
            "type":"Services"
        }
    ],
    "sg:phone":"+1 616 534 6710",
    "sg:postcode":"49548",
    "sg:province":"MI",
    "sg:tags":[
        "day"
    ],
    "wof:name":"Cheryl Spoelma",
    "wof:placetype":"venue"
},
  "geometry": {"coordinates":[-85.653942,42.869877],"type":"Point"}
}