{
  "type": "Feature",
  "properties": {
    "iso:country":"US",
    "sg:address":"6206 Ada Dr SE",
    "sg:city":"Ada",
    "sg:classifiers":[
        {
            "category":"Education",
            "subcategory":"School",
            "type":"Public Place"
        }
    ],
    "sg:phone":"+1 616 676 1289",
    "sg:postcode":"49301",
    "sg:province":"MI",
    "sg:website":"www.adachristian.com",
    "wof:name":"Ada Christian Preschool",
    "wof:placetype":"venue"
},
  "geometry": {"coordinates":[-85.514565,42.9493],"type":"Point"}
}