{
  "type": "Feature",
  "properties": {
    "iso:country":"US",
    "sg:address":"1205 S Iva Rd",
    "sg:city":"Hemlock",
    "sg:classifiers":[
        {
            "category":"Professional",
            "subcategory":"Accounting & Tax Preparation",
            "type":"Services"
        }
    ],
    "sg:phone":"+1 989 642 2779",
    "sg:postcode":"48626",
    "sg:province":"MI",
    "sg:tags":[
        "bookkeeping",
        "general"
    ],
    "wof:name":"Jim Rogers Bookkeeping & Tax",
    "wof:placetype":"venue"
},
  "geometry": {"coordinates":[-84.268804,43.402318],"type":"Point"}
}