{
  "type": "Feature",
  "properties": {
    "iso:country":"US",
    "sg:address":"700 N Mason St",
    "sg:city":"Mason",
    "sg:classifiers":[
        {
            "category":"Health Services",
            "subcategory":"Clinic",
            "type":"Services"
        }
    ],
    "sg:phone":"+1 517 796 1424",
    "sg:postcode":"48854",
    "sg:province":"MI",
    "sg:tags":[
        "home",
        "care"
    ],
    "wof:name":"Heartland Hlth Hm Care Hospice",
    "wof:placetype":"venue"
},
  "geometry": {"coordinates":[-84.451359,42.589022],"type":"Point"}
}