{
  "type": "Feature",
  "properties": {
    "iso:country":"US",
    "sg:address":"210 S Main St",
    "sg:city":"Sheridan",
    "sg:classifiers":[
        {
            "category":"Cinema",
            "subcategory":"Movie Rental",
            "type":"Entertainment"
        }
    ],
    "sg:phone":"+1 989 291 3341",
    "sg:postcode":"48884",
    "sg:province":"MI",
    "sg:tags":[
        "video",
        "tape"
    ],
    "wof:name":"Video Voyage",
    "wof:placetype":"venue"
},
  "geometry": {"coordinates":[-85.07369300000001,43.210922],"type":"Point"}
}