{
  "type": "Feature",
  "properties": {
    "iso:country":"US",
    "sg:address":"13630 Northline Rd",
    "sg:city":"Southgate",
    "sg:classifiers":[
        {
            "category":"Recreation",
            "type":"Entertainment"
        }
    ],
    "sg:phone":"+1 734 285 1210",
    "sg:postcode":"48195",
    "sg:province":"MI",
    "wof:name":"Gracie Jiu-Jitsu Training Assn",
    "wof:placetype":"venue"
},
  "geometry": {"coordinates":[-83.193715,42.213742],"type":"Point"}
}