{
  "type": "Feature",
  "properties": {
    "iso:country":"US",
    "sg:address":"7 Southwick Ct",
    "sg:city":"Ann Arbor",
    "sg:classifiers":[
        {
            "category":"Retail",
            "subcategory":"Portrait Studio",
            "type":"Services"
        }
    ],
    "sg:phone":"+1 734 769 8583",
    "sg:postcode":"48105",
    "sg:province":"MI",
    "sg:tags":[
        "photographer"
    ],
    "wof:name":"Peter J Matthews",
    "wof:placetype":"venue"
},
  "geometry": {"coordinates":[-83.704877,42.313192],"type":"Point"}
}