{
  "type": "Feature",
  "properties": {
    "iso:country":"US",
    "sg:address":"901 Mixtwood St",
    "sg:city":"Ann Arbor",
    "sg:classifiers":[
        {
            "category":"Professional",
            "subcategory":"Computer Services",
            "type":"Services"
        }
    ],
    "sg:phone":"+1 734 997 0464",
    "sg:postcode":"48103",
    "sg:province":"MI",
    "sg:tags":[
        "related"
    ],
    "wof:name":"Alinear Solutions",
    "wof:placetype":"venue"
},
  "geometry": {"coordinates":[-83.759434,42.291402],"type":"Point"}
}