{
  "type": "Feature",
  "properties": {
    "iso:country":"US",
    "sg:address":"27821 Southfield Rd",
    "sg:city":"Lathrup Village",
    "sg:classifiers":[
        {
            "category":"Shopping",
            "subcategory":"Clothing, Apparel, & Fashions",
            "type":"Retail Goods"
        }
    ],
    "sg:phone":"+1 248 557 5208",
    "sg:postcode":"48076",
    "sg:province":"MI",
    "sg:tags":[
        "accessory",
        "clothing",
        "women's"
    ],
    "wof:name":"Ashley Stewart Woman",
    "wof:placetype":"venue"
},
  "geometry": {"coordinates":[-83.22229799999999,42.494301],"type":"Point"}
}