{
  "type": "Feature",
  "properties": {
    "iso:country":"US",
    "sg:address":"1421 N Van Dyke Rd",
    "sg:city":"Imlay City",
    "sg:classifiers":[
        {
            "category":"Building & Trades",
            "subcategory":"Landscaping Services",
            "type":"Services"
        }
    ],
    "sg:phone":"+1 810 724 1251",
    "sg:postcode":"48444",
    "sg:province":"MI",
    "wof:name":"Larry Lawn Care",
    "wof:placetype":"venue"
},
  "geometry": {"coordinates":[-83.075366,43.075084],"type":"Point"}
}