{
  "type": "Feature",
  "properties": {
    "iso:country":"US",
    "sg:address":"71 S Washington St",
    "sg:city":"Oxford",
    "sg:classifiers":[
        {
            "category":"Organizations",
            "subcategory":"Religious Organization",
            "type":"Services"
        }
    ],
    "sg:phone":"+1 248 628 2135",
    "sg:postcode":"48371",
    "sg:province":"MI",
    "sg:tags":[
        "church"
    ],
    "wof:name":"Church Of Christ Scientist",
    "wof:placetype":"venue"
},
  "geometry": {"coordinates":[-83.263533,42.823253],"type":"Point"}
}