{
  "type": "Feature",
  "properties": {
    "iso:country":"US",
    "sg:address":"3067 Planeview Dr",
    "sg:city":"Adrian",
    "sg:classifiers":[
        {
            "category":"Organizations",
            "subcategory":"Religious Organization",
            "type":"Services"
        }
    ],
    "sg:phone":"+1 517 266 7970",
    "sg:postcode":"49221",
    "sg:province":"MI",
    "wof:name":"Bible Missionary Church",
    "wof:placetype":"venue"
},
  "geometry": {"coordinates":[-84.084625,41.872585],"type":"Point"}
}