{
  "type": "Feature",
  "properties": {
    "iso:country":"US",
    "sg:address":"3496 Indian Lake Rd",
    "sg:city":"National City",
    "sg:classifiers":[
        {
            "category":"Restaurant",
            "type":"Food & Drink"
        }
    ],
    "sg:phone":"+1 989 469 9551",
    "sg:postcode":"48748",
    "sg:province":"MI",
    "wof:name":"Chef's Table Restaurant",
    "wof:placetype":"venue"
},
  "geometry": {"coordinates":[-83.661806,44.334366],"type":"Point"}
}