{
  "type": "Feature",
  "properties": {
    "iso:country":"US",
    "sg:address":"904 W Erie St",
    "sg:city":"Albion",
    "sg:classifiers":[
        {
            "category":"Health Services",
            "subcategory":"Clinic",
            "type":"Services"
        }
    ],
    "sg:phone":"+1 517 629 6960",
    "sg:postcode":"49224",
    "sg:province":"MI",
    "sg:tags":[
        "home"
    ],
    "wof:name":"Washington & Assoc",
    "wof:placetype":"venue"
},
  "geometry": {"coordinates":[-84.766947,42.243042],"type":"Point"}
}