{
  "type": "Feature",
  "properties": {
    "iso:country":"US",
    "sg:address":"3064 Miller Rd",
    "sg:city":"Flint",
    "sg:classifiers":[
        {
            "category":"Real Estate",
            "subcategory":"Real Estate Operator",
            "type":"Services"
        }
    ],
    "sg:phone":"+1 810 239 2159",
    "sg:postcode":"48507",
    "sg:province":"MI",
    "sg:tags":[
        "building",
        "apartment"
    ],
    "wof:name":"Flint Heights Terrace",
    "wof:placetype":"venue"
},
  "geometry": {"coordinates":[-83.735834,42.990981],"type":"Point"}
}