{
  "type": "Feature",
  "properties": {
    "iso:country":"US",
    "sg:address":"25301 Halsted Rd",
    "sg:city":"Farmington Hills",
    "sg:classifiers":[
        {
            "category":"Place Of Worship",
            "subcategory":"Church",
            "type":"Public Place"
        }
    ],
    "sg:phone":"+1 248 478 7272",
    "sg:postcode":"48335",
    "sg:province":"MI",
    "sg:website":"uufarmington.org/uucf",
    "wof:name":"Universalist Unitarian Church of Farmington",
    "wof:placetype":"venue"
},
  "geometry": {"coordinates":[-83.4161,42.476601],"type":"Point"}
}