{
  "type": "Feature",
  "properties": {
    "iso:country":"US",
    "sg:address":"115 S Campbell Rd",
    "sg:city":"Royal Oak",
    "sg:classifiers":[
        {
            "category":"Social Services",
            "subcategory":"Child Care",
            "type":"Services"
        }
    ],
    "sg:phone":"+1 248 545 7403",
    "sg:postcode":"48067",
    "sg:province":"MI",
    "wof:name":"Luckett Preschool",
    "wof:placetype":"venue"
},
  "geometry": {"coordinates":[-83.124297,42.489337],"type":"Point"}
}