{
  "type": "Feature",
  "properties": {
    "iso:country":"US",
    "sg:address":"1064 E Sternberg Rd",
    "sg:city":"Muskegon",
    "sg:classifiers":[
        {
            "category":"Shopping",
            "subcategory":"Tobacco",
            "type":"Retail Goods"
        }
    ],
    "sg:phone":"+1 231 798 9760",
    "sg:postcode":"49444",
    "sg:province":"MI",
    "sg:tags":[
        "cigarette",
        "cigar",
        "dealer"
    ],
    "wof:name":"Admiral Discount Tobacco Store",
    "wof:placetype":"venue"
},
  "geometry": {"coordinates":[-86.21666,43.154392],"type":"Point"}
}