{
  "type": "Feature",
  "properties": {
    "iso:country":"US",
    "sg:address":"16543 Grand River Ave",
    "sg:city":"Detroit",
    "sg:classifiers":[
        {
            "category":"Restaurant",
            "type":"Food & Drink"
        }
    ],
    "sg:phone":"+1 313 837 7566",
    "sg:postcode":"48227",
    "sg:province":"MI",
    "wof:name":"Tubby's Sub Shop",
    "wof:placetype":"venue"
},
  "geometry": {"coordinates":[-83.209198,42.3969],"type":"Point"}
}