{
  "type": "Feature",
  "properties": {
    "iso:country":"US",
    "sg:address":"919 Ludington St",
    "sg:city":"Escanaba",
    "sg:classifiers":[
        {
            "category":"Personal",
            "type":"Services"
        }
    ],
    "sg:phone":"+1 906 786 8363",
    "sg:postcode":"49829",
    "sg:province":"MI",
    "wof:name":"Sunsations Tanning Salon Inc",
    "wof:placetype":"venue"
},
  "geometry": {"coordinates":[-87.06099,45.74569],"type":"Point"}
}