{
  "type": "Feature",
  "properties": {
    "iso:country":"US",
    "sg:address":"230 Orange Lake Dr",
    "sg:city":"Bloomfield Hills",
    "sg:classifiers":[
        {
            "category":"Professional",
            "subcategory":"Management & Consulting",
            "type":"Services"
        }
    ],
    "sg:phone":"+1 248 745 6850",
    "sg:postcode":"48302",
    "sg:province":"MI",
    "wof:name":"Great Lakes Capital Corp",
    "wof:placetype":"venue"
},
  "geometry": {"coordinates":[-83.26977599999999,42.594552],"type":"Point"}
}