{
  "type": "Feature",
  "properties": {
    "iso:country":"US",
    "sg:address":"1811 Wiltshire Rd",
    "sg:city":"Berkley",
    "sg:classifiers":[
        {
            "category":"Professional",
            "subcategory":"Business Services",
            "type":"Services"
        }
    ],
    "sg:phone":"+1 248 546 4963",
    "sg:postcode":"48072",
    "sg:province":"MI",
    "wof:name":"Pastoral Support Services",
    "wof:placetype":"venue"
},
  "geometry": {"coordinates":[-83.17874500000001,42.498693],"type":"Point"}
}