{
  "type": "Feature",
  "properties": {
    "iso:country":"US",
    "sg:address":"1509 Corbett St",
    "sg:city":"Lansing",
    "sg:classifiers":[
        {
            "category":"Professional",
            "subcategory":"Computer Services",
            "type":"Services"
        }
    ],
    "sg:phone":"+1 517 214 8314",
    "sg:postcode":"48910",
    "sg:province":"MI",
    "wof:name":"Trideon Enterprises",
    "wof:placetype":"venue"
},
  "geometry": {"coordinates":[-84.573562,42.718502],"type":"Point"}
}