{
  "type": "Feature",
  "properties": {
    "iso:country":"US",
    "sg:address":"22747 Woodward Ave",
    "sg:city":"Ferndale",
    "sg:classifiers":[
        {
            "category":"Arts & Performance",
            "subcategory":"Art Gallery",
            "type":"Entertainment"
        }
    ],
    "sg:phone":"+1 248 808 6536",
    "sg:postcode":"48220",
    "sg:province":"MI",
    "wof:name":"The Butcher's Daughter",
    "wof:placetype":"venue"
},
  "geometry": {"coordinates":[-83.134787,42.460236],"type":"Point"}
}