{
  "type": "Feature",
  "properties": {
    "iso:country":"US",
    "sg:address":"5580 Venture Way",
    "sg:city":"Mt Pleasant",
    "sg:classifiers":[
        {
            "category":"Mining & Drilling",
            "type":"Manufacturing & Wholesale Goods"
        }
    ],
    "sg:phone":"+1 989 775 6608",
    "sg:postcode":"48858",
    "sg:province":"MI",
    "sg:tags":[
        "well",
        "oil",
        "gas",
        "contractor"
    ],
    "wof:name":"Bigard & Huggard Drilling Inc",
    "wof:placetype":"venue"
},
  "geometry": {"coordinates":[-84.733783,43.60669],"type":"Point"}
}