{
  "type": "Feature",
  "properties": {
    "iso:country":"US",
    "sg:address":"30810 Embassy St",
    "sg:city":"Beverly Hills",
    "sg:classifiers":[
        {
            "category":"Building & Trades",
            "subcategory":"Construction",
            "type":"Services"
        }
    ],
    "sg:phone":"+1 248 593 5940",
    "sg:postcode":"48025",
    "sg:province":"MI",
    "sg:tags":[
        "contractor"
    ],
    "wof:name":"On-Line Construction & Mgmt",
    "wof:placetype":"venue"
},
  "geometry": {"coordinates":[-83.246245,42.516419],"type":"Point"}
}