{
  "type": "Feature",
  "properties": {
    "iso:country":"US",
    "sg:address":"10201 Curtis",
    "sg:city":"White Lake",
    "sg:classifiers":[
        {
            "category":"Social Services",
            "subcategory":"Child Care",
            "type":"Services"
        }
    ],
    "sg:phone":"+1 248 363 0616",
    "sg:postcode":"48386",
    "sg:province":"MI",
    "sg:tags":[
        "day"
    ],
    "wof:name":"Lynda Thibodeau",
    "wof:placetype":"venue"
},
  "geometry": {"coordinates":[-83.486407,42.622081],"type":"Point"}
}