{
  "type": "Feature",
  "properties": {
    "iso:country":"US",
    "sg:address":"5485 N Irish Rd",
    "sg:city":"Davison",
    "sg:classifiers":[
        {
            "category":"Shopping",
            "subcategory":"Used Merchandise",
            "type":"Retail Goods"
        }
    ],
    "sg:phone":"+1 810 653 8993",
    "sg:postcode":"48423",
    "sg:province":"MI",
    "wof:name":"Bad Habit Collectibles",
    "wof:placetype":"venue"
},
  "geometry": {"coordinates":[-83.557789,43.079698],"type":"Point"}
}