{
  "type": "Feature",
  "properties": {
    "iso:country":"US",
    "sg:address":"1170 Woodland Dr",
    "sg:city":"Petoskey",
    "sg:classifiers":[
        {
            "category":"Manufacturing",
            "subcategory":"Tools & Machinery",
            "type":"Manufacturing & Wholesale Goods"
        }
    ],
    "sg:phone":"+1 231 347 2263",
    "sg:postcode":"49770",
    "sg:province":"MI",
    "sg:tags":[
        "electric",
        "clean"
    ],
    "wof:name":"Pro Clean Services Network",
    "wof:placetype":"venue"
},
  "geometry": {"coordinates":[-84.999467,45.36056],"type":"Point"}
}