{
  "type": "Feature",
  "properties": {
    "iso:country":"US",
    "sg:address":"339 N Genesee St",
    "sg:city":"Montrose",
    "sg:classifiers":[
        {
            "category":"Retail",
            "subcategory":"Auto Repair",
            "type":"Services"
        }
    ],
    "sg:phone":"+1 810 639 6988",
    "sg:postcode":"48457",
    "sg:province":"MI",
    "sg:tags":[
        "wrecker"
    ],
    "wof:name":"Norm's Towing & Snowplowing",
    "wof:placetype":"venue"
},
  "geometry": {"coordinates":[-83.89437100000001,43.182875],"type":"Point"}
}