{
  "type": "Feature",
  "properties": {
    "iso:country":"US",
    "sg:address":"314 E 14 Mile Rd",
    "sg:city":"Madison Heights",
    "sg:classifiers":[
        {
            "category":"Professional",
            "subcategory":"Computer Services",
            "type":"Services"
        }
    ],
    "sg:phone":"+1 248 588 6663",
    "sg:postcode":"48071",
    "sg:province":"MI",
    "sg:tags":[
        "repair"
    ],
    "sg:website":"www.abiserv.com",
    "wof:name":"Abl Electronic Services Inc",
    "wof:placetype":"venue"
},
  "geometry": {"coordinates":[-83.105107,42.534013],"type":"Point"}
}