{
  "type": "Feature",
  "properties": {
    "iso:country":"US",
    "sg:address":"13995 Bangham Rd",
    "sg:city":"Albion",
    "sg:classifiers":[
        {
            "category":"Building & Trades",
            "subcategory":"Construction",
            "type":"Services"
        }
    ],
    "sg:phone":"+1 517 857 3980",
    "sg:postcode":"49224",
    "sg:province":"MI",
    "sg:tags":[
        "house"
    ],
    "wof:name":"P & S Carpentery",
    "wof:placetype":"venue"
},
  "geometry": {"coordinates":[-84.65284800000001,42.334412],"type":"Point"}
}