{
  "type": "Feature",
  "properties": {
    "iso:country":"US",
    "sg:address":"269 S Harris Rd",
    "sg:city":"Ypsilanti",
    "sg:classifiers":[
        {
            "category":"Health Services",
            "subcategory":"Hospital",
            "type":"Services"
        }
    ],
    "sg:phone":"+1 734 481 1370",
    "sg:postcode":"48198",
    "sg:province":"MI",
    "sg:tags":[
        "specialty"
    ],
    "wof:name":"Serenity House of Ypsilanti",
    "wof:placetype":"venue"
},
  "geometry": {"coordinates":[-83.582792,42.239421],"type":"Point"}
}