{
  "type": "Feature",
  "properties": {
    "iso:country":"US",
    "sg:address":"24200 Harper Ave",
    "sg:city":"Saint Clair Shores",
    "sg:classifiers":[
        {
            "category":"Restaurant",
            "type":"Food & Drink"
        }
    ],
    "sg:phone":"+1 586 774 7150",
    "sg:postcode":"48080",
    "sg:province":"MI",
    "sg:tags":[
        "pizza",
        "italian"
    ],
    "wof:name":"Pizza Hut",
    "wof:placetype":"venue"
},
  "geometry": {"coordinates":[-82.90454099999999,42.473043],"type":"Point"}
}