{
  "type": "Feature",
  "properties": {
    "iso:country":"US",
    "sg:address":"900 E Bellows St",
    "sg:city":"Mount Pleasant",
    "sg:classifiers":[
        {
            "category":"Health Services",
            "subcategory":"Doctor",
            "type":"Services"
        }
    ],
    "sg:phone":"+1 989 773 9081",
    "sg:postcode":"48858",
    "sg:province":"MI",
    "wof:name":"Egger Kenneth L",
    "wof:placetype":"venue"
},
  "geometry": {"coordinates":[-84.76623499999999,43.593537],"type":"Point"}
}