{
  "type": "Feature",
  "properties": {
    "iso:country":"US",
    "sg:address":"21 E Main St",
    "sg:city":"Fremont",
    "sg:classifiers":[
        {
            "category":"Shopping",
            "subcategory":"Hobbies, Toys, & Games",
            "type":"Retail Goods"
        }
    ],
    "sg:phone":"+1 231 924 8014",
    "sg:postcode":"49412",
    "sg:province":"MI",
    "wof:name":"Red Pine Crafts & Gifts",
    "wof:placetype":"venue"
},
  "geometry": {"coordinates":[-85.944659,43.467193],"type":"Point"}
}