{
  "type": "Feature",
  "properties": {
    "iso:country":"US",
    "sg:address":"901 Frost Rd",
    "sg:city":"Williamston",
    "sg:classifiers":[
        {
            "category":"Retail",
            "subcategory":"Animal Services",
            "type":"Services"
        }
    ],
    "sg:phone":"+1 517 655 4259",
    "sg:postcode":"48895",
    "sg:province":"MI",
    "wof:name":"Hart House Kennels",
    "wof:placetype":"venue"
},
  "geometry": {"coordinates":[-84.32691199999999,42.629723],"type":"Point"}
}