{
  "type": "Feature",
  "properties": {
    "iso:country":"US",
    "sg:address":"700 Brown Rd",
    "sg:city":"Auburn Hills",
    "sg:classifiers":[
        {
            "category":"Restaurant",
            "type":"Food & Drink"
        }
    ],
    "sg:menulink":"http://www.allmenus.com/mi/auburn-hills/13991-olive-garden-italian-restaurant/menu/",
    "sg:phone":"+1 248 393 1812",
    "sg:postcode":"48326",
    "sg:province":"MI",
    "sg:tags":[
        "italian"
    ],
    "wof:name":"Olive Garden Italian Restaurant",
    "wof:placetype":"venue"
},
  "geometry": {"coordinates":[-83.291554,42.707474],"type":"Point"}
}