{
  "type": "Feature",
  "properties": {
    "iso:country":"US",
    "sg:address":"1368 Division St",
    "sg:city":"Adrian",
    "sg:classifiers":[
        {
            "category":"Restaurant",
            "type":"Food & Drink"
        }
    ],
    "sg:phone":"+1 517 264 8058",
    "sg:postcode":"49221",
    "sg:province":"MI",
    "sg:website":"www.fazolis.com",
    "wof:name":"Fazoli's",
    "wof:placetype":"venue"
},
  "geometry": {"coordinates":[-84.03344300000001,41.876631],"type":"Point"}
}