{
  "type": "Feature",
  "properties": {
    "iso:country":"US",
    "sg:address":"5615 Chilson Rd",
    "sg:city":"Howell",
    "sg:classifiers":[
        {
            "category":"Building & Trades",
            "subcategory":"Construction",
            "type":"Services"
        }
    ],
    "sg:phone":"+1 810 227 2550",
    "sg:postcode":"48843",
    "sg:province":"MI",
    "sg:tags":[
        "water",
        "well",
        "drilling"
    ],
    "wof:name":"Keller Well Drilling Inc",
    "wof:placetype":"venue"
},
  "geometry": {"coordinates":[-83.85530199999999,42.518562],"type":"Point"}
}