{
  "type": "Feature",
  "properties": {
    "iso:country":"US",
    "sg:address":"3556 Apple Hill Dr SE",
    "sg:city":"Ada",
    "sg:classifiers":[
        {
            "category":"Professional",
            "subcategory":"Business Services",
            "type":"Services"
        }
    ],
    "sg:phone":"+1 616 682 0098",
    "sg:postcode":"49301",
    "sg:province":"MI",
    "wof:name":"Challenger Technology Inc",
    "wof:placetype":"venue"
},
  "geometry": {"coordinates":[-85.47696500000001,42.90035],"type":"Point"}
}