{
  "type": "Feature",
  "properties": {
    "iso:country":"US",
    "sg:address":"1643 Geddes Ave NW",
    "sg:city":"Grand Rapids",
    "sg:classifiers":[
        {
            "category":"Building & Trades",
            "subcategory":"Construction",
            "type":"Services"
        }
    ],
    "sg:phone":"+1 616 949 1860",
    "sg:postcode":"49534",
    "sg:province":"MI",
    "sg:tags":[
        "painter"
    ],
    "wof:name":"William Sterk Painters & Decor",
    "wof:placetype":"venue"
},
  "geometry": {"coordinates":[-85.75398300000001,42.994904],"type":"Point"}
}