{
  "type": "Feature",
  "properties": {
    "iso:country":"US",
    "sg:address":"8825 Krause Rd",
    "sg:city":"Engadine",
    "sg:classifiers":[
        {
            "category":"Wholesale",
            "subcategory":"Dairy",
            "type":"Manufacturing & Wholesale Goods"
        }
    ],
    "sg:phone":"+1 906 477 6680",
    "sg:postcode":"49827",
    "sg:province":"MI",
    "sg:tags":[
        "product"
    ],
    "wof:name":"Korenich Dairy Farm",
    "wof:placetype":"venue"
},
  "geometry": {"coordinates":[-85.550438,46.191999],"type":"Point"}
}