{
  "type": "Feature",
  "properties": {
    "iso:country":"US",
    "sg:address":"35367 Northmont Dr",
    "sg:city":"Farmington Hills",
    "sg:classifiers":[
        {
            "category":"Building & Trades",
            "subcategory":"Landscaping Services",
            "type":"Services"
        }
    ],
    "sg:phone":"+1 248 489 5955",
    "sg:postcode":"48331",
    "sg:province":"MI",
    "sg:tags":[
        "landscape",
        "contractor"
    ],
    "wof:name":"Lacoure Brothers Inc",
    "wof:placetype":"venue"
},
  "geometry": {"coordinates":[-83.39654400000001,42.507871],"type":"Point"}
}