{
  "type": "Feature",
  "properties": {
    "iso:country":"US",
    "sg:address":"2179 US Hwy 27 Bus",
    "sg:city":"St Johns",
    "sg:classifiers":[
        {
            "category":"Shopping",
            "subcategory":"Clothing, Apparel, & Fashions",
            "type":"Retail Goods"
        }
    ],
    "sg:phone":"+1 989 224 6599",
    "sg:postcode":"48879",
    "sg:province":"MI",
    "wof:name":"Fashion Bug",
    "wof:placetype":"venue"
},
  "geometry": {"coordinates":[-84.52016,42.929036],"type":"Point"}
}