{
  "type": "Feature",
  "properties": {
    "iso:country":"US",
    "sg:address":"4280 Matthew Ln",
    "sg:city":"White Lake",
    "sg:classifiers":[
        {
            "category":"Building & Trades",
            "subcategory":"Construction",
            "type":"Services"
        },
        {
            "category":"Building & Trades",
            "subcategory":"Landscaping Services",
            "type":"Services"
        }
    ],
    "sg:phone":"+1 248 889 9067",
    "sg:postcode":"48383",
    "sg:province":"MI",
    "sg:tags":[
        "heavy",
        "repair",
        "landscape",
        "contractor"
    ],
    "wof:name":"Progressive Irrigation Inc",
    "wof:placetype":"venue"
},
  "geometry": {"coordinates":[-83.537273,42.678537],"type":"Point"}
}