{
  "type": "Feature",
  "properties": {
    "iso:country":"US",
    "sg:address":"116 E Ash St",
    "sg:city":"Mason",
    "sg:classifiers":[
        {
            "category":"Shopping",
            "subcategory":"Crafts & Fabrics",
            "type":"Retail Goods"
        }
    ],
    "sg:phone":"+1 517 676 2973",
    "sg:postcode":"48854",
    "sg:province":"MI",
    "sg:tags":[
        "sewing"
    ],
    "wof:name":"Yards Of Fabric",
    "wof:placetype":"venue"
},
  "geometry": {"coordinates":[-84.44162900000001,42.579132],"type":"Point"}
}