{
  "type": "Feature",
  "properties": {
    "iso:country":"US",
    "sg:address":"1376 Ready St",
    "sg:city":"Burton",
    "sg:classifiers":[
        {
            "category":"Wholesale",
            "subcategory":"Durable Goods & Equipment",
            "type":"Manufacturing & Wholesale Goods"
        }
    ],
    "sg:phone":"+1 810 742 0770",
    "sg:postcode":"48529",
    "sg:province":"MI",
    "sg:tags":[
        "compact",
        "record",
        "disc",
        "tape"
    ],
    "wof:name":"Tawas Record Inc",
    "wof:placetype":"venue"
},
  "geometry": {"coordinates":[-83.67659500000001,42.963447],"type":"Point"}
}