{
  "type": "Feature",
  "properties": {
    "iso:country":"US",
    "sg:address":"207 W Cayuga St",
    "sg:city":"Bellaire",
    "sg:classifiers":[
        {
            "category":"Government",
            "subcategory":"Fire Station",
            "type":"Public Place"
        }
    ],
    "sg:phone":"+1 231 587 9212",
    "sg:postcode":"49615",
    "sg:province":"MI",
    "sg:tags":[
        "department"
    ],
    "wof:name":"Mancelona Fire Dept",
    "wof:placetype":"venue"
},
  "geometry": {"coordinates":[-85.21497599999999,44.975343],"type":"Point"}
}