{
  "type": "Feature",
  "properties": {
    "iso:country":"US",
    "sg:address":"1985 E Wattles Rd Suite E",
    "sg:city":"Troy",
    "sg:classifiers":[
        {
            "category":"Personal",
            "subcategory":"Tanning Parlor",
            "type":"Services"
        }
    ],
    "sg:phone":"+1 248 524 1180",
    "sg:postcode":"48085",
    "sg:province":"MI",
    "sg:website":"www.uniquetanning.net",
    "wof:name":"Unique Tanning",
    "wof:placetype":"venue"
},
  "geometry": {"coordinates":[-83.10924300000001,42.578539],"type":"Point"}
}