{
  "type": "Feature",
  "properties": {
    "iso:country":"US",
    "sg:address":"409 W Main St",
    "sg:city":"Brighton",
    "sg:classifiers":[
        {
            "category":"Shopping",
            "type":"Retail Goods"
        }
    ],
    "sg:phone":"+1 810 227 1477",
    "sg:postcode":"48116",
    "sg:province":"MI",
    "sg:tags":[
        "coin",
        "supply"
    ],
    "wof:name":"Brighton Coins Inc",
    "wof:placetype":"venue"
},
  "geometry": {"coordinates":[-83.783956,42.529477],"type":"Point"}
}