{
  "type": "Feature",
  "properties": {
    "iso:country":"US",
    "sg:address":"8675 E State Rd",
    "sg:city":"Nashville",
    "sg:classifiers":[
        {
            "category":"Building & Trades",
            "subcategory":"Construction",
            "type":"Services"
        }
    ],
    "sg:phone":"+1 517 852 9838",
    "sg:postcode":"49073",
    "sg:province":"MI",
    "sg:tags":[
        "carpentry",
        "contractor"
    ],
    "wof:name":"Need Help Call Bubba",
    "wof:placetype":"venue"
},
  "geometry": {"coordinates":[-85.121762,42.639617],"type":"Point"}
}