{
  "type": "Feature",
  "properties": {
    "iso:country":"US",
    "sg:address":"4300 W Pierson Rd",
    "sg:city":"Flint",
    "sg:classifiers":[
        {
            "category":"Travel",
            "subcategory":"Hotels & Motels",
            "type":"Entertainment"
        }
    ],
    "sg:phone":"+1 810 732 0400",
    "sg:postcode":"48504",
    "sg:province":"MI",
    "sg:website":"www.ramadaflint.com",
    "wof:name":"Sheraton Inn",
    "wof:placetype":"venue"
},
  "geometry": {"coordinates":[-83.762912,43.060722],"type":"Point"}
}