{
  "type": "Feature",
  "properties": {
    "iso:country":"US",
    "sg:address":"947 Covell Ave NW",
    "sg:city":"Grand Rapids",
    "sg:classifiers":[
        {
            "category":"Arts & Performance",
            "subcategory":"Theater",
            "type":"Entertainment"
        }
    ],
    "sg:phone":"+1 616 791 6933",
    "sg:postcode":"49504",
    "sg:province":"MI",
    "sg:tags":[
        "live",
        "music"
    ],
    "wof:name":"Party Down Music",
    "wof:placetype":"venue"
},
  "geometry": {"coordinates":[-85.717371,42.983077],"type":"Point"}
}