{
  "type": "Feature",
  "properties": {
    "iso:country":"US",
    "sg:address":"1495 E Empire Ave",
    "sg:city":"Benton Harbor",
    "sg:classifiers":[
        {
            "category":"Organizations",
            "subcategory":"Religious Organization",
            "type":"Services"
        }
    ],
    "sg:phone":"+1 269 925 3686",
    "sg:postcode":"49022",
    "sg:province":"MI",
    "sg:website":"www.parrett.net/~bhcoc",
    "wof:name":"Church Of Christ",
    "wof:placetype":"venue"
},
  "geometry": {"coordinates":[-86.419269,42.101545],"type":"Point"}
}