{
  "type": "Feature",
  "properties": {
    "iso:country":"US",
    "sg:address":"22456 Orchard Lake Rd",
    "sg:city":"Farmington",
    "sg:classifiers":[
        {
            "category":"Retail",
            "subcategory":"Auto Repair",
            "type":"Services"
        }
    ],
    "sg:phone":"+1 248 477 4767",
    "sg:postcode":"48336",
    "sg:province":"MI",
    "sg:tags":[
        "automotive"
    ],
    "wof:name":"Carrail Service",
    "wof:placetype":"venue"
},
  "geometry": {"coordinates":[-83.356301,42.457702],"type":"Point"}
}