{
  "type": "Feature",
  "properties": {
    "iso:country":"US",
    "sg:address":"1209 Spencer Woods Dr",
    "sg:city":"Muskegon",
    "sg:classifiers":[
        {
            "category":"Building & Trades",
            "subcategory":"Construction",
            "type":"Services"
        }
    ],
    "sg:phone":"+1 231 744 5762",
    "sg:postcode":"49445",
    "sg:province":"MI",
    "sg:tags":[
        "general",
        "contractor"
    ],
    "wof:name":"D-Kal Inc",
    "wof:placetype":"venue"
},
  "geometry": {"coordinates":[-86.226606,43.277829],"type":"Point"}
}