{
  "type": "Feature",
  "properties": {
    "iso:country":"US",
    "sg:address":"914 S 26th St",
    "sg:city":"Saginaw",
    "sg:classifiers":[
        {
            "category":"Social Services",
            "subcategory":"Child Care",
            "type":"Services"
        }
    ],
    "sg:phone":"+1 989 759 0144",
    "sg:postcode":"48601",
    "sg:province":"MI",
    "wof:name":"Ebony's Daycare",
    "wof:placetype":"venue"
},
  "geometry": {"coordinates":[-83.903175,43.416517],"type":"Point"}
}