{
  "type": "Feature",
  "properties": {
    "iso:country":"US",
    "sg:address":"7903 E Birch Point Rd",
    "sg:city":"Traverse City",
    "sg:classifiers":[
        {
            "category":"Real Estate",
            "subcategory":"Real Estate Operator",
            "type":"Services"
        }
    ],
    "sg:phone":"+1 231 946 2378",
    "sg:postcode":"49684",
    "sg:province":"MI",
    "sg:tags":[
        "mobile",
        "home",
        "community"
    ],
    "wof:name":"First Point Mobile Home Court",
    "wof:placetype":"venue"
},
  "geometry": {"coordinates":[-85.701081,44.844959],"type":"Point"}
}