{
  "type": "Feature",
  "properties": {
    "iso:country":"US",
    "sg:address":"3260 Coolidge Hwy",
    "sg:city":"Berkley",
    "sg:classifiers":[
        {
            "category":"Banks & Credit Unions",
            "subcategory":"Bank",
            "type":"Services"
        }
    ],
    "sg:phone":"+1 248 548 7655",
    "sg:postcode":"48072",
    "sg:province":"MI",
    "sg:tags":[
        "loan",
        "real estate"
    ],
    "wof:name":"Prime Financial Group",
    "wof:placetype":"venue"
},
  "geometry": {"coordinates":[-83.18379299999999,42.501755],"type":"Point"}
}