{
  "type": "Feature",
  "properties": {
    "iso:country":"US",
    "sg:address":"1 W Chicago St",
    "sg:city":"Quincy",
    "sg:classifiers":[
        {
            "category":"Food & Beverages",
            "subcategory":"Groceries & Convenience Stores",
            "type":"Retail Goods"
        }
    ],
    "sg:phone":"+1 517 639 7108",
    "sg:postcode":"49082",
    "sg:province":"MI",
    "wof:name":"Quincy Sav-Mart",
    "wof:placetype":"venue"
},
  "geometry": {"coordinates":[-84.88398599999999,41.944215],"type":"Point"}
}