{
  "type": "Feature",
  "properties": {
    "iso:country":"US",
    "sg:address":"2354 Middlecroft Dr",
    "sg:city":"Burton",
    "sg:classifiers":[
        {
            "category":"Professional",
            "subcategory":"Business Services",
            "type":"Services"
        }
    ],
    "sg:phone":"+1 810 742 4434",
    "sg:postcode":"48509",
    "sg:province":"MI",
    "sg:tags":[
        "lecture",
        "bureau",
        "seminar"
    ],
    "wof:name":"Anesthesia Seminars",
    "wof:placetype":"venue"
},
  "geometry": {"coordinates":[-83.583556,43.045262],"type":"Point"}
}