{
  "type": "Feature",
  "properties": {
    "iso:country":"US",
    "sg:address":"127 E Territorial Rd",
    "sg:city":"Battle Creek",
    "sg:classifiers":[
        {
            "category":"Retail",
            "subcategory":"Laundry & Dry Cleaning",
            "type":"Services"
        }
    ],
    "sg:phone":"+1 269 962 1703",
    "sg:postcode":"49015",
    "sg:province":"MI",
    "wof:name":"Handy Mens Store",
    "wof:placetype":"venue"
},
  "geometry": {"coordinates":[-85.192359,42.304773],"type":"Point"}
}