{
  "type": "Feature",
  "properties": {
    "iso:country":"US",
    "sg:address":"2038 W Coachlight Dr",
    "sg:city":"Jackson",
    "sg:classifiers":[
        {
            "category":"Recreation",
            "type":"Entertainment"
        }
    ],
    "sg:phone":"+1 517 782 6115",
    "sg:postcode":"49201",
    "sg:province":"MI",
    "sg:tags":[
        "beer",
        "complex",
        "softball",
        "wine"
    ],
    "wof:name":"Cooperstown Softball Complex",
    "wof:placetype":"venue"
},
  "geometry": {"coordinates":[-84.477198,42.229112],"type":"Point"}
}