{
  "type": "Feature",
  "properties": {
    "iso:country":"US",
    "sg:address":"8565 Lake Rd",
    "sg:city":"Grosse Ile",
    "sg:classifiers":[
        {
            "category":"Social Services",
            "subcategory":"Adult Care",
            "type":"Services"
        }
    ],
    "sg:phone":"+1 734 692 3805",
    "sg:postcode":"48138",
    "sg:province":"MI",
    "sg:tags":[
        "foster"
    ],
    "wof:name":"Lake Avenue Home",
    "wof:placetype":"venue"
},
  "geometry": {"coordinates":[-83.157094,42.109045],"type":"Point"}
}