{
  "type": "Feature",
  "properties": {
    "iso:country":"US",
    "sg:address":"3820 N Nicholson Rd",
    "sg:city":"Fowlerville",
    "sg:classifiers":[
        {
            "category":"Manufacturing",
            "subcategory":"Rubber & Plastics",
            "type":"Manufacturing & Wholesale Goods"
        }
    ],
    "sg:phone":"+1 517 521 4905",
    "sg:postcode":"48836",
    "sg:province":"MI",
    "wof:name":"Eckert Manufacturing Co",
    "wof:placetype":"venue"
},
  "geometry": {"coordinates":[-84.112337,42.655839],"type":"Point"}
}