{
  "type": "Feature",
  "properties": {
    "iso:country":"US",
    "sg:address":"14566 Mark Twain St",
    "sg:city":"Detroit",
    "sg:classifiers":[
        {
            "category":"Social Services",
            "type":"Services"
        }
    ],
    "sg:phone":"+1 313 836 5232",
    "sg:postcode":"48227",
    "sg:province":"MI",
    "wof:name":"Jones Preschool & Daycare Co",
    "wof:placetype":"venue"
},
  "geometry": {"coordinates":[-83.186311,42.396508],"type":"Point"}
}