{
  "type": "Feature",
  "properties": {
    "iso:country":"US",
    "sg:address":"2555 12 Mile Rd",
    "sg:city":"Berkley",
    "sg:classifiers":[
        {
            "category":"Professional",
            "type":"Services"
        }
    ],
    "sg:phone":"+1 248 399 6750",
    "sg:postcode":"48072",
    "sg:province":"MI",
    "sg:tags":[
        "caterer"
    ],
    "wof:name":"O'mara Inc",
    "wof:placetype":"venue"
},
  "geometry": {"coordinates":[-83.184538,42.503072],"type":"Point"}
}