{
  "type": "Feature",
  "properties": {
    "iso:country":"US",
    "sg:address":"206 Scheurmann St",
    "sg:city":"Essexville",
    "sg:classifiers":[
        {
            "category":"Organizations",
            "subcategory":"Religious Organization",
            "type":"Services"
        }
    ],
    "sg:phone":"+1 989 893 8031",
    "sg:postcode":"48732",
    "sg:province":"MI",
    "sg:tags":[
        "church"
    ],
    "wof:name":"St Luke's United Methodist Chr",
    "wof:placetype":"venue"
},
  "geometry": {"coordinates":[-83.847402,43.605165],"type":"Point"}
}