{
  "type": "Feature",
  "properties": {
    "iso:country":"US",
    "sg:address":"2626 Walker Ave NW",
    "sg:city":"Grand Rapids",
    "sg:classifiers":[
        {
            "category":"Social Services",
            "subcategory":"Child Care",
            "type":"Services"
        }
    ],
    "sg:phone":"+1 616 453 4145",
    "sg:postcode":"49544",
    "sg:province":"MI",
    "sg:tags":[
        "kindergarten",
        "academic",
        "school"
    ],
    "sg:website":"www.headstartinfo.org",
    "wof:name":"Kent County Head Start",
    "wof:placetype":"venue"
},
  "geometry": {"coordinates":[-85.722539,43.011241],"type":"Point"}
}