{
  "type": "Feature",
  "properties": {
    "iso:country":"US",
    "sg:address":"905 Cedar St",
    "sg:city":"Tawas City",
    "sg:classifiers":[
        {
            "category":"Manufacturing",
            "subcategory":"Retail Goods",
            "type":"Manufacturing & Wholesale Goods"
        }
    ],
    "sg:phone":"+1 989 362 7692",
    "sg:postcode":"48763",
    "sg:province":"MI",
    "sg:tags":[
        "manufacturer"
    ],
    "wof:name":"Tawas Industries Inc",
    "wof:placetype":"venue"
},
  "geometry": {"coordinates":[-83.505216,44.279087],"type":"Point"}
}