{
  "type": "Feature",
  "properties": {
    "iso:country":"US",
    "sg:address":"55 Pack St",
    "sg:city":"Harbor Beach",
    "sg:classifiers":[
        {
            "category":"Health Services",
            "subcategory":"Health Practitioner",
            "type":"Services"
        }
    ],
    "sg:phone":"+1 989 479 6097",
    "sg:postcode":"48441",
    "sg:province":"MI",
    "sg:tags":[
        "therapist",
        "physical"
    ],
    "wof:name":"Sports Plus Care",
    "wof:placetype":"venue"
},
  "geometry": {"coordinates":[-82.650941,43.849393],"type":"Point"}
}