{
  "type": "Feature",
  "properties": {
    "iso:country":"US",
    "sg:address":"116 E Front St",
    "sg:city":"Traverse City",
    "sg:classifiers":[
        {
            "category":"Banks & Credit Unions",
            "subcategory":"Investment Brokerage",
            "type":"Services"
        }
    ],
    "sg:phone":"+1 231 947 5333",
    "sg:postcode":"49684",
    "sg:province":"MI",
    "sg:tags":[
        "consultant",
        "planning",
        "financial"
    ],
    "wof:name":"Dawn Webster Financial Inc",
    "wof:placetype":"venue"
},
  "geometry": {"coordinates":[-85.621336,44.763983],"type":"Point"}
}