{
  "type": "Feature",
  "properties": {
    "iso:country":"US",
    "sg:address":"9610 Highland Rd",
    "sg:city":"White Lake",
    "sg:classifiers":[
        {
            "category":"Freight",
            "type":"Transportation"
        }
    ],
    "sg:phone":"+1 248 698 3031",
    "sg:postcode":"48386",
    "sg:province":"MI",
    "sg:tags":[
        "commercial",
        "storage"
    ],
    "wof:name":"Dixie Lock-Up",
    "wof:placetype":"venue"
},
  "geometry": {"coordinates":[-83.484028,42.653192],"type":"Point"}
}