{
  "type": "Feature",
  "properties": {
    "iso:country":"US",
    "sg:address":"100 N Main St",
    "sg:city":"Cheboygan",
    "sg:classifiers":[
        {
            "category":"Restaurant",
            "type":"Food & Drink"
        }
    ],
    "sg:menulink":"http://www.allmenus.com/mi/cheboygan/176353-kfc---kentucky-fried-chicken/menu/",
    "sg:phone":"+1 616 627 3176",
    "sg:postcode":"49721",
    "sg:province":"MI",
    "sg:tags":[
        "american",
        "chicken"
    ],
    "wof:name":"KFC - Kentucky Fried Chicken",
    "wof:placetype":"venue"
},
  "geometry": {"coordinates":[-84.478105,45.643085],"type":"Point"}
}