{
  "type": "Feature",
  "properties": {
    "iso:country":"US",
    "sg:address":"524 W 14th St",
    "sg:city":"Traverse City",
    "sg:classifiers":[
        {
            "category":"Restaurant",
            "type":"Food & Drink"
        }
    ],
    "sg:menulink":"http://www.allmenus.com/mi/traverse-city/142297-subway/menu/",
    "sg:phone":"+1 231 929 7240",
    "sg:postcode":"49684",
    "sg:province":"MI",
    "sg:tags":[
        "american",
        "sandwich"
    ],
    "wof:name":"Subway",
    "wof:placetype":"venue"
},
  "geometry": {"coordinates":[-85.631106,44.751684],"type":"Point"}
}