{
  "type": "Feature",
  "properties": {
    "iso:country":"US",
    "sg:address":"38600 Van Dyke Ave Ste 240",
    "sg:city":"Sterling Heights",
    "sg:classifiers":[
        {
            "category":"Professional",
            "subcategory":"Lawyer & Legal Services",
            "type":"Services"
        }
    ],
    "sg:phone":"+1 586 795 2375",
    "sg:postcode":"48312",
    "sg:province":"MI",
    "wof:name":"Law Offices of Richard S Mroczka",
    "wof:placetype":"venue"
},
  "geometry": {"coordinates":[-83.029774,42.577518],"type":"Point"}
}