{
  "type": "Feature",
  "properties": {
    "iso:country":"US",
    "sg:address":"2903 Biddle St",
    "sg:city":"Wyandotte",
    "sg:classifiers":[
        {
            "category":"Manufacturing",
            "subcategory":"Apparel",
            "type":"Manufacturing & Wholesale Goods"
        }
    ],
    "sg:phone":"+1 734 283 3305",
    "sg:postcode":"48192",
    "sg:province":"MI",
    "sg:tags":[
        "personal",
        "mfg"
    ],
    "wof:name":"Why Not Costumes Inc",
    "wof:placetype":"venue"
},
  "geometry": {"coordinates":[-83.149225,42.203206],"type":"Point"}
}