{
  "type": "Feature",
  "properties": {
    "iso:country":"US",
    "sg:address":"3160 Continental Dr",
    "sg:city":"Traverse City",
    "sg:classifiers":[
        {
            "category":"Building & Trades",
            "subcategory":"Plumbing",
            "type":"Services"
        }
    ],
    "sg:phone":"+1 231 929 3221",
    "sg:postcode":"49686",
    "sg:province":"MI",
    "sg:tags":[
        "plumbing",
        "contractor"
    ],
    "wof:name":"Taylor Plumbing & Heating",
    "wof:placetype":"venue"
},
  "geometry": {"coordinates":[-85.5827,44.732521],"type":"Point"}
}