{
  "type": "Feature",
  "properties": {
    "iso:country":"US",
    "sg:address":"6107 David Berger Dr",
    "sg:city":"Mount Morris",
    "sg:classifiers":[
        {
            "category":"Professional",
            "subcategory":"Business Services",
            "type":"Services"
        }
    ],
    "sg:phone":"+1 810 785 1286",
    "sg:postcode":"48458",
    "sg:province":"MI",
    "wof:name":"Cgm Productions",
    "wof:placetype":"venue"
},
  "geometry": {"coordinates":[-83.70970699999999,43.096053],"type":"Point"}
}