{
  "type": "Feature",
  "properties": {
    "iso:country":"US",
    "sg:address":"12308 Field Rd",
    "sg:city":"Clio",
    "sg:classifiers":[
        {
            "category":"Professional",
            "subcategory":"Management & Consulting",
            "type":"Services"
        }
    ],
    "sg:phone":"+1 810 686 1872",
    "sg:postcode":"48420",
    "sg:province":"MI",
    "wof:name":"Geg Advisors",
    "wof:placetype":"venue"
},
  "geometry": {"coordinates":[-83.784003,43.188319],"type":"Point"}
}