{
  "type": "Feature",
  "properties": {
    "iso:country":"US",
    "sg:address":"6200 Overlook Rd",
    "sg:city":"Clarkston",
    "sg:classifiers":[
        {
            "category":"Building & Trades",
            "subcategory":"Plumbing",
            "type":"Services"
        }
    ],
    "sg:phone":"+1 248 922 9650",
    "sg:postcode":"48346",
    "sg:province":"MI",
    "sg:tags":[
        "heating",
        "contractor"
    ],
    "wof:name":"Bowers Heating & Air Cond",
    "wof:placetype":"venue"
},
  "geometry": {"coordinates":[-83.420332,42.729417],"type":"Point"}
}