{
  "type": "Feature",
  "properties": {
    "iso:country":"US",
    "sg:address":"4852 Leafdale Blvd",
    "sg:city":"Royal Oak",
    "sg:classifiers":[
        {
            "category":"Building & Trades",
            "subcategory":"Plumbing",
            "type":"Services"
        }
    ],
    "sg:phone":"+1 248 435 6344",
    "sg:postcode":"48073",
    "sg:province":"MI",
    "wof:name":"Gp Sumner",
    "wof:placetype":"venue"
},
  "geometry": {"coordinates":[-83.175659,42.53341],"type":"Point"}
}