{
  "type": "Feature",
  "properties": {
    "iso:country":"US",
    "sg:address":"699 W Parmeter Rd",
    "sg:city":"Ionia",
    "sg:classifiers":[
        {
            "category":"Building & Trades",
            "subcategory":"Equipment Rental",
            "type":"Services"
        }
    ],
    "sg:phone":"+1 616 527 2626",
    "sg:postcode":"48846",
    "sg:province":"MI",
    "sg:tags":[
        "heavy",
        "construction"
    ],
    "wof:name":"Cook Bldrs Crane Rental G",
    "wof:placetype":"venue"
},
  "geometry": {"coordinates":[-85.086803,43.023621],"type":"Point"}
}