{
  "type": "Feature",
  "properties": {
    "iso:country":"US",
    "sg:address":"3901 Grand River Ave Ofc",
    "sg:city":"Detroit",
    "sg:classifiers":[
        {
            "category":"Real Estate",
            "subcategory":"Real Estate Operator",
            "type":"Services"
        }
    ],
    "sg:phone":"+1 313 831 3900",
    "sg:postcode":"48208",
    "sg:province":"MI",
    "sg:tags":[
        "apartment"
    ],
    "wof:name":"Roberts III Apartments",
    "wof:placetype":"venue"
},
  "geometry": {"coordinates":[-83.076797,42.343601],"type":"Point"}
}