{
  "type": "Feature",
  "properties": {
    "iso:country":"US",
    "sg:address":"15775 Middlebelt Rd",
    "sg:city":"Livonia",
    "sg:classifiers":[
        {
            "category":"Social Services",
            "subcategory":"Retirement Home",
            "type":"Services"
        }
    ],
    "sg:phone":"+1 734 522 5780",
    "sg:postcode":"48154",
    "sg:province":"MI",
    "wof:name":"Armenian Home For the Aged",
    "wof:placetype":"venue"
},
  "geometry": {"coordinates":[-83.3349,42.4025],"type":"Point"}
}