{
  "type": "Feature",
  "properties": {
    "iso:country":"US",
    "sg:address":"750 Brown Rd",
    "sg:city":"Auburn Hills",
    "sg:classifiers":[
        {
            "category":"Restaurant",
            "type":"Food & Drink"
        }
    ],
    "sg:menulink":"http://www.allmenus.com/mi/auburn-hills/43951-applebees/menu/",
    "sg:phone":"+1 248 393 1496",
    "sg:postcode":"48326",
    "sg:province":"MI",
    "sg:tags":[
        "burger",
        "american",
        "sandwich",
        "soup"
    ],
    "wof:name":"Applebee's",
    "wof:placetype":"venue"
},
  "geometry": {"coordinates":[-83.26187,42.708276],"type":"Point"}
}