{
  "type": "Feature",
  "properties": {
    "iso:country":"US",
    "sg:address":"45665 Riverwoods Dr",
    "sg:city":"Macomb",
    "sg:classifiers":[
        {
            "category":"Building & Trades",
            "subcategory":"Landscaping Services",
            "type":"Services"
        }
    ],
    "sg:phone":"+1 586 226 1380",
    "sg:postcode":"48044",
    "sg:province":"MI",
    "sg:tags":[
        "landscape"
    ],
    "wof:name":"Brownlee Landscaping",
    "wof:placetype":"venue"
},
  "geometry": {"coordinates":[-82.92246,42.629817],"type":"Point"}
}