{
  "type": "Feature",
  "properties": {
    "iso:country":"US",
    "sg:address":"817 Ravenwood Ct",
    "sg:city":"Mason",
    "sg:classifiers":[
        {
            "category":"Professional",
            "subcategory":"Business Services",
            "type":"Services"
        }
    ],
    "sg:phone":"+1 517 244 7222",
    "sg:postcode":"48854",
    "sg:province":"MI",
    "wof:name":"Retractable Screen Solutions",
    "wof:placetype":"venue"
},
  "geometry": {"coordinates":[-84.43084399999999,42.586189],"type":"Point"}
}