{
  "type": "Feature",
  "properties": {
    "iso:country":"US",
    "sg:address":"67797 Hartway Rd",
    "sg:city":"Ray",
    "sg:classifiers":[
        {
            "category":"Freight",
            "type":"Transportation"
        }
    ],
    "sg:phone":"+1 586 784 9508",
    "sg:postcode":"48096",
    "sg:province":"MI",
    "sg:tags":[
        "operator",
        "local",
        "trucking"
    ],
    "wof:name":"Dean Reinhartt Trucking",
    "wof:placetype":"venue"
},
  "geometry": {"coordinates":[-82.90307799999999,42.796641],"type":"Point"}
}