{
  "type": "Feature",
  "properties": {
    "iso:country":"US",
    "sg:address":"104 S Main St",
    "sg:city":"Evart",
    "sg:classifiers":[
        {
            "category":"Home & Garden",
            "subcategory":"Hardware",
            "type":"Retail Goods"
        }
    ],
    "sg:phone":"+1 231 734 5831",
    "sg:postcode":"49631",
    "sg:province":"MI",
    "wof:name":"Hometown Hardware",
    "wof:placetype":"venue"
},
  "geometry": {"coordinates":[-85.25954,43.900551],"type":"Point"}
}