{
  "type": "Feature",
  "properties": {
    "iso:country":"US",
    "sg:address":"7876 Kochville Rd",
    "sg:city":"Freeland",
    "sg:classifiers":[
        {
            "category":"Recreation",
            "subcategory":"Marina",
            "type":"Entertainment"
        }
    ],
    "sg:phone":"+1 989 695 9337",
    "sg:postcode":"48623",
    "sg:province":"MI",
    "sg:tags":[
        "repairing",
        "boat"
    ],
    "wof:name":"Becker Marine",
    "wof:placetype":"venue"
},
  "geometry": {"coordinates":[-84.065808,43.49548],"type":"Point"}
}