{
  "type": "Feature",
  "properties": {
    "iso:country":"US",
    "sg:address":"39885 Grand River Ave, Ste 200",
    "sg:city":"Novi",
    "sg:classifiers":[
        {
            "category":"Banks & Credit Unions",
            "subcategory":"Investment Brokerage",
            "type":"Services"
        },
        {
            "category":"Banks & Credit Unions",
            "subcategory":"Financial Services",
            "type":"Services"
        }
    ],
    "sg:phone":"+1 248 893 0170",
    "sg:postcode":"48375",
    "sg:province":"MI",
    "sg:tags":[
        "investing",
        "advising"
    ],
    "sg:website":"www.ameripriseadvisors.com",
    "wof:name":"Ameriprise Financial Advisors - Amy L. Smith & Associates",
    "wof:placetype":"venue"
},
  "geometry": {"coordinates":[-83.436607,42.472075],"type":"Point"}
}