{
  "type": "Feature",
  "properties": {
    "iso:country":"US",
    "sg:address":"233 Silman St",
    "sg:city":"Ferndale",
    "sg:classifiers":[
        {
            "category":"Retail",
            "subcategory":"Laundry & Dry Cleaning",
            "type":"Services"
        }
    ],
    "sg:phone":"+1 248 790 2694",
    "sg:postcode":"48220",
    "sg:province":"MI",
    "sg:tags":[
        "chimney"
    ],
    "wof:name":"Shades Of Grey Construction",
    "wof:placetype":"venue"
},
  "geometry": {"coordinates":[-83.127853,42.451951],"type":"Point"}
}