{
  "type": "Feature",
  "properties": {
    "iso:country":"US",
    "sg:address":"24710 Willowbrook Dr",
    "sg:city":"Novi",
    "sg:classifiers":[
        {
            "category":"Professional",
            "subcategory":"Computer Services",
            "type":"Services"
        }
    ],
    "sg:phone":"+1 248 477 6119",
    "sg:postcode":"48375",
    "sg:province":"MI",
    "sg:tags":[
        "internet"
    ],
    "wof:name":"Easy Internet Access Inc",
    "wof:placetype":"venue"
},
  "geometry": {"coordinates":[-83.445802,42.470794],"type":"Point"}
}