{
  "type": "Feature",
  "properties": {
    "iso:country":"US",
    "sg:address":"12838 Masters Rd",
    "sg:city":"Memphis",
    "sg:classifiers":[
        {
            "category":"Real Estate",
            "subcategory":"Real Estate Agent",
            "type":"Services"
        }
    ],
    "sg:phone":"+1 810 392 2818",
    "sg:postcode":"48041",
    "sg:province":"MI",
    "wof:name":"Heritage Way LLC",
    "wof:placetype":"venue"
},
  "geometry": {"coordinates":[-82.836467,42.939961],"type":"Point"}
}