{
  "type": "Feature",
  "properties": {
    "iso:country":"US",
    "sg:address":"2400 Lee Dr",
    "sg:city":"Bay City",
    "sg:classifiers":[
        {
            "category":"Professional",
            "subcategory":"Business Services",
            "type":"Services"
        }
    ],
    "sg:phone":"+1 989 893 2866",
    "sg:postcode":"48708",
    "sg:province":"MI",
    "wof:name":"Lee Moeller Interior Design",
    "wof:placetype":"venue"
},
  "geometry": {"coordinates":[-83.856402,43.596508],"type":"Point"}
}