{
  "type": "Feature",
  "properties": {
    "iso:country":"US",
    "sg:address":"1474 Johnson St",
    "sg:city":"Dansville",
    "sg:classifiers":[
        {
            "category":"Building & Trades",
            "subcategory":"Construction",
            "type":"Services"
        }
    ],
    "sg:phone":"+1 517 623 0007",
    "sg:postcode":"48819",
    "sg:province":"MI",
    "sg:tags":[
        "marking",
        "maintenance",
        "parking"
    ],
    "wof:name":"Dansville Dept Of Public Works",
    "wof:placetype":"venue"
},
  "geometry": {"coordinates":[-84.30137000000001,42.549854],"type":"Point"}
}