{
  "type": "Feature",
  "properties": {
    "iso:country":"US",
    "sg:address":"301 S 5th St",
    "sg:city":"Grand Haven",
    "sg:classifiers":[
        {
            "category":"Travel",
            "subcategory":"Hotels & Motels",
            "type":"Entertainment"
        }
    ],
    "sg:phone":"+1 616 846 3538",
    "sg:postcode":"49417",
    "sg:province":"MI",
    "sg:tags":[
        "operation"
    ],
    "wof:name":"Boyden House Bed & Breakfast",
    "wof:placetype":"venue"
},
  "geometry": {"coordinates":[-86.22763399999999,43.060004],"type":"Point"}
}