{
  "type": "Feature",
  "properties": {
    "iso:country":"US",
    "sg:address":"237 Hubbard St",
    "sg:city":"Allegan",
    "sg:classifiers":[
        {
            "category":"Professional",
            "subcategory":"Computer Services",
            "type":"Services"
        }
    ],
    "sg:phone":"+1 269 686 8648",
    "sg:postcode":"49010",
    "sg:province":"MI",
    "sg:tags":[
        "internet"
    ],
    "wof:name":"West Michigan Wireless Isp",
    "wof:placetype":"venue"
},
  "geometry": {"coordinates":[-85.850233,42.527582],"type":"Point"}
}