{
  "type": "Feature",
  "properties": {
    "iso:country":"US",
    "sg:address":"12955 Grand River Ave",
    "sg:city":"Detroit",
    "sg:classifiers":[
        {
            "category":"Food & Beverages",
            "subcategory":"Groceries & Convenience Stores",
            "type":"Retail Goods"
        }
    ],
    "sg:phone":"+1 313 934 1000",
    "sg:postcode":"48227",
    "sg:province":"MI",
    "wof:name":"Grand Price Food Center",
    "wof:placetype":"venue"
},
  "geometry": {"coordinates":[-83.170998,42.381599],"type":"Point"}
}