{
  "type": "Feature",
  "properties": {
    "iso:country":"US",
    "sg:address":"811 W State St",
    "sg:city":"St Johns",
    "sg:classifiers":[
        {
            "category":"Professional",
            "subcategory":"Testing Lab",
            "type":"Services"
        },
        {
            "category":"Professional",
            "subcategory":"Business Services",
            "type":"Services"
        }
    ],
    "sg:phone":"+1 989 224 2642",
    "sg:postcode":"48879",
    "sg:province":"MI",
    "sg:tags":[
        "specializing",
        "construction",
        "ma"
    ],
    "wof:name":"Andrew's Material Testing",
    "wof:placetype":"venue"
},
  "geometry": {"coordinates":[-84.568617,43.001468],"type":"Point"}
}