{
  "type": "Feature",
  "properties": {
    "iso:country":"US",
    "sg:address":"719 Morningside Dr",
    "sg:city":"Grand Blanc",
    "sg:classifiers":[
        {
            "category":"Building & Trades",
            "subcategory":"Cleaning & Sanitation",
            "type":"Services"
        }
    ],
    "sg:phone":"+1 810 636 4484",
    "sg:postcode":"48439",
    "sg:province":"MI",
    "sg:tags":[
        "maintenance"
    ],
    "wof:name":"Jae Properties",
    "wof:placetype":"venue"
},
  "geometry": {"coordinates":[-83.608068,42.923017],"type":"Point"}
}