{
  "type": "Feature",
  "properties": {
    "iso:country":"US",
    "sg:address":"4707 Saint Antoine St",
    "sg:city":"Detroit",
    "sg:classifiers":[
        {
            "category":"Building & Trades",
            "subcategory":"Plumbing",
            "type":"Services"
        }
    ],
    "sg:phone":"+1 313 745 6899",
    "sg:postcode":"48201",
    "sg:province":"MI",
    "sg:tags":[
        "contractor"
    ],
    "wof:name":"Nih",
    "wof:placetype":"venue"
},
  "geometry": {"coordinates":[-83.05445,42.355543],"type":"Point"}
}