{
  "type": "Feature",
  "properties": {
    "iso:country":"US",
    "sg:address":"15520 W Warren Ave",
    "sg:city":"Detroit",
    "sg:classifiers":[
        {
            "category":"Restaurant",
            "type":"Food & Drink"
        }
    ],
    "sg:menulink":"http://www.allmenus.com/mi/detroit/247288-la-bella-pizza/menu/",
    "sg:phone":"+1 313 945 8200",
    "sg:postcode":"48228",
    "sg:province":"MI",
    "sg:tags":[
        "american",
        "pizza"
    ],
    "wof:name":"La-bella Pizza",
    "wof:placetype":"venue"
},
  "geometry": {"coordinates":[-83.196529,42.343663],"type":"Point"}
}