{
  "type": "Feature",
  "properties": {
    "iso:country":"US",
    "sg:address":"207 E Monroe St",
    "sg:city":"Jackson",
    "sg:classifiers":[
        {
            "category":"Building & Trades",
            "subcategory":"Cleaning & Sanitation",
            "type":"Services"
        }
    ],
    "sg:phone":"+1 517 782 8749",
    "sg:postcode":"49202",
    "sg:province":"MI",
    "sg:tags":[
        "janitor"
    ],
    "wof:name":"White As Snow Cleaning Svc",
    "wof:placetype":"venue"
},
  "geometry": {"coordinates":[-84.39922300000001,42.264735],"type":"Point"}
}