{
  "type": "Feature",
  "properties": {
    "iso:country":"US",
    "sg:address":"1612 W Washington St",
    "sg:city":"Greenville",
    "sg:classifiers":[
        {
            "category":"Restaurant",
            "type":"Food & Drink"
        }
    ],
    "sg:menulink":"http://www.allmenus.com/mi/greenville/86813-little-caesars-pizza/menu/",
    "sg:phone":"+1 616 754 7171",
    "sg:postcode":"48838",
    "sg:province":"MI",
    "sg:tags":[
        "american",
        "pizza"
    ],
    "wof:name":"Little Caesar's Pizza",
    "wof:placetype":"venue"
},
  "geometry": {"coordinates":[-85.27834300000001,43.177175],"type":"Point"}
}