{
  "type": "Feature",
  "properties": {
    "iso:country":"US",
    "sg:address":"1620 E Saginaw St",
    "sg:city":"Lansing",
    "sg:classifiers":[
        {
            "category":"Government",
            "subcategory":"Office",
            "type":"Public Place"
        }
    ],
    "sg:phone":"+1 517 482 9150",
    "sg:postcode":"48912",
    "sg:province":"MI",
    "sg:tags":[
        "federal",
        "security"
    ],
    "wof:name":"US Naval Reserve Training Ctr",
    "wof:placetype":"venue"
},
  "geometry": {"coordinates":[-84.52611,42.740848],"type":"Point"}
}