{
  "type": "Feature",
  "properties": {
    "iso:country":"US",
    "sg:address":"302 Middle Dr",
    "sg:city":"Ypsilanti",
    "sg:classifiers":[
        {
            "category":"Government",
            "subcategory":"Office",
            "type":"Public Place"
        }
    ],
    "sg:phone":"+1 734 480 2829",
    "sg:postcode":"48197",
    "sg:province":"MI",
    "sg:tags":[
        "contract"
    ],
    "wof:name":"Pk Rabun Industries",
    "wof:placetype":"venue"
},
  "geometry": {"coordinates":[-83.62051,42.237975],"type":"Point"}
}