{
  "type": "Feature",
  "properties": {
    "iso:country":"US",
    "sg:address":"14345 Ironwood Dr NW",
    "sg:city":"Grand Rapids",
    "sg:classifiers":[
        {
            "category":"Personal",
            "subcategory":"Beauty Salon",
            "type":"Services"
        }
    ],
    "sg:phone":"+1 616 677 2284",
    "sg:postcode":"49544",
    "sg:province":"MI",
    "sg:tags":[
        "spa",
        "day"
    ],
    "wof:name":"Baths Of Caracalla",
    "wof:placetype":"venue"
},
  "geometry": {"coordinates":[-85.80743699999999,43.030561],"type":"Point"}
}