{
  "type": "Feature",
  "properties": {
    "iso:country":"US",
    "sg:address":"2842 N Tipsico Lake Rd",
    "sg:city":"Hartland",
    "sg:classifiers":[
        {
            "category":"Professional",
            "subcategory":"Computer Services",
            "type":"Services"
        }
    ],
    "sg:phone":"+1 248 245 2878",
    "sg:postcode":"48353",
    "sg:province":"MI",
    "sg:tags":[
        "design",
        "system"
    ],
    "wof:name":"Advanced Computer Support",
    "wof:placetype":"venue"
},
  "geometry": {"coordinates":[-83.686629,42.647081],"type":"Point"}
}