{
  "type": "Feature",
  "properties": {
    "iso:country":"US",
    "sg:address":"3717 Boulder Dr",
    "sg:city":"Troy",
    "sg:classifiers":[
        {
            "category":"Real Estate",
            "subcategory":"Real Estate Agent",
            "type":"Services"
        }
    ],
    "sg:phone":"+1 248 643 6895",
    "sg:postcode":"48084",
    "sg:province":"MI",
    "sg:tags":[
        "book"
    ],
    "wof:name":"Century 21",
    "wof:placetype":"venue"
},
  "geometry": {"coordinates":[-83.190617,42.571537],"type":"Point"}
}