{
  "type": "Feature",
  "properties": {
    "iso:country":"US",
    "sg:address":"7201 W Fort St",
    "sg:city":"Detroit",
    "sg:classifiers":[
        {
            "category":"Food & Beverages",
            "subcategory":"Groceries & Convenience Stores",
            "type":"Retail Goods"
        }
    ],
    "sg:phone":"+1 313 841 1111",
    "sg:postcode":"48209",
    "sg:province":"MI",
    "wof:name":"Fruit and Vegetable Mkt News",
    "wof:placetype":"venue"
},
  "geometry": {"coordinates":[-83.114284,42.302111],"type":"Point"}
}