{
  "type": "Feature",
  "properties": {
    "iso:country":"US",
    "sg:address":"395 3rd St",
    "sg:city":"Manistee",
    "sg:classifiers":[
        {
            "category":"Health Services",
            "subcategory":"Clinic",
            "type":"Services"
        }
    ],
    "sg:phone":"+1 231 723 6228",
    "sg:postcode":"49660",
    "sg:province":"MI",
    "sg:tags":[
        "specialty",
        "outpatient"
    ],
    "wof:name":"Manistee Counseling Center",
    "wof:placetype":"venue"
},
  "geometry": {"coordinates":[-86.322892,44.243985],"type":"Point"}
}