{
  "type": "Feature",
  "properties": {
    "iso:country":"US",
    "sg:address":"45424 Van Dyke Ave",
    "sg:city":"Utica",
    "sg:classifiers":[
        {
            "category":"Health Services",
            "subcategory":"Doctor",
            "type":"Services"
        }
    ],
    "sg:phone":"+1 586 739 4400",
    "sg:postcode":"48317",
    "sg:province":"MI",
    "sg:tags":[
        "dentist"
    ],
    "wof:name":"Thomas W Schmidt DDS PC",
    "wof:placetype":"venue"
},
  "geometry": {"coordinates":[-83.03243500000001,42.628199],"type":"Point"}
}