{
  "type": "Feature",
  "properties": {
    "iso:country":"US",
    "sg:address":"1235 University Dr",
    "sg:city":"Pontiac",
    "sg:classifiers":[
        {
            "category":"Organizations",
            "subcategory":"Labor Organization",
            "type":"Services"
        }
    ],
    "sg:phone":"+1 248 373 0774",
    "sg:postcode":"48342",
    "sg:province":"MI",
    "wof:name":"Security Police & Fire Pros",
    "wof:placetype":"venue"
},
  "geometry": {"coordinates":[-83.254237,42.659361],"type":"Point"}
}