{
  "type": "Feature",
  "properties": {
    "iso:country":"US",
    "sg:address":"1752 W Maple Rd",
    "sg:city":"Troy",
    "sg:classifiers":[
        {
            "category":"Retail",
            "subcategory":"Auto Repair",
            "type":"Services"
        }
    ],
    "sg:phone":"+1 248 649 3131",
    "sg:postcode":"48084",
    "sg:province":"MI",
    "sg:tags":[
        "automotive",
        "automobile",
        "customizing"
    ],
    "sg:website":"buzzoffauto.com/",
    "wof:name":"Buzz Off",
    "wof:placetype":"venue"
},
  "geometry": {"coordinates":[-83.170998,42.547901],"type":"Point"}
}