{
  "type": "Feature",
  "properties": {
    "iso:country":"US",
    "sg:address":"418 N Main St",
    "sg:city":"Frankenmuth",
    "sg:classifiers":[
        {
            "category":"Restaurant",
            "type":"Food & Drink"
        }
    ],
    "sg:menulink":"http://www.allmenus.com/mi/frankenmuth/86796-little-caesars-pizza/menu/",
    "sg:phone":"+1 989 652 3388",
    "sg:postcode":"48734",
    "sg:province":"MI",
    "sg:tags":[
        "american",
        "pizza"
    ],
    "wof:name":"Little Caesar's Pizza",
    "wof:placetype":"venue"
},
  "geometry": {"coordinates":[-83.738214,43.339876],"type":"Point"}
}