{
  "type": "Feature",
  "properties": {
    "iso:country":"US",
    "sg:address":"600 Cherry St",
    "sg:city":"Negaunee",
    "sg:classifiers":[
        {
            "category":"Government",
            "subcategory":"Office",
            "type":"Public Place"
        }
    ],
    "sg:phone":"+1 906 475 9993",
    "sg:postcode":"49866",
    "sg:province":"MI",
    "sg:tags":[
        "village"
    ],
    "wof:name":"Electric & TV Dept Maintenance",
    "wof:placetype":"venue"
},
  "geometry": {"coordinates":[-87.60065899999999,46.507469],"type":"Point"}
}