{
  "type": "Feature",
  "properties": {
    "iso:country":"US",
    "sg:address":"1375 E Main St SE",
    "sg:city":"Lowell",
    "sg:classifiers":[
        {
            "category":"Wholesale",
            "subcategory":"Machinery & Supplies",
            "type":"Manufacturing & Wholesale Goods"
        },
        {
            "category":"Government",
            "subcategory":"Fire Station",
            "type":"Public Place"
        }
    ],
    "sg:phone":"+1 616 897 0970",
    "sg:postcode":"49331",
    "sg:province":"MI",
    "sg:tags":[
        "protection",
        "sprinkler"
    ],
    "wof:name":"River City Fire Protection Inc",
    "wof:placetype":"venue"
},
  "geometry": {"coordinates":[-85.32277999999999,42.936721],"type":"Point"}
}