{
  "type": "Feature",
  "properties": {
    "iso:country":"US",
    "sg:address":"3663 Allegan Dam Rd",
    "sg:city":"Allegan",
    "sg:classifiers":[
        {
            "category":"Building & Trades",
            "subcategory":"Construction",
            "type":"Services"
        }
    ],
    "sg:phone":"+1 269 673 1671",
    "sg:postcode":"49010",
    "sg:province":"MI",
    "sg:tags":[
        "millwright"
    ],
    "wof:name":"Agri Equipment Svc",
    "wof:placetype":"venue"
},
  "geometry": {"coordinates":[-85.902541,42.557465],"type":"Point"}
}