{
  "type": "Feature",
  "properties": {
    "iso:country":"US",
    "sg:address":"8062 E Maple Rapids Rd",
    "sg:city":"Elsie",
    "sg:classifiers":[
        {
            "category":"Retail",
            "subcategory":"Repair Shop",
            "type":"Services"
        }
    ],
    "sg:phone":"+1 989 862 5698",
    "sg:postcode":"48831",
    "sg:province":"MI",
    "sg:tags":[
        "equipment",
        "industrial",
        "truck"
    ],
    "wof:name":"Mikes Service",
    "wof:placetype":"venue"
},
  "geometry": {"coordinates":[-84.406374,43.105992],"type":"Point"}
}