{
  "type": "Feature",
  "properties": {
    "iso:country":"US",
    "sg:address":"1577 N Leroy St",
    "sg:city":"Fenton",
    "sg:classifiers":[
        {
            "category":"Food & Beverages",
            "subcategory":"Groceries & Convenience Stores",
            "type":"Retail Goods"
        }
    ],
    "sg:phone":"+1 810 629 8343",
    "sg:postcode":"48430",
    "sg:province":"MI",
    "wof:name":"Sunoco Fenton Plus",
    "wof:placetype":"venue"
},
  "geometry": {"coordinates":[-83.70762999999999,42.81801],"type":"Point"}
}