{
  "type": "Feature",
  "properties": {
    "iso:country":"US",
    "sg:address":"42333 Garfield Rd",
    "sg:city":"Clinton Twp",
    "sg:classifiers":[
        {
            "category":"Banks & Credit Unions",
            "subcategory":"Bank",
            "type":"Services"
        }
    ],
    "sg:phone":"+1 586 228 5977",
    "sg:postcode":"48038",
    "sg:province":"MI",
    "sg:tags":[
        "loan",
        "real estate"
    ],
    "wof:name":"Wolverine Finance & Mortgage",
    "wof:placetype":"venue"
},
  "geometry": {"coordinates":[-82.952834,42.607903],"type":"Point"}
}