{
  "type": "Feature",
  "properties": {
    "iso:country":"US",
    "sg:address":"15195 N Holly Rd",
    "sg:city":"Holly",
    "sg:classifiers":[
        {
            "category":"Banks & Credit Unions",
            "subcategory":"Bank",
            "type":"Services"
        }
    ],
    "sg:phone":"+1 248 634 4465",
    "sg:postcode":"48442",
    "sg:province":"MI",
    "sg:tags":[
        "state",
        "commercial"
    ],
    "wof:name":"Fifth Third Bank",
    "wof:placetype":"venue"
},
  "geometry": {"coordinates":[-83.628286,42.808494],"type":"Point"}
}