{
  "type": "Feature",
  "properties": {
    "iso:country":"US",
    "sg:address":"28650 Telegraph Rd",
    "sg:city":"Flat Rock",
    "sg:classifiers":[
        {
            "category":"Professional",
            "subcategory":"Printing & Photocopies",
            "type":"Services"
        }
    ],
    "sg:phone":"+1 734 782 0663",
    "sg:postcode":"48134",
    "sg:province":"MI",
    "wof:name":"Quality Copying & Printing Services Inc",
    "wof:placetype":"venue"
},
  "geometry": {"coordinates":[-83.292198,42.098499],"type":"Point"}
}