{
  "type": "Feature",
  "properties": {
    "iso:country":"US",
    "sg:address":"6360 Jackson Rd",
    "sg:city":"Ann Arbor",
    "sg:classifiers":[
        {
            "category":"Real Estate",
            "subcategory":"Developer",
            "type":"Services"
        }
    ],
    "sg:phone":"+1 734 996 1550",
    "sg:postcode":"48103",
    "sg:province":"MI",
    "sg:tags":[
        "development"
    ],
    "wof:name":"Norfolk Development Corp",
    "wof:placetype":"venue"
},
  "geometry": {"coordinates":[-83.858082,42.291321],"type":"Point"}
}