{
  "type": "Feature",
  "properties": {
    "iso:country":"US",
    "sg:address":"6862 Fox Ln",
    "sg:city":"Waterford",
    "sg:classifiers":[
        {
            "category":"Wholesale",
            "subcategory":"Sporting Goods",
            "type":"Manufacturing & Wholesale Goods"
        }
    ],
    "sg:phone":"+1 248 681 9640",
    "sg:postcode":"48327",
    "sg:province":"MI",
    "wof:name":"Real Stuff Sports Distributor",
    "wof:placetype":"venue"
},
  "geometry": {"coordinates":[-83.42061200000001,42.646835],"type":"Point"}
}