{
  "type": "Feature",
  "properties": {
    "iso:country":"US",
    "sg:address":"6664 Crofoot Rd",
    "sg:city":"Howell",
    "sg:classifiers":[
        {
            "category":"Building & Trades",
            "subcategory":"Construction",
            "type":"Services"
        }
    ],
    "sg:phone":"+1 517 223 4184",
    "sg:postcode":"48843",
    "sg:province":"MI",
    "sg:tags":[
        "carpentry",
        "contractor"
    ],
    "wof:name":"Hart Carpentry",
    "wof:placetype":"venue"
},
  "geometry": {"coordinates":[-84.04199199999999,42.585886],"type":"Point"}
}