{
  "type": "Feature",
  "properties": {
    "iso:country":"US",
    "sg:address":"2000 Town Center",
    "sg:city":"Southfield",
    "sg:classifiers":[
        {
            "category":"Professional",
            "subcategory":"Business Services",
            "type":"Services"
        },
        {
            "category":"Professional",
            "subcategory":"Management & Consulting",
            "type":"Services"
        }
    ],
    "sg:phone":"+1 248 355 1660",
    "sg:postcode":"48075",
    "sg:province":"MI",
    "sg:tags":[
        "promotion",
        "program",
        "meeting",
        "sales",
        "incentive"
    ],
    "sg:website":"www.mmi-incentives.com",
    "wof:name":"Motivational Marketing Inc",
    "wof:placetype":"venue"
},
  "geometry": {"coordinates":[-83.242964,42.475382],"type":"Point"}
}