{
  "type": "Feature",
  "properties": {
    "iso:country":"US",
    "sg:address":"4860 E Centre Ave",
    "sg:city":"Portage",
    "sg:classifiers":[
        {
            "category":"Wholesale",
            "subcategory":"Construction Materials",
            "type":"Manufacturing & Wholesale Goods"
        }
    ],
    "sg:phone":"+1 269 321 6488",
    "sg:postcode":"49002",
    "sg:province":"MI",
    "sg:tags":[
        "flag",
        "pole"
    ],
    "sg:website":"www.flagpolesandflags.com",
    "wof:name":"A-1 American Flagpoles & Flags",
    "wof:placetype":"venue"
},
  "geometry": {"coordinates":[-85.53142699999999,42.201101],"type":"Point"}
}