{
  "type": "Feature",
  "properties": {
    "iso:country":"US",
    "sg:address":"25917 W Michigan Ave",
    "sg:city":"Albion",
    "sg:classifiers":[
        {
            "category":"Professional",
            "type":"Services"
        }
    ],
    "sg:phone":"+1 517 629 6923",
    "sg:postcode":"49224",
    "sg:province":"MI",
    "sg:tags":[
        "establishment"
    ],
    "wof:name":"Starr Commonwealth",
    "wof:placetype":"venue"
},
  "geometry": {"coordinates":[-84.753359,42.246911],"type":"Point"}
}