{
  "type": "Feature",
  "properties": {
    "iso:country":"US",
    "sg:address":"2349 E Brooks Rd",
    "sg:city":"Freeland",
    "sg:classifiers":[
        {
            "category":"Farming",
            "subcategory":"Farm",
            "type":"Manufacturing & Wholesale Goods"
        }
    ],
    "sg:phone":"+1 989 839 5763",
    "sg:postcode":"48623",
    "sg:province":"MI",
    "sg:tags":[
        "crop",
        "general"
    ],
    "wof:name":"H&H Farms",
    "wof:placetype":"venue"
},
  "geometry": {"coordinates":[-84.271733,43.53946],"type":"Point"}
}