{
  "type": "Feature",
  "properties": {
    "iso:country":"US",
    "sg:address":"19601 Lyndon St",
    "sg:city":"Detroit",
    "sg:classifiers":[
        {
            "category":"Shopping",
            "subcategory":"Florist",
            "type":"Retail Goods"
        }
    ],
    "sg:phone":"+1 313 835 7820",
    "sg:postcode":"48223",
    "sg:province":"MI",
    "wof:name":"Pleasures Boutique",
    "wof:placetype":"venue"
},
  "geometry": {"coordinates":[-83.234735,42.393393],"type":"Point"}
}