{
  "type": "Feature",
  "properties": {
    "iso:country":"US",
    "sg:address":"619 N Cass Lake Rd",
    "sg:city":"Waterford",
    "sg:classifiers":[
        {
            "category":"Communications",
            "subcategory":"Film & Video Production",
            "type":"Services"
        }
    ],
    "sg:phone":"+1 248 738 1268",
    "sg:postcode":"48328",
    "sg:province":"MI",
    "sg:tags":[
        "taping"
    ],
    "wof:name":"Able Video Productions",
    "wof:placetype":"venue"
},
  "geometry": {"coordinates":[-83.356115,42.649881],"type":"Point"}
}