{
  "type": "Feature",
  "properties": {
    "iso:country":"US",
    "sg:address":"4106 Lake Michigan Dr NW",
    "sg:city":"Grand Rapids",
    "sg:classifiers":[
        {
            "category":"Real Estate",
            "subcategory":"Real Estate Agent",
            "type":"Services"
        }
    ],
    "sg:phone":"+1 616 791 6434",
    "sg:postcode":"49544",
    "sg:province":"MI",
    "wof:name":"Bisbee Realty LLC",
    "wof:placetype":"venue"
},
  "geometry": {"coordinates":[-85.767618,42.9722],"type":"Point"}
}