{
  "type": "Feature",
  "properties": {
    "iso:country":"US",
    "sg:address":"24773 Jefferson St",
    "sg:city":"Dowagiac",
    "sg:classifiers":[
        {
            "category":"Retail",
            "subcategory":"Auto Repair",
            "type":"Services"
        }
    ],
    "sg:phone":"+1 269 782 3510",
    "sg:postcode":"49047",
    "sg:province":"MI",
    "sg:tags":[
        "automotive"
    ],
    "wof:name":"Rogers Towing & Auto Recovery",
    "wof:placetype":"venue"
},
  "geometry": {"coordinates":[-86.044856,42.038054],"type":"Point"}
}