{
  "type": "Feature",
  "properties": {
    "iso:country":"US",
    "sg:address":"4455 Seaway Dr",
    "sg:city":"Lansing",
    "sg:classifiers":[
        {
            "category":"Personal",
            "subcategory":"Beauty Salon",
            "type":"Services"
        }
    ],
    "sg:phone":"+1 517 272 5140",
    "sg:postcode":"48911",
    "sg:province":"MI",
    "wof:name":"Crystal's Hair Styles",
    "wof:placetype":"venue"
},
  "geometry": {"coordinates":[-84.609752,42.688695],"type":"Point"}
}