{
  "type": "Feature",
  "properties": {
    "iso:country":"US",
    "sg:address":"15209 Livernois Ave",
    "sg:city":"Detroit",
    "sg:classifiers":[
        {
            "category":"Restaurant",
            "type":"Food & Drink"
        }
    ],
    "sg:phone":"+1 313 345 9492",
    "sg:postcode":"48238",
    "sg:province":"MI",
    "wof:name":"Place Restaurant Tom's",
    "wof:placetype":"venue"
},
  "geometry": {"coordinates":[-83.140404,42.402401],"type":"Point"}
}