{
  "type": "Feature",
  "properties": {
    "iso:country":"US",
    "sg:address":"1237 Wood Crest Ct",
    "sg:city":"Walled Lake",
    "sg:classifiers":[
        {
            "category":"Professional",
            "subcategory":"Business Services",
            "type":"Services"
        }
    ],
    "sg:phone":"+1 248 669 1399",
    "sg:postcode":"48390",
    "sg:province":"MI",
    "wof:name":"Karniotis Enterprises Inc",
    "wof:placetype":"venue"
},
  "geometry": {"coordinates":[-83.495811,42.530547],"type":"Point"}
}