{
  "type": "Feature",
  "properties": {
    "iso:country":"US",
    "sg:address":"904 W Main St",
    "sg:city":"Owosso",
    "sg:classifiers":[
        {
            "category":"Professional",
            "subcategory":"Business Services",
            "type":"Services"
        }
    ],
    "sg:phone":"+1 989 725 2688",
    "sg:postcode":"48867",
    "sg:province":"MI",
    "wof:name":"Undertone",
    "wof:placetype":"venue"
},
  "geometry": {"coordinates":[-84.182197,42.99773],"type":"Point"}
}