{
  "type": "Feature",
  "properties": {
    "iso:country":"US",
    "sg:address":"6069 E Gaukel Rd",
    "sg:city":"Merritt",
    "sg:classifiers":[
        {
            "category":"Manufacturing",
            "subcategory":"Tools & Machinery",
            "type":"Manufacturing & Wholesale Goods"
        }
    ],
    "sg:phone":"+1 231 328 4321",
    "sg:postcode":"49667",
    "sg:province":"MI",
    "sg:tags":[
        "farm",
        "equipment"
    ],
    "wof:name":"Howey Tree Baler Corp",
    "wof:placetype":"venue"
},
  "geometry": {"coordinates":[-84.970361,44.364184],"type":"Point"}
}