{
  "type": "Feature",
  "properties": {
    "iso:country":"US",
    "sg:address":"5250 S 9th St",
    "sg:city":"Kalamazoo",
    "sg:classifiers":[
        {
            "category":"Wholesale",
            "subcategory":"Office Equipment",
            "type":"Manufacturing & Wholesale Goods"
        }
    ],
    "sg:phone":"+1 269 372 2765",
    "sg:postcode":"49009",
    "sg:province":"MI",
    "sg:tags":[
        "bank",
        "supply"
    ],
    "wof:name":"Efmark Preminum Armored",
    "wof:placetype":"venue"
},
  "geometry": {"coordinates":[-85.67756,42.241407],"type":"Point"}
}