{
  "type": "Feature",
  "properties": {
    "iso:country":"US",
    "sg:address":"6151 28th St SE",
    "sg:city":"Grand Rapids",
    "sg:classifiers":[
        {
            "category":"Professional",
            "subcategory":"Employment Agencies",
            "type":"Services"
        }
    ],
    "sg:phone":"+1 616 975 3011",
    "sg:postcode":"49546",
    "sg:province":"MI",
    "sg:tags":[
        "help",
        "supply"
    ],
    "wof:name":"Ameritemp Staffing Inc",
    "wof:placetype":"venue"
},
  "geometry": {"coordinates":[-85.529781,42.916046],"type":"Point"}
}