{
  "type": "Feature",
  "properties": {
    "iso:country":"US",
    "sg:address":"510 Germania St",
    "sg:city":"Bay City",
    "sg:classifiers":[
        {
            "category":"Manufacturing",
            "subcategory":"Metals",
            "type":"Manufacturing & Wholesale Goods"
        }
    ],
    "sg:phone":"+1 989 893 4000",
    "sg:postcode":"48706",
    "sg:province":"MI",
    "sg:tags":[
        "ornamental",
        "work"
    ],
    "wof:name":"Charboneau Fence Co",
    "wof:placetype":"venue"
},
  "geometry": {"coordinates":[-83.901111,43.590002],"type":"Point"}
}