{
  "type": "Feature",
  "properties": {
    "iso:country":"US",
    "sg:address":"19306 Ecorse Rd",
    "sg:city":"Allen Park",
    "sg:classifiers":[
        {
            "category":"Building & Trades",
            "subcategory":"Construction",
            "type":"Services"
        }
    ],
    "sg:phone":"+1 313 386 1160",
    "sg:postcode":"48101",
    "sg:province":"MI",
    "sg:tags":[
        "contractor"
    ],
    "wof:name":"Three Jay's Bg Co Inc",
    "wof:placetype":"venue"
},
  "geometry": {"coordinates":[-83.23020200000001,42.2565],"type":"Point"}
}