{
  "type": "Feature",
  "properties": {
    "iso:country":"US",
    "sg:address":"12225 Folks Rd",
    "sg:city":"Hanover",
    "sg:classifiers":[
        {
            "category":"Building & Trades",
            "subcategory":"Landscaping Services",
            "type":"Services"
        }
    ],
    "sg:phone":"+1 517 522 9923",
    "sg:postcode":"49241",
    "sg:province":"MI",
    "sg:tags":[
        "lawn",
        "maintenance",
        "grounds"
    ],
    "wof:name":"Custom Cut Lawncare & Snow",
    "wof:placetype":"venue"
},
  "geometry": {"coordinates":[-84.633286,42.114768],"type":"Point"}
}