{
  "type": "Feature",
  "properties": {
    "iso:country":"US",
    "sg:address":"2020 Teel Ave",
    "sg:city":"Lansing",
    "sg:classifiers":[
        {
            "category":"Social Services",
            "subcategory":"Child Care",
            "type":"Services"
        }
    ],
    "sg:phone":"+1 517 484 2078",
    "sg:postcode":"48910",
    "sg:province":"MI",
    "sg:tags":[
        "day"
    ],
    "wof:name":"Angels In Waiting",
    "wof:placetype":"venue"
},
  "geometry": {"coordinates":[-84.55122799999999,42.710681],"type":"Point"}
}