{
  "type": "Feature",
  "properties": {
    "iso:country":"US",
    "sg:address":"247 Teggerdine Rd",
    "sg:city":"White Lake",
    "sg:classifiers":[
        {
            "category":"Social Services",
            "subcategory":"Child Care",
            "type":"Services"
        }
    ],
    "sg:phone":"+1 248 698 4286",
    "sg:postcode":"48386",
    "sg:province":"MI",
    "sg:tags":[
        "day"
    ],
    "wof:name":"Carols Daycare",
    "wof:placetype":"venue"
},
  "geometry": {"coordinates":[-83.49454900000001,42.64493],"type":"Point"}
}