{
  "type": "Feature",
  "properties": {
    "iso:country":"US",
    "sg:address":"49 Main St",
    "sg:city":"Saranac",
    "sg:classifiers":[
        {
            "category":"Wholesale",
            "subcategory":"Groceries",
            "type":"Manufacturing & Wholesale Goods"
        }
    ],
    "sg:phone":"+1 616 642 9560",
    "sg:postcode":"48881",
    "sg:province":"MI",
    "sg:tags":[
        "sandwich"
    ],
    "wof:name":"Deli Fresh Foods",
    "wof:placetype":"venue"
},
  "geometry": {"coordinates":[-85.211547,42.931276],"type":"Point"}
}