{
  "type": "Feature",
  "properties": {
    "iso:country":"US",
    "sg:address":"13204 Cromie Dr",
    "sg:city":"Warren",
    "sg:classifiers":[
        {
            "category":"Professional",
            "type":"Services"
        }
    ],
    "sg:phone":"+1 586 582 0911",
    "sg:postcode":"48088",
    "sg:province":"MI",
    "wof:name":"Simplified Services Inc",
    "wof:placetype":"venue"
},
  "geometry": {"coordinates":[-82.991829,42.515352],"type":"Point"}
}