{
  "type": "Feature",
  "properties": {
    "iso:country":"US",
    "sg:address":"3119 Main St",
    "sg:city":"Emmett",
    "sg:classifiers":[
        {
            "category":"Government",
            "subcategory":"Office",
            "type":"Public Place"
        }
    ],
    "sg:phone":"+1 810 384 8801",
    "sg:postcode":"48022",
    "sg:province":"MI",
    "sg:tags":[
        "village"
    ],
    "wof:name":"Emmett Village Office",
    "wof:placetype":"venue"
},
  "geometry": {"coordinates":[-82.76509,42.989461],"type":"Point"}
}