{
  "type": "Feature",
  "properties": {
    "iso:country":"US",
    "sg:address":"1060 Howard St",
    "sg:city":"Algonac",
    "sg:classifiers":[
        {
            "category":"Building & Trades",
            "subcategory":"Construction",
            "type":"Services"
        }
    ],
    "sg:phone":"+1 810 794 4669",
    "sg:postcode":"48001",
    "sg:province":"MI",
    "sg:tags":[
        "layer",
        "carpet"
    ],
    "wof:name":"Carriage Trade Floor Covering",
    "wof:placetype":"venue"
},
  "geometry": {"coordinates":[-82.541099,42.620231],"type":"Point"}
}