{
  "type": "Feature",
  "properties": {
    "iso:country":"US",
    "sg:address":"13838 Stratford St",
    "sg:city":"Riverview",
    "sg:classifiers":[
        {
            "category":"Arts & Performance",
            "subcategory":"Music",
            "type":"Entertainment"
        }
    ],
    "sg:phone":"+1 877 643 8368",
    "sg:postcode":"48193",
    "sg:province":"MI",
    "sg:tags":[
        "dj"
    ],
    "sg:website":"encorepartydjs.com",
    "wof:name":"Encore Party DJs",
    "wof:placetype":"venue"
},
  "geometry": {"coordinates":[-83.19222000000001,42.181548],"type":"Point"}
}