{
  "type": "Feature",
  "properties": {
    "iso:country":"US",
    "sg:address":"4645 Dewey Rd",
    "sg:city":"Newport",
    "sg:classifiers":[
        {
            "category":"Wholesale",
            "subcategory":"Non-durable Goods",
            "type":"Manufacturing & Wholesale Goods"
        }
    ],
    "sg:phone":"+1 734 289 1099",
    "sg:postcode":"48166",
    "sg:province":"MI",
    "sg:tags":[
        "pet",
        "supply"
    ],
    "wof:name":"White Feather Distribution Inc",
    "wof:placetype":"venue"
},
  "geometry": {"coordinates":[-83.26157000000001,41.944324],"type":"Point"}
}