{
  "type": "Feature",
  "properties": {
    "iso:country":"US",
    "sg:address":"30500 Brentwood St",
    "sg:city":"Southfield",
    "sg:classifiers":[
        {
            "category":"Building & Trades",
            "subcategory":"Cleaning & Sanitation",
            "type":"Services"
        }
    ],
    "sg:phone":"+1 248 423 6391",
    "sg:postcode":"48076",
    "sg:province":"MI",
    "sg:tags":[
        "snow",
        "removal"
    ],
    "wof:name":"AGR Landscaping & Snow Remov",
    "wof:placetype":"venue"
},
  "geometry": {"coordinates":[-83.20461299999999,42.514117],"type":"Point"}
}