{
  "type": "Feature",
  "properties": {
    "iso:country":"US",
    "sg:address":"1800 N Grand River Ave",
    "sg:city":"Lansing",
    "sg:classifiers":[
        {
            "category":"Autos & Motor Vehicles",
            "subcategory":"Auto Supplies",
            "type":"Retail Goods"
        }
    ],
    "sg:phone":"+1 517 393 0125",
    "sg:postcode":"48906",
    "sg:province":"MI",
    "sg:tags":[
        "battery"
    ],
    "wof:name":"Battery Exchange",
    "wof:placetype":"venue"
},
  "geometry": {"coordinates":[-84.55708300000001,42.754105],"type":"Point"}
}