{
  "type": "Feature",
  "properties": {
    "iso:country":"US",
    "sg:address":"8095 Parkway Dr",
    "sg:city":"Jenison",
    "sg:classifiers":[
        {
            "category":"Shopping",
            "subcategory":"Books",
            "type":"Retail Goods"
        }
    ],
    "sg:phone":"+1 616 667 9553",
    "sg:postcode":"49428",
    "sg:province":"MI",
    "wof:name":"Usborne Books",
    "wof:placetype":"venue"
},
  "geometry": {"coordinates":[-85.82499900000001,42.914899],"type":"Point"}
}