{
  "type": "Feature",
  "properties": {
    "iso:country":"US",
    "sg:address":"3117 Dale Rd",
    "sg:city":"Saginaw",
    "sg:classifiers":[
        {
            "category":"Social Services",
            "subcategory":"Child Care",
            "type":"Services"
        }
    ],
    "sg:phone":"+1 989 790 9451",
    "sg:postcode":"48603",
    "sg:province":"MI",
    "sg:tags":[
        "day"
    ],
    "wof:name":"Kathi Packard",
    "wof:placetype":"venue"
},
  "geometry": {"coordinates":[-83.97784299999999,43.447309],"type":"Point"}
}