{
  "type": "Feature",
  "properties": {
    "iso:country":"US",
    "sg:address":"7717 Kensington Ct",
    "sg:city":"Brighton",
    "sg:classifiers":[
        {
            "category":"Professional",
            "subcategory":"Engineering",
            "type":"Services"
        }
    ],
    "sg:phone":"+1 517 552 1305",
    "sg:postcode":"48116",
    "sg:province":"MI",
    "wof:name":"Beltz Engineering Inc",
    "wof:placetype":"venue"
},
  "geometry": {"coordinates":[-83.684703,42.491843],"type":"Point"}
}