{
  "type": "Feature",
  "properties": {
    "iso:country":"US",
    "sg:address":"10489 Linden Rd",
    "sg:city":"Grand Blanc",
    "sg:classifiers":[
        {
            "category":"Building & Trades",
            "subcategory":"Construction",
            "type":"Services"
        }
    ],
    "sg:phone":"+1 810 735 8600",
    "sg:postcode":"48439",
    "sg:province":"MI",
    "sg:tags":[
        "concrete",
        "contractor"
    ],
    "wof:name":"Raffin Foundations",
    "wof:placetype":"venue"
},
  "geometry": {"coordinates":[-83.768693,42.877504],"type":"Point"}
}