{
  "type": "Feature",
  "properties": {
    "iso:country":"US",
    "sg:address":"8250 Hilton Rd",
    "sg:city":"Brighton",
    "sg:classifiers":[
        {
            "category":"Banks & Credit Unions",
            "subcategory":"Bank",
            "type":"Services"
        }
    ],
    "sg:phone":"+1 810 220 0561",
    "sg:postcode":"48114",
    "sg:province":"MI",
    "wof:name":"Comerica Bank",
    "wof:placetype":"venue"
},
  "geometry": {"coordinates":[-83.788371,42.549772],"type":"Point"}
}