{
  "type": "Feature",
  "properties": {
    "iso:country":"US",
    "sg:address":"4300 Main Park Dr",
    "sg:city":"Shelby Twp",
    "sg:classifiers":[
        {
            "category":"Government",
            "subcategory":"Office",
            "type":"Public Place"
        },
        {
            "category":"Recreation",
            "type":"Entertainment"
        }
    ],
    "sg:phone":"+1 586 781 4242",
    "sg:postcode":"48316",
    "sg:province":"MI",
    "sg:tags":[
        "conservation",
        "parks"
    ],
    "sg:website":"www.metroparks.com",
    "wof:name":"Stony Creek Metropark",
    "wof:placetype":"venue"
},
  "geometry": {"coordinates":[-83.07281500000001,42.71112],"type":"Point"}
}