{
  "type": "Feature",
  "properties": {
    "iso:country":"US",
    "sg:address":"803 10th Ave",
    "sg:city":"Port Huron",
    "sg:classifiers":[
        {
            "category":"Professional",
            "subcategory":"Employment Agencies",
            "type":"Services"
        }
    ],
    "sg:phone":"+1 810 987 9675",
    "sg:postcode":"48060",
    "sg:province":"MI",
    "sg:tags":[
        "opportunity"
    ],
    "wof:name":"Labor Ready Inc",
    "wof:placetype":"venue"
},
  "geometry": {"coordinates":[-82.43371500000001,42.982574],"type":"Point"}
}