{
  "type": "Feature",
  "properties": {
    "iso:country":"US",
    "sg:address":"11247 Dickerson Lake Rd",
    "sg:city":"Gowen",
    "sg:classifiers":[
        {
            "category":"Farming",
            "subcategory":"Livestock Farm",
            "type":"Manufacturing & Wholesale Goods"
        }
    ],
    "sg:phone":"+1 616 984 2474",
    "sg:postcode":"49326",
    "sg:province":"MI",
    "sg:tags":[
        "animal",
        "general"
    ],
    "wof:name":"Walters Deer Farm Inc",
    "wof:placetype":"venue"
},
  "geometry": {"coordinates":[-85.297146,43.293988],"type":"Point"}
}