{
  "type": "Feature",
  "properties": {
    "iso:country":"US",
    "sg:address":"424 Baldwin Ave",
    "sg:city":"Rochester",
    "sg:classifiers":[
        {
            "category":"Social Services",
            "type":"Services"
        }
    ],
    "sg:phone":"+1 248 656 5133",
    "sg:postcode":"48307",
    "sg:province":"MI",
    "wof:name":"Asplund Cheryl D LLP PC",
    "wof:placetype":"venue"
},
  "geometry": {"coordinates":[-83.126379,42.681211],"type":"Point"}
}