{
  "type": "Feature",
  "properties": {
    "iso:country":"US",
    "sg:address":"11191 California Rd",
    "sg:city":"Bridgman",
    "sg:classifiers":[
        {
            "category":"Retail",
            "subcategory":"Auto Repair",
            "type":"Services"
        }
    ],
    "sg:phone":"+1 269 465 5601",
    "sg:postcode":"49106",
    "sg:province":"MI",
    "sg:tags":[
        "repairing",
        "automobile",
        "general"
    ],
    "wof:name":"Verne's Auto Repair",
    "wof:placetype":"venue"
},
  "geometry": {"coordinates":[-86.55259700000001,41.915902],"type":"Point"}
}