{
  "type": "Feature",
  "properties": {
    "iso:country":"US",
    "sg:address":"2591 Fort St",
    "sg:city":"Trenton",
    "sg:classifiers":[
        {
            "category":"Sports & Exercise",
            "subcategory":"Bowling",
            "type":"Entertainment"
        }
    ],
    "sg:phone":"+1 734 675 2444",
    "sg:postcode":"48183",
    "sg:province":"MI",
    "wof:name":"Parkway Bowling Center",
    "wof:placetype":"venue"
},
  "geometry": {"coordinates":[-83.1875,42.144699],"type":"Point"}
}