{
  "type": "Feature",
  "properties": {
    "iso:country":"US",
    "sg:address":"3393 S Winn Rd",
    "sg:city":"Mt Pleasant",
    "sg:classifiers":[
        {
            "category":"Building & Trades",
            "subcategory":"Construction",
            "type":"Services"
        }
    ],
    "sg:phone":"+1 989 772 4249",
    "sg:postcode":"48858",
    "sg:province":"MI",
    "sg:tags":[
        "hanging",
        "painter",
        "contractor"
    ],
    "wof:name":"Pleasant Home Maintenance",
    "wof:placetype":"venue"
},
  "geometry": {"coordinates":[-84.907636,43.591796],"type":"Point"}
}