{
  "type": "Feature",
  "properties": {
    "iso:country":"US",
    "sg:address":"128 W Washington St",
    "sg:city":"Marquette",
    "sg:classifiers":[
        {
            "category":"Organizations",
            "subcategory":"Professional Association",
            "type":"Services"
        }
    ],
    "sg:phone":"+1 906 225 1157",
    "sg:postcode":"49855",
    "sg:province":"MI",
    "wof:name":"Masonic Building",
    "wof:placetype":"venue"
},
  "geometry": {"coordinates":[-87.394842,46.54355],"type":"Point"}
}