{
  "type": "Feature",
  "properties": {
    "iso:country":"US",
    "sg:address":"7490 21st Ave",
    "sg:city":"Jenison",
    "sg:classifiers":[
        {
            "category":"Social Services",
            "subcategory":"Child Care",
            "type":"Services"
        }
    ],
    "sg:phone":"+1 616 457 3478",
    "sg:postcode":"49428",
    "sg:province":"MI",
    "sg:tags":[
        "day"
    ],
    "wof:name":"Kings Kids Preschool",
    "wof:placetype":"venue"
},
  "geometry": {"coordinates":[-85.834191,42.905463],"type":"Point"}
}