{
  "type": "Feature",
  "properties": {
    "iso:country":"US",
    "sg:address":"36700 Woodward Ave",
    "sg:city":"Bloomfield Hills",
    "sg:classifiers":[
        {
            "category":"Banks & Credit Unions",
            "subcategory":"Bank",
            "type":"Services"
        }
    ],
    "sg:phone":"+1 248 646 2283",
    "sg:postcode":"48304",
    "sg:province":"MI",
    "wof:name":"Preferred Bankers LLC",
    "wof:placetype":"venue"
},
  "geometry": {"coordinates":[-83.22272100000001,42.558313],"type":"Point"}
}