{
  "type": "Feature",
  "properties": {
    "iso:country":"US",
    "sg:address":"425 E Mc Millan Ave",
    "sg:city":"Newberry",
    "sg:classifiers":[
        {
            "category":"Personal",
            "subcategory":"Beauty Salon",
            "type":"Services"
        }
    ],
    "sg:phone":"+1 906 293 5240",
    "sg:postcode":"49868",
    "sg:province":"MI",
    "wof:name":"Carla's Curl's R Us",
    "wof:placetype":"venue"
},
  "geometry": {"coordinates":[-85.50353800000001,46.351869],"type":"Point"}
}