{
  "type": "Feature",
  "properties": {
    "iso:country":"US",
    "sg:address":"2211 Association Dr",
    "sg:city":"Okemos",
    "sg:classifiers":[
        {
            "category":"Real Estate",
            "subcategory":"Real Estate Services",
            "type":"Services"
        }
    ],
    "sg:phone":"+1 517 347 2140",
    "sg:postcode":"48864",
    "sg:province":"MI",
    "sg:tags":[
        "company",
        "title"
    ],
    "wof:name":"Metropolitan Title Co",
    "wof:placetype":"venue"
},
  "geometry": {"coordinates":[-84.429925,42.685799],"type":"Point"}
}