{
  "type": "Feature",
  "properties": {
    "iso:country":"US",
    "sg:address":"4100 E Grand River Ave",
    "sg:city":"Howell",
    "sg:classifiers":[
        {
            "category":"Shopping",
            "type":"Retail Goods"
        }
    ],
    "sg:phone":"+1 517 540 1553",
    "sg:postcode":"48843",
    "sg:province":"MI",
    "sg:tags":[
        "miscellaneous",
        "store"
    ],
    "wof:name":"Seasonal Expressions",
    "wof:placetype":"venue"
},
  "geometry": {"coordinates":[-83.87276799999999,42.586024],"type":"Point"}
}