{
  "type": "Feature",
  "properties": {
    "iso:country":"US",
    "sg:address":"3896 Bald Mountain Rd",
    "sg:city":"Auburn Hills",
    "sg:classifiers":[
        {
            "category":"Building & Trades",
            "subcategory":"Construction",
            "type":"Services"
        }
    ],
    "sg:phone":"+1 248 373 6612",
    "sg:postcode":"48326",
    "sg:province":"MI",
    "sg:tags":[
        "hanging",
        "contractor"
    ],
    "wof:name":"Demarais Painting",
    "wof:placetype":"venue"
},
  "geometry": {"coordinates":[-83.240574,42.690055],"type":"Point"}
}