{
  "type": "Feature",
  "properties": {
    "iso:country":"US",
    "sg:address":"710 Notre Dame St",
    "sg:city":"Grosse Pointe",
    "sg:classifiers":[
        {
            "category":"Insurance",
            "subcategory":"Insurance Agent",
            "type":"Services"
        }
    ],
    "sg:phone":"+1 313 881 5322",
    "sg:postcode":"48230",
    "sg:province":"MI",
    "wof:name":"First Ind Aitken & Ormond",
    "wof:placetype":"venue"
},
  "geometry": {"coordinates":[-82.917524,42.390595],"type":"Point"}
}