{
  "type": "Feature",
  "properties": {
    "iso:country":"US",
    "sg:address":"1445 Lake Dr SE",
    "sg:city":"Grand Rapids",
    "sg:classifiers":[
        {
            "category":"Restaurant",
            "type":"Food & Drink"
        }
    ],
    "sg:phone":"+1 616 451 8600",
    "sg:postcode":"49506",
    "sg:province":"MI",
    "sg:tags":[
        "shop",
        "coffee"
    ],
    "wof:name":"Kava House",
    "wof:placetype":"venue"
},
  "geometry": {"coordinates":[-85.632121,42.95578],"type":"Point"}
}