{
  "type": "Feature",
  "properties": {
    "iso:country":"US",
    "sg:address":"3201 University Dr",
    "sg:city":"Auburn Hills",
    "sg:classifiers":[
        {
            "category":"Professional",
            "subcategory":"Accounting & Tax Preparation",
            "type":"Services"
        }
    ],
    "sg:phone":"+1 248 340 6050",
    "sg:postcode":"48326",
    "sg:province":"MI",
    "sg:tags":[
        "accountant"
    ],
    "sg:website":"www.ahpplc.com",
    "wof:name":"Andrews Hooper & Pavlik",
    "wof:placetype":"venue"
},
  "geometry": {"coordinates":[-83.22055899999999,42.672623],"type":"Point"}
}