{
  "type": "Feature",
  "properties": {
    "iso:country":"US",
    "sg:address":"5181 Hale Dr",
    "sg:city":"Troy",
    "sg:classifiers":[
        {
            "category":"Health Services",
            "subcategory":"Medical Lab",
            "type":"Services"
        }
    ],
    "sg:phone":"+1 248 689 6904",
    "sg:postcode":"48085",
    "sg:province":"MI",
    "sg:tags":[
        "laboratory",
        "dental"
    ],
    "wof:name":"Ss Crown Dental Laboratory Co",
    "wof:placetype":"venue"
},
  "geometry": {"coordinates":[-83.121354,42.594735],"type":"Point"}
}