{
  "type": "Feature",
  "properties": {
    "iso:country":"US",
    "sg:address":"4701 N Rochester Rd",
    "sg:city":"Rochester Hills",
    "sg:classifiers":[
        {
            "category":"Real Estate",
            "subcategory":"Developer",
            "type":"Services"
        }
    ],
    "sg:phone":"+1 248 601 2900",
    "sg:postcode":"48306",
    "sg:province":"MI",
    "sg:tags":[
        "cemetery"
    ],
    "wof:name":"Guardian Angel Cemetery",
    "wof:placetype":"venue"
},
  "geometry": {"coordinates":[-83.135778,42.730604],"type":"Point"}
}