{
  "type": "Feature",
  "properties": {
    "iso:country":"US",
    "sg:address":"41675 Pocatello Dr",
    "sg:city":"Canton",
    "sg:classifiers":[
        {
            "category":"Manufacturing",
            "subcategory":"Tools & Machinery",
            "type":"Manufacturing & Wholesale Goods"
        }
    ],
    "sg:phone":"+1 734 844 8550",
    "sg:postcode":"48187",
    "sg:province":"MI",
    "sg:tags":[
        "machine",
        "control",
        "electronic",
        "mfg"
    ],
    "wof:name":"Kapos Machine Control",
    "wof:placetype":"venue"
},
  "geometry": {"coordinates":[-83.451725,42.313862],"type":"Point"}
}