{
  "type": "Feature",
  "properties": {
    "iso:country":"US",
    "sg:address":"16000 Grand River Ave",
    "sg:city":"Detroit",
    "sg:classifiers":[
        {
            "category":"Retail",
            "subcategory":"Laundry & Dry Cleaning",
            "type":"Services"
        }
    ],
    "sg:phone":"+1 313 836 7020",
    "sg:postcode":"48227",
    "sg:province":"MI",
    "wof:name":"Expert's 40 Minute Cleaners",
    "wof:placetype":"venue"
},
  "geometry": {"coordinates":[-83.204002,42.3951],"type":"Point"}
}