{
  "type": "Feature",
  "properties": {
    "iso:country":"US",
    "sg:address":"1172 Jackson Xing",
    "sg:city":"Jackson",
    "sg:classifiers":[
        {
            "category":"Health Services",
            "subcategory":"Optometrist",
            "type":"Services"
        }
    ],
    "sg:phone":"+1 517 782 9388",
    "sg:postcode":"49202",
    "sg:province":"MI",
    "wof:name":"Gregory Optical Co",
    "wof:placetype":"venue"
},
  "geometry": {"coordinates":[-84.433902,42.269441],"type":"Point"}
}