{
  "type": "Feature",
  "properties": {
    "iso:country":"US",
    "sg:address":"106 Republic Ave",
    "sg:city":"Republic",
    "sg:classifiers":[
        {
            "category":"Retail",
            "subcategory":"Repair Shop",
            "type":"Services"
        }
    ],
    "sg:phone":"+1 906 376 2478",
    "sg:postcode":"49879",
    "sg:province":"MI",
    "sg:tags":[
        "repairing",
        "piano",
        "refinishing"
    ],
    "wof:name":"Gus Hult Piano Svc",
    "wof:placetype":"venue"
},
  "geometry": {"coordinates":[-87.97941899999999,46.406018],"type":"Point"}
}