{
  "type": "Feature",
  "properties": {
    "iso:country":"US",
    "sg:address":"6691 Kilmanagh Rd",
    "sg:city":"Owendale",
    "sg:classifiers":[
        {
            "category":"Farming",
            "subcategory":"Farm",
            "type":"Manufacturing & Wholesale Goods"
        }
    ],
    "sg:phone":"+1 989 678 4110",
    "sg:postcode":"48754",
    "sg:province":"MI",
    "sg:tags":[
        "crop",
        "general"
    ],
    "wof:name":"Ronald C Gayari",
    "wof:placetype":"venue"
},
  "geometry": {"coordinates":[-83.245361,43.758364],"type":"Point"}
}