{
  "type": "Feature",
  "properties": {
    "iso:country":"US",
    "sg:address":"2351 W Brewer Rd",
    "sg:city":"Owosso",
    "sg:classifiers":[
        {
            "category":"Building & Trades",
            "subcategory":"Electrical",
            "type":"Services"
        }
    ],
    "sg:phone":"+1 989 729 1113",
    "sg:postcode":"48867",
    "sg:province":"MI",
    "sg:tags":[
        "electrical",
        "contractor"
    ],
    "wof:name":"Kingsley Electric",
    "wof:placetype":"venue"
},
  "geometry": {"coordinates":[-84.20890900000001,42.907005],"type":"Point"}
}