{
  "type": "Feature",
  "properties": {
    "iso:country":"US",
    "sg:address":"1001 N Graf Rd",
    "sg:city":"Caro",
    "sg:classifiers":[
        {
            "category":"Building & Trades",
            "subcategory":"Construction",
            "type":"Services"
        }
    ],
    "sg:phone":"+1 989 673 5679",
    "sg:postcode":"48723",
    "sg:province":"MI",
    "sg:tags":[
        "house"
    ],
    "wof:name":"Doors & Doors",
    "wof:placetype":"venue"
},
  "geometry": {"coordinates":[-83.44764499999999,43.507789],"type":"Point"}
}