{
  "type": "Feature",
  "properties": {
    "iso:country":"US",
    "sg:address":"426 Clare St",
    "sg:city":"Lansing",
    "sg:classifiers":[
        {
            "category":"Organizations",
            "subcategory":"Labor Organization",
            "type":"Services"
        }
    ],
    "sg:phone":"+1 517 372 7581",
    "sg:postcode":"48917",
    "sg:province":"MI",
    "wof:name":"United Auto Workers",
    "wof:placetype":"venue"
},
  "geometry": {"coordinates":[-84.582247,42.729338],"type":"Point"}
}