{
  "type": "Feature",
  "properties": {
    "iso:country":"US",
    "sg:address":"7221 Creekside Dr",
    "sg:city":"Lansing",
    "sg:classifiers":[
        {
            "category":"Building & Trades",
            "subcategory":"Construction",
            "type":"Services"
        }
    ],
    "sg:phone":"+1 517 719 1488",
    "sg:postcode":"48917",
    "sg:province":"MI",
    "sg:tags":[
        "house"
    ],
    "wof:name":"Reigler Construction",
    "wof:placetype":"venue"
},
  "geometry": {"coordinates":[-84.656949,42.735195],"type":"Point"}
}