{
  "type": "Feature",
  "properties": {
    "iso:country":"US",
    "sg:address":"21635 Bulhand St",
    "sg:city":"Cassopolis",
    "sg:classifiers":[
        {
            "category":"Wholesale",
            "subcategory":"Construction Materials",
            "type":"Manufacturing & Wholesale Goods"
        }
    ],
    "sg:phone":"+1 269 699 7476",
    "sg:postcode":"49031",
    "sg:province":"MI",
    "sg:tags":[
        "pallet",
        "skid"
    ],
    "wof:name":"Skid World Pallet Corp",
    "wof:placetype":"venue"
},
  "geometry": {"coordinates":[-85.97751100000001,41.817832],"type":"Point"}
}