{
  "type": "Feature",
  "properties": {
    "iso:country":"US",
    "sg:address":"806 W Houghton Ave",
    "sg:city":"West Branch",
    "sg:classifiers":[
        {
            "category":"Government",
            "subcategory":"Office",
            "type":"Public Place"
        }
    ],
    "sg:phone":"+1 989 345 3375",
    "sg:postcode":"48661",
    "sg:province":"MI",
    "wof:name":"Ogemaw County Building Dept",
    "wof:placetype":"venue"
},
  "geometry": {"coordinates":[-84.246286,44.276185],"type":"Point"}
}