{
  "type": "Feature",
  "properties": {
    "iso:country":"US",
    "sg:address":"1975 Burton Ave",
    "sg:city":"Holt",
    "sg:classifiers":[
        {
            "category":"Building & Trades",
            "subcategory":"Construction",
            "type":"Services"
        }
    ],
    "sg:phone":"+1 517 694 7145",
    "sg:postcode":"48842",
    "sg:province":"MI",
    "sg:tags":[
        "house"
    ],
    "wof:name":"Jims Honey-Do Maintenance Co",
    "wof:placetype":"venue"
},
  "geometry": {"coordinates":[-84.524897,42.639054],"type":"Point"}
}