{
  "type": "Feature",
  "properties": {
    "iso:country":"US",
    "sg:address":"11733 Dunlavy Ln",
    "sg:city":"Whitmore Lake",
    "sg:classifiers":[
        {
            "category":"Professional",
            "subcategory":"Business Services",
            "type":"Services"
        }
    ],
    "sg:phone":"+1 734 426 1945",
    "sg:postcode":"48189",
    "sg:province":"MI",
    "wof:name":"Ron Blackwell & Assoc",
    "wof:placetype":"venue"
},
  "geometry": {"coordinates":[-83.865785,42.430097],"type":"Point"}
}