{
  "type": "Feature",
  "properties": {
    "iso:country":"US",
    "sg:address":"3964 Clarkston Rd",
    "sg:city":"Clarkston",
    "sg:classifiers":[
        {
            "category":"Building & Trades",
            "subcategory":"Cleaning & Sanitation",
            "type":"Services"
        }
    ],
    "sg:phone":"+1 248 628 6243",
    "sg:postcode":"48348",
    "sg:province":"MI",
    "sg:tags":[
        "house"
    ],
    "wof:name":"Merry Maids Inc",
    "wof:placetype":"venue"
},
  "geometry": {"coordinates":[-83.323071,42.765026],"type":"Point"}
}