{
  "type": "Feature",
  "properties": {
    "iso:country":"US",
    "sg:address":"45001 Ford Rd",
    "sg:city":"Canton",
    "sg:phone":"+1 734 326 6030",
    "sg:postcode":"48187",
    "sg:province":"MI",
    "sg:website":"http://www.switchboard.com/usps.1355/dir/detail.htm?&&ypcobrand=1355&sd=50&sortOrder=&Z=48112&sortBy=Distance&cntLongitude=-83.482554&listingPagination=0&CID=1222&zoom=0&cntLatitude=42.322051&navigatorChoices=&where=48112&recordid=Business%7c19459807&frompage=CategoryID&showsection=1",
    "wof:name":"USPS - United States Post Office",
    "wof:placetype":"venue"
},
  "geometry": {"coordinates":[-83.48357300000001,42.322041],"type":"Point"}
}