{
  "type": "Feature",
  "properties": {
    "iso:country":"US",
    "sg:address":"1433 Franklin St",
    "sg:city":"Haslett",
    "sg:classifiers":[
        {
            "category":"Organizations",
            "subcategory":"Community Association",
            "type":"Services"
        }
    ],
    "sg:phone":"+1 517 339 5050",
    "sg:postcode":"48840",
    "sg:province":"MI",
    "sg:tags":[
        "military"
    ],
    "wof:name":"Disabled American Veterans",
    "wof:placetype":"venue"
},
  "geometry": {"coordinates":[-84.401409,42.744335],"type":"Point"}
}