{
  "type": "Feature",
  "properties": {
    "iso:country":"US",
    "sg:address":"3751 Marketplace Cir",
    "sg:city":"Traverse City",
    "sg:classifiers":[
        {
            "category":"Shopping",
            "type":"Retail Goods"
        }
    ],
    "sg:phone":"+1 231 922 9782",
    "sg:postcode":"49684",
    "sg:province":"MI",
    "sg:tags":[
        "factory",
        "outlet"
    ],
    "wof:name":"Pendelton Outlet",
    "wof:placetype":"venue"
},
  "geometry": {"coordinates":[-85.64806400000001,44.731388],"type":"Point"}
}