{
  "type": "Feature",
  "properties": {
    "iso:country":"US",
    "sg:address":"2209 S Telegraph Rd",
    "sg:city":"Bloomfield Hills",
    "sg:classifiers":[
        {
            "category":"Restaurant",
            "type":"Food & Drink"
        }
    ],
    "sg:menulink":"http://www.allmenus.com/mi/bloomfield/185853-mcdonalds/menu/",
    "sg:postcode":"48302",
    "sg:province":"MI",
    "sg:tags":[
        "burger",
        "american"
    ],
    "wof:name":"McDonald's",
    "wof:placetype":"venue"
},
  "geometry": {"coordinates":[-83.294909,42.605944],"type":"Point"}
}