{
  "type": "Feature",
  "properties": {
    "iso:country":"US",
    "sg:address":"5721 Peach Ridge Ave NW",
    "sg:city":"Comstock Park",
    "sg:classifiers":[
        {
            "category":"Farming",
            "subcategory":"Livestock Farm",
            "type":"Manufacturing & Wholesale Goods"
        }
    ],
    "sg:phone":"+1 616 784 2759",
    "sg:postcode":"49321",
    "sg:province":"MI",
    "sg:tags":[
        "beef",
        "feedlot",
        "cattle"
    ],
    "wof:name":"Steve Tikkanen",
    "wof:placetype":"venue"
},
  "geometry": {"coordinates":[-85.748594,43.064272],"type":"Point"}
}