{
  "type": "Feature",
  "properties": {
    "iso:country":"US",
    "sg:address":"736 W Grand St",
    "sg:city":"Hastings",
    "sg:classifiers":[
        {
            "category":"Freight",
            "type":"Transportation"
        }
    ],
    "sg:phone":"+1 269 948 4154",
    "sg:postcode":"49058",
    "sg:province":"MI",
    "sg:tags":[
        "commercial",
        "storage"
    ],
    "wof:name":"State Street Mini Storage",
    "wof:placetype":"venue"
},
  "geometry": {"coordinates":[-85.297062,42.643994],"type":"Point"}
}