{
  "type": "Feature",
  "properties": {
    "iso:country":"US",
    "sg:address":"85 Childress Ave",
    "sg:city":"Rochester",
    "sg:classifiers":[
        {
            "category":"Real Estate",
            "subcategory":"Real Estate Agent",
            "type":"Services"
        }
    ],
    "sg:phone":"+1 248 650 0588",
    "sg:postcode":"48307",
    "sg:province":"MI",
    "wof:name":"Fielding Corners Condominium A",
    "wof:placetype":"venue"
},
  "geometry": {"coordinates":[-83.13502,42.673026],"type":"Point"}
}