{
  "type": "Feature",
  "properties": {
    "iso:country":"US",
    "sg:address":"914 W Chisholm St",
    "sg:city":"Alpena",
    "sg:classifiers":[
        {
            "category":"Real Estate",
            "subcategory":"Real Estate Agent",
            "type":"Services"
        }
    ],
    "sg:phone":"+1 989 354 3322",
    "sg:postcode":"49707",
    "sg:province":"MI",
    "wof:name":"Ray Chrzan Realty Inc",
    "wof:placetype":"venue"
},
  "geometry": {"coordinates":[-83.44376099999999,45.070833],"type":"Point"}
}