{
  "type": "Feature",
  "properties": {
    "iso:country":"US",
    "sg:address":"2760 Goslow Rd",
    "sg:city":"Gaylord",
    "sg:classifiers":[
        {
            "category":"Farming",
            "subcategory":"Farm & Veterinary Services",
            "type":"Manufacturing & Wholesale Goods"
        }
    ],
    "sg:phone":"+1 989 732 4044",
    "sg:postcode":"49735",
    "sg:province":"MI",
    "sg:tags":[
        "corn",
        "crop",
        "soybean",
        "harvesting"
    ],
    "wof:name":"Slivinski Farms",
    "wof:placetype":"venue"
},
  "geometry": {"coordinates":[-84.623255,45.055726],"type":"Point"}
}