{
  "type": "Feature",
  "properties": {
    "iso:country":"US",
    "sg:address":"423 N Ithaca St",
    "sg:city":"Ithaca",
    "sg:classifiers":[
        {
            "category":"Shopping",
            "subcategory":"Bicycles & Sporting Goods",
            "type":"Retail Goods"
        }
    ],
    "sg:phone":"+1 989 875 6005",
    "sg:postcode":"48847",
    "sg:province":"MI",
    "wof:name":"Vanhorn Jims Cstm Rods Tackle",
    "wof:placetype":"venue"
},
  "geometry": {"coordinates":[-84.602054,43.296695],"type":"Point"}
}