{
  "type": "Feature",
  "properties": {
    "iso:country":"US",
    "sg:address":"2690 Crooks Rd",
    "sg:city":"Royal Oak",
    "sg:classifiers":[
        {
            "category":"Professional",
            "subcategory":"Lawyer & Legal Services",
            "type":"Services"
        }
    ],
    "sg:phone":"+1 248 288 4300",
    "sg:postcode":"48073",
    "sg:province":"MI",
    "sg:tags":[
        "attorney"
    ],
    "wof:name":"James R Keller",
    "wof:placetype":"venue"
},
  "geometry": {"coordinates":[-83.159599,42.51084],"type":"Point"}
}