{
  "type": "Feature",
  "properties": {
    "iso:country":"US",
    "sg:address":"2625 N Center Rd",
    "sg:city":"Saginaw",
    "sg:classifiers":[
        {
            "category":"Organizations",
            "subcategory":"Religious Organization",
            "type":"Services"
        }
    ],
    "sg:phone":"+1 989 799 2930",
    "sg:postcode":"48603",
    "sg:province":"MI",
    "wof:name":"First Free Methodist Church",
    "wof:placetype":"venue"
},
  "geometry": {"coordinates":[-84.014948,43.44428],"type":"Point"}
}