{
  "type": "Feature",
  "properties": {
    "iso:country":"US",
    "sg:address":"1255 N White St NW",
    "sg:city":"Grand Rapids",
    "sg:classifiers":[
        {
            "category":"Wholesale",
            "subcategory":"Apparel",
            "type":"Manufacturing & Wholesale Goods"
        }
    ],
    "sg:phone":"+1 616 735 9773",
    "sg:postcode":"49544",
    "sg:province":"MI",
    "sg:tags":[
        "distributor",
        "premium",
        "representative",
        "mfg"
    ],
    "wof:name":"Image Delivery",
    "wof:placetype":"venue"
},
  "geometry": {"coordinates":[-85.81464,42.980806],"type":"Point"}
}