{
  "type": "Feature",
  "properties": {
    "iso:country":"US",
    "sg:address":"7627 S Dune Hwy",
    "sg:city":"Empire",
    "sg:classifiers":[
        {
            "category":"Wholesale",
            "subcategory":"Durable Goods & Equipment",
            "type":"Manufacturing & Wholesale Goods"
        }
    ],
    "sg:phone":"+1 231 334 3960",
    "sg:postcode":"49630",
    "sg:province":"MI",
    "sg:tags":[
        "representative",
        "manufacturer"
    ],
    "wof:name":"Solution Place Inc",
    "wof:placetype":"venue"
},
  "geometry": {"coordinates":[-86.04163699999999,44.867658],"type":"Point"}
}