{
  "type": "Feature",
  "properties": {
    "iso:country":"US",
    "sg:address":"1893 W Maumee St",
    "sg:city":"Adrian",
    "sg:classifiers":[
        {
            "category":"Health Services",
            "subcategory":"Doctor",
            "type":"Services"
        }
    ],
    "sg:phone":"+1 517 266 2222",
    "sg:postcode":"49221",
    "sg:province":"MI",
    "sg:tags":[
        "clinic"
    ],
    "wof:name":"Coleby Medical Alternatives",
    "wof:placetype":"venue"
},
  "geometry": {"coordinates":[-84.071828,41.905472],"type":"Point"}
}