{
  "type": "Feature",
  "properties": {
    "iso:country":"US",
    "sg:address":"57865 Kahler Rd",
    "sg:city":"Jones",
    "sg:phone":"+1 269 244 8479",
    "sg:postcode":"49061",
    "sg:province":"MI",
    "sg:tags":[
        "farm",
        "corn"
    ],
    "wof:name":"Allen Butchbaker",
    "wof:placetype":"venue"
},
  "geometry": {"coordinates":[-85.790007,41.963328],"type":"Point"}
}