{
  "type": "Feature",
  "properties": {
    "iso:country":"US",
    "sg:address":"1760 W US Hwy 20",
    "sg:city":"Angola",
    "sg:classifiers":[
        {
            "category":"Organizations",
            "subcategory":"Community Association",
            "type":"Services"
        }
    ],
    "sg:phone":"+1 260 665 3363",
    "sg:postcode":"46703",
    "sg:province":"MI",
    "sg:tags":[
        "military"
    ],
    "wof:name":"American Legion",
    "wof:placetype":"venue"
},
  "geometry": {"coordinates":[-85.027159,41.634995],"type":"Point"}
}