{
  "type": "Feature",
  "properties": {
    "iso:country":"US",
    "sg:address":"3965 Williams Rd",
    "sg:city":"Columbiaville",
    "sg:classifiers":[
        {
            "category":"Social Services",
            "subcategory":"Job Training",
            "type":"Services"
        }
    ],
    "sg:phone":"+1 810 793 1396",
    "sg:postcode":"48421",
    "sg:province":"MI",
    "wof:name":"Workforce Training",
    "wof:placetype":"venue"
},
  "geometry": {"coordinates":[-83.38386,43.166457],"type":"Point"}
}