{
  "type": "Feature",
  "properties": {
    "iso:country":"US",
    "sg:address":"9902 W Walnut St",
    "sg:city":"Lake City",
    "sg:classifiers":[
        {
            "category":"Retail",
            "subcategory":"Auto Repair",
            "type":"Services"
        }
    ],
    "sg:phone":"+1 231 775 3162",
    "sg:postcode":"49651",
    "sg:province":"MI",
    "sg:tags":[
        "repairing",
        "automobile"
    ],
    "wof:name":"Lee's Service",
    "wof:placetype":"venue"
},
  "geometry": {"coordinates":[-85.29307300000001,44.332031],"type":"Point"}
}