{
  "type": "Feature",
  "properties": {
    "iso:country":"US",
    "sg:address":"2321 Kent Blvd NE",
    "sg:city":"Grand Rapids",
    "sg:classifiers":[
        {
            "category":"Communications",
            "subcategory":"Film & Video Production",
            "type":"Services"
        }
    ],
    "sg:phone":"+1 616 451 4944",
    "sg:postcode":"49503",
    "sg:province":"MI",
    "sg:tags":[
        "motion"
    ],
    "wof:name":"1st Fruits Productions Co",
    "wof:placetype":"venue"
},
  "geometry": {"coordinates":[-85.612009,42.967421],"type":"Point"}
}