{
  "type": "Feature",
  "properties": {
    "iso:country":"US",
    "sg:address":"155 E Grand",
    "sg:city":"Detroit",
    "sg:classifiers":[
        {
            "category":"Banks & Credit Unions",
            "subcategory":"Financial Services",
            "type":"Services"
        }
    ],
    "sg:phone":"+1 313 867 3919",
    "sg:postcode":"48203",
    "sg:province":"MI",
    "sg:tags":[
        "investor"
    ],
    "wof:name":"MA Real Investments",
    "wof:placetype":"venue"
},
  "geometry": {"coordinates":[-83.09179899999999,42.405683],"type":"Point"}
}