{
  "type": "Feature",
  "properties": {
    "iso:country":"US",
    "sg:address":"14410 Toepfer Rd",
    "sg:city":"Warren",
    "sg:classifiers":[
        {
            "category":"Social Services",
            "subcategory":"Child Care",
            "type":"Services"
        }
    ],
    "sg:phone":"+1 586 778 8625",
    "sg:postcode":"48089",
    "sg:province":"MI",
    "sg:tags":[
        "day"
    ],
    "wof:name":"Carousel's Child Care",
    "wof:placetype":"venue"
},
  "geometry": {"coordinates":[-82.975128,42.456906],"type":"Point"}
}