{
  "type": "Feature",
  "properties": {
    "iso:country":"US",
    "sg:address":"1203 S Geneva Dr",
    "sg:city":"Dewitt",
    "sg:classifiers":[
        {
            "category":"Social Services",
            "subcategory":"Child Care",
            "type":"Services"
        }
    ],
    "sg:phone":"+1 517 669 2577",
    "sg:postcode":"48820",
    "sg:province":"MI",
    "sg:tags":[
        "day"
    ],
    "wof:name":"Deborah A Hunt",
    "wof:placetype":"venue"
},
  "geometry": {"coordinates":[-84.586766,42.829842],"type":"Point"}
}