{
  "type": "Feature",
  "properties": {
    "iso:country":"US",
    "sg:address":"21641 Meyers Rd",
    "sg:city":"Oak Park",
    "sg:classifiers":[
        {
            "category":"Professional",
            "subcategory":"Business Services",
            "type":"Services"
        }
    ],
    "sg:phone":"+1 248 544 2552",
    "sg:postcode":"48237",
    "sg:province":"MI",
    "sg:tags":[
        "water",
        "treatment"
    ],
    "sg:website":"www.biomininc.com",
    "wof:name":"Biomin Inc",
    "wof:placetype":"venue"
},
  "geometry": {"coordinates":[-83.17187699999999,42.453174],"type":"Point"}
}