{
  "type": "Feature",
  "properties": {
    "iso:country":"US",
    "sg:address":"1133 W Long Lake Rd",
    "sg:city":"Bloomfield Hills",
    "sg:classifiers":[
        {
            "category":"Professional",
            "subcategory":"Management & Consulting",
            "type":"Services"
        }
    ],
    "sg:phone":"+1 248 433 3323",
    "sg:postcode":"48302",
    "sg:province":"MI",
    "sg:tags":[
        "consultant",
        "educational"
    ],
    "wof:name":"Master Lynne Silverberg",
    "wof:placetype":"venue"
},
  "geometry": {"coordinates":[-83.283753,42.581174],"type":"Point"}
}