{
  "type": "Feature",
  "properties": {
    "iso:country":"US",
    "sg:address":"39277 Grand River Ave",
    "sg:city":"Farmington",
    "sg:classifiers":[
        {
            "category":"Shopping",
            "subcategory":"Florist",
            "type":"Retail Goods"
        }
    ],
    "sg:phone":"+1 248 477 8931",
    "sg:postcode":"48335",
    "sg:province":"MI",
    "sg:website":"www.ourlittleflowershop.net",
    "wof:name":"Little Flower Shop",
    "wof:placetype":"venue"
},
  "geometry": {"coordinates":[-83.433998,42.471401],"type":"Point"}
}