{
  "type": "Feature",
  "properties": {
    "iso:country":"US",
    "sg:address":"64 Macomb Pl",
    "sg:city":"Mount Clemens",
    "sg:classifiers":[
        {
            "category":"Restaurant",
            "type":"Food & Drink"
        }
    ],
    "sg:phone":"+1 586 468 3250",
    "sg:postcode":"48043",
    "sg:province":"MI",
    "sg:tags":[
        "sandwich"
    ],
    "sg:website":"www.mayasdeli.com",
    "wof:name":"Maya's Deli",
    "wof:placetype":"venue"
},
  "geometry": {"coordinates":[-82.87840300000001,42.5984],"type":"Point"}
}