{
  "type": "Feature",
  "properties": {
    "iso:country":"US",
    "sg:address":"727 Crosby St NW",
    "sg:city":"Grand Rapids",
    "sg:classifiers":[
        {
            "category":"Restaurant",
            "type":"Food & Drink"
        }
    ],
    "sg:phone":"+1 616 451 2737",
    "sg:postcode":"49504",
    "sg:province":"MI",
    "sg:tags":[
        "eating"
    ],
    "wof:name":"Pams Catering",
    "wof:placetype":"venue"
},
  "geometry": {"coordinates":[-85.686761,42.987078],"type":"Point"}
}