{
  "type": "Feature",
  "properties": {
    "iso:country":"US",
    "sg:address":"68339 Beech St",
    "sg:city":"Richmond",
    "sg:classifiers":[
        {
            "category":"Travel",
            "subcategory":"Hotels & Motels",
            "type":"Entertainment"
        }
    ],
    "sg:phone":"+1 586 727 9163",
    "sg:postcode":"48062",
    "sg:province":"MI",
    "wof:name":"Cook Hotel",
    "wof:placetype":"venue"
},
  "geometry": {"coordinates":[-82.750862,42.804215],"type":"Point"}
}