{
  "type": "Feature",
  "properties": {
    "iso:country":"US",
    "sg:address":"1484 Straits Dr",
    "sg:city":"Bay City",
    "sg:classifiers":[
        {
            "category":"Restaurant",
            "type":"Food & Drink"
        }
    ],
    "sg:phone":"+1 989 671 1194",
    "sg:postcode":"48706",
    "sg:province":"MI",
    "sg:tags":[
        "delicatessen"
    ],
    "wof:name":"Michigan Deli",
    "wof:placetype":"venue"
},
  "geometry": {"coordinates":[-83.993014,43.59268],"type":"Point"}
}