{
  "type": "Feature",
  "properties": {
    "iso:country":"US",
    "sg:address":"10040 Dix",
    "sg:city":"Dearborn",
    "sg:classifiers":[
        {
            "category":"Food & Beverages",
            "subcategory":"Groceries & Convenience Stores",
            "type":"Retail Goods"
        },
        {
            "category":"Food & Beverages",
            "subcategory":"Meat & Fish",
            "type":"Retail Goods"
        },
        {
            "category":"Food & Beverages",
            "subcategory":"Ethnic Foods",
            "type":"Retail Goods"
        }
    ],
    "sg:phone":"+1 313 841 4650",
    "sg:postcode":"48120",
    "sg:province":"MI",
    "sg:tags":[
        "shop"
    ],
    "wof:name":"Arabian Village Market",
    "wof:placetype":"venue"
},
  "geometry": {"coordinates":[-83.145352,42.303951],"type":"Point"}
}