{
  "type": "Feature",
  "properties": {
    "iso:country":"US",
    "sg:address":"154 84th St SW",
    "sg:city":"Byron Center",
    "sg:classifiers":[
        {
            "category":"Retail",
            "subcategory":"Repair Shop",
            "type":"Services"
        }
    ],
    "sg:phone":"+1 616 281 9500",
    "sg:postcode":"49315",
    "sg:province":"MI",
    "sg:tags":[
        "compressor"
    ],
    "sg:website":"www.aircompressors.com",
    "wof:name":"Ohio Transmission Corp Air",
    "wof:placetype":"venue"
},
  "geometry": {"coordinates":[-85.66873699999999,42.811713],"type":"Point"}
}