{
  "type": "Feature",
  "properties": {
    "iso:country":"US",
    "sg:address":"8585 Durham Ct",
    "sg:city":"Ypsilanti",
    "sg:classifiers":[
        {
            "category":"Professional",
            "subcategory":"Business Services",
            "type":"Services"
        }
    ],
    "sg:phone":"+1 734 483 5033",
    "sg:postcode":"48198",
    "sg:province":"MI",
    "wof:name":"Jabari Enterprises Inc",
    "wof:placetype":"venue"
},
  "geometry": {"coordinates":[-83.589642,42.267679],"type":"Point"}
}