{
  "type": "Feature",
  "properties": {
    "iso:country":"US",
    "sg:address":"2227 W 120th St",
    "sg:city":"Grant",
    "sg:classifiers":[
        {
            "category":"Building & Trades",
            "subcategory":"Construction",
            "type":"Services"
        }
    ],
    "sg:phone":"+1 231 834 5907",
    "sg:postcode":"49327",
    "sg:province":"MI",
    "sg:tags":[
        "excavating",
        "contractor"
    ],
    "wof:name":"Geers Excavating",
    "wof:placetype":"venue"
},
  "geometry": {"coordinates":[-85.866055,43.336526],"type":"Point"}
}