{
  "type": "Feature",
  "properties": {
    "iso:country":"US",
    "sg:address":"27727 Donelson Dr",
    "sg:city":"Novi",
    "sg:classifiers":[
        {
            "category":"Shopping",
            "subcategory":"Computers & Home Electronics",
            "type":"Retail Goods"
        }
    ],
    "sg:phone":"+1 248 347 0611",
    "sg:postcode":"48377",
    "sg:province":"MI",
    "sg:tags":[
        "game",
        "video"
    ],
    "wof:name":"Electronics Boutique",
    "wof:placetype":"venue"
},
  "geometry": {"coordinates":[-83.482423,42.494781],"type":"Point"}
}