{
  "type": "Feature",
  "properties": {
    "iso:country":"US",
    "sg:address":"14401 Hubbard Lake Rd",
    "sg:city":"Hubbard Lake",
    "sg:classifiers":[
        {
            "category":"Building & Trades",
            "subcategory":"Construction",
            "type":"Services"
        }
    ],
    "sg:phone":"+1 586 291 8314",
    "sg:postcode":"49747",
    "sg:province":"MI",
    "sg:tags":[
        "gen",
        "contractor"
    ],
    "wof:name":"Dennys Welding & Construction",
    "wof:placetype":"venue"
},
  "geometry": {"coordinates":[-83.587217,44.86643],"type":"Point"}
}