{
  "type": "Feature",
  "properties": {
    "iso:country":"US",
    "sg:address":"1572 Fort St",
    "sg:city":"Lincoln Park",
    "sg:classifiers":[
        {
            "category":"Restaurant",
            "type":"Food & Drink"
        }
    ],
    "sg:phone":"+1 313 383 9705",
    "sg:postcode":"48146",
    "sg:province":"MI",
    "sg:tags":[
        "eating"
    ],
    "wof:name":"Wong's Chop Suey",
    "wof:placetype":"venue"
},
  "geometry": {"coordinates":[-83.174896,42.2533],"type":"Point"}
}