{
  "type": "Feature",
  "properties": {
    "iso:country":"US",
    "sg:address":"3663 Washington St",
    "sg:city":"Snover",
    "sg:classifiers":[
        {
            "category":"Government",
            "subcategory":"Fire Station",
            "type":"Public Place"
        }
    ],
    "sg:phone":"+1 810 648 2131",
    "sg:postcode":"48472",
    "sg:province":"MI",
    "sg:tags":[
        "department"
    ],
    "wof:name":"Snover Fire Dept",
    "wof:placetype":"venue"
},
  "geometry": {"coordinates":[-82.975573,43.460949],"type":"Point"}
}