{
  "type": "Feature",
  "properties": {
    "iso:country":"US",
    "sg:address":"11781 Longsdorf St",
    "sg:city":"Wyandotte",
    "sg:classifiers":[
        {
            "category":"Wholesale",
            "subcategory":"Hardware",
            "type":"Manufacturing & Wholesale Goods"
        }
    ],
    "sg:phone":"+1 734 283 9292",
    "sg:postcode":"48193",
    "sg:province":"MI",
    "sg:tags":[
        "air",
        "parts",
        "conditioning",
        "heating"
    ],
    "wof:name":"Flame Furnace Co",
    "wof:placetype":"venue"
},
  "geometry": {"coordinates":[-83.171269,42.177804],"type":"Point"}
}