{
  "type": "Feature",
  "properties": {
    "iso:country":"US",
    "sg:address":"50353 Foxcrest St",
    "sg:city":"New Baltimore",
    "sg:classifiers":[
        {
            "category":"Building & Trades",
            "subcategory":"Construction",
            "type":"Services"
        }
    ],
    "sg:phone":"+1 586 716 1125",
    "sg:postcode":"48047",
    "sg:province":"MI",
    "sg:tags":[
        "excavation",
        "contractor"
    ],
    "wof:name":"C & G Excavating Services",
    "wof:placetype":"venue"
},
  "geometry": {"coordinates":[-82.780259,42.670364],"type":"Point"}
}