{
  "type": "Feature",
  "properties": {
    "iso:country":"US",
    "sg:address":"18 W Burdick St",
    "sg:city":"Oxford",
    "sg:classifiers":[
        {
            "category":"Government",
            "subcategory":"Office",
            "type":"Public Place"
        }
    ],
    "sg:phone":"+1 248 628 9787",
    "sg:postcode":"48371",
    "sg:province":"MI",
    "sg:tags":[
        "village"
    ],
    "wof:name":"Oxford Township Office",
    "wof:placetype":"venue"
},
  "geometry": {"coordinates":[-83.27425599999999,42.824433],"type":"Point"}
}