{
  "type": "Feature",
  "properties": {
    "iso:country":"US",
    "sg:address":"506 US Hwy 10",
    "sg:city":"Evart",
    "sg:classifiers":[
        {
            "category":"Building & Trades",
            "subcategory":"Construction",
            "type":"Services"
        }
    ],
    "sg:phone":"+1 231 734 2279",
    "sg:postcode":"49631",
    "sg:province":"MI",
    "sg:tags":[
        "insulation",
        "heat",
        "contractor"
    ],
    "wof:name":"Four Seasons Cellulose Insltn",
    "wof:placetype":"venue"
},
  "geometry": {"coordinates":[-85.26567900000001,43.90068],"type":"Point"}
}