{
  "type": "Feature",
  "properties": {
    "iso:country":"US",
    "sg:address":"2020 Garfield Rd N",
    "sg:city":"Traverse City",
    "sg:classifiers":[
        {
            "category":"Restaurant",
            "type":"Food & Drink"
        }
    ],
    "sg:phone":"+1 231 932 0897",
    "sg:postcode":"49686",
    "sg:province":"MI",
    "wof:name":"A & W Family Restaurant",
    "wof:placetype":"venue"
},
  "geometry": {"coordinates":[-85.595439,44.717851],"type":"Point"}
}