{
  "type": "Feature",
  "properties": {
    "iso:country":"US",
    "sg:address":"7362 Hidden Forest Ct",
    "sg:city":"Hudsonville",
    "sg:classifiers":[
        {
            "category":"Building & Trades",
            "subcategory":"Construction",
            "type":"Services"
        }
    ],
    "sg:phone":"+1 616 662 6227",
    "sg:postcode":"49426",
    "sg:province":"MI",
    "sg:tags":[
        "painter"
    ],
    "wof:name":"Sun Painting",
    "wof:placetype":"venue"
},
  "geometry": {"coordinates":[-85.896439,42.902918],"type":"Point"}
}