{
  "type": "Feature",
  "properties": {
    "iso:country":"US",
    "sg:address":"9325 W Michigan Ave",
    "sg:city":"Saline",
    "sg:classifiers":[
        {
            "category":"Wholesale",
            "subcategory":"Farm Supplies",
            "type":"Manufacturing & Wholesale Goods"
        }
    ],
    "sg:phone":"+1 734 429 2300",
    "sg:postcode":"48176",
    "sg:province":"MI",
    "sg:tags":[
        "equipment"
    ],
    "wof:name":"Saline Valley Fertilizer",
    "wof:placetype":"venue"
},
  "geometry": {"coordinates":[-83.808942,42.155586],"type":"Point"}
}