{
  "type": "Feature",
  "properties": {
    "iso:country":"US",
    "sg:address":"2800 W Big Beaver Rd",
    "sg:city":"Troy",
    "sg:classifiers":[
        {
            "category":"Building & Trades",
            "subcategory":"Construction",
            "type":"Services"
        }
    ],
    "sg:phone":"+1 248 816 0945",
    "sg:postcode":"48084",
    "sg:province":"MI",
    "sg:tags":[
        "contractor"
    ],
    "wof:name":"Forbes Cohen Construction",
    "wof:placetype":"venue"
},
  "geometry": {"coordinates":[-83.18380000000001,42.561501],"type":"Point"}
}