{
  "type": "Feature",
  "properties": {
    "iso:country":"US",
    "sg:address":"1401 Madison Ave SE",
    "sg:city":"Grand Rapids",
    "sg:classifiers":[
        {
            "category":"Wholesale",
            "subcategory":"Furniture",
            "type":"Manufacturing & Wholesale Goods"
        }
    ],
    "sg:phone":"+1 616 245 1864",
    "sg:postcode":"49507",
    "sg:province":"MI",
    "wof:name":"Jack Peterson Sales",
    "wof:placetype":"venue"
},
  "geometry": {"coordinates":[-85.65870700000001,42.937377],"type":"Point"}
}