{
  "type": "Feature",
  "properties": {
    "iso:country":"US",
    "sg:address":"201 N Riverside Ave",
    "sg:city":"Saint Clair",
    "sg:classifiers":[
        {
            "category":"Professional",
            "subcategory":"Management & Consulting",
            "type":"Services"
        }
    ],
    "sg:phone":"+1 810 326 1700",
    "sg:postcode":"48079",
    "sg:province":"MI",
    "wof:name":"Financial Coach",
    "wof:placetype":"venue"
},
  "geometry": {"coordinates":[-82.485187,42.827231],"type":"Point"}
}