{
  "type": "Feature",
  "properties": {
    "iso:country":"US",
    "sg:address":"2889 Deerfield",
    "sg:city":"Lake Orion",
    "sg:classifiers":[
        {
            "category":"Food & Beverages",
            "subcategory":"Fruits & Vegetables",
            "type":"Retail Goods"
        }
    ],
    "sg:phone":"+1 248 391 1988",
    "sg:postcode":"48360",
    "sg:province":"MI",
    "sg:tags":[
        "produce"
    ],
    "wof:name":"Ciara Produce Outlet",
    "wof:placetype":"venue"
},
  "geometry": {"coordinates":[-83.242695,42.739135],"type":"Point"}
}