{
  "type": "Feature",
  "properties": {
    "iso:country":"US",
    "sg:address":"128 Jordan",
    "sg:city":"East Jordan",
    "sg:classifiers":[
        {
            "category":"Retail",
            "subcategory":"Self-service Laundry",
            "type":"Services"
        }
    ],
    "sg:phone":"+1 231 536 2800",
    "sg:postcode":"49727",
    "sg:province":"MI",
    "wof:name":"Jordan Cleaning Ctr",
    "wof:placetype":"venue"
},
  "geometry": {"coordinates":[-85.134793,45.153524],"type":"Point"}
}