{
  "type": "Feature",
  "properties": {
    "iso:country":"US",
    "sg:address":"904 6th St",
    "sg:city":"Bay City",
    "sg:classifiers":[
        {
            "category":"Organizations",
            "subcategory":"Non-profit Organization",
            "type":"Services"
        }
    ],
    "sg:phone":"+1 989 891 0272",
    "sg:postcode":"48708",
    "sg:province":"MI",
    "sg:tags":[
        "information",
        "alcoholism",
        "treatment"
    ],
    "wof:name":"Bridgewater",
    "wof:placetype":"venue"
},
  "geometry": {"coordinates":[-83.88017000000001,43.596325],"type":"Point"}
}