{
  "type": "Feature",
  "properties": {
    "iso:country":"US",
    "sg:address":"13287 Hall Rd",
    "sg:city":"Shelby Twp",
    "sg:classifiers":[
        {
            "category":"Shopping",
            "subcategory":"Clothing, Apparel, & Fashions",
            "type":"Retail Goods"
        }
    ],
    "sg:phone":"+1 586 739 3888",
    "sg:postcode":"48315",
    "sg:province":"MI",
    "sg:tags":[
        "accessory",
        "clothing",
        "women's"
    ],
    "sg:website":"www.dots.com",
    "wof:name":"Dots Inc",
    "wof:placetype":"venue"
},
  "geometry": {"coordinates":[-82.996399,42.627399],"type":"Point"}
}