{
  "type": "Feature",
  "properties": {
    "iso:country":"US",
    "sg:address":"7825 Bellevue Rd",
    "sg:city":"Grosse Ile",
    "sg:classifiers":[
        {
            "category":"Professional",
            "subcategory":"Employment Agencies",
            "type":"Services"
        }
    ],
    "sg:phone":"+1 734 676 6236",
    "sg:postcode":"48138",
    "sg:province":"MI",
    "sg:tags":[
        "help",
        "supply"
    ],
    "wof:name":"Camco Services Inc",
    "wof:placetype":"venue"
},
  "geometry": {"coordinates":[-83.146012,42.123072],"type":"Point"}
}