{
  "type": "Feature",
  "properties": {
    "iso:country":"US",
    "sg:address":"14790 Loyola Dr",
    "sg:city":"Sterling Heights",
    "sg:classifiers":[
        {
            "category":"Building & Trades",
            "subcategory":"Equipment Rental",
            "type":"Services"
        }
    ],
    "sg:phone":"+1 586 247 9892",
    "sg:postcode":"48313",
    "sg:province":"MI",
    "sg:tags":[
        "sound",
        "lighting"
    ],
    "wof:name":"Band Ayd Systems International",
    "wof:placetype":"venue"
},
  "geometry": {"coordinates":[-82.976906,42.604892],"type":"Point"}
}