{
  "type": "Feature",
  "properties": {
    "iso:country":"US",
    "sg:address":"1843 Bradley Ave",
    "sg:city":"Lansing",
    "sg:classifiers":[
        {
            "category":"Building & Trades",
            "subcategory":"Construction",
            "type":"Services"
        }
    ],
    "sg:phone":"+1 517 484 5430",
    "sg:postcode":"48910",
    "sg:province":"MI",
    "wof:name":"Buckley Asphalt",
    "wof:placetype":"venue"
},
  "geometry": {"coordinates":[-84.558446,42.712785],"type":"Point"}
}