{
  "type": "Feature",
  "properties": {
    "iso:country":"US",
    "sg:address":"3600 W Auburn Rd",
    "sg:city":"Rochester Hills",
    "sg:classifiers":[
        {
            "category":"Retail",
            "subcategory":"Animal Services",
            "type":"Services"
        }
    ],
    "sg:phone":"+1 248 650 1059",
    "sg:postcode":"48309",
    "sg:province":"MI",
    "sg:tags":[
        "pet"
    ],
    "sg:website":"www.michiganhumane.org",
    "wof:name":"Michigan Humane Society Pet Education Center",
    "wof:placetype":"venue"
},
  "geometry": {"coordinates":[-83.203102,42.634201],"type":"Point"}
}