{
  "type": "Feature",
  "properties": {
    "iso:country":"US",
    "sg:address":"287 W 40th St",
    "sg:city":"Holland",
    "sg:classifiers":[
        {
            "category":"Real Estate",
            "subcategory":"Real Estate Operator",
            "type":"Services"
        }
    ],
    "sg:phone":"+1 616 396 7621",
    "sg:postcode":"49423",
    "sg:province":"MI",
    "sg:tags":[
        "building",
        "apartment"
    ],
    "wof:name":"Harbor Villiage Apartments",
    "wof:placetype":"venue"
},
  "geometry": {"coordinates":[-86.118989,42.761649],"type":"Point"}
}