{
  "type": "Feature",
  "properties": {
    "iso:country":"US",
    "sg:address":"1923 Pipestone Rd",
    "sg:city":"Benton Harbor",
    "sg:classifiers":[
        {
            "category":"Banks & Credit Unions",
            "subcategory":"Bank",
            "type":"Services"
        }
    ],
    "sg:phone":"+1 269 925 1433",
    "sg:postcode":"49022",
    "sg:province":"MI",
    "sg:tags":[
        "loan"
    ],
    "wof:name":"Cash Store",
    "wof:placetype":"venue"
},
  "geometry": {"coordinates":[-86.419612,42.085941],"type":"Point"}
}