{
  "type": "Feature",
  "properties": {
    "iso:country":"US",
    "sg:address":"16400 Oakley Rd",
    "sg:city":"Chesaning",
    "sg:classifiers":[
        {
            "category":"Freight",
            "type":"Transportation"
        }
    ],
    "sg:phone":"+1 989 845 6142",
    "sg:postcode":"48616",
    "sg:province":"MI",
    "sg:tags":[
        "trucking"
    ],
    "wof:name":"T & J Transport Inc",
    "wof:placetype":"venue"
},
  "geometry": {"coordinates":[-84.168981,43.181024],"type":"Point"}
}