{
  "type": "Feature",
  "properties": {
    "iso:country":"US",
    "sg:address":"24825 Hathaway St",
    "sg:city":"Farmington Hills",
    "sg:classifiers":[
        {
            "category":"Personal",
            "type":"Services"
        }
    ],
    "sg:phone":"+1 248 478 6779",
    "sg:postcode":"48335",
    "sg:province":"MI",
    "sg:tags":[
        "towing"
    ],
    "wof:name":"Allstate Towing Inc",
    "wof:placetype":"venue"
},
  "geometry": {"coordinates":[-83.423401,42.4739],"type":"Point"}
}