{
  "type": "Feature",
  "properties": {
    "iso:country":"US",
    "sg:address":"614 Capital Ave NE",
    "sg:city":"Battle Creek",
    "sg:classifiers":[
        {
            "category":"Professional",
            "subcategory":"Advertising",
            "type":"Services"
        }
    ],
    "sg:phone":"+1 269 965 1363",
    "sg:postcode":"49017",
    "sg:province":"MI",
    "sg:tags":[
        "counselor"
    ],
    "wof:name":"Montage Productions",
    "wof:placetype":"venue"
},
  "geometry": {"coordinates":[-85.158511,42.326838],"type":"Point"}
}