{
  "type": "Feature",
  "properties": {
    "iso:country":"US",
    "sg:address":"2510 Weiss St",
    "sg:city":"Saginaw",
    "sg:classifiers":[
        {
            "category":"Banks & Credit Unions",
            "subcategory":"Bank",
            "type":"Services"
        }
    ],
    "sg:phone":"+1 989 799 5580",
    "sg:postcode":"48602",
    "sg:province":"MI",
    "sg:tags":[
        "state",
        "loan",
        "broker"
    ],
    "sg:website":"www.choicecu.org",
    "wof:name":"Consumers Choice Credit Union",
    "wof:placetype":"venue"
},
  "geometry": {"coordinates":[-83.975354,43.443782],"type":"Point"}
}