{
  "type": "Feature",
  "properties": {
    "iso:country":"US",
    "sg:address":"1537 E Hill Rd Ste 400",
    "sg:city":"Grand Blanc",
    "sg:classifiers":[
        {
            "category":"Health Services",
            "subcategory":"Health Practitioner",
            "type":"Services"
        }
    ],
    "sg:phone":"+1 810 603 1100",
    "sg:postcode":"48439",
    "sg:province":"MI",
    "sg:tags":[
        "therapy",
        "physical"
    ],
    "wof:name":"Michigan Extremity Care",
    "wof:placetype":"venue"
},
  "geometry": {"coordinates":[-83.672586,42.944248],"type":"Point"}
}