{
  "type": "Feature",
  "properties": {
    "iso:country":"US",
    "sg:address":"6640 Cooley Lake Rd",
    "sg:city":"Waterford",
    "sg:classifiers":[
        {
            "category":"Shopping",
            "subcategory":"Party Supplies",
            "type":"Retail Goods"
        },
        {
            "category":"Personal",
            "type":"Services"
        }
    ],
    "sg:phone":"+1 248 366 8855",
    "sg:postcode":"48327",
    "sg:province":"MI",
    "sg:tags":[
        "planning",
        "event"
    ],
    "wof:name":"Liquor Station",
    "wof:placetype":"venue"
},
  "geometry": {"coordinates":[-83.41685,42.616094],"type":"Point"}
}