{
  "type": "Feature",
  "properties": {
    "iso:country":"US",
    "sg:address":"407 N Lincoln St",
    "sg:city":"Bay City",
    "sg:classifiers":[
        {
            "category":"Professional",
            "subcategory":"Detective & Security Services",
            "type":"Services"
        }
    ],
    "sg:phone":"+1 989 893 0352",
    "sg:postcode":"48708",
    "sg:province":"MI",
    "sg:tags":[
        "investigator"
    ],
    "wof:name":"M B Investigations",
    "wof:placetype":"venue"
},
  "geometry": {"coordinates":[-83.876531,43.594073],"type":"Point"}
}