{
  "type": "Feature",
  "properties": {
    "iso:country":"US",
    "sg:address":"11437 15 Mile Rd",
    "sg:city":"Sterling Heights",
    "sg:classifiers":[
        {
            "category":"Health Services",
            "subcategory":"Chiropractor",
            "type":"Services"
        }
    ],
    "sg:phone":"+1 586 264 4700",
    "sg:postcode":"48312",
    "sg:province":"MI",
    "sg:website":"www.renochiro.com",
    "wof:name":"Reno Chiropractic Center",
    "wof:placetype":"venue"
},
  "geometry": {"coordinates":[-83.011803,42.5518],"type":"Point"}
}