{
  "type": "Feature",
  "properties": {
    "iso:country":"US",
    "sg:address":"3310 Iroquois Ave",
    "sg:city":"Flint",
    "sg:classifiers":[
        {
            "category":"Freight",
            "type":"Transportation"
        }
    ],
    "sg:phone":"+1 810 785 7382",
    "sg:postcode":"48505",
    "sg:province":"MI",
    "sg:tags":[
        "delivery"
    ],
    "wof:name":"R D Hendrix & Svc",
    "wof:placetype":"venue"
},
  "geometry": {"coordinates":[-83.71092400000001,43.046235],"type":"Point"}
}