{
  "type": "Feature",
  "properties": {
    "iso:country":"US",
    "sg:address":"16583 Ward St",
    "sg:city":"Detroit",
    "sg:classifiers":[
        {
            "category":"Social Services",
            "subcategory":"Adult Care",
            "type":"Services"
        }
    ],
    "sg:phone":"+1 313 864 6274",
    "sg:postcode":"48235",
    "sg:province":"MI",
    "sg:tags":[
        "residential"
    ],
    "wof:name":"Jack 1",
    "wof:placetype":"venue"
},
  "geometry": {"coordinates":[-83.1742,42.413569],"type":"Point"}
}