{
  "type": "Feature",
  "properties": {
    "iso:country":"US",
    "sg:address":"47054 Malburg Way Dr",
    "sg:city":"Macomb",
    "sg:classifiers":[
        {
            "category":"Building & Trades",
            "subcategory":"Construction",
            "type":"Services"
        },
        {
            "category":"Building & Trades",
            "subcategory":"Plumbing",
            "type":"Services"
        }
    ],
    "sg:phone":"+1 586 948 5332",
    "sg:postcode":"48044",
    "sg:province":"MI",
    "sg:tags":[
        "plumbing",
        "contractor"
    ],
    "wof:name":"G Richards Plumbing Repair",
    "wof:placetype":"venue"
},
  "geometry": {"coordinates":[-82.89046500000001,42.646568],"type":"Point"}
}