{
  "type": "Feature",
  "properties": {
    "iso:country":"US",
    "sg:address":"6315 Sashabaw Rd",
    "sg:city":"Clarkston",
    "sg:classifiers":[
        {
            "category":"Restaurant",
            "type":"Food & Drink"
        }
    ],
    "sg:phone":"+1 248 620 4444",
    "sg:postcode":"48346",
    "sg:province":"MI",
    "wof:name":"Mikie's Roosters & Ribs",
    "wof:placetype":"venue"
},
  "geometry": {"coordinates":[-83.37939,42.731546],"type":"Point"}
}