{
  "type": "Feature",
  "properties": {
    "iso:country":"US",
    "sg:address":"2424 Eastern Ave SE",
    "sg:city":"Grand Rapids",
    "sg:classifiers":[
        {
            "category":"Wholesale",
            "subcategory":"Machinery & Supplies",
            "type":"Manufacturing & Wholesale Goods"
        }
    ],
    "sg:phone":"+1 616 949 1861",
    "sg:postcode":"49507",
    "sg:province":"MI",
    "sg:tags":[
        "equipment",
        "printing"
    ],
    "sg:website":"www.excellomachineco.com",
    "wof:name":"Excello Machine Co",
    "wof:placetype":"venue"
},
  "geometry": {"coordinates":[-85.647367,42.918643],"type":"Point"}
}