{
  "type": "Feature",
  "properties": {
    "iso:country":"US",
    "sg:address":"1716 Lansing Rd",
    "sg:city":"Charlotte",
    "sg:classifiers":[
        {
            "category":"Real Estate",
            "subcategory":"Real Estate Operator",
            "type":"Services"
        }
    ],
    "sg:phone":"+1 517 543 4160",
    "sg:postcode":"48813",
    "sg:province":"MI",
    "sg:tags":[
        "mobile",
        "home",
        "site"
    ],
    "wof:name":"Maple Knoll Mobile Hm Pk Cmnty",
    "wof:placetype":"venue"
},
  "geometry": {"coordinates":[-84.80426799999999,42.584339],"type":"Point"}
}