{
  "type": "Feature",
  "properties": {
    "iso:country":"US",
    "sg:address":"34835 Dequindre Rd",
    "sg:city":"Troy",
    "sg:classifiers":[
        {
            "category":"Retail",
            "subcategory":"Auto Repair",
            "type":"Services"
        }
    ],
    "sg:phone":"+1 248 528 3350",
    "sg:postcode":"48083",
    "sg:province":"MI",
    "sg:tags":[
        "muffler",
        "exhaust",
        "system"
    ],
    "wof:name":"Muffler Man",
    "wof:placetype":"venue"
},
  "geometry": {"coordinates":[-83.08820299999999,42.548698],"type":"Point"}
}