{
  "type": "Feature",
  "properties": {
    "iso:country":"US",
    "sg:address":"8590 Esper St",
    "sg:city":"Detroit",
    "sg:classifiers":[
        {
            "category":"Social Services",
            "subcategory":"Child Care",
            "type":"Services"
        }
    ],
    "sg:phone":"+1 313 834 4396",
    "sg:postcode":"48204",
    "sg:province":"MI",
    "sg:tags":[
        "day"
    ],
    "wof:name":"New Mt Olive Luthrn Church",
    "wof:placetype":"venue"
},
  "geometry": {"coordinates":[-83.159755,42.357328],"type":"Point"}
}