{
  "type": "Feature",
  "properties": {
    "iso:country":"US",
    "sg:address":"2389 S M 76",
    "sg:city":"West Branch",
    "sg:classifiers":[
        {
            "category":"Restaurant",
            "type":"Food & Drink"
        }
    ],
    "sg:menulink":"http://www.allmenus.com/mi/west-branch/43879-bellacinos-pizza--grinders/menu/",
    "sg:phone":"+1 989 345 9000",
    "sg:postcode":"48661",
    "sg:province":"MI",
    "sg:tags":[
        "wrap",
        "american",
        "sandwich",
        "pizza"
    ],
    "wof:name":"Bellacino's Pizza & Grinders",
    "wof:placetype":"venue"
},
  "geometry": {"coordinates":[-84.21657,44.264997],"type":"Point"}
}