{
  "type": "Feature",
  "properties": {
    "iso:country":"US",
    "sg:address":"2395 Elizabeth Lake Rd",
    "sg:city":"Waterford",
    "sg:classifiers":[
        {
            "category":"Retail",
            "subcategory":"Laundry & Dry Cleaning",
            "type":"Services"
        }
    ],
    "sg:phone":"+1 248 681 1103",
    "sg:postcode":"48328",
    "sg:province":"MI",
    "sg:tags":[
        "cleaners"
    ],
    "wof:name":"Mercedes Coin Laundry & Clnrs",
    "wof:placetype":"venue"
},
  "geometry": {"coordinates":[-83.335545,42.639676],"type":"Point"}
}