{
  "type": "Feature",
  "properties": {
    "iso:country":"US",
    "sg:address":"1655 Beaufield St",
    "sg:city":"Ferndale",
    "sg:classifiers":[
        {
            "category":"Real Estate",
            "subcategory":"Real Estate Agent",
            "type":"Services"
        }
    ],
    "sg:phone":"+1 248 541 8668",
    "sg:postcode":"48220",
    "sg:province":"MI",
    "wof:name":"Campbell & Co",
    "wof:placetype":"venue"
},
  "geometry": {"coordinates":[-83.14574399999999,42.459055],"type":"Point"}
}