{
  "type": "Feature",
  "properties": {
    "iso:country":"US",
    "sg:address":"796 W Hillis Rd",
    "sg:city":"Stanton",
    "sg:phone":"+1 989 831 4283",
    "sg:postcode":"48888",
    "sg:province":"MI",
    "sg:tags":[
        "farm",
        "corn"
    ],
    "wof:name":"Harry Christiansen",
    "wof:placetype":"venue"
},
  "geometry": {"coordinates":[-85.09500800000001,43.328976],"type":"Point"}
}