{
  "type": "Feature",
  "properties": {
    "iso:country":"US",
    "sg:address":"11240 Wamplers Lake Rd",
    "sg:city":"Brooklyn",
    "sg:classifiers":[
        {
            "category":"Building & Trades",
            "subcategory":"Construction",
            "type":"Services"
        }
    ],
    "sg:phone":"+1 517 592 2376",
    "sg:postcode":"49230",
    "sg:province":"MI",
    "sg:tags":[
        "house",
        "repair"
    ],
    "wof:name":"House To House Const Cleani",
    "wof:placetype":"venue"
},
  "geometry": {"coordinates":[-84.204058,42.098998],"type":"Point"}
}