{
  "type": "Feature",
  "properties": {
    "iso:country":"US",
    "sg:address":"1831 S Cedar St",
    "sg:city":"Imlay City",
    "sg:classifiers":[
        {
            "category":"Shopping",
            "subcategory":"Computers & Home Electronics",
            "type":"Retail Goods"
        }
    ],
    "sg:phone":"+1 810 721 8030",
    "sg:postcode":"48444",
    "sg:province":"MI",
    "sg:tags":[
        "equipment",
        "electronic",
        "supply"
    ],
    "sg:website":"www.imlaycityrs.com",
    "wof:name":"Radio Shack",
    "wof:placetype":"venue"
},
  "geometry": {"coordinates":[-83.071639,43.01186],"type":"Point"}
}