{
  "type": "Feature",
  "properties": {
    "iso:country":"US",
    "sg:address":"1434 Stacy Dr",
    "sg:city":"Canton",
    "sg:classifiers":[
        {
            "category":"Professional",
            "subcategory":"Management & Consulting",
            "type":"Services"
        }
    ],
    "sg:phone":"+1 734 397 0862",
    "sg:postcode":"48188",
    "sg:province":"MI",
    "sg:tags":[
        "public",
        "relations"
    ],
    "wof:name":"Rising Stat Promotions Plus",
    "wof:placetype":"venue"
},
  "geometry": {"coordinates":[-83.44695299999999,42.297396],"type":"Point"}
}