{
  "type": "Feature",
  "properties": {
    "iso:country":"US",
    "sg:address":"1110 Schavey Rd",
    "sg:city":"Dewitt",
    "sg:classifiers":[
        {
            "category":"Building & Trades",
            "subcategory":"Construction",
            "type":"Services"
        }
    ],
    "sg:phone":"+1 517 669 9130",
    "sg:postcode":"48820",
    "sg:province":"MI",
    "sg:tags":[
        "painter"
    ],
    "wof:name":"Alumicoat Corp",
    "wof:placetype":"venue"
},
  "geometry": {"coordinates":[-84.588804,42.832826],"type":"Point"}
}