{
  "type": "Feature",
  "properties": {
    "iso:country":"US",
    "sg:address":"38159 Spring Ln",
    "sg:city":"Farmington",
    "sg:classifiers":[
        {
            "category":"Wholesale",
            "subcategory":"Machinery & Supplies",
            "type":"Manufacturing & Wholesale Goods"
        }
    ],
    "sg:phone":"+1 313 506 0932",
    "sg:postcode":"48331",
    "sg:province":"MI",
    "sg:tags":[
        "equipment",
        "industrial"
    ],
    "wof:name":"Abrasive & Tool Supply Inc",
    "wof:placetype":"venue"
},
  "geometry": {"coordinates":[-83.41866899999999,42.483892],"type":"Point"}
}