{
  "type": "Feature",
  "properties": {
    "iso:country":"US",
    "sg:address":"4191 Karla Ct",
    "sg:city":"Midland",
    "sg:classifiers":[
        {
            "category":"Organizations",
            "subcategory":"Professional Association",
            "type":"Services"
        }
    ],
    "sg:phone":"+1 989 835 5992",
    "sg:postcode":"48642",
    "sg:province":"MI",
    "wof:name":"Wallwey Assoc",
    "wof:placetype":"venue"
},
  "geometry": {"coordinates":[-84.16207300000001,43.62099],"type":"Point"}
}