{
  "type": "Feature",
  "properties": {
    "iso:country":"US",
    "sg:address":"33191 Rose Bush Ct",
    "sg:city":"New Haven",
    "sg:classifiers":[
        {
            "category":"Sports & Exercise",
            "subcategory":"Bowling",
            "type":"Entertainment"
        }
    ],
    "sg:phone":"+1 586 749 5238",
    "sg:postcode":"48048",
    "sg:province":"MI",
    "sg:tags":[
        "center"
    ],
    "wof:name":"Faeries Flight",
    "wof:placetype":"venue"
},
  "geometry": {"coordinates":[-82.77843300000001,42.730505],"type":"Point"}
}