{
  "type": "Feature",
  "properties": {
    "iso:country":"US",
    "sg:address":"226 Feneis St",
    "sg:city":"Westphalia",
    "sg:classifiers":[
        {
            "category":"Insurance",
            "subcategory":"Insurance Agent",
            "type":"Services"
        }
    ],
    "sg:phone":"+1 989 587 4777",
    "sg:postcode":"48894",
    "sg:province":"MI",
    "wof:name":"CUNA Mutual Group",
    "wof:placetype":"venue"
},
  "geometry": {"coordinates":[-84.791454,42.930192],"type":"Point"}
}