{
  "type": "Feature",
  "properties": {
    "iso:country":"US",
    "sg:address":"415 N Jackson St",
    "sg:city":"Jackson",
    "sg:classifiers":[
        {
            "category":"Retail",
            "subcategory":"Auto Repair",
            "type":"Services"
        }
    ],
    "sg:phone":"+1 517 784 6173",
    "sg:postcode":"49201",
    "sg:province":"MI",
    "sg:tags":[
        "automotive",
        "exhaust"
    ],
    "wof:name":"Tuffy Service Centers",
    "wof:placetype":"venue"
},
  "geometry": {"coordinates":[-84.408817,42.250278],"type":"Point"}
}