{
  "type": "Feature",
  "properties": {
    "iso:country":"US",
    "sg:address":"452 S Haven St",
    "sg:city":"South Haven",
    "sg:classifiers":[
        {
            "category":"Wholesale",
            "subcategory":"Medical Equipment & Supplies",
            "type":"Manufacturing & Wholesale Goods"
        }
    ],
    "sg:phone":"+1 269 637 5920",
    "sg:postcode":"49090",
    "sg:province":"MI",
    "sg:tags":[
        "physician",
        "surgeon"
    ],
    "wof:name":"G W Care",
    "wof:placetype":"venue"
},
  "geometry": {"coordinates":[-86.27506700000001,42.39638],"type":"Point"}
}