{
  "type": "Feature",
  "properties": {
    "iso:country":"US",
    "sg:address":"2237 E Bennington Rd",
    "sg:city":"Durand",
    "sg:phone":"+1 989 743 5368",
    "sg:postcode":"48867",
    "sg:province":"MI",
    "sg:tags":[
        "farm",
        "corn"
    ],
    "wof:name":"Bob Bacigal",
    "wof:placetype":"venue"
},
  "geometry": {"coordinates":[-84.12018,42.937114],"type":"Point"}
}