{
  "type": "Feature",
  "properties": {
    "iso:country":"US",
    "sg:address":"6254 McKinley Rd",
    "sg:city":"Bridgeport",
    "sg:classifiers":[
        {
            "category":"Professional",
            "subcategory":"Business Services",
            "type":"Services"
        }
    ],
    "sg:phone":"+1 989 777 1202",
    "sg:postcode":"48722",
    "sg:province":"MI",
    "wof:name":"Computertek Solutions",
    "wof:placetype":"venue"
},
  "geometry": {"coordinates":[-83.877475,43.355754],"type":"Point"}
}