{
  "type": "Feature",
  "properties": {
    "iso:country":"US",
    "sg:address":"1637 Wood St",
    "sg:city":"Muskegon",
    "sg:classifiers":[
        {
            "category":"Organizations",
            "subcategory":"Religious Organization",
            "type":"Services"
        }
    ],
    "sg:phone":"+1 231 722 6778",
    "sg:postcode":"49442",
    "sg:province":"MI",
    "wof:name":"Higher Heights Ministries",
    "wof:placetype":"venue"
},
  "geometry": {"coordinates":[-86.234354,43.22268],"type":"Point"}
}