{
  "type": "Feature",
  "properties": {
    "iso:country":"US",
    "sg:address":"19165 Gudith Rd",
    "sg:city":"Trenton",
    "sg:classifiers":[
        {
            "category":"Shopping",
            "subcategory":"Bicycles & Sporting Goods",
            "type":"Retail Goods"
        }
    ],
    "sg:phone":"+1 734 479 4803",
    "sg:postcode":"48183",
    "sg:province":"MI",
    "sg:tags":[
        "g"
    ],
    "wof:name":"Beyond U Strength",
    "wof:placetype":"venue"
},
  "geometry": {"coordinates":[-83.25192,42.166653],"type":"Point"}
}