{
  "type": "Feature",
  "properties": {
    "iso:country":"US",
    "sg:address":"100 Minges Creek Pl",
    "sg:city":"Battle Creek",
    "sg:classifiers":[
        {
            "category":"Real Estate",
            "subcategory":"Real Estate Operator",
            "type":"Services"
        }
    ],
    "sg:phone":"+1 269 979 2120",
    "sg:postcode":"49015",
    "sg:province":"MI",
    "sg:tags":[
        "building",
        "apartment"
    ],
    "wof:name":"Landings The",
    "wof:placetype":"venue"
},
  "geometry": {"coordinates":[-85.193736,42.259934],"type":"Point"}
}