{
  "type": "Feature",
  "properties": {
    "iso:country":"US",
    "sg:address":"19365 Cumberland Way",
    "sg:city":"Detroit",
    "sg:classifiers":[
        {
            "category":"Professional",
            "type":"Services"
        }
    ],
    "sg:phone":"+1 313 892 7085",
    "sg:postcode":"48203",
    "sg:province":"MI",
    "wof:name":"Go MI Svcs LLC",
    "wof:placetype":"venue"
},
  "geometry": {"coordinates":[-83.12138,42.433952],"type":"Point"}
}