{
  "type": "Feature",
  "properties": {
    "iso:country":"US",
    "sg:address":"100 S 2nd Ave",
    "sg:city":"Alpena",
    "sg:classifiers":[
        {
            "category":"Banks & Credit Unions",
            "subcategory":"Financial Services",
            "type":"Services"
        },
        {
            "category":"Banks & Credit Unions",
            "subcategory":"Bank",
            "type":"Services"
        }
    ],
    "sg:phone":"+1 989 356 9041",
    "sg:postcode":"49707",
    "sg:province":"MI",
    "sg:tags":[
        "company",
        "commercial",
        "national",
        "holding"
    ],
    "wof:name":"Alpena Bancshares Inc",
    "wof:placetype":"venue"
},
  "geometry": {"coordinates":[-83.433381,45.062256],"type":"Point"}
}