{
  "type": "Feature",
  "properties": {
    "iso:country":"US",
    "sg:address":"3265 S Slocum Rd",
    "sg:city":"Ravenna",
    "sg:classifiers":[
        {
            "category":"Wholesale",
            "subcategory":"Farm Supplies",
            "type":"Manufacturing & Wholesale Goods"
        }
    ],
    "sg:phone":"+1 231 853 5738",
    "sg:postcode":"49451",
    "sg:province":"MI",
    "sg:tags":[
        "auction",
        "livestock",
        "market"
    ],
    "wof:name":"Ravenna Auction",
    "wof:placetype":"venue"
},
  "geometry": {"coordinates":[-85.936437,43.197329],"type":"Point"}
}