{
  "type": "Feature",
  "properties": {
    "iso:country":"US",
    "sg:address":"5071 Oakbrook Ct",
    "sg:city":"Saginaw",
    "sg:classifiers":[
        {
            "category":"Building & Trades",
            "subcategory":"Construction",
            "type":"Services"
        }
    ],
    "sg:phone":"+1 989 793 1920",
    "sg:postcode":"48603",
    "sg:province":"MI",
    "sg:tags":[
        "general",
        "contractor"
    ],
    "wof:name":"Randall Winterstein Builders",
    "wof:placetype":"venue"
},
  "geometry": {"coordinates":[-84.01912400000001,43.468049],"type":"Point"}
}