{
  "type": "Feature",
  "properties": {
    "iso:country":"US",
    "sg:address":"1420 Johnson St",
    "sg:city":"Dansville",
    "sg:classifiers":[
        {
            "category":"Government",
            "subcategory":"Fire Station",
            "type":"Public Place"
        }
    ],
    "sg:phone":"+1 517 623 6691",
    "sg:postcode":"48819",
    "sg:province":"MI",
    "sg:tags":[
        "department"
    ],
    "wof:name":"Ingham Fire Dept",
    "wof:placetype":"venue"
},
  "geometry": {"coordinates":[-84.299949,42.54985],"type":"Point"}
}