{
  "type": "Feature",
  "properties": {
    "iso:country":"US",
    "sg:address":"24800 Eureka Rd",
    "sg:city":"Taylor",
    "sg:classifiers":[
        {
            "category":"Sports & Exercise",
            "subcategory":"Bowling",
            "type":"Entertainment"
        }
    ],
    "sg:phone":"+1 734 946 9092",
    "sg:postcode":"48180",
    "sg:province":"MI",
    "wof:name":"Taylor Lanes",
    "wof:placetype":"venue"
},
  "geometry": {"coordinates":[-83.27510100000001,42.197498],"type":"Point"}
}