{
  "type": "Feature",
  "properties": {
    "iso:country":"US",
    "sg:address":"2927 W Vermontville Hwy",
    "sg:city":"Charlotte",
    "sg:classifiers":[
        {
            "category":"Food & Beverages",
            "subcategory":"Groceries & Convenience Stores",
            "type":"Retail Goods"
        }
    ],
    "sg:phone":"+1 517 543 9826",
    "sg:postcode":"48813",
    "sg:province":"MI",
    "sg:tags":[
        "station",
        "gasoline"
    ],
    "wof:name":"Jones Country Store",
    "wof:placetype":"venue"
},
  "geometry": {"coordinates":[-84.89312700000001,42.626101],"type":"Point"}
}