{
  "type": "Feature",
  "properties": {
    "iso:country":"US",
    "sg:address":"3310 N Main St",
    "sg:city":"Royal Oak",
    "sg:classifiers":[
        {
            "category":"Autos & Motor Vehicles",
            "subcategory":"Fuel & Gas Station",
            "type":"Retail Goods"
        }
    ],
    "sg:phone":"+1 248 585 5755",
    "sg:postcode":"48073",
    "sg:province":"MI",
    "sg:tags":[
        "oil"
    ],
    "sg:website":"www.speedway.com",
    "wof:name":"Consolidated Stations Inc",
    "wof:placetype":"venue"
},
  "geometry": {"coordinates":[-83.14540100000001,42.519402],"type":"Point"}
}