{
  "type": "Feature",
  "properties": {
    "iso:country":"US",
    "sg:address":"1061 E Front St",
    "sg:city":"Traverse City",
    "sg:classifiers":[
        {
            "category":"Banks & Credit Unions",
            "subcategory":"Bank",
            "type":"Services"
        }
    ],
    "sg:phone":"+1 231 929 1400",
    "sg:postcode":"49686",
    "sg:province":"MI",
    "wof:name":"Citizens Bank",
    "wof:placetype":"venue"
},
  "geometry": {"coordinates":[-85.596705,44.764232],"type":"Point"}
}