{
  "type": "Feature",
  "properties": {
    "iso:country":"US",
    "sg:address":"18741 E 13 Mile Rd",
    "sg:city":"Roseville",
    "sg:classifiers":[
        {
            "category":"Professional",
            "subcategory":"Business Services",
            "type":"Services"
        }
    ],
    "sg:phone":"+1 586 293 7153",
    "sg:postcode":"48066",
    "sg:province":"MI",
    "wof:name":"J & Kel Enterprise",
    "wof:placetype":"venue"
},
  "geometry": {"coordinates":[-82.927645,42.524598],"type":"Point"}
}