{
  "type": "Feature",
  "properties": {
    "iso:country":"US",
    "sg:address":"407 E Bay St",
    "sg:city":"East Tawas",
    "sg:classifiers":[
        {
            "category":"Travel",
            "subcategory":"Campground",
            "type":"Entertainment"
        }
    ],
    "sg:phone":"+1 989 362 5562",
    "sg:postcode":"48730",
    "sg:province":"MI",
    "sg:tags":[
        "trailer"
    ],
    "wof:name":"East Tawas City Park",
    "wof:placetype":"venue"
},
  "geometry": {"coordinates":[-83.48554,44.280414],"type":"Point"}
}