{
  "type": "Feature",
  "properties": {
    "iso:country":"US",
    "sg:address":"6918 S Dixie Hwy",
    "sg:city":"Erie",
    "sg:classifiers":[
        {
            "category":"Farming",
            "subcategory":"Farm",
            "type":"Manufacturing & Wholesale Goods"
        }
    ],
    "sg:phone":"+1 734 848 8902",
    "sg:postcode":"48133",
    "sg:province":"MI",
    "wof:name":"Morrin Farms Inc",
    "wof:placetype":"venue"
},
  "geometry": {"coordinates":[-83.521523,41.748978],"type":"Point"}
}