{
  "type": "Feature",
  "properties": {
    "iso:country":"US",
    "sg:address":"9540 Stadium Dr",
    "sg:city":"Kalamazoo",
    "sg:classifiers":[
        {
            "category":"Wholesale",
            "subcategory":"Machinery & Supplies",
            "type":"Manufacturing & Wholesale Goods"
        }
    ],
    "sg:phone":"+1 269 353 9754",
    "sg:postcode":"49009",
    "sg:province":"MI",
    "sg:tags":[
        "equipment",
        "establishment"
    ],
    "wof:name":"Matts Maintenance",
    "wof:placetype":"venue"
},
  "geometry": {"coordinates":[-85.734763,42.247819],"type":"Point"}
}