{
  "type": "Feature",
  "properties": {
    "iso:country":"US",
    "sg:address":"1151 E Paris Ave SE",
    "sg:city":"Grand Rapids",
    "sg:classifiers":[
        {
            "category":"Health Services",
            "subcategory":"Doctor",
            "type":"Services"
        }
    ],
    "sg:phone":"+1 616 949 5980",
    "sg:postcode":"49546",
    "sg:province":"MI",
    "sg:tags":[
        "dentist"
    ],
    "wof:name":"Bander Family Dentistry",
    "wof:placetype":"venue"
},
  "geometry": {"coordinates":[-85.570639,42.943427],"type":"Point"}
}