{
  "type": "Feature",
  "properties": {
    "iso:country":"US",
    "sg:address":"7412 Memorial St",
    "sg:city":"Detroit",
    "sg:classifiers":[
        {
            "category":"Professional",
            "subcategory":"Management & Consulting",
            "type":"Services"
        }
    ],
    "sg:phone":"+1 313 584 7363",
    "sg:postcode":"48228",
    "sg:province":"MI",
    "wof:name":"Sky Is Limit Marketing",
    "wof:placetype":"venue"
},
  "geometry": {"coordinates":[-83.210527,42.348124],"type":"Point"}
}