{
  "type": "Feature",
  "properties": {
    "iso:country":"US",
    "sg:address":"1356 Kirk Dr SE",
    "sg:city":"Grand Rapids",
    "sg:classifiers":[
        {
            "category":"Shopping",
            "type":"Retail Goods"
        }
    ],
    "sg:phone":"+1 616 942 7964",
    "sg:postcode":"49546",
    "sg:province":"MI",
    "sg:tags":[
        "cosmetic",
        "perfume"
    ],
    "wof:name":"Mary Kay Cosmetics",
    "wof:placetype":"venue"
},
  "geometry": {"coordinates":[-85.55422799999999,42.938557],"type":"Point"}
}