{
  "type": "Feature",
  "properties": {
    "iso:country":"US",
    "sg:address":"1227 Oakland St",
    "sg:city":"Traverse City",
    "sg:classifiers":[
        {
            "category":"Professional",
            "type":"Services"
        }
    ],
    "sg:phone":"+1 231 933 4375",
    "sg:postcode":"49686",
    "sg:province":"MI",
    "sg:tags":[
        "retail",
        "direct",
        "sales"
    ],
    "wof:name":"Scorpion Moon",
    "wof:placetype":"venue"
},
  "geometry": {"coordinates":[-85.59218,44.757571],"type":"Point"}
}