{
  "type": "Feature",
  "properties": {
    "iso:country":"US",
    "sg:address":"328 S Maple St",
    "sg:city":"Grant",
    "sg:classifiers":[
        {
            "category":"Restaurant",
            "type":"Food & Drink"
        }
    ],
    "sg:phone":"+1 231 834 5120",
    "sg:postcode":"49327",
    "sg:province":"MI",
    "sg:tags":[
        "shop",
        "coffee"
    ],
    "wof:name":"Wright Cup",
    "wof:placetype":"venue"
},
  "geometry": {"coordinates":[-85.810502,43.330812],"type":"Point"}
}