{
  "type": "Feature",
  "properties": {
    "iso:country":"US",
    "sg:address":"107 South Dr",
    "sg:city":"Stephenson",
    "sg:classifiers":[
        {
            "category":"Restaurant",
            "type":"Food & Drink"
        }
    ],
    "sg:phone":"+1 906 753 6464",
    "sg:postcode":"49887",
    "sg:province":"MI",
    "wof:name":"Farm House Restaurant",
    "wof:placetype":"venue"
},
  "geometry": {"coordinates":[-87.60851099999999,45.410407],"type":"Point"}
}