{
  "type": "Feature",
  "properties": {
    "iso:country":"US",
    "sg:address":"2260 E Grand River Ave",
    "sg:city":"Williamston",
    "sg:classifiers":[
        {
            "category":"Personal",
            "type":"Services"
        }
    ],
    "sg:phone":"+1 517 655 7063",
    "sg:postcode":"48895",
    "sg:province":"MI",
    "sg:tags":[
        "miscellaneous"
    ],
    "wof:name":"Perosnal Time Savers",
    "wof:placetype":"venue"
},
  "geometry": {"coordinates":[-84.266814,42.685886],"type":"Point"}
}