{
  "type": "Feature",
  "properties": {
    "iso:country":"US",
    "sg:address":"2155 Fisher Dr",
    "sg:city":"Sterling Heights",
    "sg:classifiers":[
        {
            "category":"Restaurant",
            "type":"Food & Drink"
        }
    ],
    "sg:phone":"+1 586 983 3928",
    "sg:postcode":"48310",
    "sg:province":"MI",
    "sg:tags":[
        "eating"
    ],
    "wof:name":"Druthers Inc",
    "wof:placetype":"venue"
},
  "geometry": {"coordinates":[-83.087171,42.578003],"type":"Point"}
}