{
  "type": "Feature",
  "properties": {
    "iso:country":"US",
    "sg:address":"2205 US Hwy 23",
    "sg:city":"Alpena",
    "sg:classifiers":[
        {
            "category":"Restaurant",
            "type":"Food & Drink"
        }
    ],
    "sg:phone":"+1 989 356 9031",
    "sg:postcode":"49707",
    "sg:province":"MI",
    "wof:name":"Little Caesars Pizza",
    "wof:placetype":"venue"
},
  "geometry": {"coordinates":[-83.45334699999999,45.044812],"type":"Point"}
}