{
  "type": "Feature",
  "properties": {
    "iso:country":"US",
    "sg:address":"7223 Westbrook Rd",
    "sg:city":"Fenwick",
    "sg:classifiers":[
        {
            "category":"Building & Trades",
            "subcategory":"Construction",
            "type":"Services"
        }
    ],
    "sg:phone":"+1 989 637 4710",
    "sg:postcode":"48834",
    "sg:province":"MI",
    "sg:website":"www.arboreast.com",
    "wof:name":"Arbor East Locating",
    "wof:placetype":"venue"
},
  "geometry": {"coordinates":[-84.97562600000001,43.093482],"type":"Point"}
}