{
  "type": "Feature",
  "properties": {
    "iso:country":"US",
    "sg:address":"2034 Lake Shore Dr",
    "sg:city":"Muskegon",
    "sg:classifiers":[
        {
            "category":"Retail",
            "subcategory":"Auto Repair",
            "type":"Services"
        }
    ],
    "sg:phone":"+1 231 759 3306",
    "sg:postcode":"49441",
    "sg:province":"MI",
    "sg:tags":[
        "repairing",
        "automobile"
    ],
    "wof:name":"Complete Automotive Svc",
    "wof:placetype":"venue"
},
  "geometry": {"coordinates":[-86.295191,43.214979],"type":"Point"}
}