{
  "type": "Feature",
  "properties": {
    "iso:country":"US",
    "sg:address":"5009 N Lapeer Rd",
    "sg:city":"Columbiaville",
    "sg:classifiers":[
        {
            "category":"Food & Beverages",
            "subcategory":"Groceries & Convenience Stores",
            "type":"Retail Goods"
        }
    ],
    "sg:phone":"+1 810 793 6174",
    "sg:postcode":"48421",
    "sg:province":"MI",
    "sg:tags":[
        "grocer"
    ],
    "wof:name":"Hilltop Grocery",
    "wof:placetype":"venue"
},
  "geometry": {"coordinates":[-83.31221600000001,43.175863],"type":"Point"}
}