{
  "type": "Feature",
  "properties": {
    "iso:country":"US",
    "sg:address":"7461 State Hwy 35",
    "sg:city":"Gladstone",
    "sg:classifiers":[
        {
            "category":"Autos & Motor Vehicles",
            "subcategory":"Automobile Sales",
            "type":"Retail Goods"
        }
    ],
    "sg:phone":"+1 906 786 8073",
    "sg:postcode":"49837",
    "sg:province":"MI",
    "sg:tags":[
        "used"
    ],
    "wof:name":"C J Motor Sales",
    "wof:placetype":"venue"
},
  "geometry": {"coordinates":[-87.05400299999999,45.820488],"type":"Point"}
}