{
  "type": "Feature",
  "properties": {
    "iso:country":"US",
    "sg:address":"1078 James St",
    "sg:city":"Vassar",
    "sg:classifiers":[
        {
            "category":"Building & Trades",
            "subcategory":"Construction",
            "type":"Services"
        }
    ],
    "sg:phone":"+1 989 823 9058",
    "sg:postcode":"48768",
    "sg:province":"MI",
    "sg:tags":[
        "contractor"
    ],
    "wof:name":"Amend Siding",
    "wof:placetype":"venue"
},
  "geometry": {"coordinates":[-83.600477,43.371144],"type":"Point"}
}