{
  "type": "Feature",
  "properties": {
    "iso:country":"US",
    "sg:address":"8607 N Telegraph Rd",
    "sg:city":"Dearborn Heights",
    "sg:classifiers":[
        {
            "category":"Retail",
            "subcategory":"Laundry & Dry Cleaning",
            "type":"Services"
        }
    ],
    "sg:phone":"+1 313 274 6171",
    "sg:postcode":"48127",
    "sg:province":"MI",
    "wof:name":"One Hour Martinizing of Dearborn Heights",
    "wof:placetype":"venue"
},
  "geometry": {"coordinates":[-83.27480300000001,42.3564],"type":"Point"}
}