{
  "type": "Feature",
  "properties": {
    "iso:country":"US",
    "sg:address":"3639 Acadia Dr",
    "sg:city":"Lake Orion",
    "sg:classifiers":[
        {
            "category":"Building & Trades",
            "subcategory":"Landscaping Services",
            "type":"Services"
        }
    ],
    "sg:phone":"+1 248 391 2750",
    "sg:postcode":"48360",
    "sg:province":"MI",
    "wof:name":"Advanced Tree Tech",
    "wof:placetype":"venue"
},
  "geometry": {"coordinates":[-83.32059099999999,42.740335],"type":"Point"}
}