{
  "type": "Feature",
  "properties": {
    "iso:country":"US",
    "sg:address":"4076 Baldwin Rd",
    "sg:city":"Auburn Hills",
    "sg:classifiers":[
        {
            "category":"Shopping",
            "subcategory":"Clothing, Apparel, & Fashions",
            "type":"Retail Goods"
        }
    ],
    "sg:phone":"+1 248 333 1811",
    "sg:postcode":"48326",
    "sg:province":"MI",
    "sg:tags":[
        "furnishing"
    ],
    "wof:name":"Brooks Brothers",
    "wof:placetype":"venue"
},
  "geometry": {"coordinates":[-83.30665399999999,42.699148],"type":"Point"}
}