{
  "type": "Feature",
  "properties": {
    "iso:country":"US",
    "sg:address":"6537 Thimbleweed Ln NE",
    "sg:city":"Rockford",
    "sg:classifiers":[
        {
            "category":"Building & Trades",
            "subcategory":"Landscaping Services",
            "type":"Services"
        }
    ],
    "sg:phone":"+1 616 866 8133",
    "sg:postcode":"49341",
    "sg:province":"MI",
    "wof:name":"Turf Works",
    "wof:placetype":"venue"
},
  "geometry": {"coordinates":[-85.56280099999999,43.082346],"type":"Point"}
}