{
  "type": "Feature",
  "properties": {
    "iso:country":"US",
    "sg:address":"106 Washington St",
    "sg:city":"Hart",
    "sg:classifiers":[
        {
            "category":"Retail",
            "subcategory":"Animal Services",
            "type":"Services"
        }
    ],
    "sg:phone":"+1 269 857 5880",
    "sg:postcode":"49420",
    "sg:province":"MI",
    "sg:tags":[
        "pet",
        "grooming",
        "washing"
    ],
    "wof:name":"Dogs By Design LLC",
    "wof:placetype":"venue"
},
  "geometry": {"coordinates":[-86.36495499999999,43.701848],"type":"Point"}
}