{
  "type": "Feature",
  "properties": {
    "iso:country":"US",
    "sg:address":"32013 W 12 Mile Rd",
    "sg:city":"Farmington Hills",
    "sg:classifiers":[
        {
            "category":"Professional",
            "subcategory":"Business Services",
            "type":"Services"
        }
    ],
    "sg:phone":"+1 248 553 9264",
    "sg:postcode":"48334",
    "sg:province":"MI",
    "sg:tags":[
        "translator",
        "interpreter"
    ],
    "wof:name":"Alpha Z Language Svc",
    "wof:placetype":"venue"
},
  "geometry": {"coordinates":[-83.364924,42.498969],"type":"Point"}
}