{
  "type": "Feature",
  "properties": {
    "iso:country":"US",
    "sg:address":"8481 State Rd",
    "sg:city":"Millington",
    "sg:classifiers":[
        {
            "category":"Autos & Motor Vehicles",
            "subcategory":"Automobile Sales",
            "type":"Retail Goods"
        }
    ],
    "sg:phone":"+1 989 871 4900",
    "sg:postcode":"48746",
    "sg:province":"MI",
    "sg:tags":[
        "car",
        "dealer"
    ],
    "wof:name":"Joseph Auto Sales",
    "wof:placetype":"venue"
},
  "geometry": {"coordinates":[-83.52972800000001,43.281533],"type":"Point"}
}