{
  "type": "Feature",
  "properties": {
    "iso:country":"US",
    "sg:address":"6932 Barrie St",
    "sg:city":"Dearborn",
    "sg:classifiers":[
        {
            "category":"Insurance",
            "subcategory":"Insurance Agent",
            "type":"Services"
        }
    ],
    "sg:phone":"+1 313 582 1483",
    "sg:postcode":"48126",
    "sg:province":"MI",
    "wof:name":"BJ Investagations",
    "wof:placetype":"venue"
},
  "geometry": {"coordinates":[-83.19285000000001,42.340732],"type":"Point"}
}