{
  "type": "Feature",
  "properties": {
    "iso:country":"US",
    "sg:address":"18427 Conant St",
    "sg:city":"Detroit",
    "sg:classifiers":[
        {
            "category":"Education",
            "subcategory":"Music School",
            "type":"Public Place"
        }
    ],
    "sg:phone":"+1 313 369 1186",
    "sg:postcode":"48234",
    "sg:province":"MI",
    "sg:tags":[
        "instrument",
        "teacher",
        "musical"
    ],
    "wof:name":"A A A Piano Service",
    "wof:placetype":"venue"
},
  "geometry": {"coordinates":[-83.07015199999999,42.42761],"type":"Point"}
}