{
  "type": "Feature",
  "properties": {
    "iso:country":"US",
    "sg:address":"10916 S Dixie Hwy",
    "sg:city":"Erie",
    "sg:classifiers":[
        {
            "category":"Restaurant",
            "type":"Food & Drink"
        }
    ],
    "sg:phone":"+1 734 848 3521",
    "sg:postcode":"48133",
    "sg:province":"MI",
    "wof:name":"Dixie Delights",
    "wof:placetype":"venue"
},
  "geometry": {"coordinates":[-83.485671,41.814082],"type":"Point"}
}