{
  "type": "Feature",
  "properties": {
    "iso:country":"US",
    "sg:address":"31011 John R Rd",
    "sg:city":"Madison Heights",
    "sg:classifiers":[
        {
            "category":"Shopping",
            "subcategory":"Clothing, Apparel, & Fashions",
            "type":"Retail Goods"
        }
    ],
    "sg:phone":"+1 248 585 1777",
    "sg:postcode":"48071",
    "sg:province":"MI",
    "sg:tags":[
        "item",
        "boutique"
    ],
    "wof:name":"Angelina's Psychic Boutique",
    "wof:placetype":"venue"
},
  "geometry": {"coordinates":[-83.106532,42.520471],"type":"Point"}
}