{
  "type": "Feature",
  "properties": {
    "iso:country":"US",
    "sg:address":"16706 Salerno Ct",
    "sg:city":"Macomb",
    "sg:classifiers":[
        {
            "category":"Communications",
            "subcategory":"Film & Video Production",
            "type":"Services"
        }
    ],
    "sg:phone":"+1 586 286 8181",
    "sg:postcode":"48044",
    "sg:province":"MI",
    "sg:tags":[
        "tape",
        "taping"
    ],
    "wof:name":"Lasting Image Video Services",
    "wof:placetype":"venue"
},
  "geometry": {"coordinates":[-82.954761,42.64822],"type":"Point"}
}