{
  "type": "Feature",
  "properties": {
    "iso:country":"US",
    "sg:address":"6443 S Cedar St",
    "sg:city":"Lansing",
    "sg:classifiers":[
        {
            "category":"Restaurant",
            "type":"Food & Drink"
        }
    ],
    "sg:menulink":"http://www.allmenus.com/mi/lansing/251297-asias-finest/menu/",
    "sg:phone":"+1 517 393 1688",
    "sg:postcode":"48911",
    "sg:province":"MI",
    "sg:tags":[
        "asian",
        "vietnamese"
    ],
    "wof:name":"Asia's Finest",
    "wof:placetype":"venue"
},
  "geometry": {"coordinates":[-84.540389,42.663928],"type":"Point"}
}