{
  "type": "Feature",
  "properties": {
    "iso:country":"US",
    "sg:address":"9000 Crouse Rd",
    "sg:city":"Howell",
    "sg:classifiers":[
        {
            "category":"Shopping",
            "subcategory":"Hobbies, Toys, & Games",
            "type":"Retail Goods"
        }
    ],
    "sg:phone":"+1 810 632 2053",
    "sg:postcode":"48855",
    "sg:province":"MI",
    "wof:name":"Airlooms",
    "wof:placetype":"venue"
},
  "geometry": {"coordinates":[-83.77745,42.655226],"type":"Point"}
}