{
  "type": "Feature",
  "properties": {
    "iso:country":"US",
    "sg:address":"3300 Eastern Ave SE",
    "sg:city":"Grand Rapids",
    "sg:classifiers":[
        {
            "category":"Shopping",
            "subcategory":"Computers & Home Electronics",
            "type":"Retail Goods"
        }
    ],
    "sg:phone":"+1 616 241 5897",
    "sg:postcode":"49508",
    "sg:province":"MI",
    "sg:tags":[
        "high",
        "fidelity",
        "stereophonic"
    ],
    "wof:name":"Mickey Shore's Electronics",
    "wof:placetype":"venue"
},
  "geometry": {"coordinates":[-85.646523,42.9019],"type":"Point"}
}