{
  "type": "Feature",
  "properties": {
    "iso:country":"US",
    "sg:address":"10825 Fenkell St",
    "sg:city":"Detroit",
    "sg:classifiers":[
        {
            "category":"Education",
            "subcategory":"School",
            "type":"Public Place"
        }
    ],
    "sg:phone":"+1 313 873 9460",
    "sg:postcode":"48238",
    "sg:province":"MI",
    "wof:name":"Detroit Public Schools",
    "wof:placetype":"venue"
},
  "geometry": {"coordinates":[-83.16832700000001,42.402122],"type":"Point"}
}