{
  "type": "Feature",
  "properties": {
    "iso:country":"US",
    "sg:address":"45175 W 10 Mile Rd",
    "sg:city":"Novi",
    "sg:classifiers":[
        {
            "category":"Government",
            "subcategory":"Police Station",
            "type":"Public Place"
        }
    ],
    "sg:phone":"+1 248 349 0923",
    "sg:postcode":"48375",
    "sg:province":"MI",
    "sg:tags":[
        "protection"
    ],
    "wof:name":"City of Novi Municipal Office",
    "wof:placetype":"venue"
},
  "geometry": {"coordinates":[-83.493724,42.465974],"type":"Point"}
}