{
  "type": "Feature",
  "properties": {
    "iso:country":"US",
    "sg:address":"61 1st St",
    "sg:city":"Laurium",
    "sg:classifiers":[
        {
            "category":"Manufacturing",
            "subcategory":"Tools & Machinery",
            "type":"Manufacturing & Wholesale Goods"
        }
    ],
    "sg:phone":"+1 906 337 0077",
    "sg:postcode":"49913",
    "sg:province":"MI",
    "sg:tags":[
        "machine",
        "shop"
    ],
    "wof:name":"Anttila Enterprises",
    "wof:placetype":"venue"
},
  "geometry": {"coordinates":[-88.441576,47.240722],"type":"Point"}
}