{
  "type": "Feature",
  "properties": {
    "iso:country":"US",
    "sg:address":"1595 E Melton Rd",
    "sg:city":"Birmingham",
    "sg:classifiers":[
        {
            "category":"Building & Trades",
            "subcategory":"Landscaping Services",
            "type":"Services"
        }
    ],
    "sg:phone":"+1 248 521 4003",
    "sg:postcode":"48009",
    "sg:province":"MI",
    "sg:tags":[
        "landscape"
    ],
    "wof:name":"American Landscape & Powerwash",
    "wof:placetype":"venue"
},
  "geometry": {"coordinates":[-83.193353,42.535857],"type":"Point"}
}