{
  "type": "Feature",
  "properties": {
    "iso:country":"US",
    "sg:address":"413 Linden Ave",
    "sg:city":"Jackson",
    "sg:classifiers":[
        {
            "category":"Organizations",
            "subcategory":"Religious Organization",
            "type":"Services"
        }
    ],
    "sg:phone":"+1 517 782 7270",
    "sg:postcode":"49203",
    "sg:province":"MI",
    "sg:tags":[
        "church"
    ],
    "wof:name":"Dominion Ministries Intl Chr",
    "wof:placetype":"venue"
},
  "geometry": {"coordinates":[-84.418162,42.225477],"type":"Point"}
}