{
  "type": "Feature",
  "properties": {
    "iso:country":"US",
    "sg:address":"1425 S Airport Rd W",
    "sg:city":"Traverse City",
    "sg:classifiers":[
        {
            "category":"Home & Garden",
            "subcategory":"Home Furnishings",
            "type":"Retail Goods"
        }
    ],
    "sg:phone":"+1 231 946 9751",
    "sg:postcode":"49686",
    "sg:province":"MI",
    "sg:tags":[
        "blanket"
    ],
    "wof:name":"C S Sewing",
    "wof:placetype":"venue"
},
  "geometry": {"coordinates":[-85.60497599999999,44.733436],"type":"Point"}
}