{
  "type": "Feature",
  "properties": {
    "iso:country":"US",
    "sg:address":"114 Philadelphia St",
    "sg:city":"Nashville",
    "sg:classifiers":[
        {
            "category":"Manufacturing",
            "subcategory":"Lumber",
            "type":"Manufacturing & Wholesale Goods"
        }
    ],
    "sg:phone":"+1 517 852 0145",
    "sg:postcode":"49073",
    "sg:province":"MI",
    "sg:tags":[
        "syrup",
        "maple",
        "sugar"
    ],
    "wof:name":"Nashville Maple Syrup Assn",
    "wof:placetype":"venue"
},
  "geometry": {"coordinates":[-85.093807,42.608777],"type":"Point"}
}