{
  "type": "Feature",
  "properties": {
    "iso:country":"US",
    "sg:address":"2809 W Bloomfield Oaks Dr",
    "sg:city":"West Bloomfield",
    "sg:classifiers":[
        {
            "category":"Social Services",
            "subcategory":"Adult Care",
            "type":"Services"
        }
    ],
    "sg:phone":"+1 248 360 1497",
    "sg:postcode":"48324",
    "sg:province":"MI",
    "sg:tags":[
        "home",
        "residential"
    ],
    "wof:name":"Angel's Place-Saddlewood",
    "wof:placetype":"venue"
},
  "geometry": {"coordinates":[-83.429081,42.592596],"type":"Point"}
}