{
  "type": "Feature",
  "properties": {
    "iso:country":"US",
    "sg:address":"1952 W Stadium Blvd",
    "sg:city":"Ann Arbor",
    "sg:classifiers":[
        {
            "category":"Restaurant",
            "type":"Food & Drink"
        },
        {
            "category":"Ice Cream",
            "type":"Food & Drink"
        }
    ],
    "sg:menulink":"http://www.allmenus.com/mi/ann-arbor/243258-baskin-robbins/menu/",
    "sg:phone":"+1 734 332 3349",
    "sg:postcode":"48103",
    "sg:province":"MI",
    "sg:tags":[
        "american",
        "ice",
        "cream"
    ],
    "wof:name":"Baskin-Robbins",
    "wof:placetype":"venue"
},
  "geometry": {"coordinates":[-83.772828,42.269396],"type":"Point"}
}