{
  "type": "Feature",
  "properties": {
    "iso:country":"US",
    "sg:address":"9017 Anchor Bay Dr",
    "sg:city":"Clay",
    "sg:classifiers":[
        {
            "category":"Wholesale",
            "subcategory":"Machinery & Supplies",
            "type":"Manufacturing & Wholesale Goods"
        }
    ],
    "sg:phone":"+1 810 794 8980",
    "sg:postcode":"48001",
    "sg:province":"MI",
    "sg:tags":[
        "equipment",
        "industrial"
    ],
    "wof:name":"H & G Ind Supply Inc",
    "wof:placetype":"venue"
},
  "geometry": {"coordinates":[-82.624392,42.650059],"type":"Point"}
}