{
  "type": "Feature",
  "properties": {
    "iso:country":"US",
    "sg:address":"30 E Columbia Ave",
    "sg:city":"Battle Creek",
    "sg:classifiers":[
        {
            "category":"Cinema",
            "subcategory":"Movie Rental",
            "type":"Entertainment"
        }
    ],
    "sg:phone":"+1 269 964 4800",
    "sg:postcode":"49015",
    "sg:province":"MI",
    "sg:tags":[
        "video",
        "tape"
    ],
    "wof:name":"Blockbuster",
    "wof:placetype":"venue"
},
  "geometry": {"coordinates":[-85.19745399999999,42.298484],"type":"Point"}
}