{
  "type": "Feature",
  "properties": {
    "iso:country":"US",
    "sg:address":"13640 Lakefield Rd",
    "sg:city":"Hemlock",
    "sg:classifiers":[
        {
            "category":"Building & Trades",
            "subcategory":"Construction",
            "type":"Services"
        }
    ],
    "sg:phone":"+1 989 865 9733",
    "sg:postcode":"48626",
    "sg:province":"MI",
    "sg:tags":[
        "water",
        "repair",
        "industrial",
        "well",
        "drilling"
    ],
    "wof:name":"M J Henry Well Co",
    "wof:placetype":"venue"
},
  "geometry": {"coordinates":[-84.18157600000001,43.349931],"type":"Point"}
}