{
  "type": "Feature",
  "properties": {
    "iso:country":"US",
    "sg:address":"22433 Meadow Woods Cir",
    "sg:city":"Taylor",
    "sg:classifiers":[
        {
            "category":"Professional",
            "subcategory":"Computer Services",
            "type":"Services"
        }
    ],
    "sg:phone":"+1 313 292 1122",
    "sg:postcode":"48180",
    "sg:province":"MI",
    "sg:tags":[
        "prepackaged",
        "software"
    ],
    "wof:name":"Global Internet",
    "wof:placetype":"venue"
},
  "geometry": {"coordinates":[-83.255669,42.234699],"type":"Point"}
}