{
  "type": "Feature",
  "properties": {
    "iso:country":"US",
    "sg:address":"2814 Cranbrook Rd",
    "sg:city":"Muskegon",
    "sg:classifiers":[
        {
            "category":"Education",
            "subcategory":"Special Training",
            "type":"Public Place"
        }
    ],
    "sg:phone":"+1 231 744 5823",
    "sg:postcode":"49445",
    "sg:province":"MI",
    "wof:name":"Mr BS Drivers Ed School",
    "wof:placetype":"venue"
},
  "geometry": {"coordinates":[-86.31576200000001,43.252767],"type":"Point"}
}