{
  "type": "Feature",
  "properties": {
    "iso:country":"US",
    "sg:address":"1327 Cobb Ave",
    "sg:city":"Kalamazoo",
    "sg:classifiers":[
        {
            "category":"Professional",
            "subcategory":"Business Services",
            "type":"Services"
        }
    ],
    "sg:phone":"+1 269 342 5328",
    "sg:postcode":"49007",
    "sg:province":"MI",
    "sg:tags":[
        "recording",
        "studio"
    ],
    "wof:name":"LA Val Recording & Production",
    "wof:placetype":"venue"
},
  "geometry": {"coordinates":[-85.594947,42.304547],"type":"Point"}
}