{
  "type": "Feature",
  "properties": {
    "iso:country":"US",
    "sg:address":"3842 Pine Grove Ave",
    "sg:city":"Fort Gratiot",
    "sg:classifiers":[
        {
            "category":"Home & Garden",
            "subcategory":"Carpets & Floor Coverings",
            "type":"Retail Goods"
        }
    ],
    "sg:phone":"+1 810 984 4196",
    "sg:postcode":"48059",
    "sg:province":"MI",
    "sg:tags":[
        "material"
    ],
    "wof:name":"Independent Floor Covering",
    "wof:placetype":"venue"
},
  "geometry": {"coordinates":[-82.463365,43.027144],"type":"Point"}
}