{
  "type": "Feature",
  "properties": {
    "iso:country":"US",
    "sg:address":"3186 Old Farm Ln",
    "sg:city":"Walled Lake",
    "sg:classifiers":[
        {
            "category":"Retail",
            "subcategory":"Repair Shop",
            "type":"Services"
        }
    ],
    "sg:phone":"+1 248 553 6811",
    "sg:postcode":"48390",
    "sg:province":"MI",
    "sg:tags":[
        "equipment",
        "scale"
    ],
    "wof:name":"Mettler-Toledo Inc",
    "wof:placetype":"venue"
},
  "geometry": {"coordinates":[-83.442846,42.567173],"type":"Point"}
}