{
  "type": "Feature",
  "properties": {
    "iso:country":"US",
    "sg:address":"213 S Grand Ave",
    "sg:city":"Fowlerville",
    "sg:classifiers":[
        {
            "category":"Government",
            "subcategory":"Office",
            "type":"Public Place"
        }
    ],
    "sg:phone":"+1 517 223 3771",
    "sg:postcode":"48836",
    "sg:province":"MI",
    "sg:tags":[
        "village"
    ],
    "wof:name":"Fowlerville Clerk's Ofc",
    "wof:placetype":"venue"
},
  "geometry": {"coordinates":[-84.073044,42.65937],"type":"Point"}
}