{
  "type": "Feature",
  "properties": {
    "iso:country":"US",
    "sg:address":"645 McCormick Dr",
    "sg:city":"Lapeer",
    "sg:classifiers":[
        {
            "category":"Manufacturing",
            "subcategory":"Printing",
            "type":"Manufacturing & Wholesale Goods"
        }
    ],
    "sg:phone":"+1 810 664 0643",
    "sg:postcode":"48446",
    "sg:province":"MI",
    "sg:tags":[
        "printer"
    ],
    "wof:name":"Blue Water Printing",
    "wof:placetype":"venue"
},
  "geometry": {"coordinates":[-83.31559900000001,43.043453],"type":"Point"}
}