{
  "type": "Feature",
  "properties": {
    "iso:country":"US",
    "sg:address":"1615 Monroe Ave NW",
    "sg:city":"Grand Rapids",
    "sg:classifiers":[
        {
            "category":"Professional",
            "type":"Services"
        }
    ],
    "sg:phone":"+1 616 222 0057",
    "sg:postcode":"49505",
    "sg:province":"MI",
    "sg:tags":[
        "arts",
        "artist"
    ],
    "sg:website":"www.carolroedastudio.com",
    "wof:name":"Carol Roeda Studio Inc",
    "wof:placetype":"venue"
},
  "geometry": {"coordinates":[-85.67061699999999,42.992401],"type":"Point"}
}