{
  "type": "Feature",
  "properties": {
    "iso:country":"US",
    "sg:address":"101 E Scott St",
    "sg:city":"Grand Ledge",
    "sg:classifiers":[
        {
            "category":"Building & Trades",
            "subcategory":"Construction",
            "type":"Services"
        }
    ],
    "sg:phone":"+1 517 622 1565",
    "sg:postcode":"48837",
    "sg:province":"MI",
    "sg:tags":[
        "contractor"
    ],
    "wof:name":"Grout Pro's",
    "wof:placetype":"venue"
},
  "geometry": {"coordinates":[-84.74643399999999,42.751709],"type":"Point"}
}