{
  "type": "Feature",
  "properties": {
    "iso:country":"US",
    "sg:address":"720 E B St",
    "sg:city":"Iron Mountain",
    "sg:classifiers":[
        {
            "category":"Social Services",
            "subcategory":"Adult Care",
            "type":"Services"
        }
    ],
    "sg:phone":"+1 906 774 6126",
    "sg:postcode":"49801",
    "sg:province":"MI",
    "sg:tags":[
        "residential"
    ],
    "wof:name":"Integrity House",
    "wof:placetype":"venue"
},
  "geometry": {"coordinates":[-88.057104,45.817469],"type":"Point"}
}