{
  "type": "Feature",
  "properties": {
    "iso:country":"US",
    "sg:address":"18201 Clinton River Rd",
    "sg:city":"Clinton Township",
    "sg:classifiers":[
        {
            "category":"Retail",
            "subcategory":"Funeral Services",
            "type":"Services"
        }
    ],
    "sg:phone":"+1 586 286 9020",
    "sg:postcode":"48038",
    "sg:province":"MI",
    "sg:tags":[
        "cemetery"
    ],
    "wof:name":"Resurrection Cemetery",
    "wof:placetype":"venue"
},
  "geometry": {"coordinates":[-82.9328,42.5872],"type":"Point"}
}