{
  "type": "Feature",
  "properties": {
    "iso:country":"US",
    "sg:address":"12316 Fort St",
    "sg:city":"Southgate",
    "sg:classifiers":[
        {
            "category":"Shopping",
            "subcategory":"Jewelry",
            "type":"Retail Goods"
        }
    ],
    "sg:phone":"+1 734 284 3060",
    "sg:postcode":"48195",
    "sg:province":"MI",
    "wof:name":"Brothers Video Club",
    "wof:placetype":"venue"
},
  "geometry": {"coordinates":[-83.18139600000001,42.2183],"type":"Point"}
}