{
  "type": "Feature",
  "properties": {
    "iso:country":"US",
    "sg:address":"8449 Grayfield St",
    "sg:city":"Dearborn Heights",
    "sg:classifiers":[
        {
            "category":"Manufacturing",
            "subcategory":"Wood Products",
            "type":"Manufacturing & Wholesale Goods"
        }
    ],
    "sg:phone":"+1 313 565 4405",
    "sg:postcode":"48127",
    "sg:province":"MI",
    "sg:tags":[
        "mfg"
    ],
    "wof:name":"Holiday Crafts",
    "wof:placetype":"venue"
},
  "geometry": {"coordinates":[-83.26702899999999,42.354768],"type":"Point"}
}