{
  "type": "Feature",
  "properties": {
    "iso:country":"US",
    "sg:address":"131 Dulles Dr",
    "sg:city":"Battle Creek",
    "sg:classifiers":[
        {
            "category":"Professional",
            "subcategory":"Business Services",
            "type":"Services"
        }
    ],
    "sg:phone":"+1 269 964 3371",
    "sg:postcode":"49014",
    "sg:province":"MI",
    "sg:tags":[
        "notary",
        "public"
    ],
    "wof:name":"James Roy Deveney",
    "wof:placetype":"venue"
},
  "geometry": {"coordinates":[-85.11780899999999,42.308239],"type":"Point"}
}