{
  "type": "Feature",
  "properties": {
    "iso:country":"US",
    "sg:address":"210 S Almont Ave",
    "sg:city":"Imlay City",
    "sg:classifiers":[
        {
            "category":"Professional",
            "subcategory":"Lawyer & Legal Services",
            "type":"Services"
        }
    ],
    "sg:phone":"+1 810 724 4259",
    "sg:postcode":"48444",
    "sg:province":"MI",
    "sg:tags":[
        "attorney"
    ],
    "wof:name":"Gary L Davis Law Office",
    "wof:placetype":"venue"
},
  "geometry": {"coordinates":[-83.077359,43.022969],"type":"Point"}
}