{
  "type": "Feature",
  "properties": {
    "iso:country":"US",
    "sg:address":"2361 Lancashire Dr",
    "sg:city":"Ann Arbor",
    "sg:classifiers":[
        {
            "category":"Organizations",
            "subcategory":"Membership Organization",
            "type":"Services"
        }
    ],
    "sg:phone":"+1 734 913 8660",
    "sg:postcode":"48105",
    "sg:province":"MI",
    "wof:name":"Blackrose Society",
    "wof:placetype":"venue"
},
  "geometry": {"coordinates":[-83.71380499999999,42.310017],"type":"Point"}
}