{
  "type": "Feature",
  "properties": {
    "iso:country":"US",
    "sg:address":"12044 Oakland Dr",
    "sg:city":"Schoolcraft",
    "sg:classifiers":[
        {
            "category":"Autos & Motor Vehicles",
            "subcategory":"Auto Supplies",
            "type":"Retail Goods"
        }
    ],
    "sg:phone":"+1 269 679 5098",
    "sg:postcode":"49087",
    "sg:province":"MI",
    "wof:name":"Donald Ulsh",
    "wof:placetype":"venue"
},
  "geometry": {"coordinates":[-85.613336,42.142612],"type":"Point"}
}