{
  "type": "Feature",
  "properties": {
    "iso:country":"US",
    "sg:address":"1625 Walker Ave NW",
    "sg:city":"Grand Rapids",
    "sg:classifiers":[
        {
            "category":"Government",
            "subcategory":"Post Office",
            "type":"Public Place"
        }
    ],
    "sg:phone":"+1 616 791 4005",
    "sg:postcode":"49504",
    "sg:province":"MI",
    "sg:website":"www.usps.com",
    "wof:name":"US Post Office",
    "wof:placetype":"venue"
},
  "geometry": {"coordinates":[-85.709057,42.987262],"type":"Point"}
}