{
  "type": "Feature",
  "properties": {
    "iso:country":"US",
    "sg:address":"907 S 11th St",
    "sg:city":"Niles",
    "sg:classifiers":[
        {
            "category":"Shopping",
            "subcategory":"Pharmacy",
            "type":"Retail Goods"
        }
    ],
    "sg:phone":"+1 269 683 3330",
    "sg:postcode":"49120",
    "sg:province":"MI",
    "sg:website":"www.walgreens.com",
    "wof:name":"Walgreens",
    "wof:placetype":"venue"
},
  "geometry": {"coordinates":[-86.247128,41.818609],"type":"Point"}
}