{
  "type": "Feature",
  "properties": {
    "iso:country":"US",
    "sg:address":"7792 Dutch Rd",
    "sg:city":"Saginaw",
    "sg:classifiers":[
        {
            "category":"Professional",
            "subcategory":"Business Services",
            "type":"Services"
        }
    ],
    "sg:phone":"+1 989 781 0946",
    "sg:postcode":"48609",
    "sg:province":"MI",
    "wof:name":"Whitetails Unlimited Inc",
    "wof:placetype":"venue"
},
  "geometry": {"coordinates":[-84.06453,43.401533],"type":"Point"}
}