{
  "type": "Feature",
  "properties": {
    "iso:country":"US",
    "sg:address":"590 Briarwood Dr",
    "sg:city":"Adrian",
    "sg:classifiers":[
        {
            "category":"Shopping",
            "subcategory":"Florist",
            "type":"Retail Goods"
        }
    ],
    "sg:phone":"+1 517 265 5211",
    "sg:postcode":"49221",
    "sg:province":"MI",
    "wof:name":"Rose Petal",
    "wof:placetype":"venue"
},
  "geometry": {"coordinates":[-84.07115899999999,41.889469],"type":"Point"}
}