{
  "type": "Feature",
  "properties": {
    "iso:country":"US",
    "sg:address":"4102 Doran St",
    "sg:city":"Flint",
    "sg:classifiers":[
        {
            "category":"Health Services",
            "subcategory":"Nursing And Care Facility",
            "type":"Services"
        }
    ],
    "sg:phone":"+1 810 789 2480",
    "sg:postcode":"48504",
    "sg:province":"MI",
    "wof:name":"Alternative Elderly Care",
    "wof:placetype":"venue"
},
  "geometry": {"coordinates":[-83.740864,43.063636],"type":"Point"}
}