{
  "type": "Feature",
  "properties": {
    "iso:country":"US",
    "sg:address":"2155 Wixom Trl",
    "sg:city":"Milford",
    "sg:classifiers":[
        {
            "category":"Shopping",
            "subcategory":"Hobbies, Toys, & Games",
            "type":"Retail Goods"
        }
    ],
    "sg:phone":"+1 248 684 2036",
    "sg:postcode":"48381",
    "sg:province":"MI",
    "wof:name":"Kreative Krafts",
    "wof:placetype":"venue"
},
  "geometry": {"coordinates":[-83.577905,42.582979],"type":"Point"}
}