{
  "type": "Feature",
  "properties": {
    "iso:country":"US",
    "sg:address":"301 Dorothy Dr",
    "sg:city":"Lake Orion",
    "sg:classifiers":[
        {
            "category":"Retail",
            "subcategory":"Auto Repair",
            "type":"Services"
        }
    ],
    "sg:phone":"+1 248 814 0568",
    "sg:postcode":"48362",
    "sg:province":"MI",
    "sg:tags":[
        "automotive",
        "maintenance"
    ],
    "wof:name":"Clear Line Controls LLC",
    "wof:placetype":"venue"
},
  "geometry": {"coordinates":[-83.31617300000001,42.78946],"type":"Point"}
}