{
  "type": "Feature",
  "properties": {
    "iso:country":"US",
    "sg:address":"8098 Duquette Rd",
    "sg:city":"Melvin",
    "sg:classifiers":[
        {
            "category":"Building & Trades",
            "subcategory":"Construction",
            "type":"Services"
        }
    ],
    "sg:phone":"+1 810 387 2677",
    "sg:postcode":"48454",
    "sg:province":"MI",
    "sg:tags":[
        "general",
        "contractor"
    ],
    "wof:name":"H W Hill General Contracting",
    "wof:placetype":"venue"
},
  "geometry": {"coordinates":[-82.782661,43.185827],"type":"Point"}
}