{
  "type": "Feature",
  "properties": {
    "iso:country":"US",
    "sg:address":"205 Industrial Dr",
    "sg:city":"Cromwell",
    "sg:classifiers":[
        {
            "category":"Organizations",
            "subcategory":"Non-profit Organization",
            "type":"Services"
        }
    ],
    "sg:phone":"+1 260 856 4400",
    "sg:postcode":"46703",
    "sg:province":"MI",
    "sg:tags":[
        "fund",
        "counselor",
        "raising"
    ],
    "wof:name":"Custom Services/Adpak",
    "wof:placetype":"venue"
},
  "geometry": {"coordinates":[-85.00111800000001,41.648206],"type":"Point"}
}