{
  "type": "Feature",
  "properties": {
    "iso:country":"US",
    "sg:address":"6590 E Plamondon Ct",
    "sg:city":"Lake Leelanau",
    "sg:phone":"+1 231 256 9261",
    "sg:postcode":"49653",
    "sg:province":"MI",
    "sg:tags":[
        "oil"
    ],
    "wof:name":"Leelanau Petroleum Co",
    "wof:placetype":"venue"
},
  "geometry": {"coordinates":[-85.72349699999999,44.985941],"type":"Point"}
}