{
  "type": "Feature",
  "properties": {
    "iso:country":"US",
    "sg:address":"80 Manchester Pkwy",
    "sg:city":"Highland Park",
    "sg:classifiers":[
        {
            "category":"Social Services",
            "subcategory":"Child Care",
            "type":"Services"
        }
    ],
    "sg:phone":"+1 313 865 1315",
    "sg:postcode":"48203",
    "sg:province":"MI",
    "sg:tags":[
        "day"
    ],
    "wof:name":"Lorac Child Development Cente R",
    "wof:placetype":"venue"
},
  "geometry": {"coordinates":[-83.10077099999999,42.405843],"type":"Point"}
}