{
  "type": "Feature",
  "properties": {
    "iso:country":"US",
    "sg:address":"2501 26th St",
    "sg:city":"Augusta",
    "sg:classifiers":[
        {
            "category":"Professional",
            "type":"Services"
        }
    ],
    "sg:phone":"+1 269 731 2330",
    "sg:postcode":"49012",
    "sg:province":"MI",
    "sg:tags":[
        "establishment"
    ],
    "wof:name":"CECOM",
    "wof:placetype":"venue"
},
  "geometry": {"coordinates":[-85.30086799999999,42.33615],"type":"Point"}
}