{
  "type": "Feature",
  "properties": {
    "iso:country":"US",
    "sg:address":"42386 Executive Dr",
    "sg:city":"Harrison Twp",
    "sg:classifiers":[
        {
            "category":"Manufacturing",
            "subcategory":"Metals",
            "type":"Manufacturing & Wholesale Goods"
        }
    ],
    "sg:phone":"+1 586 469 3071",
    "sg:postcode":"48045",
    "sg:province":"MI",
    "sg:tags":[
        "treating",
        "heat"
    ],
    "wof:name":"Temp-Rite Steel Treating",
    "wof:placetype":"venue"
},
  "geometry": {"coordinates":[-82.854738,42.596279],"type":"Point"}
}