{
  "type": "Feature",
  "properties": {
    "iso:country":"US",
    "sg:address":"9925 E Beaverton Rd",
    "sg:city":"Clare",
    "sg:classifiers":[
        {
            "category":"Farming",
            "subcategory":"Livestock Farm",
            "type":"Manufacturing & Wholesale Goods"
        }
    ],
    "sg:phone":"+1 989 386 9187",
    "sg:postcode":"48617",
    "sg:province":"MI",
    "sg:tags":[
        "beef",
        "feedlot",
        "cattle"
    ],
    "wof:name":"Thomas K Knoll Farm",
    "wof:placetype":"venue"
},
  "geometry": {"coordinates":[-84.648093,43.873148],"type":"Point"}
}