{
  "type": "Feature",
  "properties": {
    "iso:country":"US",
    "sg:address":"28282 Dequindre Rd",
    "sg:city":"Warren",
    "sg:classifiers":[
        {
            "category":"Restaurant",
            "type":"Food & Drink"
        }
    ],
    "sg:menulink":"http://www.allmenus.com/mi/warren/45889-bamboo-gardens-restaurant/menu/",
    "sg:phone":"+1 586 582 0444",
    "sg:postcode":"48092",
    "sg:province":"MI",
    "sg:tags":[
        "asian",
        "vietnamese"
    ],
    "wof:name":"Bamboo Gardens Restaurant",
    "wof:placetype":"venue"
},
  "geometry": {"coordinates":[-83.085449,42.501017],"type":"Point"}
}