{
  "type": "Feature",
  "properties": {
    "iso:country":"US",
    "sg:address":"1775 Monroe Beach",
    "sg:city":"Battle Creek",
    "sg:classifiers":[
        {
            "category":"Social Services",
            "subcategory":"Child Care",
            "type":"Services"
        }
    ],
    "sg:phone":"+1 269 968 1315",
    "sg:postcode":"49014",
    "sg:province":"MI",
    "sg:tags":[
        "day"
    ],
    "wof:name":"Beadle Lake Afc Home",
    "wof:placetype":"venue"
},
  "geometry": {"coordinates":[-85.14494500000001,42.271423],"type":"Point"}
}