{
  "type": "Feature",
  "properties": {
    "iso:country":"US",
    "sg:address":"18201 Canal Rd",
    "sg:city":"Clinton Township",
    "sg:classifiers":[
        {
            "category":"Building & Trades",
            "subcategory":"Locksmith",
            "type":"Services"
        }
    ],
    "sg:phone":"+1 586 913 8318",
    "sg:postcode":"48038",
    "sg:province":"MI",
    "sg:tags":[
        "key"
    ],
    "wof:name":"Abbe Locks 24 Locksmith",
    "wof:placetype":"venue"
},
  "geometry": {"coordinates":[-82.937414,42.601635],"type":"Point"}
}