{
  "type": "Feature",
  "properties": {
    "iso:country":"US",
    "sg:address":"730 Plymouth Ave NE",
    "sg:city":"Grand Rapids",
    "sg:classifiers":[
        {
            "category":"Manufacturing",
            "subcategory":"Tools & Machinery",
            "type":"Manufacturing & Wholesale Goods"
        }
    ],
    "sg:phone":"+1 616 459 9531",
    "sg:postcode":"49505",
    "sg:province":"MI",
    "sg:tags":[
        "devices"
    ],
    "sg:website":"www.burkeporter.net",
    "wof:name":"Burke E Porter Machinery Co",
    "wof:placetype":"venue"
},
  "geometry": {"coordinates":[-85.62508099999999,42.974741],"type":"Point"}
}