{
  "type": "Feature",
  "properties": {
    "iso:country":"US",
    "sg:address":"5625 Venture Way",
    "sg:city":"Mt Pleasant",
    "sg:classifiers":[
        {
            "category":"Manufacturing",
            "subcategory":"Tools & Machinery",
            "type":"Manufacturing & Wholesale Goods"
        }
    ],
    "sg:phone":"+1 989 772 4073",
    "sg:postcode":"48858",
    "sg:province":"MI",
    "sg:tags":[
        "adhesive",
        "gluing",
        "equipment"
    ],
    "wof:name":"Michael Engineering LTD",
    "wof:placetype":"venue"
},
  "geometry": {"coordinates":[-84.731252,43.606866],"type":"Point"}
}