{
  "type": "Feature",
  "properties": {
    "iso:country":"US",
    "sg:address":"79 State Rd",
    "sg:city":"Newaygo",
    "sg:classifiers":[
        {
            "category":"Real Estate",
            "subcategory":"Real Estate Agent",
            "type":"Services"
        }
    ],
    "sg:phone":"+1 231 652 1550",
    "sg:postcode":"49337",
    "sg:province":"MI",
    "wof:name":"Exit Realty Stout Group",
    "wof:placetype":"venue"
},
  "geometry": {"coordinates":[-85.801276,43.418991],"type":"Point"}
}