{
  "type": "Feature",
  "properties": {
    "iso:country":"US",
    "sg:address":"707 N Van Dyke Rd",
    "sg:city":"Bad Axe",
    "sg:classifiers":[
        {
            "category":"Home & Garden",
            "subcategory":"Building Materials",
            "type":"Retail Goods"
        }
    ],
    "sg:phone":"+1 989 269 9261",
    "sg:postcode":"48413",
    "sg:province":"MI",
    "wof:name":"Mortimer & Son Lumber Co Inc",
    "wof:placetype":"venue"
},
  "geometry": {"coordinates":[-83.001035,43.818464],"type":"Point"}
}