{
  "type": "Feature",
  "properties": {
    "iso:country":"US",
    "sg:address":"3876 Berry Manor",
    "sg:city":"Howell",
    "sg:classifiers":[
        {
            "category":"Professional",
            "subcategory":"Accounting & Tax Preparation",
            "type":"Services"
        }
    ],
    "sg:phone":"+1 517 546 6527",
    "sg:postcode":"48843",
    "sg:province":"MI",
    "wof:name":"Comprehensive Enterprise Inc",
    "wof:placetype":"venue"
},
  "geometry": {"coordinates":[-83.99259000000001,42.596623],"type":"Point"}
}