{
  "type": "Feature",
  "properties": {
    "iso:country":"US",
    "sg:address":"50850 Cable Park Rd",
    "sg:city":"Dowagiac",
    "sg:classifiers":[
        {
            "category":"Real Estate",
            "subcategory":"Developer",
            "type":"Services"
        }
    ],
    "sg:phone":"+1 269 208 9635",
    "sg:postcode":"49047",
    "sg:province":"MI",
    "wof:name":"Klett Development LLC",
    "wof:placetype":"venue"
},
  "geometry": {"coordinates":[-86.19690300000001,42.058977],"type":"Point"}
}