{
  "type": "Feature",
  "properties": {
    "iso:country":"US",
    "sg:address":"1824 E Michigan Ave",
    "sg:city":"Lansing",
    "sg:classifiers":[
        {
            "category":"Professional",
            "subcategory":"Computer Services",
            "type":"Services"
        }
    ],
    "sg:phone":"+1 517 364 0500",
    "sg:postcode":"48912",
    "sg:province":"MI",
    "sg:tags":[
        "hardware",
        "provider",
        "internet",
        "software"
    ],
    "wof:name":"Webspun Designz & Solutions",
    "wof:placetype":"venue"
},
  "geometry": {"coordinates":[-84.524061,42.733567],"type":"Point"}
}