{
  "type": "Feature",
  "properties": {
    "iso:country":"US",
    "sg:address":"4025 W Saginaw Hwy",
    "sg:city":"Lansing",
    "sg:classifiers":[
        {
            "category":"Shopping",
            "subcategory":"Clothing, Apparel, & Fashions",
            "type":"Retail Goods"
        }
    ],
    "sg:phone":"+1 517 321 7731",
    "sg:postcode":"48917",
    "sg:province":"MI",
    "sg:tags":[
        "shop",
        "bridal"
    ],
    "wof:name":"Pierre's Bridal & Floral",
    "wof:placetype":"venue"
},
  "geometry": {"coordinates":[-84.604209,42.741043],"type":"Point"}
}