{
  "type": "Feature",
  "properties": {
    "iso:country":"US",
    "sg:address":"65461 32nd St",
    "sg:city":"Lawton",
    "sg:classifiers":[
        {
            "category":"Building & Trades",
            "subcategory":"Construction",
            "type":"Services"
        }
    ],
    "sg:phone":"+1 269 624 6915",
    "sg:postcode":"49065",
    "sg:province":"MI",
    "sg:tags":[
        "paving",
        "contractor"
    ],
    "wof:name":"Foster Paving Inc",
    "wof:placetype":"venue"
},
  "geometry": {"coordinates":[-85.86183699999999,42.180914],"type":"Point"}
}