{
  "type": "Feature",
  "properties": {
    "iso:country":"US",
    "sg:address":"48 E High St",
    "sg:city":"Metamora",
    "sg:classifiers":[
        {
            "category":"Government",
            "subcategory":"Office",
            "type":"Public Place"
        }
    ],
    "sg:phone":"+1 810 678 2932",
    "sg:postcode":"48455",
    "sg:province":"MI",
    "sg:tags":[
        "village"
    ],
    "wof:name":"Metamora Village Clerk",
    "wof:placetype":"venue"
},
  "geometry": {"coordinates":[-83.288624,42.941516],"type":"Point"}
}