{
  "type": "Feature",
  "properties": {
    "iso:country":"US",
    "sg:address":"15620 Mountainside Dr",
    "sg:city":"Macomb",
    "sg:classifiers":[
        {
            "category":"Building & Trades",
            "subcategory":"Construction",
            "type":"Services"
        }
    ],
    "sg:phone":"+1 586 786 1193",
    "sg:postcode":"48042",
    "sg:province":"MI",
    "sg:tags":[
        "house",
        "contractor"
    ],
    "wof:name":"Galleria Bldrs LLC",
    "wof:placetype":"venue"
},
  "geometry": {"coordinates":[-82.969122,42.679034],"type":"Point"}
}