{
  "type": "Feature",
  "properties": {
    "iso:country":"US",
    "sg:address":"4041 Grange Hall Rd",
    "sg:city":"Holly",
    "sg:classifiers":[
        {
            "category":"Freight",
            "type":"Transportation"
        }
    ],
    "sg:phone":"+1 248 634 1084",
    "sg:postcode":"48442",
    "sg:province":"MI",
    "sg:tags":[
        "operator",
        "trucking"
    ],
    "wof:name":"Marshall Trkg",
    "wof:placetype":"venue"
},
  "geometry": {"coordinates":[-83.616691,42.809558],"type":"Point"}
}