{
  "type": "Feature",
  "properties": {
    "iso:country":"US",
    "sg:address":"5621 Zellar Rd",
    "sg:city":"Whitehall",
    "sg:classifiers":[
        {
            "category":"Building & Trades",
            "subcategory":"Construction",
            "type":"Services"
        }
    ],
    "sg:phone":"+1 231 893 2522",
    "sg:postcode":"49461",
    "sg:province":"MI",
    "sg:tags":[
        "masonry",
        "contractor"
    ],
    "wof:name":"Wabsis Masonry Inc",
    "wof:placetype":"venue"
},
  "geometry": {"coordinates":[-86.34626400000001,43.35991],"type":"Point"}
}