{
  "type": "Feature",
  "properties": {
    "iso:country":"US",
    "sg:address":"6721 Church Rd",
    "sg:city":"Central Lake",
    "sg:classifiers":[
        {
            "category":"Building & Trades",
            "subcategory":"Plumbing",
            "type":"Services"
        }
    ],
    "sg:phone":"+1 231 599 2156",
    "sg:postcode":"49622",
    "sg:province":"MI",
    "sg:tags":[
        "plumbing",
        "contractor"
    ],
    "wof:name":"Drenth Plumbing & Heating",
    "wof:placetype":"venue"
},
  "geometry": {"coordinates":[-85.31542399999999,45.127446],"type":"Point"}
}