{
  "type": "Feature",
  "properties": {
    "iso:country":"US",
    "sg:address":"2291 Van Dr",
    "sg:city":"National City",
    "sg:classifiers":[
        {
            "category":"Shopping",
            "subcategory":"Bicycles & Sporting Goods",
            "type":"Retail Goods"
        }
    ],
    "sg:phone":"+1 989 362 0081",
    "sg:postcode":"48748",
    "sg:province":"MI",
    "wof:name":"Firearm Stephens Sales",
    "wof:placetype":"venue"
},
  "geometry": {"coordinates":[-83.638656,44.347683],"type":"Point"}
}