{
  "type": "Feature",
  "properties": {
    "iso:country":"US",
    "sg:address":"1409 Mill Creek Dr",
    "sg:city":"Waterford",
    "sg:classifiers":[
        {
            "category":"Professional",
            "subcategory":"Accounting & Tax Preparation",
            "type":"Services"
        }
    ],
    "sg:phone":"+1 248 738 0976",
    "sg:postcode":"48327",
    "sg:province":"MI",
    "sg:tags":[
        "payroll"
    ],
    "wof:name":"Clipper Payroll",
    "wof:placetype":"venue"
},
  "geometry": {"coordinates":[-83.394542,42.618995],"type":"Point"}
}