{
  "type": "Feature",
  "properties": {
    "iso:country":"US",
    "sg:address":"26540 Berg Rd",
    "sg:city":"Southfield",
    "sg:classifiers":[
        {
            "category":"Professional",
            "subcategory":"Business Services",
            "type":"Services"
        }
    ],
    "sg:phone":"+1 248 213 4614",
    "sg:postcode":"48033",
    "sg:province":"MI",
    "sg:tags":[
        "embroidery"
    ],
    "wof:name":"Threads 4 Life",
    "wof:placetype":"venue"
},
  "geometry": {"coordinates":[-83.279529,42.483153],"type":"Point"}
}