{
  "type": "Feature",
  "properties": {
    "iso:country":"US",
    "sg:address":"4445 Elderberry Dr",
    "sg:city":"Brighton",
    "sg:classifiers":[
        {
            "category":"Professional",
            "subcategory":"Management & Consulting",
            "type":"Services"
        }
    ],
    "sg:phone":"+1 810 229 6027",
    "sg:postcode":"48114",
    "sg:province":"MI",
    "wof:name":"E T Fox Company",
    "wof:placetype":"venue"
},
  "geometry": {"coordinates":[-83.71807800000001,42.540326],"type":"Point"}
}