{
  "type": "Feature",
  "properties": {
    "iso:country":"US",
    "sg:address":"3200 W Pickard Rd",
    "sg:city":"Mount Pleasant",
    "sg:classifiers":[
        {
            "category":"Building & Trades",
            "subcategory":"Construction",
            "type":"Services"
        }
    ],
    "sg:phone":"+1 989 772 0702",
    "sg:postcode":"48858",
    "sg:province":"MI",
    "sg:tags":[
        "house"
    ],
    "wof:name":"Twin Oaks Construction Inc",
    "wof:placetype":"venue"
},
  "geometry": {"coordinates":[-84.910591,43.612214],"type":"Point"}
}