{
  "type": "Feature",
  "properties": {
    "iso:country":"US",
    "sg:address":"1002 N 7th Ave",
    "sg:city":"Iron River",
    "sg:classifiers":[
        {
            "category":"Freight",
            "type":"Transportation"
        }
    ],
    "sg:phone":"+1 906 265 0391",
    "sg:postcode":"49935",
    "sg:province":"MI",
    "sg:tags":[
        "operator",
        "local",
        "trucking"
    ],
    "wof:name":"Splitt Trucking Service",
    "wof:placetype":"venue"
},
  "geometry": {"coordinates":[-88.645985,46.098111],"type":"Point"}
}