{
  "type": "Feature",
  "properties": {
    "iso:country":"US",
    "sg:address":"8701 Kingswood St",
    "sg:city":"Detroit",
    "sg:classifiers":[
        {
            "category":"Restaurant",
            "type":"Food & Drink"
        }
    ],
    "sg:phone":"+1 313 861 3539",
    "sg:postcode":"48221",
    "sg:province":"MI",
    "sg:tags":[
        "eating"
    ],
    "wof:name":"Its All Good Catering",
    "wof:placetype":"venue"
},
  "geometry": {"coordinates":[-83.160179,42.436046],"type":"Point"}
}