{
  "type": "Feature",
  "properties": {
    "iso:country":"US",
    "sg:address":"329 Columbia St",
    "sg:city":"Algonac",
    "sg:classifiers":[
        {
            "category":"Health Services",
            "subcategory":"Doctor",
            "type":"Services"
        }
    ],
    "sg:phone":"+1 810 794 4917",
    "sg:postcode":"48001",
    "sg:province":"MI",
    "sg:tags":[
        "physician",
        "surgeon"
    ],
    "wof:name":"William Wadland MD",
    "wof:placetype":"venue"
},
  "geometry": {"coordinates":[-82.53364000000001,42.616317],"type":"Point"}
}