{
  "type": "Feature",
  "properties": {
    "iso:country":"US",
    "sg:address":"28001 7 Mile Rd",
    "sg:city":"Livonia",
    "sg:classifiers":[
        {
            "category":"Bars & Pubs",
            "subcategory":"Nightclub",
            "type":"Food & Drink"
        }
    ],
    "sg:phone":"+1 248 777 0511",
    "sg:postcode":"48152",
    "sg:province":"MI",
    "sg:tags":[
        "nightlife"
    ],
    "wof:name":"Sands Lounge",
    "wof:placetype":"venue"
},
  "geometry": {"coordinates":[-83.322998,42.427299],"type":"Point"}
}