{
  "type": "Feature",
  "properties": {
    "iso:country":"US",
    "sg:address":"4452 Bonnie Ave SE",
    "sg:city":"Grand Rapids",
    "sg:classifiers":[
        {
            "category":"Retail",
            "subcategory":"Laundry & Dry Cleaning",
            "type":"Services"
        }
    ],
    "sg:phone":"+1 616 301 1840",
    "sg:postcode":"49508",
    "sg:province":"MI",
    "sg:tags":[
        "cleaners",
        "rug",
        "carpet"
    ],
    "wof:name":"Integrity Restoration",
    "wof:placetype":"venue"
},
  "geometry": {"coordinates":[-85.636179,42.881393],"type":"Point"}
}