{
  "type": "Feature",
  "properties": {
    "iso:country":"US",
    "sg:address":"700 N Saginaw St",
    "sg:city":"Durand",
    "sg:classifiers":[
        {
            "category":"Education",
            "subcategory":"Library",
            "type":"Public Place"
        }
    ],
    "sg:phone":"+1 989 288 3743",
    "sg:postcode":"48429",
    "sg:province":"MI",
    "wof:name":"Shiawaffee District Library",
    "wof:placetype":"venue"
},
  "geometry": {"coordinates":[-83.98487799999999,42.918074],"type":"Point"}
}