{
  "type": "Feature",
  "properties": {
    "iso:country":"US",
    "sg:address":"29380 John R Rd",
    "sg:city":"Madison Heights",
    "sg:classifiers":[
        {
            "category":"Wholesale",
            "subcategory":"Machinery & Supplies",
            "type":"Manufacturing & Wholesale Goods"
        }
    ],
    "sg:phone":"+1 248 586 1601",
    "sg:postcode":"48071",
    "sg:province":"MI",
    "sg:tags":[
        "equipment",
        "industrial"
    ],
    "wof:name":"Mahar Tool Supply Co",
    "wof:placetype":"venue"
},
  "geometry": {"coordinates":[-83.105761,42.506496],"type":"Point"}
}