{
  "type": "Feature",
  "properties": {
    "iso:country":"US",
    "sg:address":"1610 Rolling Oaks Rd",
    "sg:city":"Rochester",
    "sg:classifiers":[
        {
            "category":"Social Services",
            "type":"Services"
        }
    ],
    "sg:phone":"+1 248 652 9099",
    "sg:postcode":"48306",
    "sg:province":"MI",
    "wof:name":"Equine Assisted Counseling",
    "wof:placetype":"venue"
},
  "geometry": {"coordinates":[-83.102941,42.753032],"type":"Point"}
}