{
  "type": "Feature",
  "properties": {
    "iso:country":"US",
    "sg:address":"14955 E 9 Mile Rd",
    "sg:city":"Eastpointe",
    "sg:classifiers":[
        {
            "category":"Professional",
            "subcategory":"Computer Services",
            "type":"Services"
        }
    ],
    "sg:phone":"+1 586 888 1767",
    "sg:postcode":"48021",
    "sg:province":"MI",
    "sg:tags":[
        "repair",
        "provider",
        "internet"
    ],
    "wof:name":"Sos Computer Usage Center",
    "wof:placetype":"venue"
},
  "geometry": {"coordinates":[-82.967686,42.464801],"type":"Point"}
}