{
  "type": "Feature",
  "properties": {
    "iso:country":"US",
    "sg:address":"7644 Durham Rd",
    "sg:city":"Whitehall",
    "sg:classifiers":[
        {
            "category":"Government",
            "subcategory":"Office",
            "type":"Public Place"
        }
    ],
    "sg:phone":"+1 231 893 2095",
    "sg:postcode":"49461",
    "sg:province":"MI",
    "sg:tags":[
        "executive"
    ],
    "wof:name":"Whitehall Township Hall",
    "wof:placetype":"venue"
},
  "geometry": {"coordinates":[-86.311359,43.391895],"type":"Point"}
}