{
  "type": "Feature",
  "properties": {
    "iso:country":"US",
    "sg:address":"371 Cass Ave",
    "sg:city":"Mount Clemens",
    "sg:classifiers":[
        {
            "category":"Food & Beverages",
            "subcategory":"Groceries & Convenience Stores",
            "type":"Retail Goods"
        }
    ],
    "sg:phone":"+1 586 463 1688",
    "sg:postcode":"48043",
    "sg:province":"MI",
    "wof:name":"Yd ES Market",
    "wof:placetype":"venue"
},
  "geometry": {"coordinates":[-82.89724099999999,42.598577],"type":"Point"}
}