{
  "type": "Feature",
  "properties": {
    "iso:country":"US",
    "sg:address":"29119 Orvylle Dr",
    "sg:city":"Warren",
    "sg:classifiers":[
        {
            "category":"Building & Trades",
            "subcategory":"Electrical",
            "type":"Services"
        }
    ],
    "sg:phone":"+1 586 582 0569",
    "sg:postcode":"48092",
    "sg:province":"MI",
    "sg:tags":[
        "electric",
        "contractor"
    ],
    "wof:name":"Tom's Electric",
    "wof:placetype":"venue"
},
  "geometry": {"coordinates":[-83.062572,42.507157],"type":"Point"}
}