{
  "type": "Feature",
  "properties": {
    "iso:country":"US",
    "sg:address":"2025 S Rochester Rd",
    "sg:city":"Rochester Hills",
    "sg:classifiers":[
        {
            "category":"Food & Beverages",
            "subcategory":"Bakery",
            "type":"Retail Goods"
        }
    ],
    "sg:phone":"+1 248 852 4777",
    "sg:postcode":"48307",
    "sg:province":"MI",
    "sg:tags":[
        "baker"
    ],
    "wof:name":"Michigan Health Consultants",
    "wof:placetype":"venue"
},
  "geometry": {"coordinates":[-83.13239299999999,42.651205],"type":"Point"}
}