{
  "type": "Feature",
  "properties": {
    "iso:country":"US",
    "sg:address":"1117 Ludington St",
    "sg:city":"Escanaba",
    "sg:classifiers":[
        {
            "category":"Bars & Pubs",
            "type":"Food & Drink"
        }
    ],
    "sg:phone":"+1 906 786 9834",
    "sg:postcode":"49829",
    "sg:province":"MI",
    "wof:name":"Baron's Bar",
    "wof:placetype":"venue"
},
  "geometry": {"coordinates":[-87.063974,45.745685],"type":"Point"}
}