{
  "type": "Feature",
  "properties": {
    "iso:country":"US",
    "sg:address":"27093 Farmbrook Villa Dr",
    "sg:city":"Southfield",
    "sg:classifiers":[
        {
            "category":"Building & Trades",
            "subcategory":"Construction",
            "type":"Services"
        }
    ],
    "sg:phone":"+1 248 357 2444",
    "sg:postcode":"48034",
    "sg:province":"MI",
    "sg:tags":[
        "home",
        "builder"
    ],
    "wof:name":"Diamond Edge Building Co",
    "wof:placetype":"venue"
},
  "geometry": {"coordinates":[-83.314578,42.507371],"type":"Point"}
}