{
  "type": "Feature",
  "properties": {
    "iso:country":"US",
    "sg:address":"527 W Sunnybrook Dr",
    "sg:city":"Royal Oak",
    "sg:classifiers":[
        {
            "category":"Manufacturing",
            "subcategory":"Retail Goods",
            "type":"Manufacturing & Wholesale Goods"
        }
    ],
    "sg:phone":"+1 248 435 8535",
    "sg:postcode":"48073",
    "sg:province":"MI",
    "sg:tags":[
        "product",
        "mfg"
    ],
    "wof:name":"About Shades",
    "wof:placetype":"venue"
},
  "geometry": {"coordinates":[-83.15097900000001,42.524361],"type":"Point"}
}