{
  "type": "Feature",
  "properties": {
    "iso:country":"US",
    "sg:address":"12605 Flanders St",
    "sg:city":"Detroit",
    "sg:classifiers":[
        {
            "category":"Personal",
            "subcategory":"Nail Salon",
            "type":"Services"
        }
    ],
    "sg:phone":"+1 313 423 0402",
    "sg:postcode":"48205",
    "sg:province":"MI",
    "wof:name":"Nails Shays",
    "wof:placetype":"venue"
},
  "geometry": {"coordinates":[-82.985606,42.41515],"type":"Point"}
}