{
  "type": "Feature",
  "properties": {
    "iso:country":"US",
    "sg:address":"4080 N Lake Rd",
    "sg:city":"Clarklake",
    "sg:classifiers":[
        {
            "category":"Building & Trades",
            "subcategory":"Construction",
            "type":"Services"
        }
    ],
    "sg:phone":"+1 517 529 4729",
    "sg:postcode":"49234",
    "sg:province":"MI",
    "sg:tags":[
        "excavation",
        "contractor"
    ],
    "wof:name":"Argent Excavating Inc",
    "wof:placetype":"venue"
},
  "geometry": {"coordinates":[-84.344796,42.124134],"type":"Point"}
}