{
  "type": "Feature",
  "properties": {
    "iso:country":"US",
    "sg:address":"419 Wilkinson St",
    "sg:city":"Chelsea",
    "sg:classifiers":[
        {
            "category":"Building & Trades",
            "subcategory":"Cleaning & Sanitation",
            "type":"Services"
        }
    ],
    "sg:phone":"+1 734 475 3810",
    "sg:postcode":"48118",
    "sg:province":"MI",
    "sg:tags":[
        "maintenance"
    ],
    "wof:name":"Myers Maintenance Services",
    "wof:placetype":"venue"
},
  "geometry": {"coordinates":[-84.029286,42.312988],"type":"Point"}
}