{
  "type": "Feature",
  "properties": {
    "iso:country":"US",
    "sg:address":"3665 E 11 Mile Rd Ste A",
    "sg:city":"Warren",
    "sg:classifiers":[
        {
            "category":"Health Services",
            "subcategory":"Hospital",
            "type":"Services"
        },
        {
            "category":"Health Services",
            "subcategory":"Nursing And Care Facility",
            "type":"Services"
        },
        {
            "category":"Health Services",
            "subcategory":"Health Practitioner",
            "type":"Services"
        },
        {
            "category":"Health Services",
            "subcategory":"Dentist",
            "type":"Services"
        }
    ],
    "sg:phone":"+1 586 573 0438",
    "sg:postcode":"48092",
    "sg:province":"MI",
    "sg:tags":[
        "holistic",
        "pain",
        "management",
        "sleep",
        "treatment",
        "medicine",
        "alternative",
        "disorders-information"
    ],
    "sg:website":"www.tmjmichigan.com",
    "wof:name":"Michigan Head & Neck Institute PC",
    "wof:placetype":"venue"
},
  "geometry": {"coordinates":[-83.069397,42.4916],"type":"Point"}
}