{
  "type": "Feature",
  "properties": {
    "iso:country":"US",
    "sg:address":"400 Dexter Rd",
    "sg:city":"Eaton Rapids",
    "sg:classifiers":[
        {
            "category":"Education",
            "subcategory":"School",
            "type":"Public Place"
        }
    ],
    "sg:phone":"+1 517 663 2571",
    "sg:postcode":"48827",
    "sg:province":"MI",
    "wof:name":"Northwestern Elementary School",
    "wof:placetype":"venue"
},
  "geometry": {"coordinates":[-84.66980100000001,42.51807],"type":"Point"}
}