{
  "type": "Feature",
  "properties": {
    "iso:country":"US",
    "sg:address":"4660 US Hwy 45",
    "sg:city":"Watersmeet",
    "sg:classifiers":[
        {
            "category":"Government",
            "subcategory":"Office",
            "type":"Public Place"
        }
    ],
    "sg:phone":"+1 906 358 4501",
    "sg:postcode":"49969",
    "sg:province":"MI",
    "sg:tags":[
        "village"
    ],
    "wof:name":"Watersmeet Township Office",
    "wof:placetype":"venue"
},
  "geometry": {"coordinates":[-89.17828,46.267447],"type":"Point"}
}