{
  "type": "Feature",
  "properties": {
    "iso:country":"US",
    "sg:address":"9809 Dixie Hwy",
    "sg:city":"Anchorville",
    "sg:classifiers":[
        {
            "category":"Building & Trades",
            "subcategory":"Plumbing",
            "type":"Services"
        }
    ],
    "sg:phone":"+1 586 727 4377",
    "sg:postcode":"48023",
    "sg:province":"MI",
    "sg:tags":[
        "conditioning",
        "air",
        "system",
        "contractor"
    ],
    "sg:website":"www.tonysheatingandcooling.com",
    "wof:name":"Tony's Refrigeration Heating",
    "wof:placetype":"venue"
},
  "geometry": {"coordinates":[-82.70235099999999,42.689932],"type":"Point"}
}