{
  "type": "Feature",
  "properties": {
    "iso:country":"US",
    "sg:address":"18501 Hall Rd",
    "sg:city":"Macomb",
    "sg:classifiers":[
        {
            "category":"Food & Beverages",
            "subcategory":"Fruits & Vegetables",
            "type":"Retail Goods"
        }
    ],
    "sg:phone":"+1 586 226 5850",
    "sg:postcode":"48044",
    "sg:province":"MI",
    "sg:tags":[
        "produce"
    ],
    "sg:website":"www.manhattanmarketplace.com",
    "wof:name":"Manhattan Marketplace Inc",
    "wof:placetype":"venue"
},
  "geometry": {"coordinates":[-82.93677599999999,42.628657],"type":"Point"}
}