{
  "type": "Feature",
  "properties": {
    "iso:country":"US",
    "sg:address":"212 W Michigan Ave",
    "sg:city":"Jackson",
    "sg:classifiers":[
        {
            "category":"Real Estate",
            "subcategory":"Real Estate Agent",
            "type":"Services"
        }
    ],
    "sg:phone":"+1 517 788 0550",
    "sg:postcode":"49201",
    "sg:province":"MI",
    "sg:tags":[
        "rental",
        "leasing"
    ],
    "wof:name":"Mec Development Corp",
    "wof:placetype":"venue"
},
  "geometry": {"coordinates":[-84.40957,42.247534],"type":"Point"}
}