{
  "type": "Feature",
  "properties": {
    "iso:country":"US",
    "sg:address":"1304 Lake Ave",
    "sg:city":"Grand Haven",
    "sg:classifiers":[
        {
            "category":"Real Estate",
            "subcategory":"Developer",
            "type":"Services"
        },
        {
            "category":"Government",
            "subcategory":"Office",
            "type":"Public Place"
        }
    ],
    "sg:phone":"+1 616 847 3489",
    "sg:postcode":"49417",
    "sg:province":"MI",
    "sg:tags":[
        "cemetery",
        "village"
    ],
    "wof:name":"Lake Forest Municipal Cemetery",
    "wof:placetype":"venue"
},
  "geometry": {"coordinates":[-86.23790099999999,43.053545],"type":"Point"}
}