{
  "type": "Feature",
  "properties": {
    "iso:country":"US",
    "sg:address":"230 W Main St",
    "sg:city":"Ionia",
    "sg:classifiers":[
        {
            "category":"Banks & Credit Unions",
            "subcategory":"Investment Brokerage",
            "type":"Services"
        }
    ],
    "sg:phone":"+1 616 527 5818",
    "sg:postcode":"48846",
    "sg:province":"MI",
    "sg:tags":[
        "security"
    ],
    "wof:name":"Primevest Financial Services",
    "wof:placetype":"venue"
},
  "geometry": {"coordinates":[-85.06585,42.982579],"type":"Point"}
}