{
  "type": "Feature",
  "properties": {
    "iso:country":"US",
    "sg:address":"934 W Commerce Dr",
    "sg:city":"Traverse City",
    "sg:classifiers":[
        {
            "category":"Home & Garden",
            "subcategory":"Furniture",
            "type":"Retail Goods"
        }
    ],
    "sg:phone":"+1 231 943 4099",
    "sg:postcode":"49684",
    "sg:province":"MI",
    "sg:tags":[
        "cabinet"
    ],
    "wof:name":"Y & S Custom Cabinets",
    "wof:placetype":"venue"
},
  "geometry": {"coordinates":[-85.66581600000001,44.673345],"type":"Point"}
}