{
  "type": "Feature",
  "properties": {
    "iso:country":"US",
    "sg:address":"766 Oakridge Rd",
    "sg:city":"St Joseph",
    "sg:classifiers":[
        {
            "category":"Organizations",
            "subcategory":"Religious Organization",
            "type":"Services"
        }
    ],
    "sg:phone":"+1 269 429 7141",
    "sg:postcode":"49085",
    "sg:province":"MI",
    "sg:tags":[
        "church"
    ],
    "sg:website":"www.oakridgebc.org",
    "wof:name":"Oakridge Baptist Church",
    "wof:placetype":"venue"
},
  "geometry": {"coordinates":[-86.471408,42.067486],"type":"Point"}
}