{
  "type": "Feature",
  "properties": {
    "iso:country":"US",
    "sg:address":"11221 Stebbins Ave",
    "sg:city":"Sparta",
    "sg:classifiers":[
        {
            "category":"Building & Trades",
            "subcategory":"Construction",
            "type":"Services"
        }
    ],
    "sg:phone":"+1 616 887 7082",
    "sg:postcode":"49345",
    "sg:province":"MI",
    "sg:tags":[
        "wallcoverings-installation",
        "wallpaper",
        "painting",
        "contractor"
    ],
    "wof:name":"Luann Decorating Originals",
    "wof:placetype":"venue"
},
  "geometry": {"coordinates":[-85.70044300000001,43.167818],"type":"Point"}
}