{
  "type": "Feature",
  "properties": {
    "iso:country":"US",
    "sg:address":"7500 Ivanrest Ave SW",
    "sg:city":"Byron Center",
    "sg:classifiers":[
        {
            "category":"Professional",
            "subcategory":"Business Services",
            "type":"Services"
        }
    ],
    "sg:phone":"+1 616 723 1763",
    "sg:postcode":"49315",
    "sg:province":"MI",
    "wof:name":"AK Training Solutions",
    "wof:placetype":"venue"
},
  "geometry": {"coordinates":[-85.742605,42.827753],"type":"Point"}
}