{
  "type": "Feature",
  "properties": {
    "iso:country":"US",
    "sg:address":"7080 Garling Dr",
    "sg:city":"Dearborn Heights",
    "sg:classifiers":[
        {
            "category":"Banks & Credit Unions",
            "subcategory":"Bank",
            "type":"Services"
        }
    ],
    "sg:phone":"+1 313 271 3330",
    "sg:postcode":"48127",
    "sg:province":"MI",
    "wof:name":"Hunt Columbus Federal Credit Union",
    "wof:placetype":"venue"
},
  "geometry": {"coordinates":[-83.239799,42.3428],"type":"Point"}
}