{
  "type": "Feature",
  "properties": {
    "iso:country":"US",
    "sg:address":"12698 Dixie Hwy",
    "sg:city":"South Rockwood",
    "sg:classifiers":[
        {
            "category":"Bars & Pubs",
            "subcategory":"Nightclub",
            "type":"Food & Drink"
        }
    ],
    "sg:phone":"+1 734 379 3823",
    "sg:postcode":"48179",
    "sg:province":"MI",
    "sg:tags":[
        "nightlife"
    ],
    "wof:name":"Drift Inn",
    "wof:placetype":"venue"
},
  "geometry": {"coordinates":[-83.25839999999999,42.058998],"type":"Point"}
}