{
  "type": "Feature",
  "properties": {
    "iso:country":"US",
    "sg:address":"4195 W Pasadena Ave",
    "sg:city":"Flint",
    "sg:classifiers":[
        {
            "category":"Education",
            "subcategory":"Library",
            "type":"Public Place"
        }
    ],
    "sg:phone":"+1 810 732 5570",
    "sg:postcode":"48504",
    "sg:province":"MI",
    "wof:name":"Genesee District Library Inc",
    "wof:placetype":"venue"
},
  "geometry": {"coordinates":[-83.757874,43.04598],"type":"Point"}
}