{
  "type": "Feature",
  "properties": {
    "iso:country":"US",
    "sg:address":"1200 E Washington St",
    "sg:city":"Greenville",
    "sg:classifiers":[
        {
            "category":"Real Estate",
            "subcategory":"Real Estate Operator",
            "type":"Services"
        }
    ],
    "sg:phone":"+1 616 754 5948",
    "sg:postcode":"48838",
    "sg:province":"MI",
    "sg:tags":[
        "apartment"
    ],
    "wof:name":"Century Place Apartments",
    "wof:placetype":"venue"
},
  "geometry": {"coordinates":[-85.235924,43.172971],"type":"Point"}
}