{
  "type": "Feature",
  "properties": {
    "iso:country":"US",
    "sg:address":"8287 N Vassar Rd",
    "sg:city":"Mount Morris",
    "sg:classifiers":[
        {
            "category":"Manufacturing",
            "subcategory":"Glass & Minerals",
            "type":"Manufacturing & Wholesale Goods"
        }
    ],
    "sg:phone":"+1 810 640 1353",
    "sg:postcode":"48458",
    "sg:province":"MI",
    "sg:tags":[
        "product",
        "mfg"
    ],
    "wof:name":"Confetti Glassworks",
    "wof:placetype":"venue"
},
  "geometry": {"coordinates":[-83.57907,43.128629],"type":"Point"}
}