{
  "type": "Feature",
  "properties": {
    "iso:country":"US",
    "sg:address":"17237 Goldwin Dr",
    "sg:city":"Southfield",
    "sg:classifiers":[
        {
            "category":"Social Services",
            "subcategory":"Child Care",
            "type":"Services"
        }
    ],
    "sg:phone":"+1 248 569 1910",
    "sg:postcode":"48075",
    "sg:province":"MI",
    "sg:tags":[
        "day"
    ],
    "wof:name":"Daycare Heads",
    "wof:placetype":"venue"
},
  "geometry": {"coordinates":[-83.21479100000001,42.477048],"type":"Point"}
}