{
  "type": "Feature",
  "properties": {
    "iso:country":"US",
    "sg:address":"95 Stanley Dr",
    "sg:city":"Bay City",
    "sg:classifiers":[
        {
            "category":"Shopping",
            "type":"Retail Goods"
        }
    ],
    "sg:phone":"+1 989 895 8997",
    "sg:postcode":"48708",
    "sg:province":"MI",
    "sg:tags":[
        "candle"
    ],
    "wof:name":"Man In The Moon Inc",
    "wof:placetype":"venue"
},
  "geometry": {"coordinates":[-83.868003,43.56385],"type":"Point"}
}