{
  "type": "Feature",
  "properties": {
    "iso:country":"US",
    "sg:address":"4754 Hunt St",
    "sg:city":"Cass City",
    "sg:classifiers":[
        {
            "category":"Professional",
            "subcategory":"Business Services",
            "type":"Services"
        }
    ],
    "sg:phone":"+1 989 872 3168",
    "sg:postcode":"48726",
    "sg:province":"MI",
    "wof:name":"Rocky Express LLC",
    "wof:placetype":"venue"
},
  "geometry": {"coordinates":[-83.178096,43.607191],"type":"Point"}
}