{
  "type": "Feature",
  "properties": {
    "iso:country":"US",
    "sg:address":"557 I- 75 Bus",
    "sg:city":"Grayling",
    "sg:classifiers":[
        {
            "category":"Social Services",
            "subcategory":"Child Care",
            "type":"Services"
        }
    ],
    "sg:phone":"+1 989 348 4448",
    "sg:postcode":"49738",
    "sg:province":"MI",
    "sg:tags":[
        "day"
    ],
    "wof:name":"Grayling Head Start",
    "wof:placetype":"venue"
},
  "geometry": {"coordinates":[-84.71662000000001,44.662689],"type":"Point"}
}