{
  "type": "Feature",
  "properties": {
    "iso:country":"US",
    "sg:address":"1017 Avon St",
    "sg:city":"Flint",
    "sg:classifiers":[
        {
            "category":"Social Services",
            "type":"Services"
        }
    ],
    "sg:phone":"+1 810 238 0463",
    "sg:postcode":"48503",
    "sg:province":"MI",
    "sg:tags":[
        "education",
        "community"
    ],
    "wof:name":"National Center For Community",
    "wof:placetype":"venue"
},
  "geometry": {"coordinates":[-83.676862,43.015751],"type":"Point"}
}