{
  "type": "Feature",
  "properties": {
    "iso:country":"US",
    "sg:address":"1143 Park St SW",
    "sg:city":"Grand Rapids",
    "sg:classifiers":[
        {
            "category":"Retail",
            "subcategory":"Repair Shop",
            "type":"Services"
        }
    ],
    "sg:phone":"+1 616 453 7463",
    "sg:postcode":"49504",
    "sg:province":"MI",
    "sg:tags":[
        "appliance"
    ],
    "wof:name":"Tony's Appliance Svc",
    "wof:placetype":"venue"
},
  "geometry": {"coordinates":[-85.697058,42.960198],"type":"Point"}
}