{
  "type": "Feature",
  "properties": {
    "iso:country":"US",
    "sg:address":"762 6th Ave",
    "sg:city":"Lake Odessa",
    "sg:classifiers":[
        {
            "category":"Banks & Credit Unions",
            "subcategory":"Financial Services",
            "type":"Services"
        }
    ],
    "sg:phone":"+1 616 374 8230",
    "sg:postcode":"48849",
    "sg:province":"MI",
    "sg:tags":[
        "trust",
        "management"
    ],
    "wof:name":"Marie L Pickens Trust",
    "wof:placetype":"venue"
},
  "geometry": {"coordinates":[-85.140736,42.778373],"type":"Point"}
}