{
  "type": "Feature",
  "properties": {
    "iso:country":"US",
    "sg:address":"3920 W Centre Ave",
    "sg:city":"Portage",
    "sg:classifiers":[
        {
            "category":"Shopping",
            "subcategory":"Jewelry",
            "type":"Retail Goods"
        }
    ],
    "sg:phone":"+1 269 324 4954",
    "sg:postcode":"49024",
    "sg:province":"MI",
    "sg:tags":[
        "jeweler"
    ],
    "wof:name":"Charmtopia",
    "wof:placetype":"venue"
},
  "geometry": {"coordinates":[-85.64130900000001,42.197991],"type":"Point"}
}