{
  "type": "Feature",
  "properties": {
    "iso:country":"US",
    "sg:address":"37140 Six Mile Road",
    "sg:city":"Livonia",
    "sg:classifiers":[
        {
            "category":"Restaurant",
            "type":"Food & Drink"
        }
    ],
    "sg:phone":"+1 734 953 2761",
    "sg:postcode":"48154",
    "sg:province":"MI",
    "sg:tags":[
        "thai"
    ],
    "wof:name":"Siam Spicy4",
    "wof:placetype":"venue"
},
  "geometry": {"coordinates":[-83.409594,42.41096],"type":"Point"}
}