{
  "type": "Feature",
  "properties": {
    "iso:country":"US",
    "sg:address":"1223 W Clarkston Rd",
    "sg:city":"Lake Orion",
    "sg:classifiers":[
        {
            "category":"Travel",
            "subcategory":"Campground",
            "type":"Entertainment"
        },
        {
            "category":"Organizations",
            "subcategory":"Community Association",
            "type":"Services"
        }
    ],
    "sg:phone":"+1 248 693 8821",
    "sg:postcode":"48362",
    "sg:province":"MI",
    "sg:tags":[
        "camp"
    ],
    "wof:name":"Camp Agawam Boy Scouts America",
    "wof:placetype":"venue"
},
  "geometry": {"coordinates":[-83.270471,42.76524],"type":"Point"}
}