{
  "type": "Feature",
  "properties": {
    "iso:country":"US",
    "sg:address":"4133 Circle Dr",
    "sg:city":"Flint",
    "sg:classifiers":[
        {
            "category":"Personal",
            "subcategory":"Beauty Salon",
            "type":"Services"
        }
    ],
    "sg:phone":"+1 810 743 4870",
    "sg:postcode":"48507",
    "sg:province":"MI",
    "sg:tags":[
        "shop"
    ],
    "wof:name":"Hairitage Hair Fashions",
    "wof:placetype":"venue"
},
  "geometry": {"coordinates":[-83.664395,42.986109],"type":"Point"}
}