{
  "type": "Feature",
  "properties": {
    "iso:country":"US",
    "sg:address":"184 S Olson Rd",
    "sg:city":"Sumner",
    "sg:classifiers":[
        {
            "category":"Retail",
            "subcategory":"Auto Repair",
            "type":"Services"
        }
    ],
    "sg:phone":"+1 989 875 5082",
    "sg:postcode":"48889",
    "sg:province":"MI",
    "sg:tags":[
        "general"
    ],
    "wof:name":"Toms Truck Repair",
    "wof:placetype":"venue"
},
  "geometry": {"coordinates":[-84.747676,43.29012],"type":"Point"}
}