{
  "type": "Feature",
  "properties": {
    "iso:country":"US",
    "sg:address":"8401 E Island Rd",
    "sg:city":"Elsie",
    "sg:classifiers":[
        {
            "category":"Shopping",
            "subcategory":"Used Merchandise",
            "type":"Retail Goods"
        }
    ],
    "sg:phone":"+1 989 862 4322",
    "sg:postcode":"48831",
    "sg:province":"MI",
    "wof:name":"Melvin Antiques & Clock Shop",
    "wof:placetype":"venue"
},
  "geometry": {"coordinates":[-84.401746,43.08877],"type":"Point"}
}