{
  "type": "Feature",
  "properties": {
    "iso:country":"US",
    "sg:address":"3820 W Landis Rd",
    "sg:city":"Angola",
    "sg:classifiers":[
        {
            "category":"Retail",
            "subcategory":"Portrait Studio",
            "type":"Services"
        }
    ],
    "sg:phone":"+1 260 665 5854",
    "sg:postcode":"46703",
    "sg:province":"MI",
    "sg:tags":[
        "photographer"
    ],
    "wof:name":"Memories By Marie",
    "wof:placetype":"venue"
},
  "geometry": {"coordinates":[-85.05334000000001,41.660709],"type":"Point"}
}