{
  "type": "Feature",
  "properties": {
    "iso:country":"US",
    "sg:address":"3122 Amherst Dr",
    "sg:city":"Lansing",
    "sg:classifiers":[
        {
            "category":"Professional",
            "subcategory":"Business Services",
            "type":"Services"
        }
    ],
    "sg:phone":"+1 517 323 2000",
    "sg:postcode":"48906",
    "sg:province":"MI",
    "wof:name":"Michigan Parades Into 21st",
    "wof:placetype":"venue"
},
  "geometry": {"coordinates":[-84.597616,42.7656],"type":"Point"}
}