{
  "type": "Feature",
  "properties": {
    "iso:country":"US",
    "sg:address":"554 Norborne Ave",
    "sg:city":"Dearborn Heights",
    "sg:classifiers":[
        {
            "category":"Professional",
            "subcategory":"Management & Consulting",
            "type":"Services"
        }
    ],
    "sg:phone":"+1 313 278 9838",
    "sg:postcode":"48127",
    "sg:province":"MI",
    "wof:name":"Kelner Zar Marketing Inc",
    "wof:placetype":"venue"
},
  "geometry": {"coordinates":[-83.293605,42.315171],"type":"Point"}
}