{
  "type": "Feature",
  "properties": {
    "iso:country":"US",
    "sg:address":"341 N Main St",
    "sg:city":"Kent City",
    "sg:classifiers":[
        {
            "category":"Professional",
            "type":"Services"
        }
    ],
    "sg:phone":"+1 616 678 4177",
    "sg:postcode":"49330",
    "sg:province":"MI",
    "sg:tags":[
        "establishment"
    ],
    "wof:name":"Merit Access",
    "wof:placetype":"venue"
},
  "geometry": {"coordinates":[-85.751394,43.225949],"type":"Point"}
}