{
  "type": "Feature",
  "properties": {
    "iso:country":"US",
    "sg:address":"4200 Grand River Dr NE",
    "sg:city":"Grand Rapids",
    "sg:classifiers":[
        {
            "category":"Organizations",
            "subcategory":"Community Association",
            "type":"Services"
        }
    ],
    "sg:phone":"+1 616 364 0239",
    "sg:postcode":"49525",
    "sg:province":"MI",
    "sg:tags":[
        "club"
    ],
    "wof:name":"Grand Valley Boat Club",
    "wof:placetype":"venue"
},
  "geometry": {"coordinates":[-85.555241,43.042424],"type":"Point"}
}