{
  "type": "Feature",
  "properties": {
    "iso:country":"US",
    "sg:address":"6967 Saint Marys St",
    "sg:city":"Brown City",
    "sg:classifiers":[
        {
            "category":"Real Estate",
            "subcategory":"Real Estate Agent",
            "type":"Services"
        }
    ],
    "sg:phone":"+1 810 346 3419",
    "sg:postcode":"48416",
    "sg:province":"MI",
    "wof:name":"Tall Pine Real Estate",
    "wof:placetype":"venue"
},
  "geometry": {"coordinates":[-82.989277,43.212807],"type":"Point"}
}