{
  "type": "Feature",
  "properties": {
    "iso:country":"US",
    "sg:address":"5082 N Saginaw St",
    "sg:city":"Flint",
    "sg:classifiers":[
        {
            "category":"Retail",
            "subcategory":"Car Wash",
            "type":"Services"
        }
    ],
    "sg:phone":"+1 810 787 4104",
    "sg:postcode":"48505",
    "sg:province":"MI",
    "sg:tags":[
        "carwash"
    ],
    "wof:name":"Embrys Car Wash",
    "wof:placetype":"venue"
},
  "geometry": {"coordinates":[-83.69408199999999,43.078694],"type":"Point"}
}