{
  "type": "Feature",
  "properties": {
    "iso:country":"US",
    "sg:address":"2232 S Main St",
    "sg:city":"Ann Arbor",
    "sg:classifiers":[
        {
            "category":"Professional",
            "subcategory":"Management & Consulting",
            "type":"Services"
        }
    ],
    "sg:phone":"+1 734 761 1867",
    "sg:postcode":"48103",
    "sg:province":"MI",
    "sg:tags":[
        "business"
    ],
    "wof:name":"Jitel Corp",
    "wof:placetype":"venue"
},
  "geometry": {"coordinates":[-83.749973,42.253531],"type":"Point"}
}