{
  "type": "Feature",
  "properties": {
    "iso:country":"US",
    "sg:address":"131 28th St SW",
    "sg:city":"Grand Rapids",
    "sg:classifiers":[
        {
            "category":"Retail",
            "subcategory":"Auto Repair",
            "type":"Services"
        }
    ],
    "sg:phone":"+1 616 245 8639",
    "sg:postcode":"49548",
    "sg:province":"MI",
    "sg:tags":[
        "muffler",
        "shop",
        "brake"
    ],
    "wof:name":"Muffler Man",
    "wof:placetype":"venue"
},
  "geometry": {"coordinates":[-85.667755,42.913175],"type":"Point"}
}