{
  "type": "Feature",
  "properties": {
    "iso:country":"US",
    "sg:address":"5227 S Dort Hwy",
    "sg:city":"Flint",
    "sg:classifiers":[
        {
            "category":"Shopping",
            "subcategory":"Bicycles & Sporting Goods",
            "type":"Retail Goods"
        }
    ],
    "sg:phone":"+1 810 695 6226",
    "sg:postcode":"48507",
    "sg:province":"MI",
    "sg:tags":[
        "equipment",
        "skateboard"
    ],
    "wof:name":"Precision Skateboard Shop",
    "wof:placetype":"venue"
},
  "geometry": {"coordinates":[-83.652958,42.954449],"type":"Point"}
}