{
  "type": "Feature",
  "properties": {
    "iso:country":"US",
    "sg:address":"7639 W McNichols Rd",
    "sg:city":"Detroit",
    "sg:classifiers":[
        {
            "category":"Personal",
            "subcategory":"Beauty Salon",
            "type":"Services"
        }
    ],
    "sg:phone":"+1 313 995 1961",
    "sg:postcode":"48221",
    "sg:province":"MI",
    "sg:tags":[
        "shop",
        "clothing"
    ],
    "wof:name":"Top Flight Designs",
    "wof:placetype":"venue"
},
  "geometry": {"coordinates":[-83.148404,42.417044],"type":"Point"}
}