{
  "type": "Feature",
  "properties": {
    "iso:country":"US",
    "sg:address":"493 N Drake Rd",
    "sg:city":"Kalamazoo",
    "sg:classifiers":[
        {
            "category":"Wholesale",
            "subcategory":"Machinery & Supplies",
            "type":"Manufacturing & Wholesale Goods"
        }
    ],
    "sg:phone":"+1 269 342 6745",
    "sg:postcode":"49009",
    "sg:province":"MI",
    "sg:tags":[
        "salon",
        "beauty"
    ],
    "wof:name":"Sally Beauty Supply",
    "wof:placetype":"venue"
},
  "geometry": {"coordinates":[-85.648241,42.293175],"type":"Point"}
}