{
  "type": "Feature",
  "properties": {
    "iso:country":"US",
    "sg:address":"6354 N McKinley Rd",
    "sg:city":"Flushing",
    "sg:classifiers":[
        {
            "category":"Shopping",
            "type":"Retail Goods"
        }
    ],
    "sg:phone":"+1 810 659 1967",
    "sg:postcode":"48433",
    "sg:province":"MI",
    "sg:tags":[
        "cosmetic",
        "perfume"
    ],
    "wof:name":"Mary Kay Cosmetcis Independent",
    "wof:placetype":"venue"
},
  "geometry": {"coordinates":[-83.85301200000001,43.099446],"type":"Point"}
}