{
  "type": "Feature",
  "properties": {
    "iso:country":"US",
    "sg:address":"2205 Abbott Rd",
    "sg:city":"East Lansing",
    "sg:classifiers":[
        {
            "category":"Insurance",
            "subcategory":"Insurance Agent",
            "type":"Services"
        }
    ],
    "sg:phone":"+1 517 337 6000",
    "sg:postcode":"48823",
    "sg:province":"MI",
    "wof:name":"James M Day Ins",
    "wof:placetype":"venue"
},
  "geometry": {"coordinates":[-84.48380299999999,42.75571],"type":"Point"}
}