{
  "type": "Feature",
  "properties": {
    "iso:country":"US",
    "sg:address":"3842 Robert T Longway Blvd",
    "sg:city":"Flint",
    "sg:classifiers":[
        {
            "category":"Building & Trades",
            "subcategory":"Construction",
            "type":"Services"
        }
    ],
    "sg:phone":"+1 810 742 9500",
    "sg:postcode":"48506",
    "sg:province":"MI",
    "sg:tags":[
        "demolition",
        "contractor"
    ],
    "wof:name":"Burnash Wrecking Inc",
    "wof:placetype":"venue"
},
  "geometry": {"coordinates":[-83.64077899999999,43.025729],"type":"Point"}
}