{
  "type": "Feature",
  "properties": {
    "iso:country":"US",
    "sg:address":"9350 Silver Maple Dr",
    "sg:city":"Whitmore Lake",
    "sg:classifiers":[
        {
            "category":"Real Estate",
            "subcategory":"Real Estate Agent",
            "type":"Services"
        }
    ],
    "sg:phone":"+1 810 231 0355",
    "sg:postcode":"48189",
    "sg:province":"MI",
    "wof:name":"Appraisals To Sales",
    "wof:placetype":"venue"
},
  "geometry": {"coordinates":[-83.82231899999999,42.466556],"type":"Point"}
}