{
  "type": "Feature",
  "properties": {
    "iso:country":"US",
    "sg:address":"1075 36th St SW",
    "sg:city":"Wyoming",
    "sg:classifiers":[
        {
            "category":"Restaurant",
            "type":"Food & Drink"
        }
    ],
    "sg:phone":"+1 616 534 7770",
    "sg:postcode":"49509",
    "sg:province":"MI",
    "wof:name":"C & N Restaurant",
    "wof:placetype":"venue"
},
  "geometry": {"coordinates":[-85.69175199999999,42.898918],"type":"Point"}
}