{
  "type": "Feature",
  "properties": {
    "iso:country":"US",
    "sg:address":"9601 Grayfield",
    "sg:city":"Redford",
    "sg:classifiers":[
        {
            "category":"Banks & Credit Unions",
            "subcategory":"Financial Services",
            "type":"Services"
        }
    ],
    "sg:phone":"+1 313 541 1473",
    "sg:postcode":"48239",
    "sg:province":"MI",
    "sg:tags":[
        "broker",
        "mortgage"
    ],
    "wof:name":"1st Securities Financial of Redford",
    "wof:placetype":"venue"
},
  "geometry": {"coordinates":[-83.268107,42.365586],"type":"Point"}
}