{
  "type": "Feature",
  "properties": {
    "iso:country":"US",
    "sg:address":"4154 Saginaw Ct",
    "sg:city":"Ann Arbor",
    "sg:classifiers":[
        {
            "category":"Health Services",
            "subcategory":"Clinic",
            "type":"Services"
        }
    ],
    "sg:phone":"+1 734 665 9095",
    "sg:postcode":"48103",
    "sg:province":"MI",
    "wof:name":"Alliance Personal Care",
    "wof:placetype":"venue"
},
  "geometry": {"coordinates":[-83.81262099999999,42.268719],"type":"Point"}
}