{
  "type": "Feature",
  "properties": {
    "iso:country":"US",
    "sg:address":"9983 Polk St",
    "sg:city":"Zeeland",
    "sg:classifiers":[
        {
            "category":"Sports & Exercise",
            "subcategory":"Race Track",
            "type":"Entertainment"
        }
    ],
    "sg:phone":"+1 616 875 3232",
    "sg:postcode":"49464",
    "sg:province":"MI",
    "wof:name":"D & B Motor Sports",
    "wof:placetype":"venue"
},
  "geometry": {"coordinates":[-86.030502,42.914047],"type":"Point"}
}