{
  "type": "Feature",
  "properties": {
    "iso:country":"US",
    "sg:address":"26657 Woodward Ave Ste 102",
    "sg:city":"Huntington Wd",
    "sg:classifiers":[
        {
            "category":"Health Services",
            "subcategory":"Doctor",
            "type":"Services"
        }
    ],
    "sg:phone":"+1 248 336 3600",
    "sg:postcode":"48070",
    "sg:province":"MI",
    "sg:tags":[
        "surgeon",
        "oral"
    ],
    "wof:name":"Winter H Karl DDS",
    "wof:placetype":"venue"
},
  "geometry": {"coordinates":[-83.156097,42.486401],"type":"Point"}
}