{
  "type": "Feature",
  "properties": {
    "iso:country":"US",
    "sg:address":"24829 Woodland Dr",
    "sg:city":"Flat Rock",
    "sg:classifiers":[
        {
            "category":"Social Services",
            "subcategory":"Adult Care",
            "type":"Services"
        }
    ],
    "sg:phone":"+1 734 782 1356",
    "sg:postcode":"48134",
    "sg:province":"MI",
    "sg:tags":[
        "residential"
    ],
    "wof:name":"Homes of Opportunity",
    "wof:placetype":"venue"
},
  "geometry": {"coordinates":[-83.277524,42.12504],"type":"Point"}
}