{
  "type": "Feature",
  "properties": {
    "iso:country":"US",
    "sg:address":"1002 10th Ave",
    "sg:city":"Port Huron",
    "sg:classifiers":[
        {
            "category":"Health Services",
            "subcategory":"Doctor",
            "type":"Services"
        }
    ],
    "sg:phone":"+1 810 985 9551",
    "sg:postcode":"48060",
    "sg:province":"MI",
    "sg:tags":[
        "physician",
        "surgeon"
    ],
    "sg:website":"www.xrayassociatesofph.com",
    "wof:name":"X-Ray Associates",
    "wof:placetype":"venue"
},
  "geometry": {"coordinates":[-82.433694,42.985097],"type":"Point"}
}