{
  "type": "Feature",
  "properties": {
    "iso:country":"US",
    "sg:address":"4241 Payne Rd",
    "sg:city":"Attica",
    "sg:classifiers":[
        {
            "category":"Retail",
            "subcategory":"Laundry & Dry Cleaning",
            "type":"Services"
        }
    ],
    "sg:phone":"+1 810 724 2407",
    "sg:postcode":"48412",
    "sg:province":"MI",
    "sg:tags":[
        "cleaners",
        "rug",
        "carpet"
    ],
    "wof:name":"B & D Carpet Cleaners",
    "wof:placetype":"venue"
},
  "geometry": {"coordinates":[-83.172927,43.025013],"type":"Point"}
}