{
  "type": "Feature",
  "properties": {
    "iso:country":"US",
    "sg:address":"2311 Jolly Rd",
    "sg:city":"Okemos",
    "sg:classifiers":[
        {
            "category":"Home & Garden",
            "subcategory":"Furniture",
            "type":"Retail Goods"
        }
    ],
    "sg:phone":"+1 517 347 1300",
    "sg:postcode":"48864",
    "sg:province":"MI",
    "sg:tags":[
        "cabinet"
    ],
    "wof:name":"Cornerstone Cabinetry Inc",
    "wof:placetype":"venue"
},
  "geometry": {"coordinates":[-84.43318600000001,42.682843],"type":"Point"}
}