{
  "type": "Feature",
  "properties": {
    "iso:country":"US",
    "sg:address":"108 W Michigan Ave",
    "sg:city":"Paw Paw",
    "sg:classifiers":[
        {
            "category":"Government",
            "subcategory":"Police Station",
            "type":"Public Place"
        }
    ],
    "sg:phone":"+1 269 657 6081",
    "sg:postcode":"49079",
    "sg:province":"MI",
    "sg:tags":[
        "protection"
    ],
    "sg:website":"www.michigan.gov",
    "wof:name":"Police 5th Dist",
    "wof:placetype":"venue"
},
  "geometry": {"coordinates":[-85.892606,42.217845],"type":"Point"}
}