{
  "type": "Feature",
  "properties": {
    "iso:country":"US",
    "sg:address":"436 Leland St",
    "sg:city":"Flushing",
    "sg:classifiers":[
        {
            "category":"Professional",
            "subcategory":"Management & Consulting",
            "type":"Services"
        }
    ],
    "sg:phone":"+1 810 659 1976",
    "sg:postcode":"48433",
    "sg:province":"MI",
    "sg:tags":[
        "business"
    ],
    "wof:name":"Evergreen Training Resources",
    "wof:placetype":"venue"
},
  "geometry": {"coordinates":[-83.83855,43.068874],"type":"Point"}
}