{
  "type": "Feature",
  "properties": {
    "iso:country":"US",
    "sg:address":"102 W Middle St",
    "sg:city":"Williamston",
    "sg:classifiers":[
        {
            "category":"Professional",
            "subcategory":"Lawyer & Legal Services",
            "type":"Services"
        }
    ],
    "sg:phone":"+1 517 655 6380",
    "sg:postcode":"48895",
    "sg:province":"MI",
    "sg:tags":[
        "attorney"
    ],
    "wof:name":"Tina S Gray PC",
    "wof:placetype":"venue"
},
  "geometry": {"coordinates":[-84.28516399999999,42.687832],"type":"Point"}
}