{
  "type": "Feature",
  "properties": {
    "iso:country":"US",
    "sg:address":"102 W Main St",
    "sg:city":"Carson City",
    "sg:classifiers":[
        {
            "category":"Education",
            "subcategory":"Library",
            "type":"Public Place"
        }
    ],
    "sg:phone":"+1 989 584 3680",
    "sg:postcode":"48811",
    "sg:province":"MI",
    "sg:website":"www.carsoncity.llcoop.org",
    "wof:name":"Carson City Public Library",
    "wof:placetype":"venue"
},
  "geometry": {"coordinates":[-84.847705,43.177084],"type":"Point"}
}