{
  "type": "Feature",
  "properties": {
    "iso:country":"US",
    "sg:address":"6132 Division Ave S",
    "sg:city":"Grand Rapids",
    "sg:classifiers":[
        {
            "category":"Building & Trades",
            "subcategory":"Construction",
            "type":"Services"
        }
    ],
    "sg:phone":"+1 616 534 3400",
    "sg:postcode":"49548",
    "sg:province":"MI",
    "sg:website":"www.preferredmobilehomes.com",
    "wof:name":"Preferred Mobile Homes",
    "wof:placetype":"venue"
},
  "geometry": {"coordinates":[-85.66372699999999,42.853213],"type":"Point"}
}