{
  "type": "Feature",
  "properties": {
    "iso:country":"US",
    "sg:address":"4425 W Main St",
    "sg:city":"Midland",
    "sg:classifiers":[
        {
            "category":"Organizations",
            "subcategory":"Religious Organization",
            "type":"Services"
        }
    ],
    "sg:phone":"+1 989 832 2554",
    "sg:postcode":"48640",
    "sg:province":"MI",
    "sg:tags":[
        "clergy"
    ],
    "wof:name":"Paul E Schneider",
    "wof:placetype":"venue"
},
  "geometry": {"coordinates":[-84.271627,43.638872],"type":"Point"}
}