{
  "type": "Feature",
  "properties": {
    "iso:country":"US",
    "sg:address":"10360 Ellis Rd",
    "sg:city":"Clarkston",
    "sg:classifiers":[
        {
            "category":"Social Services",
            "subcategory":"Adult Care",
            "type":"Services"
        }
    ],
    "sg:phone":"+1 248 625 7669",
    "sg:postcode":"48348",
    "sg:province":"MI",
    "sg:tags":[
        "foster",
        "provider"
    ],
    "wof:name":"Stephen & Kelly Hudson",
    "wof:placetype":"venue"
},
  "geometry": {"coordinates":[-83.44957700000001,42.788182],"type":"Point"}
}