{
  "type": "Feature",
  "properties": {
    "iso:country":"US",
    "sg:address":"4145 Dublin Dr",
    "sg:city":"Bloomfield Hills",
    "sg:classifiers":[
        {
            "category":"Insurance",
            "subcategory":"Hazard Insurance",
            "type":"Services"
        }
    ],
    "sg:phone":"+1 248 594 1717",
    "sg:postcode":"48302",
    "sg:province":"MI",
    "sg:tags":[
        "bond"
    ],
    "wof:name":"Great Lakes Bonding",
    "wof:placetype":"venue"
},
  "geometry": {"coordinates":[-83.282788,42.579566],"type":"Point"}
}