{
  "type": "Feature",
  "properties": {
    "iso:country":"US",
    "sg:address":"24615 Harper Ave",
    "sg:city":"St Clair Shores",
    "sg:classifiers":[
        {
            "category":"Restaurant",
            "type":"Food & Drink"
        }
    ],
    "sg:phone":"+1 586 776 3350",
    "sg:postcode":"48080",
    "sg:province":"MI",
    "sg:tags":[
        "parlor",
        "ice",
        "cream"
    ],
    "wof:name":"Country Dairy",
    "wof:placetype":"venue"
},
  "geometry": {"coordinates":[-82.90294799999999,42.47738],"type":"Point"}
}