{
  "type": "Feature",
  "properties": {
    "iso:country":"US",
    "sg:address":"5645 Balsam Dr",
    "sg:city":"Hudsonville",
    "sg:classifiers":[
        {
            "category":"Utilities",
            "subcategory":"Mobile Phone",
            "type":"Services"
        }
    ],
    "sg:phone":"+1 616 662 9822",
    "sg:postcode":"49426",
    "sg:province":"MI",
    "sg:tags":[
        "telephone",
        "cellular"
    ],
    "wof:name":"Rapid Cellular",
    "wof:placetype":"venue"
},
  "geometry": {"coordinates":[-85.86075099999999,42.87195],"type":"Point"}
}