{
  "type": "Feature",
  "properties": {
    "iso:country":"US",
    "sg:address":"408 E Grand River Ave",
    "sg:city":"Lansing",
    "sg:classifiers":[
        {
            "category":"Manufacturing",
            "subcategory":"Printing",
            "type":"Manufacturing & Wholesale Goods"
        }
    ],
    "sg:phone":"+1 517 853 3680",
    "sg:postcode":"48906",
    "sg:province":"MI",
    "sg:tags":[
        "multimedia"
    ],
    "wof:name":"Media Graphics Inc",
    "wof:placetype":"venue"
},
  "geometry": {"coordinates":[-84.54650100000001,42.747327],"type":"Point"}
}