{
  "type": "Feature",
  "properties": {
    "iso:country":"US",
    "sg:address":"107 S Evans St",
    "sg:city":"Tecumseh",
    "sg:classifiers":[
        {
            "category":"Bars & Pubs",
            "type":"Food & Drink"
        }
    ],
    "sg:phone":"+1 517 423 6364",
    "sg:postcode":"49286",
    "sg:province":"MI",
    "wof:name":"Wrong Way's Pub",
    "wof:placetype":"venue"
},
  "geometry": {"coordinates":[-83.945249,42.003619],"type":"Point"}
}