{
  "type": "Feature",
  "properties": {
    "iso:country":"US",
    "sg:address":"19181 Goldwin St",
    "sg:city":"Southfield",
    "sg:classifiers":[
        {
            "category":"Organizations",
            "subcategory":"Religious Organization",
            "type":"Services"
        }
    ],
    "sg:phone":"+1 248 368 1842",
    "sg:postcode":"48075",
    "sg:province":"MI",
    "sg:tags":[
        "church"
    ],
    "wof:name":"Covenant Community Church",
    "wof:placetype":"venue"
},
  "geometry": {"coordinates":[-83.233799,42.475769],"type":"Point"}
}