{
  "type": "Feature",
  "properties": {
    "iso:country":"US",
    "sg:address":"317 N Lake St",
    "sg:city":"Ironwood",
    "sg:classifiers":[
        {
            "category":"Local Transit",
            "type":"Transportation"
        }
    ],
    "sg:phone":"+1 906 932 4284",
    "sg:postcode":"49938",
    "sg:province":"MI",
    "sg:tags":[
        "handicapped"
    ],
    "wof:name":"Care-A-Van Convalescent",
    "wof:placetype":"venue"
},
  "geometry": {"coordinates":[-90.156561,46.459872],"type":"Point"}
}