{
  "type": "Feature",
  "properties": {
    "iso:country":"US",
    "sg:address":"58295 Place Rd",
    "sg:city":"Lenox",
    "sg:classifiers":[
        {
            "category":"Building & Trades",
            "subcategory":"Construction",
            "type":"Services"
        },
        {
            "category":"Retail",
            "subcategory":"Auto Repair",
            "type":"Services"
        }
    ],
    "sg:phone":"+1 586 749 8468",
    "sg:postcode":"48048",
    "sg:province":"MI",
    "sg:tags":[
        "glass",
        "coating",
        "tinting",
        "contractor"
    ],
    "wof:name":"Ultimate Window Tinting",
    "wof:placetype":"venue"
},
  "geometry": {"coordinates":[-82.831672,42.728348],"type":"Point"}
}