{
  "type": "Feature",
  "properties": {
    "iso:country":"US",
    "sg:address":"1752 W Michigan Ave",
    "sg:city":"Saginaw",
    "sg:classifiers":[
        {
            "category":"Building & Trades",
            "subcategory":"Cleaning & Sanitation",
            "type":"Services"
        }
    ],
    "sg:phone":"+1 989 233 3274",
    "sg:postcode":"48602",
    "sg:province":"MI",
    "sg:tags":[
        "house"
    ],
    "wof:name":"Joycee's Cleaning Svc",
    "wof:placetype":"venue"
},
  "geometry": {"coordinates":[-83.986757,43.400763],"type":"Point"}
}