{
  "type": "Feature",
  "properties": {
    "iso:country":"US",
    "sg:address":"1350 Stephenson Hwy",
    "sg:city":"Troy",
    "sg:classifiers":[
        {
            "category":"Health Services",
            "subcategory":"Hospital",
            "type":"Services"
        }
    ],
    "sg:phone":"+1 248 597 2700",
    "sg:postcode":"48083",
    "sg:province":"MI",
    "sg:tags":[
        "datum",
        "general"
    ],
    "wof:name":"William Beaumont Hospital",
    "wof:placetype":"venue"
},
  "geometry": {"coordinates":[-83.120256,42.543306],"type":"Point"}
}