{
  "type": "Feature",
  "properties": {
    "iso:country":"US",
    "sg:address":"71 Walnut Blvd",
    "sg:city":"Rochester",
    "sg:classifiers":[
        {
            "category":"Shopping",
            "type":"Retail Goods"
        }
    ],
    "sg:phone":"+1 248 652 1208",
    "sg:postcode":"48307",
    "sg:province":"MI",
    "sg:tags":[
        "hearing",
        "equipment",
        "supply",
        "impaired"
    ],
    "wof:name":"Lucas Hearing Aid Svc",
    "wof:placetype":"venue"
},
  "geometry": {"coordinates":[-83.135318,42.677712],"type":"Point"}
}