{
  "type": "Feature",
  "properties": {
    "iso:country":"US",
    "sg:address":"1026 Division Ave S",
    "sg:city":"Grand Rapids",
    "sg:classifiers":[
        {
            "category":"Autos & Motor Vehicles",
            "subcategory":"Automobile Sales",
            "type":"Retail Goods"
        }
    ],
    "sg:phone":"+1 616 452 9090",
    "sg:postcode":"49507",
    "sg:province":"MI",
    "sg:tags":[
        "car",
        "dealer"
    ],
    "wof:name":"Affordable Motor Sales Inc",
    "wof:placetype":"venue"
},
  "geometry": {"coordinates":[-85.667322,42.944751],"type":"Point"}
}