{
  "type": "Feature",
  "properties": {
    "iso:country":"US",
    "sg:address":"8690 S Oceana Dr",
    "sg:city":"Montague",
    "sg:classifiers":[
        {
            "category":"Retail",
            "subcategory":"Auto Repair",
            "type":"Services"
        }
    ],
    "sg:phone":"+1 231 893 1349",
    "sg:postcode":"49437",
    "sg:province":"MI",
    "sg:tags":[
        "marina",
        "operation",
        "general"
    ],
    "wof:name":"Blue Water Marine Service",
    "wof:placetype":"venue"
},
  "geometry": {"coordinates":[-86.347526,43.487939],"type":"Point"}
}