{
  "type": "Feature",
  "properties": {
    "iso:country":"US",
    "sg:address":"4733 Okemos Rd",
    "sg:city":"Okemos",
    "sg:classifiers":[
        {
            "category":"Insurance",
            "subcategory":"Insurance Agent",
            "type":"Services"
        }
    ],
    "sg:phone":"+1 517 347 1466",
    "sg:postcode":"48864",
    "sg:province":"MI",
    "wof:name":"Arnouts & Methner Insurance",
    "wof:placetype":"venue"
},
  "geometry": {"coordinates":[-84.427965,42.718684],"type":"Point"}
}