{
  "type": "Feature",
  "properties": {
    "iso:country":"US",
    "sg:address":"1324 Westport Dr",
    "sg:city":"Lansing",
    "sg:classifiers":[
        {
            "category":"Retail",
            "subcategory":"Repair Shop",
            "type":"Services"
        }
    ],
    "sg:phone":"+1 517 327 8774",
    "sg:postcode":"48917",
    "sg:province":"MI",
    "wof:name":"Cleaning Maid Easy",
    "wof:placetype":"venue"
},
  "geometry": {"coordinates":[-84.628896,42.750329],"type":"Point"}
}