{
  "type": "Feature",
  "properties": {
    "iso:country":"US",
    "sg:address":"33148 Chief Ln",
    "sg:city":"Westland",
    "sg:classifiers":[
        {
            "category":"Building & Trades",
            "subcategory":"Electrical",
            "type":"Services"
        }
    ],
    "sg:phone":"+1 734 266 6209",
    "sg:postcode":"48185",
    "sg:province":"MI",
    "sg:tags":[
        "electrician"
    ],
    "wof:name":"D K Electric C 0",
    "wof:placetype":"venue"
},
  "geometry": {"coordinates":[-83.367203,42.340302],"type":"Point"}
}