{
  "type": "Feature",
  "properties": {
    "iso:country":"US",
    "sg:address":"6001 Boone Rd",
    "sg:city":"Traverse City",
    "sg:classifiers":[
        {
            "category":"Real Estate",
            "subcategory":"Real Estate Agent",
            "type":"Services"
        }
    ],
    "sg:phone":"+1 231 943 9485",
    "sg:postcode":"49684",
    "sg:province":"MI",
    "wof:name":"Adams Real Estate",
    "wof:placetype":"venue"
},
  "geometry": {"coordinates":[-85.698566,44.705149],"type":"Point"}
}