{
  "type": "Feature",
  "properties": {
    "iso:country":"US",
    "sg:address":"351 E Chesterfield St",
    "sg:city":"Ferndale",
    "sg:classifiers":[
        {
            "category":"Professional",
            "type":"Services"
        }
    ],
    "sg:phone":"+1 248 547 3953",
    "sg:postcode":"48220",
    "sg:province":"MI",
    "sg:tags":[
        "establishment"
    ],
    "wof:name":"T Sn",
    "wof:placetype":"venue"
},
  "geometry": {"coordinates":[-83.117986,42.448105],"type":"Point"}
}