{
  "type": "Feature",
  "properties": {
    "iso:country":"US",
    "sg:address":"8035 S 21 Rd",
    "sg:city":"Cadillac",
    "sg:classifiers":[
        {
            "category":"Autos & Motor Vehicles",
            "subcategory":"Automobile Sales",
            "type":"Retail Goods"
        }
    ],
    "sg:phone":"+1 231 862 3549",
    "sg:postcode":"49601",
    "sg:province":"MI",
    "sg:tags":[
        "car",
        "dealer"
    ],
    "wof:name":"Galvanek's Autos & Rv's",
    "wof:placetype":"venue"
},
  "geometry": {"coordinates":[-85.61854,44.220446],"type":"Point"}
}