{
  "type": "Feature",
  "properties": {
    "iso:country":"US",
    "sg:address":"1422 Junction St",
    "sg:city":"Detroit",
    "sg:classifiers":[
        {
            "category":"Personal",
            "subcategory":"Beauty Salon",
            "type":"Services"
        }
    ],
    "sg:phone":"+1 313 843 2723",
    "sg:postcode":"48209",
    "sg:province":"MI",
    "sg:tags":[
        "shop"
    ],
    "wof:name":"Colonial Estetica Unisex",
    "wof:placetype":"venue"
},
  "geometry": {"coordinates":[-83.099332,42.314387],"type":"Point"}
}