{
  "type": "Feature",
  "properties": {
    "iso:country":"US",
    "sg:address":"700 Wealthy St SW",
    "sg:city":"Grand Rapids",
    "sg:classifiers":[
        {
            "category":"Manufacturing",
            "subcategory":"Metals",
            "type":"Manufacturing & Wholesale Goods"
        }
    ],
    "sg:phone":"+1 616 451 0784",
    "sg:postcode":"49504",
    "sg:province":"MI",
    "sg:tags":[
        "coating"
    ],
    "sg:website":"www.spectrumindustries.com",
    "wof:name":"Spectrum Industries Inc",
    "wof:placetype":"venue"
},
  "geometry": {"coordinates":[-85.684804,42.956111],"type":"Point"}
}