{
  "type": "Feature",
  "properties": {
    "iso:country":"US",
    "sg:address":"2526 Ferncliff Ave",
    "sg:city":"Royal Oak",
    "sg:classifiers":[
        {
            "category":"Social Services",
            "subcategory":"Child Care",
            "type":"Services"
        }
    ],
    "sg:phone":"+1 248 288 4524",
    "sg:postcode":"48073",
    "sg:province":"MI",
    "sg:tags":[
        "day"
    ],
    "wof:name":"Mary C Tobin",
    "wof:placetype":"venue"
},
  "geometry": {"coordinates":[-83.16848299999999,42.513241],"type":"Point"}
}