{
  "type": "Feature",
  "properties": {
    "iso:country":"US",
    "sg:address":"170 Fillmore Pl",
    "sg:city":"Bay City",
    "sg:classifiers":[
        {
            "category":"Building & Trades",
            "subcategory":"Construction",
            "type":"Services"
        }
    ],
    "sg:phone":"+1 989 892 6606",
    "sg:postcode":"48708",
    "sg:province":"MI",
    "wof:name":"Telejames Inc",
    "wof:placetype":"venue"
},
  "geometry": {"coordinates":[-83.86290200000001,43.602071],"type":"Point"}
}