{
  "type": "Feature",
  "properties": {
    "iso:country":"US",
    "sg:address":"932 9th St",
    "sg:city":"Plainwell",
    "sg:classifiers":[
        {
            "category":"Building & Trades",
            "subcategory":"Construction",
            "type":"Services"
        }
    ],
    "sg:phone":"+1 269 685 8986",
    "sg:postcode":"49080",
    "sg:province":"MI",
    "sg:tags":[
        "general",
        "contractor"
    ],
    "sg:website":"www.jpbuildersinc.com",
    "wof:name":"J P Builders Inc",
    "wof:placetype":"venue"
},
  "geometry": {"coordinates":[-85.627201,42.488108],"type":"Point"}
}