{
  "type": "Feature",
  "properties": {
    "iso:country":"US",
    "sg:address":"1575 S Milford Rd",
    "sg:city":"Highland",
    "sg:classifiers":[
        {
            "category":"Retail",
            "subcategory":"Auto Rental",
            "type":"Services"
        }
    ],
    "sg:phone":"+1 248 889 1471",
    "sg:postcode":"48357",
    "sg:province":"MI",
    "sg:tags":[
        "renting",
        "truck",
        "leasing"
    ],
    "wof:name":"U-Haul Co",
    "wof:placetype":"venue"
},
  "geometry": {"coordinates":[-83.616179,42.623894],"type":"Point"}
}