{
  "type": "Feature",
  "properties": {
    "iso:country":"US",
    "sg:address":"12028 Charlane Dr",
    "sg:city":"Brighton",
    "sg:classifiers":[
        {
            "category":"Social Services",
            "subcategory":"Job Training",
            "type":"Services"
        }
    ],
    "sg:phone":"+1 810 225 3188",
    "sg:postcode":"48114",
    "sg:province":"MI",
    "sg:tags":[
        "rehabilitation"
    ],
    "wof:name":"Willowbrook Rehabilitation Svc",
    "wof:placetype":"venue"
},
  "geometry": {"coordinates":[-83.707525,42.55009],"type":"Point"}
}