{
  "type": "Feature",
  "properties": {
    "iso:country":"US",
    "sg:address":"5186 S Pere Marquette Hwy",
    "sg:city":"Ludington",
    "sg:classifiers":[
        {
            "category":"Organizations",
            "subcategory":"Religious Organization",
            "type":"Services"
        }
    ],
    "sg:phone":"+1 231 843 1884",
    "sg:postcode":"49431",
    "sg:province":"MI",
    "wof:name":"Summit Church Of Christ",
    "wof:placetype":"venue"
},
  "geometry": {"coordinates":[-86.398805,43.863041],"type":"Point"}
}