{
  "type": "Feature",
  "properties": {
    "iso:country":"US",
    "sg:address":"613 Abbott St Ste 300",
    "sg:city":"Detroit",
    "sg:classifiers":[
        {
            "category":"Building & Trades",
            "subcategory":"Construction",
            "type":"Services"
        }
    ],
    "sg:phone":"+1 313 963 8000",
    "sg:postcode":"48226",
    "sg:province":"MI",
    "sg:tags":[
        "contractor"
    ],
    "wof:name":"Belding Walbridge Llc",
    "wof:placetype":"venue"
},
  "geometry": {"coordinates":[-83.055099,42.3307],"type":"Point"}
}