{
  "type": "Feature",
  "properties": {
    "iso:country":"US",
    "sg:address":"30440 Estate Ct",
    "sg:city":"New Hudson",
    "sg:classifiers":[
        {
            "category":"Professional",
            "subcategory":"Business Services",
            "type":"Services"
        }
    ],
    "sg:phone":"+1 248 446 1464",
    "sg:postcode":"48165",
    "sg:province":"MI",
    "wof:name":"Eland Design",
    "wof:placetype":"venue"
},
  "geometry": {"coordinates":[-83.593296,42.514607],"type":"Point"}
}