{
  "type": "Feature",
  "properties": {
    "iso:country":"US",
    "sg:address":"113 E 3rd St",
    "sg:city":"Imlay City",
    "sg:classifiers":[
        {
            "category":"Shopping",
            "subcategory":"Crafts & Fabrics",
            "type":"Retail Goods"
        }
    ],
    "sg:phone":"+1 810 724 7065",
    "sg:postcode":"48444",
    "sg:province":"MI",
    "sg:tags":[
        "shop"
    ],
    "wof:name":"Pincushion",
    "wof:placetype":"venue"
},
  "geometry": {"coordinates":[-83.077251,43.024495],"type":"Point"}
}