{
  "type": "Feature",
  "properties": {
    "iso:country":"US",
    "sg:address":"10210 Chalmers St",
    "sg:city":"Detroit",
    "sg:classifiers":[
        {
            "category":"Retail",
            "subcategory":"Auto Repair",
            "type":"Services"
        }
    ],
    "sg:phone":"+1 313 839 4020",
    "sg:postcode":"48213",
    "sg:province":"MI",
    "wof:name":"Motor City Brake & Auto Repair",
    "wof:placetype":"venue"
},
  "geometry": {"coordinates":[-82.970388,42.414235],"type":"Point"}
}