{
  "type": "Feature",
  "properties": {
    "iso:country":"US",
    "sg:address":"421 S Haven St",
    "sg:city":"South Haven",
    "sg:classifiers":[
        {
            "category":"Organizations",
            "subcategory":"Non-profit Organization",
            "type":"Services"
        }
    ],
    "sg:phone":"+1 269 637 3284",
    "sg:postcode":"49090",
    "sg:province":"MI",
    "sg:tags":[
        "information",
        "alcoholism",
        "treatment"
    ],
    "wof:name":"Alcoholics Anonymous & Al-Anon",
    "wof:placetype":"venue"
},
  "geometry": {"coordinates":[-86.275504,42.396522],"type":"Point"}
}