{
  "type": "Feature",
  "properties": {
    "iso:country":"US",
    "sg:address":"6558 S Custer Rd",
    "sg:city":"Custer",
    "sg:classifiers":[
        {
            "category":"Farming",
            "subcategory":"Livestock Farm",
            "type":"Manufacturing & Wholesale Goods"
        }
    ],
    "sg:phone":"+1 231 757 2096",
    "sg:postcode":"49405",
    "sg:province":"MI",
    "sg:tags":[
        "hog",
        "or",
        "feedlot"
    ],
    "wof:name":"Alan J Oomen",
    "wof:placetype":"venue"
},
  "geometry": {"coordinates":[-86.218279,43.836341],"type":"Point"}
}