{
  "type": "Feature",
  "properties": {
    "iso:country":"US",
    "sg:address":"111 N Brownson Ave",
    "sg:city":"Kingsley",
    "sg:classifiers":[
        {
            "category":"Banks & Credit Unions",
            "subcategory":"Bank",
            "type":"Services"
        }
    ],
    "sg:phone":"+1 231 263 5263",
    "sg:postcode":"49649",
    "sg:province":"MI",
    "wof:name":"Northwestern Bank",
    "wof:placetype":"venue"
},
  "geometry": {"coordinates":[-85.53618,44.587361],"type":"Point"}
}