{
  "type": "Feature",
  "properties": {
    "iso:country":"US",
    "sg:address":"31415 Hartford Dr",
    "sg:city":"Warren",
    "sg:classifiers":[
        {
            "category":"Shopping",
            "subcategory":"Florist",
            "type":"Retail Goods"
        }
    ],
    "sg:phone":"+1 586 294 0116",
    "sg:postcode":"48088",
    "sg:province":"MI",
    "wof:name":"J Blooming",
    "wof:placetype":"venue"
},
  "geometry": {"coordinates":[-82.97695,42.524137],"type":"Point"}
}