{
  "type": "Feature",
  "properties": {
    "iso:country":"US",
    "sg:address":"8095 Park Pl",
    "sg:city":"Brighton",
    "sg:classifiers":[
        {
            "category":"Building & Trades",
            "subcategory":"Construction",
            "type":"Services"
        }
    ],
    "sg:phone":"+1 248 446 8281",
    "sg:postcode":"48116",
    "sg:province":"MI",
    "sg:tags":[
        "control",
        "erosion"
    ],
    "wof:name":"JV1 Construction Svc",
    "wof:placetype":"venue"
},
  "geometry": {"coordinates":[-83.690518,42.485422],"type":"Point"}
}