{
  "type": "Feature",
  "properties": {
    "iso:country":"US",
    "sg:address":"4885 Chalet Dr",
    "sg:city":"Metamora",
    "sg:classifiers":[
        {
            "category":"Building & Trades",
            "subcategory":"Construction",
            "type":"Services"
        }
    ],
    "sg:phone":"+1 810 796 3853",
    "sg:postcode":"48455",
    "sg:province":"MI",
    "sg:tags":[
        "general",
        "contractor"
    ],
    "wof:name":"Mackco Construction",
    "wof:placetype":"venue"
},
  "geometry": {"coordinates":[-83.195916,42.921823],"type":"Point"}
}