{
  "type": "Feature",
  "properties": {
    "iso:country":"US",
    "sg:address":"401 Timberline Dr",
    "sg:city":"Rochester",
    "sg:classifiers":[
        {
            "category":"Professional",
            "subcategory":"Secretarial Services",
            "type":"Services"
        }
    ],
    "sg:phone":"+1 248 375 0064",
    "sg:postcode":"48309",
    "sg:province":"MI",
    "sg:tags":[
        "reporting"
    ],
    "wof:name":"Compu-Scribe",
    "wof:placetype":"venue"
},
  "geometry": {"coordinates":[-83.189436,42.687523],"type":"Point"}
}