{
  "type": "Feature",
  "properties": {
    "iso:country":"US",
    "sg:address":"102 Oswald St",
    "sg:city":"Crystal Falls",
    "sg:classifiers":[
        {
            "category":"Retail",
            "subcategory":"Repair Shop",
            "type":"Services"
        }
    ],
    "sg:phone":"+1 906 875 4659",
    "sg:postcode":"49920",
    "sg:province":"MI",
    "sg:tags":[
        "taxidermist"
    ],
    "wof:name":"Northern Star Taxidermy",
    "wof:placetype":"venue"
},
  "geometry": {"coordinates":[-88.34837,46.097698],"type":"Point"}
}