{
  "type": "Feature",
  "properties": {
    "iso:country":"US",
    "sg:address":"2200 Berkley Ave",
    "sg:city":"Berkley",
    "sg:classifiers":[
        {
            "category":"Building & Trades",
            "subcategory":"Construction",
            "type":"Services"
        }
    ],
    "sg:phone":"+1 248 541 7177",
    "sg:postcode":"48072",
    "sg:province":"MI",
    "sg:tags":[
        "paving",
        "contractor"
    ],
    "wof:name":"Prestige Pavers Inc",
    "wof:placetype":"venue"
},
  "geometry": {"coordinates":[-83.18113700000001,42.493541],"type":"Point"}
}