{
  "type": "Feature",
  "properties": {
    "iso:country":"US",
    "sg:address":"2675 E Paris Ave SE",
    "sg:city":"Grand Rapids",
    "sg:classifiers":[
        {
            "category":"Wholesale",
            "subcategory":"Groceries",
            "type":"Manufacturing & Wholesale Goods"
        }
    ],
    "sg:phone":"+1 616 464 1361",
    "sg:postcode":"49546",
    "sg:province":"MI",
    "sg:tags":[
        "baker"
    ],
    "wof:name":"Sconery",
    "wof:placetype":"venue"
},
  "geometry": {"coordinates":[-85.568871,42.914811],"type":"Point"}
}