{
  "type": "Feature",
  "properties": {
    "iso:country":"US",
    "sg:address":"35300 Spring Hill Rd",
    "sg:city":"Farmington",
    "sg:classifiers":[
        {
            "category":"Professional",
            "subcategory":"Lawyer & Legal Services",
            "type":"Services"
        }
    ],
    "sg:phone":"+1 248 661 1050",
    "sg:postcode":"48331",
    "sg:province":"MI",
    "wof:name":"Alan M Vosko PC",
    "wof:placetype":"venue"
},
  "geometry": {"coordinates":[-83.39681299999999,42.521342],"type":"Point"}
}