{
  "type": "Feature",
  "properties": {
    "iso:country":"US",
    "sg:address":"15206 Beech Daly Rd",
    "sg:city":"Redford",
    "sg:classifiers":[
        {
            "category":"Retail",
            "subcategory":"Auto Repair",
            "type":"Services"
        }
    ],
    "sg:phone":"+1 313 535 5387",
    "sg:postcode":"48239",
    "sg:province":"MI",
    "wof:name":"Township Auto Clinic",
    "wof:placetype":"venue"
},
  "geometry": {"coordinates":[-83.2957,42.398899],"type":"Point"}
}