{
  "type": "Feature",
  "properties": {
    "iso:country":"US",
    "sg:address":"29814 Newbury Ct",
    "sg:city":"Farmington",
    "sg:classifiers":[
        {
            "category":"Restaurant",
            "type":"Food & Drink"
        }
    ],
    "sg:phone":"+1 248 592 0671",
    "sg:postcode":"48331",
    "sg:province":"MI",
    "sg:tags":[
        "eating"
    ],
    "wof:name":"FM Dish",
    "wof:placetype":"venue"
},
  "geometry": {"coordinates":[-83.42598700000001,42.513126],"type":"Point"}
}