{
  "type": "Feature",
  "properties": {
    "iso:country":"US",
    "sg:address":"4002 S Dort Hwy",
    "sg:city":"Flint",
    "sg:classifiers":[
        {
            "category":"Shopping",
            "subcategory":"Discount & Variety Stores",
            "type":"Retail Goods"
        }
    ],
    "sg:phone":"+1 810 715 1570",
    "sg:postcode":"48507",
    "sg:province":"MI",
    "wof:name":"Mazel's",
    "wof:placetype":"venue"
},
  "geometry": {"coordinates":[-83.653414,42.989162],"type":"Point"}
}