{
  "type": "Feature",
  "properties": {
    "iso:country":"US",
    "sg:address":"4829 Fenton Rd",
    "sg:city":"Flint",
    "sg:classifiers":[
        {
            "category":"Building & Trades",
            "subcategory":"Equipment Rental",
            "type":"Services"
        }
    ],
    "sg:phone":"+1 810 238 3640",
    "sg:postcode":"48529",
    "sg:province":"MI",
    "sg:tags":[
        "yard"
    ],
    "wof:name":"Rent-A-Center",
    "wof:placetype":"venue"
},
  "geometry": {"coordinates":[-83.69259,42.961678],"type":"Point"}
}