{
  "type": "Feature",
  "properties": {
    "iso:country":"US",
    "sg:address":"8767 Gratiot Rd",
    "sg:city":"Saginaw",
    "sg:classifiers":[
        {
            "category":"Health Services",
            "subcategory":"Medical Lab",
            "type":"Services"
        }
    ],
    "sg:phone":"+1 989 781 5148",
    "sg:postcode":"48609",
    "sg:province":"MI",
    "sg:tags":[
        "laboratory"
    ],
    "wof:name":"Covenant Healthcare",
    "wof:placetype":"venue"
},
  "geometry": {"coordinates":[-84.08609,43.415989],"type":"Point"}
}