{
  "type": "Feature",
  "properties": {
    "iso:country":"US",
    "sg:address":"4721 E Beltline Ave NE",
    "sg:city":"Grand Rapids",
    "sg:classifiers":[
        {
            "category":"Wholesale",
            "subcategory":"Non-durable Goods",
            "type":"Manufacturing & Wholesale Goods"
        }
    ],
    "sg:phone":"+1 616 361 9777",
    "sg:postcode":"49525",
    "sg:province":"MI",
    "sg:tags":[
        "advertising"
    ],
    "sg:website":"www.conceptmarketinggroup.com",
    "wof:name":"Concept Marketing Group LTD",
    "wof:placetype":"venue"
},
  "geometry": {"coordinates":[-85.58122899999999,43.050819],"type":"Point"}
}