{
  "type": "Feature",
  "properties": {
    "iso:country":"US",
    "sg:address":"8457 Andersonville Rd",
    "sg:city":"Clarkston",
    "sg:classifiers":[
        {
            "category":"Retail",
            "subcategory":"Car Wash",
            "type":"Services"
        }
    ],
    "sg:phone":"+1 248 922 1433",
    "sg:postcode":"48346",
    "sg:province":"MI",
    "sg:tags":[
        "carwash"
    ],
    "wof:name":"Power Bright Inc",
    "wof:placetype":"venue"
},
  "geometry": {"coordinates":[-83.452303,42.703711],"type":"Point"}
}