{
  "type": "Feature",
  "properties": {
    "iso:country":"US",
    "sg:address":"3520 Gembrit Cir",
    "sg:city":"Kalamazoo",
    "sg:classifiers":[
        {
            "category":"Wholesale",
            "subcategory":"Machinery & Supplies",
            "type":"Manufacturing & Wholesale Goods"
        }
    ],
    "sg:phone":"+1 269 349 9616",
    "sg:postcode":"49001",
    "sg:province":"MI",
    "sg:tags":[
        "bearing"
    ],
    "sg:website":"www.appliedindustrial.com",
    "wof:name":"Applied Industrial Tech Inc",
    "wof:placetype":"venue"
},
  "geometry": {"coordinates":[-85.538025,42.25644],"type":"Point"}
}