{
  "type": "Feature",
  "properties": {
    "iso:country":"US",
    "sg:address":"3358 Bacon Ave",
    "sg:city":"Berkley",
    "sg:classifiers":[
        {
            "category":"Retail",
            "subcategory":"Photofinishing",
            "type":"Services"
        }
    ],
    "sg:phone":"+1 248 545 2565",
    "sg:postcode":"48072",
    "sg:province":"MI",
    "sg:tags":[
        "laboratory"
    ],
    "wof:name":"Thomas McTeers Photo Effects",
    "wof:placetype":"venue"
},
  "geometry": {"coordinates":[-83.19823700000001,42.50149],"type":"Point"}
}