{
  "type": "Feature",
  "properties": {
    "iso:country":"US",
    "sg:address":"2985 Auburn Rd",
    "sg:city":"Shelby Twp",
    "sg:classifiers":[
        {
            "category":"Recreation",
            "type":"Entertainment"
        }
    ],
    "sg:phone":"+1 586 739 6267",
    "sg:postcode":"48317",
    "sg:province":"MI",
    "sg:tags":[
        "club",
        "membership",
        "amusement"
    ],
    "sg:website":"www.shelbysoccer.com",
    "wof:name":"Shelby Soccer City Inc",
    "wof:placetype":"venue"
},
  "geometry": {"coordinates":[-83.08440400000001,42.638864],"type":"Point"}
}