{
  "type": "Feature",
  "properties": {
    "iso:country":"US",
    "sg:address":"33 Franklin St",
    "sg:city":"Grand Haven",
    "sg:classifiers":[
        {
            "category":"Retail",
            "subcategory":"Laundry & Dry Cleaning",
            "type":"Services"
        }
    ],
    "sg:phone":"+1 616 842 6950",
    "sg:postcode":"49417",
    "sg:province":"MI",
    "sg:tags":[
        "cleaners"
    ],
    "wof:name":"Plantenga's Cleaners",
    "wof:placetype":"venue"
},
  "geometry": {"coordinates":[-86.233442,43.063817],"type":"Point"}
}