{
  "type": "Feature",
  "properties": {
    "iso:country":"US",
    "sg:address":"6926 Wyoming St",
    "sg:city":"Dearborn",
    "sg:classifiers":[
        {
            "category":"Shopping",
            "subcategory":"Bicycles & Sporting Goods",
            "type":"Retail Goods"
        }
    ],
    "sg:phone":"+1 313 581 8818",
    "sg:postcode":"48126",
    "sg:province":"MI",
    "sg:tags":[
        "bike"
    ],
    "wof:name":"Eddie's Bike Shop",
    "wof:placetype":"venue"
},
  "geometry": {"coordinates":[-83.156983,42.342186],"type":"Point"}
}