{
  "type": "Feature",
  "properties": {
    "iso:country":"US",
    "sg:address":"1000 Ball Ave NE",
    "sg:city":"Grand Rapids",
    "sg:classifiers":[
        {
            "category":"Education",
            "subcategory":"School",
            "type":"Public Place"
        }
    ],
    "sg:phone":"+1 616 458 4367",
    "sg:postcode":"49505",
    "sg:province":"MI",
    "wof:name":"Plymouth Christian Elementary",
    "wof:placetype":"venue"
},
  "geometry": {"coordinates":[-85.63004599999999,42.982534],"type":"Point"}
}