{
  "type": "Feature",
  "properties": {
    "iso:country":"US",
    "sg:address":"3061 Christy Way",
    "sg:city":"Saginaw",
    "sg:classifiers":[
        {
            "category":"Health Services",
            "subcategory":"Doctor",
            "type":"Services"
        }
    ],
    "sg:phone":"+1 989 792 4901",
    "sg:postcode":"48603",
    "sg:province":"MI",
    "sg:tags":[
        "medical"
    ],
    "wof:name":"Mc Intyre Floyd J",
    "wof:placetype":"venue"
},
  "geometry": {"coordinates":[-83.976416,43.459696],"type":"Point"}
}