{
  "type": "Feature",
  "properties": {
    "iso:country":"US",
    "sg:address":"603 E Chicago Rd",
    "sg:city":"Coldwater",
    "sg:classifiers":[
        {
            "category":"Organizations",
            "subcategory":"Religious Organization",
            "type":"Services"
        }
    ],
    "sg:phone":"+1 517 278 8078",
    "sg:postcode":"49036",
    "sg:province":"MI",
    "sg:website":"www.worldharvestassembly.org",
    "wof:name":"World Harvest Assembly",
    "wof:placetype":"venue"
},
  "geometry": {"coordinates":[-84.961501,41.934284],"type":"Point"}
}