{
  "type": "Feature",
  "properties": {
    "iso:country":"US",
    "sg:address":"378 Hunters Rill",
    "sg:city":"Oxford",
    "sg:classifiers":[
        {
            "category":"Building & Trades",
            "subcategory":"Construction",
            "type":"Services"
        }
    ],
    "sg:phone":"+1 248 693 0488",
    "sg:postcode":"48371",
    "sg:province":"MI",
    "sg:tags":[
        "house"
    ],
    "wof:name":"Exterior Visual Improvement",
    "wof:placetype":"venue"
},
  "geometry": {"coordinates":[-83.228122,42.822271],"type":"Point"}
}