{
  "type": "Feature",
  "properties": {
    "iso:country":"US",
    "sg:address":"4749 Bay Rd",
    "sg:city":"Saginaw",
    "sg:classifiers":[
        {
            "category":"Shopping",
            "subcategory":"Clothing, Apparel, & Fashions",
            "type":"Retail Goods"
        }
    ],
    "sg:phone":"+1 989 793 4088",
    "sg:postcode":"48604",
    "sg:province":"MI",
    "wof:name":"Talbots",
    "wof:placetype":"venue"
},
  "geometry": {"coordinates":[-83.97556299999999,43.476213],"type":"Point"}
}