{
  "type": "Feature",
  "properties": {
    "iso:country":"US",
    "sg:address":"47852 Thistle Dr",
    "sg:city":"Macomb",
    "sg:classifiers":[
        {
            "category":"Professional",
            "subcategory":"Business Services",
            "type":"Services"
        }
    ],
    "sg:phone":"+1 586 598 3703",
    "sg:postcode":"48044",
    "sg:province":"MI",
    "wof:name":"McCoy Enterprises",
    "wof:placetype":"venue"
},
  "geometry": {"coordinates":[-82.91474700000001,42.649792],"type":"Point"}
}