{
  "type": "Feature",
  "properties": {
    "iso:country":"US",
    "sg:address":"611 S Waverly Rd",
    "sg:city":"Lansing",
    "sg:classifiers":[
        {
            "category":"Restaurant",
            "type":"Food & Drink"
        }
    ],
    "sg:menulink":"http://www.allmenus.com/mi/lansing/249813-spuds-family-restaurant/menu/",
    "sg:phone":"+1 517 321 4840",
    "sg:postcode":"48917",
    "sg:province":"MI",
    "sg:tags":[
        "american",
        "diner"
    ],
    "wof:name":"Spud's Family Restaurant",
    "wof:placetype":"venue"
},
  "geometry": {"coordinates":[-84.602985,42.727724],"type":"Point"}
}