{
  "type": "Feature",
  "properties": {
    "iso:country":"US",
    "sg:address":"14536 E Michigan Ave",
    "sg:city":"Galesburg",
    "sg:classifiers":[
        {
            "category":"Building & Trades",
            "subcategory":"Construction",
            "type":"Services"
        }
    ],
    "sg:phone":"+1 269 746 5771",
    "sg:postcode":"49053",
    "sg:province":"MI",
    "sg:tags":[
        "product",
        "asphalt"
    ],
    "sg:website":"www.thompsonmccully.com",
    "wof:name":"Globe Paving Co-Battle Creek",
    "wof:placetype":"venue"
},
  "geometry": {"coordinates":[-85.33902500000001,42.280213],"type":"Point"}
}