{
  "type": "Feature",
  "properties": {
    "iso:country":"US",
    "sg:address":"11962 Conquest St",
    "sg:city":"Birch Run",
    "sg:classifiers":[
        {
            "category":"Banks & Credit Unions",
            "subcategory":"Bank",
            "type":"Services"
        }
    ],
    "sg:phone":"+1 989 624 9344",
    "sg:postcode":"48415",
    "sg:province":"MI",
    "wof:name":"Credit Union Plus",
    "wof:placetype":"venue"
},
  "geometry": {"coordinates":[-83.79297099999999,43.250972],"type":"Point"}
}