{
  "type": "Feature",
  "properties": {
    "iso:country":"US",
    "sg:address":"1254 N Main St",
    "sg:city":"Lapeer",
    "sg:classifiers":[
        {
            "category":"Personal",
            "type":"Services"
        }
    ],
    "sg:phone":"+1 810 664 7070",
    "sg:postcode":"48446",
    "sg:province":"MI",
    "wof:name":"Mc Learn Weight Management Ctr",
    "wof:placetype":"venue"
},
  "geometry": {"coordinates":[-83.31917799999999,43.061344],"type":"Point"}
}