{
  "type": "Feature",
  "properties": {
    "iso:country":"US",
    "sg:address":"4975 Lakeshore Rd",
    "sg:city":"Fort Gratiot",
    "sg:classifiers":[
        {
            "category":"Building & Trades",
            "subcategory":"Cleaning & Sanitation",
            "type":"Services"
        }
    ],
    "sg:phone":"+1 810 385 9635",
    "sg:postcode":"48059",
    "sg:province":"MI",
    "sg:tags":[
        "janitorial"
    ],
    "wof:name":"Karl Express Cleaning",
    "wof:placetype":"venue"
},
  "geometry": {"coordinates":[-82.45292499999999,43.049255],"type":"Point"}
}