{
  "type": "Feature",
  "properties": {
    "iso:country":"US",
    "sg:address":"46645 W Ann Arbor Trl",
    "sg:city":"Plymouth",
    "sg:classifiers":[
        {
            "category":"Building & Trades",
            "subcategory":"Landscaping Services",
            "type":"Services"
        }
    ],
    "sg:phone":"+1 734 459 1640",
    "sg:postcode":"48170",
    "sg:province":"MI",
    "wof:name":"Green Giant Landscaping",
    "wof:placetype":"venue"
},
  "geometry": {"coordinates":[-83.503118,42.365373],"type":"Point"}
}