{
  "type": "Feature",
  "properties": {
    "iso:country":"US",
    "sg:address":"22042 York Mills Cir",
    "sg:city":"Novi",
    "sg:classifiers":[
        {
            "category":"Professional",
            "subcategory":"Business Services",
            "type":"Services"
        }
    ],
    "sg:phone":"+1 248 380 8687",
    "sg:postcode":"48374",
    "sg:province":"MI",
    "wof:name":"Senior Est Planning Group",
    "wof:placetype":"venue"
},
  "geometry": {"coordinates":[-83.50772000000001,42.44685],"type":"Point"}
}