{
  "type": "Feature",
  "properties": {
    "iso:country":"US",
    "sg:address":"1 Grand River Ave",
    "sg:city":"Detroit",
    "sg:classifiers":[
        {
            "category":"Communications",
            "subcategory":"Newspaper",
            "type":"Services"
        }
    ],
    "sg:phone":"+1 313 222 2300",
    "sg:postcode":"48226",
    "sg:province":"MI",
    "wof:name":"Detroit News",
    "wof:placetype":"venue"
},
  "geometry": {"coordinates":[-83.048737,42.334099],"type":"Point"}
}