{
  "type": "Feature",
  "properties": {
    "iso:country":"US",
    "sg:address":"7991 E Breitung Ave",
    "sg:city":"Iron Mountain",
    "sg:classifiers":[
        {
            "category":"Organizations",
            "subcategory":"Community Association",
            "type":"Services"
        }
    ],
    "sg:phone":"+1 906 779 5980",
    "sg:postcode":"49801",
    "sg:province":"MI",
    "sg:tags":[
        "club"
    ],
    "wof:name":"Northland Beagle",
    "wof:placetype":"venue"
},
  "geometry": {"coordinates":[-88.032072,45.802279],"type":"Point"}
}