{
  "type": "Feature",
  "properties": {
    "iso:country":"US",
    "sg:address":"536 S Rose St",
    "sg:city":"Kalamazoo",
    "sg:classifiers":[
        {
            "category":"Building & Trades",
            "subcategory":"Construction",
            "type":"Services"
        }
    ],
    "sg:phone":"+1 269 384 0204",
    "sg:postcode":"49007",
    "sg:province":"MI",
    "sg:tags":[
        "contractor"
    ],
    "wof:name":"Bryans Drywall Construction I",
    "wof:placetype":"venue"
},
  "geometry": {"coordinates":[-85.584757,42.287298],"type":"Point"}
}