{
  "type": "Feature",
  "properties": {
    "iso:country":"US",
    "sg:address":"5832 N Branch Rd",
    "sg:city":"North Branch",
    "sg:classifiers":[
        {
            "category":"Insurance",
            "subcategory":"Insurance Agent",
            "type":"Services"
        }
    ],
    "sg:phone":"+1 810 793 6666",
    "sg:postcode":"48461",
    "sg:province":"MI",
    "wof:name":"Donald W Mc Connell Insurance",
    "wof:placetype":"venue"
},
  "geometry": {"coordinates":[-83.120563,43.231163],"type":"Point"}
}