{
  "type": "Feature",
  "properties": {
    "iso:country":"US",
    "sg:address":"228 Hill St",
    "sg:city":"Milford",
    "sg:classifiers":[
        {
            "category":"Building & Trades",
            "subcategory":"Landscaping Services",
            "type":"Services"
        }
    ],
    "sg:phone":"+1 248 676 8189",
    "sg:postcode":"48381",
    "sg:province":"MI",
    "wof:name":"Lawn Works",
    "wof:placetype":"venue"
},
  "geometry": {"coordinates":[-83.58665499999999,42.59327],"type":"Point"}
}