{
  "type": "Feature",
  "properties": {
    "iso:country":"US",
    "sg:address":"342 Conner St",
    "sg:city":"Onsted",
    "sg:classifiers":[
        {
            "category":"Building & Trades",
            "subcategory":"Cleaning & Sanitation",
            "type":"Services"
        }
    ],
    "sg:phone":"+1 517 467 7411",
    "sg:postcode":"49265",
    "sg:province":"MI",
    "sg:tags":[
        "maintenance"
    ],
    "wof:name":"Greens White Glove Cleaning S",
    "wof:placetype":"venue"
},
  "geometry": {"coordinates":[-84.18840299999999,42.010867],"type":"Point"}
}