{
  "type": "Feature",
  "properties": {
    "iso:country":"US",
    "sg:address":"3845 W 8 Mile Rd",
    "sg:city":"Detroit",
    "sg:classifiers":[
        {
            "category":"Real Estate",
            "subcategory":"Real Estate Services",
            "type":"Services"
        },
        {
            "category":"Real Estate",
            "subcategory":"Real Estate Agent",
            "type":"Services"
        }
    ],
    "sg:phone":"+1 313 340 0600",
    "sg:postcode":"48221",
    "sg:province":"MI",
    "sg:tags":[
        "buyer",
        "management",
        "broker"
    ],
    "sg:website":"http://www.lynnstange.com",
    "wof:name":"Jack Christenson Realtors",
    "wof:placetype":"venue"
},
  "geometry": {"coordinates":[-83.138188,42.44617],"type":"Point"}
}