{
  "type": "Feature",
  "properties": {
    "iso:country":"US",
    "sg:address":"1210 W Saginaw St",
    "sg:city":"Lansing",
    "sg:classifiers":[
        {
            "category":"Health Services",
            "subcategory":"Hospital",
            "type":"Services"
        }
    ],
    "sg:phone":"+1 517 364 7600",
    "sg:postcode":"48915",
    "sg:province":"MI",
    "sg:tags":[
        "mental"
    ],
    "wof:name":"Mental Health Ctr",
    "wof:placetype":"venue"
},
  "geometry": {"coordinates":[-84.570042,42.741066],"type":"Point"}
}