{
  "type": "Feature",
  "properties": {
    "iso:country":"US",
    "sg:address":"311 Harbor Ave",
    "sg:city":"Monroe",
    "sg:classifiers":[
        {
            "category":"Professional",
            "subcategory":"Accounting & Tax Preparation",
            "type":"Services"
        }
    ],
    "sg:phone":"+1 734 242 1763",
    "sg:postcode":"48162",
    "sg:province":"MI",
    "wof:name":"P & L Accounting",
    "wof:placetype":"venue"
},
  "geometry": {"coordinates":[-83.37270700000001,41.917404],"type":"Point"}
}