{
  "type": "Feature",
  "properties": {
    "iso:country":"US",
    "sg:address":"5831 Wayne Rd",
    "sg:city":"Romulus",
    "sg:classifiers":[
        {
            "category":"Professional",
            "subcategory":"Business Services",
            "type":"Services"
        }
    ],
    "sg:phone":"+1 734 728 5480",
    "sg:postcode":"48174",
    "sg:province":"MI",
    "wof:name":"Delbert Slabaugh Enterprises",
    "wof:placetype":"venue"
},
  "geometry": {"coordinates":[-83.389043,42.265316],"type":"Point"}
}