{
  "type": "Feature",
  "properties": {
    "iso:country":"US",
    "sg:address":"11313 Hill Rd",
    "sg:city":"Goodrich",
    "sg:classifiers":[
        {
            "category":"Building & Trades",
            "subcategory":"Cleaning & Sanitation",
            "type":"Services"
        }
    ],
    "sg:phone":"+1 810 636 7393",
    "sg:postcode":"48438",
    "sg:province":"MI",
    "sg:tags":[
        "janitor",
        "janitorial"
    ],
    "wof:name":"Crystal K Janitorial Service",
    "wof:placetype":"venue"
},
  "geometry": {"coordinates":[-83.485541,42.947565],"type":"Point"}
}