{
  "type": "Feature",
  "properties": {
    "iso:country":"US",
    "sg:address":"15079 Kerstyn St",
    "sg:city":"Taylor",
    "sg:classifiers":[
        {
            "category":"Arts & Performance",
            "subcategory":"Theater",
            "type":"Entertainment"
        }
    ],
    "sg:phone":"+1 734 942 2787",
    "sg:postcode":"48180",
    "sg:province":"MI",
    "sg:tags":[
        "group"
    ],
    "wof:name":"Redbeard",
    "wof:placetype":"venue"
},
  "geometry": {"coordinates":[-83.302211,42.193864],"type":"Point"}
}