{
  "type": "Feature",
  "properties": {
    "iso:country":"US",
    "sg:address":"711 Bayliss St",
    "sg:city":"Midland",
    "sg:classifiers":[
        {
            "category":"Professional",
            "subcategory":"Lawyer & Legal Services",
            "type":"Services"
        }
    ],
    "sg:phone":"+1 989 837 2688",
    "sg:postcode":"48640",
    "sg:province":"MI",
    "sg:tags":[
        "attorney"
    ],
    "wof:name":"Jack Pulley Law Office",
    "wof:placetype":"venue"
},
  "geometry": {"coordinates":[-84.22309799999999,43.621253],"type":"Point"}
}