{
  "type": "Feature",
  "properties": {
    "iso:country":"US",
    "sg:address":"6812 Old 28th St SE",
    "sg:city":"Grand Rapids",
    "sg:classifiers":[
        {
            "category":"Professional",
            "subcategory":"Management & Consulting",
            "type":"Services"
        }
    ],
    "sg:phone":"+1 616 464 3602",
    "sg:postcode":"49546",
    "sg:province":"MI",
    "sg:tags":[
        "consultant",
        "business"
    ],
    "wof:name":"Corlett & Dittmer LLC",
    "wof:placetype":"venue"
},
  "geometry": {"coordinates":[-85.500236,42.913176],"type":"Point"}
}