{
  "type": "Feature",
  "properties": {
    "iso:country":"US",
    "sg:address":"3149 Dean Rd",
    "sg:city":"Erie",
    "sg:classifiers":[
        {
            "category":"Recreation",
            "type":"Entertainment"
        },
        {
            "category":"Organizations",
            "subcategory":"Community Association",
            "type":"Services"
        }
    ],
    "sg:phone":"+1 734 848 3725",
    "sg:postcode":"48133",
    "sg:province":"MI",
    "sg:tags":[
        "club",
        "membership"
    ],
    "wof:name":"Erie Shooting & Fishing Club",
    "wof:placetype":"venue"
},
  "geometry": {"coordinates":[-83.476547,41.765077],"type":"Point"}
}