{
  "type": "Feature",
  "properties": {
    "iso:country":"US",
    "sg:address":"1034 Sherbrooke St",
    "sg:city":"Commerce Township",
    "sg:classifiers":[
        {
            "category":"Professional",
            "subcategory":"Business Services",
            "type":"Services"
        }
    ],
    "sg:phone":"+1 248 363 6811",
    "sg:postcode":"48382",
    "sg:province":"MI",
    "sg:tags":[
        "notary",
        "republic"
    ],
    "wof:name":"Randolph G Ston",
    "wof:placetype":"venue"
},
  "geometry": {"coordinates":[-83.489456,42.587892],"type":"Point"}
}