{
  "type": "Feature",
  "properties": {
    "iso:country":"US",
    "sg:address":"8225 Wennie Dr",
    "sg:city":"Mancelona",
    "sg:classifiers":[
        {
            "category":"Real Estate",
            "subcategory":"Architect",
            "type":"Services"
        }
    ],
    "sg:phone":"+1 231 587 9706",
    "sg:postcode":"49659",
    "sg:province":"MI",
    "wof:name":"Slick Tubes Co",
    "wof:placetype":"venue"
},
  "geometry": {"coordinates":[-84.954596,44.836719],"type":"Point"}
}