{
  "type": "Feature",
  "properties": {
    "iso:country":"US",
    "sg:address":"3757 Maiden St",
    "sg:city":"Waterford",
    "sg:classifiers":[
        {
            "category":"Building & Trades",
            "subcategory":"Landscaping Services",
            "type":"Services"
        }
    ],
    "sg:phone":"+1 248 623 0882",
    "sg:postcode":"48329",
    "sg:province":"MI",
    "wof:name":"Sommer Tree & Landscaping",
    "wof:placetype":"venue"
},
  "geometry": {"coordinates":[-83.438823,42.692005],"type":"Point"}
}