{
  "type": "Feature",
  "properties": {
    "iso:country":"US",
    "sg:address":"1921 Dorothea Rd",
    "sg:city":"Berkley",
    "sg:classifiers":[
        {
            "category":"Professional",
            "type":"Services"
        }
    ],
    "sg:phone":"+1 248 547 0202",
    "sg:postcode":"48072",
    "sg:province":"MI",
    "sg:tags":[
        "establishment"
    ],
    "wof:name":"Shamus Television Inc",
    "wof:placetype":"venue"
},
  "geometry": {"coordinates":[-83.177621,42.497126],"type":"Point"}
}