{
  "type": "Feature",
  "properties": {
    "iso:country":"US",
    "sg:address":"19473 Farmington Rd",
    "sg:city":"Livonia",
    "sg:classifiers":[
        {
            "category":"Banks & Credit Unions",
            "subcategory":"Financial Services",
            "type":"Services"
        }
    ],
    "sg:phone":"+1 248 306 6133",
    "sg:postcode":"48152",
    "sg:province":"MI",
    "sg:tags":[
        "broker",
        "mortgage"
    ],
    "wof:name":"Garley & Association",
    "wof:placetype":"venue"
},
  "geometry": {"coordinates":[-83.375198,42.4296],"type":"Point"}
}