{
  "type": "Feature",
  "properties": {
    "iso:country":"US",
    "sg:address":"2264 Kenona Woods Dr",
    "sg:city":"Traverse City",
    "sg:classifiers":[
        {
            "category":"Professional",
            "subcategory":"Art Services",
            "type":"Services"
        }
    ],
    "sg:phone":"+1 231 941 5336",
    "sg:postcode":"49686",
    "sg:province":"MI",
    "sg:tags":[
        "graphic",
        "designer"
    ],
    "wof:name":"AGI Design",
    "wof:placetype":"venue"
},
  "geometry": {"coordinates":[-85.52714899999999,44.679544],"type":"Point"}
}