{
  "type": "Feature",
  "properties": {
    "iso:country":"US",
    "sg:address":"970 Ottawa Beach Rd",
    "sg:city":"Holland",
    "sg:classifiers":[
        {
            "category":"Professional",
            "type":"Services"
        }
    ],
    "sg:phone":"+1 616 738 8556",
    "sg:postcode":"49424",
    "sg:province":"MI",
    "sg:tags":[
        "establishment"
    ],
    "wof:name":"My Brother's House II",
    "wof:placetype":"venue"
},
  "geometry": {"coordinates":[-86.148788,42.796814],"type":"Point"}
}