{
  "type": "Feature",
  "properties": {
    "iso:country":"US",
    "sg:address":"39430 Dun Rovin Drive",
    "sg:city":"Northville",
    "sg:classifiers":[
        {
            "category":"Food & Beverages",
            "subcategory":"Meat & Fish",
            "type":"Retail Goods"
        }
    ],
    "sg:postcode":"48168",
    "sg:province":"MI",
    "sg:tags":[
        "hot",
        "dog"
    ],
    "sg:website":"www.georgessenateandconeyislandr...",
    "wof:name":"Senate Coney Island",
    "wof:placetype":"venue"
},
  "geometry": {"coordinates":[-83.441473,42.40581],"type":"Point"}
}