{
  "type": "Feature",
  "properties": {
    "iso:country":"US",
    "sg:address":"3029 Elms Rd",
    "sg:city":"Swartz Creek",
    "sg:classifiers":[
        {
            "category":"Freight",
            "type":"Transportation"
        }
    ],
    "sg:phone":"+1 810 635 8700",
    "sg:postcode":"48473",
    "sg:province":"MI",
    "sg:tags":[
        "commercial",
        "storage"
    ],
    "wof:name":"Elms Road Self Storage",
    "wof:placetype":"venue"
},
  "geometry": {"coordinates":[-83.811494,42.979307],"type":"Point"}
}