{
  "type": "Feature",
  "properties": {
    "iso:country":"US",
    "sg:address":"1264 S Tonkey Rd",
    "sg:city":"Au Gres",
    "sg:classifiers":[
        {
            "category":"Organizations",
            "subcategory":"Religious Organization",
            "type":"Services"
        }
    ],
    "sg:phone":"+1 989 876 7415",
    "sg:postcode":"48703",
    "sg:province":"MI",
    "sg:tags":[
        "church"
    ],
    "wof:name":"Saint Paul Lutheran Church",
    "wof:placetype":"venue"
},
  "geometry": {"coordinates":[-83.665881,44.052562],"type":"Point"}
}