{
  "type": "Feature",
  "properties": {
    "iso:country":"US",
    "sg:address":"560 19th St",
    "sg:city":"Otsego",
    "sg:classifiers":[
        {
            "category":"Building & Trades",
            "subcategory":"Construction",
            "type":"Services"
        }
    ],
    "sg:phone":"+1 269 694 9847",
    "sg:postcode":"49078",
    "sg:province":"MI",
    "sg:tags":[
        "boring",
        "drilling",
        "contractor"
    ],
    "wof:name":"Rex Well Drilling",
    "wof:placetype":"venue"
},
  "geometry": {"coordinates":[-85.735102,42.461112],"type":"Point"}
}