{
  "type": "Feature",
  "properties": {
    "iso:country":"US",
    "sg:address":"724 W Centre Ave",
    "sg:city":"Portage",
    "sg:classifiers":[
        {
            "category":"Organizations",
            "subcategory":"Community Association",
            "type":"Services"
        }
    ],
    "sg:phone":"+1 269 327 4008",
    "sg:postcode":"49024",
    "sg:province":"MI",
    "sg:tags":[
        "environmental",
        "org"
    ],
    "wof:name":"Kalamazoo River Watershed Cncl",
    "wof:placetype":"venue"
},
  "geometry": {"coordinates":[-85.597171,42.201047],"type":"Point"}
}