{
  "type": "Feature",
  "properties": {
    "iso:country":"US",
    "sg:address":"1324 W Milham Ave",
    "sg:city":"Portage",
    "sg:classifiers":[
        {
            "category":"Health Services",
            "subcategory":"Doctor",
            "type":"Services"
        }
    ],
    "sg:phone":"+1 269 342 0196",
    "sg:postcode":"49024",
    "sg:province":"MI",
    "sg:tags":[
        "physician",
        "pediatrics-emergency",
        "pediatrics",
        "pediatrics-allergy",
        "allergy",
        "surgeons",
        "treatment",
        "medicine",
        "immunology",
        "surgeon"
    ],
    "wof:name":"Dandamudi, Giri R",
    "wof:placetype":"venue"
},
  "geometry": {"coordinates":[-85.604904,42.230062],"type":"Point"}
}