{
  "type": "Feature",
  "properties": {
    "iso:country":"US",
    "sg:address":"15351 Hall Rd",
    "sg:city":"Macomb",
    "sg:classifiers":[
        {
            "category":"Shopping",
            "subcategory":"Discount & Variety Stores",
            "type":"Retail Goods"
        }
    ],
    "sg:phone":"+1 586 566 0892",
    "sg:postcode":"48044",
    "sg:province":"MI",
    "wof:name":"Dollar Circle",
    "wof:placetype":"venue"
},
  "geometry": {"coordinates":[-82.970952,42.627923],"type":"Point"}
}