{
  "type": "Feature",
  "properties": {
    "iso:country":"US",
    "sg:address":"5228 Lovers Ln",
    "sg:city":"Portage",
    "sg:classifiers":[
        {
            "category":"Shopping",
            "subcategory":"Computers & Home Electronics",
            "type":"Retail Goods"
        }
    ],
    "sg:phone":"+1 269 344 0116",
    "sg:postcode":"49002",
    "sg:province":"MI",
    "sg:tags":[
        "equipment",
        "dealer"
    ],
    "wof:name":"Unisys Corp",
    "wof:placetype":"venue"
},
  "geometry": {"coordinates":[-85.574868,42.240981],"type":"Point"}
}