{
  "type": "Feature",
  "properties": {
    "iso:country":"US",
    "sg:address":"5140 S Westnedge Ave",
    "sg:city":"Portage",
    "sg:classifiers":[
        {
            "category":"Restaurant",
            "type":"Food & Drink"
        }
    ],
    "sg:menulink":"http://www.allmenus.com/mi/portage/45107-papa-johns-pizza/menu/",
    "sg:phone":"+1 269 343 7272",
    "sg:postcode":"49002",
    "sg:province":"MI",
    "sg:tags":[
        "american",
        "pizza"
    ],
    "wof:name":"Papa John's Pizza",
    "wof:placetype":"venue"
},
  "geometry": {"coordinates":[-85.589583,42.242685],"type":"Point"}
}