{
  "type": "Feature",
  "properties": {
    "iso:country":"US",
    "sg:address":"12372 Dollar Lake Dr",
    "sg:city":"Fenton",
    "sg:classifiers":[
        {
            "category":"Wholesale",
            "subcategory":"Construction Materials",
            "type":"Manufacturing & Wholesale Goods"
        }
    ],
    "sg:phone":"+1 810 750 7636",
    "sg:postcode":"48430",
    "sg:province":"MI",
    "sg:tags":[
        "sand",
        "gravel"
    ],
    "wof:name":"Advantage Aggregate",
    "wof:placetype":"venue"
},
  "geometry": {"coordinates":[-83.709731,42.84883],"type":"Point"}
}