{
  "type": "Feature",
  "properties": {
    "iso:country":"US",
    "sg:address":"6058 N Branch Rd",
    "sg:city":"North Branch",
    "sg:classifiers":[
        {
            "category":"Insurance",
            "subcategory":"Insurance Agent",
            "type":"Services"
        }
    ],
    "sg:phone":"+1 810 688 8077",
    "sg:postcode":"48461",
    "sg:province":"MI",
    "wof:name":"Educational Risk Assessment SE",
    "wof:placetype":"venue"
},
  "geometry": {"coordinates":[-83.114818,43.231324],"type":"Point"}
}