{
  "type": "Feature",
  "properties": {
    "iso:country":"US",
    "sg:address":"8034 Smart St",
    "sg:city":"Detroit",
    "sg:classifiers":[
        {
            "category":"Building & Trades",
            "subcategory":"Construction",
            "type":"Services"
        }
    ],
    "sg:phone":"+1 313 894 5379",
    "sg:postcode":"48210",
    "sg:province":"MI",
    "sg:tags":[
        "contractor"
    ],
    "wof:name":"J&J Drywall",
    "wof:placetype":"venue"
},
  "geometry": {"coordinates":[-83.14962,42.337919],"type":"Point"}
}