{
  "type": "Feature",
  "properties": {
    "iso:country":"US",
    "sg:address":"152 S Main St",
    "sg:city":"Wayland",
    "sg:classifiers":[
        {
            "category":"Utilities",
            "subcategory":"Telephone",
            "type":"Services"
        },
        {
            "category":"Shopping",
            "subcategory":"Mobile Phones",
            "type":"Retail Goods"
        },
        {
            "category":"Manufacturing",
            "subcategory":"Electronics",
            "type":"Manufacturing & Wholesale Goods"
        },
        {
            "category":"Shopping",
            "subcategory":"Computers & Home Electronics",
            "type":"Retail Goods"
        },
        {
            "category":"Communications",
            "type":"Services"
        }
    ],
    "sg:phone":"+1 269 792 9221",
    "sg:postcode":"49348",
    "sg:province":"MI",
    "sg:tags":[
        "sound",
        "television",
        "theater",
        "supply",
        "system",
        "equipment",
        "radio",
        "cellular",
        "telecommunications-equipment",
        "consumer",
        "store"
    ],
    "sg:website":"http://www.radioshack.com",
    "wof:name":"RadioShack",
    "wof:placetype":"venue"
},
  "geometry": {"coordinates":[-85.64322300000001,42.673337],"type":"Point"}
}