{
  "type": "Feature",
  "properties": {
    "iso:country":"US",
    "sg:address":"39503 Neston St",
    "sg:city":"Novi",
    "sg:classifiers":[
        {
            "category":"Professional",
            "type":"Services"
        }
    ],
    "sg:phone":"+1 248 305 8450",
    "sg:postcode":"48377",
    "sg:province":"MI",
    "wof:name":"Carter Jl Mobile Home Svc",
    "wof:placetype":"venue"
},
  "geometry": {"coordinates":[-83.43828999999999,42.486816],"type":"Point"}
}