{
  "type": "Feature",
  "properties": {
    "iso:country":"US",
    "sg:address":"50258 Van Dyke Ave",
    "sg:city":"Shelby Twp",
    "sg:classifiers":[
        {
            "category":"Building & Trades",
            "subcategory":"Construction",
            "type":"Services"
        }
    ],
    "sg:phone":"+1 586 739 6100",
    "sg:postcode":"48317",
    "sg:province":"MI",
    "sg:tags":[
        "contractor"
    ],
    "sg:website":"www.salmarhomesinc.com",
    "wof:name":"Sal-Mar Homes Inc",
    "wof:placetype":"venue"
},
  "geometry": {"coordinates":[-83.033666,42.665056],"type":"Point"}
}