{
  "type": "Feature",
  "properties": {
    "iso:country":"US",
    "sg:address":"200 E Bay St",
    "sg:city":"East Tawas",
    "sg:classifiers":[
        {
            "category":"Government",
            "subcategory":"Office",
            "type":"Public Place"
        }
    ],
    "sg:phone":"+1 989 362 3559",
    "sg:postcode":"48730",
    "sg:province":"MI",
    "sg:tags":[
        "station",
        "recruiting"
    ],
    "wof:name":"Marine Corps Recruiting Stn",
    "wof:placetype":"venue"
},
  "geometry": {"coordinates":[-83.48792,44.279959],"type":"Point"}
}