{
  "type": "Feature",
  "properties": {
    "iso:country":"US",
    "sg:address":"2020 S Morey Rd",
    "sg:city":"Lake City",
    "sg:classifiers":[
        {
            "category":"Shopping",
            "subcategory":"Department Store",
            "type":"Retail Goods"
        }
    ],
    "sg:phone":"+1 231 839 3449",
    "sg:postcode":"49651",
    "sg:province":"MI",
    "sg:tags":[
        "shop"
    ],
    "wof:name":"Family Dollar Store",
    "wof:placetype":"venue"
},
  "geometry": {"coordinates":[-85.21514999999999,44.309318],"type":"Point"}
}