{
  "type": "Feature",
  "properties": {
    "iso:country":"US",
    "sg:address":"19707 Mack Ave",
    "sg:city":"Grosse Pointe",
    "sg:classifiers":[
        {
            "category":"Health Services",
            "subcategory":"Doctor",
            "type":"Services"
        }
    ],
    "sg:phone":"+1 313 882 9777",
    "sg:postcode":"48236",
    "sg:province":"MI",
    "sg:tags":[
        "medical"
    ],
    "wof:name":"Geraldine Hardy MD",
    "wof:placetype":"venue"
},
  "geometry": {"coordinates":[-82.909701,42.427272],"type":"Point"}
}