{
  "type": "Feature",
  "properties": {
    "iso:country":"US",
    "sg:address":"211 Bridge St",
    "sg:city":"Charlevoix",
    "sg:classifiers":[
        {
            "category":"Professional",
            "type":"Services"
        }
    ],
    "sg:phone":"+1 231 237 0209",
    "sg:postcode":"49720",
    "sg:province":"MI",
    "sg:tags":[
        "establishment"
    ],
    "wof:name":"Michael Enterprises",
    "wof:placetype":"venue"
},
  "geometry": {"coordinates":[-85.25875600000001,45.317995],"type":"Point"}
}