{
  "type": "Feature",
  "properties": {
    "iso:country":"US",
    "sg:address":"1963 Lake Shore Dr",
    "sg:city":"Muskegon",
    "sg:classifiers":[
        {
            "category":"Bars & Pubs",
            "type":"Food & Drink"
        }
    ],
    "sg:phone":"+1 231 759 7604",
    "sg:postcode":"49441",
    "sg:province":"MI",
    "wof:name":"Lakeshore Tavern",
    "wof:placetype":"venue"
},
  "geometry": {"coordinates":[-86.29121499999999,43.216083],"type":"Point"}
}