{
  "type": "Feature",
  "properties": {
    "iso:country":"US",
    "sg:address":"32027 Bonnet Hill Rd",
    "sg:city":"Farmington",
    "sg:classifiers":[
        {
            "category":"Professional",
            "subcategory":"Advertising",
            "type":"Services"
        }
    ],
    "sg:phone":"+1 248 489 3102",
    "sg:postcode":"48334",
    "sg:province":"MI",
    "sg:tags":[
        "mail",
        "direct"
    ],
    "wof:name":"Arrowtech",
    "wof:placetype":"venue"
},
  "geometry": {"coordinates":[-83.365403,42.505734],"type":"Point"}
}