{
  "type": "Feature",
  "properties": {
    "iso:country":"US",
    "sg:address":"156 W M-134",
    "sg:city":"Cedarville",
    "sg:classifiers":[
        {
            "category":"Real Estate",
            "subcategory":"Real Estate Agent",
            "type":"Services"
        }
    ],
    "sg:phone":"+1 906 484 2250",
    "sg:postcode":"49719",
    "sg:province":"MI",
    "wof:name":"State Wide Real Estate",
    "wof:placetype":"venue"
},
  "geometry": {"coordinates":[-84.36542300000001,45.999399],"type":"Point"}
}