{
  "type": "Feature",
  "properties": {
    "iso:country":"US",
    "sg:address":"10743 Highland Rd",
    "sg:city":"White Lake",
    "sg:classifiers":[
        {
            "category":"Personal",
            "subcategory":"Tanning Parlor",
            "type":"Services"
        }
    ],
    "sg:phone":"+1 248 698 7974",
    "sg:postcode":"48386",
    "sg:province":"MI",
    "sg:tags":[
        "salon"
    ],
    "wof:name":"Acapolco Tan",
    "wof:placetype":"venue"
},
  "geometry": {"coordinates":[-83.494201,42.649643],"type":"Point"}
}