{
  "type": "Feature",
  "properties": {
    "iso:country":"US",
    "sg:address":"25440 5 Mile Rd Ste 100",
    "sg:city":"Redford",
    "sg:classifiers":[
        {
            "category":"Real Estate",
            "subcategory":"Real Estate Services",
            "type":"Services"
        }
    ],
    "sg:phone":"+1 313 255 2273",
    "sg:postcode":"48239",
    "sg:province":"MI",
    "sg:tags":[
        "management",
        "property"
    ],
    "wof:name":"Metro Management Team Inc",
    "wof:placetype":"venue"
},
  "geometry": {"coordinates":[-83.29270200000001,42.3997],"type":"Point"}
}