{
  "type": "Feature",
  "properties": {
    "iso:country":"US",
    "sg:address":"13500 North",
    "sg:city":"Sterling Heights",
    "sg:classifiers":[
        {
            "category":"Real Estate",
            "subcategory":"Real Estate Operator",
            "type":"Services"
        }
    ],
    "sg:phone":"+1 586 825 0043",
    "sg:postcode":"48310",
    "sg:province":"MI",
    "sg:tags":[
        "apartment"
    ],
    "wof:name":"Sterling Lake Apartments",
    "wof:placetype":"venue"
},
  "geometry": {"coordinates":[-83.039536,42.54578],"type":"Point"}
}