{
  "type": "Feature",
  "properties": {
    "iso:country":"US",
    "sg:address":"311 6th St",
    "sg:city":"Calumet",
    "sg:classifiers":[
        {
            "category":"Health Services",
            "subcategory":"Clinic",
            "type":"Services"
        }
    ],
    "sg:phone":"+1 906 337 5700",
    "sg:postcode":"49913",
    "sg:province":"MI",
    "sg:tags":[
        "home"
    ],
    "sg:website":"www.khn-hospice.com",
    "wof:name":"Keweenaw Home Nursing & Hspc",
    "wof:placetype":"venue"
},
  "geometry": {"coordinates":[-88.453835,47.247913],"type":"Point"}
}