{
  "type": "Feature",
  "properties": {
    "iso:country":"US",
    "sg:address":"5440 Corporate Dr",
    "sg:city":"Troy",
    "sg:classifiers":[
        {
            "category":"Professional",
            "subcategory":"Lawyer & Legal Services",
            "type":"Services"
        }
    ],
    "sg:phone":"+1 248 641 7000",
    "sg:postcode":"48098",
    "sg:province":"MI",
    "sg:tags":[
        "attorney"
    ],
    "wof:name":"Ufer & Spaniola PC",
    "wof:placetype":"venue"
},
  "geometry": {"coordinates":[-83.17130299999999,42.5975],"type":"Point"}
}