{
  "type": "Feature",
  "properties": {
    "iso:country":"US",
    "sg:address":"229 N Broadway St",
    "sg:city":"Hastings",
    "sg:classifiers":[
        {
            "category":"Retail",
            "subcategory":"Auto Repair",
            "type":"Services"
        }
    ],
    "sg:phone":"+1 269 948 2121",
    "sg:postcode":"49058",
    "sg:province":"MI",
    "sg:tags":[
        "repairing",
        "automobile"
    ],
    "wof:name":"J & J Auto Svc",
    "wof:placetype":"venue"
},
  "geometry": {"coordinates":[-85.290595,42.650293],"type":"Point"}
}