{
  "type": "Feature",
  "properties": {
    "iso:country":"US",
    "sg:address":"5039 W Saginaw Hwy",
    "sg:city":"Lansing",
    "sg:classifiers":[
        {
            "category":"Personal",
            "subcategory":"Beauty Salon",
            "type":"Services"
        }
    ],
    "sg:phone":"+1 517 321 0829",
    "sg:postcode":"48917",
    "sg:province":"MI",
    "sg:tags":[
        "shop"
    ],
    "wof:name":"U S Nails",
    "wof:placetype":"venue"
},
  "geometry": {"coordinates":[-84.621533,42.741026],"type":"Point"}
}