{
  "type": "Feature",
  "properties": {
    "iso:country":"US",
    "sg:address":"5272 Anthony Wayne Dr",
    "sg:city":"Detroit",
    "sg:classifiers":[
        {
            "category":"Personal",
            "subcategory":"Beauty Salon",
            "type":"Services"
        }
    ],
    "sg:phone":"+1 313 833 5000",
    "sg:postcode":"48202",
    "sg:province":"MI",
    "sg:tags":[
        "hair"
    ],
    "wof:name":"Salon X 2",
    "wof:placetype":"venue"
},
  "geometry": {"coordinates":[-83.072678,42.357687],"type":"Point"}
}