{
  "type": "Feature",
  "properties": {
    "iso:country":"US",
    "sg:address":"703 N Warner St",
    "sg:city":"Bay City",
    "sg:classifiers":[
        {
            "category":"Home & Garden",
            "subcategory":"Garden Supply",
            "type":"Retail Goods"
        }
    ],
    "sg:phone":"+1 989 460 0713",
    "sg:postcode":"48706",
    "sg:province":"MI",
    "sg:tags":[
        "sprinkler"
    ],
    "wof:name":"Fish Landscaping",
    "wof:placetype":"venue"
},
  "geometry": {"coordinates":[-83.908221,43.608605],"type":"Point"}
}