{
  "type": "Feature",
  "properties": {
    "iso:country":"US",
    "sg:address":"2951 Greenfield Rd",
    "sg:city":"Dearborn",
    "sg:classifiers":[
        {
            "category":"Government",
            "subcategory":"Office",
            "type":"Public Place"
        }
    ],
    "sg:phone":"+1 313 943 2150",
    "sg:postcode":"48120",
    "sg:province":"MI",
    "sg:tags":[
        "executive"
    ],
    "wof:name":"Building & Safety",
    "wof:placetype":"venue"
},
  "geometry": {"coordinates":[-83.16712699999999,42.289384],"type":"Point"}
}