{
  "type": "Feature",
  "properties": {
    "iso:country":"US",
    "sg:address":"411 E Main St SE",
    "sg:city":"Lowell",
    "sg:classifiers":[
        {
            "category":"Building & Trades",
            "subcategory":"Plumbing",
            "type":"Services"
        }
    ],
    "sg:phone":"+1 616 897 0887",
    "sg:postcode":"49331",
    "sg:province":"MI",
    "sg:tags":[
        "plumbing",
        "contractor"
    ],
    "wof:name":"Canfield Plumbing & Heating",
    "wof:placetype":"venue"
},
  "geometry": {"coordinates":[-85.334334,42.935247],"type":"Point"}
}