{
  "type": "Feature",
  "properties": {
    "iso:country":"US",
    "sg:address":"8005 Ore Knob Dr",
    "sg:city":"Fenton",
    "sg:classifiers":[
        {
            "category":"Building & Trades",
            "subcategory":"Construction",
            "type":"Services"
        }
    ],
    "sg:phone":"+1 810 629 4790",
    "sg:postcode":"48430",
    "sg:province":"MI",
    "sg:tags":[
        "designer"
    ],
    "wof:name":"Solidesign",
    "wof:placetype":"venue"
},
  "geometry": {"coordinates":[-83.796341,42.722162],"type":"Point"}
}