{
  "type": "Feature",
  "properties": {
    "iso:country":"US",
    "sg:address":"616 E Bay St",
    "sg:city":"East Tawas",
    "sg:classifiers":[
        {
            "category":"Autos & Motor Vehicles",
            "subcategory":"Automobile Sales",
            "type":"Retail Goods"
        }
    ],
    "sg:phone":"+1 989 362 5785",
    "sg:postcode":"48730",
    "sg:province":"MI",
    "sg:tags":[
        "car",
        "dealer"
    ],
    "wof:name":"Denny's Auto Sales",
    "wof:placetype":"venue"
},
  "geometry": {"coordinates":[-83.484088,44.280514],"type":"Point"}
}