{
  "type": "Feature",
  "properties": {
    "iso:country":"US",
    "sg:address":"3926 S 9th St",
    "sg:city":"Kalamazoo",
    "sg:classifiers":[
        {
            "category":"Retail",
            "subcategory":"Funeral Services",
            "type":"Services"
        }
    ],
    "sg:phone":"+1 269 343 1508",
    "sg:postcode":"49009",
    "sg:province":"MI",
    "sg:tags":[
        "director"
    ],
    "sg:website":"www.langelands.com",
    "wof:name":"Langeland Family Funeral Homes",
    "wof:placetype":"venue"
},
  "geometry": {"coordinates":[-85.677638,42.255123],"type":"Point"}
}