{
  "type": "Feature",
  "properties": {
    "iso:country":"US",
    "sg:address":"438 Saint Antoine St",
    "sg:city":"Detroit",
    "sg:classifiers":[
        {
            "category":"Organizations",
            "subcategory":"Religious Organization",
            "type":"Services"
        }
    ],
    "sg:phone":"+1 313 961 8077",
    "sg:postcode":"48226",
    "sg:province":"MI",
    "wof:name":"STS Peter & Paul Jesuit Church",
    "wof:placetype":"venue"
},
  "geometry": {"coordinates":[-83.03854200000001,42.331999],"type":"Point"}
}