{
  "type": "Feature",
  "properties": {
    "iso:country":"US",
    "sg:address":"28680 Streamwood Ln",
    "sg:city":"Southfield",
    "sg:classifiers":[
        {
            "category":"Museum",
            "type":"Entertainment"
        }
    ],
    "sg:phone":"+1 248 352 3340",
    "sg:postcode":"48034",
    "sg:province":"MI",
    "sg:tags":[
        "art",
        "gallery"
    ],
    "wof:name":"Hamilton Place Art Gallery",
    "wof:placetype":"venue"
},
  "geometry": {"coordinates":[-83.27701500000001,42.499857],"type":"Point"}
}