{
  "type": "Feature",
  "properties": {
    "iso:country":"US",
    "sg:address":"113 S Division Ave",
    "sg:city":"Holland",
    "sg:classifiers":[
        {
            "category":"Professional",
            "subcategory":"Research",
            "type":"Services"
        }
    ],
    "sg:phone":"+1 616 393 6808",
    "sg:postcode":"49424",
    "sg:province":"MI",
    "sg:tags":[
        "nonphysical",
        "engineering",
        "commercial"
    ],
    "wof:name":"Barnett Design Works",
    "wof:placetype":"venue"
},
  "geometry": {"coordinates":[-86.13742000000001,42.793753],"type":"Point"}
}