{
  "type": "Feature",
  "properties": {
    "iso:country":"US",
    "sg:address":"6361 Sparta St",
    "sg:city":"Detroit",
    "sg:classifiers":[
        {
            "category":"Social Services",
            "subcategory":"Child Care",
            "type":"Services"
        }
    ],
    "sg:phone":"+1 313 895 0392",
    "sg:postcode":"48210",
    "sg:province":"MI",
    "sg:tags":[
        "day"
    ],
    "wof:name":"Juanita's Daycare",
    "wof:placetype":"venue"
},
  "geometry": {"coordinates":[-83.133512,42.347106],"type":"Point"}
}