{
  "type": "Feature",
  "properties": {
    "iso:country":"US",
    "sg:address":"15444 Robson St",
    "sg:city":"Detroit",
    "sg:classifiers":[
        {
            "category":"Social Services",
            "subcategory":"Adult Care",
            "type":"Services"
        }
    ],
    "sg:phone":"+1 313 836 0569",
    "sg:postcode":"48227",
    "sg:province":"MI",
    "sg:tags":[
        "foster",
        "provider"
    ],
    "wof:name":"Franklin & Bobbie Euseary",
    "wof:placetype":"venue"
},
  "geometry": {"coordinates":[-83.19270400000001,42.405059],"type":"Point"}
}