{
  "type": "Feature",
  "properties": {
    "iso:country":"US",
    "sg:address":"3016 W Burt Lake Rd",
    "sg:city":"Brutus",
    "sg:classifiers":[
        {
            "category":"Organizations",
            "subcategory":"Religious Organization",
            "type":"Services"
        }
    ],
    "sg:phone":"+1 231 529 6401",
    "sg:postcode":"49716",
    "sg:province":"MI",
    "wof:name":"Deco Industries",
    "wof:placetype":"venue"
},
  "geometry": {"coordinates":[-84.702608,45.506986],"type":"Point"}
}