{
  "type": "Feature",
  "properties": {
    "iso:country":"US",
    "sg:address":"3668 Carolyn St",
    "sg:city":"Coloma",
    "sg:classifiers":[
        {
            "category":"Building & Trades",
            "subcategory":"Construction",
            "type":"Services"
        }
    ],
    "sg:phone":"+1 269 849 0869",
    "sg:postcode":"49038",
    "sg:province":"MI",
    "sg:tags":[
        "hanging",
        "contractor"
    ],
    "wof:name":"Edward Cottrell Pntng & Wlpp",
    "wof:placetype":"venue"
},
  "geometry": {"coordinates":[-86.36845,42.220442],"type":"Point"}
}