{
  "type": "Feature",
  "properties": {
    "iso:country":"US",
    "sg:address":"3737 Carpenter Rd",
    "sg:city":"Ypsilanti",
    "sg:classifiers":[
        {
            "category":"Shopping",
            "subcategory":"Hobbies, Toys, & Games",
            "type":"Retail Goods"
        }
    ],
    "sg:phone":"+1 734 975 0310",
    "sg:postcode":"48197",
    "sg:province":"MI",
    "wof:name":"Jo-Ann Fabrics & Crafts",
    "wof:placetype":"venue"
},
  "geometry": {"coordinates":[-83.68010599999999,42.235348],"type":"Point"}
}