{
  "type": "Feature",
  "properties": {
    "iso:country":"US",
    "sg:address":"301 Jipson St",
    "sg:city":"Blissfield",
    "sg:classifiers":[
        {
            "category":"Building & Trades",
            "subcategory":"Landscaping Services",
            "type":"Services"
        }
    ],
    "sg:phone":"+1 517 486 4620",
    "sg:postcode":"49228",
    "sg:province":"MI",
    "wof:name":"Burks Lawn Care",
    "wof:placetype":"venue"
},
  "geometry": {"coordinates":[-83.85529699999999,41.827889],"type":"Point"}
}