{
  "type": "Feature",
  "properties": {
    "iso:country":"US",
    "sg:address":"1900 Columbus Ave",
    "sg:city":"Bay City",
    "sg:classifiers":[
        {
            "category":"Health Services",
            "subcategory":"Doctor",
            "type":"Services"
        }
    ],
    "sg:phone":"+1 989 894 8670",
    "sg:postcode":"48708",
    "sg:province":"MI",
    "sg:tags":[
        "medical"
    ],
    "wof:name":"Kondapaneni K B MD",
    "wof:placetype":"venue"
},
  "geometry": {"coordinates":[-83.86704,43.589421],"type":"Point"}
}