{
  "type": "Feature",
  "properties": {
    "iso:country":"US",
    "sg:address":"260 Graham Ave",
    "sg:city":"St Ignace",
    "sg:classifiers":[
        {
            "category":"Insurance",
            "subcategory":"Insurance Agent",
            "type":"Services"
        }
    ],
    "sg:phone":"+1 906 643 6933",
    "sg:postcode":"49781",
    "sg:province":"MI",
    "wof:name":"Northwestern Mutual Financial",
    "wof:placetype":"venue"
},
  "geometry": {"coordinates":[-84.705831,45.851103],"type":"Point"}
}