{
  "type": "Feature",
  "properties": {
    "iso:country":"US",
    "sg:address":"9170 Bennett Lake Rd",
    "sg:city":"Fenton",
    "sg:classifiers":[
        {
            "category":"Shopping",
            "subcategory":"Florist",
            "type":"Retail Goods"
        }
    ],
    "sg:phone":"+1 810 629 0809",
    "sg:postcode":"48430",
    "sg:province":"MI",
    "wof:name":"Flowers By Kathlynn",
    "wof:placetype":"venue"
},
  "geometry": {"coordinates":[-83.780035,42.776839],"type":"Point"}
}