{
  "type": "Feature",
  "properties": {
    "iso:country":"US",
    "sg:address":"18311 E 9 Mile Rd",
    "sg:city":"Eastpointe",
    "sg:classifiers":[
        {
            "category":"Real Estate",
            "subcategory":"Real Estate Agent",
            "type":"Services"
        }
    ],
    "sg:phone":"+1 586 777 8833",
    "sg:postcode":"48021",
    "sg:province":"MI",
    "wof:name":"Landmark Investment Co",
    "wof:placetype":"venue"
},
  "geometry": {"coordinates":[-82.93077099999999,42.465404],"type":"Point"}
}