{
  "type": "Feature",
  "properties": {
    "iso:country":"US",
    "sg:address":"620 N Old Woodward Ave",
    "sg:city":"Birmingham",
    "sg:classifiers":[
        {
            "category":"Health Services",
            "subcategory":"Health Practitioner",
            "type":"Services"
        }
    ],
    "sg:phone":"+1 248 646 5880",
    "sg:postcode":"48009",
    "sg:province":"MI",
    "sg:tags":[
        "psychotherapy"
    ],
    "wof:name":"Sydney Reiter Msw Acsw",
    "wof:placetype":"venue"
},
  "geometry": {"coordinates":[-83.219476,42.553331],"type":"Point"}
}