{
  "type": "Feature",
  "properties": {
    "iso:country":"US",
    "sg:address":"3701 E 13 Mile Rd",
    "sg:city":"Warren",
    "sg:classifiers":[
        {
            "category":"Health Services",
            "subcategory":"Doctor",
            "type":"Services"
        }
    ],
    "sg:phone":"+1 586 979 1060",
    "sg:postcode":"48092",
    "sg:province":"MI",
    "sg:tags":[
        "podiatrist"
    ],
    "wof:name":"Cohen & Mauro DPM PC",
    "wof:placetype":"venue"
},
  "geometry": {"coordinates":[-83.070999,42.520302],"type":"Point"}
}