{
  "type": "Feature",
  "properties": {
    "iso:country":"US",
    "sg:address":"12101 Townsend Rd",
    "sg:city":"Milan",
    "sg:classifiers":[
        {
            "category":"Building & Trades",
            "subcategory":"Construction",
            "type":"Services"
        }
    ],
    "sg:phone":"+1 734 439 2682",
    "sg:postcode":"48160",
    "sg:province":"MI",
    "sg:tags":[
        "hanging",
        "contractor"
    ],
    "wof:name":"Coopers Quality Painting",
    "wof:placetype":"venue"
},
  "geometry": {"coordinates":[-83.612869,42.046214],"type":"Point"}
}