{
  "type": "Feature",
  "properties": {
    "iso:country":"US",
    "sg:address":"1020 S Old Woodward Ave",
    "sg:city":"Birmingham",
    "sg:classifiers":[
        {
            "category":"Home & Garden",
            "subcategory":"Furniture",
            "type":"Retail Goods"
        }
    ],
    "sg:phone":"+1 248 203 6006",
    "sg:postcode":"48009",
    "sg:province":"MI",
    "sg:tags":[
        "cabinet"
    ],
    "wof:name":"Caden Design Group",
    "wof:placetype":"venue"
},
  "geometry": {"coordinates":[-83.20754100000001,42.539743],"type":"Point"}
}