{
  "type": "Feature",
  "properties": {
    "iso:country":"US",
    "sg:address":"4267 Macomb Industrial Dr",
    "sg:city":"Clinton Township",
    "sg:classifiers":[
        {
            "category":"Personal",
            "type":"Services"
        }
    ],
    "sg:phone":"+1 586 463 4230",
    "sg:postcode":"48035",
    "sg:province":"MI",
    "sg:tags":[
        "mover"
    ],
    "wof:name":"Preferred Moving and Storage Inc",
    "wof:placetype":"venue"
},
  "geometry": {"coordinates":[-82.9104,42.5574],"type":"Point"}
}