{
  "type": "Feature",
  "properties": {
    "iso:country":"US",
    "sg:address":"1180 Fort St",
    "sg:city":"Lincoln Park",
    "sg:classifiers":[
        {
            "category":"Food & Beverages",
            "subcategory":"Groceries & Convenience Stores",
            "type":"Retail Goods"
        }
    ],
    "sg:phone":"+1 313 388 6679",
    "sg:postcode":"48146",
    "sg:province":"MI",
    "wof:name":"Lincoln Park Fruit Market",
    "wof:placetype":"venue"
},
  "geometry": {"coordinates":[-83.170754,42.258316],"type":"Point"}
}