{
  "type": "Feature",
  "properties": {
    "iso:country":"US",
    "sg:address":"376 Robbins Dr",
    "sg:city":"Troy",
    "sg:classifiers":[
        {
            "category":"Building & Trades",
            "subcategory":"Electrical",
            "type":"Services"
        }
    ],
    "sg:phone":"+1 248 585 0732",
    "sg:postcode":"48083",
    "sg:province":"MI",
    "sg:tags":[
        "electric",
        "contractor"
    ],
    "wof:name":"G & S Electric",
    "wof:placetype":"venue"
},
  "geometry": {"coordinates":[-83.101775,42.537429],"type":"Point"}
}