{
  "type": "Feature",
  "properties": {
    "iso:country":"US",
    "sg:address":"31155 Northwestern Hwy",
    "sg:city":"Farmington Hills",
    "sg:classifiers":[
        {
            "category":"Professional",
            "subcategory":"Accounting & Tax Preparation",
            "type":"Services"
        }
    ],
    "sg:phone":"+1 248 865 9510",
    "sg:postcode":"48334",
    "sg:province":"MI",
    "sg:tags":[
        "accountant"
    ],
    "wof:name":"Robert Solomon BCPA",
    "wof:placetype":"venue"
},
  "geometry": {"coordinates":[-83.33676800000001,42.517254],"type":"Point"}
}