{
  "type": "Feature",
  "properties": {
    "iso:country":"US",
    "sg:address":"5903 Ambassador Dr",
    "sg:city":"Saginaw",
    "sg:classifiers":[
        {
            "category":"Freight",
            "type":"Transportation"
        }
    ],
    "sg:phone":"+1 989 799 0982",
    "sg:postcode":"48603",
    "sg:province":"MI",
    "sg:tags":[
        "operator",
        "local",
        "trucking"
    ],
    "wof:name":"Henslers Delivery Service",
    "wof:placetype":"venue"
},
  "geometry": {"coordinates":[-84.03313300000001,43.440719],"type":"Point"}
}