{
  "type": "Feature",
  "properties": {
    "iso:country":"US",
    "sg:address":"2540 Allen Rd",
    "sg:city":"Kimball",
    "sg:classifiers":[
        {
            "category":"Wholesale",
            "subcategory":"Construction Materials",
            "type":"Manufacturing & Wholesale Goods"
        }
    ],
    "sg:phone":"+1 810 984 4406",
    "sg:postcode":"48074",
    "sg:province":"MI",
    "sg:tags":[
        "fence"
    ],
    "wof:name":"Loxton Fence",
    "wof:placetype":"venue"
},
  "geometry": {"coordinates":[-82.523901,42.980732],"type":"Point"}
}