{
  "type": "Feature",
  "properties": {
    "iso:country":"US",
    "sg:address":"9528 Bolton Rd",
    "sg:city":"Posen",
    "sg:classifiers":[
        {
            "category":"Wholesale",
            "subcategory":"Plants",
            "type":"Manufacturing & Wholesale Goods"
        }
    ],
    "sg:phone":"+1 989 356 4807",
    "sg:postcode":"49776",
    "sg:province":"MI",
    "sg:tags":[
        "nursery",
        "tree"
    ],
    "sg:website":"www.mapleridgesupply.com",
    "wof:name":"Maple Ridge Supply",
    "wof:placetype":"venue"
},
  "geometry": {"coordinates":[-83.588206,45.187839],"type":"Point"}
}