{
  "type": "Feature",
  "properties": {
    "iso:country":"US",
    "sg:address":"134 W. University Dr. Suite 203-A",
    "sg:city":"Rochester",
    "sg:classifiers":[
        {
            "category":"Professional",
            "subcategory":"Computer Services",
            "type":"Services"
        }
    ],
    "sg:phone":"+1 248 650 7813",
    "sg:postcode":"48307",
    "sg:province":"MI",
    "sg:website":"http://www.3dconnexion.com",
    "wof:name":"3Dconnexion",
    "wof:placetype":"venue"
},
  "geometry": {"coordinates":[-83.137247,42.682087],"type":"Point"}
}