{
  "type": "Feature",
  "properties": {
    "iso:country":"US",
    "sg:address":"1400 W Columbia Ave",
    "sg:city":"Battle Creek",
    "sg:classifiers":[
        {
            "category":"Home & Garden",
            "subcategory":"Carpets & Floor Coverings",
            "type":"Retail Goods"
        }
    ],
    "sg:phone":"+1 269 965 0516",
    "sg:postcode":"49015",
    "sg:province":"MI",
    "sg:tags":[
        "dealer",
        "rug"
    ],
    "wof:name":"Migala Carpet One",
    "wof:placetype":"venue"
},
  "geometry": {"coordinates":[-85.222021,42.297534],"type":"Point"}
}