{
  "type": "Feature",
  "properties": {
    "iso:country":"US",
    "sg:address":"2340 Hemlock Ln",
    "sg:city":"Petoskey",
    "sg:classifiers":[
        {
            "category":"Professional",
            "subcategory":"Business Services",
            "type":"Services"
        }
    ],
    "sg:phone":"+1 231 439 9131",
    "sg:postcode":"49770",
    "sg:province":"MI",
    "wof:name":"Skater S Edge Foundation Inc",
    "wof:placetype":"venue"
},
  "geometry": {"coordinates":[-84.987759,45.286616],"type":"Point"}
}