{
  "type": "Feature",
  "properties": {
    "iso:country":"US",
    "sg:address":"3078 Main St",
    "sg:city":"Marlette",
    "sg:classifiers":[
        {
            "category":"Personal",
            "subcategory":"Beauty Salon",
            "type":"Services"
        }
    ],
    "sg:phone":"+1 989 635 5399",
    "sg:postcode":"48453",
    "sg:province":"MI",
    "sg:tags":[
        "shop"
    ],
    "wof:name":"New Image",
    "wof:placetype":"venue"
},
  "geometry": {"coordinates":[-83.07994100000001,43.326416],"type":"Point"}
}