{
  "type": "Feature",
  "properties": {
    "iso:country":"US",
    "sg:address":"3392 E West Maple Rd",
    "sg:city":"Commerce Township",
    "sg:classifiers":[
        {
            "category":"Health Services",
            "subcategory":"Doctor",
            "type":"Services"
        }
    ],
    "sg:phone":"+1 248 624 5551",
    "sg:postcode":"48390",
    "sg:province":"MI",
    "sg:tags":[
        "surgeon",
        "oral"
    ],
    "wof:name":"Walled Lake Dental Associates P L L C",
    "wof:placetype":"venue"
},
  "geometry": {"coordinates":[-83.440201,42.5424],"type":"Point"}
}