{
  "type": "Feature",
  "properties": {
    "iso:country":"US",
    "sg:address":"11400 Cranston St",
    "sg:city":"Livonia",
    "sg:classifiers":[
        {
            "category":"Social Services",
            "subcategory":"Adult Care",
            "type":"Services"
        }
    ],
    "sg:phone":"+1 734 421 6140",
    "sg:postcode":"48150",
    "sg:province":"MI",
    "sg:tags":[
        "residential"
    ],
    "wof:name":"Cranston",
    "wof:placetype":"venue"
},
  "geometry": {"coordinates":[-83.361057,42.367688],"type":"Point"}
}