{
  "type": "Feature",
  "properties": {
    "iso:country":"US",
    "sg:address":"1230 S Milford Rd",
    "sg:city":"Highland",
    "sg:classifiers":[
        {
            "category":"Education",
            "subcategory":"Dance Studio",
            "type":"Public Place"
        }
    ],
    "sg:phone":"+1 248 887 1807",
    "sg:postcode":"48357",
    "sg:province":"MI",
    "sg:tags":[
        "instruction",
        "dancing"
    ],
    "wof:name":"Karen's School Of Dance",
    "wof:placetype":"venue"
},
  "geometry": {"coordinates":[-83.61671,42.631919],"type":"Point"}
}