{
  "type": "Feature",
  "properties": {
    "iso:country":"US",
    "sg:address":"29895 Greenfield Rd",
    "sg:city":"Southfield",
    "sg:classifiers":[
        {
            "category":"Building & Trades",
            "subcategory":"Landscaping Services",
            "type":"Services"
        }
    ],
    "sg:phone":"+1 248 557 5588",
    "sg:postcode":"48076",
    "sg:province":"MI",
    "sg:tags":[
        "designer",
        "landscape"
    ],
    "wof:name":"Calvin Hall & Assoc",
    "wof:placetype":"venue"
},
  "geometry": {"coordinates":[-83.203456,42.508909],"type":"Point"}
}