{
  "type": "Feature",
  "properties": {
    "iso:country":"US",
    "sg:address":"8502 State Rd",
    "sg:city":"Millington",
    "sg:classifiers":[
        {
            "category":"Autos & Motor Vehicles",
            "subcategory":"Auto Supplies",
            "type":"Retail Goods"
        }
    ],
    "sg:phone":"+1 989 871 2090",
    "sg:postcode":"48746",
    "sg:province":"MI",
    "sg:tags":[
        "automobile",
        "parts"
    ],
    "wof:name":"Carquest Auto Parts",
    "wof:placetype":"venue"
},
  "geometry": {"coordinates":[-83.52986300000001,43.281262],"type":"Point"}
}