{
  "type": "Feature",
  "properties": {
    "iso:country":"US",
    "sg:address":"38116 Minton St",
    "sg:city":"Livonia",
    "sg:classifiers":[
        {
            "category":"Real Estate",
            "subcategory":"Real Estate Agent",
            "type":"Services"
        }
    ],
    "sg:phone":"+1 734 432 5166",
    "sg:postcode":"48150",
    "sg:province":"MI",
    "wof:name":"Phlippeau Fred B and Assoc",
    "wof:placetype":"venue"
},
  "geometry": {"coordinates":[-83.419303,42.357638],"type":"Point"}
}