{
  "type": "Feature",
  "properties": {
    "iso:country":"US",
    "sg:address":"12021 Beaver Rd",
    "sg:city":"St Charles",
    "sg:classifiers":[
        {
            "category":"Manufacturing",
            "subcategory":"Tools & Machinery",
            "type":"Manufacturing & Wholesale Goods"
        }
    ],
    "sg:phone":"+1 989 865 9955",
    "sg:postcode":"48655",
    "sg:province":"MI",
    "sg:tags":[
        "pattern",
        "maker"
    ],
    "wof:name":"D & K Pattern Inc",
    "wof:placetype":"venue"
},
  "geometry": {"coordinates":[-84.161537,43.314945],"type":"Point"}
}