{
  "type": "Feature",
  "properties": {
    "iso:country":"US",
    "sg:address":"1934 Detroit St",
    "sg:city":"Dearborn",
    "sg:classifiers":[
        {
            "category":"Building & Trades",
            "subcategory":"Construction",
            "type":"Services"
        }
    ],
    "sg:phone":"+1 313 441 1759",
    "sg:postcode":"48124",
    "sg:province":"MI",
    "sg:tags":[
        "carpentry",
        "contractor"
    ],
    "wof:name":"M S Woodworks",
    "wof:placetype":"venue"
},
  "geometry": {"coordinates":[-83.227176,42.291449],"type":"Point"}
}