{
  "type": "Feature",
  "properties": {
    "iso:country":"US",
    "sg:address":"125 Maywood Ave",
    "sg:city":"Bloomfield Hills",
    "sg:classifiers":[
        {
            "category":"Professional",
            "subcategory":"Employment Agencies",
            "type":"Services"
        }
    ],
    "sg:phone":"+1 248 647 4750",
    "sg:postcode":"48304",
    "sg:province":"MI",
    "wof:name":"McKenzie Scott of Michigan",
    "wof:placetype":"venue"
},
  "geometry": {"coordinates":[-83.217254,42.555519],"type":"Point"}
}