{
  "type": "Feature",
  "properties": {
    "iso:country":"US",
    "sg:address":"400 N Main St",
    "sg:city":"Milford",
    "sg:classifiers":[
        {
            "category":"Shopping",
            "subcategory":"Hobbies, Toys, & Games",
            "type":"Retail Goods"
        }
    ],
    "sg:phone":"+1 248 684 8697",
    "sg:postcode":"48381",
    "sg:province":"MI",
    "wof:name":"Village Toy Shoppe",
    "wof:placetype":"venue"
},
  "geometry": {"coordinates":[-83.600387,42.591657],"type":"Point"}
}