{
  "type": "Feature",
  "properties": {
    "iso:country":"US",
    "sg:address":"122 W. Maple Rd",
    "sg:city":"Birmingham",
    "sg:classifiers":[
        {
            "category":"Shopping",
            "type":"Retail Goods"
        }
    ],
    "sg:phone":"+1 248 723 9832",
    "sg:postcode":"48009",
    "sg:province":"MI",
    "wof:name":"Suhm-Thing",
    "wof:placetype":"venue"
},
  "geometry": {"coordinates":[-83.21504899999999,42.546844],"type":"Point"}
}