{
  "type": "Feature",
  "properties": {
    "iso:country":"US",
    "sg:address":"12941 Ida West Rd",
    "sg:city":"Petersburg",
    "sg:classifiers":[
        {
            "category":"Wholesale",
            "subcategory":"Vending Machines",
            "type":"Manufacturing & Wholesale Goods"
        }
    ],
    "sg:phone":"+1 734 269 6126",
    "sg:postcode":"49270",
    "sg:province":"MI",
    "sg:tags":[
        "operator",
        "confectionery"
    ],
    "wof:name":"Bbb Vending",
    "wof:placetype":"venue"
},
  "geometry": {"coordinates":[-83.613584,41.910357],"type":"Point"}
}