{
  "type": "Feature",
  "properties": {
    "iso:country":"US",
    "sg:address":"2801 22nd St",
    "sg:city":"Menominee",
    "sg:classifiers":[
        {
            "category":"Retail",
            "subcategory":"Auto Rental",
            "type":"Services"
        }
    ],
    "sg:phone":"+1 906 863 9412",
    "sg:postcode":"49858",
    "sg:province":"MI",
    "sg:tags":[
        "renting",
        "automobile"
    ],
    "wof:name":"Avis Rent A Car",
    "wof:placetype":"venue"
},
  "geometry": {"coordinates":[-87.629272,45.123271],"type":"Point"}
}