{
  "type": "Feature",
  "properties": {
    "iso:country":"US",
    "sg:address":"106 S Stewart Ave",
    "sg:city":"Fremont",
    "sg:classifiers":[
        {
            "category":"Banks & Credit Unions",
            "subcategory":"Bank",
            "type":"Services"
        }
    ],
    "sg:phone":"+1 231 924 2953",
    "sg:postcode":"49412",
    "sg:province":"MI",
    "sg:tags":[
        "loan",
        "real estate"
    ],
    "wof:name":"Republic Bank Mortgage Corp",
    "wof:placetype":"venue"
},
  "geometry": {"coordinates":[-85.939921,43.466157],"type":"Point"}
}