{
  "type": "Feature",
  "properties": {
    "iso:country":"US",
    "sg:address":"14444 Wuoksi Ave",
    "sg:city":"Kaleva",
    "sg:classifiers":[
        {
            "category":"Social Services",
            "subcategory":"Child Care",
            "type":"Services"
        }
    ],
    "sg:phone":"+1 231 362 2879",
    "sg:postcode":"49645",
    "sg:province":"MI",
    "wof:name":"Busy Body Daycare",
    "wof:placetype":"venue"
},
  "geometry": {"coordinates":[-86.00919500000001,44.373498],"type":"Point"}
}