{
  "type": "Feature",
  "properties": {
    "iso:country":"US",
    "sg:address":"625 2nd St",
    "sg:city":"Traverse City",
    "sg:classifiers":[
        {
            "category":"Personal",
            "type":"Services"
        }
    ],
    "sg:phone":"+1 231 510 4000",
    "sg:postcode":"49684",
    "sg:province":"MI",
    "sg:tags":[
        "therapist",
        "massage"
    ],
    "wof:name":"Mike Nangle",
    "wof:placetype":"venue"
},
  "geometry": {"coordinates":[-85.63424999999999,44.766294],"type":"Point"}
}