{
  "type": "Feature",
  "properties": {
    "iso:country":"US",
    "sg:address":"25824 Waldorf St",
    "sg:city":"Roseville",
    "sg:classifiers":[
        {
            "category":"Building & Trades",
            "subcategory":"Construction",
            "type":"Services"
        }
    ],
    "sg:phone":"+1 586 775 9060",
    "sg:postcode":"48066",
    "sg:province":"MI",
    "sg:tags":[
        "hanging",
        "contractor"
    ],
    "wof:name":"B&L Painting & Remodeling",
    "wof:placetype":"venue"
},
  "geometry": {"coordinates":[-82.92072400000001,42.485328],"type":"Point"}
}