{
  "type": "Feature",
  "properties": {
    "iso:country":"US",
    "sg:address":"6450 28th Ave",
    "sg:city":"Hudsonville",
    "sg:classifiers":[
        {
            "category":"Government",
            "subcategory":"Office",
            "type":"Public Place"
        }
    ],
    "sg:phone":"+1 616 669 5730",
    "sg:postcode":"49426",
    "sg:province":"MI",
    "sg:tags":[
        "driver",
        "to",
        "department",
        "motor",
        "vehicle",
        "test"
    ],
    "wof:name":"Department of Motor Vehicles",
    "wof:placetype":"venue"
},
  "geometry": {"coordinates":[-85.85174000000001,42.887136],"type":"Point"}
}