{
  "type": "Feature",
  "properties": {
    "iso:country":"US",
    "sg:address":"522 Elm St",
    "sg:city":"Big Rapids",
    "sg:classifiers":[
        {
            "category":"Arts & Performance",
            "subcategory":"Theater",
            "type":"Entertainment"
        }
    ],
    "sg:phone":"+1 231 592 5594",
    "sg:postcode":"49307",
    "sg:province":"MI",
    "sg:tags":[
        "bureau"
    ],
    "wof:name":"National Entertainment",
    "wof:placetype":"venue"
},
  "geometry": {"coordinates":[-85.47634100000001,43.697015],"type":"Point"}
}