{
  "type": "Feature",
  "properties": {
    "iso:country":"US",
    "sg:address":"3225 W Huron St",
    "sg:city":"Waterford",
    "sg:classifiers":[
        {
            "category":"Autos & Motor Vehicles",
            "subcategory":"Auto Supplies",
            "type":"Retail Goods"
        },
        {
            "category":"Retail",
            "subcategory":"Auto Rental",
            "type":"Services"
        },
        {
            "category":"Military Area",
            "subcategory":"Naval Base",
            "type":"Public Place"
        },
        {
            "category":"Utilities",
            "subcategory":"Electric",
            "type":"Services"
        },
        {
            "category":"Retail",
            "subcategory":"Auto Repair",
            "type":"Services"
        }
    ],
    "sg:phone":"+1 248 738 1601",
    "sg:postcode":"48328",
    "sg:province":"MI",
    "sg:tags":[
        "renting",
        "leasing",
        "trailers-automobile",
        "trailers-repair",
        "hitch",
        "equipment",
        "part",
        "trailer"
    ],
    "sg:website":"http://www.americantrailermart.com",
    "wof:name":"American Trailer Mart",
    "wof:placetype":"venue"
},
  "geometry": {"coordinates":[-83.35068699999999,42.638382],"type":"Point"}
}