{
  "type": "Feature",
  "properties": {
    "iso:country":"US",
    "sg:address":"1018 E 4th St",
    "sg:city":"Royal Oak",
    "sg:classifiers":[
        {
            "category":"Retail",
            "subcategory":"Portrait Studio",
            "type":"Services"
        }
    ],
    "sg:phone":"+1 248 246 1599",
    "sg:postcode":"48067",
    "sg:province":"MI",
    "sg:tags":[
        "photography"
    ],
    "wof:name":"Informal Formals Photography",
    "wof:placetype":"venue"
},
  "geometry": {"coordinates":[-83.132957,42.487138],"type":"Point"}
}