{
  "type": "Feature",
  "properties": {
    "iso:country":"US",
    "sg:address":"13700 Oak Park Blvd",
    "sg:city":"Oak Park",
    "sg:classifiers":[
        {
            "category":"Government",
            "subcategory":"Office",
            "type":"Public Place"
        }
    ],
    "sg:phone":"+1 248 691 7580",
    "sg:postcode":"48237",
    "sg:province":"MI",
    "sg:tags":[
        "village"
    ],
    "wof:name":"City Engineering",
    "wof:placetype":"venue"
},
  "geometry": {"coordinates":[-83.1827,42.465927],"type":"Point"}
}