{
  "type": "Feature",
  "properties": {
    "iso:country":"US",
    "sg:address":"2037 N Center Rd",
    "sg:city":"Flint",
    "sg:classifiers":[
        {
            "category":"Health Services",
            "subcategory":"Doctor",
            "type":"Services"
        }
    ],
    "sg:phone":"+1 810 744 3830",
    "sg:postcode":"48506",
    "sg:province":"MI",
    "wof:name":"Daniel Lechota DDS",
    "wof:placetype":"venue"
},
  "geometry": {"coordinates":[-83.635482,43.034017],"type":"Point"}
}