{
  "type": "Feature",
  "properties": {
    "iso:country":"US",
    "sg:address":"237 E Cloverland Dr",
    "sg:city":"Ironwood",
    "sg:classifiers":[
        {
            "category":"Government",
            "subcategory":"Office",
            "type":"Public Place"
        }
    ],
    "sg:phone":"+1 906 932 0222",
    "sg:postcode":"49938",
    "sg:province":"MI",
    "sg:tags":[
        "state",
        "program"
    ],
    "wof:name":"Rehabilitation Service",
    "wof:placetype":"venue"
},
  "geometry": {"coordinates":[-90.168656,46.463152],"type":"Point"}
}