{
  "type": "Feature",
  "properties": {
    "iso:country":"US",
    "sg:address":"679 Aiken St",
    "sg:city":"Owosso",
    "sg:classifiers":[
        {
            "category":"Freight",
            "type":"Transportation"
        }
    ],
    "sg:phone":"+1 989 729 6922",
    "sg:postcode":"48867",
    "sg:province":"MI",
    "sg:tags":[
        "hauling",
        "trucking"
    ],
    "wof:name":"D P Environmental Hauling LLC",
    "wof:placetype":"venue"
},
  "geometry": {"coordinates":[-84.147814,42.990472],"type":"Point"}
}