{
  "type": "Feature",
  "properties": {
    "iso:country":"US",
    "sg:address":"1325 S Airport Rd W",
    "sg:city":"Traverse City",
    "sg:classifiers":[
        {
            "category":"Health Services",
            "subcategory":"Optometrist",
            "type":"Services"
        }
    ],
    "sg:phone":"+1 231 947 6767",
    "sg:postcode":"49686",
    "sg:province":"MI",
    "sg:tags":[
        "optical",
        "good"
    ],
    "wof:name":"Dunscombe Optical",
    "wof:placetype":"venue"
},
  "geometry": {"coordinates":[-85.60272000000001,44.733428],"type":"Point"}
}