{
  "type": "Feature",
  "properties": {
    "iso:country":"US",
    "sg:address":"441 Saint Joseph St",
    "sg:city":"Union City",
    "sg:classifiers":[
        {
            "category":"Social Services",
            "subcategory":"Child Care",
            "type":"Services"
        }
    ],
    "sg:phone":"+1 517 741 7548",
    "sg:postcode":"49090",
    "sg:province":"MI",
    "sg:tags":[
        "day"
    ],
    "wof:name":"Stacie Swartout",
    "wof:placetype":"venue"
},
  "geometry": {"coordinates":[-86.28130299999999,42.400174],"type":"Point"}
}