{
  "type": "Feature",
  "properties": {
    "iso:country":"US",
    "sg:address":"1764 US Hwy 31",
    "sg:city":"Traverse City",
    "sg:classifiers":[
        {
            "category":"Restaurant",
            "type":"Food & Drink"
        }
    ],
    "sg:phone":"+1 231 938 9220",
    "sg:postcode":"49686",
    "sg:province":"MI",
    "sg:website":"www.rubytuesday.com",
    "wof:name":"Ruby Tuesday",
    "wof:placetype":"venue"
},
  "geometry": {"coordinates":[-85.541786,44.745504],"type":"Point"}
}