{
  "type": "Feature",
  "properties": {
    "iso:country":"US",
    "sg:address":"817 Walbridge St",
    "sg:city":"Kalamazoo",
    "sg:classifiers":[
        {
            "category":"Retail",
            "subcategory":"Laundry & Dry Cleaning",
            "type":"Services"
        }
    ],
    "sg:phone":"+1 269 373 5481",
    "sg:postcode":"49007",
    "sg:province":"MI",
    "sg:tags":[
        "linen"
    ],
    "sg:website":"www.borgess.com",
    "wof:name":"Textile Systems Inc",
    "wof:placetype":"venue"
},
  "geometry": {"coordinates":[-85.57674900000001,42.300018],"type":"Point"}
}