{
  "type": "Feature",
  "properties": {
    "iso:country":"US",
    "sg:address":"4740 Shabbona Rd",
    "sg:city":"Deckerville",
    "sg:classifiers":[
        {
            "category":"Manufacturing",
            "subcategory":"Rubber & Plastics",
            "type":"Manufacturing & Wholesale Goods"
        }
    ],
    "sg:phone":"+1 810 376 4280",
    "sg:postcode":"48427",
    "sg:province":"MI",
    "sg:tags":[
        "product"
    ],
    "wof:name":"Proto-Craft Inc",
    "wof:placetype":"venue"
},
  "geometry": {"coordinates":[-82.6524,43.5438],"type":"Point"}
}