{
  "type": "Feature",
  "properties": {
    "iso:country":"US",
    "sg:address":"1925 Elkerton Ave",
    "sg:city":"Kalamazoo",
    "sg:classifiers":[
        {
            "category":"Social Services",
            "subcategory":"Child Care",
            "type":"Services"
        }
    ],
    "sg:phone":"+1 269 349 1462",
    "sg:postcode":"49048",
    "sg:province":"MI",
    "wof:name":"Lukisha's Day Care",
    "wof:placetype":"venue"
},
  "geometry": {"coordinates":[-85.55376200000001,42.309844],"type":"Point"}
}