{
  "type": "Feature",
  "properties": {
    "iso:country":"US",
    "sg:address":"533 1st Ct",
    "sg:city":"Niles",
    "sg:classifiers":[
        {
            "category":"Education",
            "subcategory":"School",
            "type":"Public Place"
        }
    ],
    "sg:phone":"+1 269 683 8270",
    "sg:postcode":"49120",
    "sg:province":"MI",
    "wof:name":"Forte Institute",
    "wof:placetype":"venue"
},
  "geometry": {"coordinates":[-86.264195,41.830408],"type":"Point"}
}