{
  "type": "Feature",
  "properties": {
    "iso:country":"US",
    "sg:address":"2370 Wadhams Rd",
    "sg:city":"Kimball",
    "sg:classifiers":[
        {
            "category":"Home & Garden",
            "subcategory":"Building Materials",
            "type":"Retail Goods"
        }
    ],
    "sg:phone":"+1 810 385 1844",
    "sg:postcode":"48074",
    "sg:province":"MI",
    "sg:tags":[
        "modular"
    ],
    "sg:website":"www.midamconstruction.com",
    "wof:name":"Mid-American Sales Office",
    "wof:placetype":"venue"
},
  "geometry": {"coordinates":[-82.543508,42.975992],"type":"Point"}
}