{
  "type": "Feature",
  "properties": {
    "iso:country":"US",
    "sg:address":"3700 Enterprise Dr",
    "sg:city":"Allen Park",
    "sg:classifiers":[
        {
            "category":"Retail",
            "subcategory":"Auto Rental",
            "type":"Services"
        }
    ],
    "sg:phone":"+1 313 271 7724",
    "sg:postcode":"48101",
    "sg:province":"MI",
    "sg:tags":[
        "truck",
        "leasing"
    ],
    "wof:name":"Penske",
    "wof:placetype":"venue"
},
  "geometry": {"coordinates":[-83.21117,42.266482],"type":"Point"}
}