{
  "type": "Feature",
  "properties": {
    "iso:country":"US",
    "sg:address":"803 Verhoeks St",
    "sg:city":"Grand Haven",
    "sg:classifiers":[
        {
            "category":"Professional",
            "subcategory":"Management & Consulting",
            "type":"Services"
        }
    ],
    "sg:phone":"+1 616 844 5050",
    "sg:postcode":"49417",
    "sg:province":"MI",
    "sg:tags":[
        "environmental",
        "consultant"
    ],
    "wof:name":"Lakeshore Environmental",
    "wof:placetype":"venue"
},
  "geometry": {"coordinates":[-86.221874,43.055327],"type":"Point"}
}