{
  "type": "Feature",
  "properties": {
    "iso:country":"US",
    "sg:address":"2833 Ormond Rd",
    "sg:city":"White Lake",
    "sg:classifiers":[
        {
            "category":"Organizations",
            "subcategory":"Community Association",
            "type":"Services"
        }
    ],
    "sg:phone":"+1 248 887 4449",
    "sg:postcode":"48383",
    "sg:province":"MI",
    "wof:name":"Rolling Acres Beach Assn",
    "wof:placetype":"venue"
},
  "geometry": {"coordinates":[-83.55317700000001,42.668652],"type":"Point"}
}