{
  "type": "Feature",
  "properties": {
    "iso:country":"US",
    "sg:address":"218 East Rd",
    "sg:city":"Holly",
    "sg:classifiers":[
        {
            "category":"Social Services",
            "subcategory":"Child Care",
            "type":"Services"
        }
    ],
    "sg:phone":"+1 248 634 3545",
    "sg:postcode":"48442",
    "sg:province":"MI",
    "wof:name":"Sweet Pea Family Daycare",
    "wof:placetype":"venue"
},
  "geometry": {"coordinates":[-83.61312100000001,42.796185],"type":"Point"}
}