{
  "type": "Feature",
  "properties": {
    "iso:country":"US",
    "sg:address":"104 W Clinton St",
    "sg:city":"Durand",
    "sg:classifiers":[
        {
            "category":"Building & Trades",
            "subcategory":"Construction",
            "type":"Services"
        }
    ],
    "sg:phone":"+1 989 288 7454",
    "sg:postcode":"48429",
    "sg:province":"MI",
    "sg:tags":[
        "planning",
        "remodeling",
        "kitchen"
    ],
    "wof:name":"Premier Kitchen & Bath",
    "wof:placetype":"venue"
},
  "geometry": {"coordinates":[-83.984694,42.912056],"type":"Point"}
}