{
  "type": "Feature",
  "properties": {
    "iso:country":"US",
    "sg:address":"20200 Kelly Rd",
    "sg:city":"Harper Woods",
    "sg:classifiers":[
        {
            "category":"Education",
            "subcategory":"School",
            "type":"Public Place"
        }
    ],
    "sg:phone":"+1 313 526 0220",
    "sg:postcode":"48225",
    "sg:province":"MI",
    "sg:tags":[
        "organization",
        "religious"
    ],
    "wof:name":"Regina High School",
    "wof:placetype":"venue"
},
  "geometry": {"coordinates":[-82.94443699999999,42.445488],"type":"Point"}
}