{
  "type": "Feature",
  "properties": {
    "iso:country":"US",
    "sg:address":"902 N Leroy St",
    "sg:city":"Fenton",
    "sg:classifiers":[
        {
            "category":"Personal",
            "subcategory":"Beauty Salon",
            "type":"Services"
        }
    ],
    "sg:phone":"+1 810 750 8898",
    "sg:postcode":"48430",
    "sg:province":"MI",
    "sg:tags":[
        "shop",
        "spa",
        "day"
    ],
    "wof:name":"Flaunt",
    "wof:placetype":"venue"
},
  "geometry": {"coordinates":[-83.70611,42.806527],"type":"Point"}
}