{
  "type": "Feature",
  "properties": {
    "iso:country":"US",
    "sg:address":"4616 Belding Rd",
    "sg:city":"Belding",
    "sg:classifiers":[
        {
            "category":"Farming",
            "subcategory":"Farm",
            "type":"Manufacturing & Wholesale Goods"
        }
    ],
    "sg:phone":"+1 616 794 1312",
    "sg:postcode":"48809",
    "sg:province":"MI",
    "sg:tags":[
        "crop",
        "general"
    ],
    "wof:name":"Gleason Gary Farmer",
    "wof:placetype":"venue"
},
  "geometry": {"coordinates":[-85.168542,43.082889],"type":"Point"}
}