{
  "type": "Feature",
  "properties": {
    "iso:country":"US",
    "sg:address":"9721 Joseph Campau St",
    "sg:city":"Hamtramck",
    "sg:classifiers":[
        {
            "category":"Shopping",
            "subcategory":"Clothing, Apparel, & Fashions",
            "type":"Retail Goods"
        }
    ],
    "sg:phone":"+1 313 873 5053",
    "sg:postcode":"48212",
    "sg:province":"MI",
    "sg:tags":[
        "clothing",
        "women's"
    ],
    "wof:name":"Kim's Style",
    "wof:placetype":"venue"
},
  "geometry": {"coordinates":[-83.05789900000001,42.396599],"type":"Point"}
}