{
  "type": "Feature",
  "properties": {
    "iso:country":"US",
    "sg:address":"604 E Genesee St",
    "sg:city":"Durand",
    "sg:classifiers":[
        {
            "category":"Professional",
            "subcategory":"Art Services",
            "type":"Services"
        }
    ],
    "sg:phone":"+1 989 288 5948",
    "sg:postcode":"48429",
    "sg:province":"MI",
    "sg:tags":[
        "photographer"
    ],
    "wof:name":"Howe Photography Works",
    "wof:placetype":"venue"
},
  "geometry": {"coordinates":[-83.97740400000001,42.913149],"type":"Point"}
}