{
  "type": "Feature",
  "properties": {
    "iso:country":"US",
    "sg:address":"223 S Mears Ave",
    "sg:city":"Whitehall",
    "sg:classifiers":[
        {
            "category":"Travel",
            "subcategory":"Hotels & Motels",
            "type":"Entertainment"
        }
    ],
    "sg:phone":"+1 231 893 0674",
    "sg:postcode":"49461",
    "sg:province":"MI",
    "sg:tags":[
        "breakfast",
        "accommodation",
        "bed"
    ],
    "wof:name":"Cocoa Cottage",
    "wof:placetype":"venue"
},
  "geometry": {"coordinates":[-86.34770399999999,43.408251],"type":"Point"}
}