{
  "type": "Feature",
  "properties": {
    "iso:country":"US",
    "sg:address":"2871 Troy Center Dr",
    "sg:city":"Troy",
    "sg:classifiers":[
        {
            "category":"Building & Trades",
            "subcategory":"Construction",
            "type":"Services"
        }
    ],
    "sg:phone":"+1 248 645 5580",
    "sg:postcode":"48084",
    "sg:province":"MI",
    "sg:tags":[
        "builder",
        "repairer",
        "chimney"
    ],
    "wof:name":"Oakland Chimney & Roof Svc",
    "wof:placetype":"venue"
},
  "geometry": {"coordinates":[-83.16235,42.56418],"type":"Point"}
}