{
  "type": "Feature",
  "properties": {
    "iso:country":"US",
    "sg:address":"33117 Hamilton Ct",
    "sg:city":"Farmington Hills",
    "sg:classifiers":[
        {
            "category":"Professional",
            "subcategory":"Advertising",
            "type":"Services"
        }
    ],
    "sg:phone":"+1 248 553 0800",
    "sg:postcode":"48334",
    "sg:province":"MI",
    "sg:tags":[
        "counselor"
    ],
    "wof:name":"Eidos Group Inc",
    "wof:placetype":"venue"
},
  "geometry": {"coordinates":[-83.375196,42.498371],"type":"Point"}
}