{
  "type": "Feature",
  "properties": {
    "iso:country":"US",
    "sg:address":"151 E Napier Ave",
    "sg:city":"Benton Harbor",
    "sg:classifiers":[
        {
            "category":"Professional",
            "subcategory":"Business Services",
            "type":"Services"
        }
    ],
    "sg:phone":"+1 269 926 7397",
    "sg:postcode":"49022",
    "sg:province":"MI",
    "sg:tags":[
        "trade",
        "exposition",
        "association",
        "fair",
        "show"
    ],
    "sg:website":"www.blossomtimefestival.org",
    "wof:name":"Blossomtime Festival Inc",
    "wof:placetype":"venue"
},
  "geometry": {"coordinates":[-86.452129,42.087144],"type":"Point"}
}