{
  "type": "Feature",
  "properties": {
    "iso:country":"US",
    "sg:address":"144 Schroeder Park Dr",
    "sg:city":"Howell",
    "sg:classifiers":[
        {
            "category":"Organizations",
            "subcategory":"Religious Organization",
            "type":"Services"
        }
    ],
    "sg:phone":"+1 517 548 5920",
    "sg:postcode":"48843",
    "sg:province":"MI",
    "sg:tags":[
        "church"
    ],
    "sg:website":"www.crossroadsapostolicchurch.com",
    "wof:name":"Crossroads Apostolic Church",
    "wof:placetype":"venue"
},
  "geometry": {"coordinates":[-83.932957,42.585403],"type":"Point"}
}