{
  "type": "Feature",
  "properties": {
    "iso:country":"US",
    "sg:address":"22882 Firwood Ave",
    "sg:city":"Eastpointe",
    "sg:classifiers":[
        {
            "category":"Retail",
            "subcategory":"Pet Boarding",
            "type":"Services"
        }
    ],
    "sg:phone":"+1 586 778 3735",
    "sg:postcode":"48021",
    "sg:province":"MI",
    "sg:tags":[
        "boarding/pet",
        "sitting"
    ],
    "wof:name":"Kate's Pet Sitting Service",
    "wof:placetype":"venue"
},
  "geometry": {"coordinates":[-82.96970399999999,42.4678],"type":"Point"}
}