{
  "type": "Feature",
  "properties": {
    "iso:country":"US",
    "sg:address":"3023 E 8 Mile Rd",
    "sg:city":"Warren",
    "sg:classifiers":[
        {
            "category":"Recreation",
            "type":"Entertainment"
        }
    ],
    "sg:phone":"+1 313 538 8029",
    "sg:postcode":"48091",
    "sg:province":"MI",
    "sg:tags":[
        "psychic",
        "medium"
    ],
    "wof:name":"Amanda Psychic Reader",
    "wof:placetype":"venue"
},
  "geometry": {"coordinates":[-83.07407499999999,42.447134],"type":"Point"}
}