{
  "type": "Feature",
  "properties": {
    "iso:country":"US",
    "sg:address":"2760 River Rd",
    "sg:city":"Frankfort",
    "sg:classifiers":[
        {
            "category":"Manufacturing",
            "subcategory":"Soap",
            "type":"Manufacturing & Wholesale Goods"
        }
    ],
    "sg:phone":"+1 231 352 9600",
    "sg:postcode":"49635",
    "sg:province":"MI",
    "sg:tags":[
        "detergent"
    ],
    "wof:name":"Creations Soap",
    "wof:placetype":"venue"
},
  "geometry": {"coordinates":[-86.179929,44.616059],"type":"Point"}
}