{
  "type": "Feature",
  "properties": {
    "iso:country":"US",
    "sg:address":"2122 E Hemphill Rd",
    "sg:city":"Burton",
    "sg:classifiers":[
        {
            "category":"Building & Trades",
            "subcategory":"Construction",
            "type":"Services"
        }
    ],
    "sg:phone":"+1 810 742 8679",
    "sg:postcode":"48509",
    "sg:province":"MI",
    "sg:tags":[
        "contractor"
    ],
    "wof:name":"Twiss Group the",
    "wof:placetype":"venue"
},
  "geometry": {"coordinates":[-83.668914,42.980304],"type":"Point"}
}