{
  "type": "Feature",
  "properties": {
    "iso:country":"US",
    "sg:address":"151 S Rose St",
    "sg:city":"Kalamazoo",
    "sg:classifiers":[
        {
            "category":"Health Services",
            "subcategory":"Hospital",
            "type":"Services"
        }
    ],
    "sg:phone":"+1 269 303 1711",
    "sg:postcode":"49007",
    "sg:province":"MI",
    "sg:tags":[
        "mental"
    ],
    "wof:name":"Sherry Opalka",
    "wof:placetype":"venue"
},
  "geometry": {"coordinates":[-85.584659,42.290934],"type":"Point"}
}