{
  "type": "Feature",
  "properties": {
    "iso:country":"US",
    "sg:address":"157 N Eton St",
    "sg:city":"Birmingham",
    "sg:classifiers":[
        {
            "category":"Retail",
            "subcategory":"Portrait Studio",
            "type":"Services"
        }
    ],
    "sg:phone":"+1 248 822 3040",
    "sg:postcode":"48009",
    "sg:province":"MI",
    "sg:tags":[
        "photo"
    ],
    "wof:name":"Laurie Tennent Studio",
    "wof:placetype":"venue"
},
  "geometry": {"coordinates":[-83.196123,42.54792],"type":"Point"}
}