{
  "type": "Feature",
  "properties": {
    "iso:country":"US",
    "sg:address":"2855 44th St SW",
    "sg:city":"Grandville",
    "sg:classifiers":[
        {
            "category":"Professional",
            "subcategory":"Accounting & Tax Preparation",
            "type":"Services"
        }
    ],
    "sg:phone":"+1 616 534 5985",
    "sg:postcode":"49418",
    "sg:province":"MI",
    "sg:tags":[
        "accountant"
    ],
    "wof:name":"MAS Advisory Svc",
    "wof:placetype":"venue"
},
  "geometry": {"coordinates":[-85.736034,42.884753],"type":"Point"}
}