{
  "type": "Feature",
  "properties": {
    "iso:country":"US",
    "sg:address":"3914 Martin St",
    "sg:city":"Detroit",
    "sg:classifiers":[
        {
            "category":"Building & Trades",
            "subcategory":"Construction",
            "type":"Services"
        }
    ],
    "sg:phone":"+1 313 898 9380",
    "sg:postcode":"48210",
    "sg:province":"MI",
    "sg:tags":[
        "contractor"
    ],
    "wof:name":"Tostado Drywall",
    "wof:placetype":"venue"
},
  "geometry": {"coordinates":[-83.12538600000001,42.328309],"type":"Point"}
}