{
  "type": "Feature",
  "properties": {
    "iso:country":"US",
    "sg:address":"2075 Miner Ave",
    "sg:city":"Muskegon",
    "sg:classifiers":[
        {
            "category":"Building & Trades",
            "subcategory":"Landscaping Services",
            "type":"Services"
        }
    ],
    "sg:phone":"+1 231 755 2112",
    "sg:postcode":"49441",
    "sg:province":"MI",
    "sg:tags":[
        "landscape",
        "contractor"
    ],
    "wof:name":"J & J Enterprises",
    "wof:placetype":"venue"
},
  "geometry": {"coordinates":[-86.29647300000001,43.212477],"type":"Point"}
}