{
  "type": "Feature",
  "properties": {
    "iso:country":"US",
    "sg:address":"2585 Sunnyknoll Ave",
    "sg:city":"Berkley",
    "sg:classifiers":[
        {
            "category":"Real Estate",
            "subcategory":"Real Estate Agent",
            "type":"Services"
        }
    ],
    "sg:phone":"+1 248 547 6493",
    "sg:postcode":"48072",
    "sg:province":"MI",
    "sg:tags":[
        "mall",
        "owns",
        "shopping",
        "operates"
    ],
    "wof:name":"Huntington Square Partnership",
    "wof:placetype":"venue"
},
  "geometry": {"coordinates":[-83.18613499999999,42.49461],"type":"Point"}
}