{
  "type": "Feature",
  "properties": {
    "iso:country":"US",
    "sg:address":"4530 Sheridan Rd",
    "sg:city":"Flushing",
    "sg:classifiers":[
        {
            "category":"Retail",
            "subcategory":"Auto Repair",
            "type":"Services"
        }
    ],
    "sg:phone":"+1 810 659 6012",
    "sg:postcode":"48433",
    "sg:province":"MI",
    "sg:tags":[
        "repairing",
        "automobile"
    ],
    "wof:name":"Lewis Garage",
    "wof:placetype":"venue"
},
  "geometry": {"coordinates":[-83.928737,43.071343],"type":"Point"}
}