{
  "type": "Feature",
  "properties": {
    "iso:country":"US",
    "sg:address":"3289 Schust Rd",
    "sg:city":"Saginaw",
    "sg:classifiers":[
        {
            "category":"Real Estate",
            "subcategory":"Real Estate Operator",
            "type":"Services"
        }
    ],
    "sg:phone":"+1 989 249 1700",
    "sg:postcode":"48603",
    "sg:province":"MI",
    "sg:tags":[
        "building",
        "apartment"
    ],
    "wof:name":"Saginaw Pointe Apartments",
    "wof:placetype":"venue"
},
  "geometry": {"coordinates":[-83.97787700000001,43.472551],"type":"Point"}
}