{
  "type": "Feature",
  "properties": {
    "iso:country":"US",
    "sg:address":"28225 Hoover Rd",
    "sg:city":"Warren",
    "sg:classifiers":[
        {
            "category":"Health Services",
            "subcategory":"Dentist",
            "type":"Services"
        }
    ],
    "sg:phone":"+1 586 751 6868",
    "sg:postcode":"48093",
    "sg:province":"MI",
    "sg:tags":[
        "dental",
        "clinic"
    ],
    "sg:website":"www.appledental.com",
    "wof:name":"Apple Dental of Warren",
    "wof:placetype":"venue"
},
  "geometry": {"coordinates":[-83.006699,42.501301],"type":"Point"}
}