{
  "type": "Feature",
  "properties": {
    "iso:country":"US",
    "sg:address":"4012 Sheffield Blvd",
    "sg:city":"Lansing",
    "sg:classifiers":[
        {
            "category":"Social Services",
            "subcategory":"Adult Care",
            "type":"Services"
        }
    ],
    "sg:phone":"+1 517 882 7668",
    "sg:postcode":"48911",
    "sg:province":"MI",
    "sg:tags":[
        "day",
        "provider"
    ],
    "wof:name":"Rosie Lee Perteet",
    "wof:placetype":"venue"
},
  "geometry": {"coordinates":[-84.606711,42.693694],"type":"Point"}
}