{
  "type": "Feature",
  "properties": {
    "iso:country":"US",
    "sg:address":"516 S Cochran Ave",
    "sg:city":"Charlotte",
    "sg:classifiers":[
        {
            "category":"Shopping",
            "subcategory":"Gifts & Souvenirs",
            "type":"Retail Goods"
        }
    ],
    "sg:phone":"+1 517 543 2219",
    "sg:postcode":"48813",
    "sg:province":"MI",
    "wof:name":"Roses & Lace By Kara",
    "wof:placetype":"venue"
},
  "geometry": {"coordinates":[-84.835916,42.556077],"type":"Point"}
}