{
  "type": "Feature",
  "properties": {
    "iso:country":"US",
    "sg:address":"3700 Abbott Rd",
    "sg:city":"Reading",
    "sg:classifiers":[
        {
            "category":"Social Services",
            "subcategory":"Adult Care",
            "type":"Services"
        }
    ],
    "sg:phone":"+1 517 283 2314",
    "sg:postcode":"49274",
    "sg:province":"MI",
    "sg:tags":[
        "foster"
    ],
    "wof:name":"Abbott Manor Inc",
    "wof:placetype":"venue"
},
  "geometry": {"coordinates":[-84.76740100000001,41.873374],"type":"Point"}
}