{
  "type": "Feature",
  "properties": {
    "iso:country":"US",
    "sg:address":"27447 Parkview Blvd",
    "sg:city":"Warren",
    "sg:classifiers":[
        {
            "category":"Professional",
            "subcategory":"Computer Services",
            "type":"Services"
        }
    ],
    "sg:phone":"+1 586 751 1064",
    "sg:postcode":"48092",
    "sg:province":"MI",
    "sg:tags":[
        "datum"
    ],
    "wof:name":"Webahn Inc",
    "wof:placetype":"venue"
},
  "geometry": {"coordinates":[-83.082916,42.493016],"type":"Point"}
}