{
  "type": "Feature",
  "properties": {
    "iso:country":"US",
    "sg:address":"2023 Cedar St",
    "sg:city":"Holt",
    "sg:classifiers":[
        {
            "category":"Building & Trades",
            "subcategory":"Electrical",
            "type":"Services"
        }
    ],
    "sg:phone":"+1 517 628 2373",
    "sg:postcode":"48842",
    "sg:province":"MI",
    "sg:tags":[
        "electrical",
        "contractor"
    ],
    "wof:name":"Custom Electric Inc",
    "wof:placetype":"venue"
},
  "geometry": {"coordinates":[-84.515298,42.640297],"type":"Point"}
}