{
  "type": "Feature",
  "properties": {
    "iso:country":"US",
    "sg:address":"2290 28th St SW",
    "sg:city":"Wyoming",
    "sg:classifiers":[
        {
            "category":"Sports & Exercise",
            "subcategory":"Gym",
            "type":"Entertainment"
        }
    ],
    "sg:phone":"+1 616 530 2115",
    "sg:postcode":"49519",
    "sg:province":"MI",
    "sg:tags":[
        "club",
        "health",
        "studio",
        "gymnasium"
    ],
    "wof:name":"Fitzone",
    "wof:placetype":"venue"
},
  "geometry": {"coordinates":[-85.72182100000001,42.913801],"type":"Point"}
}