{
  "type": "Feature",
  "properties": {
    "iso:country":"US",
    "sg:address":"236 W Leigh St",
    "sg:city":"Homer",
    "sg:classifiers":[
        {
            "category":"Restaurant",
            "type":"Food & Drink"
        }
    ],
    "sg:phone":"+1 517 568 4568",
    "sg:postcode":"49245",
    "sg:province":"MI",
    "sg:tags":[
        "parlor",
        "ice",
        "cream"
    ],
    "wof:name":"Renfroe Dairy Delite",
    "wof:placetype":"venue"
},
  "geometry": {"coordinates":[-84.812934,42.147274],"type":"Point"}
}