{
  "type": "Feature",
  "properties": {
    "iso:country":"US",
    "sg:address":"30966 Bramley Cir",
    "sg:city":"New Hudson",
    "sg:classifiers":[
        {
            "category":"Retail",
            "subcategory":"Repair Shop",
            "type":"Services"
        }
    ],
    "sg:phone":"+1 248 437 1059",
    "sg:postcode":"48165",
    "sg:province":"MI",
    "wof:name":"Beverage Services Ltd",
    "wof:placetype":"venue"
},
  "geometry": {"coordinates":[-83.63851699999999,42.518005],"type":"Point"}
}