{
  "type": "Feature",
  "properties": {
    "iso:country":"US",
    "sg:address":"2209 Cromie Dr",
    "sg:city":"Warren",
    "sg:classifiers":[
        {
            "category":"Building & Trades",
            "subcategory":"Construction",
            "type":"Services"
        }
    ],
    "sg:phone":"+1 248 399 6840",
    "sg:postcode":"48092",
    "sg:province":"MI",
    "sg:tags":[
        "demolition",
        "contractor"
    ],
    "wof:name":"E & N Excavating",
    "wof:placetype":"venue"
},
  "geometry": {"coordinates":[-83.084102,42.514633],"type":"Point"}
}