{
  "type": "Feature",
  "properties": {
    "iso:country":"US",
    "sg:address":"529 W Main St",
    "sg:city":"Brighton",
    "sg:classifiers":[
        {
            "category":"Retail",
            "subcategory":"Repair Shop",
            "type":"Services"
        }
    ],
    "sg:phone":"+1 810 227 5153",
    "sg:postcode":"48116",
    "sg:province":"MI",
    "sg:tags":[
        "lock",
        "locksmith"
    ],
    "wof:name":"Howell Security Lock",
    "wof:placetype":"venue"
},
  "geometry": {"coordinates":[-83.785786,42.529358],"type":"Point"}
}