{
  "type": "Feature",
  "properties": {
    "iso:country":"US",
    "sg:address":"684 W Traverse Lake Rd",
    "sg:city":"Maple City",
    "sg:classifiers":[
        {
            "category":"Real Estate",
            "subcategory":"Real Estate Agent",
            "type":"Services"
        }
    ],
    "sg:phone":"+1 231 228 2020",
    "sg:postcode":"49664",
    "sg:province":"MI",
    "wof:name":"Sleeping Bear Properties",
    "wof:placetype":"venue"
},
  "geometry": {"coordinates":[-85.864178,44.92424],"type":"Point"}
}