{
  "type": "Feature",
  "properties": {
    "iso:country":"US",
    "sg:address":"3651 Balfour Ct",
    "sg:city":"Flint",
    "sg:classifiers":[
        {
            "category":"Real Estate",
            "subcategory":"Real Estate Operator",
            "type":"Services"
        }
    ],
    "sg:phone":"+1 810 233 6307",
    "sg:postcode":"48507",
    "sg:province":"MI",
    "sg:tags":[
        "building",
        "apartment"
    ],
    "wof:name":"Westgate Park Manor",
    "wof:placetype":"venue"
},
  "geometry": {"coordinates":[-83.708702,42.989498],"type":"Point"}
}