{
  "type": "Feature",
  "properties": {
    "iso:country":"US",
    "sg:address":"63 Maple St",
    "sg:city":"Manistee",
    "sg:classifiers":[
        {
            "category":"Real Estate",
            "subcategory":"Real Estate Services",
            "type":"Services"
        }
    ],
    "sg:phone":"+1 231 723 3397",
    "sg:postcode":"49660",
    "sg:province":"MI",
    "sg:tags":[
        "abstract",
        "title"
    ],
    "wof:name":"Manistee Abstract & Title Co",
    "wof:placetype":"venue"
},
  "geometry": {"coordinates":[-86.32369199999999,44.246746],"type":"Point"}
}