{
  "type": "Feature",
  "properties": {
    "iso:country":"US",
    "sg:address":"3535 Grand Oaks Dr",
    "sg:city":"Howell",
    "sg:classifiers":[
        {
            "category":"Government",
            "subcategory":"Office",
            "type":"Public Place"
        }
    ],
    "sg:phone":"+1 517 546 4250",
    "sg:postcode":"48843",
    "sg:province":"MI",
    "sg:tags":[
        "commission",
        "road"
    ],
    "wof:name":"Livingston County Road Comm",
    "wof:placetype":"venue"
},
  "geometry": {"coordinates":[-83.881743,42.578952],"type":"Point"}
}