{
  "type": "Feature",
  "properties": {
    "iso:country":"US",
    "sg:address":"14364 Carleton West Rd",
    "sg:city":"Carleton",
    "sg:phone":"+1 734 654 8625",
    "sg:postcode":"48117",
    "sg:province":"MI",
    "sg:tags":[
        "farm",
        "corn"
    ],
    "wof:name":"Robert Crouch",
    "wof:placetype":"venue"
},
  "geometry": {"coordinates":[-83.430932,42.087648],"type":"Point"}
}