{
  "type": "Feature",
  "properties": {
    "iso:country":"US",
    "sg:address":"8502 Portage Rd",
    "sg:city":"Portage",
    "sg:classifiers":[
        {
            "category":"Building & Trades",
            "subcategory":"Construction",
            "type":"Services"
        }
    ],
    "sg:phone":"+1 269 324 5991",
    "sg:postcode":"49002",
    "sg:province":"MI",
    "sg:tags":[
        "contractor"
    ],
    "wof:name":"American Village Builders",
    "wof:placetype":"venue"
},
  "geometry": {"coordinates":[-85.561689,42.192429],"type":"Point"}
}