{
  "type": "Feature",
  "properties": {
    "iso:country":"US",
    "sg:address":"537 Chicago Ave",
    "sg:city":"Kalamazoo",
    "sg:classifiers":[
        {
            "category":"Health Services",
            "subcategory":"Nursing And Care Facility",
            "type":"Services"
        }
    ],
    "sg:phone":"+1 269 382 2392",
    "sg:postcode":"49048",
    "sg:province":"MI",
    "sg:tags":[
        "home",
        "skilled",
        "convalescent"
    ],
    "sg:website":"www.borgess.com",
    "wof:name":"Borgess Nursing Home Inc",
    "wof:placetype":"venue"
},
  "geometry": {"coordinates":[-85.552875,42.297021],"type":"Point"}
}