{
  "type": "Feature",
  "properties": {
    "iso:country":"US",
    "sg:address":"51202 Romeo Plank Rd",
    "sg:city":"Macomb",
    "sg:classifiers":[
        {
            "category":"Shopping",
            "subcategory":"Florist",
            "type":"Retail Goods"
        }
    ],
    "sg:phone":"+1 586 575 9770",
    "sg:postcode":"48042",
    "sg:province":"MI",
    "wof:name":"Roses Of Warren",
    "wof:placetype":"venue"
},
  "geometry": {"coordinates":[-82.94235399999999,42.674759],"type":"Point"}
}