{
  "type": "Feature",
  "properties": {
    "iso:country":"US",
    "sg:address":"2007 S Michigan Ave",
    "sg:city":"Saginaw",
    "sg:classifiers":[
        {
            "category":"Building & Trades",
            "subcategory":"Construction",
            "type":"Services"
        }
    ],
    "sg:phone":"+1 989 799 9447",
    "sg:postcode":"48602",
    "sg:province":"MI",
    "sg:tags":[
        "woodworker"
    ],
    "wof:name":"Poor Boy Woodworks",
    "wof:placetype":"venue"
},
  "geometry": {"coordinates":[-83.979148,43.405708],"type":"Point"}
}