{
  "type": "Feature",
  "properties": {
    "iso:country":"US",
    "sg:address":"6700 Whitmore Lake Rd",
    "sg:city":"Brighton",
    "sg:classifiers":[
        {
            "category":"Wholesale",
            "subcategory":"Toys & Hobbies",
            "type":"Manufacturing & Wholesale Goods"
        }
    ],
    "sg:phone":"+1 810 220 8950",
    "sg:postcode":"48116",
    "sg:province":"MI",
    "sg:tags":[
        "wholesaler"
    ],
    "wof:name":"Costco Wholesale Inc",
    "wof:placetype":"venue"
},
  "geometry": {"coordinates":[-83.759906,42.504892],"type":"Point"}
}