{
  "type": "Feature",
  "properties": {
    "iso:country":"US",
    "sg:address":"629 S Saginaw St",
    "sg:city":"Flint",
    "sg:classifiers":[
        {
            "category":"Manufacturing",
            "subcategory":"Printing",
            "type":"Manufacturing & Wholesale Goods"
        }
    ],
    "sg:phone":"+1 810 233 3000",
    "sg:postcode":"48502",
    "sg:province":"MI",
    "sg:tags":[
        "newspaper"
    ],
    "wof:name":"Uncommon Sense",
    "wof:placetype":"venue"
},
  "geometry": {"coordinates":[-83.689177,43.014363],"type":"Point"}
}