{
  "type": "Feature",
  "properties": {
    "iso:country":"US",
    "sg:address":"2609 Charlevoix Ave",
    "sg:city":"Petoskey",
    "sg:classifiers":[
        {
            "category":"Professional",
            "subcategory":"Business Services",
            "type":"Services"
        }
    ],
    "sg:phone":"+1 231 439 3234",
    "sg:postcode":"49770",
    "sg:province":"MI",
    "sg:tags":[
        "interior",
        "consultant",
        "design",
        "decorator"
    ],
    "wof:name":"Periwinkle Lane",
    "wof:placetype":"venue"
},
  "geometry": {"coordinates":[-85.004599,45.366942],"type":"Point"}
}