{
  "type": "Feature",
  "properties": {
    "iso:country":"US",
    "sg:address":"11730 Fowler Rd",
    "sg:city":"Honor",
    "sg:classifiers":[
        {
            "category":"Retail",
            "subcategory":"Repair Shop",
            "type":"Services"
        }
    ],
    "sg:phone":"+1 231 325 2080",
    "sg:postcode":"49640",
    "sg:province":"MI",
    "sg:tags":[
        "welding"
    ],
    "wof:name":"Kerby Welding Inc",
    "wof:placetype":"venue"
},
  "geometry": {"coordinates":[-86.00466,44.747562],"type":"Point"}
}