{
  "type": "Feature",
  "properties": {
    "iso:country":"US",
    "sg:address":"1127 Centre St",
    "sg:city":"Traverse City",
    "sg:classifiers":[
        {
            "category":"Recreation",
            "type":"Entertainment"
        }
    ],
    "sg:phone":"+1 231 933 4744",
    "sg:postcode":"49686",
    "sg:province":"MI",
    "wof:name":"Ata Black Belt Academy Inc",
    "wof:placetype":"venue"
},
  "geometry": {"coordinates":[-85.595089,44.751493],"type":"Point"}
}