{
  "type": "Feature",
  "properties": {
    "iso:country":"US",
    "sg:address":"3603 N Main St",
    "sg:city":"Wayland",
    "sg:classifiers":[
        {
            "category":"Home & Garden",
            "subcategory":"Garden Supply",
            "type":"Retail Goods"
        }
    ],
    "sg:phone":"+1 269 792 0044",
    "sg:postcode":"49348",
    "sg:province":"MI",
    "sg:tags":[
        "landscaping",
        "equipment"
    ],
    "sg:website":"www.curv-rite.com",
    "wof:name":"Curv-Rite",
    "wof:placetype":"venue"
},
  "geometry": {"coordinates":[-85.643653,42.682534],"type":"Point"}
}