{
  "type": "Feature",
  "properties": {
    "iso:country":"US",
    "sg:address":"2184 Wealthy St SE",
    "sg:city":"Grand Rapids",
    "sg:classifiers":[
        {
            "category":"Retail",
            "subcategory":"Laundry & Dry Cleaning",
            "type":"Services"
        }
    ],
    "sg:phone":"+1 616 458 2088",
    "sg:postcode":"49506",
    "sg:province":"MI",
    "sg:tags":[
        "drycleaning",
        "plant"
    ],
    "wof:name":"Sheldon Clrs Tlrs & Shirt Ldry",
    "wof:placetype":"venue"
},
  "geometry": {"coordinates":[-85.61435,42.95044],"type":"Point"}
}