{
  "type": "Feature",
  "properties": {
    "iso:country":"US",
    "sg:address":"1239 Princeton Rd",
    "sg:city":"Berkley",
    "sg:classifiers":[
        {
            "category":"Building & Trades",
            "subcategory":"Construction",
            "type":"Services"
        }
    ],
    "sg:phone":"+1 248 542 7000",
    "sg:postcode":"48072",
    "sg:province":"MI",
    "sg:tags":[
        "house"
    ],
    "wof:name":"Home Remodeling Inc",
    "wof:placetype":"venue"
},
  "geometry": {"coordinates":[-83.16981199999999,42.489892],"type":"Point"}
}