{
  "type": "Feature",
  "properties": {
    "iso:country":"US",
    "sg:address":"506 Tawas St",
    "sg:city":"East Tawas",
    "sg:classifiers":[
        {
            "category":"Shopping",
            "subcategory":"Jewelry",
            "type":"Retail Goods"
        }
    ],
    "sg:phone":"+1 989 362 5748",
    "sg:postcode":"48730",
    "sg:province":"MI",
    "sg:tags":[
        "jeweler"
    ],
    "wof:name":"Dick's Silver-N-Gems",
    "wof:placetype":"venue"
},
  "geometry": {"coordinates":[-83.489592,44.285838],"type":"Point"}
}