{
  "type": "Feature",
  "properties": {
    "iso:country":"US",
    "sg:address":"4308 Nancy Ln",
    "sg:city":"White Lake",
    "sg:classifiers":[
        {
            "category":"Building & Trades",
            "subcategory":"Construction",
            "type":"Services"
        }
    ],
    "sg:phone":"+1 248 887 0700",
    "sg:postcode":"48383",
    "sg:province":"MI",
    "sg:tags":[
        "house"
    ],
    "wof:name":"Home Creators",
    "wof:placetype":"venue"
},
  "geometry": {"coordinates":[-83.549526,42.677261],"type":"Point"}
}