{
  "type": "Feature",
  "properties": {
    "iso:country":"US",
    "sg:address":"204 W State St",
    "sg:city":"Mancelona",
    "sg:classifiers":[
        {
            "category":"Health Services",
            "subcategory":"Doctor",
            "type":"Services"
        }
    ],
    "sg:phone":"+1 231 587 9458",
    "sg:postcode":"49659",
    "sg:province":"MI",
    "sg:tags":[
        "dentist"
    ],
    "wof:name":"Mancelona Family Dentistry",
    "wof:placetype":"venue"
},
  "geometry": {"coordinates":[-85.06331900000001,44.902484],"type":"Point"}
}