{
  "type": "Feature",
  "properties": {
    "iso:country":"US",
    "sg:address":"50 Filer St",
    "sg:city":"Manistee",
    "sg:classifiers":[
        {
            "category":"Building & Trades",
            "subcategory":"Construction",
            "type":"Services"
        }
    ],
    "sg:phone":"+1 231 723 9490",
    "sg:postcode":"49660",
    "sg:province":"MI",
    "wof:name":"Deltrek Inc",
    "wof:placetype":"venue"
},
  "geometry": {"coordinates":[-86.318927,44.247611],"type":"Point"}
}