{
  "type": "Feature",
  "properties": {
    "iso:country":"US",
    "sg:address":"504 Maus Ave",
    "sg:city":"Ypsilanti",
    "sg:classifiers":[
        {
            "category":"Building & Trades",
            "subcategory":"Electrical",
            "type":"Services"
        }
    ],
    "sg:phone":"+1 734 482 4466",
    "sg:postcode":"48198",
    "sg:province":"MI",
    "sg:tags":[
        "electrical",
        "contractor"
    ],
    "wof:name":"Manier El Electric Service",
    "wof:placetype":"venue"
},
  "geometry": {"coordinates":[-83.597111,42.235379],"type":"Point"}
}