{
  "type": "Feature",
  "properties": {
    "iso:country":"US",
    "sg:address":"403 Huron St",
    "sg:city":"Grayling",
    "sg:classifiers":[
        {
            "category":"Real Estate",
            "subcategory":"Surveying",
            "type":"Services"
        }
    ],
    "sg:phone":"+1 989 348 4036",
    "sg:postcode":"49738",
    "sg:province":"MI",
    "sg:tags":[
        "surveyor"
    ],
    "wof:name":"Myers Land Survey Co",
    "wof:placetype":"venue"
},
  "geometry": {"coordinates":[-84.704329,44.656595],"type":"Point"}
}