{
  "type": "Feature",
  "properties": {
    "iso:country":"US",
    "sg:address":"15600 E State Fair St",
    "sg:city":"Detroit",
    "sg:classifiers":[
        {
            "category":"Education",
            "subcategory":"School",
            "type":"Public Place"
        }
    ],
    "sg:phone":"+1 313 866 2670",
    "sg:postcode":"48205",
    "sg:province":"MI",
    "wof:name":"Detroit Public Schools",
    "wof:placetype":"venue"
},
  "geometry": {"coordinates":[-82.95962900000001,42.442648],"type":"Point"}
}