{
  "type": "Feature",
  "properties": {
    "iso:country":"US",
    "sg:address":"17051 W Warren Ave",
    "sg:city":"Detroit",
    "sg:classifiers":[
        {
            "category":"Professional",
            "subcategory":"Computer Services",
            "type":"Services"
        }
    ],
    "sg:phone":"+1 313 846 4672",
    "sg:postcode":"48228",
    "sg:province":"MI",
    "sg:tags":[
        "repair"
    ],
    "wof:name":"P C Place",
    "wof:placetype":"venue"
},
  "geometry": {"coordinates":[-83.213032,42.343278],"type":"Point"}
}