{
  "type": "Feature",
  "properties": {
    "iso:country":"US",
    "sg:address":"357 S Maple St",
    "sg:city":"Grant",
    "sg:classifiers":[
        {
            "category":"Home & Garden",
            "subcategory":"Garden Supply",
            "type":"Retail Goods"
        }
    ],
    "sg:phone":"+1 231 834 5604",
    "sg:postcode":"49327",
    "sg:province":"MI",
    "sg:tags":[
        "lawn",
        "mower"
    ],
    "wof:name":"Trade-Arama Farm & Garden City",
    "wof:placetype":"venue"
},
  "geometry": {"coordinates":[-85.81065,43.330336],"type":"Point"}
}