{
  "type": "Feature",
  "properties": {
    "iso:country":"US",
    "sg:address":"246 N State St",
    "sg:city":"Big Rapids",
    "sg:classifiers":[
        {
            "category":"Government",
            "subcategory":"Office",
            "type":"Public Place"
        }
    ],
    "sg:phone":"+1 231 796 7649",
    "sg:postcode":"49307",
    "sg:province":"MI",
    "sg:tags":[
        "county"
    ],
    "wof:name":"Mecosta County Area Chmbr-Cmrc",
    "wof:placetype":"venue"
},
  "geometry": {"coordinates":[-85.48393799999999,43.700371],"type":"Point"}
}