{
  "type": "Feature",
  "properties": {
    "iso:country":"US",
    "sg:address":"418 W Grant St",
    "sg:city":"Plainwell",
    "sg:classifiers":[
        {
            "category":"Professional",
            "subcategory":"Computer Services",
            "type":"Services"
        }
    ],
    "sg:phone":"+1 269 685 7072",
    "sg:postcode":"49080",
    "sg:province":"MI",
    "sg:tags":[
        "related"
    ],
    "wof:name":"Sweet Candygrams",
    "wof:placetype":"venue"
},
  "geometry": {"coordinates":[-85.647026,42.440998],"type":"Point"}
}