{
  "type": "Feature",
  "properties": {
    "iso:country":"US",
    "sg:address":"524 S Union St",
    "sg:city":"Parma",
    "sg:classifiers":[
        {
            "category":"Professional",
            "subcategory":"Engineering",
            "type":"Services"
        }
    ],
    "sg:phone":"+1 517 531 5773",
    "sg:postcode":"49269",
    "sg:province":"MI",
    "sg:tags":[
        "engineer"
    ],
    "wof:name":"Omm Engineering Inc",
    "wof:placetype":"venue"
},
  "geometry": {"coordinates":[-84.599868,42.25507],"type":"Point"}
}