{
  "type": "Feature",
  "properties": {
    "iso:country":"US",
    "sg:address":"1795 W Main St",
    "sg:city":"Owosso",
    "sg:classifiers":[
        {
            "category":"Professional",
            "subcategory":"Employment Agencies",
            "type":"Services"
        }
    ],
    "sg:phone":"+1 989 729 6663",
    "sg:postcode":"48867",
    "sg:province":"MI",
    "sg:tags":[
        "opportunity"
    ],
    "wof:name":"Employment Services",
    "wof:placetype":"venue"
},
  "geometry": {"coordinates":[-84.19837699999999,42.997552],"type":"Point"}
}