{
  "type": "Feature",
  "properties": {
    "iso:country":"US",
    "sg:address":"7350 Cooley Lake Rd",
    "sg:city":"Waterford",
    "sg:classifiers":[
        {
            "category":"Education",
            "subcategory":"Library",
            "type":"Public Place"
        }
    ],
    "sg:phone":"+1 248 942 3125",
    "sg:postcode":"48327",
    "sg:province":"MI",
    "wof:name":"Highland Lakes Campus Library",
    "wof:placetype":"venue"
},
  "geometry": {"coordinates":[-83.424177,42.615606],"type":"Point"}
}