{
  "type": "Feature",
  "properties": {
    "iso:country":"US",
    "sg:address":"3277 S Rochester Rd",
    "sg:city":"Rochester Hills",
    "sg:classifiers":[
        {
            "category":"Autos & Motor Vehicles",
            "subcategory":"Automobile Sales",
            "type":"Retail Goods"
        }
    ],
    "sg:phone":"+1 248 852 7200",
    "sg:postcode":"48307",
    "sg:province":"MI",
    "sg:tags":[
        "car",
        "dealer"
    ],
    "sg:website":"www.patmoran.com",
    "wof:name":"Pat Moran Oldsmobile GMC",
    "wof:placetype":"venue"
},
  "geometry": {"coordinates":[-83.131601,42.635123],"type":"Point"}
}