{
  "type": "Feature",
  "properties": {
    "iso:country":"US",
    "sg:address":"21950 Greenfield Rd",
    "sg:city":"Oak Park",
    "sg:classifiers":[
        {
            "category":"Health Services",
            "subcategory":"Dentist",
            "type":"Services"
        }
    ],
    "sg:phone":"+1 248 968 6800",
    "sg:postcode":"48237",
    "sg:province":"MI",
    "wof:name":"Pinewood Dental Associates",
    "wof:placetype":"venue"
},
  "geometry": {"coordinates":[-83.200699,42.455502],"type":"Point"}
}