{
  "type": "Feature",
  "properties": {
    "iso:country":"US",
    "sg:address":"2384 Stratton Rd",
    "sg:city":"Benton Harbor",
    "sg:classifiers":[
        {
            "category":"Retail",
            "subcategory":"Portrait Studio",
            "type":"Services"
        }
    ],
    "sg:phone":"+1 269 925 0991",
    "sg:postcode":"49022",
    "sg:province":"MI",
    "sg:tags":[
        "photographer",
        "photo"
    ],
    "wof:name":"James Meister Photography",
    "wof:placetype":"venue"
},
  "geometry": {"coordinates":[-86.442744,42.075658],"type":"Point"}
}