{
  "type": "Feature",
  "properties": {
    "iso:country":"US",
    "sg:address":"436 N Park St",
    "sg:city":"Kalamazoo",
    "sg:classifiers":[
        {
            "category":"Professional",
            "type":"Services"
        }
    ],
    "sg:phone":"+1 269 341 4367",
    "sg:postcode":"49007",
    "sg:province":"MI",
    "sg:tags":[
        "sculptor"
    ],
    "wof:name":"Sculptures By Lewis Tardy",
    "wof:placetype":"venue"
},
  "geometry": {"coordinates":[-85.587413,42.29537],"type":"Point"}
}