{
  "type": "Feature",
  "properties": {
    "iso:country":"US",
    "sg:address":"39 N Ortonville Rd",
    "sg:city":"Ortonville",
    "sg:classifiers":[
        {
            "category":"Restaurant",
            "type":"Food & Drink"
        }
    ],
    "sg:phone":"+1 248 627 3330",
    "sg:postcode":"48462",
    "sg:province":"MI",
    "wof:name":"Filling Station Cafe",
    "wof:placetype":"venue"
},
  "geometry": {"coordinates":[-83.452485,42.852892],"type":"Point"}
}