{
  "type": "Feature",
  "properties": {
    "iso:country":"US",
    "sg:address":"1422 S Shore Dr",
    "sg:city":"Holland",
    "sg:classifiers":[
        {
            "category":"Travel",
            "subcategory":"Hotels & Motels",
            "type":"Entertainment"
        }
    ],
    "sg:phone":"+1 616 335 2525",
    "sg:postcode":"49423",
    "sg:province":"MI",
    "sg:tags":[
        "operation"
    ],
    "wof:name":"Inn At Old Orchard Road",
    "wof:placetype":"venue"
},
  "geometry": {"coordinates":[-86.16739099999999,42.774959],"type":"Point"}
}