{
  "type": "Feature",
  "properties": {
    "iso:country":"US",
    "sg:address":"10 Delaware St SW",
    "sg:city":"Grand Rapids",
    "sg:classifiers":[
        {
            "category":"Personal",
            "subcategory":"Beauty Salon",
            "type":"Services"
        }
    ],
    "sg:phone":"+1 616 247 0620",
    "sg:postcode":"49507",
    "sg:province":"MI",
    "sg:tags":[
        "manicuring"
    ],
    "wof:name":"T Nails",
    "wof:placetype":"venue"
},
  "geometry": {"coordinates":[-85.67050999999999,42.945965],"type":"Point"}
}