{
  "type": "Feature",
  "properties": {
    "iso:country":"US",
    "sg:address":"1758 Plymouth Rd",
    "sg:city":"Ann Arbor",
    "sg:classifiers":[
        {
            "category":"Retail",
            "subcategory":"Laundry & Dry Cleaning",
            "type":"Services"
        }
    ],
    "sg:phone":"+1 734 662 0440",
    "sg:postcode":"48105",
    "sg:province":"MI",
    "sg:tags":[
        "drycleaning",
        "plant"
    ],
    "wof:name":"Ace Cleaners",
    "wof:placetype":"venue"
},
  "geometry": {"coordinates":[-83.728776,42.297223],"type":"Point"}
}