{
  "type": "Feature",
  "properties": {
    "iso:country":"US",
    "sg:address":"6979 Hillside Pl",
    "sg:city":"Port Sanilac",
    "sg:classifiers":[
        {
            "category":"Insurance",
            "subcategory":"Insurance Agent",
            "type":"Services"
        }
    ],
    "sg:phone":"+1 810 622 8164",
    "sg:postcode":"48469",
    "sg:province":"MI",
    "wof:name":"William Cayce",
    "wof:placetype":"venue"
},
  "geometry": {"coordinates":[-82.55559,43.453874],"type":"Point"}
}