{
  "type": "Feature",
  "properties": {
    "iso:country":"US",
    "sg:address":"8544 Walnut Road 0 1",
    "sg:city":"Stephenson",
    "sg:classifiers":[
        {
            "category":"Education",
            "subcategory":"School",
            "type":"Public Place"
        }
    ],
    "sg:phone":"+1 906 753 2232",
    "sg:postcode":"49887",
    "sg:province":"MI",
    "wof:name":"Stephenson Area Public Schools",
    "wof:placetype":"venue"
},
  "geometry": {"coordinates":[-87.614664,45.427615],"type":"Point"}
}