{
  "type": "Feature",
  "properties": {
    "iso:country":"US",
    "sg:address":"9920 Wolven Ave NE",
    "sg:city":"Rockford",
    "sg:classifiers":[
        {
            "category":"Building & Trades",
            "subcategory":"Construction",
            "type":"Services"
        }
    ],
    "sg:phone":"+1 616 866 7087",
    "sg:postcode":"49341",
    "sg:province":"MI",
    "sg:tags":[
        "house"
    ],
    "wof:name":"Dennis Dusendang Builders",
    "wof:placetype":"venue"
},
  "geometry": {"coordinates":[-85.58590599999999,43.143982],"type":"Point"}
}