{
  "type": "Feature",
  "properties": {
    "iso:country":"US",
    "sg:address":"3038 N Kings Hwy",
    "sg:city":"Luther",
    "sg:classifiers":[
        {
            "category":"Food & Beverages",
            "subcategory":"Groceries & Convenience Stores",
            "type":"Retail Goods"
        }
    ],
    "sg:phone":"+1 231 797 5411",
    "sg:postcode":"49656",
    "sg:province":"MI",
    "sg:tags":[
        "grocer"
    ],
    "wof:name":"Old Carrieville Store",
    "wof:placetype":"venue"
},
  "geometry": {"coordinates":[-85.722227,44.031459],"type":"Point"}
}