{
  "type": "Feature",
  "properties": {
    "iso:country":"US",
    "sg:address":"2654 Lake Michigan Dr NW",
    "sg:city":"Grand Rapids",
    "sg:classifiers":[
        {
            "category":"Professional",
            "subcategory":"Management & Consulting",
            "type":"Services"
        }
    ],
    "sg:phone":"+1 616 735 4231",
    "sg:postcode":"49504",
    "sg:province":"MI",
    "sg:tags":[
        "business"
    ],
    "wof:name":"Dalmatian Systems",
    "wof:placetype":"venue"
},
  "geometry": {"coordinates":[-85.735123,42.971667],"type":"Point"}
}