{
  "type": "Feature",
  "properties": {
    "iso:country":"US",
    "sg:address":"120 S Main St",
    "sg:city":"Milford",
    "sg:classifiers":[
        {
            "category":"Health Services",
            "subcategory":"Doctor",
            "type":"Services"
        }
    ],
    "sg:phone":"+1 248 684 2280",
    "sg:postcode":"48381",
    "sg:province":"MI",
    "sg:tags":[
        "dentist"
    ],
    "wof:name":"Water Park Family Dental",
    "wof:placetype":"venue"
},
  "geometry": {"coordinates":[-83.60055,42.586432],"type":"Point"}
}