{
  "type": "Feature",
  "properties": {
    "iso:country":"US",
    "sg:address":"3195 18th Ln",
    "sg:city":"Escanaba",
    "sg:classifiers":[
        {
            "category":"Professional",
            "subcategory":"Business Services",
            "type":"Services"
        }
    ],
    "sg:phone":"+1 906 789 9491",
    "sg:postcode":"49829",
    "sg:province":"MI",
    "sg:tags":[
        "fund",
        "promotion",
        "raising"
    ],
    "wof:name":"Peninsula Promotions Inc",
    "wof:placetype":"venue"
},
  "geometry": {"coordinates":[-87.2069,45.796807],"type":"Point"}
}