{
  "type": "Feature",
  "properties": {
    "iso:country":"US",
    "sg:address":"1541 E Lafayette St",
    "sg:city":"Detroit",
    "sg:classifiers":[
        {
            "category":"Restaurant",
            "type":"Food & Drink"
        }
    ],
    "sg:phone":"+1 313 567 8424",
    "sg:postcode":"48207",
    "sg:province":"MI",
    "sg:tags":[
        "thai"
    ],
    "sg:website":"www.baimaithai.com/",
    "wof:name":"Bai Mai Thai",
    "wof:placetype":"venue"
},
  "geometry": {"coordinates":[-83.032184,42.338634],"type":"Point"}
}