{
  "type": "Feature",
  "properties": {
    "iso:country":"US",
    "sg:address":"6363 136th Ave",
    "sg:city":"Holland",
    "sg:classifiers":[
        {
            "category":"Restaurant",
            "type":"Food & Drink"
        }
    ],
    "sg:menulink":"http://www.allmenus.com/mi/olive/142346-subway/menu/",
    "sg:phone":"+1 616 399 8107",
    "sg:postcode":"49424",
    "sg:province":"MI",
    "sg:tags":[
        "american",
        "sandwich"
    ],
    "wof:name":"Subway",
    "wof:placetype":"venue"
},
  "geometry": {"coordinates":[-86.11977,42.88609],"type":"Point"}
}