{
  "type": "Feature",
  "properties": {
    "iso:country":"US",
    "sg:address":"29999 Groesbeck Hwy",
    "sg:city":"Roseville",
    "sg:classifiers":[
        {
            "category":"Retail",
            "subcategory":"Auto Repair",
            "type":"Services"
        }
    ],
    "sg:phone":"+1 586 445 8822",
    "sg:postcode":"48066",
    "sg:province":"MI",
    "wof:name":"A & B Motors Inc",
    "wof:placetype":"venue"
},
  "geometry": {"coordinates":[-82.9524,42.516399],"type":"Point"}
}