{
  "type": "Feature",
  "properties": {
    "iso:country":"US",
    "sg:address":"15219 E 9 Mile Rd",
    "sg:city":"Eastpointe",
    "sg:classifiers":[
        {
            "category":"Professional",
            "subcategory":"Lawyer & Legal Services",
            "type":"Services"
        }
    ],
    "sg:phone":"+1 586 997 0611",
    "sg:postcode":"48021",
    "sg:province":"MI",
    "wof:name":"Kimberly A Fergan",
    "wof:placetype":"venue"
},
  "geometry": {"coordinates":[-82.96411500000001,42.464773],"type":"Point"}
}