{
  "type": "Feature",
  "properties": {
    "iso:country":"US",
    "sg:address":"68790 Oak St",
    "sg:city":"Richmond",
    "sg:classifiers":[
        {
            "category":"Home & Garden",
            "subcategory":"Garden Supply",
            "type":"Retail Goods"
        }
    ],
    "sg:phone":"+1 586 727 2791",
    "sg:postcode":"48062",
    "sg:province":"MI",
    "sg:tags":[
        "fertilizer"
    ],
    "wof:name":"UAP Distribution",
    "wof:placetype":"venue"
},
  "geometry": {"coordinates":[-82.751789,42.80749],"type":"Point"}
}