{
  "type": "Feature",
  "properties": {
    "iso:country":"US",
    "sg:address":"344 Clayton Ave",
    "sg:city":"Battle Creek",
    "sg:classifiers":[
        {
            "category":"Professional",
            "subcategory":"Management & Consulting",
            "type":"Services"
        }
    ],
    "sg:phone":"+1 269 963 7068",
    "sg:postcode":"49017",
    "sg:province":"MI",
    "sg:tags":[
        "business"
    ],
    "wof:name":"National Badd",
    "wof:placetype":"venue"
},
  "geometry": {"coordinates":[-85.145383,42.351164],"type":"Point"}
}