{
  "type": "Feature",
  "properties": {
    "iso:country":"US",
    "sg:address":"5291 Sanilac Rd",
    "sg:city":"Kingston",
    "sg:classifiers":[
        {
            "category":"Restaurant",
            "type":"Food & Drink"
        }
    ],
    "sg:phone":"+1 989 635 2257",
    "sg:postcode":"48741",
    "sg:province":"MI",
    "wof:name":"Poverty Nook",
    "wof:placetype":"venue"
},
  "geometry": {"coordinates":[-83.21387,43.412515],"type":"Point"}
}