{
  "type": "Feature",
  "properties": {
    "iso:country":"US",
    "sg:address":"1080 John A Papalas Dr",
    "sg:city":"Lincoln Park",
    "sg:classifiers":[
        {
            "category":"Professional",
            "subcategory":"Testing Lab",
            "type":"Services"
        }
    ],
    "sg:phone":"+1 313 383 7222",
    "sg:postcode":"48146",
    "sg:province":"MI",
    "sg:tags":[
        "automotive"
    ],
    "wof:name":"Lincoln Park Test Labs Inc",
    "wof:placetype":"venue"
},
  "geometry": {"coordinates":[-83.177243,42.262947],"type":"Point"}
}