{
  "type": "Feature",
  "properties": {
    "iso:country":"US",
    "sg:address":"1044 Alpine Ave NW",
    "sg:city":"Grand Rapids",
    "sg:classifiers":[
        {
            "category":"Insurance",
            "subcategory":"Insurance Agent",
            "type":"Services"
        }
    ],
    "sg:phone":"+1 616 913 0073",
    "sg:postcode":"49504",
    "sg:province":"MI",
    "wof:name":"Yusko & Yusko Insurance",
    "wof:placetype":"venue"
},
  "geometry": {"coordinates":[-85.687917,42.982558],"type":"Point"}
}