{
  "type": "Feature",
  "properties": {
    "iso:country":"US",
    "sg:address":"3679 Sashabaw Rd",
    "sg:city":"Waterford",
    "sg:classifiers":[
        {
            "category":"Professional",
            "subcategory":"Detective & Security Services",
            "type":"Services"
        }
    ],
    "sg:phone":"+1 248 623 5800",
    "sg:postcode":"48329",
    "sg:province":"MI",
    "sg:tags":[
        "private",
        "investigator"
    ],
    "wof:name":"Capital Investigations",
    "wof:placetype":"venue"
},
  "geometry": {"coordinates":[-83.372884,42.691554],"type":"Point"}
}