{
  "type": "Feature",
  "properties": {
    "iso:country":"US",
    "sg:address":"421 Walnut Blvd",
    "sg:city":"Rochester",
    "sg:classifiers":[
        {
            "category":"Professional",
            "subcategory":"Lawyer & Legal Services",
            "type":"Services"
        }
    ],
    "sg:phone":"+1 248 299 9999",
    "sg:postcode":"48307",
    "sg:province":"MI",
    "sg:tags":[
        "attorney"
    ],
    "wof:name":"Mark Kopson",
    "wof:placetype":"venue"
},
  "geometry": {"coordinates":[-83.135409,42.681756],"type":"Point"}
}