{
  "type": "Feature",
  "properties": {
    "iso:country":"US",
    "sg:address":"2231 13th St",
    "sg:city":"Menominee",
    "sg:classifiers":[
        {
            "category":"Professional",
            "subcategory":"Advertising",
            "type":"Services"
        }
    ],
    "sg:phone":"+1 906 864 0090",
    "sg:postcode":"49858",
    "sg:province":"MI",
    "sg:tags":[
        "distribution"
    ],
    "wof:name":"Rose Distributors",
    "wof:placetype":"venue"
},
  "geometry": {"coordinates":[-87.618449,45.119495],"type":"Point"}
}