{
  "type": "Feature",
  "properties": {
    "iso:country":"US",
    "sg:address":"4050 W River Dr NE",
    "sg:city":"Comstock Park",
    "sg:classifiers":[
        {
            "category":"Wholesale",
            "subcategory":"Construction Materials",
            "type":"Manufacturing & Wholesale Goods"
        }
    ],
    "sg:phone":"+1 616 785 8000",
    "sg:postcode":"49321",
    "sg:province":"MI",
    "sg:tags":[
        "fence"
    ],
    "wof:name":"Out Back Casual Living",
    "wof:placetype":"venue"
},
  "geometry": {"coordinates":[-85.663934,43.036841],"type":"Point"}
}