{
  "type": "Feature",
  "properties": {
    "iso:country":"US",
    "sg:address":"401 Doty St",
    "sg:city":"Leslie",
    "sg:classifiers":[
        {
            "category":"Professional",
            "subcategory":"Computer Services",
            "type":"Services"
        }
    ],
    "sg:phone":"+1 517 589 0181",
    "sg:postcode":"49251",
    "sg:province":"MI",
    "sg:tags":[
        "repair"
    ],
    "wof:name":"Traveling Tech Computer Servic",
    "wof:placetype":"venue"
},
  "geometry": {"coordinates":[-84.43780099999999,42.455784],"type":"Point"}
}