{
  "type": "Feature",
  "properties": {
    "iso:country":"US",
    "sg:address":"18686 172nd Ave",
    "sg:city":"Spring Lake",
    "sg:classifiers":[
        {
            "category":"Manufacturing",
            "subcategory":"Metals",
            "type":"Manufacturing & Wholesale Goods"
        }
    ],
    "sg:phone":"+1 616 842 6550",
    "sg:postcode":"49456",
    "sg:province":"MI",
    "sg:tags":[
        "machine",
        "screw",
        "product"
    ],
    "sg:website":"www.supreme1.com",
    "wof:name":"Supreme Machined Products Co",
    "wof:placetype":"venue"
},
  "geometry": {"coordinates":[-86.21303899999999,43.110049],"type":"Point"}
}