{
  "type": "Feature",
  "properties": {
    "iso:country":"US",
    "sg:address":"200 Howard St",
    "sg:city":"Petoskey",
    "sg:classifiers":[
        {
            "category":"Shopping",
            "subcategory":"Gifts & Souvenirs",
            "type":"Retail Goods"
        }
    ],
    "sg:phone":"+1 231 348 5079",
    "sg:postcode":"49770",
    "sg:province":"MI",
    "sg:tags":[
        "shop"
    ],
    "wof:name":"Gaslight Gallery",
    "wof:placetype":"venue"
},
  "geometry": {"coordinates":[-84.95551399999999,45.375893],"type":"Point"}
}