{
  "type": "Feature",
  "properties": {
    "iso:country":"US",
    "sg:address":"915 Main St",
    "sg:city":"Norway",
    "sg:classifiers":[
        {
            "category":"Government",
            "subcategory":"Office",
            "type":"Public Place"
        }
    ],
    "sg:phone":"+1 906 563 9961",
    "sg:postcode":"49870",
    "sg:province":"MI",
    "sg:tags":[
        "city"
    ],
    "wof:name":"Norway City Clerk",
    "wof:placetype":"venue"
},
  "geometry": {"coordinates":[-87.907557,45.789483],"type":"Point"}
}