{
  "type": "Feature",
  "properties": {
    "iso:country":"US",
    "sg:address":"1524 Gull Rd",
    "sg:city":"Kalamazoo",
    "sg:classifiers":[
        {
            "category":"Restaurant",
            "type":"Food & Drink"
        }
    ],
    "sg:phone":"+1 269 383 4213",
    "sg:postcode":"49048",
    "sg:province":"MI",
    "wof:name":"Big Joes Pizza & Deli",
    "wof:placetype":"venue"
},
  "geometry": {"coordinates":[-85.56189999999999,42.304382],"type":"Point"}
}