{
  "type": "Feature",
  "properties": {
    "iso:country":"US",
    "sg:address":"12150 Strasburg Rd",
    "sg:city":"Erie",
    "sg:classifiers":[
        {
            "category":"Home & Garden",
            "subcategory":"Garden Supply",
            "type":"Retail Goods"
        }
    ],
    "sg:phone":"+1 734 269 2321",
    "sg:postcode":"48133",
    "sg:province":"MI",
    "sg:tags":[
        "nurseryman"
    ],
    "wof:name":"De Jong Nursery & Greenhouse",
    "wof:placetype":"venue"
},
  "geometry": {"coordinates":[-83.51190699999999,41.838155],"type":"Point"}
}