{
  "type": "Feature",
  "properties": {
    "iso:country":"US",
    "sg:address":"2251 W Giles Rd",
    "sg:city":"Muskegon",
    "sg:classifiers":[
        {
            "category":"Professional",
            "type":"Services"
        }
    ],
    "sg:phone":"+1 231 744 3983",
    "sg:postcode":"49445",
    "sg:province":"MI",
    "sg:tags":[
        "establishment"
    ],
    "wof:name":"R & R Smith Inc",
    "wof:placetype":"venue"
},
  "geometry": {"coordinates":[-86.298213,43.278833],"type":"Point"}
}