{
  "type": "Feature",
  "properties": {
    "iso:country":"US",
    "sg:address":"100 S Hanselman St",
    "sg:city":"Bad Axe",
    "sg:classifiers":[
        {
            "category":"Government",
            "subcategory":"Police Station",
            "type":"Public Place"
        }
    ],
    "sg:phone":"+1 989 269 9242",
    "sg:postcode":"48413",
    "sg:province":"MI",
    "sg:tags":[
        "department"
    ],
    "wof:name":"Bad Axe Police Department",
    "wof:placetype":"venue"
},
  "geometry": {"coordinates":[-82.997406,43.801687],"type":"Point"}
}