{
  "type": "Feature",
  "properties": {
    "iso:country":"US",
    "sg:address":"860 E Walton Blvd",
    "sg:city":"Pontiac",
    "sg:classifiers":[
        {
            "category":"Real Estate",
            "subcategory":"Real Estate Operator",
            "type":"Services"
        }
    ],
    "sg:phone":"+1 248 373 6110",
    "sg:postcode":"48340",
    "sg:province":"MI",
    "sg:tags":[
        "apartment"
    ],
    "wof:name":"Wind Song Apartments",
    "wof:placetype":"venue"
},
  "geometry": {"coordinates":[-83.269355,42.677673],"type":"Point"}
}