{
  "type": "Feature",
  "properties": {
    "iso:country":"US",
    "sg:address":"1600 E 12 Mile Rd",
    "sg:city":"Madison Heights",
    "sg:classifiers":[
        {
            "category":"Restaurant",
            "type":"Food & Drink"
        }
    ],
    "sg:phone":"+1 248 542 7071",
    "sg:postcode":"48071",
    "sg:province":"MI",
    "wof:name":"Mr Pita of Madison Heights",
    "wof:placetype":"venue"
},
  "geometry": {"coordinates":[-83.08850099999999,42.505001],"type":"Point"}
}