{
  "type": "Feature",
  "properties": {
    "iso:country":"US",
    "sg:address":"3972 Thomas Ave",
    "sg:city":"Berkley",
    "sg:classifiers":[
        {
            "category":"Professional",
            "subcategory":"Business Services",
            "type":"Services"
        }
    ],
    "sg:phone":"+1 248 543 2116",
    "sg:postcode":"48072",
    "sg:province":"MI",
    "wof:name":"B&D Group",
    "wof:placetype":"venue"
},
  "geometry": {"coordinates":[-83.201042,42.505744],"type":"Point"}
}