{
  "type": "Feature",
  "properties": {
    "iso:country":"US",
    "sg:address":"50 Monroe Ave NW",
    "sg:city":"Grand Rapids",
    "sg:classifiers":[
        {
            "category":"Banks & Credit Unions",
            "subcategory":"Bank",
            "type":"Services"
        }
    ],
    "sg:phone":"+1 616 235 6477",
    "sg:postcode":"49503",
    "sg:province":"MI",
    "sg:tags":[
        "national"
    ],
    "wof:name":"Huntington National Bank",
    "wof:placetype":"venue"
},
  "geometry": {"coordinates":[-85.673439,42.963249],"type":"Point"}
}