{
  "type": "Feature",
  "properties": {
    "iso:country":"US",
    "sg:address":"13260 E 11 Mile Rd",
    "sg:city":"Warren",
    "sg:classifiers":[
        {
            "category":"Social Services",
            "type":"Services"
        }
    ],
    "sg:phone":"+1 586 756 7600",
    "sg:postcode":"48089",
    "sg:province":"MI",
    "sg:tags":[
        "organization",
        "welfare"
    ],
    "wof:name":"American Red Cross",
    "wof:placetype":"venue"
},
  "geometry": {"coordinates":[-82.99217299999999,42.491842],"type":"Point"}
}