{
  "type": "Feature",
  "properties": {
    "iso:country":"US",
    "sg:address":"8700 Monroe Rd",
    "sg:city":"Durand",
    "sg:classifiers":[
        {
            "category":"Social Services",
            "subcategory":"Adult Care",
            "type":"Services"
        }
    ],
    "sg:phone":"+1 989 288 6561",
    "sg:postcode":"48429",
    "sg:province":"MI",
    "sg:tags":[
        "home",
        "residential"
    ],
    "wof:name":"Pines Of Durand",
    "wof:placetype":"venue"
},
  "geometry": {"coordinates":[-83.991843,42.922083],"type":"Point"}
}