{
  "type": "Feature",
  "properties": {
    "iso:country":"US",
    "sg:address":"23900 Orchard Lake Rd",
    "sg:city":"Farmington",
    "sg:classifiers":[
        {
            "category":"Health Services",
            "subcategory":"Doctor",
            "type":"Services"
        }
    ],
    "sg:phone":"+1 248 474 3650",
    "sg:postcode":"48336",
    "sg:province":"MI",
    "sg:tags":[
        "medical"
    ],
    "wof:name":"Stanley Boykansky MD PC",
    "wof:placetype":"venue"
},
  "geometry": {"coordinates":[-83.356977,42.467164],"type":"Point"}
}