{
  "type": "Feature",
  "properties": {
    "iso:country":"US",
    "sg:address":"20527 Fewins Rd",
    "sg:city":"Interlochen",
    "sg:classifiers":[
        {
            "category":"Retail",
            "subcategory":"Laundry & Dry Cleaning",
            "type":"Services"
        }
    ],
    "sg:phone":"+1 231 922 7782",
    "sg:postcode":"49643",
    "sg:province":"MI",
    "sg:tags":[
        "cleaners",
        "rug",
        "carpet"
    ],
    "wof:name":"Birch View Chem-Dry Carpet Cln",
    "wof:placetype":"venue"
},
  "geometry": {"coordinates":[-85.821775,44.6734],"type":"Point"}
}