{
  "type": "Feature",
  "properties": {
    "iso:country":"US",
    "sg:address":"4520 Breton Rd SE",
    "sg:city":"Grand Rapids",
    "sg:classifiers":[
        {
            "category":"Cinema",
            "subcategory":"Movie Rental",
            "type":"Entertainment"
        }
    ],
    "sg:phone":"+1 616 455 2626",
    "sg:postcode":"49508",
    "sg:province":"MI",
    "sg:tags":[
        "leasing",
        "video",
        "disc",
        "tape"
    ],
    "wof:name":"Blockbuster Video",
    "wof:placetype":"venue"
},
  "geometry": {"coordinates":[-85.60626999999999,42.882926],"type":"Point"}
}