{
  "type": "Feature",
  "properties": {
    "iso:country":"US",
    "sg:address":"30666 Pokagon Hwy",
    "sg:city":"Dowagiac",
    "sg:classifiers":[
        {
            "category":"Retail",
            "subcategory":"Repair Shop",
            "type":"Services"
        }
    ],
    "sg:phone":"+1 269 782 7613",
    "sg:postcode":"49047",
    "sg:province":"MI",
    "sg:tags":[
        "welding"
    ],
    "wof:name":"Trues Welding Fab",
    "wof:placetype":"venue"
},
  "geometry": {"coordinates":[-86.146575,41.912481],"type":"Point"}
}