{
  "type": "Feature",
  "properties": {
    "iso:country":"US",
    "sg:address":"1214 N Burdick St",
    "sg:city":"Kalamazoo",
    "sg:classifiers":[
        {
            "category":"Personal",
            "subcategory":"Barber",
            "type":"Services"
        }
    ],
    "sg:phone":"+1 269 385 9843",
    "sg:postcode":"49007",
    "sg:province":"MI",
    "wof:name":"Sportsman's Barber Shop",
    "wof:placetype":"venue"
},
  "geometry": {"coordinates":[-85.58353099999999,42.303228],"type":"Point"}
}