{
  "type": "Feature",
  "properties": {
    "iso:country":"US",
    "sg:address":"111 S Broadway St",
    "sg:city":"Middleville",
    "sg:classifiers":[
        {
            "category":"Banks & Credit Unions",
            "subcategory":"Investment Brokerage",
            "type":"Services"
        },
        {
            "category":"Professional",
            "subcategory":"Accounting & Tax Preparation",
            "type":"Services"
        }
    ],
    "sg:phone":"+1 269 795 3387",
    "sg:postcode":"49333",
    "sg:province":"MI",
    "sg:tags":[
        "consultant",
        "planning",
        "financial"
    ],
    "wof:name":"Thornapple Financial Center",
    "wof:placetype":"venue"
},
  "geometry": {"coordinates":[-85.46994100000001,42.710914],"type":"Point"}
}