{
  "type": "Feature",
  "properties": {
    "iso:country":"US",
    "sg:address":"6232 Mission Rd",
    "sg:city":"Alanson",
    "sg:classifiers":[
        {
            "category":"Professional",
            "subcategory":"Management & Consulting",
            "type":"Services"
        }
    ],
    "sg:phone":"+1 231 548 3628",
    "sg:postcode":"49706",
    "sg:province":"MI",
    "sg:tags":[
        "sales"
    ],
    "wof:name":"Wathen Corp",
    "wof:placetype":"venue"
},
  "geometry": {"coordinates":[-84.750843,45.471789],"type":"Point"}
}