{
  "type": "Feature",
  "properties": {
    "iso:country":"US",
    "sg:address":"1912 W Wackerly St",
    "sg:city":"Midland",
    "sg:classifiers":[
        {
            "category":"Retail",
            "subcategory":"Auto Rental",
            "type":"Services"
        }
    ],
    "sg:phone":"+1 989 839 0883",
    "sg:postcode":"48640",
    "sg:province":"MI",
    "sg:tags":[
        "truck",
        "trailer",
        "utility"
    ],
    "wof:name":"U-Haul",
    "wof:placetype":"venue"
},
  "geometry": {"coordinates":[-84.255359,43.655005],"type":"Point"}
}