{
  "type": "Feature",
  "properties": {
    "iso:country":"US",
    "sg:address":"6211 Ann Arbor Rd",
    "sg:city":"Dundee",
    "sg:classifiers":[
        {
            "category":"Manufacturing",
            "subcategory":"Glass & Minerals",
            "type":"Manufacturing & Wholesale Goods"
        }
    ],
    "sg:phone":"+1 734 529 2411",
    "sg:postcode":"48131",
    "sg:province":"MI",
    "sg:tags":[
        "cement"
    ],
    "sg:website":"www.holnam.com",
    "wof:name":"Holcim Inc",
    "wof:placetype":"venue"
},
  "geometry": {"coordinates":[-83.67316,41.983233],"type":"Point"}
}