{
  "type": "Feature",
  "properties": {
    "iso:country":"US",
    "sg:address":"31 Division St",
    "sg:city":"Coldwater",
    "sg:classifiers":[
        {
            "category":"Government",
            "subcategory":"Office",
            "type":"Public Place"
        }
    ],
    "sg:phone":"+1 517 279 4301",
    "sg:postcode":"49036",
    "sg:province":"MI",
    "wof:name":"Branch County Adm",
    "wof:placetype":"venue"
},
  "geometry": {"coordinates":[-85.000919,41.939666],"type":"Point"}
}