{
  "type": "Feature",
  "properties": {
    "iso:country":"US",
    "sg:address":"24400 Civic Center Dr",
    "sg:city":"Southfield",
    "sg:classifiers":[
        {
            "category":"Real Estate",
            "subcategory":"Real Estate Agent",
            "type":"Services"
        }
    ],
    "sg:phone":"+1 248 594 7555",
    "sg:postcode":"48033",
    "sg:province":"MI",
    "wof:name":"Circle Realty Company",
    "wof:placetype":"venue"
},
  "geometry": {"coordinates":[-83.28317699999999,42.479085],"type":"Point"}
}