{
  "type": "Feature",
  "properties": {
    "iso:country":"US",
    "sg:address":"4922 Munger Rd",
    "sg:city":"Ypsilanti",
    "sg:classifiers":[
        {
            "category":"Social Services",
            "subcategory":"Adult Care",
            "type":"Services"
        }
    ],
    "sg:phone":"+1 734 572 8589",
    "sg:postcode":"48197",
    "sg:province":"MI",
    "sg:tags":[
        "residential"
    ],
    "wof:name":"George Manor",
    "wof:placetype":"venue"
},
  "geometry": {"coordinates":[-83.66019799999999,42.216778],"type":"Point"}
}