{
  "type": "Feature",
  "properties": {
    "iso:country":"US",
    "sg:address":"42118 Merrimac Cir",
    "sg:city":"Clinton Township",
    "sg:classifiers":[
        {
            "category":"Manufacturing",
            "subcategory":"Building Materials",
            "type":"Manufacturing & Wholesale Goods"
        }
    ],
    "sg:phone":"+1 586 286 4877",
    "sg:postcode":"48038",
    "sg:province":"MI",
    "sg:tags":[
        "mfg",
        "wood",
        "kitchen",
        "cabinet"
    ],
    "wof:name":"Mill A Tree Custom Cabinets",
    "wof:placetype":"venue"
},
  "geometry": {"coordinates":[-82.92485600000001,42.605021],"type":"Point"}
}