{
  "type": "Feature",
  "properties": {
    "iso:country":"US",
    "sg:address":"14 Pioneer St",
    "sg:city":"Battle Creek",
    "sg:classifiers":[
        {
            "category":"Retail",
            "subcategory":"Repair Shop",
            "type":"Services"
        }
    ],
    "sg:phone":"+1 269 969 3954",
    "sg:postcode":"49015",
    "sg:province":"MI",
    "sg:tags":[
        "repairing",
        "piano",
        "refinishing"
    ],
    "wof:name":"Anthony's Piano Svc",
    "wof:placetype":"venue"
},
  "geometry": {"coordinates":[-85.20530599999999,42.302899],"type":"Point"}
}