{
  "type": "Feature",
  "properties": {
    "iso:country":"US",
    "sg:address":"227 Goddard St",
    "sg:city":"Wyandotte",
    "sg:classifiers":[
        {
            "category":"Food & Beverages",
            "subcategory":"Groceries & Convenience Stores",
            "type":"Retail Goods"
        }
    ],
    "sg:phone":"+1 734 284 9850",
    "sg:postcode":"48192",
    "sg:province":"MI",
    "sg:tags":[
        "alcoholic"
    ],
    "wof:name":"Goddard Family Market",
    "wof:placetype":"venue"
},
  "geometry": {"coordinates":[-83.15408100000001,42.223802],"type":"Point"}
}