{
  "type": "Feature",
  "properties": {
    "iso:country":"US",
    "sg:address":"432 N Cochran Ave",
    "sg:city":"Charlotte",
    "sg:classifiers":[
        {
            "category":"Health Services",
            "subcategory":"Chiropractor",
            "type":"Services"
        }
    ],
    "sg:phone":"+1 517 543 2920",
    "sg:postcode":"48813",
    "sg:province":"MI",
    "sg:tags":[
        "food"
    ],
    "wof:name":"Davis Chiropractic Center",
    "wof:placetype":"venue"
},
  "geometry": {"coordinates":[-84.835855,42.569538],"type":"Point"}
}