{
  "type": "Feature",
  "properties": {
    "iso:country":"US",
    "sg:address":"64521 Van Dyke Rd",
    "sg:city":"Washington",
    "sg:classifiers":[
        {
            "category":"Health Services",
            "subcategory":"Doctor",
            "type":"Services"
        }
    ],
    "sg:phone":"+1 586 752 6535",
    "sg:postcode":"48095",
    "sg:province":"MI",
    "sg:tags":[
        "osteopathic"
    ],
    "wof:name":"Gary F Curatolo DO",
    "wof:placetype":"venue"
},
  "geometry": {"coordinates":[-83.018401,42.768514],"type":"Point"}
}