{
  "type": "Feature",
  "properties": {
    "iso:country":"US",
    "sg:address":"4701 Secord Lake Rd",
    "sg:city":"Leonard",
    "sg:classifiers":[
        {
            "category":"Building & Trades",
            "subcategory":"Equipment Rental",
            "type":"Services"
        }
    ],
    "sg:phone":"+1 248 628 0479",
    "sg:postcode":"48367",
    "sg:province":"MI",
    "sg:tags":[
        "party",
        "supply"
    ],
    "wof:name":"Addison Party Rental",
    "wof:placetype":"venue"
},
  "geometry": {"coordinates":[-83.112194,42.868628],"type":"Point"}
}