{
  "type": "Feature",
  "properties": {
    "iso:country":"US",
    "sg:address":"3125 Fernwood Ave",
    "sg:city":"Ann Arbor",
    "sg:classifiers":[
        {
            "category":"Professional",
            "subcategory":"Management & Consulting",
            "type":"Services"
        }
    ],
    "sg:phone":"+1 734 971 9690",
    "sg:postcode":"48108",
    "sg:province":"MI",
    "sg:tags":[
        "business"
    ],
    "wof:name":"Consultant & Envmtl Toxicology",
    "wof:placetype":"venue"
},
  "geometry": {"coordinates":[-83.694372,42.240077],"type":"Point"}
}