{
  "type": "Feature",
  "properties": {
    "iso:country":"US",
    "sg:address":"15366 S Dixie Hwy",
    "sg:city":"Monroe",
    "sg:classifiers":[
        {
            "category":"Real Estate",
            "subcategory":"Developer",
            "type":"Services"
        },
        {
            "category":"Building & Trades",
            "subcategory":"Construction",
            "type":"Services"
        }
    ],
    "sg:phone":"+1 734 457 2215",
    "sg:postcode":"48161",
    "sg:province":"MI",
    "sg:tags":[
        "contractor"
    ],
    "wof:name":"Graves & Associates Inc",
    "wof:placetype":"venue"
},
  "geometry": {"coordinates":[-83.416543,41.893889],"type":"Point"}
}