{
  "type": "Feature",
  "properties": {
    "iso:country":"US",
    "sg:address":"7729 W Chadwick Rd",
    "sg:city":"Dewitt",
    "sg:classifiers":[
        {
            "category":"Shopping",
            "subcategory":"Gifts & Souvenirs",
            "type":"Retail Goods"
        }
    ],
    "sg:phone":"+1 517 626 6880",
    "sg:postcode":"48820",
    "sg:province":"MI",
    "wof:name":"Kitchen Table Crafts",
    "wof:placetype":"venue"
},
  "geometry": {"coordinates":[-84.67098900000001,42.871324],"type":"Point"}
}