{
  "type": "Feature",
  "properties": {
    "iso:country":"US",
    "sg:address":"325 W Adrian St",
    "sg:city":"Blissfield",
    "sg:classifiers":[
        {
            "category":"Restaurant",
            "type":"Food & Drink"
        }
    ],
    "sg:phone":"+1 517 486 4466",
    "sg:postcode":"49228",
    "sg:province":"MI",
    "wof:name":"Frosty Boy",
    "wof:placetype":"venue"
},
  "geometry": {"coordinates":[-83.868566,41.834765],"type":"Point"}
}