{
  "type": "Feature",
  "properties": {
    "iso:country":"US",
    "sg:address":"3483 Section Rd",
    "sg:city":"Lambertville",
    "sg:classifiers":[
        {
            "category":"Professional",
            "type":"Services"
        }
    ],
    "sg:phone":"+1 734 854 5299",
    "sg:postcode":"48144",
    "sg:province":"MI",
    "sg:tags":[
        "establishment"
    ],
    "wof:name":"Nibco",
    "wof:placetype":"venue"
},
  "geometry": {"coordinates":[-83.627764,41.739096],"type":"Point"}
}