{
  "type": "Feature",
  "properties": {
    "iso:country":"US",
    "sg:address":"64319 Limerick Ln",
    "sg:city":"Washington",
    "sg:classifiers":[
        {
            "category":"Building & Trades",
            "subcategory":"Plumbing",
            "type":"Services"
        }
    ],
    "sg:phone":"+1 586 752 3199",
    "sg:postcode":"48095",
    "sg:province":"MI",
    "sg:tags":[
        "cooling",
        "refrigeration",
        "heating",
        "contractor"
    ],
    "wof:name":"Hoffmanns Refrigeration Inc",
    "wof:placetype":"venue"
},
  "geometry": {"coordinates":[-83.02703099999999,42.770619],"type":"Point"}
}