{
  "type": "Feature",
  "properties": {
    "iso:country":"US",
    "sg:address":"4180 W Vienna Rd",
    "sg:city":"Clio",
    "sg:classifiers":[
        {
            "category":"Restaurant",
            "type":"Food & Drink"
        }
    ],
    "sg:menulink":"http://www.allmenus.com/mi/vienna/250000-big-john-steak--onion/menu/",
    "sg:phone":"+1 810 686 9420",
    "sg:postcode":"48420",
    "sg:province":"MI",
    "sg:tags":[
        "wrap",
        "american",
        "sandwich"
    ],
    "wof:name":"Big John Steak & Onion",
    "wof:placetype":"venue"
},
  "geometry": {"coordinates":[-83.761326,43.177481],"type":"Point"}
}