{
  "type": "Feature",
  "properties": {
    "iso:country":"US",
    "sg:address":"2735 Bay Rd",
    "sg:city":"Saginaw",
    "sg:classifiers":[
        {
            "category":"Professional",
            "subcategory":"Business Services",
            "type":"Services"
        }
    ],
    "sg:phone":"+1 989 791 1581",
    "sg:postcode":"48603",
    "sg:province":"MI",
    "wof:name":"Airbrush Shoppe",
    "wof:placetype":"venue"
},
  "geometry": {"coordinates":[-83.975551,43.445463],"type":"Point"}
}