{
  "type": "Feature",
  "properties": {
    "iso:country":"US",
    "sg:address":"15945 Stuart Rd",
    "sg:city":"Chesaning",
    "sg:classifiers":[
        {
            "category":"Building & Trades",
            "subcategory":"Construction",
            "type":"Services"
        }
    ],
    "sg:phone":"+1 989 845 7729",
    "sg:postcode":"48616",
    "sg:province":"MI",
    "sg:tags":[
        "excavation",
        "contractor"
    ],
    "wof:name":"Joe Excavating",
    "wof:placetype":"venue"
},
  "geometry": {"coordinates":[-84.090171,43.189382],"type":"Point"}
}