{
  "type": "Feature",
  "properties": {
    "iso:country":"US",
    "sg:address":"10195 Carroll Rd",
    "sg:city":"Columbus",
    "sg:classifiers":[
        {
            "category":"Professional",
            "type":"Services"
        }
    ],
    "sg:phone":"+1 810 392 8030",
    "sg:postcode":"48063",
    "sg:province":"MI",
    "wof:name":"Wendys",
    "wof:placetype":"venue"
},
  "geometry": {"coordinates":[-82.72499000000001,42.883903],"type":"Point"}
}