{
  "type": "Feature",
  "properties": {
    "iso:country":"US",
    "sg:address":"15590 W 13 Mile Rd",
    "sg:city":"Beverly Hills",
    "sg:classifiers":[
        {
            "category":"Health Services",
            "subcategory":"Doctor",
            "type":"Services"
        }
    ],
    "sg:phone":"+1 248 644 5900",
    "sg:postcode":"48025",
    "sg:province":"MI",
    "sg:tags":[
        "physician",
        "surgeon"
    ],
    "wof:name":"Stephen M Tait MD",
    "wof:placetype":"venue"
},
  "geometry": {"coordinates":[-83.2041,42.517537],"type":"Point"}
}