{
  "type": "Feature",
  "properties": {
    "iso:country":"US",
    "sg:address":"3368 Fargo Rd",
    "sg:city":"Avoca",
    "sg:classifiers":[
        {
            "category":"Real Estate",
            "subcategory":"Real Estate Agent",
            "type":"Services"
        }
    ],
    "sg:phone":"+1 810 325 9178",
    "sg:postcode":"48006",
    "sg:province":"MI",
    "wof:name":"Nu Oak & Assoc",
    "wof:placetype":"venue"
},
  "geometry": {"coordinates":[-82.651748,42.998573],"type":"Point"}
}