{
  "type": "Feature",
  "properties": {
    "iso:country":"US",
    "sg:address":"5893 W Blair Townhall Rd",
    "sg:city":"Grawn",
    "sg:classifiers":[
        {
            "category":"Building & Trades",
            "subcategory":"Construction",
            "type":"Services"
        }
    ],
    "sg:phone":"+1 231 276 9031",
    "sg:postcode":"49637",
    "sg:province":"MI",
    "sg:tags":[
        "house"
    ],
    "wof:name":"Cascagnett Construction",
    "wof:placetype":"venue"
},
  "geometry": {"coordinates":[-85.69573699999999,44.643121],"type":"Point"}
}