{
  "type": "Feature",
  "properties": {
    "iso:country":"US",
    "sg:address":"1855 E Oakwood Rd",
    "sg:city":"Oxford",
    "sg:phone":"+1 248 628 2191",
    "sg:postcode":"48371",
    "sg:province":"MI",
    "sg:tags":[
        "farm",
        "corn",
        "wheat"
    ],
    "wof:name":"Richard Kupskey",
    "wof:placetype":"venue"
},
  "geometry": {"coordinates":[-83.24378900000001,42.869866],"type":"Point"}
}