{
  "type": "Feature",
  "properties": {
    "iso:country":"US",
    "sg:address":"1529 108th Ave",
    "sg:city":"Otsego",
    "sg:classifiers":[
        {
            "category":"Professional",
            "subcategory":"Business Services",
            "type":"Services"
        }
    ],
    "sg:phone":"+1 269 694 5247",
    "sg:postcode":"49078",
    "sg:province":"MI",
    "wof:name":"Origin Group",
    "wof:placetype":"venue"
},
  "geometry": {"coordinates":[-85.698933,42.479203],"type":"Point"}
}