{
  "type": "Feature",
  "properties": {
    "iso:country":"US",
    "sg:address":"10901 N M 37",
    "sg:city":"Buckley",
    "sg:classifiers":[
        {
            "category":"Manufacturing",
            "subcategory":"Motor Vehicles & Parts",
            "type":"Manufacturing & Wholesale Goods"
        }
    ],
    "sg:phone":"+1 231 269 4160",
    "sg:postcode":"49620",
    "sg:province":"MI",
    "sg:tags":[
        "equipment",
        "truck"
    ],
    "wof:name":"Payne's Truck Svc",
    "wof:placetype":"venue"
},
  "geometry": {"coordinates":[-85.696924,44.49003],"type":"Point"}
}