{
  "type": "Feature",
  "properties": {
    "iso:country":"US",
    "sg:address":"600 N Eager Rd",
    "sg:city":"Howell",
    "sg:classifiers":[
        {
            "category":"Real Estate",
            "subcategory":"Real Estate Agent",
            "type":"Services"
        }
    ],
    "sg:phone":"+1 517 548 5910",
    "sg:postcode":"48843",
    "sg:province":"MI",
    "wof:name":"Covington Greens",
    "wof:placetype":"venue"
},
  "geometry": {"coordinates":[-83.89466899999999,42.612562],"type":"Point"}
}