{
  "type": "Feature",
  "properties": {
    "iso:country":"US",
    "sg:address":"1068 Hubbard Ave",
    "sg:city":"Flint",
    "sg:classifiers":[
        {
            "category":"Retail",
            "subcategory":"Repair Shop",
            "type":"Services"
        }
    ],
    "sg:phone":"+1 810 237 7695",
    "sg:postcode":"48503",
    "sg:province":"MI",
    "sg:tags":[
        "scooter",
        "motorcycle",
        "motor"
    ],
    "wof:name":"Owens Bootleg Cycle Inc",
    "wof:placetype":"venue"
},
  "geometry": {"coordinates":[-83.73229000000001,43.002957],"type":"Point"}
}