{
  "type": "Feature",
  "properties": {
    "iso:country":"US",
    "sg:address":"6820 Muirfield Ct SE",
    "sg:city":"Grand Rapids",
    "sg:classifiers":[
        {
            "category":"Professional",
            "subcategory":"Business Services",
            "type":"Services"
        }
    ],
    "sg:phone":"+1 616 682 0822",
    "sg:postcode":"49546",
    "sg:province":"MI",
    "wof:name":"Belfer Family Ltd Partnership",
    "wof:placetype":"venue"
},
  "geometry": {"coordinates":[-85.501178,42.933934],"type":"Point"}
}