{
  "type": "Feature",
  "properties": {
    "iso:country":"US",
    "sg:address":"320 E Portage Ave",
    "sg:city":"Sault Sainte Marie",
    "sg:classifiers":[
        {
            "category":"Organizations",
            "subcategory":"Religious Organization",
            "type":"Services"
        }
    ],
    "sg:phone":"+1 906 632 3381",
    "sg:postcode":"49783",
    "sg:province":"MI",
    "wof:name":"Holy Name of Mary",
    "wof:placetype":"venue"
},
  "geometry": {"coordinates":[-84.34125899999999,46.498578],"type":"Point"}
}