{
  "type": "Feature",
  "properties": {
    "iso:country":"US",
    "sg:address":"141 S Cochran Ave",
    "sg:city":"Charlotte",
    "sg:classifiers":[
        {
            "category":"Shopping",
            "subcategory":"Florist",
            "type":"Retail Goods"
        }
    ],
    "sg:phone":"+1 517 541 9820",
    "sg:postcode":"48813",
    "sg:province":"MI",
    "wof:name":"Serendipity Florist",
    "wof:placetype":"venue"
},
  "geometry": {"coordinates":[-84.835807,42.563311],"type":"Point"}
}