{
  "type": "Feature",
  "properties": {
    "iso:country":"US",
    "sg:address":"50523 Oregon Ave",
    "sg:city":"Novi",
    "sg:classifiers":[
        {
            "category":"Building & Trades",
            "subcategory":"Construction",
            "type":"Services"
        }
    ],
    "sg:phone":"+1 248 760 5559",
    "sg:postcode":"48374",
    "sg:province":"MI",
    "sg:tags":[
        "contractor"
    ],
    "wof:name":"Jr Drywall",
    "wof:placetype":"venue"
},
  "geometry": {"coordinates":[-83.549089,42.481017],"type":"Point"}
}