{
  "type": "Feature",
  "properties": {
    "iso:country":"US",
    "sg:address":"1120 E Front St",
    "sg:city":"Traverse City",
    "sg:classifiers":[
        {
            "category":"Professional",
            "subcategory":"Lawyer & Legal Services",
            "type":"Services"
        }
    ],
    "sg:phone":"+1 231 922 9688",
    "sg:postcode":"49686",
    "sg:province":"MI",
    "sg:tags":[
        "attorney"
    ],
    "wof:name":"Bradley L Putney Plc",
    "wof:placetype":"venue"
},
  "geometry": {"coordinates":[-85.59491,44.764097],"type":"Point"}
}