{
  "type": "Feature",
  "properties": {
    "iso:country":"US",
    "sg:address":"44720 Hayes Rd Ste 100",
    "sg:city":"Clinton Township",
    "sg:classifiers":[
        {
            "category":"Real Estate",
            "subcategory":"Real Estate Services",
            "type":"Services"
        }
    ],
    "sg:phone":"+1 586 286 0300",
    "sg:postcode":"48038",
    "sg:province":"MI",
    "wof:name":"Coldwell Banker Schweitzer Real Estate",
    "wof:placetype":"venue"
},
  "geometry": {"coordinates":[-82.973198,42.625],"type":"Point"}
}