{
  "type": "Feature",
  "properties": {
    "iso:country":"US",
    "sg:address":"2795 Hickory Nut Ln",
    "sg:city":"Kalamazoo",
    "sg:classifiers":[
        {
            "category":"Building & Trades",
            "subcategory":"Plumbing",
            "type":"Services"
        }
    ],
    "sg:phone":"+1 269 345 5445",
    "sg:postcode":"49004",
    "sg:province":"MI",
    "sg:tags":[
        "contractor"
    ],
    "wof:name":"Paul Chiba Plumbing",
    "wof:placetype":"venue"
},
  "geometry": {"coordinates":[-85.62403500000001,42.329203],"type":"Point"}
}