{
  "type": "Feature",
  "properties": {
    "iso:country":"US",
    "sg:address":"9760 Mandon St",
    "sg:city":"White Lake",
    "sg:classifiers":[
        {
            "category":"Building & Trades",
            "subcategory":"Construction",
            "type":"Services"
        }
    ],
    "sg:phone":"+1 248 363 1876",
    "sg:postcode":"48386",
    "sg:province":"MI",
    "sg:tags":[
        "home",
        "improvement"
    ],
    "wof:name":"J Beasley & Son",
    "wof:placetype":"venue"
},
  "geometry": {"coordinates":[-83.47577699999999,42.626726],"type":"Point"}
}