{
  "type": "Feature",
  "properties": {
    "iso:country":"US",
    "sg:address":"12078 White Lake Rd",
    "sg:city":"Fenton",
    "sg:classifiers":[
        {
            "category":"Home & Garden",
            "subcategory":"Garden Supply",
            "type":"Retail Goods"
        }
    ],
    "sg:phone":"+1 810 750 2900",
    "sg:postcode":"48430",
    "sg:province":"MI",
    "sg:tags":[
        "sprinkler"
    ],
    "wof:name":"Maly Multi Svc Inc",
    "wof:placetype":"venue"
},
  "geometry": {"coordinates":[-83.723964,42.761799],"type":"Point"}
}