{
  "type": "Feature",
  "properties": {
    "iso:country":"US",
    "sg:address":"20 W Muskegon Ave",
    "sg:city":"Muskegon",
    "sg:classifiers":[
        {
            "category":"Professional",
            "subcategory":"Employment Agencies",
            "type":"Services"
        }
    ],
    "sg:phone":"+1 231 722 6961",
    "sg:postcode":"49440",
    "sg:province":"MI",
    "sg:tags":[
        "opportunity"
    ],
    "wof:name":"Manpower Temporary Svc",
    "wof:placetype":"venue"
},
  "geometry": {"coordinates":[-86.24556200000001,43.23603],"type":"Point"}
}