{
  "type": "Feature",
  "properties": {
    "iso:country":"US",
    "sg:address":"2493 General Motors Rd",
    "sg:city":"Milford",
    "sg:classifiers":[
        {
            "category":"Shopping",
            "subcategory":"Used Merchandise",
            "type":"Retail Goods"
        }
    ],
    "sg:phone":"+1 248 889 3237",
    "sg:postcode":"48380",
    "sg:province":"MI",
    "sg:tags":[
        "clothing"
    ],
    "wof:name":"Too Good To Be Through",
    "wof:placetype":"venue"
},
  "geometry": {"coordinates":[-83.651697,42.578244],"type":"Point"}
}