{
  "type": "Feature",
  "properties": {
    "iso:country":"US",
    "sg:address":"2436 Rochester Rd",
    "sg:city":"Royal Oak",
    "sg:classifiers":[
        {
            "category":"Health Services",
            "subcategory":"Chiropractor",
            "type":"Services"
        }
    ],
    "sg:phone":"+1 248 545 8550",
    "sg:postcode":"48073",
    "sg:province":"MI",
    "wof:name":"Upchurch Stephen M DC",
    "wof:placetype":"venue"
},
  "geometry": {"coordinates":[-83.141296,42.510799],"type":"Point"}
}