{
  "type": "Feature",
  "properties": {
    "iso:country":"US",
    "sg:address":"9070 N Saginaw Rd",
    "sg:city":"Mount Morris",
    "sg:classifiers":[
        {
            "category":"Personal",
            "subcategory":"Beauty Salon",
            "type":"Services"
        }
    ],
    "sg:phone":"+1 810 789 1175",
    "sg:postcode":"48458",
    "sg:province":"MI",
    "sg:tags":[
        "shop"
    ],
    "wof:name":"Katrinas Kreations",
    "wof:placetype":"venue"
},
  "geometry": {"coordinates":[-83.69452,43.135799],"type":"Point"}
}