{
  "type": "Feature",
  "properties": {
    "iso:country":"US",
    "sg:address":"901 E Indian St",
    "sg:city":"Midland",
    "sg:classifiers":[
        {
            "category":"Professional",
            "subcategory":"Employment Agencies",
            "type":"Services"
        }
    ],
    "sg:phone":"+1 989 631 7851",
    "sg:postcode":"48640",
    "sg:province":"MI",
    "sg:tags":[
        "reporting",
        "help",
        "supply"
    ],
    "wof:name":"Trillium Staffing Solutions",
    "wof:placetype":"venue"
},
  "geometry": {"coordinates":[-84.235883,43.610935],"type":"Point"}
}