{
  "type": "Feature",
  "properties": {
    "iso:country":"US",
    "sg:address":"5820 Buell Rd",
    "sg:city":"Vassar",
    "sg:classifiers":[
        {
            "category":"Retail",
            "subcategory":"Animal Services",
            "type":"Services"
        }
    ],
    "sg:phone":"+1 989 823 2475",
    "sg:postcode":"48768",
    "sg:province":"MI",
    "wof:name":"Sabos Kennel",
    "wof:placetype":"venue"
},
  "geometry": {"coordinates":[-83.61379700000001,43.343845],"type":"Point"}
}