{
  "type": "Feature",
  "properties": {
    "iso:country":"US",
    "sg:address":"19811 Farmington Rd",
    "sg:city":"Livonia",
    "sg:classifiers":[
        {
            "category":"Health Services",
            "subcategory":"Dentist",
            "type":"Services"
        }
    ],
    "sg:phone":"+1 248 888 0066",
    "sg:postcode":"48152",
    "sg:province":"MI",
    "wof:name":"Leighton Karen",
    "wof:placetype":"venue"
},
  "geometry": {"coordinates":[-83.375381,42.432895],"type":"Point"}
}