{
  "type": "Feature",
  "properties": {
    "iso:country":"US",
    "sg:address":"30749 M 62 W",
    "sg:city":"Dowagiac",
    "sg:classifiers":[
        {
            "category":"Building & Trades",
            "subcategory":"Construction",
            "type":"Services"
        }
    ],
    "sg:phone":"+1 269 782 8047",
    "sg:postcode":"49047",
    "sg:province":"MI",
    "sg:tags":[
        "painter"
    ],
    "wof:name":"Professional Home Svc Co Inc",
    "wof:placetype":"venue"
},
  "geometry": {"coordinates":[-86.15671,41.983915],"type":"Point"}
}