{
  "type": "Feature",
  "properties": {
    "iso:country":"US",
    "sg:address":"1382 Haynes Ct",
    "sg:city":"Birmingham",
    "sg:classifiers":[
        {
            "category":"Banks & Credit Unions",
            "subcategory":"Financial Services",
            "type":"Services"
        }
    ],
    "sg:phone":"+1 248 642 0376",
    "sg:postcode":"48009",
    "sg:province":"MI",
    "sg:tags":[
        "fund",
        "investment"
    ],
    "wof:name":"Cicciarelli Family LLC",
    "wof:placetype":"venue"
},
  "geometry": {"coordinates":[-83.202956,42.542642],"type":"Point"}
}