{
  "type": "Feature",
  "properties": {
    "iso:country":"US",
    "sg:address":"137 Terry Ave",
    "sg:city":"Rochester",
    "sg:classifiers":[
        {
            "category":"Museum",
            "type":"Entertainment"
        }
    ],
    "sg:phone":"+1 248 651 8915",
    "sg:postcode":"48307",
    "sg:province":"MI",
    "sg:tags":[
        "gallery"
    ],
    "wof:name":"McLean Military Museum",
    "wof:placetype":"venue"
},
  "geometry": {"coordinates":[-83.13189800000001,42.688727],"type":"Point"}
}