{
  "type": "Feature",
  "properties": {
    "iso:country":"US",
    "sg:address":"18600 Florence St Ste C6",
    "sg:city":"Roseville",
    "sg:classifiers":[
        {
            "category":"Professional",
            "subcategory":"Employment Agencies",
            "type":"Services"
        }
    ],
    "sg:phone":"+1 586 772 6760",
    "sg:postcode":"48066",
    "sg:province":"MI",
    "wof:name":"Snelling Personnel Services",
    "wof:placetype":"venue"
},
  "geometry": {"coordinates":[-82.929703,42.507401],"type":"Point"}
}