{
  "type": "Feature",
  "properties": {
    "iso:country":"US",
    "sg:address":"22905 Michigan Ave",
    "sg:city":"Dearborn",
    "sg:classifiers":[
        {
            "category":"Fast Food",
            "type":"Food & Drink"
        },
        {
            "category":"Restaurant",
            "type":"Food & Drink"
        }
    ],
    "sg:phone":"+1 313 565 4521",
    "sg:postcode":"48124",
    "sg:province":"MI",
    "sg:tags":[
        "style",
        "family",
        "chinese",
        "asian",
        "pan",
        "take"
    ],
    "wof:name":"Kowloon Restaurant",
    "wof:placetype":"venue"
},
  "geometry": {"coordinates":[-83.258003,42.302799],"type":"Point"}
}