{
  "type": "Feature",
  "properties": {
    "iso:country":"US",
    "sg:address":"631 Brown Rd",
    "sg:city":"Lake Orion",
    "sg:classifiers":[
        {
            "category":"Autos & Motor Vehicles",
            "subcategory":"Boat Sales",
            "type":"Retail Goods"
        }
    ],
    "sg:phone":"+1 248 391 1820",
    "sg:postcode":"48359",
    "sg:province":"MI",
    "sg:tags":[
        "dealer",
        "sales"
    ],
    "sg:website":"www.myboattech.com",
    "wof:name":"My Personal Boat Technician",
    "wof:placetype":"venue"
},
  "geometry": {"coordinates":[-83.25998199999999,42.708397],"type":"Point"}
}