{
  "type": "Feature",
  "properties": {
    "iso:country":"US",
    "sg:address":"800 US Hwy 27 Bus",
    "sg:city":"St Johns",
    "sg:classifiers":[
        {
            "category":"Home & Garden",
            "subcategory":"Carpets & Floor Coverings",
            "type":"Retail Goods"
        }
    ],
    "sg:phone":"+1 989 227 1999",
    "sg:postcode":"48879",
    "sg:province":"MI",
    "sg:tags":[
        "dealer",
        "rug"
    ],
    "wof:name":"Carpets Galore & More",
    "wof:placetype":"venue"
},
  "geometry": {"coordinates":[-84.555425,43.012367],"type":"Point"}
}