{
  "type": "Feature",
  "properties": {
    "iso:country":"US",
    "sg:address":"21415 Civic Center Dr",
    "sg:city":"Southfield",
    "sg:classifiers":[
        {
            "category":"Banks & Credit Unions",
            "subcategory":"Financial Services",
            "type":"Services"
        }
    ],
    "sg:phone":"+1 248 350 8330",
    "sg:postcode":"48076",
    "sg:province":"MI",
    "sg:tags":[
        "broker",
        "mortgage"
    ],
    "wof:name":"First Mortgage Corp",
    "wof:placetype":"venue"
},
  "geometry": {"coordinates":[-83.25408899999999,42.479175],"type":"Point"}
}