{
  "type": "Feature",
  "properties": {
    "iso:country":"US",
    "sg:address":"49115 Schoenherr Rd",
    "sg:city":"Shelby Twp",
    "sg:classifiers":[
        {
            "category":"Personal",
            "subcategory":"Beauty Salon",
            "type":"Services"
        }
    ],
    "sg:phone":"+1 586 731 4767",
    "sg:postcode":"48315",
    "sg:province":"MI",
    "wof:name":"Detail Salon",
    "wof:placetype":"venue"
},
  "geometry": {"coordinates":[-82.99426,42.656827],"type":"Point"}
}