{
  "type": "Feature",
  "properties": {
    "iso:country":"US",
    "sg:address":"19286 N Highlite Dr",
    "sg:city":"Clinton Twp",
    "sg:classifiers":[
        {
            "category":"Real Estate",
            "subcategory":"Real Estate Agent",
            "type":"Services"
        },
        {
            "category":"Organizations",
            "subcategory":"Community Association",
            "type":"Services"
        }
    ],
    "sg:phone":"+1 586 791 8230",
    "sg:postcode":"48035",
    "sg:province":"MI",
    "sg:tags":[
        "civic",
        "cooperative",
        "social"
    ],
    "wof:name":"Townhouse Green Cooperative",
    "wof:placetype":"venue"
},
  "geometry": {"coordinates":[-82.926695,42.560169],"type":"Point"}
}