{
  "type": "Feature",
  "properties": {
    "iso:country":"US",
    "sg:address":"45320 Dunbarton Dr",
    "sg:city":"Novi",
    "sg:classifiers":[
        {
            "category":"Professional",
            "subcategory":"Management & Consulting",
            "type":"Services"
        }
    ],
    "sg:phone":"+1 248 344 1532",
    "sg:postcode":"48375",
    "sg:province":"MI",
    "sg:tags":[
        "consultant",
        "business"
    ],
    "wof:name":"McAlpine Internet Consultant",
    "wof:placetype":"venue"
},
  "geometry": {"coordinates":[-83.492594,42.45397],"type":"Point"}
}