{
  "type": "Feature",
  "properties": {
    "iso:country":"US",
    "sg:address":"1129 E Easterday Ave",
    "sg:city":"Sault Ste Marie",
    "sg:classifiers":[
        {
            "category":"Autos & Motor Vehicles",
            "subcategory":"Auto Supplies",
            "type":"Retail Goods"
        }
    ],
    "sg:phone":"+1 906 632 6661",
    "sg:postcode":"49783",
    "sg:province":"MI",
    "sg:tags":[
        "tire"
    ],
    "wof:name":"U P Tire & Supply",
    "wof:placetype":"venue"
},
  "geometry": {"coordinates":[-84.33920500000001,46.491667],"type":"Point"}
}