{
  "type": "Feature",
  "properties": {
    "iso:country":"US",
    "sg:address":"5614 Alpine Ave NW",
    "sg:city":"Comstock Park",
    "sg:classifiers":[
        {
            "category":"Wholesale",
            "subcategory":"Hardware",
            "type":"Manufacturing & Wholesale Goods"
        }
    ],
    "sg:phone":"+1 616 784 6671",
    "sg:postcode":"49321",
    "sg:province":"MI",
    "sg:tags":[
        "machine",
        "making",
        "ice",
        "equipment"
    ],
    "wof:name":"Greater Michigan Distributors",
    "wof:placetype":"venue"
},
  "geometry": {"coordinates":[-85.689778,43.064617],"type":"Point"}
}