{
  "type": "Feature",
  "properties": {
    "iso:country":"US",
    "sg:address":"4154 Bramford Dr",
    "sg:city":"Shelby Twp",
    "sg:classifiers":[
        {
            "category":"Professional",
            "subcategory":"Management & Consulting",
            "type":"Services"
        }
    ],
    "sg:phone":"+1 586 731 0359",
    "sg:postcode":"48317",
    "sg:province":"MI",
    "sg:tags":[
        "consultant",
        "business"
    ],
    "wof:name":"R & W Consulting",
    "wof:placetype":"venue"
},
  "geometry": {"coordinates":[-83.06865000000001,42.636368],"type":"Point"}
}