{
  "type": "Feature",
  "properties": {
    "iso:country":"US",
    "sg:address":"1823 Mc Donald Ave",
    "sg:city":"Royal Oak",
    "sg:classifiers":[
        {
            "category":"Professional",
            "subcategory":"Computer Services",
            "type":"Services"
        }
    ],
    "sg:phone":"+1 248 547 1181",
    "sg:postcode":"48073",
    "sg:province":"MI",
    "sg:tags":[
        "repair",
        "industrial"
    ],
    "wof:name":"Alltek Inc",
    "wof:placetype":"venue"
},
  "geometry": {"coordinates":[-83.155434,42.50608],"type":"Point"}
}