{
  "type": "Feature",
  "properties": {
    "iso:country":"US",
    "sg:address":"10535 W 8 Mile Rd",
    "sg:city":"Detroit",
    "sg:classifiers":[
        {
            "category":"Retail",
            "subcategory":"Auto Repair",
            "type":"Services"
        }
    ],
    "sg:phone":"+1 313 863 5000",
    "sg:postcode":"48221",
    "sg:province":"MI",
    "sg:tags":[
        "body"
    ],
    "wof:name":"Fine Point Collision Inc",
    "wof:placetype":"venue"
},
  "geometry": {"coordinates":[-83.167253,42.445445],"type":"Point"}
}