{
  "type": "Feature",
  "properties": {
    "iso:country":"US",
    "sg:address":"2300 S 21st St",
    "sg:city":"Escanaba",
    "sg:classifiers":[
        {
            "category":"Organizations",
            "subcategory":"Religious Organization",
            "type":"Services"
        }
    ],
    "sg:phone":"+1 906 789 9699",
    "sg:postcode":"49829",
    "sg:province":"MI",
    "sg:tags":[
        "church"
    ],
    "wof:name":"Lakeside Christian Church",
    "wof:placetype":"venue"
},
  "geometry": {"coordinates":[-87.07500899999999,45.720625],"type":"Point"}
}