{
  "type": "Feature",
  "properties": {
    "iso:country":"US",
    "sg:address":"28173 Woodward Ave",
    "sg:city":"Berkley",
    "sg:classifiers":[
        {
            "category":"Donuts",
            "subcategory":"None",
            "type":"Food & Drink"
        }
    ],
    "sg:phone":"+1 248 542 4653",
    "sg:postcode":"48072",
    "sg:province":"MI",
    "wof:name":"The Donut Cutter",
    "wof:placetype":"venue"
},
  "geometry": {"coordinates":[-83.16709899999999,42.4977],"type":"Point"}
}