{
  "type": "Feature",
  "properties": {
    "iso:country":"US",
    "sg:address":"1621 44th St SW",
    "sg:city":"Wyoming",
    "sg:classifiers":[
        {
            "category":"Insurance",
            "subcategory":"Insurance Agent",
            "type":"Services"
        }
    ],
    "sg:phone":"+1 616 956 3675",
    "sg:postcode":"49509",
    "sg:province":"MI",
    "wof:name":"Northern Lights Insurance",
    "wof:placetype":"venue"
},
  "geometry": {"coordinates":[-85.706304,42.884429],"type":"Point"}
}