{
  "type": "Feature",
  "properties": {
    "iso:country":"US",
    "sg:address":"985 E 16th St",
    "sg:city":"Holland",
    "sg:classifiers":[
        {
            "category":"Real Estate",
            "subcategory":"Real Estate Agent",
            "type":"Services"
        },
        {
            "category":"Real Estate",
            "subcategory":"Real Estate Operator",
            "type":"Services"
        }
    ],
    "sg:phone":"+1 616 392 1723",
    "sg:postcode":"49423",
    "sg:province":"MI",
    "sg:tags":[
        "apartment"
    ],
    "wof:name":"Ridgeland Heights Apartments",
    "wof:placetype":"venue"
},
  "geometry": {"coordinates":[-86.0656,42.783324],"type":"Point"}
}