{
  "type": "Feature",
  "properties": {
    "iso:country":"US",
    "sg:address":"6950 Todd Rd",
    "sg:city":"Croswell",
    "sg:classifiers":[
        {
            "category":"Farming",
            "subcategory":"Farm",
            "type":"Manufacturing & Wholesale Goods"
        }
    ],
    "sg:phone":"+1 810 679 4197",
    "sg:postcode":"48422",
    "sg:province":"MI",
    "sg:tags":[
        "crop",
        "general"
    ],
    "wof:name":"George Oconnor",
    "wof:placetype":"venue"
},
  "geometry": {"coordinates":[-82.686713,43.222078],"type":"Point"}
}