{
  "type": "Feature",
  "properties": {
    "iso:country":"US",
    "sg:address":"250 Elizabeth Lake Rd",
    "sg:city":"Pontiac",
    "sg:classifiers":[
        {
            "category":"Government",
            "subcategory":"Office",
            "type":"Public Place"
        }
    ],
    "sg:phone":"+1 248 540 3420",
    "sg:postcode":"48341",
    "sg:province":"MI",
    "sg:tags":[
        "village"
    ],
    "wof:name":"Southfield Twp Assessing Dept",
    "wof:placetype":"venue"
},
  "geometry": {"coordinates":[-83.319142,42.640766],"type":"Point"}
}