{
  "type": "Feature",
  "properties": {
    "iso:country":"US",
    "sg:address":"53600 Mound Rd",
    "sg:city":"Shelby Twp",
    "sg:classifiers":[
        {
            "category":"Organizations",
            "subcategory":"Religious Organization",
            "type":"Services"
        }
    ],
    "sg:phone":"+1 586 781 4901",
    "sg:postcode":"48316",
    "sg:province":"MI",
    "sg:tags":[
        "church"
    ],
    "sg:website":"www.stkieran.org",
    "wof:name":"Saint Kieran Church",
    "wof:placetype":"venue"
},
  "geometry": {"coordinates":[-83.05413799999999,42.687016],"type":"Point"}
}