{
  "type": "Feature",
  "properties": {
    "iso:country":"US",
    "sg:address":"200 Meeske Ave",
    "sg:city":"Marquette",
    "sg:classifiers":[
        {
            "category":"Wholesale",
            "subcategory":"Dairy",
            "type":"Manufacturing & Wholesale Goods"
        }
    ],
    "sg:phone":"+1 906 225 1363",
    "sg:postcode":"49855",
    "sg:province":"MI",
    "sg:tags":[
        "product"
    ],
    "wof:name":"John R Jilbert & Co",
    "wof:placetype":"venue"
},
  "geometry": {"coordinates":[-87.426987,46.549627],"type":"Point"}
}