{
  "type": "Feature",
  "properties": {
    "iso:country":"US",
    "sg:address":"6432 Upper Pine Creek Dr",
    "sg:city":"Iron Mountain",
    "sg:classifiers":[
        {
            "category":"Building & Trades",
            "subcategory":"Landscaping Services",
            "type":"Services"
        }
    ],
    "sg:phone":"+1 906 779 1159",
    "sg:postcode":"49801",
    "sg:province":"MI",
    "sg:tags":[
        "landscape",
        "contractor"
    ],
    "wof:name":"U P Water Gardens",
    "wof:placetype":"venue"
},
  "geometry": {"coordinates":[-87.97246199999999,45.849624],"type":"Point"}
}