{
  "type": "Feature",
  "properties": {
    "iso:country":"US",
    "sg:address":"1496 N Saginaw St",
    "sg:city":"Lapeer",
    "sg:classifiers":[
        {
            "category":"Building & Trades",
            "subcategory":"Construction",
            "type":"Services"
        }
    ],
    "sg:phone":"+1 810 664 2708",
    "sg:postcode":"48446",
    "sg:province":"MI",
    "sg:tags":[
        "tile",
        "dealer"
    ],
    "wof:name":"Rmp Designs LLC",
    "wof:placetype":"venue"
},
  "geometry": {"coordinates":[-83.310964,43.06531],"type":"Point"}
}