{
  "type": "Feature",
  "properties": {
    "iso:country":"US",
    "sg:address":"5950 Portage Rd",
    "sg:city":"Portage",
    "sg:classifiers":[
        {
            "category":"Professional",
            "subcategory":"Management & Consulting",
            "type":"Services"
        }
    ],
    "sg:phone":"+1 269 344 2242",
    "sg:postcode":"49002",
    "sg:province":"MI",
    "sg:tags":[
        "consultant",
        "business"
    ],
    "wof:name":"Lawrence A Pfaff & Assoc",
    "wof:placetype":"venue"
},
  "geometry": {"coordinates":[-85.560213,42.23093],"type":"Point"}
}