{
  "type": "Feature",
  "properties": {
    "iso:country":"US",
    "sg:address":"4023 Dauncy Rd",
    "sg:city":"Flat Rock",
    "sg:classifiers":[
        {
            "category":"Building & Trades",
            "subcategory":"Construction",
            "type":"Services"
        }
    ],
    "sg:phone":"+1 734 782 2252",
    "sg:postcode":"48134",
    "sg:province":"MI",
    "sg:tags":[
        "carpentry",
        "contractor"
    ],
    "wof:name":"Carpentry Wright & Remodeling",
    "wof:placetype":"venue"
},
  "geometry": {"coordinates":[-83.289427,42.077092],"type":"Point"}
}