{
  "type": "Feature",
  "properties": {
    "iso:country":"US",
    "sg:address":"1331 Bradley Dr",
    "sg:city":"Troy",
    "sg:classifiers":[
        {
            "category":"Building & Trades",
            "subcategory":"Cleaning & Sanitation",
            "type":"Services"
        }
    ],
    "sg:phone":"+1 248 524 0516",
    "sg:postcode":"48085",
    "sg:province":"MI",
    "sg:tags":[
        "snow",
        "removal"
    ],
    "wof:name":"Legacy Excavating Inc",
    "wof:placetype":"venue"
},
  "geometry": {"coordinates":[-83.121544,42.587635],"type":"Point"}
}