{
  "type": "Feature",
  "properties": {
    "iso:country":"US",
    "sg:address":"22318 Fresard St",
    "sg:city":"Saint Clair Shores",
    "sg:classifiers":[
        {
            "category":"Professional",
            "type":"Services"
        }
    ],
    "sg:phone":"+1 586 774 8766",
    "sg:postcode":"48080",
    "sg:province":"MI",
    "wof:name":"Sabertooth Technical Services",
    "wof:placetype":"venue"
},
  "geometry": {"coordinates":[-82.88917600000001,42.472215],"type":"Point"}
}