{
  "type": "Feature",
  "properties": {
    "iso:country":"US",
    "sg:address":"29429 Southfield Rd",
    "sg:city":"Southfield",
    "sg:classifiers":[
        {
            "category":"Social Services",
            "subcategory":"Child Care",
            "type":"Services"
        },
        {
            "category":"Education",
            "subcategory":"Special Training",
            "type":"Public Place"
        },
        {
            "category":"Education",
            "subcategory":"Preschool",
            "type":"Public Place"
        },
        {
            "category":"Education",
            "subcategory":"School",
            "type":"Public Place"
        }
    ],
    "sg:phone":"+1 248 557 6412",
    "sg:postcode":"48076",
    "sg:province":"MI",
    "sg:tags":[
        "kindergarten",
        "k-",
        "high",
        "middle",
        "nursery",
        "private",
        "elementary",
        "day"
    ],
    "wof:name":"International Montessori Academy",
    "wof:placetype":"venue"
},
  "geometry": {"coordinates":[-83.22292899999999,42.506096],"type":"Point"}
}