{
  "type": "Feature",
  "properties": {
    "iso:country":"US",
    "sg:address":"400 S Pine St",
    "sg:city":"Lansing",
    "sg:classifiers":[
        {
            "category":"Government",
            "subcategory":"Office",
            "type":"Public Place"
        }
    ],
    "sg:phone":"+1 517 335 5001",
    "sg:postcode":"48933",
    "sg:province":"MI",
    "sg:tags":[
        "state",
        "resource"
    ],
    "sg:website":"www.michigan.gov",
    "wof:name":"Medical Services Adm",
    "wof:placetype":"venue"
},
  "geometry": {"coordinates":[-84.56010499999999,42.728755],"type":"Point"}
}