{
  "type": "Feature",
  "properties": {
    "iso:country":"US",
    "sg:address":"3335 Lakeshore Rd",
    "sg:city":"Lexington",
    "sg:classifiers":[
        {
            "category":"Travel",
            "subcategory":"Campground",
            "type":"Entertainment"
        }
    ],
    "sg:phone":"+1 810 359 8040",
    "sg:postcode":"48450",
    "sg:province":"MI",
    "sg:tags":[
        "camp"
    ],
    "wof:name":"Camp Cavell",
    "wof:placetype":"venue"
},
  "geometry": {"coordinates":[-82.53518099999999,43.331598],"type":"Point"}
}