{
  "type": "Feature",
  "properties": {
    "iso:country":"US",
    "sg:address":"7855 Dixon Rd",
    "sg:city":"Jackson",
    "sg:classifiers":[
        {
            "category":"Building & Trades",
            "subcategory":"Construction",
            "type":"Services"
        }
    ],
    "sg:phone":"+1 517 783 2480",
    "sg:postcode":"49201",
    "sg:province":"MI",
    "sg:tags":[
        "excavating",
        "contractor"
    ],
    "wof:name":"Swartz Excavating",
    "wof:placetype":"venue"
},
  "geometry": {"coordinates":[-84.48631399999999,42.347246],"type":"Point"}
}