{
  "type": "Feature",
  "properties": {
    "iso:country":"US",
    "sg:address":"13766 Primrose Ln",
    "sg:city":"Cedar Springs",
    "sg:classifiers":[
        {
            "category":"Professional",
            "subcategory":"Computer Services",
            "type":"Services"
        }
    ],
    "sg:phone":"+1 616 696 7862",
    "sg:postcode":"49319",
    "sg:province":"MI",
    "sg:tags":[
        "internet"
    ],
    "wof:name":"Safeweb Crafts",
    "wof:placetype":"venue"
},
  "geometry": {"coordinates":[-85.583089,43.215701],"type":"Point"}
}