{
  "type": "Feature",
  "properties": {
    "iso:country":"US",
    "sg:address":"10704 Northland Dr NE",
    "sg:city":"Rockford",
    "sg:classifiers":[
        {
            "category":"Home & Garden",
            "subcategory":"Garden Supply",
            "type":"Retail Goods"
        }
    ],
    "sg:phone":"+1 616 866 3200",
    "sg:postcode":"49341",
    "sg:province":"MI",
    "sg:tags":[
        "sprinkler"
    ],
    "wof:name":"Rickert & Assoc Landscape",
    "wof:placetype":"venue"
},
  "geometry": {"coordinates":[-85.550777,43.158563],"type":"Point"}
}