{
  "type": "Feature",
  "properties": {
    "iso:country":"US",
    "sg:address":"2254 S Lakeshore Rd",
    "sg:city":"Harbor Beach",
    "sg:classifiers":[
        {
            "category":"Retail",
            "subcategory":"Auto Repair",
            "type":"Services"
        }
    ],
    "sg:phone":"+1 989 479 9215",
    "sg:postcode":"48441",
    "sg:province":"MI",
    "sg:tags":[
        "body"
    ],
    "wof:name":"Rays Recreations",
    "wof:placetype":"venue"
},
  "geometry": {"coordinates":[-82.626019,43.778529],"type":"Point"}
}