{
  "type": "Feature",
  "properties": {
    "iso:country":"US",
    "sg:address":"4464 Division Ave S",
    "sg:city":"Grand Rapids",
    "sg:classifiers":[
        {
            "category":"Home & Garden",
            "subcategory":"Household Appliances",
            "type":"Retail Goods"
        }
    ],
    "sg:phone":"+1 616 538 3020",
    "sg:postcode":"49548",
    "sg:province":"MI",
    "sg:tags":[
        "machine",
        "sewing"
    ],
    "sg:website":"www.mrjssewing.com",
    "wof:name":"A Brother Sewing Machine Ctr",
    "wof:placetype":"venue"
},
  "geometry": {"coordinates":[-85.664574,42.881864],"type":"Point"}
}