{
  "type": "Feature",
  "properties": {
    "iso:country":"US",
    "sg:address":"14257 Northland Dr",
    "sg:city":"Big Rapids",
    "sg:classifiers":[
        {
            "category":"Retail",
            "subcategory":"Repair Shop",
            "type":"Services"
        }
    ],
    "sg:phone":"+1 231 796 9940",
    "sg:postcode":"49307",
    "sg:province":"MI",
    "wof:name":"Lightouch Tattoo",
    "wof:placetype":"venue"
},
  "geometry": {"coordinates":[-85.483448,43.672034],"type":"Point"}
}