{
  "type": "Feature",
  "properties": {
    "iso:country":"US",
    "sg:address":"26744 W 9 Mile Rd",
    "sg:city":"Southfield",
    "sg:classifiers":[
        {
            "category":"Professional",
            "subcategory":"Accounting & Tax Preparation",
            "type":"Services"
        }
    ],
    "sg:phone":"+1 248 356 7200",
    "sg:postcode":"48033",
    "sg:province":"MI",
    "sg:tags":[
        "return",
        "filing"
    ],
    "wof:name":"Max Tax LLC",
    "wof:placetype":"venue"
},
  "geometry": {"coordinates":[-83.313687,42.45628],"type":"Point"}
}