{
  "type": "Feature",
  "properties": {
    "iso:country":"US",
    "sg:address":"11010 Stone Quarry Rd",
    "sg:city":"Riga",
    "sg:classifiers":[
        {
            "category":"Building & Trades",
            "subcategory":"Cleaning & Sanitation",
            "type":"Services"
        }
    ],
    "sg:phone":"+1 517 486 2255",
    "sg:postcode":"49276",
    "sg:province":"MI",
    "sg:tags":[
        "snow",
        "removal"
    ],
    "wof:name":"Michigan Snow Pros",
    "wof:placetype":"venue"
},
  "geometry": {"coordinates":[-83.74581999999999,41.811608],"type":"Point"}
}