{
  "type": "Feature",
  "properties": {
    "iso:country":"US",
    "sg:address":"2043 US Hwy 41",
    "sg:city":"Wilson",
    "sg:classifiers":[
        {
            "category":"Manufacturing",
            "subcategory":"Metals",
            "type":"Manufacturing & Wholesale Goods"
        }
    ],
    "sg:phone":"+1 906 497 5079",
    "sg:postcode":"49896",
    "sg:province":"MI",
    "sg:tags":[
        "steel"
    ],
    "wof:name":"Steve Baird Steel & Fab",
    "wof:placetype":"venue"
},
  "geometry": {"coordinates":[-87.42094899999999,45.705004],"type":"Point"}
}