{
  "type": "Feature",
  "properties": {
    "iso:country":"US",
    "sg:address":"306 Griggs St SW",
    "sg:city":"Grand Rapids",
    "sg:classifiers":[
        {
            "category":"Organizations",
            "subcategory":"Religious Organization",
            "type":"Services"
        }
    ],
    "sg:phone":"+1 616 241 9895",
    "sg:postcode":"49507",
    "sg:province":"MI",
    "sg:tags":[
        "church"
    ],
    "wof:name":"Upper Room Bilingual Ministry",
    "wof:placetype":"venue"
},
  "geometry": {"coordinates":[-85.67420199999999,42.9313],"type":"Point"}
}