{
  "type": "Feature",
  "properties": {
    "iso:country":"US",
    "sg:address":"8061 Hahn St",
    "sg:city":"Utica",
    "sg:classifiers":[
        {
            "category":"Building & Trades",
            "subcategory":"Pest Control",
            "type":"Services"
        }
    ],
    "sg:phone":"+1 586 731 2120",
    "sg:postcode":"48317",
    "sg:province":"MI",
    "wof:name":"Environmental Systems",
    "wof:placetype":"venue"
},
  "geometry": {"coordinates":[-83.03209699999999,42.631401],"type":"Point"}
}