{
  "type": "Feature",
  "properties": {
    "iso:country":"US",
    "sg:address":"13704 Pine Ct",
    "sg:city":"Grand Haven",
    "sg:classifiers":[
        {
            "category":"Professional",
            "subcategory":"Art Services",
            "type":"Services"
        }
    ],
    "sg:phone":"+1 616 844 9027",
    "sg:postcode":"49417",
    "sg:province":"MI",
    "sg:tags":[
        "graphic",
        "design"
    ],
    "wof:name":"Sheila B Warners Design",
    "wof:placetype":"venue"
},
  "geometry": {"coordinates":[-86.12681000000001,43.022017],"type":"Point"}
}