{
  "type": "Feature",
  "properties": {
    "iso:country":"US",
    "sg:address":"1205 Washington Ave",
    "sg:city":"Bay City",
    "sg:classifiers":[
        {
            "category":"Real Estate",
            "subcategory":"Real Estate Operator",
            "type":"Services"
        }
    ],
    "sg:phone":"+1 989 893 1000",
    "sg:postcode":"48708",
    "sg:province":"MI",
    "sg:tags":[
        "building",
        "nonresidential",
        "center",
        "bowling"
    ],
    "sg:website":"www.washingtonlanesbowling.com",
    "wof:name":"Washington Lanes",
    "wof:placetype":"venue"
},
  "geometry": {"coordinates":[-83.88714899999999,43.602991],"type":"Point"}
}