{
  "type": "Feature",
  "properties": {
    "iso:country":"US",
    "sg:address":"1175 W Vienna Rd",
    "sg:city":"Clio",
    "sg:classifiers":[
        {
            "category":"Wholesale",
            "subcategory":"Machinery & Supplies",
            "type":"Manufacturing & Wholesale Goods"
        }
    ],
    "sg:phone":"+1 810 687 8612",
    "sg:postcode":"48420",
    "sg:province":"MI",
    "sg:tags":[
        "operated",
        "laundry"
    ],
    "wof:name":"ALD Equipment",
    "wof:placetype":"venue"
},
  "geometry": {"coordinates":[-83.702353,43.177695],"type":"Point"}
}