{
  "type": "Feature",
  "properties": {
    "iso:country":"US",
    "sg:address":"11327 Conant St",
    "sg:city":"Hamtramck",
    "sg:classifiers":[
        {
            "category":"Manufacturing",
            "subcategory":"Leather Goods",
            "type":"Manufacturing & Wholesale Goods"
        }
    ],
    "sg:phone":"+1 313 891 9640",
    "sg:postcode":"48212",
    "sg:province":"MI",
    "wof:name":"Al-Sazz Agencies",
    "wof:placetype":"venue"
},
  "geometry": {"coordinates":[-83.05306400000001,42.402733],"type":"Point"}
}