{
  "type": "Feature",
  "properties": {
    "iso:country":"US",
    "sg:address":"24185 Haggerty Rd",
    "sg:city":"Novi",
    "sg:classifiers":[
        {
            "category":"Food & Beverages",
            "subcategory":"Groceries & Convenience Stores",
            "type":"Retail Goods"
        }
    ],
    "sg:phone":"+1 248 476 5690",
    "sg:postcode":"48375",
    "sg:province":"MI",
    "wof:name":"Golden Oaks Convenience Store",
    "wof:placetype":"venue"
},
  "geometry": {"coordinates":[-83.43499799999999,42.467098],"type":"Point"}
}