{
  "type": "Feature",
  "properties": {
    "iso:country":"US",
    "sg:address":"106 N State St",
    "sg:city":"Howell",
    "sg:classifiers":[
        {
            "category":"Shopping",
            "subcategory":"Bicycles & Sporting Goods",
            "type":"Retail Goods"
        }
    ],
    "sg:phone":"+1 517 545 9366",
    "sg:postcode":"48843",
    "sg:province":"MI",
    "sg:tags":[
        "equipment",
        "skateboard"
    ],
    "wof:name":"Skaters Advocate",
    "wof:placetype":"venue"
},
  "geometry": {"coordinates":[-83.928453,42.607754],"type":"Point"}
}