{
  "type": "Feature",
  "properties": {
    "iso:country":"US",
    "sg:address":"25800 Northwestern Hwy Ste 880",
    "sg:city":"Southfield",
    "sg:classifiers":[
        {
            "category":"Organizations",
            "subcategory":"Religious Organization",
            "type":"Services"
        }
    ],
    "sg:phone":"+1 248 352 8661",
    "sg:postcode":"48075",
    "sg:province":"MI",
    "wof:name":"Aish Hatorah",
    "wof:placetype":"venue"
},
  "geometry": {"coordinates":[-83.24848799999999,42.47812],"type":"Point"}
}