{
  "type": "Feature",
  "properties": {
    "iso:country":"US",
    "sg:address":"760 W Wattles Rd",
    "sg:city":"Troy",
    "sg:classifiers":[
        {
            "category":"Travel",
            "subcategory":"Campground",
            "type":"Entertainment"
        }
    ],
    "sg:phone":"+1 248 269 9130",
    "sg:postcode":"48098",
    "sg:province":"MI",
    "sg:tags":[
        "camp"
    ],
    "wof:name":"Detroit Diocese Summer Camp",
    "wof:placetype":"venue"
},
  "geometry": {"coordinates":[-83.162902,42.576979],"type":"Point"}
}