{
  "type": "Feature",
  "properties": {
    "iso:country":"US",
    "sg:address":"1793 Sherbrook Way",
    "sg:city":"Haslett",
    "sg:classifiers":[
        {
            "category":"Shopping",
            "subcategory":"Crafts & Fabrics",
            "type":"Retail Goods"
        }
    ],
    "sg:phone":"+1 517 339 3791",
    "sg:postcode":"48840",
    "sg:province":"MI",
    "sg:tags":[
        "material",
        "needlework"
    ],
    "wof:name":"Photo Stitch",
    "wof:placetype":"venue"
},
  "geometry": {"coordinates":[-84.41483599999999,42.751293],"type":"Point"}
}