{
  "type": "Feature",
  "properties": {
    "iso:country":"US",
    "sg:address":"12214 Fern Pl",
    "sg:city":"Charlevoix",
    "sg:classifiers":[
        {
            "category":"Professional",
            "subcategory":"Management & Consulting",
            "type":"Services"
        }
    ],
    "sg:phone":"+1 231 547 2763",
    "sg:postcode":"49720",
    "sg:province":"MI",
    "sg:tags":[
        "business"
    ],
    "wof:name":"Sheldon Consulting",
    "wof:placetype":"venue"
},
  "geometry": {"coordinates":[-85.221372,45.326224],"type":"Point"}
}