{
  "type": "Feature",
  "properties": {
    "iso:country":"US",
    "sg:address":"1939 Rolfe Rd",
    "sg:city":"Mason",
    "sg:classifiers":[
        {
            "category":"Building & Trades",
            "subcategory":"Construction",
            "type":"Services"
        }
    ],
    "sg:phone":"+1 517 676 0784",
    "sg:postcode":"48854",
    "sg:province":"MI",
    "sg:tags":[
        "carpenter"
    ],
    "wof:name":"Tom Shaw Carpentry",
    "wof:placetype":"venue"
},
  "geometry": {"coordinates":[-84.409747,42.533161],"type":"Point"}
}