{
  "type": "Feature",
  "properties": {
    "iso:country":"US",
    "sg:address":"2256 Tipperary Rd",
    "sg:city":"Kalamazoo",
    "sg:classifiers":[
        {
            "category":"Professional",
            "subcategory":"Secretarial Services",
            "type":"Services"
        }
    ],
    "sg:phone":"+1 269 381 8605",
    "sg:postcode":"49008",
    "sg:province":"MI",
    "sg:tags":[
        "reporting"
    ],
    "wof:name":"Calligraphy By Carney",
    "wof:placetype":"venue"
},
  "geometry": {"coordinates":[-85.611744,42.269179],"type":"Point"}
}