{
  "type": "Feature",
  "properties": {
    "iso:country":"US",
    "sg:address":"439 105th Ave",
    "sg:city":"Plainwell",
    "sg:classifiers":[
        {
            "category":"Shopping",
            "subcategory":"Bicycles & Sporting Goods",
            "type":"Retail Goods"
        }
    ],
    "sg:phone":"+1 269 685 6668",
    "sg:postcode":"49080",
    "sg:province":"MI",
    "sg:tags":[
        "equipment",
        "archery",
        "supply"
    ],
    "wof:name":"Archery Shop",
    "wof:placetype":"venue"
},
  "geometry": {"coordinates":[-85.590934,42.457657],"type":"Point"}
}