{
  "type": "Feature",
  "properties": {
    "iso:country":"US",
    "sg:address":"29069 Greenfield Rd",
    "sg:city":"Southfield",
    "sg:classifiers":[
        {
            "category":"Fast Food",
            "type":"Food & Drink"
        },
        {
            "category":"Food & Beverages",
            "subcategory":"Meat & Fish",
            "type":"Retail Goods"
        }
    ],
    "sg:phone":"+1 248 552 0378",
    "sg:postcode":"48076",
    "sg:province":"MI",
    "sg:tags":[
        "burger",
        "hot",
        "dog"
    ],
    "sg:website":"www.wendys.com",
    "wof:name":"Wendys Hamburgers",
    "wof:placetype":"venue"
},
  "geometry": {"coordinates":[-83.20331,42.503494],"type":"Point"}
}