{
  "type": "Feature",
  "properties": {
    "iso:country":"US",
    "sg:address":"6390 Chief Rd",
    "sg:city":"Brethren",
    "sg:classifiers":[
        {
            "category":"Government",
            "subcategory":"Office",
            "type":"Public Place"
        }
    ],
    "sg:phone":"+1 231 889 0153",
    "sg:postcode":"49619",
    "sg:province":"MI",
    "sg:tags":[
        "national",
        "security"
    ],
    "wof:name":"West Michigan Squadron",
    "wof:placetype":"venue"
},
  "geometry": {"coordinates":[-86.10130700000001,44.330159],"type":"Point"}
}