{
  "type": "Feature",
  "properties": {
    "iso:country":"US",
    "sg:address":"930 S Main St",
    "sg:city":"Adrian",
    "sg:classifiers":[
        {
            "category":"Restaurant",
            "type":"Food & Drink"
        }
    ],
    "sg:phone":"+1 517 263 5851",
    "sg:postcode":"49221",
    "sg:province":"MI",
    "wof:name":"KFC",
    "wof:placetype":"venue"
},
  "geometry": {"coordinates":[-84.04349000000001,41.885404],"type":"Point"}
}