{
  "type": "Feature",
  "properties": {
    "iso:country":"US",
    "sg:address":"12161 Sanborn St",
    "sg:city":"Ossineke",
    "sg:classifiers":[
        {
            "category":"Organizations",
            "subcategory":"Labor Organization",
            "type":"Services"
        }
    ],
    "sg:phone":"+1 989 471 5085",
    "sg:postcode":"49766",
    "sg:province":"MI",
    "wof:name":"Internationl Assn Machinsts/Ae",
    "wof:placetype":"venue"
},
  "geometry": {"coordinates":[-83.440409,44.900265],"type":"Point"}
}