{
  "type": "Feature",
  "properties": {
    "iso:country":"US",
    "sg:address":"32888 Ryan Rd",
    "sg:city":"Warren",
    "sg:classifiers":[
        {
            "category":"Insurance",
            "subcategory":"Insurance Agent",
            "type":"Services"
        }
    ],
    "sg:phone":"+1 586 268 9956",
    "sg:postcode":"48092",
    "sg:province":"MI",
    "wof:name":"Auto Insurance Center",
    "wof:placetype":"venue"
},
  "geometry": {"coordinates":[-83.068438,42.533818],"type":"Point"}
}