{
  "type": "Feature",
  "properties": {
    "iso:country":"US",
    "sg:address":"4241 US Hwy 23 N",
    "sg:city":"Alpena",
    "sg:classifiers":[
        {
            "category":"Freight",
            "type":"Transportation"
        }
    ],
    "sg:phone":"+1 989 358 7867",
    "sg:postcode":"49707",
    "sg:province":"MI",
    "sg:tags":[
        "special"
    ],
    "wof:name":"Sunrise Storage",
    "wof:placetype":"venue"
},
  "geometry": {"coordinates":[-83.44804000000001,45.116694],"type":"Point"}
}