{
  "type": "Feature",
  "properties": {
    "iso:country":"US",
    "sg:address":"4105 Maracaibo Shores Ave SE",
    "sg:city":"Grand Rapids",
    "sg:classifiers":[
        {
            "category":"Manufacturing",
            "subcategory":"Printing",
            "type":"Manufacturing & Wholesale Goods"
        }
    ],
    "sg:phone":"+1 616 956 0087",
    "sg:postcode":"49546",
    "sg:province":"MI",
    "sg:tags":[
        "publisher"
    ],
    "sg:website":"www.clergy-financial.com",
    "wof:name":"Clergy Financial Svc",
    "wof:placetype":"venue"
},
  "geometry": {"coordinates":[-85.485258,42.890287],"type":"Point"}
}