{
  "type": "Feature",
  "properties": {
    "iso:country":"US",
    "sg:address":"5391 Nisewander St",
    "sg:city":"Buckley",
    "sg:classifiers":[
        {
            "category":"Mining & Drilling",
            "type":"Manufacturing & Wholesale Goods"
        }
    ],
    "sg:phone":"+1 231 269 3800",
    "sg:postcode":"49620",
    "sg:province":"MI",
    "sg:tags":[
        "oil",
        "well"
    ],
    "wof:name":"Double W Oil Field Svc In",
    "wof:placetype":"venue"
},
  "geometry": {"coordinates":[-85.684324,44.503346],"type":"Point"}
}