{
  "type": "Feature",
  "properties": {
    "iso:country":"US",
    "sg:address":"5424 Proctor St",
    "sg:city":"Detroit",
    "sg:classifiers":[
        {
            "category":"Building & Trades",
            "subcategory":"Construction",
            "type":"Services"
        }
    ],
    "sg:phone":"+1 313 894 3485",
    "sg:postcode":"48210",
    "sg:province":"MI",
    "sg:tags":[
        "house"
    ],
    "wof:name":"Lmb Landscaping & Construction",
    "wof:placetype":"venue"
},
  "geometry": {"coordinates":[-83.13903500000001,42.335971],"type":"Point"}
}