{
  "type": "Feature",
  "properties": {
    "iso:country":"US",
    "sg:address":"44620 Mound Rd",
    "sg:city":"Sterling Heights",
    "sg:classifiers":[
        {
            "category":"Shopping",
            "subcategory":"Tobacco",
            "type":"Retail Goods"
        }
    ],
    "sg:phone":"+1 586 997 1900",
    "sg:postcode":"48314",
    "sg:province":"MI",
    "sg:tags":[
        "shop",
        "cigarette",
        "cigar"
    ],
    "wof:name":"Smokers Express",
    "wof:placetype":"venue"
},
  "geometry": {"coordinates":[-83.05155499999999,42.62267],"type":"Point"}
}