{
  "type": "Feature",
  "properties": {
    "iso:country":"US",
    "sg:address":"6167 White Lake Rd",
    "sg:city":"Clarkston",
    "sg:classifiers":[
        {
            "category":"Restaurant",
            "type":"Food & Drink"
        }
    ],
    "sg:phone":"+1 248 625 6111",
    "sg:postcode":"48346",
    "sg:province":"MI",
    "sg:tags":[
        "caterer"
    ],
    "wof:name":"Deer Lake Banquet Ctr",
    "wof:placetype":"venue"
},
  "geometry": {"coordinates":[-83.42914399999999,42.726179],"type":"Point"}
}