{
  "type": "Feature",
  "properties": {
    "iso:country":"US",
    "sg:address":"6480 US Hwy 223",
    "sg:city":"Adrian",
    "sg:classifiers":[
        {
            "category":"Freight",
            "type":"Transportation"
        }
    ],
    "sg:phone":"+1 517 263 9500",
    "sg:postcode":"49221",
    "sg:province":"MI",
    "sg:tags":[
        "commercial",
        "storage"
    ],
    "wof:name":"Storage Pro",
    "wof:placetype":"venue"
},
  "geometry": {"coordinates":[-84.112827,41.905702],"type":"Point"}
}