{
  "type": "Feature",
  "properties": {
    "iso:country":"US",
    "sg:address":"1599 Union Lake Rd",
    "sg:city":"Commerce Township",
    "sg:classifiers":[
        {
            "category":"Ice Cream",
            "type":"Food & Drink"
        }
    ],
    "sg:menulink":"http://www.allmenus.com/mi/commerce/168527-dairy-queen/menu/",
    "sg:phone":"+1 248 363 8717",
    "sg:postcode":"48382",
    "sg:province":"MI",
    "sg:tags":[
        "burger",
        "american"
    ],
    "wof:name":"Dairy Queen",
    "wof:placetype":"venue"
},
  "geometry": {"coordinates":[-83.446428,42.613103],"type":"Point"}
}