{
  "type": "Feature",
  "properties": {
    "iso:country":"US",
    "sg:address":"5322 Chene St",
    "sg:city":"Detroit",
    "sg:classifiers":[
        {
            "category":"Organizations",
            "subcategory":"Religious Organization",
            "type":"Services"
        }
    ],
    "sg:phone":"+1 313 923 5939",
    "sg:postcode":"48211",
    "sg:province":"MI",
    "wof:name":"Peacemakers International",
    "wof:placetype":"venue"
},
  "geometry": {"coordinates":[-83.042114,42.368354],"type":"Point"}
}