{
  "type": "Feature",
  "properties": {
    "iso:country":"US",
    "sg:address":"7494 Prospect Dr",
    "sg:city":"Bessemer",
    "sg:classifiers":[
        {
            "category":"Real Estate",
            "subcategory":"Real Estate Operator",
            "type":"Services"
        }
    ],
    "sg:phone":"+1 906 663 4532",
    "sg:postcode":"49911",
    "sg:province":"MI",
    "sg:tags":[
        "building",
        "apartment",
        "dwelling"
    ],
    "wof:name":"Mm Rentals",
    "wof:placetype":"venue"
},
  "geometry": {"coordinates":[-90.035848,46.499182],"type":"Point"}
}