{
  "type": "Feature",
  "properties": {
    "iso:country":"US",
    "sg:address":"8579 30th Ave",
    "sg:city":"Evart",
    "sg:classifiers":[
        {
            "category":"Social Services",
            "type":"Services"
        }
    ],
    "sg:phone":"+1 231 734 6673",
    "sg:postcode":"49631",
    "sg:province":"MI",
    "sg:tags":[
        "youth",
        "organization",
        "center"
    ],
    "wof:name":"Moisd River Youth Home",
    "wof:placetype":"venue"
},
  "geometry": {"coordinates":[-85.148445,43.934193],"type":"Point"}
}