{
  "type": "Feature",
  "properties": {
    "iso:country":"US",
    "sg:address":"322 S 4th St",
    "sg:city":"Niles",
    "sg:classifiers":[
        {
            "category":"Building & Trades",
            "subcategory":"Construction",
            "type":"Services"
        }
    ],
    "sg:phone":"+1 269 684 7194",
    "sg:postcode":"49120",
    "sg:province":"MI",
    "sg:tags":[
        "general",
        "contractor"
    ],
    "wof:name":"Progressive Construction",
    "wof:placetype":"venue"
},
  "geometry": {"coordinates":[-86.252982,41.823998],"type":"Point"}
}