{
  "type": "Feature",
  "properties": {
    "iso:country":"US",
    "sg:address":"2978 S Commerce Rd",
    "sg:city":"Commerce Twp",
    "sg:classifiers":[
        {
            "category":"Education",
            "subcategory":"School",
            "type":"Public Place"
        }
    ],
    "sg:phone":"+1 248 669 9731",
    "sg:postcode":"48390",
    "sg:province":"MI",
    "wof:name":"Walled Lake Central High Sch",
    "wof:placetype":"venue"
},
  "geometry": {"coordinates":[-83.474423,42.568272],"type":"Point"}
}