{
  "type": "Feature",
  "properties": {
    "iso:country":"US",
    "sg:address":"6075 N Branch Rd",
    "sg:city":"North Branch",
    "sg:classifiers":[
        {
            "category":"Farming",
            "subcategory":"Farm",
            "type":"Manufacturing & Wholesale Goods"
        }
    ],
    "sg:phone":"+1 810 688 3103",
    "sg:postcode":"48461",
    "sg:province":"MI",
    "sg:tags":[
        "crop",
        "general"
    ],
    "wof:name":"David & Karen Kreiner",
    "wof:placetype":"venue"
},
  "geometry": {"coordinates":[-83.115379,43.231453],"type":"Point"}
}