{
  "type": "Feature",
  "properties": {
    "iso:country":"US",
    "sg:address":"308 Cleveland Ave",
    "sg:city":"Ishpeming",
    "sg:classifiers":[
        {
            "category":"Shopping",
            "subcategory":"Bicycles & Sporting Goods",
            "type":"Retail Goods"
        }
    ],
    "sg:phone":"+1 906 486 6845",
    "sg:postcode":"49849",
    "sg:province":"MI",
    "wof:name":"Straight Line Archery",
    "wof:placetype":"venue"
},
  "geometry": {"coordinates":[-87.666439,46.489971],"type":"Point"}
}