{
  "type": "Feature",
  "properties": {
    "iso:country":"US",
    "sg:address":"4025 S Adrian Hwy",
    "sg:city":"Adrian",
    "sg:classifiers":[
        {
            "category":"Insurance",
            "subcategory":"Insurance Agent",
            "type":"Services"
        }
    ],
    "sg:phone":"+1 517 265 2891",
    "sg:postcode":"49221",
    "sg:province":"MI",
    "wof:name":"Farm Bureau Insurance",
    "wof:placetype":"venue"
},
  "geometry": {"coordinates":[-84.04260499999999,41.860048],"type":"Point"}
}