{
  "type": "Feature",
  "properties": {
    "iso:country":"US",
    "sg:address":"1966 S State Rd",
    "sg:city":"Ionia",
    "sg:classifiers":[
        {
            "category":"Shopping",
            "subcategory":"Computers & Home Electronics",
            "type":"Retail Goods"
        }
    ],
    "sg:phone":"+1 616 522 0133",
    "sg:postcode":"48846",
    "sg:province":"MI",
    "sg:tags":[
        "equipment",
        "dealer"
    ],
    "wof:name":"Nitel PC Inc",
    "wof:placetype":"venue"
},
  "geometry": {"coordinates":[-85.07453599999999,42.961464],"type":"Point"}
}