{
  "type": "Feature",
  "properties": {
    "iso:country":"US",
    "sg:address":"8905 Lyman Rd",
    "sg:city":"Kaleva",
    "sg:classifiers":[
        {
            "category":"Social Services",
            "subcategory":"Child Care",
            "type":"Services"
        }
    ],
    "sg:phone":"+1 231 889 4868",
    "sg:postcode":"49645",
    "sg:province":"MI",
    "sg:tags":[
        "day"
    ],
    "wof:name":"Patricia Matthews",
    "wof:placetype":"venue"
},
  "geometry": {"coordinates":[-86.124332,44.343555],"type":"Point"}
}