{
  "type": "Feature",
  "properties": {
    "iso:country":"US",
    "sg:address":"5721 N W Torch Lake Dr",
    "sg:city":"Kewadin",
    "sg:classifiers":[
        {
            "category":"Building & Trades",
            "subcategory":"Construction",
            "type":"Services"
        }
    ],
    "sg:phone":"+1 231 264 9404",
    "sg:postcode":"49648",
    "sg:province":"MI",
    "sg:tags":[
        "product",
        "asphalt"
    ],
    "wof:name":"Black Diamond Asphalt Seal",
    "wof:placetype":"venue"
},
  "geometry": {"coordinates":[-85.323233,44.96265],"type":"Point"}
}