{
  "type": "Feature",
  "properties": {
    "iso:country":"US",
    "sg:address":"5075 Yorkshire Rd",
    "sg:city":"Detroit",
    "sg:classifiers":[
        {
            "category":"Building & Trades",
            "subcategory":"Equipment Rental",
            "type":"Services"
        }
    ],
    "sg:phone":"+1 313 417 9194",
    "sg:postcode":"48224",
    "sg:province":"MI",
    "wof:name":"Ja Leasing",
    "wof:placetype":"venue"
},
  "geometry": {"coordinates":[-82.93521699999999,42.406188],"type":"Point"}
}