{
  "type": "Feature",
  "properties": {
    "iso:country":"US",
    "sg:address":"1013 N Shiawassee St",
    "sg:city":"Corunna",
    "sg:classifiers":[
        {
            "category":"Manufacturing",
            "subcategory":"Motor Vehicles & Parts",
            "type":"Manufacturing & Wholesale Goods"
        }
    ],
    "sg:phone":"+1 989 743 3458",
    "sg:postcode":"48817",
    "sg:province":"MI",
    "sg:tags":[
        "automobile",
        "supply"
    ],
    "sg:website":"www.newaymfg.com",
    "wof:name":"Neway Manufacturing Inc",
    "wof:placetype":"venue"
},
  "geometry": {"coordinates":[-84.118949,42.99231],"type":"Point"}
}