{
  "type": "Feature",
  "properties": {
    "iso:country":"US",
    "sg:address":"7344 Creekside Dr",
    "sg:city":"Lansing",
    "sg:classifiers":[
        {
            "category":"Professional",
            "subcategory":"Accounting & Tax Preparation",
            "type":"Services"
        }
    ],
    "sg:phone":"+1 517 627 3159",
    "sg:postcode":"48917",
    "sg:province":"MI",
    "wof:name":"Moray & Assoc Accounting",
    "wof:placetype":"venue"
},
  "geometry": {"coordinates":[-84.658247,42.735186],"type":"Point"}
}