{
  "type": "Feature",
  "properties": {
    "iso:country":"US",
    "sg:address":"2087 Sandhill Farm Ln",
    "sg:city":"Lapeer",
    "sg:classifiers":[
        {
            "category":"Manufacturing",
            "subcategory":"Soap",
            "type":"Manufacturing & Wholesale Goods"
        }
    ],
    "sg:phone":"+1 810 667 1663",
    "sg:postcode":"48446",
    "sg:province":"MI",
    "sg:tags":[
        "detergent",
        "mfg"
    ],
    "wof:name":"Will O Way Naturals",
    "wof:placetype":"venue"
},
  "geometry": {"coordinates":[-83.36515900000001,42.996552],"type":"Point"}
}