{
  "type": "Feature",
  "properties": {
    "iso:country":"US",
    "sg:address":"610 Young Rd",
    "sg:city":"White Lake",
    "sg:classifiers":[
        {
            "category":"Manufacturing",
            "subcategory":"Glass & Minerals",
            "type":"Manufacturing & Wholesale Goods"
        }
    ],
    "sg:phone":"+1 248 887 0199",
    "sg:postcode":"48383",
    "sg:province":"MI",
    "sg:tags":[
        "product",
        "mfg"
    ],
    "wof:name":"Clear Choice Glass Co LLC",
    "wof:placetype":"venue"
},
  "geometry": {"coordinates":[-83.527221,42.641856],"type":"Point"}
}