{
  "type": "Feature",
  "properties": {
    "iso:country":"US",
    "sg:address":"1445 Emerald Ave NE",
    "sg:city":"Grand Rapids",
    "sg:classifiers":[
        {
            "category":"Education",
            "subcategory":"School",
            "type":"Public Place"
        }
    ],
    "sg:phone":"+1 616 819 2727",
    "sg:postcode":"49505",
    "sg:province":"MI",
    "sg:website":"www.grps.k12.mi.us",
    "wof:name":"Kent Hills Elementary School",
    "wof:placetype":"venue"
},
  "geometry": {"coordinates":[-85.647513,42.989029],"type":"Point"}
}