{
  "type": "Feature",
  "properties": {
    "iso:country":"US",
    "sg:address":"120 W Lake St",
    "sg:city":"Petoskey",
    "sg:classifiers":[
        {
            "category":"Taxi",
            "type":"Transportation"
        }
    ],
    "sg:phone":"+1 231 881 8800",
    "sg:postcode":"49770",
    "sg:province":"MI",
    "sg:tags":[
        "taxicab"
    ],
    "wof:name":"Petoskey Shuttle",
    "wof:placetype":"venue"
},
  "geometry": {"coordinates":[-84.961406,45.375061],"type":"Point"}
}