{
  "type": "Feature",
  "properties": {
    "iso:country":"US",
    "sg:address":"157 Chapel Hill Dr",
    "sg:city":"Battle Creek",
    "sg:classifiers":[
        {
            "category":"Organizations",
            "subcategory":"Religious Organization",
            "type":"Services"
        }
    ],
    "sg:phone":"+1 269 963 0231",
    "sg:postcode":"49015",
    "sg:province":"MI",
    "sg:tags":[
        "church"
    ],
    "sg:website":"www.chapelhill-umc.org",
    "wof:name":"Chapel Hill United Methodist",
    "wof:placetype":"venue"
},
  "geometry": {"coordinates":[-85.18710299999999,42.289797],"type":"Point"}
}