{
  "type": "Feature",
  "properties": {
    "iso:country":"US",
    "sg:address":"9169 Lake Pine Dr",
    "sg:city":"Whitmore Lake",
    "sg:classifiers":[
        {
            "category":"Social Services",
            "subcategory":"Child Care",
            "type":"Services"
        }
    ],
    "sg:phone":"+1 734 449 2738",
    "sg:postcode":"48189",
    "sg:province":"MI",
    "sg:tags":[
        "day"
    ],
    "wof:name":"Tiny Tots Play School",
    "wof:placetype":"venue"
},
  "geometry": {"coordinates":[-83.751891,42.417451],"type":"Point"}
}