{
  "type": "Feature",
  "properties": {
    "iso:country":"US",
    "sg:address":"28245 Southfield Rd",
    "sg:city":"Lathrup Village",
    "sg:classifiers":[
        {
            "category":"Health Services",
            "subcategory":"Chiropractor",
            "type":"Services"
        }
    ],
    "sg:phone":"+1 248 552 1110",
    "sg:postcode":"48076",
    "sg:province":"MI",
    "sg:website":"www.odellfamilychiropractic.com",
    "wof:name":"O' Dell Family Chiropractic",
    "wof:placetype":"venue"
},
  "geometry": {"coordinates":[-83.22250200000001,42.497015],"type":"Point"}
}