{
  "type": "Feature",
  "properties": {
    "iso:country":"US",
    "sg:address":"438 Jerome St",
    "sg:city":"Monroe",
    "sg:classifiers":[
        {
            "category":"Real Estate",
            "subcategory":"Developer",
            "type":"Services"
        }
    ],
    "sg:phone":"+1 734 384 8430",
    "sg:postcode":"48161",
    "sg:province":"MI",
    "sg:tags":[
        "cemetery"
    ],
    "wof:name":"Woodland Cemetery",
    "wof:placetype":"venue"
},
  "geometry": {"coordinates":[-83.39287,41.908802],"type":"Point"}
}