{
  "type": "Feature",
  "properties": {
    "iso:country":"US",
    "sg:address":"26699 W 12 Mile Rd Ste 105",
    "sg:city":"Southfield",
    "sg:classifiers":[
        {
            "category":"Health Services",
            "subcategory":"Doctor",
            "type":"Services"
        }
    ],
    "sg:phone":"+1 248 351 9060",
    "sg:postcode":"48034",
    "sg:province":"MI",
    "sg:tags":[
        "surgeon",
        "oral"
    ],
    "wof:name":"Nona Basil E DDS",
    "wof:placetype":"venue"
},
  "geometry": {"coordinates":[-83.31150100000001,42.500401],"type":"Point"}
}