{
  "type": "Feature",
  "properties": {
    "iso:country":"US",
    "sg:address":"36575 Fierz St",
    "sg:city":"Clinton Township",
    "sg:classifiers":[
        {
            "category":"Building & Trades",
            "subcategory":"Construction",
            "type":"Services"
        }
    ],
    "sg:phone":"+1 586 791 4729",
    "sg:postcode":"48035",
    "sg:province":"MI",
    "sg:tags":[
        "repair",
        "hanging",
        "contractor"
    ],
    "wof:name":"Charlies Maintenance & Pntg",
    "wof:placetype":"venue"
},
  "geometry": {"coordinates":[-82.87302200000001,42.565373],"type":"Point"}
}