{
  "type": "Feature",
  "properties": {
    "iso:country":"US",
    "sg:address":"300 Hayhoe Rd",
    "sg:city":"Dansville",
    "sg:classifiers":[
        {
            "category":"Building & Trades",
            "subcategory":"Construction",
            "type":"Services"
        }
    ],
    "sg:phone":"+1 517 623 0245",
    "sg:postcode":"48819",
    "sg:province":"MI",
    "sg:tags":[
        "carpentry",
        "contractor"
    ],
    "wof:name":"Jackson Trim Carpentry",
    "wof:placetype":"venue"
},
  "geometry": {"coordinates":[-84.328157,42.563028],"type":"Point"}
}