{
  "type": "Feature",
  "properties": {
    "iso:country":"US",
    "sg:address":"4095 Cherokee Dr",
    "sg:city":"New Buffalo",
    "sg:classifiers":[
        {
            "category":"Health Services",
            "subcategory":"Doctor",
            "type":"Services"
        }
    ],
    "sg:phone":"+1 269 469 1798",
    "sg:postcode":"49117",
    "sg:province":"MI",
    "sg:tags":[
        "medical"
    ],
    "wof:name":"Robert H Whalen Co",
    "wof:placetype":"venue"
},
  "geometry": {"coordinates":[-86.810108,41.761869],"type":"Point"}
}