{
  "type": "Feature",
  "properties": {
    "iso:country":"US",
    "sg:address":"1971 Vianne Dr",
    "sg:city":"Rochester",
    "sg:classifiers":[
        {
            "category":"Professional",
            "subcategory":"Engineering",
            "type":"Services"
        }
    ],
    "sg:phone":"+1 248 651 3707",
    "sg:postcode":"48309",
    "sg:province":"MI",
    "wof:name":"Cincinnati Engineering",
    "wof:placetype":"venue"
},
  "geometry": {"coordinates":[-83.16882699999999,42.686365],"type":"Point"}
}