{
  "type": "Feature",
  "properties": {
    "iso:country":"US",
    "sg:address":"5877 Valley Rd",
    "sg:city":"Alanson",
    "sg:classifiers":[
        {
            "category":"Building & Trades",
            "subcategory":"Construction",
            "type":"Services"
        }
    ],
    "sg:phone":"+1 231 548 2547",
    "sg:postcode":"49706",
    "sg:province":"MI",
    "sg:tags":[
        "house"
    ],
    "wof:name":"Kilpatrick Construction",
    "wof:placetype":"venue"
},
  "geometry": {"coordinates":[-84.802998,45.450044],"type":"Point"}
}