{
  "type": "Feature",
  "properties": {
    "iso:country":"US",
    "sg:address":"5084 Burns Line Rd",
    "sg:city":"Croswell",
    "sg:classifiers":[
        {
            "category":"Building & Trades",
            "subcategory":"Construction",
            "type":"Services"
        }
    ],
    "sg:phone":"+1 810 679 9826",
    "sg:postcode":"48422",
    "sg:province":"MI",
    "sg:tags":[
        "carpentry",
        "contractor"
    ],
    "wof:name":"Daves Carpentry",
    "wof:placetype":"venue"
},
  "geometry": {"coordinates":[-82.6087,43.223162],"type":"Point"}
}