{
  "type": "Feature",
  "properties": {
    "iso:country":"US",
    "sg:address":"21751 Wildwood St",
    "sg:city":"Dearborn",
    "sg:classifiers":[
        {
            "category":"Banks & Credit Unions",
            "subcategory":"Financial Services",
            "type":"Services"
        }
    ],
    "sg:phone":"+1 313 562 5846",
    "sg:postcode":"48128",
    "sg:province":"MI",
    "sg:tags":[
        "trust",
        "management"
    ],
    "wof:name":"Buer Den Foundation",
    "wof:placetype":"venue"
},
  "geometry": {"coordinates":[-83.250547,42.326413],"type":"Point"}
}