{
  "type": "Feature",
  "properties": {
    "iso:country":"US",
    "sg:address":"9144 Lewis Ave",
    "sg:city":"Temperance",
    "sg:classifiers":[
        {
            "category":"Organizations",
            "subcategory":"Religious Organization",
            "type":"Services"
        }
    ],
    "sg:phone":"+1 734 847 3400",
    "sg:postcode":"48182",
    "sg:province":"MI",
    "sg:tags":[
        "church"
    ],
    "wof:name":"St Paul's Lutheran Church",
    "wof:placetype":"venue"
},
  "geometry": {"coordinates":[-83.56885200000001,41.781922],"type":"Point"}
}