{
  "type": "Feature",
  "properties": {
    "iso:country":"US",
    "sg:address":"850 Stephenson Hwy",
    "sg:city":"Troy",
    "sg:classifiers":[
        {
            "category":"Manufacturing",
            "subcategory":"Metals",
            "type":"Manufacturing & Wholesale Goods"
        }
    ],
    "sg:phone":"+1 248 577 1100",
    "sg:postcode":"48083",
    "sg:province":"MI",
    "sg:website":"www.tks-america.com",
    "wof:name":"TKS Ind Co",
    "wof:placetype":"venue"
},
  "geometry": {"coordinates":[-83.120215,42.541391],"type":"Point"}
}