{
  "type": "Feature",
  "properties": {
    "iso:country":"US",
    "sg:address":"310 N Main St",
    "sg:city":"Chelsea",
    "sg:classifiers":[
        {
            "category":"Professional",
            "subcategory":"Management & Consulting",
            "type":"Services"
        }
    ],
    "sg:phone":"+1 734 433 9888",
    "sg:postcode":"48118",
    "sg:province":"MI",
    "wof:name":"Turner Marketing",
    "wof:placetype":"venue"
},
  "geometry": {"coordinates":[-84.02047899999999,42.319729],"type":"Point"}
}