{
  "type": "Feature",
  "properties": {
    "iso:country":"US",
    "sg:address":"9833 Reeck Rd",
    "sg:city":"Allen Park",
    "sg:classifiers":[
        {
            "category":"Health Services",
            "subcategory":"Chiropractor",
            "type":"Services"
        }
    ],
    "sg:phone":"+1 313 382 5222",
    "sg:postcode":"48101",
    "sg:province":"MI",
    "wof:name":"Kalis Chiropractic Clinic",
    "wof:placetype":"venue"
},
  "geometry": {"coordinates":[-83.219869,42.23682],"type":"Point"}
}