{
  "type": "Feature",
  "properties": {
    "iso:country":"US",
    "sg:address":"43761 Schoenherr Rd",
    "sg:city":"Sterling Heights",
    "sg:classifiers":[
        {
            "category":"Bakery",
            "type":"Food & Drink"
        },
        {
            "category":"Coffee & Tea",
            "type":"Food & Drink"
        },
        {
            "category":"Bagels",
            "type":"Food & Drink"
        },
        {
            "category":"Donuts",
            "type":"Food & Drink"
        }
    ],
    "sg:menulink":"http://www.allmenus.com/mi/sterling-heights/133224-dunkin-donuts/menu/",
    "sg:phone":"+1 586 726 6770",
    "sg:postcode":"48313",
    "sg:province":"MI",
    "sg:tags":[
        "american",
        "pastry"
    ],
    "wof:name":"Dunkin' Donuts",
    "wof:placetype":"venue"
},
  "geometry": {"coordinates":[-82.992777,42.618034],"type":"Point"}
}