{
  "type": "Feature",
  "properties": {
    "iso:country":"US",
    "sg:address":"42100 Garfield Rd",
    "sg:city":"Clinton Twp",
    "sg:classifiers":[
        {
            "category":"Banks & Credit Unions",
            "subcategory":"Investment Brokerage",
            "type":"Services"
        }
    ],
    "sg:phone":"+1 586 416 0807",
    "sg:postcode":"48038",
    "sg:province":"MI",
    "sg:tags":[
        "consultant",
        "planning",
        "financial"
    ],
    "wof:name":"Petitta & Assoc",
    "wof:placetype":"venue"
},
  "geometry": {"coordinates":[-82.95260500000001,42.606076],"type":"Point"}
}