{
  "type": "Feature",
  "properties": {
    "iso:country":"US",
    "sg:address":"5763 Bates Rd",
    "sg:city":"Williamsburg",
    "sg:classifiers":[
        {
            "category":"Wholesale",
            "subcategory":"Construction Materials",
            "type":"Manufacturing & Wholesale Goods"
        }
    ],
    "sg:phone":"+1 231 267 5253",
    "sg:postcode":"49690",
    "sg:province":"MI",
    "sg:tags":[
        "lumber"
    ],
    "sg:website":"www.ssslbr.com",
    "wof:name":"Schultz Snyder & Steele Lumber",
    "wof:placetype":"venue"
},
  "geometry": {"coordinates":[-85.44467,44.759117],"type":"Point"}
}