{
  "type": "Feature",
  "properties": {
    "iso:country":"US",
    "sg:address":"2555 S Telegraph Rd",
    "sg:city":"Bloomfield Hills",
    "sg:classifiers":[
        {
            "category":"Autos & Motor Vehicles",
            "subcategory":"Automobile Sales",
            "type":"Retail Goods"
        }
    ],
    "sg:phone":"+1 248 648 2500",
    "sg:postcode":"48302",
    "sg:province":"MI",
    "sg:tags":[
        "car",
        "dealer"
    ],
    "sg:website":"www.unitedauto.com",
    "wof:name":"United Auto Group Inc",
    "wof:placetype":"venue"
},
  "geometry": {"coordinates":[-83.28881800000001,42.602695],"type":"Point"}
}