{
  "type": "Feature",
  "properties": {
    "iso:country":"US",
    "sg:address":"9238 Cleveland St",
    "sg:city":"Nunica",
    "sg:classifiers":[
        {
            "category":"Retail",
            "subcategory":"Animal Services",
            "type":"Services"
        }
    ],
    "sg:phone":"+1 616 837 3647",
    "sg:postcode":"49448",
    "sg:province":"MI",
    "sg:tags":[
        "pet",
        "grooming",
        "washing"
    ],
    "wof:name":"J & C Grimminck",
    "wof:placetype":"venue"
},
  "geometry": {"coordinates":[-86.015542,43.07435],"type":"Point"}
}