{
  "type": "Feature",
  "properties": {
    "iso:country":"US",
    "sg:address":"1375 N Main St",
    "sg:city":"Lapeer",
    "sg:classifiers":[
        {
            "category":"Health Services",
            "subcategory":"Hospital",
            "type":"Services"
        }
    ],
    "sg:phone":"+1 810 667 5500",
    "sg:postcode":"48446",
    "sg:province":"MI",
    "sg:website":"www.lapeerhospital.org",
    "wof:name":"Lapeer Regional Hospital",
    "wof:placetype":"venue"
},
  "geometry": {"coordinates":[-83.319399,43.062176],"type":"Point"}
}