{
  "type": "Feature",
  "properties": {
    "iso:country":"US",
    "sg:address":"6684 Dixie Hwy",
    "sg:city":"Clarkston",
    "sg:classifiers":[
        {
            "category":"Education",
            "subcategory":"Dance Studio",
            "type":"Public Place"
        }
    ],
    "sg:phone":"+1 248 625 1930",
    "sg:postcode":"48346",
    "sg:province":"MI",
    "sg:tags":[
        "instruction",
        "dancing"
    ],
    "wof:name":"Roxana's Dance Expressions",
    "wof:placetype":"venue"
},
  "geometry": {"coordinates":[-83.416417,42.718498],"type":"Point"}
}