{
  "type": "Feature",
  "properties": {
    "iso:country":"US",
    "sg:address":"15580 US Hwy 27 N",
    "sg:city":"Marshall",
    "sg:classifiers":[
        {
            "category":"Freight",
            "type":"Transportation"
        }
    ],
    "sg:phone":"+1 269 781 9066",
    "sg:postcode":"49068",
    "sg:province":"MI",
    "sg:tags":[
        "local",
        "trucking"
    ],
    "wof:name":"Tyler Transport LLC",
    "wof:placetype":"venue"
},
  "geometry": {"coordinates":[-84.964528,42.296378],"type":"Point"}
}