{
  "type": "Feature",
  "properties": {
    "iso:country":"US",
    "sg:address":"70 Devon Rd",
    "sg:city":"Bloomfield Hills",
    "sg:classifiers":[
        {
            "category":"Real Estate",
            "subcategory":"Real Estate Agent",
            "type":"Services"
        }
    ],
    "sg:phone":"+1 248 338 4204",
    "sg:postcode":"48302",
    "sg:province":"MI",
    "wof:name":"Real Time Designs Inc",
    "wof:placetype":"venue"
},
  "geometry": {"coordinates":[-83.267757,42.602011],"type":"Point"}
}