{
  "type": "Feature",
  "properties": {
    "iso:country":"US",
    "sg:address":"385 N Lapeer Rd",
    "sg:city":"Oxford",
    "sg:classifiers":[
        {
            "category":"Health Services",
            "subcategory":"Clinic",
            "type":"Services"
        }
    ],
    "sg:phone":"+1 248 628 0023",
    "sg:postcode":"48371",
    "sg:province":"MI",
    "wof:name":"Michigan Resonance Imaging",
    "wof:placetype":"venue"
},
  "geometry": {"coordinates":[-83.269565,42.830796],"type":"Point"}
}