{
  "type": "Feature",
  "properties": {
    "iso:country":"US",
    "sg:address":"2090 Morrill Rd",
    "sg:city":"Jackson",
    "sg:phone":"+1 517 784 7121",
    "sg:postcode":"49201",
    "sg:province":"MI",
    "sg:tags":[
        "product",
        "petroleum"
    ],
    "sg:website":"www.mapllc.com",
    "wof:name":"Marathon Ashland Petroleum",
    "wof:placetype":"venue"
},
  "geometry": {"coordinates":[-84.429756,42.310672],"type":"Point"}
}