{
  "type": "Feature",
  "properties": {
    "iso:country":"US",
    "sg:address":"21905 Allen Rd",
    "sg:city":"Woodhaven",
    "sg:classifiers":[
        {
            "category":"Retail",
            "subcategory":"Auto Repair",
            "type":"Services"
        }
    ],
    "sg:phone":"+1 734 692 2019",
    "sg:postcode":"48183",
    "sg:province":"MI",
    "wof:name":"Michael & Sons Auto Repair Inc",
    "wof:placetype":"venue"
},
  "geometry": {"coordinates":[-83.226281,42.148776],"type":"Point"}
}