{
  "type": "Feature",
  "properties": {
    "iso:country":"US",
    "sg:address":"12759 136th Ave",
    "sg:city":"Grand Haven",
    "sg:classifiers":[
        {
            "category":"Restaurant",
            "type":"Food & Drink"
        }
    ],
    "sg:phone":"+1 616 846 2292",
    "sg:postcode":"49417",
    "sg:province":"MI",
    "sg:tags":[
        "pizza"
    ],
    "wof:name":"Grand Haven Pizza Ent Inc",
    "wof:placetype":"venue"
},
  "geometry": {"coordinates":[-86.123904,42.994779],"type":"Point"}
}