{
  "type": "Feature",
  "properties": {
    "iso:country":"US",
    "sg:address":"9790 Cherry Valley Ave SE",
    "sg:city":"Caledonia",
    "sg:classifiers":[
        {
            "category":"Home & Garden",
            "subcategory":"Building Materials",
            "type":"Retail Goods"
        }
    ],
    "sg:phone":"+1 616 891 4270",
    "sg:postcode":"49316",
    "sg:province":"MI",
    "sg:tags":[
        "windows"
    ],
    "sg:website":"www.revivalwindoor.com",
    "wof:name":"Revival Windows Doors",
    "wof:placetype":"venue"
},
  "geometry": {"coordinates":[-85.506756,42.78833],"type":"Point"}
}