{
  "type": "Feature",
  "properties": {
    "iso:country":"US",
    "sg:address":"7171 E Mcnichols Rd",
    "sg:city":"Hamtramck",
    "sg:classifiers":[
        {
            "category":"Train Station",
            "subcategory":"Light Rail",
            "type":"Transportation"
        }
    ],
    "sg:phone":"+1 313 365 2222",
    "sg:postcode":"48212",
    "sg:province":"MI",
    "sg:tags":[
        "steel",
        "processing"
    ],
    "wof:name":"Pacific Steel",
    "wof:placetype":"venue"
},
  "geometry": {"coordinates":[-83.029335,42.419383],"type":"Point"}
}