{
  "type": "Feature",
  "properties": {
    "iso:country":"US",
    "sg:address":"9998 Steffas Rd",
    "sg:city":"Maybee",
    "sg:classifiers":[
        {
            "category":"Professional",
            "subcategory":"Art Services",
            "type":"Services"
        }
    ],
    "sg:phone":"+1 734 654 9743",
    "sg:postcode":"48159",
    "sg:province":"MI",
    "sg:tags":[
        "commercial",
        "design"
    ],
    "wof:name":"Mll Designs",
    "wof:placetype":"venue"
},
  "geometry": {"coordinates":[-83.454812,42.019448],"type":"Point"}
}