{
  "type": "Feature",
  "properties": {
    "iso:country":"US",
    "sg:address":"2425 W Michigan Ave",
    "sg:city":"Jackson",
    "sg:classifiers":[
        {
            "category":"Wholesale",
            "subcategory":"Machinery & Supplies",
            "type":"Manufacturing & Wholesale Goods"
        }
    ],
    "sg:phone":"+1 517 787 7220",
    "sg:postcode":"49202",
    "sg:province":"MI",
    "sg:tags":[
        "equipment",
        "hydraulic"
    ],
    "sg:website":"www.eaton.com",
    "wof:name":"Eaton Hydraulics",
    "wof:placetype":"venue"
},
  "geometry": {"coordinates":[-84.446511,42.2509],"type":"Point"}
}