{
  "type": "Feature",
  "properties": {
    "iso:country":"US",
    "sg:address":"17894 Mack Ave",
    "sg:city":"Grosse Pointe",
    "sg:classifiers":[
        {
            "category":"Health Services",
            "subcategory":"Doctor",
            "type":"Services"
        }
    ],
    "sg:phone":"+1 313 882 7480",
    "sg:postcode":"48230",
    "sg:province":"MI",
    "sg:tags":[
        "podiatrist"
    ],
    "wof:name":"Black James DPM",
    "wof:placetype":"venue"
},
  "geometry": {"coordinates":[-82.916298,42.404301],"type":"Point"}
}