{
  "type": "Feature",
  "properties": {
    "iso:country":"US",
    "sg:address":"103 E John St",
    "sg:city":"Newberry",
    "sg:classifiers":[
        {
            "category":"Health Services",
            "subcategory":"Hospital",
            "type":"Services"
        }
    ],
    "sg:phone":"+1 906 293 9451",
    "sg:postcode":"49868",
    "sg:province":"MI",
    "sg:tags":[
        "mental"
    ],
    "wof:name":"Rainbow's End",
    "wof:placetype":"venue"
},
  "geometry": {"coordinates":[-85.509744,46.355024],"type":"Point"}
}