{
  "type": "Feature",
  "properties": {
    "iso:country":"US",
    "sg:address":"18645 15 Mile Rd",
    "sg:city":"Clinton Township",
    "sg:classifiers":[
        {
            "category":"Restaurant",
            "type":"Food & Drink"
        }
    ],
    "sg:menulink":"http://www.allmenus.com/mi/clinton/27384-stackers-coney--grill/menu/",
    "sg:phone":"+1 586 792 5555",
    "sg:postcode":"48035",
    "sg:province":"MI",
    "sg:tags":[
        "american"
    ],
    "wof:name":"Stacker's Coney & Grill",
    "wof:placetype":"venue"
},
  "geometry": {"coordinates":[-82.930842,42.554008],"type":"Point"}
}