{
  "type": "Feature",
  "properties": {
    "iso:country":"US",
    "sg:address":"7714 Cooley Lake Rd",
    "sg:city":"Waterford",
    "sg:classifiers":[
        {
            "category":"Food & Beverages",
            "subcategory":"Meat & Fish",
            "type":"Retail Goods"
        }
    ],
    "sg:phone":"+1 248 363 2041",
    "sg:postcode":"48327",
    "sg:province":"MI",
    "sg:website":"www.meatbundles.net",
    "wof:name":"Market Place Meats & Deli",
    "wof:placetype":"venue"
},
  "geometry": {"coordinates":[-83.423821,42.615619],"type":"Point"}
}