{
  "type": "Feature",
  "properties": {
    "iso:country":"US",
    "sg:address":"15196 S Telegraph Rd",
    "sg:city":"Monroe",
    "sg:classifiers":[
        {
            "category":"Freight",
            "type":"Transportation"
        }
    ],
    "sg:phone":"+1 734 241 3600",
    "sg:postcode":"48161",
    "sg:province":"MI",
    "sg:tags":[
        "commercial",
        "storage"
    ],
    "wof:name":"South Telegraph Towing & Stge",
    "wof:placetype":"venue"
},
  "geometry": {"coordinates":[-83.431472,41.89716],"type":"Point"}
}