{
  "type": "Feature",
  "properties": {
    "iso:country":"US",
    "sg:address":"1871 Holton Rd",
    "sg:city":"Muskegon",
    "sg:classifiers":[
        {
            "category":"Shopping",
            "subcategory":"Optical Goods",
            "type":"Retail Goods"
        }
    ],
    "sg:phone":"+1 231 719 9200",
    "sg:postcode":"49445",
    "sg:province":"MI",
    "wof:name":"Eye Care One",
    "wof:placetype":"venue"
},
  "geometry": {"coordinates":[-86.22102700000001,43.286315],"type":"Point"}
}