{
  "type": "Feature",
  "properties": {
    "iso:country":"US",
    "sg:address":"35021 Kelly Rd",
    "sg:city":"Clinton Township",
    "sg:classifiers":[
        {
            "category":"Professional",
            "subcategory":"Accounting & Tax Preparation",
            "type":"Services"
        }
    ],
    "sg:phone":"+1 586 790 9012",
    "sg:postcode":"48035",
    "sg:province":"MI",
    "sg:tags":[
        "accountant"
    ],
    "wof:name":"Grzywacz & Grzywacz CPA",
    "wof:placetype":"venue"
},
  "geometry": {"coordinates":[-82.93029799999999,42.554001],"type":"Point"}
}