{
  "type": "Feature",
  "properties": {
    "iso:country":"US",
    "sg:address":"5126 US Hwy 51",
    "sg:city":"Mercer",
    "sg:classifiers":[
        {
            "category":"Food & Beverages",
            "subcategory":"Groceries & Convenience Stores",
            "type":"Retail Goods"
        }
    ],
    "sg:phone":"+1 715 476 9150",
    "sg:postcode":"54547",
    "sg:province":"WI",
    "sg:tags":[
        "grocer"
    ],
    "wof:name":"Snow's Family Market",
    "wof:placetype":"venue"
},
  "geometry": {"coordinates":[-90.056878,46.163039],"type":"Point"}
}