{
  "type": "Feature",
  "properties": {
    "iso:country":"US",
    "sg:address":"41440 Ann Arbor Rd E",
    "sg:city":"Plymouth",
    "sg:classifiers":[
        {
            "category":"Retail",
            "subcategory":"Laundry & Dry Cleaning",
            "type":"Services"
        }
    ],
    "sg:phone":"+1 734 335 7701",
    "sg:postcode":"48170",
    "sg:province":"MI",
    "wof:name":"Lavanderia Cleaners",
    "wof:placetype":"venue"
},
  "geometry": {"coordinates":[-83.449988,42.359334],"type":"Point"}
}