{
  "type": "Feature",
  "properties": {
    "iso:country":"US",
    "sg:address":"7336 E Baldwin Rd",
    "sg:city":"Grand Blanc",
    "sg:classifiers":[
        {
            "category":"Sports & Exercise",
            "subcategory":"Gym",
            "type":"Entertainment"
        }
    ],
    "sg:phone":"+1 810 695 2298",
    "sg:postcode":"48439",
    "sg:province":"MI",
    "sg:tags":[
        "fitness",
        "physical",
        "facility"
    ],
    "wof:name":"Total Body Fitness Training",
    "wof:placetype":"venue"
},
  "geometry": {"coordinates":[-83.55249999999999,42.888577],"type":"Point"}
}