{
  "type": "Feature",
  "properties": {
    "iso:country":"US",
    "sg:address":"615 N State St",
    "sg:city":"Caro",
    "sg:classifiers":[
        {
            "category":"Cinema",
            "subcategory":"Movie Rental",
            "type":"Entertainment"
        }
    ],
    "sg:phone":"+1 989 673 5110",
    "sg:postcode":"48723",
    "sg:province":"MI",
    "sg:tags":[
        "video",
        "tape",
        "merchandise"
    ],
    "wof:name":"Entertainer",
    "wof:placetype":"venue"
},
  "geometry": {"coordinates":[-83.391149,43.493024],"type":"Point"}
}