{
  "type": "Feature",
  "properties": {
    "iso:country":"US",
    "sg:address":"8714 W Grand River Ave",
    "sg:city":"Brighton",
    "sg:classifiers":[
        {
            "category":"Coffee & Tea",
            "type":"Food & Drink"
        }
    ],
    "sg:menulink":"http://www.allmenus.com/mi/brighton/248921-beaners/menu/",
    "sg:phone":"+1 810 227 2271",
    "sg:postcode":"48116",
    "sg:province":"MI",
    "sg:tags":[
        "american"
    ],
    "wof:name":"Beaners",
    "wof:placetype":"venue"
},
  "geometry": {"coordinates":[-83.78482099999999,42.537832],"type":"Point"}
}