{
  "type": "Feature",
  "properties": {
    "iso:country":"US",
    "sg:address":"21901 Allen Rd",
    "sg:city":"Trenton",
    "sg:classifiers":[
        {
            "category":"Retail",
            "subcategory":"Auto Repair",
            "type":"Services"
        }
    ],
    "sg:phone":"+1 734 676 6055",
    "sg:postcode":"48183",
    "sg:province":"MI",
    "sg:tags":[
        "shop",
        "lube"
    ],
    "wof:name":"Lube Max II",
    "wof:placetype":"venue"
},
  "geometry": {"coordinates":[-83.226404,42.149091],"type":"Point"}
}