{
  "type": "Feature",
  "properties": {
    "iso:country":"US",
    "sg:address":"2962 Michigan Rd",
    "sg:city":"Port Huron",
    "sg:classifiers":[
        {
            "category":"Social Services",
            "subcategory":"Adult Care",
            "type":"Services"
        }
    ],
    "sg:phone":"+1 810 984 3553",
    "sg:postcode":"48060",
    "sg:province":"MI",
    "sg:tags":[
        "residential"
    ],
    "wof:name":"Impact",
    "wof:placetype":"venue"
},
  "geometry": {"coordinates":[-82.48359499999999,42.986291],"type":"Point"}
}