{
  "type": "Feature",
  "properties": {
    "iso:country":"US",
    "sg:address":"3031 Silverstone Ln",
    "sg:city":"Waterford",
    "sg:classifiers":[
        {
            "category":"Manufacturing",
            "subcategory":"Tools & Machinery",
            "type":"Manufacturing & Wholesale Goods"
        }
    ],
    "sg:phone":"+1 248 334 2309",
    "sg:postcode":"48329",
    "sg:province":"MI",
    "sg:tags":[
        "mfg",
        "custom",
        "machine",
        "computer",
        "accessory",
        "programing"
    ],
    "wof:name":"Croft Metrology Solutions",
    "wof:placetype":"venue"
},
  "geometry": {"coordinates":[-83.33109,42.680682],"type":"Point"}
}