{
  "type": "Feature",
  "properties": {
    "iso:country":"US",
    "sg:address":"21450 24th Ave",
    "sg:city":"Conklin",
    "sg:classifiers":[
        {
            "category":"Farming",
            "subcategory":"Livestock Farm",
            "type":"Manufacturing & Wholesale Goods"
        }
    ],
    "sg:phone":"+1 616 899 2327",
    "sg:postcode":"49403",
    "sg:province":"MI",
    "sg:tags":[
        "beef",
        "feedlot",
        "cattle"
    ],
    "wof:name":"Springdale Farm",
    "wof:placetype":"venue"
},
  "geometry": {"coordinates":[-85.84939300000001,43.159695],"type":"Point"}
}