{
  "type": "Feature",
  "properties": {
    "iso:country":"US",
    "sg:address":"401 W Jenny St",
    "sg:city":"Bay City",
    "sg:classifiers":[
        {
            "category":"Building & Trades",
            "subcategory":"Construction",
            "type":"Services"
        }
    ],
    "sg:phone":"+1 989 893 7608",
    "sg:postcode":"48706",
    "sg:province":"MI",
    "sg:tags":[
        "tower",
        "maintenance"
    ],
    "wof:name":"C A T S",
    "wof:placetype":"venue"
},
  "geometry": {"coordinates":[-83.90956799999999,43.598718],"type":"Point"}
}