{
  "type": "Feature",
  "properties": {
    "iso:country":"US",
    "sg:address":"52892 Seven Oaks Dr",
    "sg:city":"Shelby Twp",
    "sg:classifiers":[
        {
            "category":"Real Estate",
            "subcategory":"Real Estate Agent",
            "type":"Services"
        }
    ],
    "sg:phone":"+1 586 726 7305",
    "sg:postcode":"48316",
    "sg:province":"MI",
    "sg:tags":[
        "management"
    ],
    "wof:name":"Emerald Creek Inc",
    "wof:placetype":"venue"
},
  "geometry": {"coordinates":[-83.077828,42.682766],"type":"Point"}
}