{
  "type": "Feature",
  "properties": {
    "iso:country":"US",
    "sg:address":"26200 Town Center Dr",
    "sg:city":"Novi",
    "sg:classifiers":[
        {
            "category":"Wholesale",
            "subcategory":"Auto Parts",
            "type":"Manufacturing & Wholesale Goods"
        }
    ],
    "sg:phone":"+1 248 449 8696",
    "sg:postcode":"48375",
    "sg:province":"MI",
    "sg:tags":[
        "tire"
    ],
    "wof:name":"Toyo Tire USA Inc",
    "wof:placetype":"venue"
},
  "geometry": {"coordinates":[-83.469684,42.483418],"type":"Point"}
}