{
  "type": "Feature",
  "properties": {
    "iso:country":"US",
    "sg:address":"307 S Harbor Dr",
    "sg:city":"Grand Haven",
    "sg:classifiers":[
        {
            "category":"Government",
            "subcategory":"Office",
            "type":"Public Place"
        }
    ],
    "sg:phone":"+1 616 842 5510",
    "sg:postcode":"49417",
    "sg:province":"MI",
    "sg:tags":[
        "federal"
    ],
    "wof:name":"US Army Corps Of Engineers",
    "wof:placetype":"venue"
},
  "geometry": {"coordinates":[-86.235927,43.061895],"type":"Point"}
}