{
  "type": "Feature",
  "properties": {
    "iso:country":"US",
    "sg:address":"1038 N Bridge St",
    "sg:city":"Linden",
    "sg:classifiers":[
        {
            "category":"Retail",
            "subcategory":"Veterinary Services",
            "type":"Services"
        }
    ],
    "sg:phone":"+1 810 735 7857",
    "sg:postcode":"48451",
    "sg:province":"MI",
    "sg:tags":[
        "veterinarian"
    ],
    "wof:name":"VCA Companion Animal Hospital",
    "wof:placetype":"venue"
},
  "geometry": {"coordinates":[-83.782687,42.824715],"type":"Point"}
}