{
  "type": "Feature",
  "properties": {
    "iso:country":"US",
    "sg:address":"5740 Newhaven Dr",
    "sg:city":"Portage",
    "sg:classifiers":[
        {
            "category":"Building & Trades",
            "subcategory":"Landscaping Services",
            "type":"Services"
        }
    ],
    "sg:phone":"+1 269 327 4824",
    "sg:postcode":"49024",
    "sg:province":"MI",
    "sg:tags":[
        "landscape",
        "contractor"
    ],
    "wof:name":"RCB Landscaping",
    "wof:placetype":"venue"
},
  "geometry": {"coordinates":[-85.619591,42.233858],"type":"Point"}
}