{
  "type": "Feature",
  "properties": {
    "iso:country":"US",
    "sg:address":"4493 Kuebler Ct",
    "sg:city":"Ann Arbor",
    "sg:classifiers":[
        {
            "category":"Organizations",
            "subcategory":"Labor Organization",
            "type":"Services"
        }
    ],
    "sg:phone":"+1 734 761 1807",
    "sg:postcode":"48103",
    "sg:province":"MI",
    "wof:name":"P & S Properties Lc",
    "wof:placetype":"venue"
},
  "geometry": {"coordinates":[-83.817002,42.29619],"type":"Point"}
}