{
  "type": "Feature",
  "properties": {
    "iso:country":"US",
    "sg:address":"1521 Georgia Ave",
    "sg:city":"Marysville",
    "sg:classifiers":[
        {
            "category":"Health Services",
            "subcategory":"Clinic",
            "type":"Services"
        }
    ],
    "sg:phone":"+1 810 388 5222",
    "sg:postcode":"48040",
    "sg:province":"MI",
    "wof:name":"Progressive Health Concepts",
    "wof:placetype":"venue"
},
  "geometry": {"coordinates":[-82.492271,42.906756],"type":"Point"}
}