{
  "type": "Feature",
  "properties": {
    "iso:country":"US",
    "sg:address":"2979 Sand Beach Rd",
    "sg:city":"Bad Axe",
    "sg:classifiers":[
        {
            "category":"Building & Trades",
            "subcategory":"Construction",
            "type":"Services"
        }
    ],
    "sg:phone":"+1 989 269 9665",
    "sg:postcode":"48413",
    "sg:province":"MI",
    "sg:tags":[
        "nonresidential"
    ],
    "wof:name":"Schenk Brothers Construction",
    "wof:placetype":"venue"
},
  "geometry": {"coordinates":[-82.884012,43.805784],"type":"Point"}
}