{
  "type": "Feature",
  "properties": {
    "iso:country":"US",
    "sg:address":"5612 E Boardman Rd",
    "sg:city":"South Boardman",
    "sg:classifiers":[
        {
            "category":"Professional",
            "subcategory":"Management & Consulting",
            "type":"Services"
        }
    ],
    "sg:phone":"+1 231 369 2977",
    "sg:postcode":"49680",
    "sg:province":"MI",
    "sg:tags":[
        "consultant",
        "safety"
    ],
    "wof:name":"Safety By Design",
    "wof:placetype":"venue"
},
  "geometry": {"coordinates":[-85.28527,44.641319],"type":"Point"}
}