{
  "type": "Feature",
  "properties": {
    "iso:country":"US",
    "sg:address":"524 King St",
    "sg:city":"Ionia",
    "sg:classifiers":[
        {
            "category":"Food & Beverages",
            "subcategory":"Specialty",
            "type":"Retail Goods"
        }
    ],
    "sg:phone":"+1 616 527 3950",
    "sg:postcode":"48846",
    "sg:province":"MI",
    "sg:tags":[
        "vitamin"
    ],
    "wof:name":"L & E Distributors",
    "wof:placetype":"venue"
},
  "geometry": {"coordinates":[-85.076623,42.988273],"type":"Point"}
}