{
  "type": "Feature",
  "properties": {
    "iso:country":"US",
    "sg:address":"316 Hillview St",
    "sg:city":"Buchanan",
    "sg:classifiers":[
        {
            "category":"Shopping",
            "subcategory":"Computers & Home Electronics",
            "type":"Retail Goods"
        }
    ],
    "sg:phone":"+1 269 695 5547",
    "sg:postcode":"49107",
    "sg:province":"MI",
    "sg:tags":[
        "regulation",
        "commercial"
    ],
    "wof:name":"Bobs Computer Sales",
    "wof:placetype":"venue"
},
  "geometry": {"coordinates":[-86.376082,41.824136],"type":"Point"}
}