{
  "type": "Feature",
  "properties": {
    "iso:country":"US",
    "sg:address":"135 W Green St",
    "sg:city":"Marshall",
    "sg:classifiers":[
        {
            "category":"Organizations",
            "subcategory":"Religious Organization",
            "type":"Services"
        }
    ],
    "sg:phone":"+1 269 781 8982",
    "sg:postcode":"49068",
    "sg:province":"MI",
    "sg:tags":[
        "church"
    ],
    "wof:name":"Zion Luteheran Church",
    "wof:placetype":"venue"
},
  "geometry": {"coordinates":[-84.96056799999999,42.270974],"type":"Point"}
}