{
  "type": "Feature",
  "properties": {
    "iso:country":"US",
    "sg:address":"14836 Bassett St",
    "sg:city":"Livonia",
    "sg:classifiers":[
        {
            "category":"Professional",
            "subcategory":"Management & Consulting",
            "type":"Services"
        }
    ],
    "sg:phone":"+1 734 542 8076",
    "sg:postcode":"48154",
    "sg:province":"MI",
    "sg:tags":[
        "programming",
        "system",
        "analysis"
    ],
    "wof:name":"Karl Systems Inc",
    "wof:placetype":"venue"
},
  "geometry": {"coordinates":[-83.429534,42.391575],"type":"Point"}
}