{
  "type": "Feature",
  "properties": {
    "iso:country":"US",
    "sg:address":"530 N State St",
    "sg:city":"Sparta",
    "sg:classifiers":[
        {
            "category":"Shopping",
            "subcategory":"Discount & Variety Stores",
            "type":"Retail Goods"
        }
    ],
    "sg:phone":"+1 616 887 7313",
    "sg:postcode":"49345",
    "sg:province":"MI",
    "wof:name":"Dollar N' More Store",
    "wof:placetype":"venue"
},
  "geometry": {"coordinates":[-85.710201,43.168111],"type":"Point"}
}