{
  "type": "Feature",
  "properties": {
    "iso:country":"US",
    "sg:address":"1034 S Grand Traverse St",
    "sg:city":"Flint",
    "sg:classifiers":[
        {
            "category":"Banks & Credit Unions",
            "subcategory":"Atm",
            "type":"Services"
        },
        {
            "category":"Professional",
            "subcategory":"Lawyer & Legal Services",
            "type":"Services"
        },
        {
            "category":"Bars & Pubs",
            "subcategory":"Nightclub",
            "type":"Food & Drink"
        }
    ],
    "sg:phone":"+1 810 238 0900",
    "sg:postcode":"48502",
    "sg:province":"MI",
    "sg:tags":[
        "notary",
        "nightlife",
        "bankruptcy"
    ],
    "wof:name":"Meiers Erwin F III PC Atty",
    "wof:placetype":"venue"
},
  "geometry": {"coordinates":[-83.689796,43.0084],"type":"Point"}
}