{
  "type": "Feature",
  "properties": {
    "iso:country":"US",
    "sg:address":"20670 Kensington Ct",
    "sg:city":"Southfield",
    "sg:classifiers":[
        {
            "category":"Professional",
            "subcategory":"Accounting & Tax Preparation",
            "type":"Services"
        }
    ],
    "sg:phone":"+1 248 350 1044",
    "sg:postcode":"48076",
    "sg:province":"MI",
    "sg:tags":[
        "accountant"
    ],
    "wof:name":"Cooper & Co",
    "wof:placetype":"venue"
},
  "geometry": {"coordinates":[-83.251696,42.484648],"type":"Point"}
}