{
  "type": "Feature",
  "properties": {
    "iso:country":"US",
    "sg:address":"1531 N Telegraph Rd",
    "sg:city":"Monroe",
    "sg:classifiers":[
        {
            "category":"Government",
            "subcategory":"Office",
            "type":"Public Place"
        }
    ],
    "sg:phone":"+1 734 240 7950",
    "sg:postcode":"48162",
    "sg:province":"MI",
    "wof:name":"Michigan Works-Monroe County",
    "wof:placetype":"venue"
},
  "geometry": {"coordinates":[-83.40589,41.939514],"type":"Point"}
}