{
  "type": "Feature",
  "properties": {
    "iso:country":"US",
    "sg:address":"5084 W Pierson Rd",
    "sg:city":"Flint",
    "sg:classifiers":[
        {
            "category":"Health Services",
            "subcategory":"Doctor",
            "type":"Services"
        }
    ],
    "sg:phone":"+1 810 732 2950",
    "sg:postcode":"48504",
    "sg:province":"MI",
    "sg:tags":[
        "medical"
    ],
    "wof:name":"Internal Medicine & Pediatrics",
    "wof:placetype":"venue"
},
  "geometry": {"coordinates":[-83.775458,43.060628],"type":"Point"}
}