{
  "type": "Feature",
  "properties": {
    "iso:country":"US",
    "sg:address":"1285 N Telegraph Rd",
    "sg:city":"Monroe",
    "sg:classifiers":[
        {
            "category":"Shopping",
            "subcategory":"Computers & Home Electronics",
            "type":"Retail Goods"
        }
    ],
    "sg:phone":"+1 734 241 2449",
    "sg:postcode":"48162",
    "sg:province":"MI",
    "sg:tags":[
        "equipment",
        "dealer"
    ],
    "wof:name":"Priority Computers",
    "wof:placetype":"venue"
},
  "geometry": {"coordinates":[-83.40636000000001,41.938709],"type":"Point"}
}