{
  "type": "Feature",
  "properties": {
    "iso:country":"US",
    "sg:address":"229 E Front St",
    "sg:city":"Traverse City",
    "sg:classifiers":[
        {
            "category":"Restaurant",
            "type":"Food & Drink"
        }
    ],
    "sg:phone":"+1 231 941 8888",
    "sg:postcode":"49686",
    "sg:province":"MI",
    "sg:website":"www.amical.com",
    "wof:name":"LA Cuisine Amical",
    "wof:placetype":"venue"
},
  "geometry": {"coordinates":[-85.62044400000001,44.764139],"type":"Point"}
}