{
  "type": "Feature",
  "properties": {
    "iso:country":"US",
    "sg:address":"424 N 3rd St",
    "sg:city":"Marquette",
    "sg:classifiers":[
        {
            "category":"Shopping",
            "subcategory":"Stationery & Office Supplies",
            "type":"Retail Goods"
        }
    ],
    "sg:phone":"+1 906 226 6131",
    "sg:postcode":"49855",
    "sg:province":"MI",
    "wof:name":"Standard Register Company",
    "wof:placetype":"venue"
},
  "geometry": {"coordinates":[-87.394655,46.546908],"type":"Point"}
}