{
  "type": "Feature",
  "properties": {
    "iso:country":"US",
    "sg:address":"8469 Hollywood Rd",
    "sg:city":"Berrien Springs",
    "sg:classifiers":[
        {
            "category":"Retail",
            "subcategory":"Repair Shop",
            "type":"Services"
        }
    ],
    "sg:phone":"+1 269 473 1140",
    "sg:postcode":"49103",
    "sg:province":"MI",
    "sg:tags":[
        "welding"
    ],
    "wof:name":"Rays Welding Co Inc",
    "wof:placetype":"venue"
},
  "geometry": {"coordinates":[-86.455782,41.964011],"type":"Point"}
}