{
  "type": "Feature",
  "properties": {
    "iso:country":"US",
    "sg:address":"303 Park St",
    "sg:city":"Wayland",
    "sg:classifiers":[
        {
            "category":"Professional",
            "subcategory":"Research",
            "type":"Services"
        }
    ],
    "sg:phone":"+1 269 792 9935",
    "sg:postcode":"49348",
    "sg:province":"MI",
    "sg:tags":[
        "commercial",
        "physical"
    ],
    "wof:name":"Koch Envmtl Analytical Conslt",
    "wof:placetype":"venue"
},
  "geometry": {"coordinates":[-85.646837,42.677582],"type":"Point"}
}