{
  "type": "Feature",
  "properties": {
    "iso:country":"US",
    "sg:address":"28500 Franklin Rd",
    "sg:city":"Southfield",
    "sg:classifiers":[
        {
            "category":"Food & Beverages",
            "subcategory":"Liquor & Beverages",
            "type":"Retail Goods"
        }
    ],
    "sg:phone":"+1 248 827 6000",
    "sg:postcode":"48034",
    "sg:province":"MI",
    "sg:tags":[
        "beer",
        "spirit",
        "wine"
    ],
    "wof:name":"Franklin Liquor and Deli",
    "wof:placetype":"venue"
},
  "geometry": {"coordinates":[-83.304384,42.49756],"type":"Point"}
}