{
  "type": "Feature",
  "properties": {
    "iso:country":"US",
    "sg:address":"711 Washington Ave",
    "sg:city":"Bay City",
    "sg:classifiers":[
        {
            "category":"Travel",
            "subcategory":"Travel Agent",
            "type":"Entertainment"
        }
    ],
    "sg:phone":"+1 989 894 0560",
    "sg:postcode":"48708",
    "sg:province":"MI",
    "sg:tags":[
        "agency",
        "bureau"
    ],
    "wof:name":"Journey's Unlimited Inc",
    "wof:placetype":"venue"
},
  "geometry": {"coordinates":[-83.88788099999999,43.597955],"type":"Point"}
}