{
  "type": "Feature",
  "properties": {
    "iso:country":"US",
    "sg:address":"2105 Pless Dr",
    "sg:city":"Brighton",
    "sg:classifiers":[
        {
            "category":"Professional",
            "subcategory":"Testing Lab",
            "type":"Services"
        }
    ],
    "sg:phone":"+1 810 229 7575",
    "sg:postcode":"48114",
    "sg:province":"MI",
    "sg:tags":[
        "laboratory",
        "environmental"
    ],
    "wof:name":"Brighton Analytical Inc",
    "wof:placetype":"venue"
},
  "geometry": {"coordinates":[-83.812673,42.569146],"type":"Point"}
}