{
  "type": "Feature",
  "properties": {
    "iso:country":"US",
    "sg:address":"1133 S Long Lake Blvd",
    "sg:city":"Lake Orion",
    "sg:classifiers":[
        {
            "category":"Social Services",
            "subcategory":"Adult Care",
            "type":"Services"
        }
    ],
    "sg:phone":"+1 248 814 1068",
    "sg:postcode":"48362",
    "sg:province":"MI",
    "sg:tags":[
        "foster",
        "provider"
    ],
    "wof:name":"Nancy Birkenhaver",
    "wof:placetype":"venue"
},
  "geometry": {"coordinates":[-83.223741,42.790576],"type":"Point"}
}