{
  "type": "Feature",
  "properties": {
    "iso:country":"US",
    "sg:address":"120 W Hamlin St",
    "sg:city":"Eaton Rapids",
    "sg:classifiers":[
        {
            "category":"Shopping",
            "subcategory":"Gifts & Souvenirs",
            "type":"Retail Goods"
        }
    ],
    "sg:phone":"+1 517 663 5334",
    "sg:postcode":"48827",
    "sg:province":"MI",
    "sg:tags":[
        "collectible"
    ],
    "wof:name":"When I Was A Kid Collectibles",
    "wof:placetype":"venue"
},
  "geometry": {"coordinates":[-84.655934,42.511646],"type":"Point"}
}