{
  "type": "Feature",
  "properties": {
    "iso:country":"US",
    "sg:address":"10313 Morse Lake Ave SE",
    "sg:city":"Alto",
    "sg:classifiers":[
        {
            "category":"Retail",
            "subcategory":"Animal Services",
            "type":"Services"
        }
    ],
    "sg:phone":"+1 616 891 8730",
    "sg:postcode":"49302",
    "sg:province":"MI",
    "sg:tags":[
        "pet"
    ],
    "wof:name":"Pinebrook Pet Care",
    "wof:placetype":"venue"
},
  "geometry": {"coordinates":[-85.40816599999999,42.777558],"type":"Point"}
}