{
  "type": "Feature",
  "properties": {
    "iso:country":"US",
    "sg:address":"2708 Gorno St",
    "sg:city":"Trenton",
    "sg:classifiers":[
        {
            "category":"Restaurant",
            "type":"Food & Drink"
        }
    ],
    "sg:phone":"+1 734 692 7336",
    "sg:postcode":"48183",
    "sg:province":"MI",
    "sg:tags":[
        "eating"
    ],
    "wof:name":"Cottage Coffee House Inc",
    "wof:placetype":"venue"
},
  "geometry": {"coordinates":[-83.191413,42.142573],"type":"Point"}
}