{
  "type": "Feature",
  "properties": {
    "iso:country":"US",
    "sg:address":"7629 W White Birch Ave",
    "sg:city":"Lake City",
    "sg:classifiers":[
        {
            "category":"Professional",
            "type":"Services"
        }
    ],
    "sg:phone":"+1 231 839 4558",
    "sg:postcode":"49651",
    "sg:province":"MI",
    "sg:tags":[
        "establishment"
    ],
    "wof:name":"Carney Cottage",
    "wof:placetype":"venue"
},
  "geometry": {"coordinates":[-85.235821,44.334522],"type":"Point"}
}