{
  "type": "Feature",
  "properties": {
    "iso:country":"US",
    "sg:address":"2404 S Airport Rd W",
    "sg:city":"Traverse City",
    "sg:classifiers":[
        {
            "category":"Wholesale",
            "subcategory":"Machinery & Supplies",
            "type":"Manufacturing & Wholesale Goods"
        }
    ],
    "sg:phone":"+1 231 946 2650",
    "sg:postcode":"49684",
    "sg:province":"MI",
    "sg:tags":[
        "bearing"
    ],
    "wof:name":"Applied Industrial Tech",
    "wof:placetype":"venue"
},
  "geometry": {"coordinates":[-85.625283,44.733511],"type":"Point"}
}