{
  "type": "Feature",
  "properties": {
    "iso:country":"US",
    "sg:address":"308 E Cayuga St",
    "sg:city":"Bellaire",
    "sg:classifiers":[
        {
            "category":"Organizations",
            "subcategory":"Professional Association",
            "type":"Services"
        }
    ],
    "sg:phone":"+1 231 533 6023",
    "sg:postcode":"49615",
    "sg:province":"MI",
    "sg:tags":[
        "chambers",
        "commerce"
    ],
    "sg:website":"www.bellairemichigan.com",
    "wof:name":"Bellaire Chamber Of Commerce",
    "wof:placetype":"venue"
},
  "geometry": {"coordinates":[-85.20598,44.975374],"type":"Point"}
}