{
  "type": "Feature",
  "properties": {
    "iso:country":"US",
    "sg:address":"4001 S Telegraph Rd",
    "sg:city":"Dearborn Heights",
    "sg:classifiers":[
        {
            "category":"Cinema",
            "subcategory":"Movie Rental",
            "type":"Entertainment"
        }
    ],
    "sg:phone":"+1 313 277 4747",
    "sg:postcode":"48125",
    "sg:province":"MI",
    "sg:tags":[
        "game",
        "video"
    ],
    "sg:website":"www.blockbuster.com",
    "wof:name":"Blockbuster Video",
    "wof:placetype":"venue"
},
  "geometry": {"coordinates":[-83.27040100000001,42.280499],"type":"Point"}
}