{
  "type": "Feature",
  "properties": {
    "iso:country":"US",
    "sg:address":"5833 Division St",
    "sg:city":"Newaygo",
    "sg:classifiers":[
        {
            "category":"Government",
            "subcategory":"Office",
            "type":"Public Place"
        }
    ],
    "sg:phone":"+1 231 652 4301",
    "sg:postcode":"49337",
    "sg:province":"MI",
    "sg:tags":[
        "village"
    ],
    "wof:name":"Croton Twp Office",
    "wof:placetype":"venue"
},
  "geometry": {"coordinates":[-85.655494,43.439665],"type":"Point"}
}