{
  "type": "Feature",
  "properties": {
    "iso:country":"US",
    "sg:address":"2500 Normadele St",
    "sg:city":"Waterford",
    "sg:classifiers":[
        {
            "category":"Building & Trades",
            "subcategory":"Construction",
            "type":"Services"
        }
    ],
    "sg:phone":"+1 248 674 8210",
    "sg:postcode":"48328",
    "sg:province":"MI",
    "sg:tags":[
        "dry wall",
        "contractor"
    ],
    "wof:name":"Hamilton Dry Wall & Paint Co",
    "wof:placetype":"venue"
},
  "geometry": {"coordinates":[-83.336727,42.67368],"type":"Point"}
}