{
  "type": "Feature",
  "properties": {
    "iso:country":"US",
    "sg:address":"8800 Ferry St",
    "sg:city":"Montague",
    "sg:classifiers":[
        {
            "category":"Building & Trades",
            "subcategory":"Construction",
            "type":"Services"
        }
    ],
    "sg:phone":"+1 231 893 8650",
    "sg:postcode":"49437",
    "sg:province":"MI",
    "sg:tags":[
        "general",
        "contractor"
    ],
    "wof:name":"White Lake Builders Inc",
    "wof:placetype":"venue"
},
  "geometry": {"coordinates":[-86.354579,43.418912],"type":"Point"}
}