{
  "type": "Feature",
  "properties": {
    "iso:country":"US",
    "sg:address":"1004 N Sheridan St",
    "sg:city":"Bay City",
    "sg:classifiers":[
        {
            "category":"Shopping",
            "subcategory":"Computers & Home Electronics",
            "type":"Retail Goods"
        }
    ],
    "sg:phone":"+1 989 893 7623",
    "sg:postcode":"48708",
    "sg:province":"MI",
    "sg:tags":[
        "software"
    ],
    "wof:name":"FBE Assoc",
    "wof:placetype":"venue"
},
  "geometry": {"coordinates":[-83.87652,43.600169],"type":"Point"}
}