{
  "type": "Feature",
  "properties": {
    "iso:country":"US",
    "sg:address":"3705 State Hwy 65",
    "sg:city":"Hale",
    "sg:classifiers":[
        {
            "category":"Shopping",
            "subcategory":"Computers & Home Electronics",
            "type":"Retail Goods"
        }
    ],
    "sg:phone":"+1 989 728 2207",
    "sg:postcode":"48739",
    "sg:province":"MI",
    "sg:tags":[
        "software"
    ],
    "wof:name":"Custom Software Inc",
    "wof:placetype":"venue"
},
  "geometry": {"coordinates":[-83.804946,44.382179],"type":"Point"}
}