{
  "type": "Feature",
  "properties": {
    "iso:country":"US",
    "sg:address":"72825 McFadden Rd",
    "sg:city":"Armada",
    "sg:classifiers":[
        {
            "category":"Retail",
            "subcategory":"Repair Shop",
            "type":"Services"
        }
    ],
    "sg:phone":"+1 586 336 9319",
    "sg:postcode":"48005",
    "sg:province":"MI",
    "sg:tags":[
        "snowmobile",
        "maintenance"
    ],
    "wof:name":"Extreme Performance",
    "wof:placetype":"venue"
},
  "geometry": {"coordinates":[-82.973691,42.833138],"type":"Point"}
}