{
  "type": "Feature",
  "properties": {
    "iso:country":"US",
    "sg:address":"1740 Holton Rd",
    "sg:city":"North Muskegon",
    "sg:classifiers":[
        {
            "category":"Autos & Motor Vehicles",
            "subcategory":"Auto Supplies",
            "type":"Retail Goods"
        }
    ],
    "sg:phone":"+1 231 744 4265",
    "sg:postcode":"49445",
    "sg:province":"MI",
    "sg:tags":[
        "automobile",
        "parts"
    ],
    "sg:website":"www.autozone.com",
    "wof:name":"Autozone",
    "wof:placetype":"venue"
},
  "geometry": {"coordinates":[-86.22369,43.284526],"type":"Point"}
}