{
  "type": "Feature",
  "properties": {
    "iso:country":"US",
    "sg:address":"24327 Ann Arbor Trl",
    "sg:city":"Dearborn Heights",
    "sg:classifiers":[
        {
            "category":"Retail",
            "subcategory":"Auto Repair",
            "type":"Services"
        }
    ],
    "sg:phone":"+1 313 562 1700",
    "sg:postcode":"48127",
    "sg:province":"MI",
    "wof:name":"Quality Auto Care",
    "wof:placetype":"venue"
},
  "geometry": {"coordinates":[-83.276448,42.350064],"type":"Point"}
}