{
  "type": "Feature",
  "properties": {
    "iso:country":"US",
    "sg:address":"123 E Herman St",
    "sg:city":"Alpena",
    "sg:classifiers":[
        {
            "category":"Freight",
            "type":"Transportation"
        }
    ],
    "sg:phone":"+1 989 356 3491",
    "sg:postcode":"49707",
    "sg:province":"MI",
    "sg:tags":[
        "hauling",
        "trucking"
    ],
    "wof:name":"Byrdsway Trucking",
    "wof:placetype":"venue"
},
  "geometry": {"coordinates":[-83.417401,45.071281],"type":"Point"}
}