{
  "type": "Feature",
  "properties": {
    "iso:country":"US",
    "sg:address":"3495 Seneca Hwy",
    "sg:city":"Clayton",
    "sg:classifiers":[
        {
            "category":"Building & Trades",
            "subcategory":"Construction",
            "type":"Services"
        }
    ],
    "sg:phone":"+1 517 445 2059",
    "sg:postcode":"49235",
    "sg:province":"MI",
    "sg:tags":[
        "general",
        "contractor"
    ],
    "wof:name":"New Dominion Construction Inc",
    "wof:placetype":"venue"
},
  "geometry": {"coordinates":[-84.17919999999999,41.865868],"type":"Point"}
}