{
  "type": "Feature",
  "properties": {
    "iso:country":"US",
    "sg:address":"23851 Ryan Rd",
    "sg:city":"Warren",
    "sg:classifiers":[
        {
            "category":"Wholesale",
            "subcategory":"Construction Materials",
            "type":"Manufacturing & Wholesale Goods"
        }
    ],
    "sg:phone":"+1 586 758 6364",
    "sg:postcode":"48091",
    "sg:province":"MI",
    "sg:tags":[
        "granite"
    ],
    "wof:name":"Marble & Granite Fabricators",
    "wof:placetype":"venue"
},
  "geometry": {"coordinates":[-83.064899,42.469007],"type":"Point"}
}