{
  "type": "Feature",
  "properties": {
    "iso:country":"US",
    "sg:address":"410 Bernard St",
    "sg:city":"Schoolcraft",
    "sg:classifiers":[
        {
            "category":"Travel",
            "subcategory":"Hotels & Motels",
            "type":"Entertainment"
        }
    ],
    "sg:phone":"+1 269 679 3900",
    "sg:postcode":"49087",
    "sg:province":"MI",
    "wof:name":"Innkeeper",
    "wof:placetype":"venue"
},
  "geometry": {"coordinates":[-85.643113,42.121469],"type":"Point"}
}