{
  "type": "Feature",
  "properties": {
    "iso:country":"US",
    "sg:address":"516 Pine St",
    "sg:city":"Spring Lake",
    "sg:classifiers":[
        {
            "category":"Recreation",
            "type":"Entertainment"
        }
    ],
    "sg:phone":"+1 616 844 1488",
    "sg:postcode":"49456",
    "sg:province":"MI",
    "wof:name":"Spring Lake Cheer & Tumbling S",
    "wof:placetype":"venue"
},
  "geometry": {"coordinates":[-86.21235900000001,43.081705],"type":"Point"}
}