{
  "type": "Feature",
  "properties": {
    "iso:country":"US",
    "sg:address":"11037 E 7 Mile Rd",
    "sg:city":"Detroit",
    "sg:classifiers":[
        {
            "category":"Retail",
            "subcategory":"Auto Repair",
            "type":"Services"
        }
    ],
    "sg:phone":"+1 313 245 1772",
    "sg:postcode":"48234",
    "sg:province":"MI",
    "wof:name":"Seven Mile and Outer Drive Auto Center",
    "wof:placetype":"venue"
},
  "geometry": {"coordinates":[-83.013228,42.434337],"type":"Point"}
}