{
  "type": "Feature",
  "properties": {
    "iso:country":"US",
    "sg:address":"4199 Island Lake Rd NW",
    "sg:city":"Kalkaska",
    "sg:classifiers":[
        {
            "category":"Professional",
            "type":"Services"
        }
    ],
    "sg:phone":"+1 231 258 6712",
    "sg:postcode":"49646",
    "sg:province":"MI",
    "sg:tags":[
        "establishment"
    ],
    "wof:name":"Mercury Exploration Co",
    "wof:placetype":"venue"
},
  "geometry": {"coordinates":[-85.25228199999999,44.728386],"type":"Point"}
}