{
  "type": "Feature",
  "properties": {
    "iso:country":"US",
    "sg:address":"20700 Harper Ave",
    "sg:city":"Harper Woods",
    "sg:classifiers":[
        {
            "category":"Food & Beverages",
            "subcategory":"Groceries & Convenience Stores",
            "type":"Retail Goods"
        }
    ],
    "sg:phone":"+1 313 882 6335",
    "sg:postcode":"48225",
    "sg:province":"MI",
    "wof:name":"Marathon",
    "wof:placetype":"venue"
},
  "geometry": {"coordinates":[-82.916496,42.446098],"type":"Point"}
}