{
  "type": "Feature",
  "properties": {
    "iso:country":"US",
    "sg:address":"4849 W Outer Dr",
    "sg:city":"Detroit",
    "sg:classifiers":[
        {
            "category":"Organizations",
            "subcategory":"Religious Organization",
            "type":"Services"
        }
    ],
    "sg:phone":"+1 313 342 2288",
    "sg:postcode":"48235",
    "sg:province":"MI",
    "wof:name":"Trinity Cmnty Presbt Church",
    "wof:placetype":"venue"
},
  "geometry": {"coordinates":[-83.175415,42.431542],"type":"Point"}
}