{
  "type": "Feature",
  "properties": {
    "iso:country":"US",
    "sg:address":"8500 Garfield Rd",
    "sg:city":"Freeland",
    "sg:classifiers":[
        {
            "category":"Professional",
            "subcategory":"Engineering",
            "type":"Services"
        }
    ],
    "sg:phone":"+1 989 695 5592",
    "sg:postcode":"48623",
    "sg:province":"MI",
    "sg:tags":[
        "engineer"
    ],
    "wof:name":"Peckham Engineering Inc",
    "wof:placetype":"venue"
},
  "geometry": {"coordinates":[-84.09520999999999,43.532047],"type":"Point"}
}