{
  "type": "Feature",
  "properties": {
    "iso:country":"US",
    "sg:address":"3153 E Crystal Waters Dr",
    "sg:city":"Holland",
    "sg:classifiers":[
        {
            "category":"Retail",
            "subcategory":"Portrait Studio",
            "type":"Services"
        }
    ],
    "sg:phone":"+1 616 399 0130",
    "sg:postcode":"49424",
    "sg:province":"MI",
    "sg:tags":[
        "photo"
    ],
    "wof:name":"William Schumann Photography",
    "wof:placetype":"venue"
},
  "geometry": {"coordinates":[-86.08221899999999,42.825435],"type":"Point"}
}