{
  "type": "Feature",
  "properties": {
    "iso:country":"US",
    "sg:address":"1032 N Crooks Rd",
    "sg:city":"Clawson",
    "sg:classifiers":[
        {
            "category":"Building & Trades",
            "subcategory":"Construction",
            "type":"Services"
        }
    ],
    "sg:phone":"+1 248 601 5100",
    "sg:postcode":"48017",
    "sg:province":"MI",
    "sg:tags":[
        "contractor"
    ],
    "wof:name":"Homestead Building Restoration",
    "wof:placetype":"venue"
},
  "geometry": {"coordinates":[-83.166342,42.543346],"type":"Point"}
}