{
  "type": "Feature",
  "properties": {
    "iso:country":"US",
    "sg:address":"128 Babcock St",
    "sg:city":"Owosso",
    "sg:classifiers":[
        {
            "category":"Freight",
            "type":"Transportation"
        }
    ],
    "sg:phone":"+1 989 723 5685",
    "sg:postcode":"48867",
    "sg:province":"MI",
    "sg:tags":[
        "operator",
        "local",
        "trucking"
    ],
    "wof:name":"Spencer Trucking",
    "wof:placetype":"venue"
},
  "geometry": {"coordinates":[-84.19743800000001,42.999546],"type":"Point"}
}