{
  "type": "Feature",
  "properties": {
    "iso:country":"US",
    "sg:address":"3018 Wisner St",
    "sg:city":"Flint",
    "sg:classifiers":[
        {
            "category":"Professional",
            "type":"Services"
        }
    ],
    "sg:phone":"+1 810 233 0563",
    "sg:postcode":"48504",
    "sg:province":"MI",
    "wof:name":"New Paint Company",
    "wof:placetype":"venue"
},
  "geometry": {"coordinates":[-83.731493,43.043959],"type":"Point"}
}