{
  "type": "Feature",
  "properties": {
    "iso:country":"US",
    "sg:address":"6818 Cooley Lake Rd",
    "sg:city":"Waterford",
    "sg:classifiers":[
        {
            "category":"Retail",
            "subcategory":"Auto Repair",
            "type":"Services"
        }
    ],
    "sg:phone":"+1 248 363 8004",
    "sg:postcode":"48327",
    "sg:province":"MI",
    "sg:tags":[
        "body",
        "automobile",
        "painting"
    ],
    "sg:website":"www.campbellscollision.com",
    "wof:name":"Campbell's Collision",
    "wof:placetype":"venue"
},
  "geometry": {"coordinates":[-83.42160699999999,42.615674],"type":"Point"}
}