{
  "type": "Feature",
  "properties": {
    "iso:country":"US",
    "sg:address":"109 W Stewart Ave",
    "sg:city":"Flint",
    "sg:classifiers":[
        {
            "category":"Building & Trades",
            "subcategory":"Construction",
            "type":"Services"
        }
    ],
    "sg:phone":"+1 810 785 2234",
    "sg:postcode":"48505",
    "sg:province":"MI",
    "sg:tags":[
        "carpentry",
        "contractor"
    ],
    "wof:name":"Currans Custom Carpentry",
    "wof:placetype":"venue"
},
  "geometry": {"coordinates":[-83.709666,43.054014],"type":"Point"}
}