{
  "type": "Feature",
  "properties": {
    "iso:country":"US",
    "sg:address":"5060 Corunna Rd",
    "sg:city":"Flint",
    "sg:classifiers":[
        {
            "category":"Restaurant",
            "type":"Food & Drink"
        }
    ],
    "sg:menulink":"http://www.allmenus.com/mi/flint/196816-burger-king/menu/",
    "sg:phone":"+1 810 732 7150",
    "sg:postcode":"48532",
    "sg:province":"MI",
    "sg:tags":[
        "burger",
        "american"
    ],
    "wof:name":"Burger King",
    "wof:placetype":"venue"
},
  "geometry": {"coordinates":[-83.774209,43.001994],"type":"Point"}
}