{
  "type": "Feature",
  "properties": {
    "iso:country":"US",
    "sg:address":"1005 1st Ave S",
    "sg:city":"Escanaba",
    "sg:classifiers":[
        {
            "category":"Professional",
            "type":"Services"
        }
    ],
    "sg:phone":"+1 906 786 4560",
    "sg:postcode":"49829",
    "sg:province":"MI",
    "sg:tags":[
        "establishment"
    ],
    "wof:name":"Lighthouse Computers",
    "wof:placetype":"venue"
},
  "geometry": {"coordinates":[-87.06263,45.744565],"type":"Point"}
}