{
  "type": "Feature",
  "properties": {
    "iso:country":"US",
    "sg:address":"58 Michigan Ave E",
    "sg:city":"Battle Creek",
    "sg:classifiers":[
        {
            "category":"Shopping",
            "subcategory":"Books",
            "type":"Retail Goods"
        }
    ],
    "sg:phone":"+1 269 962 2665",
    "sg:postcode":"49017",
    "sg:province":"MI",
    "sg:tags":[
        "dealer"
    ],
    "wof:name":"Good Books & Warm Quilts",
    "wof:placetype":"venue"
},
  "geometry": {"coordinates":[-85.179947,42.316603],"type":"Point"}
}