{
  "type": "Feature",
  "properties": {
    "iso:country":"US",
    "sg:address":"500 W Saint Marys St",
    "sg:city":"Decatur",
    "sg:classifiers":[
        {
            "category":"Organizations",
            "subcategory":"Religious Organization",
            "type":"Services"
        }
    ],
    "sg:phone":"+1 269 423 3151",
    "sg:postcode":"49045",
    "sg:province":"MI",
    "sg:tags":[
        "church"
    ],
    "wof:name":"Holy Family Catholic Church",
    "wof:placetype":"venue"
},
  "geometry": {"coordinates":[-85.98329699999999,42.105368],"type":"Point"}
}