{
  "type": "Feature",
  "properties": {
    "iso:country":"US",
    "sg:address":"2520 S Telegraph Rd",
    "sg:city":"Bloomfield Hills",
    "sg:classifiers":[
        {
            "category":"Health Services",
            "subcategory":"Doctor",
            "type":"Services"
        }
    ],
    "sg:phone":"+1 248 333 7063",
    "sg:postcode":"48302",
    "sg:province":"MI",
    "sg:tags":[
        "physician",
        "surgeon"
    ],
    "wof:name":"Oakland Physician Assoc PC",
    "wof:placetype":"venue"
},
  "geometry": {"coordinates":[-83.28864299999999,42.602179],"type":"Point"}
}