{
  "type": "Feature",
  "properties": {
    "iso:country":"US",
    "sg:address":"25505 Plymouth Rd",
    "sg:city":"Redford",
    "sg:classifiers":[
        {
            "category":"Restaurant",
            "type":"Food & Drink"
        }
    ],
    "sg:phone":"+1 313 937 7970",
    "sg:postcode":"48239",
    "sg:province":"MI",
    "sg:tags":[
        "eating"
    ],
    "wof:name":"Tamales Express",
    "wof:placetype":"venue"
},
  "geometry": {"coordinates":[-83.292441,42.370776],"type":"Point"}
}