{
  "type": "Feature",
  "properties": {
    "iso:country":"US",
    "sg:address":"1426 Lake Grove Ave SE",
    "sg:city":"Grand Rapids",
    "sg:classifiers":[
        {
            "category":"Local Transit",
            "type":"Transportation"
        }
    ],
    "sg:phone":"+1 616 957 0439",
    "sg:postcode":"49506",
    "sg:province":"MI",
    "sg:tags":[
        "passenger"
    ],
    "wof:name":"Better Grand Rapds Tranprt",
    "wof:placetype":"venue"
},
  "geometry": {"coordinates":[-85.606326,42.937206],"type":"Point"}
}