{
  "type": "Feature",
  "properties": {
    "iso:country":"US",
    "sg:address":"1185 Matt Urban Dr",
    "sg:city":"Holland",
    "sg:classifiers":[
        {
            "category":"Organizations",
            "subcategory":"Community Association",
            "type":"Services"
        }
    ],
    "sg:phone":"+1 616 396 2714",
    "sg:postcode":"49423",
    "sg:province":"MI",
    "sg:tags":[
        "military"
    ],
    "wof:name":"Disabled American Veterans",
    "wof:placetype":"venue"
},
  "geometry": {"coordinates":[-86.11861500000001,42.754359],"type":"Point"}
}