{
  "type": "Feature",
  "properties": {
    "iso:country":"US",
    "sg:address":"28366 Franklin Rd",
    "sg:city":"Southfield",
    "sg:classifiers":[
        {
            "category":"Professional",
            "subcategory":"Lawyer & Legal Services",
            "type":"Services"
        }
    ],
    "sg:phone":"+1 248 352 4340",
    "sg:postcode":"48034",
    "sg:province":"MI",
    "wof:name":"Holzman Ritter & Leduc",
    "wof:placetype":"venue"
},
  "geometry": {"coordinates":[-83.302002,42.495399],"type":"Point"}
}