{
  "type": "Feature",
  "properties": {
    "iso:country":"US",
    "sg:address":"57900 Van Dyke Rd",
    "sg:city":"Washington",
    "sg:classifiers":[
        {
            "category":"Government",
            "subcategory":"Office",
            "type":"Public Place"
        }
    ],
    "sg:phone":"+1 586 786 0020",
    "sg:postcode":"48094",
    "sg:province":"MI",
    "sg:tags":[
        "village"
    ],
    "wof:name":"Washington Bookkeeping",
    "wof:placetype":"venue"
},
  "geometry": {"coordinates":[-83.035764,42.723091],"type":"Point"}
}