{
  "type": "Feature",
  "properties": {
    "iso:country":"US",
    "sg:address":"2690 Ewald Cir Apt 27",
    "sg:city":"Detroit",
    "sg:classifiers":[
        {
            "category":"Real Estate",
            "subcategory":"Real Estate Operator",
            "type":"Services"
        }
    ],
    "sg:phone":"+1 313 934 2444",
    "sg:postcode":"48238",
    "sg:province":"MI",
    "sg:tags":[
        "apartment"
    ],
    "wof:name":"Oakman-Belleterre Place",
    "wof:placetype":"venue"
},
  "geometry": {"coordinates":[-83.142601,42.3904],"type":"Point"}
}