{
  "type": "Feature",
  "properties": {
    "iso:country":"US",
    "sg:address":"471 68th St SW",
    "sg:city":"Grand Rapids",
    "sg:classifiers":[
        {
            "category":"Restaurant",
            "type":"Food & Drink"
        }
    ],
    "sg:menulink":"http://www.allmenus.com/mi/byron/196955-burger-king/menu/",
    "sg:phone":"+1 616 827 0684",
    "sg:postcode":"49548",
    "sg:province":"MI",
    "sg:tags":[
        "burger",
        "american"
    ],
    "wof:name":"Burger King",
    "wof:placetype":"venue"
},
  "geometry": {"coordinates":[-85.674971,42.8409],"type":"Point"}
}