{
  "type": "Feature",
  "properties": {
    "iso:country":"US",
    "sg:address":"445 S Livernois Rd",
    "sg:city":"Rochester Hills",
    "sg:classifiers":[
        {
            "category":"Banks & Credit Unions",
            "subcategory":"Investment Brokerage",
            "type":"Services"
        }
    ],
    "sg:phone":"+1 248 651 2426",
    "sg:postcode":"48307",
    "sg:province":"MI",
    "sg:tags":[
        "security"
    ],
    "wof:name":"Edward Jones Co",
    "wof:placetype":"venue"
},
  "geometry": {"coordinates":[-83.153285,42.674194],"type":"Point"}
}