{
  "type": "Feature",
  "properties": {
    "iso:country":"US",
    "sg:address":"3979 Holt Rd",
    "sg:city":"Holt",
    "sg:classifiers":[
        {
            "category":"Professional",
            "subcategory":"Computer Services",
            "type":"Services"
        }
    ],
    "sg:phone":"+1 517 699 5000",
    "sg:postcode":"48842",
    "sg:province":"MI",
    "sg:tags":[
        "wiring"
    ],
    "sg:website":"www.datacomgroup.com",
    "wof:name":"DATACOM Group",
    "wof:placetype":"venue"
},
  "geometry": {"coordinates":[-84.50363299999999,42.640154],"type":"Point"}
}