{
  "type": "Feature",
  "properties": {
    "iso:country":"US",
    "sg:address":"1026 Woodrow Ave NW",
    "sg:city":"Grand Rapids",
    "sg:classifiers":[
        {
            "category":"Wholesale",
            "subcategory":"Machinery & Supplies",
            "type":"Manufacturing & Wholesale Goods"
        }
    ],
    "sg:phone":"+1 616 453 4058",
    "sg:postcode":"49504",
    "sg:province":"MI",
    "wof:name":"G Van Sales",
    "wof:placetype":"venue"
},
  "geometry": {"coordinates":[-85.70553200000001,42.983299],"type":"Point"}
}