{
  "type": "Feature",
  "properties": {
    "iso:country":"US",
    "sg:address":"14600 Lakeside Cir",
    "sg:city":"Sterling Heights",
    "sg:classifiers":[
        {
            "category":"Shopping",
            "subcategory":"Clothing, Apparel, & Fashions",
            "type":"Retail Goods"
        }
    ],
    "sg:phone":"+1 586 532 6600",
    "sg:postcode":"48313",
    "sg:province":"MI",
    "wof:name":"Top This",
    "wof:placetype":"venue"
},
  "geometry": {"coordinates":[-82.98860999999999,42.620414],"type":"Point"}
}