{
  "type": "Feature",
  "properties": {
    "iso:country":"US",
    "sg:address":"139 Beth St",
    "sg:city":"Holland",
    "sg:classifiers":[
        {
            "category":"Professional",
            "subcategory":"Computer Services",
            "type":"Services"
        }
    ],
    "sg:phone":"+1 616 396 5518",
    "sg:postcode":"49424",
    "sg:province":"MI",
    "sg:tags":[
        "consultant",
        "designer"
    ],
    "wof:name":"Creative Information Solutions",
    "wof:placetype":"venue"
},
  "geometry": {"coordinates":[-86.100774,42.810735],"type":"Point"}
}