{
  "type": "Feature",
  "properties": {
    "iso:country":"US",
    "sg:address":"1042 E Sternberg Rd",
    "sg:city":"Muskegon",
    "sg:classifiers":[
        {
            "category":"Professional",
            "subcategory":"Employment Agencies",
            "type":"Services"
        }
    ],
    "sg:phone":"+1 231 799 2100",
    "sg:postcode":"49444",
    "sg:province":"MI",
    "sg:tags":[
        "opportunity",
        "help",
        "supply"
    ],
    "wof:name":"Forge Industrial Staffing",
    "wof:placetype":"venue"
},
  "geometry": {"coordinates":[-86.216252,43.154386],"type":"Point"}
}