{
  "type": "Feature",
  "properties": {
    "iso:country":"US",
    "sg:address":"900 Lake Shore Rd",
    "sg:city":"Grosse Pointe",
    "sg:classifiers":[
        {
            "category":"Professional",
            "subcategory":"Lawyer & Legal Services",
            "type":"Services"
        }
    ],
    "sg:phone":"+1 313 885 5370",
    "sg:postcode":"48236",
    "sg:province":"MI",
    "sg:tags":[
        "law"
    ],
    "wof:name":"Van Til Association",
    "wof:placetype":"venue"
},
  "geometry": {"coordinates":[-82.875714,42.44325],"type":"Point"}
}