{
  "type": "Feature",
  "properties": {
    "iso:country":"US",
    "sg:address":"6990 W M 21",
    "sg:city":"Owosso",
    "sg:classifiers":[
        {
            "category":"Home & Garden",
            "subcategory":"Home Furnishings",
            "type":"Retail Goods"
        }
    ],
    "sg:phone":"+1 989 723 2177",
    "sg:postcode":"48866",
    "sg:province":"MI",
    "sg:tags":[
        "equipment",
        "fireplace"
    ],
    "sg:website":"www.hearthman.com",
    "wof:name":"Hearth N Home Inc",
    "wof:placetype":"venue"
},
  "geometry": {"coordinates":[-84.30328799999999,42.999277],"type":"Point"}
}