{
  "type": "Feature",
  "properties": {
    "iso:country":"US",
    "sg:address":"7235 Torrey Rd",
    "sg:city":"Swartz Creek",
    "sg:classifiers":[
        {
            "category":"Organizations",
            "subcategory":"Religious Organization",
            "type":"Services"
        }
    ],
    "sg:phone":"+1 810 655 3336",
    "sg:postcode":"48473",
    "sg:province":"MI",
    "sg:website":"www.newlifelutheran.net",
    "wof:name":"New Life Community Lutheran",
    "wof:placetype":"venue"
},
  "geometry": {"coordinates":[-83.730757,42.923517],"type":"Point"}
}