{
  "type": "Feature",
  "properties": {
    "iso:country":"US",
    "sg:address":"220 W Houghton Ave",
    "sg:city":"West Branch",
    "sg:classifiers":[
        {
            "category":"Shopping",
            "subcategory":"Jewelry",
            "type":"Retail Goods"
        }
    ],
    "sg:phone":"+1 989 345 0681",
    "sg:postcode":"48661",
    "sg:province":"MI",
    "sg:tags":[
        "jeweler"
    ],
    "wof:name":"West Branch Jewelry & Gifts",
    "wof:placetype":"venue"
},
  "geometry": {"coordinates":[-84.23835200000001,44.276196],"type":"Point"}
}