{
  "type": "Feature",
  "properties": {
    "iso:country":"US",
    "sg:address":"5137 Dryden Rd",
    "sg:city":"Dryden",
    "sg:classifiers":[
        {
            "category":"Banks & Credit Unions",
            "subcategory":"Investment Brokerage",
            "type":"Services"
        }
    ],
    "sg:phone":"+1 810 796 9878",
    "sg:postcode":"48428",
    "sg:province":"MI",
    "sg:tags":[
        "consultant",
        "planning",
        "financial"
    ],
    "wof:name":"American Express Financial Adv",
    "wof:placetype":"venue"
},
  "geometry": {"coordinates":[-83.138791,42.94568],"type":"Point"}
}