{
  "type": "Feature",
  "properties": {
    "iso:country":"US",
    "sg:address":"3001 W Big Beaver Rd",
    "sg:city":"Troy",
    "sg:classifiers":[
        {
            "category":"Professional",
            "subcategory":"Lawyer & Legal Services",
            "type":"Services"
        }
    ],
    "sg:phone":"+1 248 643 6500",
    "sg:postcode":"48084",
    "sg:province":"MI",
    "wof:name":"Deagostino L Gene",
    "wof:placetype":"venue"
},
  "geometry": {"coordinates":[-83.18699599999999,42.561001],"type":"Point"}
}