{
  "type": "Feature",
  "properties": {
    "iso:country":"US",
    "sg:address":"125 N Clippert St",
    "sg:city":"Lansing",
    "sg:classifiers":[
        {
            "category":"Wholesale",
            "subcategory":"Machinery & Supplies",
            "type":"Manufacturing & Wholesale Goods"
        }
    ],
    "sg:phone":"+1 517 332 3121",
    "sg:postcode":"48912",
    "sg:province":"MI",
    "sg:tags":[
        "salon",
        "beauty"
    ],
    "wof:name":"Maly's Inc",
    "wof:placetype":"venue"
},
  "geometry": {"coordinates":[-84.508408,42.735748],"type":"Point"}
}