{
  "type": "Feature",
  "properties": {
    "iso:country":"US",
    "sg:address":"836 Centennial Way",
    "sg:city":"Lansing",
    "sg:classifiers":[
        {
            "category":"Real Estate",
            "subcategory":"Real Estate Services",
            "type":"Services"
        }
    ],
    "sg:phone":"+1 517 323 6819",
    "sg:postcode":"48917",
    "sg:province":"MI",
    "sg:tags":[
        "company",
        "title"
    ],
    "wof:name":"Allen Title Svc",
    "wof:placetype":"venue"
},
  "geometry": {"coordinates":[-84.646179,42.723096],"type":"Point"}
}