{
  "type": "Feature",
  "properties": {
    "iso:country":"US",
    "sg:address":"116 S Cochran Ave",
    "sg:city":"Charlotte",
    "sg:classifiers":[
        {
            "category":"Shopping",
            "subcategory":"Hobbies, Toys, & Games",
            "type":"Retail Goods"
        }
    ],
    "sg:phone":"+1 517 543 7288",
    "sg:postcode":"48813",
    "sg:province":"MI",
    "wof:name":"Doll Shop",
    "wof:placetype":"venue"
},
  "geometry": {"coordinates":[-84.83595699999999,42.563705],"type":"Point"}
}