{
  "type": "Feature",
  "properties": {
    "iso:country":"US",
    "sg:address":"137 W Main St",
    "sg:city":"Gaylord",
    "sg:classifiers":[
        {
            "category":"Real Estate",
            "subcategory":"Real Estate Agent",
            "type":"Services"
        }
    ],
    "sg:phone":"+1 989 732 6221",
    "sg:postcode":"49735",
    "sg:province":"MI",
    "wof:name":"Seven Oaks Real Estate",
    "wof:placetype":"venue"
},
  "geometry": {"coordinates":[-84.674396,45.027445],"type":"Point"}
}