{
  "type": "Feature",
  "properties": {
    "iso:country":"US",
    "sg:address":"615 Schuring Rd",
    "sg:city":"Portage",
    "sg:classifiers":[
        {
            "category":"Banks & Credit Unions",
            "subcategory":"Financial Services",
            "type":"Services"
        }
    ],
    "sg:phone":"+1 269 375 7713",
    "sg:postcode":"49024",
    "sg:province":"MI",
    "sg:tags":[
        "company",
        "holding"
    ],
    "wof:name":"J D Development & Holdings Inc",
    "wof:placetype":"venue"
},
  "geometry": {"coordinates":[-85.596358,42.208159],"type":"Point"}
}