{
  "type": "Feature",
  "properties": {
    "iso:country":"US",
    "sg:address":"96 W Garfield Ave",
    "sg:city":"Coldwater",
    "sg:classifiers":[
        {
            "category":"Autos & Motor Vehicles",
            "subcategory":"Fuel & Gas Station",
            "type":"Retail Goods"
        }
    ],
    "sg:phone":"+1 517 278 8944",
    "sg:postcode":"49036",
    "sg:province":"MI",
    "sg:tags":[
        "oil"
    ],
    "wof:name":"Consolidated Energy",
    "wof:placetype":"venue"
},
  "geometry": {"coordinates":[-85.00926,41.927343],"type":"Point"}
}