{
  "type": "Feature",
  "properties": {
    "iso:country":"US",
    "sg:address":"1455 E M-55",
    "sg:city":"West Branch",
    "sg:classifiers":[
        {
            "category":"Home & Garden",
            "subcategory":"Building Materials",
            "type":"Retail Goods"
        }
    ],
    "sg:phone":"+1 989 345 2244",
    "sg:postcode":"48661",
    "sg:province":"MI",
    "sg:tags":[
        "glass",
        "window",
        "plate"
    ],
    "wof:name":"Glass Doctor",
    "wof:placetype":"venue"
},
  "geometry": {"coordinates":[-84.074412,44.276831],"type":"Point"}
}