{
  "type": "Feature",
  "properties": {
    "iso:country":"US",
    "sg:address":"20735 Washington St",
    "sg:city":"Roseville",
    "sg:classifiers":[
        {
            "category":"Professional",
            "subcategory":"Management & Consulting",
            "type":"Services"
        }
    ],
    "sg:phone":"+1 586 445 9755",
    "sg:postcode":"48066",
    "sg:province":"MI",
    "sg:tags":[
        "party",
        "planning"
    ],
    "wof:name":"Parties By Cheryl Ann",
    "wof:placetype":"venue"
},
  "geometry": {"coordinates":[-82.90734,42.51391],"type":"Point"}
}