{
  "type": "Feature",
  "properties": {
    "iso:country":"US",
    "sg:address":"7760 State Rd",
    "sg:city":"Millington",
    "sg:classifiers":[
        {
            "category":"Retail",
            "subcategory":"Animal Services",
            "type":"Services"
        }
    ],
    "sg:phone":"+1 989 871 3885",
    "sg:postcode":"48746",
    "sg:province":"MI",
    "sg:tags":[
        "pet",
        "grooming",
        "washing"
    ],
    "wof:name":"Barking Lot",
    "wof:placetype":"venue"
},
  "geometry": {"coordinates":[-83.538943,43.299965],"type":"Point"}
}