{
  "type": "Feature",
  "properties": {
    "iso:country":"US",
    "sg:address":"3121 Trappers Cove Trl",
    "sg:city":"Lansing",
    "sg:classifiers":[
        {
            "category":"Retail",
            "subcategory":"Laundry & Dry Cleaning",
            "type":"Services"
        }
    ],
    "sg:phone":"+1 517 676 2490",
    "sg:postcode":"48910",
    "sg:province":"MI",
    "wof:name":"Pioneer Cleaning & Carpet",
    "wof:placetype":"venue"
},
  "geometry": {"coordinates":[-84.507243,42.687138],"type":"Point"}
}