{
  "type": "Feature",
  "properties": {
    "iso:country":"US",
    "sg:address":"2123 S Center Rd",
    "sg:city":"Burton",
    "sg:classifiers":[
        {
            "category":"Professional",
            "subcategory":"Detective & Security Services",
            "type":"Services"
        }
    ],
    "sg:phone":"+1 810 742 8189",
    "sg:postcode":"48519",
    "sg:province":"MI",
    "sg:tags":[
        "guard",
        "patrol"
    ],
    "wof:name":"Lagarda Security",
    "wof:placetype":"venue"
},
  "geometry": {"coordinates":[-83.63441899999999,43.003184],"type":"Point"}
}