{
  "type": "Feature",
  "properties": {
    "iso:country":"US",
    "sg:address":"2296 W Carpenter Rd",
    "sg:city":"Flint",
    "sg:classifiers":[
        {
            "category":"Organizations",
            "subcategory":"Religious Organization",
            "type":"Services"
        }
    ],
    "sg:phone":"+1 810 785 0481",
    "sg:postcode":"48505",
    "sg:province":"MI",
    "wof:name":"West Carptr Rd Church Christ",
    "wof:placetype":"venue"
},
  "geometry": {"coordinates":[-83.721113,43.075333],"type":"Point"}
}