{
  "type": "Feature",
  "properties": {
    "iso:country":"US",
    "sg:address":"24830 Ryan Rd",
    "sg:city":"Warren",
    "sg:classifiers":[
        {
            "category":"Travel",
            "subcategory":"Hotels & Motels",
            "type":"Entertainment"
        }
    ],
    "sg:phone":"+1 586 757 9998",
    "sg:postcode":"48091",
    "sg:province":"MI",
    "wof:name":"Reinhart Foodservices",
    "wof:placetype":"venue"
},
  "geometry": {"coordinates":[-83.065095,42.475479],"type":"Point"}
}