{
  "type": "Feature",
  "properties": {
    "iso:country":"US",
    "sg:address":"10501 Telegraph Rd Ste 102",
    "sg:city":"Taylor",
    "sg:classifiers":[
        {
            "category":"Health Services",
            "subcategory":"Health Practitioner",
            "type":"Services"
        }
    ],
    "sg:phone":"+1 313 299 0000",
    "sg:postcode":"48180",
    "sg:province":"MI",
    "sg:tags":[
        "therapy",
        "physical"
    ],
    "wof:name":"Pro Physical Therapy & Rehab",
    "wof:placetype":"venue"
},
  "geometry": {"coordinates":[-83.26906,42.230647],"type":"Point"}
}