{
  "type": "Feature",
  "properties": {
    "iso:country":"US",
    "sg:address":"22500 Heslip Dr",
    "sg:city":"Novi",
    "sg:classifiers":[
        {
            "category":"Wholesale",
            "subcategory":"Construction Materials",
            "type":"Manufacturing & Wholesale Goods"
        }
    ],
    "sg:phone":"+1 248 348 1900",
    "sg:postcode":"48375",
    "sg:province":"MI",
    "sg:tags":[
        "marble"
    ],
    "wof:name":"Marbelite Corp",
    "wof:placetype":"venue"
},
  "geometry": {"coordinates":[-83.46763300000001,42.456014],"type":"Point"}
}