{
  "type": "Feature",
  "properties": {
    "iso:country":"US",
    "sg:address":"690 S French Rd",
    "sg:city":"Lake Leelanau",
    "sg:classifiers":[
        {
            "category":"Building & Trades",
            "subcategory":"Landscaping Services",
            "type":"Services"
        }
    ],
    "sg:phone":"+1 231 256 9171",
    "sg:postcode":"49653",
    "sg:province":"MI",
    "sg:tags":[
        "landscape",
        "contractor"
    ],
    "wof:name":"Leelanau Landscaping Co",
    "wof:placetype":"venue"
},
  "geometry": {"coordinates":[-85.747449,44.970999],"type":"Point"}
}