{
  "type": "Feature",
  "properties": {
    "iso:country":"US",
    "sg:address":"110 W Knox Rd",
    "sg:city":"Beaverton",
    "sg:classifiers":[
        {
            "category":"Professional",
            "type":"Services"
        }
    ],
    "sg:phone":"+1 989 435 7535",
    "sg:postcode":"48612",
    "sg:province":"MI",
    "sg:tags":[
        "establishment"
    ],
    "wof:name":"Beaverton Manor",
    "wof:placetype":"venue"
},
  "geometry": {"coordinates":[-84.38377199999999,43.886226],"type":"Point"}
}