{
  "type": "Feature",
  "properties": {
    "iso:country":"US",
    "sg:address":"330 E Mitchell St",
    "sg:city":"Petoskey",
    "sg:classifiers":[
        {
            "category":"Banks & Credit Unions",
            "subcategory":"Bank",
            "type":"Services"
        }
    ],
    "sg:phone":"+1 231 348 1800",
    "sg:postcode":"49770",
    "sg:province":"MI",
    "sg:tags":[
        "state"
    ],
    "sg:website":"www.firstcb.com",
    "wof:name":"First Community Bank",
    "wof:placetype":"venue"
},
  "geometry": {"coordinates":[-84.956553,45.373895],"type":"Point"}
}