{
  "type": "Feature",
  "properties": {
    "iso:country":"US",
    "sg:address":"9000 Headley Dr",
    "sg:city":"Sterling Heights",
    "sg:classifiers":[
        {
            "category":"Health Services",
            "subcategory":"Clinic",
            "type":"Services"
        }
    ],
    "sg:phone":"+1 586 739 6259",
    "sg:postcode":"48314",
    "sg:province":"MI",
    "wof:name":"United Ostomy Associates",
    "wof:placetype":"venue"
},
  "geometry": {"coordinates":[-83.016856,42.617658],"type":"Point"}
}