{
  "type": "Feature",
  "properties": {
    "iso:country":"US",
    "sg:address":"1600 N Stephenson Hwy",
    "sg:city":"Royal Oak",
    "sg:classifiers":[
        {
            "category":"Sports & Exercise",
            "subcategory":"Gym",
            "type":"Entertainment"
        }
    ],
    "sg:phone":"+1 248 543 7100",
    "sg:postcode":"48067",
    "sg:province":"MI",
    "sg:tags":[
        "trainer"
    ],
    "wof:name":"Royal Oak Gym",
    "wof:placetype":"venue"
},
  "geometry": {"coordinates":[-83.117699,42.500801],"type":"Point"}
}