{
  "type": "Feature",
  "properties": {
    "iso:country":"US",
    "sg:address":"5506 S Harvey St",
    "sg:city":"Muskegon",
    "sg:classifiers":[
        {
            "category":"Shopping",
            "subcategory":"Gifts & Souvenirs",
            "type":"Retail Goods"
        }
    ],
    "sg:phone":"+1 231 798 0024",
    "sg:postcode":"49444",
    "sg:province":"MI",
    "sg:tags":[
        "shop"
    ],
    "wof:name":"Family Christain Book Store",
    "wof:placetype":"venue"
},
  "geometry": {"coordinates":[-86.205761,43.15098],"type":"Point"}
}