{
  "type": "Feature",
  "properties": {
    "iso:country":"US",
    "sg:address":"1581 US Hwy 41",
    "sg:city":"Menominee",
    "sg:classifiers":[
        {
            "category":"Retail",
            "subcategory":"Auto Repair",
            "type":"Services"
        }
    ],
    "sg:phone":"+1 906 863 3673",
    "sg:postcode":"49858",
    "sg:province":"MI",
    "sg:tags":[
        "body",
        "automobile",
        "painting"
    ],
    "wof:name":"Body Works Plus",
    "wof:placetype":"venue"
},
  "geometry": {"coordinates":[-87.61444299999999,45.112597],"type":"Point"}
}