{
  "type": "Feature",
  "properties": {
    "iso:country":"US",
    "sg:address":"6835 US Hwy 41",
    "sg:city":"Gladstone",
    "sg:classifiers":[
        {
            "category":"Government",
            "subcategory":"Fire Station",
            "type":"Public Place"
        }
    ],
    "sg:phone":"+1 906 000 1111",
    "sg:postcode":"49837",
    "sg:province":"MI",
    "sg:tags":[
        "department"
    ],
    "wof:name":"Michigan State Fire Dept",
    "wof:placetype":"venue"
},
  "geometry": {"coordinates":[-87.077879,45.795055],"type":"Point"}
}