{
  "type": "Feature",
  "properties": {
    "iso:country":"US",
    "sg:address":"1330 Lenox Rd SE",
    "sg:city":"Grand Rapids",
    "sg:classifiers":[
        {
            "category":"Professional",
            "subcategory":"Business Services",
            "type":"Services"
        }
    ],
    "sg:phone":"+1 616 243 5086",
    "sg:postcode":"49506",
    "sg:province":"MI",
    "sg:tags":[
        "broker"
    ],
    "wof:name":"Ripperger & Assoc",
    "wof:placetype":"venue"
},
  "geometry": {"coordinates":[-85.61739300000001,42.938609],"type":"Point"}
}