{
  "type": "Feature",
  "properties": {
    "iso:country":"US",
    "sg:address":"154 Wenonah Dr",
    "sg:city":"Rogers City",
    "sg:classifiers":[
        {
            "category":"Real Estate",
            "subcategory":"Real Estate Operator",
            "type":"Services"
        }
    ],
    "sg:phone":"+1 989 734 4754",
    "sg:postcode":"49779",
    "sg:province":"MI",
    "sg:tags":[
        "apartment"
    ],
    "wof:name":"Harbor House Apartments",
    "wof:placetype":"venue"
},
  "geometry": {"coordinates":[-83.824439,45.413312],"type":"Point"}
}