{
  "type": "Feature",
  "properties": {
    "iso:country":"US",
    "sg:address":"Detroit Metro Airport PO Box 42102",
    "sg:city":"Detroit",
    "sg:classifiers":[
        {
            "category":"Taxi",
            "type":"Transportation"
        },
        {
            "category":"Airline",
            "type":"Transportation"
        }
    ],
    "sg:phone":"+1 800 880 5199",
    "sg:postcode":"48242",
    "sg:province":"MI",
    "sg:tags":[
        "shuttle",
        "airport"
    ],
    "sg:website":"www.detroitsedan.com",
    "wof:name":"Detroit Sedan",
    "wof:placetype":"venue"
},
  "geometry": {"coordinates":[-83.35629299999999,42.207822],"type":"Point"}
}