{
  "type": "Feature",
  "properties": {
    "iso:country":"US",
    "sg:address":"9769 Sandypointe Dr",
    "sg:city":"Fair Haven",
    "sg:classifiers":[
        {
            "category":"Building & Trades",
            "subcategory":"Construction",
            "type":"Services"
        }
    ],
    "sg:phone":"+1 586 716 0660",
    "sg:postcode":"48023",
    "sg:province":"MI",
    "sg:tags":[
        "hanging",
        "contractor"
    ],
    "wof:name":"Integrity Wall Covering",
    "wof:placetype":"venue"
},
  "geometry": {"coordinates":[-82.70805799999999,42.696293],"type":"Point"}
}