{
  "type": "Feature",
  "properties": {
    "iso:country":"US",
    "sg:address":"23325 Orchard Lake Rd",
    "sg:city":"Farmington",
    "sg:classifiers":[
        {
            "category":"Social Services",
            "subcategory":"Child Care",
            "type":"Services"
        }
    ],
    "sg:phone":"+1 248 476 4704",
    "sg:postcode":"48336",
    "sg:province":"MI",
    "sg:tags":[
        "day"
    ],
    "wof:name":"Brown Academy Montessori Center",
    "wof:placetype":"venue"
},
  "geometry": {"coordinates":[-83.356971,42.463076],"type":"Point"}
}