{
  "type": "Feature",
  "properties": {
    "iso:country":"US",
    "sg:address":"9261 Harrison St",
    "sg:city":"Livonia",
    "sg:classifiers":[
        {
            "category":"Building & Trades",
            "subcategory":"Cleaning & Sanitation",
            "type":"Services"
        }
    ],
    "sg:phone":"+1 734 525 6630",
    "sg:postcode":"48150",
    "sg:province":"MI",
    "sg:tags":[
        "maintenance"
    ],
    "wof:name":"A1 Building Services",
    "wof:placetype":"venue"
},
  "geometry": {"coordinates":[-83.322911,42.359512],"type":"Point"}
}