{
  "type": "Feature",
  "properties": {
    "iso:country":"US",
    "sg:address":"3801 Rochester Rd",
    "sg:city":"Troy",
    "sg:classifiers":[
        {
            "category":"Retail",
            "subcategory":"Auto Repair",
            "type":"Services"
        }
    ],
    "sg:phone":"+1 248 689 9250",
    "sg:postcode":"48083",
    "sg:province":"MI",
    "sg:website":"www.uncleedsoil.com",
    "wof:name":"Uncle Ed's Oil Shoppe",
    "wof:placetype":"venue"
},
  "geometry": {"coordinates":[-83.12839200000001,42.574211],"type":"Point"}
}