{
  "type": "Feature",
  "properties": {
    "iso:country":"US",
    "sg:address":"3030 W Long Lake Rd",
    "sg:city":"Orleans",
    "sg:classifiers":[
        {
            "category":"Professional",
            "subcategory":"Computer Services",
            "type":"Services"
        }
    ],
    "sg:phone":"+1 616 794 4068",
    "sg:postcode":"48865",
    "sg:province":"MI",
    "wof:name":"Home Computers",
    "wof:placetype":"venue"
},
  "geometry": {"coordinates":[-85.135524,43.115678],"type":"Point"}
}