{
  "type": "Feature",
  "properties": {
    "iso:country":"US",
    "sg:address":"3277 Bewell Ave SE",
    "sg:city":"Lowell",
    "sg:classifiers":[
        {
            "category":"Professional",
            "subcategory":"Business Services",
            "type":"Services"
        }
    ],
    "sg:phone":"+1 616 897 3145",
    "sg:postcode":"49331",
    "sg:province":"MI",
    "wof:name":"Sha Fur Enterprises Inc",
    "wof:placetype":"venue"
},
  "geometry": {"coordinates":[-85.38104199999999,42.906407],"type":"Point"}
}