{
  "type": "Feature",
  "properties": {
    "iso:country":"US",
    "sg:address":"1778 Bonneville Dr",
    "sg:city":"Muskegon",
    "sg:classifiers":[
        {
            "category":"Building & Trades",
            "subcategory":"Landscaping Services",
            "type":"Services"
        }
    ],
    "sg:phone":"+1 231 755 6365",
    "sg:postcode":"49441",
    "sg:province":"MI",
    "wof:name":"Beyond Lawn Ldscpg Irrigation",
    "wof:placetype":"venue"
},
  "geometry": {"coordinates":[-86.289615,43.198916],"type":"Point"}
}