{
  "type": "Feature",
  "properties": {
    "iso:country":"US",
    "sg:address":"281 Kublick Dr",
    "sg:city":"Benton Harbor",
    "sg:classifiers":[
        {
            "category":"Building & Trades",
            "subcategory":"Construction",
            "type":"Services"
        }
    ],
    "sg:phone":"+1 269 927 2086",
    "sg:postcode":"49022",
    "sg:province":"MI",
    "sg:tags":[
        "general",
        "contractor"
    ],
    "wof:name":"Jeff Construction",
    "wof:placetype":"venue"
},
  "geometry": {"coordinates":[-86.45303699999999,42.079985],"type":"Point"}
}