{
  "type": "Feature",
  "properties": {
    "iso:country":"US",
    "sg:address":"1065 E 9 Mile Rd",
    "sg:city":"Hazel Park",
    "sg:classifiers":[
        {
            "category":"Shopping",
            "subcategory":"Gifts & Souvenirs",
            "type":"Retail Goods"
        }
    ],
    "sg:phone":"+1 248 547 4755",
    "sg:postcode":"48030",
    "sg:province":"MI",
    "sg:tags":[
        "party",
        "planning",
        "event",
        "supply"
    ],
    "wof:name":"House of Beer and Party Store",
    "wof:placetype":"venue"
},
  "geometry": {"coordinates":[-83.093903,42.4617],"type":"Point"}
}