{
  "type": "Feature",
  "properties": {
    "iso:country":"US",
    "sg:address":"37617 Pembroke Ave",
    "sg:city":"Livonia",
    "sg:classifiers":[
        {
            "category":"Health Services",
            "subcategory":"Doctor",
            "type":"Services"
        }
    ],
    "sg:phone":"+1 734 591 0223",
    "sg:postcode":"48152",
    "sg:province":"MI",
    "sg:tags":[
        "surgeon",
        "oral"
    ],
    "wof:name":"Varga Thomas A DDS",
    "wof:placetype":"venue"
},
  "geometry": {"coordinates":[-83.415001,42.432499],"type":"Point"}
}