{
  "type": "Feature",
  "properties": {
    "iso:country":"US",
    "sg:address":"805 N Euclid Ave",
    "sg:city":"Bay City",
    "sg:classifiers":[
        {
            "category":"Banks & Credit Unions",
            "subcategory":"Investment Brokerage",
            "type":"Services"
        }
    ],
    "sg:phone":"+1 989 671 1024",
    "sg:postcode":"48706",
    "sg:province":"MI",
    "wof:name":"Laframboise Investments LLC",
    "wof:placetype":"venue"
},
  "geometry": {"coordinates":[-83.91485900000001,43.61042],"type":"Point"}
}