{
  "type": "Feature",
  "properties": {
    "iso:country":"US",
    "sg:address":"14044 Roselawn St",
    "sg:city":"Detroit",
    "sg:classifiers":[
        {
            "category":"Professional",
            "subcategory":"Business Services",
            "type":"Services"
        }
    ],
    "sg:phone":"+1 313 834 3165",
    "sg:postcode":"48238",
    "sg:province":"MI",
    "wof:name":"Tek Bros",
    "wof:placetype":"venue"
},
  "geometry": {"coordinates":[-83.15076999999999,42.389316],"type":"Point"}
}