{
  "type": "Feature",
  "properties": {
    "iso:country":"US",
    "sg:address":"130 E Clinton St",
    "sg:city":"St Charles",
    "sg:classifiers":[
        {
            "category":"Organizations",
            "subcategory":"Religious Organization",
            "type":"Services"
        }
    ],
    "sg:phone":"+1 989 865 6000",
    "sg:postcode":"48655",
    "sg:province":"MI",
    "sg:tags":[
        "church"
    ],
    "wof:name":"First Baptist Church",
    "wof:placetype":"venue"
},
  "geometry": {"coordinates":[-84.138947,43.2967],"type":"Point"}
}