{
  "type": "Feature",
  "properties": {
    "iso:country":"US",
    "sg:address":"431 Millburg Dr",
    "sg:city":"Benton Harbor",
    "sg:classifiers":[
        {
            "category":"Building & Trades",
            "subcategory":"Construction",
            "type":"Services"
        }
    ],
    "sg:phone":"+1 269 944 0294",
    "sg:postcode":"49022",
    "sg:province":"MI",
    "sg:tags":[
        "general",
        "contractor"
    ],
    "wof:name":"General Help",
    "wof:placetype":"venue"
},
  "geometry": {"coordinates":[-86.336427,42.11493],"type":"Point"}
}