{
  "type": "Feature",
  "properties": {
    "iso:country":"US",
    "sg:address":"47145 James Dr",
    "sg:city":"Macomb",
    "sg:classifiers":[
        {
            "category":"Arts & Performance",
            "subcategory":"Theater",
            "type":"Entertainment"
        }
    ],
    "sg:phone":"+1 586 247 8586",
    "sg:postcode":"48044",
    "sg:province":"MI",
    "sg:tags":[
        "group"
    ],
    "wof:name":"Stephanie Nichols",
    "wof:placetype":"venue"
},
  "geometry": {"coordinates":[-82.96925,42.642708],"type":"Point"}
}