{
  "type": "Feature",
  "properties": {
    "iso:country":"US",
    "sg:address":"40 Wolverine Dr",
    "sg:city":"Walled Lake",
    "sg:classifiers":[
        {
            "category":"Building & Trades",
            "subcategory":"Landscaping Services",
            "type":"Services"
        }
    ],
    "sg:phone":"+1 248 624 7304",
    "sg:postcode":"48390",
    "sg:province":"MI",
    "wof:name":"Sunset Landscape",
    "wof:placetype":"venue"
},
  "geometry": {"coordinates":[-83.480113,42.544738],"type":"Point"}
}