{
  "type": "Feature",
  "properties": {
    "iso:country":"US",
    "sg:address":"4555 Schoedel Rd",
    "sg:city":"Manistee",
    "sg:classifiers":[
        {
            "category":"Wholesale",
            "subcategory":"Petroleum",
            "type":"Manufacturing & Wholesale Goods"
        }
    ],
    "sg:phone":"+1 231 889 0360",
    "sg:postcode":"49660",
    "sg:province":"MI",
    "sg:tags":[
        "pipe",
        "line",
        "company"
    ],
    "wof:name":"Mark West Michigan Pipeline Co",
    "wof:placetype":"venue"
},
  "geometry": {"coordinates":[-86.21504400000001,44.316917],"type":"Point"}
}