{
  "type": "Feature",
  "properties": {
    "iso:country":"US",
    "sg:address":"904 Ann Arbor Trail Ste 3",
    "sg:city":"Plymouth",
    "sg:classifiers":[
        {
            "category":"Coffee & Tea",
            "type":"Food & Drink"
        },
        {
            "category":"Shopping",
            "type":"Retail Goods"
        }
    ],
    "sg:phone":"+1 734 459 9686",
    "sg:postcode":"48170",
    "sg:province":"MI",
    "sg:website":"tranquilitea.com",
    "wof:name":"TranquiliTea",
    "wof:placetype":"venue"
},
  "geometry": {"coordinates":[-83.470664,42.370224],"type":"Point"}
}