{
  "type": "Feature",
  "properties": {
    "iso:country":"US",
    "sg:address":"20087 Herzog Dr",
    "sg:city":"Rockwood",
    "sg:classifiers":[
        {
            "category":"Arts & Performance",
            "subcategory":"Theater",
            "type":"Entertainment"
        }
    ],
    "sg:phone":"+1 734 379 0469",
    "sg:postcode":"48173",
    "sg:province":"MI",
    "sg:tags":[
        "group"
    ],
    "wof:name":"D&A Entertainment Inc",
    "wof:placetype":"venue"
},
  "geometry": {"coordinates":[-83.263611,42.077765],"type":"Point"}
}