{
  "type": "Feature",
  "properties": {
    "iso:country":"US",
    "sg:address":"2760 Lakes North Dr",
    "sg:city":"Interlochen",
    "sg:classifiers":[
        {
            "category":"Retail",
            "subcategory":"Laundry & Dry Cleaning",
            "type":"Services"
        }
    ],
    "sg:phone":"+1 231 276 2373",
    "sg:postcode":"49643",
    "sg:province":"MI",
    "sg:tags":[
        "cleaners",
        "rug",
        "carpet"
    ],
    "wof:name":"Procare Carpet Cleaning Svc",
    "wof:placetype":"venue"
},
  "geometry": {"coordinates":[-85.787728,44.651158],"type":"Point"}
}