{
  "type": "Feature",
  "properties": {
    "iso:country":"US",
    "sg:address":"2138 Plaza Dr",
    "sg:city":"Benton Harbor",
    "sg:classifiers":[
        {
            "category":"Real Estate",
            "subcategory":"Real Estate Agent",
            "type":"Services"
        }
    ],
    "sg:phone":"+1 269 683 1382",
    "sg:postcode":"49022",
    "sg:province":"MI",
    "sg:tags":[
        "property",
        "lessor"
    ],
    "wof:name":"Lynn Saroni",
    "wof:placetype":"venue"
},
  "geometry": {"coordinates":[-86.430774,42.078938],"type":"Point"}
}