{
  "type": "Feature",
  "properties": {
    "iso:country":"US",
    "sg:address":"2110 Ardenne Dr",
    "sg:city":"Ann Arbor",
    "sg:classifiers":[
        {
            "category":"Professional",
            "subcategory":"Management & Consulting",
            "type":"Services"
        }
    ],
    "sg:phone":"+1 734 769 7664",
    "sg:postcode":"48105",
    "sg:province":"MI",
    "wof:name":"Evergreen Financial Mgmt LLC",
    "wof:placetype":"venue"
},
  "geometry": {"coordinates":[-83.700766,42.304416],"type":"Point"}
}