{
  "type": "Feature",
  "properties": {
    "iso:country":"US",
    "sg:address":"1404 Zeeland Dr",
    "sg:city":"Holt",
    "sg:classifiers":[
        {
            "category":"Building & Trades",
            "subcategory":"Construction",
            "type":"Services"
        }
    ],
    "sg:phone":"+1 517 694 0246",
    "sg:postcode":"48842",
    "sg:province":"MI",
    "sg:tags":[
        "marking",
        "maintenance",
        "parking"
    ],
    "wof:name":"Ray's Driveway Sealing",
    "wof:placetype":"venue"
},
  "geometry": {"coordinates":[-84.546926,42.622797],"type":"Point"}
}