{
  "type": "Feature",
  "properties": {
    "iso:country":"US",
    "sg:address":"843 Bellamy Rd",
    "sg:city":"Ionia",
    "sg:classifiers":[
        {
            "category":"Shopping",
            "subcategory":"Gifts & Souvenirs",
            "type":"Retail Goods"
        }
    ],
    "sg:phone":"+1 616 527 6883",
    "sg:postcode":"48846",
    "sg:province":"MI",
    "sg:tags":[
        "basket",
        "parcel"
    ],
    "wof:name":"Gifts In A Basket",
    "wof:placetype":"venue"
},
  "geometry": {"coordinates":[-85.134224,42.987483],"type":"Point"}
}