{
  "type": "Feature",
  "properties": {
    "iso:country":"US",
    "sg:address":"2228 S M 33",
    "sg:city":"Rose City",
    "sg:classifiers":[
        {
            "category":"Autos & Motor Vehicles",
            "subcategory":"Recreational Vehicle Sales",
            "type":"Retail Goods"
        }
    ],
    "sg:phone":"+1 989 685 3461",
    "sg:postcode":"48654",
    "sg:province":"MI",
    "sg:tags":[
        "repair",
        "travel",
        "used",
        "trailer",
        "new"
    ],
    "wof:name":"Rose City Rv Center Inc",
    "wof:placetype":"venue"
},
  "geometry": {"coordinates":[-84.116462,44.40018],"type":"Point"}
}