{
  "type": "Feature",
  "properties": {
    "iso:country":"US",
    "sg:address":"437 E Division St",
    "sg:city":"Cadillac",
    "sg:classifiers":[
        {
            "category":"Government",
            "subcategory":"Court House",
            "type":"Public Place"
        }
    ],
    "sg:phone":"+1 231 779 9515",
    "sg:postcode":"49601",
    "sg:province":"MI",
    "wof:name":"District Court 84th",
    "wof:placetype":"venue"
},
  "geometry": {"coordinates":[-85.393788,44.252697],"type":"Point"}
}