{
  "type": "Feature",
  "properties": {
    "iso:country":"US",
    "sg:address":"2159 Alpine Ave NW",
    "sg:city":"Grand Rapids",
    "sg:classifiers":[
        {
            "category":"Manufacturing",
            "subcategory":"Retail Goods",
            "type":"Manufacturing & Wholesale Goods"
        }
    ],
    "sg:phone":"+1 616 252 3778",
    "sg:postcode":"49544",
    "sg:province":"MI",
    "sg:tags":[
        "assembly",
        "fabricating"
    ],
    "sg:website":"www.lear.com",
    "wof:name":"Lear Corp Grand Rapids",
    "wof:placetype":"venue"
},
  "geometry": {"coordinates":[-85.688585,43.002826],"type":"Point"}
}