{
  "type": "Feature",
  "properties": {
    "iso:country":"US",
    "sg:address":"4350 Concourse Dr",
    "sg:city":"Ann Arbor",
    "sg:classifiers":[
        {
            "category":"Organizations",
            "subcategory":"Labor Organization",
            "type":"Services"
        }
    ],
    "sg:phone":"+1 734 665 1054",
    "sg:postcode":"48108",
    "sg:province":"MI",
    "wof:name":"United Auto Wkrs Local Un 38",
    "wof:placetype":"venue"
},
  "geometry": {"coordinates":[-83.729372,42.221711],"type":"Point"}
}