{
  "type": "Feature",
  "properties": {
    "iso:country":"US",
    "sg:address":"14904 Coventry Dr",
    "sg:city":"Southgate",
    "sg:classifiers":[
        {
            "category":"Home & Garden",
            "subcategory":"Building Materials",
            "type":"Retail Goods"
        }
    ],
    "sg:phone":"+1 734 281 9862",
    "sg:postcode":"48195",
    "sg:province":"MI",
    "wof:name":"Precision Fit Windows",
    "wof:placetype":"venue"
},
  "geometry": {"coordinates":[-83.206138,42.218776],"type":"Point"}
}