{
  "type": "Feature",
  "properties": {
    "iso:country":"US",
    "sg:address":"1320 Pompton Cir",
    "sg:city":"Lansing",
    "sg:classifiers":[
        {
            "category":"Restaurant",
            "type":"Food & Drink"
        }
    ],
    "sg:phone":"+1 517 393 4762",
    "sg:postcode":"48910",
    "sg:province":"MI",
    "sg:tags":[
        "eating"
    ],
    "wof:name":"Cheesecake Bistro",
    "wof:placetype":"venue"
},
  "geometry": {"coordinates":[-84.571432,42.694313],"type":"Point"}
}