{
  "type": "Feature",
  "properties": {
    "iso:country":"US",
    "sg:address":"409 E Main St",
    "sg:city":"Fennville",
    "sg:classifiers":[
        {
            "category":"Autos & Motor Vehicles",
            "subcategory":"Fuel & Gas Station",
            "type":"Retail Goods"
        }
    ],
    "sg:phone":"+1 269 561 5237",
    "sg:postcode":"49408",
    "sg:province":"MI",
    "sg:tags":[
        "oil"
    ],
    "wof:name":"Merle Boes Inc",
    "wof:placetype":"venue"
},
  "geometry": {"coordinates":[-86.10037800000001,42.594365],"type":"Point"}
}