{
  "type": "Feature",
  "properties": {
    "iso:country":"US",
    "sg:address":"1105 W State St",
    "sg:city":"Hastings",
    "sg:classifiers":[
        {
            "category":"Restaurant",
            "type":"Food & Drink"
        }
    ],
    "sg:menulink":"http://www.allmenus.com/mi/rutland/26722-big-boy-restaurants/menu/",
    "sg:phone":"+1 269 948 2701",
    "sg:postcode":"49058",
    "sg:province":"MI",
    "sg:tags":[
        "sandwich",
        "salad",
        "burger",
        "dog",
        "soup",
        "hot",
        "wrap",
        "american"
    ],
    "wof:name":"Big Boy Restaurants",
    "wof:placetype":"venue"
},
  "geometry": {"coordinates":[-85.31061,42.648356],"type":"Point"}
}