{
  "type": "Feature",
  "properties": {
    "iso:country":"US",
    "sg:address":"3534 Southfield Fwy",
    "sg:city":"Dearborn",
    "sg:classifiers":[
        {
            "category":"Banks & Credit Unions",
            "subcategory":"Financial Services",
            "type":"Services"
        }
    ],
    "sg:phone":"+1 313 561 0195",
    "sg:postcode":"48124",
    "sg:province":"MI",
    "sg:tags":[
        "investor"
    ],
    "wof:name":"New Horizons Investments Inc",
    "wof:placetype":"venue"
},
  "geometry": {"coordinates":[-83.21647,42.279196],"type":"Point"}
}