{
  "type": "Feature",
  "properties": {
    "iso:country":"US",
    "sg:address":"4702 James Savage Rd",
    "sg:city":"Midland",
    "sg:classifiers":[
        {
            "category":"Professional",
            "type":"Services"
        }
    ],
    "sg:phone":"+1 989 631 8650",
    "sg:postcode":"48642",
    "sg:province":"MI",
    "sg:tags":[
        "arts",
        "artist"
    ],
    "wof:name":"Singing Wind Silks",
    "wof:placetype":"venue"
},
  "geometry": {"coordinates":[-84.169831,43.610559],"type":"Point"}
}