{
  "type": "Feature",
  "properties": {
    "iso:country":"US",
    "sg:address":"2712 Portage St",
    "sg:city":"Kalamazoo",
    "sg:classifiers":[
        {
            "category":"Professional",
            "type":"Services"
        }
    ],
    "sg:phone":"+1 269 383 1588",
    "sg:postcode":"49001",
    "sg:province":"MI",
    "sg:tags":[
        "establishment"
    ],
    "wof:name":"Wonderful's",
    "wof:placetype":"venue"
},
  "geometry": {"coordinates":[-85.568838,42.263662],"type":"Point"}
}