{
  "type": "Feature",
  "properties": {
    "iso:country":"US",
    "sg:address":"1891 E Chicago Rd",
    "sg:city":"Jonesville",
    "sg:classifiers":[
        {
            "category":"Professional",
            "subcategory":"Business Services",
            "type":"Services"
        }
    ],
    "sg:phone":"+1 517 849 2834",
    "sg:postcode":"49250",
    "sg:province":"MI",
    "sg:tags":[
        "appraiser"
    ],
    "wof:name":"Ned Clevidence Appraisals",
    "wof:placetype":"venue"
},
  "geometry": {"coordinates":[-84.633082,41.996276],"type":"Point"}
}