{
  "type": "Feature",
  "properties": {
    "iso:country":"US",
    "sg:address":"6090 US Hwy 31",
    "sg:city":"Levering",
    "sg:classifiers":[
        {
            "category":"Personal",
            "subcategory":"Beauty Salon",
            "type":"Services"
        }
    ],
    "sg:phone":"+1 231 537 6400",
    "sg:postcode":"49755",
    "sg:province":"MI",
    "wof:name":"Georgia's Stylin' Station",
    "wof:placetype":"venue"
},
  "geometry": {"coordinates":[-84.775065,45.645044],"type":"Point"}
}