{
  "type": "Feature",
  "properties": {
    "iso:country":"US",
    "sg:address":"4123 Embassy Dr SE",
    "sg:city":"Grand Rapids",
    "sg:classifiers":[
        {
            "category":"Organizations",
            "subcategory":"Non-profit Organization",
            "type":"Services"
        }
    ],
    "sg:phone":"+1 616 954 9747",
    "sg:postcode":"49546",
    "sg:province":"MI",
    "wof:name":"Gray Center",
    "wof:placetype":"venue"
},
  "geometry": {"coordinates":[-85.567891,42.917088],"type":"Point"}
}