{
  "type": "Feature",
  "properties": {
    "iso:country":"US",
    "sg:address":"3120 Brisbane St",
    "sg:city":"Walled Lake",
    "sg:classifiers":[
        {
            "category":"Building & Trades",
            "subcategory":"Landscaping Services",
            "type":"Services"
        }
    ],
    "sg:phone":"+1 248 624 4403",
    "sg:postcode":"48390",
    "sg:province":"MI",
    "sg:tags":[
        "landscape"
    ],
    "wof:name":"Craigs Landscape Service",
    "wof:placetype":"venue"
},
  "geometry": {"coordinates":[-83.498756,42.56861],"type":"Point"}
}