{
  "type": "Feature",
  "properties": {
    "iso:country":"US",
    "sg:address":"9266 Cherry Point Rd",
    "sg:city":"Manitou Beach",
    "sg:classifiers":[
        {
            "category":"Professional",
            "subcategory":"Management & Consulting",
            "type":"Services"
        }
    ],
    "sg:phone":"+1 517 547 4212",
    "sg:postcode":"49253",
    "sg:province":"MI",
    "sg:tags":[
        "development",
        "consultant",
        "business"
    ],
    "wof:name":"Sikorski Consulting LLC",
    "wof:placetype":"venue"
},
  "geometry": {"coordinates":[-84.30116,41.979728],"type":"Point"}
}