{
  "type": "Feature",
  "properties": {
    "iso:country":"US",
    "sg:address":"28901 Greenfield Rd",
    "sg:city":"Southfield",
    "sg:classifiers":[
        {
            "category":"Retail",
            "subcategory":"Portrait Studio",
            "type":"Services"
        },
        {
            "category":"Shopping",
            "subcategory":"Pharmacy",
            "type":"Retail Goods"
        }
    ],
    "sg:phone":"+1 248 552 0847",
    "sg:postcode":"48076",
    "sg:province":"MI",
    "sg:tags":[
        "photography",
        "drugstore",
        "store"
    ],
    "wof:name":"Walgreen Drug Stores",
    "wof:placetype":"venue"
},
  "geometry": {"coordinates":[-83.20320100000001,42.502602],"type":"Point"}
}