{
  "type": "Feature",
  "properties": {
    "iso:country":"US",
    "sg:address":"2355 E Dodge Rd",
    "sg:city":"Clio",
    "sg:classifiers":[
        {
            "category":"Real Estate",
            "subcategory":"Real Estate Agent",
            "type":"Services"
        }
    ],
    "sg:phone":"+1 810 686 3310",
    "sg:postcode":"48420",
    "sg:province":"MI",
    "wof:name":"W H Johnston Real Estate Inc",
    "wof:placetype":"venue"
},
  "geometry": {"coordinates":[-83.663606,43.149633],"type":"Point"}
}