{
  "type": "Feature",
  "properties": {
    "iso:country":"US",
    "sg:address":"601 W Fort St",
    "sg:city":"Detroit",
    "sg:classifiers":[
        {
            "category":"Professional",
            "type":"Services"
        }
    ],
    "sg:phone":"+1 313 223 3333",
    "sg:postcode":"48226",
    "sg:province":"MI",
    "sg:tags":[
        "publication",
        "editorial"
    ],
    "wof:name":"Third Street Publications",
    "wof:placetype":"venue"
},
  "geometry": {"coordinates":[-83.053146,42.328232],"type":"Point"}
}