{
  "type": "Feature",
  "properties": {
    "iso:country":"US",
    "sg:address":"767 Capital Ave NE",
    "sg:city":"Battle Creek",
    "sg:classifiers":[
        {
            "category":"Retail",
            "subcategory":"Repair Shop",
            "type":"Services"
        }
    ],
    "sg:phone":"+1 269 964 3461",
    "sg:postcode":"49017",
    "sg:province":"MI",
    "sg:tags":[
        "appliance",
        "household",
        "electrical"
    ],
    "wof:name":"Soules Appliance Repair",
    "wof:placetype":"venue"
},
  "geometry": {"coordinates":[-85.15566800000001,42.33003],"type":"Point"}
}