{
  "type": "Feature",
  "properties": {
    "iso:country":"US",
    "sg:address":"4238 24th St",
    "sg:city":"Detroit",
    "sg:classifiers":[
        {
            "category":"Manufacturing",
            "subcategory":"Printing",
            "type":"Manufacturing & Wholesale Goods"
        }
    ],
    "sg:phone":"+1 313 897 9400",
    "sg:postcode":"48208",
    "sg:province":"MI",
    "sg:tags":[
        "work"
    ],
    "wof:name":"Triangle Bookbinding Inc",
    "wof:placetype":"venue"
},
  "geometry": {"coordinates":[-83.097902,42.340613],"type":"Point"}
}