{
  "type": "Feature",
  "properties": {
    "iso:country":"US",
    "sg:address":"8590 Alabaster Rd",
    "sg:city":"Whittemore",
    "sg:classifiers":[
        {
            "category":"Recreation",
            "type":"Entertainment"
        }
    ],
    "sg:phone":"+1 989 756 3034",
    "sg:postcode":"48770",
    "sg:province":"MI",
    "sg:tags":[
        "stable"
    ],
    "wof:name":"J Allen Horseshoeing",
    "wof:placetype":"venue"
},
  "geometry": {"coordinates":[-83.872741,44.204945],"type":"Point"}
}