{
  "type": "Feature",
  "properties": {
    "iso:country":"US",
    "sg:address":"3435 Broadmoor Ave SE",
    "sg:city":"Grand Rapids",
    "sg:classifiers":[
        {
            "category":"Building & Trades",
            "subcategory":"Construction",
            "type":"Services"
        }
    ],
    "sg:phone":"+1 616 949 0800",
    "sg:postcode":"49512",
    "sg:province":"MI",
    "sg:tags":[
        "excavating",
        "contractor"
    ],
    "wof:name":"Kamminga & Roodvoets",
    "wof:placetype":"venue"
},
  "geometry": {"coordinates":[-85.57969799999999,42.900911],"type":"Point"}
}