{
  "type": "Feature",
  "properties": {
    "iso:country":"US",
    "sg:address":"12791 Morseville Rd",
    "sg:city":"Birch Run",
    "sg:classifiers":[
        {
            "category":"Building & Trades",
            "subcategory":"Construction",
            "type":"Services"
        }
    ],
    "sg:phone":"+1 989 624 4162",
    "sg:postcode":"48415",
    "sg:province":"MI",
    "sg:tags":[
        "house"
    ],
    "wof:name":"KC3 Inc",
    "wof:placetype":"venue"
},
  "geometry": {"coordinates":[-83.86690299999999,43.238895],"type":"Point"}
}