{
  "type": "Feature",
  "properties": {
    "iso:country":"US",
    "sg:address":"11307 Hillview Dr",
    "sg:city":"Cement City",
    "sg:classifiers":[
        {
            "category":"Building & Trades",
            "subcategory":"Electrical",
            "type":"Services"
        }
    ],
    "sg:phone":"+1 517 206 5539",
    "sg:postcode":"49282",
    "sg:province":"MI",
    "sg:tags":[
        "electrical",
        "contractor"
    ],
    "wof:name":"David Kisner Construction",
    "wof:placetype":"venue"
},
  "geometry": {"coordinates":[-84.366517,42.06275],"type":"Point"}
}