{
  "type": "Feature",
  "properties": {
    "iso:country":"US",
    "sg:address":"19400 E 10 Mile Rd",
    "sg:city":"Eastpointe",
    "sg:classifiers":[
        {
            "category":"Bars & Pubs",
            "type":"Food & Drink"
        }
    ],
    "sg:menulink":"http://www.allmenus.com/mi/eastpointe/114044-fairway-bar--grill/menu/",
    "sg:phone":"+1 586 771 4995",
    "sg:postcode":"48021",
    "sg:province":"MI",
    "sg:tags":[
        "burger",
        "american"
    ],
    "wof:name":"Fairway Bar & Grill",
    "wof:placetype":"venue"
},
  "geometry": {"coordinates":[-82.918131,42.479994],"type":"Point"}
}