{
  "type": "Feature",
  "properties": {
    "iso:country":"US",
    "sg:address":"2810 E Mount Garfield Rd",
    "sg:city":"Muskegon",
    "sg:classifiers":[
        {
            "category":"Government",
            "subcategory":"Office",
            "type":"Public Place"
        }
    ],
    "sg:phone":"+1 231 865 7343",
    "sg:postcode":"49444",
    "sg:province":"MI",
    "sg:tags":[
        "village"
    ],
    "wof:name":"Fruitport Township Sewer Dept",
    "wof:placetype":"venue"
},
  "geometry": {"coordinates":[-86.175121,43.14681],"type":"Point"}
}