{
  "type": "Feature",
  "properties": {
    "iso:country":"US",
    "sg:address":"23324 5th Ave",
    "sg:city":"Gobles",
    "sg:classifiers":[
        {
            "category":"Building & Trades",
            "subcategory":"Landscaping Services",
            "type":"Services"
        }
    ],
    "sg:phone":"+1 616 889 7133",
    "sg:postcode":"49055",
    "sg:province":"MI",
    "sg:tags":[
        "landscape",
        "contractor"
    ],
    "wof:name":"B & B Lawn Care & Landscaping",
    "wof:placetype":"venue"
},
  "geometry": {"coordinates":[-85.776601,42.400622],"type":"Point"}
}