{
  "type": "Feature",
  "properties": {
    "iso:country":"US",
    "sg:address":"94 Laperell Rd",
    "sg:city":"Cheboygan",
    "sg:classifiers":[
        {
            "category":"Personal",
            "subcategory":"Beauty Salon",
            "type":"Services"
        }
    ],
    "sg:phone":"+1 231 627 6625",
    "sg:postcode":"49721",
    "sg:province":"MI",
    "wof:name":"Sharon's Country Salon",
    "wof:placetype":"venue"
},
  "geometry": {"coordinates":[-84.48947099999999,45.591552],"type":"Point"}
}