{
  "type": "Feature",
  "properties": {
    "iso:country":"US",
    "sg:address":"64249 Van Dyke Rd",
    "sg:city":"Washington",
    "sg:classifiers":[
        {
            "category":"Professional",
            "subcategory":"Lawyer & Legal Services",
            "type":"Services"
        }
    ],
    "sg:phone":"+1 586 752 7373",
    "sg:postcode":"48095",
    "sg:province":"MI",
    "sg:tags":[
        "attorney"
    ],
    "wof:name":"Anthony E Jacobs Law Offices",
    "wof:placetype":"venue"
},
  "geometry": {"coordinates":[-83.018349,42.766423],"type":"Point"}
}