{
  "type": "Feature",
  "properties": {
    "iso:country":"US",
    "sg:address":"19880 Fort St",
    "sg:city":"Wyandotte",
    "sg:classifiers":[
        {
            "category":"Real Estate",
            "subcategory":"Real Estate Operator",
            "type":"Services"
        }
    ],
    "sg:phone":"+1 734 479 2000",
    "sg:postcode":"48193",
    "sg:province":"MI",
    "sg:tags":[
        "apartment"
    ],
    "wof:name":"Greentrees Apartments",
    "wof:placetype":"venue"
},
  "geometry": {"coordinates":[-83.189339,42.163962],"type":"Point"}
}