{
  "type": "Feature",
  "properties": {
    "iso:country":"US",
    "sg:address":"26190 Groesbeck Hwy",
    "sg:city":"Warren",
    "sg:classifiers":[
        {
            "category":"Building & Trades",
            "subcategory":"Construction",
            "type":"Services"
        }
    ],
    "sg:phone":"+1 586 773 8359",
    "sg:postcode":"48089",
    "sg:province":"MI",
    "sg:tags":[
        "concrete",
        "cutting",
        "breaking",
        "sawing"
    ],
    "wof:name":"Andre Gelle Concrete Removal",
    "wof:placetype":"venue"
},
  "geometry": {"coordinates":[-82.971311,42.490474],"type":"Point"}
}