{
  "type": "Feature",
  "properties": {
    "iso:country":"US",
    "sg:address":"720 Ash St",
    "sg:city":"Carleton",
    "sg:classifiers":[
        {
            "category":"Building & Trades",
            "subcategory":"Landscaping Services",
            "type":"Services"
        }
    ],
    "sg:phone":"+1 734 654 8344",
    "sg:postcode":"48117",
    "sg:province":"MI",
    "sg:tags":[
        "landscape",
        "contractor"
    ],
    "wof:name":"S & S Hydroseeding Inc",
    "wof:placetype":"venue"
},
  "geometry": {"coordinates":[-83.387495,42.06082],"type":"Point"}
}