{
  "type": "Feature",
  "properties": {
    "iso:country":"US",
    "sg:address":"631 E Chauvez Rd",
    "sg:city":"Scottville",
    "sg:classifiers":[
        {
            "category":"Restaurant",
            "type":"Food & Drink"
        }
    ],
    "sg:phone":"+1 231 757 2525",
    "sg:postcode":"49454",
    "sg:province":"MI",
    "sg:tags":[
        "membership",
        "eating",
        "lodging"
    ],
    "wof:name":"Reeds Enterprises",
    "wof:placetype":"venue"
},
  "geometry": {"coordinates":[-86.263597,43.90419],"type":"Point"}
}