{
  "type": "Feature",
  "properties": {
    "iso:country":"US",
    "sg:address":"59477 Hardy Ln",
    "sg:city":"New Haven",
    "sg:classifiers":[
        {
            "category":"Real Estate",
            "subcategory":"Real Estate Operator",
            "type":"Services"
        }
    ],
    "sg:phone":"+1 586 749 3404",
    "sg:postcode":"48048",
    "sg:province":"MI",
    "sg:tags":[
        "mobile",
        "home",
        "community"
    ],
    "wof:name":"Riverbrook Manufactured Hsng",
    "wof:placetype":"venue"
},
  "geometry": {"coordinates":[-82.784144,42.740028],"type":"Point"}
}