{
  "type": "Feature",
  "properties": {
    "iso:country":"US",
    "sg:address":"3145 Midland Rd",
    "sg:city":"Saginaw",
    "sg:classifiers":[
        {
            "category":"Manufacturing",
            "subcategory":"Retail Goods",
            "type":"Manufacturing & Wholesale Goods"
        }
    ],
    "sg:phone":"+1 989 497 8809",
    "sg:postcode":"48603",
    "sg:province":"MI",
    "sg:tags":[
        "manufacturer"
    ],
    "wof:name":"Hydraulic Installations Bllng",
    "wof:placetype":"venue"
},
  "geometry": {"coordinates":[-84.06796300000001,43.45341],"type":"Point"}
}