{
  "type": "Feature",
  "properties": {
    "iso:country":"US",
    "sg:address":"1000 W Ann Arbor Trl",
    "sg:city":"Plymouth",
    "sg:classifiers":[
        {
            "category":"Building & Trades",
            "subcategory":"Construction",
            "type":"Services"
        }
    ],
    "sg:phone":"+1 734 453 6560",
    "sg:postcode":"48170",
    "sg:province":"MI",
    "sg:tags":[
        "contractor"
    ],
    "wof:name":"M P K Construction Co",
    "wof:placetype":"venue"
},
  "geometry": {"coordinates":[-83.47199999999999,42.3703],"type":"Point"}
}