{
  "type": "Feature",
  "properties": {
    "iso:country":"US",
    "sg:address":"427 I- 75 Bus",
    "sg:city":"Grayling",
    "sg:classifiers":[
        {
            "category":"Shopping",
            "type":"Retail Goods"
        }
    ],
    "sg:phone":"+1 989 344 2088",
    "sg:postcode":"49738",
    "sg:province":"MI",
    "sg:tags":[
        "ice"
    ],
    "wof:name":"Northern Pure Ice Co",
    "wof:placetype":"venue"
},
  "geometry": {"coordinates":[-84.717833,44.678958],"type":"Point"}
}