{
  "type": "Feature",
  "properties": {
    "iso:country":"US",
    "sg:address":"12780 Partlow St",
    "sg:city":"Grand Ledge",
    "sg:classifiers":[
        {
            "category":"Wholesale",
            "subcategory":"Stationery",
            "type":"Manufacturing & Wholesale Goods"
        }
    ],
    "sg:phone":"+1 517 627 3273",
    "sg:postcode":"48837",
    "sg:province":"MI",
    "sg:tags":[
        "packaging",
        "material"
    ],
    "wof:name":"K & K Supply Inc",
    "wof:placetype":"venue"
},
  "geometry": {"coordinates":[-84.76425999999999,42.753192],"type":"Point"}
}