{
  "type": "Feature",
  "properties": {
    "iso:country":"US",
    "sg:address":"2951 Michigan Rd",
    "sg:city":"Port Huron",
    "sg:classifiers":[
        {
            "category":"Building & Trades",
            "subcategory":"Construction",
            "type":"Services"
        }
    ],
    "sg:phone":"+1 810 650 4920",
    "sg:postcode":"48060",
    "sg:province":"MI",
    "sg:tags":[
        "home",
        "improvement"
    ],
    "wof:name":"Interlakes Construction",
    "wof:placetype":"venue"
},
  "geometry": {"coordinates":[-82.483757,42.986576],"type":"Point"}
}