{
  "type": "Feature",
  "properties": {
    "iso:country":"US",
    "sg:address":"1480 E Hastings Lake Rd",
    "sg:city":"Jonesville",
    "sg:classifiers":[
        {
            "category":"Building & Trades",
            "subcategory":"Construction",
            "type":"Services"
        }
    ],
    "sg:phone":"+1 517 849 2334",
    "sg:postcode":"49250",
    "sg:province":"MI",
    "sg:tags":[
        "contractor"
    ],
    "wof:name":"Domack Building",
    "wof:placetype":"venue"
},
  "geometry": {"coordinates":[-84.632592,42.029217],"type":"Point"}
}