{
  "type": "Feature",
  "properties": {
    "iso:country":"US",
    "sg:address":"835 S Garfield Ave",
    "sg:city":"Traverse City",
    "sg:classifiers":[
        {
            "category":"Food & Beverages",
            "subcategory":"Specialty",
            "type":"Retail Goods"
        }
    ],
    "sg:phone":"+1 231 941 5221",
    "sg:postcode":"49686",
    "sg:province":"MI",
    "sg:tags":[
        "health",
        "diet"
    ],
    "wof:name":"Edson Farms Natural Foods",
    "wof:placetype":"venue"
},
  "geometry": {"coordinates":[-85.595237,44.752594],"type":"Point"}
}