{
  "type": "Feature",
  "properties": {
    "iso:country":"US",
    "sg:address":"3373 Thar Rd",
    "sg:city":"Coloma",
    "sg:classifiers":[
        {
            "category":"Restaurant",
            "type":"Food & Drink"
        }
    ],
    "sg:phone":"+1 269 849 3155",
    "sg:postcode":"49038",
    "sg:province":"MI",
    "sg:tags":[
        "banquet",
        "rooms"
    ],
    "wof:name":"Country Cove Banquet",
    "wof:placetype":"venue"
},
  "geometry": {"coordinates":[-86.37649500000001,42.193532],"type":"Point"}
}