{
  "type": "Feature",
  "properties": {
    "iso:country":"US",
    "sg:address":"4100 Lehman Rd",
    "sg:city":"Dewitt",
    "sg:classifiers":[
        {
            "category":"Education",
            "subcategory":"Special Training",
            "type":"Public Place"
        }
    ],
    "sg:phone":"+1 517 669 5089",
    "sg:postcode":"48820",
    "sg:province":"MI",
    "sg:tags":[
        "educational"
    ],
    "wof:name":"Daniel Quisenberry",
    "wof:placetype":"venue"
},
  "geometry": {"coordinates":[-84.605665,42.885683],"type":"Point"}
}