{
  "type": "Feature",
  "properties": {
    "iso:country":"US",
    "sg:address":"33117 Alvin St",
    "sg:city":"Garden City",
    "sg:classifiers":[
        {
            "category":"Home & Garden",
            "subcategory":"Home Furnishings",
            "type":"Retail Goods"
        }
    ],
    "sg:phone":"+1 734 427 2114",
    "sg:postcode":"48135",
    "sg:province":"MI",
    "wof:name":"Fuller Brush Home Products",
    "wof:placetype":"venue"
},
  "geometry": {"coordinates":[-83.368165,42.313155],"type":"Point"}
}