{
  "type": "Feature",
  "properties": {
    "iso:country":"US",
    "sg:address":"1033 Hickory St",
    "sg:city":"Lansing",
    "sg:classifiers":[
        {
            "category":"Organizations",
            "subcategory":"Religious Organization",
            "type":"Services"
        }
    ],
    "sg:phone":"+1 517 372 0513",
    "sg:postcode":"48912",
    "sg:province":"MI",
    "sg:tags":[
        "church"
    ],
    "wof:name":"Grace Of Love",
    "wof:placetype":"venue"
},
  "geometry": {"coordinates":[-84.53522100000001,42.729075],"type":"Point"}
}