{
  "type": "Feature",
  "properties": {
    "iso:country":"US",
    "sg:address":"1084 Leffingwell Ave NE",
    "sg:city":"Grand Rapids",
    "sg:classifiers":[
        {
            "category":"Social Services",
            "subcategory":"Child Care",
            "type":"Services"
        }
    ],
    "sg:phone":"+1 616 222 1468",
    "sg:postcode":"49525",
    "sg:province":"MI",
    "sg:tags":[
        "day"
    ],
    "wof:name":"Rebecca Wittenberger",
    "wof:placetype":"venue"
},
  "geometry": {"coordinates":[-85.60062499999999,42.979513],"type":"Point"}
}