{
  "type": "Feature",
  "properties": {
    "iso:country":"US",
    "sg:address":"30776 John R Rd",
    "sg:city":"Madison Heights",
    "sg:classifiers":[
        {
            "category":"Professional",
            "type":"Services"
        }
    ],
    "sg:phone":"+1 248 589 0767",
    "sg:postcode":"48071",
    "sg:province":"MI",
    "sg:tags":[
        "establishment"
    ],
    "wof:name":"Johnny Wong Famous Carrier",
    "wof:placetype":"venue"
},
  "geometry": {"coordinates":[-83.10633900000001,42.519433],"type":"Point"}
}