{
  "type": "Feature",
  "properties": {
    "iso:country":"US",
    "sg:address":"10490 Gratiot Ave",
    "sg:city":"Columbus",
    "sg:classifiers":[
        {
            "category":"Retail",
            "subcategory":"Auto Repair",
            "type":"Services"
        }
    ],
    "sg:phone":"+1 586 727 5419",
    "sg:postcode":"48063",
    "sg:province":"MI",
    "sg:tags":[
        "repairing",
        "automobile"
    ],
    "wof:name":"Jeremy's Automotive Prfrmnce",
    "wof:placetype":"venue"
},
  "geometry": {"coordinates":[-82.71861699999999,42.816263],"type":"Point"}
}