{
  "type": "Feature",
  "properties": {
    "iso:country":"US",
    "sg:address":"24390 W 10 Mile Rd",
    "sg:city":"Southfield",
    "sg:classifiers":[
        {
            "category":"Shopping",
            "subcategory":"Mobile Phones",
            "type":"Retail Goods"
        }
    ],
    "sg:phone":"+1 248 799 9959",
    "sg:postcode":"48033",
    "sg:province":"MI",
    "sg:website":"www.metropcs.com",
    "wof:name":"Metro Pcs",
    "wof:placetype":"venue"
},
  "geometry": {"coordinates":[-83.283001,42.471996],"type":"Point"}
}