{
  "type": "Feature",
  "properties": {
    "iso:country":"US",
    "sg:address":"12701 Calhoun Rd",
    "sg:city":"Milan",
    "sg:classifiers":[
        {
            "category":"Professional",
            "subcategory":"Management & Consulting",
            "type":"Services"
        }
    ],
    "sg:phone":"+1 734 439 2381",
    "sg:postcode":"48160",
    "sg:province":"MI",
    "wof:name":"Team Stevens",
    "wof:placetype":"venue"
},
  "geometry": {"coordinates":[-83.620537,42.052675],"type":"Point"}
}