{
  "type": "Feature",
  "properties": {
    "iso:country":"US",
    "sg:address":"299 W Sunset Dr",
    "sg:city":"Roscommon",
    "sg:classifiers":[
        {
            "category":"Education",
            "subcategory":"School",
            "type":"Public Place"
        }
    ],
    "sg:phone":"+1 989 275 6640",
    "sg:postcode":"48653",
    "sg:province":"MI",
    "wof:name":"Roscommon Middle School",
    "wof:placetype":"venue"
},
  "geometry": {"coordinates":[-84.615235,44.494265],"type":"Point"}
}