{
  "type": "Feature",
  "properties": {
    "iso:country":"US",
    "sg:address":"1011 S Farragut St",
    "sg:city":"Bay City",
    "sg:classifiers":[
        {
            "category":"Shopping",
            "subcategory":"Clothing, Apparel, & Fashions",
            "type":"Retail Goods"
        }
    ],
    "sg:phone":"+1 989 892 0929",
    "sg:postcode":"48708",
    "sg:province":"MI",
    "wof:name":"Independent Uniform Rental",
    "wof:placetype":"venue"
},
  "geometry": {"coordinates":[-83.88021000000001,43.579122],"type":"Point"}
}