{
  "type": "Feature",
  "properties": {
    "iso:country":"US",
    "sg:address":"32357 Knapp Ave",
    "sg:city":"Warren",
    "sg:classifiers":[
        {
            "category":"Building & Trades",
            "subcategory":"Electrical",
            "type":"Services"
        }
    ],
    "sg:phone":"+1 586 978 1234",
    "sg:postcode":"48093",
    "sg:province":"MI",
    "sg:tags":[
        "electrician"
    ],
    "wof:name":"Macomb Liberty Electric",
    "wof:placetype":"venue"
},
  "geometry": {"coordinates":[-83.025902,42.531502],"type":"Point"}
}