{
  "type": "Feature",
  "properties": {
    "iso:country":"US",
    "sg:address":"2345 E Apple Ave",
    "sg:city":"Muskegon",
    "sg:classifiers":[
        {
            "category":"Restaurant",
            "type":"Food & Drink"
        }
    ],
    "sg:phone":"+1 231 773 5555",
    "sg:postcode":"49442",
    "sg:province":"MI",
    "sg:tags":[
        "mexican"
    ],
    "wof:name":"Pablo's Tacos",
    "wof:placetype":"venue"
},
  "geometry": {"coordinates":[-86.185394,43.234234],"type":"Point"}
}