{
  "type": "Feature",
  "properties": {
    "iso:country":"US",
    "sg:address":"2666 Metropolitan Pkwy",
    "sg:city":"Sterling Heights",
    "sg:classifiers":[
        {
            "category":"Sports & Exercise",
            "subcategory":"Bowling",
            "type":"Entertainment"
        }
    ],
    "sg:phone":"+1 586 939 2550",
    "sg:postcode":"48310",
    "sg:province":"MI",
    "sg:tags":[
        "center"
    ],
    "sg:website":"www.five-starlanes.com",
    "wof:name":"Five Star Lanes",
    "wof:placetype":"venue"
},
  "geometry": {"coordinates":[-83.0812,42.5639],"type":"Point"}
}