{
  "type": "Feature",
  "properties": {
    "iso:country":"US",
    "sg:address":"1668 Olympian Way",
    "sg:city":"Howell",
    "sg:classifiers":[
        {
            "category":"Building & Trades",
            "subcategory":"Construction",
            "type":"Services"
        }
    ],
    "sg:phone":"+1 517 552 9834",
    "sg:postcode":"48843",
    "sg:province":"MI",
    "sg:tags":[
        "home",
        "builder"
    ],
    "wof:name":"KDB Custom Homes",
    "wof:placetype":"venue"
},
  "geometry": {"coordinates":[-83.866671,42.6279],"type":"Point"}
}