{
  "type": "Feature",
  "properties": {
    "iso:country":"US",
    "sg:address":"7303 Morrison Lake Rd",
    "sg:city":"Saranac",
    "sg:classifiers":[
        {
            "category":"Farming",
            "subcategory":"Dairy Farm",
            "type":"Manufacturing & Wholesale Goods"
        }
    ],
    "sg:phone":"+1 616 642 9525",
    "sg:postcode":"48881",
    "sg:province":"MI",
    "wof:name":"Joe Mutschler",
    "wof:placetype":"venue"
},
  "geometry": {"coordinates":[-85.213345,42.881835],"type":"Point"}
}