{
  "type": "Feature",
  "properties": {
    "iso:country":"US",
    "sg:address":"4373 Hazel St",
    "sg:city":"Clarkston",
    "sg:classifiers":[
        {
            "category":"Wholesale",
            "subcategory":"Toys & Hobbies",
            "type":"Manufacturing & Wholesale Goods"
        }
    ],
    "sg:phone":"+1 248 236 9209",
    "sg:postcode":"48348",
    "sg:province":"MI",
    "wof:name":"Craft Connection",
    "wof:placetype":"venue"
},
  "geometry": {"coordinates":[-83.362709,42.795377],"type":"Point"}
}