{
  "type": "Feature",
  "properties": {
    "iso:country":"US",
    "sg:address":"50714 Van Dyke Ave",
    "sg:city":"Shelby Twp",
    "sg:classifiers":[
        {
            "category":"Building & Trades",
            "subcategory":"Construction",
            "type":"Services"
        }
    ],
    "sg:phone":"+1 586 323 1302",
    "sg:postcode":"48317",
    "sg:province":"MI",
    "sg:tags":[
        "home",
        "builder"
    ],
    "sg:website":"www.nicholashomes.net",
    "wof:name":"Nicholas Homes Inc",
    "wof:placetype":"venue"
},
  "geometry": {"coordinates":[-83.033778,42.669373],"type":"Point"}
}