{
  "type": "Feature",
  "properties": {
    "iso:country":"US",
    "sg:address":"6677 Belgian Ave",
    "sg:city":"Kalamazoo",
    "sg:classifiers":[
        {
            "category":"Professional",
            "subcategory":"Management & Consulting",
            "type":"Services"
        }
    ],
    "sg:phone":"+1 269 544 0780",
    "sg:postcode":"49009",
    "sg:province":"MI",
    "sg:tags":[
        "farm",
        "consultant"
    ],
    "wof:name":"Capasso Farm Consultants LLC",
    "wof:placetype":"venue"
},
  "geometry": {"coordinates":[-85.680173,42.205177],"type":"Point"}
}