{
  "type": "Feature",
  "properties": {
    "iso:country":"US",
    "sg:address":"2706 W Michigan Ave",
    "sg:city":"Kalamazoo",
    "sg:classifiers":[
        {
            "category":"Restaurant",
            "type":"Food & Drink"
        }
    ],
    "sg:menulink":"http://www.allmenus.com/mi/kalamazoo/45120-panda-express/menu/",
    "sg:phone":"+1 269 382 8169",
    "sg:postcode":"49006",
    "sg:province":"MI",
    "sg:tags":[
        "asian",
        "chinese"
    ],
    "wof:name":"Panda Express",
    "wof:placetype":"venue"
},
  "geometry": {"coordinates":[-85.623835,42.280998],"type":"Point"}
}