{
  "type": "Feature",
  "properties": {
    "iso:country":"US",
    "sg:address":"123 W Maumee St",
    "sg:city":"Adrian",
    "sg:classifiers":[
        {
            "category":"Shopping",
            "subcategory":"Jewelry",
            "type":"Retail Goods"
        }
    ],
    "sg:phone":"+1 517 265 6117",
    "sg:postcode":"49221",
    "sg:province":"MI",
    "sg:tags":[
        "jeweler"
    ],
    "wof:name":"Cottrell Jewelers",
    "wof:placetype":"venue"
},
  "geometry": {"coordinates":[-84.037547,41.899148],"type":"Point"}
}