{
  "type": "Feature",
  "properties": {
    "iso:country":"US",
    "sg:address":"5252 Exchange Dr",
    "sg:city":"Flint",
    "sg:classifiers":[
        {
            "category":"Professional",
            "subcategory":"Printing & Photocopies",
            "type":"Services"
        }
    ],
    "sg:phone":"+1 810 715 2583",
    "sg:postcode":"48507",
    "sg:province":"MI",
    "sg:tags":[
        "blueprinting"
    ],
    "wof:name":"Burton Blueprinting",
    "wof:placetype":"venue"
},
  "geometry": {"coordinates":[-83.77862500000001,42.969573],"type":"Point"}
}