{
  "type": "Feature",
  "properties": {
    "iso:country":"US",
    "sg:address":"11138 S West-Bay Shore Dr",
    "sg:city":"Traverse City",
    "sg:classifiers":[
        {
            "category":"Education",
            "subcategory":"Special Training",
            "type":"Public Place"
        }
    ],
    "sg:phone":"+1 231 947 8714",
    "sg:postcode":"49684",
    "sg:province":"MI",
    "wof:name":"Pat Ford Studio",
    "wof:placetype":"venue"
},
  "geometry": {"coordinates":[-85.645894,44.81863],"type":"Point"}
}