{
  "type": "Feature",
  "properties": {
    "iso:country":"US",
    "sg:address":"137 N Main St",
    "sg:city":"Perry",
    "sg:classifiers":[
        {
            "category":"Food & Beverages",
            "subcategory":"Groceries & Convenience Stores",
            "type":"Retail Goods"
        }
    ],
    "sg:phone":"+1 517 625 7000",
    "sg:postcode":"48872",
    "sg:province":"MI",
    "wof:name":"Mugg & Bopps",
    "wof:placetype":"venue"
},
  "geometry": {"coordinates":[-84.21914700000001,42.825564],"type":"Point"}
}