{
  "type": "Feature",
  "properties": {
    "iso:country":"US",
    "sg:address":"1001 W Washington Ave",
    "sg:city":"Alpena",
    "sg:classifiers":[
        {
            "category":"Professional",
            "subcategory":"Management & Consulting",
            "type":"Services"
        }
    ],
    "sg:phone":"+1 989 358 8720",
    "sg:postcode":"49707",
    "sg:province":"MI",
    "sg:tags":[
        "consultant",
        "energy",
        "conservation"
    ],
    "wof:name":"Samson Resources Co",
    "wof:placetype":"venue"
},
  "geometry": {"coordinates":[-83.453959,45.061707],"type":"Point"}
}