{
  "type": "Feature",
  "properties": {
    "iso:country":"US",
    "sg:address":"105 E Bethune St",
    "sg:city":"Detroit",
    "sg:classifiers":[
        {
            "category":"Professional",
            "subcategory":"Computer Services",
            "type":"Services"
        }
    ],
    "sg:phone":"+1 866 310 4761",
    "sg:postcode":"48202",
    "sg:province":"MI",
    "sg:tags":[
        "isp",
        "provider",
        "internet"
    ],
    "sg:website":"http://www.directsattv.com/directv/?tfid=ypm",
    "wof:name":"Direct Sat TV - An Authorized DIRECTV Dealer",
    "wof:placetype":"venue"
},
  "geometry": {"coordinates":[-83.073539,42.372794],"type":"Point"}
}