{
  "type": "Feature",
  "properties": {
    "iso:country":"US",
    "sg:address":"1870 S Elba Rd",
    "sg:city":"Lapeer",
    "sg:classifiers":[
        {
            "category":"Manufacturing",
            "subcategory":"Tools & Machinery",
            "type":"Manufacturing & Wholesale Goods"
        }
    ],
    "sg:phone":"+1 810 664 0358",
    "sg:postcode":"48446",
    "sg:province":"MI",
    "sg:tags":[
        "equipment",
        "safety",
        "clothing"
    ],
    "wof:name":"M & C Supplies",
    "wof:placetype":"venue"
},
  "geometry": {"coordinates":[-83.42877799999999,43.001557],"type":"Point"}
}