{
  "type": "Feature",
  "properties": {
    "iso:country":"US",
    "sg:address":"23300 Providence Dr",
    "sg:city":"Southfield",
    "sg:classifiers":[
        {
            "category":"Organizations",
            "subcategory":"Religious Organization",
            "type":"Services"
        }
    ],
    "sg:phone":"+1 248 559 5277",
    "sg:postcode":"48075",
    "sg:province":"MI",
    "wof:name":"Go In Faith Ministries Cathedr",
    "wof:placetype":"venue"
},
  "geometry": {"coordinates":[-83.206784,42.459362],"type":"Point"}
}