{
  "type": "Feature",
  "properties": {
    "iso:country":"US",
    "sg:address":"541 Woodside Rd",
    "sg:city":"Royal Oak",
    "sg:classifiers":[
        {
            "category":"Professional",
            "subcategory":"Business Services",
            "type":"Services"
        }
    ],
    "sg:phone":"+1 248 588 0379",
    "sg:postcode":"48073",
    "sg:province":"MI",
    "wof:name":"Thors Sign & Design",
    "wof:placetype":"venue"
},
  "geometry": {"coordinates":[-83.13893400000001,42.526899],"type":"Point"}
}