{
  "type": "Feature",
  "properties": {
    "iso:country":"US",
    "sg:address":"104 N Cedar St",
    "sg:city":"Kalkaska",
    "sg:classifiers":[
        {
            "category":"Personal",
            "subcategory":"Tattoo Parlor",
            "type":"Services"
        }
    ],
    "sg:phone":"+1 231 258 0680",
    "sg:postcode":"49646",
    "sg:province":"MI",
    "sg:tags":[
        "tattooing"
    ],
    "wof:name":"TNT Ink",
    "wof:placetype":"venue"
},
  "geometry": {"coordinates":[-85.174446,44.736008],"type":"Point"}
}