{
  "type": "Feature",
  "properties": {
    "iso:country":"US",
    "sg:address":"4875 28th St SE",
    "sg:city":"Grand Rapids",
    "sg:classifiers":[
        {
            "category":"Restaurant",
            "type":"Food & Drink"
        }
    ],
    "sg:phone":"+1 616 975 0076",
    "sg:postcode":"49512",
    "sg:province":"MI",
    "sg:tags":[
        "mexican"
    ],
    "wof:name":"Rio Bravo Cantina",
    "wof:placetype":"venue"
},
  "geometry": {"coordinates":[-85.547684,42.912642],"type":"Point"}
}