{
  "type": "Feature",
  "properties": {
    "iso:country":"US",
    "sg:address":"1717 Shaffer St",
    "sg:city":"Kalamazoo",
    "sg:classifiers":[
        {
            "category":"Health Services",
            "subcategory":"Doctor",
            "type":"Services"
        }
    ],
    "sg:phone":"+1 269 343 1264",
    "sg:postcode":"49048",
    "sg:province":"MI",
    "sg:tags":[
        "medical",
        "group"
    ],
    "wof:name":"Paragon Health PC",
    "wof:placetype":"venue"
},
  "geometry": {"coordinates":[-85.558323,42.306228],"type":"Point"}
}