{
  "type": "Feature",
  "properties": {
    "iso:country":"US",
    "sg:address":"23444 Elmira St",
    "sg:city":"St Clair Shores",
    "sg:classifiers":[
        {
            "category":"Wholesale",
            "subcategory":"Electrical",
            "type":"Manufacturing & Wholesale Goods"
        }
    ],
    "sg:phone":"+1 586 293 3099",
    "sg:postcode":"48082",
    "sg:province":"MI",
    "sg:tags":[
        "alarm",
        "burglar",
        "system"
    ],
    "wof:name":"Hoffman Security Systems Inc",
    "wof:placetype":"venue"
},
  "geometry": {"coordinates":[-82.87272299999999,42.538312],"type":"Point"}
}