{
  "type": "Feature",
  "properties": {
    "iso:country":"US",
    "sg:address":"1900 W Houghton Lake Dr",
    "sg:city":"Houghton Lake",
    "sg:classifiers":[
        {
            "category":"Insurance",
            "subcategory":"Insurance Agent",
            "type":"Services"
        }
    ],
    "sg:phone":"+1 989 366 8500",
    "sg:postcode":"48629",
    "sg:province":"MI",
    "sg:tags":[
        "agency"
    ],
    "wof:name":"Douglas Williams & Associates",
    "wof:placetype":"venue"
},
  "geometry": {"coordinates":[-84.77063800000001,44.326701],"type":"Point"}
}