{
  "type": "Feature",
  "properties": {
    "iso:country":"US",
    "sg:address":"12261 Farr Rd",
    "sg:city":"Ravenna",
    "sg:classifiers":[
        {
            "category":"Manufacturing",
            "subcategory":"Rubber & Plastics",
            "type":"Manufacturing & Wholesale Goods"
        }
    ],
    "sg:phone":"+1 231 853 6288",
    "sg:postcode":"49451",
    "sg:province":"MI",
    "wof:name":"Reliable Mold & Engineering",
    "wof:placetype":"venue"
},
  "geometry": {"coordinates":[-85.94275500000001,43.140448],"type":"Point"}
}