{
  "type": "Feature",
  "properties": {
    "iso:country":"US",
    "sg:address":"2768 Dormax St SW",
    "sg:city":"Wyoming",
    "sg:classifiers":[
        {
            "category":"Wholesale",
            "subcategory":"Metals & Minerals",
            "type":"Manufacturing & Wholesale Goods"
        }
    ],
    "sg:phone":"+1 616 531 4000",
    "sg:postcode":"49519",
    "sg:province":"MI",
    "sg:tags":[
        "steel",
        "warehouse"
    ],
    "sg:website":"www.contractorssteel.com",
    "wof:name":"Contractors Steel Co",
    "wof:placetype":"venue"
},
  "geometry": {"coordinates":[-85.734583,42.91144],"type":"Point"}
}