{
  "type": "Feature",
  "properties": {
    "iso:country":"US",
    "sg:address":"193 Campbell Ln",
    "sg:city":"Saginaw",
    "sg:classifiers":[
        {
            "category":"Banks & Credit Unions",
            "subcategory":"Bank",
            "type":"Services"
        }
    ],
    "sg:phone":"+1 989 781 1430",
    "sg:postcode":"48609",
    "sg:province":"MI",
    "sg:tags":[
        "state"
    ],
    "wof:name":"First Area Credit UNION",
    "wof:placetype":"venue"
},
  "geometry": {"coordinates":[-84.066715,43.417286],"type":"Point"}
}