{
  "type": "Feature",
  "properties": {
    "iso:country":"US",
    "sg:address":"30181 Mullane Dr",
    "sg:city":"Farmington",
    "sg:classifiers":[
        {
            "category":"Professional",
            "subcategory":"Management & Consulting",
            "type":"Services"
        }
    ],
    "sg:phone":"+1 248 538 4220",
    "sg:postcode":"48334",
    "sg:province":"MI",
    "wof:name":"Michigan Pension & Fincl Inc",
    "wof:placetype":"venue"
},
  "geometry": {"coordinates":[-83.366157,42.516303],"type":"Point"}
}