{
  "type": "Feature",
  "properties": {
    "iso:country":"US",
    "sg:address":"9224 Cherry Ave",
    "sg:city":"Rapid City",
    "sg:classifiers":[
        {
            "category":"Travel",
            "subcategory":"Hotels & Motels",
            "type":"Entertainment"
        }
    ],
    "sg:phone":"+1 231 264 8947",
    "sg:postcode":"49676",
    "sg:province":"MI",
    "sg:tags":[
        "operation"
    ],
    "wof:name":"Wiseacres Bed & Breakfast",
    "wof:placetype":"venue"
},
  "geometry": {"coordinates":[-85.350086,44.901225],"type":"Point"}
}