{
  "type": "Feature",
  "properties": {
    "iso:country":"US",
    "sg:address":"30155 Pleasant Trl",
    "sg:city":"Southfield",
    "sg:classifiers":[
        {
            "category":"Real Estate",
            "subcategory":"Real Estate Agent",
            "type":"Services"
        }
    ],
    "sg:phone":"+1 248 647 1771",
    "sg:postcode":"48076",
    "sg:province":"MI",
    "wof:name":"Acorn Realty LLC",
    "wof:placetype":"venue"
},
  "geometry": {"coordinates":[-83.228949,42.512353],"type":"Point"}
}