{
  "type": "Feature",
  "properties": {
    "iso:country":"US",
    "sg:address":"3536 Rainbow Ct",
    "sg:city":"Okemos",
    "sg:classifiers":[
        {
            "category":"Real Estate",
            "subcategory":"Real Estate Agent",
            "type":"Services"
        }
    ],
    "sg:phone":"+1 517 349 3783",
    "sg:postcode":"48864",
    "sg:province":"MI",
    "wof:name":"Roffle Coml Realty Co LLC",
    "wof:placetype":"venue"
},
  "geometry": {"coordinates":[-84.41598,42.684029],"type":"Point"}
}