{
  "type": "Feature",
  "properties": {
    "iso:country":"US",
    "sg:address":"13451 Hall Rd",
    "sg:city":"Shelby Twp",
    "sg:classifiers":[
        {
            "category":"Shopping",
            "subcategory":"Clothing, Apparel, & Fashions",
            "type":"Retail Goods"
        }
    ],
    "sg:phone":"+1 586 731 2171",
    "sg:postcode":"48315",
    "sg:province":"MI",
    "sg:tags":[
        "furnishing"
    ],
    "wof:name":"Casual Male Big & Tall",
    "wof:placetype":"venue"
},
  "geometry": {"coordinates":[-82.994095,42.62746],"type":"Point"}
}