{
  "type": "Feature",
  "properties": {
    "iso:country":"US",
    "sg:address":"100 S Waverly Rd",
    "sg:city":"Holland",
    "sg:classifiers":[
        {
            "category":"Wholesale",
            "subcategory":"Office Equipment",
            "type":"Manufacturing & Wholesale Goods"
        },
        {
            "category":"Shopping",
            "type":"Retail Goods"
        }
    ],
    "sg:phone":"+1 616 394 4610",
    "sg:postcode":"49423",
    "sg:province":"MI",
    "sg:tags":[
        "machine",
        "duplicating",
        "merchandise",
        "copying"
    ],
    "wof:name":"Commercial Equipment Company",
    "wof:placetype":"venue"
},
  "geometry": {"coordinates":[-86.07782899999999,42.795182],"type":"Point"}
}