{
  "type": "Feature",
  "properties": {
    "iso:country":"US",
    "sg:address":"5677 Number 7 Rd",
    "sg:city":"Menominee",
    "sg:classifiers":[
        {
            "category":"Building & Trades",
            "subcategory":"Plumbing",
            "type":"Services"
        }
    ],
    "sg:phone":"+1 906 863 7306",
    "sg:postcode":"49858",
    "sg:province":"MI",
    "sg:tags":[
        "sheet",
        "work",
        "metal",
        "contractor"
    ],
    "wof:name":"Great Lakes Sheet Metal Inc",
    "wof:placetype":"venue"
},
  "geometry": {"coordinates":[-87.603165,45.21688],"type":"Point"}
}