{
  "type": "Feature",
  "properties": {
    "iso:country":"US",
    "sg:address":"1849 Columbia Rd",
    "sg:city":"Berkley",
    "sg:classifiers":[
        {
            "category":"Communications",
            "subcategory":"Film & Video Production",
            "type":"Services"
        }
    ],
    "sg:phone":"+1 248 414 9542",
    "sg:postcode":"48072",
    "sg:province":"MI",
    "sg:tags":[
        "taping"
    ],
    "wof:name":"North Forty Two Media",
    "wof:placetype":"venue"
},
  "geometry": {"coordinates":[-83.17809099999999,42.490405],"type":"Point"}
}