{
  "type": "Feature",
  "properties": {
    "iso:country":"US",
    "sg:address":"41670 Ford Rd",
    "sg:city":"Canton",
    "sg:classifiers":[
        {
            "category":"Restaurant",
            "type":"Food & Drink"
        }
    ],
    "sg:phone":"+1 734 981 4090",
    "sg:postcode":"48187",
    "sg:province":"MI",
    "wof:name":"Kentucky Fried Chicken",
    "wof:placetype":"venue"
},
  "geometry": {"coordinates":[-83.451401,42.323002],"type":"Point"}
}