{
  "type": "Feature",
  "properties": {
    "iso:country":"US",
    "sg:address":"34965 Wadsworth St",
    "sg:city":"Livonia",
    "sg:classifiers":[
        {
            "category":"Professional",
            "subcategory":"Business Services",
            "type":"Services"
        }
    ],
    "sg:phone":"+1 734 261 2535",
    "sg:postcode":"48150",
    "sg:province":"MI",
    "wof:name":"J & M Enterprises",
    "wof:placetype":"venue"
},
  "geometry": {"coordinates":[-83.385766,42.370764],"type":"Point"}
}