{
  "type": "Feature",
  "properties": {
    "iso:country":"US",
    "sg:address":"1001 Industrial Blvd",
    "sg:city":"Albion",
    "sg:classifiers":[
        {
            "category":"Manufacturing",
            "subcategory":"Tools & Machinery",
            "type":"Manufacturing & Wholesale Goods"
        }
    ],
    "sg:phone":"+1 517 629 9135",
    "sg:postcode":"49224",
    "sg:province":"MI",
    "sg:tags":[
        "machine",
        "shop"
    ],
    "sg:website":"www.albionmachine.com",
    "wof:name":"Albion Machine & Tool Co",
    "wof:placetype":"venue"
},
  "geometry": {"coordinates":[-84.77584299999999,42.2543],"type":"Point"}
}