{
  "type": "Feature",
  "properties": {
    "iso:country":"US",
    "sg:address":"90 W Garfield Ave",
    "sg:city":"Coldwater",
    "sg:classifiers":[
        {
            "category":"Retail",
            "subcategory":"Repair Shop",
            "type":"Services"
        }
    ],
    "sg:phone":"+1 517 278 9513",
    "sg:postcode":"49036",
    "sg:province":"MI",
    "wof:name":"Heinemann Taxidermy & Tannery",
    "wof:placetype":"venue"
},
  "geometry": {"coordinates":[-85.009061,41.927344],"type":"Point"}
}