{
  "type": "Feature",
  "properties": {
    "iso:country":"US",
    "sg:address":"37257 Mound Rd",
    "sg:city":"Sterling Heights",
    "sg:classifiers":[
        {
            "category":"Banks & Credit Unions",
            "subcategory":"Bank",
            "type":"Services"
        }
    ],
    "sg:phone":"+1 586 979 9560",
    "sg:postcode":"48310",
    "sg:province":"MI",
    "sg:tags":[
        "mortgage",
        "loan",
        "broker",
        "real estate"
    ],
    "wof:name":"Optimal Mortgage",
    "wof:placetype":"venue"
},
  "geometry": {"coordinates":[-83.04969800000001,42.567001],"type":"Point"}
}