{
  "type": "Feature",
  "properties": {
    "iso:country":"US",
    "sg:address":"7704 N Riverview Dr",
    "sg:city":"Kalamazoo",
    "sg:classifiers":[
        {
            "category":"Building & Trades",
            "subcategory":"Construction",
            "type":"Services"
        }
    ],
    "sg:phone":"+1 269 276 9950",
    "sg:postcode":"49004",
    "sg:province":"MI",
    "sg:tags":[
        "home",
        "builder"
    ],
    "wof:name":"Born To Be Homes",
    "wof:placetype":"venue"
},
  "geometry": {"coordinates":[-85.55132399999999,42.372131],"type":"Point"}
}