{
  "type": "Feature",
  "properties": {
    "iso:country":"US",
    "sg:address":"26 Wood Ave",
    "sg:city":"Quincy",
    "sg:classifiers":[
        {
            "category":"Building & Trades",
            "subcategory":"Plumbing",
            "type":"Services"
        }
    ],
    "sg:phone":"+1 517 639 4505",
    "sg:postcode":"49082",
    "sg:province":"MI",
    "sg:tags":[
        "heating",
        "contractor"
    ],
    "wof:name":"Kohler Heating & Air Cond",
    "wof:placetype":"venue"
},
  "geometry": {"coordinates":[-84.882818,41.94073],"type":"Point"}
}