{
  "type": "Feature",
  "properties": {
    "iso:country":"US",
    "sg:address":"7577 US Hwy 12",
    "sg:city":"Onsted",
    "sg:classifiers":[
        {
            "category":"Restaurant",
            "type":"Food & Drink"
        }
    ],
    "sg:phone":"+1 517 467 4950",
    "sg:postcode":"49265",
    "sg:province":"MI",
    "sg:tags":[
        "shop",
        "coffee"
    ],
    "wof:name":"Bearclaw Coffee",
    "wof:placetype":"venue"
},
  "geometry": {"coordinates":[-84.13958700000001,42.056503],"type":"Point"}
}