{
  "type": "Feature",
  "properties": {
    "iso:country":"US",
    "sg:address":"24126 Michigan Ave",
    "sg:city":"Dearborn",
    "sg:classifiers":[
        {
            "category":"Retail",
            "subcategory":"Auto Repair",
            "type":"Services"
        }
    ],
    "sg:phone":"+1 313 278 7820",
    "sg:postcode":"48124",
    "sg:province":"MI",
    "sg:tags":[
        "automotive"
    ],
    "wof:name":"Dearborn Quick Lube Center",
    "wof:placetype":"venue"
},
  "geometry": {"coordinates":[-83.271812,42.29989],"type":"Point"}
}