{
  "type": "Feature",
  "properties": {
    "iso:country":"US",
    "sg:address":"22720 S Woodward Ave",
    "sg:city":"Ferndale",
    "sg:classifiers":[
        {
            "category":"Professional",
            "subcategory":"Lawyer & Legal Services",
            "type":"Services"
        }
    ],
    "sg:phone":"+1 248 399 0845",
    "sg:postcode":"48220",
    "sg:province":"MI",
    "sg:tags":[
        "attorney"
    ],
    "wof:name":"T Dean Warren",
    "wof:placetype":"venue"
},
  "geometry": {"coordinates":[-83.13383899999999,42.459951],"type":"Point"}
}