{
  "type": "Feature",
  "properties": {
    "iso:country":"US",
    "sg:address":"479 E Erie Rd",
    "sg:city":"Temperance",
    "sg:classifiers":[
        {
            "category":"Building & Trades",
            "subcategory":"Construction",
            "type":"Services"
        }
    ],
    "sg:phone":"+1 734 847 1127",
    "sg:postcode":"48182",
    "sg:province":"MI",
    "sg:tags":[
        "house"
    ],
    "wof:name":"Garno Custom Homes",
    "wof:placetype":"venue"
},
  "geometry": {"coordinates":[-83.536024,41.794032],"type":"Point"}
}