{
  "type": "Feature",
  "properties": {
    "iso:country":"US",
    "sg:address":"1482 Roat Ct",
    "sg:city":"Burton",
    "sg:classifiers":[
        {
            "category":"Professional",
            "subcategory":"Business Services",
            "type":"Services"
        }
    ],
    "sg:phone":"+1 810 743 6838",
    "sg:postcode":"48509",
    "sg:province":"MI",
    "wof:name":"Group S Contract Solutions",
    "wof:placetype":"venue"
},
  "geometry": {"coordinates":[-83.612483,43.0052],"type":"Point"}
}