{
  "type": "Feature",
  "properties": {
    "iso:country":"US",
    "sg:address":"10351 Bishop Rd",
    "sg:city":"Saint Charles",
    "sg:phone":"+1 989 770 4284",
    "sg:postcode":"48655",
    "sg:province":"MI",
    "sg:tags":[
        "farm",
        "beet"
    ],
    "wof:name":"Kevin Brabant",
    "wof:placetype":"venue"
},
  "geometry": {"coordinates":[-84.031926,43.272961],"type":"Point"}
}