{
  "type": "Feature",
  "properties": {
    "iso:country":"US",
    "sg:address":"220 W M 48",
    "sg:city":"Pickford",
    "sg:classifiers":[
        {
            "category":"Freight",
            "type":"Transportation"
        }
    ],
    "sg:phone":"+1 906 647 3595",
    "sg:postcode":"49774",
    "sg:province":"MI",
    "sg:tags":[
        "operator",
        "local",
        "trucking"
    ],
    "wof:name":"Halsey Trucking",
    "wof:placetype":"venue"
},
  "geometry": {"coordinates":[-84.36685199999999,46.186937],"type":"Point"}
}