{
  "type": "Feature",
  "properties": {
    "iso:country":"US",
    "sg:address":"11096 S Cedar Rd",
    "sg:city":"Cedar",
    "sg:classifiers":[
        {
            "category":"Building & Trades",
            "subcategory":"Construction",
            "type":"Services"
        }
    ],
    "sg:phone":"+1 231 228 5117",
    "sg:postcode":"49621",
    "sg:province":"MI",
    "sg:tags":[
        "contractor"
    ],
    "wof:name":"Sheffer Dan Construction",
    "wof:placetype":"venue"
},
  "geometry": {"coordinates":[-85.790802,44.815102],"type":"Point"}
}