{
  "type": "Feature",
  "properties": {
    "iso:country":"US",
    "sg:address":"43 E 9 Mile Rd",
    "sg:city":"Hazel Park",
    "sg:classifiers":[
        {
            "category":"Government",
            "subcategory":"Court House",
            "type":"Public Place"
        }
    ],
    "sg:phone":"+1 248 547 3034",
    "sg:postcode":"48030",
    "sg:province":"MI",
    "wof:name":"Oakland County Dst Court/43b",
    "wof:placetype":"venue"
},
  "geometry": {"coordinates":[-83.102986,42.461502],"type":"Point"}
}