{
  "type": "Feature",
  "properties": {
    "iso:country":"US",
    "sg:address":"6363 56th Ave",
    "sg:city":"Hudsonville",
    "sg:classifiers":[
        {
            "category":"Wholesale",
            "subcategory":"Meat",
            "type":"Manufacturing & Wholesale Goods"
        }
    ],
    "sg:phone":"+1 616 669 6140",
    "sg:postcode":"49426",
    "sg:province":"MI",
    "wof:name":"Tolman's Wholesale Meats",
    "wof:placetype":"venue"
},
  "geometry": {"coordinates":[-85.92100499999999,42.871468],"type":"Point"}
}