{
  "type": "Feature",
  "properties": {
    "iso:country":"US",
    "sg:address":"5221 Dania St",
    "sg:city":"Flint",
    "sg:classifiers":[
        {
            "category":"Social Services",
            "subcategory":"Child Care",
            "type":"Services"
        }
    ],
    "sg:phone":"+1 810 732 7019",
    "sg:postcode":"48532",
    "sg:province":"MI",
    "sg:tags":[
        "day",
        "provider"
    ],
    "wof:name":"Sherry Beary Daycare",
    "wof:placetype":"venue"
},
  "geometry": {"coordinates":[-83.78170799999999,42.997824],"type":"Point"}
}