{
  "type": "Feature",
  "properties": {
    "iso:country":"US",
    "sg:address":"5300 S Pennsylvania Ave",
    "sg:city":"Lansing",
    "sg:classifiers":[
        {
            "category":"Home & Garden",
            "subcategory":"Carpets & Floor Coverings",
            "type":"Retail Goods"
        }
    ],
    "sg:phone":"+1 517 887 8720",
    "sg:postcode":"48911",
    "sg:province":"MI",
    "sg:tags":[
        "material"
    ],
    "wof:name":"Rycus Floor Covering",
    "wof:placetype":"venue"
},
  "geometry": {"coordinates":[-84.53819,42.680012],"type":"Point"}
}