{
  "type": "Feature",
  "properties": {
    "iso:country":"US",
    "sg:address":"3469 Pierson Pl",
    "sg:city":"Flushing",
    "sg:classifiers":[
        {
            "category":"Building & Trades",
            "subcategory":"Construction",
            "type":"Services"
        }
    ],
    "sg:phone":"+1 810 687 5134",
    "sg:postcode":"48433",
    "sg:province":"MI",
    "sg:tags":[
        "house",
        "contractor"
    ],
    "wof:name":"Rinks Construction Co",
    "wof:placetype":"venue"
},
  "geometry": {"coordinates":[-83.783784,43.05943],"type":"Point"}
}