{
  "type": "Feature",
  "properties": {
    "iso:country":"US",
    "sg:address":"812 S Long Lake Blvd",
    "sg:city":"Lake Orion",
    "sg:classifiers":[
        {
            "category":"Building & Trades",
            "subcategory":"Construction",
            "type":"Services"
        }
    ],
    "sg:phone":"+1 248 693 6333",
    "sg:postcode":"48362",
    "sg:province":"MI",
    "sg:tags":[
        "painter"
    ],
    "wof:name":"Giampa Painting & Drywall",
    "wof:placetype":"venue"
},
  "geometry": {"coordinates":[-83.22504000000001,42.789113],"type":"Point"}
}