{
  "type": "Feature",
  "properties": {
    "iso:country":"US",
    "sg:address":"11340 Toles Rd",
    "sg:city":"Eaton Rapids",
    "sg:classifiers":[
        {
            "category":"Building & Trades",
            "subcategory":"Construction",
            "type":"Services"
        }
    ],
    "sg:phone":"+1 517 663 4688",
    "sg:postcode":"48827",
    "sg:province":"MI",
    "sg:tags":[
        "excavating",
        "contractor"
    ],
    "wof:name":"Mark Burley Excavating",
    "wof:placetype":"venue"
},
  "geometry": {"coordinates":[-84.617071,42.538397],"type":"Point"}
}