{
  "type": "Feature",
  "properties": {
    "iso:country":"US",
    "sg:address":"209 S Grove St",
    "sg:city":"Ypsilanti",
    "sg:classifiers":[
        {
            "category":"Shopping",
            "subcategory":"Computers & Home Electronics",
            "type":"Retail Goods"
        }
    ],
    "sg:phone":"+1 734 481 9098",
    "sg:postcode":"48198",
    "sg:province":"MI",
    "wof:name":"Computers Priced Right",
    "wof:placetype":"venue"
},
  "geometry": {"coordinates":[-83.60387,42.237308],"type":"Point"}
}