{
  "type": "Feature",
  "properties": {
    "iso:country":"US",
    "sg:address":"21736 Sunrise Blvd",
    "sg:city":"Novi",
    "sg:classifiers":[
        {
            "category":"Banks & Credit Unions",
            "subcategory":"Bank",
            "type":"Services"
        }
    ],
    "sg:phone":"+1 248 344 1529",
    "sg:postcode":"48375",
    "sg:province":"MI",
    "sg:tags":[
        "mortgage"
    ],
    "wof:name":"Rowe Mortgage Co",
    "wof:placetype":"venue"
},
  "geometry": {"coordinates":[-83.443986,42.447055],"type":"Point"}
}