{
  "type": "Feature",
  "properties": {
    "iso:country":"US",
    "sg:address":"21999 Farmington Rd Ste 900",
    "sg:city":"Farmington",
    "sg:classifiers":[
        {
            "category":"Personal",
            "subcategory":"Hair Removal",
            "type":"Services"
        }
    ],
    "sg:phone":"+1 248 474 9100",
    "sg:postcode":"48336",
    "sg:province":"MI",
    "wof:name":"Alcove the",
    "wof:placetype":"venue"
},
  "geometry": {"coordinates":[-83.37607300000001,42.453846],"type":"Point"}
}