{
  "type": "Feature",
  "properties": {
    "iso:country":"US",
    "sg:address":"304 Tawas St",
    "sg:city":"East Tawas",
    "sg:classifiers":[
        {
            "category":"Shopping",
            "subcategory":"Florist",
            "type":"Retail Goods"
        }
    ],
    "sg:phone":"+1 989 362 3041",
    "sg:postcode":"48730",
    "sg:province":"MI",
    "wof:name":"Moehring's Greenhouse",
    "wof:placetype":"venue"
},
  "geometry": {"coordinates":[-83.488877,44.283397],"type":"Point"}
}