{
  "type": "Feature",
  "properties": {
    "iso:country":"US",
    "sg:address":"1045 Grant St",
    "sg:city":"Fenton",
    "sg:classifiers":[
        {
            "category":"Freight",
            "type":"Transportation"
        }
    ],
    "sg:phone":"+1 810 629 4183",
    "sg:postcode":"48430",
    "sg:province":"MI",
    "sg:tags":[
        "commercial",
        "storage"
    ],
    "wof:name":"Brewer Storage",
    "wof:placetype":"venue"
},
  "geometry": {"coordinates":[-83.722928,42.791946],"type":"Point"}
}