{
  "type": "Feature",
  "properties": {
    "iso:country":"US",
    "sg:address":"6638 Stadium Dr",
    "sg:city":"Kalamazoo",
    "sg:classifiers":[
        {
            "category":"Personal",
            "subcategory":"Beauty Salon",
            "type":"Services"
        }
    ],
    "sg:phone":"+1 269 372 2232",
    "sg:postcode":"49009",
    "sg:province":"MI",
    "wof:name":"Leocadia A Full Svc Salon",
    "wof:placetype":"venue"
},
  "geometry": {"coordinates":[-85.68328099999999,42.258093],"type":"Point"}
}