{
  "type": "Feature",
  "properties": {
    "iso:country":"US",
    "sg:address":"519 W Erie St",
    "sg:city":"Albion",
    "sg:classifiers":[
        {
            "category":"Professional",
            "subcategory":"Management & Consulting",
            "type":"Services"
        }
    ],
    "sg:phone":"+1 517 629 3743",
    "sg:postcode":"49224",
    "sg:province":"MI",
    "sg:tags":[
        "retail",
        "direct",
        "sales"
    ],
    "wof:name":"Special Events By Tee",
    "wof:placetype":"venue"
},
  "geometry": {"coordinates":[-84.760453,42.242904],"type":"Point"}
}