{
  "type": "Feature",
  "properties": {
    "iso:country":"US",
    "sg:address":"3339 Upton Dr",
    "sg:city":"Troy",
    "sg:classifiers":[
        {
            "category":"Professional",
            "subcategory":"Management & Consulting",
            "type":"Services"
        }
    ],
    "sg:phone":"+1 248 709 0996",
    "sg:postcode":"48084",
    "sg:province":"MI",
    "wof:name":"Emergingimagellc",
    "wof:placetype":"venue"
},
  "geometry": {"coordinates":[-83.205173,42.565239],"type":"Point"}
}