{
  "type": "Feature",
  "properties": {
    "iso:country":"US",
    "sg:address":"1231 Minnesota St",
    "sg:city":"Hancock",
    "sg:classifiers":[
        {
            "category":"Real Estate",
            "subcategory":"Real Estate Operator",
            "type":"Services"
        }
    ],
    "sg:phone":"+1 906 482 0606",
    "sg:postcode":"49930",
    "sg:province":"MI",
    "sg:tags":[
        "building",
        "nonresidential"
    ],
    "wof:name":"Scholie Properties",
    "wof:placetype":"venue"
},
  "geometry": {"coordinates":[-88.604077,47.128766],"type":"Point"}
}