{
  "type": "Feature",
  "properties": {
    "iso:country":"US",
    "sg:address":"611 N Burdick St",
    "sg:city":"Kalamazoo",
    "sg:classifiers":[
        {
            "category":"Banks & Credit Unions",
            "subcategory":"Bank",
            "type":"Services"
        }
    ],
    "sg:phone":"+1 269 342 2007",
    "sg:postcode":"49007",
    "sg:province":"MI",
    "sg:tags":[
        "loan",
        "real estate"
    ],
    "wof:name":"Savannah Mortgage Corp",
    "wof:placetype":"venue"
},
  "geometry": {"coordinates":[-85.58348700000001,42.29695],"type":"Point"}
}