{
  "type": "Feature",
  "properties": {
    "iso:country":"US",
    "sg:address":"14705 Tireman Ave",
    "sg:city":"Dearborn",
    "sg:classifiers":[
        {
            "category":"Food & Beverages",
            "subcategory":"Meat & Fish",
            "type":"Retail Goods"
        }
    ],
    "sg:phone":"+1 313 584 7553",
    "sg:postcode":"48126",
    "sg:province":"MI",
    "sg:tags":[
        "seafood",
        "market"
    ],
    "wof:name":"Rizk Fish Market",
    "wof:placetype":"venue"
},
  "geometry": {"coordinates":[-83.188301,42.350899],"type":"Point"}
}