{
  "type": "Feature",
  "properties": {
    "iso:country":"US",
    "sg:address":"10085 Borgman Ave",
    "sg:city":"Huntington Woods",
    "sg:classifiers":[
        {
            "category":"Shopping",
            "subcategory":"Jewelry",
            "type":"Retail Goods"
        }
    ],
    "sg:phone":"+1 248 541 5515",
    "sg:postcode":"48070",
    "sg:province":"MI",
    "sg:tags":[
        "designer"
    ],
    "wof:name":"Susan Fox Jewelry Design",
    "wof:placetype":"venue"
},
  "geometry": {"coordinates":[-83.166147,42.486604],"type":"Point"}
}