{
  "type": "Feature",
  "properties": {
    "iso:country":"US",
    "sg:address":"3860 Rochester Rd",
    "sg:city":"Troy",
    "sg:classifiers":[
        {
            "category":"Education",
            "subcategory":"Vocational School",
            "type":"Public Place"
        }
    ],
    "sg:phone":"+1 248 740 9393",
    "sg:postcode":"48083",
    "sg:province":"MI",
    "sg:tags":[
        "technical",
        "trade"
    ],
    "wof:name":"Computer Technology Institute",
    "wof:placetype":"venue"
},
  "geometry": {"coordinates":[-83.12826099999999,42.576415],"type":"Point"}
}