{
  "type": "Feature",
  "properties": {
    "iso:country":"US",
    "sg:address":"218 W Genesee St",
    "sg:city":"Frankenmuth",
    "sg:classifiers":[
        {
            "category":"Government",
            "subcategory":"Office",
            "type":"Public Place"
        }
    ],
    "sg:phone":"+1 989 652 6741",
    "sg:postcode":"48734",
    "sg:province":"MI",
    "sg:tags":[
        "village"
    ],
    "wof:name":"Frankenmuth Twp Office",
    "wof:placetype":"venue"
},
  "geometry": {"coordinates":[-83.741145,43.335906],"type":"Point"}
}