{
  "type": "Feature",
  "properties": {
    "iso:country":"US",
    "sg:address":"12380 S Kinross Rd",
    "sg:city":"Brimley",
    "sg:classifiers":[
        {
            "category":"Professional",
            "subcategory":"Management & Consulting",
            "type":"Services"
        }
    ],
    "sg:phone":"+1 906 248 2571",
    "sg:postcode":"49724",
    "sg:province":"MI",
    "sg:tags":[
        "fuel"
    ],
    "wof:name":"JKT Management",
    "wof:placetype":"venue"
},
  "geometry": {"coordinates":[-84.509754,46.326533],"type":"Point"}
}