{
  "type": "Feature",
  "properties": {
    "iso:country":"US",
    "sg:address":"1201 Wohlert St",
    "sg:city":"Angola",
    "sg:classifiers":[
        {
            "category":"Utilities",
            "subcategory":"Refuse",
            "type":"Services"
        }
    ],
    "sg:phone":"+1 260 665 6317",
    "sg:postcode":"46703",
    "sg:province":"MI",
    "sg:tags":[
        "garbage",
        "collection"
    ],
    "wof:name":"Sunrise Disposal Inc",
    "wof:placetype":"venue"
},
  "geometry": {"coordinates":[-85.00442,41.65602],"type":"Point"}
}