{
  "type": "Feature",
  "properties": {
    "iso:country":"US",
    "sg:address":"31996 Woodward Ave",
    "sg:city":"Royal Oak",
    "sg:classifiers":[
        {
            "category":"Personal",
            "subcategory":"Beauty Salon",
            "type":"Services"
        }
    ],
    "sg:phone":"+1 248 549 5900",
    "sg:postcode":"48073",
    "sg:province":"MI",
    "wof:name":"Cristini Salon",
    "wof:placetype":"venue"
},
  "geometry": {"coordinates":[-83.192078,42.524004],"type":"Point"}
}