{
  "type": "Feature",
  "properties": {
    "iso:country":"US",
    "sg:address":"77 Cambridge Ct",
    "sg:city":"Chelsea",
    "sg:classifiers":[
        {
            "category":"Retail",
            "subcategory":"Repair Shop",
            "type":"Services"
        }
    ],
    "sg:phone":"+1 734 433 2640",
    "sg:postcode":"48118",
    "sg:province":"MI",
    "wof:name":"Daves Camera Repair Inc",
    "wof:placetype":"venue"
},
  "geometry": {"coordinates":[-84.00292399999999,42.303005],"type":"Point"}
}