{
  "type": "Feature",
  "properties": {
    "iso:country":"US",
    "sg:address":"38300 Van Dyke Ave Ste 101",
    "sg:city":"Sterling Heights",
    "sg:classifiers":[
        {
            "category":"Health Services",
            "subcategory":"Health Practitioner",
            "type":"Services"
        }
    ],
    "sg:phone":"+1 586 977 5700",
    "sg:postcode":"48312",
    "sg:province":"MI",
    "sg:tags":[
        "therapy",
        "physical"
    ],
    "sg:website":"www.globalpt.org",
    "wof:name":"Global Physical Therapy",
    "wof:placetype":"venue"
},
  "geometry": {"coordinates":[-83.0299,42.575001],"type":"Point"}
}