{
  "type": "Feature",
  "properties": {
    "iso:country":"US",
    "sg:address":"2339 Delwood Dr",
    "sg:city":"Clio",
    "sg:classifiers":[
        {
            "category":"Wholesale",
            "subcategory":"Durable Goods & Equipment",
            "type":"Manufacturing & Wholesale Goods"
        }
    ],
    "sg:phone":"+1 810 564 9390",
    "sg:postcode":"48420",
    "sg:province":"MI",
    "sg:tags":[
        "importer"
    ],
    "wof:name":"Euro Trading Group",
    "wof:placetype":"venue"
},
  "geometry": {"coordinates":[-83.66530899999999,43.197833],"type":"Point"}
}