{
  "type": "Feature",
  "properties": {
    "iso:country":"US",
    "sg:address":"272 Brunson Ave",
    "sg:city":"Benton Harbor",
    "sg:classifiers":[
        {
            "category":"Organizations",
            "subcategory":"Community Association",
            "type":"Services"
        }
    ],
    "sg:phone":"+1 269 927 6011",
    "sg:postcode":"49022",
    "sg:province":"MI",
    "wof:name":"Individual Family & Community",
    "wof:placetype":"venue"
},
  "geometry": {"coordinates":[-86.451609,42.115096],"type":"Point"}
}