{
  "type": "Feature",
  "properties": {
    "iso:country":"US",
    "sg:address":"1129 Five Lakes Rd",
    "sg:city":"Gaylord",
    "sg:classifiers":[
        {
            "category":"Retail",
            "subcategory":"Auto Repair",
            "type":"Services"
        }
    ],
    "sg:phone":"+1 989 731 9646",
    "sg:postcode":"49735",
    "sg:province":"MI",
    "sg:tags":[
        "automotive",
        "general"
    ],
    "wof:name":"Freds Garage Inc",
    "wof:placetype":"venue"
},
  "geometry": {"coordinates":[-84.70434,45.041959],"type":"Point"}
}