{
  "type": "Feature",
  "properties": {
    "iso:country":"US",
    "sg:address":"1222 E M-36",
    "sg:city":"Pinckney",
    "sg:classifiers":[
        {
            "category":"Restaurant",
            "type":"Food & Drink"
        }
    ],
    "sg:menulink":"http://www.allmenus.com/mi/putnam/68871-marcos-pizza/menu/",
    "sg:phone":"+1 734 954 1111",
    "sg:postcode":"48169",
    "sg:province":"MI",
    "sg:tags":[
        "american",
        "pizza"
    ],
    "wof:name":"Marco's Pizza",
    "wof:placetype":"venue"
},
  "geometry": {"coordinates":[-83.931034,42.458169],"type":"Point"}
}