{
  "type": "Feature",
  "properties": {
    "iso:country":"US",
    "sg:address":"32090 John R Rd",
    "sg:city":"Madison Heights",
    "sg:classifiers":[
        {
            "category":"Building & Trades",
            "subcategory":"Construction",
            "type":"Services"
        }
    ],
    "sg:phone":"+1 248 588 6370",
    "sg:postcode":"48071",
    "sg:province":"MI",
    "sg:tags":[
        "bathroom",
        "remodeling"
    ],
    "sg:website":"www.ritewayonline.com",
    "wof:name":"Kitchen & Bath By Rite-Way",
    "wof:placetype":"venue"
},
  "geometry": {"coordinates":[-83.106747,42.52883],"type":"Point"}
}