{
  "type": "Feature",
  "properties": {
    "iso:country":"US",
    "sg:address":"21400 Littlestone Rd",
    "sg:city":"Harper Woods",
    "sg:classifiers":[
        {
            "category":"Health Services",
            "subcategory":"Clinic",
            "type":"Services"
        }
    ],
    "sg:phone":"+1 313 884 1110",
    "sg:postcode":"48225",
    "sg:province":"MI",
    "wof:name":"Pyramid Home Health Care Inc",
    "wof:placetype":"venue"
},
  "geometry": {"coordinates":[-82.916529,42.428566],"type":"Point"}
}