{
  "type": "Feature",
  "properties": {
    "iso:country":"US",
    "sg:address":"1750 Range Rd",
    "sg:city":"Port Huron",
    "sg:classifiers":[
        {
            "category":"Building & Trades",
            "subcategory":"Construction",
            "type":"Services"
        }
    ],
    "sg:phone":"+1 810 982 8290",
    "sg:postcode":"48060",
    "sg:province":"MI",
    "sg:tags":[
        "product",
        "asphalt"
    ],
    "wof:name":"Angelo's Asphalt Materials",
    "wof:placetype":"venue"
},
  "geometry": {"coordinates":[-82.50206300000001,42.957754],"type":"Point"}
}