{
  "type": "Feature",
  "properties": {
    "iso:country":"US",
    "sg:address":"45507 Addington Ln",
    "sg:city":"Novi",
    "sg:classifiers":[
        {
            "category":"Real Estate",
            "subcategory":"Real Estate Operator",
            "type":"Services"
        }
    ],
    "sg:phone":"+1 248 449 8022",
    "sg:postcode":"48374",
    "sg:province":"MI",
    "sg:tags":[
        "building",
        "nonresidential"
    ],
    "wof:name":"Robert J Eliassen & Sons",
    "wof:placetype":"venue"
},
  "geometry": {"coordinates":[-83.497524,42.460479],"type":"Point"}
}