{
  "type": "Feature",
  "properties": {
    "iso:country":"US",
    "sg:address":"130 S Monroe St",
    "sg:city":"Lapeer",
    "sg:classifiers":[
        {
            "category":"Retail",
            "subcategory":"Auto Repair",
            "type":"Services"
        }
    ],
    "sg:phone":"+1 810 664 4047",
    "sg:postcode":"48446",
    "sg:province":"MI",
    "sg:tags":[
        "automotive",
        "wrecker"
    ],
    "wof:name":"Don Mc Kay Towing",
    "wof:placetype":"venue"
},
  "geometry": {"coordinates":[-83.315693,43.049135],"type":"Point"}
}