{
  "type": "Feature",
  "properties": {
    "iso:country":"US",
    "sg:address":"120 Ottawa Ave NW",
    "sg:city":"Grand Rapids",
    "sg:classifiers":[
        {
            "category":"Organizations",
            "subcategory":"Community Association",
            "type":"Services"
        }
    ],
    "sg:phone":"+1 616 222 7620",
    "sg:postcode":"49503",
    "sg:province":"MI",
    "sg:tags":[
        "club",
        "physical",
        "fitness"
    ],
    "wof:name":"Peninsular Club",
    "wof:placetype":"venue"
},
  "geometry": {"coordinates":[-85.67006499999999,42.966104],"type":"Point"}
}