{
  "type": "Feature",
  "properties": {
    "iso:country":"US",
    "sg:address":"6366 Youngman Rd",
    "sg:city":"Greenville",
    "sg:classifiers":[
        {
            "category":"Manufacturing",
            "subcategory":"Lumber",
            "type":"Manufacturing & Wholesale Goods"
        }
    ],
    "sg:phone":"+1 616 754 7498",
    "sg:postcode":"48838",
    "sg:province":"MI",
    "sg:tags":[
        "operation",
        "timber",
        "tract"
    ],
    "wof:name":"William Finkhouse",
    "wof:placetype":"venue"
},
  "geometry": {"coordinates":[-85.28271599999999,43.200423],"type":"Point"}
}