{
  "type": "Feature",
  "properties": {
    "iso:country":"US",
    "sg:address":"5185 E Spicerville Hwy",
    "sg:city":"Eaton Rapids",
    "sg:phone":"+1 517 663 8694",
    "sg:postcode":"48827",
    "sg:province":"MI",
    "sg:tags":[
        "real",
        "wheat",
        "lessor",
        "farm",
        "corn",
        "soybean",
        "property"
    ],
    "wof:name":"Mc Manus Alden",
    "wof:placetype":"venue"
},
  "geometry": {"coordinates":[-84.73603,42.494246],"type":"Point"}
}