{
  "type": "Feature",
  "properties": {
    "iso:country":"US",
    "sg:address":"4198 Tipton Hwy",
    "sg:city":"Adrian",
    "sg:classifiers":[
        {
            "category":"Professional",
            "type":"Services"
        }
    ],
    "sg:phone":"+1 517 266 2989",
    "sg:postcode":"49221",
    "sg:province":"MI",
    "sg:tags":[
        "establishment"
    ],
    "wof:name":"Lenawee Intermediate Ag Ctr",
    "wof:placetype":"venue"
},
  "geometry": {"coordinates":[-84.06523,41.953549],"type":"Point"}
}