{
  "type": "Feature",
  "properties": {
    "iso:country":"US",
    "sg:address":"7101 Lahser Rd",
    "sg:city":"Bloomfield Hills",
    "sg:classifiers":[
        {
            "category":"Education",
            "subcategory":"School",
            "type":"Public Place"
        }
    ],
    "sg:phone":"+1 248 647 2526",
    "sg:postcode":"48301",
    "sg:province":"MI",
    "wof:name":"Brother Rice High School",
    "wof:placetype":"venue"
},
  "geometry": {"coordinates":[-83.26411899999999,42.535687],"type":"Point"}
}