{
  "type": "Feature",
  "properties": {
    "iso:country":"US",
    "sg:address":"1900 Almond Rd",
    "sg:city":"Barton City",
    "sg:classifiers":[
        {
            "category":"Organizations",
            "subcategory":"Community Association",
            "type":"Services"
        }
    ],
    "sg:phone":"+1 517 736 6738",
    "sg:postcode":"48705",
    "sg:province":"MI",
    "wof:name":"Veterans of Foreign Wars",
    "wof:placetype":"venue"
},
  "geometry": {"coordinates":[-83.60650099999999,44.690576],"type":"Point"}
}