{
  "type": "Feature",
  "properties": {
    "iso:country":"US",
    "sg:address":"1001 Cedar Ave",
    "sg:city":"Iron Mountain",
    "sg:classifiers":[
        {
            "category":"Organizations",
            "subcategory":"Community Association",
            "type":"Services"
        }
    ],
    "sg:phone":"+1 906 774 0700",
    "sg:postcode":"49801",
    "sg:province":"MI",
    "sg:tags":[
        "fraternal"
    ],
    "wof:name":"Elks Lodge",
    "wof:placetype":"venue"
},
  "geometry": {"coordinates":[-88.06452899999999,45.813673],"type":"Point"}
}