{
  "type": "Feature",
  "properties": {
    "iso:country":"US",
    "sg:address":"24024 Evergreen Rd",
    "sg:city":"Southfield",
    "sg:classifiers":[
        {
            "category":"Shopping",
            "subcategory":"Musical Instruments",
            "type":"Retail Goods"
        }
    ],
    "sg:phone":"+1 248 350 0469",
    "sg:postcode":"48075",
    "sg:province":"MI",
    "sg:tags":[
        "music",
        "dealer"
    ],
    "wof:name":"Clint's Music",
    "wof:placetype":"venue"
},
  "geometry": {"coordinates":[-83.23992200000001,42.461593],"type":"Point"}
}