{
  "type": "Feature",
  "properties": {
    "iso:country":"US",
    "sg:address":"2314 Monroe St",
    "sg:city":"Dearborn",
    "sg:classifiers":[
        {
            "category":"Real Estate",
            "subcategory":"Real Estate Agent",
            "type":"Services"
        }
    ],
    "sg:phone":"+1 313 357 3800",
    "sg:postcode":"48124",
    "sg:province":"MI",
    "wof:name":"Cass Realty LLC",
    "wof:placetype":"venue"
},
  "geometry": {"coordinates":[-83.247651,42.295503],"type":"Point"}
}