{
  "type": "Feature",
  "properties": {
    "iso:country":"US",
    "sg:address":"300 Monroe Ave NW",
    "sg:city":"Grand Rapids",
    "sg:classifiers":[
        {
            "category":"Government",
            "subcategory":"Office",
            "type":"Public Place"
        }
    ],
    "sg:phone":"+1 616 456 3176",
    "sg:postcode":"49503",
    "sg:province":"MI",
    "sg:tags":[
        "village"
    ],
    "sg:website":"www.ci.grand-rapids.mi.us",
    "wof:name":"Grand Rapids Human Resources",
    "wof:placetype":"venue"
},
  "geometry": {"coordinates":[-85.672175,42.969175],"type":"Point"}
}