{
  "type": "Feature",
  "properties": {
    "iso:country":"US",
    "sg:address":"14 N Washington St",
    "sg:city":"Ypsilanti",
    "sg:classifiers":[
        {
            "category":"Health Services",
            "subcategory":"Hospital",
            "type":"Services"
        }
    ],
    "sg:phone":"+1 734 547 0980",
    "sg:postcode":"48197",
    "sg:province":"MI",
    "sg:tags":[
        "specialty"
    ],
    "wof:name":"Vonschwarz Associates Inc",
    "wof:placetype":"venue"
},
  "geometry": {"coordinates":[-83.61447800000001,42.242095],"type":"Point"}
}