{
  "type": "Feature",
  "properties": {
    "iso:country":"US",
    "sg:address":"27241 Bertrand St",
    "sg:city":"Chesterfield",
    "sg:classifiers":[
        {
            "category":"Building & Trades",
            "subcategory":"Construction",
            "type":"Services"
        }
    ],
    "sg:phone":"+1 586 749 9565",
    "sg:postcode":"48051",
    "sg:province":"MI",
    "sg:tags":[
        "ceiling"
    ],
    "wof:name":"Excel Ceiling",
    "wof:placetype":"venue"
},
  "geometry": {"coordinates":[-82.831703,42.693225],"type":"Point"}
}