{
  "type": "Feature",
  "properties": {
    "iso:country":"US",
    "sg:address":"119 N Church St",
    "sg:city":"Kalamazoo",
    "sg:classifiers":[
        {
            "category":"Professional",
            "subcategory":"Secretarial Services",
            "type":"Services"
        }
    ],
    "sg:phone":"+1 269 343 2200",
    "sg:postcode":"49007",
    "sg:province":"MI",
    "sg:tags":[
        "convention",
        "reporting",
        "court",
        "reporter"
    ],
    "wof:name":"Kal-Reporting",
    "wof:placetype":"venue"
},
  "geometry": {"coordinates":[-85.586158,42.292375],"type":"Point"}
}