{
  "type": "Feature",
  "properties": {
    "iso:country":"US",
    "sg:address":"26092 John R Rd",
    "sg:city":"Madison Heights",
    "sg:classifiers":[
        {
            "category":"Arts & Performance",
            "subcategory":"Arts Center",
            "type":"Entertainment"
        }
    ],
    "sg:phone":"+1 248 544 3340",
    "sg:postcode":"48071",
    "sg:province":"MI",
    "sg:tags":[
        "performing"
    ],
    "wof:name":"Royal Oak Center For Performing Arts",
    "wof:placetype":"venue"
},
  "geometry": {"coordinates":[-83.10502200000001,42.484204],"type":"Point"}
}