{
  "type": "Feature",
  "properties": {
    "iso:country":"US",
    "sg:address":"231 State St",
    "sg:city":"Petoskey",
    "sg:classifiers":[
        {
            "category":"Professional",
            "subcategory":"Computer Services",
            "type":"Services"
        }
    ],
    "sg:phone":"+1 231 347 8866",
    "sg:postcode":"49770",
    "sg:province":"MI",
    "sg:tags":[
        "programming"
    ],
    "sg:website":"www.worthywords.com",
    "wof:name":"HARBOR Software",
    "wof:placetype":"venue"
},
  "geometry": {"coordinates":[-84.958484,45.371966],"type":"Point"}
}