{
  "type": "Feature",
  "properties": {
    "iso:country":"US",
    "sg:address":"3830 Golf Vista Dr",
    "sg:city":"Lapeer",
    "sg:classifiers":[
        {
            "category":"Building & Trades",
            "subcategory":"Construction",
            "type":"Services"
        }
    ],
    "sg:phone":"+1 810 245 2788",
    "sg:postcode":"48446",
    "sg:province":"MI",
    "sg:tags":[
        "plastering",
        "contractor"
    ],
    "wof:name":"Everlast Trust Co",
    "wof:placetype":"venue"
},
  "geometry": {"coordinates":[-83.373982,43.032991],"type":"Point"}
}