{
  "type": "Feature",
  "properties": {
    "iso:country":"US",
    "sg:address":"54 Cherry St",
    "sg:city":"Mount Clemens",
    "sg:classifiers":[
        {
            "category":"Food & Beverages",
            "subcategory":"Chocolate",
            "type":"Retail Goods"
        }
    ],
    "sg:phone":"+1 586 468 1170",
    "sg:postcode":"48043",
    "sg:province":"MI",
    "sg:tags":[
        "shop",
        "chocolatiers"
    ],
    "sg:website":"www.champagnechocolates.com",
    "wof:name":"Champagne Chocolates",
    "wof:placetype":"venue"
},
  "geometry": {"coordinates":[-82.87748999999999,42.59956],"type":"Point"}
}