{
  "type": "Feature",
  "properties": {
    "iso:country":"US",
    "sg:address":"511 Bridge St NW",
    "sg:city":"Grand Rapids",
    "sg:classifiers":[
        {
            "category":"Bars & Pubs",
            "type":"Food & Drink"
        }
    ],
    "sg:phone":"+1 616 451 9638",
    "sg:postcode":"49504",
    "sg:province":"MI",
    "wof:name":"Kale's Korner Bar",
    "wof:placetype":"venue"
},
  "geometry": {"coordinates":[-85.681443,42.970691],"type":"Point"}
}