{
  "type": "Feature",
  "properties": {
    "iso:country":"US",
    "sg:address":"1400 Townsend Dr",
    "sg:city":"Houghton",
    "sg:classifiers":[
        {
            "category":"Sports & Exercise",
            "subcategory":"Golf",
            "type":"Entertainment"
        }
    ],
    "sg:phone":"+1 906 487 2641",
    "sg:postcode":"49931",
    "sg:province":"MI",
    "sg:tags":[
        "course",
        "public"
    ],
    "wof:name":"Michigan Tech University",
    "wof:placetype":"venue"
},
  "geometry": {"coordinates":[-88.53358299999999,47.112463],"type":"Point"}
}