{
  "type": "Feature",
  "properties": {
    "iso:country":"US",
    "sg:address":"161 E Beech St",
    "sg:city":"Harrison",
    "sg:classifiers":[
        {
            "category":"Shopping",
            "subcategory":"Pharmacy",
            "type":"Retail Goods"
        }
    ],
    "sg:phone":"+1 989 539 4380",
    "sg:postcode":"48625",
    "sg:province":"MI",
    "wof:name":"Rite Aid Pharmacy",
    "wof:placetype":"venue"
},
  "geometry": {"coordinates":[-84.80036200000001,44.020711],"type":"Point"}
}