{
  "type": "Feature",
  "properties": {
    "iso:country":"US",
    "sg:address":"7200 State Hwy 140",
    "sg:city":"Eau Claire",
    "sg:classifiers":[
        {
            "category":"Insurance",
            "subcategory":"Insurance Agent",
            "type":"Services"
        }
    ],
    "sg:phone":"+1 269 461 6975",
    "sg:postcode":"49111",
    "sg:province":"MI",
    "wof:name":"Cuthbert Agency Inc",
    "wof:placetype":"venue"
},
  "geometry": {"coordinates":[-86.26381499999999,41.986668],"type":"Point"}
}