{
  "type": "Feature",
  "properties": {
    "iso:country":"US",
    "sg:address":"16901 Mack Ave",
    "sg:city":"Detroit",
    "sg:classifiers":[
        {
            "category":"Autos & Motor Vehicles",
            "subcategory":"Automobile Sales",
            "type":"Retail Goods"
        },
        {
            "category":"Retail",
            "subcategory":"Auto Rental",
            "type":"Services"
        }
    ],
    "sg:phone":"+1 313 567 0250",
    "sg:postcode":"48224",
    "sg:province":"MI",
    "sg:tags":[
        "car"
    ],
    "wof:name":"Bob Maxey Ford",
    "wof:placetype":"venue"
},
  "geometry": {"coordinates":[-82.92469800000001,42.3941],"type":"Point"}
}