{
  "type": "Feature",
  "properties": {
    "iso:country":"US",
    "sg:address":"725 Grand Marais St",
    "sg:city":"Grosse Pointe",
    "sg:classifiers":[
        {
            "category":"Professional",
            "subcategory":"Lawyer & Legal Services",
            "type":"Services"
        }
    ],
    "sg:phone":"+1 313 821 2376",
    "sg:postcode":"48230",
    "sg:province":"MI",
    "wof:name":"Nancy B Loffredo PC",
    "wof:placetype":"venue"
},
  "geometry": {"coordinates":[-82.920349,42.376204],"type":"Point"}
}