{
  "type": "Feature",
  "properties": {
    "iso:country":"US",
    "sg:address":"3828 Davison Rd",
    "sg:city":"Flint",
    "sg:classifiers":[
        {
            "category":"Personal",
            "subcategory":"Barber",
            "type":"Services"
        }
    ],
    "sg:phone":"+1 810 715 4517",
    "sg:postcode":"48506",
    "sg:province":"MI",
    "wof:name":"Kim's Barber Shop",
    "wof:placetype":"venue"
},
  "geometry": {"coordinates":[-83.636703,43.033001],"type":"Point"}
}