{
  "type": "Feature",
  "properties": {
    "iso:country":"US",
    "sg:address":"233 S Stephenson Ave",
    "sg:city":"Iron Mountain",
    "sg:classifiers":[
        {
            "category":"Banks & Credit Unions",
            "subcategory":"Financial Services",
            "type":"Services"
        }
    ],
    "sg:phone":"+1 906 774 2200",
    "sg:postcode":"49801",
    "sg:province":"MI",
    "sg:tags":[
        "company",
        "holding"
    ],
    "wof:name":"Fnb Bancshares Inc",
    "wof:placetype":"venue"
},
  "geometry": {"coordinates":[-88.065164,45.82086],"type":"Point"}
}