{
  "type": "Feature",
  "properties": {
    "iso:country":"US",
    "sg:address":"5016 Rochester Rd",
    "sg:city":"Troy",
    "sg:classifiers":[
        {
            "category":"Personal",
            "subcategory":"Barber",
            "type":"Services"
        }
    ],
    "sg:phone":"+1 248 528 9585",
    "sg:postcode":"48085",
    "sg:province":"MI",
    "sg:tags":[
        "shop"
    ],
    "wof:name":"Jerrys Barber Shop",
    "wof:placetype":"venue"
},
  "geometry": {"coordinates":[-83.129098,42.593852],"type":"Point"}
}