{
  "type": "Feature",
  "properties": {
    "iso:country":"US",
    "sg:address":"3162 Martin Rd",
    "sg:city":"Commerce Twp",
    "sg:classifiers":[
        {
            "category":"Wholesale",
            "subcategory":"Medical Equipment & Supplies",
            "type":"Manufacturing & Wholesale Goods"
        }
    ],
    "sg:phone":"+1 248 926 9500",
    "sg:postcode":"48390",
    "sg:province":"MI",
    "sg:tags":[
        "physician",
        "surgeon"
    ],
    "sg:website":"www.medinuc.com",
    "wof:name":"Medi-Nuclear",
    "wof:placetype":"venue"
},
  "geometry": {"coordinates":[-83.449645,42.568052],"type":"Point"}
}