{
  "type": "Feature",
  "properties": {
    "iso:country":"US",
    "sg:address":"19645 Allen Rd",
    "sg:city":"Melvindale",
    "sg:classifiers":[
        {
            "category":"Autos & Motor Vehicles",
            "subcategory":"Fuel & Gas Station",
            "type":"Retail Goods"
        }
    ],
    "sg:phone":"+1 313 383 8428",
    "sg:postcode":"48122",
    "sg:province":"MI",
    "wof:name":"Clark Service Stations No 618",
    "wof:placetype":"venue"
},
  "geometry": {"coordinates":[-83.1931,42.275101],"type":"Point"}
}