{
  "type": "Feature",
  "properties": {
    "iso:country":"US",
    "sg:address":"792 Cobblestone Dr",
    "sg:city":"Rochester",
    "sg:classifiers":[
        {
            "category":"Building & Trades",
            "subcategory":"Landscaping Services",
            "type":"Services"
        }
    ],
    "sg:phone":"+1 248 651 1774",
    "sg:postcode":"48309",
    "sg:province":"MI",
    "wof:name":"Henrys Lawn Care Inc",
    "wof:placetype":"venue"
},
  "geometry": {"coordinates":[-83.16780900000001,42.690963],"type":"Point"}
}