{
  "type": "Feature",
  "properties": {
    "iso:country":"US",
    "sg:address":"287 Howard Ave",
    "sg:city":"Holland",
    "sg:classifiers":[
        {
            "category":"Professional",
            "subcategory":"Computer Services",
            "type":"Services"
        }
    ],
    "sg:phone":"+1 616 796 6630",
    "sg:postcode":"49424",
    "sg:province":"MI",
    "sg:tags":[
        "programing",
        "custom"
    ],
    "wof:name":"Eglyph Inc",
    "wof:placetype":"venue"
},
  "geometry": {"coordinates":[-86.11979100000001,42.798294],"type":"Point"}
}