{
  "type": "Feature",
  "properties": {
    "iso:country":"US",
    "sg:address":"7618 Charrington Dr",
    "sg:city":"Canton",
    "sg:classifiers":[
        {
            "category":"Professional",
            "subcategory":"Management & Consulting",
            "type":"Services"
        }
    ],
    "sg:phone":"+1 734 459 3421",
    "sg:postcode":"48187",
    "sg:province":"MI",
    "sg:tags":[
        "business"
    ],
    "wof:name":"V P Network Consult",
    "wof:placetype":"venue"
},
  "geometry": {"coordinates":[-83.484617,42.342582],"type":"Point"}
}