{
  "type": "Feature",
  "properties": {
    "iso:country":"US",
    "sg:address":"18210 Mack Ave",
    "sg:city":"Grosse Pointe",
    "sg:classifiers":[
        {
            "category":"Retail",
            "subcategory":"Auto Rental",
            "type":"Services"
        }
    ],
    "sg:phone":"+1 313 884 0881",
    "sg:postcode":"48236",
    "sg:province":"MI",
    "sg:tags":[
        "is",
        "an",
        "leasing",
        "company",
        "franchising"
    ],
    "wof:name":"Thrifty Car Rental",
    "wof:placetype":"venue"
},
  "geometry": {"coordinates":[-82.91433000000001,42.408117],"type":"Point"}
}