{
  "type": "Feature",
  "properties": {
    "iso:country":"US",
    "sg:address":"27700 Northwestern Hwy",
    "sg:city":"Southfield",
    "sg:classifiers":[
        {
            "category":"Professional",
            "type":"Services"
        }
    ],
    "sg:phone":"+1 248 352 4807",
    "sg:postcode":"48034",
    "sg:province":"MI",
    "sg:tags":[
        "establishment"
    ],
    "wof:name":"Benjamine Levine PC",
    "wof:placetype":"venue"
},
  "geometry": {"coordinates":[-83.277834,42.489242],"type":"Point"}
}