{
  "type": "Feature",
  "properties": {
    "iso:country":"US",
    "sg:address":"5601 Hatchery Rd",
    "sg:city":"Waterford",
    "sg:classifiers":[
        {
            "category":"Health Services",
            "subcategory":"Nursing And Care Facility",
            "type":"Services"
        },
        {
            "category":"Social Services",
            "subcategory":"Adult Care",
            "type":"Services"
        }
    ],
    "sg:phone":"+1 248 674 9292",
    "sg:postcode":"48329",
    "sg:province":"MI",
    "sg:tags":[
        "residential",
        "retirement",
        "community",
        "home"
    ],
    "wof:name":"Canterbury On The Lake",
    "wof:placetype":"venue"
},
  "geometry": {"coordinates":[-83.396654,42.67465],"type":"Point"}
}