{
  "type": "Feature",
  "properties": {
    "iso:country":"US",
    "sg:address":"12744 Elmira St",
    "sg:city":"Detroit",
    "sg:classifiers":[
        {
            "category":"Education",
            "subcategory":"School",
            "type":"Public Place"
        }
    ],
    "sg:phone":"+1 313 873 0260",
    "sg:postcode":"48227",
    "sg:province":"MI",
    "wof:name":"Detroit Public Schools",
    "wof:placetype":"venue"
},
  "geometry": {"coordinates":[-83.168622,42.370954],"type":"Point"}
}