{
  "type": "Feature",
  "properties": {
    "iso:country":"US",
    "sg:address":"2904 Fleetwood Dr",
    "sg:city":"Portage",
    "sg:classifiers":[
        {
            "category":"Organizations",
            "subcategory":"Membership Organization",
            "type":"Services"
        }
    ],
    "sg:phone":"+1 269 345 5993",
    "sg:postcode":"49024",
    "sg:province":"MI",
    "wof:name":"Jewish SW",
    "wof:placetype":"venue"
},
  "geometry": {"coordinates":[-85.628045,42.241905],"type":"Point"}
}