{
  "type": "Feature",
  "properties": {
    "iso:country":"US",
    "sg:address":"419 N Rogers St",
    "sg:city":"Mason",
    "sg:classifiers":[
        {
            "category":"Professional",
            "subcategory":"Computer Services",
            "type":"Services"
        }
    ],
    "sg:phone":"+1 517 676 2061",
    "sg:postcode":"48854",
    "sg:province":"MI",
    "wof:name":"Penn Central",
    "wof:placetype":"venue"
},
  "geometry": {"coordinates":[-84.440128,42.58871],"type":"Point"}
}