{
  "type": "Feature",
  "properties": {
    "iso:country":"US",
    "sg:address":"2180 Curtis Rd",
    "sg:city":"Birch Run",
    "sg:classifiers":[
        {
            "category":"Professional",
            "subcategory":"Accounting & Tax Preparation",
            "type":"Services"
        }
    ],
    "sg:phone":"+1 989 777 1089",
    "sg:postcode":"48415",
    "sg:province":"MI",
    "sg:tags":[
        "return"
    ],
    "wof:name":"Kenneth Gawlak",
    "wof:placetype":"venue"
},
  "geometry": {"coordinates":[-83.91242800000001,43.322001],"type":"Point"}
}