{
  "type": "Feature",
  "properties": {
    "iso:country":"US",
    "sg:address":"264 Burgess Dr",
    "sg:city":"Galesburg",
    "sg:classifiers":[
        {
            "category":"Building & Trades",
            "subcategory":"Plumbing",
            "type":"Services"
        }
    ],
    "sg:phone":"+1 269 665 7629",
    "sg:postcode":"49053",
    "sg:province":"MI",
    "sg:tags":[
        "contractor"
    ],
    "wof:name":"Bill Hambright Heating & Cooli",
    "wof:placetype":"venue"
},
  "geometry": {"coordinates":[-85.414275,42.295653],"type":"Point"}
}