{
  "type": "Feature",
  "properties": {
    "iso:country":"US",
    "sg:address":"2000 E Cavanaugh Rd",
    "sg:city":"Lansing",
    "sg:classifiers":[
        {
            "category":"Manufacturing",
            "subcategory":"Tools & Machinery",
            "type":"Manufacturing & Wholesale Goods"
        }
    ],
    "sg:phone":"+1 517 887 7332",
    "sg:postcode":"48910",
    "sg:province":"MI",
    "sg:tags":[
        "car",
        "used",
        "computer",
        "quilt"
    ],
    "wof:name":"Rods Used Cars",
    "wof:placetype":"venue"
},
  "geometry": {"coordinates":[-84.521596,42.690113],"type":"Point"}
}