{
  "type": "Feature",
  "properties": {
    "iso:country":"US",
    "sg:address":"39565 Mound Rd",
    "sg:city":"Sterling Heights",
    "sg:classifiers":[
        {
            "category":"Wholesale",
            "subcategory":"Electrical",
            "type":"Manufacturing & Wholesale Goods"
        }
    ],
    "sg:phone":"+1 586 268 3900",
    "sg:postcode":"48310",
    "sg:province":"MI",
    "sg:tags":[
        "meter"
    ],
    "wof:name":"Electrical Inspection & Svcng",
    "wof:placetype":"venue"
},
  "geometry": {"coordinates":[-83.050377,42.584213],"type":"Point"}
}