{
  "type": "Feature",
  "properties": {
    "iso:country":"US",
    "sg:address":"27240 Haggerty Rd",
    "sg:city":"Farmington Hills",
    "sg:classifiers":[
        {
            "category":"Wholesale",
            "subcategory":"Durable Goods & Equipment",
            "type":"Manufacturing & Wholesale Goods"
        }
    ],
    "sg:phone":"+1 248 489 1090",
    "sg:postcode":"48331",
    "sg:province":"MI",
    "sg:tags":[
        "instrument",
        "scientific",
        "apparatus"
    ],
    "wof:name":"Kistler Instrument Corp",
    "wof:placetype":"venue"
},
  "geometry": {"coordinates":[-83.435965,42.491921],"type":"Point"}
}