{
  "type": "Feature",
  "properties": {
    "iso:country":"US",
    "sg:address":"711 E Miller Rd",
    "sg:city":"Lansing",
    "sg:classifiers":[
        {
            "category":"Restaurant",
            "type":"Food & Drink"
        }
    ],
    "sg:menulink":"http://www.allmenus.com/mi/lansing/251267-china-king/menu/",
    "sg:phone":"+1 517 394 9999",
    "sg:postcode":"48911",
    "sg:province":"MI",
    "sg:tags":[
        "asian",
        "chinese"
    ],
    "wof:name":"China King",
    "wof:placetype":"venue"
},
  "geometry": {"coordinates":[-84.542632,42.669252],"type":"Point"}
}