{
  "type": "Feature",
  "properties": {
    "iso:country":"US",
    "sg:address":"5798 Deer Trail Dr",
    "sg:city":"Traverse City",
    "sg:classifiers":[
        {
            "category":"Professional",
            "subcategory":"Business Services",
            "type":"Services"
        }
    ],
    "sg:phone":"+1 231 275 6162",
    "sg:postcode":"49684",
    "sg:province":"MI",
    "wof:name":"Perfect World Studios",
    "wof:placetype":"venue"
},
  "geometry": {"coordinates":[-85.787533,44.773396],"type":"Point"}
}