{
  "type": "Feature",
  "properties": {
    "iso:country":"US",
    "sg:address":"4516 Rathbun Rd",
    "sg:city":"Birch Run",
    "sg:classifiers":[
        {
            "category":"Utilities",
            "subcategory":"Electric",
            "type":"Services"
        }
    ],
    "sg:phone":"+1 989 777 6284",
    "sg:postcode":"48415",
    "sg:province":"MI",
    "sg:tags":[
        "company"
    ],
    "wof:name":"North American Natural Resrcs",
    "wof:placetype":"venue"
},
  "geometry": {"coordinates":[-83.868771,43.280043],"type":"Point"}
}