{
  "type": "Feature",
  "properties": {
    "iso:country":"US",
    "sg:address":"61023 Co Rd 657",
    "sg:city":"Lawton",
    "sg:classifiers":[
        {
            "category":"Building & Trades",
            "subcategory":"Construction",
            "type":"Services"
        }
    ],
    "sg:phone":"+1 269 624 7394",
    "sg:postcode":"49065",
    "sg:province":"MI",
    "sg:tags":[
        "siding",
        "contractor"
    ],
    "wof:name":"Hiscock Aluminum & Vinyl",
    "wof:placetype":"venue"
},
  "geometry": {"coordinates":[-85.823216,42.196737],"type":"Point"}
}