{
  "type": "Feature",
  "properties": {
    "iso:country":"US",
    "sg:address":"1781 Pine Creek Cir",
    "sg:city":"Haslett",
    "sg:classifiers":[
        {
            "category":"Organizations",
            "subcategory":"Community Association",
            "type":"Services"
        }
    ],
    "sg:phone":"+1 517 339 1681",
    "sg:postcode":"48840",
    "sg:province":"MI",
    "wof:name":"Border Wars Wrestling",
    "wof:placetype":"venue"
},
  "geometry": {"coordinates":[-84.413707,42.762199],"type":"Point"}
}