{
  "type": "Feature",
  "properties": {
    "iso:country":"US",
    "sg:address":"25620 W 8 Mile Rd",
    "sg:city":"Southfield",
    "sg:classifiers":[
        {
            "category":"Shopping",
            "subcategory":"Shoes",
            "type":"Retail Goods"
        }
    ],
    "sg:phone":"+1 248 208 7554",
    "sg:postcode":"48033",
    "sg:province":"MI",
    "sg:tags":[
        "store"
    ],
    "wof:name":"Save-On Shoes",
    "wof:placetype":"venue"
},
  "geometry": {"coordinates":[-83.29745200000001,42.442794],"type":"Point"}
}