{
  "type": "Feature",
  "properties": {
    "iso:country":"US",
    "sg:address":"320 S Hancock St",
    "sg:city":"Pentwater",
    "sg:classifiers":[
        {
            "category":"Shopping",
            "subcategory":"Gifts & Souvenirs",
            "type":"Retail Goods"
        }
    ],
    "sg:phone":"+1 231 869 4522",
    "sg:postcode":"49449",
    "sg:province":"MI",
    "sg:tags":[
        "shop"
    ],
    "wof:name":"Chez Moi",
    "wof:placetype":"venue"
},
  "geometry": {"coordinates":[-86.43290500000001,43.778881],"type":"Point"}
}