{
  "type": "Feature",
  "properties": {
    "iso:country":"US",
    "sg:address":"914 E Grand Blvd",
    "sg:city":"Detroit",
    "sg:classifiers":[
        {
            "category":"Health Services",
            "subcategory":"Nursing And Care Facility",
            "type":"Services"
        },
        {
            "category":"Social Services",
            "subcategory":"Adult Care",
            "type":"Services"
        }
    ],
    "sg:phone":"+1 313 923 4155",
    "sg:postcode":"48207",
    "sg:province":"MI",
    "sg:tags":[
        "living",
        "assisted",
        "homes-elderly",
        "elder",
        "people"
    ],
    "wof:name":"Mitchells A F C",
    "wof:placetype":"venue"
},
  "geometry": {"coordinates":[-83.014977,42.3675],"type":"Point"}
}