{
  "type": "Feature",
  "properties": {
    "iso:country":"US",
    "sg:address":"1751 Barlow St",
    "sg:city":"Traverse City",
    "sg:classifiers":[
        {
            "category":"Professional",
            "subcategory":"Engineering",
            "type":"Services"
        }
    ],
    "sg:phone":"+1 231 947 1707",
    "sg:postcode":"49686",
    "sg:province":"MI",
    "sg:tags":[
        "engineer"
    ],
    "wof:name":"Rhoades Engineering Corp",
    "wof:placetype":"venue"
},
  "geometry": {"coordinates":[-85.605498,44.73515],"type":"Point"}
}