{
  "type": "Feature",
  "properties": {
    "iso:country":"US",
    "sg:address":"1140 Cooper St",
    "sg:city":"Jackson",
    "sg:classifiers":[
        {
            "category":"Manufacturing",
            "subcategory":"Printing",
            "type":"Manufacturing & Wholesale Goods"
        }
    ],
    "sg:phone":"+1 517 841 9266",
    "sg:postcode":"49202",
    "sg:province":"MI",
    "sg:tags":[
        "decal"
    ],
    "wof:name":"O'Neil Signs & Racing Designs",
    "wof:placetype":"venue"
},
  "geometry": {"coordinates":[-84.403864,42.262665],"type":"Point"}
}