{
  "type": "Feature",
  "properties": {
    "iso:country":"US",
    "sg:address":"14411 Day Rd",
    "sg:city":"Hudson",
    "sg:phone":"+1 517 448 8202",
    "sg:postcode":"49247",
    "sg:province":"MI",
    "sg:tags":[
        "farm",
        "corn"
    ],
    "wof:name":"Earl Stoyke",
    "wof:placetype":"venue"
},
  "geometry": {"coordinates":[-84.37809900000001,41.869375],"type":"Point"}
}