{
  "type": "Feature",
  "properties": {
    "iso:country":"US",
    "sg:address":"2425 Schuette Rd",
    "sg:city":"Midland",
    "sg:classifiers":[
        {
            "category":"Wholesale",
            "subcategory":"Hardware",
            "type":"Manufacturing & Wholesale Goods"
        }
    ],
    "sg:phone":"+1 989 496 0600",
    "sg:postcode":"48642",
    "sg:province":"MI",
    "sg:tags":[
        "fastener"
    ],
    "wof:name":"Prime Industrial Fasteners",
    "wof:placetype":"venue"
},
  "geometry": {"coordinates":[-84.199209,43.600558],"type":"Point"}
}