{
  "type": "Feature",
  "properties": {
    "iso:country":"US",
    "sg:address":"4734 Breckenridge Dr NE",
    "sg:city":"Grand Rapids",
    "sg:classifiers":[
        {
            "category":"Communications",
            "subcategory":"Film & Video Production",
            "type":"Services"
        }
    ],
    "sg:phone":"+1 616 915 5004",
    "sg:postcode":"49525",
    "sg:province":"MI",
    "sg:tags":[
        "motion"
    ],
    "wof:name":"Ic Images",
    "wof:placetype":"venue"
},
  "geometry": {"coordinates":[-85.590439,43.047595],"type":"Point"}
}