{
  "type": "Feature",
  "properties": {
    "iso:country":"US",
    "sg:address":"1175 Crooks Rd",
    "sg:city":"Troy",
    "sg:classifiers":[
        {
            "category":"Professional",
            "subcategory":"Advertising",
            "type":"Services"
        }
    ],
    "sg:phone":"+1 248 280 1010",
    "sg:postcode":"48084",
    "sg:province":"MI",
    "sg:tags":[
        "counselor"
    ],
    "sg:website":"www.hppelzer.com",
    "wof:name":"H P Pelzer",
    "wof:placetype":"venue"
},
  "geometry": {"coordinates":[-83.16623199999999,42.54032],"type":"Point"}
}