{
  "type": "Feature",
  "properties": {
    "iso:country":"US",
    "sg:address":"640 Eastern Ave SE",
    "sg:city":"Grand Rapids",
    "sg:classifiers":[
        {
            "category":"Organizations",
            "subcategory":"Professional Association",
            "type":"Services"
        }
    ],
    "sg:phone":"+1 616 243 1300",
    "sg:postcode":"49503",
    "sg:province":"MI",
    "wof:name":"NAACP",
    "wof:placetype":"venue"
},
  "geometry": {"coordinates":[-85.64919500000001,42.95022],"type":"Point"}
}