{
  "type": "Feature",
  "properties": {
    "iso:country":"US",
    "sg:address":"3566 Cass Ave",
    "sg:city":"Detroit",
    "sg:classifiers":[
        {
            "category":"Real Estate",
            "subcategory":"Real Estate Operator",
            "type":"Services"
        }
    ],
    "sg:phone":"+1 313 832 3307",
    "sg:postcode":"48201",
    "sg:province":"MI",
    "sg:tags":[
        "apartment"
    ],
    "wof:name":"Chesterfield Apartments",
    "wof:placetype":"venue"
},
  "geometry": {"coordinates":[-83.060788,42.346072],"type":"Point"}
}