{
  "type": "Feature",
  "properties": {
    "iso:country":"US",
    "sg:address":"207 N Whittaker St",
    "sg:city":"New Buffalo",
    "sg:classifiers":[
        {
            "category":"Real Estate",
            "subcategory":"Real Estate Services",
            "type":"Services"
        }
    ],
    "sg:phone":"+1 269 469 4780",
    "sg:postcode":"49117",
    "sg:province":"MI",
    "sg:tags":[
        "company",
        "title"
    ],
    "wof:name":"Chicago Title Insurance Co",
    "wof:placetype":"venue"
},
  "geometry": {"coordinates":[-86.745519,41.796601],"type":"Point"}
}