{
  "type": "Feature",
  "properties": {
    "iso:country":"US",
    "sg:address":"37530 Cherry Hill Rd",
    "sg:city":"Westland",
    "sg:classifiers":[
        {
            "category":"Shopping",
            "subcategory":"Pharmacy",
            "type":"Retail Goods"
        }
    ],
    "sg:phone":"+1 734 727 0322",
    "sg:postcode":"48185",
    "sg:province":"MI",
    "sg:tags":[
        "drugstore"
    ],
    "sg:website":"www.cvs.com",
    "wof:name":"Cvs Pharmacy",
    "wof:placetype":"venue"
},
  "geometry": {"coordinates":[-83.409346,42.30969],"type":"Point"}
}