{
  "type": "Feature",
  "properties": {
    "iso:country":"US",
    "sg:address":"715 W Ellsworth Rd",
    "sg:city":"Morrice",
    "sg:phone":"+1 517 625 4228",
    "sg:postcode":"48857",
    "sg:province":"MI",
    "sg:tags":[
        "farm",
        "corn"
    ],
    "wof:name":"Banker Construction",
    "wof:placetype":"venue"
},
  "geometry": {"coordinates":[-84.176663,42.81269],"type":"Point"}
}