{
  "type": "Feature",
  "properties": {
    "iso:country":"US",
    "sg:address":"2703 19th Ave",
    "sg:city":"Port Huron",
    "sg:classifiers":[
        {
            "category":"Retail",
            "subcategory":"Repair Shop",
            "type":"Services"
        }
    ],
    "sg:phone":"+1 810 650 2244",
    "sg:postcode":"48060",
    "sg:province":"MI",
    "sg:tags":[
        "sewer",
        "cleaning"
    ],
    "wof:name":"Tri-County Vac Services",
    "wof:placetype":"venue"
},
  "geometry": {"coordinates":[-82.447406,43.003277],"type":"Point"}
}