{
  "type": "Feature",
  "properties": {
    "iso:country":"US",
    "sg:address":"2375 E Grand River Ave",
    "sg:city":"Howell",
    "sg:classifiers":[
        {
            "category":"Restaurant",
            "type":"Food & Drink"
        }
    ],
    "sg:menulink":"http://www.allmenus.com/mi/genoa/70013-cottage-inn-pizza/menu/",
    "sg:phone":"+1 517 545 8900",
    "sg:postcode":"48843",
    "sg:province":"MI",
    "sg:tags":[
        "wrap",
        "american",
        "sandwich",
        "pizza"
    ],
    "wof:name":"Cottage Inn Pizza",
    "wof:placetype":"venue"
},
  "geometry": {"coordinates":[-83.906522,42.598783],"type":"Point"}
}