{
  "type": "Feature",
  "properties": {
    "iso:country":"US",
    "sg:address":"37 N Broadway St",
    "sg:city":"Lake Orion",
    "sg:classifiers":[
        {
            "category":"Retail",
            "subcategory":"Portrait Studio",
            "type":"Services"
        }
    ],
    "sg:phone":"+1 248 693 8770",
    "sg:postcode":"48362",
    "sg:province":"MI",
    "sg:tags":[
        "photo"
    ],
    "wof:name":"Joshs Tire Supply",
    "wof:placetype":"venue"
},
  "geometry": {"coordinates":[-83.239873,42.784955],"type":"Point"}
}