{
  "type": "Feature",
  "properties": {
    "iso:country":"US",
    "sg:address":"5401 Portage Rd",
    "sg:city":"Portage",
    "sg:classifiers":[
        {
            "category":"Food & Beverages",
            "subcategory":"Bakery",
            "type":"Retail Goods"
        }
    ],
    "sg:phone":"+1 269 384 0355",
    "sg:postcode":"49002",
    "sg:province":"MI",
    "sg:tags":[
        "baker"
    ],
    "wof:name":"Schafer-Aunt Millie Outlet",
    "wof:placetype":"venue"
},
  "geometry": {"coordinates":[-85.560143,42.23912],"type":"Point"}
}