{
  "type": "Feature",
  "properties": {
    "iso:country":"US",
    "sg:address":"15627 Center Rd",
    "sg:city":"Traverse City",
    "sg:classifiers":[
        {
            "category":"Travel",
            "subcategory":"Hotels & Motels",
            "type":"Entertainment"
        }
    ],
    "sg:phone":"+1 231 223 7686",
    "sg:postcode":"49686",
    "sg:province":"MI",
    "sg:tags":[
        "breakfast",
        "operation",
        "bed",
        "accommodation"
    ],
    "wof:name":"Field Of Dreams Bed & Breakfst",
    "wof:placetype":"venue"
},
  "geometry": {"coordinates":[-85.505205,44.920346],"type":"Point"}
}