{
  "type": "Feature",
  "properties": {
    "iso:country":"US",
    "sg:address":"6170 Knapp St NE",
    "sg:city":"Ada",
    "sg:classifiers":[
        {
            "category":"Professional",
            "subcategory":"Detective & Security Services",
            "type":"Services"
        }
    ],
    "sg:phone":"+1 616 676 1352",
    "sg:postcode":"49301",
    "sg:province":"MI",
    "sg:tags":[
        "guard",
        "contract"
    ],
    "wof:name":"Van Doorne Dirk J",
    "wof:placetype":"venue"
},
  "geometry": {"coordinates":[-85.518124,43.007203],"type":"Point"}
}