{
  "type": "Feature",
  "properties": {
    "iso:country":"US",
    "sg:address":"46401 Grand River Ave",
    "sg:city":"Novi",
    "sg:classifiers":[
        {
            "category":"Wholesale",
            "subcategory":"Machinery & Supplies",
            "type":"Manufacturing & Wholesale Goods"
        }
    ],
    "sg:phone":"+1 248 348 3444",
    "sg:postcode":"48374",
    "sg:province":"MI",
    "sg:tags":[
        "tractor"
    ],
    "wof:name":"Foote Tractor Inc",
    "wof:placetype":"venue"
},
  "geometry": {"coordinates":[-83.497435,42.485482],"type":"Point"}
}