{
  "type": "Feature",
  "properties": {
    "iso:country":"US",
    "sg:address":"515 S Main St",
    "sg:city":"Vicksburg",
    "sg:classifiers":[
        {
            "category":"Building & Trades",
            "subcategory":"Construction",
            "type":"Services"
        }
    ],
    "sg:phone":"+1 269 649 1178",
    "sg:postcode":"49097",
    "sg:province":"MI",
    "sg:tags":[
        "roofing",
        "contractor"
    ],
    "wof:name":"Vicksburg Siding Wndws & Rfng",
    "wof:placetype":"venue"
},
  "geometry": {"coordinates":[-85.532282,42.115232],"type":"Point"}
}