{
  "type": "Feature",
  "properties": {
    "iso:country":"US",
    "sg:address":"30500 Northwestern Hwy",
    "sg:city":"Farmington Hills",
    "sg:classifiers":[
        {
            "category":"Insurance",
            "subcategory":"Insurance Agent",
            "type":"Services"
        }
    ],
    "sg:phone":"+1 248 538 0470",
    "sg:postcode":"48334",
    "sg:province":"MI",
    "sg:website":"www.ibexagency.com",
    "wof:name":"Ibex Enterprises",
    "wof:placetype":"venue"
},
  "geometry": {"coordinates":[-83.331155,42.513843],"type":"Point"}
}