{
  "type": "Feature",
  "properties": {
    "iso:country":"US",
    "sg:address":"3285 Henry St",
    "sg:city":"Muskegon",
    "sg:classifiers":[
        {
            "category":"Restaurant",
            "type":"Food & Drink"
        }
    ],
    "sg:menulink":"http://www.allmenus.com/mi/norton-shores/146431-subway/menu/",
    "sg:phone":"+1 231 733 9540",
    "sg:postcode":"49441",
    "sg:province":"MI",
    "sg:tags":[
        "american",
        "sandwich"
    ],
    "wof:name":"Subway",
    "wof:placetype":"venue"
},
  "geometry": {"coordinates":[-86.263471,43.190009],"type":"Point"}
}