{
  "type": "Feature",
  "properties": {
    "iso:country":"US",
    "sg:address":"2532 Lansing Rd",
    "sg:city":"Charlotte",
    "sg:classifiers":[
        {
            "category":"Manufacturing",
            "subcategory":"Glass & Minerals",
            "type":"Manufacturing & Wholesale Goods"
        }
    ],
    "sg:phone":"+1 517 337 1381",
    "sg:postcode":"48813",
    "sg:province":"MI",
    "sg:tags":[
        "ready"
    ],
    "wof:name":"Consumers Concrete Corp",
    "wof:placetype":"venue"
},
  "geometry": {"coordinates":[-84.78268,42.597216],"type":"Point"}
}