{
  "type": "Feature",
  "properties": {
    "iso:country":"US",
    "sg:address":"1884 Port Austin Rd",
    "sg:city":"Port Austin",
    "sg:classifiers":[
        {
            "category":"Restaurant",
            "type":"Food & Drink"
        }
    ],
    "sg:phone":"+1 989 738 7175",
    "sg:postcode":"48467",
    "sg:province":"MI",
    "wof:name":"Buccaneer Den",
    "wof:placetype":"venue"
},
  "geometry": {"coordinates":[-83.05176899999999,44.006547],"type":"Point"}
}