{
  "type": "Feature",
  "properties": {
    "iso:country":"US",
    "sg:address":"13110 W Warren Ave",
    "sg:city":"Dearborn",
    "sg:classifiers":[
        {
            "category":"Wholesale",
            "subcategory":"Fruits & Vegetables",
            "type":"Manufacturing & Wholesale Goods"
        }
    ],
    "sg:phone":"+1 313 582 8057",
    "sg:postcode":"48126",
    "sg:province":"MI",
    "sg:tags":[
        "veggie"
    ],
    "wof:name":"Cedar Fruit Market",
    "wof:placetype":"venue"
},
  "geometry": {"coordinates":[-83.17240099999999,42.3442],"type":"Point"}
}