{
  "type": "Feature",
  "properties": {
    "iso:country":"US",
    "sg:address":"690 Golf Course Rd",
    "sg:city":"Alpena",
    "sg:classifiers":[
        {
            "category":"Manufacturing",
            "subcategory":"Lumber",
            "type":"Manufacturing & Wholesale Goods"
        }
    ],
    "sg:phone":"+1 989 358 1064",
    "sg:postcode":"49707",
    "sg:province":"MI",
    "sg:tags":[
        "company",
        "logging"
    ],
    "wof:name":"Anderson Forestry Products",
    "wof:placetype":"venue"
},
  "geometry": {"coordinates":[-83.48374,45.08671],"type":"Point"}
}