{
  "type": "Feature",
  "properties": {
    "iso:country":"US",
    "sg:address":"26545 American",
    "sg:city":"Southfield",
    "sg:classifiers":[
        {
            "category":"Building & Trades",
            "subcategory":"Construction",
            "type":"Services"
        }
    ],
    "sg:phone":"+1 248 352 1550",
    "sg:postcode":"48034",
    "sg:province":"MI",
    "sg:tags":[
        "general",
        "contractor"
    ],
    "wof:name":"Jonna Co",
    "wof:placetype":"venue"
},
  "geometry": {"coordinates":[-83.307164,42.490869],"type":"Point"}
}