{
  "type": "Feature",
  "properties": {
    "iso:country":"US",
    "sg:address":"6173 Henry St",
    "sg:city":"Muskegon",
    "sg:classifiers":[
        {
            "category":"Organizations",
            "subcategory":"Religious Organization",
            "type":"Services"
        }
    ],
    "sg:phone":"+1 231 798 0183",
    "sg:postcode":"49441",
    "sg:province":"MI",
    "sg:tags":[
        "church"
    ],
    "wof:name":"Calvary Chapel of Muskegon",
    "wof:placetype":"venue"
},
  "geometry": {"coordinates":[-86.264815,43.137358],"type":"Point"}
}