{
  "type": "Feature",
  "properties": {
    "iso:country":"US",
    "sg:address":"1868 Southwood Ave",
    "sg:city":"Muskegon",
    "sg:classifiers":[
        {
            "category":"Freight",
            "type":"Transportation"
        }
    ],
    "sg:phone":"+1 231 759 4551",
    "sg:postcode":"49441",
    "sg:province":"MI",
    "sg:tags":[
        "cargo",
        "handler",
        "marine"
    ],
    "wof:name":"Lakeshore Dock & Lift",
    "wof:placetype":"venue"
},
  "geometry": {"coordinates":[-86.291023,43.197094],"type":"Point"}
}