{
  "type": "Feature",
  "properties": {
    "iso:country":"US",
    "sg:address":"5104 Industrial Ave",
    "sg:city":"Flint",
    "sg:classifiers":[
        {
            "category":"Food & Beverages",
            "subcategory":"Groceries & Convenience Stores",
            "type":"Retail Goods"
        }
    ],
    "sg:phone":"+1 810 787 6031",
    "sg:postcode":"48505",
    "sg:province":"MI",
    "sg:tags":[
        "grocer"
    ],
    "wof:name":"Harden's Grocery",
    "wof:placetype":"venue"
},
  "geometry": {"coordinates":[-83.68740099999999,43.060799],"type":"Point"}
}