{
  "type": "Feature",
  "properties": {
    "iso:country":"US",
    "sg:address":"750 Monte Rd",
    "sg:city":"Benton Harbor",
    "sg:classifiers":[
        {
            "category":"Manufacturing",
            "subcategory":"Tools & Machinery",
            "type":"Manufacturing & Wholesale Goods"
        }
    ],
    "sg:phone":"+1 269 923 6536",
    "sg:postcode":"49022",
    "sg:province":"MI",
    "sg:tags":[
        "household",
        "appliance"
    ],
    "wof:name":"Kitchen Aid Appliance Group",
    "wof:placetype":"venue"
},
  "geometry": {"coordinates":[-86.44073400000001,42.152321],"type":"Point"}
}