{
  "type": "Feature",
  "properties": {
    "iso:country":"US",
    "sg:address":"3633 W Maple Rd",
    "sg:city":"Bloomfield Hills",
    "sg:classifiers":[
        {
            "category":"Shopping",
            "subcategory":"Gifts & Souvenirs",
            "type":"Retail Goods"
        }
    ],
    "sg:phone":"+1 248 647 4457",
    "sg:postcode":"48301",
    "sg:province":"MI",
    "sg:tags":[
        "shop"
    ],
    "wof:name":"Dianne's Hallmark",
    "wof:placetype":"venue"
},
  "geometry": {"coordinates":[-83.26212599999999,42.545273],"type":"Point"}
}