{
  "type": "Feature",
  "properties": {
    "iso:country":"US",
    "sg:address":"27446 Novi Rd",
    "sg:city":"Novi",
    "sg:classifiers":[
        {
            "category":"Shopping",
            "subcategory":"Optical Goods",
            "type":"Retail Goods"
        }
    ],
    "sg:phone":"+1 248 348 8878",
    "sg:postcode":"48167",
    "sg:province":"MI",
    "sg:tags":[
        "sun",
        "goggles",
        "sunglasses"
    ],
    "wof:name":"Sunglass Hut",
    "wof:placetype":"venue"
},
  "geometry": {"coordinates":[-83.475914,42.490093],"type":"Point"}
}