{
  "type": "Feature",
  "properties": {
    "iso:country":"US",
    "sg:address":"1313 US Hwy 223",
    "sg:city":"Adrian",
    "sg:classifiers":[
        {
            "category":"Autos & Motor Vehicles",
            "subcategory":"Automobile Sales",
            "type":"Retail Goods"
        }
    ],
    "sg:phone":"+1 517 265 7156",
    "sg:postcode":"49221",
    "sg:province":"MI",
    "sg:tags":[
        "car",
        "dealer"
    ],
    "sg:website":"www.gregbell.com",
    "wof:name":"Greg Bell Chevrolet-Oldsmobile",
    "wof:placetype":"venue"
},
  "geometry": {"coordinates":[-84.03766899999999,41.874991],"type":"Point"}
}