{
  "type": "Feature",
  "properties": {
    "iso:country":"US",
    "sg:address":"23101 John R Rd",
    "sg:city":"Hazel Park",
    "sg:classifiers":[
        {
            "category":"Food & Beverages",
            "subcategory":"Groceries & Convenience Stores",
            "type":"Retail Goods"
        }
    ],
    "sg:phone":"+1 248 658 1641",
    "sg:postcode":"48030",
    "sg:province":"MI",
    "sg:website":"www.kroger.com",
    "wof:name":"Kroger",
    "wof:placetype":"venue"
},
  "geometry": {"coordinates":[-83.10402999999999,42.461947],"type":"Point"}
}