{
  "type": "Feature",
  "properties": {
    "iso:country":"US",
    "sg:address":"5794 Canton Dr",
    "sg:city":"Kalamazoo",
    "sg:classifiers":[
        {
            "category":"Shopping",
            "type":"Retail Goods"
        }
    ],
    "sg:phone":"+1 269 382 5905",
    "sg:postcode":"49004",
    "sg:province":"MI",
    "sg:tags":[
        "merchandise"
    ],
    "wof:name":"Frame Station",
    "wof:placetype":"venue"
},
  "geometry": {"coordinates":[-85.545177,42.343195],"type":"Point"}
}