{
  "type": "Feature",
  "properties": {
    "iso:country":"US",
    "sg:address":"8921 Crown St",
    "sg:city":"Livonia",
    "sg:classifiers":[
        {
            "category":"Retail",
            "subcategory":"Car Wash",
            "type":"Services"
        }
    ],
    "sg:phone":"+1 734 425 1015",
    "sg:postcode":"48150",
    "sg:province":"MI",
    "sg:tags":[
        "carwash"
    ],
    "wof:name":"C G M Detroit",
    "wof:placetype":"venue"
},
  "geometry": {"coordinates":[-83.40024,42.35502],"type":"Point"}
}