{
  "type": "Feature",
  "properties": {
    "iso:country":"US",
    "sg:address":"31971 Block St",
    "sg:city":"Garden City",
    "sg:classifiers":[
        {
            "category":"Professional",
            "subcategory":"Business Services",
            "type":"Services"
        }
    ],
    "sg:phone":"+1 734 266 1484",
    "sg:postcode":"48135",
    "sg:province":"MI",
    "wof:name":"Fancy Partners Inc",
    "wof:placetype":"venue"
},
  "geometry": {"coordinates":[-83.355419,42.329499],"type":"Point"}
}