{
  "type": "Feature",
  "properties": {
    "iso:country":"US",
    "sg:address":"955 S Lapeer Rd",
    "sg:city":"Oxford",
    "sg:classifiers":[
        {
            "category":"Restaurant",
            "type":"Food & Drink"
        }
    ],
    "sg:phone":"+1 248 628 4875",
    "sg:postcode":"48371",
    "sg:province":"MI",
    "wof:name":"Oxford Big Boy",
    "wof:placetype":"venue"
},
  "geometry": {"coordinates":[-83.253771,42.812615],"type":"Point"}
}