{
  "type": "Feature",
  "properties": {
    "iso:country":"US",
    "sg:address":"27530 Harper Ave",
    "sg:city":"Saint Clair Shores",
    "sg:classifiers":[
        {
            "category":"Professional",
            "subcategory":"Accounting & Tax Preparation",
            "type":"Services"
        }
    ],
    "sg:phone":"+1 586 774 5770",
    "sg:postcode":"48081",
    "sg:province":"MI",
    "sg:tags":[
        "accountant"
    ],
    "wof:name":"Lakeshore Accounting Service",
    "wof:placetype":"venue"
},
  "geometry": {"coordinates":[-82.8974,42.494801],"type":"Point"}
}