{
  "type": "Feature",
  "properties": {
    "iso:country":"US",
    "sg:address":"51757 Shadywood Dr",
    "sg:city":"Macomb",
    "sg:classifiers":[
        {
            "category":"Professional",
            "subcategory":"Business Services",
            "type":"Services"
        }
    ],
    "sg:phone":"+1 586 781 5280",
    "sg:postcode":"48042",
    "sg:province":"MI",
    "wof:name":"Interiorscape Inc",
    "wof:placetype":"venue"
},
  "geometry": {"coordinates":[-82.93117100000001,42.67312],"type":"Point"}
}