{
  "type": "Feature",
  "properties": {
    "iso:country":"US",
    "sg:address":"31770 Staman Cir",
    "sg:city":"Farmington",
    "sg:classifiers":[
        {
            "category":"Professional",
            "subcategory":"Art Services",
            "type":"Services"
        }
    ],
    "sg:phone":"+1 248 477 1179",
    "sg:postcode":"48336",
    "sg:province":"MI",
    "sg:tags":[
        "graphic",
        "design"
    ],
    "wof:name":"401 Inc",
    "wof:placetype":"venue"
},
  "geometry": {"coordinates":[-83.360113,42.474409],"type":"Point"}
}