{
  "type": "Feature",
  "properties": {
    "iso:country":"US",
    "sg:address":"3958 Berkshire St",
    "sg:city":"Detroit",
    "sg:classifiers":[
        {
            "category":"Professional",
            "subcategory":"Management & Consulting",
            "type":"Services"
        }
    ],
    "sg:phone":"+1 313 886 8206",
    "sg:postcode":"48224",
    "sg:province":"MI",
    "sg:tags":[
        "business"
    ],
    "wof:name":"Made Training & Consulting",
    "wof:placetype":"venue"
},
  "geometry": {"coordinates":[-82.94016499999999,42.393578],"type":"Point"}
}