{
  "type": "Feature",
  "properties": {
    "iso:country":"US",
    "sg:address":"4889 Fashion Square Blvd",
    "sg:city":"Saginaw",
    "sg:classifiers":[
        {
            "category":"Shopping",
            "subcategory":"Gifts & Souvenirs",
            "type":"Retail Goods"
        }
    ],
    "sg:phone":"+1 989 497 8372",
    "sg:postcode":"48604",
    "sg:province":"MI",
    "sg:tags":[
        "shop"
    ],
    "wof:name":"Global Gifts",
    "wof:placetype":"venue"
},
  "geometry": {"coordinates":[-83.97071800000001,43.477795],"type":"Point"}
}