{
  "type": "Feature",
  "properties": {
    "iso:country":"US",
    "sg:address":"6705 US Hwy 2",
    "sg:city":"Quinnesec",
    "sg:classifiers":[
        {
            "category":"Building & Trades",
            "subcategory":"Plumbing",
            "type":"Services"
        }
    ],
    "sg:phone":"+1 906 779 9625",
    "sg:postcode":"49876",
    "sg:province":"MI",
    "sg:tags":[
        "mechanical",
        "contractor"
    ],
    "wof:name":"Jamar Co",
    "wof:placetype":"venue"
},
  "geometry": {"coordinates":[-87.95905999999999,45.802045],"type":"Point"}
}