{
  "type": "Feature",
  "properties": {
    "iso:country":"US",
    "sg:address":"544 N Telegraph Rd",
    "sg:city":"Dearborn",
    "sg:classifiers":[
        {
            "category":"Retail",
            "subcategory":"Auto Repair",
            "type":"Services"
        }
    ],
    "sg:phone":"+1 313 278 4310",
    "sg:postcode":"48128",
    "sg:province":"MI",
    "sg:tags":[
        "automotive",
        "lubrication"
    ],
    "wof:name":"Jiffy Lube",
    "wof:placetype":"venue"
},
  "geometry": {"coordinates":[-83.271764,42.314415],"type":"Point"}
}