{
  "type": "Feature",
  "properties": {
    "iso:country":"US",
    "sg:address":"15816 Turner St",
    "sg:city":"Lansing",
    "sg:classifiers":[
        {
            "category":"Retail",
            "subcategory":"Auto Repair",
            "type":"Services"
        }
    ],
    "sg:phone":"+1 517 482 3057",
    "sg:postcode":"48906",
    "sg:province":"MI",
    "sg:tags":[
        "automotive",
        "automobile"
    ],
    "wof:name":"Cunningham MBL Trck Trlr Repr",
    "wof:placetype":"venue"
},
  "geometry": {"coordinates":[-84.55869,42.790716],"type":"Point"}
}