{
  "type": "Feature",
  "properties": {
    "iso:country":"US",
    "sg:address":"1050 Lake Park Dr",
    "sg:city":"Birmingham",
    "sg:classifiers":[
        {
            "category":"Professional",
            "subcategory":"Management & Consulting",
            "type":"Services"
        }
    ],
    "sg:phone":"+1 248 540 5970",
    "sg:postcode":"48009",
    "sg:province":"MI",
    "sg:tags":[
        "marketing",
        "consultant"
    ],
    "wof:name":"Wolk Advertising",
    "wof:placetype":"venue"
},
  "geometry": {"coordinates":[-83.22828,42.554546],"type":"Point"}
}