{
  "type": "Feature",
  "properties": {
    "iso:country":"US",
    "sg:address":"130 S Green St",
    "sg:city":"Detroit",
    "sg:classifiers":[
        {
            "category":"Retail",
            "subcategory":"Repair Shop",
            "type":"Services"
        }
    ],
    "sg:phone":"+1 313 842 7380",
    "sg:postcode":"48209",
    "sg:province":"MI",
    "wof:name":"P S C Industrial Services Inc",
    "wof:placetype":"venue"
},
  "geometry": {"coordinates":[-83.111542,42.300273],"type":"Point"}
}