{
  "type": "Feature",
  "properties": {
    "iso:country":"US",
    "sg:address":"1325 Sunnyfield Rd",
    "sg:city":"Sturgis",
    "sg:classifiers":[
        {
            "category":"Shopping",
            "subcategory":"Hobbies, Toys, & Games",
            "type":"Retail Goods"
        }
    ],
    "sg:phone":"+1 269 659 0788",
    "sg:postcode":"49091",
    "sg:province":"MI",
    "wof:name":"Scents From Nanas House",
    "wof:placetype":"venue"
},
  "geometry": {"coordinates":[-85.416237,41.787304],"type":"Point"}
}