{
  "type": "Feature",
  "properties": {
    "iso:country":"US",
    "sg:address":"93283 Co Rd 690",
    "sg:city":"Dowagiac",
    "sg:classifiers":[
        {
            "category":"Travel",
            "subcategory":"Campground",
            "type":"Entertainment"
        }
    ],
    "sg:phone":"+1 269 424 5070",
    "sg:postcode":"49047",
    "sg:province":"MI",
    "sg:tags":[
        "trailer"
    ],
    "wof:name":"Land Of Lakes Campground",
    "wof:placetype":"venue"
},
  "geometry": {"coordinates":[-86.20275700000001,42.08101],"type":"Point"}
}