{
  "type": "Feature",
  "properties": {
    "iso:country":"US",
    "sg:address":"1211 Tupper Lake St",
    "sg:city":"Lake Odessa",
    "sg:classifiers":[
        {
            "category":"Social Services",
            "subcategory":"Child Care",
            "type":"Services"
        }
    ],
    "sg:phone":"+1 616 374 0912",
    "sg:postcode":"48849",
    "sg:province":"MI",
    "sg:tags":[
        "day"
    ],
    "wof:name":"Tammy Lynn Pixley",
    "wof:placetype":"venue"
},
  "geometry": {"coordinates":[-85.133343,42.784914],"type":"Point"}
}