{
  "type": "Feature",
  "properties": {
    "iso:country":"US",
    "sg:address":"2722 Fern St",
    "sg:city":"Royal Oak",
    "sg:classifiers":[
        {
            "category":"Professional",
            "type":"Services"
        }
    ],
    "sg:phone":"+1 248 588 0891",
    "sg:postcode":"48073",
    "sg:province":"MI",
    "sg:tags":[
        "adv",
        "mail",
        "public",
        "relations",
        "direct"
    ],
    "wof:name":"Clynes Melinda",
    "wof:placetype":"venue"
},
  "geometry": {"coordinates":[-83.138544,42.514384],"type":"Point"}
}