{
  "type": "Feature",
  "properties": {
    "iso:country":"US",
    "sg:address":"502 E Michigan Ave",
    "sg:city":"Saline",
    "sg:classifiers":[
        {
            "category":"Restaurant",
            "type":"Food & Drink"
        }
    ],
    "sg:menulink":"http://www.allmenus.com/mi/saline/176486-kfc---kentucky-fried-chicken/menu/",
    "sg:phone":"+1 734 429 4350",
    "sg:postcode":"48176",
    "sg:province":"MI",
    "sg:tags":[
        "american",
        "chicken"
    ],
    "wof:name":"KFC - Kentucky Fried Chicken",
    "wof:placetype":"venue"
},
  "geometry": {"coordinates":[-83.771232,42.171292],"type":"Point"}
}