{
  "type": "Feature",
  "properties": {
    "iso:country":"US",
    "sg:address":"4648 Brafferton Dr",
    "sg:city":"Bloomfield Hills",
    "sg:classifiers":[
        {
            "category":"Professional",
            "subcategory":"Lawyer & Legal Services",
            "type":"Services"
        }
    ],
    "sg:phone":"+1 248 932 2166",
    "sg:postcode":"48302",
    "sg:province":"MI",
    "wof:name":"Genworks International",
    "wof:placetype":"venue"
},
  "geometry": {"coordinates":[-83.308751,42.570601],"type":"Point"}
}