{
  "type": "Feature",
  "properties": {
    "iso:country":"US",
    "sg:address":"336 N Main St",
    "sg:city":"Milford",
    "sg:classifiers":[
        {
            "category":"Shopping",
            "subcategory":"Clothing, Apparel, & Fashions",
            "type":"Retail Goods"
        }
    ],
    "sg:phone":"+1 248 685 2582",
    "sg:postcode":"48381",
    "sg:province":"MI",
    "sg:tags":[
        "item",
        "boutique"
    ],
    "wof:name":"Twigs & Berries Boutique",
    "wof:placetype":"venue"
},
  "geometry": {"coordinates":[-83.600235,42.590216],"type":"Point"}
}