{
  "type": "Feature",
  "properties": {
    "iso:country":"US",
    "sg:address":"2206 Mitchell Park Dr",
    "sg:city":"Petoskey",
    "sg:classifiers":[
        {
            "category":"Health Services",
            "subcategory":"Doctor",
            "type":"Services"
        }
    ],
    "sg:phone":"+1 231 487 2415",
    "sg:postcode":"49770",
    "sg:province":"MI",
    "sg:tags":[
        "medical"
    ],
    "wof:name":"Little Trvrse Psychatric Assoc",
    "wof:placetype":"venue"
},
  "geometry": {"coordinates":[-84.92199100000001,45.374903],"type":"Point"}
}