{
  "type": "Feature",
  "properties": {
    "iso:country":"US",
    "sg:address":"8035 Gratiot Rd",
    "sg:city":"Saginaw",
    "sg:classifiers":[
        {
            "category":"Personal",
            "subcategory":"Beauty Salon",
            "type":"Services"
        }
    ],
    "sg:phone":"+1 989 781 3170",
    "sg:postcode":"48609",
    "sg:province":"MI",
    "wof:name":"Valerie's Beauty Ctr",
    "wof:placetype":"venue"
},
  "geometry": {"coordinates":[-84.07241,43.415893],"type":"Point"}
}