{
  "type": "Feature",
  "properties": {
    "iso:country":"US",
    "sg:address":"2600 Smith Rd",
    "sg:city":"Lambertville",
    "sg:classifiers":[
        {
            "category":"Building & Trades",
            "subcategory":"Construction",
            "type":"Services"
        }
    ],
    "sg:phone":"+1 734 856 2255",
    "sg:postcode":"48144",
    "sg:province":"MI",
    "sg:tags":[
        "contractor"
    ],
    "wof:name":"Janowicz Sheet Metal",
    "wof:placetype":"venue"
},
  "geometry": {"coordinates":[-83.609264,41.735273],"type":"Point"}
}