{
  "type": "Feature",
  "properties": {
    "iso:country":"US",
    "sg:address":"90 Navy St",
    "sg:city":"Hancock",
    "sg:classifiers":[
        {
            "category":"Autos & Motor Vehicles",
            "subcategory":"Motorcycle Sales",
            "type":"Retail Goods"
        }
    ],
    "sg:phone":"+1 906 482 9990",
    "sg:postcode":"49930",
    "sg:province":"MI",
    "sg:tags":[
        "all",
        "terrain"
    ],
    "wof:name":"M & M Powersports Inc",
    "wof:placetype":"venue"
},
  "geometry": {"coordinates":[-88.57825,47.125047],"type":"Point"}
}