{
  "type": "Feature",
  "properties": {
    "iso:country":"US",
    "sg:address":"10760 Grassy Knoll Ct",
    "sg:city":"Brighton",
    "sg:classifiers":[
        {
            "category":"Professional",
            "subcategory":"Management & Consulting",
            "type":"Services"
        }
    ],
    "sg:phone":"+1 810 220 8639",
    "sg:postcode":"48114",
    "sg:province":"MI",
    "sg:tags":[
        "business"
    ],
    "wof:name":"Sigma Consultants Inc",
    "wof:placetype":"venue"
},
  "geometry": {"coordinates":[-83.738175,42.534788],"type":"Point"}
}