{
  "type": "Feature",
  "properties": {
    "iso:country":"US",
    "sg:address":"3725 W Auburn Rd",
    "sg:city":"Rochester Hills",
    "sg:classifiers":[
        {
            "category":"Retail",
            "subcategory":"Pet Boarding",
            "type":"Services"
        }
    ],
    "sg:phone":"+1 248 852 0210",
    "sg:postcode":"48309",
    "sg:province":"MI",
    "sg:tags":[
        "boarding/pet",
        "sitting"
    ],
    "wof:name":"Pandora's Sewing Box",
    "wof:placetype":"venue"
},
  "geometry": {"coordinates":[-83.205597,42.633999],"type":"Point"}
}