{
  "type": "Feature",
  "properties": {
    "iso:country":"US",
    "sg:address":"1270 Rankin Dr Ste A",
    "sg:city":"Troy",
    "sg:classifiers":[
        {
            "category":"Professional",
            "subcategory":"Printing & Photocopies",
            "type":"Services"
        }
    ],
    "sg:phone":"+1 248 588 1900",
    "sg:postcode":"48083",
    "sg:province":"MI",
    "wof:name":"SIR Speedy Printing Centers",
    "wof:placetype":"venue"
},
  "geometry": {"coordinates":[-83.125702,42.5429],"type":"Point"}
}