{
  "type": "Feature",
  "properties": {
    "iso:country":"US",
    "sg:address":"101 N Groesbeck Hwy",
    "sg:city":"Mount Clemens",
    "sg:classifiers":[
        {
            "category":"Shopping",
            "subcategory":"Florist",
            "type":"Retail Goods"
        }
    ],
    "sg:phone":"+1 586 463 8688",
    "sg:postcode":"48043",
    "sg:province":"MI",
    "wof:name":"Kraatz Florists",
    "wof:placetype":"venue"
},
  "geometry": {"coordinates":[-82.89919999999999,42.603401],"type":"Point"}
}