{
  "type": "Feature",
  "properties": {
    "iso:country":"US",
    "sg:address":"1515 Orchard Ave",
    "sg:city":"Kalamazoo",
    "sg:classifiers":[
        {
            "category":"Building & Trades",
            "subcategory":"Construction",
            "type":"Services"
        }
    ],
    "sg:phone":"+1 269 385 3458",
    "sg:postcode":"49007",
    "sg:province":"MI",
    "sg:tags":[
        "general",
        "contractor"
    ],
    "wof:name":"BAM Construction",
    "wof:placetype":"venue"
},
  "geometry": {"coordinates":[-85.60447000000001,42.313272],"type":"Point"}
}