{
  "type": "Feature",
  "properties": {
    "iso:country":"US",
    "sg:address":"207 Hoosier Dr",
    "sg:city":"Angola",
    "sg:classifiers":[
        {
            "category":"Wholesale",
            "subcategory":"Electrical",
            "type":"Manufacturing & Wholesale Goods"
        }
    ],
    "sg:phone":"+1 260 668 7149",
    "sg:postcode":"46703",
    "sg:province":"MI",
    "sg:tags":[
        "wire",
        "cable"
    ],
    "wof:name":"Cable Solutions Co Inc",
    "wof:placetype":"venue"
},
  "geometry": {"coordinates":[-85.003007,41.663454],"type":"Point"}
}