{
  "type": "Feature",
  "properties": {
    "iso:country":"US",
    "sg:address":"9817 Quincy St",
    "sg:city":"Detroit",
    "sg:classifiers":[
        {
            "category":"Utilities",
            "subcategory":"Telephone",
            "type":"Services"
        }
    ],
    "sg:phone":"+1 313 896 5878",
    "sg:postcode":"48204",
    "sg:province":"MI",
    "sg:tags":[
        "communications"
    ],
    "wof:name":"Clarence McAdory",
    "wof:placetype":"venue"
},
  "geometry": {"coordinates":[-83.12379900000001,42.372249],"type":"Point"}
}