{
  "type": "Feature",
  "properties": {
    "iso:country":"US",
    "sg:address":"14600 Lakeside Cir Unit 1380",
    "sg:city":"Sterling Heights",
    "sg:classifiers":[
        {
            "category":"Sports & Exercise",
            "subcategory":"Bicycle Rental",
            "type":"Entertainment"
        }
    ],
    "sg:phone":"+1 586 566 2500",
    "sg:postcode":"48313",
    "sg:province":"MI",
    "sg:tags":[
        "wear"
    ],
    "sg:website":"www.ae.com",
    "wof:name":"American Eagle Outfitters",
    "wof:placetype":"venue"
},
  "geometry": {"coordinates":[-82.98833500000001,42.620288],"type":"Point"}
}