{
  "type": "Feature",
  "properties": {
    "iso:country":"US",
    "sg:address":"11151 Twin Lake Rd NE",
    "sg:city":"Kalkaska",
    "sg:classifiers":[
        {
            "category":"Mining & Drilling",
            "type":"Manufacturing & Wholesale Goods"
        }
    ],
    "sg:phone":"+1 231 587 8079",
    "sg:postcode":"49646",
    "sg:province":"MI",
    "sg:tags":[
        "oil",
        "gas",
        "producer"
    ],
    "wof:name":"Swepi",
    "wof:placetype":"venue"
},
  "geometry": {"coordinates":[-84.93617999999999,44.807752],"type":"Point"}
}