{
  "type": "Feature",
  "properties": {
    "iso:country":"US",
    "sg:address":"1455 Lincoln Ave",
    "sg:city":"Holland",
    "sg:classifiers":[
        {
            "category":"Manufacturing",
            "subcategory":"Glass & Minerals",
            "type":"Manufacturing & Wholesale Goods"
        }
    ],
    "sg:phone":"+1 616 395 3634",
    "sg:postcode":"49423",
    "sg:province":"MI",
    "sg:tags":[
        "product"
    ],
    "sg:website":"www.gemtron.com",
    "wof:name":"Gemtron Corp",
    "wof:placetype":"venue"
},
  "geometry": {"coordinates":[-86.096475,42.749387],"type":"Point"}
}