{
  "type": "Feature",
  "properties": {
    "iso:country":"US",
    "sg:address":"171 N State St",
    "sg:city":"Caro",
    "sg:classifiers":[
        {
            "category":"Wholesale",
            "subcategory":"Medical Equipment & Supplies",
            "type":"Manufacturing & Wholesale Goods"
        }
    ],
    "sg:phone":"+1 989 673 8448",
    "sg:postcode":"48723",
    "sg:province":"MI",
    "sg:tags":[
        "physician",
        "surgeon"
    ],
    "wof:name":"United Health Svc Inc",
    "wof:placetype":"venue"
},
  "geometry": {"coordinates":[-83.39601399999999,43.489181],"type":"Point"}
}