{
  "type": "Feature",
  "properties": {
    "iso:country":"US",
    "sg:address":"5900 Haist Rd",
    "sg:city":"Pigeon",
    "sg:classifiers":[
        {
            "category":"Farming",
            "subcategory":"Dairy Farm",
            "type":"Manufacturing & Wholesale Goods"
        }
    ],
    "sg:phone":"+1 989 375 2307",
    "sg:postcode":"48755",
    "sg:province":"MI",
    "wof:name":"Kasserman Farms",
    "wof:placetype":"venue"
},
  "geometry": {"coordinates":[-83.215377,43.78829],"type":"Point"}
}