{
  "type": "Feature",
  "properties": {
    "iso:country":"US",
    "sg:address":"4875 Product Dr",
    "sg:city":"Wixom",
    "sg:classifiers":[
        {
            "category":"Building & Trades",
            "subcategory":"Landscaping Services",
            "type":"Services"
        }
    ],
    "sg:phone":"+1 248 685 0123",
    "sg:postcode":"48393",
    "sg:province":"MI",
    "sg:tags":[
        "landscape",
        "contractor"
    ],
    "sg:website":"www.tcla.com",
    "wof:name":"Troy Clogg Landscape Assoc",
    "wof:placetype":"venue"
},
  "geometry": {"coordinates":[-83.558587,42.526],"type":"Point"}
}