{
  "type": "Feature",
  "properties": {
    "iso:country":"US",
    "sg:address":"35548 Mound Rd",
    "sg:city":"Sterling Heights",
    "sg:classifiers":[
        {
            "category":"Wholesale",
            "subcategory":"Chemicals & Plastics",
            "type":"Manufacturing & Wholesale Goods"
        }
    ],
    "sg:phone":"+1 586 795 1781",
    "sg:postcode":"48310",
    "sg:province":"MI",
    "sg:tags":[
        "adhesive",
        "glue"
    ],
    "wof:name":"Ellsworth Adhesives Systems",
    "wof:placetype":"venue"
},
  "geometry": {"coordinates":[-83.04839,42.554729],"type":"Point"}
}