{
  "type": "Feature",
  "properties": {
    "iso:country":"US",
    "sg:address":"53165 Maranatha Ln",
    "sg:city":"Wixom",
    "sg:classifiers":[
        {
            "category":"Professional",
            "subcategory":"Engineering",
            "type":"Services"
        }
    ],
    "sg:phone":"+1 248 486 1552",
    "sg:postcode":"48393",
    "sg:province":"MI",
    "sg:tags":[
        "engineer"
    ],
    "wof:name":"Elcore Inc",
    "wof:placetype":"venue"
},
  "geometry": {"coordinates":[-83.576931,42.516501],"type":"Point"}
}