{
  "type": "Feature",
  "properties": {
    "iso:country":"US",
    "sg:address":"5605 Bent Oak Hwy",
    "sg:city":"Adrian",
    "sg:classifiers":[
        {
            "category":"Building & Trades",
            "subcategory":"Plumbing",
            "type":"Services"
        }
    ],
    "sg:phone":"+1 517 263 9194",
    "sg:postcode":"49221",
    "sg:province":"MI",
    "sg:tags":[
        "heating",
        "contractor"
    ],
    "wof:name":"Smith's Heating & Air Cond",
    "wof:placetype":"venue"
},
  "geometry": {"coordinates":[-84.035528,41.962712],"type":"Point"}
}