{
  "type": "Feature",
  "properties": {
    "iso:country":"US",
    "sg:address":"905 W 11 Mile Rd",
    "sg:city":"Madison Heights",
    "sg:classifiers":[
        {
            "category":"Retail",
            "subcategory":"Veterinary Services",
            "type":"Services"
        }
    ],
    "sg:phone":"+1 248 546 8090",
    "sg:postcode":"48071",
    "sg:province":"MI",
    "sg:tags":[
        "veterinarian"
    ],
    "wof:name":"Animal Health Services Vet",
    "wof:placetype":"venue"
},
  "geometry": {"coordinates":[-83.11509700000001,42.490501],"type":"Point"}
}