{
  "type": "Feature",
  "properties": {
    "iso:country":"US",
    "sg:address":"20080 Houghton St",
    "sg:city":"Detroit",
    "sg:classifiers":[
        {
            "category":"Banks & Credit Unions",
            "subcategory":"Investment Brokerage",
            "type":"Services"
        }
    ],
    "sg:phone":"+1 313 534 5188",
    "sg:postcode":"48219",
    "sg:province":"MI",
    "sg:tags":[
        "security"
    ],
    "wof:name":"Milsar Carolina Holding Co",
    "wof:placetype":"venue"
},
  "geometry": {"coordinates":[-83.260953,42.440575],"type":"Point"}
}