{
  "type": "Feature",
  "properties": {
    "iso:country":"US",
    "sg:address":"1122 N Leroy St",
    "sg:city":"Fenton",
    "sg:classifiers":[
        {
            "category":"Health Services",
            "subcategory":"Doctor",
            "type":"Services"
        }
    ],
    "sg:phone":"+1 810 629 8303",
    "sg:postcode":"48430",
    "sg:province":"MI",
    "sg:tags":[
        "medical"
    ],
    "wof:name":"Genesys Pho",
    "wof:placetype":"venue"
},
  "geometry": {"coordinates":[-83.707206,42.809247],"type":"Point"}
}