{
  "type": "Feature",
  "properties": {
    "iso:country":"US",
    "sg:address":"19256 Kendaville Rd",
    "sg:city":"Howard City",
    "sg:classifiers":[
        {
            "category":"Professional",
            "subcategory":"Testing Lab",
            "type":"Services"
        }
    ],
    "sg:phone":"+1 231 937 5680",
    "sg:postcode":"49329",
    "sg:province":"MI",
    "sg:tags":[
        "laboratory"
    ],
    "wof:name":"R & R Research Breeders",
    "wof:placetype":"venue"
},
  "geometry": {"coordinates":[-85.464147,43.366994],"type":"Point"}
}