{
  "type": "Feature",
  "properties": {
    "iso:country":"US",
    "sg:address":"1158 Snyder Rd",
    "sg:city":"East Lansing",
    "sg:classifiers":[
        {
            "category":"Real Estate",
            "subcategory":"Real Estate Agent",
            "type":"Services"
        }
    ],
    "sg:phone":"+1 517 333 3320",
    "sg:postcode":"48823",
    "sg:province":"MI",
    "wof:name":"Campus Property Management",
    "wof:placetype":"venue"
},
  "geometry": {"coordinates":[-84.46751399999999,42.738477],"type":"Point"}
}