{
  "type": "Feature",
  "properties": {
    "iso:country":"US",
    "sg:address":"112 S Carpenter Ave",
    "sg:city":"Kingsford",
    "sg:classifiers":[
        {
            "category":"Organizations",
            "subcategory":"Non-profit Organization",
            "type":"Services"
        }
    ],
    "sg:phone":"+1 906 779 0846",
    "sg:postcode":"49802",
    "sg:province":"MI",
    "sg:tags":[
        "information",
        "alcoholism",
        "treatment"
    ],
    "wof:name":"Community Substance Abuse",
    "wof:placetype":"venue"
},
  "geometry": {"coordinates":[-88.06882400000001,45.807714],"type":"Point"}
}