{
  "type": "Feature",
  "properties": {
    "iso:country":"US",
    "sg:address":"350 E Warren Ave",
    "sg:city":"Detroit",
    "sg:classifiers":[
        {
            "category":"Shopping",
            "subcategory":"Pharmacy",
            "type":"Retail Goods"
        }
    ],
    "sg:phone":"+1 313 831 8547",
    "sg:postcode":"48201",
    "sg:province":"MI",
    "sg:tags":[
        "drugstore"
    ],
    "sg:website":"www.cvs.com",
    "wof:name":"Cvs Pharmacy",
    "wof:placetype":"venue"
},
  "geometry": {"coordinates":[-83.059929,42.358439],"type":"Point"}
}