{
  "type": "Feature",
  "properties": {
    "iso:country":"US",
    "sg:address":"7942 Dixie Hwy",
    "sg:city":"Ira",
    "sg:classifiers":[
        {
            "category":"Autos & Motor Vehicles",
            "subcategory":"Automobile Sales",
            "type":"Retail Goods"
        }
    ],
    "sg:phone":"+1 586 725 1921",
    "sg:postcode":"48023",
    "sg:province":"MI",
    "sg:tags":[
        "car",
        "dealer"
    ],
    "wof:name":"Tom Thornton",
    "wof:placetype":"venue"
},
  "geometry": {"coordinates":[-82.627611,42.674523],"type":"Point"}
}