{
  "type": "Feature",
  "properties": {
    "iso:country":"US",
    "sg:address":"128 W Midland Rd",
    "sg:city":"Auburn",
    "sg:classifiers":[
        {
            "category":"Retail",
            "subcategory":"Auto Repair",
            "type":"Services"
        }
    ],
    "sg:phone":"+1 989 662 4081",
    "sg:postcode":"48611",
    "sg:province":"MI",
    "sg:tags":[
        "general"
    ],
    "wof:name":"Wee Care Auto",
    "wof:placetype":"venue"
},
  "geometry": {"coordinates":[-84.053983,43.60334],"type":"Point"}
}