{
  "type": "Feature",
  "properties": {
    "iso:country":"US",
    "sg:address":"103 N Grove St",
    "sg:city":"Delton",
    "sg:classifiers":[
        {
            "category":"Food & Beverages",
            "subcategory":"Groceries & Convenience Stores",
            "type":"Retail Goods"
        }
    ],
    "sg:phone":"+1 269 623 2389",
    "sg:postcode":"49046",
    "sg:province":"MI",
    "sg:tags":[
        "grocer"
    ],
    "wof:name":"Felpausch Food Ctr",
    "wof:placetype":"venue"
},
  "geometry": {"coordinates":[-85.408536,42.502153],"type":"Point"}
}