{
  "type": "Feature",
  "properties": {
    "iso:country":"US",
    "sg:address":"10751 Highland Rd",
    "sg:city":"White Lake",
    "sg:classifiers":[
        {
            "category":"Shopping",
            "subcategory":"Used Merchandise",
            "type":"Retail Goods"
        }
    ],
    "sg:phone":"+1 248 698 9575",
    "sg:postcode":"48386",
    "sg:province":"MI",
    "sg:tags":[
        "antique"
    ],
    "wof:name":"Val's Antiques",
    "wof:placetype":"venue"
},
  "geometry": {"coordinates":[-83.494091,42.649664],"type":"Point"}
}