{
  "type": "Feature",
  "properties": {
    "iso:country":"US",
    "sg:address":"160 Saint John Rd",
    "sg:city":"Highland",
    "sg:classifiers":[
        {
            "category":"Manufacturing",
            "subcategory":"Metals",
            "type":"Manufacturing & Wholesale Goods"
        }
    ],
    "sg:phone":"+1 248 887 7289",
    "sg:postcode":"48357",
    "sg:province":"MI",
    "wof:name":"United Fabricating",
    "wof:placetype":"venue"
},
  "geometry": {"coordinates":[-83.61642399999999,42.641107],"type":"Point"}
}