{
  "type": "Feature",
  "properties": {
    "iso:country":"US",
    "sg:address":"23280 Farmington Rd",
    "sg:city":"Farmington",
    "sg:classifiers":[
        {
            "category":"Health Services",
            "subcategory":"Chiropractor",
            "type":"Services"
        }
    ],
    "sg:phone":"+1 248 474 4484",
    "sg:postcode":"48336",
    "sg:province":"MI",
    "sg:website":"www.lowenclinic.com",
    "wof:name":"Lowen Chiropractic Clinic",
    "wof:placetype":"venue"
},
  "geometry": {"coordinates":[-83.376099,42.462002],"type":"Point"}
}