{
  "type": "Feature",
  "properties": {
    "iso:country":"US",
    "sg:address":"36743 Groesbeck Hwy",
    "sg:city":"Clinton Twp",
    "sg:classifiers":[
        {
            "category":"Shopping",
            "type":"Retail Goods"
        }
    ],
    "sg:phone":"+1 586 790 7410",
    "sg:postcode":"48035",
    "sg:province":"MI",
    "sg:tags":[
        "wedding",
        "supply"
    ],
    "wof:name":"Wedding Cakes By Arlene",
    "wof:placetype":"venue"
},
  "geometry": {"coordinates":[-82.912342,42.569137],"type":"Point"}
}