{
  "type": "Feature",
  "properties": {
    "iso:country":"US",
    "sg:address":"29331 Warren Rd",
    "sg:city":"Garden City",
    "sg:classifiers":[
        {
            "category":"Food & Beverages",
            "subcategory":"Groceries & Convenience Stores",
            "type":"Retail Goods"
        }
    ],
    "sg:phone":"+1 734 522 8720",
    "sg:postcode":"48135",
    "sg:province":"MI",
    "sg:website":"www.7-eleven.com",
    "wof:name":"7-Eleven",
    "wof:placetype":"venue"
},
  "geometry": {"coordinates":[-83.331873,42.339837],"type":"Point"}
}