{
  "type": "Feature",
  "properties": {
    "iso:country":"US",
    "sg:address":"32802 Franklin Rd",
    "sg:city":"Franklin",
    "sg:classifiers":[
        {
            "category":"Education",
            "subcategory":"Special Training",
            "type":"Public Place"
        }
    ],
    "sg:phone":"+1 248 932 3474",
    "sg:postcode":"48025",
    "sg:province":"MI",
    "sg:tags":[
        "clinic"
    ],
    "wof:name":"Cheer Michigan Enterprises",
    "wof:placetype":"venue"
},
  "geometry": {"coordinates":[-83.30595099999999,42.528101],"type":"Point"}
}