{
  "type": "Feature",
  "properties": {
    "iso:country":"US",
    "sg:address":"951 112th Ave",
    "sg:city":"Martin",
    "sg:classifiers":[
        {
            "category":"Building & Trades",
            "subcategory":"Construction",
            "type":"Services"
        }
    ],
    "sg:phone":"+1 269 685 0123",
    "sg:postcode":"49070",
    "sg:province":"MI",
    "sg:tags":[
        "house"
    ],
    "wof:name":"Hildebrand Construction",
    "wof:placetype":"venue"
},
  "geometry": {"coordinates":[-85.637484,42.508353],"type":"Point"}
}