{
  "type": "Feature",
  "properties": {
    "iso:country":"US",
    "sg:address":"1871 Birchwood Dr",
    "sg:city":"Troy",
    "sg:classifiers":[
        {
            "category":"Retail",
            "subcategory":"Auto Repair",
            "type":"Services"
        }
    ],
    "sg:phone":"+1 248 680 0540",
    "sg:postcode":"48083",
    "sg:province":"MI",
    "sg:tags":[
        "wrecker"
    ],
    "wof:name":"Coleman's Towing & Recovery",
    "wof:placetype":"venue"
},
  "geometry": {"coordinates":[-83.111362,42.550809],"type":"Point"}
}