{
  "type": "Feature",
  "properties": {
    "iso:country":"US",
    "sg:address":"5655 Woodland Pass",
    "sg:city":"Bloomfield Hills",
    "sg:classifiers":[
        {
            "category":"Manufacturing",
            "subcategory":"Tools & Machinery",
            "type":"Manufacturing & Wholesale Goods"
        }
    ],
    "sg:phone":"+1 248 855 2215",
    "sg:postcode":"48301",
    "sg:province":"MI",
    "sg:tags":[
        "die",
        "maker"
    ],
    "wof:name":"Willie Horton Inc Technologies",
    "wof:placetype":"venue"
},
  "geometry": {"coordinates":[-83.286697,42.557627],"type":"Point"}
}