{
  "type": "Feature",
  "properties": {
    "iso:country":"US",
    "sg:address":"10915 Newcosta Ave",
    "sg:city":"Pierson",
    "sg:classifiers":[
        {
            "category":"Professional",
            "subcategory":"Engineering",
            "type":"Services"
        }
    ],
    "sg:phone":"+1 231 937 6528",
    "sg:postcode":"49339",
    "sg:province":"MI",
    "wof:name":"Buckowing & Associates",
    "wof:placetype":"venue"
},
  "geometry": {"coordinates":[-85.562726,43.359435],"type":"Point"}
}