{
  "type": "Feature",
  "properties": {
    "iso:country":"US",
    "sg:address":"26333 Jefferson Ave",
    "sg:city":"Saint Clair Shores",
    "sg:classifiers":[
        {
            "category":"Professional",
            "subcategory":"Accounting & Tax Preparation",
            "type":"Services"
        }
    ],
    "sg:phone":"+1 586 773 7720",
    "sg:postcode":"48081",
    "sg:province":"MI",
    "sg:tags":[
        "accountant"
    ],
    "wof:name":"Ricci Robert F CPA",
    "wof:placetype":"venue"
},
  "geometry": {"coordinates":[-82.88922100000001,42.484842],"type":"Point"}
}