{
  "type": "Feature",
  "properties": {
    "iso:country":"US",
    "sg:address":"1402 Hudson Rd",
    "sg:city":"Hillsdale",
    "sg:classifiers":[
        {
            "category":"Organizations",
            "subcategory":"Religious Organization",
            "type":"Services"
        }
    ],
    "sg:phone":"+1 517 437 3402",
    "sg:postcode":"49242",
    "sg:province":"MI",
    "wof:name":"First Church Christ Scientist",
    "wof:placetype":"venue"
},
  "geometry": {"coordinates":[-84.623994,41.904092],"type":"Point"}
}