{
  "type": "Feature",
  "properties": {
    "iso:country":"US",
    "sg:address":"5531 28th St SE",
    "sg:city":"Grand Rapids",
    "sg:classifiers":[
        {
            "category":"Retail",
            "subcategory":"Portrait Studio",
            "type":"Services"
        }
    ],
    "sg:phone":"+1 616 975 9856",
    "sg:postcode":"49512",
    "sg:province":"MI",
    "sg:tags":[
        "photographer"
    ],
    "wof:name":"Olan Mills",
    "wof:placetype":"venue"
},
  "geometry": {"coordinates":[-85.53330699999999,42.912957],"type":"Point"}
}