{
  "type": "Feature",
  "properties": {
    "iso:country":"US",
    "sg:address":"182 Parkside Ct",
    "sg:city":"Saginaw",
    "sg:classifiers":[
        {
            "category":"Professional",
            "type":"Services"
        }
    ],
    "sg:phone":"+1 989 771 5510",
    "sg:postcode":"48601",
    "sg:province":"MI",
    "sg:tags":[
        "establishment"
    ],
    "wof:name":"Demante's Delights",
    "wof:placetype":"venue"
},
  "geometry": {"coordinates":[-83.956119,43.389884],"type":"Point"}
}