{
  "type": "Feature",
  "properties": {
    "iso:country":"US",
    "sg:address":"800 W State Rd 727",
    "sg:city":"Angola",
    "sg:classifiers":[
        {
            "category":"Food & Beverages",
            "subcategory":"Groceries & Convenience Stores",
            "type":"Retail Goods"
        }
    ],
    "sg:phone":"+1 260 833 3028",
    "sg:postcode":"46703",
    "sg:province":"MI",
    "wof:name":"Pokagon General Store",
    "wof:placetype":"venue"
},
  "geometry": {"coordinates":[-85.007791,41.707218],"type":"Point"}
}