{
  "type": "Feature",
  "properties": {
    "iso:country":"US",
    "sg:address":"113 Main St",
    "sg:city":"East Jordan",
    "sg:classifiers":[
        {
            "category":"Professional",
            "type":"Services"
        }
    ],
    "sg:phone":"+1 231 536 9835",
    "sg:postcode":"49727",
    "sg:province":"MI",
    "sg:tags":[
        "establishment"
    ],
    "wof:name":"Gatherings",
    "wof:placetype":"venue"
},
  "geometry": {"coordinates":[-85.127672,45.155235],"type":"Point"}
}