{
  "type": "Feature",
  "properties": {
    "iso:country":"US",
    "sg:address":"319 W Main St",
    "sg:city":"Stanton",
    "sg:classifiers":[
        {
            "category":"Restaurant",
            "type":"Food & Drink"
        }
    ],
    "sg:menulink":"http://www.allmenus.com/mi/stanton/146415-subway/menu/",
    "sg:phone":"+1 989 831 8171",
    "sg:postcode":"48888",
    "sg:province":"MI",
    "sg:tags":[
        "american",
        "sandwich"
    ],
    "wof:name":"Subway",
    "wof:placetype":"venue"
},
  "geometry": {"coordinates":[-85.084152,43.292569],"type":"Point"}
}