{
  "type": "Feature",
  "properties": {
    "iso:country":"US",
    "sg:address":"29131 Shenandoah Dr",
    "sg:city":"Farmington",
    "sg:classifiers":[
        {
            "category":"Manufacturing",
            "subcategory":"Jewelry",
            "type":"Manufacturing & Wholesale Goods"
        }
    ],
    "sg:phone":"+1 248 489 5417",
    "sg:postcode":"48331",
    "sg:province":"MI",
    "sg:tags":[
        "material",
        "mfg"
    ],
    "wof:name":"Lambert Ro Designs",
    "wof:placetype":"venue"
},
  "geometry": {"coordinates":[-83.411952,42.506704],"type":"Point"}
}