{
  "type": "Feature",
  "properties": {
    "iso:country":"US",
    "sg:address":"2339 Monica Ln",
    "sg:city":"Muskegon",
    "sg:classifiers":[
        {
            "category":"Building & Trades",
            "subcategory":"Construction",
            "type":"Services"
        }
    ],
    "sg:phone":"+1 231 744 0606",
    "sg:postcode":"49442",
    "sg:province":"MI",
    "sg:tags":[
        "contractor"
    ],
    "wof:name":"Harbor Construction Co",
    "wof:placetype":"venue"
},
  "geometry": {"coordinates":[-86.185914,43.24048],"type":"Point"}
}