{
  "type": "Feature",
  "properties": {
    "iso:country":"US",
    "sg:address":"11447 Waterman Rd",
    "sg:city":"Brooklyn",
    "sg:classifiers":[
        {
            "category":"Building & Trades",
            "subcategory":"Construction",
            "type":"Services"
        }
    ],
    "sg:phone":"+1 517 592 4639",
    "sg:postcode":"49230",
    "sg:province":"MI",
    "sg:tags":[
        "house"
    ],
    "wof:name":"Arvidson Construction",
    "wof:placetype":"venue"
},
  "geometry": {"coordinates":[-84.19623300000001,42.109594],"type":"Point"}
}