{
  "type": "Feature",
  "properties": {
    "iso:country":"US",
    "sg:address":"127 E Superior St",
    "sg:city":"Munising",
    "sg:classifiers":[
        {
            "category":"Bars & Pubs",
            "type":"Food & Drink"
        }
    ],
    "sg:phone":"+1 906 387 3737",
    "sg:postcode":"49862",
    "sg:province":"MI",
    "wof:name":"Mac's Hideway North",
    "wof:placetype":"venue"
},
  "geometry": {"coordinates":[-86.655378,46.410568],"type":"Point"}
}