{
  "type": "Feature",
  "properties": {
    "iso:country":"US",
    "sg:address":"17592 S Simonsen Rd",
    "sg:city":"Barbeau",
    "sg:classifiers":[
        {
            "category":"Professional",
            "subcategory":"Employment Agencies",
            "type":"Services"
        }
    ],
    "sg:phone":"+1 906 635 0941",
    "sg:postcode":"49710",
    "sg:province":"MI",
    "sg:tags":[
        "ferry",
        "operation",
        "help",
        "supply"
    ],
    "wof:name":"Schallips Inc",
    "wof:placetype":"venue"
},
  "geometry": {"coordinates":[-84.175117,46.251498],"type":"Point"}
}