{
  "type": "Feature",
  "properties": {
    "iso:country":"US",
    "sg:address":"2826 S Lakeshore Dr",
    "sg:city":"Saint Joseph",
    "sg:classifiers":[
        {
            "category":"Real Estate",
            "subcategory":"Developer",
            "type":"Services"
        }
    ],
    "sg:phone":"+1 269 429 4506",
    "sg:postcode":"49085",
    "sg:province":"MI",
    "wof:name":"Harbor Area Properties",
    "wof:placetype":"venue"
},
  "geometry": {"coordinates":[-86.50866600000001,42.066757],"type":"Point"}
}