{
  "type": "Feature",
  "properties": {
    "iso:country":"US",
    "sg:address":"1221 Richardson St",
    "sg:city":"Port Huron",
    "sg:classifiers":[
        {
            "category":"Health Services",
            "subcategory":"Doctor",
            "type":"Services"
        }
    ],
    "sg:phone":"+1 810 985 9898",
    "sg:postcode":"48060",
    "sg:province":"MI",
    "sg:tags":[
        "medical"
    ],
    "wof:name":"Blue Water Vascular Clinic",
    "wof:placetype":"venue"
},
  "geometry": {"coordinates":[-82.431974,42.987565],"type":"Point"}
}