{
  "type": "Feature",
  "properties": {
    "iso:country":"US",
    "sg:address":"6633 Allar Dr",
    "sg:city":"Sterling Heights",
    "sg:classifiers":[
        {
            "category":"Manufacturing",
            "subcategory":"Metals",
            "type":"Manufacturing & Wholesale Goods"
        }
    ],
    "sg:phone":"+1 586 268 9600",
    "sg:postcode":"48312",
    "sg:province":"MI",
    "sg:tags":[
        "tool"
    ],
    "sg:website":"www.edwardandrews.com",
    "wof:name":"Edward Andrews Intl",
    "wof:placetype":"venue"
},
  "geometry": {"coordinates":[-83.04137799999999,42.554678],"type":"Point"}
}