{
  "type": "Feature",
  "properties": {
    "iso:country":"US",
    "sg:address":"2761 Harvest Meadow",
    "sg:city":"Brighton",
    "sg:classifiers":[
        {
            "category":"Wholesale",
            "subcategory":"Chemicals & Plastics",
            "type":"Manufacturing & Wholesale Goods"
        }
    ],
    "sg:phone":"+1 810 225 1826",
    "sg:postcode":"48114",
    "sg:province":"MI",
    "wof:name":"Monaco Sales",
    "wof:placetype":"venue"
},
  "geometry": {"coordinates":[-83.721926,42.566009],"type":"Point"}
}