{
  "type": "Feature",
  "properties": {
    "iso:country":"US",
    "sg:address":"5165 Prentis Dr",
    "sg:city":"Troy",
    "sg:classifiers":[
        {
            "category":"Retail",
            "subcategory":"Repair Shop",
            "type":"Services"
        }
    ],
    "sg:phone":"+1 248 689 0558",
    "sg:postcode":"48085",
    "sg:province":"MI",
    "sg:tags":[
        "personal"
    ],
    "wof:name":"Lin Win Enterprises",
    "wof:placetype":"venue"
},
  "geometry": {"coordinates":[-83.118578,42.592831],"type":"Point"}
}