{
  "type": "Feature",
  "properties": {
    "iso:country":"US",
    "sg:address":"18230 Grand River Ave",
    "sg:city":"Detroit",
    "sg:classifiers":[
        {
            "category":"Sports & Exercise",
            "subcategory":"Gym",
            "type":"Entertainment"
        }
    ],
    "sg:phone":"+1 313 397 3615",
    "sg:postcode":"48223",
    "sg:province":"MI",
    "sg:website":"www.powerhousegym.com",
    "wof:name":"Powerhouse Gym",
    "wof:placetype":"venue"
},
  "geometry": {"coordinates":[-83.220247,42.401651],"type":"Point"}
}