{
  "type": "Feature",
  "properties": {
    "iso:country":"US",
    "sg:address":"1856 Elk Ln",
    "sg:city":"Okemos",
    "sg:classifiers":[
        {
            "category":"Professional",
            "type":"Services"
        }
    ],
    "sg:phone":"+1 517 347 0244",
    "sg:postcode":"48864",
    "sg:province":"MI",
    "wof:name":"Written Procedure Svc",
    "wof:placetype":"venue"
},
  "geometry": {"coordinates":[-84.41664900000001,42.684576],"type":"Point"}
}