{
  "type": "Feature",
  "properties": {
    "iso:country":"US",
    "sg:address":"24395 Lois Ln",
    "sg:city":"Southfield",
    "sg:classifiers":[
        {
            "category":"Building & Trades",
            "subcategory":"Construction",
            "type":"Services"
        }
    ],
    "sg:phone":"+1 248 354 2355",
    "sg:postcode":"48075",
    "sg:province":"MI",
    "sg:tags":[
        "residential"
    ],
    "wof:name":"Red Top Enterprises",
    "wof:placetype":"venue"
},
  "geometry": {"coordinates":[-83.25743199999999,42.470919],"type":"Point"}
}