{
  "type": "Feature",
  "properties": {
    "iso:country":"US",
    "sg:address":"5242 S 11th St",
    "sg:city":"Kalamazoo",
    "sg:classifiers":[
        {
            "category":"Building & Trades",
            "subcategory":"Construction",
            "type":"Services"
        }
    ],
    "sg:phone":"+1 269 353 6960",
    "sg:postcode":"49009",
    "sg:province":"MI",
    "sg:tags":[
        "downspouts",
        "gutter"
    ],
    "wof:name":"Shugars Gutter Svc Inc",
    "wof:placetype":"venue"
},
  "geometry": {"coordinates":[-85.658019,42.243413],"type":"Point"}
}