{
  "type": "Feature",
  "properties": {
    "iso:country":"US",
    "sg:address":"7095 Park Rd",
    "sg:city":"Ann Arbor",
    "sg:classifiers":[
        {
            "category":"Real Estate",
            "subcategory":"Real Estate Operator",
            "type":"Services"
        }
    ],
    "sg:phone":"+1 734 665 9050",
    "sg:postcode":"48103",
    "sg:province":"MI",
    "sg:tags":[
        "property",
        "lessor"
    ],
    "wof:name":"Uphaus Farms Inc",
    "wof:placetype":"venue"
},
  "geometry": {"coordinates":[-83.872499,42.276955],"type":"Point"}
}