{
  "type": "Feature",
  "properties": {
    "iso:country":"US",
    "sg:address":"962 Industrial Pkwy",
    "sg:city":"Plainwell",
    "sg:classifiers":[
        {
            "category":"Insurance",
            "subcategory":"Insurance Agent",
            "type":"Services"
        }
    ],
    "sg:phone":"+1 269 685 9654",
    "sg:postcode":"49080",
    "sg:province":"MI",
    "wof:name":"Baker Agency",
    "wof:placetype":"venue"
},
  "geometry": {"coordinates":[-85.62495800000001,42.448073],"type":"Point"}
}