{
  "type": "Feature",
  "properties": {
    "iso:country":"US",
    "sg:address":"715 Ashman St",
    "sg:city":"Midland",
    "sg:classifiers":[
        {
            "category":"Personal",
            "subcategory":"Beauty Salon",
            "type":"Services"
        }
    ],
    "sg:phone":"+1 989 837 8711",
    "sg:postcode":"48640",
    "sg:province":"MI",
    "sg:tags":[
        "shop"
    ],
    "wof:name":"Allure Styling Studio",
    "wof:placetype":"venue"
},
  "geometry": {"coordinates":[-84.239665,43.617455],"type":"Point"}
}