{
  "type": "Feature",
  "properties": {
    "iso:country":"US",
    "sg:address":"21400 E 11 Mile Rd",
    "sg:city":"Saint Clair Shores",
    "sg:classifiers":[
        {
            "category":"Health Services",
            "subcategory":"Doctor",
            "type":"Services"
        }
    ],
    "sg:phone":"+1 586 498 4400",
    "sg:postcode":"48081",
    "sg:province":"MI",
    "sg:tags":[
        "practice",
        "family"
    ],
    "wof:name":"Rollinger Kathleen DO",
    "wof:placetype":"venue"
},
  "geometry": {"coordinates":[-82.898697,42.495602],"type":"Point"}
}