{
  "type": "Feature",
  "properties": {
    "iso:country":"US",
    "sg:address":"5605 Galbraith Line Rd",
    "sg:city":"Croswell",
    "sg:classifiers":[
        {
            "category":"Retail",
            "subcategory":"Portrait Studio",
            "type":"Services"
        }
    ],
    "sg:phone":"+1 810 679 3992",
    "sg:postcode":"48422",
    "sg:province":"MI",
    "sg:tags":[
        "photo",
        "consulting",
        "management",
        "bu"
    ],
    "wof:name":"Total Entertainment",
    "wof:placetype":"venue"
},
  "geometry": {"coordinates":[-82.594007,43.194805],"type":"Point"}
}