{
  "type": "Feature",
  "properties": {
    "iso:country":"US",
    "sg:address":"7811 Easton Rd",
    "sg:city":"New Lothrop",
    "sg:classifiers":[
        {
            "category":"Professional",
            "type":"Services"
        }
    ],
    "sg:phone":"+1 810 638 5466",
    "sg:postcode":"48460",
    "sg:province":"MI",
    "wof:name":"Dollmakers",
    "wof:placetype":"venue"
},
  "geometry": {"coordinates":[-84.01908299999999,43.116635],"type":"Point"}
}