{
  "type": "Feature",
  "properties": {
    "iso:country":"US",
    "sg:address":"2919 Sturm Rd",
    "sg:city":"Pigeon",
    "sg:classifiers":[
        {
            "category":"Personal",
            "subcategory":"Beauty Salon",
            "type":"Services"
        }
    ],
    "sg:phone":"+1 989 453 3868",
    "sg:postcode":"48755",
    "sg:province":"MI",
    "sg:tags":[
        "shop"
    ],
    "wof:name":"Peggys Cut n Curl",
    "wof:placetype":"venue"
},
  "geometry": {"coordinates":[-83.260688,43.86157],"type":"Point"}
}