{
  "type": "Feature",
  "properties": {
    "iso:country":"US",
    "sg:address":"254 Colfax Ave",
    "sg:city":"Benton Harbor",
    "sg:classifiers":[
        {
            "category":"Organizations",
            "subcategory":"Labor Organization",
            "type":"Services"
        }
    ],
    "sg:phone":"+1 269 934 7051",
    "sg:postcode":"49022",
    "sg:province":"MI",
    "wof:name":"IAMAW",
    "wof:placetype":"venue"
},
  "geometry": {"coordinates":[-86.456199,42.113011],"type":"Point"}
}