{
  "type": "Feature",
  "properties": {
    "iso:country":"US",
    "sg:address":"101 Rich Ln",
    "sg:city":"Battle Creek",
    "sg:classifiers":[
        {
            "category":"Insurance",
            "subcategory":"Insurance Agent",
            "type":"Services"
        }
    ],
    "sg:phone":"+1 269 962 0792",
    "sg:postcode":"49015",
    "sg:province":"MI",
    "wof:name":"Safeware The Insurance Agency",
    "wof:placetype":"venue"
},
  "geometry": {"coordinates":[-85.20453999999999,42.284009],"type":"Point"}
}