{
  "type": "Feature",
  "properties": {
    "iso:country":"US",
    "sg:address":"18479 Mack Ave",
    "sg:city":"Grosse Pointe",
    "sg:classifiers":[
        {
            "category":"Retail",
            "subcategory":"Veterinary Services",
            "type":"Services"
        }
    ],
    "sg:phone":"+1 313 882 3026",
    "sg:postcode":"48236",
    "sg:province":"MI",
    "sg:tags":[
        "veterinarian"
    ],
    "wof:name":"Alexander J E DVM",
    "wof:placetype":"venue"
},
  "geometry": {"coordinates":[-82.913399,42.410999],"type":"Point"}
}