{
  "type": "Feature",
  "properties": {
    "iso:country":"US",
    "sg:address":"8598 Paradise Trl",
    "sg:city":"Carp Lake",
    "sg:classifiers":[
        {
            "category":"Travel",
            "subcategory":"Hotels & Motels",
            "type":"Entertainment"
        }
    ],
    "sg:phone":"+1 231 537 2121",
    "sg:postcode":"49718",
    "sg:province":"MI",
    "sg:tags":[
        "operation"
    ],
    "wof:name":"Anchor Lights Resort",
    "wof:placetype":"venue"
},
  "geometry": {"coordinates":[-84.738365,45.6987],"type":"Point"}
}