{
  "type": "Feature",
  "properties": {
    "iso:country":"US",
    "sg:address":"406 6th St",
    "sg:city":"Calumet",
    "sg:classifiers":[
        {
            "category":"Professional",
            "subcategory":"Business Services",
            "type":"Services"
        }
    ],
    "sg:phone":"+1 906 337 0760",
    "sg:postcode":"49913",
    "sg:province":"MI",
    "sg:tags":[
        "record",
        "document"
    ],
    "wof:name":"Keweenaw Shredding Co Inc",
    "wof:placetype":"venue"
},
  "geometry": {"coordinates":[-88.453686,47.248216],"type":"Point"}
}