{
  "type": "Feature",
  "properties": {
    "iso:country":"US",
    "sg:address":"2772 Mayfair Dr",
    "sg:city":"Troy",
    "sg:classifiers":[
        {
            "category":"Professional",
            "type":"Services"
        }
    ],
    "sg:phone":"+1 248 649 2773",
    "sg:postcode":"48084",
    "sg:province":"MI",
    "wof:name":"Donald C Ross M D",
    "wof:placetype":"venue"
},
  "geometry": {"coordinates":[-83.194941,42.558917],"type":"Point"}
}