{
  "type": "Feature",
  "properties": {
    "iso:country":"US",
    "sg:address":"625 Kenyon Dr",
    "sg:city":"Troy",
    "sg:classifiers":[
        {
            "category":"Building & Trades",
            "subcategory":"Construction",
            "type":"Services"
        }
    ],
    "sg:phone":"+1 248 588 2890",
    "sg:postcode":"48083",
    "sg:province":"MI",
    "sg:tags":[
        "paving",
        "contractor"
    ],
    "wof:name":"Bowen Paving Inc",
    "wof:placetype":"venue"
},
  "geometry": {"coordinates":[-83.125068,42.539658],"type":"Point"}
}