{
  "type": "Feature",
  "properties": {
    "iso:country":"US",
    "sg:address":"2314 Pine Orchard Dr",
    "sg:city":"Waterford",
    "sg:classifiers":[
        {
            "category":"Professional",
            "subcategory":"Management & Consulting",
            "type":"Services"
        }
    ],
    "sg:phone":"+1 248 673 6373",
    "sg:postcode":"48329",
    "sg:province":"MI",
    "sg:tags":[
        "consultant"
    ],
    "wof:name":"D D Nance Consultants",
    "wof:placetype":"venue"
},
  "geometry": {"coordinates":[-83.36374499999999,42.673974],"type":"Point"}
}