{
  "type": "Feature",
  "properties": {
    "iso:country":"US",
    "sg:address":"5700 N Gleaner Rd",
    "sg:city":"Freeland",
    "sg:classifiers":[
        {
            "category":"Organizations",
            "subcategory":"Religious Organization",
            "type":"Services"
        }
    ],
    "sg:phone":"+1 989 751 2191",
    "sg:postcode":"48623",
    "sg:province":"MI",
    "wof:name":"Eye Witness",
    "wof:placetype":"venue"
},
  "geometry": {"coordinates":[-84.15047800000001,43.489903],"type":"Point"}
}