{
  "type": "Feature",
  "properties": {
    "iso:country":"US",
    "sg:address":"6091 Franklin Rd",
    "sg:city":"Bloomfield Hills",
    "sg:classifiers":[
        {
            "category":"Health Services",
            "subcategory":"Doctor",
            "type":"Services"
        }
    ],
    "sg:phone":"+1 248 737 6853",
    "sg:postcode":"48301",
    "sg:province":"MI",
    "sg:tags":[
        "medical"
    ],
    "wof:name":"Michigan Hematology Onocology",
    "wof:placetype":"venue"
},
  "geometry": {"coordinates":[-83.30249499999999,42.549063],"type":"Point"}
}