{
  "type": "Feature",
  "properties": {
    "iso:country":"US",
    "sg:address":"1755 S Mitchell St",
    "sg:city":"Cadillac",
    "sg:classifiers":[
        {
            "category":"Manufacturing",
            "subcategory":"Lumber",
            "type":"Manufacturing & Wholesale Goods"
        }
    ],
    "sg:phone":"+1 231 775 2421",
    "sg:postcode":"49601",
    "sg:province":"MI",
    "sg:tags":[
        "government"
    ],
    "wof:name":"US Forest Svc Supervisor",
    "wof:placetype":"venue"
},
  "geometry": {"coordinates":[-85.396321,44.234051],"type":"Point"}
}