{
  "type": "Feature",
  "properties": {
    "iso:country":"US",
    "sg:address":"68286 S Main St",
    "sg:city":"Richmond",
    "sg:classifiers":[
        {
            "category":"Home & Garden",
            "subcategory":"Furniture",
            "type":"Retail Goods"
        }
    ],
    "sg:phone":"+1 586 727 0400",
    "sg:postcode":"48062",
    "sg:province":"MI",
    "wof:name":"J Alan Furniture",
    "wof:placetype":"venue"
},
  "geometry": {"coordinates":[-82.74966000000001,42.802878],"type":"Point"}
}