{
  "type": "Feature",
  "properties": {
    "iso:country":"US",
    "sg:address":"2340 Chicago Dr",
    "sg:city":"Hudsonville",
    "sg:classifiers":[
        {
            "category":"Retail",
            "subcategory":"Photofinishing",
            "type":"Services"
        }
    ],
    "sg:phone":"+1 616 669 7188",
    "sg:postcode":"49426",
    "sg:province":"MI",
    "sg:tags":[
        "photo",
        "finishing",
        "photographic",
        "lab"
    ],
    "wof:name":"Portraits By The Artists",
    "wof:placetype":"venue"
},
  "geometry": {"coordinates":[-85.84303300000001,42.880559],"type":"Point"}
}