{
  "type": "Feature",
  "properties": {
    "iso:country":"US",
    "sg:address":"1640 S Greenfield Cir NE",
    "sg:city":"Grand Rapids",
    "sg:classifiers":[
        {
            "category":"Real Estate",
            "subcategory":"Real Estate Operator",
            "type":"Services"
        }
    ],
    "sg:phone":"+1 616 774 0443",
    "sg:postcode":"49505",
    "sg:province":"MI",
    "sg:tags":[
        "building",
        "apartment"
    ],
    "wof:name":"Greenfield Apartments",
    "wof:placetype":"venue"
},
  "geometry": {"coordinates":[-85.62567199999999,42.986436],"type":"Point"}
}