{
  "type": "Feature",
  "properties": {
    "iso:country":"US",
    "sg:address":"5561 Dixie Hwy",
    "sg:city":"Saginaw",
    "sg:classifiers":[
        {
            "category":"Autos & Motor Vehicles",
            "subcategory":"Automobile Sales",
            "type":"Retail Goods"
        }
    ],
    "sg:phone":"+1 989 777 5200",
    "sg:postcode":"48601",
    "sg:province":"MI",
    "sg:tags":[
        "car",
        "dealer"
    ],
    "wof:name":"R L Co",
    "wof:placetype":"venue"
},
  "geometry": {"coordinates":[-83.896019,43.379042],"type":"Point"}
}