{
  "type": "Feature",
  "properties": {
    "iso:country":"US",
    "sg:address":"2816 S Thomas Rd",
    "sg:city":"Bad Axe",
    "sg:classifiers":[
        {
            "category":"Professional",
            "type":"Services"
        }
    ],
    "sg:phone":"+1 989 269 7013",
    "sg:postcode":"48413",
    "sg:province":"MI",
    "wof:name":"Richard Koroleski",
    "wof:placetype":"venue"
},
  "geometry": {"coordinates":[-83.039333,43.755681],"type":"Point"}
}