{
  "type": "Feature",
  "properties": {
    "iso:country":"US",
    "sg:address":"301 Maplewood St",
    "sg:city":"Greenville",
    "sg:classifiers":[
        {
            "category":"Professional",
            "subcategory":"Accounting & Tax Preparation",
            "type":"Services"
        }
    ],
    "sg:phone":"+1 616 754 2281",
    "sg:postcode":"48838",
    "sg:province":"MI",
    "sg:tags":[
        "return",
        "filing"
    ],
    "wof:name":"H & R Block Tax Svc",
    "wof:placetype":"venue"
},
  "geometry": {"coordinates":[-85.275729,43.179804],"type":"Point"}
}