{
  "type": "Feature",
  "properties": {
    "iso:country":"US",
    "sg:address":"3300 General Motors Rd",
    "sg:city":"Milford",
    "sg:classifiers":[
        {
            "category":"Professional",
            "subcategory":"Employment Agencies",
            "type":"Services"
        }
    ],
    "sg:phone":"+1 248 684 7981",
    "sg:postcode":"48380",
    "sg:province":"MI",
    "sg:tags":[
        "opportunity"
    ],
    "wof:name":"Manpower Metro Detroit",
    "wof:placetype":"venue"
},
  "geometry": {"coordinates":[-83.657691,42.578004],"type":"Point"}
}