{
  "type": "Feature",
  "properties": {
    "iso:country":"US",
    "sg:address":"110 E Hampton St",
    "sg:city":"Marquette",
    "sg:classifiers":[
        {
            "category":"Insurance",
            "subcategory":"Insurance Agent",
            "type":"Services"
        }
    ],
    "sg:phone":"+1 906 225 1329",
    "sg:postcode":"49855",
    "sg:province":"MI",
    "sg:tags":[
        "adjuster"
    ],
    "wof:name":"Crawford & Co",
    "wof:placetype":"venue"
},
  "geometry": {"coordinates":[-87.396208,46.531519],"type":"Point"}
}