{
  "type": "Feature",
  "properties": {
    "iso:country":"US",
    "sg:address":"915 E Front St",
    "sg:city":"Monroe",
    "sg:classifiers":[
        {
            "category":"Government",
            "subcategory":"Office",
            "type":"Public Place"
        }
    ],
    "sg:phone":"+1 734 241 5947",
    "sg:postcode":"48161",
    "sg:province":"MI",
    "sg:tags":[
        "village"
    ],
    "wof:name":"Monroe City Water Filtration",
    "wof:placetype":"venue"
},
  "geometry": {"coordinates":[-83.38508400000001,41.911946],"type":"Point"}
}