{
  "type": "Feature",
  "properties": {
    "iso:country":"US",
    "sg:address":"2049 Granite Ave",
    "sg:city":"Marquette",
    "sg:classifiers":[
        {
            "category":"Building & Trades",
            "subcategory":"Construction",
            "type":"Services"
        }
    ],
    "sg:phone":"+1 906 226 3382",
    "sg:postcode":"49855",
    "sg:province":"MI",
    "sg:tags":[
        "home",
        "builder"
    ],
    "wof:name":"Piirala Builders",
    "wof:placetype":"venue"
},
  "geometry": {"coordinates":[-87.42924499999999,46.56675],"type":"Point"}
}