{
  "type": "Feature",
  "properties": {
    "iso:country":"US",
    "sg:address":"917 S Burdick St",
    "sg:city":"Kalamazoo",
    "sg:classifiers":[
        {
            "category":"Retail",
            "subcategory":"Funeral Services",
            "type":"Services"
        }
    ],
    "sg:phone":"+1 269 343 2628",
    "sg:postcode":"49001",
    "sg:province":"MI",
    "sg:tags":[
        "mortician"
    ],
    "wof:name":"Joldersma & Klein Funeral Home",
    "wof:placetype":"venue"
},
  "geometry": {"coordinates":[-85.582877,42.282591],"type":"Point"}
}