{
  "type": "Feature",
  "properties": {
    "iso:country":"US",
    "sg:address":"150 Sunday Dr",
    "sg:city":"Lincoln",
    "sg:classifiers":[
        {
            "category":"Building & Trades",
            "subcategory":"Electrical",
            "type":"Services"
        }
    ],
    "sg:phone":"+1 989 736 6361",
    "sg:postcode":"48740",
    "sg:province":"MI",
    "sg:tags":[
        "electric",
        "contractor"
    ],
    "wof:name":"Cordes Electric Inc",
    "wof:placetype":"venue"
},
  "geometry": {"coordinates":[-83.451064,44.650152],"type":"Point"}
}