{
  "type": "Feature",
  "properties": {
    "iso:country":"US",
    "sg:address":"3420 Remembrance Rd NW",
    "sg:city":"Grand Rapids",
    "sg:classifiers":[
        {
            "category":"Banks & Credit Unions",
            "subcategory":"Bank",
            "type":"Services"
        }
    ],
    "sg:phone":"+1 616 771 6253",
    "sg:postcode":"49534",
    "sg:province":"MI",
    "sg:tags":[
        "national"
    ],
    "wof:name":"Huntington National Bank",
    "wof:placetype":"venue"
},
  "geometry": {"coordinates":[-85.753675,42.990727],"type":"Point"}
}