{
  "type": "Feature",
  "properties": {
    "iso:country":"US",
    "sg:address":"10114 Ridge Rd",
    "sg:city":"Goodrich",
    "sg:classifiers":[
        {
            "category":"Professional",
            "type":"Services"
        }
    ],
    "sg:phone":"+1 810 636 3632",
    "sg:postcode":"48438",
    "sg:province":"MI",
    "wof:name":"JP Tree Service",
    "wof:placetype":"venue"
},
  "geometry": {"coordinates":[-83.503198,42.886668],"type":"Point"}
}