{
  "type": "Feature",
  "properties": {
    "iso:country":"US",
    "sg:address":"36549 Harper Ave",
    "sg:city":"Clinton Township",
    "sg:classifiers":[
        {
            "category":"Health Services",
            "subcategory":"Doctor",
            "type":"Services"
        }
    ],
    "sg:phone":"+1 586 791 3150",
    "sg:postcode":"48035",
    "sg:province":"MI",
    "sg:tags":[
        "osteopathic"
    ],
    "wof:name":"Przybylski Albert DO",
    "wof:placetype":"venue"
},
  "geometry": {"coordinates":[-82.871498,42.566502],"type":"Point"}
}