{
  "type": "Feature",
  "properties": {
    "iso:country":"US",
    "sg:address":"26400 Sherwood Ave",
    "sg:city":"Warren",
    "sg:classifiers":[
        {
            "category":"Building & Trades",
            "subcategory":"Construction",
            "type":"Services"
        }
    ],
    "sg:phone":"+1 717 796 1158",
    "sg:postcode":"48091",
    "sg:province":"MI",
    "sg:tags":[
        "contractor"
    ],
    "wof:name":"Angelo Iafrate Construction Co",
    "wof:placetype":"venue"
},
  "geometry": {"coordinates":[-83.041496,42.487202],"type":"Point"}
}