{
  "type": "Feature",
  "properties": {
    "iso:country":"US",
    "sg:address":"45214 Hecker Dr",
    "sg:city":"Utica",
    "sg:classifiers":[
        {
            "category":"Building & Trades",
            "subcategory":"Cleaning & Sanitation",
            "type":"Services"
        }
    ],
    "sg:phone":"+1 586 739 6493",
    "sg:postcode":"48317",
    "sg:province":"MI",
    "sg:tags":[
        "fire",
        "water",
        "restoration",
        "damage"
    ],
    "wof:name":"Ricketts' Restoration Inc",
    "wof:placetype":"venue"
},
  "geometry": {"coordinates":[-83.018925,42.627844],"type":"Point"}
}