{
  "type": "Feature",
  "properties": {
    "iso:country":"US",
    "sg:address":"1433 S Oak Rd",
    "sg:city":"Davison",
    "sg:classifiers":[
        {
            "category":"Professional",
            "subcategory":"Business Services",
            "type":"Services"
        }
    ],
    "sg:phone":"+1 810 653 5088",
    "sg:postcode":"48423",
    "sg:province":"MI",
    "sg:tags":[
        "appraiser"
    ],
    "wof:name":"United 4 Appraisers LLC",
    "wof:placetype":"venue"
},
  "geometry": {"coordinates":[-83.497531,43.00996],"type":"Point"}
}