{
  "type": "Feature",
  "properties": {
    "iso:country":"US",
    "sg:address":"56 Hampton Rd",
    "sg:city":"Grosse Pointe",
    "sg:classifiers":[
        {
            "category":"Banks & Credit Unions",
            "subcategory":"Investment Brokerage",
            "type":"Services"
        }
    ],
    "sg:phone":"+1 313 884 6625",
    "sg:postcode":"48236",
    "sg:province":"MI",
    "sg:tags":[
        "security"
    ],
    "wof:name":"Schaeffner & Company Inc",
    "wof:placetype":"venue"
},
  "geometry": {"coordinates":[-82.87898800000001,42.441024],"type":"Point"}
}