{
  "type": "Feature",
  "properties": {
    "iso:country":"US",
    "sg:address":"13314 136th Ave",
    "sg:city":"Grand Haven",
    "sg:classifiers":[
        {
            "category":"Real Estate",
            "subcategory":"Architect",
            "type":"Services"
        }
    ],
    "sg:phone":"+1 616 847 3651",
    "sg:postcode":"49417",
    "sg:province":"MI",
    "sg:tags":[
        "architectural"
    ],
    "wof:name":"Home Plans & Designs",
    "wof:placetype":"venue"
},
  "geometry": {"coordinates":[-86.124534,43.011215],"type":"Point"}
}