{
  "type": "Feature",
  "properties": {
    "iso:country":"US",
    "sg:address":"225 E Main St",
    "sg:city":"Benton Harbor",
    "sg:classifiers":[
        {
            "category":"Personal",
            "subcategory":"Barber",
            "type":"Services"
        }
    ],
    "sg:phone":"+1 269 926 9686",
    "sg:postcode":"49022",
    "sg:province":"MI",
    "sg:tags":[
        "shop"
    ],
    "wof:name":"U Know Barber Shop",
    "wof:placetype":"venue"
},
  "geometry": {"coordinates":[-86.45360700000001,42.116427],"type":"Point"}
}