{
  "type": "Feature",
  "properties": {
    "iso:country":"US",
    "sg:address":"2775 State Hwy 32",
    "sg:city":"Alpena",
    "sg:classifiers":[
        {
            "category":"Retail",
            "subcategory":"Animal Services",
            "type":"Services"
        }
    ],
    "sg:phone":"+1 989 356 6399",
    "sg:postcode":"49707",
    "sg:province":"MI",
    "wof:name":"Pampered Pets Salon",
    "wof:placetype":"venue"
},
  "geometry": {"coordinates":[-83.509162,45.061335],"type":"Point"}
}