{
  "type": "Feature",
  "properties": {
    "iso:country":"US",
    "sg:address":"125 N Ortonville Rd",
    "sg:city":"Ortonville",
    "sg:classifiers":[
        {
            "category":"Insurance",
            "subcategory":"Insurance Agent",
            "type":"Services"
        }
    ],
    "sg:phone":"+1 248 627 2804",
    "sg:postcode":"48462",
    "sg:province":"MI",
    "wof:name":"Connie Brewer Insurance",
    "wof:placetype":"venue"
},
  "geometry": {"coordinates":[-83.45290900000001,42.853371],"type":"Point"}
}