{
  "type": "Feature",
  "properties": {
    "iso:country":"US",
    "sg:address":"1055 S Wayne Rd",
    "sg:city":"Westland",
    "sg:classifiers":[
        {
            "category":"Retail",
            "subcategory":"Event Space",
            "type":"Services"
        }
    ],
    "sg:phone":"+1 734 326 3323",
    "sg:postcode":"48186",
    "sg:province":"MI",
    "sg:tags":[
        "venue"
    ],
    "sg:website":"www.vfw.org",
    "wof:name":"Veterans of Foreign Wars",
    "wof:placetype":"venue"
},
  "geometry": {"coordinates":[-83.388199,42.301498],"type":"Point"}
}