{
  "type": "Feature",
  "properties": {
    "iso:country":"US",
    "sg:address":"40361 Langton Dr",
    "sg:city":"Sterling Heights",
    "sg:classifiers":[
        {
            "category":"Professional",
            "subcategory":"Business Services",
            "type":"Services"
        }
    ],
    "sg:phone":"+1 586 978 7858",
    "sg:postcode":"48310",
    "sg:province":"MI",
    "wof:name":"Ad Wireless Communications",
    "wof:placetype":"venue"
},
  "geometry": {"coordinates":[-83.08308599999999,42.589044],"type":"Point"}
}