{
  "type": "Feature",
  "properties": {
    "iso:country":"US",
    "sg:address":"18428 Pellett Dr",
    "sg:city":"Fenton",
    "sg:classifiers":[
        {
            "category":"Retail",
            "subcategory":"Repair Shop",
            "type":"Services"
        }
    ],
    "sg:phone":"+1 248 634 9399",
    "sg:postcode":"48430",
    "sg:province":"MI",
    "sg:tags":[
        "upholsterer"
    ],
    "wof:name":"Best Furniture Repair",
    "wof:placetype":"venue"
},
  "geometry": {"coordinates":[-83.663313,42.754849],"type":"Point"}
}