{
  "type": "Feature",
  "properties": {
    "iso:country":"US",
    "sg:address":"56968 Dailey Rd",
    "sg:city":"Dowagiac",
    "sg:classifiers":[
        {
            "category":"Education",
            "subcategory":"School",
            "type":"Public Place"
        }
    ],
    "sg:phone":"+1 269 782 0392",
    "sg:postcode":"49047",
    "sg:province":"MI",
    "wof:name":"Institute For Intl Coop &",
    "wof:placetype":"venue"
},
  "geometry": {"coordinates":[-86.087835,41.96966],"type":"Point"}
}