{
  "type": "Feature",
  "properties": {
    "iso:country":"US",
    "sg:address":"6398 Linsdale St",
    "sg:city":"Detroit",
    "sg:classifiers":[
        {
            "category":"Professional",
            "subcategory":"Management & Consulting",
            "type":"Services"
        }
    ],
    "sg:phone":"+1 313 934 4144",
    "sg:postcode":"48204",
    "sg:province":"MI",
    "wof:name":"Cousins Management",
    "wof:placetype":"venue"
},
  "geometry": {"coordinates":[-83.14079099999999,42.35635],"type":"Point"}
}