{
  "type": "Feature",
  "properties": {
    "iso:country":"US",
    "sg:address":"48989 West Rd",
    "sg:city":"Wixom",
    "sg:classifiers":[
        {
            "category":"Retail",
            "subcategory":"Auto Repair",
            "type":"Services"
        }
    ],
    "sg:phone":"+1 248 349 1659",
    "sg:postcode":"48393",
    "sg:province":"MI",
    "sg:tags":[
        "carwash",
        "automotive"
    ],
    "wof:name":"Auto Magic Inc",
    "wof:placetype":"venue"
},
  "geometry": {"coordinates":[-83.534611,42.508176],"type":"Point"}
}