{
  "type": "Feature",
  "properties": {
    "iso:country":"US",
    "sg:address":"3959 Clay Ave SW",
    "sg:city":"Grand Rapids",
    "sg:classifiers":[
        {
            "category":"Organizations",
            "subcategory":"Professional Association",
            "type":"Services"
        }
    ],
    "sg:phone":"+1 616 257 3050",
    "sg:postcode":"49548",
    "sg:province":"MI",
    "wof:name":"National Association - Credit",
    "wof:placetype":"venue"
},
  "geometry": {"coordinates":[-85.67751800000001,42.893149],"type":"Point"}
}