{
  "type": "Feature",
  "properties": {
    "iso:country":"US",
    "sg:address":"70007 Powell Rd",
    "sg:city":"Bruce",
    "sg:classifiers":[
        {
            "category":"Retail",
            "subcategory":"Repair Shop",
            "type":"Services"
        },
        {
            "category":"Retail",
            "subcategory":"Auto Repair",
            "type":"Services"
        }
    ],
    "sg:phone":"+1 586 336 9166",
    "sg:postcode":"48065",
    "sg:province":"MI",
    "sg:tags":[
        "trailer"
    ],
    "wof:name":"Kustom Truck & Trailer",
    "wof:placetype":"venue"
},
  "geometry": {"coordinates":[-82.980563,42.815502],"type":"Point"}
}