{
  "type": "Feature",
  "properties": {
    "iso:country":"US",
    "sg:address":"2075 W Big Beaver Rd",
    "sg:city":"Troy",
    "sg:classifiers":[
        {
            "category":"Communications",
            "subcategory":"Newspaper",
            "type":"Services"
        }
    ],
    "sg:phone":"+1 248 643 9910",
    "sg:postcode":"48084",
    "sg:province":"MI",
    "sg:tags":[
        "print",
        "medium"
    ],
    "sg:website":"www.anrinc.net",
    "wof:name":"American Newspaper Representatives Inc",
    "wof:placetype":"venue"
},
  "geometry": {"coordinates":[-83.17479,42.56144],"type":"Point"}
}