{
  "type": "Feature",
  "properties": {
    "iso:country":"US",
    "sg:address":"7565 Barnsbury St",
    "sg:city":"West Bloomfield",
    "sg:classifiers":[
        {
            "category":"Real Estate",
            "subcategory":"Real Estate Agent",
            "type":"Services"
        }
    ],
    "sg:phone":"+1 248 366 7068",
    "sg:postcode":"48324",
    "sg:province":"MI",
    "wof:name":"Worthington Appraisl",
    "wof:placetype":"venue"
},
  "geometry": {"coordinates":[-83.43350700000001,42.603683],"type":"Point"}
}