{
  "type": "Feature",
  "properties": {
    "iso:country":"US",
    "sg:address":"4335 S Smith Crossing Rd",
    "sg:city":"Freeland",
    "sg:classifiers":[
        {
            "category":"Retail",
            "subcategory":"Car Wash",
            "type":"Services"
        }
    ],
    "sg:phone":"+1 989 695 4888",
    "sg:postcode":"48623",
    "sg:province":"MI",
    "sg:tags":[
        "carwash"
    ],
    "wof:name":"Lbr2 Powerwash",
    "wof:placetype":"venue"
},
  "geometry": {"coordinates":[-84.190237,43.486722],"type":"Point"}
}