{
  "type": "Feature",
  "properties": {
    "iso:country":"US",
    "sg:address":"15704 Jonas Ave",
    "sg:city":"Allen Park",
    "sg:classifiers":[
        {
            "category":"Professional",
            "subcategory":"Secretarial Services",
            "type":"Services"
        }
    ],
    "sg:phone":"+1 313 386 1230",
    "sg:postcode":"48101",
    "sg:province":"MI",
    "sg:tags":[
        "reporting"
    ],
    "wof:name":"Traylor & Traylor Court",
    "wof:placetype":"venue"
},
  "geometry": {"coordinates":[-83.21695699999999,42.251338],"type":"Point"}
}