{
  "type": "Feature",
  "properties": {
    "iso:country":"US",
    "sg:address":"318 4th St",
    "sg:city":"Blanchard",
    "sg:classifiers":[
        {
            "category":"Building & Trades",
            "subcategory":"Landscaping Services",
            "type":"Services"
        }
    ],
    "sg:phone":"+1 989 561 5135",
    "sg:postcode":"49310",
    "sg:province":"MI",
    "wof:name":"Town & Cntry Ldscp & Lawn Care",
    "wof:placetype":"venue"
},
  "geometry": {"coordinates":[-85.07831299999999,43.517534],"type":"Point"}
}