{
  "type": "Feature",
  "properties": {
    "iso:country":"US",
    "sg:address":"17700 Northland Park Ct",
    "sg:city":"Southfield",
    "sg:classifiers":[
        {
            "category":"Health Services",
            "subcategory":"Clinic",
            "type":"Services"
        }
    ],
    "sg:phone":"+1 248 569 7900",
    "sg:postcode":"48075",
    "sg:province":"MI",
    "sg:tags":[
        "home"
    ],
    "wof:name":"Diamond Home Health Svc",
    "wof:placetype":"venue"
},
  "geometry": {"coordinates":[-83.219337,42.445338],"type":"Point"}
}