{
  "type": "Feature",
  "properties": {
    "iso:country":"US",
    "sg:address":"3301 Mindi Ln",
    "sg:city":"Kalamazoo",
    "sg:classifiers":[
        {
            "category":"Building & Trades",
            "subcategory":"Construction",
            "type":"Services"
        }
    ],
    "sg:phone":"+1 269 342 6666",
    "sg:postcode":"49001",
    "sg:province":"MI",
    "sg:tags":[
        "downspouts",
        "gutter"
    ],
    "wof:name":"Leaffilter-Southwest Mi",
    "wof:placetype":"venue"
},
  "geometry": {"coordinates":[-85.575131,42.259101],"type":"Point"}
}