{
  "type": "Feature",
  "properties": {
    "iso:country":"US",
    "sg:address":"166 E Center St",
    "sg:city":"Ithaca",
    "sg:classifiers":[
        {
            "category":"Professional",
            "type":"Services"
        }
    ],
    "sg:phone":"+1 989 875 4844",
    "sg:postcode":"48847",
    "sg:province":"MI",
    "sg:tags":[
        "establishment"
    ],
    "wof:name":"Downtown Dime",
    "wof:placetype":"venue"
},
  "geometry": {"coordinates":[-84.606645,43.291578],"type":"Point"}
}