{
  "type": "Feature",
  "properties": {
    "iso:country":"US",
    "sg:address":"558 E Lewiston Ave",
    "sg:city":"Ferndale",
    "sg:classifiers":[
        {
            "category":"Professional",
            "subcategory":"Art Services",
            "type":"Services"
        }
    ],
    "sg:phone":"+1 248 548 4298",
    "sg:postcode":"48220",
    "sg:province":"MI",
    "sg:tags":[
        "photography",
        "commercial"
    ],
    "wof:name":"Professional Amateurs",
    "wof:placetype":"venue"
},
  "geometry": {"coordinates":[-83.12845299999999,42.464389],"type":"Point"}
}