{
  "type": "Feature",
  "properties": {
    "iso:country":"US",
    "sg:address":"467 S Meridian Rd",
    "sg:city":"Hudson",
    "sg:classifiers":[
        {
            "category":"Shopping",
            "subcategory":"Bicycles & Sporting Goods",
            "type":"Retail Goods"
        }
    ],
    "sg:phone":"+1 517 448 5015",
    "sg:postcode":"49247",
    "sg:province":"MI",
    "wof:name":"Smittys Sports Center",
    "wof:placetype":"venue"
},
  "geometry": {"coordinates":[-84.36188300000001,41.861475],"type":"Point"}
}