{
  "type": "Feature",
  "properties": {
    "iso:country":"US",
    "sg:address":"20000 Mc Cormick St",
    "sg:city":"Detroit",
    "sg:classifiers":[
        {
            "category":"Professional",
            "subcategory":"Business Services",
            "type":"Services"
        }
    ],
    "sg:phone":"+1 313 527 7924",
    "sg:postcode":"48224",
    "sg:province":"MI",
    "wof:name":"Kaleidiscope Group",
    "wof:placetype":"venue"
},
  "geometry": {"coordinates":[-82.935652,42.428509],"type":"Point"}
}