{
  "type": "Feature",
  "properties": {
    "iso:country":"US",
    "sg:address":"3328 John F Donnelly Dr",
    "sg:city":"Holland",
    "sg:classifiers":[
        {
            "category":"Wholesale",
            "subcategory":"Drugs",
            "type":"Manufacturing & Wholesale Goods"
        }
    ],
    "sg:phone":"+1 616 786 4000",
    "sg:postcode":"49424",
    "sg:province":"MI",
    "sg:tags":[
        "pharmaceutical",
        "product"
    ],
    "sg:website":"www.charlesbowman.com",
    "wof:name":"Charles Bowman Co",
    "wof:placetype":"venue"
},
  "geometry": {"coordinates":[-86.104108,42.830683],"type":"Point"}
}