{
  "type": "Feature",
  "properties": {
    "iso:country":"US",
    "sg:address":"7838 Dixie Hwy",
    "sg:city":"Fair Haven",
    "sg:classifiers":[
        {
            "category":"Recreation",
            "subcategory":"Marina",
            "type":"Entertainment"
        }
    ],
    "sg:phone":"+1 586 725 6530",
    "sg:postcode":"48023",
    "sg:province":"MI",
    "sg:tags":[
        "operation"
    ],
    "wof:name":"Bouvier Bridge Marina",
    "wof:placetype":"venue"
},
  "geometry": {"coordinates":[-82.626167,42.674042],"type":"Point"}
}