{
  "type": "Feature",
  "properties": {
    "iso:country":"US",
    "sg:address":"3881 E Railroad Trl",
    "sg:city":"Grayling",
    "sg:classifiers":[
        {
            "category":"Home & Garden",
            "subcategory":"Building Materials",
            "type":"Retail Goods"
        }
    ],
    "sg:phone":"+1 989 348 7431",
    "sg:postcode":"49738",
    "sg:province":"MI",
    "sg:tags":[
        "mixed",
        "concrete"
    ],
    "wof:name":"Lake City Redi-Mix",
    "wof:placetype":"venue"
},
  "geometry": {"coordinates":[-84.692246,44.644219],"type":"Point"}
}