{
  "type": "Feature",
  "properties": {
    "iso:country":"US",
    "sg:address":"7400 Bay Rd",
    "sg:city":"Bay City",
    "sg:classifiers":[
        {
            "category":"Education",
            "subcategory":"Library",
            "type":"Public Place"
        }
    ],
    "sg:phone":"+1 989 964 4240",
    "sg:postcode":"48710",
    "sg:province":"MI",
    "sg:website":"www.svsu.edu",
    "wof:name":"Melvin J Zahnow Library",
    "wof:placetype":"venue"
},
  "geometry": {"coordinates":[-83.97380699999999,43.516696],"type":"Point"}
}