{
  "type": "Feature",
  "properties": {
    "iso:country":"US",
    "sg:address":"31063 Hoover Rd",
    "sg:city":"Warren",
    "sg:classifiers":[
        {
            "category":"Building & Trades",
            "subcategory":"Plumbing",
            "type":"Services"
        }
    ],
    "sg:phone":"+1 248 546 6883",
    "sg:postcode":"48093",
    "sg:province":"MI",
    "sg:website":"www.markdownsplumbing.com",
    "wof:name":"MarkDowns Plumbing & Drains",
    "wof:placetype":"venue"
},
  "geometry": {"coordinates":[-83.00847,42.522474],"type":"Point"}
}