{
  "type": "Feature",
  "properties": {
    "iso:country":"US",
    "sg:address":"1520 Nye Hwy",
    "sg:city":"Charlotte",
    "sg:phone":"+1 517 543 7987",
    "sg:postcode":"48813",
    "sg:province":"MI",
    "sg:tags":[
        "farm",
        "corn",
        "soybean"
    ],
    "wof:name":"Jerry Wittman",
    "wof:placetype":"venue"
},
  "geometry": {"coordinates":[-84.80905,42.47968],"type":"Point"}
}