{
  "type": "Feature",
  "properties": {
    "iso:country":"US",
    "sg:address":"32300 Northwestern Hwy",
    "sg:city":"Farmington Hills",
    "sg:classifiers":[
        {
            "category":"Banks & Credit Unions",
            "subcategory":"Investment Brokerage",
            "type":"Services"
        }
    ],
    "sg:phone":"+1 248 851 1001",
    "sg:postcode":"48334",
    "sg:province":"MI",
    "sg:tags":[
        "stock",
        "bond"
    ],
    "wof:name":"UBS Financial Svc",
    "wof:placetype":"venue"
},
  "geometry": {"coordinates":[-83.354017,42.526836],"type":"Point"}
}