{
  "type": "Feature",
  "properties": {
    "iso:country":"US",
    "sg:address":"2017 Hill St",
    "sg:city":"Ann Arbor",
    "sg:classifiers":[
        {
            "category":"Professional",
            "subcategory":"Printing & Photocopies",
            "type":"Services"
        }
    ],
    "sg:phone":"+1 734 668 0087",
    "sg:postcode":"48104",
    "sg:province":"MI",
    "sg:tags":[
        "photocopying"
    ],
    "wof:name":"RMS Associates",
    "wof:placetype":"venue"
},
  "geometry": {"coordinates":[-83.723381,42.273696],"type":"Point"}
}