{
  "type": "Feature",
  "properties": {
    "iso:country":"US",
    "sg:address":"1372 N Main St",
    "sg:city":"Adrian",
    "sg:classifiers":[
        {
            "category":"Education",
            "subcategory":"Vocational School",
            "type":"Public Place"
        }
    ],
    "sg:phone":"+1 517 263 2108",
    "sg:postcode":"49221",
    "sg:province":"MI",
    "sg:tags":[
        "technical",
        "trade"
    ],
    "sg:website":"www.lisd.k12.mi.us",
    "wof:name":"Lemowee Vo-Tech",
    "wof:placetype":"venue"
},
  "geometry": {"coordinates":[-84.030068,41.909148],"type":"Point"}
}