{
  "type": "Feature",
  "properties": {
    "iso:country":"US",
    "sg:address":"2360 84th St SW",
    "sg:city":"Byron Center",
    "sg:classifiers":[
        {
            "category":"Health Services",
            "subcategory":"Chiropractor",
            "type":"Services"
        }
    ],
    "sg:phone":"+1 616 878 1579",
    "sg:postcode":"49315",
    "sg:province":"MI",
    "wof:name":"Harrison Chiropractic Office",
    "wof:placetype":"venue"
},
  "geometry": {"coordinates":[-85.721216,42.812126],"type":"Point"}
}