{
  "type": "Feature",
  "properties": {
    "iso:country":"US",
    "sg:address":"4216 Legacy Pkwy",
    "sg:city":"Lansing",
    "sg:classifiers":[
        {
            "category":"Autos & Motor Vehicles",
            "subcategory":"Automobile Sales",
            "type":"Retail Goods"
        }
    ],
    "sg:phone":"+1 517 272 7728",
    "sg:postcode":"48911",
    "sg:province":"MI",
    "sg:tags":[
        "performance",
        "race",
        "dealer"
    ],
    "wof:name":"V T Engines Inc",
    "wof:placetype":"venue"
},
  "geometry": {"coordinates":[-84.50973399999999,42.678327],"type":"Point"}
}