{
  "type": "Feature",
  "properties": {
    "iso:country":"US",
    "sg:address":"4341 Larkin Dr",
    "sg:city":"Burton",
    "sg:classifiers":[
        {
            "category":"Education",
            "subcategory":"School",
            "type":"Public Place"
        }
    ],
    "sg:phone":"+1 810 591 0620",
    "sg:postcode":"48529",
    "sg:province":"MI",
    "sg:tags":[
        "high",
        "middle",
        "elementary"
    ],
    "wof:name":"Bendle Public Schools",
    "wof:placetype":"venue"
},
  "geometry": {"coordinates":[-83.66239899999999,42.965099],"type":"Point"}
}