{
  "type": "Feature",
  "properties": {
    "iso:country":"US",
    "sg:address":"2945 Eagle Dr",
    "sg:city":"Rochester Hills",
    "sg:classifiers":[
        {
            "category":"Professional",
            "subcategory":"Business Services",
            "type":"Services"
        }
    ],
    "sg:phone":"+1 248 375 0632",
    "sg:postcode":"48309",
    "sg:province":"MI",
    "sg:tags":[
        "interior",
        "consultant",
        "design",
        "decorator"
    ],
    "wof:name":"Sterling Interiors LLC",
    "wof:placetype":"venue"
},
  "geometry": {"coordinates":[-83.191547,42.657111],"type":"Point"}
}