{
  "type": "Feature",
  "properties": {
    "iso:country":"US",
    "sg:address":"5611 Springridge St",
    "sg:city":"Portage",
    "sg:classifiers":[
        {
            "category":"Retail",
            "subcategory":"Repair Shop",
            "type":"Services"
        }
    ],
    "sg:phone":"+1 269 321 9941",
    "sg:postcode":"49024",
    "sg:province":"MI",
    "sg:tags":[
        "commercial",
        "design"
    ],
    "wof:name":"Unison Design",
    "wof:placetype":"venue"
},
  "geometry": {"coordinates":[-85.620679,42.235711],"type":"Point"}
}