{
  "type": "Feature",
  "properties": {
    "iso:country":"US",
    "sg:address":"2420 N Westnedge Ave",
    "sg:city":"Kalamazoo",
    "sg:classifiers":[
        {
            "category":"Building & Trades",
            "subcategory":"Landscaping Services",
            "type":"Services"
        }
    ],
    "sg:phone":"+1 269 342 4008",
    "sg:postcode":"49004",
    "sg:province":"MI",
    "sg:tags":[
        "lawn",
        "maintenance",
        "grounds"
    ],
    "wof:name":"Wolverine Lawn Maintenance Inc",
    "wof:placetype":"venue"
},
  "geometry": {"coordinates":[-85.58992000000001,42.317187],"type":"Point"}
}