{
  "type": "Feature",
  "properties": {
    "iso:country":"US",
    "sg:address":"2068 Doty Rd",
    "sg:city":"Monroe",
    "sg:phone":"+1 734 587 3909",
    "sg:postcode":"48162",
    "sg:province":"MI",
    "sg:tags":[
        "farm",
        "corn",
        "soybean"
    ],
    "wof:name":"Kohlman Farms",
    "wof:placetype":"venue"
},
  "geometry": {"coordinates":[-83.50728599999999,41.980567],"type":"Point"}
}