{
  "type": "Feature",
  "properties": {
    "iso:country":"US",
    "sg:address":"8508 State Rd",
    "sg:city":"Millington",
    "sg:classifiers":[
        {
            "category":"Personal",
            "subcategory":"Tanning Parlor",
            "type":"Services"
        }
    ],
    "sg:phone":"+1 989 871 5542",
    "sg:postcode":"48746",
    "sg:province":"MI",
    "sg:tags":[
        "salon"
    ],
    "wof:name":"Prime Time Tanning & Video",
    "wof:placetype":"venue"
},
  "geometry": {"coordinates":[-83.52986,43.281079],"type":"Point"}
}