{
  "type": "Feature",
  "properties": {
    "iso:country":"US",
    "sg:address":"2244 Hammerslea Rd",
    "sg:city":"Lake Orion",
    "sg:classifiers":[
        {
            "category":"Retail",
            "subcategory":"Laundry & Dry Cleaning",
            "type":"Services"
        }
    ],
    "sg:phone":"+1 248 391 0274",
    "sg:postcode":"48359",
    "sg:province":"MI",
    "wof:name":"Coombs Steam Carpet Cleaners",
    "wof:placetype":"venue"
},
  "geometry": {"coordinates":[-83.287093,42.723586],"type":"Point"}
}