{
  "type": "Feature",
  "properties": {
    "iso:country":"US",
    "sg:address":"336 W Saginaw Rd",
    "sg:city":"Sanford",
    "sg:classifiers":[
        {
            "category":"Restaurant",
            "type":"Food & Drink"
        }
    ],
    "sg:phone":"+1 989 687 7358",
    "sg:postcode":"48657",
    "sg:province":"MI",
    "wof:name":"Lanny's Restaurant",
    "wof:placetype":"venue"
},
  "geometry": {"coordinates":[-84.3817,43.672379],"type":"Point"}
}