{
  "type": "Feature",
  "properties": {
    "iso:country":"US",
    "sg:address":"1335 Pine Ave",
    "sg:city":"Alma",
    "sg:classifiers":[
        {
            "category":"Health Services",
            "subcategory":"Doctor",
            "type":"Services"
        }
    ],
    "sg:phone":"+1 989 463 2181",
    "sg:postcode":"48801",
    "sg:province":"MI",
    "sg:tags":[
        "physician",
        "surgeon"
    ],
    "wof:name":"Alma Family Practice",
    "wof:placetype":"venue"
},
  "geometry": {"coordinates":[-84.65692,43.388348],"type":"Point"}
}