{
  "type": "Feature",
  "properties": {
    "iso:country":"US",
    "sg:address":"118 N Roland St",
    "sg:city":"Mc Bain",
    "sg:classifiers":[
        {
            "category":"Home & Garden",
            "subcategory":"Hardware",
            "type":"Retail Goods"
        }
    ],
    "sg:phone":"+1 231 825 2111",
    "sg:postcode":"49657",
    "sg:province":"MI",
    "wof:name":"Mc Bain Hardware Co",
    "wof:placetype":"venue"
},
  "geometry": {"coordinates":[-85.21043299999999,44.193495],"type":"Point"}
}