{
  "type": "Feature",
  "properties": {
    "iso:country":"US",
    "sg:address":"29675 Grand River Ave",
    "sg:city":"Farmington Hills",
    "sg:classifiers":[
        {
            "category":"Retail",
            "subcategory":"Auto Repair",
            "type":"Services"
        }
    ],
    "sg:phone":"+1 248 478 9900",
    "sg:postcode":"48336",
    "sg:province":"MI",
    "wof:name":"Titan Automotive Service Center",
    "wof:placetype":"venue"
},
  "geometry": {"coordinates":[-83.33977400000001,42.449134],"type":"Point"}
}