{
  "type": "Feature",
  "properties": {
    "iso:country":"US",
    "sg:address":"16061 White Water Dr",
    "sg:city":"Macomb",
    "sg:classifiers":[
        {
            "category":"Professional",
            "type":"Services"
        }
    ],
    "sg:phone":"+1 586 786 0793",
    "sg:postcode":"48042",
    "sg:province":"MI",
    "sg:tags":[
        "establishment"
    ],
    "wof:name":"Ciszek Jaroslaw",
    "wof:placetype":"venue"
},
  "geometry": {"coordinates":[-82.96319200000001,42.706043],"type":"Point"}
}