{
  "type": "Feature",
  "properties": {
    "iso:country":"US",
    "sg:address":"312 N Main St",
    "sg:city":"Wayland",
    "sg:classifiers":[
        {
            "category":"Retail",
            "subcategory":"Funeral Services",
            "type":"Services"
        }
    ],
    "sg:phone":"+1 269 792 2237",
    "sg:postcode":"49348",
    "sg:province":"MI",
    "sg:tags":[
        "director"
    ],
    "wof:name":"Archer-Hampel & Kubiak Funeral",
    "wof:placetype":"venue"
},
  "geometry": {"coordinates":[-85.643237,42.67745],"type":"Point"}
}