{
  "type": "Feature",
  "properties": {
    "iso:country":"US",
    "sg:address":"130 W Superior St",
    "sg:city":"Wayland",
    "sg:classifiers":[
        {
            "category":"Shopping",
            "subcategory":"Florist",
            "type":"Retail Goods"
        }
    ],
    "sg:phone":"+1 269 792 6360",
    "sg:postcode":"49348",
    "sg:province":"MI",
    "wof:name":"Wayland Floral & Gifts Inc",
    "wof:placetype":"venue"
},
  "geometry": {"coordinates":[-85.64455700000001,42.6739],"type":"Point"}
}