{
  "type": "Feature",
  "properties": {
    "iso:country":"US",
    "sg:address":"3132 Newport Ct",
    "sg:city":"Troy",
    "sg:classifiers":[
        {
            "category":"Arts & Performance",
            "subcategory":"Theater",
            "type":"Entertainment"
        }
    ],
    "sg:phone":"+1 248 588 2914",
    "sg:postcode":"48084",
    "sg:province":"MI",
    "sg:tags":[
        "theatrical"
    ],
    "wof:name":"Imagination Theater Etc",
    "wof:placetype":"venue"
},
  "geometry": {"coordinates":[-83.19613099999999,42.562722],"type":"Point"}
}