{
  "type": "Feature",
  "properties": {
    "iso:country":"US",
    "sg:address":"2077 E Paris Ave SE",
    "sg:city":"Grand Rapids",
    "sg:classifiers":[
        {
            "category":"Organizations",
            "subcategory":"Religious Organization",
            "type":"Services"
        }
    ],
    "sg:phone":"+1 616 949 5690",
    "sg:postcode":"49546",
    "sg:province":"MI",
    "wof:name":"First Evangelical Free Church",
    "wof:placetype":"venue"
},
  "geometry": {"coordinates":[-85.56959999999999,42.92655],"type":"Point"}
}