{
  "type": "Feature",
  "properties": {
    "iso:country":"US",
    "sg:address":"611 N Burdick St",
    "sg:city":"Kalamazoo",
    "sg:classifiers":[
        {
            "category":"Real Estate",
            "subcategory":"Real Estate Agent",
            "type":"Services"
        }
    ],
    "sg:phone":"+1 269 388 7504",
    "sg:postcode":"49007",
    "sg:province":"MI",
    "sg:tags":[
        "broker",
        "mortgage"
    ],
    "wof:name":"Common Cents Realty",
    "wof:placetype":"venue"
},
  "geometry": {"coordinates":[-85.58348700000001,42.29695],"type":"Point"}
}