{
  "type": "Feature",
  "properties": {
    "iso:country":"US",
    "sg:address":"17691 174th Ave",
    "sg:city":"Spring Lake",
    "sg:classifiers":[
        {
            "category":"Health Services",
            "subcategory":"Doctor",
            "type":"Services"
        }
    ],
    "sg:phone":"+1 616 842 1276",
    "sg:postcode":"49456",
    "sg:province":"MI",
    "sg:tags":[
        "physician",
        "surgeon"
    ],
    "wof:name":"Horizon Medical",
    "wof:placetype":"venue"
},
  "geometry": {"coordinates":[-86.22077299999999,43.090414],"type":"Point"}
}