{
  "type": "Feature",
  "properties": {
    "iso:country":"US",
    "sg:address":"35501 Ford Rd",
    "sg:city":"Westland",
    "sg:classifiers":[
        {
            "category":"Food & Beverages",
            "subcategory":"Groceries & Convenience Stores",
            "type":"Retail Goods"
        }
    ],
    "sg:postcode":"48185",
    "sg:province":"MI",
    "wof:name":"Green Lot Market",
    "wof:placetype":"venue"
},
  "geometry": {"coordinates":[-83.390839,42.324409],"type":"Point"}
}