{
  "type": "Feature",
  "properties": {
    "iso:country":"US",
    "sg:address":"244 N Rose St",
    "sg:city":"Kalamazoo",
    "sg:classifiers":[
        {
            "category":"Banks & Credit Unions",
            "subcategory":"Investment Brokerage",
            "type":"Services"
        }
    ],
    "sg:phone":"+1 269 343 0133",
    "sg:postcode":"49007",
    "sg:province":"MI",
    "sg:tags":[
        "advisory",
        "financial"
    ],
    "sg:website":"www.sdmg-ncb.com",
    "wof:name":"SDMG Investment Advisory",
    "wof:placetype":"venue"
},
  "geometry": {"coordinates":[-85.58474,42.293112],"type":"Point"}
}