{
  "type": "Feature",
  "properties": {
    "iso:country":"US",
    "sg:address":"8566 Littlefield St",
    "sg:city":"Detroit",
    "sg:classifiers":[
        {
            "category":"Retail",
            "subcategory":"Portrait Studio",
            "type":"Services"
        }
    ],
    "sg:phone":"+1 313 491 1524",
    "sg:postcode":"48228",
    "sg:province":"MI",
    "sg:tags":[
        "photo"
    ],
    "wof:name":"Professional Touch Portraits",
    "wof:placetype":"venue"
},
  "geometry": {"coordinates":[-83.174395,42.35641],"type":"Point"}
}