{
  "type": "Feature",
  "properties": {
    "iso:country":"US",
    "sg:address":"420 36th St SE",
    "sg:city":"Grand Rapids",
    "sg:classifiers":[
        {
            "category":"Home & Garden",
            "subcategory":"Building Materials",
            "type":"Retail Goods"
        }
    ],
    "sg:phone":"+1 616 452 8728",
    "sg:postcode":"49548",
    "sg:province":"MI",
    "sg:tags":[
        "door"
    ],
    "wof:name":"Pre-Fit Door Inc",
    "wof:placetype":"venue"
},
  "geometry": {"coordinates":[-85.654574,42.898333],"type":"Point"}
}