{
  "type": "Feature",
  "properties": {
    "iso:country":"US",
    "sg:address":"394 N 6th St",
    "sg:city":"Rogers City",
    "sg:classifiers":[
        {
            "category":"Shopping",
            "subcategory":"Computers & Home Electronics",
            "type":"Retail Goods"
        }
    ],
    "sg:phone":"+1 989 734 2592",
    "sg:postcode":"49779",
    "sg:province":"MI",
    "wof:name":"Arthur Getzinger",
    "wof:placetype":"venue"
},
  "geometry": {"coordinates":[-83.82253,45.42023],"type":"Point"}
}