{
  "type": "Feature",
  "properties": {
    "iso:country":"US",
    "sg:address":"5794 143rd Ave",
    "sg:city":"Holland",
    "sg:classifiers":[
        {
            "category":"Building & Trades",
            "subcategory":"Plumbing",
            "type":"Services"
        }
    ],
    "sg:phone":"+1 616 392 3367",
    "sg:postcode":"49423",
    "sg:province":"MI",
    "sg:tags":[
        "conditioning",
        "air",
        "system",
        "contractor"
    ],
    "wof:name":"Action Heating & Cooling Inc",
    "wof:placetype":"venue"
},
  "geometry": {"coordinates":[-86.10549399999999,42.732597],"type":"Point"}
}