{
  "type": "Feature",
  "properties": {
    "iso:country":"US",
    "sg:address":"254 S McCord St",
    "sg:city":"Benton Harbor",
    "sg:classifiers":[
        {
            "category":"Food & Beverages",
            "subcategory":"Groceries & Convenience Stores",
            "type":"Retail Goods"
        }
    ],
    "sg:phone":"+1 269 926 4003",
    "sg:postcode":"49022",
    "sg:province":"MI",
    "wof:name":"Rogers & Rogers Convenience",
    "wof:placetype":"venue"
},
  "geometry": {"coordinates":[-86.440586,42.113066],"type":"Point"}
}