{
  "type": "Feature",
  "properties": {
    "iso:country":"US",
    "sg:address":"40170 Hayes Rd",
    "sg:city":"Clinton Township",
    "sg:classifiers":[
        {
            "category":"Sports & Exercise",
            "subcategory":"Gym",
            "type":"Entertainment"
        },
        {
            "category":"Arena",
            "subcategory":"Sports Club",
            "type":"Entertainment"
        }
    ],
    "sg:phone":"+1 586 566 1397",
    "sg:postcode":"48038",
    "sg:province":"MI",
    "sg:tags":[
        "martial art"
    ],
    "wof:name":"Master K's",
    "wof:placetype":"venue"
},
  "geometry": {"coordinates":[-82.97170300000001,42.591599],"type":"Point"}
}