{
  "type": "Feature",
  "properties": {
    "iso:country":"US",
    "sg:address":"42730 Merrill Rd",
    "sg:city":"Sterling Heights",
    "sg:classifiers":[
        {
            "category":"Building & Trades",
            "subcategory":"Construction",
            "type":"Services"
        }
    ],
    "sg:phone":"+1 586 731 1661",
    "sg:postcode":"48314",
    "sg:province":"MI",
    "sg:tags":[
        "builder",
        "stair"
    ],
    "wof:name":"Timberline Stairs Inc",
    "wof:placetype":"venue"
},
  "geometry": {"coordinates":[-83.046043,42.603602],"type":"Point"}
}