{
  "type": "Feature",
  "properties": {
    "iso:country":"US",
    "sg:address":"2442 E Maple Ave",
    "sg:city":"Flint",
    "sg:classifiers":[
        {
            "category":"Banks & Credit Unions",
            "subcategory":"Financial Services",
            "type":"Services"
        }
    ],
    "sg:phone":"+1 810 744 1600",
    "sg:postcode":"48507",
    "sg:province":"MI",
    "sg:tags":[
        "broker",
        "mortgage"
    ],
    "wof:name":"Icon Mortgage Lending",
    "wof:placetype":"venue"
},
  "geometry": {"coordinates":[-83.65567299999999,42.96008],"type":"Point"}
}