{
  "type": "Feature",
  "properties": {
    "iso:country":"US",
    "sg:address":"330 E Columbia Ave",
    "sg:city":"Battle Creek",
    "sg:classifiers":[
        {
            "category":"Professional",
            "type":"Services"
        }
    ],
    "sg:phone":"+1 269 964 5777",
    "sg:postcode":"49015",
    "sg:province":"MI",
    "sg:tags":[
        "establishment"
    ],
    "wof:name":"New Day Ctr Of Battle Creek",
    "wof:placetype":"venue"
},
  "geometry": {"coordinates":[-85.188537,42.298472],"type":"Point"}
}