{
  "type": "Feature",
  "properties": {
    "iso:country":"US",
    "sg:address":"4776 Brookwoods Meadow Dr",
    "sg:city":"Brighton",
    "sg:classifiers":[
        {
            "category":"Shopping",
            "subcategory":"Pharmacy",
            "type":"Retail Goods"
        }
    ],
    "sg:phone":"+1 810 229 3377",
    "sg:postcode":"48116",
    "sg:province":"MI",
    "sg:tags":[
        "aid",
        "first",
        "supply"
    ],
    "wof:name":"Dot First Aid & Safety",
    "wof:placetype":"venue"
},
  "geometry": {"coordinates":[-83.817661,42.530676],"type":"Point"}
}