{
  "type": "Feature",
  "properties": {
    "iso:country":"US",
    "sg:address":"530 Netherfield St NW",
    "sg:city":"Comstock Park",
    "sg:classifiers":[
        {
            "category":"Building & Trades",
            "subcategory":"Electrical",
            "type":"Services"
        }
    ],
    "sg:phone":"+1 616 785 8236",
    "sg:postcode":"49321",
    "sg:province":"MI",
    "sg:tags":[
        "electrical",
        "contractor"
    ],
    "wof:name":"Parsons Electric",
    "wof:placetype":"venue"
},
  "geometry": {"coordinates":[-85.68208799999999,43.044859],"type":"Point"}
}