{
  "type": "Feature",
  "properties": {
    "iso:country":"US",
    "sg:address":"31000 Telegraph Rd",
    "sg:city":"Bingham Farms",
    "sg:classifiers":[
        {
            "category":"Professional",
            "subcategory":"Employment Agencies",
            "type":"Services"
        }
    ],
    "sg:phone":"+1 248 203 0490",
    "sg:postcode":"48025",
    "sg:province":"MI",
    "sg:website":"www.careerstaff.com",
    "wof:name":"Careerstaff Unlimited",
    "wof:placetype":"venue"
},
  "geometry": {"coordinates":[-83.285354,42.515546],"type":"Point"}
}