{
  "type": "Feature",
  "properties": {
    "iso:country":"US",
    "sg:address":"120 E Silver Lake Rd",
    "sg:city":"Fenton",
    "sg:classifiers":[
        {
            "category":"Banks & Credit Unions",
            "subcategory":"Bank",
            "type":"Services"
        }
    ],
    "sg:phone":"+1 810 629 2289",
    "sg:postcode":"48430",
    "sg:province":"MI",
    "sg:tags":[
        "state",
        "commercial"
    ],
    "wof:name":"Republic Bank",
    "wof:placetype":"venue"
},
  "geometry": {"coordinates":[-83.70459200000001,42.797645],"type":"Point"}
}