{
  "type": "Feature",
  "properties": {
    "iso:country":"US",
    "sg:address":"6650 S Westnedge Ave",
    "sg:city":"Portage",
    "sg:classifiers":[
        {
            "category":"Utilities",
            "subcategory":"Mobile Phone",
            "type":"Services"
        }
    ],
    "sg:phone":"+1 269 321 3300",
    "sg:postcode":"49024",
    "sg:province":"MI",
    "sg:tags":[
        "telephone",
        "cellular"
    ],
    "wof:name":"Wireless 4U",
    "wof:placetype":"venue"
},
  "geometry": {"coordinates":[-85.589541,42.222355],"type":"Point"}
}