{
  "type": "Feature",
  "properties": {
    "iso:country":"US",
    "sg:address":"1402 Timber Dr",
    "sg:city":"Midland",
    "sg:classifiers":[
        {
            "category":"Professional",
            "subcategory":"Employment Agencies",
            "type":"Services"
        }
    ],
    "sg:phone":"+1 989 835 1627",
    "sg:postcode":"48642",
    "sg:province":"MI",
    "sg:tags":[
        "help",
        "supply"
    ],
    "wof:name":"B L K Inc",
    "wof:placetype":"venue"
},
  "geometry": {"coordinates":[-84.21039500000001,43.650571],"type":"Point"}
}