{
  "type": "Feature",
  "properties": {
    "iso:country":"US",
    "sg:address":"17744 Winsome Rd",
    "sg:city":"Fraser",
    "sg:classifiers":[
        {
            "category":"Professional",
            "subcategory":"Business Services",
            "type":"Services"
        }
    ],
    "sg:phone":"+1 586 296 3701",
    "sg:postcode":"48026",
    "sg:province":"MI",
    "wof:name":"Rak Enterprises",
    "wof:placetype":"venue"
},
  "geometry": {"coordinates":[-82.932073,42.529966],"type":"Point"}
}