{
  "type": "Feature",
  "properties": {
    "iso:country":"US",
    "sg:address":"3631 Helen St",
    "sg:city":"Ypsilanti",
    "sg:classifiers":[
        {
            "category":"Arts & Performance",
            "subcategory":"Theater",
            "type":"Entertainment"
        }
    ],
    "sg:phone":"+1 734 572 8533",
    "sg:postcode":"48197",
    "sg:province":"MI",
    "sg:tags":[
        "group",
        "business"
    ],
    "wof:name":"Badgerow Entertainment",
    "wof:placetype":"venue"
},
  "geometry": {"coordinates":[-83.6666,42.235952],"type":"Point"}
}