{
  "type": "Feature",
  "properties": {
    "iso:country":"US",
    "sg:address":"946 Gulley Rd",
    "sg:city":"Howell",
    "sg:classifiers":[
        {
            "category":"Building & Trades",
            "subcategory":"Construction",
            "type":"Services"
        }
    ],
    "sg:phone":"+1 517 552 1010",
    "sg:postcode":"48843",
    "sg:province":"MI",
    "sg:tags":[
        "house"
    ],
    "wof:name":"Schemer Construction",
    "wof:placetype":"venue"
},
  "geometry": {"coordinates":[-83.865025,42.613879],"type":"Point"}
}