{
  "type": "Feature",
  "properties": {
    "iso:country":"US",
    "sg:address":"4004 W Lennon Rd",
    "sg:city":"Flint",
    "sg:classifiers":[
        {
            "category":"Organizations",
            "subcategory":"Religious Organization",
            "type":"Services"
        }
    ],
    "sg:phone":"+1 810 720 0211",
    "sg:postcode":"48507",
    "sg:province":"MI",
    "sg:tags":[
        "church"
    ],
    "wof:name":"North Baptist Church",
    "wof:placetype":"venue"
},
  "geometry": {"coordinates":[-83.748458,42.987586],"type":"Point"}
}