{
  "type": "Feature",
  "properties": {
    "iso:country":"US",
    "sg:address":"2621 W Pierson Rd",
    "sg:city":"Flint",
    "sg:classifiers":[
        {
            "category":"Shopping",
            "subcategory":"Clothing, Apparel, & Fashions",
            "type":"Retail Goods"
        }
    ],
    "sg:phone":"+1 810 787 1872",
    "sg:postcode":"48504",
    "sg:province":"MI",
    "wof:name":"Fashion Cents",
    "wof:placetype":"venue"
},
  "geometry": {"coordinates":[-83.73310499999999,43.060557],"type":"Point"}
}