{
  "type": "Feature",
  "properties": {
    "iso:country":"US",
    "sg:address":"700 Stewart Rd",
    "sg:city":"Monroe",
    "sg:classifiers":[
        {
            "category":"Wholesale",
            "subcategory":"Medical Equipment & Supplies",
            "type":"Manufacturing & Wholesale Goods"
        }
    ],
    "sg:phone":"+1 734 457 2997",
    "sg:postcode":"48162",
    "sg:province":"MI",
    "sg:tags":[
        "therapy",
        "physical"
    ],
    "wof:name":"Rehabcare Group",
    "wof:placetype":"venue"
},
  "geometry": {"coordinates":[-83.397925,41.938094],"type":"Point"}
}