{
  "type": "Feature",
  "properties": {
    "iso:country":"US",
    "sg:address":"408 S Stephenson Ave",
    "sg:city":"Iron Mountain",
    "sg:classifiers":[
        {
            "category":"Shopping",
            "type":"Retail Goods"
        }
    ],
    "sg:phone":"+1 906 774 2001",
    "sg:postcode":"49801",
    "sg:province":"MI",
    "sg:tags":[
        "pet",
        "shop"
    ],
    "wof:name":"Wendy's Blue Lagoon",
    "wof:placetype":"venue"
},
  "geometry": {"coordinates":[-88.065788,45.819308],"type":"Point"}
}