{
  "type": "Feature",
  "properties": {
    "iso:country":"US",
    "sg:address":"500 Cooper St",
    "sg:city":"Jackson",
    "sg:classifiers":[
        {
            "category":"Taxi",
            "type":"Transportation"
        }
    ],
    "sg:phone":"+1 517 782 7700",
    "sg:postcode":"49201",
    "sg:province":"MI",
    "sg:tags":[
        "taxicab"
    ],
    "wof:name":"Colonial Cab",
    "wof:placetype":"venue"
},
  "geometry": {"coordinates":[-84.403786,42.252345],"type":"Point"}
}