{
  "type": "Feature",
  "properties": {
    "iso:country":"US",
    "sg:address":"5 June St",
    "sg:city":"Ypsilanti",
    "sg:classifiers":[
        {
            "category":"Retail",
            "subcategory":"Auto Repair",
            "type":"Services"
        }
    ],
    "sg:phone":"+1 734 480 0760",
    "sg:postcode":"48198",
    "sg:province":"MI",
    "sg:tags":[
        "body",
        "shop"
    ],
    "wof:name":"D V Auto Repair",
    "wof:placetype":"venue"
},
  "geometry": {"coordinates":[-83.57379899999999,42.2477],"type":"Point"}
}