{
  "type": "Feature",
  "properties": {
    "iso:country":"US",
    "sg:address":"783 Nadeau Rd",
    "sg:city":"Monroe",
    "sg:classifiers":[
        {
            "category":"Building & Trades",
            "subcategory":"Construction",
            "type":"Services"
        }
    ],
    "sg:phone":"+1 734 242 3391",
    "sg:postcode":"48162",
    "sg:province":"MI",
    "sg:tags":[
        "sewer",
        "contractor"
    ],
    "wof:name":"E-Z Sewer Cleaning",
    "wof:placetype":"venue"
},
  "geometry": {"coordinates":[-83.35840399999999,41.964288],"type":"Point"}
}