{
  "type": "Feature",
  "properties": {
    "iso:country":"US",
    "sg:address":"26682 Pattow St",
    "sg:city":"Roseville",
    "sg:classifiers":[
        {
            "category":"Building & Trades",
            "subcategory":"Construction",
            "type":"Services"
        }
    ],
    "sg:phone":"+1 586 498 9977",
    "sg:postcode":"48066",
    "sg:province":"MI",
    "sg:tags":[
        "handyman"
    ],
    "wof:name":"C & L Unlimited Svc",
    "wof:placetype":"venue"
},
  "geometry": {"coordinates":[-82.923143,42.49279],"type":"Point"}
}