{
  "type": "Feature",
  "properties": {
    "iso:country":"US",
    "sg:address":"1908 N Mitchell St",
    "sg:city":"Cadillac",
    "sg:classifiers":[
        {
            "category":"Shopping",
            "type":"Retail Goods"
        }
    ],
    "sg:phone":"+1 231 775 2443",
    "sg:postcode":"49601",
    "sg:province":"MI",
    "sg:tags":[
        "equipment",
        "care",
        "health",
        "home"
    ],
    "sg:website":"www.airwayoxygeninc.com",
    "wof:name":"Airway Oxygen Inc",
    "wof:placetype":"venue"
},
  "geometry": {"coordinates":[-85.40664599999999,44.281271],"type":"Point"}
}