{
  "type": "Feature",
  "properties": {
    "iso:country":"US",
    "sg:address":"4119 N Eager Rd",
    "sg:city":"Howell",
    "sg:classifiers":[
        {
            "category":"Professional",
            "subcategory":"Research",
            "type":"Services"
        }
    ],
    "sg:phone":"+1 517 546 4768",
    "sg:postcode":"48855",
    "sg:province":"MI",
    "sg:tags":[
        "nonphysical",
        "commercial"
    ],
    "wof:name":"Nancy J Wood",
    "wof:placetype":"venue"
},
  "geometry": {"coordinates":[-83.896214,42.659014],"type":"Point"}
}