{
  "type": "Feature",
  "properties": {
    "iso:country":"US",
    "sg:address":"2575 S Slocum Rd",
    "sg:city":"Ravenna",
    "sg:classifiers":[
        {
            "category":"Wholesale",
            "subcategory":"Farm Supplies",
            "type":"Manufacturing & Wholesale Goods"
        }
    ],
    "sg:phone":"+1 231 853 2720",
    "sg:postcode":"49451",
    "sg:province":"MI",
    "sg:tags":[
        "equipment",
        "livestock"
    ],
    "wof:name":"Michigan Agri-Bedding",
    "wof:placetype":"venue"
},
  "geometry": {"coordinates":[-85.932299,43.206095],"type":"Point"}
}