{
  "type": "Feature",
  "properties": {
    "iso:country":"US",
    "sg:address":"640 Lookout St",
    "sg:city":"Pontiac",
    "sg:classifiers":[
        {
            "category":"Education",
            "subcategory":"Special Training",
            "type":"Public Place"
        }
    ],
    "sg:phone":"+1 248 894 5824",
    "sg:postcode":"48342",
    "sg:province":"MI",
    "sg:tags":[
        "teaching",
        "biblical",
        "ministry"
    ],
    "wof:name":"KEM",
    "wof:placetype":"venue"
},
  "geometry": {"coordinates":[-83.266859,42.637548],"type":"Point"}
}