{
  "type": "Feature",
  "properties": {
    "iso:country":"US",
    "sg:address":"18900 Eureka Rd",
    "sg:city":"Southgate",
    "sg:classifiers":[
        {
            "category":"Health Services",
            "subcategory":"Optometrist",
            "type":"Services"
        },
        {
            "category":"Shopping",
            "subcategory":"Optician",
            "type":"Retail Goods"
        }
    ],
    "sg:phone":"+1 734 324 0996",
    "sg:postcode":"48195",
    "sg:province":"MI",
    "sg:tags":[
        "eyewear"
    ],
    "wof:name":"Henry Ford Optimeyes",
    "wof:placetype":"venue"
},
  "geometry": {"coordinates":[-83.222362,42.198925],"type":"Point"}
}