{
  "type": "Feature",
  "properties": {
    "iso:country":"US",
    "sg:address":"215 S River Ave",
    "sg:city":"Holland",
    "sg:classifiers":[
        {
            "category":"Home & Garden",
            "subcategory":"Furniture",
            "type":"Retail Goods"
        },
        {
            "category":"Home & Garden",
            "subcategory":"Home Furnishings",
            "type":"Retail Goods"
        }
    ],
    "sg:phone":"+1 616 393 9433",
    "sg:postcode":"49423",
    "sg:province":"MI",
    "sg:tags":[
        "business"
    ],
    "wof:name":"Three Chairs Co",
    "wof:placetype":"venue"
},
  "geometry": {"coordinates":[-86.108986,42.789383],"type":"Point"}
}