{
  "type": "Feature",
  "properties": {
    "iso:country":"US",
    "sg:address":"920 3rd St",
    "sg:city":"Three Rivers",
    "sg:classifiers":[
        {
            "category":"Education",
            "subcategory":"Library",
            "type":"Public Place"
        }
    ],
    "sg:phone":"+1 269 273 8666",
    "sg:postcode":"49093",
    "sg:province":"MI",
    "sg:tags":[
        "executive"
    ],
    "wof:name":"Three Rivers Public Library",
    "wof:placetype":"venue"
},
  "geometry": {"coordinates":[-85.630937,41.933981],"type":"Point"}
}