{
  "type": "Feature",
  "properties": {
    "iso:country":"US",
    "sg:address":"3075 Dix Hwy",
    "sg:city":"Lincoln Park",
    "sg:classifiers":[
        {
            "category":"Building & Trades",
            "subcategory":"Construction",
            "type":"Services"
        }
    ],
    "sg:phone":"+1 313 928 4807",
    "sg:postcode":"48146",
    "sg:province":"MI",
    "sg:tags":[
        "house"
    ],
    "wof:name":"Matthew Brightmans Constructio",
    "wof:placetype":"venue"
},
  "geometry": {"coordinates":[-83.194855,42.23952],"type":"Point"}
}