{
  "type": "Feature",
  "properties": {
    "iso:country":"US",
    "sg:address":"306 1st St",
    "sg:city":"Jackson",
    "sg:classifiers":[
        {
            "category":"Personal",
            "subcategory":"Tattoo Parlor",
            "type":"Services"
        }
    ],
    "sg:phone":"+1 517 796 1147",
    "sg:postcode":"49201",
    "sg:province":"MI",
    "sg:tags":[
        "tattooing"
    ],
    "wof:name":"Mortatts Ink Spot Tatoos",
    "wof:placetype":"venue"
},
  "geometry": {"coordinates":[-84.414855,42.244727],"type":"Point"}
}