{
  "type": "Feature",
  "properties": {
    "iso:country":"US",
    "sg:address":"705 Bridge St NW",
    "sg:city":"Grand Rapids",
    "sg:classifiers":[
        {
            "category":"Social Services",
            "type":"Services"
        }
    ],
    "sg:phone":"+1 616 459 9139",
    "sg:postcode":"49504",
    "sg:province":"MI",
    "wof:name":"Help Pregnancy Crisis Aid Inc",
    "wof:placetype":"venue"
},
  "geometry": {"coordinates":[-85.685329,42.97078],"type":"Point"}
}