{
  "type": "Feature",
  "properties": {
    "iso:country":"US",
    "sg:address":"1500 Pierce Rd",
    "sg:city":"Caro",
    "sg:classifiers":[
        {
            "category":"Government",
            "subcategory":"Office",
            "type":"Public Place"
        }
    ],
    "sg:phone":"+1 989 672 3748",
    "sg:postcode":"48723",
    "sg:province":"MI",
    "sg:tags":[
        "executive"
    ],
    "wof:name":"Mosquito Abatement",
    "wof:placetype":"venue"
},
  "geometry": {"coordinates":[-83.34645500000001,43.467948],"type":"Point"}
}