{
  "type": "Feature",
  "properties": {
    "iso:country":"US",
    "sg:address":"410 W Grand River Ave",
    "sg:city":"Brighton",
    "sg:classifiers":[
        {
            "category":"Insurance",
            "subcategory":"Insurance Agent",
            "type":"Services"
        }
    ],
    "sg:phone":"+1 810 227 6552",
    "sg:postcode":"48116",
    "sg:province":"MI",
    "wof:name":"Shawn Pipoly Agency",
    "wof:placetype":"venue"
},
  "geometry": {"coordinates":[-83.782533,42.533688],"type":"Point"}
}