{
  "type": "Feature",
  "properties": {
    "iso:country":"US",
    "sg:address":"1115 W Lincoln Ave",
    "sg:city":"Ionia",
    "sg:classifiers":[
        {
            "category":"Personal",
            "subcategory":"Beauty Salon",
            "type":"Services"
        }
    ],
    "sg:phone":"+1 616 527 3981",
    "sg:postcode":"48846",
    "sg:province":"MI",
    "wof:name":"Creative Edge",
    "wof:placetype":"venue"
},
  "geometry": {"coordinates":[-85.084658,42.987283],"type":"Point"}
}