{
  "type": "Feature",
  "properties": {
    "iso:country":"US",
    "sg:address":"98 Woodland Dr",
    "sg:city":"Spruce",
    "sg:classifiers":[
        {
            "category":"Manufacturing",
            "subcategory":"Lumber",
            "type":"Manufacturing & Wholesale Goods"
        }
    ],
    "sg:phone":"+1 989 727 4511",
    "sg:postcode":"48762",
    "sg:province":"MI",
    "sg:tags":[
        "forester"
    ],
    "wof:name":"Barry's Land & Timber",
    "wof:placetype":"venue"
},
  "geometry": {"coordinates":[-83.52882200000001,44.814505],"type":"Point"}
}