{
  "type": "Feature",
  "properties": {
    "iso:country":"US",
    "sg:address":"714 W Grand River Ave",
    "sg:city":"Brighton",
    "sg:classifiers":[
        {
            "category":"Professional",
            "subcategory":"Accounting & Tax Preparation",
            "type":"Services"
        }
    ],
    "sg:phone":"+1 810 227 7248",
    "sg:postcode":"48116",
    "sg:province":"MI",
    "sg:tags":[
        "accountant"
    ],
    "wof:name":"Goron & Goron Assoc Inc",
    "wof:placetype":"venue"
},
  "geometry": {"coordinates":[-83.783783,42.535919],"type":"Point"}
}