{
  "type": "Feature",
  "properties": {
    "iso:country":"US",
    "sg:address":"33305 Grand River Ave",
    "sg:city":"Farmington Hills",
    "sg:classifiers":[
        {
            "category":"Education",
            "subcategory":"Vocational School",
            "type":"Public Place"
        }
    ],
    "sg:phone":"+1 248 478 0720",
    "sg:postcode":"48336",
    "sg:province":"MI",
    "sg:tags":[
        "cooking"
    ],
    "wof:name":"Kitchen Creations",
    "wof:placetype":"venue"
},
  "geometry": {"coordinates":[-83.375702,42.4646],"type":"Point"}
}