{
  "type": "Feature",
  "properties": {
    "iso:country":"US",
    "sg:address":"207 Post Rd",
    "sg:city":"Buchanan",
    "sg:classifiers":[
        {
            "category":"Retail",
            "subcategory":"Auto Repair",
            "type":"Services"
        }
    ],
    "sg:phone":"+1 269 695 6282",
    "sg:postcode":"49107",
    "sg:province":"MI",
    "sg:tags":[
        "body",
        "automobile",
        "painting"
    ],
    "wof:name":"Buchanan Automotive & Body Shp",
    "wof:placetype":"venue"
},
  "geometry": {"coordinates":[-86.381336,41.825913],"type":"Point"}
}