{
  "type": "Feature",
  "properties": {
    "iso:country":"US",
    "sg:address":"326 E Portage Ave",
    "sg:city":"Sault Ste Marie",
    "sg:classifiers":[
        {
            "category":"Organizations",
            "subcategory":"Membership Organization",
            "type":"Services"
        }
    ],
    "sg:phone":"+1 906 632 3658",
    "sg:postcode":"49783",
    "sg:province":"MI",
    "wof:name":"Tower Of History",
    "wof:placetype":"venue"
},
  "geometry": {"coordinates":[-84.34070800000001,46.498563],"type":"Point"}
}