{
  "type": "Feature",
  "properties": {
    "iso:country":"US",
    "sg:address":"209 W Cedar Ave",
    "sg:city":"Gladwin",
    "sg:classifiers":[
        {
            "category":"Shopping",
            "subcategory":"Computers & Home Electronics",
            "type":"Retail Goods"
        }
    ],
    "sg:phone":"+1 989 246 0285",
    "sg:postcode":"48624",
    "sg:province":"MI",
    "sg:tags":[
        "a",
        "as",
        "operates",
        "center",
        "sale"
    ],
    "wof:name":"CPR Parts & Repair",
    "wof:placetype":"venue"
},
  "geometry": {"coordinates":[-84.48912,43.980606],"type":"Point"}
}