{
  "type": "Feature",
  "properties": {
    "iso:country":"US",
    "sg:address":"1234 Leonard St NW",
    "sg:city":"Grand Rapids",
    "sg:classifiers":[
        {
            "category":"Autos & Motor Vehicles",
            "subcategory":"Recreational Vehicle Sales",
            "type":"Retail Goods"
        }
    ],
    "sg:phone":"+1 616 459 0727",
    "sg:postcode":"49504",
    "sg:province":"MI",
    "wof:name":"Al's Trailer Mart",
    "wof:placetype":"venue"
},
  "geometry": {"coordinates":[-85.70021199999999,42.98562],"type":"Point"}
}