{
  "type": "Feature",
  "properties": {
    "iso:country":"US",
    "sg:address":"25845 W 8 Mile Rd",
    "sg:city":"Redford",
    "sg:classifiers":[
        {
            "category":"Retail",
            "subcategory":"Auto Repair",
            "type":"Services"
        }
    ],
    "sg:phone":"+1 313 535 0735",
    "sg:postcode":"48240",
    "sg:province":"MI",
    "wof:name":"Beech-8-Shell",
    "wof:placetype":"venue"
},
  "geometry": {"coordinates":[-83.297809,42.442173],"type":"Point"}
}