{
  "type": "Feature",
  "properties": {
    "iso:country":"US",
    "sg:address":"2438 Rochester Rd",
    "sg:city":"Oakland",
    "sg:classifiers":[
        {
            "category":"Farming",
            "subcategory":"Farm",
            "type":"Manufacturing & Wholesale Goods"
        }
    ],
    "sg:phone":"+1 248 651 6234",
    "sg:postcode":"48363",
    "sg:province":"MI",
    "sg:tags":[
        "crop",
        "general"
    ],
    "wof:name":"Hillside Farms Ldscp",
    "wof:placetype":"venue"
},
  "geometry": {"coordinates":[-83.137395,42.759992],"type":"Point"}
}