{
  "type": "Feature",
  "properties": {
    "iso:country":"US",
    "sg:address":"25714 Dewey Lake St",
    "sg:city":"Dowagiac",
    "sg:phone":"+1 269 783 0048",
    "sg:postcode":"49047",
    "sg:province":"MI",
    "sg:tags":[
        "farm",
        "corn"
    ],
    "wof:name":"Joseph Van Tuyle",
    "wof:placetype":"venue"
},
  "geometry": {"coordinates":[-86.06587,42.055876],"type":"Point"}
}