{
  "type": "Feature",
  "properties": {
    "iso:country":"US",
    "sg:address":"3923 S Riverside Dr",
    "sg:city":"Sault Ste Marie",
    "sg:classifiers":[
        {
            "category":"Food & Beverages",
            "subcategory":"Groceries & Convenience Stores",
            "type":"Retail Goods"
        }
    ],
    "sg:phone":"+1 906 632 9451",
    "sg:postcode":"49783",
    "sg:province":"MI",
    "wof:name":"Riverside Party Store",
    "wof:placetype":"venue"
},
  "geometry": {"coordinates":[-84.279003,46.450273],"type":"Point"}
}