{
  "type": "Feature",
  "properties": {
    "iso:country":"US",
    "sg:address":"1956 Rupert St NE",
    "sg:city":"Grand Rapids",
    "sg:classifiers":[
        {
            "category":"Wholesale",
            "subcategory":"Chemicals & Plastics",
            "type":"Manufacturing & Wholesale Goods"
        }
    ],
    "sg:phone":"+1 616 363 3366",
    "sg:postcode":"49525",
    "sg:province":"MI",
    "sg:tags":[
        "resin"
    ],
    "wof:name":"M Holland Co",
    "wof:placetype":"venue"
},
  "geometry": {"coordinates":[-85.62089400000001,43.024843],"type":"Point"}
}