{
  "type": "Feature",
  "properties": {
    "iso:country":"US",
    "sg:address":"4526 Spahr Ave",
    "sg:city":"Holt",
    "sg:classifiers":[
        {
            "category":"Health Services",
            "subcategory":"Clinic",
            "type":"Services"
        }
    ],
    "sg:phone":"+1 517 694 8422",
    "sg:postcode":"48842",
    "sg:province":"MI",
    "wof:name":"Womens Wisdom & Wellness Conf",
    "wof:placetype":"venue"
},
  "geometry": {"coordinates":[-84.525682,42.646292],"type":"Point"}
}