{
  "type": "Feature",
  "properties": {
    "iso:country":"US",
    "sg:address":"510 Michigan Ave",
    "sg:city":"Marysville",
    "sg:classifiers":[
        {
            "category":"Real Estate",
            "subcategory":"Architect",
            "type":"Services"
        }
    ],
    "sg:phone":"+1 810 388 0190",
    "sg:postcode":"48040",
    "sg:province":"MI",
    "sg:tags":[
        "architectural"
    ],
    "wof:name":"Cr Design",
    "wof:placetype":"venue"
},
  "geometry": {"coordinates":[-82.48073100000001,42.924252],"type":"Point"}
}