{
  "type": "Feature",
  "properties": {
    "iso:country":"US",
    "sg:address":"699 Case Rd",
    "sg:city":"Beulah",
    "sg:classifiers":[
        {
            "category":"Home & Garden",
            "subcategory":"Hardware",
            "type":"Retail Goods"
        }
    ],
    "sg:phone":"+1 231 882 4406",
    "sg:postcode":"49617",
    "sg:province":"MI",
    "wof:name":"Mister Ed's True Value Ctr",
    "wof:placetype":"venue"
},
  "geometry": {"coordinates":[-86.087329,44.622948],"type":"Point"}
}