{
  "type": "Feature",
  "properties": {
    "iso:country":"US",
    "sg:address":"4780 Cleveland Ave",
    "sg:city":"Stevensville",
    "sg:classifiers":[
        {
            "category":"Shopping",
            "subcategory":"Computers & Home Electronics",
            "type":"Retail Goods"
        }
    ],
    "sg:phone":"+1 269 556 0207",
    "sg:postcode":"49127",
    "sg:province":"MI",
    "sg:tags":[
        "audio"
    ],
    "wof:name":"Amplivox",
    "wof:placetype":"venue"
},
  "geometry": {"coordinates":[-86.49486899999999,42.028901],"type":"Point"}
}