{
  "type": "Feature",
  "properties": {
    "iso:country":"US",
    "sg:address":"7741 Shippy Rd SW",
    "sg:city":"Fife Lake",
    "sg:classifiers":[
        {
            "category":"Education",
            "subcategory":"School",
            "type":"Public Place"
        }
    ],
    "sg:phone":"+1 231 879 3362",
    "sg:postcode":"49633",
    "sg:province":"MI",
    "wof:name":"Fife Lake Elementary School",
    "wof:placetype":"venue"
},
  "geometry": {"coordinates":[-85.312226,44.601633],"type":"Point"}
}