{
  "type": "Feature",
  "properties": {
    "iso:country":"US",
    "sg:address":"2701 Troy Center Dr Ste 400",
    "sg:city":"Troy",
    "sg:classifiers":[
        {
            "category":"Professional",
            "subcategory":"Lawyer & Legal Services",
            "type":"Services"
        }
    ],
    "sg:phone":"+1 248 362 2030",
    "sg:postcode":"48084",
    "sg:province":"MI",
    "wof:name":"Stone Biber & O'toole Pllc",
    "wof:placetype":"venue"
},
  "geometry": {"coordinates":[-83.162102,42.558601],"type":"Point"}
}