{
  "type": "Feature",
  "properties": {
    "iso:country":"US",
    "sg:address":"1905 21st Ave S",
    "sg:city":"Escanaba",
    "sg:classifiers":[
        {
            "category":"Manufacturing",
            "subcategory":"Aerospace",
            "type":"Manufacturing & Wholesale Goods"
        }
    ],
    "sg:phone":"+1 906 789 7767",
    "sg:postcode":"49829",
    "sg:province":"MI",
    "sg:tags":[
        "propeller"
    ],
    "wof:name":"U P Prop Repair",
    "wof:placetype":"venue"
},
  "geometry": {"coordinates":[-87.07383400000001,45.721539],"type":"Point"}
}