{
  "type": "Feature",
  "properties": {
    "iso:country":"US",
    "sg:address":"3923 28th St SE",
    "sg:city":"Grand Rapids",
    "sg:classifiers":[
        {
            "category":"Professional",
            "subcategory":"Research",
            "type":"Services"
        }
    ],
    "sg:phone":"+1 616 977 3127",
    "sg:postcode":"49512",
    "sg:province":"MI",
    "sg:tags":[
        "nonphysical",
        "commercial"
    ],
    "wof:name":"Phoenix One Enterprises",
    "wof:placetype":"venue"
},
  "geometry": {"coordinates":[-85.57329300000001,42.912604],"type":"Point"}
}