{
  "type": "Feature",
  "properties": {
    "iso:country":"US",
    "sg:address":"68323 Sugar Creek Dr",
    "sg:city":"Washington",
    "sg:classifiers":[
        {
            "category":"Manufacturing",
            "subcategory":"Furniture",
            "type":"Manufacturing & Wholesale Goods"
        }
    ],
    "sg:phone":"+1 586 752 1812",
    "sg:postcode":"48095",
    "sg:province":"MI",
    "sg:tags":[
        "drapery",
        "mfg"
    ],
    "wof:name":"Blind Broker The",
    "wof:placetype":"venue"
},
  "geometry": {"coordinates":[-83.02757699999999,42.797253],"type":"Point"}
}