{
  "type": "Feature",
  "properties": {
    "iso:country":"US",
    "sg:address":"7150 S Lakeshore Dr",
    "sg:city":"Pentwater",
    "sg:classifiers":[
        {
            "category":"Professional",
            "subcategory":"Art Services",
            "type":"Services"
        }
    ],
    "sg:phone":"+1 231 869 5881",
    "sg:postcode":"49449",
    "sg:province":"MI",
    "sg:tags":[
        "commercial",
        "design"
    ],
    "wof:name":"Rich Favre Graphic Arts Inc",
    "wof:placetype":"venue"
},
  "geometry": {"coordinates":[-86.420051,43.828471],"type":"Point"}
}