{
  "type": "Feature",
  "properties": {
    "iso:country":"US",
    "sg:address":"210 E John Beers Rd",
    "sg:city":"St Joseph",
    "sg:classifiers":[
        {
            "category":"Retail",
            "subcategory":"Repair Shop",
            "type":"Services"
        }
    ],
    "sg:phone":"+1 269 556 1052",
    "sg:postcode":"49085",
    "sg:province":"MI",
    "sg:tags":[
        "repairing",
        "lawn",
        "mower"
    ],
    "wof:name":"Hollywod Small Engine",
    "wof:placetype":"venue"
},
  "geometry": {"coordinates":[-86.452995,42.014549],"type":"Point"}
}