{
  "type": "Feature",
  "properties": {
    "iso:country":"US",
    "sg:address":"6245 N Old 27",
    "sg:city":"Fremont",
    "sg:classifiers":[
        {
            "category":"Shopping",
            "subcategory":"Luggage & Leather Goods",
            "type":"Retail Goods"
        }
    ],
    "sg:phone":"+1 260 833 1327",
    "sg:postcode":"46737",
    "sg:province":"MI",
    "sg:website":"www.coach.com",
    "wof:name":"Coach Store",
    "wof:placetype":"venue"
},
  "geometry": {"coordinates":[-85.00219300000001,41.730961],"type":"Point"}
}