{
  "type": "Feature",
  "properties": {
    "iso:country":"US",
    "sg:address":"3415 E Genesee Ave",
    "sg:city":"Saginaw",
    "sg:classifiers":[
        {
            "category":"Banks & Credit Unions",
            "subcategory":"Bank",
            "type":"Services"
        }
    ],
    "sg:phone":"+1 989 755 3130",
    "sg:postcode":"48601",
    "sg:province":"MI",
    "sg:tags":[
        "cashing",
        "check"
    ],
    "wof:name":"Check 'n Go",
    "wof:placetype":"venue"
},
  "geometry": {"coordinates":[-83.912216,43.40046],"type":"Point"}
}