{
  "type": "Feature",
  "properties": {
    "iso:country":"US",
    "sg:address":"34000 Woodward Ave",
    "sg:city":"Birmingham",
    "sg:classifiers":[
        {
            "category":"Shopping",
            "subcategory":"Clothing, Apparel, & Fashions",
            "type":"Retail Goods"
        }
    ],
    "sg:phone":"+1 248 645 0500",
    "sg:postcode":"48009",
    "sg:province":"MI",
    "sg:tags":[
        "shop",
        "bridal"
    ],
    "wof:name":"Julie's Bridal Couture",
    "wof:placetype":"venue"
},
  "geometry": {"coordinates":[-83.206402,42.539094],"type":"Point"}
}