{
  "type": "Feature",
  "properties": {
    "iso:country":"US",
    "sg:address":"10767 E Traverse Hwy",
    "sg:city":"Traverse City",
    "sg:classifiers":[
        {
            "category":"Organizations",
            "subcategory":"Membership Organization",
            "type":"Services"
        },
        {
            "category":"Social Services",
            "subcategory":"Job Training",
            "type":"Services"
        }
    ],
    "sg:phone":"+1 231 941 5300",
    "sg:postcode":"49684",
    "sg:province":"MI",
    "wof:name":"Telamon Corp",
    "wof:placetype":"venue"
},
  "geometry": {"coordinates":[-85.645152,44.775193],"type":"Point"}
}