{
  "type": "Feature",
  "properties": {
    "iso:country":"US",
    "sg:address":"1530 Rochester Rd",
    "sg:city":"Royal Oak",
    "sg:classifiers":[
        {
            "category":"Professional",
            "subcategory":"Accounting & Tax Preparation",
            "type":"Services"
        },
        {
            "category":"Professional",
            "subcategory":"Lawyer & Legal Services",
            "type":"Services"
        }
    ],
    "sg:phone":"+1 248 541 7725",
    "sg:postcode":"48067",
    "sg:province":"MI",
    "sg:tags":[
        "accountant"
    ],
    "wof:name":"Reinert & Company PC",
    "wof:placetype":"venue"
},
  "geometry": {"coordinates":[-83.144203,42.4995],"type":"Point"}
}