{
  "type": "Feature",
  "properties": {
    "iso:country":"US",
    "sg:address":"17217 Fairfield St",
    "sg:city":"Detroit",
    "sg:classifiers":[
        {
            "category":"Communications",
            "subcategory":"Film & Video Production",
            "type":"Services"
        }
    ],
    "sg:phone":"+1 313 341 7377",
    "sg:postcode":"48221",
    "sg:province":"MI",
    "wof:name":"Emage Inc",
    "wof:placetype":"venue"
},
  "geometry": {"coordinates":[-83.135434,42.41804],"type":"Point"}
}