{
  "type": "Feature",
  "properties": {
    "iso:country":"US",
    "sg:address":"1440 N Linden Rd",
    "sg:city":"Flint",
    "sg:classifiers":[
        {
            "category":"Real Estate",
            "subcategory":"Real Estate Operator",
            "type":"Services"
        }
    ],
    "sg:phone":"+1 810 733 1471",
    "sg:postcode":"48532",
    "sg:province":"MI",
    "sg:tags":[
        "apartment"
    ],
    "wof:name":"Walnut Square Apartments",
    "wof:placetype":"venue"
},
  "geometry": {"coordinates":[-83.773487,43.028346],"type":"Point"}
}