{
  "type": "Feature",
  "properties": {
    "iso:country":"US",
    "sg:address":"3541 Division Ave S",
    "sg:city":"Grand Rapids",
    "sg:classifiers":[
        {
            "category":"Restaurant",
            "type":"Food & Drink"
        }
    ],
    "sg:menulink":"http://www.allmenus.com/mi/wyoming/142154-subway/menu/",
    "sg:phone":"+1 616 247 5000",
    "sg:postcode":"49548",
    "sg:province":"MI",
    "sg:tags":[
        "american",
        "sandwich"
    ],
    "wof:name":"Subway",
    "wof:placetype":"venue"
},
  "geometry": {"coordinates":[-85.665391,42.899923],"type":"Point"}
}