{
  "type": "Feature",
  "properties": {
    "iso:country":"US",
    "sg:address":"22756 Oakwood Ave",
    "sg:city":"Eastpointe",
    "sg:classifiers":[
        {
            "category":"Building & Trades",
            "subcategory":"Landscaping Services",
            "type":"Services"
        }
    ],
    "sg:phone":"+1 586 776 1484",
    "sg:postcode":"48021",
    "sg:province":"MI",
    "wof:name":"Bill Crothers Landscaping",
    "wof:placetype":"venue"
},
  "geometry": {"coordinates":[-82.968486,42.467499],"type":"Point"}
}