{
  "type": "Feature",
  "properties": {
    "iso:country":"US",
    "sg:address":"1292 28th St SW",
    "sg:city":"Wyoming",
    "sg:classifiers":[
        {
            "category":"Restaurant",
            "type":"Food & Drink"
        }
    ],
    "sg:phone":"+1 616 261 2280",
    "sg:postcode":"49509",
    "sg:province":"MI",
    "sg:tags":[
        "mexican"
    ],
    "wof:name":"Lindo Mexico Restaurant",
    "wof:placetype":"venue"
},
  "geometry": {"coordinates":[-85.698522,42.91341],"type":"Point"}
}