{
  "type": "Feature",
  "properties": {
    "iso:country":"US",
    "sg:address":"1209 Applewood Dr",
    "sg:city":"Owosso",
    "sg:classifiers":[
        {
            "category":"Professional",
            "subcategory":"Management & Consulting",
            "type":"Services"
        }
    ],
    "sg:phone":"+1 989 723 3435",
    "sg:postcode":"48867",
    "sg:province":"MI",
    "sg:tags":[
        "consultant"
    ],
    "wof:name":"Creative Focus",
    "wof:placetype":"venue"
},
  "geometry": {"coordinates":[-84.185242,43.009131],"type":"Point"}
}