{
  "type": "Feature",
  "properties": {
    "iso:country":"US",
    "sg:address":"2900 Kraft Rd",
    "sg:city":"Fort Gratiot",
    "sg:classifiers":[
        {
            "category":"Recreation",
            "type":"Entertainment"
        }
    ],
    "sg:phone":"+1 810 385 4475",
    "sg:postcode":"48059",
    "sg:province":"MI",
    "sg:tags":[
        "club",
        "sport",
        "private"
    ],
    "wof:name":"Birchwood Athletic Club",
    "wof:placetype":"venue"
},
  "geometry": {"coordinates":[-82.450975,43.025235],"type":"Point"}
}