{
  "type": "Feature",
  "properties": {
    "iso:country":"US",
    "sg:address":"34200 Woodward Ave",
    "sg:city":"Birmingham",
    "sg:classifiers":[
        {
            "category":"Shopping",
            "subcategory":"Mobile Phones",
            "type":"Retail Goods"
        }
    ],
    "sg:phone":"+1 248 593 8579",
    "sg:postcode":"48009",
    "sg:province":"MI",
    "wof:name":"AT&T Detroit",
    "wof:placetype":"venue"
},
  "geometry": {"coordinates":[-83.207441,42.540713],"type":"Point"}
}