{
  "type": "Feature",
  "properties": {
    "iso:country":"US",
    "sg:address":"1600 Rochester Rd",
    "sg:city":"Royal Oak",
    "sg:classifiers":[
        {
            "category":"Shopping",
            "subcategory":"Thrift Store",
            "type":"Retail Goods"
        }
    ],
    "sg:phone":"+1 248 542 7767",
    "sg:postcode":"48067",
    "sg:province":"MI",
    "wof:name":"TJ's Sweet Repeats",
    "wof:placetype":"venue"
},
  "geometry": {"coordinates":[-83.14313,42.503076],"type":"Point"}
}