{
  "type": "Feature",
  "properties": {
    "iso:country":"US",
    "sg:address":"3906 Limerick Cir",
    "sg:city":"Lansing",
    "sg:classifiers":[
        {
            "category":"Professional",
            "subcategory":"Business Services",
            "type":"Services"
        }
    ],
    "sg:phone":"+1 517 393 7247",
    "sg:postcode":"48911",
    "sg:province":"MI",
    "wof:name":"Burgess Liquidations",
    "wof:placetype":"venue"
},
  "geometry": {"coordinates":[-84.604912,42.69011],"type":"Point"}
}