{
  "type": "Feature",
  "properties": {
    "iso:country":"US",
    "sg:address":"180 N Nanagosa Trl",
    "sg:city":"Suttons Bay",
    "sg:classifiers":[
        {
            "category":"Farming",
            "subcategory":"Orchard",
            "type":"Manufacturing & Wholesale Goods"
        }
    ],
    "sg:phone":"+1 231 271 6681",
    "sg:postcode":"49682",
    "sg:province":"MI",
    "sg:tags":[
        "fruit",
        "tree"
    ],
    "wof:name":"Sutton Point Farms",
    "wof:placetype":"venue"
},
  "geometry": {"coordinates":[-85.600826,44.982593],"type":"Point"}
}