{
  "type": "Feature",
  "properties": {
    "iso:country":"US",
    "sg:address":"34705 W 12 Mile Rd Ste 311",
    "sg:city":"Farmington Hills",
    "sg:classifiers":[
        {
            "category":"Banks & Credit Unions",
            "subcategory":"Atm",
            "type":"Services"
        }
    ],
    "sg:phone":"+1 248 553 4333",
    "sg:postcode":"48331",
    "sg:province":"MI",
    "sg:tags":[
        "bankruptcy"
    ],
    "wof:name":"Debrincat and Padgett",
    "wof:placetype":"venue"
},
  "geometry": {"coordinates":[-83.391998,42.4981],"type":"Point"}
}