{
  "type": "Feature",
  "properties": {
    "iso:country":"US",
    "sg:address":"63237 State Hwy 40",
    "sg:city":"Lawton",
    "sg:classifiers":[
        {
            "category":"Organizations",
            "subcategory":"Community Association",
            "type":"Services"
        }
    ],
    "sg:phone":"+1 269 624 5500",
    "sg:postcode":"49065",
    "sg:province":"MI",
    "sg:tags":[
        "fraternal"
    ],
    "wof:name":"Paw Paw Eagles",
    "wof:placetype":"venue"
},
  "geometry": {"coordinates":[-85.855532,42.189253],"type":"Point"}
}