{
  "type": "Feature",
  "properties": {
    "iso:country":"US",
    "sg:address":"Laurel Park Pl",
    "sg:city":"Livonia",
    "sg:classifiers":[
        {
            "category":"Shopping",
            "subcategory":"Optician",
            "type":"Retail Goods"
        },
        {
            "category":"Shopping",
            "subcategory":"Jewelry",
            "type":"Retail Goods"
        }
    ],
    "sg:phone":"+1 734 591 6250",
    "sg:postcode":"48150",
    "sg:province":"MI",
    "sg:tags":[
        "watch",
        "eyewear"
    ],
    "wof:name":"Sunglass Hut International-Watch Station",
    "wof:placetype":"venue"
},
  "geometry": {"coordinates":[-83.369698,42.363602],"type":"Point"}
}