{
  "type": "Feature",
  "properties": {
    "iso:country":"US",
    "sg:address":"23104 Croft Ave",
    "sg:city":"Flat Rock",
    "sg:classifiers":[
        {
            "category":"Manufacturing",
            "subcategory":"Toys & Sporting Goods",
            "type":"Manufacturing & Wholesale Goods"
        }
    ],
    "sg:phone":"+1 734 379 4665",
    "sg:postcode":"48134",
    "sg:province":"MI",
    "sg:tags":[
        "mfg"
    ],
    "wof:name":"Pams Country Corner",
    "wof:placetype":"venue"
},
  "geometry": {"coordinates":[-83.258473,42.091096],"type":"Point"}
}