{
  "type": "Feature",
  "properties": {
    "iso:country":"US",
    "sg:address":"120 Cleveland St E",
    "sg:city":"Coopersville",
    "sg:classifiers":[
        {
            "category":"Professional",
            "subcategory":"Business Services",
            "type":"Services"
        }
    ],
    "sg:phone":"+1 616 837 6669",
    "sg:postcode":"49404",
    "sg:province":"MI",
    "sg:tags":[
        "notary",
        "public"
    ],
    "wof:name":"Doug Lemmen",
    "wof:placetype":"venue"
},
  "geometry": {"coordinates":[-85.925839,43.074571],"type":"Point"}
}