{
  "type": "Feature",
  "properties": {
    "iso:country":"US",
    "sg:address":"19541 Grand River Ave",
    "sg:city":"Detroit",
    "sg:classifiers":[
        {
            "category":"Retail",
            "subcategory":"Auto Repair",
            "type":"Services"
        }
    ],
    "sg:phone":"+1 313 535 3600",
    "sg:postcode":"48223",
    "sg:province":"MI",
    "sg:tags":[
        "glass",
        "replacement"
    ],
    "sg:website":"hendersonglass.com/",
    "wof:name":"Henderson Glass Inc",
    "wof:placetype":"venue"
},
  "geometry": {"coordinates":[-83.23490099999999,42.407299],"type":"Point"}
}