{
  "type": "Feature",
  "properties": {
    "iso:country":"US",
    "sg:address":"9640 Highland Rd",
    "sg:city":"White Lake",
    "sg:classifiers":[
        {
            "category":"Retail",
            "subcategory":"Auto Repair",
            "type":"Services"
        }
    ],
    "sg:phone":"+1 248 698 3000",
    "sg:postcode":"48386",
    "sg:province":"MI",
    "sg:tags":[
        "general"
    ],
    "wof:name":"Cars Inc",
    "wof:placetype":"venue"
},
  "geometry": {"coordinates":[-83.49153099999999,42.650324],"type":"Point"}
}