{
  "type": "Feature",
  "properties": {
    "iso:country":"US",
    "sg:address":"6995 Center Rd",
    "sg:city":"Traverse City",
    "sg:classifiers":[
        {
            "category":"Shopping",
            "subcategory":"Used Merchandise",
            "type":"Retail Goods"
        }
    ],
    "sg:phone":"+1 231 941 1181",
    "sg:postcode":"49686",
    "sg:province":"MI",
    "wof:name":"Amy Jos Folk Art & Antiques",
    "wof:placetype":"venue"
},
  "geometry": {"coordinates":[-85.574873,44.788114],"type":"Point"}
}