{
  "type": "Feature",
  "properties": {
    "iso:country":"US",
    "sg:address":"58922 Main St",
    "sg:city":"New Haven",
    "sg:classifiers":[
        {
            "category":"Professional",
            "subcategory":"Management & Consulting",
            "type":"Services"
        }
    ],
    "sg:phone":"+1 586 749 3890",
    "sg:postcode":"48048",
    "sg:province":"MI",
    "sg:tags":[
        "consultant",
        "business"
    ],
    "wof:name":"Bob Richard & Assoc",
    "wof:placetype":"venue"
},
  "geometry": {"coordinates":[-82.80733600000001,42.733294],"type":"Point"}
}