{
  "type": "Feature",
  "properties": {
    "iso:country":"US",
    "sg:address":"3955 W Big Beaver Rd",
    "sg:city":"Troy",
    "sg:classifiers":[
        {
            "category":"Organizations",
            "subcategory":"Religious Organization",
            "type":"Services"
        }
    ],
    "sg:phone":"+1 248 644 0512",
    "sg:postcode":"48084",
    "sg:province":"MI",
    "sg:tags":[
        "christian",
        "church"
    ],
    "wof:name":"Central Wodward Christn Church",
    "wof:placetype":"venue"
},
  "geometry": {"coordinates":[-83.206098,42.560582],"type":"Point"}
}