{
  "type": "Feature",
  "properties": {
    "iso:country":"US",
    "sg:address":"2751 Elmridge Dr NW",
    "sg:city":"Grand Rapids",
    "sg:classifiers":[
        {
            "category":"Wholesale",
            "subcategory":"Vending Machines",
            "type":"Manufacturing & Wholesale Goods"
        }
    ],
    "sg:phone":"+1 616 791 2025",
    "sg:postcode":"49534",
    "sg:province":"MI",
    "sg:website":"www.jbosvending.com",
    "wof:name":"J Bos Vending Svc",
    "wof:placetype":"venue"
},
  "geometry": {"coordinates":[-85.742491,43.010939],"type":"Point"}
}