{
  "type": "Feature",
  "properties": {
    "iso:country":"US",
    "sg:address":"233 S Cochran Ave",
    "sg:city":"Charlotte",
    "sg:classifiers":[
        {
            "category":"Shopping",
            "subcategory":"Clothing, Apparel, & Fashions",
            "type":"Retail Goods"
        }
    ],
    "sg:phone":"+1 517 543 7571",
    "sg:postcode":"48813",
    "sg:province":"MI",
    "wof:name":"Fashion Tailoring",
    "wof:placetype":"venue"
},
  "geometry": {"coordinates":[-84.835809,42.561823],"type":"Point"}
}