{
  "type": "Feature",
  "properties": {
    "iso:country":"US",
    "sg:address":"40715 Brentwood Dr",
    "sg:city":"Sterling Heights",
    "sg:classifiers":[
        {
            "category":"Manufacturing",
            "subcategory":"Aerospace",
            "type":"Manufacturing & Wholesale Goods"
        }
    ],
    "sg:phone":"+1 586 268 0624",
    "sg:postcode":"48310",
    "sg:province":"MI",
    "sg:tags":[
        "aircraft"
    ],
    "wof:name":"Sterner Aircraft",
    "wof:placetype":"venue"
},
  "geometry": {"coordinates":[-83.055108,42.592518],"type":"Point"}
}