{
  "type": "Feature",
  "properties": {
    "iso:country":"US",
    "sg:address":"25500 Meadowbrook Rd",
    "sg:city":"Novi",
    "sg:classifiers":[
        {
            "category":"Health Services",
            "subcategory":"Doctor",
            "type":"Services"
        }
    ],
    "sg:phone":"+1 248 426 1300",
    "sg:postcode":"48375",
    "sg:province":"MI",
    "sg:tags":[
        "physician",
        "oncology",
        "urology",
        "surgeons",
        "pediatrics-urology",
        "surgeon",
        "sexual",
        "dysfunction"
    ],
    "sg:website":"http://tcurology.com",
    "wof:name":"Tri County Urologists",
    "wof:placetype":"venue"
},
  "geometry": {"coordinates":[-83.45568799999999,42.478802],"type":"Point"}
}