{
  "type": "Feature",
  "properties": {
    "iso:country":"US",
    "sg:address":"205 S Main St",
    "sg:city":"Marine City",
    "sg:classifiers":[
        {
            "category":"Organizations",
            "subcategory":"Religious Organization",
            "type":"Services"
        }
    ],
    "sg:phone":"+1 810 765 5653",
    "sg:postcode":"48039",
    "sg:province":"MI",
    "wof:name":"Kings Road Christian Chapel",
    "wof:placetype":"venue"
},
  "geometry": {"coordinates":[-82.493039,42.718005],"type":"Point"}
}