{
  "type": "Feature",
  "properties": {
    "iso:country":"US",
    "sg:address":"260 Town Center Dr",
    "sg:city":"Dearborn",
    "sg:classifiers":[
        {
            "category":"Travel",
            "subcategory":"Hotels & Motels",
            "type":"Entertainment"
        },
        {
            "category":"Real Estate",
            "subcategory":"Real Estate Operator",
            "type":"Services"
        }
    ],
    "sg:phone":"+1 313 336 0021",
    "sg:postcode":"48126",
    "sg:province":"MI",
    "sg:tags":[
        "apartment"
    ],
    "sg:website":"www.extendedstayamerica.com",
    "wof:name":"Extended Stayamerica",
    "wof:placetype":"venue"
},
  "geometry": {"coordinates":[-83.221001,42.32],"type":"Point"}
}