{
  "type": "Feature",
  "properties": {
    "iso:country":"US",
    "sg:address":"3148 S State Rd",
    "sg:city":"Ionia",
    "sg:classifiers":[
        {
            "category":"Government",
            "subcategory":"Police Station",
            "type":"Public Place"
        }
    ],
    "sg:phone":"+1 616 523 1852",
    "sg:postcode":"48846",
    "sg:province":"MI",
    "sg:tags":[
        "sheriff"
    ],
    "wof:name":"Ionia County Sheriff Office",
    "wof:placetype":"venue"
},
  "geometry": {"coordinates":[-85.07483000000001,42.940027],"type":"Point"}
}