{
  "type": "Feature",
  "properties": {
    "iso:country":"US",
    "sg:address":"15099 Northline Rd",
    "sg:city":"Southgate",
    "sg:classifiers":[
        {
            "category":"Restaurant",
            "type":"Food & Drink"
        },
        {
            "category":"Food & Beverages",
            "subcategory":"Meat & Fish",
            "type":"Retail Goods"
        }
    ],
    "sg:phone":"+1 734 324 1111",
    "sg:postcode":"48195",
    "sg:province":"MI",
    "sg:tags":[
        "greek",
        "hot",
        "dog"
    ],
    "sg:website":"www.wildconey.com",
    "wof:name":"Wild Coney & Grill",
    "wof:placetype":"venue"
},
  "geometry": {"coordinates":[-83.206693,42.213179],"type":"Point"}
}