{
  "type": "Feature",
  "properties": {
    "iso:country":"US",
    "sg:address":"22546 Michigan Ave",
    "sg:city":"Dearborn",
    "sg:classifiers":[
        {
            "category":"Retail",
            "subcategory":"Funeral Services",
            "type":"Services"
        }
    ],
    "sg:phone":"+1 313 561 1500",
    "sg:postcode":"48124",
    "sg:province":"MI",
    "sg:tags":[
        "home",
        "cemetery"
    ],
    "wof:name":"Howe-Peterson Funeral Home",
    "wof:placetype":"venue"
},
  "geometry": {"coordinates":[-83.25279999999999,42.304298],"type":"Point"}
}