{
  "type": "Feature",
  "properties": {
    "iso:country":"US",
    "sg:address":"538 Nichols Rd",
    "sg:city":"Kalamazoo",
    "sg:classifiers":[
        {
            "category":"Organizations",
            "subcategory":"Religious Organization",
            "type":"Services"
        }
    ],
    "sg:phone":"+1 269 344 7165",
    "sg:postcode":"49006",
    "sg:province":"MI",
    "sg:tags":[
        "church"
    ],
    "wof:name":"Westwood United Methodist Chr",
    "wof:placetype":"venue"
},
  "geometry": {"coordinates":[-85.628737,42.296713],"type":"Point"}
}