{
  "type": "Feature",
  "properties": {
    "iso:country":"US",
    "sg:address":"33242 Woodward Ave",
    "sg:city":"Birmingham",
    "sg:classifiers":[
        {
            "category":"Home & Garden",
            "subcategory":"Household Appliances",
            "type":"Retail Goods"
        }
    ],
    "sg:phone":"+1 248 258 8911",
    "sg:postcode":"48009",
    "sg:province":"MI",
    "sg:tags":[
        "cleaners",
        "vacuum"
    ],
    "wof:name":"Bank's Vacuum Superstores",
    "wof:placetype":"venue"
},
  "geometry": {"coordinates":[-83.201382,42.533228],"type":"Point"}
}