{
  "type": "Feature",
  "properties": {
    "iso:country":"US",
    "sg:address":"1739 Manistee Dr",
    "sg:city":"Muskegon",
    "sg:classifiers":[
        {
            "category":"Building & Trades",
            "subcategory":"Construction",
            "type":"Services"
        }
    ],
    "sg:phone":"+1 231 744 8354",
    "sg:postcode":"49445",
    "sg:province":"MI",
    "sg:tags":[
        "steel",
        "erectors"
    ],
    "wof:name":"Neux's Welding Erection Co",
    "wof:placetype":"venue"
},
  "geometry": {"coordinates":[-86.284541,43.274025],"type":"Point"}
}