{
  "type": "Feature",
  "properties": {
    "iso:country":"US",
    "sg:address":"11600 Wayne Rd",
    "sg:city":"Romulus",
    "sg:classifiers":[
        {
            "category":"Manufacturing",
            "subcategory":"Paper Products",
            "type":"Manufacturing & Wholesale Goods"
        }
    ],
    "sg:phone":"+1 734 941 6090",
    "sg:postcode":"48174",
    "sg:province":"MI",
    "sg:tags":[
        "label"
    ],
    "wof:name":"Rainbow Tape & Label Inc",
    "wof:placetype":"venue"
},
  "geometry": {"coordinates":[-83.384381,42.218192],"type":"Point"}
}