{
  "type": "Feature",
  "properties": {
    "iso:country":"US",
    "sg:address":"20535 Powers Ave",
    "sg:city":"Dearborn Heights",
    "sg:classifiers":[
        {
            "category":"Shopping",
            "type":"Retail Goods"
        }
    ],
    "sg:phone":"+1 313 565 3974",
    "sg:postcode":"48125",
    "sg:province":"MI",
    "sg:tags":[
        "merchandise"
    ],
    "wof:name":"Silver Solution",
    "wof:placetype":"venue"
},
  "geometry": {"coordinates":[-83.238274,42.27327],"type":"Point"}
}