{
  "type": "Feature",
  "properties": {
    "iso:country":"US",
    "sg:address":"5833 W Saginaw Hwy",
    "sg:city":"Lansing",
    "sg:classifiers":[
        {
            "category":"Shopping",
            "subcategory":"Department Store",
            "type":"Retail Goods"
        }
    ],
    "sg:phone":"+1 517 321 1304",
    "sg:postcode":"48917",
    "sg:province":"MI",
    "sg:website":"www.tjmaxx.com",
    "wof:name":"T J Maxx",
    "wof:placetype":"venue"
},
  "geometry": {"coordinates":[-84.633049,42.740972],"type":"Point"}
}