{
  "type": "Feature",
  "properties": {
    "iso:country":"US",
    "sg:address":"106 W Walker St",
    "sg:city":"Saint Johns",
    "sg:classifiers":[
        {
            "category":"Professional",
            "subcategory":"Lawyer & Legal Services",
            "type":"Services"
        }
    ],
    "sg:phone":"+1 989 224 1500",
    "sg:postcode":"48879",
    "sg:province":"MI",
    "wof:name":"Louis K Nigg",
    "wof:placetype":"venue"
},
  "geometry": {"coordinates":[-84.559769,43.002522],"type":"Point"}
}