{
  "type": "Feature",
  "properties": {
    "iso:country":"US",
    "sg:address":"4160 Keller Rd",
    "sg:city":"Holt",
    "sg:classifiers":[
        {
            "category":"Wholesale",
            "subcategory":"Machinery & Supplies",
            "type":"Manufacturing & Wholesale Goods"
        }
    ],
    "sg:phone":"+1 517 694 7824",
    "sg:postcode":"48842",
    "sg:province":"MI",
    "sg:tags":[
        "repair",
        "industrial",
        "for",
        "equipment"
    ],
    "wof:name":"J B Equipment Inc",
    "wof:placetype":"venue"
},
  "geometry": {"coordinates":[-84.510578,42.647552],"type":"Point"}
}