{
  "type": "Feature",
  "properties": {
    "iso:country":"US",
    "sg:address":"96 Market St",
    "sg:city":"Mount Clemens",
    "sg:classifiers":[
        {
            "category":"Manufacturing",
            "subcategory":"Printing",
            "type":"Manufacturing & Wholesale Goods"
        }
    ],
    "sg:phone":"+1 586 804 3827",
    "sg:postcode":"48043",
    "sg:province":"MI",
    "sg:tags":[
        "newspaper"
    ],
    "wof:name":"Bar Street Journal",
    "wof:placetype":"venue"
},
  "geometry": {"coordinates":[-82.878598,42.601385],"type":"Point"}
}