{
  "type": "Feature",
  "properties": {
    "iso:country":"US",
    "sg:address":"435 S State St",
    "sg:city":"Ann Arbor",
    "sg:classifiers":[
        {
            "category":"Education",
            "subcategory":"College",
            "type":"Public Place"
        }
    ],
    "sg:phone":"+1 734 763 2066",
    "sg:postcode":"48109",
    "sg:province":"MI",
    "sg:tags":[
        "department",
        "university"
    ],
    "wof:name":"Marc",
    "wof:placetype":"venue"
},
  "geometry": {"coordinates":[-83.740635,42.276823],"type":"Point"}
}