{
  "type": "Feature",
  "properties": {
    "iso:country":"US",
    "sg:address":"31155 Northwestern Hwy Ste 250",
    "sg:city":"Farmington Hills",
    "sg:classifiers":[
        {
            "category":"Banks & Credit Unions",
            "subcategory":"Bank",
            "type":"Services"
        }
    ],
    "sg:phone":"+1 248 785 5500",
    "sg:postcode":"48334",
    "sg:province":"MI",
    "wof:name":"Community Choice Credit Union",
    "wof:placetype":"venue"
},
  "geometry": {"coordinates":[-83.33414399999999,42.515055],"type":"Point"}
}