{
  "type": "Feature",
  "properties": {
    "iso:country":"US",
    "sg:address":"2690 W Bloomfield Oaks Dr",
    "sg:city":"West Bloomfield",
    "sg:classifiers":[
        {
            "category":"Building & Trades",
            "subcategory":"Construction",
            "type":"Services"
        }
    ],
    "sg:phone":"+1 248 363 4262",
    "sg:postcode":"48324",
    "sg:province":"MI",
    "sg:tags":[
        "house"
    ],
    "wof:name":"Sonshine Construction Co",
    "wof:placetype":"venue"
},
  "geometry": {"coordinates":[-83.425568,42.596687],"type":"Point"}
}