{
  "type": "Feature",
  "properties": {
    "iso:country":"US",
    "sg:address":"1020 E Main St",
    "sg:city":"Owosso",
    "sg:classifiers":[
        {
            "category":"Autos & Motor Vehicles",
            "subcategory":"Auto Supplies",
            "type":"Retail Goods"
        }
    ],
    "sg:phone":"+1 989 725 2972",
    "sg:postcode":"48867",
    "sg:province":"MI",
    "sg:tags":[
        "automobile",
        "parts"
    ],
    "wof:name":"Advance Auto Parts Inc",
    "wof:placetype":"venue"
},
  "geometry": {"coordinates":[-84.153548,42.997616],"type":"Point"}
}