{
  "type": "Feature",
  "properties": {
    "iso:country":"US",
    "sg:address":"2769 Walker Rd",
    "sg:city":"Carsonville",
    "sg:classifiers":[
        {
            "category":"Shopping",
            "subcategory":"Used Merchandise",
            "type":"Retail Goods"
        }
    ],
    "sg:phone":"+1 810 657 9192",
    "sg:postcode":"48419",
    "sg:province":"MI",
    "wof:name":"Grandmas Closet",
    "wof:placetype":"venue"
},
  "geometry": {"coordinates":[-82.72392000000001,43.38125],"type":"Point"}
}