{
  "type": "Feature",
  "properties": {
    "iso:country":"US",
    "sg:address":"717 Ament St",
    "sg:city":"Owosso",
    "sg:classifiers":[
        {
            "category":"Social Services",
            "subcategory":"Child Care",
            "type":"Services"
        }
    ],
    "sg:phone":"+1 989 725 2927",
    "sg:postcode":"48867",
    "sg:province":"MI",
    "sg:tags":[
        "day"
    ],
    "wof:name":"Elaine Sue Zalesak",
    "wof:placetype":"venue"
},
  "geometry": {"coordinates":[-84.180751,42.989439],"type":"Point"}
}