{
  "type": "Feature",
  "properties": {
    "iso:country":"US",
    "sg:address":"2248 Crooks Rd",
    "sg:city":"Rochester Hills",
    "sg:classifiers":[
        {
            "category":"Shopping",
            "subcategory":"Jewelry",
            "type":"Retail Goods"
        }
    ],
    "sg:phone":"+1 248 299 5250",
    "sg:postcode":"48309",
    "sg:province":"MI",
    "sg:tags":[
        "jeweler"
    ],
    "wof:name":"J Thomas Jewelers",
    "wof:placetype":"venue"
},
  "geometry": {"coordinates":[-83.170844,42.644647],"type":"Point"}
}