{
  "type": "Feature",
  "properties": {
    "iso:country":"US",
    "sg:address":"27240 Haggerty Rd",
    "sg:city":"Farmington Hills",
    "sg:classifiers":[
        {
            "category":"Professional",
            "subcategory":"Employment Agencies",
            "type":"Services"
        }
    ],
    "sg:phone":"+1 248 488 0350",
    "sg:postcode":"48331",
    "sg:province":"MI",
    "sg:tags":[
        "help",
        "contractor"
    ],
    "wof:name":"Prime Health Care Staffing",
    "wof:placetype":"venue"
},
  "geometry": {"coordinates":[-83.436027,42.492525],"type":"Point"}
}