{
  "type": "Feature",
  "properties": {
    "iso:country":"US",
    "sg:address":"811 W Maumee St",
    "sg:city":"Adrian",
    "sg:classifiers":[
        {
            "category":"Professional",
            "subcategory":"Detective & Security Services",
            "type":"Services"
        }
    ],
    "sg:phone":"+1 517 263 8112",
    "sg:postcode":"49221",
    "sg:province":"MI",
    "sg:tags":[
        "car"
    ],
    "wof:name":"Brazee Safety & Security Inc",
    "wof:placetype":"venue"
},
  "geometry": {"coordinates":[-84.048975,41.899891],"type":"Point"}
}