{
  "type": "Feature",
  "properties": {
    "iso:country":"US",
    "sg:address":"12935 Quincy St",
    "sg:city":"Holland",
    "sg:classifiers":[
        {
            "category":"Building & Trades",
            "subcategory":"Construction",
            "type":"Services"
        }
    ],
    "sg:phone":"+1 616 399 9785",
    "sg:postcode":"49424",
    "sg:province":"MI",
    "sg:tags":[
        "roofing",
        "contractor"
    ],
    "wof:name":"Holland Ready Roofing Co",
    "wof:placetype":"venue"
},
  "geometry": {"coordinates":[-86.100813,42.84107],"type":"Point"}
}