{
  "type": "Feature",
  "properties": {
    "iso:country":"US",
    "sg:address":"3510 Hanes Rd",
    "sg:city":"Vassar",
    "sg:classifiers":[
        {
            "category":"Wholesale",
            "subcategory":"Vending Machines",
            "type":"Manufacturing & Wholesale Goods"
        }
    ],
    "sg:phone":"+1 989 823 3024",
    "sg:postcode":"48768",
    "sg:province":"MI",
    "sg:tags":[
        "operator"
    ],
    "wof:name":"Charles L Smithson",
    "wof:placetype":"venue"
},
  "geometry": {"coordinates":[-83.482071,43.337814],"type":"Point"}
}