{
  "type": "Feature",
  "properties": {
    "iso:country":"US",
    "sg:address":"7679 Capac Rd",
    "sg:city":"Lynn",
    "sg:classifiers":[
        {
            "category":"Real Estate",
            "subcategory":"Surveying",
            "type":"Services"
        },
        {
            "category":"Professional",
            "subcategory":"Business Services",
            "type":"Services"
        }
    ],
    "sg:phone":"+1 810 395 8515",
    "sg:postcode":"48097",
    "sg:province":"MI",
    "sg:tags":[
        "surveyor"
    ],
    "wof:name":"Polaris Survey",
    "wof:placetype":"venue"
},
  "geometry": {"coordinates":[-82.933457,43.115452],"type":"Point"}
}