{
  "type": "Feature",
  "properties": {
    "iso:country":"US",
    "sg:address":"201 E Lead St",
    "sg:city":"Bessemer",
    "sg:classifiers":[
        {
            "category":"Ice Cream",
            "type":"Food & Drink"
        }
    ],
    "sg:menulink":"http://www.allmenus.com/mi/bessemer/168505-dairy-queen/menu/",
    "sg:phone":"+1 906 663 6061",
    "sg:postcode":"49911",
    "sg:province":"MI",
    "sg:tags":[
        "burger",
        "american"
    ],
    "wof:name":"Dairy Queen",
    "wof:placetype":"venue"
},
  "geometry": {"coordinates":[-90.050331,46.481229],"type":"Point"}
}