{
  "type": "Feature",
  "properties": {
    "iso:country":"US",
    "sg:address":"1405 Aiken Rd",
    "sg:city":"Owosso",
    "sg:classifiers":[
        {
            "category":"Retail",
            "subcategory":"Repair Shop",
            "type":"Services"
        }
    ],
    "sg:phone":"+1 989 725 7700",
    "sg:postcode":"48867",
    "sg:province":"MI",
    "sg:tags":[
        "appliance"
    ],
    "wof:name":"All Brands Appliance Service",
    "wof:placetype":"venue"
},
  "geometry": {"coordinates":[-84.148138,42.977056],"type":"Point"}
}