{
  "type": "Feature",
  "properties": {
    "iso:country":"US",
    "sg:address":"2176 Baldwin Rd",
    "sg:city":"Lapeer",
    "sg:classifiers":[
        {
            "category":"Building & Trades",
            "subcategory":"Construction",
            "type":"Services"
        }
    ],
    "sg:phone":"+1 810 667 4635",
    "sg:postcode":"48446",
    "sg:province":"MI",
    "sg:tags":[
        "hanging",
        "painter",
        "contractor"
    ],
    "wof:name":"Sweeney's Painting Contractors",
    "wof:placetype":"venue"
},
  "geometry": {"coordinates":[-83.340458,42.996575],"type":"Point"}
}