{
  "type": "Feature",
  "properties": {
    "iso:country":"US",
    "sg:address":"12150 S Fox Hollow Dr",
    "sg:city":"Cedar",
    "sg:classifiers":[
        {
            "category":"Manufacturing",
            "subcategory":"Retail Goods",
            "type":"Manufacturing & Wholesale Goods"
        }
    ],
    "sg:phone":"+1 231 933 0502",
    "sg:postcode":"49621",
    "sg:province":"MI",
    "sg:tags":[
        "product",
        "mfg"
    ],
    "wof:name":"Leones",
    "wof:placetype":"venue"
},
  "geometry": {"coordinates":[-85.716914,44.802971],"type":"Point"}
}