{
  "type": "Feature",
  "properties": {
    "iso:country":"US",
    "sg:address":"950 28th St SE",
    "sg:city":"Grand Rapids",
    "sg:classifiers":[
        {
            "category":"Professional",
            "subcategory":"Management & Consulting",
            "type":"Services"
        }
    ],
    "sg:phone":"+1 616 243 5577",
    "sg:postcode":"49508",
    "sg:province":"MI",
    "sg:tags":[
        "sales",
        "representative"
    ],
    "wof:name":"H S Buy Van",
    "wof:placetype":"venue"
},
  "geometry": {"coordinates":[-85.64458,42.912712],"type":"Point"}
}