{
  "type": "Feature",
  "properties": {
    "iso:country":"US",
    "sg:address":"3855 Dix Hwy",
    "sg:city":"Lincoln Park",
    "sg:classifiers":[
        {
            "category":"Retail",
            "subcategory":"Laundry & Dry Cleaning",
            "type":"Services"
        }
    ],
    "sg:phone":"+1 313 383 3600",
    "sg:postcode":"48146",
    "sg:province":"MI",
    "wof:name":"Annex Cleaners",
    "wof:placetype":"venue"
},
  "geometry": {"coordinates":[-83.194298,42.227901],"type":"Point"}
}