{
  "type": "Feature",
  "properties": {
    "iso:country":"US",
    "sg:address":"42075 Grand River Ave",
    "sg:city":"Novi",
    "sg:classifiers":[
        {
            "category":"Real Estate",
            "subcategory":"Developer",
            "type":"Services"
        }
    ],
    "sg:phone":"+1 248 344 8690",
    "sg:postcode":"48375",
    "sg:province":"MI",
    "wof:name":"T G Land Development",
    "wof:placetype":"venue"
},
  "geometry": {"coordinates":[-83.4653,42.478394],"type":"Point"}
}