{
  "type": "Feature",
  "properties": {
    "iso:country":"US",
    "sg:address":"4532 Vanderbilt Ave",
    "sg:city":"Portage",
    "sg:classifiers":[
        {
            "category":"Professional",
            "subcategory":"Management & Consulting",
            "type":"Services"
        }
    ],
    "sg:phone":"+1 269 329 6949",
    "sg:postcode":"49024",
    "sg:province":"MI",
    "sg:tags":[
        "business"
    ],
    "wof:name":"Progressive Consulting Service",
    "wof:placetype":"venue"
},
  "geometry": {"coordinates":[-85.640612,42.186565],"type":"Point"}
}