{
  "type": "Feature",
  "properties": {
    "iso:country":"US",
    "sg:address":"3564 Rabidue Rd",
    "sg:city":"North Street",
    "sg:classifiers":[
        {
            "category":"Insurance",
            "subcategory":"Insurance Agent",
            "type":"Services"
        }
    ],
    "sg:phone":"+1 810 987 3458",
    "sg:postcode":"48049",
    "sg:province":"MI",
    "wof:name":"AAL",
    "wof:placetype":"venue"
},
  "geometry": {"coordinates":[-82.612662,43.008558],"type":"Point"}
}