{
  "type": "Feature",
  "properties": {
    "iso:country":"US",
    "sg:address":"7637 Division Ave S",
    "sg:city":"Grand Rapids",
    "sg:classifiers":[
        {
            "category":"Retail",
            "subcategory":"Auto Repair",
            "type":"Services"
        }
    ],
    "sg:phone":"+1 616 281 2730",
    "sg:postcode":"49548",
    "sg:province":"MI",
    "sg:tags":[
        "body",
        "automobile",
        "painting"
    ],
    "wof:name":"O'Kennedys Collision",
    "wof:placetype":"venue"
},
  "geometry": {"coordinates":[-85.663647,42.825906],"type":"Point"}
}