{
  "type": "Feature",
  "properties": {
    "iso:country":"US",
    "sg:address":"770 Gilead Lake Rd",
    "sg:city":"Bronson",
    "sg:classifiers":[
        {
            "category":"Professional",
            "subcategory":"Business Services",
            "type":"Services"
        }
    ],
    "sg:phone":"+1 517 369 7213",
    "sg:postcode":"49028",
    "sg:province":"MI",
    "wof:name":"Stateline Computer Solutions",
    "wof:placetype":"venue"
},
  "geometry": {"coordinates":[-85.15549300000001,41.800957],"type":"Point"}
}