{
  "type": "Feature",
  "properties": {
    "iso:country":"US",
    "sg:address":"3000 E Telluride Ave",
    "sg:city":"Brighton",
    "sg:classifiers":[
        {
            "category":"Home & Garden",
            "subcategory":"Household Appliances",
            "type":"Retail Goods"
        }
    ],
    "sg:phone":"+1 810 599 7825",
    "sg:postcode":"48114",
    "sg:province":"MI",
    "sg:tags":[
        "cleaners",
        "vacuum"
    ],
    "wof:name":"Accs Consulting LLC",
    "wof:placetype":"venue"
},
  "geometry": {"coordinates":[-83.799688,42.558884],"type":"Point"}
}