{
  "type": "Feature",
  "properties": {
    "iso:country":"US",
    "sg:address":"8510 Algoma Ave NE",
    "sg:city":"Rockford",
    "sg:classifiers":[
        {
            "category":"Retail",
            "subcategory":"Auto Rental",
            "type":"Services"
        }
    ],
    "sg:phone":"+1 616 866 7788",
    "sg:postcode":"49341",
    "sg:province":"MI",
    "sg:tags":[
        "mobile",
        "home",
        "lease"
    ],
    "sg:website":"www.brsalesandleasing.com",
    "wof:name":"B & R Sales & Leasing",
    "wof:placetype":"venue"
},
  "geometry": {"coordinates":[-85.61075200000001,43.118711],"type":"Point"}
}