{
  "type": "Feature",
  "properties": {
    "iso:country":"US",
    "sg:address":"187 Monroe Ave NW",
    "sg:city":"Grand Rapids",
    "sg:classifiers":[
        {
            "category":"Real Estate",
            "subcategory":"Real Estate Operator",
            "type":"Services"
        }
    ],
    "sg:phone":"+1 616 774 2000",
    "sg:postcode":"49503",
    "sg:province":"MI",
    "sg:tags":[
        "building",
        "hotel",
        "commercial"
    ],
    "wof:name":"Amway Properties Inc",
    "wof:placetype":"venue"
},
  "geometry": {"coordinates":[-85.67224899999999,42.966803],"type":"Point"}
}