{
  "type": "Feature",
  "properties": {
    "iso:country":"US",
    "sg:address":"69262 N Main St",
    "sg:city":"Richmond",
    "sg:classifiers":[
        {
            "category":"Health Services",
            "subcategory":"Doctor",
            "type":"Services"
        }
    ],
    "sg:phone":"+1 586 727 6215",
    "sg:postcode":"48062",
    "sg:province":"MI",
    "sg:tags":[
        "dentist"
    ],
    "wof:name":"Kenneth Pozolo DDS",
    "wof:placetype":"venue"
},
  "geometry": {"coordinates":[-82.75716199999999,42.811135],"type":"Point"}
}