{
  "type": "Feature",
  "properties": {
    "iso:country":"US",
    "sg:address":"3201 Portage St",
    "sg:city":"Kalamazoo",
    "sg:classifiers":[
        {
            "category":"Banks & Credit Unions",
            "subcategory":"Bank",
            "type":"Services"
        }
    ],
    "sg:phone":"+1 269 388 6249",
    "sg:postcode":"49001",
    "sg:province":"MI",
    "wof:name":"Fidelity Savings Bank FSB",
    "wof:placetype":"venue"
},
  "geometry": {"coordinates":[-85.565432,42.258652],"type":"Point"}
}