{
  "type": "Feature",
  "properties": {
    "iso:country":"US",
    "sg:address":"1316 S Airport Rd W",
    "sg:city":"Traverse City",
    "sg:classifiers":[
        {
            "category":"Shopping",
            "subcategory":"Clothing, Apparel, & Fashions",
            "type":"Retail Goods"
        }
    ],
    "sg:phone":"+1 231 946 0840",
    "sg:postcode":"49686",
    "sg:province":"MI",
    "sg:tags":[
        "shop",
        "bridal"
    ],
    "wof:name":"Fashion Formals Bridal & Tux",
    "wof:placetype":"venue"
},
  "geometry": {"coordinates":[-85.602839,44.733279],"type":"Point"}
}