{
  "type": "Feature",
  "properties": {
    "iso:country":"US",
    "sg:address":"3587 E Apple Ave",
    "sg:city":"Muskegon",
    "sg:classifiers":[
        {
            "category":"Retail",
            "subcategory":"Auto Rental",
            "type":"Services"
        }
    ],
    "sg:phone":"+1 231 777 3921",
    "sg:postcode":"49442",
    "sg:province":"MI",
    "sg:tags":[
        "renting",
        "truck",
        "leasing"
    ],
    "wof:name":"U-Haul Co",
    "wof:placetype":"venue"
},
  "geometry": {"coordinates":[-86.16139800000001,43.234161],"type":"Point"}
}