{
  "type": "Feature",
  "properties": {
    "iso:country":"US",
    "sg:address":"20025 Shadyside St",
    "sg:city":"Livonia",
    "sg:classifiers":[
        {
            "category":"Building & Trades",
            "subcategory":"Construction",
            "type":"Services"
        }
    ],
    "sg:phone":"+1 248 478 3110",
    "sg:postcode":"48152",
    "sg:province":"MI",
    "sg:tags":[
        "contractor"
    ],
    "wof:name":"Twin Valley Corp",
    "wof:placetype":"venue"
},
  "geometry": {"coordinates":[-83.372597,42.435902],"type":"Point"}
}