{
  "type": "Feature",
  "properties": {
    "iso:country":"US",
    "sg:address":"245 Church St",
    "sg:city":"Hubbardston",
    "sg:classifiers":[
        {
            "category":"Professional",
            "subcategory":"Computer Services",
            "type":"Services"
        }
    ],
    "sg:phone":"+1 989 981 6875",
    "sg:postcode":"48845",
    "sg:province":"MI",
    "sg:tags":[
        "related"
    ],
    "wof:name":"A Plus Computer Services",
    "wof:placetype":"venue"
},
  "geometry": {"coordinates":[-84.839468,43.091998],"type":"Point"}
}