{
  "type": "Feature",
  "properties": {
    "iso:country":"US",
    "sg:address":"19035 W Davison Ave",
    "sg:city":"Detroit",
    "sg:classifiers":[
        {
            "category":"Retail",
            "subcategory":"Auto Repair",
            "type":"Services"
        }
    ],
    "sg:phone":"+1 313 835 3425",
    "sg:postcode":"48223",
    "sg:province":"MI",
    "sg:tags":[
        "body",
        "automotive",
        "business"
    ],
    "wof:name":"Solomac Inc",
    "wof:placetype":"venue"
},
  "geometry": {"coordinates":[-83.22799999999999,42.384036],"type":"Point"}
}