{
  "type": "Feature",
  "properties": {
    "iso:country":"US",
    "sg:address":"3181 Donley Rd",
    "sg:city":"Rochester",
    "sg:classifiers":[
        {
            "category":"Freight",
            "type":"Transportation"
        }
    ],
    "sg:phone":"+1 248 844 2976",
    "sg:postcode":"48309",
    "sg:province":"MI",
    "sg:tags":[
        "operator",
        "local",
        "trucking"
    ],
    "wof:name":"Setelia Trucking Inc",
    "wof:placetype":"venue"
},
  "geometry": {"coordinates":[-83.172264,42.631334],"type":"Point"}
}