{
  "type": "Feature",
  "properties": {
    "iso:country":"US",
    "sg:address":"2510 Burton St SE",
    "sg:city":"Grand Rapids",
    "sg:classifiers":[
        {
            "category":"Bars & Pubs",
            "type":"Food & Drink"
        }
    ],
    "sg:menulink":"http://www.allmenus.com/mi/grand-rapids/59130-heroes-bar--grill/menu/",
    "sg:phone":"+1 616 301 8326",
    "sg:postcode":"49546",
    "sg:province":"MI",
    "sg:tags":[
        "new",
        "american"
    ],
    "wof:name":"Heroes Bar & Grill",
    "wof:placetype":"venue"
},
  "geometry": {"coordinates":[-85.606964,42.927098],"type":"Point"}
}