{
  "type": "Feature",
  "properties": {
    "iso:country":"US",
    "sg:address":"714 Newton St",
    "sg:city":"Lansing",
    "sg:classifiers":[
        {
            "category":"Professional",
            "subcategory":"Management & Consulting",
            "type":"Services"
        }
    ],
    "sg:phone":"+1 517 316 7900",
    "sg:postcode":"48912",
    "sg:province":"MI",
    "wof:name":"Shaw Phone Bank Management",
    "wof:placetype":"venue"
},
  "geometry": {"coordinates":[-84.514177,42.743143],"type":"Point"}
}