{
  "type": "Feature",
  "properties": {
    "iso:country":"US",
    "sg:address":"526 Donald Ave",
    "sg:city":"Clawson",
    "sg:classifiers":[
        {
            "category":"Building & Trades",
            "subcategory":"Construction",
            "type":"Services"
        }
    ],
    "sg:phone":"+1 248 585 9170",
    "sg:postcode":"48017",
    "sg:province":"MI",
    "sg:tags":[
        "hanging",
        "contractor"
    ],
    "wof:name":"Marquis Painting",
    "wof:placetype":"venue"
},
  "geometry": {"coordinates":[-83.13882099999999,42.528898],"type":"Point"}
}