{
  "type": "Feature",
  "properties": {
    "iso:country":"US",
    "sg:address":"5444 Bay Park Rd",
    "sg:city":"Unionville",
    "sg:classifiers":[
        {
            "category":"Retail",
            "subcategory":"Laundry & Dry Cleaning",
            "type":"Services"
        }
    ],
    "sg:phone":"+1 989 674 2961",
    "sg:postcode":"48767",
    "sg:province":"MI",
    "sg:tags":[
        "cleaners",
        "rug",
        "carpet"
    ],
    "wof:name":"Servpro",
    "wof:placetype":"venue"
},
  "geometry": {"coordinates":[-83.55963300000001,43.653135],"type":"Point"}
}