{
  "type": "Feature",
  "properties": {
    "iso:country":"US",
    "sg:address":"43260 Garfield Rd",
    "sg:city":"Clinton Twp",
    "sg:classifiers":[
        {
            "category":"Professional",
            "subcategory":"Management & Consulting",
            "type":"Services"
        }
    ],
    "sg:phone":"+1 586 416 2740",
    "sg:postcode":"48038",
    "sg:province":"MI",
    "sg:tags":[
        "town",
        "city",
        "regional",
        "planner"
    ],
    "sg:website":"www.cpmpc.com",
    "wof:name":"Community Planning & Mgmt PC",
    "wof:placetype":"venue"
},
  "geometry": {"coordinates":[-82.952969,42.614894],"type":"Point"}
}