{
  "type": "Feature",
  "properties": {
    "iso:country":"US",
    "sg:address":"2311 N Woodbridge St",
    "sg:city":"Saginaw",
    "sg:classifiers":[
        {
            "category":"Mining & Drilling",
            "type":"Manufacturing & Wholesale Goods"
        }
    ],
    "sg:phone":"+1 989 793 9597",
    "sg:postcode":"48602",
    "sg:province":"MI",
    "sg:tags":[
        "stone"
    ],
    "wof:name":"H A Cederberg Jr & Co",
    "wof:placetype":"venue"
},
  "geometry": {"coordinates":[-83.96189099999999,43.440483],"type":"Point"}
}