{
  "type": "Feature",
  "properties": {
    "iso:country":"US",
    "sg:address":"21555 Haggerty Rd",
    "sg:city":"Novi",
    "sg:classifiers":[
        {
            "category":"Travel",
            "subcategory":"Hotels & Motels",
            "type":"Entertainment"
        },
        {
            "category":"Real Estate",
            "subcategory":"Real Estate Operator",
            "type":"Services"
        }
    ],
    "sg:phone":"+1 248 305 9955",
    "sg:postcode":"48375",
    "sg:province":"MI",
    "sg:tags":[
        "apartment"
    ],
    "sg:website":"www.extendedstayamerica.com",
    "wof:name":"Extended Stayamerica",
    "wof:placetype":"venue"
},
  "geometry": {"coordinates":[-83.434196,42.4473],"type":"Point"}
}