{
  "type": "Feature",
  "properties": {
    "iso:country":"US",
    "sg:address":"1601 N Main St",
    "sg:city":"Martin",
    "sg:classifiers":[
        {
            "category":"Banks & Credit Unions",
            "subcategory":"Bank",
            "type":"Services"
        }
    ],
    "sg:phone":"+1 269 672 5551",
    "sg:postcode":"49070",
    "sg:province":"MI",
    "sg:tags":[
        "national"
    ],
    "wof:name":"National City Bank",
    "wof:placetype":"venue"
},
  "geometry": {"coordinates":[-85.641706,42.538011],"type":"Point"}
}