{
  "type": "Feature",
  "properties": {
    "iso:country":"US",
    "sg:address":"722 Abbott Rd",
    "sg:city":"East Lansing",
    "sg:classifiers":[
        {
            "category":"Professional",
            "subcategory":"Management & Consulting",
            "type":"Services"
        }
    ],
    "sg:phone":"+1 517 351 6102",
    "sg:postcode":"48823",
    "sg:province":"MI",
    "wof:name":"Analytic Consulting Inc",
    "wof:placetype":"venue"
},
  "geometry": {"coordinates":[-84.483665,42.742312],"type":"Point"}
}