{
  "type": "Feature",
  "properties": {
    "iso:country":"US",
    "sg:address":"12441 Anson Pt",
    "sg:city":"Plainwell",
    "sg:classifiers":[
        {
            "category":"Organizations",
            "subcategory":"Community Association",
            "type":"Services"
        }
    ],
    "sg:phone":"+1 269 664 5595",
    "sg:postcode":"49080",
    "sg:province":"MI",
    "sg:tags":[
        "club"
    ],
    "wof:name":"Western Michigan Mopar Club",
    "wof:placetype":"venue"
},
  "geometry": {"coordinates":[-85.536478,42.502537],"type":"Point"}
}