{
  "type": "Feature",
  "properties": {
    "iso:country":"US",
    "sg:address":"1904 S Niagara St",
    "sg:city":"Saginaw",
    "sg:classifiers":[
        {
            "category":"Building & Trades",
            "subcategory":"Landscaping Services",
            "type":"Services"
        }
    ],
    "sg:phone":"+1 989 790 3401",
    "sg:postcode":"48602",
    "sg:province":"MI",
    "sg:tags":[
        "lawn",
        "maintenance",
        "grounds"
    ],
    "wof:name":"A-Tom's Landscaping",
    "wof:placetype":"venue"
},
  "geometry": {"coordinates":[-83.976995,43.404745],"type":"Point"}
}