{
  "type": "Feature",
  "properties": {
    "iso:country":"US",
    "sg:address":"1707 Sheridan Ave",
    "sg:city":"Saginaw",
    "sg:classifiers":[
        {
            "category":"Professional",
            "subcategory":"Computer Services",
            "type":"Services"
        }
    ],
    "sg:phone":"+1 989 754 3601",
    "sg:postcode":"48601",
    "sg:province":"MI",
    "sg:tags":[
        "processing",
        "word",
        "system"
    ],
    "wof:name":"Joe Danin Co",
    "wof:placetype":"venue"
},
  "geometry": {"coordinates":[-83.93601,43.412826],"type":"Point"}
}