{
  "type": "Feature",
  "properties": {
    "iso:country":"US",
    "sg:address":"3143 Prairie St",
    "sg:city":"Ida",
    "sg:classifiers":[
        {
            "category":"Education",
            "subcategory":"School",
            "type":"Public Place"
        }
    ],
    "sg:phone":"+1 734 269 2220",
    "sg:postcode":"48140",
    "sg:province":"MI",
    "sg:tags":[
        "middle"
    ],
    "wof:name":"Ida Middle School",
    "wof:placetype":"venue"
},
  "geometry": {"coordinates":[-83.570497,41.906432],"type":"Point"}
}