{
  "type": "Feature",
  "properties": {
    "iso:country":"US",
    "sg:address":"5157 N Eight Mile Rd",
    "sg:city":"Pinconning",
    "sg:classifiers":[
        {
            "category":"Manufacturing",
            "subcategory":"Printing",
            "type":"Manufacturing & Wholesale Goods"
        }
    ],
    "sg:phone":"+1 989 879 4324",
    "sg:postcode":"48650",
    "sg:province":"MI",
    "sg:tags":[
        "book"
    ],
    "wof:name":"Sunshine Publisher",
    "wof:placetype":"venue"
},
  "geometry": {"coordinates":[-84.045107,43.884236],"type":"Point"}
}