{
  "type": "Feature",
  "properties": {
    "iso:country":"US",
    "sg:address":"105 State St",
    "sg:city":"Twining",
    "sg:classifiers":[
        {
            "category":"Food & Beverages",
            "subcategory":"Groceries & Convenience Stores",
            "type":"Retail Goods"
        }
    ],
    "sg:phone":"+1 989 867 4211",
    "sg:postcode":"48766",
    "sg:province":"MI",
    "sg:tags":[
        "grocer"
    ],
    "wof:name":"Twining Food Market",
    "wof:placetype":"venue"
},
  "geometry": {"coordinates":[-83.80718899999999,44.115202],"type":"Point"}
}