{
  "type": "Feature",
  "properties": {
    "iso:country":"US",
    "sg:address":"12353 Camden Ave",
    "sg:city":"Detroit",
    "sg:classifiers":[
        {
            "category":"Professional",
            "subcategory":"Business Services",
            "type":"Services"
        }
    ],
    "sg:phone":"+1 313 839 7414",
    "sg:postcode":"48213",
    "sg:province":"MI",
    "sg:tags":[
        "coffee"
    ],
    "wof:name":"J TS Coffee Service Inc",
    "wof:placetype":"venue"
},
  "geometry": {"coordinates":[-82.98146,42.401726],"type":"Point"}
}