{
  "type": "Feature",
  "properties": {
    "iso:country":"US",
    "sg:address":"4107 Yorkshire Rd",
    "sg:city":"Detroit",
    "sg:classifiers":[
        {
            "category":"Building & Trades",
            "subcategory":"Construction",
            "type":"Services"
        }
    ],
    "sg:phone":"+1 313 343 6630",
    "sg:postcode":"48224",
    "sg:province":"MI",
    "sg:tags":[
        "nonresidential"
    ],
    "wof:name":"Brink Constructon Inc",
    "wof:placetype":"venue"
},
  "geometry": {"coordinates":[-82.93098500000001,42.399597],"type":"Point"}
}