{
  "type": "Feature",
  "properties": {
    "iso:country":"US",
    "sg:address":"22940 W Main St",
    "sg:city":"Armada",
    "sg:classifiers":[
        {
            "category":"Personal",
            "subcategory":"Beauty Salon",
            "type":"Services"
        }
    ],
    "sg:phone":"+1 586 784 8797",
    "sg:postcode":"48005",
    "sg:province":"MI",
    "sg:tags":[
        "shop"
    ],
    "wof:name":"Expressions Hair Design Inc",
    "wof:placetype":"venue"
},
  "geometry": {"coordinates":[-82.89242299999999,42.842843],"type":"Point"}
}