{
  "type": "Feature",
  "properties": {
    "iso:country":"US",
    "sg:address":"12250 N Saginaw Rd",
    "sg:city":"Clio",
    "sg:classifiers":[
        {
            "category":"Retail",
            "subcategory":"Repair Shop",
            "type":"Services"
        }
    ],
    "sg:phone":"+1 810 687 1320",
    "sg:postcode":"48420",
    "sg:province":"MI",
    "sg:tags":[
        "equipment",
        "scale",
        "commercial"
    ],
    "wof:name":"Kanawha Scales Systems Mich",
    "wof:placetype":"venue"
},
  "geometry": {"coordinates":[-83.718287,43.182742],"type":"Point"}
}