{
  "type": "Feature",
  "properties": {
    "iso:country":"US",
    "sg:address":"701 W Cedar Ave",
    "sg:city":"Gladwin",
    "sg:classifiers":[
        {
            "category":"Restaurant",
            "type":"Food & Drink"
        }
    ],
    "sg:phone":"+1 989 246 1041",
    "sg:postcode":"48624",
    "sg:province":"MI",
    "wof:name":"Burger King",
    "wof:placetype":"venue"
},
  "geometry": {"coordinates":[-84.49552799999999,43.980778],"type":"Point"}
}