{
  "type": "Feature",
  "properties": {
    "iso:country":"US",
    "sg:address":"2750 Main St",
    "sg:city":"Marlette",
    "sg:classifiers":[
        {
            "category":"Health Services",
            "subcategory":"Doctor",
            "type":"Services"
        }
    ],
    "sg:phone":"+1 989 635 3295",
    "sg:postcode":"48453",
    "sg:province":"MI",
    "sg:tags":[
        "medical"
    ],
    "wof:name":"Marlette Health Care Office",
    "wof:placetype":"venue"
},
  "geometry": {"coordinates":[-83.08099300000001,43.334181],"type":"Point"}
}