{
  "type": "Feature",
  "properties": {
    "iso:country":"US",
    "sg:address":"2529 E Mount Hope Ave",
    "sg:city":"Lansing",
    "sg:classifiers":[
        {
            "category":"Shopping",
            "type":"Retail Goods"
        }
    ],
    "sg:phone":"+1 517 482 6266",
    "sg:postcode":"48910",
    "sg:province":"MI",
    "sg:tags":[
        "monument"
    ],
    "wof:name":"Mount Hope Monument Co",
    "wof:placetype":"venue"
},
  "geometry": {"coordinates":[-84.519418,42.711967],"type":"Point"}
}