{
  "type": "Feature",
  "properties": {
    "iso:country":"US",
    "sg:address":"1422 S 25th St",
    "sg:city":"Saginaw",
    "sg:classifiers":[
        {
            "category":"Manufacturing",
            "subcategory":"Tools & Machinery",
            "type":"Manufacturing & Wholesale Goods"
        }
    ],
    "sg:phone":"+1 989 754 7496",
    "sg:postcode":"48601",
    "sg:province":"MI",
    "sg:tags":[
        "cutting"
    ],
    "sg:website":"www.johnsoncarbide.com",
    "wof:name":"Johnson Carbide Products Inc",
    "wof:placetype":"venue"
},
  "geometry": {"coordinates":[-83.90440700000001,43.413003],"type":"Point"}
}