{
  "type": "Feature",
  "properties": {
    "iso:country":"US",
    "sg:address":"801 Broadway Ave NW",
    "sg:city":"Grand Rapids",
    "sg:classifiers":[
        {
            "category":"Communications",
            "subcategory":"Film & Video Production",
            "type":"Services"
        }
    ],
    "sg:phone":"+1 616 451 2700",
    "sg:postcode":"49504",
    "sg:province":"MI",
    "sg:tags":[
        "taping"
    ],
    "wof:name":"A Storytelling Pictures",
    "wof:placetype":"venue"
},
  "geometry": {"coordinates":[-85.67939200000001,42.978432],"type":"Point"}
}