{
  "type": "Feature",
  "properties": {
    "iso:country":"US",
    "sg:address":"915 W State St",
    "sg:city":"St Johns",
    "sg:classifiers":[
        {
            "category":"Organizations",
            "subcategory":"Professional Association",
            "type":"Services"
        }
    ],
    "sg:phone":"+1 989 224 2755",
    "sg:postcode":"48879",
    "sg:province":"MI",
    "wof:name":"Masonic Lodge",
    "wof:placetype":"venue"
},
  "geometry": {"coordinates":[-84.56976400000001,43.001477],"type":"Point"}
}