{
  "type": "Feature",
  "properties": {
    "iso:country":"US",
    "sg:address":"24443 Gratiot Ave",
    "sg:city":"Eastpointe",
    "sg:classifiers":[
        {
            "category":"Restaurant",
            "type":"Food & Drink"
        }
    ],
    "sg:phone":"+1 586 777 5391",
    "sg:postcode":"48021",
    "sg:province":"MI",
    "wof:name":"Cloverleaf Bar & Restaurant",
    "wof:placetype":"venue"
},
  "geometry": {"coordinates":[-82.952135,42.474088],"type":"Point"}
}