{
  "type": "Feature",
  "properties": {
    "iso:country":"US",
    "sg:address":"9775 E Cherry Bend Rd",
    "sg:city":"Traverse City",
    "sg:classifiers":[
        {
            "category":"Building & Trades",
            "subcategory":"Construction",
            "type":"Services"
        }
    ],
    "sg:phone":"+1 231 941 7588",
    "sg:postcode":"49684",
    "sg:province":"MI",
    "sg:tags":[
        "residential"
    ],
    "wof:name":"Meeuwenberg Eugene Lee Cnstr",
    "wof:placetype":"venue"
},
  "geometry": {"coordinates":[-85.65998999999999,44.814252],"type":"Point"}
}