{
  "type": "Feature",
  "properties": {
    "iso:country":"US",
    "sg:address":"129 E Main St",
    "sg:city":"Midland",
    "sg:classifiers":[
        {
            "category":"Shopping",
            "subcategory":"Clothing, Apparel, & Fashions",
            "type":"Retail Goods"
        }
    ],
    "sg:phone":"+1 989 832 8651",
    "sg:postcode":"48640",
    "sg:province":"MI",
    "sg:tags":[
        "furnishing"
    ],
    "wof:name":"Baringer's Men Shop",
    "wof:placetype":"venue"
},
  "geometry": {"coordinates":[-84.245329,43.613079],"type":"Point"}
}