{
  "type": "Feature",
  "properties": {
    "iso:country":"US",
    "sg:address":"615 Trombley Dr",
    "sg:city":"Troy",
    "sg:classifiers":[
        {
            "category":"Building & Trades",
            "subcategory":"Construction",
            "type":"Services"
        }
    ],
    "sg:phone":"+1 248 524 4910",
    "sg:postcode":"48083",
    "sg:province":"MI",
    "sg:tags":[
        "contractor"
    ],
    "wof:name":"R G R Corporatioon",
    "wof:placetype":"venue"
},
  "geometry": {"coordinates":[-83.137683,42.569938],"type":"Point"}
}