{
  "type": "Feature",
  "properties": {
    "iso:country":"US",
    "sg:address":"4330 1 Mile Rd",
    "sg:city":"White Cloud",
    "sg:classifiers":[
        {
            "category":"Building & Trades",
            "subcategory":"Construction",
            "type":"Services"
        }
    ],
    "sg:phone":"+1 231 924 2246",
    "sg:postcode":"49349",
    "sg:province":"MI",
    "sg:tags":[
        "contractor"
    ],
    "wof:name":"Smalligan Builders",
    "wof:placetype":"venue"
},
  "geometry": {"coordinates":[-85.810452,43.249714],"type":"Point"}
}