{
  "type": "Feature",
  "properties": {
    "iso:country":"US",
    "sg:address":"4430 Quarton Rd",
    "sg:city":"Bloomfield Hills",
    "sg:classifiers":[
        {
            "category":"Health Services",
            "subcategory":"Doctor",
            "type":"Services"
        }
    ],
    "sg:phone":"+1 248 851 2515",
    "sg:postcode":"48302",
    "sg:province":"MI",
    "sg:tags":[
        "medical"
    ],
    "wof:name":"Subrin Mayer",
    "wof:placetype":"venue"
},
  "geometry": {"coordinates":[-83.29804300000001,42.558627],"type":"Point"}
}