{
  "type": "Feature",
  "properties": {
    "iso:country":"US",
    "sg:address":"6650 S Westnedge Ave",
    "sg:city":"Portage",
    "sg:classifiers":[
        {
            "category":"Shopping",
            "subcategory":"Gifts & Souvenirs",
            "type":"Retail Goods"
        }
    ],
    "sg:phone":"+1 269 324 9027",
    "sg:postcode":"49024",
    "sg:province":"MI",
    "sg:tags":[
        "shop"
    ],
    "wof:name":"Spencer Gifts",
    "wof:placetype":"venue"
},
  "geometry": {"coordinates":[-85.589541,42.222355],"type":"Point"}
}