{
  "type": "Feature",
  "properties": {
    "iso:country":"US",
    "sg:address":"42 Garrison Ave",
    "sg:city":"Battle Creek",
    "sg:classifiers":[
        {
            "category":"Building & Trades",
            "subcategory":"Construction",
            "type":"Services"
        }
    ],
    "sg:phone":"+1 269 969 0757",
    "sg:postcode":"49017",
    "sg:province":"MI",
    "sg:tags":[
        "house"
    ],
    "wof:name":"K&M Remodeling",
    "wof:placetype":"venue"
},
  "geometry": {"coordinates":[-85.16876000000001,42.325128],"type":"Point"}
}