{
  "type": "Feature",
  "properties": {
    "iso:country":"US",
    "sg:address":"2801 Trumbull St",
    "sg:city":"Detroit",
    "sg:classifiers":[
        {
            "category":"Organizations",
            "subcategory":"Labor Organization",
            "type":"Services"
        }
    ],
    "sg:phone":"+1 313 965 9833",
    "sg:postcode":"48216",
    "sg:province":"MI",
    "wof:name":"Local 337",
    "wof:placetype":"venue"
},
  "geometry": {"coordinates":[-83.070622,42.337924],"type":"Point"}
}