{
  "type": "Feature",
  "properties": {
    "iso:country":"US",
    "sg:address":"668 S Harvest Ln",
    "sg:city":"Muskegon",
    "sg:classifiers":[
        {
            "category":"Building & Trades",
            "subcategory":"Construction",
            "type":"Services"
        }
    ],
    "sg:phone":"+1 231 788 2141",
    "sg:postcode":"49442",
    "sg:province":"MI",
    "sg:tags":[
        "masonry",
        "contractor"
    ],
    "wof:name":"Kingdom Masonry Inc",
    "wof:placetype":"venue"
},
  "geometry": {"coordinates":[-86.12255999999999,43.242194],"type":"Point"}
}