{
  "type": "Feature",
  "properties": {
    "iso:country":"US",
    "sg:address":"705 US Hwy 27 Bus",
    "sg:city":"St Johns",
    "sg:classifiers":[
        {
            "category":"Autos & Motor Vehicles",
            "subcategory":"Automobile Sales",
            "type":"Retail Goods"
        }
    ],
    "sg:phone":"+1 989 224 1857",
    "sg:postcode":"48879",
    "sg:province":"MI",
    "sg:tags":[
        "car",
        "dealer"
    ],
    "wof:name":"Morgan Used Cars",
    "wof:placetype":"venue"
},
  "geometry": {"coordinates":[-84.55119000000001,43.007622],"type":"Point"}
}