{
  "type": "Feature",
  "properties": {
    "iso:country":"US",
    "sg:address":"1501 Court St",
    "sg:city":"Port Huron",
    "sg:classifiers":[
        {
            "category":"Organizations",
            "subcategory":"Religious Organization",
            "type":"Services"
        }
    ],
    "sg:phone":"+1 810 982 8811",
    "sg:postcode":"48060",
    "sg:province":"MI",
    "wof:name":"Court Street Baptist Church",
    "wof:placetype":"venue"
},
  "geometry": {"coordinates":[-82.44119499999999,42.971295],"type":"Point"}
}