{
  "type": "Feature",
  "properties": {
    "iso:country":"US",
    "sg:address":"3650 Dixie Hwy",
    "sg:city":"Waterford",
    "sg:classifiers":[
        {
            "category":"Government",
            "subcategory":"Office",
            "type":"Public Place"
        }
    ],
    "sg:phone":"+1 248 673 6910",
    "sg:postcode":"48329",
    "sg:province":"MI",
    "sg:tags":[
        "state",
        "program"
    ],
    "wof:name":"Transportation Dept Constr",
    "wof:placetype":"venue"
},
  "geometry": {"coordinates":[-83.371342,42.679743],"type":"Point"}
}