{
  "type": "Feature",
  "properties": {
    "iso:country":"US",
    "sg:address":"224 Riverside Rd",
    "sg:city":"Marquette",
    "sg:classifiers":[
        {
            "category":"Manufacturing",
            "subcategory":"Printing",
            "type":"Manufacturing & Wholesale Goods"
        }
    ],
    "sg:phone":"+1 906 249 9248",
    "sg:postcode":"49855",
    "sg:province":"MI",
    "sg:tags":[
        "book"
    ],
    "wof:name":"Winter Cabin Books & Services",
    "wof:placetype":"venue"
},
  "geometry": {"coordinates":[-87.337839,46.493096],"type":"Point"}
}