{
  "type": "Feature",
  "properties": {
    "iso:country":"US",
    "sg:address":"2611 Arrowwood Trl",
    "sg:city":"Ann Arbor",
    "sg:classifiers":[
        {
            "category":"Social Services",
            "subcategory":"Child Care",
            "type":"Services"
        }
    ],
    "sg:phone":"+1 734 663 2431",
    "sg:postcode":"48105",
    "sg:province":"MI",
    "sg:tags":[
        "day"
    ],
    "wof:name":"Nimer Wafa",
    "wof:placetype":"venue"
},
  "geometry": {"coordinates":[-83.731613,42.308981],"type":"Point"}
}