{
  "type": "Feature",
  "properties": {
    "iso:country":"US",
    "sg:address":"8536 Shaver Rd",
    "sg:city":"Portage",
    "sg:classifiers":[
        {
            "category":"Shopping",
            "subcategory":"Bicycles & Sporting Goods",
            "type":"Retail Goods"
        }
    ],
    "sg:phone":"+1 269 321 6676",
    "sg:postcode":"49024",
    "sg:province":"MI",
    "sg:tags":[
        "equipment",
        "golf",
        "supply"
    ],
    "wof:name":"Norm's Golf Ctr",
    "wof:placetype":"venue"
},
  "geometry": {"coordinates":[-85.59810400000001,42.192896],"type":"Point"}
}