{
  "type": "Feature",
  "properties": {
    "iso:country":"US",
    "sg:address":"3660 E Townline Lake Rd",
    "sg:city":"Harrison",
    "sg:classifiers":[
        {
            "category":"Building & Trades",
            "subcategory":"Construction",
            "type":"Services"
        }
    ],
    "sg:phone":"+1 989 539 9625",
    "sg:postcode":"48625",
    "sg:province":"MI",
    "sg:tags":[
        "house"
    ],
    "wof:name":"Sleight Construction Co",
    "wof:placetype":"venue"
},
  "geometry": {"coordinates":[-84.772755,44.031562],"type":"Point"}
}