{
  "type": "Feature",
  "properties": {
    "iso:country":"US",
    "sg:address":"3225 28th St SE",
    "sg:city":"Grand Rapids",
    "sg:classifiers":[
        {
            "category":"Shopping",
            "subcategory":"Department Store",
            "type":"Retail Goods"
        }
    ],
    "sg:phone":"+1 616 949 7600",
    "sg:postcode":"49512",
    "sg:province":"MI",
    "sg:website":"www.jcpenney.com",
    "wof:name":"J C Penney Co",
    "wof:placetype":"venue"
},
  "geometry": {"coordinates":[-85.586528,42.912573],"type":"Point"}
}