{
  "type": "Feature",
  "properties": {
    "iso:country":"US",
    "sg:address":"42180 Ford Rd",
    "sg:city":"Canton",
    "sg:classifiers":[
        {
            "category":"Professional",
            "subcategory":"Management & Consulting",
            "type":"Services"
        }
    ],
    "sg:phone":"+1 734 844 3400",
    "sg:postcode":"48187",
    "sg:province":"MI",
    "wof:name":"C Curtis & Associates Inc",
    "wof:placetype":"venue"
},
  "geometry": {"coordinates":[-83.45563300000001,42.322829],"type":"Point"}
}