{
  "type": "Feature",
  "properties": {
    "iso:country":"US",
    "sg:address":"22672 Elm Ct",
    "sg:city":"Hazel Park",
    "sg:classifiers":[
        {
            "category":"Organizations",
            "subcategory":"Community Association",
            "type":"Services"
        }
    ],
    "sg:phone":"+1 248 548 3916",
    "sg:postcode":"48030",
    "sg:province":"MI",
    "wof:name":"International Assoc Lions Club",
    "wof:placetype":"venue"
},
  "geometry": {"coordinates":[-83.087413,42.458798],"type":"Point"}
}