{
  "type": "Feature",
  "properties": {
    "iso:country":"US",
    "sg:address":"18077 Martinsville Rd",
    "sg:city":"Belleville",
    "sg:classifiers":[
        {
            "category":"Manufacturing",
            "subcategory":"Furniture",
            "type":"Manufacturing & Wholesale Goods"
        }
    ],
    "sg:phone":"+1 734 697 7436",
    "sg:postcode":"48111",
    "sg:province":"MI",
    "sg:tags":[
        "household",
        "wood",
        "mfg"
    ],
    "wof:name":"Woodcrafter",
    "wof:placetype":"venue"
},
  "geometry": {"coordinates":[-83.461645,42.17353],"type":"Point"}
}