{
  "type": "Feature",
  "properties": {
    "iso:country":"US",
    "sg:address":"941 Kirts Blvd",
    "sg:city":"Troy",
    "sg:classifiers":[
        {
            "category":"Professional",
            "subcategory":"Accounting & Tax Preparation",
            "type":"Services"
        }
    ],
    "sg:phone":"+1 248 269 9011",
    "sg:postcode":"48084",
    "sg:province":"MI",
    "sg:tags":[
        "billing"
    ],
    "wof:name":"Annie Harrison Med Billing Co",
    "wof:placetype":"venue"
},
  "geometry": {"coordinates":[-83.160438,42.556603],"type":"Point"}
}