{
  "type": "Feature",
  "properties": {
    "iso:country":"US",
    "sg:address":"10291 Grand River Rd",
    "sg:city":"Brighton",
    "sg:classifiers":[
        {
            "category":"Professional",
            "subcategory":"Employment Agencies",
            "type":"Services"
        }
    ],
    "sg:phone":"+1 810 227 7055",
    "sg:postcode":"48116",
    "sg:province":"MI",
    "sg:tags":[
        "opportunity"
    ],
    "sg:website":"www.hcrintl.com",
    "wof:name":"Healthcare Recruiters Intl",
    "wof:placetype":"venue"
},
  "geometry": {"coordinates":[-83.75236099999999,42.51952],"type":"Point"}
}