{
  "type": "Feature",
  "properties": {
    "iso:country":"US",
    "sg:address":"4510 Joy Rd",
    "sg:city":"Detroit",
    "sg:classifiers":[
        {
            "category":"Retail",
            "subcategory":"Laundry & Dry Cleaning",
            "type":"Services"
        }
    ],
    "sg:phone":"+1 313 931 1690",
    "sg:postcode":"48204",
    "sg:province":"MI",
    "sg:tags":[
        "drycleaning",
        "plant"
    ],
    "wof:name":"Grand Joy Cleaners Inc",
    "wof:placetype":"venue"
},
  "geometry": {"coordinates":[-83.125818,42.367148],"type":"Point"}
}