{
  "type": "Feature",
  "properties": {
    "iso:country":"US",
    "sg:address":"2170 Shore Rd",
    "sg:city":"Rogers City",
    "sg:classifiers":[
        {
            "category":"Health Services",
            "subcategory":"Doctor",
            "type":"Services"
        }
    ],
    "sg:phone":"+1 989 734 7161",
    "sg:postcode":"49779",
    "sg:province":"MI",
    "sg:tags":[
        "medical"
    ],
    "wof:name":"Chung M D Pc Youn Tai",
    "wof:placetype":"venue"
},
  "geometry": {"coordinates":[-83.84920200000001,45.439814],"type":"Point"}
}