{
  "type": "Feature",
  "properties": {
    "iso:country":"US",
    "sg:address":"2809 58th St",
    "sg:city":"Fennville",
    "sg:classifiers":[
        {
            "category":"Farming",
            "subcategory":"Farm",
            "type":"Manufacturing & Wholesale Goods"
        }
    ],
    "sg:phone":"+1 269 561 6871",
    "sg:postcode":"49408",
    "sg:province":"MI",
    "wof:name":"Gran Sport Farm",
    "wof:placetype":"venue"
},
  "geometry": {"coordinates":[-86.11448799999999,42.624969],"type":"Point"}
}