{
  "type": "Feature",
  "properties": {
    "iso:country":"US",
    "sg:address":"934 Clark St",
    "sg:city":"Lansing",
    "sg:classifiers":[
        {
            "category":"Professional",
            "subcategory":"Computer Services",
            "type":"Services"
        }
    ],
    "sg:phone":"+1 517 333 1760",
    "sg:postcode":"48906",
    "sg:province":"MI",
    "sg:tags":[
        "hardware",
        "provider",
        "internet",
        "software"
    ],
    "sg:website":"www.cowmattress.com",
    "wof:name":"ARQ Internet Solutions",
    "wof:placetype":"venue"
},
  "geometry": {"coordinates":[-84.531975,42.745973],"type":"Point"}
}