{
  "type": "Feature",
  "properties": {
    "iso:country":"US",
    "sg:address":"6348 Wall St",
    "sg:city":"Sterling Heights",
    "sg:classifiers":[
        {
            "category":"Professional",
            "subcategory":"Business Services",
            "type":"Services"
        }
    ],
    "sg:phone":"+1 586 826 8818",
    "sg:postcode":"48312",
    "sg:province":"MI",
    "wof:name":"Densteadt & Associates",
    "wof:placetype":"venue"
},
  "geometry": {"coordinates":[-83.04284,42.570555],"type":"Point"}
}