{
  "type": "Feature",
  "properties": {
    "iso:country":"US",
    "sg:address":"20411 W 12 Mile Rd",
    "sg:city":"Southfield",
    "sg:classifiers":[
        {
            "category":"Professional",
            "subcategory":"Lawyer & Legal Services",
            "type":"Services"
        }
    ],
    "sg:phone":"+1 248 352 7202",
    "sg:postcode":"48076",
    "sg:province":"MI",
    "wof:name":"Friedman Alvin J Atty",
    "wof:placetype":"venue"
},
  "geometry": {"coordinates":[-83.246498,42.501801],"type":"Point"}
}