{
  "type": "Feature",
  "properties": {
    "iso:country":"US",
    "sg:address":"623 W 29th St",
    "sg:city":"Holland",
    "sg:classifiers":[
        {
            "category":"Shopping",
            "type":"Retail Goods"
        }
    ],
    "sg:phone":"+1 616 392 3493",
    "sg:postcode":"49423",
    "sg:province":"MI",
    "sg:tags":[
        "merchandise"
    ],
    "wof:name":"Knitting Nest",
    "wof:placetype":"venue"
},
  "geometry": {"coordinates":[-86.13475200000001,42.771168],"type":"Point"}
}