{
  "type": "Feature",
  "properties": {
    "iso:country":"US",
    "sg:address":"1026 E Kearsley St",
    "sg:city":"Flint",
    "sg:classifiers":[
        {
            "category":"Education",
            "subcategory":"Library",
            "type":"Public Place"
        }
    ],
    "sg:phone":"+1 810 232 7111",
    "sg:postcode":"48503",
    "sg:province":"MI",
    "sg:website":"www.flint.lib.mi.us",
    "wof:name":"Flint Public Library",
    "wof:placetype":"venue"
},
  "geometry": {"coordinates":[-83.68000000000001,43.021999],"type":"Point"}
}