{
  "type": "Feature",
  "properties": {
    "iso:country":"US",
    "sg:address":"4300 Chicago Dr SW",
    "sg:city":"Grandville",
    "sg:classifiers":[
        {
            "category":"Shopping",
            "subcategory":"Bicycles & Sporting Goods",
            "type":"Retail Goods"
        }
    ],
    "sg:phone":"+1 616 531 9911",
    "sg:postcode":"49418",
    "sg:province":"MI",
    "sg:tags":[
        "equipment",
        "exercise"
    ],
    "wof:name":"Chicago Drive Schwinn Cycling",
    "wof:placetype":"venue"
},
  "geometry": {"coordinates":[-85.769976,42.907241],"type":"Point"}
}