{
  "type": "Feature",
  "properties": {
    "iso:country":"US",
    "sg:address":"12045 Littlefield St",
    "sg:city":"Detroit",
    "sg:classifiers":[
        {
            "category":"Farming",
            "subcategory":"Farm",
            "type":"Manufacturing & Wholesale Goods"
        }
    ],
    "sg:phone":"+1 313 931 4478",
    "sg:postcode":"48227",
    "sg:province":"MI",
    "wof:name":"Bradley Farms",
    "wof:placetype":"venue"
},
  "geometry": {"coordinates":[-83.17563199999999,42.375891],"type":"Point"}
}