{
  "type": "Feature",
  "properties": {
    "iso:country":"US",
    "sg:address":"3420 N Bard Rd",
    "sg:city":"Gladwin",
    "sg:classifiers":[
        {
            "category":"Manufacturing",
            "subcategory":"Lumber",
            "type":"Manufacturing & Wholesale Goods"
        }
    ],
    "sg:phone":"+1 989 426 3987",
    "sg:postcode":"48624",
    "sg:province":"MI",
    "sg:tags":[
        "logging"
    ],
    "wof:name":"McCoys Logging",
    "wof:placetype":"venue"
},
  "geometry": {"coordinates":[-84.586118,44.074649],"type":"Point"}
}