{
  "type": "Feature",
  "properties": {
    "iso:country":"US",
    "sg:address":"5187 W Houghton Lake Dr",
    "sg:city":"Houghton Lake",
    "sg:classifiers":[
        {
            "category":"Personal",
            "subcategory":"Beauty Salon",
            "type":"Services"
        }
    ],
    "sg:phone":"+1 989 366 1919",
    "sg:postcode":"48629",
    "sg:province":"MI",
    "sg:tags":[
        "shop"
    ],
    "wof:name":"Shearmadness Hair Designers",
    "wof:placetype":"venue"
},
  "geometry": {"coordinates":[-84.743565,44.300419],"type":"Point"}
}