{
  "type": "Feature",
  "properties": {
    "iso:country":"US",
    "sg:address":"2755 Whitefeather Rd",
    "sg:city":"Bentley",
    "sg:classifiers":[
        {
            "category":"Freight",
            "type":"Transportation"
        }
    ],
    "sg:phone":"+1 989 879 3773",
    "sg:postcode":"48652",
    "sg:province":"MI",
    "sg:tags":[
        "operator",
        "trucking"
    ],
    "wof:name":"M & M Trucking",
    "wof:placetype":"venue"
},
  "geometry": {"coordinates":[-84.144317,43.897926],"type":"Point"}
}