{
  "type": "Feature",
  "properties": {
    "iso:country":"US",
    "sg:address":"2000 N Telegraph Rd",
    "sg:city":"Dearborn",
    "sg:classifiers":[
        {
            "category":"Building & Trades",
            "subcategory":"Construction",
            "type":"Services"
        }
    ],
    "sg:phone":"+1 888 355 6700",
    "sg:postcode":"48128",
    "sg:province":"MI",
    "sg:tags":[
        "roofing"
    ],
    "sg:website":"www.kearnsbrothers.com",
    "wof:name":"Kearns Brothers Inc",
    "wof:placetype":"venue"
},
  "geometry": {"coordinates":[-83.272212,42.325381],"type":"Point"}
}