{
  "type": "Feature",
  "properties": {
    "iso:country":"US",
    "sg:address":"4880 Highland Rd",
    "sg:city":"Waterford",
    "sg:classifiers":[
        {
            "category":"Restaurant",
            "type":"Food & Drink"
        }
    ],
    "sg:phone":"+1 248 674 4666",
    "sg:postcode":"48328",
    "sg:province":"MI",
    "sg:tags":[
        "pizza"
    ],
    "wof:name":"Ken's Pizza & Submarine",
    "wof:placetype":"venue"
},
  "geometry": {"coordinates":[-83.38580399999999,42.660052],"type":"Point"}
}