{
  "type": "Feature",
  "properties": {
    "iso:country":"US",
    "sg:address":"7525 Cedar Run Rd",
    "sg:city":"Traverse City",
    "sg:classifiers":[
        {
            "category":"Sports & Exercise",
            "subcategory":"Golf",
            "type":"Entertainment"
        }
    ],
    "sg:phone":"+1 231 947 8237",
    "sg:postcode":"49684",
    "sg:province":"MI",
    "sg:tags":[
        "course",
        "public"
    ],
    "wof:name":"Cedar Hills Golf Course",
    "wof:placetype":"venue"
},
  "geometry": {"coordinates":[-85.722286,44.758416],"type":"Point"}
}