{
  "type": "Feature",
  "properties": {
    "iso:country":"US",
    "sg:address":"1506 N Maple Rd",
    "sg:city":"Ann Arbor",
    "sg:classifiers":[
        {
            "category":"Restaurant",
            "type":"Food & Drink"
        }
    ],
    "sg:menulink":"http://www.allmenus.com/mi/ann-arbor/246956-wengs-kitchen/menu/",
    "sg:phone":"+1 734 669 8889",
    "sg:postcode":"48103",
    "sg:province":"MI",
    "sg:tags":[
        "asian",
        "chinese"
    ],
    "wof:name":"Weng's Kitchen",
    "wof:placetype":"venue"
},
  "geometry": {"coordinates":[-83.780964,42.296115],"type":"Point"}
}