{
  "type": "Feature",
  "properties": {
    "iso:country":"US",
    "sg:address":"39393 Van Dyke Ave Ste 208",
    "sg:city":"Sterling Heights",
    "sg:classifiers":[
        {
            "category":"Professional",
            "subcategory":"Accounting & Tax Preparation",
            "type":"Services"
        }
    ],
    "sg:phone":"+1 586 978 1440",
    "sg:postcode":"48313",
    "sg:province":"MI",
    "sg:tags":[
        "accountant"
    ],
    "wof:name":"McClellan Edward B CPA PC",
    "wof:placetype":"venue"
},
  "geometry": {"coordinates":[-83.030602,42.582401],"type":"Point"}
}