{
  "type": "Feature",
  "properties": {
    "iso:country":"US",
    "sg:address":"1683 Woodbine Dr",
    "sg:city":"Lapeer",
    "sg:classifiers":[
        {
            "category":"Professional",
            "type":"Services"
        }
    ],
    "sg:phone":"+1 810 245 2220",
    "sg:postcode":"48446",
    "sg:province":"MI",
    "wof:name":"Artillery",
    "wof:placetype":"venue"
},
  "geometry": {"coordinates":[-83.294493,43.078283],"type":"Point"}
}