{
  "type": "Feature",
  "properties": {
    "iso:country":"US",
    "sg:address":"300 S State St",
    "sg:city":"Zeeland",
    "sg:classifiers":[
        {
            "category":"Health Services",
            "subcategory":"Doctor",
            "type":"Services"
        }
    ],
    "sg:phone":"+1 616 772 6243",
    "sg:postcode":"49464",
    "sg:province":"MI",
    "sg:tags":[
        "dentist"
    ],
    "wof:name":"Patrick M Sweeney DDS",
    "wof:placetype":"venue"
},
  "geometry": {"coordinates":[-86.018922,42.80644],"type":"Point"}
}