{
  "type": "Feature",
  "properties": {
    "iso:country":"US",
    "sg:address":"5425 W Jefferson Ave",
    "sg:city":"Detroit",
    "sg:classifiers":[
        {
            "category":"Utilities",
            "subcategory":"Electric",
            "type":"Services"
        }
    ],
    "sg:phone":"+1 313 267 4113",
    "sg:postcode":"48209",
    "sg:province":"MI",
    "wof:name":"Public Lighting Dept",
    "wof:placetype":"venue"
},
  "geometry": {"coordinates":[-83.091573,42.30379],"type":"Point"}
}