{
  "type": "Feature",
  "properties": {
    "iso:country":"US",
    "sg:address":"289 Lucas Dr",
    "sg:city":"Detroit",
    "sg:classifiers":[
        {
            "category":"Professional",
            "subcategory":"Management & Consulting",
            "type":"Services"
        }
    ],
    "sg:phone":"+1 734 941 7920",
    "sg:postcode":"48242",
    "sg:province":"MI",
    "sg:tags":[
        "passenger",
        "local",
        "transportation"
    ],
    "wof:name":"Hertz",
    "wof:placetype":"venue"
},
  "geometry": {"coordinates":[-83.334436,42.235797],"type":"Point"}
}