{
  "type": "Feature",
  "properties": {
    "iso:country":"US",
    "sg:address":"20003 Joy Rd",
    "sg:city":"Detroit",
    "sg:classifiers":[
        {
            "category":"Restaurant",
            "type":"Food & Drink"
        }
    ],
    "sg:phone":"+1 313 581 3136",
    "sg:postcode":"48228",
    "sg:province":"MI",
    "wof:name":"L George's Coney Island",
    "wof:placetype":"venue"
},
  "geometry": {"coordinates":[-83.236397,42.357498],"type":"Point"}
}