{
  "type": "Feature",
  "properties": {
    "iso:country":"US",
    "sg:address":"70509 Hilltop Dr",
    "sg:city":"Union",
    "sg:classifiers":[
        {
            "category":"Professional",
            "subcategory":"Business Services",
            "type":"Services"
        }
    ],
    "sg:phone":"+1 269 641 7907",
    "sg:postcode":"49130",
    "sg:province":"MI",
    "wof:name":"Mlp Limited Partnership",
    "wof:placetype":"venue"
},
  "geometry": {"coordinates":[-85.833248,41.774811],"type":"Point"}
}