{
  "type": "Feature",
  "properties": {
    "iso:country":"US",
    "sg:address":"101 E Superior St",
    "sg:city":"Alma",
    "sg:classifiers":[
        {
            "category":"Shopping",
            "subcategory":"Clothing, Apparel, & Fashions",
            "type":"Retail Goods"
        }
    ],
    "sg:phone":"+1 989 463 3330",
    "sg:postcode":"48801",
    "sg:province":"MI",
    "wof:name":"Hay Stack",
    "wof:placetype":"venue"
},
  "geometry": {"coordinates":[-84.661846,43.378982],"type":"Point"}
}