{
  "type": "Feature",
  "properties": {
    "iso:country":"US",
    "sg:address":"209 E Apple Ave",
    "sg:city":"Muskegon",
    "sg:classifiers":[
        {
            "category":"Organizations",
            "subcategory":"Non-profit Organization",
            "type":"Services"
        }
    ],
    "sg:phone":"+1 231 724 6350",
    "sg:postcode":"49442",
    "sg:province":"MI",
    "sg:website":"www.muskegonhealth.net",
    "wof:name":"Health Education & Substance",
    "wof:placetype":"venue"
},
  "geometry": {"coordinates":[-86.23813199999999,43.234251],"type":"Point"}
}