{
  "type": "Feature",
  "properties": {
    "iso:country":"US",
    "sg:address":"308 S Main St",
    "sg:city":"Plainwell",
    "sg:classifiers":[
        {
            "category":"Building & Trades",
            "subcategory":"Construction",
            "type":"Services"
        }
    ],
    "sg:phone":"+1 269 685 9661",
    "sg:postcode":"49080",
    "sg:province":"MI",
    "sg:tags":[
        "hanging",
        "contractor"
    ],
    "wof:name":"Saeger Wallpapering",
    "wof:placetype":"venue"
},
  "geometry": {"coordinates":[-85.641899,42.440873],"type":"Point"}
}