{
  "type": "Feature",
  "properties": {
    "iso:country":"US",
    "sg:address":"2241 Siboney Ct",
    "sg:city":"Rochester",
    "sg:classifiers":[
        {
            "category":"Home & Garden",
            "subcategory":"Furniture",
            "type":"Retail Goods"
        }
    ],
    "sg:phone":"+1 248 650 2143",
    "sg:postcode":"48309",
    "sg:province":"MI",
    "sg:tags":[
        "interior",
        "designer"
    ],
    "wof:name":"Creative Concepts By Connie",
    "wof:placetype":"venue"
},
  "geometry": {"coordinates":[-83.161936,42.647473],"type":"Point"}
}