{
  "type": "Feature",
  "properties": {
    "iso:country":"US",
    "sg:address":"46660 Van Dyke Ave",
    "sg:city":"Shelby Twp",
    "sg:classifiers":[
        {
            "category":"Shopping",
            "subcategory":"Hobbies, Toys, & Games",
            "type":"Retail Goods"
        }
    ],
    "sg:phone":"+1 586 323 1300",
    "sg:postcode":"48317",
    "sg:province":"MI",
    "sg:tags":[
        "model",
        "supply"
    ],
    "sg:website":"www.greatlakeshobby.com",
    "wof:name":"Great Lakes Hobby & Train",
    "wof:placetype":"venue"
},
  "geometry": {"coordinates":[-83.03279000000001,42.638154],"type":"Point"}
}