{
  "type": "Feature",
  "properties": {
    "iso:country":"US",
    "sg:address":"4585 S Luce Ave",
    "sg:city":"Fremont",
    "sg:classifiers":[
        {
            "category":"Professional",
            "subcategory":"Computer Services",
            "type":"Services"
        }
    ],
    "sg:phone":"+1 231 924 6494",
    "sg:postcode":"49412",
    "sg:province":"MI",
    "wof:name":"S Webb Computer Repair",
    "wof:placetype":"venue"
},
  "geometry": {"coordinates":[-85.92012200000001,43.47126],"type":"Point"}
}