{
  "type": "Feature",
  "properties": {
    "iso:country":"US",
    "sg:address":"307 S Washington Sq",
    "sg:city":"Lansing",
    "sg:classifiers":[
        {
            "category":"Restaurant",
            "type":"Food & Drink"
        }
    ],
    "sg:menulink":"http://www.allmenus.com/mi/lansing/251419-jalapenos/menu/",
    "sg:phone":"+1 517 482 2326",
    "sg:postcode":"48933",
    "sg:province":"MI",
    "sg:tags":[
        "mexican"
    ],
    "wof:name":"Jalapenos",
    "wof:placetype":"venue"
},
  "geometry": {"coordinates":[-84.552272,42.731247],"type":"Point"}
}