{
  "type": "Feature",
  "properties": {
    "iso:country":"US",
    "sg:address":"31007 Groesbeck Hwy",
    "sg:city":"Fraser",
    "sg:classifiers":[
        {
            "category":"Food & Beverages",
            "subcategory":"Groceries & Convenience Stores",
            "type":"Retail Goods"
        }
    ],
    "sg:phone":"+1 586 415 0070",
    "sg:postcode":"48026",
    "sg:province":"MI",
    "wof:name":"Sunshine Foods",
    "wof:placetype":"venue"
},
  "geometry": {"coordinates":[-82.946404,42.524502],"type":"Point"}
}