{
  "type": "Feature",
  "properties": {
    "iso:country":"US",
    "sg:address":"309 S Hanselman St",
    "sg:city":"Bad Axe",
    "sg:classifiers":[
        {
            "category":"Wholesale",
            "subcategory":"Hardware",
            "type":"Manufacturing & Wholesale Goods"
        }
    ],
    "sg:phone":"+1 989 269 7291",
    "sg:postcode":"48413",
    "sg:province":"MI",
    "sg:tags":[
        "refrigerating"
    ],
    "sg:website":"www.rapson.com",
    "wof:name":"Rapson Refrigeration Inc",
    "wof:placetype":"venue"
},
  "geometry": {"coordinates":[-82.997519,43.798058],"type":"Point"}
}