{
  "type": "Feature",
  "properties": {
    "iso:country":"US",
    "sg:address":"39221 Woodward Avenue",
    "sg:city":"Bloomfield Hills",
    "sg:classifiers":[
        {
            "category":"Museum",
            "type":"Entertainment"
        }
    ],
    "sg:phone":"+1 248 645 3323",
    "sg:postcode":"48304",
    "sg:province":"MI",
    "sg:website":"www.cranbrookart.edu/museum/",
    "wof:name":"Cranbrook Art Museum",
    "wof:placetype":"venue"
},
  "geometry": {"coordinates":[-83.24288,42.575374],"type":"Point"}
}