{
  "type": "Feature",
  "properties": {
    "iso:country":"US",
    "sg:address":"41630 Garfield Rd",
    "sg:city":"Clinton Twp",
    "sg:classifiers":[
        {
            "category":"Utilities",
            "subcategory":"Mobile Phone",
            "type":"Services"
        }
    ],
    "sg:phone":"+1 586 286 5200",
    "sg:postcode":"48038",
    "sg:province":"MI",
    "sg:tags":[
        "telephone",
        "cellular"
    ],
    "wof:name":"Verizon Wireless",
    "wof:placetype":"venue"
},
  "geometry": {"coordinates":[-82.952581,42.605229],"type":"Point"}
}