{
  "type": "Feature",
  "properties": {
    "iso:country":"US",
    "sg:address":"5725 Renville St",
    "sg:city":"Detroit",
    "sg:classifiers":[
        {
            "category":"Building & Trades",
            "subcategory":"Locksmith",
            "type":"Services"
        }
    ],
    "sg:phone":"+1 313 915 9105",
    "sg:postcode":"48210",
    "sg:province":"MI",
    "sg:tags":[
        "key"
    ],
    "wof:name":"Abbe Locks 24 Locksmith",
    "wof:placetype":"venue"
},
  "geometry": {"coordinates":[-83.148246,42.333842],"type":"Point"}
}