{
  "type": "Feature",
  "properties": {
    "iso:country":"US",
    "sg:address":"2526 Driftwood Dr",
    "sg:city":"Waterford",
    "sg:classifiers":[
        {
            "category":"Professional",
            "subcategory":"Secretarial Services",
            "type":"Services"
        }
    ],
    "sg:phone":"+1 248 618 0766",
    "sg:postcode":"48329",
    "sg:province":"MI",
    "sg:tags":[
        "convention",
        "court",
        "reporter"
    ],
    "wof:name":"Accu-Dep Reporting",
    "wof:placetype":"venue"
},
  "geometry": {"coordinates":[-83.395909,42.675809],"type":"Point"}
}