{
  "type": "Feature",
  "properties": {
    "iso:country":"US",
    "sg:address":"7925 Morey Hwy",
    "sg:city":"Morenci",
    "sg:classifiers":[
        {
            "category":"Food & Beverages",
            "subcategory":"Groceries & Convenience Stores",
            "type":"Retail Goods"
        }
    ],
    "sg:phone":"+1 517 458 6287",
    "sg:postcode":"49247",
    "sg:province":"MI",
    "sg:tags":[
        "grocer"
    ],
    "wof:name":"Hudson Lake Market",
    "wof:placetype":"venue"
},
  "geometry": {"coordinates":[-84.23419199999999,41.798284],"type":"Point"}
}