{
  "type": "Feature",
  "properties": {
    "iso:country":"US",
    "sg:address":"20220 Cornillie Dr",
    "sg:city":"Roseville",
    "sg:classifiers":[
        {
            "category":"Professional",
            "subcategory":"Computer Services",
            "type":"Services"
        }
    ],
    "sg:phone":"+1 586 463 5753",
    "sg:postcode":"48066",
    "sg:province":"MI",
    "sg:tags":[
        "web",
        "design",
        "related"
    ],
    "sg:website":"yourdomain.com|comtechcentral.com",
    "wof:name":"Comtech Central",
    "wof:placetype":"venue"
},
  "geometry": {"coordinates":[-82.9114,42.521044],"type":"Point"}
}