{
  "type": "Feature",
  "properties": {
    "iso:country":"US",
    "sg:address":"1120 W Huron St",
    "sg:city":"Ann Arbor",
    "sg:classifiers":[
        {
            "category":"Health Services",
            "subcategory":"Doctor",
            "type":"Services"
        }
    ],
    "sg:phone":"+1 734 665 8212",
    "sg:postcode":"48103",
    "sg:province":"MI",
    "wof:name":"Michael E Krause Ms PC",
    "wof:placetype":"venue"
},
  "geometry": {"coordinates":[-83.76176,42.281918],"type":"Point"}
}