{
  "type": "Feature",
  "properties": {
    "iso:country":"US",
    "sg:address":"61278 Miriam Dr",
    "sg:city":"Washington",
    "sg:classifiers":[
        {
            "category":"Building & Trades",
            "subcategory":"Construction",
            "type":"Services"
        }
    ],
    "sg:phone":"+1 586 786 9110",
    "sg:postcode":"48094",
    "sg:province":"MI",
    "sg:tags":[
        "contractor"
    ],
    "wof:name":"River City Resteel Inc",
    "wof:placetype":"venue"
},
  "geometry": {"coordinates":[-83.043702,42.745401],"type":"Point"}
}