{
  "type": "Feature",
  "properties": {
    "iso:country":"US",
    "sg:address":"43361 Commons Dr",
    "sg:city":"Clinton Township",
    "sg:classifiers":[
        {
            "category":"Health Services",
            "subcategory":"Doctor",
            "type":"Services"
        }
    ],
    "sg:phone":"+1 586 263 0500",
    "sg:postcode":"48038",
    "sg:province":"MI",
    "wof:name":"Villanueva Regina",
    "wof:placetype":"venue"
},
  "geometry": {"coordinates":[-82.958186,42.615691],"type":"Point"}
}