{
  "type": "Feature",
  "properties": {
    "iso:country":"US",
    "sg:address":"100 E McKay St",
    "sg:city":"Saline",
    "sg:classifiers":[
        {
            "category":"Retail",
            "subcategory":"Auto Repair",
            "type":"Services"
        }
    ],
    "sg:phone":"+1 734 944 2366",
    "sg:postcode":"48176",
    "sg:province":"MI",
    "sg:tags":[
        "body"
    ],
    "wof:name":"Finchs Collision & Restoration",
    "wof:placetype":"venue"
},
  "geometry": {"coordinates":[-83.781961,42.167653],"type":"Point"}
}