{
  "type": "Feature",
  "properties": {
    "iso:country":"US",
    "sg:address":"382 S Huron Rd",
    "sg:city":"Linwood",
    "sg:phone":"+1 989 697 5761",
    "sg:postcode":"48634",
    "sg:province":"MI",
    "sg:tags":[
        "gas"
    ],
    "wof:name":"Northwest Energy Inc",
    "wof:placetype":"venue"
},
  "geometry": {"coordinates":[-83.973736,43.727318],"type":"Point"}
}