{
  "type": "Feature",
  "properties": {
    "iso:country":"US",
    "sg:address":"2216 E Michigan Ave",
    "sg:city":"Lansing",
    "sg:classifiers":[
        {
            "category":"Organizations",
            "subcategory":"Community Association",
            "type":"Services"
        }
    ],
    "sg:phone":"+1 517 342 9955",
    "sg:postcode":"48912",
    "sg:province":"MI",
    "sg:tags":[
        "club"
    ],
    "wof:name":"Jug & Mug Ski Club",
    "wof:placetype":"venue"
},
  "geometry": {"coordinates":[-84.518933,42.73356],"type":"Point"}
}