{
  "type": "Feature",
  "properties": {
    "iso:country":"US",
    "sg:address":"837 Van Eyck St",
    "sg:city":"Muskegon",
    "sg:classifiers":[
        {
            "category":"Professional",
            "subcategory":"Employment Agencies",
            "type":"Services"
        }
    ],
    "sg:phone":"+1 231 788 5639",
    "sg:postcode":"49442",
    "sg:province":"MI",
    "sg:tags":[
        "help",
        "supply"
    ],
    "wof:name":"L M C Transcription",
    "wof:placetype":"venue"
},
  "geometry": {"coordinates":[-86.094787,43.238281],"type":"Point"}
}