{
  "type": "Feature",
  "properties": {
    "iso:country":"US",
    "sg:address":"542 Kinloch St",
    "sg:city":"Dearborn Heights",
    "sg:classifiers":[
        {
            "category":"Social Services",
            "subcategory":"Adult Care",
            "type":"Services"
        }
    ],
    "sg:phone":"+1 313 277 8193",
    "sg:postcode":"48127",
    "sg:province":"MI",
    "sg:tags":[
        "foster"
    ],
    "wof:name":"Kinloch Home",
    "wof:placetype":"venue"
},
  "geometry": {"coordinates":[-83.295703,42.314767],"type":"Point"}
}