{
  "type": "Feature",
  "properties": {
    "iso:country":"US",
    "sg:address":"319 S 5th St",
    "sg:city":"Escanaba",
    "sg:classifiers":[
        {
            "category":"Shopping",
            "subcategory":"Hobbies, Toys, & Games",
            "type":"Retail Goods"
        }
    ],
    "sg:phone":"+1 906 786 3611",
    "sg:postcode":"49829",
    "sg:province":"MI",
    "wof:name":"Watercolors By Julie",
    "wof:placetype":"venue"
},
  "geometry": {"coordinates":[-87.053646,45.742705],"type":"Point"}
}