{
  "type": "Feature",
  "properties": {
    "iso:country":"US",
    "sg:address":"3670 Woodward Ave",
    "sg:city":"Detroit",
    "sg:classifiers":[
        {
            "category":"Parking",
            "type":"Transportation"
        }
    ],
    "sg:phone":"+1 313 831 8901",
    "sg:postcode":"48201",
    "sg:province":"MI",
    "wof:name":"Wm Garage",
    "wof:placetype":"venue"
},
  "geometry": {"coordinates":[-83.05819700000001,42.347599],"type":"Point"}
}