{
  "type": "Feature",
  "properties": {
    "iso:country":"US",
    "sg:address":"7180 Highland Rd",
    "sg:city":"Waterford",
    "sg:classifiers":[
        {
            "category":"Shopping",
            "subcategory":"Optical Goods",
            "type":"Retail Goods"
        }
    ],
    "sg:phone":"+1 248 666 4020",
    "sg:postcode":"48327",
    "sg:province":"MI",
    "wof:name":"SVS Vision",
    "wof:placetype":"venue"
},
  "geometry": {"coordinates":[-83.43056900000001,42.66038],"type":"Point"}
}