{
  "type": "Feature",
  "properties": {
    "iso:country":"US",
    "sg:address":"1475 111th Ave",
    "sg:city":"Otsego",
    "sg:classifiers":[
        {
            "category":"Building & Trades",
            "subcategory":"Construction",
            "type":"Services"
        }
    ],
    "sg:phone":"+1 269 692 6014",
    "sg:postcode":"49078",
    "sg:province":"MI",
    "sg:tags":[
        "house"
    ],
    "wof:name":"Jeffery S Cherrington",
    "wof:placetype":"venue"
},
  "geometry": {"coordinates":[-85.68756500000001,42.501032],"type":"Point"}
}