{
  "type": "Feature",
  "properties": {
    "iso:country":"US",
    "sg:address":"6764 Bloomfield Ln",
    "sg:city":"West Bloomfield",
    "sg:classifiers":[
        {
            "category":"Professional",
            "subcategory":"Lawyer & Legal Services",
            "type":"Services"
        }
    ],
    "sg:phone":"+1 248 626 8122",
    "sg:postcode":"48322",
    "sg:province":"MI",
    "sg:tags":[
        "attorney"
    ],
    "wof:name":"Robert Kozlow",
    "wof:placetype":"venue"
},
  "geometry": {"coordinates":[-83.332977,42.543241],"type":"Point"}
}