{
  "type": "Feature",
  "properties": {
    "iso:country":"US",
    "sg:address":"118 N 2nd Ave",
    "sg:city":"Alpena",
    "sg:classifiers":[
        {
            "category":"Shopping",
            "subcategory":"Clothing, Apparel, & Fashions",
            "type":"Retail Goods"
        }
    ],
    "sg:phone":"+1 989 354 5705",
    "sg:postcode":"49707",
    "sg:province":"MI",
    "wof:name":"Country Cousin Shop",
    "wof:placetype":"venue"
},
  "geometry": {"coordinates":[-83.432428,45.062733],"type":"Point"}
}