{
  "type": "Feature",
  "properties": {
    "iso:country":"US",
    "sg:address":"5282 W Chadwick Rd",
    "sg:city":"Dewitt",
    "sg:classifiers":[
        {
            "category":"Professional",
            "subcategory":"Computer Services",
            "type":"Services"
        }
    ],
    "sg:phone":"+1 517 669 3595",
    "sg:postcode":"48820",
    "sg:province":"MI",
    "sg:tags":[
        "repair"
    ],
    "wof:name":"Americomp Computers",
    "wof:placetype":"venue"
},
  "geometry": {"coordinates":[-84.626758,42.871355],"type":"Point"}
}