{
  "type": "Feature",
  "properties": {
    "iso:country":"US",
    "sg:address":"3002 Lovers Ln",
    "sg:city":"Kalamazoo",
    "sg:classifiers":[
        {
            "category":"Personal",
            "type":"Services"
        }
    ],
    "sg:phone":"+1 269 217 7814",
    "sg:postcode":"49001",
    "sg:province":"MI",
    "sg:tags":[
        "therapist",
        "massage"
    ],
    "wof:name":"A Soft Tissue Joint",
    "wof:placetype":"venue"
},
  "geometry": {"coordinates":[-85.56764699999999,42.260782],"type":"Point"}
}