{
  "type": "Feature",
  "properties": {
    "iso:country":"US",
    "sg:address":"26400 Lahser Rd Ste 444",
    "sg:city":"Southfield",
    "sg:classifiers":[
        {
            "category":"Banks & Credit Unions",
            "subcategory":"Financial Services",
            "type":"Services"
        }
    ],
    "sg:phone":"+1 248 352 6622",
    "sg:postcode":"48033",
    "sg:province":"MI",
    "sg:tags":[
        "broker",
        "mortgage"
    ],
    "wof:name":"Assurafirst Financial",
    "wof:placetype":"venue"
},
  "geometry": {"coordinates":[-83.260993,42.482572],"type":"Point"}
}