{
  "type": "Feature",
  "properties": {
    "iso:country":"US",
    "sg:address":"415 E Peck Rd",
    "sg:city":"Peck",
    "sg:classifiers":[
        {
            "category":"Social Services",
            "subcategory":"Child Care",
            "type":"Services"
        }
    ],
    "sg:phone":"+1 810 378 6031",
    "sg:postcode":"48466",
    "sg:province":"MI",
    "sg:tags":[
        "day"
    ],
    "wof:name":"Debs Daycare",
    "wof:placetype":"venue"
},
  "geometry": {"coordinates":[-82.787888,43.259383],"type":"Point"}
}