{
  "type": "Feature",
  "properties": {
    "iso:country":"US",
    "sg:address":"33 Hiram",
    "sg:city":"Lake Orion",
    "sg:classifiers":[
        {
            "category":"Freight",
            "type":"Transportation"
        }
    ],
    "sg:phone":"+1 248 988 2520",
    "sg:postcode":"48360",
    "sg:province":"MI",
    "sg:tags":[
        "courier"
    ],
    "wof:name":"Service American Courier Corp",
    "wof:placetype":"venue"
},
  "geometry": {"coordinates":[-83.244601,42.745441],"type":"Point"}
}