{
  "type": "Feature",
  "properties": {
    "iso:country":"US",
    "sg:address":"5599 Pochert Rd",
    "sg:city":"Port Hope",
    "sg:classifiers":[
        {
            "category":"Building & Trades",
            "subcategory":"Plumbing",
            "type":"Services"
        }
    ],
    "sg:phone":"+1 989 428 4948",
    "sg:postcode":"48468",
    "sg:province":"MI",
    "sg:tags":[
        "air",
        "heating",
        "conditioning",
        "contractor"
    ],
    "wof:name":"Thumb Cooling",
    "wof:placetype":"venue"
},
  "geometry": {"coordinates":[-82.74647400000001,43.971303],"type":"Point"}
}