{
  "type": "Feature",
  "properties": {
    "iso:country":"US",
    "sg:address":"496 W Ann Arbor Trl Ste 205",
    "sg:city":"Plymouth",
    "sg:classifiers":[
        {
            "category":"Real Estate",
            "subcategory":"Architect",
            "type":"Services"
        }
    ],
    "sg:phone":"+1 734 416 1090",
    "sg:postcode":"48170",
    "sg:province":"MI",
    "wof:name":"Arconcepts Inc",
    "wof:placetype":"venue"
},
  "geometry": {"coordinates":[-83.466103,42.369301],"type":"Point"}
}