{
  "type": "Feature",
  "properties": {
    "iso:country":"US",
    "sg:address":"15310 Fish Lake Rd",
    "sg:city":"Holly",
    "sg:classifiers":[
        {
            "category":"Retail",
            "subcategory":"Auto Repair",
            "type":"Services"
        }
    ],
    "sg:phone":"+1 248 634 0399",
    "sg:postcode":"48442",
    "sg:province":"MI",
    "sg:tags":[
        "repairing",
        "automobile"
    ],
    "wof:name":"Armstead Automotive Repair",
    "wof:placetype":"venue"
},
  "geometry": {"coordinates":[-83.64801300000001,42.80996],"type":"Point"}
}