{
  "type": "Feature",
  "properties": {
    "iso:country":"US",
    "sg:address":"2702 Ravine Rd",
    "sg:city":"Kalamazoo",
    "sg:classifiers":[
        {
            "category":"Wholesale",
            "subcategory":"Construction Materials",
            "type":"Manufacturing & Wholesale Goods"
        }
    ],
    "sg:phone":"+1 269 383 4655",
    "sg:postcode":"49004",
    "sg:province":"MI",
    "sg:tags":[
        "sand",
        "gravel"
    ],
    "wof:name":"Triple B Aggregates",
    "wof:placetype":"venue"
},
  "geometry": {"coordinates":[-85.619786,42.311193],"type":"Point"}
}