{
  "type": "Feature",
  "properties": {
    "iso:country":"US",
    "sg:address":"496 Lincoln Ave",
    "sg:city":"Holland",
    "sg:classifiers":[
        {
            "category":"Building & Trades",
            "subcategory":"Construction",
            "type":"Services"
        }
    ],
    "sg:phone":"+1 616 392 7225",
    "sg:postcode":"49423",
    "sg:province":"MI",
    "sg:tags":[
        "general",
        "contractor"
    ],
    "wof:name":"Deyoung Builders",
    "wof:placetype":"venue"
},
  "geometry": {"coordinates":[-86.09734899999999,42.778962],"type":"Point"}
}