{
  "type": "Feature",
  "properties": {
    "iso:country":"US",
    "sg:address":"1401 W Michigan Ave",
    "sg:city":"Jackson",
    "sg:classifiers":[
        {
            "category":"Professional",
            "subcategory":"Lawyer & Legal Services",
            "type":"Services"
        }
    ],
    "sg:phone":"+1 517 780 4088",
    "sg:postcode":"49202",
    "sg:province":"MI",
    "sg:tags":[
        "attorney"
    ],
    "wof:name":"Patricia J Worth",
    "wof:placetype":"venue"
},
  "geometry": {"coordinates":[-84.431945,42.247408],"type":"Point"}
}