{
  "type": "Feature",
  "properties": {
    "iso:country":"US",
    "sg:address":"6672 Stadium Dr",
    "sg:city":"Kalamazoo",
    "sg:classifiers":[
        {
            "category":"Insurance",
            "subcategory":"Insurance Agent",
            "type":"Services"
        }
    ],
    "sg:phone":"+1 269 381 4311",
    "sg:postcode":"49009",
    "sg:province":"MI",
    "wof:name":"Liberty Group Inc",
    "wof:placetype":"venue"
},
  "geometry": {"coordinates":[-85.68293199999999,42.258186],"type":"Point"}
}