{
  "type": "Feature",
  "properties": {
    "iso:country":"US",
    "sg:address":"38110 Executive Dr N",
    "sg:city":"Westland",
    "sg:classifiers":[
        {
            "category":"Professional",
            "subcategory":"Lawyer & Legal Services",
            "type":"Services"
        }
    ],
    "sg:phone":"+1 734 729 6500",
    "sg:postcode":"48185",
    "sg:province":"MI",
    "wof:name":"Rose and Abramson",
    "wof:placetype":"venue"
},
  "geometry": {"coordinates":[-83.41732,42.3297],"type":"Point"}
}