{
  "type": "Feature",
  "properties": {
    "iso:country":"US",
    "sg:address":"21150 Belleview St",
    "sg:city":"Clinton Twp",
    "sg:classifiers":[
        {
            "category":"Professional",
            "subcategory":"Business Services",
            "type":"Services"
        },
        {
            "category":"Building & Trades",
            "subcategory":"Construction",
            "type":"Services"
        }
    ],
    "sg:phone":"+1 586 307 3977",
    "sg:postcode":"48036",
    "sg:province":"MI",
    "sg:tags":[
        "television",
        "telephone",
        "cable",
        "contractor"
    ],
    "wof:name":"Direct Cablers",
    "wof:placetype":"venue"
},
  "geometry": {"coordinates":[-82.904028,42.592557],"type":"Point"}
}