{
  "type": "Feature",
  "properties": {
    "iso:country":"US",
    "sg:address":"4008 Wainwright Ave",
    "sg:city":"Lansing",
    "sg:classifiers":[
        {
            "category":"Social Services",
            "subcategory":"Adult Care",
            "type":"Services"
        }
    ],
    "sg:phone":"+1 517 887 2119",
    "sg:postcode":"48911",
    "sg:province":"MI",
    "sg:tags":[
        "foster",
        "provider"
    ],
    "wof:name":"Charles E & Loris Askew",
    "wof:placetype":"venue"
},
  "geometry": {"coordinates":[-84.592758,42.692626],"type":"Point"}
}