{
  "type": "Feature",
  "properties": {
    "iso:country":"US",
    "sg:address":"51221 Industrial Dr",
    "sg:city":"Macomb",
    "sg:classifiers":[
        {
            "category":"Wholesale",
            "subcategory":"Meat",
            "type":"Manufacturing & Wholesale Goods"
        }
    ],
    "sg:phone":"+1 586 781 3000",
    "sg:postcode":"48042",
    "sg:province":"MI",
    "sg:tags":[
        "sausage"
    ],
    "sg:website":"www.jerkyoutlet.com",
    "wof:name":"American Food Co",
    "wof:placetype":"venue"
},
  "geometry": {"coordinates":[-82.969843,42.673194],"type":"Point"}
}