{
  "type": "Feature",
  "properties": {
    "iso:country":"US",
    "sg:address":"25011 Ford Rd",
    "sg:city":"Dearborn",
    "sg:classifiers":[
        {
            "category":"Food & Beverages",
            "subcategory":"Liquor & Beverages",
            "type":"Retail Goods"
        }
    ],
    "sg:phone":"+1 313 563 6145",
    "sg:postcode":"48128",
    "sg:province":"MI",
    "sg:tags":[
        "beer",
        "spirit",
        "wine"
    ],
    "wof:name":"Spirits Plus",
    "wof:placetype":"venue"
},
  "geometry": {"coordinates":[-83.28299699999999,42.326698],"type":"Point"}
}