{
  "type": "Feature",
  "properties": {
    "iso:country":"US",
    "sg:address":"11539 E Lakewood Blvd",
    "sg:city":"Holland",
    "sg:classifiers":[
        {
            "category":"Restaurant",
            "type":"Food & Drink"
        }
    ],
    "sg:phone":"+1 616 396 9102",
    "sg:postcode":"49424",
    "sg:province":"MI",
    "sg:tags":[
        "out"
    ],
    "wof:name":"Main Dish Kitchen",
    "wof:placetype":"venue"
},
  "geometry": {"coordinates":[-86.065515,42.805016],"type":"Point"}
}