{
  "type": "Feature",
  "properties": {
    "iso:country":"US",
    "sg:address":"1389 Wheaton Dr",
    "sg:city":"Troy",
    "sg:classifiers":[
        {
            "category":"Wholesale",
            "subcategory":"Auto Parts",
            "type":"Manufacturing & Wholesale Goods"
        }
    ],
    "sg:phone":"+1 248 680 8872",
    "sg:postcode":"48083",
    "sg:province":"MI",
    "sg:tags":[
        "automobile"
    ],
    "wof:name":"Cofap Of America",
    "wof:placetype":"venue"
},
  "geometry": {"coordinates":[-83.128068,42.557233],"type":"Point"}
}