{
  "type": "Feature",
  "properties": {
    "iso:country":"US",
    "sg:address":"1094 S State Rd",
    "sg:city":"Davison",
    "sg:classifiers":[
        {
            "category":"Health Services",
            "subcategory":"Medical Lab",
            "type":"Services"
        }
    ],
    "sg:phone":"+1 810 653 7651",
    "sg:postcode":"48423",
    "sg:province":"MI",
    "sg:tags":[
        "laboratory"
    ],
    "wof:name":"Quest Diagnostics Inc",
    "wof:placetype":"venue"
},
  "geometry": {"coordinates":[-83.517664,43.016618],"type":"Point"}
}