{
  "type": "Feature",
  "properties": {
    "iso:country":"US",
    "sg:address":"1825 Brinston Dr",
    "sg:city":"Troy",
    "sg:classifiers":[
        {
            "category":"Building & Trades",
            "subcategory":"Plumbing",
            "type":"Services"
        }
    ],
    "sg:phone":"+1 248 689 9887",
    "sg:postcode":"48083",
    "sg:province":"MI",
    "sg:tags":[
        "plumbing",
        "contractor"
    ],
    "wof:name":"Donald R Kellett Plumbing",
    "wof:placetype":"venue"
},
  "geometry": {"coordinates":[-83.110726,42.55554],"type":"Point"}
}