{
  "type": "Feature",
  "properties": {
    "iso:country":"US",
    "sg:address":"1600 E Newberg Rd",
    "sg:city":"Pinconning",
    "sg:classifiers":[
        {
            "category":"Retail",
            "subcategory":"Repair Shop",
            "type":"Services"
        }
    ],
    "sg:phone":"+1 989 879 2302",
    "sg:postcode":"48650",
    "sg:province":"MI",
    "sg:tags":[
        "welding"
    ],
    "wof:name":"Town and Country Welding",
    "wof:placetype":"venue"
},
  "geometry": {"coordinates":[-83.983386,43.810586],"type":"Point"}
}