{
  "type": "Feature",
  "properties": {
    "iso:country":"US",
    "sg:address":"37228 Huron River Dr",
    "sg:city":"New Boston",
    "sg:classifiers":[
        {
            "category":"Health Services",
            "subcategory":"Dentist",
            "type":"Services"
        }
    ],
    "sg:phone":"+1 734 753 4300",
    "sg:postcode":"48164",
    "sg:province":"MI",
    "wof:name":"New Boston Dental Clinic PC",
    "wof:placetype":"venue"
},
  "geometry": {"coordinates":[-83.401802,42.162498],"type":"Point"}
}