{
  "type": "Feature",
  "properties": {
    "iso:country":"US",
    "sg:address":"517 S O Keefe St",
    "sg:city":"Cassopolis",
    "sg:classifiers":[
        {
            "category":"Social Services",
            "subcategory":"Adult Care",
            "type":"Services"
        }
    ],
    "sg:phone":"+1 269 445 1936",
    "sg:postcode":"49031",
    "sg:province":"MI",
    "sg:tags":[
        "home",
        "sheltered"
    ],
    "wof:name":"SMCAA Cass Shelter",
    "wof:placetype":"venue"
},
  "geometry": {"coordinates":[-86.00996000000001,41.903377],"type":"Point"}
}