{
  "type": "Feature",
  "properties": {
    "iso:country":"US",
    "sg:address":"4501 Van Slyke Rd",
    "sg:city":"Flint",
    "sg:classifiers":[
        {
            "category":"Retail",
            "subcategory":"Event Space",
            "type":"Services"
        }
    ],
    "sg:phone":"+1 810 767 0600",
    "sg:postcode":"48507",
    "sg:province":"MI",
    "sg:tags":[
        "venue"
    ],
    "wof:name":"Fisher Hall",
    "wof:placetype":"venue"
},
  "geometry": {"coordinates":[-83.713154,42.983775],"type":"Point"}
}