{
  "type": "Feature",
  "properties": {
    "iso:country":"US",
    "sg:address":"1241 S Monroe St",
    "sg:city":"Monroe",
    "sg:classifiers":[
        {
            "category":"Home & Garden",
            "subcategory":"Furniture",
            "type":"Retail Goods"
        }
    ],
    "sg:phone":"+1 734 241 8100",
    "sg:postcode":"48161",
    "sg:province":"MI",
    "wof:name":"Dinettes & Patio Plus",
    "wof:placetype":"venue"
},
  "geometry": {"coordinates":[-83.405665,41.906716],"type":"Point"}
}