{
  "type": "Feature",
  "properties": {
    "iso:country":"US",
    "sg:address":"2510 Binbrooke Dr",
    "sg:city":"Troy",
    "sg:classifiers":[
        {
            "category":"Restaurant",
            "type":"Food & Drink"
        }
    ],
    "sg:phone":"+1 248 593 1405",
    "sg:postcode":"48084",
    "sg:province":"MI",
    "sg:tags":[
        "pizza"
    ],
    "wof:name":"Bosco's Pizza Co",
    "wof:placetype":"venue"
},
  "geometry": {"coordinates":[-83.197496,42.575111],"type":"Point"}
}