{
  "type": "Feature",
  "properties": {
    "iso:country":"US",
    "sg:address":"438 Sandalwood Dr",
    "sg:city":"Rochester",
    "sg:classifiers":[
        {
            "category":"Health Services",
            "subcategory":"Clinic",
            "type":"Services"
        }
    ],
    "sg:phone":"+1 248 650 0993",
    "sg:postcode":"48307",
    "sg:province":"MI",
    "wof:name":"Substance Abuse Medical Svc",
    "wof:placetype":"venue"
},
  "geometry": {"coordinates":[-83.14008800000001,42.65791],"type":"Point"}
}