{
  "type": "Feature",
  "properties": {
    "iso:country":"US",
    "sg:address":"5835 Oakland Dr",
    "sg:city":"Portage",
    "sg:classifiers":[
        {
            "category":"Health Services",
            "subcategory":"Doctor",
            "type":"Services"
        }
    ],
    "sg:phone":"+1 269 345 9625",
    "sg:postcode":"49024",
    "sg:province":"MI",
    "sg:tags":[
        "dentist"
    ],
    "wof:name":"Scott F Ellard & Assoc",
    "wof:placetype":"venue"
},
  "geometry": {"coordinates":[-85.613899,42.230159],"type":"Point"}
}