{
  "type": "Feature",
  "properties": {
    "iso:country":"US",
    "sg:address":"5236 Portage Rd",
    "sg:city":"Portage",
    "sg:classifiers":[
        {
            "category":"Restaurant",
            "type":"Food & Drink"
        }
    ],
    "sg:phone":"+1 269 381 8692",
    "sg:postcode":"49002",
    "sg:province":"MI",
    "sg:tags":[
        "pizza"
    ],
    "sg:website":"http://www.ringtheking.com",
    "wof:name":"Pizza King",
    "wof:placetype":"venue"
},
  "geometry": {"coordinates":[-85.56014999999999,42.240974],"type":"Point"}
}