{
  "type": "Feature",
  "properties": {
    "iso:country":"US",
    "sg:address":"95 W Grand Ledge Hwy",
    "sg:city":"Mulliken",
    "sg:classifiers":[
        {
            "category":"Food & Beverages",
            "subcategory":"Groceries & Convenience Stores",
            "type":"Retail Goods"
        }
    ],
    "sg:phone":"+1 517 649 8811",
    "sg:postcode":"48861",
    "sg:province":"MI",
    "sg:tags":[
        "grocer"
    ],
    "wof:name":"Mulliken Thriftway Grocery",
    "wof:placetype":"venue"
},
  "geometry": {"coordinates":[-84.83879899999999,42.755537],"type":"Point"}
}