{
  "type": "Feature",
  "properties": {
    "iso:country":"US",
    "sg:address":"12680 Hedges Ln",
    "sg:city":"Battle Creek",
    "sg:classifiers":[
        {
            "category":"Building & Trades",
            "subcategory":"Electrical",
            "type":"Services"
        }
    ],
    "sg:phone":"+1 269 979 4038",
    "sg:postcode":"49015",
    "sg:province":"MI",
    "sg:tags":[
        "electric",
        "contractor"
    ],
    "wof:name":"Lance Electric",
    "wof:placetype":"venue"
},
  "geometry": {"coordinates":[-85.26737300000001,42.258249],"type":"Point"}
}