{
  "type": "Feature",
  "properties": {
    "iso:country":"US",
    "sg:address":"1820 Ormond Rd",
    "sg:city":"White Lake",
    "sg:classifiers":[
        {
            "category":"Building & Trades",
            "subcategory":"Construction",
            "type":"Services"
        }
    ],
    "sg:phone":"+1 248 887 4626",
    "sg:postcode":"48383",
    "sg:province":"MI",
    "sg:tags":[
        "paving",
        "contractor"
    ],
    "wof:name":"Michigan All Pro Asphalt Pvng",
    "wof:placetype":"venue"
},
  "geometry": {"coordinates":[-83.55256,42.657534],"type":"Point"}
}