{
  "type": "Feature",
  "properties": {
    "iso:country":"US",
    "sg:address":"15 N Caseville Rd",
    "sg:city":"Pigeon",
    "sg:classifiers":[
        {
            "category":"Food & Beverages",
            "subcategory":"Groceries & Convenience Stores",
            "type":"Retail Goods"
        }
    ],
    "sg:phone":"+1 989 453 2800",
    "sg:postcode":"48755",
    "sg:province":"MI",
    "sg:tags":[
        "grocer"
    ],
    "wof:name":"Pigeon IGA Foodliner",
    "wof:placetype":"venue"
},
  "geometry": {"coordinates":[-83.279487,43.829665],"type":"Point"}
}