{
  "type": "Feature",
  "properties": {
    "iso:country":"US",
    "sg:address":"1055 Forest Hill Ave SE",
    "sg:city":"Grand Rapids",
    "sg:classifiers":[
        {
            "category":"Banks & Credit Unions",
            "subcategory":"Bank",
            "type":"Services"
        }
    ],
    "sg:phone":"+1 616 235 4280",
    "sg:postcode":"49546",
    "sg:province":"MI",
    "sg:tags":[
        "national",
        "commercial"
    ],
    "wof:name":"National City Bank",
    "wof:placetype":"venue"
},
  "geometry": {"coordinates":[-85.55588,42.94465],"type":"Point"}
}