{
  "type": "Feature",
  "properties": {
    "iso:country":"US",
    "sg:address":"1043 Comstock St",
    "sg:city":"Marne",
    "sg:classifiers":[
        {
            "category":"Manufacturing",
            "subcategory":"Retail Goods",
            "type":"Manufacturing & Wholesale Goods"
        }
    ],
    "sg:phone":"+1 616 677 3630",
    "sg:postcode":"49435",
    "sg:province":"MI",
    "sg:tags":[
        "assembly",
        "fabricating"
    ],
    "wof:name":"Z B Enterprises",
    "wof:placetype":"venue"
},
  "geometry": {"coordinates":[-85.812809,43.038275],"type":"Point"}
}