{
  "type": "Feature",
  "properties": {
    "iso:country":"US",
    "sg:address":"751 Lamoreaux Dr NW",
    "sg:city":"Comstock Park",
    "sg:classifiers":[
        {
            "category":"Retail",
            "subcategory":"Veterinary Services",
            "type":"Services"
        }
    ],
    "sg:phone":"+1 616 784 7144",
    "sg:postcode":"49321",
    "sg:province":"MI",
    "wof:name":"Northwest Animal Hospital",
    "wof:placetype":"venue"
},
  "geometry": {"coordinates":[-85.688548,43.043572],"type":"Point"}
}