{
  "type": "Feature",
  "properties": {
    "iso:country":"US",
    "sg:address":"4044 Stafford Dr",
    "sg:city":"Pinckney",
    "sg:classifiers":[
        {
            "category":"Education",
            "subcategory":"Special Training",
            "type":"Public Place"
        }
    ],
    "sg:phone":"+1 734 878 5273",
    "sg:postcode":"48169",
    "sg:province":"MI",
    "sg:tags":[
        "aircraft",
        "school"
    ],
    "wof:name":"Dean A Pode CFI",
    "wof:placetype":"venue"
},
  "geometry": {"coordinates":[-83.868914,42.48224],"type":"Point"}
}