{
  "type": "Feature",
  "properties": {
    "iso:country":"US",
    "sg:address":"3105 Cabaret Trl S",
    "sg:city":"Saginaw",
    "sg:classifiers":[
        {
            "category":"Social Services",
            "subcategory":"Job Training",
            "type":"Services"
        }
    ],
    "sg:phone":"+1 989 799 5316",
    "sg:postcode":"48603",
    "sg:province":"MI",
    "sg:tags":[
        "rehabilitation"
    ],
    "wof:name":"Woida Lorentzen & Assoc",
    "wof:placetype":"venue"
},
  "geometry": {"coordinates":[-83.978314,43.462793],"type":"Point"}
}