{
  "type": "Feature",
  "properties": {
    "iso:country":"US",
    "sg:address":"500 Country Pine Ln",
    "sg:city":"Battle Creek",
    "sg:classifiers":[
        {
            "category":"Government",
            "subcategory":"Office",
            "type":"Public Place"
        }
    ],
    "sg:phone":"+1 269 979 8919",
    "sg:postcode":"49015",
    "sg:province":"MI",
    "sg:tags":[
        "federal"
    ],
    "wof:name":"Natural Resources Conservation",
    "wof:placetype":"venue"
},
  "geometry": {"coordinates":[-85.19893399999999,42.258607],"type":"Point"}
}