{
  "type": "Feature",
  "properties": {
    "iso:country":"US",
    "sg:address":"39600 Michigan Ave",
    "sg:city":"Canton",
    "sg:classifiers":[
        {
            "category":"Retail",
            "subcategory":"Auto Repair",
            "type":"Services"
        }
    ],
    "sg:phone":"+1 734 728 2000",
    "sg:postcode":"48188",
    "sg:province":"MI",
    "wof:name":"Mel's Auto Clinic",
    "wof:placetype":"venue"
},
  "geometry": {"coordinates":[-83.42759700000001,42.2794],"type":"Point"}
}