{
  "type": "Feature",
  "properties": {
    "iso:country":"US",
    "sg:address":"1475 W Big Beaver Rd Ste 300",
    "sg:city":"Troy",
    "sg:classifiers":[
        {
            "category":"Banks & Credit Unions",
            "subcategory":"Financial Services",
            "type":"Services"
        }
    ],
    "sg:phone":"+1 248 649 5100",
    "sg:postcode":"48084",
    "sg:province":"MI",
    "sg:tags":[
        "broker",
        "mortgage"
    ],
    "wof:name":"1st National Financial Corporation",
    "wof:placetype":"venue"
},
  "geometry": {"coordinates":[-83.168503,42.5616],"type":"Point"}
}