{
  "type": "Feature",
  "properties": {
    "iso:country":"US",
    "sg:address":"2333 Cole St",
    "sg:city":"Birmingham",
    "sg:classifiers":[
        {
            "category":"Building & Trades",
            "subcategory":"Equipment Rental",
            "type":"Services"
        }
    ],
    "sg:phone":"+1 248 646 0550",
    "sg:postcode":"48009",
    "sg:province":"MI",
    "sg:tags":[
        "heater",
        "natural",
        "mfg",
        "propane",
        "gas",
        "air",
        "rent"
    ],
    "wof:name":"Sundog Construction Heaters",
    "wof:placetype":"venue"
},
  "geometry": {"coordinates":[-83.194901,42.540227],"type":"Point"}
}