{
  "type": "Feature",
  "properties": {
    "iso:country":"US",
    "sg:address":"10450 Homestead Rd",
    "sg:city":"Beulah",
    "sg:classifiers":[
        {
            "category":"Building & Trades",
            "subcategory":"Construction",
            "type":"Services"
        }
    ],
    "sg:phone":"+1 231 882 4609",
    "sg:postcode":"49617",
    "sg:province":"MI",
    "sg:tags":[
        "roofing",
        "contractor"
    ],
    "wof:name":"J & G Roofing & Siding Inc",
    "wof:placetype":"venue"
},
  "geometry": {"coordinates":[-86.02499,44.617038],"type":"Point"}
}