{
  "type": "Feature",
  "properties": {
    "iso:country":"US",
    "sg:address":"2855 Coolidge Hwy",
    "sg:city":"Troy",
    "sg:classifiers":[
        {
            "category":"Autos & Motor Vehicles",
            "subcategory":"Automobile Sales",
            "type":"Retail Goods"
        }
    ],
    "sg:phone":"+1 248 643 4337",
    "sg:postcode":"48084",
    "sg:province":"MI",
    "wof:name":"Cadillac Manchester 2005",
    "wof:placetype":"venue"
},
  "geometry": {"coordinates":[-83.18690100000001,42.559359],"type":"Point"}
}