{
  "type": "Feature",
  "properties": {
    "iso:country":"US",
    "sg:address":"14228 Industrial Center Dr",
    "sg:city":"Shelby Twp",
    "sg:classifiers":[
        {
            "category":"Manufacturing",
            "subcategory":"Tools & Machinery",
            "type":"Manufacturing & Wholesale Goods"
        }
    ],
    "sg:phone":"+1 586 532 0237",
    "sg:postcode":"48315",
    "sg:province":"MI",
    "sg:tags":[
        "mold"
    ],
    "wof:name":"Vertex Mold Inc",
    "wof:placetype":"venue"
},
  "geometry": {"coordinates":[-82.98352800000001,42.666426],"type":"Point"}
}