{
  "type": "Feature",
  "properties": {
    "iso:country":"US",
    "sg:address":"47 E Adams Ave",
    "sg:city":"Detroit",
    "sg:classifiers":[
        {
            "category":"Bars & Pubs",
            "subcategory":"Sports Bar",
            "type":"Food & Drink"
        },
        {
            "category":"Restaurant",
            "type":"Food & Drink"
        }
    ],
    "sg:phone":"+1 313 961 1700",
    "sg:postcode":"48226",
    "sg:province":"MI",
    "sg:tags":[
        "traditional",
        "american"
    ],
    "sg:website":"www.chelischilibar.com",
    "wof:name":"Cheli's Chili Bar",
    "wof:placetype":"venue"
},
  "geometry": {"coordinates":[-83.05038399999999,42.337497],"type":"Point"}
}