{
  "type": "Feature",
  "properties": {
    "iso:country":"US",
    "sg:address":"1324 Pipestone Rd",
    "sg:city":"Benton Harbor",
    "sg:classifiers":[
        {
            "category":"Shopping",
            "subcategory":"Used Merchandise",
            "type":"Retail Goods"
        }
    ],
    "sg:phone":"+1 269 925 8028",
    "sg:postcode":"49022",
    "sg:province":"MI",
    "sg:tags":[
        "furniture"
    ],
    "wof:name":"Shabby Chic",
    "wof:placetype":"venue"
},
  "geometry": {"coordinates":[-86.42992599999999,42.094094],"type":"Point"}
}