{
  "type": "Feature",
  "properties": {
    "iso:country":"US",
    "sg:address":"2161 Ferguson Rd",
    "sg:city":"Jackson",
    "sg:classifiers":[
        {
            "category":"Retail",
            "subcategory":"Laundry & Dry Cleaning",
            "type":"Services"
        }
    ],
    "sg:phone":"+1 517 788 7553",
    "sg:postcode":"49203",
    "sg:province":"MI",
    "sg:tags":[
        "cleaners"
    ],
    "wof:name":"Wheeler's Cleaners & Tux",
    "wof:placetype":"venue"
},
  "geometry": {"coordinates":[-84.43920300000001,42.199043],"type":"Point"}
}