{
  "type": "Feature",
  "properties": {
    "iso:country":"US",
    "sg:address":"7868 Gratiot Rd",
    "sg:city":"Saginaw",
    "sg:classifiers":[
        {
            "category":"Restaurant",
            "type":"Food & Drink"
        }
    ],
    "sg:menulink":"http://www.allmenus.com/mi/thomas/196823-burger-king/menu/",
    "sg:phone":"+1 989 781 0190",
    "sg:postcode":"48609",
    "sg:province":"MI",
    "sg:tags":[
        "burger",
        "american"
    ],
    "wof:name":"Burger King",
    "wof:placetype":"venue"
},
  "geometry": {"coordinates":[-84.06956599999999,43.415958],"type":"Point"}
}