{
  "type": "Feature",
  "properties": {
    "iso:country":"US",
    "sg:address":"15511 Pless Ln",
    "sg:city":"Spring Lake",
    "sg:classifiers":[
        {
            "category":"Professional",
            "subcategory":"Business Services",
            "type":"Services"
        }
    ],
    "sg:phone":"+1 616 844 9272",
    "sg:postcode":"49456",
    "sg:province":"MI",
    "wof:name":"Plesslane Design Inc",
    "wof:placetype":"venue"
},
  "geometry": {"coordinates":[-86.17421899999999,43.096149],"type":"Point"}
}