{
  "type": "Feature",
  "properties": {
    "iso:country":"US",
    "sg:address":"11435 Anna Lisa Dr",
    "sg:city":"Sterling Heights",
    "sg:classifiers":[
        {
            "category":"Shopping",
            "subcategory":"Clothing, Apparel, & Fashions",
            "type":"Retail Goods"
        }
    ],
    "sg:phone":"+1 586 264 0089",
    "sg:postcode":"48312",
    "sg:province":"MI",
    "wof:name":"Helen's Apparel",
    "wof:placetype":"venue"
},
  "geometry": {"coordinates":[-83.013733,42.568653],"type":"Point"}
}