{
  "type": "Feature",
  "properties": {
    "iso:country":"US",
    "sg:address":"12897 Main St",
    "sg:city":"Buchanan",
    "sg:classifiers":[
        {
            "category":"Retail",
            "subcategory":"Repair Shop",
            "type":"Services"
        }
    ],
    "sg:phone":"+1 269 362 1518",
    "sg:postcode":"49107",
    "sg:province":"MI",
    "wof:name":"Foxy Clean",
    "wof:placetype":"venue"
},
  "geometry": {"coordinates":[-86.39113999999999,41.885241],"type":"Point"}
}