{
  "type": "Feature",
  "properties": {
    "iso:country":"US",
    "sg:address":"1700 W Highland Rd",
    "sg:city":"Howell",
    "sg:classifiers":[
        {
            "category":"Banks & Credit Unions",
            "subcategory":"Bank",
            "type":"Services"
        }
    ],
    "sg:phone":"+1 517 546 7766",
    "sg:postcode":"48843",
    "sg:province":"MI",
    "sg:tags":[
        "state",
        "chartered"
    ],
    "wof:name":"Huron River Area Credit Union",
    "wof:placetype":"venue"
},
  "geometry": {"coordinates":[-83.95268299999999,42.621845],"type":"Point"}
}