{
  "type": "Feature",
  "properties": {
    "iso:country":"US",
    "sg:address":"527 E 8th St",
    "sg:city":"Traverse City",
    "sg:classifiers":[
        {
            "category":"Personal",
            "subcategory":"Beauty Salon",
            "type":"Services"
        }
    ],
    "sg:phone":"+1 231 933 4176",
    "sg:postcode":"49686",
    "sg:province":"MI",
    "sg:tags":[
        "shop"
    ],
    "wof:name":"Laura King",
    "wof:placetype":"venue"
},
  "geometry": {"coordinates":[-85.613004,44.759477],"type":"Point"}
}