{
  "type": "Feature",
  "properties": {
    "iso:country":"US",
    "sg:address":"3401 Livernois Ave",
    "sg:city":"Detroit",
    "sg:classifiers":[
        {
            "category":"Food & Beverages",
            "subcategory":"Groceries & Convenience Stores",
            "type":"Retail Goods"
        }
    ],
    "sg:phone":"+1 313 256 1869",
    "sg:postcode":"48210",
    "sg:province":"MI",
    "wof:name":"Alcapone Market",
    "wof:placetype":"venue"
},
  "geometry": {"coordinates":[-83.11694799999999,42.326123],"type":"Point"}
}