{
  "type": "Feature",
  "properties": {
    "iso:country":"US",
    "sg:address":"23629 S Chrysler Dr",
    "sg:city":"Hazel Park",
    "sg:classifiers":[
        {
            "category":"Building & Trades",
            "subcategory":"Cleaning & Sanitation",
            "type":"Services"
        }
    ],
    "sg:phone":"+1 248 336 0352",
    "sg:postcode":"48030",
    "sg:province":"MI",
    "sg:tags":[
        "window"
    ],
    "wof:name":"D & R Window Cleaning",
    "wof:placetype":"venue"
},
  "geometry": {"coordinates":[-83.108459,42.466301],"type":"Point"}
}