{
  "type": "Feature",
  "properties": {
    "iso:country":"US",
    "sg:address":"4831 Jurgess Rd",
    "sg:city":"Ubly",
    "sg:classifiers":[
        {
            "category":"Building & Trades",
            "subcategory":"Plumbing",
            "type":"Services"
        }
    ],
    "sg:phone":"+1 989 658 2084",
    "sg:postcode":"48475",
    "sg:province":"MI",
    "sg:tags":[
        "plumbing",
        "contractor"
    ],
    "wof:name":"Great Lakes Plumbing & Heating",
    "wof:placetype":"venue"
},
  "geometry": {"coordinates":[-82.91852900000001,43.700945],"type":"Point"}
}