{
  "type": "Feature",
  "properties": {
    "iso:country":"US",
    "sg:address":"10906 Grand River Rd",
    "sg:city":"Brighton",
    "sg:classifiers":[
        {
            "category":"Bars & Pubs",
            "type":"Food & Drink"
        }
    ],
    "sg:phone":"+1 810 229 9941",
    "sg:postcode":"48116",
    "sg:province":"MI",
    "wof:name":"Cozy Inn",
    "wof:placetype":"venue"
},
  "geometry": {"coordinates":[-83.734841,42.516219],"type":"Point"}
}