{
  "type": "Feature",
  "properties": {
    "iso:country":"US",
    "sg:address":"2265 58th St",
    "sg:city":"Fennville",
    "sg:phone":"+1 269 561 6571",
    "sg:postcode":"49408",
    "sg:province":"MI",
    "sg:tags":[
        "farm",
        "soybean"
    ],
    "wof:name":"Bryan Shields",
    "wof:placetype":"venue"
},
  "geometry": {"coordinates":[-86.114696,42.585883],"type":"Point"}
}