{
  "type": "Feature",
  "properties": {
    "iso:country":"US",
    "sg:address":"301 S Crapo St",
    "sg:city":"Mount Pleasant",
    "sg:classifiers":[
        {
            "category":"Social Services",
            "type":"Services"
        }
    ],
    "sg:phone":"+1 989 772 5938",
    "sg:postcode":"48858",
    "sg:province":"MI",
    "sg:tags":[
        "clinic",
        "specialty",
        "outpatient"
    ],
    "wof:name":"Community Mental Health",
    "wof:placetype":"venue"
},
  "geometry": {"coordinates":[-84.757678,43.602716],"type":"Point"}
}