{
  "type": "Feature",
  "properties": {
    "iso:country":"US",
    "sg:address":"5462 Gull Rd",
    "sg:city":"Kalamazoo",
    "sg:classifiers":[
        {
            "category":"Shopping",
            "subcategory":"Used Merchandise",
            "type":"Retail Goods"
        }
    ],
    "sg:phone":"+1 269 381 8450",
    "sg:postcode":"49048",
    "sg:province":"MI",
    "sg:tags":[
        "shop",
        "consignment"
    ],
    "wof:name":"Hand Me Down Rose",
    "wof:placetype":"venue"
},
  "geometry": {"coordinates":[-85.524728,42.321536],"type":"Point"}
}