{
  "type": "Feature",
  "properties": {
    "iso:country":"US",
    "sg:address":"333 Gilmore Ct",
    "sg:city":"Michigan Center",
    "sg:classifiers":[
        {
            "category":"Freight",
            "type":"Transportation"
        }
    ],
    "sg:phone":"+1 517 764 6926",
    "sg:postcode":"49254",
    "sg:province":"MI",
    "sg:tags":[
        "operator",
        "local",
        "trucking"
    ],
    "wof:name":"William Dixon Trucking",
    "wof:placetype":"venue"
},
  "geometry": {"coordinates":[-84.323042,42.225691],"type":"Point"}
}