{
  "type": "Feature",
  "properties": {
    "iso:country":"US",
    "sg:address":"31165 Sheridan Dr",
    "sg:city":"Franklin",
    "sg:classifiers":[
        {
            "category":"Social Services",
            "subcategory":"Child Care",
            "type":"Services"
        }
    ],
    "sg:phone":"+1 248 642 1238",
    "sg:postcode":"48025",
    "sg:province":"MI",
    "sg:tags":[
        "day"
    ],
    "wof:name":"Kathleen Gerwin",
    "wof:placetype":"venue"
},
  "geometry": {"coordinates":[-83.209993,42.518576],"type":"Point"}
}