{
  "type": "Feature",
  "properties": {
    "iso:country":"US",
    "sg:address":"3060 Butler Rd",
    "sg:city":"Marlette",
    "sg:classifiers":[
        {
            "category":"Professional",
            "subcategory":"Employment Agencies",
            "type":"Services"
        }
    ],
    "sg:phone":"+1 989 635 3159",
    "sg:postcode":"48453",
    "sg:province":"MI",
    "sg:tags":[
        "help",
        "supply"
    ],
    "wof:name":"Mr Lambert Transport",
    "wof:placetype":"venue"
},
  "geometry": {"coordinates":[-83.059892,43.325951],"type":"Point"}
}