{
  "type": "Feature",
  "properties": {
    "iso:country":"US",
    "sg:address":"20275 D Dr S",
    "sg:city":"Marshall",
    "sg:phone":"+1 269 781 7209",
    "sg:postcode":"49068",
    "sg:province":"MI",
    "sg:tags":[
        "farm",
        "field",
        "crop"
    ],
    "wof:name":"Larry Baker",
    "wof:placetype":"venue"
},
  "geometry": {"coordinates":[-84.89404,42.217817],"type":"Point"}
}