{
  "type": "Feature",
  "properties": {
    "iso:country":"US",
    "sg:address":"2891 Crooks Rd",
    "sg:city":"Troy",
    "sg:classifiers":[
        {
            "category":"Food & Beverages",
            "subcategory":"Groceries & Convenience Stores",
            "type":"Retail Goods"
        }
    ],
    "sg:phone":"+1 248 643 7281",
    "sg:postcode":"48084",
    "sg:province":"MI",
    "sg:website":"www.7-eleven.com",
    "wof:name":"Seven Eleven Stores",
    "wof:placetype":"venue"
},
  "geometry": {"coordinates":[-83.167,42.560001],"type":"Point"}
}