{
  "type": "Feature",
  "properties": {
    "iso:country":"US",
    "sg:address":"1161 Gleneagles",
    "sg:city":"Highland",
    "sg:classifiers":[
        {
            "category":"Professional",
            "subcategory":"Management & Consulting",
            "type":"Services"
        }
    ],
    "sg:phone":"+1 248 887 8657",
    "sg:postcode":"48357",
    "sg:province":"MI",
    "sg:tags":[
        "marketing",
        "consultant"
    ],
    "wof:name":"Hess Marketing Associates LLC",
    "wof:placetype":"venue"
},
  "geometry": {"coordinates":[-83.63602899999999,42.631278],"type":"Point"}
}