{
  "type": "Feature",
  "properties": {
    "iso:country":"US",
    "sg:address":"1952 Pine Ridge Ct",
    "sg:city":"Bloomfield Hills",
    "sg:classifiers":[
        {
            "category":"Banks & Credit Unions",
            "subcategory":"Bank",
            "type":"Services"
        }
    ],
    "sg:phone":"+1 248 646 1000",
    "sg:postcode":"48302",
    "sg:province":"MI",
    "sg:tags":[
        "broker",
        "mortgage"
    ],
    "wof:name":"Ark Financial Group Inc",
    "wof:placetype":"venue"
},
  "geometry": {"coordinates":[-83.31910999999999,42.578771],"type":"Point"}
}