{
  "type": "Feature",
  "properties": {
    "iso:country":"US",
    "sg:address":"416 W Ellsworth St",
    "sg:city":"Midland",
    "sg:classifiers":[
        {
            "category":"Personal",
            "type":"Services"
        }
    ],
    "sg:phone":"+1 989 631 4826",
    "sg:postcode":"48640",
    "sg:province":"MI",
    "wof:name":"Totally Tan Salon LLC",
    "wof:placetype":"venue"
},
  "geometry": {"coordinates":[-84.24697999999999,43.616725],"type":"Point"}
}