{
  "type": "Feature",
  "properties": {
    "iso:country":"US",
    "sg:address":"905 Crescent Dr",
    "sg:city":"Dearborn",
    "sg:classifiers":[
        {
            "category":"Professional",
            "subcategory":"Management & Consulting",
            "type":"Services"
        }
    ],
    "sg:phone":"+1 313 278 4009",
    "sg:postcode":"48124",
    "sg:province":"MI",
    "sg:tags":[
        "business"
    ],
    "wof:name":"Gonzalez Consulting Inc",
    "wof:placetype":"venue"
},
  "geometry": {"coordinates":[-83.284442,42.305825],"type":"Point"}
}