{
  "type": "Feature",
  "properties": {
    "iso:country":"US",
    "sg:address":"504 E Spruce St",
    "sg:city":"Sault Ste Marie",
    "sg:classifiers":[
        {
            "category":"Shopping",
            "subcategory":"Gifts & Souvenirs",
            "type":"Retail Goods"
        }
    ],
    "sg:phone":"+1 906 632 7945",
    "sg:postcode":"49783",
    "sg:province":"MI",
    "sg:tags":[
        "party",
        "supply"
    ],
    "wof:name":"Lock City Party Store",
    "wof:placetype":"venue"
},
  "geometry": {"coordinates":[-84.339106,46.494683],"type":"Point"}
}