{
  "type": "Feature",
  "properties": {
    "iso:country":"US",
    "sg:address":"363 E Grand Blanc Rd",
    "sg:city":"Grand Blanc",
    "sg:classifiers":[
        {
            "category":"Personal",
            "subcategory":"Beauty Salon",
            "type":"Services"
        }
    ],
    "sg:phone":"+1 810 695 4020",
    "sg:postcode":"48439",
    "sg:province":"MI",
    "wof:name":"Styling Post",
    "wof:placetype":"venue"
},
  "geometry": {"coordinates":[-83.632831,42.925429],"type":"Point"}
}