{
  "type": "Feature",
  "properties": {
    "iso:country":"US",
    "sg:address":"111 W 14th St",
    "sg:city":"Traverse City",
    "sg:classifiers":[
        {
            "category":"Building & Trades",
            "subcategory":"Construction",
            "type":"Services"
        }
    ],
    "sg:phone":"+1 231 946 6807",
    "sg:postcode":"49684",
    "sg:province":"MI",
    "sg:tags":[
        "siding",
        "contractor"
    ],
    "wof:name":"Ray's Siding",
    "wof:placetype":"venue"
},
  "geometry": {"coordinates":[-85.624583,44.751592],"type":"Point"}
}