{
  "type": "Feature",
  "properties": {
    "iso:country":"US",
    "sg:address":"10280 Dice Rd",
    "sg:city":"Freeland",
    "sg:classifiers":[
        {
            "category":"Building & Trades",
            "subcategory":"Construction",
            "type":"Services"
        }
    ],
    "sg:phone":"+1 989 781 2466",
    "sg:postcode":"48623",
    "sg:province":"MI",
    "sg:tags":[
        "house"
    ],
    "wof:name":"Brenske Construction LLC",
    "wof:placetype":"venue"
},
  "geometry": {"coordinates":[-84.11762899999999,43.466733],"type":"Point"}
}