{
  "type": "Feature",
  "properties": {
    "iso:country":"US",
    "sg:address":"27200 Lahser Rd",
    "sg:city":"Southfield",
    "sg:classifiers":[
        {
            "category":"Professional",
            "subcategory":"Lawyer & Legal Services",
            "type":"Services"
        }
    ],
    "sg:phone":"+1 248 357 2900",
    "sg:postcode":"48034",
    "sg:province":"MI",
    "wof:name":"Norman W Stern Attorney",
    "wof:placetype":"venue"
},
  "geometry": {"coordinates":[-83.261352,42.488391],"type":"Point"}
}