{
  "type": "Feature",
  "properties": {
    "iso:country":"US",
    "sg:address":"37085 Grand River Ave",
    "sg:city":"Farmington",
    "sg:classifiers":[
        {
            "category":"Personal",
            "subcategory":"Barber",
            "type":"Services"
        }
    ],
    "sg:phone":"+1 248 471 0880",
    "sg:postcode":"48335",
    "sg:province":"MI",
    "sg:website":"www.borics.com",
    "wof:name":"Borics Haircare For Everyone",
    "wof:placetype":"venue"
},
  "geometry": {"coordinates":[-83.414001,42.468498],"type":"Point"}
}