{
  "type": "Feature",
  "properties": {
    "iso:country":"US",
    "sg:address":"2951 Thornhills Ave SE",
    "sg:city":"Grand Rapids",
    "sg:classifiers":[
        {
            "category":"Building & Trades",
            "subcategory":"Equipment Rental",
            "type":"Services"
        }
    ],
    "sg:phone":"+1 616 949 2853",
    "sg:postcode":"49546",
    "sg:province":"MI",
    "wof:name":"Let Leasing Inc",
    "wof:placetype":"venue"
},
  "geometry": {"coordinates":[-85.50819199999999,42.910602],"type":"Point"}
}