{
  "type": "Feature",
  "properties": {
    "iso:country":"US",
    "sg:address":"2998 State Hwy 65",
    "sg:city":"Whittemore",
    "sg:classifiers":[
        {
            "category":"Autos & Motor Vehicles",
            "subcategory":"Automobile Sales",
            "type":"Retail Goods"
        }
    ],
    "sg:phone":"+1 989 756 2147",
    "sg:postcode":"48770",
    "sg:province":"MI",
    "sg:tags":[
        "car",
        "dealer"
    ],
    "wof:name":"Spencer Auto Parts",
    "wof:placetype":"venue"
},
  "geometry": {"coordinates":[-83.803344,44.190563],"type":"Point"}
}