{
  "type": "Feature",
  "properties": {
    "iso:country":"US",
    "sg:address":"3498 Indian Lake Rd",
    "sg:city":"National City",
    "sg:classifiers":[
        {
            "category":"Real Estate",
            "subcategory":"Real Estate Agent",
            "type":"Services"
        }
    ],
    "sg:phone":"+1 989 469 2055",
    "sg:postcode":"48748",
    "sg:province":"MI",
    "sg:website":"www.all-northern-michigan.com",
    "wof:name":"Best Choice Realty Inc",
    "wof:placetype":"venue"
},
  "geometry": {"coordinates":[-83.66153,44.334312],"type":"Point"}
}