{
  "type": "Feature",
  "properties": {
    "iso:country":"US",
    "sg:address":"18252 N Laurel Park Dr",
    "sg:city":"Livonia",
    "sg:classifiers":[
        {
            "category":"Manufacturing",
            "subcategory":"Motor Vehicles & Parts",
            "type":"Manufacturing & Wholesale Goods"
        }
    ],
    "sg:phone":"+1 734 853 6844",
    "sg:postcode":"48154",
    "sg:province":"MI",
    "sg:tags":[
        "automotive",
        "component",
        "mfg"
    ],
    "wof:name":"TRW Automotive Inc",
    "wof:placetype":"venue"
},
  "geometry": {"coordinates":[-83.417957,42.415921],"type":"Point"}
}