{
  "type": "Feature",
  "properties": {
    "iso:country":"US",
    "sg:address":"17108 Mack Ave Ste 3",
    "sg:city":"Grosse Pointe",
    "sg:classifiers":[
        {
            "category":"Real Estate",
            "subcategory":"Real Estate Services",
            "type":"Services"
        }
    ],
    "sg:phone":"+1 313 640 1788",
    "sg:postcode":"48230",
    "sg:province":"MI",
    "sg:tags":[
        "management",
        "property"
    ],
    "wof:name":"Southeastern Property Management Llc",
    "wof:placetype":"venue"
},
  "geometry": {"coordinates":[-82.923203,42.383301],"type":"Point"}
}