{
  "type": "Feature",
  "properties": {
    "iso:country":"US",
    "sg:address":"7140 Highland Rd",
    "sg:city":"Waterford",
    "sg:classifiers":[
        {
            "category":"Personal",
            "subcategory":"Beauty Salon",
            "type":"Services"
        }
    ],
    "sg:phone":"+1 248 666 4247",
    "sg:postcode":"48327",
    "sg:province":"MI",
    "wof:name":"Headquarters Salon",
    "wof:placetype":"venue"
},
  "geometry": {"coordinates":[-83.422892,42.659479],"type":"Point"}
}