{
  "type": "Feature",
  "properties": {
    "iso:country":"US",
    "sg:address":"809 Mills Ave",
    "sg:city":"Muskegon",
    "sg:classifiers":[
        {
            "category":"Social Services",
            "type":"Services"
        }
    ],
    "sg:phone":"+1 231 744 5787",
    "sg:postcode":"49445",
    "sg:province":"MI",
    "sg:tags":[
        "counselor",
        "marriage",
        "family"
    ],
    "wof:name":"J Daniel Collison PHD",
    "wof:placetype":"venue"
},
  "geometry": {"coordinates":[-86.276134,43.251336],"type":"Point"}
}