{
  "type": "Feature",
  "properties": {
    "iso:country":"US",
    "sg:address":"14253 Greenfield Rd",
    "sg:city":"Detroit",
    "sg:classifiers":[
        {
            "category":"Restaurant",
            "type":"Food & Drink"
        }
    ],
    "sg:menulink":"http://www.allmenus.com/mi/detroit/247318-olgas-coney-island/menu/",
    "sg:phone":"+1 313 416 2661",
    "sg:postcode":"48227",
    "sg:province":"MI",
    "sg:tags":[
        "american",
        "diner"
    ],
    "wof:name":"Olga's Coney Island",
    "wof:placetype":"venue"
},
  "geometry": {"coordinates":[-83.198311,42.391168],"type":"Point"}
}