{
  "type": "Feature",
  "properties": {
    "iso:country":"US",
    "sg:address":"7318 Haggerty Rd",
    "sg:city":"West Bloomfield",
    "sg:classifiers":[
        {
            "category":"Freight",
            "type":"Transportation"
        },
        {
            "category":"Professional",
            "subcategory":"Printing & Photocopies",
            "type":"Services"
        }
    ],
    "sg:phone":"+1 248 788 3987",
    "sg:postcode":"48322",
    "sg:province":"MI",
    "sg:tags":[
        "shipping"
    ],
    "sg:website":"www.fedex.com/us/office/",
    "wof:name":"FedEx Office Print & Ship Center",
    "wof:placetype":"venue"
},
  "geometry": {"coordinates":[-83.437607,42.540422],"type":"Point"}
}