{
  "type": "Feature",
  "properties": {
    "iso:country":"US",
    "sg:address":"6990 County Farm Rd",
    "sg:city":"Lexington",
    "sg:classifiers":[
        {
            "category":"Retail",
            "subcategory":"Repair Shop",
            "type":"Services"
        }
    ],
    "sg:phone":"+1 810 359 7420",
    "sg:postcode":"48450",
    "sg:province":"MI",
    "wof:name":"Gregs Maintenance & Repair",
    "wof:placetype":"venue"
},
  "geometry": {"coordinates":[-82.54989500000001,43.310776],"type":"Point"}
}