{
  "type": "Feature",
  "properties": {
    "iso:country":"US",
    "sg:address":"58649 Co Rd 380",
    "sg:city":"Bangor",
    "sg:classifiers":[
        {
            "category":"Professional",
            "subcategory":"Employment Agencies",
            "type":"Services"
        }
    ],
    "sg:phone":"+1 269 427 0081",
    "sg:postcode":"49013",
    "sg:province":"MI",
    "wof:name":"Network Nursing Service",
    "wof:placetype":"venue"
},
  "geometry": {"coordinates":[-86.11435899999999,42.346566],"type":"Point"}
}