{
  "type": "Feature",
  "properties": {
    "iso:country":"US",
    "sg:address":"24 Mill Rd",
    "sg:city":"Shelby Twp",
    "sg:classifiers":[
        {
            "category":"Insurance",
            "subcategory":"Insurance Agent",
            "type":"Services"
        }
    ],
    "sg:phone":"+1 586 731 2222",
    "sg:postcode":"48386",
    "sg:province":"MI",
    "sg:website":"www.wod-clan.com",
    "wof:name":"State Farm Insurance",
    "wof:placetype":"venue"
},
  "geometry": {"coordinates":[-83.487593,42.639051],"type":"Point"}
}