{
  "type": "Feature",
  "properties": {
    "iso:country":"US",
    "sg:address":"215 W Summit St",
    "sg:city":"Chelsea",
    "sg:classifiers":[
        {
            "category":"Communications",
            "subcategory":"Film & Video Production",
            "type":"Services"
        },
        {
            "category":"Professional",
            "subcategory":"Art Services",
            "type":"Services"
        }
    ],
    "sg:phone":"+1 734 433 5440",
    "sg:postcode":"48118",
    "sg:province":"MI",
    "sg:tags":[
        "creative",
        "audio-visual"
    ],
    "wof:name":"City Annimation",
    "wof:placetype":"venue"
},
  "geometry": {"coordinates":[-84.022417,42.315127],"type":"Point"}
}