{
  "type": "Feature",
  "properties": {
    "iso:country":"US",
    "sg:address":"2510 Juhl Rd",
    "sg:city":"Marlette",
    "sg:classifiers":[
        {
            "category":"Organizations",
            "subcategory":"Religious Organization",
            "type":"Services"
        }
    ],
    "sg:phone":"+1 989 635 3055",
    "sg:postcode":"48453",
    "sg:province":"MI",
    "sg:tags":[
        "church"
    ],
    "wof:name":"Hope Lutheran Church-E L C A",
    "wof:placetype":"venue"
},
  "geometry": {"coordinates":[-82.94557399999999,43.344906],"type":"Point"}
}