{
  "type": "Feature",
  "properties": {
    "iso:country":"US",
    "sg:address":"184 Streamview Dr",
    "sg:city":"Troy",
    "sg:classifiers":[
        {
            "category":"Professional",
            "subcategory":"Accounting & Tax Preparation",
            "type":"Services"
        }
    ],
    "sg:phone":"+1 248 689 8863",
    "sg:postcode":"48085",
    "sg:province":"MI",
    "sg:tags":[
        "accountant"
    ],
    "wof:name":"Schraeger Richard E CPA",
    "wof:placetype":"venue"
},
  "geometry": {"coordinates":[-83.14510300000001,42.5858],"type":"Point"}
}