{
  "type": "Feature",
  "properties": {
    "iso:country":"US",
    "sg:address":"8572 Silver Lake Rd",
    "sg:city":"Linden",
    "sg:classifiers":[
        {
            "category":"Food & Beverages",
            "subcategory":"Specialty",
            "type":"Retail Goods"
        }
    ],
    "sg:phone":"+1 810 735 9192",
    "sg:postcode":"48451",
    "sg:province":"MI",
    "sg:tags":[
        "health",
        "diet"
    ],
    "wof:name":"Westwind Milling Co",
    "wof:placetype":"venue"
},
  "geometry": {"coordinates":[-83.83567600000001,42.796203],"type":"Point"}
}