{
  "type": "Feature",
  "properties": {
    "iso:country":"US",
    "sg:address":"4016 Custer Ave",
    "sg:city":"Royal Oak",
    "sg:classifiers":[
        {
            "category":"Social Services",
            "type":"Services"
        }
    ],
    "sg:phone":"+1 248 435 3365",
    "sg:postcode":"48073",
    "sg:province":"MI",
    "sg:tags":[
        "senior",
        "citizen"
    ],
    "wof:name":"Friendly Senior Services Inc",
    "wof:placetype":"venue"
},
  "geometry": {"coordinates":[-83.152568,42.525112],"type":"Point"}
}