{
  "type": "Feature",
  "properties": {
    "iso:country":"US",
    "sg:address":"865 S Coleman Rd",
    "sg:city":"Shepherd",
    "sg:classifiers":[
        {
            "category":"Retail",
            "subcategory":"Auto Repair",
            "type":"Services"
        }
    ],
    "sg:phone":"+1 989 773 3003",
    "sg:postcode":"48883",
    "sg:province":"MI",
    "sg:tags":[
        "repairing",
        "automobile"
    ],
    "wof:name":"Affordable Auto Repair",
    "wof:placetype":"venue"
},
  "geometry": {"coordinates":[-84.58818100000001,43.585509],"type":"Point"}
}