{
  "type": "Feature",
  "properties": {
    "iso:country":"US",
    "sg:address":"1975 Chancery Dr",
    "sg:city":"Troy",
    "sg:classifiers":[
        {
            "category":"Home & Garden",
            "subcategory":"Building Materials",
            "type":"Retail Goods"
        }
    ],
    "sg:phone":"+1 248 879 7134",
    "sg:postcode":"48085",
    "sg:province":"MI",
    "sg:tags":[
        "windows"
    ],
    "wof:name":"Superior Windows & Doors Inc",
    "wof:placetype":"venue"
},
  "geometry": {"coordinates":[-83.11245599999999,42.619898],"type":"Point"}
}