{
  "type": "Feature",
  "properties": {
    "iso:country":"US",
    "sg:address":"5090 N Saginaw St",
    "sg:city":"Flint",
    "sg:classifiers":[
        {
            "category":"Building & Trades",
            "subcategory":"Construction",
            "type":"Services"
        }
    ],
    "sg:phone":"+1 810 789 5090",
    "sg:postcode":"48505",
    "sg:province":"MI",
    "sg:tags":[
        "home",
        "improvement"
    ],
    "wof:name":"New Century Builders",
    "wof:placetype":"venue"
},
  "geometry": {"coordinates":[-83.69378500000001,43.059765],"type":"Point"}
}