{
  "type": "Feature",
  "properties": {
    "iso:country":"US",
    "sg:address":"4621 135th Ave",
    "sg:city":"Hamilton",
    "sg:classifiers":[
        {
            "category":"Autos & Motor Vehicles",
            "subcategory":"Automobile Sales",
            "type":"Retail Goods"
        }
    ],
    "sg:phone":"+1 269 751 1090",
    "sg:postcode":"49419",
    "sg:province":"MI",
    "sg:tags":[
        "car",
        "dealer"
    ],
    "wof:name":"Hamilton Chevrolet",
    "wof:placetype":"venue"
},
  "geometry": {"coordinates":[-85.999026,42.67376],"type":"Point"}
}