{
  "type": "Feature",
  "properties": {
    "iso:country":"US",
    "sg:address":"2406 Victoria Ave",
    "sg:city":"Ann Arbor",
    "sg:classifiers":[
        {
            "category":"Professional",
            "subcategory":"Secretarial Services",
            "type":"Services"
        }
    ],
    "sg:phone":"+1 734 662 5034",
    "sg:postcode":"48104",
    "sg:province":"MI",
    "sg:tags":[
        "reporting"
    ],
    "wof:name":"Ken Stockton",
    "wof:placetype":"venue"
},
  "geometry": {"coordinates":[-83.72013099999999,42.254507],"type":"Point"}
}