{
  "type": "Feature",
  "properties": {
    "iso:country":"US",
    "sg:address":"105 E Saginaw Hwy",
    "sg:city":"Grand Ledge",
    "sg:classifiers":[
        {
            "category":"Professional",
            "type":"Services"
        }
    ],
    "sg:phone":"+1 517 622 8551",
    "sg:postcode":"48837",
    "sg:province":"MI",
    "sg:tags":[
        "establishment"
    ],
    "wof:name":"Natural Systems Inc",
    "wof:placetype":"venue"
},
  "geometry": {"coordinates":[-84.74866400000001,42.740934],"type":"Point"}
}