{
  "type": "Feature",
  "properties": {
    "iso:country":"US",
    "sg:address":"4359 N Jebavy Dr",
    "sg:city":"Ludington",
    "sg:classifiers":[
        {
            "category":"Personal",
            "type":"Services"
        }
    ],
    "sg:phone":"+1 231 843 4832",
    "sg:postcode":"49431",
    "sg:province":"MI",
    "wof:name":"Faith Ministries",
    "wof:placetype":"venue"
},
  "geometry": {"coordinates":[-86.419804,44.041394],"type":"Point"}
}