{
  "type": "Feature",
  "properties": {
    "iso:country":"US",
    "sg:address":"15171 N Sheldon Rd",
    "sg:city":"Plymouth",
    "sg:classifiers":[
        {
            "category":"Coffee & Tea",
            "type":"Food & Drink"
        },
        {
            "category":"Cafe",
            "type":"Food & Drink"
        }
    ],
    "sg:menulink":"http://www.allmenus.com/mi/plymouth/241181-wild-bean-cafe/menu/",
    "sg:phone":"+1 734 259 0000",
    "sg:postcode":"48170",
    "sg:province":"MI",
    "sg:tags":[
        "soup",
        "american",
        "salad"
    ],
    "wof:name":"Wild Bean Cafe",
    "wof:placetype":"venue"
},
  "geometry": {"coordinates":[-83.481522,42.394502],"type":"Point"}
}