{
  "type": "Feature",
  "properties": {
    "iso:country":"US",
    "sg:address":"9301 Pearl Beach Blvd",
    "sg:city":"Algonac",
    "sg:classifiers":[
        {
            "category":"Retail",
            "subcategory":"Animal Services",
            "type":"Services"
        }
    ],
    "sg:phone":"+1 810 794 0961",
    "sg:postcode":"48001",
    "sg:province":"MI",
    "wof:name":"Marshwood Acre Dogues",
    "wof:placetype":"venue"
},
  "geometry": {"coordinates":[-82.59613899999999,42.632695],"type":"Point"}
}