{
  "type": "Feature",
  "properties": {
    "iso:country":"US",
    "sg:address":"522 Pearl St",
    "sg:city":"Charlotte",
    "sg:classifiers":[
        {
            "category":"Professional",
            "subcategory":"Accounting & Tax Preparation",
            "type":"Services"
        }
    ],
    "sg:phone":"+1 517 541 3858",
    "sg:postcode":"48813",
    "sg:province":"MI",
    "sg:tags":[
        "bookkeeping",
        "general"
    ],
    "wof:name":"Gretzner's Bookkeeping",
    "wof:placetype":"venue"
},
  "geometry": {"coordinates":[-84.840822,42.556137],"type":"Point"}
}