{
  "type": "Feature",
  "properties": {
    "iso:country":"US",
    "sg:address":"11345 Caberfae Ave",
    "sg:city":"Allendale",
    "sg:classifiers":[
        {
            "category":"Professional",
            "subcategory":"Computer Services",
            "type":"Services"
        }
    ],
    "sg:phone":"+1 616 895 5947",
    "sg:postcode":"49401",
    "sg:province":"MI",
    "sg:tags":[
        "prepackaged",
        "software"
    ],
    "wof:name":"R Datalogic-G",
    "wof:placetype":"venue"
},
  "geometry": {"coordinates":[-85.915099,42.974781],"type":"Point"}
}