{
  "type": "Feature",
  "properties": {
    "iso:country":"US",
    "sg:address":"3473 W US Hwy 10",
    "sg:city":"Ludington",
    "sg:classifiers":[
        {
            "category":"Retail",
            "subcategory":"Auto Repair",
            "type":"Services"
        }
    ],
    "sg:phone":"+1 231 845 6202",
    "sg:postcode":"49431",
    "sg:province":"MI",
    "sg:tags":[
        "repairing",
        "automobile"
    ],
    "wof:name":"Marek Auto Parts & Svc",
    "wof:placetype":"venue"
},
  "geometry": {"coordinates":[-86.354844,43.955778],"type":"Point"}
}