{
  "type": "Feature",
  "properties": {
    "iso:country":"US",
    "sg:address":"7435 Orchard Lake Rd",
    "sg:city":"West Bloomfield",
    "sg:classifiers":[
        {
            "category":"Deli",
            "type":"Food & Drink"
        }
    ],
    "sg:phone":"+1 248 538 6700",
    "sg:postcode":"48322",
    "sg:province":"MI",
    "wof:name":"New York International Foods",
    "wof:placetype":"venue"
},
  "geometry": {"coordinates":[-83.35990099999999,42.528702],"type":"Point"}
}