{
  "type": "Feature",
  "properties": {
    "iso:country":"US",
    "sg:address":"2500 Crescent Dr",
    "sg:city":"Kalamazoo",
    "sg:classifiers":[
        {
            "category":"Professional",
            "subcategory":"Management & Consulting",
            "type":"Services"
        }
    ],
    "sg:phone":"+1 269 384 2247",
    "sg:postcode":"49001",
    "sg:province":"MI",
    "sg:tags":[
        "consultant",
        "educational"
    ],
    "wof:name":"Anderson & Assoc",
    "wof:placetype":"venue"
},
  "geometry": {"coordinates":[-85.58191100000001,42.266197],"type":"Point"}
}