{
  "type": "Feature",
  "properties": {
    "iso:country":"US",
    "sg:address":"200 S Wenona St",
    "sg:city":"Bay City",
    "sg:classifiers":[
        {
            "category":"Health Services",
            "subcategory":"Clinic",
            "type":"Services"
        }
    ],
    "sg:phone":"+1 989 891 9163",
    "sg:postcode":"48706",
    "sg:province":"MI",
    "sg:tags":[
        "agency",
        "welfare"
    ],
    "wof:name":"Covenant Healthcare",
    "wof:placetype":"venue"
},
  "geometry": {"coordinates":[-83.90524000000001,43.599973],"type":"Point"}
}