{
  "type": "Feature",
  "properties": {
    "iso:country":"US",
    "sg:address":"23911 Allen Rd",
    "sg:city":"Trenton",
    "sg:classifiers":[
        {
            "category":"Sports & Exercise",
            "subcategory":"Ice Rink",
            "type":"Entertainment"
        }
    ],
    "sg:phone":"+1 734 671 0220",
    "sg:postcode":"48183",
    "sg:province":"MI",
    "sg:tags":[
        "skating"
    ],
    "wof:name":"Skateland of Woodhaven",
    "wof:placetype":"venue"
},
  "geometry": {"coordinates":[-83.2257,42.134102],"type":"Point"}
}