{
  "type": "Feature",
  "properties": {
    "iso:country":"US",
    "sg:address":"352 Romeo Rd",
    "sg:city":"Rochester",
    "sg:classifiers":[
        {
            "category":"Professional",
            "subcategory":"Business Services",
            "type":"Services"
        }
    ],
    "sg:phone":"+1 248 656 3873",
    "sg:postcode":"48307",
    "sg:province":"MI",
    "wof:name":"Marcotte Financial Relations",
    "wof:placetype":"venue"
},
  "geometry": {"coordinates":[-83.125799,42.6888],"type":"Point"}
}