{
  "type": "Feature",
  "properties": {
    "iso:country":"US",
    "sg:address":"14163 Lakeside Blvd N",
    "sg:city":"Shelby Township",
    "sg:classifiers":[
        {
            "category":"Communications",
            "subcategory":"Newspaper",
            "type":"Services"
        }
    ],
    "sg:phone":"+1 586 566 9388",
    "sg:postcode":"48315",
    "sg:province":"MI",
    "sg:tags":[
        "print",
        "medium"
    ],
    "wof:name":"Psi Publishing Inc",
    "wof:placetype":"venue"
},
  "geometry": {"coordinates":[-82.98637100000001,42.631977],"type":"Point"}
}