{
  "type": "Feature",
  "properties": {
    "iso:country":"US",
    "sg:address":"1027 Church St",
    "sg:city":"Flint",
    "sg:classifiers":[
        {
            "category":"Utilities",
            "type":"Services"
        }
    ],
    "sg:phone":"+1 810 249 4638",
    "sg:postcode":"48502",
    "sg:province":"MI",
    "sg:tags":[
        "provider",
        "internet"
    ],
    "wof:name":"Blc Links",
    "wof:placetype":"venue"
},
  "geometry": {"coordinates":[-83.68907299999999,43.009989],"type":"Point"}
}