{
  "type": "Feature",
  "properties": {
    "iso:country":"US",
    "sg:address":"3126 Jefferson Ave",
    "sg:city":"Midland",
    "sg:classifiers":[
        {
            "category":"Sports & Exercise",
            "subcategory":"Gym",
            "type":"Entertainment"
        }
    ],
    "sg:phone":"+1 989 631 3868",
    "sg:postcode":"48640",
    "sg:province":"MI",
    "sg:tags":[
        "club",
        "health",
        "studio",
        "gymnasium"
    ],
    "wof:name":"Blitz 20 Minute Total Fitness",
    "wof:placetype":"venue"
},
  "geometry": {"coordinates":[-84.22685799999999,43.627432],"type":"Point"}
}