{
  "type": "Feature",
  "properties": {
    "iso:country":"US",
    "sg:address":"115 S Dexter St",
    "sg:city":"Ionia",
    "sg:classifiers":[
        {
            "category":"Autos & Motor Vehicles",
            "subcategory":"Auto Supplies",
            "type":"Retail Goods"
        }
    ],
    "sg:phone":"+1 616 522 9222",
    "sg:postcode":"48846",
    "sg:province":"MI",
    "sg:tags":[
        "automobile",
        "parts"
    ],
    "wof:name":"Autozone",
    "wof:placetype":"venue"
},
  "geometry": {"coordinates":[-85.07026399999999,42.982059],"type":"Point"}
}