{
  "type": "Feature",
  "properties": {
    "iso:country":"US",
    "sg:address":"45276 Brownell St",
    "sg:city":"Utica",
    "sg:classifiers":[
        {
            "category":"Retail",
            "subcategory":"Portrait Studio",
            "type":"Services"
        }
    ],
    "sg:phone":"+1 586 731 4410",
    "sg:postcode":"48317",
    "sg:province":"MI",
    "sg:tags":[
        "photo"
    ],
    "wof:name":"Gene & Ann Kay Photographers",
    "wof:placetype":"venue"
},
  "geometry": {"coordinates":[-83.035203,42.627884],"type":"Point"}
}