{
  "type": "Feature",
  "properties": {
    "iso:country":"US",
    "sg:address":"5400 Mary Ct",
    "sg:city":"Saginaw",
    "sg:classifiers":[
        {
            "category":"Wholesale",
            "subcategory":"Non-durable Goods",
            "type":"Manufacturing & Wholesale Goods"
        }
    ],
    "sg:phone":"+1 989 792 5600",
    "sg:postcode":"48603",
    "sg:province":"MI",
    "wof:name":"Fields Advertising",
    "wof:placetype":"venue"
},
  "geometry": {"coordinates":[-84.023787,43.440116],"type":"Point"}
}