{
  "type": "Feature",
  "properties": {
    "iso:country":"US",
    "sg:address":"10622 W Warren Ave",
    "sg:city":"Dearborn",
    "sg:classifiers":[
        {
            "category":"Bakery",
            "type":"Food & Drink"
        }
    ],
    "sg:phone":"+1 313 584 4636",
    "sg:postcode":"48126",
    "sg:province":"MI",
    "wof:name":"The Princess Bakery",
    "wof:placetype":"venue"
},
  "geometry": {"coordinates":[-83.16480300000001,42.344398],"type":"Point"}
}