{
  "type": "Feature",
  "properties": {
    "iso:country":"US",
    "sg:address":"46390 Dequindre Rd",
    "sg:city":"Shelby Township",
    "sg:classifiers":[
        {
            "category":"Personal",
            "type":"Services"
        }
    ],
    "sg:phone":"+1 586 737 2828",
    "sg:postcode":"48317",
    "sg:province":"MI",
    "sg:tags":[
        "towing"
    ],
    "wof:name":"A G Towing",
    "wof:placetype":"venue"
},
  "geometry": {"coordinates":[-83.091797,42.633999],"type":"Point"}
}