{
  "type": "Feature",
  "properties": {
    "iso:country":"US",
    "sg:address":"7905 Pere Marquette Rd",
    "sg:city":"Clare",
    "sg:classifiers":[
        {
            "category":"Autos & Motor Vehicles",
            "subcategory":"Motorcycle Sales",
            "type":"Retail Goods"
        }
    ],
    "sg:phone":"+1 989 386 2280",
    "sg:postcode":"48617",
    "sg:province":"MI",
    "sg:tags":[
        "scooter"
    ],
    "wof:name":"Bolles Sport Ctr",
    "wof:placetype":"venue"
},
  "geometry": {"coordinates":[-84.692734,43.80054],"type":"Point"}
}