{
  "type": "Feature",
  "properties": {
    "iso:country":"US",
    "sg:address":"4231 Portage St",
    "sg:city":"Kalamazoo",
    "sg:classifiers":[
        {
            "category":"Home & Garden",
            "subcategory":"Home Furnishings",
            "type":"Retail Goods"
        }
    ],
    "sg:phone":"+1 269 345 0967",
    "sg:postcode":"49001",
    "sg:province":"MI",
    "sg:tags":[
        "lighting",
        "fixture"
    ],
    "sg:website":"www.lymanlighting.com",
    "wof:name":"Lyman Lamps & Accessories",
    "wof:placetype":"venue"
},
  "geometry": {"coordinates":[-85.56017,42.248474],"type":"Point"}
}