{
  "type": "Feature",
  "properties": {
    "iso:country":"US",
    "sg:address":"317 N Rowe St",
    "sg:city":"Ludington",
    "sg:classifiers":[
        {
            "category":"Health Services",
            "subcategory":"Doctor",
            "type":"Services"
        }
    ],
    "sg:phone":"+1 231 845 1235",
    "sg:postcode":"49431",
    "sg:province":"MI",
    "sg:tags":[
        "medical",
        "imaging"
    ],
    "wof:name":"Pere Marquette Medical Imaging",
    "wof:placetype":"venue"
},
  "geometry": {"coordinates":[-86.44515,43.959389],"type":"Point"}
}