{
  "type": "Feature",
  "properties": {
    "iso:country":"US",
    "sg:address":"880 S Saginaw St",
    "sg:city":"Lapeer",
    "sg:classifiers":[
        {
            "category":"Recreation",
            "type":"Entertainment"
        }
    ],
    "sg:phone":"+1 810 664 4431",
    "sg:postcode":"48446",
    "sg:province":"MI",
    "sg:tags":[
        "executive"
    ],
    "wof:name":"Lapeer Recreation Center",
    "wof:placetype":"venue"
},
  "geometry": {"coordinates":[-83.30391400000001,43.039202],"type":"Point"}
}