{
  "type": "Feature",
  "properties": {
    "iso:country":"US",
    "sg:address":"2458 N Center Rd",
    "sg:city":"Burton",
    "sg:classifiers":[
        {
            "category":"Building & Trades",
            "subcategory":"Plumbing",
            "type":"Services"
        }
    ],
    "sg:phone":"+1 810 736 0660",
    "sg:postcode":"48509",
    "sg:province":"MI",
    "wof:name":"American Sewer Cleaners",
    "wof:placetype":"venue"
},
  "geometry": {"coordinates":[-83.63539900000001,43.038399],"type":"Point"}
}