{
  "type": "Feature",
  "properties": {
    "iso:country":"US",
    "sg:address":"177 M 66 N",
    "sg:city":"Charlevoix",
    "sg:classifiers":[
        {
            "category":"Professional",
            "subcategory":"Accounting & Tax Preparation",
            "type":"Services"
        }
    ],
    "sg:phone":"+1 231 547 0660",
    "sg:postcode":"49720",
    "sg:province":"MI",
    "sg:tags":[
        "return",
        "filing"
    ],
    "wof:name":"H & R Block Tax Svc",
    "wof:placetype":"venue"
},
  "geometry": {"coordinates":[-85.171171,45.211854],"type":"Point"}
}