{
  "type": "Feature",
  "properties": {
    "iso:country":"US",
    "sg:address":"1160 James Savage Rd",
    "sg:city":"Midland",
    "sg:classifiers":[
        {
            "category":"Professional",
            "subcategory":"Computer Services",
            "type":"Services"
        }
    ],
    "sg:phone":"+1 989 631 8710",
    "sg:postcode":"48640",
    "sg:province":"MI",
    "sg:tags":[
        "equipment",
        "datum"
    ],
    "wof:name":"Vucom Data Services",
    "wof:placetype":"venue"
},
  "geometry": {"coordinates":[-84.21569700000001,43.610963],"type":"Point"}
}