{
  "type": "Feature",
  "properties": {
    "iso:country":"US",
    "sg:address":"8425 Arlis St",
    "sg:city":"Commerce Twp",
    "sg:classifiers":[
        {
            "category":"Social Services",
            "type":"Services"
        }
    ],
    "sg:phone":"+1 248 366 6747",
    "sg:postcode":"48382",
    "sg:province":"MI",
    "sg:tags":[
        "counselor",
        "marriage",
        "family"
    ],
    "wof:name":"Joanne O'Rourke",
    "wof:placetype":"venue"
},
  "geometry": {"coordinates":[-83.44915399999999,42.587872],"type":"Point"}
}