{
  "type": "Feature",
  "properties": {
    "iso:country":"US",
    "sg:address":"424 W Grand River Ave",
    "sg:city":"Brighton",
    "sg:classifiers":[
        {
            "category":"Insurance",
            "subcategory":"Insurance Agent",
            "type":"Services"
        }
    ],
    "sg:phone":"+1 810 229 6158",
    "sg:postcode":"48116",
    "sg:province":"MI",
    "wof:name":"Shultz Agency",
    "wof:placetype":"venue"
},
  "geometry": {"coordinates":[-83.78248600000001,42.533567],"type":"Point"}
}