{
  "type": "Feature",
  "properties": {
    "iso:country":"US",
    "sg:address":"4535 Riggsville Rd",
    "sg:city":"Cheboygan",
    "sg:classifiers":[
        {
            "category":"Farming",
            "subcategory":"Livestock Farm",
            "type":"Manufacturing & Wholesale Goods"
        }
    ],
    "sg:phone":"+1 231 627 7087",
    "sg:postcode":"49721",
    "sg:province":"MI",
    "sg:tags":[
        "animal",
        "general"
    ],
    "wof:name":"Plesant View Elk Ranch",
    "wof:placetype":"venue"
},
  "geometry": {"coordinates":[-84.57708700000001,45.587247],"type":"Point"}
}