{
  "type": "Feature",
  "properties": {
    "iso:country":"US",
    "sg:address":"42245 Ann Arbor Rd E",
    "sg:city":"Plymouth",
    "sg:classifiers":[
        {
            "category":"Building & Trades",
            "subcategory":"Cleaning & Sanitation",
            "type":"Services"
        }
    ],
    "sg:phone":"+1 734 254 9070",
    "sg:postcode":"48170",
    "sg:province":"MI",
    "sg:tags":[
        "carpet"
    ],
    "wof:name":"Corrective Cleaning Service",
    "wof:placetype":"venue"
},
  "geometry": {"coordinates":[-83.458099,42.359001],"type":"Point"}
}