{
  "type": "Feature",
  "properties": {
    "iso:country":"US",
    "sg:address":"24487 Gratiot Ave",
    "sg:city":"Eastpointe",
    "sg:classifiers":[
        {
            "category":"Building & Trades",
            "subcategory":"Construction",
            "type":"Services"
        }
    ],
    "sg:phone":"+1 586 773 6050",
    "sg:postcode":"48021",
    "sg:province":"MI",
    "sg:tags":[
        "home",
        "siding",
        "commercial",
        "remodeling",
        "contractor"
    ],
    "wof:name":"Savage Building Company",
    "wof:placetype":"venue"
},
  "geometry": {"coordinates":[-82.951571,42.474851],"type":"Point"}
}