{
  "type": "Feature",
  "properties": {
    "iso:country":"US",
    "sg:address":"7268 Hawkes Rd",
    "sg:city":"Lake Ann",
    "sg:classifiers":[
        {
            "category":"Farming",
            "subcategory":"Poultry Farm",
            "type":"Manufacturing & Wholesale Goods"
        }
    ],
    "sg:phone":"+1 231 275 7584",
    "sg:postcode":"49650",
    "sg:province":"MI",
    "sg:tags":[
        "chicken",
        "egg",
        "feedlot",
        "beef",
        "cattle"
    ],
    "wof:name":"Brookhaven",
    "wof:placetype":"venue"
},
  "geometry": {"coordinates":[-85.866721,44.735099],"type":"Point"}
}