{
  "type": "Feature",
  "properties": {
    "iso:country":"US",
    "sg:address":"1126 Ottawa Beach Rd",
    "sg:city":"Holland",
    "sg:classifiers":[
        {
            "category":"Personal",
            "subcategory":"Beauty Salon",
            "type":"Services"
        }
    ],
    "sg:phone":"+1 616 994 7447",
    "sg:postcode":"49424",
    "sg:province":"MI",
    "sg:tags":[
        "shop",
        "treatment",
        "skin"
    ],
    "wof:name":"Lundi Bleu",
    "wof:placetype":"venue"
},
  "geometry": {"coordinates":[-86.15539200000001,42.793758],"type":"Point"}
}