{
  "type": "Feature",
  "properties": {
    "iso:country":"US",
    "sg:address":"3940 Patterson Rd",
    "sg:city":"Bay City",
    "sg:classifiers":[
        {
            "category":"Building & Trades",
            "subcategory":"Landscaping Services",
            "type":"Services"
        }
    ],
    "sg:phone":"+1 989 686 7036",
    "sg:postcode":"48706",
    "sg:province":"MI",
    "wof:name":"Phelps Lawn Services",
    "wof:placetype":"venue"
},
  "geometry": {"coordinates":[-83.874161,43.62602],"type":"Point"}
}