{
  "type": "Feature",
  "properties": {
    "iso:country":"US",
    "sg:address":"1833 Bass Lake Rd",
    "sg:city":"Traverse City",
    "sg:classifiers":[
        {
            "category":"Building & Trades",
            "subcategory":"Construction",
            "type":"Services"
        }
    ],
    "sg:phone":"+1 231 946 5839",
    "sg:postcode":"49684",
    "sg:province":"MI",
    "sg:tags":[
        "maker",
        "cabinet"
    ],
    "wof:name":"Pine Crest Woodworking",
    "wof:placetype":"venue"
},
  "geometry": {"coordinates":[-85.71635499999999,44.714845],"type":"Point"}
}