{
  "type": "Feature",
  "properties": {
    "iso:country":"US",
    "sg:address":"6170 Gaitway Dr",
    "sg:city":"Grand Blanc",
    "sg:classifiers":[
        {
            "category":"Real Estate",
            "subcategory":"Real Estate Agent",
            "type":"Services"
        }
    ],
    "sg:phone":"+1 810 694 0694",
    "sg:postcode":"48439",
    "sg:province":"MI",
    "wof:name":"Pine Hollow Estates",
    "wof:placetype":"venue"
},
  "geometry": {"coordinates":[-83.58487700000001,42.90987],"type":"Point"}
}