{
  "type": "Feature",
  "properties": {
    "iso:country":"US",
    "sg:address":"319 E Main St",
    "sg:city":"Addison",
    "sg:classifiers":[
        {
            "category":"Government",
            "subcategory":"Fire Station",
            "type":"Public Place"
        }
    ],
    "sg:phone":"+1 517 547 6776",
    "sg:postcode":"49220",
    "sg:province":"MI",
    "sg:tags":[
        "department"
    ],
    "wof:name":"Addison Fire Dept",
    "wof:placetype":"venue"
},
  "geometry": {"coordinates":[-84.34389400000001,41.986578],"type":"Point"}
}