{
  "type": "Feature",
  "properties": {
    "iso:country":"US",
    "sg:address":"24500 Tudor Ln",
    "sg:city":"Franklin",
    "sg:classifiers":[
        {
            "category":"Professional",
            "subcategory":"Advertising",
            "type":"Services"
        }
    ],
    "sg:phone":"+1 313 224 5428",
    "sg:postcode":"48025",
    "sg:province":"MI",
    "sg:tags":[
        "agency"
    ],
    "wof:name":"Susan Szczurek Creative Svcs",
    "wof:placetype":"venue"
},
  "geometry": {"coordinates":[-83.289146,42.524405],"type":"Point"}
}