{
  "type": "Feature",
  "properties": {
    "iso:country":"US",
    "sg:address":"5119 US Hwy 10 Bus",
    "sg:city":"Clare",
    "sg:classifiers":[
        {
            "category":"Building & Trades",
            "subcategory":"Construction",
            "type":"Services"
        }
    ],
    "sg:phone":"+1 989 386 8003",
    "sg:postcode":"48617",
    "sg:province":"MI",
    "sg:tags":[
        "designer"
    ],
    "wof:name":"Fussman Designs",
    "wof:placetype":"venue"
},
  "geometry": {"coordinates":[-84.74664799999999,43.812073],"type":"Point"}
}