{
  "type": "Feature",
  "properties": {
    "iso:country":"US",
    "sg:address":"1280 33rd St",
    "sg:city":"Allegan",
    "sg:classifiers":[
        {
            "category":"Building & Trades",
            "subcategory":"Construction",
            "type":"Services"
        }
    ],
    "sg:phone":"+1 269 673 6465",
    "sg:postcode":"49010",
    "sg:province":"MI",
    "sg:tags":[
        "house"
    ],
    "wof:name":"Martin & June Nielsen",
    "wof:placetype":"venue"
},
  "geometry": {"coordinates":[-85.869587,42.513829],"type":"Point"}
}