{
  "type": "Feature",
  "properties": {
    "iso:country":"US",
    "sg:address":"315 N Auburn Rd",
    "sg:city":"Auburn",
    "sg:classifiers":[
        {
            "category":"Professional",
            "subcategory":"Business Services",
            "type":"Services"
        }
    ],
    "sg:phone":"+1 989 662 7777",
    "sg:postcode":"48611",
    "sg:province":"MI",
    "sg:tags":[
        "interior",
        "consultant",
        "design",
        "decorator"
    ],
    "wof:name":"Interiors By Decorators Den",
    "wof:placetype":"venue"
},
  "geometry": {"coordinates":[-84.069396,43.606198],"type":"Point"}
}