{
  "type": "Feature",
  "properties": {
    "iso:country":"US",
    "sg:address":"3117 Heights Ravenna Rd",
    "sg:city":"Muskegon",
    "sg:classifiers":[
        {
            "category":"Retail",
            "subcategory":"Animal Services",
            "type":"Services"
        }
    ],
    "sg:phone":"+1 231 777 4848",
    "sg:postcode":"49444",
    "sg:province":"MI",
    "wof:name":"Grooming Room",
    "wof:placetype":"venue"
},
  "geometry": {"coordinates":[-86.167399,43.190259],"type":"Point"}
}