{
  "type": "Feature",
  "properties": {
    "iso:country":"US",
    "sg:address":"1058 Adams St SE",
    "sg:city":"Grand Rapids",
    "sg:classifiers":[
        {
            "category":"Restaurant",
            "type":"Food & Drink"
        }
    ],
    "sg:phone":"+1 616 475 0910",
    "sg:postcode":"49507",
    "sg:province":"MI",
    "sg:tags":[
        "eating"
    ],
    "wof:name":"Rancho Grande Distributors Who",
    "wof:placetype":"venue"
},
  "geometry": {"coordinates":[-85.642319,42.938038],"type":"Point"}
}