{
  "type": "Feature",
  "properties": {
    "iso:country":"US",
    "sg:address":"7373 Perry St",
    "sg:city":"Zeeland",
    "sg:classifiers":[
        {
            "category":"Retail",
            "subcategory":"Auto Repair",
            "type":"Services"
        }
    ],
    "sg:phone":"+1 616 772 4959",
    "sg:postcode":"49464",
    "sg:province":"MI",
    "sg:tags":[
        "body"
    ],
    "wof:name":"Bobs Collision",
    "wof:placetype":"venue"
},
  "geometry": {"coordinates":[-85.961934,42.79778],"type":"Point"}
}