{
  "type": "Feature",
  "properties": {
    "iso:country":"US",
    "sg:address":"3663 Saint Anthony Rd",
    "sg:city":"Temperance",
    "sg:classifiers":[
        {
            "category":"Retail",
            "subcategory":"Repair Shop",
            "type":"Services"
        }
    ],
    "sg:phone":"+1 734 854 4097",
    "sg:postcode":"48182",
    "sg:province":"MI",
    "sg:tags":[
        "tool",
        "parts"
    ],
    "wof:name":"Bedford Service & Repair",
    "wof:placetype":"venue"
},
  "geometry": {"coordinates":[-83.63449799999999,41.799625],"type":"Point"}
}