{
  "type": "Feature",
  "properties": {
    "iso:country":"US",
    "sg:address":"2579 Bell Oak Rd",
    "sg:city":"Howell",
    "sg:classifiers":[
        {
            "category":"Building & Trades",
            "subcategory":"Construction",
            "type":"Services"
        }
    ],
    "sg:phone":"+1 517 548 5448",
    "sg:postcode":"48895",
    "sg:province":"MI",
    "sg:tags":[
        "paving",
        "asphalt",
        "contractor"
    ],
    "wof:name":"All Star Asphalt Paving",
    "wof:placetype":"venue"
},
  "geometry": {"coordinates":[-84.261807,42.729984],"type":"Point"}
}