{
  "type": "Feature",
  "properties": {
    "iso:country":"US",
    "sg:address":"29260 Franklin Rd",
    "sg:city":"Southfield",
    "sg:classifiers":[
        {
            "category":"Home & Garden",
            "subcategory":"Carpets & Floor Coverings",
            "type":"Retail Goods"
        }
    ],
    "sg:phone":"+1 248 353 9174",
    "sg:postcode":"48034",
    "sg:province":"MI",
    "sg:tags":[
        "dealer",
        "rug"
    ],
    "wof:name":"Bloomfield Custom Remodeling",
    "wof:placetype":"venue"
},
  "geometry": {"coordinates":[-83.309788,42.502924],"type":"Point"}
}