{
  "type": "Feature",
  "properties": {
    "iso:country":"US",
    "sg:address":"19374 Lancaster Dr",
    "sg:city":"Trenton",
    "sg:classifiers":[
        {
            "category":"Arts & Performance",
            "subcategory":"Music",
            "type":"Entertainment"
        }
    ],
    "sg:phone":"+1 734 676 1991",
    "sg:postcode":"48183",
    "sg:province":"MI",
    "sg:tags":[
        "dj"
    ],
    "wof:name":"Mystro's Entertainment",
    "wof:placetype":"venue"
},
  "geometry": {"coordinates":[-83.223602,42.1208],"type":"Point"}
}