{
  "type": "Feature",
  "properties": {
    "iso:country":"US",
    "sg:address":"16 S Howell St",
    "sg:city":"Hillsdale",
    "sg:classifiers":[
        {
            "category":"Professional",
            "subcategory":"Lawyer & Legal Services",
            "type":"Services"
        }
    ],
    "sg:phone":"+1 517 437 7210",
    "sg:postcode":"49242",
    "sg:province":"MI",
    "sg:tags":[
        "attorney"
    ],
    "wof:name":"Parker Hayes & Lovinger",
    "wof:placetype":"venue"
},
  "geometry": {"coordinates":[-84.632088,41.91948],"type":"Point"}
}