{
  "type": "Feature",
  "properties": {
    "iso:country":"US",
    "sg:address":"55338 Park Pl",
    "sg:city":"New Hudson",
    "sg:classifiers":[
        {
            "category":"Wholesale",
            "subcategory":"Machinery & Supplies",
            "type":"Manufacturing & Wholesale Goods"
        }
    ],
    "sg:phone":"+1 248 437 4108",
    "sg:postcode":"48165",
    "sg:province":"MI",
    "sg:tags":[
        "industrial"
    ],
    "wof:name":"Jeger Systems Inc",
    "wof:placetype":"venue"
},
  "geometry": {"coordinates":[-83.59953299999999,42.518719],"type":"Point"}
}