{
  "type": "Feature",
  "properties": {
    "iso:country":"US",
    "sg:address":"47900 Grand River Ave",
    "sg:city":"Novi",
    "sg:classifiers":[
        {
            "category":"Restaurant",
            "type":"Food & Drink"
        }
    ],
    "sg:phone":"+1 248 449 1592",
    "sg:postcode":"48374",
    "sg:province":"MI",
    "sg:tags":[
        "american"
    ],
    "sg:website":"http://www.applebees.com",
    "wof:name":"Applebee's",
    "wof:placetype":"venue"
},
  "geometry": {"coordinates":[-83.520994,42.490949],"type":"Point"}
}