{
  "type": "Feature",
  "properties": {
    "iso:country":"US",
    "sg:address":"26 W Speaker St",
    "sg:city":"Sandusky",
    "sg:classifiers":[
        {
            "category":"Organizations",
            "subcategory":"Professional Association",
            "type":"Services"
        }
    ],
    "sg:phone":"+1 810 648 4445",
    "sg:postcode":"48471",
    "sg:province":"MI",
    "sg:tags":[
        "business"
    ],
    "wof:name":"Sandusky Chamber Of Commerce",
    "wof:placetype":"venue"
},
  "geometry": {"coordinates":[-82.830517,43.419235],"type":"Point"}
}