{
  "type": "Feature",
  "properties": {
    "iso:country":"US",
    "sg:address":"259 Mill St",
    "sg:city":"Rochester",
    "sg:classifiers":[
        {
            "category":"Retail",
            "subcategory":"Auto Repair",
            "type":"Services"
        }
    ],
    "sg:phone":"+1 248 651 6339",
    "sg:postcode":"48307",
    "sg:province":"MI",
    "sg:tags":[
        "repairing",
        "automobile"
    ],
    "wof:name":"Bill's Automotive",
    "wof:placetype":"venue"
},
  "geometry": {"coordinates":[-83.131472,42.677419],"type":"Point"}
}