{
  "type": "Feature",
  "properties": {
    "iso:country":"US",
    "sg:address":"625 E Ayer St",
    "sg:city":"Ironwood",
    "sg:classifiers":[
        {
            "category":"Professional",
            "subcategory":"Accounting & Tax Preparation",
            "type":"Services"
        }
    ],
    "sg:phone":"+1 906 932 1215",
    "sg:postcode":"49938",
    "sg:province":"MI",
    "wof:name":"James D Oliver CPA",
    "wof:placetype":"venue"
},
  "geometry": {"coordinates":[-90.159744,46.457277],"type":"Point"}
}