{
  "type": "Feature",
  "properties": {
    "iso:country":"US",
    "sg:address":"130 Division St N",
    "sg:city":"Battle Creek",
    "sg:classifiers":[
        {
            "category":"Wholesale",
            "subcategory":"Non-durable Goods",
            "type":"Manufacturing & Wholesale Goods"
        }
    ],
    "sg:phone":"+1 269 963 3732",
    "sg:postcode":"49017",
    "sg:province":"MI",
    "sg:tags":[
        "advertising"
    ],
    "wof:name":"Cereal City Advertising",
    "wof:placetype":"venue"
},
  "geometry": {"coordinates":[-85.17768599999999,42.320286],"type":"Point"}
}