{
  "type": "Feature",
  "properties": {
    "iso:country":"US",
    "sg:address":"102 W Randolph St",
    "sg:city":"Lansing",
    "sg:classifiers":[
        {
            "category":"Organizations",
            "subcategory":"Religious Organization",
            "type":"Services"
        }
    ],
    "sg:phone":"+1 517 487 3749",
    "sg:postcode":"48906",
    "sg:province":"MI",
    "sg:website":"www.sttherese.org",
    "wof:name":"St Therese Church",
    "wof:placetype":"venue"
},
  "geometry": {"coordinates":[-84.554349,42.760084],"type":"Point"}
}