{
  "type": "Feature",
  "properties": {
    "iso:country":"US",
    "sg:address":"6676 Naontah Trl NE",
    "sg:city":"Rockford",
    "sg:classifiers":[
        {
            "category":"Professional",
            "subcategory":"Computer Services",
            "type":"Services"
        }
    ],
    "sg:phone":"+1 616 874 6084",
    "sg:postcode":"49341",
    "sg:province":"MI",
    "sg:tags":[
        "related"
    ],
    "wof:name":"N T G",
    "wof:placetype":"venue"
},
  "geometry": {"coordinates":[-85.45370200000001,43.084291],"type":"Point"}
}