{
  "type": "Feature",
  "properties": {
    "iso:country":"US",
    "sg:address":"21819 Middlebelt Rd",
    "sg:city":"Farmington Hills",
    "sg:classifiers":[
        {
            "category":"Social Services",
            "subcategory":"Adult Care",
            "type":"Services"
        }
    ],
    "sg:phone":"+1 248 471 2898",
    "sg:postcode":"48336",
    "sg:province":"MI",
    "sg:tags":[
        "home",
        "residential"
    ],
    "wof:name":"Ladies Home For Gentle Care",
    "wof:placetype":"venue"
},
  "geometry": {"coordinates":[-83.336983,42.453784],"type":"Point"}
}