{
  "type": "Feature",
  "properties": {
    "iso:country":"US",
    "sg:address":"42627 Garfield Rd Ste 211",
    "sg:city":"Clinton Township",
    "sg:classifiers":[
        {
            "category":"Communications",
            "subcategory":"Newspaper",
            "type":"Services"
        }
    ],
    "sg:phone":"+1 586 412 8500",
    "sg:postcode":"48038",
    "sg:province":"MI",
    "sg:tags":[
        "print",
        "medium"
    ],
    "wof:name":"Your Hometown Shopper",
    "wof:placetype":"venue"
},
  "geometry": {"coordinates":[-82.953022,42.610438],"type":"Point"}
}