{
  "type": "Feature",
  "properties": {
    "iso:country":"US",
    "sg:address":"517 E Main St",
    "sg:city":"Bannister",
    "sg:classifiers":[
        {
            "category":"Organizations",
            "subcategory":"Religious Organization",
            "type":"Services"
        }
    ],
    "sg:phone":"+1 989 862 5270",
    "sg:postcode":"48807",
    "sg:province":"MI",
    "sg:tags":[
        "a",
        "as",
        "church",
        "operates"
    ],
    "wof:name":"St Cyril RC Church",
    "wof:placetype":"venue"
},
  "geometry": {"coordinates":[-84.418801,43.132406],"type":"Point"}
}