{
  "type": "Feature",
  "properties": {
    "iso:country":"US",
    "sg:address":"455 Post Rd",
    "sg:city":"Buchanan",
    "sg:classifiers":[
        {
            "category":"Wholesale",
            "subcategory":"Groceries",
            "type":"Manufacturing & Wholesale Goods"
        }
    ],
    "sg:phone":"+1 269 695 5600",
    "sg:postcode":"49107",
    "sg:province":"MI",
    "sg:tags":[
        "food"
    ],
    "sg:website":"www.jrpack.com",
    "wof:name":"Ja Food Svc",
    "wof:placetype":"venue"
},
  "geometry": {"coordinates":[-86.38134700000001,41.822666],"type":"Point"}
}