{
  "type": "Feature",
  "properties": {
    "iso:country":"US",
    "sg:address":"4464 Elderberry Dr",
    "sg:city":"Brighton",
    "sg:classifiers":[
        {
            "category":"Professional",
            "subcategory":"Management & Consulting",
            "type":"Services"
        }
    ],
    "sg:phone":"+1 810 229 4102",
    "sg:postcode":"48114",
    "sg:province":"MI",
    "sg:tags":[
        "business"
    ],
    "wof:name":"Norman L Twork",
    "wof:placetype":"venue"
},
  "geometry": {"coordinates":[-83.718097,42.539902],"type":"Point"}
}