{
  "type": "Feature",
  "properties": {
    "iso:country":"US",
    "sg:address":"109 S 3rd St",
    "sg:city":"West Branch",
    "sg:classifiers":[
        {
            "category":"Personal",
            "subcategory":"Beauty Salon",
            "type":"Services"
        }
    ],
    "sg:phone":"+1 989 345 5508",
    "sg:postcode":"48661",
    "sg:province":"MI",
    "wof:name":"Studio 1",
    "wof:placetype":"venue"
},
  "geometry": {"coordinates":[-84.238613,44.276161],"type":"Point"}
}