{
  "type": "Feature",
  "properties": {
    "iso:country":"US",
    "sg:address":"19250 W 11 Mile Rd",
    "sg:city":"Lathrup Village",
    "sg:classifiers":[
        {
            "category":"Education",
            "subcategory":"Special Training",
            "type":"Public Place"
        }
    ],
    "sg:phone":"+1 248 569 3000",
    "sg:postcode":"48076",
    "sg:province":"MI",
    "sg:tags":[
        "instruction",
        "music"
    ],
    "wof:name":"Piano & Violin Studio",
    "wof:placetype":"venue"
},
  "geometry": {"coordinates":[-83.232303,42.487976],"type":"Point"}
}