{
  "type": "Feature",
  "properties": {
    "iso:country":"US",
    "sg:address":"12295 Spencer Rd",
    "sg:city":"Saginaw",
    "sg:classifiers":[
        {
            "category":"Retail",
            "subcategory":"Auto Repair",
            "type":"Services"
        }
    ],
    "sg:phone":"+1 989 642 9007",
    "sg:postcode":"48609",
    "sg:province":"MI",
    "sg:tags":[
        "body"
    ],
    "wof:name":"Pauls Auto Body",
    "wof:placetype":"venue"
},
  "geometry": {"coordinates":[-84.17033499999999,43.35838],"type":"Point"}
}