{
  "type": "Feature",
  "properties": {
    "iso:country":"US",
    "sg:address":"1419 Davenport Ave",
    "sg:city":"Saginaw",
    "sg:classifiers":[
        {
            "category":"Autos & Motor Vehicles",
            "subcategory":"Fuel & Gas Station",
            "type":"Retail Goods"
        }
    ],
    "sg:phone":"+1 989 792 1200",
    "sg:postcode":"48602",
    "sg:province":"MI",
    "sg:tags":[
        "oil"
    ],
    "wof:name":"Wally King's Svc",
    "wof:placetype":"venue"
},
  "geometry": {"coordinates":[-83.960691,43.437222],"type":"Point"}
}