{
  "type": "Feature",
  "properties": {
    "iso:country":"US",
    "sg:address":"180 S Telegraph Rd",
    "sg:city":"Waterford",
    "sg:classifiers":[
        {
            "category":"Autos & Motor Vehicles",
            "subcategory":"Auto Supplies",
            "type":"Retail Goods"
        },
        {
            "category":"Retail",
            "subcategory":"Auto Repair",
            "type":"Services"
        }
    ],
    "sg:phone":"+1 248 681 3000",
    "sg:postcode":"48328",
    "sg:province":"MI",
    "sg:tags":[
        "tire"
    ],
    "wof:name":"Chuck Spadafore's Full Service Auto Repairs & Tires",
    "wof:placetype":"venue"
},
  "geometry": {"coordinates":[-83.325968,42.630002],"type":"Point"}
}