{
  "type": "Feature",
  "properties": {
    "iso:country":"US",
    "sg:address":"6314 W Pierson Rd",
    "sg:city":"Flushing",
    "sg:classifiers":[
        {
            "category":"Real Estate",
            "subcategory":"Real Estate Operator",
            "type":"Services"
        }
    ],
    "sg:phone":"+1 810 659 5637",
    "sg:postcode":"48433",
    "sg:province":"MI",
    "sg:tags":[
        "commercial"
    ],
    "wof:name":"Model Properties",
    "wof:placetype":"venue"
},
  "geometry": {"coordinates":[-83.809918,43.060359],"type":"Point"}
}