{
  "type": "Feature",
  "properties": {
    "iso:country":"US",
    "sg:address":"1135 W University Dr",
    "sg:city":"Rochester",
    "sg:classifiers":[
        {
            "category":"Health Services",
            "subcategory":"Doctor",
            "type":"Services"
        }
    ],
    "sg:phone":"+1 248 828 5013",
    "sg:postcode":"48307",
    "sg:province":"MI",
    "sg:tags":[
        "medical"
    ],
    "wof:name":"Dale Hoekstra",
    "wof:placetype":"venue"
},
  "geometry": {"coordinates":[-83.147043,42.681741],"type":"Point"}
}