{
  "type": "Feature",
  "properties": {
    "iso:country":"US",
    "sg:address":"28382 Franklin Rd",
    "sg:city":"Southfield",
    "sg:classifiers":[
        {
            "category":"Real Estate",
            "subcategory":"Architect",
            "type":"Services"
        }
    ],
    "sg:phone":"+1 248 356 3400",
    "sg:postcode":"48034",
    "sg:province":"MI",
    "wof:name":"Fusco Shaffer & Pappas Inc",
    "wof:placetype":"venue"
},
  "geometry": {"coordinates":[-83.303318,42.496397],"type":"Point"}
}