{
  "type": "Feature",
  "properties": {
    "iso:country":"US",
    "sg:address":"108 Prospect St",
    "sg:city":"Norvell",
    "sg:classifiers":[
        {
            "category":"Manufacturing",
            "subcategory":"Tools & Machinery",
            "type":"Manufacturing & Wholesale Goods"
        }
    ],
    "sg:phone":"+1 517 536 4006",
    "sg:postcode":"49263",
    "sg:province":"MI",
    "sg:tags":[
        "machine",
        "shop"
    ],
    "wof:name":"Mid-America Machining",
    "wof:placetype":"venue"
},
  "geometry": {"coordinates":[-84.18356,42.159364],"type":"Point"}
}