{
  "type": "Feature",
  "properties": {
    "iso:country":"US",
    "sg:address":"1522 Plumtree Ave",
    "sg:city":"Portage",
    "sg:classifiers":[
        {
            "category":"Professional",
            "subcategory":"Detective & Security Services",
            "type":"Services"
        }
    ],
    "sg:phone":"+1 269 327 7280",
    "sg:postcode":"49002",
    "sg:province":"MI",
    "sg:tags":[
        "car"
    ],
    "wof:name":"20/20 Investigation Services",
    "wof:placetype":"venue"
},
  "geometry": {"coordinates":[-85.571766,42.197451],"type":"Point"}
}