{
  "type": "Feature",
  "properties": {
    "iso:country":"US",
    "sg:address":"25300 W 6 Mile Rd",
    "sg:city":"Redford",
    "sg:classifiers":[
        {
            "category":"Real Estate",
            "subcategory":"Real Estate Operator",
            "type":"Services"
        }
    ],
    "sg:phone":"+1 313 537 3142",
    "sg:postcode":"48240",
    "sg:province":"MI",
    "sg:tags":[
        "apartment"
    ],
    "wof:name":"Presbyterian Villages of Michigan",
    "wof:placetype":"venue"
},
  "geometry": {"coordinates":[-83.289055,42.414337],"type":"Point"}
}