{
  "type": "Feature",
  "properties": {
    "iso:country":"US",
    "sg:address":"1526 Airway Dr",
    "sg:city":"Mt Pleasant",
    "sg:classifiers":[
        {
            "category":"Organizations",
            "subcategory":"Religious Organization",
            "type":"Services"
        }
    ],
    "sg:phone":"+1 989 773 3690",
    "sg:postcode":"48858",
    "sg:province":"MI",
    "sg:tags":[
        "church"
    ],
    "wof:name":"Maranatha Baptist Church",
    "wof:placetype":"venue"
},
  "geometry": {"coordinates":[-84.74167,43.618585],"type":"Point"}
}