{
  "type": "Feature",
  "properties": {
    "iso:country":"US",
    "sg:address":"441 E Chicago St",
    "sg:city":"Coldwater",
    "sg:classifiers":[
        {
            "category":"Banks & Credit Unions",
            "subcategory":"Bank",
            "type":"Services"
        }
    ],
    "sg:phone":"+1 517 279 5522",
    "sg:postcode":"49036",
    "sg:province":"MI",
    "sg:tags":[
        "state",
        "commercial"
    ],
    "wof:name":"Southern Michigan Bank & Trust",
    "wof:placetype":"venue"
},
  "geometry": {"coordinates":[-84.98243100000001,41.937709],"type":"Point"}
}