{
  "type": "Feature",
  "properties": {
    "iso:country":"US",
    "sg:address":"9318 Old Plank Ln",
    "sg:city":"Brighton",
    "sg:classifiers":[
        {
            "category":"Professional",
            "subcategory":"Business Services",
            "type":"Services"
        }
    ],
    "sg:phone":"+1 810 227 5161",
    "sg:postcode":"48114",
    "sg:province":"MI",
    "sg:tags":[
        "organizing"
    ],
    "wof:name":"Organize It",
    "wof:placetype":"venue"
},
  "geometry": {"coordinates":[-83.765084,42.577752],"type":"Point"}
}