{
  "type": "Feature",
  "properties": {
    "iso:country":"US",
    "sg:address":"317 W Chicago St",
    "sg:city":"Jonesville",
    "sg:classifiers":[
        {
            "category":"Retail",
            "subcategory":"Auto Repair",
            "type":"Services"
        }
    ],
    "sg:phone":"+1 517 849 7115",
    "sg:postcode":"49250",
    "sg:province":"MI",
    "sg:tags":[
        "body",
        "automobile",
        "painting"
    ],
    "wof:name":"Collins Auto Body",
    "wof:placetype":"venue"
},
  "geometry": {"coordinates":[-84.670449,41.980044],"type":"Point"}
}