{
  "type": "Feature",
  "properties": {
    "iso:country":"US",
    "sg:address":"5035 Wyoming St",
    "sg:city":"Dearborn",
    "sg:classifiers":[
        {
            "category":"Retail",
            "subcategory":"Repair Shop",
            "type":"Services"
        }
    ],
    "sg:phone":"+1 313 945 1800",
    "sg:postcode":"48126",
    "sg:province":"MI",
    "sg:tags":[
        "equipment",
        "gas",
        "install"
    ],
    "wof:name":"American Tank & Installation",
    "wof:placetype":"venue"
},
  "geometry": {"coordinates":[-83.156661,42.327751],"type":"Point"}
}