{
  "type": "Feature",
  "properties": {
    "iso:country":"US",
    "sg:address":"1234 6th St",
    "sg:city":"Marysville",
    "sg:classifiers":[
        {
            "category":"Organizations",
            "subcategory":"Religious Organization",
            "type":"Services"
        }
    ],
    "sg:phone":"+1 810 364 4540",
    "sg:postcode":"48040",
    "sg:province":"MI",
    "sg:tags":[
        "church"
    ],
    "wof:name":"First Baptist Church Inc",
    "wof:placetype":"venue"
},
  "geometry": {"coordinates":[-82.493557,42.920998],"type":"Point"}
}