{
  "type": "Feature",
  "properties": {
    "iso:country":"US",
    "sg:address":"58187 State Hwy 62",
    "sg:city":"Cassopolis",
    "sg:classifiers":[
        {
            "category":"Restaurant",
            "type":"Food & Drink"
        }
    ],
    "sg:phone":"+1 269 782 7309",
    "sg:postcode":"49031",
    "sg:province":"MI",
    "wof:name":"In-Between",
    "wof:placetype":"venue"
},
  "geometry": {"coordinates":[-86.040419,41.952342],"type":"Point"}
}