{
  "type": "Feature",
  "properties": {
    "iso:country":"US",
    "sg:address":"8700 W 9 Mile Rd",
    "sg:city":"Oak Park",
    "sg:classifiers":[
        {
            "category":"Education",
            "subcategory":"Special Training",
            "type":"Public Place"
        }
    ],
    "sg:phone":"+1 248 414 9617",
    "sg:postcode":"48237",
    "sg:province":"MI",
    "sg:tags":[
        "tutoring"
    ],
    "wof:name":"Ferndale Kumon Ctr",
    "wof:placetype":"venue"
},
  "geometry": {"coordinates":[-83.16092999999999,42.460189],"type":"Point"}
}