{
  "type": "Feature",
  "properties": {
    "iso:country":"US",
    "sg:address":"48595 West Rd",
    "sg:city":"Wixom",
    "sg:classifiers":[
        {
            "category":"Building & Trades",
            "subcategory":"Construction",
            "type":"Services"
        }
    ],
    "sg:phone":"+1 248 349 7000",
    "sg:postcode":"48393",
    "sg:province":"MI",
    "sg:tags":[
        "foundation"
    ],
    "wof:name":"Tru-Wall Construction Co",
    "wof:placetype":"venue"
},
  "geometry": {"coordinates":[-83.535996,42.508109],"type":"Point"}
}