{
  "type": "Feature",
  "properties": {
    "iso:country":"US",
    "sg:address":"28065 Mound Rd",
    "sg:city":"Warren",
    "sg:classifiers":[
        {
            "category":"Retail",
            "subcategory":"Repair Shop",
            "type":"Services"
        }
    ],
    "sg:phone":"+1 586 558 9999",
    "sg:postcode":"48092",
    "sg:province":"MI",
    "sg:tags":[
        "electronics",
        "satellite",
        "system"
    ],
    "wof:name":"Wireless World of Warren",
    "wof:placetype":"venue"
},
  "geometry": {"coordinates":[-83.0467,42.499901],"type":"Point"}
}