{
  "type": "Feature",
  "properties": {
    "iso:country":"US",
    "sg:address":"7007 Gratiot Ave",
    "sg:city":"Detroit",
    "sg:classifiers":[
        {
            "category":"Utilities",
            "subcategory":"Telephone",
            "type":"Services"
        },
        {
            "category":"Communications",
            "type":"Services"
        },
        {
            "category":"Shopping",
            "subcategory":"Computers & Home Electronics",
            "type":"Retail Goods"
        }
    ],
    "sg:phone":"+1 313 571 2300",
    "sg:postcode":"48207",
    "sg:province":"MI",
    "sg:tags":[
        "sound",
        "television",
        "system",
        "equipment",
        "radio",
        "store"
    ],
    "wof:name":"Pre Cell",
    "wof:placetype":"venue"
},
  "geometry": {"coordinates":[-83.019476,42.371559],"type":"Point"}
}