{
  "type": "Feature",
  "properties": {
    "iso:country":"US",
    "sg:address":"6544 Cardwell St",
    "sg:city":"Garden City",
    "sg:classifiers":[
        {
            "category":"Building & Trades",
            "subcategory":"Landscaping Services",
            "type":"Services"
        }
    ],
    "sg:phone":"+1 734 513 6722",
    "sg:postcode":"48135",
    "sg:province":"MI",
    "sg:tags":[
        "landscape"
    ],
    "wof:name":"Mark Agge",
    "wof:placetype":"venue"
},
  "geometry": {"coordinates":[-83.315533,42.335131],"type":"Point"}
}