{
  "type": "Feature",
  "properties": {
    "iso:country":"US",
    "sg:address":"29216 Orchard Lake Rd",
    "sg:city":"Farmington Hills",
    "sg:classifiers":[
        {
            "category":"Fast Food",
            "type":"Food & Drink"
        },
        {
            "category":"Restaurant",
            "type":"Food & Drink"
        },
        {
            "category":"Food & Beverages",
            "subcategory":"Cheese",
            "type":"Retail Goods"
        }
    ],
    "sg:phone":"+1 248 855 2228",
    "sg:postcode":"48334",
    "sg:province":"MI",
    "sg:tags":[
        "traditional",
        "burger",
        "american",
        "cheesesteaks"
    ],
    "sg:website":"jawsjumboburgers.net/",
    "wof:name":"Jaws Jumbo Burgers",
    "wof:placetype":"venue"
},
  "geometry": {"coordinates":[-83.359253,42.511822],"type":"Point"}
}