{
  "type": "Feature",
  "properties": {
    "iso:country":"US",
    "sg:address":"10500 Dix",
    "sg:city":"Dearborn",
    "sg:classifiers":[
        {
            "category":"Freight",
            "type":"Transportation"
        }
    ],
    "sg:phone":"+1 313 843 3831",
    "sg:postcode":"48120",
    "sg:province":"MI",
    "sg:tags":[
        "shipping",
        "arrangement"
    ],
    "wof:name":"United Mail Centers",
    "wof:placetype":"venue"
},
  "geometry": {"coordinates":[-83.146563,42.302253],"type":"Point"}
}