{
  "type": "Feature",
  "properties": {
    "iso:country":"US",
    "sg:address":"80 S Ortonville Rd",
    "sg:city":"Ortonville",
    "sg:classifiers":[
        {
            "category":"Personal",
            "subcategory":"Beauty Salon",
            "type":"Services"
        }
    ],
    "sg:phone":"+1 248 627 5228",
    "sg:postcode":"48462",
    "sg:province":"MI",
    "sg:tags":[
        "manicuring"
    ],
    "wof:name":"Creations Nail & Spa",
    "wof:placetype":"venue"
},
  "geometry": {"coordinates":[-83.451573,42.8515],"type":"Point"}
}