{
  "type": "Feature",
  "properties": {
    "iso:country":"US",
    "sg:address":"3639 Marketplace Cir",
    "sg:city":"Traverse City",
    "sg:classifiers":[
        {
            "category":"Shopping",
            "subcategory":"Gifts & Souvenirs",
            "type":"Retail Goods"
        },
        {
            "category":"Shopping",
            "subcategory":"Clothing, Apparel, & Fashions",
            "type":"Retail Goods"
        }
    ],
    "sg:phone":"+1 231 922 9070",
    "sg:postcode":"49684",
    "sg:province":"MI",
    "sg:tags":[
        "sportswear"
    ],
    "wof:name":"Nascar Connection",
    "wof:placetype":"venue"
},
  "geometry": {"coordinates":[-85.64712,44.731457],"type":"Point"}
}