{
  "type": "Feature",
  "properties": {
    "iso:country":"US",
    "sg:address":"15300 W 9 Mile Rd",
    "sg:city":"Oak Park",
    "sg:classifiers":[
        {
            "category":"Health Services",
            "subcategory":"Doctor",
            "type":"Services"
        }
    ],
    "sg:phone":"+1 248 967 3668",
    "sg:postcode":"48237",
    "sg:province":"MI",
    "sg:tags":[
        "podiatrist"
    ],
    "wof:name":"Lazar Daniel DPM",
    "wof:placetype":"venue"
},
  "geometry": {"coordinates":[-83.1987,42.4594],"type":"Point"}
}