{
  "type": "Feature",
  "properties": {
    "iso:country":"US",
    "sg:address":"1968 S Morey Rd",
    "sg:city":"Lake City",
    "sg:classifiers":[
        {
            "category":"Insurance",
            "subcategory":"Insurance Agent",
            "type":"Services"
        }
    ],
    "sg:phone":"+1 231 839 3072",
    "sg:postcode":"49651",
    "sg:province":"MI",
    "wof:name":"A-One Agency",
    "wof:placetype":"venue"
},
  "geometry": {"coordinates":[-85.215181,44.310168],"type":"Point"}
}