{
  "type": "Feature",
  "properties": {
    "iso:country":"US",
    "sg:address":"401 Richards Rd",
    "sg:city":"Bay City",
    "sg:classifiers":[
        {
            "category":"Retail",
            "subcategory":"Repair Shop",
            "type":"Services"
        }
    ],
    "sg:phone":"+1 989 894 1016",
    "sg:postcode":"48706",
    "sg:province":"MI",
    "wof:name":"Garys Lock Service",
    "wof:placetype":"venue"
},
  "geometry": {"coordinates":[-83.87799,43.65498],"type":"Point"}
}