{
  "type": "Feature",
  "properties": {
    "iso:country":"US",
    "sg:address":"7494 McDonald Rd",
    "sg:city":"Olivet",
    "sg:classifiers":[
        {
            "category":"Professional",
            "subcategory":"Business Services",
            "type":"Services"
        }
    ],
    "sg:phone":"+1 517 204 4535",
    "sg:postcode":"49076",
    "sg:province":"MI",
    "sg:tags":[
        "operator",
        "local",
        "trucking"
    ],
    "wof:name":"Wildfire Express Expedite",
    "wof:placetype":"venue"
},
  "geometry": {"coordinates":[-84.914901,42.45702],"type":"Point"}
}