{
  "type": "Feature",
  "properties": {
    "iso:country":"US",
    "sg:address":"8121 E Grand Lake Rd",
    "sg:city":"Presque Isle",
    "sg:classifiers":[
        {
            "category":"Food & Beverages",
            "subcategory":"Groceries & Convenience Stores",
            "type":"Retail Goods"
        }
    ],
    "sg:phone":"+1 989 595 6595",
    "sg:postcode":"49777",
    "sg:province":"MI",
    "sg:tags":[
        "grocer"
    ],
    "wof:name":"Birch Hill Grocery",
    "wof:placetype":"venue"
},
  "geometry": {"coordinates":[-83.476974,45.303872],"type":"Point"}
}