{
  "type": "Feature",
  "properties": {
    "iso:country":"US",
    "sg:address":"5402 Seneca St",
    "sg:city":"Detroit",
    "sg:classifiers":[
        {
            "category":"Social Services",
            "subcategory":"Child Care",
            "type":"Services"
        }
    ],
    "sg:phone":"+1 313 923 8172",
    "sg:postcode":"48213",
    "sg:province":"MI",
    "sg:tags":[
        "day"
    ],
    "wof:name":"Jumpstart Early Learning Villa",
    "wof:placetype":"venue"
},
  "geometry": {"coordinates":[-83.010822,42.382157],"type":"Point"}
}