{
  "type": "Feature",
  "properties": {
    "iso:country":"US",
    "sg:address":"1521 E Michigan Ave",
    "sg:city":"Jackson",
    "sg:classifiers":[
        {
            "category":"Shopping",
            "subcategory":"Department Store",
            "type":"Retail Goods"
        }
    ],
    "sg:phone":"+1 517 784 1704",
    "sg:postcode":"49202",
    "sg:province":"MI",
    "sg:tags":[
        "shop"
    ],
    "wof:name":"Family Dollar Store",
    "wof:placetype":"venue"
},
  "geometry": {"coordinates":[-84.38464399999999,42.251243],"type":"Point"}
}