{
  "type": "Feature",
  "properties": {
    "iso:country":"US",
    "sg:address":"1100 S Milford Rd",
    "sg:city":"Highland",
    "sg:classifiers":[
        {
            "category":"Restaurant",
            "type":"Food & Drink"
        }
    ],
    "sg:phone":"+1 248 887 4500",
    "sg:postcode":"48357",
    "sg:province":"MI",
    "sg:tags":[
        "shop",
        "coffee"
    ],
    "wof:name":"It's A Grind",
    "wof:placetype":"venue"
},
  "geometry": {"coordinates":[-83.616651,42.630939],"type":"Point"}
}