{
  "type": "Feature",
  "properties": {
    "iso:country":"US",
    "sg:address":"651 Beck St",
    "sg:city":"Jonesville",
    "sg:classifiers":[
        {
            "category":"Manufacturing",
            "subcategory":"Motor Vehicles & Parts",
            "type":"Manufacturing & Wholesale Goods"
        }
    ],
    "sg:phone":"+1 517 849 9918",
    "sg:postcode":"49250",
    "sg:province":"MI",
    "sg:tags":[
        "automobile",
        "supply"
    ],
    "sg:website":"www.eaglepicher.com",
    "wof:name":"Hillsdale Tool & Mfg Co",
    "wof:placetype":"venue"
},
  "geometry": {"coordinates":[-84.66543,41.967933],"type":"Point"}
}