{
  "type": "Feature",
  "properties": {
    "iso:country":"US",
    "sg:address":"1521 Imlay City Rd",
    "sg:city":"Lapeer",
    "sg:classifiers":[
        {
            "category":"Professional",
            "subcategory":"Advertising",
            "type":"Services"
        }
    ],
    "sg:phone":"+1 810 664 1877",
    "sg:postcode":"48446",
    "sg:province":"MI",
    "sg:tags":[
        "guide"
    ],
    "wof:name":"Buyer's Guide",
    "wof:placetype":"venue"
},
  "geometry": {"coordinates":[-83.28407199999999,43.046068],"type":"Point"}
}