{
  "type": "Feature",
  "properties": {
    "iso:country":"US",
    "sg:address":"1250 Fuller Ave NE",
    "sg:city":"Grand Rapids",
    "sg:classifiers":[
        {
            "category":"Building & Trades",
            "subcategory":"Construction",
            "type":"Services"
        }
    ],
    "sg:phone":"+1 616 458 6655",
    "sg:postcode":"49505",
    "sg:province":"MI",
    "sg:tags":[
        "designer",
        "dealer",
        "pool",
        "swimming"
    ],
    "sg:website":"www.poolplaceofgr.com",
    "wof:name":"Pool Place Of Grand Rapids Inc",
    "wof:placetype":"venue"
},
  "geometry": {"coordinates":[-85.63987299999999,42.984424],"type":"Point"}
}