{
  "type": "Feature",
  "properties": {
    "iso:country":"US",
    "sg:address":"1633 Lawndale",
    "sg:city":"Detroit",
    "sg:classifiers":[
        {
            "category":"Restaurant",
            "type":"Food & Drink"
        }
    ],
    "sg:phone":"+1 313 843 1433",
    "sg:postcode":"48209",
    "sg:province":"MI",
    "sg:tags":[
        "seafood",
        "mexican"
    ],
    "sg:website":"laterrazadetroit.com/",
    "wof:name":"La Terraza",
    "wof:placetype":"venue"
},
  "geometry": {"coordinates":[-83.129661,42.304657],"type":"Point"}
}