{
  "type": "Feature",
  "properties": {
    "iso:country":"US",
    "sg:address":"501 Lakeside Drive",
    "sg:city":"Birmingham",
    "sg:classifiers":[
        {
            "category":"Park",
            "type":"Public Place"
        }
    ],
    "sg:postcode":"48009",
    "sg:province":"MI",
    "wof:name":"Quarton Lake Park",
    "wof:placetype":"venue"
},
  "geometry": {"coordinates":[-83.22684099999999,42.549615],"type":"Point"}
}