{
  "type": "Feature",
  "properties": {
    "iso:country":"US",
    "sg:address":"6030 S Pennsylvania Ave",
    "sg:city":"Lansing",
    "sg:classifiers":[
        {
            "category":"Shopping",
            "type":"Retail Goods"
        }
    ],
    "sg:phone":"+1 517 887 8130",
    "sg:postcode":"48911",
    "sg:province":"MI",
    "sg:tags":[
        "pet",
        "food",
        "supply"
    ],
    "wof:name":"Pet Supplies Plus",
    "wof:placetype":"venue"
},
  "geometry": {"coordinates":[-84.538257,42.669838],"type":"Point"}
}