{
  "type": "Feature",
  "properties": {
    "iso:country":"US",
    "sg:address":"738 S Garfield Ave",
    "sg:city":"Traverse City",
    "sg:classifiers":[
        {
            "category":"Bars & Pubs",
            "type":"Food & Drink"
        }
    ],
    "sg:phone":"+1 231 941 0988",
    "sg:postcode":"49686",
    "sg:province":"MI",
    "wof:name":"Other Place",
    "wof:placetype":"venue"
},
  "geometry": {"coordinates":[-85.59537899999999,44.754357],"type":"Point"}
}