{
  "type": "Feature",
  "properties": {
    "iso:country":"US",
    "sg:address":"2836 Riordan St",
    "sg:city":"Muskegon",
    "sg:classifiers":[
        {
            "category":"Shopping",
            "subcategory":"Clothing, Apparel, & Fashions",
            "type":"Retail Goods"
        }
    ],
    "sg:phone":"+1 231 737 9136",
    "sg:postcode":"49444",
    "sg:province":"MI",
    "wof:name":"Auntie's Attic & More",
    "wof:placetype":"venue"
},
  "geometry": {"coordinates":[-86.235907,43.199947],"type":"Point"}
}