{
  "type": "Feature",
  "properties": {
    "iso:country":"US",
    "sg:address":"24744 Crestview",
    "sg:city":"Farmington Hills",
    "sg:classifiers":[
        {
            "category":"Retail",
            "subcategory":"Auto Repair",
            "type":"Services"
        }
    ],
    "sg:phone":"+1 248 615 8964",
    "sg:postcode":"48335",
    "sg:province":"MI",
    "sg:tags":[
        "repairing",
        "automobile"
    ],
    "wof:name":"Automotive Techniques Inc",
    "wof:placetype":"venue"
},
  "geometry": {"coordinates":[-83.427224,42.471097],"type":"Point"}
}