{
  "type": "Feature",
  "properties": {
    "iso:country":"US",
    "sg:address":"609 Vernon Ave",
    "sg:city":"Lansing",
    "sg:classifiers":[
        {
            "category":"Professional",
            "subcategory":"Business Services",
            "type":"Services"
        }
    ],
    "sg:phone":"+1 517 827 0696",
    "sg:postcode":"48910",
    "sg:province":"MI",
    "wof:name":"Identity Creative Group",
    "wof:placetype":"venue"
},
  "geometry": {"coordinates":[-84.543109,42.69658],"type":"Point"}
}