{
  "type": "Feature",
  "properties": {
    "iso:country":"US",
    "sg:address":"34326 Marquette St",
    "sg:city":"Westland",
    "sg:classifiers":[
        {
            "category":"Freight",
            "type":"Transportation"
        }
    ],
    "sg:phone":"+1 734 721 9710",
    "sg:postcode":"48185",
    "sg:province":"MI",
    "sg:tags":[
        "operator",
        "local",
        "trucking"
    ],
    "wof:name":"Srw Trucking Inc",
    "wof:placetype":"venue"
},
  "geometry": {"coordinates":[-83.376828,42.317537],"type":"Point"}
}