{
  "type": "Feature",
  "properties": {
    "iso:country":"US",
    "sg:address":"15310 Kercheval Ave",
    "sg:city":"Grosse Pointe Park",
    "sg:classifiers":[
        {
            "category":"Shopping",
            "subcategory":"Antiques",
            "type":"Retail Goods"
        }
    ],
    "sg:phone":"+1 313 822 3452",
    "sg:postcode":"48230",
    "sg:province":"MI",
    "wof:name":"Lloyd David Antique's",
    "wof:placetype":"venue"
},
  "geometry": {"coordinates":[-82.93814,42.381989],"type":"Point"}
}