{
  "type": "Feature",
  "properties": {
    "iso:country":"US",
    "sg:address":"268 N Adams Rd",
    "sg:city":"Rochester Hills",
    "sg:classifiers":[
        {
            "category":"Home & Garden",
            "subcategory":"Furniture",
            "type":"Retail Goods"
        }
    ],
    "sg:phone":"+1 248 375 8829",
    "sg:postcode":"48309",
    "sg:province":"MI",
    "wof:name":"Pottery Barn",
    "wof:placetype":"venue"
},
  "geometry": {"coordinates":[-83.194202,42.686089],"type":"Point"}
}