{
  "type": "Feature",
  "properties": {
    "iso:country":"US",
    "sg:address":"44621 Morley Dr",
    "sg:city":"Clinton Township",
    "sg:classifiers":[
        {
            "category":"Sports & Exercise",
            "subcategory":"Skate Park",
            "type":"Entertainment"
        }
    ],
    "sg:phone":"+1 586 469 1170",
    "sg:postcode":"48036",
    "sg:province":"MI",
    "wof:name":"Landslide Skate Park",
    "wof:placetype":"venue"
},
  "geometry": {"coordinates":[-82.867699,42.626701],"type":"Point"}
}