{
  "type": "Feature",
  "properties": {
    "iso:country":"US",
    "sg:address":"5123 Aurelius Rd",
    "sg:city":"Lansing",
    "sg:classifiers":[
        {
            "category":"Wholesale",
            "subcategory":"Non-durable Goods",
            "type":"Manufacturing & Wholesale Goods"
        }
    ],
    "sg:phone":"+1 517 394 3300",
    "sg:postcode":"48911",
    "sg:province":"MI",
    "wof:name":"Creemers Enterprises",
    "wof:placetype":"venue"
},
  "geometry": {"coordinates":[-84.523447,42.679128],"type":"Point"}
}