{
  "type": "Feature",
  "properties": {
    "iso:country":"US",
    "sg:address":"575 N Cedar St",
    "sg:city":"Mason",
    "sg:classifiers":[
        {
            "category":"Retail",
            "subcategory":"Auto Rental",
            "type":"Services"
        }
    ],
    "sg:phone":"+1 517 676 1292",
    "sg:postcode":"48854",
    "sg:province":"MI",
    "sg:tags":[
        "renting",
        "truck",
        "leasing"
    ],
    "wof:name":"U-Haul Co",
    "wof:placetype":"venue"
},
  "geometry": {"coordinates":[-84.452913,42.584269],"type":"Point"}
}