{
  "type": "Feature",
  "properties": {
    "iso:country":"US",
    "sg:address":"28477 Hoover Rd",
    "sg:city":"Warren",
    "sg:classifiers":[
        {
            "category":"Health Services",
            "subcategory":"Doctor",
            "type":"Services"
        }
    ],
    "sg:phone":"+1 586 751 1500",
    "sg:postcode":"48093",
    "sg:province":"MI",
    "sg:tags":[
        "medical"
    ],
    "wof:name":"L Manyam MD",
    "wof:placetype":"venue"
},
  "geometry": {"coordinates":[-83.00661100000001,42.500112],"type":"Point"}
}