{
  "type": "Feature",
  "properties": {
    "iso:country":"US",
    "sg:address":"10629 Brookview Dr",
    "sg:city":"Zeeland",
    "sg:classifiers":[
        {
            "category":"Insurance",
            "subcategory":"Insurance Agent",
            "type":"Services"
        }
    ],
    "sg:phone":"+1 616 772 4367",
    "sg:postcode":"49464",
    "sg:province":"MI",
    "wof:name":"National Assoc For Rtrd Fdrl E",
    "wof:placetype":"venue"
},
  "geometry": {"coordinates":[-86.044062,42.828124],"type":"Point"}
}