{
  "type": "Feature",
  "properties": {
    "iso:country":"US",
    "sg:address":"10244 W 7 Mile Rd",
    "sg:city":"Detroit",
    "sg:classifiers":[
        {
            "category":"Health Services",
            "subcategory":"Doctor",
            "type":"Services"
        }
    ],
    "sg:phone":"+1 313 862 5800",
    "sg:postcode":"48221",
    "sg:province":"MI",
    "sg:tags":[
        "podiatrist"
    ],
    "wof:name":"Johnson Charles M DPM",
    "wof:placetype":"venue"
},
  "geometry": {"coordinates":[-83.16390199999999,42.4314],"type":"Point"}
}