{
  "type": "Feature",
  "properties": {
    "iso:country":"US",
    "sg:address":"14500 Grand River Ave",
    "sg:city":"Detroit",
    "sg:classifiers":[
        {
            "category":"Organizations",
            "subcategory":"Religious Organization",
            "type":"Services"
        }
    ],
    "sg:phone":"+1 313 835 3570",
    "sg:postcode":"48227",
    "sg:province":"MI",
    "wof:name":"Thomas Temple Church Inc",
    "wof:placetype":"venue"
},
  "geometry": {"coordinates":[-83.188379,42.388633],"type":"Point"}
}