{
  "type": "Feature",
  "properties": {
    "iso:country":"US",
    "sg:address":"12073 Telegraph Rd",
    "sg:city":"Erie",
    "sg:classifiers":[
        {
            "category":"Organizations",
            "subcategory":"Religious Organization",
            "type":"Services"
        }
    ],
    "sg:phone":"+1 734 848 8707",
    "sg:postcode":"48133",
    "sg:province":"MI",
    "sg:tags":[
        "clergy"
    ],
    "wof:name":"Jack L Branham Rev",
    "wof:placetype":"venue"
},
  "geometry": {"coordinates":[-83.486565,41.835038],"type":"Point"}
}