{
  "type": "Feature",
  "properties": {
    "iso:country":"US",
    "sg:address":"809 Rynearson St",
    "sg:city":"Buchanan",
    "sg:classifiers":[
        {
            "category":"Health Services",
            "subcategory":"Nursing And Care Facility",
            "type":"Services"
        },
        {
            "category":"Real Estate",
            "subcategory":"Real Estate Agent",
            "type":"Services"
        }
    ],
    "sg:phone":"+1 269 695 9842",
    "sg:postcode":"49107",
    "sg:province":"MI",
    "sg:tags":[
        "home",
        "manager",
        "retirement",
        "community"
    ],
    "wof:name":"Metea Court Seniors",
    "wof:placetype":"venue"
},
  "geometry": {"coordinates":[-86.351077,41.824906],"type":"Point"}
}