{
  "type": "Feature",
  "properties": {
    "iso:country":"US",
    "sg:address":"107 W Riverside St",
    "sg:city":"Williamston",
    "sg:classifiers":[
        {
            "category":"Organizations",
            "subcategory":"Community Association",
            "type":"Services"
        }
    ],
    "sg:phone":"+1 517 655 3238",
    "sg:postcode":"48895",
    "sg:province":"MI",
    "wof:name":"Michigan Area Rdo Enthusiasts",
    "wof:placetype":"venue"
},
  "geometry": {"coordinates":[-84.284909,42.691365],"type":"Point"}
}