{
  "type": "Feature",
  "properties": {
    "iso:country":"US",
    "sg:address":"725 Oakwood Rd",
    "sg:city":"Ortonville",
    "sg:classifiers":[
        {
            "category":"Sports & Exercise",
            "subcategory":"Bowling",
            "type":"Entertainment"
        }
    ],
    "sg:phone":"+1 248 627 3336",
    "sg:postcode":"48462",
    "sg:province":"MI",
    "sg:tags":[
        "center"
    ],
    "wof:name":"Steve Bowling",
    "wof:placetype":"venue"
},
  "geometry": {"coordinates":[-83.440268,42.858423],"type":"Point"}
}