{
  "type": "Feature",
  "properties": {
    "iso:country":"US",
    "sg:address":"510 S Cass St",
    "sg:city":"Mecosta",
    "sg:classifiers":[
        {
            "category":"Retail",
            "subcategory":"Auto Repair",
            "type":"Services"
        }
    ],
    "sg:phone":"+1 231 972 2564",
    "sg:postcode":"49332",
    "sg:province":"MI",
    "sg:tags":[
        "body",
        "automobile",
        "painting"
    ],
    "wof:name":"Mid State Auto Body",
    "wof:placetype":"venue"
},
  "geometry": {"coordinates":[-85.225403,43.61801],"type":"Point"}
}