{
  "type": "Feature",
  "properties": {
    "iso:country":"US",
    "sg:address":"2931 Judson Rd",
    "sg:city":"Spring Lake",
    "sg:classifiers":[
        {
            "category":"Personal",
            "subcategory":"Hair Removal",
            "type":"Services"
        }
    ],
    "sg:phone":"+1 616 847 1977",
    "sg:postcode":"49456",
    "sg:province":"MI",
    "wof:name":"LAP Financial Group",
    "wof:placetype":"venue"
},
  "geometry": {"coordinates":[-86.185743,43.120858],"type":"Point"}
}