{
  "type": "Feature",
  "properties": {
    "iso:country":"US",
    "sg:address":"832 S Main St",
    "sg:city":"Lapeer",
    "sg:classifiers":[
        {
            "category":"Shopping",
            "subcategory":"Gifts & Souvenirs",
            "type":"Retail Goods"
        }
    ],
    "sg:phone":"+1 810 664 1246",
    "sg:postcode":"48446",
    "sg:province":"MI",
    "sg:tags":[
        "party",
        "supply"
    ],
    "wof:name":"Depot Party Store",
    "wof:placetype":"venue"
},
  "geometry": {"coordinates":[-83.321562,43.039306],"type":"Point"}
}