{
  "type": "Feature",
  "properties": {
    "iso:country":"US",
    "sg:address":"32800 Lahser Rd",
    "sg:city":"Beverly Hills",
    "sg:classifiers":[
        {
            "category":"Real Estate",
            "subcategory":"Real Estate Agent",
            "type":"Services"
        }
    ],
    "sg:phone":"+1 248 593 8881",
    "sg:postcode":"48025",
    "sg:province":"MI",
    "wof:name":"James Merritt Real Estate Dev",
    "wof:placetype":"venue"
},
  "geometry": {"coordinates":[-83.264032,42.528304],"type":"Point"}
}