{
  "type": "Feature",
  "properties": {
    "iso:country":"US",
    "sg:address":"25223 Buick St",
    "sg:city":"Roseville",
    "sg:classifiers":[
        {
            "category":"Building & Trades",
            "subcategory":"Plumbing",
            "type":"Services"
        }
    ],
    "sg:phone":"+1 586 615 0808",
    "sg:postcode":"48066",
    "sg:province":"MI",
    "sg:tags":[
        "contractor"
    ],
    "wof:name":"Jims Sprinklers",
    "wof:placetype":"venue"
},
  "geometry": {"coordinates":[-82.956399,42.482449],"type":"Point"}
}