{
  "type": "Feature",
  "properties": {
    "iso:country":"US",
    "sg:address":"28409 Harper Ave",
    "sg:city":"Saint Clair Shores",
    "sg:classifiers":[
        {
            "category":"Autos & Motor Vehicles",
            "subcategory":"Auto Supplies",
            "type":"Retail Goods"
        },
        {
            "category":"Retail",
            "subcategory":"Auto Repair",
            "type":"Services"
        }
    ],
    "sg:phone":"+1 586 776 9201",
    "sg:postcode":"48081",
    "sg:province":"MI",
    "sg:tags":[
        "repairing",
        "transmission",
        "part",
        "automobile",
        "automotive"
    ],
    "wof:name":"Pointe Automatic Transmission",
    "wof:placetype":"venue"
},
  "geometry": {"coordinates":[-82.898003,42.502899],"type":"Point"}
}