{
  "type": "Feature",
  "properties": {
    "iso:country":"US",
    "sg:address":"2858 Crown Point Rd",
    "sg:city":"Stevensville",
    "sg:classifiers":[
        {
            "category":"Wholesale",
            "subcategory":"Home Furnishings",
            "type":"Manufacturing & Wholesale Goods"
        }
    ],
    "sg:phone":"+1 269 465 4270",
    "sg:postcode":"49127",
    "sg:province":"MI",
    "wof:name":"Frankly Creative Enterprises",
    "wof:placetype":"venue"
},
  "geometry": {"coordinates":[-86.523126,42.002173],"type":"Point"}
}