{
  "type": "Feature",
  "properties": {
    "iso:country":"US",
    "sg:address":"2023 Pine Grove Ave",
    "sg:city":"Port Huron",
    "sg:classifiers":[
        {
            "category":"Retail",
            "subcategory":"Auto Rental",
            "type":"Services"
        }
    ],
    "sg:phone":"+1 810 985 4668",
    "sg:postcode":"48060",
    "sg:province":"MI",
    "sg:tags":[
        "passenger",
        "car"
    ],
    "wof:name":"Econo Car Rentals",
    "wof:placetype":"venue"
},
  "geometry": {"coordinates":[-82.435328,42.996425],"type":"Point"}
}