{
  "type": "Feature",
  "properties": {
    "iso:country":"US",
    "sg:address":"5989 Tahoe Dr SE",
    "sg:city":"Grand Rapids",
    "sg:classifiers":[
        {
            "category":"Organizations",
            "subcategory":"Religious Organization",
            "type":"Services"
        }
    ],
    "sg:phone":"+1 616 954 6740",
    "sg:postcode":"49546",
    "sg:province":"MI",
    "sg:tags":[
        "youth",
        "evangelism"
    ],
    "wof:name":"Young Life",
    "wof:placetype":"venue"
},
  "geometry": {"coordinates":[-85.52002400000001,42.910302],"type":"Point"}
}