{
  "type": "Feature",
  "properties": {
    "iso:country":"US",
    "sg:address":"11833 Tall Tree Dr",
    "sg:city":"Plymouth",
    "sg:classifiers":[
        {
            "category":"Banks & Credit Unions",
            "subcategory":"Investment Brokerage",
            "type":"Services"
        }
    ],
    "sg:phone":"+1 734 451 0664",
    "sg:postcode":"48170",
    "sg:province":"MI",
    "sg:tags":[
        "advisory"
    ],
    "wof:name":"Kirk Nuechterlein Amer Xpress",
    "wof:placetype":"venue"
},
  "geometry": {"coordinates":[-83.48657799999999,42.3696],"type":"Point"}
}