{
  "type": "Feature",
  "properties": {
    "iso:country":"US",
    "sg:address":"1200 Woodfield East Dr SE",
    "sg:city":"Grand Rapids",
    "sg:classifiers":[
        {
            "category":"Professional",
            "type":"Services"
        }
    ],
    "sg:phone":"+1 616 224 2300",
    "sg:postcode":"49508",
    "sg:province":"MI",
    "sg:tags":[
        "establishment"
    ],
    "wof:name":"Amway Corp",
    "wof:placetype":"venue"
},
  "geometry": {"coordinates":[-85.638108,42.850411],"type":"Point"}
}