{
  "type": "Feature",
  "properties": {
    "iso:country":"US",
    "sg:address":"5265 Pointe Tremble Rd",
    "sg:city":"Algonac",
    "sg:classifiers":[
        {
            "category":"Retail",
            "subcategory":"Portrait Studio",
            "type":"Services"
        }
    ],
    "sg:phone":"+1 810 794 0951",
    "sg:postcode":"48001",
    "sg:province":"MI",
    "sg:tags":[
        "photo"
    ],
    "wof:name":"Blue Water Reflectrions",
    "wof:placetype":"venue"
},
  "geometry": {"coordinates":[-82.58296199999999,42.623208],"type":"Point"}
}