{
  "type": "Feature",
  "properties": {
    "iso:country":"US",
    "sg:address":"618 Ash St",
    "sg:city":"Kingsley",
    "sg:classifiers":[
        {
            "category":"Personal",
            "subcategory":"Beauty Salon",
            "type":"Services"
        }
    ],
    "sg:phone":"+1 231 263 5693",
    "sg:postcode":"49649",
    "sg:province":"MI",
    "sg:tags":[
        "shop"
    ],
    "wof:name":"Sallie's Beauty Salon",
    "wof:placetype":"venue"
},
  "geometry": {"coordinates":[-85.544718,44.581955],"type":"Point"}
}