{
  "type": "Feature",
  "properties": {
    "iso:country":"US",
    "sg:address":"2350 E Buno Rd",
    "sg:city":"Milford",
    "sg:classifiers":[
        {
            "category":"Building & Trades",
            "subcategory":"Landscaping Services",
            "type":"Services"
        }
    ],
    "sg:phone":"+1 248 685 2308",
    "sg:postcode":"48381",
    "sg:province":"MI",
    "sg:tags":[
        "landscape",
        "contractor"
    ],
    "sg:website":"www.national-landscape.com",
    "wof:name":"National Landscape",
    "wof:placetype":"venue"
},
  "geometry": {"coordinates":[-83.569147,42.552333],"type":"Point"}
}