{
  "type": "Feature",
  "properties": {
    "iso:country":"US",
    "sg:address":"605 N Mission St",
    "sg:city":"Mount Pleasant",
    "sg:classifiers":[
        {
            "category":"Professional",
            "subcategory":"Employment Agencies",
            "type":"Services"
        }
    ],
    "sg:phone":"+1 989 772 0315",
    "sg:postcode":"48858",
    "sg:province":"MI",
    "wof:name":"CD Workers",
    "wof:placetype":"venue"
},
  "geometry": {"coordinates":[-84.767821,43.609955],"type":"Point"}
}