{
  "type": "Feature",
  "properties": {
    "iso:country":"US",
    "sg:address":"4141 N Conway Rd",
    "sg:city":"Alanson",
    "sg:classifiers":[
        {
            "category":"Building & Trades",
            "subcategory":"Construction",
            "type":"Services"
        }
    ],
    "sg:phone":"+1 231 529 6787",
    "sg:postcode":"49706",
    "sg:province":"MI",
    "sg:tags":[
        "house"
    ],
    "wof:name":"Timothy Walker Builder",
    "wof:placetype":"venue"
},
  "geometry": {"coordinates":[-84.873053,45.490812],"type":"Point"}
}