{
  "type": "Feature",
  "properties": {
    "iso:country":"US",
    "sg:address":"301 N State St",
    "sg:city":"Alma",
    "sg:classifiers":[
        {
            "category":"Banks & Credit Unions",
            "subcategory":"Bank",
            "type":"Services"
        }
    ],
    "sg:phone":"+1 989 463 2185",
    "sg:postcode":"48801",
    "sg:province":"MI",
    "sg:website":"www.commercial-bank.com",
    "wof:name":"Commercial Bank",
    "wof:placetype":"venue"
},
  "geometry": {"coordinates":[-84.661846,43.378982],"type":"Point"}
}