{
  "type": "Feature",
  "properties": {
    "iso:country":"US",
    "sg:address":"1647 Inkster Rd",
    "sg:city":"Garden City",
    "sg:classifiers":[
        {
            "category":"Health Services",
            "subcategory":"Doctor",
            "type":"Services"
        }
    ],
    "sg:phone":"+1 734 421 5200",
    "sg:postcode":"48135",
    "sg:province":"MI",
    "sg:tags":[
        "surgeon",
        "oral"
    ],
    "wof:name":"Abramson Marc A DDS",
    "wof:placetype":"venue"
},
  "geometry": {"coordinates":[-83.311302,42.3223],"type":"Point"}
}