{
  "type": "Feature",
  "properties": {
    "iso:country":"US",
    "sg:address":"9191 Hadley Rd",
    "sg:city":"Litchfield",
    "sg:classifiers":[
        {
            "category":"Retail",
            "subcategory":"Animal Services",
            "type":"Services"
        }
    ],
    "sg:phone":"+1 517 542 3074",
    "sg:postcode":"49252",
    "sg:province":"MI",
    "wof:name":"High Country Kennels",
    "wof:placetype":"venue"
},
  "geometry": {"coordinates":[-84.806952,42.041124],"type":"Point"}
}