{
  "type": "Feature",
  "properties": {
    "iso:country":"US",
    "sg:address":"3780 Mackinaw Trl",
    "sg:city":"Leroy",
    "sg:classifiers":[
        {
            "category":"Restaurant",
            "type":"Food & Drink"
        }
    ],
    "sg:phone":"+1 231 768 5288",
    "sg:postcode":"49655",
    "sg:province":"MI",
    "wof:name":"Mr Pibs",
    "wof:placetype":"venue"
},
  "geometry": {"coordinates":[-85.459937,44.032691],"type":"Point"}
}