{
  "type": "Feature",
  "properties": {
    "iso:country":"US",
    "sg:address":"3201 Michigamme Woods Dr",
    "sg:city":"Kalamazoo",
    "sg:classifiers":[
        {
            "category":"Real Estate",
            "subcategory":"Real Estate Operator",
            "type":"Services"
        }
    ],
    "sg:phone":"+1 269 372 4655",
    "sg:postcode":"49006",
    "sg:province":"MI",
    "sg:tags":[
        "apartment",
        "complex"
    ],
    "wof:name":"West MI Woods Ltd Div Housing",
    "wof:placetype":"venue"
},
  "geometry": {"coordinates":[-85.63036099999999,42.277114],"type":"Point"}
}