{
  "type": "Feature",
  "properties": {
    "iso:country":"US",
    "sg:address":"22025 Greater Mack Ave",
    "sg:city":"Saint Clair Shores",
    "sg:classifiers":[
        {
            "category":"Autos & Motor Vehicles",
            "subcategory":"Auto Supplies",
            "type":"Retail Goods"
        }
    ],
    "sg:phone":"+1 586 771 7050",
    "sg:postcode":"48080",
    "sg:province":"MI",
    "sg:tags":[
        "tire"
    ],
    "wof:name":"Mack Alger Firestone Metro 25",
    "wof:placetype":"venue"
},
  "geometry": {"coordinates":[-82.90239699999999,42.456299],"type":"Point"}
}