{
  "type": "Feature",
  "properties": {
    "iso:country":"US",
    "sg:address":"4027 Stryker Dr",
    "sg:city":"Muskegon",
    "sg:classifiers":[
        {
            "category":"Retail",
            "subcategory":"Portrait Studio",
            "type":"Services"
        }
    ],
    "sg:phone":"+1 231 780 4555",
    "sg:postcode":"49441",
    "sg:province":"MI",
    "sg:tags":[
        "photographer"
    ],
    "wof:name":"Photos By Anton",
    "wof:placetype":"venue"
},
  "geometry": {"coordinates":[-86.279721,43.178708],"type":"Point"}
}