{
  "type": "Feature",
  "properties": {
    "iso:country":"US",
    "sg:address":"321 Wilson St",
    "sg:city":"Belding",
    "sg:classifiers":[
        {
            "category":"Social Services",
            "subcategory":"Child Care",
            "type":"Services"
        }
    ],
    "sg:phone":"+1 616 794 0119",
    "sg:postcode":"48809",
    "sg:province":"MI",
    "sg:tags":[
        "day"
    ],
    "wof:name":"Alma Public Schools",
    "wof:placetype":"venue"
},
  "geometry": {"coordinates":[-85.224296,43.095816],"type":"Point"}
}