{
  "type": "Feature",
  "properties": {
    "iso:country":"US",
    "sg:address":"1029 N Jebavy Dr",
    "sg:city":"Ludington",
    "sg:classifiers":[
        {
            "category":"Retail",
            "subcategory":"Repair Shop",
            "type":"Services"
        }
    ],
    "sg:phone":"+1 231 843 0043",
    "sg:postcode":"49431",
    "sg:province":"MI",
    "sg:tags":[
        "cleaning"
    ],
    "wof:name":"E-Z Clean",
    "wof:placetype":"venue"
},
  "geometry": {"coordinates":[-86.41922700000001,43.973581],"type":"Point"}
}