{
  "type": "Feature",
  "properties": {
    "iso:country":"US",
    "sg:address":"7806 Stevensville-Baroda Rd",
    "sg:city":"Baroda",
    "sg:classifiers":[
        {
            "category":"Professional",
            "subcategory":"Management & Consulting",
            "type":"Services"
        }
    ],
    "sg:phone":"+1 269 369 2054",
    "sg:postcode":"49101",
    "sg:province":"MI",
    "sg:tags":[
        "business"
    ],
    "wof:name":"Gwmeek LLC",
    "wof:placetype":"venue"
},
  "geometry": {"coordinates":[-86.495887,41.977555],"type":"Point"}
}