{
  "type": "Feature",
  "properties": {
    "iso:country":"US",
    "sg:address":"1160 Airport Rd",
    "sg:city":"Waterford",
    "sg:classifiers":[
        {
            "category":"Shopping",
            "type":"Retail Goods"
        }
    ],
    "sg:phone":"+1 248 673 0922",
    "sg:postcode":"48327",
    "sg:province":"MI",
    "sg:tags":[
        "equipment",
        "telephone",
        "supply"
    ],
    "wof:name":"Waterford Tele-Communications",
    "wof:placetype":"venue"
},
  "geometry": {"coordinates":[-83.405573,42.65316],"type":"Point"}
}