{
  "type": "Feature",
  "properties": {
    "iso:country":"US",
    "sg:address":"220 E Lewis Ave",
    "sg:city":"Milan",
    "sg:classifiers":[
        {
            "category":"Building & Trades",
            "subcategory":"Construction",
            "type":"Services"
        }
    ],
    "sg:phone":"+1 734 439 2697",
    "sg:postcode":"48160",
    "sg:province":"MI",
    "sg:tags":[
        "house"
    ],
    "wof:name":"David M Conger Licensed Bldr",
    "wof:placetype":"venue"
},
  "geometry": {"coordinates":[-83.67877900000001,42.094297],"type":"Point"}
}