{
  "type": "Feature",
  "properties": {
    "iso:country":"US",
    "sg:address":"10 W Main St",
    "sg:city":"Hartford",
    "sg:classifiers":[
        {
            "category":"Shopping",
            "subcategory":"Used Merchandise",
            "type":"Retail Goods"
        }
    ],
    "sg:phone":"+1 269 621 0997",
    "sg:postcode":"49057",
    "sg:province":"MI",
    "wof:name":"Hartford Outlet",
    "wof:placetype":"venue"
},
  "geometry": {"coordinates":[-86.166854,42.206832],"type":"Point"}
}