{
  "type": "Feature",
  "properties": {
    "iso:country":"US",
    "sg:address":"3100 Copper Ave",
    "sg:city":"Fenton",
    "sg:classifiers":[
        {
            "category":"Manufacturing",
            "subcategory":"Tools & Machinery",
            "type":"Manufacturing & Wholesale Goods"
        }
    ],
    "sg:phone":"+1 810 629 6663",
    "sg:postcode":"48430",
    "sg:province":"MI",
    "sg:tags":[
        "equipment",
        "system",
        "automation"
    ],
    "sg:website":"www.atlastechnologies.com",
    "wof:name":"Atlas Technologies Inc",
    "wof:placetype":"venue"
},
  "geometry": {"coordinates":[-83.73041600000001,42.792735],"type":"Point"}
}