{
  "type": "Feature",
  "properties": {
    "iso:country":"US",
    "sg:address":"17515 W 9 Mile Rd Ste 420",
    "sg:city":"Southfield",
    "sg:classifiers":[
        {
            "category":"Professional",
            "subcategory":"Lawyer & Legal Services",
            "type":"Services"
        }
    ],
    "sg:phone":"+1 248 559 4055",
    "sg:postcode":"48075",
    "sg:province":"MI",
    "sg:website":"www.steinbergerlaw.com",
    "wof:name":"Steinberger John A PC",
    "wof:placetype":"venue"
},
  "geometry": {"coordinates":[-83.21790300000001,42.4589],"type":"Point"}
}