{
  "type": "Feature",
  "properties": {
    "iso:country":"US",
    "sg:address":"3533 S 35th St",
    "sg:city":"Galesburg",
    "sg:classifiers":[
        {
            "category":"Building & Trades",
            "subcategory":"Construction",
            "type":"Services"
        }
    ],
    "sg:phone":"+1 269 665 9107",
    "sg:postcode":"49053",
    "sg:province":"MI",
    "sg:tags":[
        "general",
        "contractor"
    ],
    "wof:name":"Max Haase & Son Custom Builder",
    "wof:placetype":"venue"
},
  "geometry": {"coordinates":[-85.42840099999999,42.256712],"type":"Point"}
}