{
  "type": "Feature",
  "properties": {
    "iso:country":"US",
    "sg:address":"819 Hamman Rd",
    "sg:city":"Montgomery",
    "sg:phone":"+1 517 238 2254",
    "sg:postcode":"49255",
    "sg:province":"MI",
    "sg:tags":[
        "farm",
        "corn",
        "soybean"
    ],
    "wof:name":"Ed Kuryvail",
    "wof:placetype":"venue"
},
  "geometry": {"coordinates":[-84.893063,41.794265],"type":"Point"}
}