{
  "type": "Feature",
  "properties": {
    "iso:country":"US",
    "sg:address":"1450 E South Blvd",
    "sg:city":"Troy",
    "sg:classifiers":[
        {
            "category":"Sports & Exercise",
            "subcategory":"Golf",
            "type":"Entertainment"
        }
    ],
    "sg:phone":"+1 248 619 7600",
    "sg:postcode":"48085",
    "sg:province":"MI",
    "wof:name":"Santuary Lake Golf Course",
    "wof:placetype":"venue"
},
  "geometry": {"coordinates":[-83.100297,42.623813],"type":"Point"}
}