{
  "type": "Feature",
  "properties": {
    "iso:country":"US",
    "sg:address":"4012 N Waldo Rd",
    "sg:city":"Midland",
    "sg:classifiers":[
        {
            "category":"Social Services",
            "subcategory":"Adult Care",
            "type":"Services"
        }
    ],
    "sg:phone":"+1 989 832 5000",
    "sg:postcode":"48642",
    "sg:province":"MI",
    "sg:tags":[
        "home",
        "residential"
    ],
    "wof:name":"Alterra Clare Bridge",
    "wof:placetype":"venue"
},
  "geometry": {"coordinates":[-84.186905,43.722439],"type":"Point"}
}