{
  "type": "Feature",
  "properties": {
    "iso:country":"US",
    "sg:address":"9602 S Beyer Rd",
    "sg:city":"Birch Run",
    "sg:classifiers":[
        {
            "category":"Building & Trades",
            "subcategory":"Landscaping Services",
            "type":"Services"
        }
    ],
    "sg:phone":"+1 989 624 1322",
    "sg:postcode":"48415",
    "sg:province":"MI",
    "wof:name":"American Tree Movers Etc",
    "wof:placetype":"venue"
},
  "geometry": {"coordinates":[-83.77441899999999,43.283971],"type":"Point"}
}