{
  "type": "Feature",
  "properties": {
    "iso:country":"US",
    "sg:address":"900 W Hamlin Rd",
    "sg:city":"Rochester Hills",
    "sg:classifiers":[
        {
            "category":"Organizations",
            "subcategory":"Religious Organization",
            "type":"Services"
        }
    ],
    "sg:phone":"+1 248 650 3770",
    "sg:postcode":"48307",
    "sg:province":"MI",
    "sg:tags":[
        "church"
    ],
    "wof:name":"Covenant Christian Church",
    "wof:placetype":"venue"
},
  "geometry": {"coordinates":[-83.15066,42.652107],"type":"Point"}
}