{
  "type": "Feature",
  "properties": {
    "iso:country":"US",
    "sg:address":"601 W Houghton Ave",
    "sg:city":"West Branch",
    "sg:classifiers":[
        {
            "category":"Professional",
            "subcategory":"Accounting & Tax Preparation",
            "type":"Services"
        }
    ],
    "sg:phone":"+1 989 345 2219",
    "sg:postcode":"48661",
    "sg:province":"MI",
    "wof:name":"Elizabeth Steinhurst CPA",
    "wof:placetype":"venue"
},
  "geometry": {"coordinates":[-84.24388999999999,44.276253],"type":"Point"}
}