{
  "type": "Feature",
  "properties": {
    "iso:country":"US",
    "sg:address":"48709 Van Dyke Ave",
    "sg:city":"Utica",
    "sg:classifiers":[
        {
            "category":"Health Services",
            "subcategory":"Doctor",
            "type":"Services"
        }
    ],
    "sg:phone":"+1 586 731 3000",
    "sg:postcode":"48317",
    "sg:province":"MI",
    "wof:name":"Feuer Marshall B DDS",
    "wof:placetype":"venue"
},
  "geometry": {"coordinates":[-83.03344300000001,42.652947],"type":"Point"}
}