{
  "type": "Feature",
  "properties": {
    "iso:country":"US",
    "sg:address":"350 N Main St",
    "sg:city":"Onsted",
    "sg:classifiers":[
        {
            "category":"Real Estate",
            "subcategory":"Real Estate Operator",
            "type":"Services"
        }
    ],
    "sg:phone":"+1 517 467 2508",
    "sg:postcode":"49265",
    "sg:province":"MI",
    "sg:tags":[
        "apartment"
    ],
    "wof:name":"Wexford Manor",
    "wof:placetype":"venue"
},
  "geometry": {"coordinates":[-84.189722,42.011026],"type":"Point"}
}