{
  "type": "Feature",
  "properties": {
    "iso:country":"US",
    "sg:address":"321 Johnson Rd",
    "sg:city":"Gaylord",
    "sg:classifiers":[
        {
            "category":"Travel",
            "subcategory":"Hotels & Motels",
            "type":"Entertainment"
        }
    ],
    "sg:phone":"+1 989 731 6708",
    "sg:postcode":"49735",
    "sg:province":"MI",
    "sg:tags":[
        "operation"
    ],
    "wof:name":"Brentwood Inn",
    "wof:placetype":"venue"
},
  "geometry": {"coordinates":[-84.665381,44.98694],"type":"Point"}
}