{
  "type": "Feature",
  "properties": {
    "iso:country":"US",
    "sg:address":"3536 Harbor Acres Dr",
    "sg:city":"Sodus",
    "sg:classifiers":[
        {
            "category":"Professional",
            "type":"Services"
        }
    ],
    "sg:phone":"+1 269 925 4949",
    "sg:postcode":"49126",
    "sg:province":"MI",
    "wof:name":"Steven Macgowen Studio",
    "wof:placetype":"venue"
},
  "geometry": {"coordinates":[-86.388318,42.05436],"type":"Point"}
}