{
  "type": "Feature",
  "properties": {
    "iso:country":"US",
    "sg:address":"212 River",
    "sg:city":"Elk Rapids",
    "sg:classifiers":[
        {
            "category":"Building & Trades",
            "subcategory":"Construction",
            "type":"Services"
        }
    ],
    "sg:phone":"+1 231 264 6342",
    "sg:postcode":"49629",
    "sg:province":"MI",
    "sg:tags":[
        "carpentry",
        "contractor"
    ],
    "wof:name":"Clearwater Carpentry",
    "wof:placetype":"venue"
},
  "geometry": {"coordinates":[-85.414373,44.897916],"type":"Point"}
}