{
  "type": "Feature",
  "properties": {
    "iso:country":"US",
    "sg:address":"14740 Plymouth Rd",
    "sg:city":"Detroit",
    "sg:classifiers":[
        {
            "category":"Social Services",
            "subcategory":"Child Care",
            "type":"Services"
        },
        {
            "category":"Education",
            "subcategory":"Preschool",
            "type":"Public Place"
        },
        {
            "category":"Education",
            "subcategory":"School",
            "type":"Public Place"
        }
    ],
    "sg:phone":"+1 313 272 0934",
    "sg:postcode":"48227",
    "sg:province":"MI",
    "sg:tags":[
        "elementary",
        "day"
    ],
    "wof:name":"Toddler Center Daycare the",
    "wof:placetype":"venue"
},
  "geometry": {"coordinates":[-83.189201,42.372898],"type":"Point"}
}