{
  "type": "Feature",
  "properties": {
    "iso:country":"US",
    "sg:address":"4801 W Saginaw Hwy",
    "sg:city":"Lansing",
    "sg:classifiers":[
        {
            "category":"Personal",
            "type":"Services"
        }
    ],
    "sg:phone":"+1 517 323 7444",
    "sg:postcode":"48917",
    "sg:province":"MI",
    "sg:tags":[
        "tuxedo",
        "rental",
        "or",
        "sales"
    ],
    "wof:name":"Davids Bridal",
    "wof:placetype":"venue"
},
  "geometry": {"coordinates":[-84.61823,42.741084],"type":"Point"}
}