{
  "type": "Feature",
  "properties": {
    "iso:country":"US",
    "sg:address":"208 W Boulevard St",
    "sg:city":"Shepherd",
    "sg:classifiers":[
        {
            "category":"Retail",
            "subcategory":"Auto Repair",
            "type":"Services"
        }
    ],
    "sg:phone":"+1 989 828 5062",
    "sg:postcode":"48883",
    "sg:province":"MI",
    "sg:tags":[
        "general"
    ],
    "wof:name":"Village Garage",
    "wof:placetype":"venue"
},
  "geometry": {"coordinates":[-84.692791,43.529165],"type":"Point"}
}