{
  "type": "Feature",
  "properties": {
    "iso:country":"US",
    "sg:address":"4332 Oak Pointe Dr",
    "sg:city":"Brighton",
    "sg:classifiers":[
        {
            "category":"Wholesale",
            "subcategory":"Machinery & Supplies",
            "type":"Manufacturing & Wholesale Goods"
        }
    ],
    "sg:phone":"+1 810 220 7886",
    "sg:postcode":"48116",
    "sg:province":"MI",
    "sg:tags":[
        "material",
        "handling"
    ],
    "wof:name":"Adept Technology Inc",
    "wof:placetype":"venue"
},
  "geometry": {"coordinates":[-83.865903,42.533415],"type":"Point"}
}