{
  "type": "Feature",
  "properties": {
    "iso:country":"US",
    "sg:address":"32020 Edward Ave",
    "sg:city":"Madison Heights",
    "sg:classifiers":[
        {
            "category":"Manufacturing",
            "subcategory":"Tools & Machinery",
            "type":"Manufacturing & Wholesale Goods"
        }
    ],
    "sg:phone":"+1 248 583 9636",
    "sg:postcode":"48071",
    "sg:province":"MI",
    "sg:tags":[
        "machine",
        "shop"
    ],
    "wof:name":"Triad Manufacturing Co",
    "wof:placetype":"venue"
},
  "geometry": {"coordinates":[-83.101822,42.530204],"type":"Point"}
}