{
  "type": "Feature",
  "properties": {
    "iso:country":"US",
    "sg:address":"20787 Albany Ave",
    "sg:city":"Warren",
    "sg:classifiers":[
        {
            "category":"Shopping",
            "subcategory":"Hobbies, Toys, & Games",
            "type":"Retail Goods"
        }
    ],
    "sg:phone":"+1 586 759 4745",
    "sg:postcode":"48091",
    "sg:province":"MI",
    "wof:name":"Toms Darts & Supplys",
    "wof:placetype":"venue"
},
  "geometry": {"coordinates":[-83.045635,42.449567],"type":"Point"}
}