{
  "type": "Feature",
  "properties": {
    "iso:country":"US",
    "sg:address":"5318 Pointe Tremble Rd",
    "sg:city":"Algonac",
    "sg:classifiers":[
        {
            "category":"Professional",
            "subcategory":"Management & Consulting",
            "type":"Services"
        },
        {
            "category":"Wholesale",
            "subcategory":"Durable Goods & Equipment",
            "type":"Manufacturing & Wholesale Goods"
        }
    ],
    "sg:phone":"+1 810 794 2000",
    "sg:postcode":"48001",
    "sg:province":"MI",
    "sg:tags":[
        "consultant",
        "industrial"
    ],
    "sg:website":"www.fannoninfrared.com",
    "wof:name":"Fannon Products LLC",
    "wof:placetype":"venue"
},
  "geometry": {"coordinates":[-82.585223,42.62365],"type":"Point"}
}