{
  "type": "Feature",
  "properties": {
    "iso:country":"US",
    "sg:address":"50721 Wing Dr",
    "sg:city":"Shelby Twp",
    "sg:classifiers":[
        {
            "category":"Building & Trades",
            "subcategory":"Construction",
            "type":"Services"
        }
    ],
    "sg:phone":"+1 586 532 7000",
    "sg:postcode":"48315",
    "sg:province":"MI",
    "sg:tags":[
        "acoustical",
        "contractor"
    ],
    "wof:name":"Acoustical Ceiling Contractors",
    "wof:placetype":"venue"
},
  "geometry": {"coordinates":[-82.98502000000001,42.668621],"type":"Point"}
}