{
  "type": "Feature",
  "properties": {
    "iso:country":"US",
    "sg:address":"4646 28th St SE",
    "sg:city":"Grand Rapids",
    "sg:classifiers":[
        {
            "category":"Professional",
            "subcategory":"Management & Consulting",
            "type":"Services"
        }
    ],
    "sg:phone":"+1 616 975 7404",
    "sg:postcode":"49512",
    "sg:province":"MI",
    "wof:name":"Home Depot",
    "wof:placetype":"venue"
},
  "geometry": {"coordinates":[-85.556769,42.91248],"type":"Point"}
}