{
  "type": "Feature",
  "properties": {
    "iso:country":"US",
    "sg:address":"4435 W Saginaw Hwy",
    "sg:city":"Lansing",
    "sg:classifiers":[
        {
            "category":"Professional",
            "subcategory":"Accounting & Tax Preparation",
            "type":"Services"
        }
    ],
    "sg:phone":"+1 517 327 8244",
    "sg:postcode":"48917",
    "sg:province":"MI",
    "sg:tags":[
        "accountant"
    ],
    "wof:name":"Day Arthur Tax & Accounting",
    "wof:placetype":"venue"
},
  "geometry": {"coordinates":[-84.61134300000001,42.741035],"type":"Point"}
}