{
  "type": "Feature",
  "properties": {
    "iso:country":"US",
    "sg:address":"6400 W Blue Rd",
    "sg:city":"Lake City",
    "sg:classifiers":[
        {
            "category":"Manufacturing",
            "subcategory":"Rubber & Plastics",
            "type":"Manufacturing & Wholesale Goods"
        }
    ],
    "sg:phone":"+1 231 839 5309",
    "sg:postcode":"49651",
    "sg:province":"MI",
    "sg:tags":[
        "product"
    ],
    "wof:name":"Missaukee Molded Rubber",
    "wof:placetype":"venue"
},
  "geometry": {"coordinates":[-85.23040899999999,44.266673],"type":"Point"}
}