{
  "type": "Feature",
  "properties": {
    "iso:country":"US",
    "sg:address":"11404 Rugby Dr NW",
    "sg:city":"Grand Rapids",
    "sg:classifiers":[
        {
            "category":"Shopping",
            "subcategory":"Gifts & Souvenirs",
            "type":"Retail Goods"
        }
    ],
    "sg:phone":"+1 616 453 2260",
    "sg:postcode":"49544",
    "sg:province":"MI",
    "wof:name":"Pat S Curios Sew Alterations",
    "wof:placetype":"venue"
},
  "geometry": {"coordinates":[-85.802734,42.975199],"type":"Point"}
}