{
  "type": "Feature",
  "properties": {
    "iso:country":"US",
    "sg:address":"915 24th St",
    "sg:city":"Port Huron",
    "sg:classifiers":[
        {
            "category":"Restaurant",
            "type":"Food & Drink"
        }
    ],
    "sg:menulink":"http://www.allmenus.com/mi/port-huron/84447-papa-johns-pizza/menu/",
    "sg:phone":"+1 810 985 7272",
    "sg:postcode":"48060",
    "sg:province":"MI",
    "sg:tags":[
        "american",
        "pizza"
    ],
    "wof:name":"Papa John's Pizza",
    "wof:placetype":"venue"
},
  "geometry": {"coordinates":[-82.45276,42.973764],"type":"Point"}
}