{
  "type": "Feature",
  "properties": {
    "iso:country":"US",
    "sg:address":"324 Forest Hill Ave SE",
    "sg:city":"Grand Rapids",
    "sg:classifiers":[
        {
            "category":"Health Services",
            "subcategory":"Doctor",
            "type":"Services"
        }
    ],
    "sg:phone":"+1 616 949 2138",
    "sg:postcode":"49546",
    "sg:province":"MI",
    "sg:tags":[
        "medical"
    ],
    "wof:name":"Emergency Phy Inc",
    "wof:placetype":"venue"
},
  "geometry": {"coordinates":[-85.555803,42.955075],"type":"Point"}
}