{
  "type": "Feature",
  "properties": {
    "iso:country":"US",
    "sg:address":"108 W Saint Joe St",
    "sg:city":"Litchfield",
    "sg:classifiers":[
        {
            "category":"Building & Trades",
            "subcategory":"Electrical",
            "type":"Services"
        }
    ],
    "sg:phone":"+1 517 542 3465",
    "sg:postcode":"49252",
    "sg:province":"MI",
    "sg:tags":[
        "electric",
        "contractor"
    ],
    "wof:name":"Wade Electro Svc",
    "wof:placetype":"venue"
},
  "geometry": {"coordinates":[-84.760181,42.043927],"type":"Point"}
}