{
  "type": "Feature",
  "properties": {
    "iso:country":"US",
    "sg:address":"2110 S Cedar St",
    "sg:city":"Lansing",
    "sg:classifiers":[
        {
            "category":"Social Services",
            "subcategory":"Job Training",
            "type":"Services"
        }
    ],
    "sg:phone":"+1 517 492 5599",
    "sg:postcode":"48910",
    "sg:province":"MI",
    "sg:tags":[
        "related"
    ],
    "sg:website":"www.camw.net",
    "wof:name":"Capital Area Michigan Works",
    "wof:placetype":"venue"
},
  "geometry": {"coordinates":[-84.54805399999999,42.710908],"type":"Point"}
}