{
  "type": "Feature",
  "properties": {
    "iso:country":"US",
    "sg:address":"7861 Wagner",
    "sg:city":"Ira",
    "sg:classifiers":[
        {
            "category":"Wholesale",
            "subcategory":"Electrical",
            "type":"Manufacturing & Wholesale Goods"
        }
    ],
    "sg:phone":"+1 586 725 1861",
    "sg:postcode":"48023",
    "sg:province":"MI",
    "sg:tags":[
        "control",
        "security",
        "system"
    ],
    "wof:name":"Alarm Engineering Svc",
    "wof:placetype":"venue"
},
  "geometry": {"coordinates":[-82.649978,42.676674],"type":"Point"}
}