{
  "type": "Feature",
  "properties": {
    "iso:country":"US",
    "sg:address":"30153 Shoreham St",
    "sg:city":"Southfield",
    "sg:classifiers":[
        {
            "category":"Real Estate",
            "subcategory":"Real Estate Agent",
            "type":"Services"
        }
    ],
    "sg:phone":"+1 248 258 6421",
    "sg:postcode":"48076",
    "sg:province":"MI",
    "sg:tags":[
        "investment"
    ],
    "wof:name":"S & H Realty Investments Inc",
    "wof:placetype":"venue"
},
  "geometry": {"coordinates":[-83.241674,42.512426],"type":"Point"}
}