{
  "type": "Feature",
  "properties": {
    "iso:country":"US",
    "sg:address":"7295 50th Ave",
    "sg:city":"Sears",
    "sg:classifiers":[
        {
            "category":"Home & Garden",
            "subcategory":"Household Appliances",
            "type":"Retail Goods"
        }
    ],
    "sg:phone":"+1 231 825 4013",
    "sg:postcode":"49679",
    "sg:province":"MI",
    "sg:tags":[
        "refrigerator",
        "freezer"
    ],
    "wof:name":"Miller Refrigeration",
    "wof:placetype":"venue"
},
  "geometry": {"coordinates":[-85.188346,43.92878],"type":"Point"}
}