{
  "type": "Feature",
  "properties": {
    "iso:country":"US",
    "sg:address":"429 Mitchell St",
    "sg:city":"Marshall",
    "sg:classifiers":[
        {
            "category":"Retail",
            "subcategory":"Animal Services",
            "type":"Services"
        }
    ],
    "sg:phone":"+1 269 781 3645",
    "sg:postcode":"49068",
    "sg:province":"MI",
    "wof:name":"Animal House Grooming Salon",
    "wof:placetype":"venue"
},
  "geometry": {"coordinates":[-84.96802099999999,42.267729],"type":"Point"}
}