{
  "type": "Feature",
  "properties": {
    "iso:country":"US",
    "sg:address":"7255 Bluewater Dr",
    "sg:city":"Clarkston",
    "sg:classifiers":[
        {
            "category":"Personal",
            "type":"Services"
        }
    ],
    "sg:phone":"+1 248 625 2994",
    "sg:postcode":"48348",
    "sg:province":"MI",
    "sg:tags":[
        "program",
        "physical",
        "exercise",
        "fitness"
    ],
    "wof:name":"Clarkston Fitness & Nutrition",
    "wof:placetype":"venue"
},
  "geometry": {"coordinates":[-83.464268,42.74205],"type":"Point"}
}