{
  "type": "Feature",
  "properties": {
    "iso:country":"US",
    "sg:address":"15530 Farmington Rd",
    "sg:city":"Livonia",
    "sg:classifiers":[
        {
            "category":"Professional",
            "subcategory":"Lawyer & Legal Services",
            "type":"Services"
        }
    ],
    "sg:phone":"+1 734 421 4220",
    "sg:postcode":"48154",
    "sg:province":"MI",
    "wof:name":"Stevens David A Atty",
    "wof:placetype":"venue"
},
  "geometry": {"coordinates":[-83.373497,42.4002],"type":"Point"}
}