{
  "type": "Feature",
  "properties": {
    "iso:country":"US",
    "sg:address":"19770 Mack Ave",
    "sg:city":"Grosse Pointe",
    "sg:classifiers":[
        {
            "category":"Banks & Credit Unions",
            "subcategory":"Investment Brokerage",
            "type":"Services"
        }
    ],
    "sg:phone":"+1 313 417 2600",
    "sg:postcode":"48236",
    "sg:province":"MI",
    "sg:tags":[
        "security"
    ],
    "wof:name":"McDonald Investments Inc",
    "wof:placetype":"venue"
},
  "geometry": {"coordinates":[-82.909102,42.42835],"type":"Point"}
}