{
  "type": "Feature",
  "properties": {
    "iso:country":"US",
    "sg:address":"6160 Minosa Dr SE",
    "sg:city":"Grand Rapids",
    "sg:classifiers":[
        {
            "category":"Cinema",
            "subcategory":"Movie Rental",
            "type":"Entertainment"
        }
    ],
    "sg:phone":"+1 616 281 2886",
    "sg:postcode":"49548",
    "sg:province":"MI",
    "sg:tags":[
        "video",
        "tape"
    ],
    "wof:name":"John Barr Vdeo Mstr Plainfield",
    "wof:placetype":"venue"
},
  "geometry": {"coordinates":[-85.65170500000001,42.851957],"type":"Point"}
}