{
  "type": "Feature",
  "properties": {
    "iso:country":"US",
    "sg:address":"4601 W Saginaw Hwy",
    "sg:city":"Lansing",
    "sg:classifiers":[
        {
            "category":"Professional",
            "subcategory":"Management & Consulting",
            "type":"Services"
        }
    ],
    "sg:phone":"+1 517 323 8149",
    "sg:postcode":"48917",
    "sg:province":"MI",
    "wof:name":"Prevention Trining Svc P A T S",
    "wof:placetype":"venue"
},
  "geometry": {"coordinates":[-84.615161,42.741051],"type":"Point"}
}