{
  "type": "Feature",
  "properties": {
    "iso:country":"US",
    "sg:address":"160 Brown Rd",
    "sg:city":"Auburn Hills",
    "sg:classifiers":[
        {
            "category":"Restaurant",
            "type":"Food & Drink"
        }
    ],
    "sg:menulink":"http://www.allmenus.com/mi/orion/210726-arbys/menu/",
    "sg:phone":"+1 248 393 1255",
    "sg:postcode":"48326",
    "sg:province":"MI",
    "sg:tags":[
        "burger",
        "american"
    ],
    "wof:name":"Arby's",
    "wof:placetype":"venue"
},
  "geometry": {"coordinates":[-83.30186,42.707227],"type":"Point"}
}