{
  "type": "Feature",
  "properties": {
    "iso:country":"US",
    "sg:address":"4601 Center St",
    "sg:city":"Millington",
    "sg:classifiers":[
        {
            "category":"Autos & Motor Vehicles",
            "subcategory":"Automobile Sales",
            "type":"Retail Goods"
        }
    ],
    "sg:phone":"+1 517 871 2780",
    "sg:postcode":"48746",
    "sg:province":"MI",
    "sg:tags":[
        "used"
    ],
    "wof:name":"L A Autos",
    "wof:placetype":"venue"
},
  "geometry": {"coordinates":[-83.52577599999999,43.279876],"type":"Point"}
}