{
  "type": "Feature",
  "properties": {
    "iso:country":"US",
    "sg:address":"3020 US Hwy 23 N",
    "sg:city":"Alpena",
    "sg:classifiers":[
        {
            "category":"Social Services",
            "type":"Services"
        }
    ],
    "sg:phone":"+1 989 356 2560",
    "sg:postcode":"49707",
    "sg:province":"MI",
    "sg:tags":[
        "substance",
        "center",
        "abuse"
    ],
    "wof:name":"Shelter Inc",
    "wof:placetype":"venue"
},
  "geometry": {"coordinates":[-83.455681,45.097911],"type":"Point"}
}