{
  "type": "Feature",
  "properties": {
    "iso:country":"US",
    "sg:address":"701 W Filmore Rd",
    "sg:city":"Hart",
    "sg:classifiers":[
        {
            "category":"Farming",
            "subcategory":"Livestock Farm",
            "type":"Manufacturing & Wholesale Goods"
        }
    ],
    "sg:phone":"+1 231 873 2932",
    "sg:postcode":"49420",
    "sg:province":"MI",
    "sg:tags":[
        "beef",
        "feedlot",
        "cattle"
    ],
    "wof:name":"Kenneth Johnson",
    "wof:placetype":"venue"
},
  "geometry": {"coordinates":[-86.298221,43.658295],"type":"Point"}
}