{
  "type": "Feature",
  "properties": {
    "iso:country":"US",
    "sg:address":"95 W Burdick St",
    "sg:city":"Oxford",
    "sg:classifiers":[
        {
            "category":"Restaurant",
            "type":"Food & Drink"
        }
    ],
    "sg:menulink":"http://www.allmenus.com/mi/oxford/142450-subway/menu/",
    "sg:phone":"+1 248 969 6920",
    "sg:postcode":"48371",
    "sg:province":"MI",
    "sg:tags":[
        "american",
        "sandwich"
    ],
    "wof:name":"Subway",
    "wof:placetype":"venue"
},
  "geometry": {"coordinates":[-83.27314800000001,42.824529],"type":"Point"}
}