{
  "type": "Feature",
  "properties": {
    "iso:country":"US",
    "sg:address":"816 Maple St",
    "sg:city":"Big Rapids",
    "sg:classifiers":[
        {
            "category":"Cinema",
            "subcategory":"Movie Rental",
            "type":"Entertainment"
        }
    ],
    "sg:phone":"+1 231 796 0700",
    "sg:postcode":"49307",
    "sg:province":"MI",
    "sg:tags":[
        "leasing",
        "video",
        "disc",
        "tape"
    ],
    "wof:name":"Video City",
    "wof:placetype":"venue"
},
  "geometry": {"coordinates":[-85.472465,43.700821],"type":"Point"}
}