{
  "type": "Feature",
  "properties": {
    "iso:country":"US",
    "sg:address":"604 S Lapeer Rd",
    "sg:city":"Lake Orion",
    "sg:classifiers":[
        {
            "category":"Shopping",
            "subcategory":"Bicycles & Sporting Goods",
            "type":"Retail Goods"
        }
    ],
    "sg:phone":"+1 248 693 9801",
    "sg:postcode":"48362",
    "sg:province":"MI",
    "sg:tags":[
        "equipment",
        "diver",
        "supply"
    ],
    "wof:name":"Diver's Den",
    "wof:placetype":"venue"
},
  "geometry": {"coordinates":[-83.238849,42.769103],"type":"Point"}
}