{
  "type": "Feature",
  "properties": {
    "iso:country":"US",
    "sg:address":"341 E Linwood Rd",
    "sg:city":"Linwood",
    "sg:classifiers":[
        {
            "category":"Farming",
            "subcategory":"Farm",
            "type":"Manufacturing & Wholesale Goods"
        }
    ],
    "sg:phone":"+1 989 697 4389",
    "sg:postcode":"48634",
    "sg:province":"MI",
    "wof:name":"D & D Schultz Farms",
    "wof:placetype":"venue"
},
  "geometry": {"coordinates":[-84.034333,43.739218],"type":"Point"}
}