{
  "type": "Feature",
  "properties": {
    "iso:country":"US",
    "sg:address":"33837 Harper Ave",
    "sg:city":"Clinton Twp",
    "sg:classifiers":[
        {
            "category":"Wholesale",
            "subcategory":"Machinery & Supplies",
            "type":"Manufacturing & Wholesale Goods"
        }
    ],
    "sg:phone":"+1 586 792 4442",
    "sg:postcode":"48035",
    "sg:province":"MI",
    "sg:tags":[
        "janitor"
    ],
    "wof:name":"Arnold Sales",
    "wof:placetype":"venue"
},
  "geometry": {"coordinates":[-82.878269,42.544749],"type":"Point"}
}