{
  "type": "Feature",
  "properties": {
    "iso:country":"US",
    "sg:address":"16667 Waterman Dr",
    "sg:city":"Roseville",
    "sg:classifiers":[
        {
            "category":"Building & Trades",
            "subcategory":"Construction",
            "type":"Services"
        }
    ],
    "sg:phone":"+1 586 778 0232",
    "sg:postcode":"48066",
    "sg:province":"MI",
    "sg:tags":[
        "house"
    ],
    "wof:name":"Foster Construction Co",
    "wof:placetype":"venue"
},
  "geometry": {"coordinates":[-82.94861400000001,42.482176],"type":"Point"}
}