{
  "type": "Feature",
  "properties": {
    "iso:country":"US",
    "sg:address":"2435 E Grand River Ave",
    "sg:city":"Howell",
    "sg:classifiers":[
        {
            "category":"Retail",
            "subcategory":"Repair Shop",
            "type":"Services"
        }
    ],
    "sg:phone":"+1 517 546 2790",
    "sg:postcode":"48843",
    "sg:province":"MI",
    "sg:tags":[
        "automotive"
    ],
    "wof:name":"Howell Lawn Mower & RAD Svc",
    "wof:placetype":"venue"
},
  "geometry": {"coordinates":[-83.90551000000001,42.598242],"type":"Point"}
}