{
  "type": "Feature",
  "properties": {
    "iso:country":"US",
    "sg:address":"6059 S 9th St",
    "sg:city":"Kalamazoo",
    "sg:classifiers":[
        {
            "category":"Real Estate",
            "subcategory":"Architect",
            "type":"Services"
        }
    ],
    "sg:phone":"+1 269 375 5584",
    "sg:postcode":"49009",
    "sg:province":"MI",
    "sg:tags":[
        "architectural"
    ],
    "wof:name":"George W Sprau",
    "wof:placetype":"venue"
},
  "geometry": {"coordinates":[-85.677504,42.230111],"type":"Point"}
}