{
  "type": "Feature",
  "properties": {
    "iso:country":"US",
    "sg:address":"3415 E Traverse Hwy",
    "sg:city":"Traverse City",
    "sg:classifiers":[
        {
            "category":"Building & Trades",
            "subcategory":"Construction",
            "type":"Services"
        }
    ],
    "sg:phone":"+1 231 228 6465",
    "sg:postcode":"49684",
    "sg:province":"MI",
    "sg:tags":[
        "steel",
        "erectors"
    ],
    "wof:name":"T L Steel Erection Inc",
    "wof:placetype":"venue"
},
  "geometry": {"coordinates":[-85.79438500000001,44.777449],"type":"Point"}
}