{
  "type": "Feature",
  "properties": {
    "iso:country":"US",
    "sg:address":"24698 Westhampton St",
    "sg:city":"Oak Park",
    "sg:classifiers":[
        {
            "category":"Wholesale",
            "subcategory":"Durable Goods & Equipment",
            "type":"Manufacturing & Wholesale Goods"
        }
    ],
    "sg:phone":"+1 248 541 0642",
    "sg:postcode":"48237",
    "sg:province":"MI",
    "sg:tags":[
        "representative",
        "manufacturer"
    ],
    "wof:name":"Mc Rae Rogers Assoc",
    "wof:placetype":"venue"
},
  "geometry": {"coordinates":[-83.185019,42.473568],"type":"Point"}
}