{
  "type": "Feature",
  "properties": {
    "iso:country":"US",
    "sg:address":"1500 W North St",
    "sg:city":"Jackson",
    "sg:classifiers":[
        {
            "category":"Professional",
            "type":"Services"
        }
    ],
    "sg:phone":"+1 517 780 9100",
    "sg:postcode":"49202",
    "sg:province":"MI",
    "sg:tags":[
        "establishment"
    ],
    "wof:name":"Able Families",
    "wof:placetype":"venue"
},
  "geometry": {"coordinates":[-84.428675,42.259046],"type":"Point"}
}