{
  "type": "Feature",
  "properties": {
    "iso:country":"US",
    "sg:address":"9171 Deitering Rd",
    "sg:city":"Chesaning",
    "sg:classifiers":[
        {
            "category":"Organizations",
            "subcategory":"Non-profit Organization",
            "type":"Services"
        }
    ],
    "sg:phone":"+1 989 845 7449",
    "sg:postcode":"48616",
    "sg:province":"MI",
    "wof:name":"Knights Of Columbus",
    "wof:placetype":"venue"
},
  "geometry": {"coordinates":[-84.092249,43.181307],"type":"Point"}
}