{
  "type": "Feature",
  "properties": {
    "iso:country":"US",
    "sg:address":"1115 S Lapeer Rd",
    "sg:city":"Lake Orion",
    "sg:classifiers":[
        {
            "category":"Banks & Credit Unions",
            "subcategory":"Bank",
            "type":"Services"
        }
    ],
    "sg:phone":"+1 248 693 6261",
    "sg:postcode":"48360",
    "sg:province":"MI",
    "sg:website":"www.oxfordbank.com",
    "wof:name":"Oxford Bank",
    "wof:placetype":"venue"
},
  "geometry": {"coordinates":[-83.245751,42.756435],"type":"Point"}
}