{
  "type": "Feature",
  "properties": {
    "iso:country":"US",
    "sg:address":"220 S Broadway St",
    "sg:city":"Cassopolis",
    "sg:classifiers":[
        {
            "category":"Restaurant",
            "type":"Food & Drink"
        }
    ],
    "sg:phone":"+1 269 445 3837",
    "sg:postcode":"49031",
    "sg:province":"MI",
    "wof:name":"Tastee Twirl",
    "wof:placetype":"venue"
},
  "geometry": {"coordinates":[-86.012565,41.909432],"type":"Point"}
}