{
  "type": "Feature",
  "properties": {
    "iso:country":"US",
    "sg:address":"15 S 2nd St",
    "sg:city":"Grand Haven",
    "sg:classifiers":[
        {
            "category":"Professional",
            "subcategory":"Computer Services",
            "type":"Services"
        }
    ],
    "sg:phone":"+1 616 604 6452",
    "sg:postcode":"49417",
    "sg:province":"MI",
    "sg:tags":[
        "consultant",
        "designer",
        "related"
    ],
    "wof:name":"Idealistic Technologies",
    "wof:placetype":"venue"
},
  "geometry": {"coordinates":[-86.231532,43.063276],"type":"Point"}
}