{
  "type": "Feature",
  "properties": {
    "iso:country":"US",
    "sg:address":"5923 Misty Hill Ct",
    "sg:city":"Clarkston",
    "sg:classifiers":[
        {
            "category":"Wholesale",
            "subcategory":"Groceries",
            "type":"Manufacturing & Wholesale Goods"
        }
    ],
    "sg:phone":"+1 248 620 2616",
    "sg:postcode":"48346",
    "sg:province":"MI",
    "sg:tags":[
        "pretzel"
    ],
    "wof:name":"Pretzel Peddler",
    "wof:placetype":"venue"
},
  "geometry": {"coordinates":[-83.407297,42.724924],"type":"Point"}
}