{
  "type": "Feature",
  "properties": {
    "iso:country":"US",
    "sg:address":"5261 Winchester Way",
    "sg:city":"Gladwin",
    "sg:classifiers":[
        {
            "category":"Professional",
            "subcategory":"Business Services",
            "type":"Services"
        }
    ],
    "sg:phone":"+1 989 426 5163",
    "sg:postcode":"48624",
    "sg:province":"MI",
    "sg:tags":[
        "notary",
        "public"
    ],
    "wof:name":"Linda K Fornwall",
    "wof:placetype":"venue"
},
  "geometry": {"coordinates":[-84.438193,44.124936],"type":"Point"}
}