{
  "type": "Feature",
  "properties": {
    "iso:country":"US",
    "sg:address":"1011 Court St",
    "sg:city":"St Joseph",
    "sg:classifiers":[
        {
            "category":"Professional",
            "subcategory":"Business Services",
            "type":"Services"
        }
    ],
    "sg:phone":"+1 269 926 7530",
    "sg:postcode":"49085",
    "sg:province":"MI",
    "sg:tags":[
        "repossessing"
    ],
    "wof:name":"Capital Reclaim Svc",
    "wof:placetype":"venue"
},
  "geometry": {"coordinates":[-86.484505,42.10225],"type":"Point"}
}