{
  "type": "Feature",
  "properties": {
    "iso:country":"US",
    "sg:address":"2609 E Genesee Ave",
    "sg:city":"Saginaw",
    "sg:classifiers":[
        {
            "category":"Shopping",
            "type":"Retail Goods"
        }
    ],
    "sg:phone":"+1 989 753 5479",
    "sg:postcode":"48601",
    "sg:province":"MI",
    "sg:tags":[
        "cosmetic",
        "perfume"
    ],
    "wof:name":"R & D Beauty & Barber Supply",
    "wof:placetype":"venue"
},
  "geometry": {"coordinates":[-83.916979,43.407549],"type":"Point"}
}