{
  "type": "Feature",
  "properties": {
    "iso:country":"US",
    "sg:address":"416 N Sears St",
    "sg:city":"Reed City",
    "sg:classifiers":[
        {
            "category":"Retail",
            "subcategory":"Auto Repair",
            "type":"Services"
        }
    ],
    "sg:phone":"+1 231 832 2022",
    "sg:postcode":"49677",
    "sg:province":"MI",
    "sg:tags":[
        "general"
    ],
    "wof:name":"Herring Larry G Gargage",
    "wof:placetype":"venue"
},
  "geometry": {"coordinates":[-85.51639299999999,43.880355],"type":"Point"}
}