{
  "type": "Feature",
  "properties": {
    "iso:country":"US",
    "sg:address":"8811 US Hwy 31",
    "sg:city":"Grawn",
    "sg:classifiers":[
        {
            "category":"Professional",
            "subcategory":"Accounting & Tax Preparation",
            "type":"Services"
        }
    ],
    "sg:phone":"+1 231 276 0086",
    "sg:postcode":"49637",
    "sg:province":"MI",
    "sg:tags":[
        "return",
        "filing"
    ],
    "wof:name":"Integrity Tax Svc LLC",
    "wof:placetype":"venue"
},
  "geometry": {"coordinates":[-85.75530000000001,44.658544],"type":"Point"}
}