{
  "type": "Feature",
  "properties": {
    "iso:country":"US",
    "sg:address":"761 W Giles Rd",
    "sg:city":"Muskegon",
    "sg:classifiers":[
        {
            "category":"Personal",
            "subcategory":"Beauty Salon",
            "type":"Services"
        }
    ],
    "sg:phone":"+1 231 744 1977",
    "sg:postcode":"49445",
    "sg:province":"MI",
    "sg:tags":[
        "shop"
    ],
    "wof:name":"Class Act Salon",
    "wof:placetype":"venue"
},
  "geometry": {"coordinates":[-86.258939,43.277792],"type":"Point"}
}