{
  "type": "Feature",
  "properties": {
    "iso:country":"US",
    "sg:address":"1645 32nd Ave",
    "sg:city":"Hudsonville",
    "sg:classifiers":[
        {
            "category":"Education",
            "subcategory":"School",
            "type":"Public Place"
        }
    ],
    "sg:phone":"+1 616 896 9429",
    "sg:postcode":"49426",
    "sg:province":"MI",
    "sg:tags":[
        "high",
        "middle",
        "elementary"
    ],
    "wof:name":"Hudsonville School District",
    "wof:placetype":"venue"
},
  "geometry": {"coordinates":[-85.86180299999999,42.797462],"type":"Point"}
}