{
  "type": "Feature",
  "properties": {
    "iso:country":"US",
    "sg:address":"18500 Fort St",
    "sg:city":"Wyandotte",
    "sg:classifiers":[
        {
            "category":"Retail",
            "subcategory":"Auto Repair",
            "type":"Services"
        }
    ],
    "sg:phone":"+1 734 281 2000",
    "sg:postcode":"48193",
    "sg:province":"MI",
    "sg:tags":[
        "oil",
        "change"
    ],
    "wof:name":"Pennzoil",
    "wof:placetype":"venue"
},
  "geometry": {"coordinates":[-83.189342,42.17399],"type":"Point"}
}