{
  "type": "Feature",
  "properties": {
    "iso:country":"US",
    "sg:address":"3770 Lackawana St",
    "sg:city":"Auburn Hills",
    "sg:classifiers":[
        {
            "category":"Building & Trades",
            "subcategory":"Construction",
            "type":"Services"
        }
    ],
    "sg:phone":"+1 248 332 4880",
    "sg:postcode":"48326",
    "sg:province":"MI",
    "sg:tags":[
        "excavation",
        "contractor"
    ],
    "wof:name":"Gregory Excavating",
    "wof:placetype":"venue"
},
  "geometry": {"coordinates":[-83.304345,42.693037],"type":"Point"}
}