{
  "type": "Feature",
  "properties": {
    "iso:country":"US",
    "sg:address":"24100 Southfield Rd",
    "sg:city":"Southfield",
    "sg:classifiers":[
        {
            "category":"Professional",
            "subcategory":"Management & Consulting",
            "type":"Services"
        }
    ],
    "sg:phone":"+1 248 569 4800",
    "sg:postcode":"48075",
    "sg:province":"MI",
    "wof:name":"Primerica",
    "wof:placetype":"venue"
},
  "geometry": {"coordinates":[-83.220797,42.467397],"type":"Point"}
}