{
  "type": "Feature",
  "properties": {
    "iso:country":"US",
    "sg:address":"1095 Medical Park Dr SE",
    "sg:city":"Grand Rapids",
    "sg:classifiers":[
        {
            "category":"Health Services",
            "subcategory":"Nursing And Care Facility",
            "type":"Services"
        }
    ],
    "sg:phone":"+1 616 949 7220",
    "sg:postcode":"49546",
    "sg:province":"MI",
    "sg:tags":[
        "home",
        "convalescent"
    ],
    "wof:name":"Metron Of Forest Hills",
    "wof:placetype":"venue"
},
  "geometry": {"coordinates":[-85.557423,42.942436],"type":"Point"}
}