{
  "type": "Feature",
  "properties": {
    "iso:country":"US",
    "sg:address":"6670 Orchard Lake Rd",
    "sg:city":"West Bloomfield",
    "sg:classifiers":[
        {
            "category":"Restaurant",
            "type":"Food & Drink"
        }
    ],
    "sg:menulink":"http://www.allmenus.com/mi/west-bloomfield/142356-subway/menu/",
    "sg:phone":"+1 248 737 6950",
    "sg:postcode":"48322",
    "sg:province":"MI",
    "sg:tags":[
        "american",
        "sandwich"
    ],
    "wof:name":"Subway",
    "wof:placetype":"venue"
},
  "geometry": {"coordinates":[-83.360606,42.540389],"type":"Point"}
}