{
  "type": "Feature",
  "properties": {
    "iso:country":"US",
    "sg:address":"5026 State Rd",
    "sg:city":"Fort Gratiot",
    "sg:classifiers":[
        {
            "category":"Building & Trades",
            "subcategory":"Electrical",
            "type":"Services"
        }
    ],
    "sg:phone":"+1 810 385 2873",
    "sg:postcode":"48059",
    "sg:province":"MI",
    "sg:tags":[
        "electrical",
        "contractor"
    ],
    "wof:name":"Kreidler Audio",
    "wof:placetype":"venue"
},
  "geometry": {"coordinates":[-82.49769499999999,43.064887],"type":"Point"}
}