{
  "type": "Feature",
  "properties": {
    "iso:country":"US",
    "sg:address":"11383 Bach Rd",
    "sg:city":"Sebewaing",
    "sg:classifiers":[
        {
            "category":"Farming",
            "subcategory":"Farm",
            "type":"Manufacturing & Wholesale Goods"
        }
    ],
    "sg:phone":"+1 989 883 2191",
    "sg:postcode":"48759",
    "sg:province":"MI",
    "sg:tags":[
        "crop",
        "general"
    ],
    "wof:name":"Kuhl Farms",
    "wof:placetype":"venue"
},
  "geometry": {"coordinates":[-83.43287100000001,43.682664],"type":"Point"}
}