{
  "type": "Feature",
  "properties": {
    "iso:country":"US",
    "sg:address":"20169 James Couzens Fwy",
    "sg:city":"Detroit",
    "sg:classifiers":[
        {
            "category":"Real Estate",
            "subcategory":"Real Estate Agent",
            "type":"Services"
        }
    ],
    "sg:phone":"+1 313 863 6998",
    "sg:postcode":"48235",
    "sg:province":"MI",
    "sg:tags":[
        "consultant"
    ],
    "wof:name":"A Unique Realty",
    "wof:placetype":"venue"
},
  "geometry": {"coordinates":[-83.198312,42.440357],"type":"Point"}
}