{
  "type": "Feature",
  "properties": {
    "iso:country":"US",
    "sg:address":"11 N State St",
    "sg:city":"Sparta",
    "sg:classifiers":[
        {
            "category":"Banks & Credit Unions",
            "subcategory":"Bank",
            "type":"Services"
        }
    ],
    "sg:phone":"+1 616 887 8816",
    "sg:postcode":"49345",
    "sg:province":"MI",
    "sg:tags":[
        "st"
    ],
    "wof:name":"Valley Ridge Bank",
    "wof:placetype":"venue"
},
  "geometry": {"coordinates":[-85.71019699999999,43.161887],"type":"Point"}
}