{
  "type": "Feature",
  "properties": {
    "iso:country":"US",
    "sg:address":"1472 N Maple Leaf Rd",
    "sg:city":"Lapeer",
    "sg:classifiers":[
        {
            "category":"Social Services",
            "subcategory":"Child Care",
            "type":"Services"
        }
    ],
    "sg:phone":"+1 810 245 7046",
    "sg:postcode":"48446",
    "sg:province":"MI",
    "wof:name":"Busy Little Hands Home Child",
    "wof:placetype":"venue"
},
  "geometry": {"coordinates":[-83.43273000000001,43.067124],"type":"Point"}
}