{
  "type": "Feature",
  "properties": {
    "iso:country":"US",
    "sg:address":"1661 Range Rd",
    "sg:city":"Smiths Creek",
    "sg:classifiers":[
        {
            "category":"Social Services",
            "subcategory":"Child Care",
            "type":"Services"
        }
    ],
    "sg:phone":"+1 810 388 5437",
    "sg:postcode":"48074",
    "sg:province":"MI",
    "sg:tags":[
        "day"
    ],
    "wof:name":"Over Rainbow Daycare",
    "wof:placetype":"venue"
},
  "geometry": {"coordinates":[-82.502206,42.956635],"type":"Point"}
}