{
  "type": "Feature",
  "properties": {
    "iso:country":"US",
    "sg:address":"15115 Mack Ave",
    "sg:city":"Detroit",
    "sg:classifiers":[
        {
            "category":"Professional",
            "subcategory":"Testing Lab",
            "type":"Services"
        }
    ],
    "sg:phone":"+1 313 343 9188",
    "sg:postcode":"48224",
    "sg:province":"MI",
    "sg:tags":[
        "emission",
        "motor"
    ],
    "wof:name":"Detroit Engine Tech LLC",
    "wof:placetype":"venue"
},
  "geometry": {"coordinates":[-82.94461,42.387892],"type":"Point"}
}