{
  "type": "Feature",
  "properties": {
    "iso:country":"US",
    "sg:address":"26120 Van Dyke Ave",
    "sg:city":"Center Line",
    "sg:classifiers":[
        {
            "category":"Professional",
            "subcategory":"Lawyer & Legal Services",
            "type":"Services"
        }
    ],
    "sg:phone":"+1 586 754 8300",
    "sg:postcode":"48015",
    "sg:province":"MI",
    "wof:name":"Palombo Salvatore D & Associates PC",
    "wof:placetype":"venue"
},
  "geometry": {"coordinates":[-83.02739699999999,42.485699],"type":"Point"}
}