{
  "type": "Feature",
  "properties": {
    "iso:country":"US",
    "sg:address":"109 N 7th St",
    "sg:city":"Grand Haven",
    "sg:classifiers":[
        {
            "category":"Food & Beverages",
            "subcategory":"Specialty",
            "type":"Retail Goods"
        }
    ],
    "sg:phone":"+1 616 846 4161",
    "sg:postcode":"49417",
    "sg:province":"MI",
    "sg:tags":[
        "health",
        "diet"
    ],
    "wof:name":"Better Health Products",
    "wof:placetype":"venue"
},
  "geometry": {"coordinates":[-86.222582,43.062549],"type":"Point"}
}