{
  "type": "Feature",
  "properties": {
    "iso:country":"US",
    "sg:address":"70 2nd St NE",
    "sg:city":"Sand Lake",
    "sg:classifiers":[
        {
            "category":"Food & Beverages",
            "subcategory":"Groceries & Convenience Stores",
            "type":"Retail Goods"
        }
    ],
    "sg:phone":"+1 616 636 5795",
    "sg:postcode":"49343",
    "sg:province":"MI",
    "sg:tags":[
        "grocer"
    ],
    "wof:name":"Vern's Wooden Nickel",
    "wof:placetype":"venue"
},
  "geometry": {"coordinates":[-85.51329,43.290926],"type":"Point"}
}