{
  "type": "Feature",
  "properties": {
    "iso:country":"US",
    "sg:address":"34900 Kelly Rd",
    "sg:city":"Clinton Township",
    "sg:classifiers":[
        {
            "category":"Retail",
            "subcategory":"Auto Repair",
            "type":"Services"
        }
    ],
    "sg:phone":"+1 586 791 5330",
    "sg:postcode":"48035",
    "sg:province":"MI",
    "sg:tags":[
        "body",
        "shop"
    ],
    "wof:name":"Cox Collision Center Inc",
    "wof:placetype":"venue"
},
  "geometry": {"coordinates":[-82.930099,42.553699],"type":"Point"}
}