{
  "type": "Feature",
  "properties": {
    "iso:country":"US",
    "sg:address":"1115 142nd Ave",
    "sg:city":"Wayland",
    "sg:classifiers":[
        {
            "category":"Manufacturing",
            "subcategory":"Tools & Machinery",
            "type":"Manufacturing & Wholesale Goods"
        }
    ],
    "sg:phone":"+1 616 877 0426",
    "sg:postcode":"49348",
    "sg:province":"MI",
    "sg:tags":[
        "machine",
        "shop"
    ],
    "wof:name":"Blain Machining Inc",
    "wof:placetype":"venue"
},
  "geometry": {"coordinates":[-85.65554,42.724802],"type":"Point"}
}