{
  "type": "Feature",
  "properties": {
    "iso:country":"US",
    "sg:address":"1355 E Apple Ave",
    "sg:city":"Muskegon",
    "sg:classifiers":[
        {
            "category":"Shopping",
            "subcategory":"Department Store",
            "type":"Retail Goods"
        }
    ],
    "sg:phone":"+1 231 767 9636",
    "sg:postcode":"49442",
    "sg:province":"MI",
    "sg:tags":[
        "shop"
    ],
    "sg:website":"www.dollargeneral.com",
    "wof:name":"Dollar General",
    "wof:placetype":"venue"
},
  "geometry": {"coordinates":[-86.209886,43.234075],"type":"Point"}
}