{
  "type": "Feature",
  "properties": {
    "iso:country":"US",
    "sg:address":"3934 S Lynn St",
    "sg:city":"Onaway",
    "sg:classifiers":[
        {
            "category":"Professional",
            "subcategory":"Business Services",
            "type":"Services"
        }
    ],
    "sg:phone":"+1 231 420 3902",
    "sg:postcode":"49765",
    "sg:province":"MI",
    "sg:tags":[
        "fixture",
        "retail",
        "installation",
        "display",
        "related"
    ],
    "wof:name":"Great Lakes Retail Solutions",
    "wof:placetype":"venue"
},
  "geometry": {"coordinates":[-84.223831,45.354925],"type":"Point"}
}