{
  "type": "Feature",
  "properties": {
    "iso:country":"US",
    "sg:address":"23 Mill Rd",
    "sg:city":"Shelby Twp",
    "sg:classifiers":[
        {
            "category":"Home & Garden",
            "subcategory":"Building Materials",
            "type":"Retail Goods"
        },
        {
            "category":"Retail",
            "subcategory":"Auto Repair",
            "type":"Services"
        }
    ],
    "sg:phone":"+1 586 739 6111",
    "sg:postcode":"48386",
    "sg:province":"MI",
    "sg:tags":[
        "plate",
        "window",
        "commercial",
        "glass",
        "accessory"
    ],
    "wof:name":"Henderson Glass Inc",
    "wof:placetype":"venue"
},
  "geometry": {"coordinates":[-83.48759800000001,42.638901],"type":"Point"}
}