{
  "type": "Feature",
  "properties": {
    "iso:country":"US",
    "sg:address":"905 Johnstone St",
    "sg:city":"Port Huron",
    "sg:classifiers":[
        {
            "category":"Wholesale",
            "subcategory":"Office Equipment",
            "type":"Manufacturing & Wholesale Goods"
        }
    ],
    "sg:phone":"+1 810 984 5021",
    "sg:postcode":"48060",
    "sg:province":"MI",
    "sg:tags":[
        "register",
        "cash",
        "supply"
    ],
    "wof:name":"Krestik's Business Machines",
    "wof:placetype":"venue"
},
  "geometry": {"coordinates":[-82.430519,42.960905],"type":"Point"}
}