{
  "type": "Feature",
  "properties": {
    "iso:country":"US",
    "sg:address":"51 S Washington St",
    "sg:city":"Oxford",
    "sg:classifiers":[
        {
            "category":"Health Services",
            "subcategory":"Chiropractor",
            "type":"Services"
        }
    ],
    "sg:phone":"+1 248 628 4886",
    "sg:postcode":"48371",
    "sg:province":"MI",
    "wof:name":"Chiropractic USA",
    "wof:placetype":"venue"
},
  "geometry": {"coordinates":[-83.264712,42.8246],"type":"Point"}
}