{
  "type": "Feature",
  "properties": {
    "iso:country":"US",
    "sg:address":"12504 E D Ave",
    "sg:city":"Richland",
    "sg:classifiers":[
        {
            "category":"Restaurant",
            "type":"Food & Drink"
        }
    ],
    "sg:phone":"+1 269 731 4911",
    "sg:postcode":"49083",
    "sg:province":"MI",
    "wof:name":"Bayview Gardens",
    "wof:placetype":"venue"
},
  "geometry": {"coordinates":[-85.386352,42.371132],"type":"Point"}
}