{
  "type": "Feature",
  "properties": {
    "iso:country":"US",
    "sg:address":"13244 W Warren Ave",
    "sg:city":"Dearborn",
    "sg:classifiers":[
        {
            "category":"Health Services",
            "subcategory":"Doctor",
            "type":"Services"
        }
    ],
    "sg:phone":"+1 313 846 6080",
    "sg:postcode":"48126",
    "sg:province":"MI",
    "sg:tags":[
        "podiatrist"
    ],
    "wof:name":"Baig Mirza DPM",
    "wof:placetype":"venue"
},
  "geometry": {"coordinates":[-83.17330200000001,42.3442],"type":"Point"}
}