{
  "type": "Feature",
  "properties": {
    "iso:country":"US",
    "sg:address":"330 Jonesville Rd",
    "sg:city":"Jonesville",
    "sg:classifiers":[
        {
            "category":"Professional",
            "subcategory":"Management & Consulting",
            "type":"Services"
        }
    ],
    "sg:phone":"+1 517 849 3132",
    "sg:postcode":"49250",
    "sg:province":"MI",
    "wof:name":"Subway",
    "wof:placetype":"venue"
},
  "geometry": {"coordinates":[-84.67556399999999,41.985479],"type":"Point"}
}