{
  "type": "Feature",
  "properties": {
    "iso:country":"US",
    "sg:address":"3147 Logan Valley Rd",
    "sg:city":"Traverse City",
    "sg:classifiers":[
        {
            "category":"Health Services",
            "subcategory":"Doctor",
            "type":"Services"
        }
    ],
    "sg:phone":"+1 231 935 0668",
    "sg:postcode":"49684",
    "sg:province":"MI",
    "sg:tags":[
        "clinic"
    ],
    "wof:name":"Community Health Clinic",
    "wof:placetype":"venue"
},
  "geometry": {"coordinates":[-85.61872700000001,44.731741],"type":"Point"}
}