{
  "type": "Feature",
  "properties": {
    "iso:country":"US",
    "sg:address":"5654 Main St",
    "sg:city":"Lexington",
    "sg:classifiers":[
        {
            "category":"Shopping",
            "subcategory":"Used Merchandise",
            "type":"Retail Goods"
        }
    ],
    "sg:phone":"+1 810 359 8016",
    "sg:postcode":"48450",
    "sg:province":"MI",
    "sg:tags":[
        "antique"
    ],
    "wof:name":"Hunter House Antiques",
    "wof:placetype":"venue"
},
  "geometry": {"coordinates":[-82.53088,43.265426],"type":"Point"}
}