{
  "type": "Feature",
  "properties": {
    "iso:country":"US",
    "sg:address":"123 W Main St",
    "sg:city":"Gaylord",
    "sg:classifiers":[
        {
            "category":"Banks & Credit Unions",
            "subcategory":"Bank",
            "type":"Services"
        }
    ],
    "sg:phone":"+1 989 732 0211",
    "sg:postcode":"49735",
    "sg:province":"MI",
    "sg:tags":[
        "state"
    ],
    "wof:name":"Fifth Third Bank",
    "wof:placetype":"venue"
},
  "geometry": {"coordinates":[-84.67419700000001,45.027444],"type":"Point"}
}