{
  "type": "Feature",
  "properties": {
    "iso:country":"US",
    "sg:address":"330 Charles St",
    "sg:city":"Chesaning",
    "sg:classifiers":[
        {
            "category":"Shopping",
            "type":"Retail Goods"
        }
    ],
    "sg:phone":"+1 989 845 3000",
    "sg:postcode":"48616",
    "sg:province":"MI",
    "sg:tags":[
        "communications",
        "merchandise",
        "telephone",
        "business"
    ],
    "wof:name":"National Telephone Co",
    "wof:placetype":"venue"
},
  "geometry": {"coordinates":[-84.123107,43.183746],"type":"Point"}
}