{
  "type": "Feature",
  "properties": {
    "iso:country":"US",
    "sg:address":"2298 Norcrest Dr",
    "sg:city":"Muskegon",
    "sg:classifiers":[
        {
            "category":"Social Services",
            "type":"Services"
        }
    ],
    "sg:phone":"+1 231 780 5115",
    "sg:postcode":"49441",
    "sg:province":"MI",
    "sg:tags":[
        "youth",
        "organization",
        "center"
    ],
    "wof:name":"West Shore Youth Symphony",
    "wof:placetype":"venue"
},
  "geometry": {"coordinates":[-86.30095300000001,43.185712],"type":"Point"}
}