{
  "type": "Feature",
  "properties": {
    "iso:country":"US",
    "sg:address":"473 W Sanilac Rd",
    "sg:city":"Sandusky",
    "sg:classifiers":[
        {
            "category":"Food & Beverages",
            "subcategory":"Groceries & Convenience Stores",
            "type":"Retail Goods"
        }
    ],
    "sg:phone":"+1 810 648 4343",
    "sg:postcode":"48471",
    "sg:province":"MI",
    "wof:name":"Mr Chips Food Store",
    "wof:placetype":"venue"
},
  "geometry": {"coordinates":[-82.839718,43.420963],"type":"Point"}
}