{
  "type": "Feature",
  "properties": {
    "iso:country":"US",
    "sg:address":"29832 Southfield Rd",
    "sg:city":"Southfield",
    "sg:classifiers":[
        {
            "category":"Shopping",
            "subcategory":"Beauty & Cosmetics",
            "type":"Retail Goods"
        }
    ],
    "sg:phone":"+1 248 443 1820",
    "sg:postcode":"48076",
    "sg:province":"MI",
    "sg:tags":[
        "supply"
    ],
    "sg:website":"www.sallybeauty.com",
    "wof:name":"Sally Beauty Supply",
    "wof:placetype":"venue"
},
  "geometry": {"coordinates":[-83.222702,42.508202],"type":"Point"}
}