{
  "type": "Feature",
  "properties": {
    "iso:country":"US",
    "sg:address":"813 E Chicago Rd",
    "sg:city":"Quincy",
    "sg:classifiers":[
        {
            "category":"Farming",
            "subcategory":"Farm",
            "type":"Manufacturing & Wholesale Goods"
        }
    ],
    "sg:phone":"+1 517 639 3821",
    "sg:postcode":"49082",
    "sg:province":"MI",
    "wof:name":"Anderson Farms",
    "wof:placetype":"venue"
},
  "geometry": {"coordinates":[-84.91817500000001,41.938993],"type":"Point"}
}