{
  "type": "Feature",
  "properties": {
    "iso:country":"US",
    "sg:address":"1907 W M 21",
    "sg:city":"Owosso",
    "sg:classifiers":[
        {
            "category":"Manufacturing",
            "subcategory":"Printing",
            "type":"Manufacturing & Wholesale Goods"
        }
    ],
    "sg:phone":"+1 989 723 1118",
    "sg:postcode":"48867",
    "sg:province":"MI",
    "sg:tags":[
        "commercial"
    ],
    "wof:name":"Quality Printing Svc",
    "wof:placetype":"venue"
},
  "geometry": {"coordinates":[-84.20249,42.997521],"type":"Point"}
}