{
  "type": "Feature",
  "properties": {
    "iso:country":"US",
    "sg:address":"335 S Telegraph Rd",
    "sg:city":"Monroe",
    "sg:classifiers":[
        {
            "category":"Cinema",
            "subcategory":"Movie Rental",
            "type":"Entertainment"
        }
    ],
    "sg:phone":"+1 734 457 0619",
    "sg:postcode":"48161",
    "sg:province":"MI",
    "sg:tags":[
        "leasing",
        "video",
        "disc",
        "tape"
    ],
    "wof:name":"Hollywood Video",
    "wof:placetype":"venue"
},
  "geometry": {"coordinates":[-83.41723,41.918293],"type":"Point"}
}