{
  "type": "Feature",
  "properties": {
    "iso:country":"US",
    "sg:address":"24445 Northwestern Hwy",
    "sg:city":"Southfield",
    "sg:classifiers":[
        {
            "category":"Organizations",
            "subcategory":"Professional Association",
            "type":"Services"
        }
    ],
    "sg:phone":"+1 248 208 9915",
    "sg:postcode":"48075",
    "sg:province":"MI",
    "sg:tags":[
        "chamber",
        "commerce"
    ],
    "wof:name":"Michigan Hspnic Chmber Cmmerce",
    "wof:placetype":"venue"
},
  "geometry": {"coordinates":[-83.23999499999999,42.47071],"type":"Point"}
}