{
  "type": "Feature",
  "properties": {
    "iso:country":"US",
    "sg:address":"1458 E Hayes Ave",
    "sg:city":"Hazel Park",
    "sg:classifiers":[
        {
            "category":"Building & Trades",
            "subcategory":"Construction",
            "type":"Services"
        }
    ],
    "sg:phone":"+1 248 543 0214",
    "sg:postcode":"48030",
    "sg:province":"MI",
    "sg:tags":[
        "contractor"
    ],
    "wof:name":"Your Design Carpentry",
    "wof:placetype":"venue"
},
  "geometry": {"coordinates":[-83.089699,42.449402],"type":"Point"}
}