{
  "type": "Feature",
  "properties": {
    "iso:country":"US",
    "sg:address":"29551 Greenfield Rd",
    "sg:city":"Southfield",
    "sg:classifiers":[
        {
            "category":"Social Services",
            "type":"Services"
        }
    ],
    "sg:phone":"+1 248 443 4932",
    "sg:postcode":"48076",
    "sg:province":"MI",
    "sg:tags":[
        "counseling"
    ],
    "wof:name":"West Side Counseling Ctr",
    "wof:placetype":"venue"
},
  "geometry": {"coordinates":[-83.203335,42.506101],"type":"Point"}
}