{
  "type": "Feature",
  "properties": {
    "iso:country":"US",
    "sg:address":"17455 Sumner",
    "sg:city":"Redford",
    "sg:classifiers":[
        {
            "category":"Arts & Performance",
            "subcategory":"Theater",
            "type":"Entertainment"
        }
    ],
    "sg:phone":"+1 313 538 6521",
    "sg:postcode":"48240",
    "sg:province":"MI",
    "sg:tags":[
        "group"
    ],
    "wof:name":"Detroit Cowboy Association",
    "wof:placetype":"venue"
},
  "geometry": {"coordinates":[-83.293479,42.420937],"type":"Point"}
}