{
  "type": "Feature",
  "properties": {
    "iso:country":"US",
    "sg:address":"2295 W Stadium Blvd",
    "sg:city":"Ann Arbor",
    "sg:classifiers":[
        {
            "category":"Restaurant",
            "type":"Food & Drink"
        }
    ],
    "sg:menulink":"http://www.allmenus.com/mi/ann-arbor/197228-burger-king/menu/",
    "sg:phone":"+1 734 761 8943",
    "sg:postcode":"48103",
    "sg:province":"MI",
    "sg:tags":[
        "burger",
        "american"
    ],
    "wof:name":"Burger King",
    "wof:placetype":"venue"
},
  "geometry": {"coordinates":[-83.777917,42.276],"type":"Point"}
}