{
  "type": "Feature",
  "properties": {
    "iso:country":"US",
    "sg:address":"24641 Jefferson Ave",
    "sg:city":"Saint Clair Shores",
    "sg:classifiers":[
        {
            "category":"Health Services",
            "subcategory":"Doctor",
            "type":"Services"
        }
    ],
    "sg:phone":"+1 586 772 7373",
    "sg:postcode":"48080",
    "sg:province":"MI",
    "sg:tags":[
        "surgeon",
        "oral"
    ],
    "wof:name":"Hunt Brian J DDS",
    "wof:placetype":"venue"
},
  "geometry": {"coordinates":[-82.889397,42.474098],"type":"Point"}
}