{
  "type": "Feature",
  "properties": {
    "iso:country":"US",
    "sg:address":"2945 Mountain Vw",
    "sg:city":"Lake Orion",
    "sg:classifiers":[
        {
            "category":"Personal",
            "subcategory":"Beauty Salon",
            "type":"Services"
        }
    ],
    "sg:phone":"+1 248 393 6640",
    "sg:postcode":"48360",
    "sg:province":"MI",
    "sg:tags":[
        "shop"
    ],
    "wof:name":"Royalty Affair Inc",
    "wof:placetype":"venue"
},
  "geometry": {"coordinates":[-83.238491,42.737759],"type":"Point"}
}