{
  "type": "Feature",
  "properties": {
    "iso:country":"US",
    "sg:address":"8989 Cedar Run Rd",
    "sg:city":"Traverse City",
    "sg:classifiers":[
        {
            "category":"Building & Trades",
            "subcategory":"Cleaning & Sanitation",
            "type":"Services"
        }
    ],
    "sg:phone":"+1 231 932 9228",
    "sg:postcode":"49684",
    "sg:province":"MI",
    "sg:tags":[
        "maintenance"
    ],
    "wof:name":"Cleaning Lady",
    "wof:placetype":"venue"
},
  "geometry": {"coordinates":[-85.751919,44.760327],"type":"Point"}
}