{
  "type": "Feature",
  "properties": {
    "iso:country":"US",
    "sg:address":"218 Mill St",
    "sg:city":"Davison",
    "sg:classifiers":[
        {
            "category":"Manufacturing",
            "subcategory":"Printing",
            "type":"Manufacturing & Wholesale Goods"
        }
    ],
    "sg:phone":"+1 810 653 8420",
    "sg:postcode":"48423",
    "sg:province":"MI",
    "sg:tags":[
        "commercial"
    ],
    "wof:name":"Pariseau's Printing Inc",
    "wof:placetype":"venue"
},
  "geometry": {"coordinates":[-83.51577899999999,43.030816],"type":"Point"}
}