{
  "type": "Feature",
  "properties": {
    "iso:country":"US",
    "sg:address":"3294 Stone Rd",
    "sg:city":"Snover",
    "sg:phone":"+1 810 672 8908",
    "sg:postcode":"48472",
    "sg:province":"MI",
    "sg:tags":[
        "farm",
        "corn"
    ],
    "wof:name":"Melvin Shaum",
    "wof:placetype":"venue"
},
  "geometry": {"coordinates":[-82.965132,43.548835],"type":"Point"}
}