{
  "type": "Feature",
  "properties": {
    "iso:country":"US",
    "sg:address":"2211 Eastlawn Dr",
    "sg:city":"Midland",
    "sg:classifiers":[
        {
            "category":"Real Estate",
            "subcategory":"Real Estate Operator",
            "type":"Services"
        }
    ],
    "sg:phone":"+1 989 631 0341",
    "sg:postcode":"48642",
    "sg:province":"MI",
    "sg:tags":[
        "apartment"
    ],
    "wof:name":"Eastlawn Arms",
    "wof:placetype":"venue"
},
  "geometry": {"coordinates":[-84.197442,43.619565],"type":"Point"}
}