{
  "type": "Feature",
  "properties": {
    "iso:country":"US",
    "sg:address":"20200 W Warren Ave",
    "sg:city":"Detroit",
    "sg:classifiers":[
        {
            "category":"Autos & Motor Vehicles",
            "subcategory":"Automobile Sales",
            "type":"Retail Goods"
        }
    ],
    "sg:phone":"+1 313 271 2040",
    "sg:postcode":"48228",
    "sg:province":"MI",
    "sg:tags":[
        "new",
        "used",
        "car"
    ],
    "wof:name":"Sara's Auto Sales",
    "wof:placetype":"venue"
},
  "geometry": {"coordinates":[-83.23783899999999,42.343079],"type":"Point"}
}