{
  "type": "Feature",
  "properties": {
    "iso:country":"US",
    "sg:address":"381 Baldwin St",
    "sg:city":"Jenison",
    "sg:classifiers":[
        {
            "category":"Cinema",
            "subcategory":"Movie Rental",
            "type":"Entertainment"
        }
    ],
    "sg:phone":"+1 616 457 8585",
    "sg:postcode":"49428",
    "sg:province":"MI",
    "sg:tags":[
        "leasing",
        "video",
        "disc",
        "tape"
    ],
    "sg:website":"www.blockbuster.com",
    "wof:name":"Blockbuster Video",
    "wof:placetype":"venue"
},
  "geometry": {"coordinates":[-85.791471,42.90721],"type":"Point"}
}