{
  "type": "Feature",
  "properties": {
    "iso:country":"US",
    "sg:address":"3483 Prairie St SW",
    "sg:city":"Grandville",
    "sg:classifiers":[
        {
            "category":"Retail",
            "subcategory":"Portrait Studio",
            "type":"Services"
        }
    ],
    "sg:phone":"+1 616 257 8615",
    "sg:postcode":"49418",
    "sg:province":"MI",
    "sg:tags":[
        "photographer"
    ],
    "wof:name":"Kasberger Photography",
    "wof:placetype":"venue"
},
  "geometry": {"coordinates":[-85.752101,42.906366],"type":"Point"}
}