{
  "type": "Feature",
  "properties": {
    "iso:country":"US",
    "sg:address":"7051 Maplewood Dr",
    "sg:city":"Temperance",
    "sg:classifiers":[
        {
            "category":"Building & Trades",
            "subcategory":"Construction",
            "type":"Services"
        }
    ],
    "sg:phone":"+1 734 847 4317",
    "sg:postcode":"48182",
    "sg:province":"MI",
    "sg:tags":[
        "painter"
    ],
    "wof:name":"Apple House Painting",
    "wof:placetype":"venue"
},
  "geometry": {"coordinates":[-83.595224,41.744378],"type":"Point"}
}