{
  "type": "Feature",
  "properties": {
    "iso:country":"US",
    "sg:address":"606 N Ohio Ave",
    "sg:city":"Gaylord",
    "sg:classifiers":[
        {
            "category":"Organizations",
            "subcategory":"Religious Organization",
            "type":"Services"
        }
    ],
    "sg:phone":"+1 989 732 5448",
    "sg:postcode":"49735",
    "sg:province":"MI",
    "wof:name":"Saint Marys Cathedral",
    "wof:placetype":"venue"
},
  "geometry": {"coordinates":[-84.683958,45.034513],"type":"Point"}
}