{
  "type": "Feature",
  "properties": {
    "iso:country":"US",
    "sg:address":"331 N Sorrell St",
    "sg:city":"Fowler",
    "sg:classifiers":[
        {
            "category":"Organizations",
            "subcategory":"Religious Organization",
            "type":"Services"
        }
    ],
    "sg:phone":"+1 989 593 2354",
    "sg:postcode":"48835",
    "sg:province":"MI",
    "sg:tags":[
        "clergy"
    ],
    "wof:name":"Paul M Clark",
    "wof:placetype":"venue"
},
  "geometry": {"coordinates":[-84.742463,43.005184],"type":"Point"}
}