{
  "type": "Feature",
  "properties": {
    "iso:country":"US",
    "sg:address":"30856 Groesbeck Hwy",
    "sg:city":"Roseville",
    "sg:classifiers":[
        {
            "category":"Building & Trades",
            "subcategory":"Construction",
            "type":"Services"
        }
    ],
    "sg:phone":"+1 586 779 6155",
    "sg:postcode":"48066",
    "sg:province":"MI",
    "sg:tags":[
        "general",
        "contractor"
    ],
    "wof:name":"Woodlane Construction Co",
    "wof:placetype":"venue"
},
  "geometry": {"coordinates":[-82.946904,42.523265],"type":"Point"}
}