{
  "type": "Feature",
  "properties": {
    "iso:country":"US",
    "sg:address":"870 Whitney Dr",
    "sg:city":"Lapeer",
    "sg:classifiers":[
        {
            "category":"Manufacturing",
            "subcategory":"Tools & Machinery",
            "type":"Manufacturing & Wholesale Goods"
        }
    ],
    "sg:phone":"+1 810 664 3686",
    "sg:postcode":"48446",
    "sg:province":"MI",
    "sg:tags":[
        "mold"
    ],
    "wof:name":"Byrnes Tool Co",
    "wof:placetype":"venue"
},
  "geometry": {"coordinates":[-83.30765599999999,43.038893],"type":"Point"}
}