{
  "type": "Feature",
  "properties": {
    "iso:country":"US",
    "sg:address":"1010 S Mears Ave",
    "sg:city":"Whitehall",
    "sg:classifiers":[
        {
            "category":"Home & Garden",
            "subcategory":"Building Materials",
            "type":"Retail Goods"
        }
    ],
    "sg:phone":"+1 231 893 8541",
    "sg:postcode":"49461",
    "sg:province":"MI",
    "sg:tags":[
        "paint"
    ],
    "wof:name":"Oceana Glass & Paint Co",
    "wof:placetype":"venue"
},
  "geometry": {"coordinates":[-86.347889,43.398174],"type":"Point"}
}