{
  "type": "Feature",
  "properties": {
    "iso:country":"US",
    "sg:address":"1249 Portage St",
    "sg:city":"Kalamazoo",
    "sg:classifiers":[
        {
            "category":"Building & Trades",
            "subcategory":"Cleaning & Sanitation",
            "type":"Services"
        }
    ],
    "sg:phone":"+1 269 349 1414",
    "sg:postcode":"49001",
    "sg:province":"MI",
    "sg:tags":[
        "house"
    ],
    "sg:website":"www.expertcleaningservicesinc.com",
    "wof:name":"Expert Cleaning Svc",
    "wof:placetype":"venue"
},
  "geometry": {"coordinates":[-85.56981399999999,42.278909],"type":"Point"}
}