{
  "type": "Feature",
  "properties": {
    "iso:country":"US",
    "sg:address":"3730 Laramie Dr NE",
    "sg:city":"Comstock Park",
    "sg:classifiers":[
        {
            "category":"Building & Trades",
            "subcategory":"Construction",
            "type":"Services"
        }
    ],
    "sg:phone":"+1 616 785 3236",
    "sg:postcode":"49321",
    "sg:province":"MI",
    "sg:tags":[
        "painter"
    ],
    "wof:name":"De Maat Bros Painting Contract",
    "wof:placetype":"venue"
},
  "geometry": {"coordinates":[-85.667918,43.030693],"type":"Point"}
}