{
  "type": "Feature",
  "properties": {
    "iso:country":"US",
    "sg:address":"3865 Sandusky Rd",
    "sg:city":"Peck",
    "sg:classifiers":[
        {
            "category":"Personal",
            "type":"Services"
        }
    ],
    "sg:phone":"+1 810 378 6004",
    "sg:postcode":"48466",
    "sg:province":"MI",
    "wof:name":"Jack & Jills Golden Touch",
    "wof:placetype":"venue"
},
  "geometry": {"coordinates":[-82.82073800000001,43.30788],"type":"Point"}
}