{
  "type": "Feature",
  "properties": {
    "iso:country":"US",
    "sg:address":"7000 W Outer Dr",
    "sg:city":"Detroit",
    "sg:classifiers":[
        {
            "category":"Education",
            "subcategory":"School",
            "type":"Public Place"
        }
    ],
    "sg:phone":"+1 313 653 3888",
    "sg:postcode":"48235",
    "sg:province":"MI",
    "sg:tags":[
        "high",
        "middle",
        "elementary"
    ],
    "wof:name":"Innovative Teaching Solutions",
    "wof:placetype":"venue"
},
  "geometry": {"coordinates":[-83.1996,42.4198],"type":"Point"}
}