{
  "type": "Feature",
  "properties": {
    "iso:country":"US",
    "sg:address":"200 E Liberty St",
    "sg:city":"Ann Arbor",
    "sg:classifiers":[
        {
            "category":"Professional",
            "subcategory":"Secretarial Services",
            "type":"Services"
        }
    ],
    "sg:phone":"+1 734 913 5822",
    "sg:postcode":"48104",
    "sg:province":"MI",
    "sg:tags":[
        "reporting"
    ],
    "wof:name":"Allen T Burnham",
    "wof:placetype":"venue"
},
  "geometry": {"coordinates":[-83.7461,42.279511],"type":"Point"}
}