{
  "type": "Feature",
  "properties": {
    "iso:country":"US",
    "sg:address":"2045 Holton Rd",
    "sg:city":"Muskegon",
    "sg:classifiers":[
        {
            "category":"Professional",
            "subcategory":"Business Services",
            "type":"Services"
        }
    ],
    "sg:phone":"+1 231 744 9572",
    "sg:postcode":"49445",
    "sg:province":"MI",
    "sg:tags":[
        "interior",
        "decorating"
    ],
    "wof:name":"Vogue Interiors",
    "wof:placetype":"venue"
},
  "geometry": {"coordinates":[-86.211372,43.29126],"type":"Point"}
}