{
  "type": "Feature",
  "properties": {
    "iso:country":"US",
    "sg:address":"3288 W Stoll Rd",
    "sg:city":"Lansing",
    "sg:classifiers":[
        {
            "category":"Organizations",
            "subcategory":"Community Association",
            "type":"Services"
        }
    ],
    "sg:phone":"+1 517 323 7737",
    "sg:postcode":"48906",
    "sg:province":"MI",
    "wof:name":"Klc Inc",
    "wof:placetype":"venue"
},
  "geometry": {"coordinates":[-84.58012100000001,42.798877],"type":"Point"}
}