{
  "type": "Feature",
  "properties": {
    "iso:country":"US",
    "sg:address":"1506 W Bennett St",
    "sg:city":"Lansing",
    "sg:classifiers":[
        {
            "category":"Building & Trades",
            "subcategory":"Plumbing",
            "type":"Services"
        }
    ],
    "sg:phone":"+1 517 484 1430",
    "sg:postcode":"48906",
    "sg:province":"MI",
    "sg:tags":[
        "contractor"
    ],
    "wof:name":"Hazel Heating",
    "wof:placetype":"venue"
},
  "geometry": {"coordinates":[-84.553977,42.782193],"type":"Point"}
}