{
  "type": "Feature",
  "properties": {
    "iso:country":"US",
    "sg:address":"615 Springbrook Ave",
    "sg:city":"Adrian",
    "sg:classifiers":[
        {
            "category":"Education",
            "subcategory":"School",
            "type":"Public Place"
        }
    ],
    "sg:phone":"+1 517 263 0543",
    "sg:postcode":"49221",
    "sg:province":"MI",
    "wof:name":"Springbrook Middle School",
    "wof:placetype":"venue"
},
  "geometry": {"coordinates":[-84.039985,41.908897],"type":"Point"}
}