{
  "type": "Feature",
  "properties": {
    "iso:country":"US",
    "sg:address":"7921 Krisdale Dr",
    "sg:city":"Saginaw",
    "sg:classifiers":[
        {
            "category":"Social Services",
            "subcategory":"Child Care",
            "type":"Services"
        }
    ],
    "sg:phone":"+1 989 781 1438",
    "sg:postcode":"48609",
    "sg:province":"MI",
    "sg:tags":[
        "day",
        "provider"
    ],
    "wof:name":"Mancillas Constance Day Care",
    "wof:placetype":"venue"
},
  "geometry": {"coordinates":[-84.069969,43.427881],"type":"Point"}
}