{
  "type": "Feature",
  "properties": {
    "iso:country":"US",
    "sg:address":"15301 Park St",
    "sg:city":"Oak Park",
    "sg:classifiers":[
        {
            "category":"Manufacturing",
            "subcategory":"Printing",
            "type":"Manufacturing & Wholesale Goods"
        }
    ],
    "sg:phone":"+1 248 968 3807",
    "sg:postcode":"48237",
    "sg:province":"MI",
    "sg:tags":[
        "printer"
    ],
    "wof:name":"Bluesky Specialty & Graphics",
    "wof:placetype":"venue"
},
  "geometry": {"coordinates":[-83.200546,42.46572],"type":"Point"}
}