{
  "type": "Feature",
  "properties": {
    "iso:country":"US",
    "sg:address":"6175 Northland Dr NE",
    "sg:city":"Rockford",
    "sg:classifiers":[
        {
            "category":"Organizations",
            "subcategory":"Religious Organization",
            "type":"Services"
        }
    ],
    "sg:phone":"+1 616 866 9546",
    "sg:postcode":"49341",
    "sg:province":"MI",
    "sg:tags":[
        "church"
    ],
    "wof:name":"Victory Church",
    "wof:placetype":"venue"
},
  "geometry": {"coordinates":[-85.57548800000001,43.07432],"type":"Point"}
}