{
  "type": "Feature",
  "properties": {
    "iso:country":"US",
    "sg:address":"1915 Lansing Ave",
    "sg:city":"Jackson",
    "sg:classifiers":[
        {
            "category":"Personal",
            "subcategory":"Beauty Salon",
            "type":"Services"
        }
    ],
    "sg:phone":"+1 517 768 7450",
    "sg:postcode":"49202",
    "sg:province":"MI",
    "wof:name":"Beauty Factor",
    "wof:placetype":"venue"
},
  "geometry": {"coordinates":[-84.415414,42.270821],"type":"Point"}
}