{
  "type": "Feature",
  "properties": {
    "iso:country":"US",
    "sg:address":"945 Riley Center Rd",
    "sg:city":"Memphis",
    "sg:classifiers":[
        {
            "category":"Retail",
            "subcategory":"Auto Repair",
            "type":"Services"
        }
    ],
    "sg:phone":"+1 810 392 3561",
    "sg:postcode":"48041",
    "sg:province":"MI",
    "sg:tags":[
        "general"
    ],
    "wof:name":"V Racing",
    "wof:placetype":"venue"
},
  "geometry": {"coordinates":[-82.841103,42.923426],"type":"Point"}
}