{
  "type": "Feature",
  "properties": {
    "iso:country":"US",
    "sg:address":"26678 Telegraph Rd",
    "sg:city":"Flat Rock",
    "sg:classifiers":[
        {
            "category":"Restaurant",
            "type":"Food & Drink"
        }
    ],
    "sg:menulink":"http://www.allmenus.com/mi/flat-rock/146276-subway/menu/",
    "sg:phone":"+1 734 782 6555",
    "sg:postcode":"48134",
    "sg:province":"MI",
    "sg:tags":[
        "american",
        "sandwich"
    ],
    "wof:name":"Subway",
    "wof:placetype":"venue"
},
  "geometry": {"coordinates":[-83.284057,42.111053],"type":"Point"}
}