{
  "type": "Feature",
  "properties": {
    "iso:country":"US",
    "sg:address":"23300 Greenfield Rd",
    "sg:city":"Oak Park",
    "sg:classifiers":[
        {
            "category":"Communications",
            "type":"Services"
        }
    ],
    "sg:phone":"+1 248 440 5611",
    "sg:postcode":"48237",
    "sg:province":"MI",
    "sg:tags":[
        "web",
        "design"
    ],
    "wof:name":"Enet Designs",
    "wof:placetype":"venue"
},
  "geometry": {"coordinates":[-83.201103,42.4613],"type":"Point"}
}