{
  "type": "Feature",
  "properties": {
    "iso:country":"US",
    "sg:address":"1111 E Beecher St",
    "sg:city":"Adrian",
    "sg:classifiers":[
        {
            "category":"Wholesale",
            "subcategory":"Machinery & Supplies",
            "type":"Manufacturing & Wholesale Goods"
        }
    ],
    "sg:phone":"+1 517 263 4671",
    "sg:postcode":"49221",
    "sg:province":"MI",
    "sg:tags":[
        "equipment",
        "industrial"
    ],
    "wof:name":"Industrial Mill Supply Corp",
    "wof:placetype":"venue"
},
  "geometry": {"coordinates":[-84.01909499999999,41.889852],"type":"Point"}
}