{
  "type": "Feature",
  "properties": {
    "iso:country":"US",
    "sg:address":"150 Marblehead Dr",
    "sg:city":"Bloomfield Hills",
    "sg:classifiers":[
        {
            "category":"Professional",
            "subcategory":"Business Services",
            "type":"Services"
        }
    ],
    "sg:phone":"+1 248 647 5430",
    "sg:postcode":"48304",
    "sg:province":"MI",
    "sg:tags":[
        "furniture"
    ],
    "wof:name":"R L Interior Associates Inc",
    "wof:placetype":"venue"
},
  "geometry": {"coordinates":[-83.25912700000001,42.562721],"type":"Point"}
}