{
  "type": "Feature",
  "properties": {
    "iso:country":"US",
    "sg:address":"152 Hillsdale St",
    "sg:city":"Hillsdale",
    "sg:classifiers":[
        {
            "category":"Organizations",
            "subcategory":"Religious Organization",
            "type":"Services"
        }
    ],
    "sg:phone":"+1 517 439 9412",
    "sg:postcode":"49242",
    "sg:province":"MI",
    "wof:name":"Christ Church Hillsdale",
    "wof:placetype":"venue"
},
  "geometry": {"coordinates":[-84.63173,41.927908],"type":"Point"}
}