{
  "type": "Feature",
  "properties": {
    "iso:country":"US",
    "sg:address":"5370 Marl Lake Rd",
    "sg:city":"Roscommon",
    "sg:classifiers":[
        {
            "category":"Travel",
            "subcategory":"Campground",
            "type":"Entertainment"
        }
    ],
    "sg:phone":"+1 989 821 9486",
    "sg:postcode":"48653",
    "sg:province":"MI",
    "sg:tags":[
        "trailer"
    ],
    "wof:name":"Great Circle Campground",
    "wof:placetype":"venue"
},
  "geometry": {"coordinates":[-84.72454500000001,44.421184],"type":"Point"}
}