{
  "type": "Feature",
  "properties": {
    "iso:country":"US",
    "sg:address":"7752 Hidden Ridge Ct",
    "sg:city":"Hudsonville",
    "sg:classifiers":[
        {
            "category":"Building & Trades",
            "subcategory":"Construction",
            "type":"Services"
        }
    ],
    "sg:phone":"+1 616 669 0446",
    "sg:postcode":"49426",
    "sg:province":"MI",
    "sg:tags":[
        "home",
        "builder"
    ],
    "wof:name":"R & R Custom Homes",
    "wof:placetype":"venue"
},
  "geometry": {"coordinates":[-85.896342,42.909889],"type":"Point"}
}