{
  "type": "Feature",
  "properties": {
    "iso:country":"US",
    "sg:address":"512 W Michigan Ave",
    "sg:city":"Marshall",
    "sg:classifiers":[
        {
            "category":"Mining & Drilling",
            "type":"Manufacturing & Wholesale Goods"
        }
    ],
    "sg:phone":"+1 269 781 5507",
    "sg:postcode":"49068",
    "sg:province":"MI",
    "sg:tags":[
        "home",
        "repair"
    ],
    "wof:name":"Woods Home Maintenance",
    "wof:placetype":"venue"
},
  "geometry": {"coordinates":[-84.96697,42.272112],"type":"Point"}
}