{
  "type": "Feature",
  "properties": {
    "iso:country":"US",
    "sg:address":"5930 Lovers Ln",
    "sg:city":"Portage",
    "sg:classifiers":[
        {
            "category":"Health Services",
            "subcategory":"Health Practitioner",
            "type":"Services"
        }
    ],
    "sg:phone":"+1 269 383 0248",
    "sg:postcode":"49002",
    "sg:province":"MI",
    "sg:tags":[
        "psychologist"
    ],
    "wof:name":"Patricia Guilford PHD",
    "wof:placetype":"venue"
},
  "geometry": {"coordinates":[-85.57452000000001,42.232934],"type":"Point"}
}