{
  "type": "Feature",
  "properties": {
    "iso:country":"US",
    "sg:address":"8656 War Bonnet Dr",
    "sg:city":"Commerce Township",
    "sg:classifiers":[
        {
            "category":"Personal",
            "subcategory":"Shoe Repair & Shine",
            "type":"Services"
        }
    ],
    "sg:phone":"+1 248 926 3115",
    "sg:postcode":"48382",
    "sg:province":"MI",
    "sg:tags":[
        "making",
        "boot"
    ],
    "wof:name":"Walled Lake Shoe Repair",
    "wof:placetype":"venue"
},
  "geometry": {"coordinates":[-83.45627399999999,42.597933],"type":"Point"}
}