{
  "type": "Feature",
  "properties": {
    "iso:country":"US",
    "sg:address":"25 Moeller St",
    "sg:city":"Pigeon",
    "sg:classifiers":[
        {
            "category":"Organizations",
            "subcategory":"Religious Organization",
            "type":"Services"
        }
    ],
    "sg:phone":"+1 989 453 2151",
    "sg:postcode":"48755",
    "sg:province":"MI",
    "sg:tags":[
        "church"
    ],
    "wof:name":"St Francis Borgia Catholic",
    "wof:placetype":"venue"
},
  "geometry": {"coordinates":[-83.276955,43.830677],"type":"Point"}
}