{
  "type": "Feature",
  "properties": {
    "iso:country":"US",
    "sg:address":"37200 Amrhein Rd",
    "sg:city":"Livonia",
    "sg:classifiers":[
        {
            "category":"Professional",
            "subcategory":"Research",
            "type":"Services"
        }
    ],
    "sg:phone":"+1 313 252 7676",
    "sg:postcode":"48150",
    "sg:province":"MI",
    "sg:tags":[
        "engine",
        "car",
        "design",
        "build"
    ],
    "wof:name":"Daimlerchrysler Corporation",
    "wof:placetype":"venue"
},
  "geometry": {"coordinates":[-83.410377,42.374703],"type":"Point"}
}