{
  "type": "Feature",
  "properties": {
    "iso:country":"US",
    "sg:address":"1861 S Scott Rd",
    "sg:city":"St Johns",
    "sg:classifiers":[
        {
            "category":"Restaurant",
            "type":"Food & Drink"
        }
    ],
    "sg:phone":"+1 989 224 1090",
    "sg:postcode":"48879",
    "sg:province":"MI",
    "wof:name":"Dairy Queen",
    "wof:placetype":"venue"
},
  "geometry": {"coordinates":[-84.542377,42.988116],"type":"Point"}
}