{
  "type": "Feature",
  "properties": {
    "iso:country":"US",
    "sg:address":"6365 Oak St",
    "sg:city":"Gladwin",
    "sg:classifiers":[
        {
            "category":"Bars & Pubs",
            "type":"Food & Drink"
        }
    ],
    "sg:phone":"+1 989 345 4373",
    "sg:postcode":"48624",
    "sg:province":"MI",
    "wof:name":"Elk Lake Bar",
    "wof:placetype":"venue"
},
  "geometry": {"coordinates":[-84.355981,44.160733],"type":"Point"}
}