{
  "type": "Feature",
  "properties": {
    "iso:country":"US",
    "sg:address":"49 Le Gault St",
    "sg:city":"Howell",
    "sg:classifiers":[
        {
            "category":"Social Services",
            "subcategory":"Child Care",
            "type":"Services"
        }
    ],
    "sg:phone":"+1 517 546 7240",
    "sg:postcode":"48843",
    "sg:province":"MI",
    "sg:tags":[
        "day"
    ],
    "wof:name":"Missy Munchkins Daycare",
    "wof:placetype":"venue"
},
  "geometry": {"coordinates":[-83.93778,42.596361],"type":"Point"}
}