{
  "type": "Feature",
  "properties": {
    "iso:country":"US",
    "sg:address":"5588 N Sturgeon Rd",
    "sg:city":"Midland",
    "sg:classifiers":[
        {
            "category":"Professional",
            "subcategory":"Computer Services",
            "type":"Services"
        }
    ],
    "sg:phone":"+1 989 689 5485",
    "sg:postcode":"48642",
    "sg:province":"MI",
    "sg:tags":[
        "repair"
    ],
    "wof:name":"Elite Computer Svc Inc",
    "wof:placetype":"venue"
},
  "geometry": {"coordinates":[-84.26702400000001,43.782583],"type":"Point"}
}