{
  "type": "Feature",
  "properties": {
    "iso:country":"US",
    "sg:address":"33155 Annapolis St",
    "sg:city":"Wayne",
    "sg:classifiers":[
        {
            "category":"Health Services",
            "subcategory":"Clinic",
            "type":"Services"
        }
    ],
    "sg:phone":"+1 734 467 4200",
    "sg:postcode":"48184",
    "sg:province":"MI",
    "wof:name":"Oak Wood Annapolis Center",
    "wof:placetype":"venue"
},
  "geometry": {"coordinates":[-83.364046,42.27426],"type":"Point"}
}