{
  "type": "Feature",
  "properties": {
    "iso:country":"US",
    "sg:address":"1383 Park St",
    "sg:city":"Muskegon",
    "sg:classifiers":[
        {
            "category":"Social Services",
            "subcategory":"Adult Care",
            "type":"Services"
        },
        {
            "category":"Health Services",
            "subcategory":"Nursing And Care Facility",
            "type":"Services"
        }
    ],
    "sg:phone":"+1 231 722 3972",
    "sg:postcode":"49441",
    "sg:province":"MI",
    "sg:tags":[
        "residential"
    ],
    "wof:name":"Park Place Personal Care Home",
    "wof:placetype":"venue"
},
  "geometry": {"coordinates":[-86.25426299999999,43.227477],"type":"Point"}
}