{
  "type": "Feature",
  "properties": {
    "iso:country":"US",
    "sg:address":"615 W Lafayette Blvd",
    "sg:city":"Detroit",
    "sg:classifiers":[
        {
            "category":"Education",
            "subcategory":"Library",
            "type":"Public Place"
        }
    ],
    "sg:phone":"+1 313 222 2110",
    "sg:postcode":"48226",
    "sg:province":"MI",
    "wof:name":"George B Catlin Memorial Libr",
    "wof:placetype":"venue"
},
  "geometry": {"coordinates":[-83.05493,42.328572],"type":"Point"}
}