{
  "type": "Feature",
  "properties": {
    "iso:country":"US",
    "sg:address":"1819 Bagwell St",
    "sg:city":"Flint",
    "sg:classifiers":[
        {
            "category":"Professional",
            "subcategory":"Management & Consulting",
            "type":"Services"
        }
    ],
    "sg:phone":"+1 810 635 1262",
    "sg:postcode":"48503",
    "sg:province":"MI",
    "sg:tags":[
        "retail",
        "direct",
        "sales"
    ],
    "wof:name":"Glenn & Assoc",
    "wof:placetype":"venue"
},
  "geometry": {"coordinates":[-83.647999,43.00423],"type":"Point"}
}