{
  "type": "Feature",
  "properties": {
    "iso:country":"US",
    "sg:address":"5235 Park Ave",
    "sg:city":"Hudsonville",
    "sg:classifiers":[
        {
            "category":"Organizations",
            "subcategory":"Professional Association",
            "type":"Services"
        }
    ],
    "sg:phone":"+1 616 669 1630",
    "sg:postcode":"49426",
    "sg:province":"MI",
    "wof:name":"Hudsonville Fair Assn",
    "wof:placetype":"venue"
},
  "geometry": {"coordinates":[-85.875556,42.863994],"type":"Point"}
}