{
  "type": "Feature",
  "properties": {
    "iso:country":"US",
    "sg:address":"1719 S Otsego Ave",
    "sg:city":"Gaylord",
    "sg:classifiers":[
        {
            "category":"Retail",
            "subcategory":"Repair Shop",
            "type":"Services"
        }
    ],
    "sg:phone":"+1 989 732 8337",
    "sg:postcode":"49735",
    "sg:province":"MI",
    "sg:tags":[
        "small",
        "engine"
    ],
    "wof:name":"Small Engine Service Inc",
    "wof:placetype":"venue"
},
  "geometry": {"coordinates":[-84.677454,45.005486],"type":"Point"}
}