{
  "type": "Feature",
  "properties": {
    "iso:country":"US",
    "sg:address":"10314 Ford Hwy",
    "sg:city":"Tecumseh",
    "sg:classifiers":[
        {
            "category":"Building & Trades",
            "subcategory":"Cleaning & Sanitation",
            "type":"Services"
        }
    ],
    "sg:phone":"+1 517 423 4427",
    "sg:postcode":"49286",
    "sg:province":"MI",
    "sg:tags":[
        "light",
        "sandblasting",
        "maintenance",
        "paint"
    ],
    "wof:name":"Schafers Inc",
    "wof:placetype":"venue"
},
  "geometry": {"coordinates":[-83.870656,42.046096],"type":"Point"}
}