{
  "type": "Feature",
  "properties": {
    "iso:country":"US",
    "sg:address":"249 Sprague Rd",
    "sg:city":"Coldwater",
    "sg:classifiers":[
        {
            "category":"Building & Trades",
            "subcategory":"Construction",
            "type":"Services"
        }
    ],
    "sg:phone":"+1 517 278 4995",
    "sg:postcode":"49036",
    "sg:province":"MI",
    "sg:tags":[
        "house"
    ],
    "wof:name":"Charles R Todd Residential Bui",
    "wof:placetype":"venue"
},
  "geometry": {"coordinates":[-84.99041099999999,41.915332],"type":"Point"}
}