{
  "type": "Feature",
  "properties": {
    "iso:country":"US",
    "sg:address":"4020 W River Dr NE",
    "sg:city":"Comstock Park",
    "sg:classifiers":[
        {
            "category":"Freight",
            "type":"Transportation"
        }
    ],
    "sg:phone":"+1 616 361 3930",
    "sg:postcode":"49321",
    "sg:province":"MI",
    "sg:tags":[
        "delivery"
    ],
    "wof:name":"Two Men & A Truck",
    "wof:placetype":"venue"
},
  "geometry": {"coordinates":[-85.663788,43.037193],"type":"Point"}
}