{
  "type": "Feature",
  "properties": {
    "iso:country":"US",
    "sg:address":"1725 E 14 Mile Rd",
    "sg:city":"Troy",
    "sg:classifiers":[
        {
            "category":"Wholesale",
            "subcategory":"Durable Goods & Equipment",
            "type":"Manufacturing & Wholesale Goods"
        }
    ],
    "sg:phone":"+1 248 577 0718",
    "sg:postcode":"48083",
    "sg:province":"MI",
    "sg:tags":[
        "exporter"
    ],
    "wof:name":"U S Export LLC",
    "wof:placetype":"venue"
},
  "geometry": {"coordinates":[-83.08776,42.534826],"type":"Point"}
}