{
  "type": "Feature",
  "properties": {
    "iso:country":"US",
    "sg:address":"322 Willow Grove Ln",
    "sg:city":"Rochester Hills",
    "sg:classifiers":[
        {
            "category":"Professional",
            "type":"Services"
        }
    ],
    "sg:phone":"+1 248 650 9282",
    "sg:postcode":"48307",
    "sg:province":"MI",
    "sg:tags":[
        "establishment"
    ],
    "wof:name":"High Point Marketing Assoc",
    "wof:placetype":"venue"
},
  "geometry": {"coordinates":[-83.150961,42.676506],"type":"Point"}
}