{
  "type": "Feature",
  "properties": {
    "iso:country":"US",
    "sg:address":"5180 N Dort Hwy",
    "sg:city":"Flint",
    "sg:classifiers":[
        {
            "category":"Freight",
            "type":"Transportation"
        }
    ],
    "sg:phone":"+1 810 695 0540",
    "sg:postcode":"48505",
    "sg:province":"MI",
    "sg:tags":[
        "storage",
        "rent",
        "unit"
    ],
    "wof:name":"Shurgard Storage Centers",
    "wof:placetype":"venue"
},
  "geometry": {"coordinates":[-83.6738,43.059706],"type":"Point"}
}