{
  "type": "Feature",
  "properties": {
    "iso:country":"US",
    "sg:address":"3460 Flansburgh Rd",
    "sg:city":"Jackson",
    "sg:classifiers":[
        {
            "category":"Retail",
            "subcategory":"Repair Shop",
            "type":"Services"
        }
    ],
    "sg:phone":"+1 517 764 6939",
    "sg:postcode":"49203",
    "sg:province":"MI",
    "wof:name":"Tri State Hydraulics Company",
    "wof:placetype":"venue"
},
  "geometry": {"coordinates":[-84.35078900000001,42.217358],"type":"Point"}
}