{
  "type": "Feature",
  "properties": {
    "iso:country":"US",
    "sg:address":"2315 E Carriage Hills Dr",
    "sg:city":"Traverse City",
    "sg:classifiers":[
        {
            "category":"Freight",
            "type":"Transportation"
        }
    ],
    "sg:phone":"+1 231 929 0439",
    "sg:postcode":"49686",
    "sg:province":"MI",
    "sg:tags":[
        "operator",
        "local",
        "trucking"
    ],
    "wof:name":"Joseph W Schueller",
    "wof:placetype":"venue"
},
  "geometry": {"coordinates":[-85.597606,44.719633],"type":"Point"}
}