{
  "type": "Feature",
  "properties": {
    "iso:country":"US",
    "sg:address":"85 Logan St",
    "sg:city":"Battle Creek",
    "sg:classifiers":[
        {
            "category":"Retail",
            "subcategory":"Self-service Laundry",
            "type":"Services"
        }
    ],
    "sg:phone":"+1 269 968 8675",
    "sg:postcode":"49015",
    "sg:province":"MI",
    "sg:tags":[
        "coin"
    ],
    "wof:name":"Quick Clean",
    "wof:placetype":"venue"
},
  "geometry": {"coordinates":[-85.190867,42.305164],"type":"Point"}
}