{
  "type": "Feature",
  "properties": {
    "iso:country":"US",
    "sg:address":"10580 Tefft Ave NE",
    "sg:city":"Rockford",
    "sg:classifiers":[
        {
            "category":"Building & Trades",
            "subcategory":"Cleaning & Sanitation",
            "type":"Services"
        }
    ],
    "sg:phone":"+1 616 866 1027",
    "sg:postcode":"49341",
    "sg:province":"MI",
    "sg:tags":[
        "snow",
        "removal"
    ],
    "wof:name":"Horticultural Designs Inc",
    "wof:placetype":"venue"
},
  "geometry": {"coordinates":[-85.52045699999999,43.149296],"type":"Point"}
}