{
  "type": "Feature",
  "properties": {
    "iso:country":"US",
    "sg:address":"204 Ideal Rd",
    "sg:city":"Milan",
    "sg:classifiers":[
        {
            "category":"Personal",
            "subcategory":"Beauty Salon",
            "type":"Services"
        }
    ],
    "sg:phone":"+1 734 439 2285",
    "sg:postcode":"48160",
    "sg:province":"MI",
    "sg:tags":[
        "shop"
    ],
    "wof:name":"Hair By Debra",
    "wof:placetype":"venue"
},
  "geometry": {"coordinates":[-83.670613,42.087186],"type":"Point"}
}