{
  "type": "Feature",
  "properties": {
    "iso:country":"US",
    "sg:address":"6371 State St",
    "sg:city":"Caseville",
    "sg:classifiers":[
        {
            "category":"Real Estate",
            "subcategory":"Real Estate Agent",
            "type":"Services"
        }
    ],
    "sg:phone":"+1 989 856 4631",
    "sg:postcode":"48725",
    "sg:province":"MI",
    "wof:name":"Riverside Real Estate",
    "wof:placetype":"venue"
},
  "geometry": {"coordinates":[-83.26979799999999,43.947451],"type":"Point"}
}