{
  "type": "Feature",
  "properties": {
    "iso:country":"US",
    "sg:address":"3949 E 9 Mile Rd",
    "sg:city":"Warren",
    "sg:classifiers":[
        {
            "category":"Organizations",
            "subcategory":"Religious Organization",
            "type":"Services"
        }
    ],
    "sg:phone":"+1 248 689 1270",
    "sg:postcode":"48091",
    "sg:province":"MI",
    "wof:name":"Assembly of God",
    "wof:placetype":"venue"
},
  "geometry": {"coordinates":[-83.065804,42.462299],"type":"Point"}
}