{
  "type": "Feature",
  "properties": {
    "iso:country":"US",
    "sg:address":"7237 N Canton Center Rd",
    "sg:city":"Canton",
    "sg:classifiers":[
        {
            "category":"Health Services",
            "subcategory":"Optometrist",
            "type":"Services"
        },
        {
            "category":"Shopping",
            "subcategory":"Optician",
            "type":"Retail Goods"
        }
    ],
    "sg:phone":"+1 734 416 5005",
    "sg:postcode":"48187",
    "sg:province":"MI",
    "sg:tags":[
        "eyewear"
    ],
    "wof:name":"Canton Visionpro Eye Care",
    "wof:placetype":"venue"
},
  "geometry": {"coordinates":[-83.488899,42.337399],"type":"Point"}
}