{
  "type": "Feature",
  "properties": {
    "iso:country":"US",
    "sg:address":"4545 Nestrom Rd",
    "sg:city":"Whitehall",
    "sg:classifiers":[
        {
            "category":"Government",
            "subcategory":"Office",
            "type":"Public Place"
        }
    ],
    "sg:phone":"+1 231 766 3208",
    "sg:postcode":"49461",
    "sg:province":"MI",
    "sg:tags":[
        "village"
    ],
    "wof:name":"Fruitland Twp Office",
    "wof:placetype":"venue"
},
  "geometry": {"coordinates":[-86.37654499999999,43.335584],"type":"Point"}
}