{
  "type": "Feature",
  "properties": {
    "iso:country":"US",
    "sg:address":"4622 E Brutus Rd",
    "sg:city":"Alanson",
    "sg:classifiers":[
        {
            "category":"Building & Trades",
            "subcategory":"Landscaping Services",
            "type":"Services"
        }
    ],
    "sg:phone":"+1 231 529 8585",
    "sg:postcode":"49706",
    "sg:province":"MI",
    "sg:tags":[
        "landscape"
    ],
    "wof:name":"Birchwood Landscaping Co",
    "wof:placetype":"venue"
},
  "geometry": {"coordinates":[-84.820336,45.492984],"type":"Point"}
}