{
  "type": "Feature",
  "properties": {
    "iso:country":"US",
    "sg:address":"82 Park Dr",
    "sg:city":"Troy",
    "sg:classifiers":[
        {
            "category":"Professional",
            "type":"Services"
        }
    ],
    "sg:phone":"+1 248 589 8010",
    "sg:postcode":"48083",
    "sg:province":"MI",
    "sg:tags":[
        "establishment"
    ],
    "wof:name":"Quality Water & Air Inc",
    "wof:placetype":"venue"
},
  "geometry": {"coordinates":[-83.148848,42.54359],"type":"Point"}
}