{
  "type": "Feature",
  "properties": {
    "iso:country":"US",
    "sg:address":"6321 Normandy Dr",
    "sg:city":"Saginaw",
    "sg:classifiers":[
        {
            "category":"Wholesale",
            "subcategory":"Non-durable Goods",
            "type":"Manufacturing & Wholesale Goods"
        }
    ],
    "sg:phone":"+1 989 797 2632",
    "sg:postcode":"48638",
    "sg:province":"MI",
    "sg:tags":[
        "advertising"
    ],
    "wof:name":"Panda Promotional Products",
    "wof:placetype":"venue"
},
  "geometry": {"coordinates":[-84.03912099999999,43.43184],"type":"Point"}
}