{
  "type": "Feature",
  "properties": {
    "iso:country":"US",
    "sg:address":"183 W Gates St",
    "sg:city":"Romeo",
    "sg:classifiers":[
        {
            "category":"Travel",
            "subcategory":"Hotels & Motels",
            "type":"Entertainment"
        }
    ],
    "sg:phone":"+1 586 752 3535",
    "sg:postcode":"48065",
    "sg:province":"MI",
    "wof:name":"Romeo Inn",
    "wof:placetype":"venue"
},
  "geometry": {"coordinates":[-83.01627999999999,42.809878],"type":"Point"}
}