{
  "type": "Feature",
  "properties": {
    "iso:country":"US",
    "sg:address":"16606 Marlowe St",
    "sg:city":"Detroit",
    "sg:classifiers":[
        {
            "category":"Social Services",
            "subcategory":"Child Care",
            "type":"Services"
        }
    ],
    "sg:phone":"+1 313 837 2444",
    "sg:postcode":"48235",
    "sg:province":"MI",
    "sg:tags":[
        "day"
    ],
    "wof:name":"A Time For Everything",
    "wof:placetype":"venue"
},
  "geometry": {"coordinates":[-83.19052600000001,42.413254],"type":"Point"}
}