{
  "type": "Feature",
  "properties": {
    "iso:country":"US",
    "sg:address":"6840 Bluegrass Dr",
    "sg:city":"Clarkston",
    "sg:classifiers":[
        {
            "category":"Building & Trades",
            "subcategory":"Construction",
            "type":"Services"
        }
    ],
    "sg:phone":"+1 248 620 6330",
    "sg:postcode":"48346",
    "sg:province":"MI",
    "sg:tags":[
        "contractor"
    ],
    "wof:name":"Armand Drilling & Dewatering",
    "wof:placetype":"venue"
},
  "geometry": {"coordinates":[-83.422732,42.74392],"type":"Point"}
}