{
  "type": "Feature",
  "properties": {
    "iso:country":"US",
    "sg:address":"4730 Clarkston Rd",
    "sg:city":"Clarkston",
    "sg:classifiers":[
        {
            "category":"Retail",
            "subcategory":"Laundry & Dry Cleaning",
            "type":"Services"
        }
    ],
    "sg:phone":"+1 248 394 0688",
    "sg:postcode":"48348",
    "sg:province":"MI",
    "sg:tags":[
        "cleaners"
    ],
    "wof:name":"Sim Dry Cleaning",
    "wof:placetype":"venue"
},
  "geometry": {"coordinates":[-83.33941799999999,42.763945],"type":"Point"}
}