{
  "type": "Feature",
  "properties": {
    "iso:country":"US",
    "sg:address":"119 S Matteson St",
    "sg:city":"Bronson",
    "sg:classifiers":[
        {
            "category":"Professional",
            "type":"Services"
        }
    ],
    "sg:phone":"+1 269 489 2232",
    "sg:postcode":"49028",
    "sg:province":"MI",
    "wof:name":"Angel Wolf Studio Inc",
    "wof:placetype":"venue"
},
  "geometry": {"coordinates":[-85.19457300000001,41.872147],"type":"Point"}
}