{
  "type": "Feature",
  "properties": {
    "iso:country":"US",
    "sg:address":"725 Seneca Pl",
    "sg:city":"Cadillac",
    "sg:classifiers":[
        {
            "category":"Government",
            "subcategory":"Office",
            "type":"Public Place"
        }
    ],
    "sg:phone":"+1 231 775 3581",
    "sg:postcode":"49601",
    "sg:province":"MI",
    "sg:website":"www.michigan.gov",
    "wof:name":"Highway Sign Shop",
    "wof:placetype":"venue"
},
  "geometry": {"coordinates":[-85.436673,44.254469],"type":"Point"}
}