{
  "type": "Feature",
  "properties": {
    "iso:country":"US",
    "sg:address":"1408 W 48th St",
    "sg:city":"Fremont",
    "sg:classifiers":[
        {
            "category":"Restaurant",
            "type":"Food & Drink"
        }
    ],
    "sg:menulink":"http://www.allmenus.com/mi/sherman/210808-arbys/menu/",
    "sg:phone":"+1 231 928 0644",
    "sg:postcode":"49412",
    "sg:province":"MI",
    "sg:tags":[
        "burger",
        "american"
    ],
    "wof:name":"Arby's",
    "wof:placetype":"venue"
},
  "geometry": {"coordinates":[-85.83579899999999,43.466846],"type":"Point"}
}