{
  "type": "Feature",
  "properties": {
    "iso:country":"US",
    "sg:address":"21258 Hetke Dr",
    "sg:city":"Farmington Hills",
    "sg:classifiers":[
        {
            "category":"Real Estate",
            "subcategory":"Architect",
            "type":"Services"
        }
    ],
    "sg:phone":"+1 248 755 0388",
    "sg:postcode":"48335",
    "sg:province":"MI",
    "sg:tags":[
        "estimate",
        "construction"
    ],
    "wof:name":"Des Consulting",
    "wof:placetype":"venue"
},
  "geometry": {"coordinates":[-83.409009,42.445475],"type":"Point"}
}