{
  "type": "Feature",
  "properties": {
    "iso:country":"US",
    "sg:address":"5109 Chene St",
    "sg:city":"Detroit",
    "sg:classifiers":[
        {
            "category":"Organizations",
            "subcategory":"Religious Organization",
            "type":"Services"
        }
    ],
    "sg:phone":"+1 313 924 3022",
    "sg:postcode":"48211",
    "sg:province":"MI",
    "wof:name":"Jericho Mssonary Baptst Church",
    "wof:placetype":"venue"
},
  "geometry": {"coordinates":[-83.04178400000001,42.367043],"type":"Point"}
}