{
  "type": "Feature",
  "properties": {
    "iso:country":"US",
    "sg:address":"3999 County 416 20th Rd",
    "sg:city":"Gladstone",
    "sg:classifiers":[
        {
            "category":"Wholesale",
            "subcategory":"Stationery",
            "type":"Manufacturing & Wholesale Goods"
        }
    ],
    "sg:phone":"+1 906 786 8088",
    "sg:postcode":"49837",
    "sg:province":"MI",
    "sg:tags":[
        "school",
        "supply"
    ],
    "wof:name":"Chenier Educational Ent",
    "wof:placetype":"venue"
},
  "geometry": {"coordinates":[-87.164911,45.826026],"type":"Point"}
}