{
  "type": "Feature",
  "properties": {
    "iso:country":"US",
    "sg:address":"420 Prospect St",
    "sg:city":"Munising",
    "sg:classifiers":[
        {
            "category":"Travel",
            "subcategory":"Hotels & Motels",
            "type":"Entertainment"
        }
    ],
    "sg:phone":"+1 906 387 2735",
    "sg:postcode":"49862",
    "sg:province":"MI",
    "wof:name":"Terrace Motel",
    "wof:placetype":"venue"
},
  "geometry": {"coordinates":[-86.651644,46.403881],"type":"Point"}
}