{
  "type": "Feature",
  "properties": {
    "iso:country":"US",
    "sg:address":"1136 Shepard St",
    "sg:city":"Lansing",
    "sg:classifiers":[
        {
            "category":"Museum",
            "type":"Entertainment"
        }
    ],
    "sg:phone":"+1 517 484 7480",
    "sg:postcode":"48912",
    "sg:province":"MI",
    "sg:tags":[
        "gallery"
    ],
    "wof:name":"African Afrcan Amrcn Rsrce Ctr",
    "wof:placetype":"venue"
},
  "geometry": {"coordinates":[-84.52623699999999,42.721645],"type":"Point"}
}