{
  "type": "Feature",
  "properties": {
    "iso:country":"US",
    "sg:address":"357 W Beaver Rd",
    "sg:city":"Auburn",
    "sg:classifiers":[
        {
            "category":"Professional",
            "subcategory":"Business Services",
            "type":"Services"
        }
    ],
    "sg:phone":"+1 989 662 2315",
    "sg:postcode":"48611",
    "sg:province":"MI",
    "wof:name":"R & L Interiors Inc",
    "wof:placetype":"venue"
},
  "geometry": {"coordinates":[-84.06270499999999,43.667879],"type":"Point"}
}