{
  "type": "Feature",
  "properties": {
    "iso:country":"US",
    "sg:address":"23056 Hawthorne St",
    "sg:city":"Farmington",
    "sg:classifiers":[
        {
            "category":"Autos & Motor Vehicles",
            "subcategory":"Automobile Sales",
            "type":"Retail Goods"
        }
    ],
    "sg:phone":"+1 248 471 4842",
    "sg:postcode":"48336",
    "sg:province":"MI",
    "sg:tags":[
        "limo"
    ],
    "wof:name":"Adventure Limousine Llc",
    "wof:placetype":"venue"
},
  "geometry": {"coordinates":[-83.35169999999999,42.460499],"type":"Point"}
}