{
  "type": "Feature",
  "properties": {
    "iso:country":"US",
    "sg:address":"3121 E Saginaw St",
    "sg:city":"Lansing",
    "sg:classifiers":[
        {
            "category":"Restaurant",
            "type":"Food & Drink"
        }
    ],
    "sg:menulink":"http://www.allmenus.com/mi/lansing/196862-burger-king/menu/",
    "sg:phone":"+1 517 332 2600",
    "sg:postcode":"48912",
    "sg:province":"MI",
    "sg:tags":[
        "burger",
        "american"
    ],
    "wof:name":"Burger King",
    "wof:placetype":"venue"
},
  "geometry": {"coordinates":[-84.508498,42.740864],"type":"Point"}
}