{
  "type": "Feature",
  "properties": {
    "iso:country":"US",
    "sg:address":"3904 Norwalk St",
    "sg:city":"Detroit",
    "sg:classifiers":[
        {
            "category":"Building & Trades",
            "subcategory":"Landscaping Services",
            "type":"Services"
        }
    ],
    "sg:phone":"+1 313 872 3345",
    "sg:postcode":"48212",
    "sg:province":"MI",
    "sg:tags":[
        "landscape"
    ],
    "wof:name":"Rayshawns Landscaping",
    "wof:placetype":"venue"
},
  "geometry": {"coordinates":[-83.04817199999999,42.398854],"type":"Point"}
}