{
  "type": "Feature",
  "properties": {
    "iso:country":"US",
    "sg:address":"5389 Turtle Rd",
    "sg:city":"Turner",
    "sg:classifiers":[
        {
            "category":"Building & Trades",
            "subcategory":"Construction",
            "type":"Services"
        }
    ],
    "sg:phone":"+1 989 756 4904",
    "sg:postcode":"48765",
    "sg:province":"MI",
    "sg:tags":[
        "general",
        "contractor"
    ],
    "wof:name":"Giori Construction",
    "wof:placetype":"venue"
},
  "geometry": {"coordinates":[-83.737842,44.190689],"type":"Point"}
}