{
  "type": "Feature",
  "properties": {
    "iso:country":"US",
    "sg:address":"174 Clark St",
    "sg:city":"Detroit",
    "sg:classifiers":[
        {
            "category":"Government",
            "subcategory":"Jail",
            "type":"Public Place"
        }
    ],
    "sg:phone":"+1 313 297 5200",
    "sg:postcode":"48209",
    "sg:province":"MI",
    "sg:tags":[
        "correctional",
        "institution"
    ],
    "wof:name":"Probation Offc-Spcialized Unit",
    "wof:placetype":"venue"
},
  "geometry": {"coordinates":[-83.089889,42.312031],"type":"Point"}
}