{
  "type": "Feature",
  "properties": {
    "iso:country":"US",
    "sg:address":"1805 Windingway Dr",
    "sg:city":"Wixom",
    "sg:classifiers":[
        {
            "category":"Building & Trades",
            "subcategory":"Equipment Rental",
            "type":"Services"
        }
    ],
    "sg:phone":"+1 248 669 9615",
    "sg:postcode":"48393",
    "sg:province":"MI",
    "sg:tags":[
        "leasing"
    ],
    "wof:name":"Skydiving Services Inc",
    "wof:placetype":"venue"
},
  "geometry": {"coordinates":[-83.544867,42.547712],"type":"Point"}
}