{
  "type": "Feature",
  "properties": {
    "iso:country":"US",
    "sg:address":"5694 Dorado Ct",
    "sg:city":"Rockford",
    "sg:classifiers":[
        {
            "category":"Professional",
            "subcategory":"Management & Consulting",
            "type":"Services"
        }
    ],
    "sg:phone":"+1 616 874 0545",
    "sg:postcode":"49341",
    "sg:province":"MI",
    "wof:name":"Hafele Amer Scott Debbie Mills",
    "wof:placetype":"venue"
},
  "geometry": {"coordinates":[-85.52829199999999,43.096601],"type":"Point"}
}