{
  "type": "Feature",
  "properties": {
    "iso:country":"US",
    "sg:address":"1077 Gidner Rd",
    "sg:city":"Charlotte",
    "sg:classifiers":[
        {
            "category":"Professional",
            "subcategory":"Business Services",
            "type":"Services"
        }
    ],
    "sg:phone":"+1 517 543 9539",
    "sg:postcode":"48813",
    "sg:province":"MI",
    "wof:name":"Shaw Ford & Mavis",
    "wof:placetype":"venue"
},
  "geometry": {"coordinates":[-84.778312,42.595729],"type":"Point"}
}