{
  "type": "Feature",
  "properties": {
    "iso:country":"US",
    "sg:address":"51180 Bedford St",
    "sg:city":"New Baltimore",
    "sg:classifiers":[
        {
            "category":"Wholesale",
            "subcategory":"Books, Periodicals, & Newspapers",
            "type":"Manufacturing & Wholesale Goods"
        }
    ],
    "sg:phone":"+1 586 716 8100",
    "sg:postcode":"48047",
    "sg:province":"MI",
    "sg:tags":[
        "distributor"
    ],
    "sg:website":"www.voicenews.com",
    "wof:name":"Voice Newspapers",
    "wof:placetype":"venue"
},
  "geometry": {"coordinates":[-82.735243,42.681287],"type":"Point"}
}