{
  "type": "Feature",
  "properties": {
    "iso:country":"US",
    "sg:address":"30345 Woodward Ave",
    "sg:city":"Royal Oak",
    "sg:classifiers":[
        {
            "category":"Shopping",
            "subcategory":"Jewelry",
            "type":"Retail Goods"
        }
    ],
    "sg:phone":"+1 248 435 2100",
    "sg:postcode":"48073",
    "sg:province":"MI",
    "sg:tags":[
        "jeweler"
    ],
    "wof:name":"Johannes Diamond",
    "wof:placetype":"venue"
},
  "geometry": {"coordinates":[-83.18180099999999,42.512901],"type":"Point"}
}