{
  "type": "Feature",
  "properties": {
    "iso:country":"US",
    "sg:address":"4860 Hough Rd",
    "sg:city":"Dryden",
    "sg:classifiers":[
        {
            "category":"Building & Trades",
            "subcategory":"Construction",
            "type":"Services"
        }
    ],
    "sg:phone":"+1 810 796 3949",
    "sg:postcode":"48428",
    "sg:province":"MI",
    "sg:tags":[
        "woodworker"
    ],
    "wof:name":"Shaker & Things",
    "wof:placetype":"venue"
},
  "geometry": {"coordinates":[-83.147916,42.902055],"type":"Point"}
}