{
  "type": "Feature",
  "properties": {
    "iso:country":"US",
    "sg:address":"107 N Saginaw St",
    "sg:city":"Durand",
    "sg:classifiers":[
        {
            "category":"Personal",
            "subcategory":"Shoe Repair & Shine",
            "type":"Services"
        }
    ],
    "sg:phone":"+1 989 288 2000",
    "sg:postcode":"48429",
    "sg:province":"MI",
    "sg:tags":[
        "repairing",
        "boot"
    ],
    "wof:name":"Bill's Shoe Store",
    "wof:placetype":"venue"
},
  "geometry": {"coordinates":[-83.984652,42.910876],"type":"Point"}
}