{
  "type": "Feature",
  "properties": {
    "iso:country":"US",
    "sg:address":"1402 Jolly Rd",
    "sg:city":"Okemos",
    "sg:classifiers":[
        {
            "category":"Retail",
            "subcategory":"Repair Shop",
            "type":"Services"
        }
    ],
    "sg:phone":"+1 517 349 2443",
    "sg:postcode":"48864",
    "sg:province":"MI",
    "sg:tags":[
        "welding"
    ],
    "wof:name":"Alden Enterprise",
    "wof:placetype":"venue"
},
  "geometry": {"coordinates":[-84.40537999999999,42.682958],"type":"Point"}
}