{
  "type": "Feature",
  "properties": {
    "iso:country":"US",
    "sg:address":"12238 Linden Ave",
    "sg:city":"Sawyer",
    "sg:classifiers":[
        {
            "category":"Building & Trades",
            "subcategory":"Construction",
            "type":"Services"
        }
    ],
    "sg:phone":"+1 269 426 7251",
    "sg:postcode":"49125",
    "sg:province":"MI",
    "sg:tags":[
        "contractor"
    ],
    "wof:name":"Tollas Construction Inc",
    "wof:placetype":"venue"
},
  "geometry": {"coordinates":[-86.600893,41.897189],"type":"Point"}
}