{
  "type": "Feature",
  "properties": {
    "iso:country":"US",
    "sg:address":"3531 Antor",
    "sg:city":"Newaygo",
    "sg:classifiers":[
        {
            "category":"Real Estate",
            "subcategory":"Real Estate Operator",
            "type":"Services"
        }
    ],
    "sg:phone":"+1 231 652 9845",
    "sg:postcode":"49337",
    "sg:province":"MI",
    "sg:tags":[
        "mobile",
        "home",
        "community"
    ],
    "wof:name":"Four Seasons Trailer Park",
    "wof:placetype":"venue"
},
  "geometry": {"coordinates":[-85.61066599999999,43.492008],"type":"Point"}
}