{
  "type": "Feature",
  "properties": {
    "iso:country":"US",
    "sg:address":"468 Essex Dr",
    "sg:city":"Rochester Hills",
    "sg:classifiers":[
        {
            "category":"Shopping",
            "type":"Retail Goods"
        },
        {
            "category":"Museum",
            "type":"Entertainment"
        }
    ],
    "sg:phone":"+1 248 652 3532",
    "sg:postcode":"48307",
    "sg:province":"MI",
    "sg:tags":[
        "organization",
        "arts",
        "merchandise",
        "information"
    ],
    "wof:name":"Art Acquisitions Unlimited",
    "wof:placetype":"venue"
},
  "geometry": {"coordinates":[-83.121359,42.658749],"type":"Point"}
}