{
  "type": "Feature",
  "properties": {
    "iso:country":"US",
    "sg:address":"4805 N Harsdale Rd",
    "sg:city":"Bloomfield Hills",
    "sg:classifiers":[
        {
            "category":"Professional",
            "subcategory":"Engineering",
            "type":"Services"
        }
    ],
    "sg:phone":"+1 248 645 9574",
    "sg:postcode":"48302",
    "sg:province":"MI",
    "sg:tags":[
        "engineer"
    ],
    "wof:name":"John Jay Wetzel PE",
    "wof:placetype":"venue"
},
  "geometry": {"coordinates":[-83.269728,42.568819],"type":"Point"}
}