{
  "type": "Feature",
  "properties": {
    "iso:country":"US",
    "sg:address":"20735 Lakefield Rd",
    "sg:city":"Merrill",
    "sg:classifiers":[
        {
            "category":"Retail",
            "subcategory":"Repair Shop",
            "type":"Services"
        }
    ],
    "sg:phone":"+1 989 643 7459",
    "sg:postcode":"48637",
    "sg:province":"MI",
    "sg:tags":[
        "taxidermist"
    ],
    "wof:name":"Kaufman's Wildlife Creations",
    "wof:placetype":"venue"
},
  "geometry": {"coordinates":[-84.318546,43.346387],"type":"Point"}
}