{
  "type": "Feature",
  "properties": {
    "iso:country":"US",
    "sg:address":"1988 S Elm Ave",
    "sg:city":"White Cloud",
    "sg:classifiers":[
        {
            "category":"Organizations",
            "subcategory":"Religious Organization",
            "type":"Services"
        }
    ],
    "sg:phone":"+1 231 689 0255",
    "sg:postcode":"49349",
    "sg:province":"MI",
    "sg:tags":[
        "church"
    ],
    "wof:name":"Big Prairie Community Church",
    "wof:placetype":"venue"
},
  "geometry": {"coordinates":[-85.642647,43.52249],"type":"Point"}
}