{
  "type": "Feature",
  "properties": {
    "iso:country":"US",
    "sg:address":"13472 Lowe Dr",
    "sg:city":"Warren",
    "sg:classifiers":[
        {
            "category":"Shopping",
            "type":"Retail Goods"
        }
    ],
    "sg:phone":"+1 586 795 5978",
    "sg:postcode":"48088",
    "sg:province":"MI",
    "sg:tags":[
        "plant",
        "flower",
        "tree",
        "artificial"
    ],
    "wof:name":"Forever Green Interiors Inc",
    "wof:placetype":"venue"
},
  "geometry": {"coordinates":[-82.988798,42.534721],"type":"Point"}
}