{
  "type": "Feature",
  "properties": {
    "iso:country":"US",
    "sg:address":"5911 S Rickfield Rd",
    "sg:city":"Jackson",
    "sg:classifiers":[
        {
            "category":"Real Estate",
            "subcategory":"Real Estate Operator",
            "type":"Services"
        }
    ],
    "sg:phone":"+1 517 783 2553",
    "sg:postcode":"49201",
    "sg:province":"MI",
    "sg:tags":[
        "building",
        "nonresidential"
    ],
    "wof:name":"Rickfield Properties",
    "wof:placetype":"venue"
},
  "geometry": {"coordinates":[-84.42939200000001,42.17957],"type":"Point"}
}