{
  "type": "Feature",
  "properties": {
    "iso:country":"US",
    "sg:address":"12350 Pike Ave",
    "sg:city":"Grant",
    "sg:classifiers":[
        {
            "category":"Government",
            "subcategory":"Office",
            "type":"Public Place"
        }
    ],
    "sg:phone":"+1 231 924 2028",
    "sg:postcode":"49327",
    "sg:province":"MI",
    "sg:tags":[
        "executive"
    ],
    "wof:name":"Bridgeton Township",
    "wof:placetype":"venue"
},
  "geometry": {"coordinates":[-86.02439099999999,43.335181],"type":"Point"}
}