{
  "type": "Feature",
  "properties": {
    "iso:country":"US",
    "sg:address":"43266 Hillcrest Dr",
    "sg:city":"Sterling Heights",
    "sg:classifiers":[
        {
            "category":"Manufacturing",
            "subcategory":"Lumber",
            "type":"Manufacturing & Wholesale Goods"
        }
    ],
    "sg:phone":"+1 586 247 5246",
    "sg:postcode":"48313",
    "sg:province":"MI",
    "sg:tags":[
        "operation",
        "timber",
        "tract"
    ],
    "wof:name":"Loria Tree Farm",
    "wof:placetype":"venue"
},
  "geometry": {"coordinates":[-82.976294,42.612605],"type":"Point"}
}