{
  "type": "Feature",
  "properties": {
    "iso:country":"US",
    "sg:address":"30555 Southfield Rd Ste 320",
    "sg:city":"Southfield",
    "sg:classifiers":[
        {
            "category":"Health Services",
            "subcategory":"Doctor",
            "type":"Services"
        }
    ],
    "sg:phone":"+1 248 433 1469",
    "sg:postcode":"48076",
    "sg:province":"MI",
    "sg:tags":[
        "surgeon",
        "oral"
    ],
    "wof:name":"Aviles Jose Ddph DDS",
    "wof:placetype":"venue"
},
  "geometry": {"coordinates":[-83.223198,42.514099],"type":"Point"}
}