{
  "type": "Feature",
  "properties": {
    "iso:country":"US",
    "sg:address":"31487 Gratiot Ave",
    "sg:city":"Roseville",
    "sg:classifiers":[
        {
            "category":"Retail",
            "subcategory":"Auto Repair",
            "type":"Services"
        }
    ],
    "sg:phone":"+1 586 294 4160",
    "sg:postcode":"48066",
    "sg:province":"MI",
    "sg:tags":[
        "repairing",
        "automobile"
    ],
    "sg:website":"www.shadowoodsauto.com",
    "wof:name":"Shadowoods Auto Center",
    "wof:placetype":"venue"
},
  "geometry": {"coordinates":[-82.917297,42.527699],"type":"Point"}
}