{
  "type": "Feature",
  "properties": {
    "iso:country":"US",
    "sg:address":"5440 Dixie Hwy",
    "sg:city":"Waterford",
    "sg:classifiers":[
        {
            "category":"Retail",
            "subcategory":"Auto Repair",
            "type":"Services"
        }
    ],
    "sg:phone":"+1 248 623 6900",
    "sg:postcode":"48329",
    "sg:province":"MI",
    "sg:tags":[
        "repairing",
        "automobile"
    ],
    "wof:name":"A-C Tire & Svc Ctr",
    "wof:placetype":"venue"
},
  "geometry": {"coordinates":[-83.395088,42.696293],"type":"Point"}
}