{
  "type": "Feature",
  "properties": {
    "iso:country":"US",
    "sg:address":"15800 Providence Dr",
    "sg:city":"Southfield",
    "sg:classifiers":[
        {
            "category":"Real Estate",
            "subcategory":"Real Estate Operator",
            "type":"Services"
        }
    ],
    "sg:phone":"+1 248 559 2680",
    "sg:postcode":"48075",
    "sg:province":"MI",
    "sg:tags":[
        "apartment"
    ],
    "sg:website":"www.4theeagle.com",
    "wof:name":"Eagle's Landing Of Southfield",
    "wof:placetype":"venue"
},
  "geometry": {"coordinates":[-83.206656,42.455985],"type":"Point"}
}