{
  "type": "Feature",
  "properties": {
    "iso:country":"US",
    "sg:address":"306 Capital Ave NE",
    "sg:city":"Battle Creek",
    "sg:classifiers":[
        {
            "category":"Organizations",
            "subcategory":"Religious Organization",
            "type":"Services"
        }
    ],
    "sg:phone":"+1 269 963 4921",
    "sg:postcode":"49017",
    "sg:province":"MI",
    "wof:name":"Temple Beth El",
    "wof:placetype":"venue"
},
  "geometry": {"coordinates":[-85.172014,42.322612],"type":"Point"}
}