{
  "type": "Feature",
  "properties": {
    "iso:country":"US",
    "sg:address":"625 Byron St",
    "sg:city":"Plymouth",
    "sg:classifiers":[
        {
            "category":"Organizations",
            "subcategory":"Community Association",
            "type":"Services"
        }
    ],
    "sg:phone":"+1 734 453 0387",
    "sg:postcode":"48170",
    "sg:province":"MI",
    "wof:name":"Youth Empowerment Source",
    "wof:placetype":"venue"
},
  "geometry": {"coordinates":[-83.46778500000001,42.359755],"type":"Point"}
}