{
  "type": "Feature",
  "properties": {
    "iso:country":"US",
    "sg:address":"840 S Outer Dr",
    "sg:city":"Saginaw",
    "sg:classifiers":[
        {
            "category":"Retail",
            "subcategory":"Car Wash",
            "type":"Services"
        },
        {
            "category":"Manufacturing",
            "subcategory":"Tools & Machinery",
            "type":"Manufacturing & Wholesale Goods"
        }
    ],
    "sg:phone":"+1 989 752 4821",
    "sg:postcode":"48601",
    "sg:province":"MI",
    "sg:tags":[
        "automatic",
        "filling",
        "station",
        "gasoline",
        "ga"
    ],
    "wof:name":"Central Metallizing & Machine",
    "wof:placetype":"venue"
},
  "geometry": {"coordinates":[-83.896106,43.415166],"type":"Point"}
}