{
  "type": "Feature",
  "properties": {
    "iso:country":"US",
    "sg:address":"210 Mac Ave",
    "sg:city":"East Lansing",
    "sg:classifiers":[
        {
            "category":"Restaurant",
            "type":"Food & Drink"
        }
    ],
    "sg:phone":"+1 517 337 2222",
    "sg:postcode":"48823",
    "sg:province":"MI",
    "wof:name":"Omi Japanese Restaurant",
    "wof:placetype":"venue"
},
  "geometry": {"coordinates":[-84.481168,42.735271],"type":"Point"}
}