{
  "type": "Feature",
  "properties": {
    "iso:country":"US",
    "sg:address":"29215 Northwestern Hwy",
    "sg:city":"Southfield",
    "sg:classifiers":[
        {
            "category":"Personal",
            "subcategory":"Tanning Parlor",
            "type":"Services"
        }
    ],
    "sg:phone":"+1 248 352 2001",
    "sg:postcode":"48034",
    "sg:province":"MI",
    "sg:tags":[
        "salon"
    ],
    "wof:name":"Planet Sun Tanning Salon",
    "wof:placetype":"venue"
},
  "geometry": {"coordinates":[-83.31596399999999,42.505164],"type":"Point"}
}