{
  "type": "Feature",
  "properties": {
    "iso:country":"US",
    "sg:address":"1796 Briarcliff",
    "sg:city":"Sylvan Lake",
    "sg:classifiers":[
        {
            "category":"Manufacturing",
            "subcategory":"Retail Goods",
            "type":"Manufacturing & Wholesale Goods"
        }
    ],
    "sg:phone":"+1 248 738 7249",
    "sg:postcode":"48320",
    "sg:province":"MI",
    "sg:tags":[
        "assembly",
        "fabricating"
    ],
    "wof:name":"Vast Production Svc",
    "wof:placetype":"venue"
},
  "geometry": {"coordinates":[-83.331917,42.613711],"type":"Point"}
}