{
  "type": "Feature",
  "properties": {
    "iso:country":"US",
    "sg:address":"955 Jennings Ave",
    "sg:city":"Benton Harbor",
    "sg:classifiers":[
        {
            "category":"Shopping",
            "subcategory":"Discount & Variety Stores",
            "type":"Retail Goods"
        }
    ],
    "sg:phone":"+1 269 927 1394",
    "sg:postcode":"49022",
    "sg:province":"MI",
    "sg:tags":[
        "merchandise",
        "general"
    ],
    "wof:name":"Bargain Basement",
    "wof:placetype":"venue"
},
  "geometry": {"coordinates":[-86.44397499999999,42.100772],"type":"Point"}
}