{
  "type": "Feature",
  "properties": {
    "iso:country":"US",
    "sg:address":"29090 Tiffany Dr E",
    "sg:city":"Southfield",
    "sg:classifiers":[
        {
            "category":"Real Estate",
            "subcategory":"Real Estate Operator",
            "type":"Services"
        }
    ],
    "sg:phone":"+1 248 356 3780",
    "sg:postcode":"48034",
    "sg:province":"MI",
    "sg:tags":[
        "apartment"
    ],
    "wof:name":"Wakefield Apartments",
    "wof:placetype":"venue"
},
  "geometry": {"coordinates":[-83.295236,42.501696],"type":"Point"}
}