{
  "type": "Feature",
  "properties": {
    "iso:country":"US",
    "sg:address":"417 Seymour Ave",
    "sg:city":"Lansing",
    "sg:classifiers":[
        {
            "category":"Organizations",
            "subcategory":"Professional Association",
            "type":"Services"
        }
    ],
    "sg:phone":"+1 517 484 5588",
    "sg:postcode":"48933",
    "sg:province":"MI",
    "wof:name":"Maro Employment & Training",
    "wof:placetype":"venue"
},
  "geometry": {"coordinates":[-84.55544399999999,42.738399],"type":"Point"}
}