{
  "type": "Feature",
  "properties": {
    "iso:country":"US",
    "sg:address":"3722 E Apple Ave",
    "sg:city":"Muskegon",
    "sg:classifiers":[
        {
            "category":"Manufacturing",
            "subcategory":"Motor Vehicles & Parts",
            "type":"Manufacturing & Wholesale Goods"
        }
    ],
    "sg:phone":"+1 231 773 0695",
    "sg:postcode":"49442",
    "sg:province":"MI",
    "sg:tags":[
        "mfg"
    ],
    "wof:name":"West Michigan Rack & Pinion",
    "wof:placetype":"venue"
},
  "geometry": {"coordinates":[-86.15094000000001,43.234364],"type":"Point"}
}