{
  "type": "Feature",
  "properties": {
    "iso:country":"US",
    "sg:address":"18000 Vernier Rd",
    "sg:city":"Harper Woods",
    "sg:classifiers":[
        {
            "category":"Restaurant",
            "type":"Food & Drink"
        }
    ],
    "sg:menulink":"http://www.allmenus.com/mi/harper-woods/95842-charleys-grilled-subs/menu/",
    "sg:phone":"+1 248 703 1452",
    "sg:postcode":"48225",
    "sg:province":"MI",
    "sg:tags":[
        "wrap",
        "american",
        "sandwich"
    ],
    "wof:name":"Charley's Grilled Subs",
    "wof:placetype":"venue"
},
  "geometry": {"coordinates":[-82.934243,42.44992],"type":"Point"}
}