{
  "type": "Feature",
  "properties": {
    "iso:country":"US",
    "sg:address":"9959 Pulaski Rd",
    "sg:city":"Hanover",
    "sg:classifiers":[
        {
            "category":"Food & Beverages",
            "subcategory":"Groceries & Convenience Stores",
            "type":"Retail Goods"
        }
    ],
    "sg:phone":"+1 517 524 6164",
    "sg:postcode":"49241",
    "sg:province":"MI",
    "wof:name":"Pulaski Grocery Store",
    "wof:placetype":"venue"
},
  "geometry": {"coordinates":[-84.64228199999999,42.115328],"type":"Point"}
}