{
  "type": "Feature",
  "properties": {
    "iso:country":"US",
    "sg:address":"2181 E Freeman Rd",
    "sg:city":"Free Soil",
    "sg:classifiers":[
        {
            "category":"Professional",
            "subcategory":"Accounting & Tax Preparation",
            "type":"Services"
        }
    ],
    "sg:phone":"+1 231 464 7139",
    "sg:postcode":"49411",
    "sg:province":"MI",
    "wof:name":"Ptrc S Harder Accntng/Csh Cns",
    "wof:placetype":"venue"
},
  "geometry": {"coordinates":[-86.22800100000001,44.092722],"type":"Point"}
}