{
  "type": "Feature",
  "properties": {
    "iso:country":"US",
    "sg:address":"47388 Brockmor Dr",
    "sg:city":"Utica",
    "sg:classifiers":[
        {
            "category":"Organizations",
            "subcategory":"Religious Organization",
            "type":"Services"
        }
    ],
    "sg:phone":"+1 586 566 5692",
    "sg:postcode":"48315",
    "sg:province":"MI",
    "sg:tags":[
        "worship",
        "leader"
    ],
    "wof:name":"Duncan Carswell",
    "wof:placetype":"venue"
},
  "geometry": {"coordinates":[-82.975915,42.644826],"type":"Point"}
}