{
  "type": "Feature",
  "properties": {
    "iso:country":"US",
    "sg:address":"425 W Huron St",
    "sg:city":"Milford",
    "sg:classifiers":[
        {
            "category":"Professional",
            "subcategory":"Business Services",
            "type":"Services"
        }
    ],
    "sg:phone":"+1 248 685 1166",
    "sg:postcode":"48381",
    "sg:province":"MI",
    "sg:tags":[
        "management",
        "recruiting"
    ],
    "wof:name":"Management Recruiters Intl",
    "wof:placetype":"venue"
},
  "geometry": {"coordinates":[-83.604854,42.58518],"type":"Point"}
}