{
  "type": "Feature",
  "properties": {
    "iso:country":"US",
    "sg:address":"3005 Claude Ave",
    "sg:city":"Flint",
    "sg:classifiers":[
        {
            "category":"Local Transit",
            "type":"Transportation"
        }
    ],
    "sg:phone":"+1 810 733 1135",
    "sg:postcode":"48507",
    "sg:province":"MI",
    "sg:tags":[
        "ambulance"
    ],
    "wof:name":"Regional EMS",
    "wof:placetype":"venue"
},
  "geometry": {"coordinates":[-83.741102,42.988532],"type":"Point"}
}