{
  "type": "Feature",
  "properties": {
    "iso:country":"US",
    "sg:address":"2649 Caniff St",
    "sg:city":"Hamtramck",
    "sg:classifiers":[
        {
            "category":"Retail",
            "subcategory":"Auto Repair",
            "type":"Services"
        }
    ],
    "sg:phone":"+1 313 365 9222",
    "sg:postcode":"48212",
    "sg:province":"MI",
    "wof:name":"Hamtramck Auto Repair",
    "wof:placetype":"venue"
},
  "geometry": {"coordinates":[-83.061798,42.398998],"type":"Point"}
}