{
  "type": "Feature",
  "properties": {
    "iso:country":"US",
    "sg:address":"24453 Woodham Rd",
    "sg:city":"Novi",
    "sg:classifiers":[
        {
            "category":"Professional",
            "subcategory":"Computer Services",
            "type":"Services"
        }
    ],
    "sg:phone":"+1 248 449 7101",
    "sg:postcode":"48374",
    "sg:province":"MI",
    "wof:name":"Piton Design Inc",
    "wof:placetype":"venue"
},
  "geometry": {"coordinates":[-83.523661,42.469619],"type":"Point"}
}