{
  "type": "Feature",
  "properties": {
    "iso:country":"US",
    "sg:address":"4965 Briarwood Cir",
    "sg:city":"West Bloomfield",
    "sg:classifiers":[
        {
            "category":"Retail",
            "subcategory":"Auto Rental",
            "type":"Services"
        }
    ],
    "sg:phone":"+1 248 706 2327",
    "sg:postcode":"48323",
    "sg:province":"MI",
    "sg:tags":[
        "car"
    ],
    "wof:name":"Angel Auto Leasing Inc",
    "wof:placetype":"venue"
},
  "geometry": {"coordinates":[-83.42130299999999,42.562901],"type":"Point"}
}