{
  "type": "Feature",
  "properties": {
    "iso:country":"US",
    "sg:address":"2632 E Jefferson Ave",
    "sg:city":"Detroit",
    "sg:classifiers":[
        {
            "category":"Personal",
            "subcategory":"Barber",
            "type":"Services"
        }
    ],
    "sg:phone":"+1 313 396 5269",
    "sg:postcode":"48207",
    "sg:province":"MI",
    "wof:name":"Cut It Out",
    "wof:placetype":"venue"
},
  "geometry": {"coordinates":[-83.020641,42.338952],"type":"Point"}
}