{
  "type": "Feature",
  "properties": {
    "iso:country":"US",
    "sg:address":"9347 Tecumseh Clinton Hwy",
    "sg:city":"Tecumseh",
    "sg:classifiers":[
        {
            "category":"Building & Trades",
            "subcategory":"Construction",
            "type":"Services"
        }
    ],
    "sg:phone":"+1 517 423 4800",
    "sg:postcode":"49286",
    "sg:province":"MI",
    "sg:tags":[
        "maker",
        "cabinet"
    ],
    "wof:name":"L A Drouillard & Sons Custom",
    "wof:placetype":"venue"
},
  "geometry": {"coordinates":[-83.94502,42.026004],"type":"Point"}
}