{
  "type": "Feature",
  "properties": {
    "iso:country":"US",
    "sg:address":"1212 US Hwy 23 N",
    "sg:city":"Alpena",
    "sg:classifiers":[
        {
            "category":"Retail",
            "subcategory":"Auto Repair",
            "type":"Services"
        }
    ],
    "sg:phone":"+1 989 354 5577",
    "sg:postcode":"49707",
    "sg:province":"MI",
    "sg:tags":[
        "body",
        "automobile",
        "painting"
    ],
    "wof:name":"Larry's Collision",
    "wof:placetype":"venue"
},
  "geometry": {"coordinates":[-83.45743299999999,45.089],"type":"Point"}
}