{
  "type": "Feature",
  "properties": {
    "iso:country":"US",
    "sg:address":"13326 Wenwood Dr",
    "sg:city":"Fenton",
    "sg:classifiers":[
        {
            "category":"Food & Beverages",
            "subcategory":"Specialty",
            "type":"Retail Goods"
        }
    ],
    "sg:phone":"+1 810 629 1793",
    "sg:postcode":"48430",
    "sg:province":"MI",
    "wof:name":"Best Water",
    "wof:placetype":"venue"
},
  "geometry": {"coordinates":[-83.702466,42.83358],"type":"Point"}
}