{
  "type": "Feature",
  "properties": {
    "iso:country":"US",
    "sg:address":"1500 S Main St",
    "sg:city":"Eaton Rapids",
    "sg:classifiers":[
        {
            "category":"Sports & Exercise",
            "subcategory":"Gym",
            "type":"Entertainment"
        }
    ],
    "sg:phone":"+1 517 663 9530",
    "sg:postcode":"48827",
    "sg:province":"MI",
    "sg:tags":[
        "club",
        "health",
        "studio",
        "gymnasium"
    ],
    "wof:name":"Healthworks",
    "wof:placetype":"venue"
},
  "geometry": {"coordinates":[-84.657561,42.496044],"type":"Point"}
}