{
  "type": "Feature",
  "properties": {
    "iso:country":"US",
    "sg:address":"39710 W 14 Mile Rd",
    "sg:city":"Commerce Township",
    "sg:classifiers":[
        {
            "category":"Arena",
            "subcategory":"Stadium",
            "type":"Entertainment"
        }
    ],
    "sg:phone":"+1 248 669 6670",
    "sg:postcode":"48390",
    "sg:province":"MI",
    "wof:name":"Old Ball Park the",
    "wof:placetype":"venue"
},
  "geometry": {"coordinates":[-83.442398,42.5271],"type":"Point"}
}