{
  "type": "Feature",
  "properties": {
    "iso:country":"US",
    "sg:address":"736 S Washington Ave",
    "sg:city":"Royal Oak",
    "sg:classifiers":[
        {
            "category":"Professional",
            "subcategory":"Employment Agencies",
            "type":"Services"
        }
    ],
    "sg:phone":"+1 248 542 9232",
    "sg:postcode":"48067",
    "sg:province":"MI",
    "sg:tags":[
        "help",
        "contractor"
    ],
    "sg:website":"www.scottgroup.net",
    "wof:name":"Scott Group Inc",
    "wof:placetype":"venue"
},
  "geometry": {"coordinates":[-83.14659899999999,42.483898],"type":"Point"}
}