{
  "type": "Feature",
  "properties": {
    "iso:country":"US",
    "sg:address":"47511 Van Dyke Ave",
    "sg:city":"Shelby Twp",
    "sg:classifiers":[
        {
            "category":"Building & Trades",
            "subcategory":"Construction",
            "type":"Services"
        }
    ],
    "sg:phone":"+1 586 726 0475",
    "sg:postcode":"48317",
    "sg:province":"MI",
    "sg:tags":[
        "contractor"
    ],
    "wof:name":"Burgett Builders",
    "wof:placetype":"venue"
},
  "geometry": {"coordinates":[-83.033083,42.642018],"type":"Point"}
}