{
  "type": "Feature",
  "properties": {
    "iso:country":"US",
    "sg:address":"1021 N Parker Rd",
    "sg:city":"Dexter",
    "sg:classifiers":[
        {
            "category":"Building & Trades",
            "subcategory":"Construction",
            "type":"Services"
        }
    ],
    "sg:phone":"+1 734 426 8152",
    "sg:postcode":"48130",
    "sg:province":"MI",
    "wof:name":"Bastion Homes",
    "wof:placetype":"venue"
},
  "geometry": {"coordinates":[-83.89872200000001,42.302957],"type":"Point"}
}