{
  "type": "Feature",
  "properties": {
    "iso:country":"US",
    "sg:address":"1115 Cadillac Dr SE",
    "sg:city":"Grand Rapids",
    "sg:classifiers":[
        {
            "category":"Manufacturing",
            "subcategory":"Chemicals & Compounds",
            "type":"Manufacturing & Wholesale Goods"
        }
    ],
    "sg:phone":"+1 616 246 7190",
    "sg:postcode":"49506",
    "sg:province":"MI",
    "sg:tags":[
        "plastic"
    ],
    "wof:name":"Chase Plastics Svc",
    "wof:placetype":"venue"
},
  "geometry": {"coordinates":[-85.630398,42.94271],"type":"Point"}
}