{
  "type": "Feature",
  "properties": {
    "iso:country":"US",
    "sg:address":"4571 John R Rd",
    "sg:city":"Troy",
    "sg:classifiers":[
        {
            "category":"Education",
            "subcategory":"School",
            "type":"Public Place"
        }
    ],
    "sg:phone":"+1 248 689 1431",
    "sg:postcode":"48085",
    "sg:province":"MI",
    "wof:name":"St Anastasia Church",
    "wof:placetype":"venue"
},
  "geometry": {"coordinates":[-83.109398,42.586399],"type":"Point"}
}