{
  "type": "Feature",
  "properties": {
    "iso:country":"US",
    "sg:address":"4630 Spartan Industrial Dr SW",
    "sg:city":"Grandville",
    "sg:classifiers":[
        {
            "category":"Wholesale",
            "subcategory":"Painting Supplies",
            "type":"Manufacturing & Wholesale Goods"
        }
    ],
    "sg:phone":"+1 616 538 5505",
    "sg:postcode":"49418",
    "sg:province":"MI",
    "sg:tags":[
        "paint"
    ],
    "sg:website":"www.sherwin.com",
    "wof:name":"Sherwin-Williams Paints",
    "wof:placetype":"venue"
},
  "geometry": {"coordinates":[-85.736334,42.881222],"type":"Point"}
}