{
  "type": "Feature",
  "properties": {
    "iso:country":"US",
    "sg:address":"22309 Greater Mack Ave",
    "sg:city":"Saint Clair Shores",
    "sg:classifiers":[
        {
            "category":"Building & Trades",
            "subcategory":"Plumbing",
            "type":"Services"
        }
    ],
    "sg:phone":"+1 586 774 5020",
    "sg:postcode":"48080",
    "sg:province":"MI",
    "sg:tags":[
        "contractor"
    ],
    "wof:name":"Amber Furnance Company",
    "wof:placetype":"venue"
},
  "geometry": {"coordinates":[-82.901597,42.457896],"type":"Point"}
}