{
  "type": "Feature",
  "properties": {
    "iso:country":"US",
    "sg:address":"835 Call St",
    "sg:city":"Lansing",
    "sg:classifiers":[
        {
            "category":"Shopping",
            "subcategory":"Catalog Store",
            "type":"Retail Goods"
        }
    ],
    "sg:phone":"+1 517 484 1767",
    "sg:postcode":"48906",
    "sg:province":"MI",
    "sg:tags":[
        "mail",
        "house"
    ],
    "wof:name":"Grandpa Randys",
    "wof:placetype":"venue"
},
  "geometry": {"coordinates":[-84.53943700000001,42.759657],"type":"Point"}
}