{
  "type": "Feature",
  "properties": {
    "iso:country":"US",
    "sg:address":"1126 W Hile Rd",
    "sg:city":"Muskegon",
    "sg:classifiers":[
        {
            "category":"Social Services",
            "subcategory":"Child Care",
            "type":"Services"
        }
    ],
    "sg:phone":"+1 231 798 1109",
    "sg:postcode":"49441",
    "sg:province":"MI",
    "sg:tags":[
        "day",
        "provider"
    ],
    "wof:name":"Cathy Moblo",
    "wof:placetype":"venue"
},
  "geometry": {"coordinates":[-86.27116700000001,43.169202],"type":"Point"}
}