{
  "type": "Feature",
  "properties": {
    "iso:country":"US",
    "sg:address":"196 N Rose St",
    "sg:city":"Mount Clemens",
    "sg:classifiers":[
        {
            "category":"Education",
            "subcategory":"School",
            "type":"Public Place"
        }
    ],
    "sg:phone":"+1 586 469 6100",
    "sg:postcode":"48043",
    "sg:province":"MI",
    "wof:name":"Washington Acdemy Science Arts",
    "wof:placetype":"venue"
},
  "geometry": {"coordinates":[-82.89539000000001,42.603933],"type":"Point"}
}