{
  "type": "Feature",
  "properties": {
    "iso:country":"US",
    "sg:address":"2510 Champion Way",
    "sg:city":"Lansing",
    "sg:classifiers":[
        {
            "category":"Social Services",
            "type":"Services"
        }
    ],
    "sg:phone":"+1 517 393 0505",
    "sg:postcode":"48910",
    "sg:province":"MI",
    "sg:tags":[
        "senior",
        "citizen"
    ],
    "wof:name":"North American Senior Circuit",
    "wof:placetype":"venue"
},
  "geometry": {"coordinates":[-84.51627499999999,42.692468],"type":"Point"}
}