{
  "type": "Feature",
  "properties": {
    "iso:country":"US",
    "sg:address":"8445 Stein Rd",
    "sg:city":"Pigeon",
    "sg:classifiers":[
        {
            "category":"Real Estate",
            "subcategory":"Real Estate Operator",
            "type":"Services"
        }
    ],
    "sg:phone":"+1 989 453 2248",
    "sg:postcode":"48755",
    "sg:province":"MI",
    "sg:tags":[
        "property",
        "lessor"
    ],
    "wof:name":"Dwight Jacobs",
    "wof:placetype":"venue"
},
  "geometry": {"coordinates":[-83.312766,43.771351],"type":"Point"}
}