{
  "type": "Feature",
  "properties": {
    "iso:country":"US",
    "sg:address":"18844 Hillcrest St",
    "sg:city":"Beverly Hills",
    "sg:classifiers":[
        {
            "category":"Autos & Motor Vehicles",
            "subcategory":"Automobile Sales",
            "type":"Retail Goods"
        },
        {
            "category":"Retail",
            "subcategory":"Auto Repair",
            "type":"Services"
        }
    ],
    "sg:phone":"+1 248 258 9875",
    "sg:postcode":"48025",
    "sg:province":"MI",
    "sg:tags":[
        "performance",
        "race",
        "dealer",
        "general"
    ],
    "wof:name":"Klain Auto Racing",
    "wof:placetype":"venue"
},
  "geometry": {"coordinates":[-83.23173199999999,42.529292],"type":"Point"}
}