{
  "type": "Feature",
  "properties": {
    "iso:country":"US",
    "sg:address":"1001 E Carpenter St",
    "sg:city":"Midland",
    "sg:classifiers":[
        {
            "category":"Shopping",
            "subcategory":"Used Merchandise",
            "type":"Retail Goods"
        }
    ],
    "sg:phone":"+1 989 832 6067",
    "sg:postcode":"48640",
    "sg:province":"MI",
    "sg:tags":[
        "furniture"
    ],
    "wof:name":"Second To None",
    "wof:placetype":"venue"
},
  "geometry": {"coordinates":[-84.23095499999999,43.613261],"type":"Point"}
}