{
  "type": "Feature",
  "properties": {
    "iso:country":"US",
    "sg:address":"711 Johnston St",
    "sg:city":"Sault Ste Marie",
    "sg:classifiers":[
        {
            "category":"Food & Beverages",
            "subcategory":"Bakery",
            "type":"Retail Goods"
        }
    ],
    "sg:phone":"+1 906 253 2122",
    "sg:postcode":"49783",
    "sg:province":"MI",
    "sg:tags":[
        "baker"
    ],
    "wof:name":"Cindy Lou's Cafe & Bakery",
    "wof:placetype":"venue"
},
  "geometry": {"coordinates":[-84.34138799999999,46.492564],"type":"Point"}
}