{
  "type": "Feature",
  "properties": {
    "iso:country":"US",
    "sg:address":"6735 N 19 Rd",
    "sg:city":"Mesick",
    "sg:classifiers":[
        {
            "category":"Shopping",
            "type":"Retail Goods"
        }
    ],
    "sg:phone":"+1 231 885 1320",
    "sg:postcode":"49668",
    "sg:province":"MI",
    "sg:tags":[
        "hearing",
        "equipment",
        "supply",
        "impaired"
    ],
    "wof:name":"Long's Prescription Hearing",
    "wof:placetype":"venue"
},
  "geometry": {"coordinates":[-85.638948,44.432961],"type":"Point"}
}