{
  "type": "Feature",
  "properties": {
    "iso:country":"US",
    "sg:address":"4200 S Vassar Rd",
    "sg:city":"Burton",
    "sg:classifiers":[
        {
            "category":"Wholesale",
            "subcategory":"Vending Machines",
            "type":"Manufacturing & Wholesale Goods"
        }
    ],
    "sg:phone":"+1 810 742 8404",
    "sg:postcode":"48519",
    "sg:province":"MI",
    "sg:tags":[
        "operator"
    ],
    "wof:name":"Primetime Vending",
    "wof:placetype":"venue"
},
  "geometry": {"coordinates":[-83.57414799999999,42.971187],"type":"Point"}
}