{
  "type": "Feature",
  "properties": {
    "iso:country":"US",
    "sg:address":"612 Page Ave",
    "sg:city":"Jackson",
    "sg:classifiers":[
        {
            "category":"Insurance",
            "subcategory":"Insurance Agent",
            "type":"Services"
        }
    ],
    "sg:phone":"+1 517 782 2492",
    "sg:postcode":"49203",
    "sg:province":"MI",
    "sg:tags":[
        "adjuster"
    ],
    "wof:name":"Warner Adjustment Co",
    "wof:placetype":"venue"
},
  "geometry": {"coordinates":[-84.38736900000001,42.24495],"type":"Point"}
}