{
  "type": "Feature",
  "properties": {
    "iso:country":"US",
    "sg:address":"19172 Porter Dr",
    "sg:city":"Clinton Township",
    "sg:classifiers":[
        {
            "category":"Professional",
            "subcategory":"Business Services",
            "type":"Services"
        }
    ],
    "sg:phone":"+1 586 228 7772",
    "sg:postcode":"48038",
    "sg:province":"MI",
    "sg:tags":[
        "notary",
        "public"
    ],
    "wof:name":"Thomas R Mazza",
    "wof:placetype":"venue"
},
  "geometry": {"coordinates":[-82.926754,42.58884],"type":"Point"}
}