{
  "type": "Feature",
  "properties": {
    "iso:country":"US",
    "sg:address":"14080 S Wright Rd",
    "sg:city":"Eagle",
    "sg:classifiers":[
        {
            "category":"Retail",
            "subcategory":"Veterinary Services",
            "type":"Services"
        }
    ],
    "sg:phone":"+1 517 626 6900",
    "sg:postcode":"48822",
    "sg:province":"MI",
    "sg:tags":[
        "veterinarian"
    ],
    "wof:name":"House Calls Veterinary Svc",
    "wof:placetype":"venue"
},
  "geometry": {"coordinates":[-84.739474,42.802015],"type":"Point"}
}