{
  "type": "Feature",
  "properties": {
    "iso:country":"US",
    "sg:address":"31822 Grand River Ave",
    "sg:city":"Farmington",
    "sg:classifiers":[
        {
            "category":"Government",
            "subcategory":"Office",
            "type":"Public Place"
        }
    ],
    "sg:phone":"+1 248 473 7640",
    "sg:postcode":"48336",
    "sg:province":"MI",
    "sg:tags":[
        "army",
        "recruiting",
        "facility"
    ],
    "wof:name":"Health Care Recruiting Team",
    "wof:placetype":"venue"
},
  "geometry": {"coordinates":[-83.36299200000001,42.459233],"type":"Point"}
}