{
  "type": "Feature",
  "properties": {
    "iso:country":"US",
    "sg:address":"6469 Ancroft Ct",
    "sg:city":"Clarkston",
    "sg:classifiers":[
        {
            "category":"Professional",
            "subcategory":"Accounting & Tax Preparation",
            "type":"Services"
        }
    ],
    "sg:phone":"+1 248 620 6486",
    "sg:postcode":"48346",
    "sg:province":"MI",
    "wof:name":"Carolyn Stesney",
    "wof:placetype":"venue"
},
  "geometry": {"coordinates":[-83.395568,42.724355],"type":"Point"}
}