{
  "type": "Feature",
  "properties": {
    "iso:country":"US",
    "sg:address":"515 W Jefferson St",
    "sg:city":"Petoskey",
    "sg:classifiers":[
        {
            "category":"Health Services",
            "subcategory":"Doctor",
            "type":"Services"
        }
    ],
    "sg:phone":"+1 231 348 5622",
    "sg:postcode":"49770",
    "sg:province":"MI",
    "sg:tags":[
        "physician",
        "surgeon"
    ],
    "wof:name":"Center For Neurological Srgry",
    "wof:placetype":"venue"
},
  "geometry": {"coordinates":[-84.96760399999999,45.37445],"type":"Point"}
}