{
  "type": "Feature",
  "properties": {
    "iso:country":"US",
    "sg:address":"3294 Holiday View Dr",
    "sg:city":"Traverse City",
    "sg:classifiers":[
        {
            "category":"Manufacturing",
            "subcategory":"Lumber",
            "type":"Manufacturing & Wholesale Goods"
        }
    ],
    "sg:phone":"+1 231 938 1588",
    "sg:postcode":"49686",
    "sg:province":"MI",
    "sg:tags":[
        "company",
        "logging"
    ],
    "wof:name":"Russell West Forest Management",
    "wof:placetype":"venue"
},
  "geometry": {"coordinates":[-85.511605,44.739602],"type":"Point"}
}