{
  "type": "Feature",
  "properties": {
    "iso:country":"US",
    "sg:address":"21034 John R Rd",
    "sg:city":"Hazel Park",
    "sg:classifiers":[
        {
            "category":"Utilities",
            "subcategory":"Refuse",
            "type":"Services"
        }
    ],
    "sg:phone":"+1 248 544 3043",
    "sg:postcode":"48030",
    "sg:province":"MI",
    "sg:tags":[
        "garbage",
        "collection"
    ],
    "wof:name":"A & J Svc",
    "wof:placetype":"venue"
},
  "geometry": {"coordinates":[-83.102998,42.449852],"type":"Point"}
}