{
  "type": "Feature",
  "properties": {
    "iso:country":"US",
    "sg:address":"6748 Green Rd",
    "sg:city":"Ottawa Lake",
    "sg:classifiers":[
        {
            "category":"Farming",
            "subcategory":"Nursery",
            "type":"Manufacturing & Wholesale Goods"
        }
    ],
    "sg:phone":"+1 734 888 1297",
    "sg:postcode":"49267",
    "sg:province":"MI",
    "sg:tags":[
        "greenhouse"
    ],
    "wof:name":"Fitkin Greenhouse",
    "wof:placetype":"venue"
},
  "geometry": {"coordinates":[-83.708493,41.726192],"type":"Point"}
}