{
  "type": "Feature",
  "properties": {
    "iso:country":"US",
    "sg:address":"830 W Broad St",
    "sg:city":"Chesaning",
    "sg:classifiers":[
        {
            "category":"Retail",
            "subcategory":"Auto Repair",
            "type":"Services"
        }
    ],
    "sg:phone":"+1 989 845 7080",
    "sg:postcode":"48616",
    "sg:province":"MI",
    "sg:tags":[
        "muffler",
        "exhaust",
        "system"
    ],
    "wof:name":"Muffler Man",
    "wof:placetype":"venue"
},
  "geometry": {"coordinates":[-84.124178,43.186157],"type":"Point"}
}