{
  "type": "Feature",
  "properties": {
    "iso:country":"US",
    "sg:address":"2308 S Mission St",
    "sg:city":"Mount Pleasant",
    "sg:classifiers":[
        {
            "category":"Shopping",
            "subcategory":"Clothing, Apparel, & Fashions",
            "type":"Retail Goods"
        }
    ],
    "sg:phone":"+1 989 772 4133",
    "sg:postcode":"48858",
    "sg:province":"MI",
    "sg:tags":[
        "gift"
    ],
    "wof:name":"Ethnic Creations Inc",
    "wof:placetype":"venue"
},
  "geometry": {"coordinates":[-84.76751899999999,43.578476],"type":"Point"}
}