{
  "type": "Feature",
  "properties": {
    "iso:country":"US",
    "sg:address":"328 W Roosevelt Ave",
    "sg:city":"Zeeland",
    "sg:classifiers":[
        {
            "category":"Freight",
            "type":"Transportation"
        }
    ],
    "sg:phone":"+1 616 748 1088",
    "sg:postcode":"49464",
    "sg:province":"MI",
    "sg:tags":[
        "operator",
        "local",
        "trucking"
    ],
    "wof:name":"Geerlings",
    "wof:placetype":"venue"
},
  "geometry": {"coordinates":[-86.026174,42.819638],"type":"Point"}
}