{
  "type": "Feature",
  "properties": {
    "iso:country":"US",
    "sg:address":"21026 Cass Ave",
    "sg:city":"Clinton Twp",
    "sg:classifiers":[
        {
            "category":"Retail",
            "subcategory":"Auto Repair",
            "type":"Services"
        }
    ],
    "sg:phone":"+1 586 465 5444",
    "sg:postcode":"48036",
    "sg:province":"MI",
    "sg:tags":[
        "repairing",
        "automobile",
        "general"
    ],
    "wof:name":"Hillcrest Auto Electric Inc",
    "wof:placetype":"venue"
},
  "geometry": {"coordinates":[-82.905477,42.600187],"type":"Point"}
}