{
  "type": "Feature",
  "properties": {
    "iso:country":"US",
    "sg:address":"3668 Northwood Pl",
    "sg:city":"Saginaw",
    "sg:classifiers":[
        {
            "category":"Social Services",
            "subcategory":"Child Care",
            "type":"Services"
        }
    ],
    "sg:phone":"+1 989 497 0562",
    "sg:postcode":"48603",
    "sg:province":"MI",
    "wof:name":"Playful Learners Childrens Ctr",
    "wof:placetype":"venue"
},
  "geometry": {"coordinates":[-83.987571,43.457783],"type":"Point"}
}