{
  "type": "Feature",
  "properties": {
    "iso:country":"US",
    "sg:address":"39600 Van Dyke Ave",
    "sg:city":"Sterling Heights",
    "sg:classifiers":[
        {
            "category":"Autos & Motor Vehicles",
            "subcategory":"Fuel & Gas Station",
            "type":"Retail Goods"
        }
    ],
    "sg:phone":"+1 586 268 1560",
    "sg:postcode":"48313",
    "sg:province":"MI",
    "sg:tags":[
        "oil"
    ],
    "wof:name":"Shell Food Mart",
    "wof:placetype":"venue"
},
  "geometry": {"coordinates":[-83.030886,42.588374],"type":"Point"}
}