{
  "type": "Feature",
  "properties": {
    "iso:country":"US",
    "sg:address":"4205 Blanche Ave",
    "sg:city":"Lansing",
    "sg:classifiers":[
        {
            "category":"Manufacturing",
            "subcategory":"Printing",
            "type":"Manufacturing & Wholesale Goods"
        }
    ],
    "sg:phone":"+1 517 886 1693",
    "sg:postcode":"48917",
    "sg:province":"MI",
    "sg:tags":[
        "publishing"
    ],
    "wof:name":"BCM Publishing",
    "wof:placetype":"venue"
},
  "geometry": {"coordinates":[-84.60841000000001,42.729073],"type":"Point"}
}