{
  "type": "Feature",
  "properties": {
    "iso:country":"US",
    "sg:address":"22750 S Woodward Ave",
    "sg:city":"Ferndale",
    "sg:classifiers":[
        {
            "category":"Professional",
            "subcategory":"Lawyer & Legal Services",
            "type":"Services"
        }
    ],
    "sg:phone":"+1 248 544 9770",
    "sg:postcode":"48220",
    "sg:province":"MI",
    "wof:name":"Aero Legal Support Svc",
    "wof:placetype":"venue"
},
  "geometry": {"coordinates":[-83.13432,42.46058],"type":"Point"}
}