{
  "type": "Feature",
  "properties": {
    "iso:country":"US",
    "sg:address":"207 N Cedar St",
    "sg:city":"Traverse City",
    "sg:classifiers":[
        {
            "category":"Building & Trades",
            "subcategory":"Plumbing",
            "type":"Services"
        }
    ],
    "sg:phone":"+1 231 922 0048",
    "sg:postcode":"49684",
    "sg:province":"MI",
    "sg:tags":[
        "plumbing",
        "contractor"
    ],
    "wof:name":"Champion Plumbing",
    "wof:placetype":"venue"
},
  "geometry": {"coordinates":[-85.636489,44.765888],"type":"Point"}
}