{
  "type": "Feature",
  "properties": {
    "iso:country":"US",
    "sg:address":"661 Stonehenge Dr",
    "sg:city":"Canton",
    "sg:classifiers":[
        {
            "category":"Wholesale",
            "subcategory":"Vending Machines",
            "type":"Manufacturing & Wholesale Goods"
        }
    ],
    "sg:phone":"+1 734 397 5989",
    "sg:postcode":"48188",
    "sg:province":"MI",
    "sg:tags":[
        "operator"
    ],
    "wof:name":"Can Pop Vending",
    "wof:placetype":"venue"
},
  "geometry": {"coordinates":[-83.449868,42.304891],"type":"Point"}
}