{
  "type": "Feature",
  "properties": {
    "iso:country":"US",
    "sg:address":"609 N Morton St",
    "sg:city":"St Johns",
    "sg:classifiers":[
        {
            "category":"Real Estate",
            "subcategory":"Developer",
            "type":"Services"
        }
    ],
    "sg:phone":"+1 989 224 7913",
    "sg:postcode":"48879",
    "sg:province":"MI",
    "sg:tags":[
        "mobile",
        "home"
    ],
    "wof:name":"St Johns Mobile Home Village",
    "wof:placetype":"venue"
},
  "geometry": {"coordinates":[-84.566776,43.00699],"type":"Point"}
}