{
  "type": "Feature",
  "properties": {
    "iso:country":"US",
    "sg:address":"16235 Carlisle St",
    "sg:city":"Detroit",
    "sg:classifiers":[
        {
            "category":"Professional",
            "subcategory":"Secretarial Services",
            "type":"Services"
        }
    ],
    "sg:phone":"+1 313 839 3650",
    "sg:postcode":"48205",
    "sg:province":"MI",
    "sg:tags":[
        "reporting"
    ],
    "wof:name":"Lioness Clerical Service",
    "wof:placetype":"venue"
},
  "geometry": {"coordinates":[-82.95161,42.449326],"type":"Point"}
}