{
  "type": "Feature",
  "properties": {
    "iso:country":"US",
    "sg:address":"327 Collindale Ave SW",
    "sg:city":"Grand Rapids",
    "sg:classifiers":[
        {
            "category":"Shopping",
            "subcategory":"Gifts & Souvenirs",
            "type":"Retail Goods"
        }
    ],
    "sg:phone":"+1 616 791 1800",
    "sg:postcode":"49504",
    "sg:province":"MI",
    "sg:tags":[
        "shop"
    ],
    "wof:name":"Gift Basket",
    "wof:placetype":"venue"
},
  "geometry": {"coordinates":[-85.736805,42.96066],"type":"Point"}
}