{
  "type": "Feature",
  "properties": {
    "iso:country":"US",
    "sg:address":"675 Park St",
    "sg:city":"Birmingham",
    "sg:classifiers":[
        {
            "category":"Real Estate",
            "subcategory":"Architect",
            "type":"Services"
        }
    ],
    "sg:phone":"+1 248 569 8803",
    "sg:postcode":"48009",
    "sg:province":"MI",
    "wof:name":"Pastor Nicholas & Associates",
    "wof:placetype":"venue"
},
  "geometry": {"coordinates":[-83.216499,42.551399],"type":"Point"}
}