{
  "type": "Feature",
  "properties": {
    "iso:country":"US",
    "sg:address":"1243 Hull Rd",
    "sg:city":"Mason",
    "sg:classifiers":[
        {
            "category":"Organizations",
            "subcategory":"Community Association",
            "type":"Services"
        }
    ],
    "sg:phone":"+1 517 676 3181",
    "sg:postcode":"48854",
    "sg:province":"MI",
    "wof:name":"Anderson Vet Foreign War 7039",
    "wof:placetype":"venue"
},
  "geometry": {"coordinates":[-84.442866,42.548184],"type":"Point"}
}