{
  "type": "Feature",
  "properties": {
    "iso:country":"US",
    "sg:address":"24528 Ford Rd",
    "sg:city":"Dearborn Heights",
    "sg:classifiers":[
        {
            "category":"Banks & Credit Unions",
            "subcategory":"Bank",
            "type":"Services"
        }
    ],
    "sg:phone":"+1 313 561 6200",
    "sg:postcode":"48127",
    "sg:province":"MI",
    "sg:website":"statefarm.com",
    "wof:name":"State Farm Bank",
    "wof:placetype":"venue"
},
  "geometry": {"coordinates":[-83.277672,42.327023],"type":"Point"}
}