{
  "type": "Feature",
  "properties": {
    "iso:country":"US",
    "sg:address":"2341 Helen Ave",
    "sg:city":"Flint",
    "sg:classifiers":[
        {
            "category":"Professional",
            "subcategory":"Management & Consulting",
            "type":"Services"
        }
    ],
    "sg:phone":"+1 810 695 4152",
    "sg:postcode":"48507",
    "sg:province":"MI",
    "sg:tags":[
        "business"
    ],
    "wof:name":"Helms Consulting Svcs",
    "wof:placetype":"venue"
},
  "geometry": {"coordinates":[-83.661669,42.95566],"type":"Point"}
}