{
  "type": "Feature",
  "properties": {
    "iso:country":"US",
    "sg:address":"43422 W Oaks Dr",
    "sg:city":"Novi",
    "sg:classifiers":[
        {
            "category":"Building & Trades",
            "subcategory":"Cleaning & Sanitation",
            "type":"Services"
        }
    ],
    "sg:phone":"+1 248 982 9145",
    "sg:postcode":"48377",
    "sg:province":"MI",
    "sg:tags":[
        "house"
    ],
    "wof:name":"Unique Maids Svc",
    "wof:placetype":"venue"
},
  "geometry": {"coordinates":[-83.47649199999999,42.491184],"type":"Point"}
}