{
  "type": "Feature",
  "properties": {
    "iso:country":"US",
    "sg:address":"726 Westwood Dr",
    "sg:city":"Monroe",
    "sg:classifiers":[
        {
            "category":"Professional",
            "subcategory":"Secretarial Services",
            "type":"Services"
        }
    ],
    "sg:phone":"+1 734 457 5944",
    "sg:postcode":"48161",
    "sg:province":"MI",
    "sg:tags":[
        "convention",
        "reporting",
        "court",
        "reporter"
    ],
    "wof:name":"Rapid Court Reporters LLC",
    "wof:placetype":"venue"
},
  "geometry": {"coordinates":[-83.43050599999999,41.921454],"type":"Point"}
}