{
  "type": "Feature",
  "properties": {
    "iso:country":"US",
    "sg:address":"3610 M 40 S",
    "sg:city":"Hamilton",
    "sg:classifiers":[
        {
            "category":"Travel",
            "subcategory":"Travel Agent",
            "type":"Entertainment"
        }
    ],
    "sg:phone":"+1 269 751 7311",
    "sg:postcode":"49419",
    "sg:province":"MI",
    "sg:tags":[
        "agency",
        "bureau"
    ],
    "wof:name":"Crusies Unlimited",
    "wof:placetype":"venue"
},
  "geometry": {"coordinates":[-85.859408,42.687944],"type":"Point"}
}