{
  "type": "Feature",
  "properties": {
    "iso:country":"US",
    "sg:address":"394 2nd Ave",
    "sg:city":"Pontiac",
    "sg:classifiers":[
        {
            "category":"Building & Trades",
            "subcategory":"Construction",
            "type":"Services"
        }
    ],
    "sg:phone":"+1 248 334 7884",
    "sg:postcode":"48340",
    "sg:province":"MI",
    "sg:tags":[
        "house"
    ],
    "wof:name":"T&S Const Improvements",
    "wof:placetype":"venue"
},
  "geometry": {"coordinates":[-83.284736,42.667495],"type":"Point"}
}