{
  "type": "Feature",
  "properties": {
    "iso:country":"US",
    "sg:address":"1321 Robin Hood Trl",
    "sg:city":"Sturgis",
    "sg:classifiers":[
        {
            "category":"Professional",
            "subcategory":"Business Services",
            "type":"Services"
        }
    ],
    "sg:phone":"+1 269 651 3024",
    "sg:postcode":"49091",
    "sg:province":"MI",
    "wof:name":"Buoyant Solutions Inc",
    "wof:placetype":"venue"
},
  "geometry": {"coordinates":[-85.40800299999999,41.82063],"type":"Point"}
}