{
  "type": "Feature",
  "properties": {
    "iso:country":"US",
    "sg:address":"9133 Big Creek Lodge Rd",
    "sg:city":"Grayling",
    "sg:classifiers":[
        {
            "category":"Organizations",
            "subcategory":"Community Association",
            "type":"Services"
        }
    ],
    "sg:phone":"+1 989 348 4337",
    "sg:postcode":"49738",
    "sg:province":"MI",
    "sg:tags":[
        "fraternal"
    ],
    "wof:name":"Big Creek Lodge",
    "wof:placetype":"venue"
},
  "geometry": {"coordinates":[-84.42934099999999,44.785288],"type":"Point"}
}