{
  "type": "Feature",
  "properties": {
    "iso:country":"US",
    "sg:address":"36435 Grant St",
    "sg:city":"Romulus",
    "sg:classifiers":[
        {
            "category":"Retail",
            "subcategory":"Photofinishing",
            "type":"Services"
        }
    ],
    "sg:phone":"+1 734 941 1728",
    "sg:postcode":"48174",
    "sg:province":"MI",
    "sg:tags":[
        "laboratory"
    ],
    "wof:name":"Joseph Lisowski Premiere Photo",
    "wof:placetype":"venue"
},
  "geometry": {"coordinates":[-83.39846300000001,42.2158],"type":"Point"}
}