{
  "type": "Feature",
  "properties": {
    "iso:country":"US",
    "sg:address":"209 Maple St",
    "sg:city":"Bellaire",
    "sg:classifiers":[
        {
            "category":"Building & Trades",
            "subcategory":"Construction",
            "type":"Services"
        }
    ],
    "sg:phone":"+1 231 533 8235",
    "sg:postcode":"49615",
    "sg:province":"MI",
    "sg:tags":[
        "contractor"
    ],
    "wof:name":"Reed Builders",
    "wof:placetype":"venue"
},
  "geometry": {"coordinates":[-85.20504800000001,44.978211],"type":"Point"}
}