{
  "type": "Feature",
  "properties": {
    "iso:country":"US",
    "sg:address":"359 Summit Dr",
    "sg:city":"Waterford",
    "sg:classifiers":[
        {
            "category":"Shopping",
            "subcategory":"Clothing, Apparel, & Fashions",
            "type":"Retail Goods"
        }
    ],
    "sg:phone":"+1 248 683 9565",
    "sg:postcode":"48328",
    "sg:province":"MI",
    "wof:name":"Dots Inc",
    "wof:placetype":"venue"
},
  "geometry": {"coordinates":[-83.332438,42.64845],"type":"Point"}
}