{
  "type": "Feature",
  "properties": {
    "iso:country":"US",
    "sg:address":"8771 Bellman",
    "sg:city":"Utica",
    "sg:classifiers":[
        {
            "category":"Building & Trades",
            "subcategory":"Landscaping Services",
            "type":"Services"
        }
    ],
    "sg:phone":"+1 586 781 4185",
    "sg:postcode":"48316",
    "sg:province":"MI",
    "wof:name":"Everlasting Landscaping",
    "wof:placetype":"venue"
},
  "geometry": {"coordinates":[-83.026652,42.703811],"type":"Point"}
}