{
  "type": "Feature",
  "properties": {
    "iso:country":"US",
    "sg:address":"17615 Bailey Rd",
    "sg:city":"Bailey",
    "sg:classifiers":[
        {
            "category":"Real Estate",
            "subcategory":"Real Estate Agent",
            "type":"Services"
        }
    ],
    "sg:phone":"+1 231 834 8040",
    "sg:postcode":"49303",
    "sg:province":"MI",
    "sg:tags":[
        "appraisal"
    ],
    "wof:name":"Haden Appraisal",
    "wof:placetype":"venue"
},
  "geometry": {"coordinates":[-85.810123,43.278129],"type":"Point"}
}