{
  "type": "Feature",
  "properties": {
    "iso:country":"US",
    "sg:address":"1317 N Main St",
    "sg:city":"Royal Oak",
    "sg:classifiers":[
        {
            "category":"Retail",
            "subcategory":"Auto Repair",
            "type":"Services"
        }
    ],
    "sg:phone":"+1 248 548 9225",
    "sg:postcode":"48067",
    "sg:province":"MI",
    "wof:name":"S & K Muffler",
    "wof:placetype":"venue"
},
  "geometry": {"coordinates":[-83.144997,42.500999],"type":"Point"}
}