{
  "type": "Feature",
  "properties": {
    "iso:country":"US",
    "sg:address":"22601 Harper Ave",
    "sg:city":"Saint Clair Shores",
    "sg:classifiers":[
        {
            "category":"Health Services",
            "subcategory":"Doctor",
            "type":"Services"
        }
    ],
    "sg:phone":"+1 586 776 7785",
    "sg:postcode":"48080",
    "sg:province":"MI",
    "sg:tags":[
        "surgeon",
        "oral"
    ],
    "wof:name":"Post Arthur J DDS",
    "wof:placetype":"venue"
},
  "geometry": {"coordinates":[-82.90949999999999,42.462601],"type":"Point"}
}