{
  "type": "Feature",
  "properties": {
    "iso:country":"US",
    "sg:address":"630 36th St SW",
    "sg:city":"Grand Rapids",
    "sg:classifiers":[
        {
            "category":"Health Services",
            "subcategory":"Medical Lab",
            "type":"Services"
        }
    ],
    "sg:phone":"+1 616 531 6440",
    "sg:postcode":"49509",
    "sg:province":"MI",
    "sg:tags":[
        "laboratory",
        "dental"
    ],
    "wof:name":"Professional Ceramics Inc",
    "wof:placetype":"venue"
},
  "geometry": {"coordinates":[-85.68303,42.898706],"type":"Point"}
}