{
  "type": "Feature",
  "properties": {
    "iso:country":"US",
    "sg:address":"645 Griswold St",
    "sg:city":"Detroit",
    "sg:classifiers":[
        {
            "category":"Professional",
            "subcategory":"Lawyer & Legal Services",
            "type":"Services"
        }
    ],
    "sg:phone":"+1 313 967 0100",
    "sg:postcode":"48226",
    "sg:province":"MI",
    "wof:name":"N C Deday Larene",
    "wof:placetype":"venue"
},
  "geometry": {"coordinates":[-83.04723300000001,42.330278],"type":"Point"}
}