{
  "type": "Feature",
  "properties": {
    "iso:country":"US",
    "sg:address":"309 S Main St",
    "sg:city":"Royal Oak",
    "sg:classifiers":[
        {
            "category":"Wholesale",
            "subcategory":"Auto Parts",
            "type":"Manufacturing & Wholesale Goods"
        }
    ],
    "sg:phone":"+1 248 399 7808",
    "sg:postcode":"48067",
    "sg:province":"MI",
    "sg:tags":[
        "automobile",
        "supply"
    ],
    "wof:name":"Edward Levine",
    "wof:placetype":"venue"
},
  "geometry": {"coordinates":[-83.14412,42.48735],"type":"Point"}
}