{
  "type": "Feature",
  "properties": {
    "iso:country":"US",
    "sg:address":"12171 Hart St NE",
    "sg:city":"Greenville",
    "sg:phone":"+1 866 838 3403",
    "sg:postcode":"48838",
    "sg:province":"MI",
    "wof:name":"St. Denis Construction",
    "wof:placetype":"venue"
},
  "geometry": {"coordinates":[-85.366508,43.125944],"type":"Point"}
}