{
  "type": "Feature",
  "properties": {
    "iso:country":"US",
    "sg:address":"7635 Pinckney Rd",
    "sg:city":"Pinckney",
    "sg:classifiers":[
        {
            "category":"Retail",
            "subcategory":"Repair Shop",
            "type":"Services"
        }
    ],
    "sg:phone":"+1 734 878 2986",
    "sg:postcode":"48169",
    "sg:province":"MI",
    "wof:name":"J Gar Industries LLC",
    "wof:placetype":"venue"
},
  "geometry": {"coordinates":[-83.93288,42.487834],"type":"Point"}
}