{
  "type": "Feature",
  "properties": {
    "iso:country":"US",
    "sg:address":"68820 Wallowa Rd",
    "sg:city":"White Pigeon",
    "sg:classifiers":[
        {
            "category":"Farming",
            "subcategory":"Farm",
            "type":"Manufacturing & Wholesale Goods"
        }
    ],
    "sg:phone":"+1 269 483 7310",
    "sg:postcode":"49099",
    "sg:province":"MI",
    "sg:tags":[
        "textile",
        "general",
        "crop",
        "mfg"
    ],
    "wof:name":"Race America Technology",
    "wof:placetype":"venue"
},
  "geometry": {"coordinates":[-85.56614500000001,41.796746],"type":"Point"}
}