{
  "type": "Feature",
  "properties": {
    "iso:country":"US",
    "sg:address":"2800 Greyberry Dr",
    "sg:city":"Waterford",
    "sg:classifiers":[
        {
            "category":"Building & Trades",
            "subcategory":"Construction",
            "type":"Services"
        }
    ],
    "sg:phone":"+1 248 738 2643",
    "sg:postcode":"48328",
    "sg:province":"MI",
    "sg:tags":[
        "hanging",
        "contractor"
    ],
    "wof:name":"Jantech Interior Painting Inc",
    "wof:placetype":"venue"
},
  "geometry": {"coordinates":[-83.341336,42.648376],"type":"Point"}
}