{
  "type": "Feature",
  "properties": {
    "iso:country":"US",
    "sg:address":"5402 Campau Dr",
    "sg:city":"Midland",
    "sg:classifiers":[
        {
            "category":"Banks & Credit Unions",
            "subcategory":"Investment Brokerage",
            "type":"Services"
        }
    ],
    "sg:phone":"+1 989 631 5553",
    "sg:postcode":"48640",
    "sg:province":"MI",
    "sg:tags":[
        "security"
    ],
    "wof:name":"G Mock Investments",
    "wof:placetype":"venue"
},
  "geometry": {"coordinates":[-84.254622,43.646247],"type":"Point"}
}