{
  "type": "Feature",
  "properties": {
    "iso:country":"US",
    "sg:address":"1005 Delta Ave",
    "sg:city":"Gladstone",
    "sg:classifiers":[
        {
            "category":"Banks & Credit Unions",
            "subcategory":"Bank",
            "type":"Services"
        }
    ],
    "sg:phone":"+1 906 428 2362",
    "sg:postcode":"49837",
    "sg:province":"MI",
    "sg:tags":[
        "chartered",
        "state",
        "federally"
    ],
    "sg:website":"www.glffcu.com",
    "wof:name":"Great Lakes First Federal CU",
    "wof:placetype":"venue"
},
  "geometry": {"coordinates":[-87.022227,45.847175],"type":"Point"}
}