{
  "type": "Feature",
  "properties": {
    "iso:country":"US",
    "sg:address":"25100 J Dr S",
    "sg:city":"Homer",
    "sg:classifiers":[
        {
            "category":"Retail",
            "subcategory":"Repair Shop",
            "type":"Services"
        }
    ],
    "sg:phone":"+1 517 568 3254",
    "sg:postcode":"49245",
    "sg:province":"MI",
    "wof:name":"Jerrys Tractor Clinic",
    "wof:placetype":"venue"
},
  "geometry": {"coordinates":[-84.80644599999999,42.173842],"type":"Point"}
}