{
  "type": "Feature",
  "properties": {
    "iso:country":"US",
    "sg:address":"4202 Barber Rd",
    "sg:city":"Hastings",
    "sg:classifiers":[
        {
            "category":"Retail",
            "subcategory":"Car Wash",
            "type":"Services"
        },
        {
            "category":"Building & Trades",
            "subcategory":"Construction",
            "type":"Services"
        }
    ],
    "sg:phone":"+1 269 945 0657",
    "sg:postcode":"49058",
    "sg:province":"MI",
    "sg:tags":[
        "carwash",
        "restoration",
        "cleaning",
        "patio",
        "deck"
    ],
    "wof:name":"Power Wash Techniques",
    "wof:placetype":"venue"
},
  "geometry": {"coordinates":[-85.261264,42.710398],"type":"Point"}
}