{
  "type": "Feature",
  "properties": {
    "iso:country":"US",
    "sg:address":"7 N State St",
    "sg:city":"Zeeland",
    "sg:classifiers":[
        {
            "category":"Health Services",
            "subcategory":"Chiropractor",
            "type":"Services"
        }
    ],
    "sg:phone":"+1 616 772 0344",
    "sg:postcode":"49464",
    "sg:province":"MI",
    "wof:name":"Zeeland Family Chiropractic",
    "wof:placetype":"venue"
},
  "geometry": {"coordinates":[-86.018973,42.81377],"type":"Point"}
}