{
  "type": "Feature",
  "properties": {
    "iso:country":"US",
    "sg:address":"7581 Secor Rd",
    "sg:city":"Lambertville",
    "sg:classifiers":[
        {
            "category":"Health Services",
            "subcategory":"Doctor",
            "type":"Services"
        }
    ],
    "sg:phone":"+1 734 856 6360",
    "sg:postcode":"48144",
    "sg:province":"MI",
    "sg:tags":[
        "clinic"
    ],
    "wof:name":"Aspen Medical Partners",
    "wof:placetype":"venue"
},
  "geometry": {"coordinates":[-83.625844,41.752006],"type":"Point"}
}