{
  "type": "Feature",
  "properties": {
    "iso:country":"US",
    "sg:address":"2500 Takata Dr",
    "sg:city":"Auburn Hills",
    "sg:classifiers":[
        {
            "category":"Manufacturing",
            "subcategory":"Apparel",
            "type":"Manufacturing & Wholesale Goods"
        }
    ],
    "sg:phone":"+1 248 373 8040",
    "sg:postcode":"48326",
    "sg:province":"MI",
    "sg:tags":[
        "textile",
        "product",
        "fabricated",
        "mfg"
    ],
    "wof:name":"Tk Holdings Inc",
    "wof:placetype":"venue"
},
  "geometry": {"coordinates":[-83.243387,42.659769],"type":"Point"}
}