{
  "type": "Feature",
  "properties": {
    "iso:country":"US",
    "sg:address":"1348 Baldwin Ave",
    "sg:city":"Pontiac",
    "sg:classifiers":[
        {
            "category":"Organizations",
            "subcategory":"Religious Organization",
            "type":"Services"
        }
    ],
    "sg:phone":"+1 248 332 1930",
    "sg:postcode":"48340",
    "sg:province":"MI",
    "wof:name":"Bethel Tabernacle Church",
    "wof:placetype":"venue"
},
  "geometry": {"coordinates":[-83.300517,42.673893],"type":"Point"}
}