{
  "type": "Feature",
  "properties": {
    "iso:country":"US",
    "sg:address":"401 S Lafayette Ave",
    "sg:city":"Royal Oak",
    "sg:classifiers":[
        {
            "category":"Restaurant",
            "type":"Food & Drink"
        }
    ],
    "sg:menulink":"http://www.allmenus.com/mi/royal-oak/11101-sangria/menu/",
    "sg:phone":"+1 248 543 1964",
    "sg:postcode":"48067",
    "sg:province":"MI",
    "sg:tags":[
        "mexican"
    ],
    "wof:name":"Sangria",
    "wof:placetype":"venue"
},
  "geometry": {"coordinates":[-83.147808,42.487083],"type":"Point"}
}