{
  "type": "Feature",
  "properties": {
    "iso:country":"US",
    "sg:address":"1405 W Columbia Ave",
    "sg:city":"Battle Creek",
    "sg:classifiers":[
        {
            "category":"Autos & Motor Vehicles",
            "subcategory":"Auto Supplies",
            "type":"Retail Goods"
        }
    ],
    "sg:phone":"+1 269 964 1351",
    "sg:postcode":"49015",
    "sg:province":"MI",
    "sg:tags":[
        "automobile",
        "parts"
    ],
    "wof:name":"Advance Auto Parts Inc",
    "wof:placetype":"venue"
},
  "geometry": {"coordinates":[-85.22198299999999,42.297385],"type":"Point"}
}