{
  "type": "Feature",
  "properties": {
    "iso:country":"US",
    "sg:address":"58 Benjamin Ave NE",
    "sg:city":"Grand Rapids",
    "sg:classifiers":[
        {
            "category":"Banks & Credit Unions",
            "subcategory":"Financial Services",
            "type":"Services"
        }
    ],
    "sg:phone":"+1 616 459 2191",
    "sg:postcode":"49503",
    "sg:province":"MI",
    "sg:tags":[
        "investor"
    ],
    "wof:name":"Alelon Investments LLC",
    "wof:placetype":"venue"
},
  "geometry": {"coordinates":[-85.63767900000001,42.964496],"type":"Point"}
}