{
  "type": "Feature",
  "properties": {
    "iso:country":"US",
    "sg:address":"11 S Huron Rd",
    "sg:city":"Linwood",
    "sg:classifiers":[
        {
            "category":"Food & Beverages",
            "subcategory":"Bakery",
            "type":"Retail Goods"
        }
    ],
    "sg:phone":"+1 989 697 4430",
    "sg:postcode":"48634",
    "sg:province":"MI",
    "sg:tags":[
        "baker"
    ],
    "wof:name":"Judy's Famous Pies",
    "wof:placetype":"venue"
},
  "geometry": {"coordinates":[-83.97613200000001,43.737958],"type":"Point"}
}