{
  "type": "Feature",
  "properties": {
    "iso:country":"US",
    "sg:address":"2803 Danforth Rd",
    "sg:city":"Escanaba",
    "sg:classifiers":[
        {
            "category":"Building & Trades",
            "subcategory":"Plumbing",
            "type":"Services"
        }
    ],
    "sg:phone":"+1 906 786 8605",
    "sg:postcode":"49829",
    "sg:province":"MI",
    "sg:tags":[
        "plumbing",
        "contractor"
    ],
    "wof:name":"B & B Plumbing & Heating",
    "wof:placetype":"venue"
},
  "geometry": {"coordinates":[-87.08665000000001,45.769588],"type":"Point"}
}