{
  "type": "Feature",
  "properties": {
    "iso:country":"US",
    "sg:address":"2248 Stafford Ave SW",
    "sg:city":"Grand Rapids",
    "sg:classifiers":[
        {
            "category":"Shopping",
            "subcategory":"Gifts & Souvenirs",
            "type":"Retail Goods"
        }
    ],
    "sg:phone":"+1 616 245 6591",
    "sg:postcode":"49507",
    "sg:province":"MI",
    "wof:name":"Shepherd Specialty Merchandise",
    "wof:placetype":"venue"
},
  "geometry": {"coordinates":[-85.675585,42.922596],"type":"Point"}
}