{
  "type": "Feature",
  "properties": {
    "iso:country":"US",
    "sg:address":"7802 Auburn St",
    "sg:city":"Detroit",
    "sg:classifiers":[
        {
            "category":"Professional",
            "type":"Services"
        }
    ],
    "sg:phone":"+1 313 271 4336",
    "sg:postcode":"48228",
    "sg:province":"MI",
    "wof:name":"Mobile Disc Jock Services",
    "wof:placetype":"venue"
},
  "geometry": {"coordinates":[-83.233091,42.348574],"type":"Point"}
}