{
  "type": "Feature",
  "properties": {
    "iso:country":"US",
    "sg:address":"2505 Whitehall Rd",
    "sg:city":"Muskegon",
    "sg:classifiers":[
        {
            "category":"Freight",
            "type":"Transportation"
        }
    ],
    "sg:phone":"+1 231 744 1449",
    "sg:postcode":"49445",
    "sg:province":"MI",
    "sg:tags":[
        "commercial",
        "storage"
    ],
    "wof:name":"A-1 Store & Lock",
    "wof:placetype":"venue"
},
  "geometry": {"coordinates":[-86.261903,43.301095],"type":"Point"}
}