{
  "type": "Feature",
  "properties": {
    "iso:country":"US",
    "sg:address":"115 W Superior St",
    "sg:city":"Munising",
    "sg:classifiers":[
        {
            "category":"Food & Beverages",
            "subcategory":"Bakery",
            "type":"Retail Goods"
        }
    ],
    "sg:phone":"+1 906 387 2148",
    "sg:postcode":"49862",
    "sg:province":"MI",
    "sg:tags":[
        "baker"
    ],
    "wof:name":"Munising Bakery",
    "wof:placetype":"venue"
},
  "geometry": {"coordinates":[-86.657326,46.411289],"type":"Point"}
}