{
  "type": "Feature",
  "properties": {
    "iso:country":"US",
    "sg:address":"3023 Watkins Lake Rd",
    "sg:city":"Waterford",
    "sg:classifiers":[
        {
            "category":"Retail",
            "subcategory":"Repair Shop",
            "type":"Services"
        }
    ],
    "sg:phone":"+1 248 682 2420",
    "sg:postcode":"48328",
    "sg:province":"MI",
    "sg:tags":[
        "plumbing",
        "drain",
        "cleaning",
        "sewer"
    ],
    "wof:name":"E & B Electric Sewer Cleaners",
    "wof:placetype":"venue"
},
  "geometry": {"coordinates":[-83.35718900000001,42.671977],"type":"Point"}
}