{
  "type": "Feature",
  "properties": {
    "iso:country":"US",
    "sg:address":"5627 W Macfarlane Rd",
    "sg:city":"Glen Arbor",
    "sg:classifiers":[
        {
            "category":"Health Services",
            "subcategory":"Health Practitioner",
            "type":"Services"
        }
    ],
    "sg:phone":"+1 231 334 4455",
    "sg:postcode":"49636",
    "sg:province":"MI",
    "wof:name":"Janice Richards Physio Ther",
    "wof:placetype":"venue"
},
  "geometry": {"coordinates":[-85.967613,44.844034],"type":"Point"}
}