{
  "type": "Feature",
  "properties": {
    "iso:country":"US",
    "sg:address":"6003 Danbury Ct",
    "sg:city":"West Bloomfield",
    "sg:classifiers":[
        {
            "category":"Professional",
            "subcategory":"Management & Consulting",
            "type":"Services"
        }
    ],
    "sg:phone":"+1 248 851 8806",
    "sg:postcode":"48322",
    "sg:province":"MI",
    "sg:tags":[
        "business"
    ],
    "wof:name":"Norman Wachler",
    "wof:placetype":"venue"
},
  "geometry": {"coordinates":[-83.375057,42.529458],"type":"Point"}
}