{
  "type": "Feature",
  "properties": {
    "iso:country":"US",
    "sg:address":"37872 Van Dyke Ave",
    "sg:city":"Sterling Heights",
    "sg:classifiers":[
        {
            "category":"Professional",
            "subcategory":"Accounting & Tax Preparation",
            "type":"Services"
        }
    ],
    "sg:phone":"+1 586 795 2615",
    "sg:postcode":"48312",
    "sg:province":"MI",
    "sg:tags":[
        "return",
        "filing"
    ],
    "wof:name":"Liberty Tax Svc",
    "wof:placetype":"venue"
},
  "geometry": {"coordinates":[-83.029743,42.572361],"type":"Point"}
}