{
  "type": "Feature",
  "properties": {
    "iso:country":"US",
    "sg:address":"3108 E Bristol Rd",
    "sg:city":"Burton",
    "sg:classifiers":[
        {
            "category":"Retail",
            "subcategory":"Car Wash",
            "type":"Services"
        }
    ],
    "sg:phone":"+1 810 742 8077",
    "sg:postcode":"48529",
    "sg:province":"MI",
    "sg:tags":[
        "polishing",
        "washing"
    ],
    "wof:name":"Top Shelf Auto Detailing",
    "wof:placetype":"venue"
},
  "geometry": {"coordinates":[-83.65071,42.97466],"type":"Point"}
}