{
  "type": "Feature",
  "properties": {
    "iso:country":"US",
    "sg:address":"G-2333 S Center Rd",
    "sg:city":"Flint",
    "sg:classifiers":[
        {
            "category":"Food & Beverages",
            "subcategory":"Groceries & Convenience Stores",
            "type":"Retail Goods"
        }
    ],
    "sg:phone":"+1 810 744 9706",
    "sg:postcode":"48502",
    "sg:province":"MI",
    "sg:website":"www.meijer.com",
    "wof:name":"Meijer Inc",
    "wof:placetype":"venue"
},
  "geometry": {"coordinates":[-83.635549,43.037441],"type":"Point"}
}