{
  "type": "Feature",
  "properties": {
    "iso:country":"US",
    "sg:address":"339 S Grove St",
    "sg:city":"Delton",
    "sg:classifiers":[
        {
            "category":"Building & Trades",
            "subcategory":"Cleaning & Sanitation",
            "type":"Services"
        }
    ],
    "sg:phone":"+1 269 623 3968",
    "sg:postcode":"49046",
    "sg:province":"MI",
    "wof:name":"Diana's Cleaning Svc",
    "wof:placetype":"venue"
},
  "geometry": {"coordinates":[-85.40788999999999,42.498337],"type":"Point"}
}