{
  "type": "Feature",
  "properties": {
    "iso:country":"US",
    "sg:address":"917 Woodward Ave",
    "sg:city":"Kingsford",
    "sg:classifiers":[
        {
            "category":"Building & Trades",
            "subcategory":"Electrical",
            "type":"Services"
        }
    ],
    "sg:phone":"+1 906 779 5891",
    "sg:postcode":"49802",
    "sg:province":"MI",
    "sg:tags":[
        "electric",
        "contractor"
    ],
    "wof:name":"M J Electric",
    "wof:placetype":"venue"
},
  "geometry": {"coordinates":[-88.082409,45.807704],"type":"Point"}
}