{
  "type": "Feature",
  "properties": {
    "iso:country":"US",
    "sg:address":"842 W Michigan Ave",
    "sg:city":"Marshall",
    "sg:classifiers":[
        {
            "category":"Shopping",
            "type":"Retail Goods"
        }
    ],
    "sg:phone":"+1 269 781 1145",
    "sg:postcode":"49068",
    "sg:province":"MI",
    "sg:tags":[
        "telephone",
        "cellular"
    ],
    "wof:name":"Wireless World",
    "wof:placetype":"venue"
},
  "geometry": {"coordinates":[-84.972048,42.272104],"type":"Point"}
}