{
  "type": "Feature",
  "properties": {
    "iso:country":"US",
    "sg:address":"23233 Lahser Rd",
    "sg:city":"Southfield",
    "sg:classifiers":[
        {
            "category":"Wholesale",
            "subcategory":"Hardware",
            "type":"Manufacturing & Wholesale Goods"
        }
    ],
    "sg:phone":"+1 248 358 0200",
    "sg:postcode":"48033",
    "sg:province":"MI",
    "sg:tags":[
        "plumbing",
        "fixture",
        "supply"
    ],
    "wof:name":"Contractors Pipe & Supply Corp",
    "wof:placetype":"venue"
},
  "geometry": {"coordinates":[-83.26008299999999,42.457857],"type":"Point"}
}