{
  "type": "Feature",
  "properties": {
    "iso:country":"US",
    "sg:address":"2919 Westbrook Rd",
    "sg:city":"Ionia",
    "sg:classifiers":[
        {
            "category":"Building & Trades",
            "subcategory":"Construction",
            "type":"Services"
        }
    ],
    "sg:phone":"+1 616 527 8145",
    "sg:postcode":"48846",
    "sg:province":"MI",
    "sg:tags":[
        "house"
    ],
    "wof:name":"Cannata Home Improvements",
    "wof:placetype":"venue"
},
  "geometry": {"coordinates":[-84.975786,43.017616],"type":"Point"}
}