{
  "type": "Feature",
  "properties": {
    "iso:country":"US",
    "sg:address":"603 Iris Ave",
    "sg:city":"Lansing",
    "sg:classifiers":[
        {
            "category":"Personal",
            "subcategory":"Barber",
            "type":"Services"
        }
    ],
    "sg:phone":"+1 517 886 3833",
    "sg:postcode":"48917",
    "sg:province":"MI",
    "sg:tags":[
        "shop"
    ],
    "wof:name":"R Barber",
    "wof:placetype":"venue"
},
  "geometry": {"coordinates":[-84.619598,42.738668],"type":"Point"}
}