{
  "type": "Feature",
  "properties": {
    "iso:country":"US",
    "sg:address":"3395 Bay Rd",
    "sg:city":"Saginaw",
    "sg:classifiers":[
        {
            "category":"Retail",
            "subcategory":"Auto Repair",
            "type":"Services"
        }
    ],
    "sg:phone":"+1 989 790 8178",
    "sg:postcode":"48603",
    "sg:province":"MI",
    "sg:tags":[
        "body",
        "automobile",
        "painting"
    ],
    "sg:website":"www.paintball.com",
    "wof:name":"Paint Bull Express",
    "wof:placetype":"venue"
},
  "geometry": {"coordinates":[-83.97565899999999,43.45627],"type":"Point"}
}