{
  "type": "Feature",
  "properties": {
    "iso:country":"US",
    "sg:address":"11251 Baker Blackjack Rd",
    "sg:city":"Bessemer",
    "sg:classifiers":[
        {
            "category":"Travel",
            "subcategory":"Hotels & Motels",
            "type":"Entertainment"
        }
    ],
    "sg:phone":"+1 906 229 5157",
    "sg:postcode":"49911",
    "sg:province":"MI",
    "sg:tags":[
        "resort",
        "center",
        "skiing"
    ],
    "sg:website":"www.blackjacklodging.com",
    "wof:name":"Blackjack Ski Resort",
    "wof:placetype":"venue"
},
  "geometry": {"coordinates":[-89.989726,46.485335],"type":"Point"}
}