{
  "type": "Feature",
  "properties": {
    "iso:country":"US",
    "sg:address":"4489 Pegasus Blvd",
    "sg:city":"Dryden",
    "sg:classifiers":[
        {
            "category":"Building & Trades",
            "subcategory":"Construction",
            "type":"Services"
        }
    ],
    "sg:phone":"+1 810 796 2932",
    "sg:postcode":"48428",
    "sg:province":"MI",
    "sg:tags":[
        "hanging",
        "contractor"
    ],
    "wof:name":"Charlie Suddeth Painting",
    "wof:placetype":"venue"
},
  "geometry": {"coordinates":[-83.169881,42.930662],"type":"Point"}
}