{
  "type": "Feature",
  "properties": {
    "iso:country":"US",
    "sg:address":"4082 Ramsgate Ct",
    "sg:city":"Ann Arbor",
    "sg:classifiers":[
        {
            "category":"Professional",
            "subcategory":"Management & Consulting",
            "type":"Services"
        }
    ],
    "sg:phone":"+1 734 936 0636",
    "sg:postcode":"48103",
    "sg:province":"MI",
    "wof:name":"James Kulik",
    "wof:placetype":"venue"
},
  "geometry": {"coordinates":[-83.808719,42.301295],"type":"Point"}
}