{
  "type": "Feature",
  "properties": {
    "iso:country":"US",
    "sg:address":"3341 Eastern Ave SE",
    "sg:city":"Grand Rapids",
    "sg:classifiers":[
        {
            "category":"Retail",
            "subcategory":"Auto Repair",
            "type":"Services"
        }
    ],
    "sg:phone":"+1 616 245 0011",
    "sg:postcode":"49508",
    "sg:province":"MI",
    "sg:tags":[
        "repairing",
        "automobile"
    ],
    "wof:name":"Eastern Auto Svc",
    "wof:placetype":"venue"
},
  "geometry": {"coordinates":[-85.646738,42.90553],"type":"Point"}
}