{
  "type": "Feature",
  "properties": {
    "iso:country":"US",
    "sg:address":"27725 Stansbury St",
    "sg:city":"Farmington Hills",
    "sg:classifiers":[
        {
            "category":"Banks & Credit Unions",
            "subcategory":"Bank",
            "type":"Services"
        }
    ],
    "sg:phone":"+1 248 476 3029",
    "sg:postcode":"48334",
    "sg:province":"MI",
    "sg:tags":[
        "loan",
        "institution",
        "business",
        "broker"
    ],
    "sg:website":"www.rockloans.com",
    "wof:name":"Rock Financial",
    "wof:placetype":"venue"
},
  "geometry": {"coordinates":[-83.35232000000001,42.498426],"type":"Point"}
}