{
  "type": "Feature",
  "properties": {
    "iso:country":"US",
    "sg:address":"174 Southern Shores Dr",
    "sg:city":"Brooklyn",
    "sg:classifiers":[
        {
            "category":"Banks & Credit Unions",
            "subcategory":"Investment Brokerage",
            "type":"Services"
        }
    ],
    "sg:phone":"+1 517 592 3908",
    "sg:postcode":"49230",
    "sg:province":"MI",
    "sg:tags":[
        "consultant",
        "planning",
        "financial"
    ],
    "wof:name":"Gerweck & Co",
    "wof:placetype":"venue"
},
  "geometry": {"coordinates":[-84.305216,42.075385],"type":"Point"}
}