{
  "type": "Feature",
  "properties": {
    "iso:country":"US",
    "sg:address":"615 W 1st St",
    "sg:city":"Scottville",
    "sg:classifiers":[
        {
            "category":"Wholesale",
            "subcategory":"Machinery & Supplies",
            "type":"Manufacturing & Wholesale Goods"
        }
    ],
    "sg:phone":"+1 231 757 2168",
    "sg:postcode":"49454",
    "sg:province":"MI",
    "sg:tags":[
        "equipment",
        "mining"
    ],
    "wof:name":"PCI Us",
    "wof:placetype":"venue"
},
  "geometry": {"coordinates":[-86.28957,43.947745],"type":"Point"}
}