{
  "type": "Feature",
  "properties": {
    "iso:country":"US",
    "sg:address":"6424 San Ru Ave",
    "sg:city":"Jenison",
    "sg:classifiers":[
        {
            "category":"Wholesale",
            "subcategory":"Non-durable Goods",
            "type":"Manufacturing & Wholesale Goods"
        }
    ],
    "sg:phone":"+1 616 957 2111",
    "sg:postcode":"49428",
    "sg:province":"MI",
    "sg:tags":[
        "advertising"
    ],
    "wof:name":"Banana Splitz",
    "wof:placetype":"venue"
},
  "geometry": {"coordinates":[-85.847537,42.88582],"type":"Point"}
}