{
  "type": "Feature",
  "properties": {
    "iso:country":"US",
    "sg:address":"3337 Auburn Rd",
    "sg:city":"Auburn Hills",
    "sg:classifiers":[
        {
            "category":"Personal",
            "subcategory":"Nail Salon",
            "type":"Services"
        }
    ],
    "sg:phone":"+1 248 852 4920",
    "sg:postcode":"48326",
    "sg:province":"MI",
    "sg:website":"www.serenity-hair-salon.com",
    "wof:name":"Serenity Hair Salon Llc",
    "wof:placetype":"venue"
},
  "geometry": {"coordinates":[-83.222103,42.633799],"type":"Point"}
}