{
  "type": "Feature",
  "properties": {
    "iso:country":"US",
    "sg:address":"440 W Centre Ave",
    "sg:city":"Portage",
    "sg:classifiers":[
        {
            "category":"Banks & Credit Unions",
            "subcategory":"Investment Brokerage",
            "type":"Services"
        }
    ],
    "sg:phone":"+1 269 383 1330",
    "sg:postcode":"49024",
    "sg:province":"MI",
    "sg:tags":[
        "consultant",
        "planning",
        "financial"
    ],
    "wof:name":"Albion Financial Inc",
    "wof:placetype":"venue"
},
  "geometry": {"coordinates":[-85.59481,42.20105],"type":"Point"}
}