{
  "type": "Feature",
  "properties": {
    "iso:country":"US",
    "sg:address":"29800 Southfield Rd",
    "sg:city":"Southfield",
    "sg:classifiers":[
        {
            "category":"Food & Beverages",
            "subcategory":"Groceries & Convenience Stores",
            "type":"Retail Goods"
        }
    ],
    "sg:phone":"+1 248 559 6121",
    "sg:postcode":"48076",
    "sg:province":"MI",
    "sg:tags":[
        "grocer"
    ],
    "wof:name":"Farmer Jack Market",
    "wof:placetype":"venue"
},
  "geometry": {"coordinates":[-83.22275999999999,42.507163],"type":"Point"}
}