{
  "type": "Feature",
  "properties": {
    "iso:country":"US",
    "sg:address":"23922 W 12 Mile Rd",
    "sg:city":"Southfield",
    "sg:classifiers":[
        {
            "category":"Professional",
            "subcategory":"Management & Consulting",
            "type":"Services"
        }
    ],
    "sg:phone":"+1 248 358 0481",
    "sg:postcode":"48034",
    "sg:province":"MI",
    "wof:name":"Doc Collins Construction Co In",
    "wof:placetype":"venue"
},
  "geometry": {"coordinates":[-83.280968,42.501233],"type":"Point"}
}