{
  "type": "Feature",
  "properties": {
    "iso:country":"US",
    "sg:address":"1263 S Adams Rd",
    "sg:city":"Rochester Hills",
    "sg:classifiers":[
        {
            "category":"Social Services",
            "subcategory":"Child Care",
            "type":"Services"
        }
    ],
    "sg:phone":"+1 248 375 1700",
    "sg:postcode":"48309",
    "sg:province":"MI",
    "wof:name":"Brookfield Academy",
    "wof:placetype":"venue"
},
  "geometry": {"coordinates":[-83.192993,42.658809],"type":"Point"}
}