{
  "type": "Feature",
  "properties": {
    "iso:country":"US",
    "sg:address":"4677 Hiawatha Dr",
    "sg:city":"Cheboygan",
    "sg:classifiers":[
        {
            "category":"Wholesale",
            "subcategory":"Non-durable Goods",
            "type":"Manufacturing & Wholesale Goods"
        }
    ],
    "sg:phone":"+1 231 625 2906",
    "sg:postcode":"49721",
    "sg:province":"MI",
    "sg:tags":[
        "rubber",
        "sponge"
    ],
    "sg:website":"www.decarloassociates.com",
    "wof:name":"De Carlo Assoc Inc",
    "wof:placetype":"venue"
},
  "geometry": {"coordinates":[-84.40289,45.531467],"type":"Point"}
}