{
  "type": "Feature",
  "properties": {
    "iso:country":"US",
    "sg:address":"7750 Mill Rd",
    "sg:city":"Brooklyn",
    "sg:classifiers":[
        {
            "category":"Building & Trades",
            "subcategory":"Construction",
            "type":"Services"
        }
    ],
    "sg:phone":"+1 517 536 0176",
    "sg:postcode":"49230",
    "sg:province":"MI",
    "sg:tags":[
        "house"
    ],
    "wof:name":"Schwab Construction",
    "wof:placetype":"venue"
},
  "geometry": {"coordinates":[-84.184499,42.155694],"type":"Point"}
}