{
  "type": "Feature",
  "properties": {
    "iso:country":"US",
    "sg:address":"2035 28th St SE",
    "sg:city":"Grand Rapids",
    "sg:classifiers":[
        {
            "category":"Retail",
            "subcategory":"Portrait Studio",
            "type":"Services"
        }
    ],
    "sg:phone":"+1 616 452 2070",
    "sg:postcode":"49508",
    "sg:province":"MI",
    "sg:tags":[
        "photographer"
    ],
    "wof:name":"Senior Photography Showcase",
    "wof:placetype":"venue"
},
  "geometry": {"coordinates":[-85.61716,42.912711],"type":"Point"}
}