{
  "type": "Feature",
  "properties": {
    "iso:country":"US",
    "sg:address":"2609 Sloan St",
    "sg:city":"Flint",
    "sg:classifiers":[
        {
            "category":"Building & Trades",
            "subcategory":"Construction",
            "type":"Services"
        }
    ],
    "sg:phone":"+1 810 233 4601",
    "sg:postcode":"48504",
    "sg:province":"MI",
    "sg:tags":[
        "hanging",
        "contractor"
    ],
    "wof:name":"Expert Painting Inc",
    "wof:placetype":"venue"
},
  "geometry": {"coordinates":[-83.725961,43.023782],"type":"Point"}
}