{
  "type": "Feature",
  "properties": {
    "iso:country":"US",
    "sg:address":"1607 Merrill St",
    "sg:city":"Kalamazoo",
    "sg:classifiers":[
        {
            "category":"Building & Trades",
            "subcategory":"Construction",
            "type":"Services"
        }
    ],
    "sg:phone":"+1 269 349 9882",
    "sg:postcode":"49008",
    "sg:province":"MI",
    "sg:tags":[
        "hanging",
        "contractor"
    ],
    "wof:name":"Ikes Painting Service",
    "wof:placetype":"venue"
},
  "geometry": {"coordinates":[-85.59428200000001,42.275204],"type":"Point"}
}