{
  "type": "Feature",
  "properties": {
    "iso:country":"US",
    "sg:address":"38259 W 10 Mile Rd",
    "sg:city":"Farmington Hills",
    "sg:classifiers":[
        {
            "category":"Restaurant",
            "type":"Food & Drink"
        }
    ],
    "sg:phone":"+1 248 987 2303",
    "sg:postcode":"48336",
    "sg:province":"MI",
    "sg:website":"www.sophias-restaurant.com",
    "wof:name":"Sophia's Restaurant",
    "wof:placetype":"venue"
},
  "geometry": {"coordinates":[-83.37482799999999,42.469656],"type":"Point"}
}