{
  "type": "Feature",
  "properties": {
    "iso:country":"US",
    "sg:address":"10704 Oviatt Rd",
    "sg:city":"Honor",
    "sg:phone":"+1 231 326 5444",
    "sg:postcode":"49640",
    "sg:province":"MI",
    "sg:tags":[
        "food",
        "equipment",
        "processing"
    ],
    "sg:website":"www.giftsthatmatter.com",
    "wof:name":"Food For Thought Inc",
    "wof:placetype":"venue"
},
  "geometry": {"coordinates":[-86.028993,44.769293],"type":"Point"}
}