{
  "type": "Feature",
  "properties": {
    "iso:country":"US",
    "sg:address":"29217 Parkwood St",
    "sg:city":"Inkster",
    "sg:classifiers":[
        {
            "category":"Social Services",
            "subcategory":"Child Care",
            "type":"Services"
        }
    ],
    "sg:phone":"+1 734 721 2457",
    "sg:postcode":"48141",
    "sg:province":"MI",
    "sg:tags":[
        "day"
    ],
    "wof:name":"Phat Baby",
    "wof:placetype":"venue"
},
  "geometry": {"coordinates":[-83.328389,42.3003],"type":"Point"}
}