{
  "type": "Feature",
  "properties": {
    "iso:country":"US",
    "sg:address":"14040 Talbot St",
    "sg:city":"Oak Park",
    "sg:classifiers":[
        {
            "category":"Building & Trades",
            "subcategory":"Construction",
            "type":"Services"
        }
    ],
    "sg:phone":"+1 248 399 3004",
    "sg:postcode":"48237",
    "sg:province":"MI",
    "sg:tags":[
        "dry wall",
        "contractor"
    ],
    "wof:name":"Inner Lakes Drywall Paint",
    "wof:placetype":"venue"
},
  "geometry": {"coordinates":[-83.18980999999999,42.485497],"type":"Point"}
}