{
  "type": "Feature",
  "properties": {
    "iso:country":"US",
    "sg:address":"17608 Reed St",
    "sg:city":"Melvindale",
    "sg:classifiers":[
        {
            "category":"Professional",
            "subcategory":"Business Services",
            "type":"Services"
        }
    ],
    "sg:phone":"+1 313 381 6353",
    "sg:postcode":"48122",
    "sg:province":"MI",
    "wof:name":"Ken Logan Presents 20 Minutes",
    "wof:placetype":"venue"
},
  "geometry": {"coordinates":[-83.182654,42.284725],"type":"Point"}
}