{
  "type": "Feature",
  "properties": {
    "iso:country":"US",
    "sg:address":"2150 Lawnel Ave",
    "sg:city":"Muskegon",
    "sg:classifiers":[
        {
            "category":"Building & Trades",
            "subcategory":"Construction",
            "type":"Services"
        }
    ],
    "sg:phone":"+1 231 759 4175",
    "sg:postcode":"49441",
    "sg:province":"MI",
    "sg:tags":[
        "roofing",
        "contractor"
    ],
    "wof:name":"Accent Roofing",
    "wof:placetype":"venue"
},
  "geometry": {"coordinates":[-86.2975,43.19394],"type":"Point"}
}