{
  "type": "Feature",
  "properties": {
    "iso:country":"US",
    "sg:address":"132 W Chicago Blvd",
    "sg:city":"Tecumseh",
    "sg:classifiers":[
        {
            "category":"Professional",
            "subcategory":"Accounting & Tax Preparation",
            "type":"Services"
        }
    ],
    "sg:phone":"+1 517 423 0433",
    "sg:postcode":"49286",
    "sg:province":"MI",
    "sg:tags":[
        "billing"
    ],
    "wof:name":"D & B Billing Svc",
    "wof:placetype":"venue"
},
  "geometry": {"coordinates":[-83.94568099999999,42.003976],"type":"Point"}
}