{
  "type": "Feature",
  "properties": {
    "iso:country":"US",
    "sg:address":"3244 Charity Dr",
    "sg:city":"Sterling Heights",
    "sg:classifiers":[
        {
            "category":"Building & Trades",
            "subcategory":"Construction",
            "type":"Services"
        }
    ],
    "sg:phone":"+1 586 274 4201",
    "sg:postcode":"48310",
    "sg:province":"MI",
    "sg:tags":[
        "hanging",
        "contractor"
    ],
    "wof:name":"G&J Custom Painting",
    "wof:placetype":"venue"
},
  "geometry": {"coordinates":[-83.07923099999999,42.576364],"type":"Point"}
}