{
  "type": "Feature",
  "properties": {
    "iso:country":"US",
    "sg:address":"1430 Lake Nepessing Rd",
    "sg:city":"Lapeer",
    "sg:classifiers":[
        {
            "category":"Social Services",
            "subcategory":"Adult Care",
            "type":"Services"
        }
    ],
    "sg:phone":"+1 810 667 3010",
    "sg:postcode":"48446",
    "sg:province":"MI",
    "sg:tags":[
        "home",
        "group"
    ],
    "wof:name":"Lake Nepessing House",
    "wof:placetype":"venue"
},
  "geometry": {"coordinates":[-83.355885,43.015244],"type":"Point"}
}