{
  "type": "Feature",
  "properties": {
    "iso:country":"US",
    "sg:address":"112 Ward St",
    "sg:city":"Rose City",
    "sg:classifiers":[
        {
            "category":"Home & Garden",
            "subcategory":"Home Furnishings",
            "type":"Retail Goods"
        }
    ],
    "sg:phone":"+1 989 685 2515",
    "sg:postcode":"48654",
    "sg:province":"MI",
    "sg:tags":[
        "pottery"
    ],
    "wof:name":"Clay Lady",
    "wof:placetype":"venue"
},
  "geometry": {"coordinates":[-84.120712,44.421403],"type":"Point"}
}