{
  "type": "Feature",
  "properties": {
    "iso:country":"US",
    "sg:address":"15156 N Holly Rd",
    "sg:city":"Holly",
    "sg:classifiers":[
        {
            "category":"Banks & Credit Unions",
            "subcategory":"Bank",
            "type":"Services"
        }
    ],
    "sg:phone":"+1 248 634 9061",
    "sg:postcode":"48442",
    "sg:province":"MI",
    "sg:tags":[
        "state"
    ],
    "wof:name":"Metro N Fdral Cr Un Non Profit",
    "wof:placetype":"venue"
},
  "geometry": {"coordinates":[-83.628366,42.8111],"type":"Point"}
}