{
  "type": "Feature",
  "properties": {
    "iso:country":"US",
    "sg:address":"22625 Martin Rd",
    "sg:city":"Saint Clair Shores",
    "sg:classifiers":[
        {
            "category":"Manufacturing",
            "subcategory":"Printing",
            "type":"Manufacturing & Wholesale Goods"
        }
    ],
    "sg:phone":"+1 586 772 6316",
    "sg:postcode":"48081",
    "sg:province":"MI",
    "sg:tags":[
        "publishing"
    ],
    "wof:name":"Specially Made Publications",
    "wof:placetype":"venue"
},
  "geometry": {"coordinates":[-82.888232,42.502691],"type":"Point"}
}