{
  "type": "Feature",
  "properties": {
    "iso:country":"US",
    "sg:address":"14049 E 13 Mile Rd",
    "sg:city":"Warren",
    "sg:classifiers":[
        {
            "category":"Insurance",
            "subcategory":"Insurance Agent",
            "type":"Services"
        }
    ],
    "sg:phone":"+1 586 293 0750",
    "sg:postcode":"48088",
    "sg:province":"MI",
    "wof:name":"State Farm Insurance",
    "wof:placetype":"venue"
},
  "geometry": {"coordinates":[-82.98208099999999,42.522371],"type":"Point"}
}