{
  "type": "Feature",
  "properties": {
    "iso:country":"US",
    "sg:address":"3309 17th St",
    "sg:city":"Menominee",
    "sg:classifiers":[
        {
            "category":"Shopping",
            "subcategory":"Clothing, Apparel, & Fashions",
            "type":"Retail Goods"
        }
    ],
    "sg:phone":"+1 906 863 5797",
    "sg:postcode":"49858",
    "sg:province":"MI",
    "sg:tags":[
        "sporting"
    ],
    "wof:name":"Great Lakes Sports",
    "wof:placetype":"venue"
},
  "geometry": {"coordinates":[-87.622742,45.128888],"type":"Point"}
}