{
  "type": "Feature",
  "properties": {
    "iso:country":"US",
    "sg:address":"6541 Blue Star Hwy",
    "sg:city":"Saugatuck",
    "sg:classifiers":[
        {
            "category":"Travel",
            "subcategory":"Hotels & Motels",
            "type":"Entertainment"
        }
    ],
    "sg:phone":"+1 269 857 1039",
    "sg:postcode":"49453",
    "sg:province":"MI",
    "sg:tags":[
        "operation"
    ],
    "wof:name":"Hoopeninn Motel",
    "wof:placetype":"venue"
},
  "geometry": {"coordinates":[-86.182914,42.676889],"type":"Point"}
}