{
  "type": "Feature",
  "properties": {
    "iso:country":"US",
    "sg:address":"342 S Harvey St",
    "sg:city":"Plymouth",
    "sg:classifiers":[
        {
            "category":"Professional",
            "subcategory":"Lawyer & Legal Services",
            "type":"Services"
        }
    ],
    "sg:phone":"+1 734 207 3889",
    "sg:postcode":"48170",
    "sg:province":"MI",
    "wof:name":"Jameson John S ESQ",
    "wof:placetype":"venue"
},
  "geometry": {"coordinates":[-83.471497,42.370899],"type":"Point"}
}