{
  "type": "Feature",
  "properties": {
    "iso:country":"US",
    "sg:address":"503 Hyacinthe St",
    "sg:city":"Ecorse",
    "sg:classifiers":[
        {
            "category":"Education",
            "subcategory":"School",
            "type":"Public Place"
        }
    ],
    "sg:phone":"+1 313 382 1201",
    "sg:postcode":"48229",
    "sg:province":"MI",
    "sg:tags":[
        "high",
        "middle",
        "elementary"
    ],
    "wof:name":"Ecorse Public Schools",
    "wof:placetype":"venue"
},
  "geometry": {"coordinates":[-83.153704,42.25854],"type":"Point"}
}