{
  "type": "Feature",
  "properties": {
    "iso:country":"US",
    "sg:address":"6688 Bloomfield Ln",
    "sg:city":"West Bloomfield",
    "sg:classifiers":[
        {
            "category":"Restaurant",
            "type":"Food & Drink"
        }
    ],
    "sg:phone":"+1 248 855 4777",
    "sg:postcode":"48322",
    "sg:province":"MI",
    "wof:name":"Papa Romano's",
    "wof:placetype":"venue"
},
  "geometry": {"coordinates":[-83.332733,42.542262],"type":"Point"}
}