{
  "type": "Feature",
  "properties": {
    "iso:country":"US",
    "sg:address":"108 N Camburn St",
    "sg:city":"Stanton",
    "sg:classifiers":[
        {
            "category":"Personal",
            "type":"Services"
        }
    ],
    "sg:phone":"+1 989 831 9080",
    "sg:postcode":"48888",
    "sg:province":"MI",
    "sg:tags":[
        "consultant",
        "program",
        "health",
        "fitness"
    ],
    "wof:name":"Great Shapes Body Wraps",
    "wof:placetype":"venue"
},
  "geometry": {"coordinates":[-85.08144900000001,43.293642],"type":"Point"}
}