{
  "type": "Feature",
  "properties": {
    "iso:country":"US",
    "sg:address":"4885 Crooked Lake Rd",
    "sg:city":"Howell",
    "sg:classifiers":[
        {
            "category":"Retail",
            "subcategory":"Auto Repair",
            "type":"Services"
        }
    ],
    "sg:phone":"+1 517 552 3838",
    "sg:postcode":"48843",
    "sg:province":"MI",
    "sg:tags":[
        "shop",
        "supply",
        "car",
        "racing",
        "race",
        "owner",
        "speed"
    ],
    "wof:name":"Trp Racing",
    "wof:placetype":"venue"
},
  "geometry": {"coordinates":[-83.856185,42.556855],"type":"Point"}
}