{
  "type": "Feature",
  "properties": {
    "iso:country":"US",
    "sg:address":"5005 Cramer Hwy",
    "sg:city":"Hudson",
    "sg:classifiers":[
        {
            "category":"Retail",
            "subcategory":"Auto Repair",
            "type":"Services"
        }
    ],
    "sg:phone":"+1 517 448 7093",
    "sg:postcode":"49247",
    "sg:province":"MI",
    "sg:tags":[
        "automotive",
        "wrecker"
    ],
    "wof:name":"George's Towing",
    "wof:placetype":"venue"
},
  "geometry": {"coordinates":[-84.35471099999999,41.844109],"type":"Point"}
}