{
  "type": "Feature",
  "properties": {
    "iso:country":"US",
    "sg:address":"2075 Kenney Ave",
    "sg:city":"Warren",
    "sg:classifiers":[
        {
            "category":"Real Estate",
            "subcategory":"Architect",
            "type":"Services"
        }
    ],
    "sg:phone":"+1 586 754 7500",
    "sg:postcode":"48091",
    "sg:province":"MI",
    "sg:tags":[
        "estimate",
        "construction"
    ],
    "wof:name":"Greer Construction Inc",
    "wof:placetype":"venue"
},
  "geometry": {"coordinates":[-83.083634,42.477537],"type":"Point"}
}