{
  "type": "Feature",
  "properties": {
    "iso:country":"US",
    "sg:address":"101 5th St",
    "sg:city":"Calumet",
    "sg:classifiers":[
        {
            "category":"Shopping",
            "subcategory":"Gifts & Souvenirs",
            "type":"Retail Goods"
        }
    ],
    "sg:phone":"+1 906 337 4016",
    "sg:postcode":"49913",
    "sg:province":"MI",
    "sg:tags":[
        "shop"
    ],
    "wof:name":"Copper World",
    "wof:placetype":"venue"
},
  "geometry": {"coordinates":[-88.45262099999999,47.245294],"type":"Point"}
}