{
  "type": "Feature",
  "properties": {
    "iso:country":"US",
    "sg:address":"12331 James St",
    "sg:city":"Holland",
    "sg:classifiers":[
        {
            "category":"Communications",
            "type":"Services"
        }
    ],
    "sg:phone":"+1 616 396 9070",
    "sg:postcode":"49424",
    "sg:province":"MI",
    "wof:name":"Delta Communications Holland",
    "wof:placetype":"venue"
},
  "geometry": {"coordinates":[-86.087469,42.812151],"type":"Point"}
}