{
  "type": "Feature",
  "properties": {
    "iso:country":"US",
    "sg:address":"4983 Burt Rd",
    "sg:city":"Stockbridge",
    "sg:classifiers":[
        {
            "category":"Retail",
            "subcategory":"Veterinary Services",
            "type":"Services"
        }
    ],
    "sg:phone":"+1 517 851 8244",
    "sg:postcode":"49242",
    "sg:province":"MI",
    "sg:tags":[
        "veterinarian"
    ],
    "sg:website":"www.midwestabs.com",
    "wof:name":"Midwest Animal Blood Svc Inc",
    "wof:placetype":"venue"
},
  "geometry": {"coordinates":[-84.557339,41.767307],"type":"Point"}
}