{
  "type": "Feature",
  "properties": {
    "iso:country":"US",
    "sg:address":"437 W Lincoln Ave",
    "sg:city":"Ionia",
    "sg:classifiers":[
        {
            "category":"Wholesale",
            "subcategory":"Medical Equipment & Supplies",
            "type":"Manufacturing & Wholesale Goods"
        }
    ],
    "sg:phone":"+1 616 522 0515",
    "sg:postcode":"48846",
    "sg:province":"MI",
    "sg:tags":[
        "hospital"
    ],
    "wof:name":"Sparrow Regional Medical Supl",
    "wof:placetype":"venue"
},
  "geometry": {"coordinates":[-85.070325,42.987325],"type":"Point"}
}