{
  "type": "Feature",
  "properties": {
    "iso:country":"US",
    "sg:address":"211 N Main St",
    "sg:city":"Davison",
    "sg:classifiers":[
        {
            "category":"Home & Garden",
            "subcategory":"Building Materials",
            "type":"Retail Goods"
        }
    ],
    "sg:phone":"+1 810 654 9939",
    "sg:postcode":"48423",
    "sg:province":"MI",
    "sg:tags":[
        "windows"
    ],
    "wof:name":"Window Decor",
    "wof:placetype":"venue"
},
  "geometry": {"coordinates":[-83.51684299999999,43.031711],"type":"Point"}
}