{
  "type": "Feature",
  "properties": {
    "iso:country":"US",
    "sg:address":"2105 Huizen Ave SW",
    "sg:city":"Grand Rapids",
    "sg:classifiers":[
        {
            "category":"Professional",
            "subcategory":"Business Services",
            "type":"Services"
        }
    ],
    "sg:phone":"+1 616 243 1306",
    "sg:postcode":"49509",
    "sg:province":"MI",
    "wof:name":"Rvk Enterprises Inc",
    "wof:placetype":"venue"
},
  "geometry": {"coordinates":[-85.69176899999999,42.92682],"type":"Point"}
}