{
  "type": "Feature",
  "properties": {
    "iso:country":"US",
    "sg:address":"4526 Kehoe Rd",
    "sg:city":"Clinton",
    "sg:classifiers":[
        {
            "category":"Building & Trades",
            "subcategory":"Construction",
            "type":"Services"
        }
    ],
    "sg:phone":"+1 517 456 4701",
    "sg:postcode":"49236",
    "sg:province":"MI",
    "sg:tags":[
        "woodworker"
    ],
    "wof:name":"Bob-Craft Wood Specialties",
    "wof:placetype":"venue"
},
  "geometry": {"coordinates":[-83.93974799999999,42.072764],"type":"Point"}
}