{
  "type": "Feature",
  "properties": {
    "iso:country":"US",
    "sg:address":"4431 US Hwy 23",
    "sg:city":"Oscoda",
    "sg:classifiers":[
        {
            "category":"Retail",
            "subcategory":"Repair Shop",
            "type":"Services"
        }
    ],
    "sg:phone":"+1 989 739 7911",
    "sg:postcode":"48750",
    "sg:province":"MI",
    "sg:tags":[
        "television",
        "radio"
    ],
    "wof:name":"Rup's TV Nook",
    "wof:placetype":"venue"
},
  "geometry": {"coordinates":[-83.32478399999999,44.407513],"type":"Point"}
}