{
  "type": "Feature",
  "properties": {
    "iso:country":"US",
    "sg:address":"2922 W Airport Rd",
    "sg:city":"Hastings",
    "sg:classifiers":[
        {
            "category":"Manufacturing",
            "subcategory":"Electronics",
            "type":"Manufacturing & Wholesale Goods"
        }
    ],
    "sg:phone":"+1 269 948 9580",
    "sg:postcode":"49058",
    "sg:province":"MI",
    "sg:tags":[
        "electronic",
        "component",
        "mfg"
    ],
    "wof:name":"Gemtec",
    "wof:placetype":"venue"
},
  "geometry": {"coordinates":[-85.345191,42.667625],"type":"Point"}
}