{
  "type": "Feature",
  "properties": {
    "iso:country":"US",
    "sg:address":"251 N Main St",
    "sg:city":"Plymouth",
    "sg:classifiers":[
        {
            "category":"Arena",
            "subcategory":"Sports Club",
            "type":"Entertainment"
        }
    ],
    "sg:phone":"+1 734 459 4183",
    "sg:postcode":"48170",
    "sg:province":"MI",
    "sg:tags":[
        "martial art"
    ],
    "sg:website":"www.midwesttaekwondo.com",
    "wof:name":"Midwest Tae Kwon DO",
    "wof:placetype":"venue"
},
  "geometry": {"coordinates":[-83.46473400000001,42.374575],"type":"Point"}
}