{
  "type": "Feature",
  "properties": {
    "iso:country":"US",
    "sg:address":"1274 Valley Dr",
    "sg:city":"Traverse City",
    "sg:classifiers":[
        {
            "category":"Social Services",
            "subcategory":"Child Care",
            "type":"Services"
        }
    ],
    "sg:phone":"+1 231 941 5308",
    "sg:postcode":"49684",
    "sg:province":"MI",
    "sg:tags":[
        "day"
    ],
    "wof:name":"Playfull Bear Daycare",
    "wof:placetype":"venue"
},
  "geometry": {"coordinates":[-85.681912,44.705045],"type":"Point"}
}