{
  "type": "Feature",
  "properties": {
    "iso:country":"US",
    "sg:address":"28438 Joy Rd",
    "sg:city":"Livonia",
    "sg:classifiers":[
        {
            "category":"Retail",
            "subcategory":"Self-service Laundry",
            "type":"Services"
        }
    ],
    "sg:phone":"+1 734 421 2790",
    "sg:postcode":"48150",
    "sg:province":"MI",
    "sg:tags":[
        "coin"
    ],
    "wof:name":"Livonia Collectibles",
    "wof:placetype":"venue"
},
  "geometry": {"coordinates":[-83.32194800000001,42.355061],"type":"Point"}
}