{
  "type": "Feature",
  "properties": {
    "iso:country":"US",
    "sg:address":"23845 W Warren St",
    "sg:city":"Dearborn Heights",
    "sg:classifiers":[
        {
            "category":"Bars & Pubs",
            "subcategory":"Nightclub",
            "type":"Food & Drink"
        }
    ],
    "sg:phone":"+1 313 274 6005",
    "sg:postcode":"48127",
    "sg:province":"MI",
    "sg:tags":[
        "nightlife"
    ],
    "wof:name":"Buck's Place",
    "wof:placetype":"venue"
},
  "geometry": {"coordinates":[-83.272301,42.341301],"type":"Point"}
}