{
  "type": "Feature",
  "properties": {
    "iso:country":"US",
    "sg:address":"75 S Elk St",
    "sg:city":"Sandusky",
    "sg:classifiers":[
        {
            "category":"Professional",
            "subcategory":"Lawyer & Legal Services",
            "type":"Services"
        }
    ],
    "sg:phone":"+1 810 648 0800",
    "sg:postcode":"48471",
    "sg:province":"MI",
    "sg:tags":[
        "attorney"
    ],
    "wof:name":"Smith & Sawyer Plc",
    "wof:placetype":"venue"
},
  "geometry": {"coordinates":[-82.829797,43.419956],"type":"Point"}
}