{
  "type": "Feature",
  "properties": {
    "iso:country":"US",
    "sg:address":"1024 Burton St SW",
    "sg:city":"Wyoming",
    "sg:classifiers":[
        {
            "category":"Restaurant",
            "type":"Food & Drink"
        }
    ],
    "sg:phone":"+1 616 246 6180",
    "sg:postcode":"49509",
    "sg:province":"MI",
    "wof:name":"Tacos El Ganadero",
    "wof:placetype":"venue"
},
  "geometry": {"coordinates":[-85.692167,42.927902],"type":"Point"}
}