{
  "type": "Feature",
  "properties": {
    "iso:country":"US",
    "sg:address":"29697 M 152",
    "sg:city":"Dowagiac",
    "sg:classifiers":[
        {
            "category":"Building & Trades",
            "subcategory":"Cleaning & Sanitation",
            "type":"Services"
        }
    ],
    "sg:phone":"+1 269 424 6506",
    "sg:postcode":"49047",
    "sg:province":"MI",
    "sg:tags":[
        "maintenance"
    ],
    "wof:name":"R&R Maintenance",
    "wof:placetype":"venue"
},
  "geometry": {"coordinates":[-86.129255,42.056159],"type":"Point"}
}