{
  "type": "Feature",
  "properties": {
    "iso:country":"US",
    "sg:address":"3785 Plainfield Ave NE",
    "sg:city":"Grand Rapids",
    "sg:classifiers":[
        {
            "category":"Banks & Credit Unions",
            "subcategory":"Bank",
            "type":"Services"
        }
    ],
    "sg:phone":"+1 616 771 5793",
    "sg:postcode":"49525",
    "sg:province":"MI",
    "sg:tags":[
        "state",
        "comm"
    ],
    "sg:website":"www.53.com",
    "wof:name":"Fifth Third Bank",
    "wof:placetype":"venue"
},
  "geometry": {"coordinates":[-85.625798,43.032182],"type":"Point"}
}