{
  "type": "Feature",
  "properties": {
    "iso:country":"US",
    "sg:address":"647 W Sebewaing St",
    "sg:city":"Sebewaing",
    "sg:classifiers":[
        {
            "category":"Travel",
            "subcategory":"Hotels & Motels",
            "type":"Entertainment"
        }
    ],
    "sg:phone":"+1 989 883 3320",
    "sg:postcode":"48759",
    "sg:province":"MI",
    "sg:tags":[
        "operation"
    ],
    "wof:name":"Airport Motel",
    "wof:placetype":"venue"
},
  "geometry": {"coordinates":[-83.459352,43.732976],"type":"Point"}
}