{
  "type": "Feature",
  "properties": {
    "iso:country":"US",
    "sg:address":"2603 W Wackerly St",
    "sg:city":"Midland",
    "sg:classifiers":[
        {
            "category":"Social Services",
            "subcategory":"Adult Care",
            "type":"Services"
        }
    ],
    "sg:phone":"+1 989 631 1820",
    "sg:postcode":"48640",
    "sg:province":"MI",
    "sg:tags":[
        "residential"
    ],
    "wof:name":"Inter-Disciplinary Advantage",
    "wof:placetype":"venue"
},
  "geometry": {"coordinates":[-84.25613199999999,43.654853],"type":"Point"}
}