{
  "type": "Feature",
  "properties": {
    "iso:country":"US",
    "sg:address":"16100 Fort St",
    "sg:city":"Southgate",
    "sg:classifiers":[
        {
            "category":"Autos & Motor Vehicles",
            "subcategory":"Automobile Sales",
            "type":"Retail Goods"
        }
    ],
    "sg:phone":"+1 734 282 1313",
    "sg:postcode":"48195",
    "sg:province":"MI",
    "sg:tags":[
        "car"
    ],
    "wof:name":"Southgate Mitsubishi",
    "wof:placetype":"venue"
},
  "geometry": {"coordinates":[-83.18049600000001,42.191601],"type":"Point"}
}