{
  "type": "Feature",
  "properties": {
    "iso:country":"US",
    "sg:address":"207 E Front St",
    "sg:city":"Traverse City",
    "sg:classifiers":[
        {
            "category":"Shopping",
            "subcategory":"Gifts & Souvenirs",
            "type":"Retail Goods"
        }
    ],
    "sg:phone":"+1 231 935 4470",
    "sg:postcode":"49684",
    "sg:province":"MI",
    "wof:name":"Leaping Lizard",
    "wof:placetype":"venue"
},
  "geometry": {"coordinates":[-85.620891,44.764137],"type":"Point"}
}