{
  "type": "Feature",
  "properties": {
    "iso:country":"US",
    "sg:address":"620 N Port Crescent St",
    "sg:city":"Bad Axe",
    "sg:classifiers":[
        {
            "category":"Personal",
            "subcategory":"Tanning Parlor",
            "type":"Services"
        }
    ],
    "sg:phone":"+1 989 269 7545",
    "sg:postcode":"48413",
    "sg:province":"MI",
    "sg:tags":[
        "salon"
    ],
    "wof:name":"Hot Spot Tanning Salon",
    "wof:placetype":"venue"
},
  "geometry": {"coordinates":[-83.000596,43.808126],"type":"Point"}
}