{
  "type": "Feature",
  "properties": {
    "iso:country":"US",
    "sg:address":"6078 S Saginaw Rd",
    "sg:city":"Grand Blanc",
    "sg:classifiers":[
        {
            "category":"Home & Garden",
            "subcategory":"Household Appliances",
            "type":"Retail Goods"
        },
        {
            "category":"Home & Garden",
            "subcategory":"Carpets & Floor Coverings",
            "type":"Retail Goods"
        }
    ],
    "sg:phone":"+1 810 238 5160",
    "sg:postcode":"48439",
    "sg:province":"MI",
    "sg:tags":[
        "repair",
        "mattress"
    ],
    "wof:name":"Carl's Appliance & Mattresses",
    "wof:placetype":"venue"
},
  "geometry": {"coordinates":[-83.649101,42.943199],"type":"Point"}
}