{
  "type": "Feature",
  "properties": {
    "iso:country":"US",
    "sg:address":"24155 Groesbeck Hwy",
    "sg:city":"Warren",
    "sg:classifiers":[
        {
            "category":"Wholesale",
            "subcategory":"Hardware",
            "type":"Manufacturing & Wholesale Goods"
        }
    ],
    "sg:phone":"+1 586 776 5138",
    "sg:postcode":"48089",
    "sg:province":"MI",
    "sg:tags":[
        "plumbing",
        "fixture",
        "supply"
    ],
    "wof:name":"Art's Plumbing Supply Co",
    "wof:placetype":"venue"
},
  "geometry": {"coordinates":[-82.981179,42.477731],"type":"Point"}
}