{
  "type": "Feature",
  "properties": {
    "iso:country":"US",
    "sg:address":"15479 S Telegraph Rd",
    "sg:city":"Monroe",
    "sg:classifiers":[
        {
            "category":"Professional",
            "subcategory":"Management & Consulting",
            "type":"Services"
        }
    ],
    "sg:phone":"+1 734 457 9131",
    "sg:postcode":"48161",
    "sg:province":"MI",
    "sg:tags":[
        "consultant",
        "training"
    ],
    "wof:name":"Frg Corp",
    "wof:placetype":"venue"
},
  "geometry": {"coordinates":[-83.42677500000001,41.90307],"type":"Point"}
}