{
  "type": "Feature",
  "properties": {
    "iso:country":"US",
    "sg:address":"23300 Greenfield Rd",
    "sg:city":"Oak Park",
    "sg:classifiers":[
        {
            "category":"Banks & Credit Unions",
            "subcategory":"Financial Services",
            "type":"Services"
        }
    ],
    "sg:phone":"+1 248 967 3500",
    "sg:postcode":"48237",
    "sg:province":"MI",
    "sg:tags":[
        "broker",
        "mortgage"
    ],
    "wof:name":"Savannah Mortgage",
    "wof:placetype":"venue"
},
  "geometry": {"coordinates":[-83.201103,42.4613],"type":"Point"}
}