{
  "type": "Feature",
  "properties": {
    "iso:country":"US",
    "sg:address":"1813 Hosler St",
    "sg:city":"Flint",
    "sg:classifiers":[
        {
            "category":"Real Estate",
            "subcategory":"Real Estate Agent",
            "type":"Services"
        }
    ],
    "sg:phone":"+1 810 742 4800",
    "sg:postcode":"48503",
    "sg:province":"MI",
    "wof:name":"Roe-Vic & Assoc",
    "wof:placetype":"venue"
},
  "geometry": {"coordinates":[-83.645223,43.007844],"type":"Point"}
}