{
  "type": "Feature",
  "properties": {
    "iso:country":"US",
    "sg:address":"1031 N Pine River St",
    "sg:city":"Ithaca",
    "sg:classifiers":[
        {
            "category":"Health Services",
            "subcategory":"Health Practitioner",
            "type":"Services"
        }
    ],
    "sg:phone":"+1 989 875 4937",
    "sg:postcode":"48847",
    "sg:province":"MI",
    "wof:name":"Transcription Worx Inc",
    "wof:placetype":"venue"
},
  "geometry": {"coordinates":[-84.607608,43.301975],"type":"Point"}
}