{
  "type": "Feature",
  "properties": {
    "iso:country":"US",
    "sg:address":"1010 N Chipman St",
    "sg:city":"Owosso",
    "sg:classifiers":[
        {
            "category":"Building & Trades",
            "subcategory":"Construction",
            "type":"Services"
        }
    ],
    "sg:phone":"+1 989 725 8497",
    "sg:postcode":"48867",
    "sg:province":"MI",
    "sg:tags":[
        "roofing",
        "contractor"
    ],
    "wof:name":"Farr's Roofing",
    "wof:placetype":"venue"
},
  "geometry": {"coordinates":[-84.186322,43.007998],"type":"Point"}
}