{
  "type": "Feature",
  "properties": {
    "iso:country":"US",
    "sg:address":"46325 W 10 Mile Rd",
    "sg:city":"Novi",
    "sg:classifiers":[
        {
            "category":"Organizations",
            "subcategory":"Religious Organization",
            "type":"Services"
        }
    ],
    "sg:phone":"+1 248 347 7778",
    "sg:postcode":"48374",
    "sg:province":"MI",
    "sg:website":"www.stjamesofnovi.4lpi.com",
    "wof:name":"St James Catholic Church",
    "wof:placetype":"venue"
},
  "geometry": {"coordinates":[-83.50396000000001,42.46569],"type":"Point"}
}