{
  "type": "Feature",
  "properties": {
    "iso:country":"US",
    "sg:address":"4450 Oakman Blvd",
    "sg:city":"Detroit",
    "sg:classifiers":[
        {
            "category":"Home & Garden",
            "subcategory":"Carpets & Floor Coverings",
            "type":"Retail Goods"
        }
    ],
    "sg:phone":"+1 313 931 5230",
    "sg:postcode":"48204",
    "sg:province":"MI",
    "sg:tags":[
        "flooring"
    ],
    "wof:name":"Spicer Floor Sanding & Finishing Inc",
    "wof:placetype":"venue"
},
  "geometry": {"coordinates":[-83.152247,42.370289],"type":"Point"}
}