{
  "type": "Feature",
  "properties": {
    "iso:country":"US",
    "sg:address":"15841 State St",
    "sg:city":"Hillman",
    "sg:classifiers":[
        {
            "category":"Social Services",
            "type":"Services"
        }
    ],
    "sg:phone":"+1 989 742 3453",
    "sg:postcode":"49746",
    "sg:province":"MI",
    "sg:tags":[
        "intermediate",
        "care",
        "facility"
    ],
    "wof:name":"Orchard View Ais",
    "wof:placetype":"venue"
},
  "geometry": {"coordinates":[-83.90076500000001,45.071149],"type":"Point"}
}