{
  "type": "Feature",
  "properties": {
    "iso:country":"US",
    "sg:address":"739 Hawthorne Rd",
    "sg:city":"Twin Lake",
    "sg:classifiers":[
        {
            "category":"Building & Trades",
            "subcategory":"Construction",
            "type":"Services"
        }
    ],
    "sg:phone":"+1 231 894 2781",
    "sg:postcode":"49457",
    "sg:province":"MI",
    "sg:tags":[
        "nonresidential"
    ],
    "wof:name":"Building By Bob",
    "wof:placetype":"venue"
},
  "geometry": {"coordinates":[-86.258639,43.374528],"type":"Point"}
}