{
  "type": "Feature",
  "properties": {
    "iso:country":"US",
    "sg:address":"12803 E Michigan Ave",
    "sg:city":"Clinton",
    "sg:classifiers":[
        {
            "category":"Museum",
            "type":"Entertainment"
        }
    ],
    "sg:phone":"+1 517 456 8800",
    "sg:postcode":"49236",
    "sg:province":"MI",
    "sg:tags":[
        "gallery"
    ],
    "wof:name":"Wings of Love",
    "wof:placetype":"venue"
},
  "geometry": {"coordinates":[-83.905874,42.0972],"type":"Point"}
}