{
  "type": "Feature",
  "properties": {
    "iso:country":"US",
    "sg:address":"22125 Studio St",
    "sg:city":"Taylor",
    "sg:classifiers":[
        {
            "category":"Building & Trades",
            "subcategory":"Construction",
            "type":"Services"
        }
    ],
    "sg:phone":"+1 313 291 2357",
    "sg:postcode":"48180",
    "sg:province":"MI",
    "sg:tags":[
        "house"
    ],
    "wof:name":"Lockwoods Home Improvements",
    "wof:placetype":"venue"
},
  "geometry": {"coordinates":[-83.25385,42.253088],"type":"Point"}
}