{
  "type": "Feature",
  "properties": {
    "iso:country":"US",
    "sg:address":"8920 Victor Ave",
    "sg:city":"Jenison",
    "sg:classifiers":[
        {
            "category":"Building & Trades",
            "subcategory":"Construction",
            "type":"Services"
        }
    ],
    "sg:phone":"+1 616 457 4451",
    "sg:postcode":"49428",
    "sg:province":"MI",
    "sg:tags":[
        "contractor"
    ],
    "wof:name":"A & W Installations",
    "wof:placetype":"venue"
},
  "geometry": {"coordinates":[-85.83283,42.931388],"type":"Point"}
}