{
  "type": "Feature",
  "properties": {
    "iso:country":"US",
    "sg:address":"3415 E Seymour Lake Rd",
    "sg:city":"Ortonville",
    "sg:classifiers":[
        {
            "category":"Manufacturing",
            "subcategory":"Tools & Machinery",
            "type":"Manufacturing & Wholesale Goods"
        }
    ],
    "sg:phone":"+1 248 628 3458",
    "sg:postcode":"48462",
    "sg:province":"MI",
    "sg:tags":[
        "woodworking",
        "mfg"
    ],
    "wof:name":"Classic Wood Works",
    "wof:placetype":"venue"
},
  "geometry": {"coordinates":[-83.38891599999999,42.808465],"type":"Point"}
}