{
  "type": "Feature",
  "properties": {
    "iso:country":"US",
    "sg:address":"32732 W 8 Mile Rd",
    "sg:city":"Farmington",
    "sg:classifiers":[
        {
            "category":"Home & Garden",
            "subcategory":"Furniture",
            "type":"Retail Goods"
        }
    ],
    "sg:phone":"+1 248 473 0909",
    "sg:postcode":"48336",
    "sg:province":"MI",
    "sg:tags":[
        "cabinet"
    ],
    "wof:name":"Custom Cabinets Ricks",
    "wof:placetype":"venue"
},
  "geometry": {"coordinates":[-83.372589,42.440712],"type":"Point"}
}