{
  "type": "Feature",
  "properties": {
    "iso:country":"US",
    "sg:address":"5051 S Edon Rd",
    "sg:city":"Reading",
    "sg:classifiers":[
        {
            "category":"Food & Beverages",
            "subcategory":"Groceries & Convenience Stores",
            "type":"Retail Goods"
        }
    ],
    "sg:phone":"+1 517 283 3191",
    "sg:postcode":"49274",
    "sg:province":"MI",
    "sg:tags":[
        "grocer"
    ],
    "wof:name":"Baker's Acres Country Store",
    "wof:placetype":"venue"
},
  "geometry": {"coordinates":[-84.747855,41.853792],"type":"Point"}
}