{
  "type": "Feature",
  "properties": {
    "iso:country":"US",
    "sg:address":"1201 Washington Ave",
    "sg:city":"Bay City",
    "sg:classifiers":[
        {
            "category":"Organizations",
            "subcategory":"Community Association",
            "type":"Services"
        }
    ],
    "sg:phone":"+1 989 892 4581",
    "sg:postcode":"48708",
    "sg:province":"MI",
    "sg:tags":[
        "club"
    ],
    "wof:name":"Empire Club",
    "wof:placetype":"venue"
},
  "geometry": {"coordinates":[-83.88706999999999,43.603023],"type":"Point"}
}