{
  "type": "Feature",
  "properties": {
    "iso:country":"US",
    "sg:address":"644 W Garfield Ave",
    "sg:city":"Hazel Park",
    "sg:classifiers":[
        {
            "category":"Social Services",
            "type":"Services"
        }
    ],
    "sg:phone":"+1 248 548 6291",
    "sg:postcode":"48030",
    "sg:province":"MI",
    "sg:tags":[
        "agency",
        "adoption"
    ],
    "wof:name":"Adoption Identity Movement",
    "wof:placetype":"venue"
},
  "geometry": {"coordinates":[-83.111239,42.471641],"type":"Point"}
}