{
  "type": "Feature",
  "properties": {
    "iso:country":"US",
    "sg:address":"2290 Auburn Rd",
    "sg:city":"Auburn Hills",
    "sg:classifiers":[
        {
            "category":"Retail",
            "subcategory":"Auto Repair",
            "type":"Services"
        }
    ],
    "sg:phone":"+1 248 338 3700",
    "sg:postcode":"48326",
    "sg:province":"MI",
    "sg:tags":[
        "automotive"
    ],
    "wof:name":"General Towing & Auto Repair",
    "wof:placetype":"venue"
},
  "geometry": {"coordinates":[-83.24429600000001,42.635272],"type":"Point"}
}