{
  "type": "Feature",
  "properties": {
    "iso:country":"US",
    "sg:address":"284 Norlyn Dr",
    "sg:city":"Howell",
    "sg:classifiers":[
        {
            "category":"Professional",
            "subcategory":"Engineering",
            "type":"Services"
        }
    ],
    "sg:phone":"+1 810 225 0618",
    "sg:postcode":"48843",
    "sg:province":"MI",
    "sg:tags":[
        "plant",
        "assembly",
        "automation"
    ],
    "wof:name":"Extreme Automation Inc",
    "wof:placetype":"venue"
},
  "geometry": {"coordinates":[-83.800995,42.607421],"type":"Point"}
}