{
  "type": "Feature",
  "properties": {
    "iso:country":"US",
    "sg:address":"1700 Waterman St",
    "sg:city":"Detroit",
    "sg:classifiers":[
        {
            "category":"Real Estate",
            "subcategory":"Real Estate Agent",
            "type":"Services"
        }
    ],
    "sg:phone":"+1 313 841 2595",
    "sg:postcode":"48209",
    "sg:province":"MI",
    "sg:tags":[
        "manager"
    ],
    "wof:name":"Southwest Non Prfit Hsing Corp",
    "wof:placetype":"venue"
},
  "geometry": {"coordinates":[-83.113742,42.311927],"type":"Point"}
}