{
  "type": "Feature",
  "properties": {
    "iso:country":"US",
    "sg:address":"16822 Warwick St",
    "sg:city":"Detroit",
    "sg:classifiers":[
        {
            "category":"Health Services",
            "subcategory":"Doctor",
            "type":"Services"
        }
    ],
    "sg:phone":"+1 313 255 7947",
    "sg:postcode":"48219",
    "sg:province":"MI",
    "sg:tags":[
        "medical"
    ],
    "wof:name":"Jones Raymond MD",
    "wof:placetype":"venue"
},
  "geometry": {"coordinates":[-83.229178,42.41522],"type":"Point"}
}