{
  "type": "Feature",
  "properties": {
    "iso:country":"US",
    "sg:address":"21500 Northwestern Hwy Ste 464",
    "sg:city":"Southfield",
    "sg:classifiers":[
        {
            "category":"Shopping",
            "subcategory":"Bicycles & Sporting Goods",
            "type":"Retail Goods"
        }
    ],
    "sg:phone":"+1 248 443 2944",
    "sg:postcode":"48075",
    "sg:province":"MI",
    "sg:website":"www.champssports.com",
    "wof:name":"Champs Sports",
    "wof:placetype":"venue"
},
  "geometry": {"coordinates":[-83.207703,42.449501],"type":"Point"}
}