{
  "type": "Feature",
  "properties": {
    "iso:country":"US",
    "sg:address":"8300 Richardson Rd",
    "sg:city":"Commerce Township",
    "sg:classifiers":[
        {
            "category":"Restaurant",
            "type":"Food & Drink"
        }
    ],
    "sg:menulink":"http://www.allmenus.com/mi/commerce/186112-mcdonalds/menu/",
    "sg:postcode":"48382",
    "sg:province":"MI",
    "sg:tags":[
        "burger",
        "american"
    ],
    "wof:name":"McDonald's",
    "wof:placetype":"venue"
},
  "geometry": {"coordinates":[-83.446668,42.578367],"type":"Point"}
}