{
  "type": "Feature",
  "properties": {
    "iso:country":"US",
    "sg:address":"138 S Washington St",
    "sg:city":"Charlotte",
    "sg:classifiers":[
        {
            "category":"Health Services",
            "subcategory":"Doctor",
            "type":"Services"
        }
    ],
    "sg:phone":"+1 517 541 1000",
    "sg:postcode":"48813",
    "sg:province":"MI",
    "sg:tags":[
        "osteopathic"
    ],
    "wof:name":"R Kwapiszewski Do",
    "wof:placetype":"venue"
},
  "geometry": {"coordinates":[-84.834693,42.563346],"type":"Point"}
}