{
  "type": "Feature",
  "properties": {
    "iso:country":"US",
    "sg:address":"2991 Military St",
    "sg:city":"Port Huron",
    "sg:classifiers":[
        {
            "category":"Professional",
            "subcategory":"Computer Services",
            "type":"Services"
        }
    ],
    "sg:phone":"+1 810 985 9697",
    "sg:postcode":"48060",
    "sg:province":"MI",
    "sg:tags":[
        "website",
        "design",
        "hosting",
        "internet"
    ],
    "wof:name":"Robin Frontiero LLC",
    "wof:placetype":"venue"
},
  "geometry": {"coordinates":[-82.437861,42.951293],"type":"Point"}
}