{
  "type": "Feature",
  "properties": {
    "iso:country":"US",
    "sg:address":"17700 Telegraph Rd",
    "sg:city":"Romulus",
    "sg:classifiers":[
        {
            "category":"Autos & Motor Vehicles",
            "subcategory":"Motorcycle Sales",
            "type":"Retail Goods"
        }
    ],
    "sg:phone":"+1 734 229 1009",
    "sg:postcode":"48174",
    "sg:province":"MI",
    "wof:name":"Winners Power Store",
    "wof:placetype":"venue"
},
  "geometry": {"coordinates":[-83.267132,42.176583],"type":"Point"}
}