{
  "type": "Feature",
  "properties": {
    "iso:country":"US",
    "sg:address":"20090 Livernois Ave",
    "sg:city":"Detroit",
    "sg:classifiers":[
        {
            "category":"Shopping",
            "subcategory":"Shoes",
            "type":"Retail Goods"
        }
    ],
    "sg:phone":"+1 313 345 9550",
    "sg:postcode":"48221",
    "sg:province":"MI",
    "sg:tags":[
        "store"
    ],
    "wof:name":"Bestwear Store Inc",
    "wof:placetype":"venue"
},
  "geometry": {"coordinates":[-83.141622,42.441533],"type":"Point"}
}