{
  "type": "Feature",
  "properties": {
    "iso:country":"US",
    "sg:address":"1200 E 7 Mile Rd",
    "sg:city":"Detroit",
    "sg:classifiers":[
        {
            "category":"Food & Beverages",
            "subcategory":"Groceries & Convenience Stores",
            "type":"Retail Goods"
        }
    ],
    "sg:phone":"+1 313 366 9637",
    "sg:postcode":"48203",
    "sg:province":"MI",
    "wof:name":"Balasan Mini-Mart Inc",
    "wof:placetype":"venue"
},
  "geometry": {"coordinates":[-83.091413,42.432463],"type":"Point"}
}