{
  "type": "Feature",
  "properties": {
    "iso:country":"US",
    "sg:address":"4985 Crystal Rd",
    "sg:city":"Carson City",
    "sg:classifiers":[
        {
            "category":"Professional",
            "subcategory":"Computer Services",
            "type":"Services"
        }
    ],
    "sg:phone":"+1 989 235 5204",
    "sg:postcode":"48811",
    "sg:province":"MI",
    "sg:tags":[
        "website",
        "design"
    ],
    "wof:name":"Custom Touch Web Design",
    "wof:placetype":"venue"
},
  "geometry": {"coordinates":[-84.915387,43.220862],"type":"Point"}
}