{
  "type": "Feature",
  "properties": {
    "iso:country":"US",
    "sg:address":"15621 Mason St",
    "sg:city":"Union",
    "sg:classifiers":[
        {
            "category":"Utilities",
            "subcategory":"Refuse",
            "type":"Services"
        }
    ],
    "sg:phone":"+1 269 641 7502",
    "sg:postcode":"49130",
    "sg:province":"MI",
    "sg:tags":[
        "garbage",
        "collection"
    ],
    "wof:name":"American Waste Systems",
    "wof:placetype":"venue"
},
  "geometry": {"coordinates":[-85.87298800000001,41.787515],"type":"Point"}
}