{
  "type": "Feature",
  "properties": {
    "iso:country":"US",
    "sg:address":"410 Rose St",
    "sg:city":"Petoskey",
    "sg:classifiers":[
        {
            "category":"Shopping",
            "subcategory":"Used Merchandise",
            "type":"Retail Goods"
        }
    ],
    "sg:phone":"+1 231 347 9672",
    "sg:postcode":"49770",
    "sg:province":"MI",
    "sg:tags":[
        "antique"
    ],
    "wof:name":"Longton Hall Antiques",
    "wof:placetype":"venue"
},
  "geometry": {"coordinates":[-84.954003,45.376776],"type":"Point"}
}