{
  "type": "Feature",
  "properties": {
    "iso:country":"US",
    "sg:address":"2241 Hilton Rd",
    "sg:city":"Ferndale",
    "sg:classifiers":[
        {
            "category":"Professional",
            "subcategory":"Employment Agencies",
            "type":"Services"
        }
    ],
    "sg:phone":"+1 248 544 6477",
    "sg:postcode":"48220",
    "sg:province":"MI",
    "wof:name":"Resource Group the",
    "wof:placetype":"venue"
},
  "geometry": {"coordinates":[-83.12342099999999,42.464646],"type":"Point"}
}