{
  "type": "Feature",
  "properties": {
    "iso:country":"US",
    "sg:address":"37 Ward St",
    "sg:city":"Croswell",
    "sg:classifiers":[
        {
            "category":"Retail",
            "subcategory":"Self-service Laundry",
            "type":"Services"
        }
    ],
    "sg:phone":"+1 810 679 4220",
    "sg:postcode":"48422",
    "sg:province":"MI",
    "sg:tags":[
        "coin"
    ],
    "wof:name":"Cros-Lex Laundromat",
    "wof:placetype":"venue"
},
  "geometry": {"coordinates":[-82.61775799999999,43.273672],"type":"Point"}
}