{
  "type": "Feature",
  "properties": {
    "iso:country":"US",
    "sg:address":"1341 Lakeshore Dr",
    "sg:city":"Lake City",
    "sg:classifiers":[
        {
            "category":"Travel",
            "subcategory":"Hotels & Motels",
            "type":"Entertainment"
        }
    ],
    "sg:phone":"+1 231 839 2075",
    "sg:postcode":"49651",
    "sg:province":"MI",
    "wof:name":"Northcrest Motel",
    "wof:placetype":"venue"
},
  "geometry": {"coordinates":[-85.21289400000001,44.317444],"type":"Point"}
}