{
  "type": "Feature",
  "properties": {
    "iso:country":"US",
    "sg:address":"12802 Artesian St",
    "sg:city":"Detroit",
    "sg:classifiers":[
        {
            "category":"Professional",
            "subcategory":"Employment Agencies",
            "type":"Services"
        }
    ],
    "sg:phone":"+1 313 838 9205",
    "sg:postcode":"48223",
    "sg:province":"MI",
    "wof:name":"Select Staffing",
    "wof:placetype":"venue"
},
  "geometry": {"coordinates":[-83.226765,42.381849],"type":"Point"}
}