{
  "type": "Feature",
  "properties": {
    "iso:country":"US",
    "sg:address":"4291 S Lapeer Rd",
    "sg:city":"Lake Orion",
    "sg:classifiers":[
        {
            "category":"Restaurant",
            "type":"Food & Drink"
        }
    ],
    "sg:menulink":"http://www.allmenus.com/mi/orion/9574-palazzo-di-bocce/menu/",
    "sg:phone":"+1 248 371 9987",
    "sg:postcode":"48359",
    "sg:province":"MI",
    "sg:tags":[
        "italian"
    ],
    "wof:name":"Palazzo di Bocce",
    "wof:placetype":"venue"
},
  "geometry": {"coordinates":[-83.24256200000001,42.718943],"type":"Point"}
}