{
  "type": "Feature",
  "properties": {
    "iso:country":"US",
    "sg:address":"3015 Nichols Rd",
    "sg:city":"Kalamazoo",
    "sg:classifiers":[
        {
            "category":"Organizations",
            "subcategory":"Religious Organization",
            "type":"Services"
        }
    ],
    "sg:phone":"+1 269 344 7128",
    "sg:postcode":"49004",
    "sg:province":"MI",
    "sg:tags":[
        "church"
    ],
    "wof:name":"Second Christian Reform Church",
    "wof:placetype":"venue"
},
  "geometry": {"coordinates":[-85.628889,42.323375],"type":"Point"}
}