{
  "type": "Feature",
  "properties": {
    "iso:country":"US",
    "sg:address":"18181 W 12 Mile Rd",
    "sg:city":"Lathrup Village",
    "sg:classifiers":[
        {
            "category":"Health Services",
            "subcategory":"Dentist",
            "type":"Services"
        }
    ],
    "sg:phone":"+1 248 557 5756",
    "sg:postcode":"48076",
    "sg:province":"MI",
    "wof:name":"Signature Smiles",
    "wof:placetype":"venue"
},
  "geometry": {"coordinates":[-83.224802,42.502227],"type":"Point"}
}