{
  "type": "Feature",
  "properties": {
    "iso:country":"US",
    "sg:address":"16733 Industrial Pkwy",
    "sg:city":"Lansing",
    "sg:classifiers":[
        {
            "category":"Manufacturing",
            "subcategory":"Tools & Machinery",
            "type":"Manufacturing & Wholesale Goods"
        }
    ],
    "sg:phone":"+1 517 703 0777",
    "sg:postcode":"48906",
    "sg:province":"MI",
    "sg:tags":[
        "mold",
        "special"
    ],
    "wof:name":"Tool Craft Corp",
    "wof:placetype":"venue"
},
  "geometry": {"coordinates":[-84.624493,42.775034],"type":"Point"}
}