{
  "type": "Feature",
  "properties": {
    "iso:country":"US",
    "sg:address":"607 Eastern Ave",
    "sg:city":"Allegan",
    "sg:classifiers":[
        {
            "category":"Building & Trades",
            "subcategory":"Construction",
            "type":"Services"
        }
    ],
    "sg:phone":"+1 269 686 0664",
    "sg:postcode":"49010",
    "sg:province":"MI",
    "sg:tags":[
        "fire",
        "restoration",
        "damage"
    ],
    "sg:website":"www.servpro.com",
    "wof:name":"Servpro Of Van Buren County",
    "wof:placetype":"venue"
},
  "geometry": {"coordinates":[-85.83621599999999,42.522651],"type":"Point"}
}