{
  "type": "Feature",
  "properties": {
    "iso:country":"US",
    "sg:address":"192 Van Bruggen St",
    "sg:city":"Galesburg",
    "sg:classifiers":[
        {
            "category":"Shopping",
            "subcategory":"Discount & Variety Stores",
            "type":"Retail Goods"
        }
    ],
    "sg:phone":"+1 269 321 9598",
    "sg:postcode":"49053",
    "sg:province":"MI",
    "sg:tags":[
        "merchandise",
        "general"
    ],
    "wof:name":"Equinox Underwater Products",
    "wof:placetype":"venue"
},
  "geometry": {"coordinates":[-85.460838,42.288458],"type":"Point"}
}