{
  "type": "Feature",
  "properties": {
    "iso:country":"US",
    "sg:address":"1402 Carlisle Rd",
    "sg:city":"Traverse City",
    "sg:classifiers":[
        {
            "category":"Organizations",
            "subcategory":"Religious Organization",
            "type":"Services"
        }
    ],
    "sg:phone":"+1 231 922 0893",
    "sg:postcode":"49686",
    "sg:province":"MI",
    "wof:name":"Resurction Lf Chrch Trverse Cy",
    "wof:placetype":"venue"
},
  "geometry": {"coordinates":[-85.546319,44.706645],"type":"Point"}
}