{
  "type": "Feature",
  "properties": {
    "iso:country":"US",
    "sg:address":"11025 S Jackson Rd",
    "sg:city":"Cement City",
    "sg:classifiers":[
        {
            "category":"Farming",
            "subcategory":"Orchard",
            "type":"Manufacturing & Wholesale Goods"
        }
    ],
    "sg:phone":"+1 517 688 3455",
    "sg:postcode":"49233",
    "sg:province":"MI",
    "sg:tags":[
        "grove",
        "management"
    ],
    "wof:name":"Flavor Fruit Farms Inc",
    "wof:placetype":"venue"
},
  "geometry": {"coordinates":[-84.40647800000001,42.058048],"type":"Point"}
}