{
  "type": "Feature",
  "properties": {
    "iso:country":"US",
    "sg:address":"736 S Michigan Ave",
    "sg:city":"Howell",
    "sg:classifiers":[
        {
            "category":"Shopping",
            "type":"Retail Goods"
        },
        {
            "category":"Health Services",
            "subcategory":"Clinic",
            "type":"Services"
        }
    ],
    "sg:phone":"+1 517 546 7456",
    "sg:postcode":"48843",
    "sg:province":"MI",
    "sg:tags":[
        "hearing",
        "equipment",
        "supply",
        "merchandise",
        "impaired"
    ],
    "wof:name":"Denson Hearing Center Inc",
    "wof:placetype":"venue"
},
  "geometry": {"coordinates":[-83.93368100000001,42.601107],"type":"Point"}
}