{
  "type": "Feature",
  "properties": {
    "iso:country":"US",
    "sg:address":"2364 Pinehurst Trl",
    "sg:city":"Traverse City",
    "sg:classifiers":[
        {
            "category":"Building & Trades",
            "subcategory":"Landscaping Services",
            "type":"Services"
        }
    ],
    "sg:phone":"+1 231 946 7242",
    "sg:postcode":"49686",
    "sg:province":"MI",
    "sg:tags":[
        "landscape",
        "contractor"
    ],
    "wof:name":"Bay's Tree Care",
    "wof:placetype":"venue"
},
  "geometry": {"coordinates":[-85.525458,44.651083],"type":"Point"}
}