{
  "type": "Feature",
  "properties": {
    "iso:country":"US",
    "sg:address":"112 W Main St",
    "sg:city":"Hale",
    "sg:classifiers":[
        {
            "category":"Retail",
            "subcategory":"Auto Repair",
            "type":"Services"
        }
    ],
    "sg:phone":"+1 989 728 4481",
    "sg:postcode":"48739",
    "sg:province":"MI",
    "sg:tags":[
        "body"
    ],
    "wof:name":"West Side Body Shop",
    "wof:placetype":"venue"
},
  "geometry": {"coordinates":[-83.806291,44.378051],"type":"Point"}
}