{
  "type": "Feature",
  "properties": {
    "iso:country":"US",
    "sg:address":"1305 S Cedar St",
    "sg:city":"Lansing",
    "sg:classifiers":[
        {
            "category":"Manufacturing",
            "subcategory":"Printing",
            "type":"Manufacturing & Wholesale Goods"
        }
    ],
    "sg:phone":"+1 517 267 1229",
    "sg:postcode":"48910",
    "sg:province":"MI",
    "sg:tags":[
        "publisher"
    ],
    "wof:name":"Lone Pine Publishing",
    "wof:placetype":"venue"
},
  "geometry": {"coordinates":[-84.545486,42.719207],"type":"Point"}
}