{
  "type": "Feature",
  "properties": {
    "iso:country":"US",
    "sg:address":"201 S Main St",
    "sg:city":"Nashville",
    "sg:classifiers":[
        {
            "category":"Shopping",
            "subcategory":"Bicycles & Sporting Goods",
            "type":"Retail Goods"
        }
    ],
    "sg:phone":"+1 517 852 0820",
    "sg:postcode":"49073",
    "sg:province":"MI",
    "sg:tags":[
        "equipment",
        "archery",
        "supply"
    ],
    "wof:name":"Great Northern Bowhunting Co",
    "wof:placetype":"venue"
},
  "geometry": {"coordinates":[-85.0936,42.602281],"type":"Point"}
}