{
  "type": "Feature",
  "properties": {
    "iso:country":"US",
    "sg:address":"1036 Fuller Ave NE",
    "sg:city":"Grand Rapids",
    "sg:classifiers":[
        {
            "category":"Health Services",
            "subcategory":"Clinic",
            "type":"Services"
        }
    ],
    "sg:phone":"+1 616 774 2300",
    "sg:postcode":"49503",
    "sg:province":"MI",
    "sg:tags":[
        "banks",
        "blood",
        "center"
    ],
    "wof:name":"Grand Valley Blood Program",
    "wof:placetype":"venue"
},
  "geometry": {"coordinates":[-85.63978299999999,42.98299],"type":"Point"}
}