{
  "type": "Feature",
  "properties": {
    "iso:country":"US",
    "sg:address":"50421 E Russell Schmidt Blvd",
    "sg:city":"Chesterfield",
    "sg:classifiers":[
        {
            "category":"Professional",
            "subcategory":"Business Services",
            "type":"Services"
        }
    ],
    "sg:phone":"+1 586 598 9240",
    "sg:postcode":"48051",
    "sg:province":"MI",
    "sg:tags":[
        "packaging"
    ],
    "wof:name":"One Source Packaging",
    "wof:placetype":"venue"
},
  "geometry": {"coordinates":[-82.849217,42.664775],"type":"Point"}
}