{
  "type": "Feature",
  "properties": {
    "iso:country":"US",
    "sg:address":"5820 Lincoln Lake Rd NE",
    "sg:city":"Belding",
    "sg:classifiers":[
        {
            "category":"Building & Trades",
            "subcategory":"Construction",
            "type":"Services"
        }
    ],
    "sg:phone":"+1 616 691 8496",
    "sg:postcode":"48809",
    "sg:province":"MI",
    "sg:tags":[
        "contractor"
    ],
    "wof:name":"Steve Hessler Builders",
    "wof:placetype":"venue"
},
  "geometry": {"coordinates":[-85.352243,43.059555],"type":"Point"}
}