{
  "type": "Feature",
  "properties": {
    "iso:country":"US",
    "sg:address":"9961 Hamburg Rd",
    "sg:city":"Brighton",
    "sg:classifiers":[
        {
            "category":"Manufacturing",
            "subcategory":"Tools & Machinery",
            "type":"Manufacturing & Wholesale Goods"
        }
    ],
    "sg:phone":"+1 810 231 2400",
    "sg:postcode":"48116",
    "sg:province":"MI",
    "sg:tags":[
        "machine"
    ],
    "sg:website":"www.trudex.com",
    "wof:name":"Trudex",
    "wof:placetype":"venue"
},
  "geometry": {"coordinates":[-83.7989,42.4587],"type":"Point"}
}