{
  "type": "Feature",
  "properties": {
    "iso:country":"US",
    "sg:address":"16731 Karenina Ct",
    "sg:city":"Macomb",
    "sg:classifiers":[
        {
            "category":"Professional",
            "subcategory":"Computer Services",
            "type":"Services"
        }
    ],
    "sg:phone":"+1 586 412 0373",
    "sg:postcode":"48044",
    "sg:province":"MI",
    "wof:name":"Futuretech Inc",
    "wof:placetype":"venue"
},
  "geometry": {"coordinates":[-82.9546,42.643757],"type":"Point"}
}