{
  "type": "Feature",
  "properties": {
    "iso:country":"US",
    "sg:address":"4805 Haggerty Rd",
    "sg:city":"West Bloomfield",
    "sg:classifiers":[
        {
            "category":"Banks & Credit Unions",
            "subcategory":"Bank",
            "type":"Services"
        }
    ],
    "sg:phone":"+1 248 624 8775",
    "sg:postcode":"48323",
    "sg:province":"MI",
    "wof:name":"Comerica Bank",
    "wof:placetype":"venue"
},
  "geometry": {"coordinates":[-83.44001,42.576537],"type":"Point"}
}