{
  "type": "Feature",
  "properties": {
    "iso:country":"US",
    "sg:address":"8132 N Straits Hwy",
    "sg:city":"Cheboygan",
    "sg:classifiers":[
        {
            "category":"Shopping",
            "subcategory":"Bicycles & Sporting Goods",
            "type":"Retail Goods"
        }
    ],
    "sg:phone":"+1 231 627 4234",
    "sg:postcode":"49721",
    "sg:province":"MI",
    "wof:name":"Action Sports",
    "wof:placetype":"venue"
},
  "geometry": {"coordinates":[-84.51047800000001,45.579715],"type":"Point"}
}