{
  "type": "Feature",
  "properties": {
    "iso:country":"US",
    "sg:address":"2258 Franklin Rd",
    "sg:city":"Bloomfield Hills",
    "sg:classifiers":[
        {
            "category":"Home & Garden",
            "subcategory":"Carpets & Floor Coverings",
            "type":"Retail Goods"
        }
    ],
    "sg:phone":"+1 248 332 9430",
    "sg:postcode":"48302",
    "sg:province":"MI",
    "sg:tags":[
        "dealer",
        "rug"
    ],
    "wof:name":"Franklin Floor Covering",
    "wof:placetype":"venue"
},
  "geometry": {"coordinates":[-83.287606,42.605258],"type":"Point"}
}