{
  "type": "Feature",
  "properties": {
    "iso:country":"US",
    "sg:address":"25001 Michigan Ave",
    "sg:city":"Dearborn",
    "sg:classifiers":[
        {
            "category":"Insurance",
            "subcategory":"Insurance Agent",
            "type":"Services"
        }
    ],
    "sg:phone":"+1 313 563 4300",
    "sg:postcode":"48124",
    "sg:province":"MI",
    "wof:name":"Wallace Clifford Ins",
    "wof:placetype":"venue"
},
  "geometry": {"coordinates":[-83.28094299999999,42.297996],"type":"Point"}
}