{
  "type": "Feature",
  "properties": {
    "iso:country":"US",
    "sg:address":"12502 Lillie Rd",
    "sg:city":"Byron",
    "sg:classifiers":[
        {
            "category":"Retail",
            "subcategory":"Repair Shop",
            "type":"Services"
        }
    ],
    "sg:phone":"+1 810 266 4944",
    "sg:postcode":"48418",
    "sg:province":"MI",
    "wof:name":"Craigs Small Engine Parts",
    "wof:placetype":"venue"
},
  "geometry": {"coordinates":[-83.91471300000001,42.79559],"type":"Point"}
}