{
  "type": "Feature",
  "properties": {
    "iso:country":"US",
    "sg:address":"6701 Wabasis Rd NE",
    "sg:city":"Belding",
    "sg:classifiers":[
        {
            "category":"Wholesale",
            "subcategory":"Sporting Goods",
            "type":"Manufacturing & Wholesale Goods"
        }
    ],
    "sg:phone":"+1 616 691 7200",
    "sg:postcode":"48809",
    "sg:province":"MI",
    "sg:website":"www.deerquest.com",
    "wof:name":"Deer Quest LTD",
    "wof:placetype":"venue"
},
  "geometry": {"coordinates":[-85.397047,43.087295],"type":"Point"}
}