{
  "type": "Feature",
  "properties": {
    "iso:country":"US",
    "sg:address":"30195 Mound Rd",
    "sg:city":"Warren",
    "sg:classifiers":[
        {
            "category":"Sports & Exercise",
            "subcategory":"Playing Field",
            "type":"Entertainment"
        }
    ],
    "sg:phone":"+1 586 501 0008",
    "sg:postcode":"48092",
    "sg:province":"MI",
    "sg:tags":[
        "instruction",
        "fitness"
    ],
    "wof:name":"LA Fitness",
    "wof:placetype":"venue"
},
  "geometry": {"coordinates":[-83.047044,42.514557],"type":"Point"}
}