{
  "type": "Feature",
  "properties": {
    "iso:country":"US",
    "sg:address":"52211 Van Dyke Ave",
    "sg:city":"Shelby Twp",
    "sg:classifiers":[
        {
            "category":"Retail",
            "subcategory":"Repair Shop",
            "type":"Services"
        }
    ],
    "sg:phone":"+1 586 731 7175",
    "sg:postcode":"48316",
    "sg:province":"MI",
    "sg:tags":[
        "repairing",
        "saw"
    ],
    "wof:name":"Robinson Saw Svc Inc",
    "wof:placetype":"venue"
},
  "geometry": {"coordinates":[-83.03427600000001,42.677266],"type":"Point"}
}