{
  "type": "Feature",
  "properties": {
    "iso:country":"US",
    "sg:address":"3560 E 9 Mile Rd",
    "sg:city":"Warren",
    "sg:classifiers":[
        {
            "category":"Professional",
            "subcategory":"Business Services",
            "type":"Services"
        },
        {
            "category":"Building & Trades",
            "subcategory":"Construction",
            "type":"Services"
        }
    ],
    "sg:phone":"+1 586 759 2143",
    "sg:postcode":"48091",
    "sg:province":"MI",
    "sg:tags":[
        "roofing",
        "consultation",
        "inspection",
        "roof",
        "contractor"
    ],
    "sg:website":"www.drisonthenet.com",
    "wof:name":"Detroit Roofing Inspection Svc",
    "wof:placetype":"venue"
},
  "geometry": {"coordinates":[-83.07356,42.461953],"type":"Point"}
}