{
  "type": "Feature",
  "properties": {
    "iso:country":"US",
    "sg:address":"6356 Blue Beech Rd",
    "sg:city":"Rochester Hills",
    "sg:classifiers":[
        {
            "category":"Retail",
            "subcategory":"Laundry & Dry Cleaning",
            "type":"Services"
        }
    ],
    "sg:phone":"+1 248 651 5438",
    "sg:postcode":"48306",
    "sg:province":"MI",
    "sg:tags":[
        "cleaners",
        "rug",
        "carpet"
    ],
    "wof:name":"Great Lakes Carpet Steam Clean",
    "wof:placetype":"venue"
},
  "geometry": {"coordinates":[-83.126767,42.707569],"type":"Point"}
}