{
  "type": "Feature",
  "properties": {
    "iso:country":"US",
    "sg:address":"11350 J Dr S",
    "sg:city":"Burlington",
    "sg:classifiers":[
        {
            "category":"Health Services",
            "subcategory":"Doctor",
            "type":"Services"
        }
    ],
    "sg:phone":"+1 517 765 2033",
    "sg:postcode":"49029",
    "sg:province":"MI",
    "sg:tags":[
        "medical",
        "osteopathic"
    ],
    "wof:name":"Bronson Family Health Center",
    "wof:placetype":"venue"
},
  "geometry": {"coordinates":[-85.069141,42.177929],"type":"Point"}
}