{
  "type": "Feature",
  "properties": {
    "iso:country":"US",
    "sg:address":"2227 W Knox Rd",
    "sg:city":"Beaverton",
    "sg:classifiers":[
        {
            "category":"Social Services",
            "subcategory":"Adult Care",
            "type":"Services"
        }
    ],
    "sg:phone":"+1 989 435 3310",
    "sg:postcode":"48612",
    "sg:province":"MI",
    "sg:tags":[
        "foster",
        "provider"
    ],
    "wof:name":"Robert & Rebecca Phillips",
    "wof:placetype":"venue"
},
  "geometry": {"coordinates":[-84.456346,43.886739],"type":"Point"}
}