{
  "type": "Feature",
  "properties": {
    "iso:country":"US",
    "sg:address":"12465 James St",
    "sg:city":"Holland",
    "sg:classifiers":[
        {
            "category":"Shopping",
            "subcategory":"Shoes",
            "type":"Retail Goods"
        }
    ],
    "sg:phone":"+1 616 994 9734",
    "sg:postcode":"49424",
    "sg:province":"MI",
    "wof:name":"Red Wing Shoe Store",
    "wof:placetype":"venue"
},
  "geometry": {"coordinates":[-86.089457,42.812089],"type":"Point"}
}