{
  "type": "Feature",
  "properties": {
    "iso:country":"US",
    "sg:address":"3266 Adventure Ln",
    "sg:city":"Oxford",
    "sg:classifiers":[
        {
            "category":"Building & Trades",
            "subcategory":"Construction",
            "type":"Services"
        }
    ],
    "sg:phone":"+1 248 236 9677",
    "sg:postcode":"48371",
    "sg:province":"MI",
    "sg:tags":[
        "home",
        "improvement"
    ],
    "wof:name":"Brooks Home Improvement",
    "wof:placetype":"venue"
},
  "geometry": {"coordinates":[-83.29469400000001,42.871297],"type":"Point"}
}