{
  "type": "Feature",
  "properties": {
    "iso:country":"US",
    "sg:address":"1904 Nashville Rd",
    "sg:city":"Hastings",
    "sg:classifiers":[
        {
            "category":"Retail",
            "subcategory":"Repair Shop",
            "type":"Services"
        }
    ],
    "sg:phone":"+1 269 945 9100",
    "sg:postcode":"49058",
    "sg:province":"MI",
    "sg:tags":[
        "electrical"
    ],
    "wof:name":"James Ray Elctromechanical Svc",
    "wof:placetype":"venue"
},
  "geometry": {"coordinates":[-85.25036,42.62031],"type":"Point"}
}