{
  "type": "Feature",
  "properties": {
    "iso:country":"US",
    "sg:address":"14932 Mercury Dr",
    "sg:city":"Grand Haven",
    "sg:classifiers":[
        {
            "category":"Organizations",
            "subcategory":"Religious Organization",
            "type":"Services"
        }
    ],
    "sg:phone":"+1 616 842 9150",
    "sg:postcode":"49417",
    "sg:province":"MI",
    "wof:name":"Hope Reformed Church",
    "wof:placetype":"venue"
},
  "geometry": {"coordinates":[-86.157989,43.027836],"type":"Point"}
}