{
  "type": "Feature",
  "properties": {
    "iso:country":"US",
    "sg:address":"5925 Red Arrow Hwy",
    "sg:city":"Coloma",
    "sg:classifiers":[
        {
            "category":"Food & Beverages",
            "subcategory":"Candy",
            "type":"Retail Goods"
        },
        {
            "category":"Shopping",
            "type":"Retail Goods"
        }
    ],
    "sg:phone":"+1 269 468 4646",
    "sg:postcode":"49038",
    "sg:province":"MI",
    "sg:tags":[
        "making",
        "bakery",
        "merchandise",
        "supply"
    ],
    "wof:name":"Karen's Kakes & Kake Things",
    "wof:placetype":"venue"
},
  "geometry": {"coordinates":[-86.317115,42.177412],"type":"Point"}
}