{
  "type": "Feature",
  "properties": {
    "iso:country":"US",
    "sg:address":"1591 Kingston Dr",
    "sg:city":"Saginaw",
    "sg:classifiers":[
        {
            "category":"Wholesale",
            "subcategory":"Groceries",
            "type":"Manufacturing & Wholesale Goods"
        }
    ],
    "sg:phone":"+1 989 751 0712",
    "sg:postcode":"48638",
    "sg:province":"MI",
    "sg:tags":[
        "confectionery"
    ],
    "wof:name":"Vlassi",
    "wof:placetype":"venue"
},
  "geometry": {"coordinates":[-84.029055,43.43165],"type":"Point"}
}