{
  "type": "Feature",
  "properties": {
    "iso:country":"US",
    "sg:address":"18877 W 10 Mile Rd",
    "sg:city":"Southfield",
    "sg:classifiers":[
        {
            "category":"Wholesale",
            "subcategory":"Construction Materials",
            "type":"Manufacturing & Wholesale Goods"
        }
    ],
    "sg:phone":"+1 248 569 5212",
    "sg:postcode":"48075",
    "sg:province":"MI",
    "sg:tags":[
        "granite"
    ],
    "wof:name":"Galaxy Stones",
    "wof:placetype":"venue"
},
  "geometry": {"coordinates":[-83.22954799999999,42.473129],"type":"Point"}
}