{
  "type": "Feature",
  "properties": {
    "iso:country":"US",
    "sg:address":"340 S State St",
    "sg:city":"Harbor Springs",
    "sg:classifiers":[
        {
            "category":"Real Estate",
            "subcategory":"Architect",
            "type":"Services"
        }
    ],
    "sg:phone":"+1 231 526 5729",
    "sg:postcode":"49740",
    "sg:province":"MI",
    "sg:tags":[
        "architectural"
    ],
    "wof:name":"Gorman Design & Associates",
    "wof:placetype":"venue"
},
  "geometry": {"coordinates":[-85.013746,45.544934],"type":"Point"}
}