{
  "type": "Feature",
  "properties": {
    "iso:country":"US",
    "sg:address":"19100 W 10 Mile Rd Ste 106",
    "sg:city":"Southfield",
    "sg:classifiers":[
        {
            "category":"Professional",
            "subcategory":"Lawyer & Legal Services",
            "type":"Services"
        }
    ],
    "sg:phone":"+1 248 355 9885",
    "sg:postcode":"48075",
    "sg:province":"MI",
    "wof:name":"Spector Eric M Atty",
    "wof:placetype":"venue"
},
  "geometry": {"coordinates":[-83.23249800000001,42.473099],"type":"Point"}
}