{
  "type": "Feature",
  "properties": {
    "iso:country":"US",
    "sg:address":"937 N Opdyke Rd",
    "sg:city":"Auburn Hills",
    "sg:classifiers":[
        {
            "category":"Shopping",
            "subcategory":"Stationery & Office Supplies",
            "type":"Retail Goods"
        }
    ],
    "sg:phone":"+1 248 377 3200",
    "sg:postcode":"48326",
    "sg:province":"MI",
    "sg:website":"www.thomop.com",
    "wof:name":"Thom Office Plus",
    "wof:placetype":"venue"
},
  "geometry": {"coordinates":[-83.247236,42.651924],"type":"Point"}
}