{
  "type": "Feature",
  "properties": {
    "iso:country":"US",
    "sg:address":"315 Adams St",
    "sg:city":"St Clair",
    "sg:classifiers":[
        {
            "category":"Health Services",
            "subcategory":"Doctor",
            "type":"Services"
        }
    ],
    "sg:phone":"+1 810 329 0924",
    "sg:postcode":"48079",
    "sg:province":"MI",
    "sg:tags":[
        "dentist"
    ],
    "wof:name":"George L Friederichs DDS",
    "wof:placetype":"venue"
},
  "geometry": {"coordinates":[-82.488427,42.82466],"type":"Point"}
}