{
  "type": "Feature",
  "properties": {
    "iso:country":"US",
    "sg:address":"6974 Shattuck Rd",
    "sg:city":"Saginaw",
    "sg:classifiers":[
        {
            "category":"Wholesale",
            "subcategory":"Durable Goods & Equipment",
            "type":"Manufacturing & Wholesale Goods"
        }
    ],
    "sg:phone":"+1 989 793 9404",
    "sg:postcode":"48603",
    "sg:province":"MI",
    "sg:tags":[
        "fire",
        "extinguisher"
    ],
    "wof:name":"Delta Fire Protection",
    "wof:placetype":"venue"
},
  "geometry": {"coordinates":[-84.04980399999999,43.451696],"type":"Point"}
}