{
  "type": "Feature",
  "properties": {
    "iso:country":"US",
    "sg:address":"14610 14th Rd",
    "sg:city":"Garden",
    "sg:classifiers":[
        {
            "category":"Professional",
            "subcategory":"Accounting & Tax Preparation",
            "type":"Services"
        }
    ],
    "sg:phone":"+1 906 644 2809",
    "sg:postcode":"49835",
    "sg:province":"MI",
    "sg:tags":[
        "return"
    ],
    "wof:name":"Great Lakes Tax Accountin",
    "wof:placetype":"venue"
},
  "geometry": {"coordinates":[-86.621202,45.732896],"type":"Point"}
}