{
  "type": "Feature",
  "properties": {
    "iso:country":"US",
    "sg:address":"4000 Sprinkle Rd",
    "sg:city":"Kalamazoo",
    "sg:classifiers":[
        {
            "category":"Banks & Credit Unions",
            "subcategory":"Bank",
            "type":"Services"
        }
    ],
    "sg:phone":"+1 269 342 4651",
    "sg:postcode":"49001",
    "sg:province":"MI",
    "sg:tags":[
        "federally",
        "chartered"
    ],
    "wof:name":"Kalamazoo District Bell CU",
    "wof:placetype":"venue"
},
  "geometry": {"coordinates":[-85.53089199999999,42.252002],"type":"Point"}
}