{
  "type": "Feature",
  "properties": {
    "iso:country":"US",
    "sg:address":"1722 Humphrey Ave",
    "sg:city":"Birmingham",
    "sg:classifiers":[
        {
            "category":"Banks & Credit Unions",
            "subcategory":"Bank",
            "type":"Services"
        }
    ],
    "sg:phone":"+1 248 646 2505",
    "sg:postcode":"48009",
    "sg:province":"MI",
    "sg:tags":[
        "broker",
        "mortgage"
    ],
    "wof:name":"Etaks",
    "wof:placetype":"venue"
},
  "geometry": {"coordinates":[-83.19936300000001,42.537529],"type":"Point"}
}