{
  "type": "Feature",
  "properties": {
    "iso:country":"US",
    "sg:address":"5690 S Westnedge Ave",
    "sg:city":"Portage",
    "sg:classifiers":[
        {
            "category":"Restaurant",
            "type":"Food & Drink"
        }
    ],
    "sg:menulink":"http://www.allmenus.com/mi/portage/98422-carrabbas/menu/",
    "sg:phone":"+1 269 381 0819",
    "sg:postcode":"49002",
    "sg:province":"MI",
    "sg:tags":[
        "italian"
    ],
    "wof:name":"Carrabba's",
    "wof:placetype":"venue"
},
  "geometry": {"coordinates":[-85.589586,42.233157],"type":"Point"}
}