{
  "type": "Feature",
  "properties": {
    "iso:country":"US",
    "sg:address":"119 N Roland St",
    "sg:city":"Mc Bain",
    "sg:classifiers":[
        {
            "category":"Health Services",
            "subcategory":"Doctor",
            "type":"Services"
        }
    ],
    "sg:phone":"+1 231 825 2643",
    "sg:postcode":"49657",
    "sg:province":"MI",
    "sg:tags":[
        "clinic"
    ],
    "wof:name":"Great Lakes Family Care",
    "wof:placetype":"venue"
},
  "geometry": {"coordinates":[-85.210583,44.193493],"type":"Point"}
}