{
  "type": "Feature",
  "properties": {
    "iso:country":"US",
    "sg:address":"18240 Stratford Dr",
    "sg:city":"Southfield",
    "sg:classifiers":[
        {
            "category":"Professional",
            "subcategory":"Art Services",
            "type":"Services"
        }
    ],
    "sg:phone":"+1 248 552 8548",
    "sg:postcode":"48075",
    "sg:province":"MI",
    "sg:tags":[
        "commercial",
        "design"
    ],
    "wof:name":"Klines HI Tech Home",
    "wof:placetype":"venue"
},
  "geometry": {"coordinates":[-83.223973,42.469719],"type":"Point"}
}