{
  "type": "Feature",
  "properties": {
    "iso:country":"US",
    "sg:address":"8155 Ritter",
    "sg:city":"Center Line",
    "sg:classifiers":[
        {
            "category":"Education",
            "subcategory":"School",
            "type":"Public Place"
        }
    ],
    "sg:phone":"+1 586 757 7500",
    "sg:postcode":"48015",
    "sg:province":"MI",
    "sg:tags":[
        "high",
        "middle",
        "elementary"
    ],
    "wof:name":"St Clement",
    "wof:placetype":"venue"
},
  "geometry": {"coordinates":[-83.025002,42.479801],"type":"Point"}
}