{
  "type": "Feature",
  "properties": {
    "iso:country":"US",
    "sg:address":"975 E Maple Rd",
    "sg:city":"Birmingham",
    "sg:classifiers":[
        {
            "category":"Wholesale",
            "subcategory":"Durable Goods & Equipment",
            "type":"Manufacturing & Wholesale Goods"
        }
    ],
    "sg:phone":"+1 248 645 1336",
    "sg:postcode":"48009",
    "sg:province":"MI",
    "sg:tags":[
        "representative",
        "manufacturer"
    ],
    "wof:name":"William F Gray Assoc",
    "wof:placetype":"venue"
},
  "geometry": {"coordinates":[-83.20826099999999,42.546924],"type":"Point"}
}