{
  "type": "Feature",
  "properties": {
    "iso:country":"US",
    "sg:address":"30200 Schoenherr Rd",
    "sg:city":"Warren",
    "sg:classifiers":[
        {
            "category":"Organizations",
            "subcategory":"Religious Organization",
            "type":"Services"
        }
    ],
    "sg:phone":"+1 586 771 6720",
    "sg:postcode":"48088",
    "sg:province":"MI",
    "sg:tags":[
        "church"
    ],
    "sg:website":"www.web.triton.net/cotmrca",
    "wof:name":"Church-The Master Reformed Ch",
    "wof:placetype":"venue"
},
  "geometry": {"coordinates":[-82.987968,42.515616],"type":"Point"}
}