{
  "type": "Feature",
  "properties": {
    "iso:country":"US",
    "sg:address":"141 Dwight Ave",
    "sg:city":"Pontiac",
    "sg:classifiers":[
        {
            "category":"Social Services",
            "subcategory":"Adult Care",
            "type":"Services"
        }
    ],
    "sg:phone":"+1 248 335 3712",
    "sg:postcode":"48341",
    "sg:province":"MI",
    "sg:tags":[
        "foster",
        "provider"
    ],
    "wof:name":"Sandra Bell-Hodge",
    "wof:placetype":"venue"
},
  "geometry": {"coordinates":[-83.314393,42.64049],"type":"Point"}
}