{
  "type": "Feature",
  "properties": {
    "iso:country":"US",
    "sg:address":"12188 Southgate Dr",
    "sg:city":"Plainwell",
    "sg:classifiers":[
        {
            "category":"Insurance",
            "subcategory":"Insurance Agent",
            "type":"Services"
        }
    ],
    "sg:phone":"+1 269 664 4321",
    "sg:postcode":"49080",
    "sg:province":"MI",
    "wof:name":"K Of C Insurance",
    "wof:placetype":"venue"
},
  "geometry": {"coordinates":[-85.523832,42.482694],"type":"Point"}
}