{
  "type": "Feature",
  "properties": {
    "iso:country":"US",
    "sg:address":"2422 Ashford Blvd",
    "sg:city":"Flushing",
    "sg:classifiers":[
        {
            "category":"Shopping",
            "subcategory":"Hobbies, Toys, & Games",
            "type":"Retail Goods"
        }
    ],
    "sg:phone":"+1 810 732 7636",
    "sg:postcode":"48433",
    "sg:province":"MI",
    "wof:name":"Olde Folkies",
    "wof:placetype":"venue"
},
  "geometry": {"coordinates":[-83.80189300000001,43.041588],"type":"Point"}
}