{
  "type": "Feature",
  "properties": {
    "iso:country":"US",
    "sg:address":"3370 S Graham Rd",
    "sg:city":"Saginaw",
    "sg:classifiers":[
        {
            "category":"Professional",
            "subcategory":"Accounting & Tax Preparation",
            "type":"Services"
        }
    ],
    "sg:phone":"+1 989 781 2491",
    "sg:postcode":"48609",
    "sg:province":"MI",
    "sg:tags":[
        "return"
    ],
    "wof:name":"Lonsway Tax Service",
    "wof:placetype":"venue"
},
  "geometry": {"coordinates":[-84.131086,43.374467],"type":"Point"}
}