{
  "type": "Feature",
  "properties": {
    "iso:country":"US",
    "sg:address":"104 Clover St",
    "sg:city":"Holland",
    "sg:classifiers":[
        {
            "category":"Social Services",
            "type":"Services"
        }
    ],
    "sg:phone":"+1 616 392 4461",
    "sg:postcode":"49423",
    "sg:province":"MI",
    "sg:tags":[
        "organization",
        "welfare"
    ],
    "wof:name":"Salvation Army",
    "wof:placetype":"venue"
},
  "geometry": {"coordinates":[-86.084355,42.792823],"type":"Point"}
}