{
  "type": "Feature",
  "properties": {
    "iso:country":"US",
    "sg:address":"400 S Main St",
    "sg:city":"Standish",
    "sg:classifiers":[
        {
            "category":"Retail",
            "subcategory":"Auto Repair",
            "type":"Services"
        }
    ],
    "sg:phone":"+1 989 846 4127",
    "sg:postcode":"48658",
    "sg:province":"MI",
    "sg:tags":[
        "general"
    ],
    "wof:name":"Marcotts Auto Repair",
    "wof:placetype":"venue"
},
  "geometry": {"coordinates":[-83.959844,43.978538],"type":"Point"}
}