{
  "type": "Feature",
  "properties": {
    "iso:country":"US",
    "sg:address":"19431 Broadacres St",
    "sg:city":"Clinton Township",
    "sg:classifiers":[
        {
            "category":"Shopping",
            "subcategory":"Discount & Variety Stores",
            "type":"Retail Goods"
        }
    ],
    "sg:phone":"+1 586 790 3016",
    "sg:postcode":"48035",
    "sg:province":"MI",
    "sg:tags":[
        "merchandise",
        "general"
    ],
    "wof:name":"Lb Products",
    "wof:placetype":"venue"
},
  "geometry": {"coordinates":[-82.92131500000001,42.542629],"type":"Point"}
}