{
  "type": "Feature",
  "properties": {
    "iso:country":"US",
    "sg:address":"1771 Glenlord Rd",
    "sg:city":"Stevensville",
    "sg:classifiers":[
        {
            "category":"Organizations",
            "subcategory":"Religious Organization",
            "type":"Services"
        }
    ],
    "sg:phone":"+1 269 428 2399",
    "sg:postcode":"49127",
    "sg:province":"MI",
    "sg:tags":[
        "church"
    ],
    "wof:name":"Kingdom Hall-Jehovah's Witness",
    "wof:placetype":"venue"
},
  "geometry": {"coordinates":[-86.496167,42.04346],"type":"Point"}
}