{
  "type": "Feature",
  "properties": {
    "iso:country":"US",
    "sg:address":"74263 Fulton St",
    "sg:city":"Armada",
    "sg:classifiers":[
        {
            "category":"Home & Garden",
            "subcategory":"Furniture",
            "type":"Retail Goods"
        }
    ],
    "sg:phone":"+1 586 784 5990",
    "sg:postcode":"48005",
    "sg:province":"MI",
    "sg:tags":[
        "cabinet"
    ],
    "wof:name":"Carolynn's Cabinets",
    "wof:placetype":"venue"
},
  "geometry": {"coordinates":[-82.884748,42.844515],"type":"Point"}
}