{
  "type": "Feature",
  "properties": {
    "iso:country":"US",
    "sg:address":"493 Riverview Dr",
    "sg:city":"Plainwell",
    "sg:classifiers":[
        {
            "category":"Shopping",
            "subcategory":"Computers & Home Electronics",
            "type":"Retail Goods"
        }
    ],
    "sg:phone":"+1 269 650 0934",
    "sg:postcode":"49080",
    "sg:province":"MI",
    "sg:tags":[
        "printer",
        "sales"
    ],
    "wof:name":"Total Image Computers",
    "wof:placetype":"venue"
},
  "geometry": {"coordinates":[-85.59586299999999,42.430709],"type":"Point"}
}