{
  "type": "Feature",
  "properties": {
    "iso:country":"US",
    "sg:address":"711 N Main St",
    "sg:city":"Royal Oak",
    "sg:classifiers":[
        {
            "category":"Food & Beverages",
            "subcategory":"Liquor & Beverages",
            "type":"Retail Goods"
        }
    ],
    "sg:phone":"+1 248 399 7166",
    "sg:postcode":"48067",
    "sg:province":"MI",
    "sg:tags":[
        "beer",
        "spirit",
        "wine"
    ],
    "wof:name":"Cloverleaf Acquisition",
    "wof:placetype":"venue"
},
  "geometry": {"coordinates":[-83.144706,42.494784],"type":"Point"}
}