{
  "type": "Feature",
  "properties": {
    "iso:country":"US",
    "sg:address":"2895 Wixom Trl",
    "sg:city":"Milford",
    "sg:classifiers":[
        {
            "category":"Building & Trades",
            "subcategory":"Landscaping Services",
            "type":"Services"
        }
    ],
    "sg:phone":"+1 248 684 8441",
    "sg:postcode":"48381",
    "sg:province":"MI",
    "sg:tags":[
        "landscape",
        "contractor"
    ],
    "wof:name":"Verdure H2o",
    "wof:placetype":"venue"
},
  "geometry": {"coordinates":[-83.579205,42.58129],"type":"Point"}
}