{
  "type": "Feature",
  "properties": {
    "iso:country":"US",
    "sg:address":"4235 Prairie St SW",
    "sg:city":"Grandville",
    "sg:classifiers":[
        {
            "category":"Retail",
            "subcategory":"Funeral Services",
            "type":"Services"
        }
    ],
    "sg:phone":"+1 616 406 1709",
    "sg:postcode":"49418",
    "sg:province":"MI",
    "sg:tags":[
        "crematory"
    ],
    "wof:name":"Great Lakes Cremation Svc LLC",
    "wof:placetype":"venue"
},
  "geometry": {"coordinates":[-85.767833,42.906562],"type":"Point"}
}