{
  "type": "Feature",
  "properties": {
    "iso:country":"US",
    "sg:address":"22 George Dr",
    "sg:city":"Monroe",
    "sg:classifiers":[
        {
            "category":"Retail",
            "subcategory":"Laundry & Dry Cleaning",
            "type":"Services"
        }
    ],
    "sg:phone":"+1 734 240 4611",
    "sg:postcode":"48162",
    "sg:province":"MI",
    "sg:tags":[
        "upholstery",
        "dying",
        "carpet"
    ],
    "wof:name":"Rainbow International",
    "wof:placetype":"venue"
},
  "geometry": {"coordinates":[-83.356103,41.966869],"type":"Point"}
}