{
  "type": "Feature",
  "properties": {
    "iso:country":"US",
    "sg:address":"319 State Hwy 62",
    "sg:city":"Cassopolis",
    "sg:classifiers":[
        {
            "category":"Education",
            "subcategory":"Library",
            "type":"Public Place"
        }
    ],
    "sg:phone":"+1 269 445 3400",
    "sg:postcode":"49031",
    "sg:province":"MI",
    "sg:website":"www.cass.lib.mi.us",
    "wof:name":"Cass District Library",
    "wof:placetype":"venue"
},
  "geometry": {"coordinates":[-86.01236400000001,41.907932],"type":"Point"}
}