{
  "type": "Feature",
  "properties": {
    "iso:country":"US",
    "sg:address":"5529 Madison Ave SE",
    "sg:city":"Grand Rapids",
    "sg:classifiers":[
        {
            "category":"Building & Trades",
            "subcategory":"Construction",
            "type":"Services"
        }
    ],
    "sg:phone":"+1 616 406 0665",
    "sg:postcode":"49548",
    "sg:province":"MI",
    "sg:tags":[
        "house"
    ],
    "wof:name":"Born Again Construction",
    "wof:placetype":"venue"
},
  "geometry": {"coordinates":[-85.654597,42.86449],"type":"Point"}
}