{
  "type": "Feature",
  "properties": {
    "iso:country":"US",
    "sg:address":"3035 Crestwood Ct",
    "sg:city":"Bay City",
    "sg:classifiers":[
        {
            "category":"Building & Trades",
            "subcategory":"Construction",
            "type":"Services"
        }
    ],
    "sg:phone":"+1 989 684 1805",
    "sg:postcode":"48706",
    "sg:province":"MI",
    "sg:tags":[
        "house"
    ],
    "wof:name":"Marc Owczarzak Builders",
    "wof:placetype":"venue"
},
  "geometry": {"coordinates":[-83.929528,43.614294],"type":"Point"}
}