{
  "type": "Feature",
  "properties": {
    "iso:country":"US",
    "sg:address":"18507 Fox",
    "sg:city":"Redford",
    "sg:classifiers":[
        {
            "category":"Social Services",
            "subcategory":"Child Care",
            "type":"Services"
        }
    ],
    "sg:phone":"+1 313 538 1610",
    "sg:postcode":"48240",
    "sg:province":"MI",
    "sg:tags":[
        "day"
    ],
    "wof:name":"Susan E Hall",
    "wof:placetype":"venue"
},
  "geometry": {"coordinates":[-83.308938,42.42154],"type":"Point"}
}