{
  "type": "Feature",
  "properties": {
    "iso:country":"US",
    "sg:address":"7656 Hodges Hwy",
    "sg:city":"Blissfield",
    "sg:phone":"+1 517 443 5450",
    "sg:postcode":"49228",
    "sg:province":"MI",
    "sg:tags":[
        "farm",
        "corn",
        "grain",
        "cash"
    ],
    "wof:name":"Harold Hodges",
    "wof:placetype":"venue"
},
  "geometry": {"coordinates":[-83.979632,41.804092],"type":"Point"}
}