{
  "type": "Feature",
  "properties": {
    "iso:country":"US",
    "sg:address":"751 Kolinske Rd",
    "sg:city":"Petoskey",
    "sg:classifiers":[
        {
            "category":"Organizations",
            "subcategory":"Membership Organization",
            "type":"Services"
        }
    ],
    "sg:phone":"+1 231 347 5427",
    "sg:postcode":"49770",
    "sg:province":"MI",
    "wof:name":"Bryan Foundation",
    "wof:placetype":"venue"
},
  "geometry": {"coordinates":[-84.88889500000001,45.38773],"type":"Point"}
}