{
  "type": "Feature",
  "properties": {
    "iso:country":"US",
    "sg:address":"4950 S Meridian Rd",
    "sg:city":"Jackson",
    "sg:classifiers":[
        {
            "category":"Manufacturing",
            "subcategory":"Printing",
            "type":"Manufacturing & Wholesale Goods"
        }
    ],
    "sg:phone":"+1 517 782 0030",
    "sg:postcode":"49201",
    "sg:province":"MI",
    "sg:tags":[
        "printer"
    ],
    "wof:name":"Anglin Offset & Design",
    "wof:placetype":"venue"
},
  "geometry": {"coordinates":[-84.368047,42.182317],"type":"Point"}
}