{
  "type": "Feature",
  "properties": {
    "iso:country":"US",
    "sg:address":"205 S 4th Ave",
    "sg:city":"Ann Arbor",
    "sg:classifiers":[
        {
            "category":"Restaurant",
            "type":"Food & Drink"
        }
    ],
    "sg:menulink":"http://www.allmenus.com/mi/ann-arbor/248004-sottinis-sub-shop/menu/",
    "sg:phone":"+1 734 769 7827",
    "sg:postcode":"48104",
    "sg:province":"MI",
    "sg:tags":[
        "wrap",
        "american",
        "sandwich"
    ],
    "wof:name":"Sottini's Sub Shop",
    "wof:placetype":"venue"
},
  "geometry": {"coordinates":[-83.74727799999999,42.280402],"type":"Point"}
}