{
  "type": "Feature",
  "properties": {
    "iso:country":"US",
    "sg:address":"1217 E Grand River Ave",
    "sg:city":"Lansing",
    "sg:classifiers":[
        {
            "category":"Freight",
            "type":"Transportation"
        }
    ],
    "sg:phone":"+1 517 482 1270",
    "sg:postcode":"48906",
    "sg:province":"MI",
    "sg:tags":[
        "mover"
    ],
    "wof:name":"Food Movers",
    "wof:placetype":"venue"
},
  "geometry": {"coordinates":[-84.53474300000001,42.747402],"type":"Point"}
}