{
  "type": "Feature",
  "properties": {
    "iso:country":"US",
    "sg:address":"6330 W Cutler Rd",
    "sg:city":"Dewitt",
    "sg:classifiers":[
        {
            "category":"Wholesale",
            "subcategory":"Furniture",
            "type":"Manufacturing & Wholesale Goods"
        }
    ],
    "sg:phone":"+1 517 669 1683",
    "sg:postcode":"48820",
    "sg:province":"MI",
    "sg:tags":[
        "household",
        "furnishing",
        "mfg"
    ],
    "wof:name":"Ewing Savoie",
    "wof:placetype":"venue"
},
  "geometry": {"coordinates":[-84.650881,42.856913],"type":"Point"}
}