{
  "type": "Feature",
  "properties": {
    "iso:country":"US",
    "sg:address":"212 S Milford Rd",
    "sg:city":"Highland",
    "sg:classifiers":[
        {
            "category":"Retail",
            "subcategory":"Repair Shop",
            "type":"Services"
        }
    ],
    "sg:phone":"+1 248 887 6011",
    "sg:postcode":"48357",
    "sg:province":"MI",
    "sg:tags":[
        "lock",
        "locksmith"
    ],
    "wof:name":"Steve's Locksmith",
    "wof:placetype":"venue"
},
  "geometry": {"coordinates":[-83.616775,42.632867],"type":"Point"}
}