{
  "type": "Feature",
  "properties": {
    "iso:country":"US",
    "sg:address":"30412 Charmaine St",
    "sg:city":"Roseville",
    "sg:classifiers":[
        {
            "category":"Professional",
            "subcategory":"Computer Services",
            "type":"Services"
        }
    ],
    "sg:phone":"+1 586 775 8945",
    "sg:postcode":"48066",
    "sg:province":"MI",
    "sg:tags":[
        "prepackaged",
        "software"
    ],
    "wof:name":"Bronzemist Software Systems",
    "wof:placetype":"venue"
},
  "geometry": {"coordinates":[-82.96684,42.520205],"type":"Point"}
}