{
  "type": "Feature",
  "properties": {
    "iso:country":"US",
    "sg:address":"2221 Livernois Rd",
    "sg:city":"Troy",
    "sg:classifiers":[
        {
            "category":"Personal",
            "type":"Services"
        }
    ],
    "sg:phone":"+1 248 273 9150",
    "sg:postcode":"48083",
    "sg:province":"MI",
    "sg:tags":[
        "hair",
        "replacement"
    ],
    "wof:name":"Troy Hair Transplant Ctr",
    "wof:placetype":"venue"
},
  "geometry": {"coordinates":[-83.147386,42.554582],"type":"Point"}
}