{
  "type": "Feature",
  "properties": {
    "iso:country":"US",
    "sg:address":"48357 Valley Forge Dr",
    "sg:city":"Macomb",
    "sg:classifiers":[
        {
            "category":"Building & Trades",
            "subcategory":"Construction",
            "type":"Services"
        }
    ],
    "sg:phone":"+1 586 263 5012",
    "sg:postcode":"48044",
    "sg:province":"MI",
    "sg:tags":[
        "hanging",
        "contractor"
    ],
    "wof:name":"C&D Painting",
    "wof:placetype":"venue"
},
  "geometry": {"coordinates":[-82.946292,42.652184],"type":"Point"}
}