{
  "type": "Feature",
  "properties": {
    "iso:country":"US",
    "sg:address":"405 N Phillip Rd",
    "sg:city":"Niles",
    "sg:classifiers":[
        {
            "category":"Professional",
            "subcategory":"Research",
            "type":"Services"
        }
    ],
    "sg:phone":"+1 269 684 7943",
    "sg:postcode":"49120",
    "sg:province":"MI",
    "sg:tags":[
        "entomology"
    ],
    "wof:name":"Deborah Grooms",
    "wof:placetype":"venue"
},
  "geometry": {"coordinates":[-86.282995,41.832188],"type":"Point"}
}