{
  "type": "Feature",
  "properties": {
    "iso:country":"US",
    "sg:address":"259 Michigan St NE",
    "sg:city":"Grand Rapids",
    "sg:classifiers":[
        {
            "category":"Banks & Credit Unions",
            "subcategory":"Bank",
            "type":"Services"
        }
    ],
    "sg:phone":"+1 616 771 5751",
    "sg:postcode":"49503",
    "sg:province":"MI",
    "wof:name":"Fifth Third Bank",
    "wof:placetype":"venue"
},
  "geometry": {"coordinates":[-85.662474,42.970382],"type":"Point"}
}