{
  "type": "Feature",
  "properties": {
    "iso:country":"US",
    "sg:address":"8445 Webster Rd",
    "sg:city":"Freeland",
    "sg:classifiers":[
        {
            "category":"Organizations",
            "subcategory":"Religious Organization",
            "type":"Services"
        }
    ],
    "sg:phone":"+1 989 695 6414",
    "sg:postcode":"48623",
    "sg:province":"MI",
    "sg:tags":[
        "church"
    ],
    "sg:website":"www.fbcfreeland.com",
    "wof:name":"First Baptist Church-Freeland",
    "wof:placetype":"venue"
},
  "geometry": {"coordinates":[-84.110242,43.531469],"type":"Point"}
}