{
  "type": "Feature",
  "properties": {
    "iso:country":"US",
    "sg:address":"601 Rogell Dr North Terminal",
    "sg:city":"Detroit",
    "sg:classifiers":[
        {
            "category":"Restaurant",
            "type":"Food & Drink"
        }
    ],
    "sg:phone":"+1 734 247 1118",
    "sg:postcode":"48242",
    "sg:province":"MI",
    "sg:website":"www.rubytuesday.com/",
    "wof:name":"Ruby Tuesday",
    "wof:placetype":"venue"
},
  "geometry": {"coordinates":[-83.348274,42.225725],"type":"Point"}
}