{
  "type": "Feature",
  "properties": {
    "iso:country":"US",
    "sg:address":"22372 Masch Ave",
    "sg:city":"Warren",
    "sg:classifiers":[
        {
            "category":"Professional",
            "subcategory":"Business Services",
            "type":"Services"
        }
    ],
    "sg:phone":"+1 586 755 2804",
    "sg:postcode":"48091",
    "sg:province":"MI",
    "wof:name":"Arens Contracting Co",
    "wof:placetype":"venue"
},
  "geometry": {"coordinates":[-83.056426,42.45868],"type":"Point"}
}