{
  "type": "Feature",
  "properties": {
    "iso:country":"US",
    "sg:address":"111 W River St",
    "sg:city":"Cadillac",
    "sg:classifiers":[
        {
            "category":"Mining & Drilling",
            "type":"Manufacturing & Wholesale Goods"
        }
    ],
    "sg:phone":"+1 231 876 2195",
    "sg:postcode":"49601",
    "sg:province":"MI",
    "sg:tags":[
        "oil",
        "gas",
        "producer"
    ],
    "wof:name":"Blarney Castle Oil Co",
    "wof:placetype":"venue"
},
  "geometry": {"coordinates":[-85.405137,44.256337],"type":"Point"}
}