{
  "type": "Feature",
  "properties": {
    "iso:country":"US",
    "sg:address":"4499 W Walton Blvd",
    "sg:city":"Waterford",
    "sg:classifiers":[
        {
            "category":"Food & Beverages",
            "subcategory":"Specialty",
            "type":"Retail Goods"
        }
    ],
    "sg:phone":"+1 248 674 8982",
    "sg:postcode":"48329",
    "sg:province":"MI",
    "sg:tags":[
        "vitamin"
    ],
    "wof:name":"Nutri-Concepts",
    "wof:placetype":"venue"
},
  "geometry": {"coordinates":[-83.377206,42.689811],"type":"Point"}
}