{
  "type": "Feature",
  "properties": {
    "iso:country":"US",
    "sg:address":"44450 Pinetree Dr",
    "sg:city":"Plymouth",
    "sg:classifiers":[
        {
            "category":"Banks & Credit Unions",
            "subcategory":"Financial Services",
            "type":"Services"
        }
    ],
    "sg:phone":"+1 734 259 0724",
    "sg:postcode":"48170",
    "sg:province":"MI",
    "sg:tags":[
        "broker",
        "mortgage"
    ],
    "wof:name":"Vandyk Mortgage Corp",
    "wof:placetype":"venue"
},
  "geometry": {"coordinates":[-83.47962699999999,42.36023],"type":"Point"}
}