{
  "type": "Feature",
  "properties": {
    "iso:country":"US",
    "sg:address":"850 Stephenson Hwy",
    "sg:city":"Troy",
    "sg:classifiers":[
        {
            "category":"Health Services",
            "subcategory":"Clinic",
            "type":"Services"
        }
    ],
    "sg:phone":"+1 248 588 0069",
    "sg:postcode":"48083",
    "sg:province":"MI",
    "sg:tags":[
        "home"
    ],
    "wof:name":"Advanced Home Care Inc",
    "wof:placetype":"venue"
},
  "geometry": {"coordinates":[-83.120215,42.541391],"type":"Point"}
}