{
  "type": "Feature",
  "properties": {
    "iso:country":"US",
    "sg:address":"4474 E Monroe Rd",
    "sg:city":"Midland",
    "sg:classifiers":[
        {
            "category":"Building & Trades",
            "subcategory":"Electrical",
            "type":"Services"
        }
    ],
    "sg:phone":"+1 989 631 3760",
    "sg:postcode":"48642",
    "sg:province":"MI",
    "sg:tags":[
        "electrical",
        "contractor"
    ],
    "wof:name":"Hitchcock Electric",
    "wof:placetype":"venue"
},
  "geometry": {"coordinates":[-84.189357,43.683483],"type":"Point"}
}