{
  "type": "Feature",
  "properties": {
    "iso:country":"US",
    "sg:address":"68111 16th Ave",
    "sg:city":"South Haven",
    "sg:classifiers":[
        {
            "category":"Personal",
            "subcategory":"Beauty Salon",
            "type":"Services"
        }
    ],
    "sg:phone":"+1 269 637 8749",
    "sg:postcode":"49090",
    "sg:province":"MI",
    "sg:tags":[
        "shop"
    ],
    "wof:name":"Hair Craft Studio",
    "wof:placetype":"venue"
},
  "geometry": {"coordinates":[-86.20716,42.360507],"type":"Point"}
}