{
  "type": "Feature",
  "properties": {
    "iso:country":"US",
    "sg:address":"35450 Dequindre Rd",
    "sg:city":"Sterling Heights",
    "sg:classifiers":[
        {
            "category":"Shopping",
            "subcategory":"Pharmacy",
            "type":"Retail Goods"
        }
    ],
    "sg:phone":"+1 586 977 9192",
    "sg:postcode":"48310",
    "sg:province":"MI",
    "sg:tags":[
        "drugstore"
    ],
    "wof:name":"Maplecrest Drugs",
    "wof:placetype":"venue"
},
  "geometry": {"coordinates":[-83.088303,42.5527],"type":"Point"}
}