{
  "type": "Feature",
  "properties": {
    "iso:country":"US",
    "sg:address":"4030 Huron St",
    "sg:city":"North Branch",
    "sg:classifiers":[
        {
            "category":"Personal",
            "subcategory":"Beauty Salon",
            "type":"Services"
        }
    ],
    "sg:phone":"+1 810 688 3830",
    "sg:postcode":"48461",
    "sg:province":"MI",
    "sg:tags":[
        "shop"
    ],
    "wof:name":"Mikes Barber Shop",
    "wof:placetype":"venue"
},
  "geometry": {"coordinates":[-83.19520900000001,43.229335],"type":"Point"}
}