{
  "type": "Feature",
  "properties": {
    "iso:country":"US",
    "sg:address":"445 N Ortonville Rd",
    "sg:city":"Ortonville",
    "sg:classifiers":[
        {
            "category":"Wholesale",
            "subcategory":"Machinery & Supplies",
            "type":"Manufacturing & Wholesale Goods"
        }
    ],
    "sg:phone":"+1 248 627 3511",
    "sg:postcode":"48462",
    "sg:province":"MI",
    "sg:tags":[
        "pump"
    ],
    "wof:name":"Fleming Well Drilling",
    "wof:placetype":"venue"
},
  "geometry": {"coordinates":[-83.455556,42.856675],"type":"Point"}
}