{
  "type": "Feature",
  "properties": {
    "iso:country":"US",
    "sg:address":"325 Edwards St",
    "sg:city":"Grand Ledge",
    "sg:classifiers":[
        {
            "category":"Education",
            "subcategory":"School",
            "type":"Public Place"
        }
    ],
    "sg:phone":"+1 517 627 2167",
    "sg:postcode":"48837",
    "sg:province":"MI",
    "wof:name":"St Michaels School",
    "wof:placetype":"venue"
},
  "geometry": {"coordinates":[-84.746011,42.744544],"type":"Point"}
}