{
  "type": "Feature",
  "properties": {
    "iso:country":"US",
    "sg:address":"14145 Stony Point Rd",
    "sg:city":"Cheboygan",
    "sg:classifiers":[
        {
            "category":"Retail",
            "subcategory":"Auto Repair",
            "type":"Services"
        }
    ],
    "sg:phone":"+1 231 627 1100",
    "sg:postcode":"49721",
    "sg:province":"MI",
    "sg:tags":[
        "repairing",
        "automobile"
    ],
    "wof:name":"Jay's Auto Svc LLC",
    "wof:placetype":"venue"
},
  "geometry": {"coordinates":[-84.497803,45.665867],"type":"Point"}
}