{
  "type": "Feature",
  "properties": {
    "iso:country":"US",
    "sg:address":"327 8th St",
    "sg:city":"Ann Arbor",
    "sg:classifiers":[
        {
            "category":"Professional",
            "type":"Services"
        }
    ],
    "sg:phone":"+1 734 930 9666",
    "sg:postcode":"48103",
    "sg:province":"MI",
    "wof:name":"Stephen Rosoff",
    "wof:placetype":"venue"
},
  "geometry": {"coordinates":[-83.759728,42.280413],"type":"Point"}
}