{
  "type": "Feature",
  "properties": {
    "iso:country":"US",
    "sg:address":"6059 Norton Center Dr",
    "sg:city":"Muskegon",
    "sg:classifiers":[
        {
            "category":"Manufacturing",
            "subcategory":"Metals",
            "type":"Manufacturing & Wholesale Goods"
        }
    ],
    "sg:phone":"+1 231 798 7034",
    "sg:postcode":"49441",
    "sg:province":"MI",
    "sg:tags":[
        "hardware"
    ],
    "sg:website":"www.grandproducts.cc",
    "wof:name":"Grand Products",
    "wof:placetype":"venue"
},
  "geometry": {"coordinates":[-86.217974,43.142435],"type":"Point"}
}