{
  "type": "Feature",
  "properties": {
    "iso:country":"US",
    "sg:address":"140 Veterans Dr",
    "sg:city":"Fowlerville",
    "sg:classifiers":[
        {
            "category":"Autos & Motor Vehicles",
            "subcategory":"Auto Supplies",
            "type":"Retail Goods"
        }
    ],
    "sg:phone":"+1 517 223 9135",
    "sg:postcode":"48836",
    "sg:province":"MI",
    "sg:tags":[
        "automobile",
        "parts"
    ],
    "wof:name":"Carquest Auto Parts",
    "wof:placetype":"venue"
},
  "geometry": {"coordinates":[-84.077315,42.660161],"type":"Point"}
}