{
  "type": "Feature",
  "properties": {
    "iso:country":"US",
    "sg:address":"2500 Holmes Rd Unit 623",
    "sg:city":"Ypsilanti",
    "sg:classifiers":[
        {
            "category":"Building & Trades",
            "subcategory":"Construction",
            "type":"Services"
        }
    ],
    "sg:phone":"+1 734 480 7173",
    "sg:postcode":"48198",
    "sg:province":"MI",
    "sg:tags":[
        "painter"
    ],
    "wof:name":"George's Painting Service",
    "wof:placetype":"venue"
},
  "geometry": {"coordinates":[-83.563599,42.254002],"type":"Point"}
}