{
  "type": "Feature",
  "properties": {
    "iso:country":"US",
    "sg:address":"891 Goddard St",
    "sg:city":"Wyandotte",
    "sg:classifiers":[
        {
            "category":"Education",
            "subcategory":"School",
            "type":"Public Place"
        }
    ],
    "sg:phone":"+1 734 759 5900",
    "sg:postcode":"48192",
    "sg:province":"MI",
    "sg:tags":[
        "high",
        "middle",
        "elementary"
    ],
    "wof:name":"Wyandotte Public Schools",
    "wof:placetype":"venue"
},
  "geometry": {"coordinates":[-83.163505,42.223175],"type":"Point"}
}