{
  "type": "Feature",
  "properties": {
    "iso:country":"US",
    "sg:address":"20400 Woodmont St",
    "sg:city":"Harper Woods",
    "sg:classifiers":[
        {
            "category":"Building & Trades",
            "subcategory":"Construction",
            "type":"Services"
        }
    ],
    "sg:phone":"+1 313 882 6895",
    "sg:postcode":"48225",
    "sg:province":"MI",
    "sg:tags":[
        "house"
    ],
    "wof:name":"Adirondack Repair & Maint",
    "wof:placetype":"venue"
},
  "geometry": {"coordinates":[-82.92376299999999,42.437043],"type":"Point"}
}