{
  "type": "Feature",
  "properties": {
    "iso:country":"US",
    "sg:address":"18512 Outer Drive",
    "sg:city":"Dearborn",
    "sg:classifiers":[
        {
            "category":"Retail",
            "subcategory":"Laundry & Dry Cleaning",
            "type":"Services"
        }
    ],
    "sg:phone":"+1 313 565 5095",
    "sg:postcode":"48128",
    "sg:province":"MI",
    "wof:name":"Pioneer Dry Cleaning",
    "wof:placetype":"venue"
},
  "geometry": {"coordinates":[-83.257401,42.319871],"type":"Point"}
}