{
  "type": "Feature",
  "properties": {
    "iso:country":"US",
    "sg:address":"1257 S Main St",
    "sg:city":"Plymouth",
    "sg:classifiers":[
        {
            "category":"Personal",
            "subcategory":"Tattoo Parlor",
            "type":"Services"
        }
    ],
    "sg:phone":"+1 734 455 6980",
    "sg:postcode":"48170",
    "sg:province":"MI",
    "wof:name":"That's My Color Salon",
    "wof:placetype":"venue"
},
  "geometry": {"coordinates":[-83.469498,42.361099],"type":"Point"}
}