{
  "type": "Feature",
  "properties": {
    "iso:country":"US",
    "sg:address":"38 N Division St",
    "sg:city":"Hesperia",
    "sg:classifiers":[
        {
            "category":"Health Services",
            "subcategory":"Doctor",
            "type":"Services"
        }
    ],
    "sg:phone":"+1 231 854 2601",
    "sg:postcode":"49421",
    "sg:province":"MI",
    "wof:name":"Horton Ralph E DDS PC",
    "wof:placetype":"venue"
},
  "geometry": {"coordinates":[-86.039585,43.568458],"type":"Point"}
}