{
  "type": "Feature",
  "properties": {
    "iso:country":"US",
    "sg:address":"5749 Beebe Ave",
    "sg:city":"Warren",
    "sg:classifiers":[
        {
            "category":"Professional",
            "subcategory":"Management & Consulting",
            "type":"Services"
        }
    ],
    "sg:phone":"+1 586 268 8050",
    "sg:postcode":"48092",
    "sg:province":"MI",
    "sg:tags":[
        "fleet"
    ],
    "wof:name":"Qek Global Solutions US LP",
    "wof:placetype":"venue"
},
  "geometry": {"coordinates":[-83.04775600000001,42.525095],"type":"Point"}
}