{
  "type": "Feature",
  "properties": {
    "iso:country":"US",
    "sg:address":"9460 Camley St",
    "sg:city":"Detroit",
    "sg:classifiers":[
        {
            "category":"Real Estate",
            "subcategory":"Real Estate Operator",
            "type":"Services"
        }
    ],
    "sg:phone":"+1 313 642 0249",
    "sg:postcode":"48224",
    "sg:province":"MI",
    "sg:tags":[
        "building",
        "nonresidential"
    ],
    "wof:name":"Linwood Property Development",
    "wof:placetype":"venue"
},
  "geometry": {"coordinates":[-82.932374,42.422072],"type":"Point"}
}