{
  "type": "Feature",
  "properties": {
    "iso:country":"US",
    "sg:address":"620 Graceland St NE",
    "sg:city":"Grand Rapids",
    "sg:classifiers":[
        {
            "category":"Wholesale",
            "subcategory":"Electrical",
            "type":"Manufacturing & Wholesale Goods"
        }
    ],
    "sg:phone":"+1 616 301 7773",
    "sg:postcode":"49505",
    "sg:province":"MI",
    "sg:tags":[
        "telephone"
    ],
    "wof:name":"Burns Group",
    "wof:placetype":"venue"
},
  "geometry": {"coordinates":[-85.65432,43.000594],"type":"Point"}
}