{
  "type": "Feature",
  "properties": {
    "iso:country":"US",
    "sg:address":"4797 Pickering Rd",
    "sg:city":"Bloomfield Hills",
    "sg:classifiers":[
        {
            "category":"Professional",
            "subcategory":"Management & Consulting",
            "type":"Services"
        }
    ],
    "sg:phone":"+1 248 626 6854",
    "sg:postcode":"48301",
    "sg:province":"MI",
    "sg:tags":[
        "business"
    ],
    "wof:name":"E A Whitefield Consulting",
    "wof:placetype":"venue"
},
  "geometry": {"coordinates":[-83.31271599999999,42.531813],"type":"Point"}
}