{
  "type": "Feature",
  "properties": {
    "iso:country":"US",
    "sg:address":"6217 Greenview Dr",
    "sg:city":"Burton",
    "sg:classifiers":[
        {
            "category":"Home & Garden",
            "subcategory":"Home Furnishings",
            "type":"Retail Goods"
        }
    ],
    "sg:phone":"+1 810 743 4726",
    "sg:postcode":"48509",
    "sg:province":"MI",
    "sg:tags":[
        "curtain",
        "made",
        "drapery"
    ],
    "wof:name":"Barbara's Draperies",
    "wof:placetype":"venue"
},
  "geometry": {"coordinates":[-83.588246,43.042793],"type":"Point"}
}