{
  "type": "Feature",
  "properties": {
    "iso:country":"US",
    "sg:address":"5660 Lantana Ave",
    "sg:city":"Kalamazoo",
    "sg:classifiers":[
        {
            "category":"Building & Trades",
            "subcategory":"Plumbing",
            "type":"Services"
        }
    ],
    "sg:phone":"+1 269 552 4220",
    "sg:postcode":"49048",
    "sg:province":"MI",
    "sg:tags":[
        "plumbing",
        "contractor"
    ],
    "wof:name":"J & J Plumbing",
    "wof:placetype":"venue"
},
  "geometry": {"coordinates":[-85.51948299999999,42.300842],"type":"Point"}
}