{
  "type": "Feature",
  "properties": {
    "iso:country":"US",
    "sg:address":"6362 Almond Ln",
    "sg:city":"Clarkston",
    "sg:classifiers":[
        {
            "category":"Social Services",
            "type":"Services"
        }
    ],
    "sg:phone":"+1 248 625 8261",
    "sg:postcode":"48346",
    "sg:province":"MI",
    "wof:name":"Richard Carrier Msw Csw",
    "wof:placetype":"venue"
},
  "geometry": {"coordinates":[-83.39822599999999,42.7304],"type":"Point"}
}