{
  "type": "Feature",
  "properties": {
    "iso:country":"US",
    "sg:address":"3393 N M 52",
    "sg:city":"Stockbridge",
    "sg:classifiers":[
        {
            "category":"Shopping",
            "subcategory":"Used Merchandise",
            "type":"Retail Goods"
        }
    ],
    "sg:phone":"+1 517 851 7677",
    "sg:postcode":"49285",
    "sg:province":"MI",
    "wof:name":"Hafner Antiques",
    "wof:placetype":"venue"
},
  "geometry": {"coordinates":[-84.19001400000001,42.472003],"type":"Point"}
}