{
  "type": "Feature",
  "properties": {
    "iso:country":"US",
    "sg:address":"711 S Marvel Dr",
    "sg:city":"Greenville",
    "sg:classifiers":[
        {
            "category":"Wholesale",
            "subcategory":"Hardware",
            "type":"Manufacturing & Wholesale Goods"
        }
    ],
    "sg:phone":"+1 616 754 7681",
    "sg:postcode":"48838",
    "sg:province":"MI",
    "sg:tags":[
        "purifying",
        "cleaning",
        "air"
    ],
    "wof:name":"Clean Air Technologies",
    "wof:placetype":"venue"
},
  "geometry": {"coordinates":[-85.267714,43.174491],"type":"Point"}
}