{
  "type": "Feature",
  "properties": {
    "iso:country":"US",
    "sg:address":"428 West Ave",
    "sg:city":"Big Rapids",
    "sg:classifiers":[
        {
            "category":"Organizations",
            "subcategory":"Religious Organization",
            "type":"Services"
        }
    ],
    "sg:phone":"+1 231 796 4433",
    "sg:postcode":"49307",
    "sg:province":"MI",
    "sg:tags":[
        "church"
    ],
    "wof:name":"Lighthouse Apostolic Church",
    "wof:placetype":"venue"
},
  "geometry": {"coordinates":[-85.492542,43.712874],"type":"Point"}
}