{
  "type": "Feature",
  "properties": {
    "iso:country":"US",
    "sg:address":"27208 Eureka Rd",
    "sg:city":"Taylor",
    "sg:classifiers":[
        {
            "category":"Shopping",
            "subcategory":"Department Store",
            "type":"Retail Goods"
        }
    ],
    "sg:phone":"+1 734 942 1810",
    "sg:postcode":"48180",
    "sg:province":"MI",
    "sg:website":"www.familydollar.com",
    "wof:name":"Family Dollar Stores Inc",
    "wof:placetype":"venue"
},
  "geometry": {"coordinates":[-83.305435,42.196204],"type":"Point"}
}