{
  "type": "Feature",
  "properties": {
    "iso:country":"US",
    "sg:address":"344 N Main St",
    "sg:city":"Milford",
    "sg:classifiers":[
        {
            "category":"Banks & Credit Unions",
            "subcategory":"Bank",
            "type":"Services"
        }
    ],
    "sg:phone":"+1 248 684 1165",
    "sg:postcode":"48381",
    "sg:province":"MI",
    "sg:tags":[
        "national",
        "commercial"
    ],
    "wof:name":"National City Bank",
    "wof:placetype":"venue"
},
  "geometry": {"coordinates":[-83.60023200000001,42.590123],"type":"Point"}
}