{
  "type": "Feature",
  "properties": {
    "iso:country":"US",
    "sg:address":"133 N Cass Ave",
    "sg:city":"Vassar",
    "sg:classifiers":[
        {
            "category":"Arena",
            "subcategory":"Sports Club",
            "type":"Entertainment"
        }
    ],
    "sg:phone":"+1 989 823 2265",
    "sg:postcode":"48768",
    "sg:province":"MI",
    "wof:name":"Vassar Fishing Club",
    "wof:placetype":"venue"
},
  "geometry": {"coordinates":[-83.580746,43.372161],"type":"Point"}
}