{
  "type": "Feature",
  "properties": {
    "iso:country":"US",
    "sg:address":"1050 W Southern Ave",
    "sg:city":"Muskegon",
    "sg:classifiers":[
        {
            "category":"Organizations",
            "subcategory":"Religious Organization",
            "type":"Services"
        }
    ],
    "sg:phone":"+1 231 722 3046",
    "sg:postcode":"49441",
    "sg:province":"MI",
    "sg:website":"www.olivetefc.org",
    "wof:name":"Olivet Evangelical Free Church",
    "wof:placetype":"venue"
},
  "geometry": {"coordinates":[-86.270454,43.224499],"type":"Point"}
}