{
  "type": "Feature",
  "properties": {
    "iso:country":"US",
    "sg:address":"16720 US Hwy 12",
    "sg:city":"Cement City",
    "sg:classifiers":[
        {
            "category":"Manufacturing",
            "subcategory":"Metals",
            "type":"Manufacturing & Wholesale Goods"
        }
    ],
    "sg:phone":"+1 517 592 8605",
    "sg:postcode":"49233",
    "sg:province":"MI",
    "sg:tags":[
        "stamping"
    ],
    "sg:website":"www.rossdesign.net",
    "wof:name":"Ross Design",
    "wof:placetype":"venue"
},
  "geometry": {"coordinates":[-84.319211,42.049203],"type":"Point"}
}