{
  "type": "Feature",
  "properties": {
    "iso:country":"US",
    "sg:address":"8525 Jon-Era Ln",
    "sg:city":"Howell",
    "sg:classifiers":[
        {
            "category":"Wholesale",
            "subcategory":"Medical Equipment & Supplies",
            "type":"Manufacturing & Wholesale Goods"
        }
    ],
    "sg:phone":"+1 517 546 6616",
    "sg:postcode":"48855",
    "sg:province":"MI",
    "sg:tags":[
        "hospital"
    ],
    "wof:name":"Healthcare Furniture",
    "wof:placetype":"venue"
},
  "geometry": {"coordinates":[-83.93643299999999,42.71996],"type":"Point"}
}