{
  "type": "Feature",
  "properties": {
    "iso:country":"US",
    "sg:address":"2652 Hoyt St",
    "sg:city":"Muskegon",
    "sg:classifiers":[
        {
            "category":"Manufacturing",
            "subcategory":"Metals",
            "type":"Manufacturing & Wholesale Goods"
        }
    ],
    "sg:phone":"+1 231 733 9736",
    "sg:postcode":"49444",
    "sg:province":"MI",
    "sg:tags":[
        "plating"
    ],
    "wof:name":"Metal Finishing Technology",
    "wof:placetype":"venue"
},
  "geometry": {"coordinates":[-86.2396,43.204098],"type":"Point"}
}