{
  "type": "Feature",
  "properties": {
    "iso:country":"US",
    "sg:address":"14431 124th Ave",
    "sg:city":"Grand Haven",
    "sg:classifiers":[
        {
            "category":"Insurance",
            "subcategory":"Insurance Agent",
            "type":"Services"
        }
    ],
    "sg:phone":"+1 616 844 7092",
    "sg:postcode":"49417",
    "sg:province":"MI",
    "wof:name":"Nationwide Insurance",
    "wof:placetype":"venue"
},
  "geometry": {"coordinates":[-86.09617299999999,43.032217],"type":"Point"}
}