{
  "type": "Feature",
  "properties": {
    "iso:country":"US",
    "sg:address":"17 N 17th St",
    "sg:city":"Battle Creek",
    "sg:classifiers":[
        {
            "category":"Building & Trades",
            "subcategory":"Landscaping Services",
            "type":"Services"
        }
    ],
    "sg:phone":"+1 269 660 0824",
    "sg:postcode":"49015",
    "sg:province":"MI",
    "wof:name":"Leatherman Land & Lawn Co",
    "wof:placetype":"venue"
},
  "geometry": {"coordinates":[-85.217443,42.323561],"type":"Point"}
}