{
  "type": "Feature",
  "properties": {
    "iso:country":"US",
    "sg:address":"68798 6th St",
    "sg:city":"Edwardsburg",
    "sg:classifiers":[
        {
            "category":"Autos & Motor Vehicles",
            "subcategory":"Boat Sales",
            "type":"Retail Goods"
        }
    ],
    "sg:phone":"+1 269 699 5601",
    "sg:postcode":"49112",
    "sg:province":"MI",
    "wof:name":"Anthony Nasco",
    "wof:placetype":"venue"
},
  "geometry": {"coordinates":[-86.028463,41.796313],"type":"Point"}
}