{
  "type": "Feature",
  "properties": {
    "iso:country":"US",
    "sg:address":"10008 Highland Rd",
    "sg:city":"Hartland",
    "sg:classifiers":[
        {
            "category":"Building & Trades",
            "subcategory":"Construction",
            "type":"Services"
        }
    ],
    "sg:phone":"+1 810 632 0636",
    "sg:postcode":"48353",
    "sg:province":"MI",
    "sg:tags":[
        "home",
        "improvement"
    ],
    "wof:name":"Creative Closet Designs",
    "wof:placetype":"venue"
},
  "geometry": {"coordinates":[-83.752881,42.633015],"type":"Point"}
}