{
  "type": "Feature",
  "properties": {
    "iso:country":"US",
    "sg:address":"110 N Clinton Ave",
    "sg:city":"St Johns",
    "sg:classifiers":[
        {
            "category":"Restaurant",
            "type":"Food & Drink"
        }
    ],
    "sg:phone":"+1 989 224 7188",
    "sg:postcode":"48879",
    "sg:province":"MI",
    "wof:name":"Kar-Cello's Coffee House",
    "wof:placetype":"venue"
},
  "geometry": {"coordinates":[-84.55839,43.002323],"type":"Point"}
}