{
  "type": "Feature",
  "properties": {
    "iso:country":"US",
    "sg:address":"719 Capital Ave SW",
    "sg:city":"Battle Creek",
    "sg:classifiers":[
        {
            "category":"Health Services",
            "subcategory":"Doctor",
            "type":"Services"
        }
    ],
    "sg:phone":"+1 269 969 6060",
    "sg:postcode":"49015",
    "sg:province":"MI",
    "sg:tags":[
        "medical"
    ],
    "wof:name":"Oakes Robert W MD PC",
    "wof:placetype":"venue"
},
  "geometry": {"coordinates":[-85.199404,42.301279],"type":"Point"}
}