{
  "type": "Feature",
  "properties": {
    "iso:country":"US",
    "sg:address":"2211 Nottawa Lake Dr",
    "sg:city":"Marshall",
    "sg:classifiers":[
        {
            "category":"Wholesale",
            "subcategory":"Groceries",
            "type":"Manufacturing & Wholesale Goods"
        }
    ],
    "sg:phone":"+1 517 767 3532",
    "sg:postcode":"49068",
    "sg:province":"MI",
    "sg:tags":[
        "confectionery"
    ],
    "wof:name":"Ke Walters Distributing I",
    "wof:placetype":"venue"
},
  "geometry": {"coordinates":[-84.982404,42.152114],"type":"Point"}
}