{
  "type": "Feature",
  "properties": {
    "iso:country":"US",
    "sg:address":"1022 Northlawn St NE",
    "sg:city":"Grand Rapids",
    "sg:classifiers":[
        {
            "category":"Building & Trades",
            "subcategory":"Construction",
            "type":"Services"
        }
    ],
    "sg:phone":"+1 616 364 0307",
    "sg:postcode":"49505",
    "sg:province":"MI",
    "sg:tags":[
        "hanging",
        "contractor"
    ],
    "wof:name":"Schutz & Ladder Paint Company",
    "wof:placetype":"venue"
},
  "geometry": {"coordinates":[-85.644184,43.009748],"type":"Point"}
}