{
  "type": "Feature",
  "properties": {
    "iso:country":"US",
    "sg:address":"27772 Novi Rd",
    "sg:city":"Novi",
    "sg:classifiers":[
        {
            "category":"Professional",
            "subcategory":"Business Services",
            "type":"Services"
        }
    ],
    "sg:phone":"+1 248 349 4600",
    "sg:postcode":"48377",
    "sg:province":"MI",
    "sg:tags":[
        "interior",
        "consultant",
        "design",
        "decorator"
    ],
    "wof:name":"Newton Furniture Inc",
    "wof:placetype":"venue"
},
  "geometry": {"coordinates":[-83.476106,42.49393],"type":"Point"}
}