{
  "type": "Feature",
  "properties": {
    "iso:country":"US",
    "sg:address":"2870 Eddy St",
    "sg:city":"Saginaw",
    "sg:classifiers":[
        {
            "category":"Freight",
            "type":"Transportation"
        }
    ],
    "sg:phone":"+1 989 753 5918",
    "sg:postcode":"48604",
    "sg:province":"MI",
    "sg:tags":[
        "consultant"
    ],
    "wof:name":"Towne Air Freight",
    "wof:placetype":"venue"
},
  "geometry": {"coordinates":[-83.94873800000001,43.446392],"type":"Point"}
}