{
  "type": "Feature",
  "properties": {
    "iso:country":"US",
    "sg:address":"413 S 5 Mile Rd",
    "sg:city":"Midland",
    "sg:classifiers":[
        {
            "category":"Building & Trades",
            "subcategory":"Electrical",
            "type":"Services"
        }
    ],
    "sg:phone":"+1 989 835 3587",
    "sg:postcode":"48640",
    "sg:province":"MI",
    "sg:tags":[
        "electric",
        "contractor"
    ],
    "wof:name":"Select Electric",
    "wof:placetype":"venue"
},
  "geometry": {"coordinates":[-84.35020799999999,43.603824],"type":"Point"}
}