{
  "type": "Feature",
  "properties": {
    "iso:country":"US",
    "sg:address":"5638 McMillan St",
    "sg:city":"Detroit",
    "sg:classifiers":[
        {
            "category":"Building & Trades",
            "subcategory":"Construction",
            "type":"Services"
        }
    ],
    "sg:phone":"+1 313 841 6839",
    "sg:postcode":"48209",
    "sg:province":"MI",
    "sg:tags":[
        "residential"
    ],
    "wof:name":"Pacos Mother House",
    "wof:placetype":"venue"
},
  "geometry": {"coordinates":[-83.10467800000001,42.31879],"type":"Point"}
}