{
  "type": "Feature",
  "properties": {
    "iso:country":"US",
    "sg:address":"1030 Featherstone St",
    "sg:city":"Pontiac",
    "sg:classifiers":[
        {
            "category":"Professional",
            "subcategory":"Business Services",
            "type":"Services"
        }
    ],
    "sg:phone":"+1 248 874 3400",
    "sg:postcode":"48342",
    "sg:province":"MI",
    "sg:tags":[
        "notification",
        "provides",
        "utility"
    ],
    "wof:name":"Miss Dig System Inc",
    "wof:placetype":"venue"
},
  "geometry": {"coordinates":[-83.259906,42.648815],"type":"Point"}
}