{
  "type": "Feature",
  "properties": {
    "iso:country":"US",
    "sg:address":"208 W Pearl St",
    "sg:city":"Coldwater",
    "sg:classifiers":[
        {
            "category":"Professional",
            "subcategory":"Research",
            "type":"Services"
        },
        {
            "category":"Manufacturing",
            "subcategory":"Tools & Machinery",
            "type":"Manufacturing & Wholesale Goods"
        }
    ],
    "sg:phone":"+1 517 278 3484",
    "sg:postcode":"49036",
    "sg:province":"MI",
    "sg:tags":[
        "measuring",
        "development",
        "mfg",
        "commercial",
        "instrument",
        "electrical",
        "electronic"
    ],
    "wof:name":"Thermotronics",
    "wof:placetype":"venue"
},
  "geometry": {"coordinates":[-85.010256,41.940895],"type":"Point"}
}