{
  "type": "Feature",
  "properties": {
    "iso:country":"US",
    "sg:address":"3830 Crooks Rd",
    "sg:city":"Troy",
    "sg:classifiers":[
        {
            "category":"Place Of Worship",
            "subcategory":"Church",
            "type":"Public Place"
        }
    ],
    "sg:phone":"+1 248 244 9545",
    "sg:postcode":"48084",
    "sg:province":"MI",
    "sg:website":"www.cofchrist-troyoaks.org",
    "wof:name":"Community of Christ-Troy Oaks",
    "wof:placetype":"venue"
},
  "geometry": {"coordinates":[-83.167603,42.573502],"type":"Point"}
}