{
  "type": "Feature",
  "properties": {
    "iso:country":"US",
    "sg:address":"1341 Coolidge Hwy",
    "sg:city":"Troy",
    "sg:classifiers":[
        {
            "category":"Freight",
            "type":"Transportation"
        },
        {
            "category":"Professional",
            "subcategory":"Printing & Photocopies",
            "type":"Services"
        }
    ],
    "sg:phone":"+1 248 643 6316",
    "sg:postcode":"48084",
    "sg:province":"MI",
    "sg:tags":[
        "shipping"
    ],
    "sg:website":"www.fedex.com/us/office/",
    "wof:name":"FedEx Office Ship Center",
    "wof:placetype":"venue"
},
  "geometry": {"coordinates":[-83.18634400000001,42.546327],"type":"Point"}
}