{
  "type": "Feature",
  "properties": {
    "iso:country":"US",
    "sg:address":"58990 Van Dyke Rd",
    "sg:city":"Washington",
    "sg:classifiers":[
        {
            "category":"Retail",
            "subcategory":"Car Wash",
            "type":"Services"
        }
    ],
    "sg:phone":"+1 586 992 9985",
    "sg:postcode":"48094",
    "sg:province":"MI",
    "sg:tags":[
        "polishing",
        "washing"
    ],
    "wof:name":"Washington Carwash Inc",
    "wof:placetype":"venue"
},
  "geometry": {"coordinates":[-83.035971,42.727002],"type":"Point"}
}