{
  "type": "Feature",
  "properties": {
    "iso:country":"US",
    "sg:address":"8800 W D Ave",
    "sg:city":"Kalamazoo",
    "sg:classifiers":[
        {
            "category":"Farming",
            "subcategory":"Livestock Farm",
            "type":"Manufacturing & Wholesale Goods"
        }
    ],
    "sg:phone":"+1 269 344 8511",
    "sg:postcode":"49009",
    "sg:province":"MI",
    "sg:tags":[
        "hog",
        "or",
        "feedlot"
    ],
    "wof:name":"Bachelder Farms",
    "wof:placetype":"venue"
},
  "geometry": {"coordinates":[-85.74342,42.375134],"type":"Point"}
}