{
  "type": "Feature",
  "properties": {
    "iso:country":"US",
    "sg:address":"917 Midland Rd",
    "sg:city":"Bay City",
    "sg:classifiers":[
        {
            "category":"Freight",
            "type":"Transportation"
        }
    ],
    "sg:phone":"+1 989 684 5905",
    "sg:postcode":"48706",
    "sg:province":"MI",
    "sg:tags":[
        "operator",
        "local",
        "trucking"
    ],
    "wof:name":"D&D Trucking",
    "wof:placetype":"venue"
},
  "geometry": {"coordinates":[-84.026515,43.603571],"type":"Point"}
}