{
  "type": "Feature",
  "properties": {
    "iso:country":"US",
    "sg:address":"36869 Heatherton Dr",
    "sg:city":"Farmington",
    "sg:classifiers":[
        {
            "category":"Professional",
            "subcategory":"Management & Consulting",
            "type":"Services"
        }
    ],
    "sg:phone":"+1 248 477 7545",
    "sg:postcode":"48335",
    "sg:province":"MI",
    "sg:tags":[
        "business"
    ],
    "wof:name":"J ORourke Consulting LLC",
    "wof:placetype":"venue"
},
  "geometry": {"coordinates":[-83.412943,42.464142],"type":"Point"}
}