{
  "type": "Feature",
  "properties": {
    "iso:country":"US",
    "sg:address":"685 9th St",
    "sg:city":"Wyandotte",
    "sg:classifiers":[
        {
            "category":"Building & Trades",
            "subcategory":"Plumbing",
            "type":"Services"
        }
    ],
    "sg:phone":"+1 734 285 8609",
    "sg:postcode":"48192",
    "sg:province":"MI",
    "sg:tags":[
        "contractor"
    ],
    "wof:name":"RMS Heating & Cooling",
    "wof:placetype":"venue"
},
  "geometry": {"coordinates":[-83.163916,42.22788],"type":"Point"}
}