{
  "type": "Feature",
  "properties": {
    "iso:country":"US",
    "sg:address":"26451 Raine St",
    "sg:city":"Oak Park",
    "sg:classifiers":[
        {
            "category":"Professional",
            "subcategory":"Art Services",
            "type":"Services"
        }
    ],
    "sg:phone":"+1 248 541 2219",
    "sg:postcode":"48237",
    "sg:province":"MI",
    "sg:tags":[
        "commercial",
        "design"
    ],
    "wof:name":"Nachman Levine Design",
    "wof:placetype":"venue"
},
  "geometry": {"coordinates":[-83.19807,42.485646],"type":"Point"}
}