{
  "type": "Feature",
  "properties": {
    "iso:country":"US",
    "sg:address":"29430 Chatham Ct",
    "sg:city":"Southfield",
    "sg:classifiers":[
        {
            "category":"Professional",
            "subcategory":"Engineering",
            "type":"Services"
        }
    ],
    "sg:phone":"+1 248 358 4863",
    "sg:postcode":"48076",
    "sg:province":"MI",
    "wof:name":"R M Williams Engineering Cons",
    "wof:placetype":"venue"
},
  "geometry": {"coordinates":[-83.246274,42.504617],"type":"Point"}
}