{
  "type": "Feature",
  "properties": {
    "iso:country":"US",
    "sg:address":"1115 S Washington Ave",
    "sg:city":"Lansing",
    "sg:classifiers":[
        {
            "category":"Restaurant",
            "type":"Food & Drink"
        }
    ],
    "sg:phone":"+1 517 853 1912",
    "sg:postcode":"48910",
    "sg:province":"MI",
    "wof:name":"Cadillac Club",
    "wof:placetype":"venue"
},
  "geometry": {"coordinates":[-84.55229,42.720959],"type":"Point"}
}