{
  "type": "Feature",
  "properties": {
    "iso:country":"US",
    "sg:address":"1350 Waterways Dr",
    "sg:city":"Ann Arbor",
    "sg:classifiers":[
        {
            "category":"Professional",
            "subcategory":"Management & Consulting",
            "type":"Services"
        }
    ],
    "sg:phone":"+1 734 332 3405",
    "sg:postcode":"48108",
    "sg:province":"MI",
    "sg:tags":[
        "educational",
        "author"
    ],
    "wof:name":"Edward Waltz",
    "wof:placetype":"venue"
},
  "geometry": {"coordinates":[-83.74929899999999,42.208414],"type":"Point"}
}