{
  "type": "Feature",
  "properties": {
    "iso:country":"US",
    "sg:address":"2203 Red Maple Dr",
    "sg:city":"Troy",
    "sg:classifiers":[
        {
            "category":"Professional",
            "subcategory":"Management & Consulting",
            "type":"Services"
        }
    ],
    "sg:phone":"+1 248 828 8622",
    "sg:postcode":"48098",
    "sg:province":"MI",
    "wof:name":"Intergrity Leasing",
    "wof:placetype":"venue"
},
  "geometry": {"coordinates":[-83.191834,42.610579],"type":"Point"}
}