{
  "type": "Feature",
  "properties": {
    "iso:country":"US",
    "sg:address":"10269 US Hwy 31 N",
    "sg:city":"Charlevoix",
    "sg:classifiers":[
        {
            "category":"Professional",
            "subcategory":"Business Services",
            "type":"Services"
        }
    ],
    "sg:phone":"+1 231 547 8411",
    "sg:postcode":"49720",
    "sg:province":"MI",
    "wof:name":"Bnfl Inc",
    "wof:placetype":"venue"
},
  "geometry": {"coordinates":[-85.194542,45.345342],"type":"Point"}
}