{
  "type": "Feature",
  "properties": {
    "iso:country":"US",
    "sg:address":"17145 E 9 Mile Rd",
    "sg:city":"Eastpointe",
    "sg:classifiers":[
        {
            "category":"Wholesale",
            "subcategory":"Home Furnishings",
            "type":"Manufacturing & Wholesale Goods"
        }
    ],
    "sg:phone":"+1 586 775 5811",
    "sg:postcode":"48021",
    "sg:province":"MI",
    "sg:tags":[
        "blind",
        "shade"
    ],
    "wof:name":"Hahn Paint Co",
    "wof:placetype":"venue"
},
  "geometry": {"coordinates":[-82.94499999999999,42.465],"type":"Point"}
}