{
  "type": "Feature",
  "properties": {
    "iso:country":"US",
    "sg:address":"11782 Monsbrook Ct",
    "sg:city":"Sterling Heights",
    "sg:classifiers":[
        {
            "category":"Retail",
            "subcategory":"Animal Services",
            "type":"Services"
        }
    ],
    "sg:phone":"+1 586 939 3622",
    "sg:postcode":"48312",
    "sg:province":"MI",
    "wof:name":"Four Paws Pantry",
    "wof:placetype":"venue"
},
  "geometry": {"coordinates":[-83.008938,42.577632],"type":"Point"}
}