{
  "type": "Feature",
  "properties": {
    "iso:country":"US",
    "sg:address":"26285 Hoover Rd",
    "sg:city":"Warren",
    "sg:classifiers":[
        {
            "category":"Shopping",
            "subcategory":"Department Store",
            "type":"Retail Goods"
        }
    ],
    "sg:phone":"+1 586 757 4050",
    "sg:postcode":"48089",
    "sg:province":"MI",
    "wof:name":"T J Maxx",
    "wof:placetype":"venue"
},
  "geometry": {"coordinates":[-83.006445,42.485958],"type":"Point"}
}