{
  "type": "Feature",
  "properties": {
    "iso:country":"US",
    "sg:address":"3243 E Paris Ave SE",
    "sg:city":"Kentwood",
    "sg:classifiers":[
        {
            "category":"Real Estate",
            "subcategory":"Real Estate Agent",
            "type":"Services"
        }
    ],
    "sg:phone":"+1 616 956 7722",
    "sg:postcode":"49512",
    "sg:province":"MI",
    "sg:tags":[
        "management"
    ],
    "wof:name":"Cambridge Partners Inc",
    "wof:placetype":"venue"
},
  "geometry": {"coordinates":[-85.568254,42.904253],"type":"Point"}
}