{
  "type": "Feature",
  "properties": {
    "iso:country":"US",
    "sg:address":"4035 Broadmoor Ave SE",
    "sg:city":"Kentwood",
    "sg:classifiers":[
        {
            "category":"Building & Trades",
            "subcategory":"Construction",
            "type":"Services"
        }
    ],
    "sg:phone":"+1 616 940 0685",
    "sg:postcode":"49512",
    "sg:province":"MI",
    "sg:tags":[
        "siding",
        "contractor"
    ],
    "sg:website":"www.pacesettercorp.com",
    "wof:name":"Pacesetter Corp",
    "wof:placetype":"venue"
},
  "geometry": {"coordinates":[-85.56962799999999,42.888501],"type":"Point"}
}