{
  "type": "Feature",
  "properties": {
    "iso:country":"US",
    "sg:address":"4125 Cedar Run Rd",
    "sg:city":"Traverse City",
    "sg:classifiers":[
        {
            "category":"Health Services",
            "subcategory":"Doctor",
            "type":"Services"
        }
    ],
    "sg:phone":"+1 231 947 1886",
    "sg:postcode":"49684",
    "sg:province":"MI",
    "sg:tags":[
        "physician",
        "surgeon"
    ],
    "wof:name":"Larry G Thompson MD",
    "wof:placetype":"venue"
},
  "geometry": {"coordinates":[-85.66004,44.760333],"type":"Point"}
}