{
  "type": "Feature",
  "properties": {
    "iso:country":"US",
    "sg:address":"1215 Gratiot Blvd",
    "sg:city":"Marysville",
    "sg:classifiers":[
        {
            "category":"Autos & Motor Vehicles",
            "subcategory":"Auto Supplies",
            "type":"Retail Goods"
        }
    ],
    "sg:phone":"+1 810 364 9416",
    "sg:postcode":"48040",
    "sg:province":"MI",
    "sg:tags":[
        "automobile",
        "alarm"
    ],
    "wof:name":"Auto Stylers & Rv",
    "wof:placetype":"venue"
},
  "geometry": {"coordinates":[-82.474518,42.921025],"type":"Point"}
}