{
  "type": "Feature",
  "properties": {
    "iso:country":"US",
    "sg:address":"16596 Harlow St",
    "sg:city":"Detroit",
    "sg:classifiers":[
        {
            "category":"Social Services",
            "subcategory":"Child Care",
            "type":"Services"
        }
    ],
    "sg:phone":"+1 313 835 0239",
    "sg:postcode":"48235",
    "sg:province":"MI",
    "sg:tags":[
        "day"
    ],
    "wof:name":"Moms Touch Daycare",
    "wof:placetype":"venue"
},
  "geometry": {"coordinates":[-83.21534699999999,42.41112],"type":"Point"}
}