{
  "type": "Feature",
  "properties": {
    "iso:country":"US",
    "sg:address":"1375 N Leroy St",
    "sg:city":"Fenton",
    "sg:classifiers":[
        {
            "category":"Autos & Motor Vehicles",
            "subcategory":"Fuel & Gas Station",
            "type":"Retail Goods"
        }
    ],
    "sg:phone":"+1 810 629 0252",
    "sg:postcode":"48430",
    "sg:province":"MI",
    "sg:tags":[
        "oil"
    ],
    "wof:name":"A & J Plus Inc",
    "wof:placetype":"venue"
},
  "geometry": {"coordinates":[-83.707508,42.813958],"type":"Point"}
}