{
  "type": "Feature",
  "properties": {
    "iso:country":"US",
    "sg:address":"225 W Grand River Ave",
    "sg:city":"Williamston",
    "sg:classifiers":[
        {
            "category":"Banks & Credit Unions",
            "subcategory":"Bank",
            "type":"Services"
        }
    ],
    "sg:phone":"+1 517 655 2178",
    "sg:postcode":"48895",
    "sg:province":"MI",
    "sg:tags":[
        "state",
        "commercial"
    ],
    "wof:name":"Fifth Third Bank",
    "wof:placetype":"venue"
},
  "geometry": {"coordinates":[-84.286615,42.688415],"type":"Point"}
}