{
  "type": "Feature",
  "properties": {
    "iso:country":"US",
    "sg:address":"15110 Mack Ave",
    "sg:city":"Grosse Pointe Park",
    "sg:classifiers":[
        {
            "category":"Restaurant",
            "type":"Food & Drink"
        },
        {
            "category":"Bars & Pubs",
            "subcategory":"Nightclub",
            "type":"Food & Drink"
        }
    ],
    "sg:phone":"+1 313 822 1270",
    "sg:postcode":"48230",
    "sg:province":"MI",
    "sg:tags":[
        "mexican",
        "nightlife"
    ],
    "wof:name":"Sierra Station",
    "wof:placetype":"venue"
},
  "geometry": {"coordinates":[-82.945106,42.38746],"type":"Point"}
}