{
  "type": "Feature",
  "properties": {
    "iso:country":"US",
    "sg:address":"1254 Morningside St",
    "sg:city":"Muskegon",
    "sg:classifiers":[
        {
            "category":"Building & Trades",
            "subcategory":"Construction",
            "type":"Services"
        }
    ],
    "sg:phone":"+1 231 773 4028",
    "sg:postcode":"49442",
    "sg:province":"MI",
    "sg:tags":[
        "house"
    ],
    "wof:name":"Klunder Construction",
    "wof:placetype":"venue"
},
  "geometry": {"coordinates":[-86.17106200000001,43.229381],"type":"Point"}
}