{
  "type": "Feature",
  "properties": {
    "iso:country":"US",
    "sg:address":"1901 Larchwood Dr",
    "sg:city":"Troy",
    "sg:classifiers":[
        {
            "category":"Manufacturing",
            "subcategory":"Metals",
            "type":"Manufacturing & Wholesale Goods"
        }
    ],
    "sg:phone":"+1 248 544 3852",
    "sg:postcode":"48083",
    "sg:province":"MI",
    "sg:tags":[
        "tool"
    ],
    "wof:name":"A-W Systems Co",
    "wof:placetype":"venue"
},
  "geometry": {"coordinates":[-83.10839300000001,42.55406],"type":"Point"}
}