{
  "type": "Feature",
  "properties": {
    "iso:country":"US",
    "sg:address":"26200 Town Center Dr",
    "sg:city":"Novi",
    "sg:classifiers":[
        {
            "category":"Travel",
            "subcategory":"Travel Agent",
            "type":"Entertainment"
        }
    ],
    "sg:phone":"+1 248 344 1706",
    "sg:postcode":"48375",
    "sg:province":"MI",
    "sg:tags":[
        "agency",
        "bureau"
    ],
    "wof:name":"Nippon Express Travel USA",
    "wof:placetype":"venue"
},
  "geometry": {"coordinates":[-83.469684,42.483418],"type":"Point"}
}