{
  "type": "Feature",
  "properties": {
    "iso:country":"US",
    "sg:address":"15730 Addison St",
    "sg:city":"Southfield",
    "sg:classifiers":[
        {
            "category":"Real Estate",
            "subcategory":"Developer",
            "type":"Services"
        }
    ],
    "sg:phone":"+1 248 569 1827",
    "sg:postcode":"48075",
    "sg:province":"MI",
    "sg:tags":[
        "investment"
    ],
    "wof:name":"Sylvester Jo-Lenn",
    "wof:placetype":"venue"
},
  "geometry": {"coordinates":[-83.202792,42.472981],"type":"Point"}
}