{
  "type": "Feature",
  "properties": {
    "iso:country":"US",
    "sg:address":"18620 W 10 Mile Rd",
    "sg:city":"Southfield",
    "sg:classifiers":[
        {
            "category":"Banks & Credit Unions",
            "subcategory":"Bank",
            "type":"Services"
        }
    ],
    "sg:phone":"+1 248 559 5303",
    "sg:postcode":"48075",
    "sg:province":"MI",
    "sg:tags":[
        "loan",
        "real estate"
    ],
    "wof:name":"Quik Processing Ctr",
    "wof:placetype":"venue"
},
  "geometry": {"coordinates":[-83.225899,42.473365],"type":"Point"}
}