{
  "type": "Feature",
  "properties": {
    "iso:country":"US",
    "sg:address":"1539 Merrill Ave",
    "sg:city":"Lincoln Park",
    "sg:classifiers":[
        {
            "category":"Professional",
            "subcategory":"Business Services",
            "type":"Services"
        }
    ],
    "sg:phone":"+1 313 386 5946",
    "sg:postcode":"48146",
    "sg:province":"MI",
    "wof:name":"Jds Enterprises",
    "wof:placetype":"venue"
},
  "geometry": {"coordinates":[-83.186373,42.238023],"type":"Point"}
}