{
  "type": "Feature",
  "properties": {
    "iso:country":"US",
    "sg:address":"4190 Diebold Ranch Rd",
    "sg:city":"West Branch",
    "sg:classifiers":[
        {
            "category":"Building & Trades",
            "subcategory":"Construction",
            "type":"Services"
        }
    ],
    "sg:phone":"+1 989 345 1502",
    "sg:postcode":"48661",
    "sg:province":"MI",
    "sg:tags":[
        "concrete",
        "contractor"
    ],
    "wof:name":"Dan Winter Poured Walls Inc",
    "wof:placetype":"venue"
},
  "geometry": {"coordinates":[-84.296566,44.205483],"type":"Point"}
}