{
  "type": "Feature",
  "properties": {
    "iso:country":"US",
    "sg:address":"2855 Bird Lake Rd S",
    "sg:city":"Osseo",
    "sg:classifiers":[
        {
            "category":"Organizations",
            "subcategory":"Religious Organization",
            "type":"Services"
        }
    ],
    "sg:phone":"+1 517 523 3316",
    "sg:postcode":"49266",
    "sg:province":"MI",
    "sg:tags":[
        "church"
    ],
    "wof:name":"Osseo United Methodist Church",
    "wof:placetype":"venue"
},
  "geometry": {"coordinates":[-84.544014,41.885211],"type":"Point"}
}