{
  "type": "Feature",
  "properties": {
    "iso:country":"US",
    "sg:address":"89 S Merrimac St",
    "sg:city":"Pontiac",
    "sg:classifiers":[
        {
            "category":"Personal",
            "subcategory":"Barber",
            "type":"Services"
        }
    ],
    "sg:phone":"+1 248 322 2492",
    "sg:postcode":"48340",
    "sg:province":"MI",
    "sg:tags":[
        "shop"
    ],
    "wof:name":"Leanne Barbering",
    "wof:placetype":"venue"
},
  "geometry": {"coordinates":[-83.305621,42.65938],"type":"Point"}
}