{
  "type": "Feature",
  "properties": {
    "iso:country":"US",
    "sg:address":"489 W Custer Rd",
    "sg:city":"Sandusky",
    "sg:classifiers":[
        {
            "category":"Manufacturing",
            "subcategory":"Tools & Machinery",
            "type":"Manufacturing & Wholesale Goods"
        }
    ],
    "sg:phone":"+1 810 648 2030",
    "sg:postcode":"48471",
    "sg:province":"MI",
    "sg:tags":[
        "mfg",
        "repair",
        "industrial",
        "welding"
    ],
    "wof:name":"Nelson Machining & Fabrication",
    "wof:placetype":"venue"
},
  "geometry": {"coordinates":[-82.85193200000001,43.449922],"type":"Point"}
}