{
  "type": "Feature",
  "properties": {
    "iso:country":"US",
    "sg:address":"8755 N Middlebelt Rd",
    "sg:city":"Westland",
    "sg:classifiers":[
        {
            "category":"Autos & Motor Vehicles",
            "subcategory":"Fuel & Gas Station",
            "type":"Retail Goods"
        },
        {
            "category":"Food & Beverages",
            "subcategory":"Groceries & Convenience Stores",
            "type":"Retail Goods"
        }
    ],
    "sg:phone":"+1 734 425 2428",
    "sg:postcode":"48185",
    "sg:province":"MI",
    "wof:name":"Epic Oil Inc",
    "wof:placetype":"venue"
},
  "geometry": {"coordinates":[-83.332438,42.354351],"type":"Point"}
}