{
  "type": "Feature",
  "properties": {
    "iso:country":"US",
    "sg:address":"171 28th St SE",
    "sg:city":"Grand Rapids",
    "sg:classifiers":[
        {
            "category":"Travel",
            "subcategory":"Hotels & Motels",
            "type":"Entertainment"
        }
    ],
    "sg:phone":"+1 616 241 0151",
    "sg:postcode":"49548",
    "sg:province":"MI",
    "wof:name":"Landmark Lodging",
    "wof:placetype":"venue"
},
  "geometry": {"coordinates":[-85.664007,42.913028],"type":"Point"}
}