{
  "type": "Feature",
  "properties": {
    "iso:country":"US",
    "sg:address":"8524 Kraft Ave SE",
    "sg:city":"Caledonia",
    "sg:classifiers":[
        {
            "category":"Manufacturing",
            "subcategory":"Metals",
            "type":"Manufacturing & Wholesale Goods"
        },
        {
            "category":"Manufacturing",
            "subcategory":"Retail Goods",
            "type":"Manufacturing & Wholesale Goods"
        }
    ],
    "sg:phone":"+1 616 891 8376",
    "sg:postcode":"49316",
    "sg:province":"MI",
    "sg:tags":[
        "small",
        "ammunition",
        "arms",
        "manufacturer",
        "mfg"
    ],
    "wof:name":"Cowboy Up Bullets",
    "wof:placetype":"venue"
},
  "geometry": {"coordinates":[-85.526669,42.807281],"type":"Point"}
}