{
  "type": "Feature",
  "properties": {
    "iso:country":"US",
    "sg:address":"1972 Hyde Park Rd",
    "sg:city":"Detroit",
    "sg:classifiers":[
        {
            "category":"Banks & Credit Unions",
            "subcategory":"Financial Services",
            "type":"Services"
        }
    ],
    "sg:phone":"+1 313 446 2129",
    "sg:postcode":"48207",
    "sg:province":"MI",
    "sg:tags":[
        "consultant",
        "planning"
    ],
    "sg:website":"http://www.harlemstreamllc.com/",
    "wof:name":"Harlem Stream",
    "wof:placetype":"venue"
},
  "geometry": {"coordinates":[-83.030871,42.34431],"type":"Point"}
}