{
  "type": "Feature",
  "properties": {
    "iso:country":"US",
    "sg:address":"226 N Michigan Ave",
    "sg:city":"Big Rapids",
    "sg:classifiers":[
        {
            "category":"Government",
            "subcategory":"Office",
            "type":"Public Place"
        }
    ],
    "sg:phone":"+1 231 592 4015",
    "sg:postcode":"49307",
    "sg:province":"MI",
    "sg:tags":[
        "executive"
    ],
    "wof:name":"City Parks",
    "wof:placetype":"venue"
},
  "geometry": {"coordinates":[-85.48194700000001,43.700622],"type":"Point"}
}