{
  "type": "Feature",
  "properties": {
    "iso:country":"US",
    "sg:address":"15985 Canal Rd",
    "sg:city":"Clinton Township",
    "sg:classifiers":[
        {
            "category":"Professional",
            "subcategory":"Accounting & Tax Preparation",
            "type":"Services"
        }
    ],
    "sg:phone":"+1 586 228 0197",
    "sg:postcode":"48038",
    "sg:province":"MI",
    "sg:tags":[
        "accountant"
    ],
    "wof:name":"Pellegrino Masi & Co PC",
    "wof:placetype":"venue"
},
  "geometry": {"coordinates":[-82.962997,42.607899],"type":"Point"}
}