{
  "type": "Feature",
  "properties": {
    "iso:country":"US",
    "sg:address":"20 N Adams St",
    "sg:city":"Ypsilanti",
    "sg:classifiers":[
        {
            "category":"Retail",
            "subcategory":"Laundry & Dry Cleaning",
            "type":"Services"
        }
    ],
    "sg:phone":"+1 734 482 5280",
    "sg:postcode":"48197",
    "sg:province":"MI",
    "sg:tags":[
        "drycleaning",
        "plant"
    ],
    "wof:name":"Trojan Dry Cleaners",
    "wof:placetype":"venue"
},
  "geometry": {"coordinates":[-83.61593499999999,42.241423],"type":"Point"}
}