{
  "type": "Feature",
  "properties": {
    "iso:country":"US",
    "sg:address":"1777 E Lansing Dr",
    "sg:city":"East Lansing",
    "sg:classifiers":[
        {
            "category":"Professional",
            "subcategory":"Lawyer & Legal Services",
            "type":"Services"
        }
    ],
    "sg:phone":"+1 517 282 2525",
    "sg:postcode":"48823",
    "sg:province":"MI",
    "sg:tags":[
        "specialized"
    ],
    "wof:name":"James Halverson Attorney",
    "wof:placetype":"venue"
},
  "geometry": {"coordinates":[-84.452291,42.747811],"type":"Point"}
}