{
  "type": "Feature",
  "properties": {
    "iso:country":"US",
    "sg:address":"1000 E Stadium Blvd",
    "sg:city":"Ann Arbor",
    "sg:classifiers":[
        {
            "category":"Real Estate",
            "subcategory":"Real Estate Agent",
            "type":"Services"
        }
    ],
    "sg:phone":"+1 734 302 8820",
    "sg:postcode":"48104",
    "sg:province":"MI",
    "wof:name":"Re/Max",
    "wof:placetype":"venue"
},
  "geometry": {"coordinates":[-83.73610600000001,42.260999],"type":"Point"}
}