{
  "type": "Feature",
  "properties": {
    "iso:country":"US",
    "sg:address":"238 Taft Ave",
    "sg:city":"Ypsilanti",
    "sg:classifiers":[
        {
            "category":"Manufacturing",
            "subcategory":"Printing",
            "type":"Manufacturing & Wholesale Goods"
        }
    ],
    "sg:phone":"+1 734 483 4756",
    "sg:postcode":"48197",
    "sg:province":"MI",
    "sg:tags":[
        "publishing"
    ],
    "wof:name":"Snap It Publications",
    "wof:placetype":"venue"
},
  "geometry": {"coordinates":[-83.63278800000001,42.236185],"type":"Point"}
}