{
  "type": "Feature",
  "properties": {
    "iso:country":"US",
    "sg:address":"8368 W C Ave",
    "sg:city":"Kalamazoo",
    "sg:phone":"+1 269 342 1529",
    "sg:postcode":"49009",
    "sg:province":"MI",
    "wof:name":"American Campgrounds",
    "wof:placetype":"venue"
},
  "geometry": {"coordinates":[-85.718035,42.389576],"type":"Point"}
}