{
  "type": "Feature",
  "properties": {
    "iso:country":"US",
    "sg:address":"6864 Hart Dr",
    "sg:city":"Kalamazoo",
    "sg:classifiers":[
        {
            "category":"Building & Trades",
            "subcategory":"Construction",
            "type":"Services"
        }
    ],
    "sg:phone":"+1 269 342 0956",
    "sg:postcode":"49009",
    "sg:province":"MI",
    "sg:tags":[
        "excavating",
        "contractor"
    ],
    "wof:name":"Vander Veen Excavating",
    "wof:placetype":"venue"
},
  "geometry": {"coordinates":[-85.69125699999999,42.358795],"type":"Point"}
}