{
  "type": "Feature",
  "properties": {
    "iso:country":"US",
    "sg:address":"3375 M 129",
    "sg:city":"Sault Ste Marie",
    "sg:classifiers":[
        {
            "category":"Government",
            "subcategory":"Office",
            "type":"Public Place"
        }
    ],
    "sg:phone":"+1 906 635 0556",
    "sg:postcode":"49783",
    "sg:province":"MI",
    "wof:name":"Construction Sault Tribe",
    "wof:placetype":"venue"
},
  "geometry": {"coordinates":[-84.353983,46.45759],"type":"Point"}
}