{
  "type": "Feature",
  "properties": {
    "iso:country":"US",
    "sg:address":"1111 E 9 Mile Rd",
    "sg:city":"Ferndale",
    "sg:classifiers":[
        {
            "category":"Wholesale",
            "subcategory":"Electrical",
            "type":"Manufacturing & Wholesale Goods"
        }
    ],
    "sg:phone":"+1 248 544 4210",
    "sg:postcode":"48220",
    "sg:province":"MI",
    "sg:tags":[
        "equipment",
        "electric",
        "supply"
    ],
    "wof:name":"Madison Electric Co",
    "wof:placetype":"venue"
},
  "geometry": {"coordinates":[-83.11833900000001,42.461059],"type":"Point"}
}