{
  "type": "Feature",
  "properties": {
    "iso:country":"US",
    "sg:address":"1000 E 7 Mile Rd",
    "sg:city":"Highland Park",
    "sg:classifiers":[
        {
            "category":"Food & Beverages",
            "subcategory":"Groceries & Convenience Stores",
            "type":"Retail Goods"
        }
    ],
    "sg:phone":"+1 313 892 1346",
    "sg:postcode":"48203",
    "sg:province":"MI",
    "wof:name":"Seven Express Market",
    "wof:placetype":"venue"
},
  "geometry": {"coordinates":[-83.09369700000001,42.432598],"type":"Point"}
}