{
  "type": "Feature",
  "properties": {
    "iso:country":"US",
    "sg:address":"1313 Underwood Ave SE",
    "sg:city":"Grand Rapids",
    "sg:classifiers":[
        {
            "category":"Building & Trades",
            "subcategory":"Construction",
            "type":"Services"
        }
    ],
    "sg:phone":"+1 616 245 1963",
    "sg:postcode":"49506",
    "sg:province":"MI",
    "sg:tags":[
        "house"
    ],
    "wof:name":"Space Framing Company",
    "wof:placetype":"venue"
},
  "geometry": {"coordinates":[-85.638211,42.938246],"type":"Point"}
}