{
  "type": "Feature",
  "properties": {
    "iso:country":"US",
    "sg:address":"42871 Ford Rd",
    "sg:city":"Canton",
    "sg:classifiers":[
        {
            "category":"Restaurant",
            "type":"Food & Drink"
        }
    ],
    "sg:phone":"+1 734 981 4144",
    "sg:postcode":"48187",
    "sg:province":"MI",
    "wof:name":"Outback Steakhouse",
    "wof:placetype":"venue"
},
  "geometry": {"coordinates":[-83.466797,42.322201],"type":"Point"}
}