{
  "type": "Feature",
  "properties": {
    "iso:country":"US",
    "sg:address":"2168 US Hwy 41",
    "sg:city":"Marquette",
    "sg:classifiers":[
        {
            "category":"Home & Garden",
            "subcategory":"Garden Supply",
            "type":"Retail Goods"
        }
    ],
    "sg:phone":"+1 906 228 2301",
    "sg:postcode":"49855",
    "sg:province":"MI",
    "sg:tags":[
        "house",
        "bird",
        "feeder"
    ],
    "wof:name":"Wild Birds Unlimited",
    "wof:placetype":"venue"
},
  "geometry": {"coordinates":[-87.36946399999999,46.507837],"type":"Point"}
}