{
  "type": "Feature",
  "properties": {
    "iso:country":"US",
    "sg:address":"400 E Bay St",
    "sg:city":"Harbor Springs",
    "sg:classifiers":[
        {
            "category":"Autos & Motor Vehicles",
            "subcategory":"Boat Sales",
            "type":"Retail Goods"
        }
    ],
    "sg:phone":"+1 231 526 6225",
    "sg:postcode":"49740",
    "sg:province":"MI",
    "sg:tags":[
        "dealer",
        "sales"
    ],
    "sg:website":"www.irishboatshop.com",
    "wof:name":"Irish Boat Shop",
    "wof:placetype":"venue"
},
  "geometry": {"coordinates":[-84.983445,45.430155],"type":"Point"}
}