{
  "type": "Feature",
  "properties": {
    "iso:country":"US",
    "sg:address":"1800 7th Ave N",
    "sg:city":"Escanaba",
    "sg:classifiers":[
        {
            "category":"Government",
            "subcategory":"Office",
            "type":"Public Place"
        }
    ],
    "sg:phone":"+1 906 786 9847",
    "sg:postcode":"49829",
    "sg:province":"MI",
    "sg:tags":[
        "village"
    ],
    "wof:name":"Royce Park Shelter House",
    "wof:placetype":"venue"
},
  "geometry": {"coordinates":[-87.07444099999999,45.754891],"type":"Point"}
}