{
  "type": "Feature",
  "properties": {
    "iso:country":"US",
    "sg:address":"650 Hannah Ave",
    "sg:city":"Traverse City",
    "sg:classifiers":[
        {
            "category":"Travel",
            "subcategory":"Campground",
            "type":"Entertainment"
        }
    ],
    "sg:phone":"+1 231 922 5922",
    "sg:postcode":"49686",
    "sg:province":"MI",
    "sg:tags":[
        "camp"
    ],
    "wof:name":"Traverse Area Community Sail",
    "wof:placetype":"venue"
},
  "geometry": {"coordinates":[-85.607665,44.755371],"type":"Point"}
}