{
  "type": "Feature",
  "properties": {
    "iso:country":"US",
    "sg:address":"1301 16th Ave",
    "sg:city":"Menominee",
    "sg:classifiers":[
        {
            "category":"Professional",
            "subcategory":"Printing & Photocopies",
            "type":"Services"
        }
    ],
    "sg:phone":"+1 906 864 9890",
    "sg:postcode":"49858",
    "sg:province":"MI",
    "sg:tags":[
        "duplicating",
        "copying"
    ],
    "wof:name":"Superior Office Solutions LLC",
    "wof:placetype":"venue"
},
  "geometry": {"coordinates":[-87.619511,45.113268],"type":"Point"}
}