{
  "type": "Feature",
  "properties": {
    "iso:country":"US",
    "sg:address":"978 N Van Dyke Rd",
    "sg:city":"Bad Axe",
    "sg:classifiers":[
        {
            "category":"Health Services",
            "subcategory":"Health Practitioner",
            "type":"Services"
        }
    ],
    "sg:phone":"+1 989 269 6978",
    "sg:postcode":"48413",
    "sg:province":"MI",
    "sg:tags":[
        "medical",
        "therapist"
    ],
    "wof:name":"Medical Hypnosis Clinic",
    "wof:placetype":"venue"
},
  "geometry": {"coordinates":[-83.000972,43.820939],"type":"Point"}
}