{
  "type": "Feature",
  "properties": {
    "iso:country":"US",
    "sg:address":"20769 Whitlock St",
    "sg:city":"Farmington",
    "sg:classifiers":[
        {
            "category":"Building & Trades",
            "subcategory":"Construction",
            "type":"Services"
        }
    ],
    "sg:phone":"+1 248 888 0343",
    "sg:postcode":"48336",
    "sg:province":"MI",
    "sg:tags":[
        "wood",
        "contractor",
        "cabinet",
        "kitchen",
        "mfg"
    ],
    "wof:name":"Mother Hubbards Cupboards",
    "wof:placetype":"venue"
},
  "geometry": {"coordinates":[-83.366985,42.443593],"type":"Point"}
}