{
  "type": "Feature",
  "properties": {
    "iso:country":"US",
    "sg:address":"13918 M-M28",
    "sg:city":"Newberry",
    "sg:classifiers":[
        {
            "category":"Restaurant",
            "type":"Food & Drink"
        }
    ],
    "sg:menulink":"http://www.allmenus.com/mi/pentland/79562-pizza-hut/menu/",
    "sg:phone":"+1 906 293 3273",
    "sg:postcode":"49868",
    "sg:province":"MI",
    "sg:tags":[
        "american",
        "pizza"
    ],
    "wof:name":"Pizza Hut",
    "wof:placetype":"venue"
},
  "geometry": {"coordinates":[-85.41516,46.303631],"type":"Point"}
}