{
  "type": "Feature",
  "properties": {
    "iso:country":"US",
    "sg:address":"4027 W Michigan Ave",
    "sg:city":"Jackson",
    "sg:classifiers":[
        {
            "category":"Real Estate",
            "subcategory":"Real Estate Agent",
            "type":"Services"
        }
    ],
    "sg:phone":"+1 517 750 3933",
    "sg:postcode":"49202",
    "sg:province":"MI",
    "wof:name":"Century 21",
    "wof:placetype":"venue"
},
  "geometry": {"coordinates":[-84.46876899999999,42.254705],"type":"Point"}
}