{
  "type": "Feature",
  "properties": {
    "iso:country":"US",
    "sg:address":"20735 Grand River Ave",
    "sg:city":"Detroit",
    "sg:classifiers":[
        {
            "category":"Retail",
            "subcategory":"Auto Repair",
            "type":"Services"
        }
    ],
    "sg:phone":"+1 313 535 8122",
    "sg:postcode":"48219",
    "sg:province":"MI",
    "sg:tags":[
        "body",
        "shop"
    ],
    "sg:website":"www.karkraftcollision.com",
    "wof:name":"Kar Kraft Collision Center Inc",
    "wof:placetype":"venue"
},
  "geometry": {"coordinates":[-83.245796,42.411598],"type":"Point"}
}