{
  "type": "Feature",
  "properties": {
    "iso:country":"US",
    "sg:address":"109 E Comstock St",
    "sg:city":"Owosso",
    "sg:classifiers":[
        {
            "category":"Bus Charters",
            "type":"Transportation"
        }
    ],
    "sg:phone":"+1 989 723 6666",
    "sg:postcode":"48867",
    "sg:province":"MI",
    "sg:tags":[
        "rental"
    ],
    "sg:website":"www.indiantrails.com",
    "wof:name":"Indian Trails Motorcoach",
    "wof:placetype":"venue"
},
  "geometry": {"coordinates":[-84.17058400000001,42.996633],"type":"Point"}
}