{
  "type": "Feature",
  "properties": {
    "iso:country":"US",
    "sg:address":"320 E Tienken Rd",
    "sg:city":"Rochester Hills",
    "sg:classifiers":[
        {
            "category":"Retail",
            "subcategory":"Portrait Studio",
            "type":"Services"
        }
    ],
    "sg:phone":"+1 248 650 4292",
    "sg:postcode":"48306",
    "sg:province":"MI",
    "sg:tags":[
        "photographer"
    ],
    "wof:name":"Bellentyne Photography",
    "wof:placetype":"venue"
},
  "geometry": {"coordinates":[-83.126274,42.695786],"type":"Point"}
}