{
  "type": "Feature",
  "properties": {
    "iso:country":"US",
    "sg:address":"6495 Orchard Lake Rd",
    "sg:city":"West Bloomfield",
    "sg:classifiers":[
        {
            "category":"Autos & Motor Vehicles",
            "subcategory":"Fuel & Gas Station",
            "type":"Retail Goods"
        }
    ],
    "sg:phone":"+1 248 626 1865",
    "sg:postcode":"48322",
    "sg:province":"MI",
    "wof:name":"Maple & Orchard Lake Shell",
    "wof:placetype":"venue"
},
  "geometry": {"coordinates":[-83.360516,42.542986],"type":"Point"}
}