{
  "type": "Feature",
  "properties": {
    "iso:country":"US",
    "sg:address":"23955 Freeway Park Dr",
    "sg:city":"Farmington Hills",
    "sg:classifiers":[
        {
            "category":"Health Services",
            "subcategory":"Medical Lab",
            "type":"Services"
        }
    ],
    "sg:phone":"+1 248 471 4111",
    "sg:postcode":"48335",
    "sg:province":"MI",
    "sg:tags":[
        "laboratory"
    ],
    "wof:name":"Detroit Biomedical Labs Inc",
    "wof:placetype":"venue"
},
  "geometry": {"coordinates":[-83.421426,42.464704],"type":"Point"}
}