{
  "type": "Feature",
  "properties": {
    "iso:country":"US",
    "sg:address":"1609 E Cork St",
    "sg:city":"Kalamazoo",
    "sg:classifiers":[
        {
            "category":"Banks & Credit Unions",
            "subcategory":"Bank",
            "type":"Services"
        }
    ],
    "sg:phone":"+1 269 381 0336",
    "sg:postcode":"49001",
    "sg:province":"MI",
    "wof:name":"Kalamazoo Postal Federal Cr Un",
    "wof:placetype":"venue"
},
  "geometry": {"coordinates":[-85.559228,42.259636],"type":"Point"}
}