{
  "type": "Feature",
  "properties": {
    "iso:country":"US",
    "sg:address":"2435 S 13th St",
    "sg:city":"Niles",
    "sg:classifiers":[
        {
            "category":"Professional",
            "subcategory":"Business Services",
            "type":"Services"
        }
    ],
    "sg:phone":"+1 269 684 0211",
    "sg:postcode":"49120",
    "sg:province":"MI",
    "wof:name":"Techno Service & Sales",
    "wof:placetype":"venue"
},
  "geometry": {"coordinates":[-86.245017,41.781567],"type":"Point"}
}