{
  "type": "Feature",
  "properties": {
    "iso:country":"US",
    "sg:address":"3534 Pine Grove Ave",
    "sg:city":"Port Huron",
    "sg:classifiers":[
        {
            "category":"Shopping",
            "subcategory":"Department Store",
            "type":"Retail Goods"
        }
    ],
    "sg:phone":"+1 810 982 7030",
    "sg:postcode":"48060",
    "sg:province":"MI",
    "sg:tags":[
        "shop"
    ],
    "wof:name":"Dollar Bills",
    "wof:placetype":"venue"
},
  "geometry": {"coordinates":[-82.448561,43.013714],"type":"Point"}
}