{
  "type": "Feature",
  "properties": {
    "iso:country":"US",
    "sg:address":"4243 Remembrance Rd NW",
    "sg:city":"Grand Rapids",
    "sg:classifiers":[
        {
            "category":"Government",
            "subcategory":"Office",
            "type":"Public Place"
        }
    ],
    "sg:phone":"+1 616 453 6311",
    "sg:postcode":"49504",
    "sg:province":"MI",
    "sg:tags":[
        "city",
        "council",
        "commission"
    ],
    "wof:name":"City Hall",
    "wof:placetype":"venue"
},
  "geometry": {"coordinates":[-85.77219100000001,43.00449],"type":"Point"}
}