{
  "type": "Feature",
  "properties": {
    "iso:country":"US",
    "sg:address":"8900 Gull Rd",
    "sg:city":"Richland",
    "sg:classifiers":[
        {
            "category":"Shopping",
            "subcategory":"Pharmacy",
            "type":"Retail Goods"
        }
    ],
    "sg:phone":"+1 269 629 9550",
    "sg:postcode":"49083",
    "sg:province":"MI",
    "wof:name":"Richland Village Drug Store",
    "wof:placetype":"venue"
},
  "geometry": {"coordinates":[-85.461556,42.370446],"type":"Point"}
}