{
  "type": "Feature",
  "properties": {
    "iso:country":"US",
    "sg:address":"1820 Cross Bend St NE",
    "sg:city":"Grand Rapids",
    "sg:classifiers":[
        {
            "category":"Professional",
            "subcategory":"Business Services",
            "type":"Services"
        }
    ],
    "sg:phone":"+1 616 364 6178",
    "sg:postcode":"49505",
    "sg:province":"MI",
    "wof:name":"Dolphin Express Electronics",
    "wof:placetype":"venue"
},
  "geometry": {"coordinates":[-85.62173,43.002022],"type":"Point"}
}