{
  "type": "Feature",
  "properties": {
    "iso:country":"US",
    "sg:address":"1314 Arella Blvd",
    "sg:city":"Ann Arbor",
    "sg:classifiers":[
        {
            "category":"Shopping",
            "subcategory":"Hobbies, Toys, & Games",
            "type":"Retail Goods"
        }
    ],
    "sg:phone":"+1 734 662 7048",
    "sg:postcode":"48103",
    "sg:province":"MI",
    "wof:name":"Powell Ueantee Ceramic",
    "wof:placetype":"venue"
},
  "geometry": {"coordinates":[-83.766293,42.265071],"type":"Point"}
}