{
  "type": "Feature",
  "properties": {
    "iso:country":"US",
    "sg:address":"6193 Lindsay Dr",
    "sg:city":"Waterford",
    "sg:classifiers":[
        {
            "category":"Autos & Motor Vehicles",
            "subcategory":"Automobile Sales",
            "type":"Retail Goods"
        }
    ],
    "sg:phone":"+1 248 623 5007",
    "sg:postcode":"48329",
    "sg:province":"MI",
    "sg:tags":[
        "used"
    ],
    "wof:name":"Finishline Proformance LLC",
    "wof:placetype":"venue"
},
  "geometry": {"coordinates":[-83.41044599999999,42.687909],"type":"Point"}
}