{
  "type": "Feature",
  "properties": {
    "iso:country":"US",
    "sg:address":"23701 Lakewood St",
    "sg:city":"Saint Clair Shores",
    "sg:classifiers":[
        {
            "category":"Building & Trades",
            "subcategory":"Construction",
            "type":"Services"
        }
    ],
    "sg:phone":"+1 586 294 2118",
    "sg:postcode":"48082",
    "sg:province":"MI",
    "sg:tags":[
        "contractor"
    ],
    "wof:name":"Sharp Drywall",
    "wof:placetype":"venue"
},
  "geometry": {"coordinates":[-82.87004,42.539586],"type":"Point"}
}