{
  "type": "Feature",
  "properties": {
    "iso:country":"US",
    "sg:address":"8637 Brown Rd",
    "sg:city":"Fenwick",
    "sg:classifiers":[
        {
            "category":"Professional",
            "subcategory":"Computer Services",
            "type":"Services"
        }
    ],
    "sg:phone":"+1 989 291 5162",
    "sg:postcode":"48834",
    "sg:province":"MI",
    "sg:tags":[
        "programing",
        "custom"
    ],
    "wof:name":"Abra Enterprises",
    "wof:placetype":"venue"
},
  "geometry": {"coordinates":[-85.09321799999999,43.168888],"type":"Point"}
}