{
  "type": "Feature",
  "properties": {
    "iso:country":"US",
    "sg:address":"2780 Garfield Rd N",
    "sg:city":"Traverse City",
    "sg:classifiers":[
        {
            "category":"Mining & Drilling",
            "type":"Manufacturing & Wholesale Goods"
        }
    ],
    "sg:phone":"+1 231 946 8090",
    "sg:postcode":"49686",
    "sg:province":"MI",
    "sg:tags":[
        "development",
        "gas",
        "oil",
        "exploration"
    ],
    "wof:name":"Miracle Petroleum",
    "wof:placetype":"venue"
},
  "geometry": {"coordinates":[-85.59535700000001,44.727068],"type":"Point"}
}