{
  "type": "Feature",
  "properties": {
    "iso:country":"US",
    "sg:address":"121 Franklin St SE",
    "sg:city":"Grand Rapids",
    "sg:classifiers":[
        {
            "category":"Social Services",
            "type":"Services"
        }
    ],
    "sg:phone":"+1 616 336 4000",
    "sg:postcode":"49507",
    "sg:province":"MI",
    "sg:tags":[
        "organization",
        "welfare"
    ],
    "wof:name":"Sheldon Complex",
    "wof:placetype":"venue"
},
  "geometry": {"coordinates":[-85.664868,42.948673],"type":"Point"}
}