{
  "type": "Feature",
  "properties": {
    "iso:country":"US",
    "sg:address":"2605 Lone Pine Rd",
    "sg:city":"Farwell",
    "sg:classifiers":[
        {
            "category":"Freight",
            "type":"Transportation"
        }
    ],
    "sg:phone":"+1 989 386 7096",
    "sg:postcode":"48622",
    "sg:province":"MI",
    "sg:tags":[
        "operator",
        "local",
        "trucking"
    ],
    "wof:name":"McKindles Trucking",
    "wof:placetype":"venue"
},
  "geometry": {"coordinates":[-84.801676,43.877734],"type":"Point"}
}