{
  "type": "Feature",
  "properties": {
    "iso:country":"US",
    "sg:address":"1539 E Saginaw Rd",
    "sg:city":"Midland",
    "sg:classifiers":[
        {
            "category":"Retail",
            "subcategory":"Auto Repair",
            "type":"Services"
        }
    ],
    "sg:phone":"+1 989 835 4072",
    "sg:postcode":"48642",
    "sg:province":"MI",
    "sg:tags":[
        "body",
        "automobile",
        "painting",
        "repairing"
    ],
    "wof:name":"John's Body Shop",
    "wof:placetype":"venue"
},
  "geometry": {"coordinates":[-84.318223,43.653629],"type":"Point"}
}