{
  "type": "Feature",
  "properties": {
    "iso:country":"US",
    "sg:address":"179 Pine Hill Lake Dr",
    "sg:city":"Horton",
    "sg:classifiers":[
        {
            "category":"Professional",
            "type":"Services"
        }
    ],
    "sg:phone":"+1 517 688 6277",
    "sg:postcode":"49246",
    "sg:province":"MI",
    "wof:name":"Rlw Analytics Inc",
    "wof:placetype":"venue"
},
  "geometry": {"coordinates":[-84.484329,42.095836],"type":"Point"}
}