{
  "type": "Feature",
  "properties": {
    "iso:country":"US",
    "sg:address":"114 Catherine St",
    "sg:city":"Kalamazoo",
    "sg:classifiers":[
        {
            "category":"Organizations",
            "subcategory":"Membership Organization",
            "type":"Services"
        }
    ],
    "sg:phone":"+1 269 337 7407",
    "sg:postcode":"49006",
    "sg:province":"MI",
    "wof:name":"Bach Festival Society-Klmz",
    "wof:placetype":"venue"
},
  "geometry": {"coordinates":[-85.59763599999999,42.290651],"type":"Point"}
}