{
  "type": "Feature",
  "properties": {
    "iso:country":"US",
    "sg:address":"9938 Cady Rd",
    "sg:city":"Jackson",
    "sg:phone":"+1 517 536 8246",
    "sg:postcode":"49201",
    "sg:province":"MI",
    "sg:tags":[
        "farm",
        "corn",
        "soybean"
    ],
    "wof:name":"Scott Lantis",
    "wof:placetype":"venue"
},
  "geometry": {"coordinates":[-84.234762,42.174757],"type":"Point"}
}