{
  "type": "Feature",
  "properties": {
    "iso:country":"US",
    "sg:address":"2594 Cades Cove",
    "sg:city":"Brighton",
    "sg:classifiers":[
        {
            "category":"Professional",
            "subcategory":"Business Services",
            "type":"Services"
        }
    ],
    "sg:phone":"+1 810 229 3155",
    "sg:postcode":"48114",
    "sg:province":"MI",
    "sg:tags":[
        "notary",
        "public"
    ],
    "wof:name":"Robyn Hermes",
    "wof:placetype":"venue"
},
  "geometry": {"coordinates":[-83.74664199999999,42.566036],"type":"Point"}
}