{
  "type": "Feature",
  "properties": {
    "iso:country":"US",
    "sg:address":"730 W Brocker Rd",
    "sg:city":"Metamora",
    "sg:classifiers":[
        {
            "category":"Communications",
            "subcategory":"Film & Video Production",
            "type":"Services"
        }
    ],
    "sg:phone":"+1 810 678 2313",
    "sg:postcode":"48455",
    "sg:province":"MI",
    "sg:tags":[
        "taping"
    ],
    "wof:name":"Younglove Broadcast Svc Inc",
    "wof:placetype":"venue"
},
  "geometry": {"coordinates":[-83.307878,42.912366],"type":"Point"}
}