{
  "type": "Feature",
  "properties": {
    "iso:country":"US",
    "sg:address":"407 E John St",
    "sg:city":"Bay City",
    "sg:classifiers":[
        {
            "category":"Retail",
            "subcategory":"Auto Repair",
            "type":"Services"
        }
    ],
    "sg:phone":"+1 989 895 8693",
    "sg:postcode":"48706",
    "sg:province":"MI",
    "sg:tags":[
        "repairing",
        "automobile"
    ],
    "wof:name":"Gary's All Car Svc",
    "wof:placetype":"venue"
},
  "geometry": {"coordinates":[-83.901274,43.601291],"type":"Point"}
}