{
  "type": "Feature",
  "properties": {
    "iso:country":"US",
    "sg:address":"33330 W 8 Mile Rd",
    "sg:city":"Farmington",
    "sg:classifiers":[
        {
            "category":"Food & Beverages",
            "subcategory":"Groceries & Convenience Stores",
            "type":"Retail Goods"
        }
    ],
    "sg:phone":"+1 248 426 8730",
    "sg:postcode":"48336",
    "sg:province":"MI",
    "wof:name":"Knight Enterprises",
    "wof:placetype":"venue"
},
  "geometry": {"coordinates":[-83.374808,42.440708],"type":"Point"}
}