{
  "type": "Feature",
  "properties": {
    "iso:country":"US",
    "sg:address":"36357 Groesbeck Hwy",
    "sg:city":"Clinton Twp",
    "sg:classifiers":[
        {
            "category":"Banks & Credit Unions",
            "subcategory":"Bank",
            "type":"Services"
        }
    ],
    "sg:phone":"+1 586 746 1654",
    "sg:postcode":"48035",
    "sg:province":"MI",
    "sg:tags":[
        "loan"
    ],
    "wof:name":"Payday Advances Inc",
    "wof:placetype":"venue"
},
  "geometry": {"coordinates":[-82.914933,42.565633],"type":"Point"}
}