{
  "type": "Feature",
  "properties": {
    "iso:country":"US",
    "sg:address":"662 Butternut Dr",
    "sg:city":"Holland",
    "sg:classifiers":[
        {
            "category":"Personal",
            "subcategory":"Beauty Salon",
            "type":"Services"
        }
    ],
    "sg:phone":"+1 616 738 0024",
    "sg:postcode":"49424",
    "sg:province":"MI",
    "wof:name":"Studio 662 Hair Salon",
    "wof:placetype":"venue"
},
  "geometry": {"coordinates":[-86.12616199999999,42.817285],"type":"Point"}
}