{
  "type": "Feature",
  "properties": {
    "iso:country":"US",
    "sg:address":"53464 Dequindre Rd",
    "sg:city":"Shelby Twp",
    "sg:classifiers":[
        {
            "category":"Social Services",
            "subcategory":"Adult Care",
            "type":"Services"
        }
    ],
    "sg:phone":"+1 248 453 0009",
    "sg:postcode":"48316",
    "sg:province":"MI",
    "sg:tags":[
        "home",
        "group"
    ],
    "wof:name":"New Passage Autum Manor",
    "wof:placetype":"venue"
},
  "geometry": {"coordinates":[-83.094233,42.685899],"type":"Point"}
}