{
  "type": "Feature",
  "properties": {
    "iso:country":"US",
    "sg:address":"3500 S Derenzy Rd",
    "sg:city":"Bellaire",
    "sg:classifiers":[
        {
            "category":"Government",
            "subcategory":"Office",
            "type":"Public Place"
        }
    ],
    "sg:phone":"+1 231 533 6569",
    "sg:postcode":"49615",
    "sg:province":"MI",
    "sg:tags":[
        "county",
        "safety",
        "order"
    ],
    "wof:name":"Antrim County Emergency Svc",
    "wof:placetype":"venue"
},
  "geometry": {"coordinates":[-85.193209,44.982875],"type":"Point"}
}