{
  "type": "Feature",
  "properties": {
    "iso:country":"US",
    "sg:address":"282 Parkland Dr",
    "sg:city":"Rochester Hills",
    "sg:classifiers":[
        {
            "category":"Professional",
            "type":"Services"
        }
    ],
    "sg:phone":"+1 248 608 5473",
    "sg:postcode":"48307",
    "sg:province":"MI",
    "sg:tags":[
        "establishment"
    ],
    "wof:name":"AVDSFE Corp",
    "wof:placetype":"venue"
},
  "geometry": {"coordinates":[-83.139077,42.656334],"type":"Point"}
}