{
  "type": "Feature",
  "properties": {
    "iso:country":"US",
    "sg:address":"8228 Morenci Rd",
    "sg:city":"Morenci",
    "sg:classifiers":[
        {
            "category":"Farming",
            "subcategory":"Farm",
            "type":"Manufacturing & Wholesale Goods"
        }
    ],
    "sg:phone":"+1 517 458 6297",
    "sg:postcode":"49256",
    "sg:province":"MI",
    "sg:tags":[
        "crop",
        "general"
    ],
    "wof:name":"P&L Stained Glass & Leaded GL",
    "wof:placetype":"venue"
},
  "geometry": {"coordinates":[-84.19241599999999,41.715449],"type":"Point"}
}