{
  "type": "Feature",
  "properties": {
    "iso:country":"US",
    "sg:address":"4493 Woodschool Rd",
    "sg:city":"Hastings",
    "sg:classifiers":[
        {
            "category":"Social Services",
            "type":"Services"
        }
    ],
    "sg:phone":"+1 269 948 7736",
    "sg:postcode":"49058",
    "sg:province":"MI",
    "wof:name":"New Life Outreach Inc",
    "wof:placetype":"venue"
},
  "geometry": {"coordinates":[-85.358611,42.71694],"type":"Point"}
}