{
  "type": "Feature",
  "properties": {
    "iso:country":"US",
    "sg:address":"16750 Masonic Blvd",
    "sg:city":"Fraser",
    "sg:classifiers":[
        {
            "category":"Building & Trades",
            "subcategory":"Construction",
            "type":"Services"
        }
    ],
    "sg:phone":"+1 586 293 0203",
    "sg:postcode":"48026",
    "sg:province":"MI",
    "sg:tags":[
        "roofing",
        "contractor"
    ],
    "wof:name":"Macomb Home Improvement Inc",
    "wof:placetype":"venue"
},
  "geometry": {"coordinates":[-82.949406,42.531412],"type":"Point"}
}