{
  "type": "Feature",
  "properties": {
    "iso:country":"US",
    "sg:address":"17769 Paradise Lake Rd",
    "sg:city":"Vandalia",
    "sg:classifiers":[
        {
            "category":"Organizations",
            "subcategory":"Membership Organization",
            "type":"Services"
        },
        {
            "category":"Professional",
            "type":"Services"
        }
    ],
    "sg:phone":"+1 269 476 9387",
    "sg:postcode":"49095",
    "sg:province":"MI",
    "sg:tags":[
        "establishment"
    ],
    "wof:name":"International Project Help Inc",
    "wof:placetype":"venue"
},
  "geometry": {"coordinates":[-85.894813,41.889298],"type":"Point"}
}