{
  "type": "Feature",
  "properties": {
    "iso:country":"US",
    "sg:address":"4640 S Edon Rd",
    "sg:city":"Reading",
    "sg:classifiers":[
        {
            "category":"Manufacturing",
            "subcategory":"Tools & Machinery",
            "type":"Manufacturing & Wholesale Goods"
        }
    ],
    "sg:phone":"+1 517 283 1808",
    "sg:postcode":"49274",
    "sg:province":"MI",
    "sg:tags":[
        "die",
        "maker"
    ],
    "wof:name":"A-One Tool Inc",
    "wof:placetype":"venue"
},
  "geometry": {"coordinates":[-84.748008,41.859303],"type":"Point"}
}