{
  "type": "Feature",
  "properties": {
    "iso:country":"US",
    "sg:address":"1693 Ewing St",
    "sg:city":"Grawn",
    "sg:classifiers":[
        {
            "category":"Recreation",
            "type":"Entertainment"
        }
    ],
    "sg:phone":"+1 231 276 6837",
    "sg:postcode":"49637",
    "sg:province":"MI",
    "wof:name":"Bay Area Kung Fu",
    "wof:placetype":"venue"
},
  "geometry": {"coordinates":[-85.695125,44.66306],"type":"Point"}
}