{
  "type": "Feature",
  "properties": {
    "iso:country":"US",
    "sg:address":"7530 W S Ave",
    "sg:city":"Schoolcraft",
    "sg:classifiers":[
        {
            "category":"Home & Garden",
            "subcategory":"Garden Supply",
            "type":"Retail Goods"
        }
    ],
    "sg:phone":"+1 269 375 8510",
    "sg:postcode":"49087",
    "sg:province":"MI",
    "sg:tags":[
        "sprinkler"
    ],
    "wof:name":"Geren Irrigation",
    "wof:placetype":"venue"
},
  "geometry": {"coordinates":[-85.694249,42.17208],"type":"Point"}
}