{
  "type": "Feature",
  "properties": {
    "iso:country":"US",
    "sg:address":"1746 Thunderbird Dr",
    "sg:city":"Troy",
    "sg:classifiers":[
        {
            "category":"Professional",
            "subcategory":"Research",
            "type":"Services"
        },
        {
            "category":"Manufacturing",
            "subcategory":"Rubber & Plastics",
            "type":"Manufacturing & Wholesale Goods"
        }
    ],
    "sg:phone":"+1 248 362 7000",
    "sg:postcode":"48084",
    "sg:province":"MI",
    "sg:tags":[
        "lining",
        "brake",
        "automotive"
    ],
    "wof:name":"Honeywell",
    "wof:placetype":"venue"
},
  "geometry": {"coordinates":[-83.154033,42.5519],"type":"Point"}
}