{
  "type": "Feature",
  "properties": {
    "iso:country":"US",
    "sg:address":"15390 Bishop Rd",
    "sg:city":"Chesaning",
    "sg:classifiers":[
        {
            "category":"Building & Trades",
            "subcategory":"Construction",
            "type":"Services"
        }
    ],
    "sg:phone":"+1 989 845 2429",
    "sg:postcode":"48616",
    "sg:province":"MI",
    "sg:tags":[
        "house"
    ],
    "wof:name":"Vrable Builders",
    "wof:placetype":"venue"
},
  "geometry": {"coordinates":[-84.02930000000001,43.198584],"type":"Point"}
}