{
  "type": "Feature",
  "properties": {
    "iso:country":"US",
    "sg:address":"22137 Gratiot Ave",
    "sg:city":"Eastpointe",
    "sg:classifiers":[
        {
            "category":"Home & Garden",
            "subcategory":"Building Materials",
            "type":"Retail Goods"
        }
    ],
    "sg:phone":"+1 586 778 1220",
    "sg:postcode":"48021",
    "sg:province":"MI",
    "sg:tags":[
        "glass",
        "window",
        "plate"
    ],
    "wof:name":"East Detroit Glass Co",
    "wof:placetype":"venue"
},
  "geometry": {"coordinates":[-82.96134000000001,42.459806],"type":"Point"}
}