{
  "type": "Feature",
  "properties": {
    "iso:country":"US",
    "sg:address":"2015 Gates St",
    "sg:city":"Reese",
    "sg:classifiers":[
        {
            "category":"Restaurant",
            "type":"Food & Drink"
        }
    ],
    "sg:menulink":"http://www.allmenus.com/mi/denmark/146120-subway/menu/",
    "sg:phone":"+1 989 868 4611",
    "sg:postcode":"48757",
    "sg:province":"MI",
    "sg:tags":[
        "american",
        "sandwich"
    ],
    "wof:name":"Subway",
    "wof:placetype":"venue"
},
  "geometry": {"coordinates":[-83.696422,43.450161],"type":"Point"}
}