{
  "type": "Feature",
  "properties": {
    "iso:country":"US",
    "sg:address":"567 Ashmun St",
    "sg:city":"Sault Ste Marie",
    "sg:classifiers":[
        {
            "category":"Home & Garden",
            "subcategory":"Carpets & Floor Coverings",
            "type":"Retail Goods"
        }
    ],
    "sg:phone":"+1 906 632 3367",
    "sg:postcode":"49783",
    "sg:province":"MI",
    "sg:tags":[
        "dealer",
        "rug"
    ],
    "wof:name":"House Of Bargains Inc",
    "wof:placetype":"venue"
},
  "geometry": {"coordinates":[-84.348719,46.496],"type":"Point"}
}