{
  "type": "Feature",
  "properties": {
    "iso:country":"US",
    "sg:address":"457 E Edgewood Blvd",
    "sg:city":"Lansing",
    "sg:classifiers":[
        {
            "category":"Real Estate",
            "subcategory":"Real Estate Operator",
            "type":"Services"
        }
    ],
    "sg:phone":"+1 517 887 0315",
    "sg:postcode":"48911",
    "sg:province":"MI",
    "sg:tags":[
        "building",
        "apartment"
    ],
    "wof:name":"Keystone Management Grp",
    "wof:placetype":"venue"
},
  "geometry": {"coordinates":[-84.546075,42.66433],"type":"Point"}
}