{
  "type": "Feature",
  "properties": {
    "iso:country":"US",
    "sg:address":"1985 McLean St",
    "sg:city":"Detroit",
    "sg:classifiers":[
        {
            "category":"Arts & Performance",
            "subcategory":"Theater",
            "type":"Entertainment"
        }
    ],
    "sg:phone":"+1 313 862 5193",
    "sg:postcode":"48212",
    "sg:province":"MI",
    "sg:tags":[
        "theatrical"
    ],
    "wof:name":"Total Step Productions LLC",
    "wof:placetype":"venue"
},
  "geometry": {"coordinates":[-83.07105300000001,42.407149],"type":"Point"}
}