{
  "type": "Feature",
  "properties": {
    "iso:country":"US",
    "sg:address":"1518 W Grand Blanc Rd",
    "sg:city":"Grand Blanc",
    "sg:classifiers":[
        {
            "category":"Manufacturing",
            "subcategory":"Tools & Machinery",
            "type":"Manufacturing & Wholesale Goods"
        }
    ],
    "sg:phone":"+1 810 655 6689",
    "sg:postcode":"48439",
    "sg:province":"MI",
    "sg:tags":[
        "recording",
        "medium",
        "mfg"
    ],
    "wof:name":"Golfsoft Company",
    "wof:placetype":"venue"
},
  "geometry": {"coordinates":[-83.705325,42.915094],"type":"Point"}
}