{
  "type": "Feature",
  "properties": {
    "iso:country":"US",
    "sg:address":"348 Elder Rd",
    "sg:city":"Mancelona",
    "sg:classifiers":[
        {
            "category":"Personal",
            "subcategory":"Beauty Salon",
            "type":"Services"
        }
    ],
    "sg:phone":"+1 231 587 5441",
    "sg:postcode":"49659",
    "sg:province":"MI",
    "sg:tags":[
        "shop"
    ],
    "wof:name":"A Cut Above",
    "wof:placetype":"venue"
},
  "geometry": {"coordinates":[-85.085206,44.887656],"type":"Point"}
}