{
  "type": "Feature",
  "properties": {
    "iso:country":"US",
    "sg:address":"17200 E 10 Mile Rd Ste 140",
    "sg:city":"Eastpointe",
    "sg:classifiers":[
        {
            "category":"Professional",
            "subcategory":"Lawyer & Legal Services",
            "type":"Services"
        }
    ],
    "sg:phone":"+1 586 775 2917",
    "sg:postcode":"48021",
    "sg:province":"MI",
    "wof:name":"Loy Dennis K PC",
    "wof:placetype":"venue"
},
  "geometry": {"coordinates":[-82.944003,42.479603],"type":"Point"}
}