{
  "type": "Feature",
  "properties": {
    "iso:country":"US",
    "sg:address":"6049 S Meridian Rd",
    "sg:city":"Jackson",
    "sg:classifiers":[
        {
            "category":"Health Services",
            "subcategory":"Medical Lab",
            "type":"Services"
        }
    ],
    "sg:phone":"+1 517 783 2383",
    "sg:postcode":"49201",
    "sg:province":"MI",
    "sg:tags":[
        "laboratory",
        "dental"
    ],
    "wof:name":"Moon Lake Dental Lab",
    "wof:placetype":"venue"
},
  "geometry": {"coordinates":[-84.364217,42.168704],"type":"Point"}
}