{
  "type": "Feature",
  "properties": {
    "iso:country":"US",
    "sg:address":"10049 Grand River Rd",
    "sg:city":"Brighton",
    "sg:classifiers":[
        {
            "category":"Personal",
            "subcategory":"Beauty Salon",
            "type":"Services"
        }
    ],
    "sg:phone":"+1 810 229 8883",
    "sg:postcode":"48116",
    "sg:province":"MI",
    "wof:name":"Salon At Brighton Beach",
    "wof:placetype":"venue"
},
  "geometry": {"coordinates":[-83.758414,42.520827],"type":"Point"}
}