{
  "type": "Feature",
  "properties": {
    "iso:country":"US",
    "sg:address":"18292 Hampton Ct",
    "sg:city":"Livonia",
    "sg:classifiers":[
        {
            "category":"Recreation",
            "type":"Entertainment"
        }
    ],
    "sg:phone":"+1 248 478 1514",
    "sg:postcode":"48152",
    "sg:province":"MI",
    "sg:tags":[
        "business"
    ],
    "wof:name":"L L Czan Gllery Fashion Design",
    "wof:placetype":"venue"
},
  "geometry": {"coordinates":[-83.39577,42.419361],"type":"Point"}
}