{
  "type": "Feature",
  "properties": {
    "iso:country":"US",
    "sg:address":"3308 Miller Rd",
    "sg:city":"Flint",
    "sg:classifiers":[
        {
            "category":"Education",
            "subcategory":"Special Training",
            "type":"Public Place"
        }
    ],
    "sg:phone":"+1 810 733 0740",
    "sg:postcode":"48507",
    "sg:province":"MI",
    "sg:tags":[
        "tutoring"
    ],
    "wof:name":"Learning Center Sw Flint",
    "wof:placetype":"venue"
},
  "geometry": {"coordinates":[-83.742683,42.987932],"type":"Point"}
}