{
  "type": "Feature",
  "properties": {
    "iso:country":"US",
    "sg:address":"3604 Mason Lake Rd NE",
    "sg:city":"Grand Rapids",
    "sg:classifiers":[
        {
            "category":"Real Estate",
            "subcategory":"Real Estate Agent",
            "type":"Services"
        }
    ],
    "sg:phone":"+1 616 361 6644",
    "sg:postcode":"49525",
    "sg:province":"MI",
    "wof:name":"J Sukup Realty Inc",
    "wof:placetype":"venue"
},
  "geometry": {"coordinates":[-85.580761,43.004384],"type":"Point"}
}