{
  "type": "Feature",
  "properties": {
    "iso:country":"US",
    "sg:address":"6491 E Jk Ave",
    "sg:city":"Kalamazoo",
    "sg:classifiers":[
        {
            "category":"Building & Trades",
            "subcategory":"Landscaping Services",
            "type":"Services"
        }
    ],
    "sg:phone":"+1 269 342 5362",
    "sg:postcode":"49048",
    "sg:province":"MI",
    "sg:tags":[
        "tree"
    ],
    "wof:name":"Don Bowman Tree Care Spec",
    "wof:placetype":"venue"
},
  "geometry": {"coordinates":[-85.503764,42.295697],"type":"Point"}
}