{
  "type": "Feature",
  "properties": {
    "iso:country":"US",
    "sg:address":"36712 Dina Ct",
    "sg:city":"Farmington Hills",
    "sg:classifiers":[
        {
            "category":"Building & Trades",
            "subcategory":"Construction",
            "type":"Services"
        }
    ],
    "sg:phone":"+1 810 844 0641",
    "sg:postcode":"48335",
    "sg:province":"MI",
    "sg:tags":[
        "general",
        "contractor"
    ],
    "wof:name":"Barringer Construction Inc",
    "wof:placetype":"venue"
},
  "geometry": {"coordinates":[-83.408788,42.457059],"type":"Point"}
}