{
  "type": "Feature",
  "properties": {
    "iso:country":"US",
    "sg:address":"19614 Korte Dr",
    "sg:city":"Clinton Township",
    "sg:classifiers":[
        {
            "category":"Real Estate",
            "subcategory":"Developer",
            "type":"Services"
        }
    ],
    "sg:phone":"+1 586 286 3340",
    "sg:postcode":"48038",
    "sg:province":"MI",
    "sg:tags":[
        "cemetery"
    ],
    "wof:name":"Forever Cemetery Care",
    "wof:placetype":"venue"
},
  "geometry": {"coordinates":[-82.922589,42.596435],"type":"Point"}
}