{
  "type": "Feature",
  "properties": {
    "iso:country":"US",
    "sg:address":"124 Cole Rd",
    "sg:city":"Monroe",
    "sg:classifiers":[
        {
            "category":"Shopping",
            "type":"Retail Goods"
        }
    ],
    "sg:phone":"+1 734 241 4397",
    "sg:postcode":"48162",
    "sg:province":"MI",
    "sg:tags":[
        "limb",
        "artificial"
    ],
    "wof:name":"Swanson Orthotic & Prosthetic",
    "wof:placetype":"venue"
},
  "geometry": {"coordinates":[-83.384547,41.936115],"type":"Point"}
}