{
  "type": "Feature",
  "properties": {
    "iso:country":"US",
    "sg:address":"111 Townley Dr",
    "sg:city":"Harbor Beach",
    "sg:classifiers":[
        {
            "category":"Professional",
            "subcategory":"Computer Services",
            "type":"Services"
        }
    ],
    "sg:phone":"+1 989 479 3109",
    "sg:postcode":"48441",
    "sg:province":"MI",
    "sg:tags":[
        "datum"
    ],
    "wof:name":"Jensoft Computer Services",
    "wof:placetype":"venue"
},
  "geometry": {"coordinates":[-82.66414,43.843226],"type":"Point"}
}