{
  "type": "Feature",
  "properties": {
    "iso:country":"US",
    "sg:address":"5930 S 6th St",
    "sg:city":"Kalamazoo",
    "sg:classifiers":[
        {
            "category":"Real Estate",
            "subcategory":"Architect",
            "type":"Services"
        }
    ],
    "sg:phone":"+1 269 372 7425",
    "sg:postcode":"49009",
    "sg:province":"MI",
    "wof:name":"AB2 Architecture",
    "wof:placetype":"venue"
},
  "geometry": {"coordinates":[-85.70625699999999,42.232644],"type":"Point"}
}