{
  "type": "Feature",
  "properties": {
    "iso:country":"US",
    "sg:address":"6400 Farmington Rd Ste 220",
    "sg:city":"West Bloomfield",
    "sg:classifiers":[
        {
            "category":"Banks & Credit Unions",
            "subcategory":"Financial Services",
            "type":"Services"
        }
    ],
    "sg:phone":"+1 248 592 4000",
    "sg:postcode":"48322",
    "sg:province":"MI",
    "sg:tags":[
        "broker",
        "mortgage"
    ],
    "sg:website":"www.firstmortgageamerica.com",
    "wof:name":"First Mortgage America",
    "wof:placetype":"venue"
},
  "geometry": {"coordinates":[-83.380402,42.544201],"type":"Point"}
}