{
  "type": "Feature",
  "properties": {
    "iso:country":"US",
    "sg:address":"401 S Tecumseh St",
    "sg:city":"Adrian",
    "sg:classifiers":[
        {
            "category":"Local Transit",
            "type":"Transportation"
        }
    ],
    "sg:phone":"+1 517 265 6611",
    "sg:postcode":"49221",
    "sg:province":"MI",
    "sg:tags":[
        "line"
    ],
    "wof:name":"Dial-A-Ride",
    "wof:placetype":"venue"
},
  "geometry": {"coordinates":[-84.026758,41.894628],"type":"Point"}
}