{
  "type": "Feature",
  "properties": {
    "iso:country":"US",
    "sg:address":"5100 Marsh Rd",
    "sg:city":"Okemos",
    "sg:classifiers":[
        {
            "category":"Personal",
            "subcategory":"Shoe Repair & Shine",
            "type":"Services"
        }
    ],
    "sg:phone":"+1 517 347 0411",
    "sg:postcode":"48864",
    "sg:province":"MI",
    "sg:tags":[
        "repairing",
        "boot"
    ],
    "wof:name":"Cobblers Bench",
    "wof:placetype":"venue"
},
  "geometry": {"coordinates":[-84.413133,42.729102],"type":"Point"}
}