{
  "type": "Feature",
  "properties": {
    "iso:country":"US",
    "sg:address":"4444 Kalamazoo Ave SE",
    "sg:city":"Grand Rapids",
    "sg:classifiers":[
        {
            "category":"Health Services",
            "subcategory":"Doctor",
            "type":"Services"
        }
    ],
    "sg:phone":"+1 616 455 9180",
    "sg:postcode":"49508",
    "sg:province":"MI",
    "sg:tags":[
        "medical"
    ],
    "wof:name":"McDonald Audiology",
    "wof:placetype":"venue"
},
  "geometry": {"coordinates":[-85.62596499999999,42.883303],"type":"Point"}
}