{
  "type": "Feature",
  "properties": {
    "iso:country":"US",
    "sg:address":"1907 Southfield Rd",
    "sg:city":"Lincoln Park",
    "sg:classifiers":[
        {
            "category":"Health Services",
            "subcategory":"Doctor",
            "type":"Services"
        },
        {
            "category":"Community Center",
            "type":"Public Place"
        }
    ],
    "sg:phone":"+1 313 383 3333",
    "sg:postcode":"48146",
    "sg:province":"MI",
    "sg:tags":[
        "medical"
    ],
    "wof:name":"Lincoln Park Medical Center & Urgent",
    "wof:placetype":"venue"
},
  "geometry": {"coordinates":[-83.191597,42.254299],"type":"Point"}
}