{
  "type": "Feature",
  "properties": {
    "iso:country":"US",
    "sg:address":"5040 Nadlie Ln",
    "sg:city":"Mt Morris",
    "sg:classifiers":[
        {
            "category":"Building & Trades",
            "subcategory":"Construction",
            "type":"Services"
        }
    ],
    "sg:phone":"+1 810 686 5223",
    "sg:postcode":"48458",
    "sg:province":"MI",
    "sg:tags":[
        "general",
        "contractor"
    ],
    "wof:name":"C Shaull Construction",
    "wof:placetype":"venue"
},
  "geometry": {"coordinates":[-83.663786,43.114158],"type":"Point"}
}