{
  "type": "Feature",
  "properties": {
    "iso:country":"US",
    "sg:address":"519 W Commerce Rd",
    "sg:city":"Commerce Twp",
    "sg:classifiers":[
        {
            "category":"Autos & Motor Vehicles",
            "subcategory":"Fuel & Gas Station",
            "type":"Retail Goods"
        }
    ],
    "sg:phone":"+1 248 360 0055",
    "sg:postcode":"48382",
    "sg:province":"MI",
    "sg:tags":[
        "oil"
    ],
    "wof:name":"Clark Gas Station",
    "wof:placetype":"venue"
},
  "geometry": {"coordinates":[-83.486901,42.591043],"type":"Point"}
}