{
  "type": "Feature",
  "properties": {
    "iso:country":"US",
    "sg:address":"4775 24th Ave",
    "sg:city":"Fort Gratiot",
    "sg:classifiers":[
        {
            "category":"Shopping",
            "type":"Retail Goods"
        }
    ],
    "sg:phone":"+1 810 385 1632",
    "sg:postcode":"48059",
    "sg:province":"MI",
    "sg:tags":[
        "picture"
    ],
    "wof:name":"Olan Mills",
    "wof:placetype":"venue"
},
  "geometry": {"coordinates":[-82.45724,43.046179],"type":"Point"}
}