{
  "type": "Feature",
  "properties": {
    "iso:country":"US",
    "sg:address":"28105 Woodward Ave",
    "sg:city":"Berkley",
    "sg:classifiers":[
        {
            "category":"Professional",
            "subcategory":"Research",
            "type":"Services"
        }
    ],
    "sg:phone":"+1 248 543 7982",
    "sg:postcode":"48072",
    "sg:province":"MI",
    "wof:name":"Affilted Mich Cncer Foundation",
    "wof:placetype":"venue"
},
  "geometry": {"coordinates":[-83.166425,42.496906],"type":"Point"}
}