{
  "type": "Feature",
  "properties": {
    "iso:country":"US",
    "sg:address":"950 W University Dr",
    "sg:city":"Rochester",
    "sg:classifiers":[
        {
            "category":"Professional",
            "type":"Services"
        }
    ],
    "sg:phone":"+1 248 841 9400",
    "sg:postcode":"48307",
    "sg:province":"MI",
    "sg:tags":[
        "establishment"
    ],
    "wof:name":"Weinner & Gould PC",
    "wof:placetype":"venue"
},
  "geometry": {"coordinates":[-83.14557600000001,42.681915],"type":"Point"}
}