{
  "type": "Feature",
  "properties": {
    "iso:country":"US",
    "sg:address":"7936 Lakecrest Dr",
    "sg:city":"Ypsilanti",
    "sg:classifiers":[
        {
            "category":"Professional",
            "subcategory":"Computer Services",
            "type":"Services"
        }
    ],
    "sg:phone":"+1 734 717 8224",
    "sg:postcode":"48197",
    "sg:province":"MI",
    "sg:tags":[
        "programing",
        "custom"
    ],
    "wof:name":"Virtual Model Shop Inc",
    "wof:placetype":"venue"
},
  "geometry": {"coordinates":[-83.60347400000001,42.214247],"type":"Point"}
}