{
  "type": "Feature",
  "properties": {
    "iso:country":"US",
    "sg:address":"1200 Central Ave",
    "sg:city":"Holland",
    "sg:classifiers":[
        {
            "category":"Freight",
            "type":"Transportation"
        }
    ],
    "sg:phone":"+1 616 396 1525",
    "sg:postcode":"49423",
    "sg:province":"MI",
    "sg:tags":[
        "commercial",
        "storage"
    ],
    "wof:name":"Stor-It",
    "wof:placetype":"venue"
},
  "geometry": {"coordinates":[-86.10677,42.756945],"type":"Point"}
}