{
  "type": "Feature",
  "properties": {
    "iso:country":"US",
    "sg:address":"2541 Kalamazoo Ave SE",
    "sg:city":"Grand Rapids",
    "sg:classifiers":[
        {
            "category":"Government",
            "subcategory":"Fire Station",
            "type":"Public Place"
        }
    ],
    "sg:phone":"+1 616 243 5235",
    "sg:postcode":"49507",
    "sg:province":"MI",
    "sg:tags":[
        "department"
    ],
    "wof:name":"Fire Station",
    "wof:placetype":"venue"
},
  "geometry": {"coordinates":[-85.631387,42.917442],"type":"Point"}
}