{
  "type": "Feature",
  "properties": {
    "iso:country":"US",
    "sg:address":"36330 Woodward Ave",
    "sg:city":"Bloomfield Hills",
    "sg:classifiers":[
        {
            "category":"Wholesale",
            "subcategory":"Durable Goods & Equipment",
            "type":"Manufacturing & Wholesale Goods"
        }
    ],
    "sg:phone":"+1 248 645 5620",
    "sg:postcode":"48304",
    "sg:province":"MI",
    "sg:tags":[
        "representative",
        "manufacturer"
    ],
    "wof:name":"CSI",
    "wof:placetype":"venue"
},
  "geometry": {"coordinates":[-83.22251199999999,42.558015],"type":"Point"}
}