{
  "type": "Feature",
  "properties": {
    "iso:country":"US",
    "sg:address":"34330 New Jersey St",
    "sg:city":"Clinton Township",
    "sg:classifiers":[
        {
            "category":"Arts & Performance",
            "subcategory":"Theater",
            "type":"Entertainment"
        }
    ],
    "sg:phone":"+1 586 791 4721",
    "sg:postcode":"48035",
    "sg:province":"MI",
    "sg:tags":[
        "dj",
        "live",
        "music",
        "group"
    ],
    "wof:name":"Superior Sounds Disk Jockeys",
    "wof:placetype":"venue"
},
  "geometry": {"coordinates":[-82.87159699999999,42.546799],"type":"Point"}
}