{
  "type": "Feature",
  "properties": {
    "iso:country":"US",
    "sg:address":"111 S Old Woodward Ave",
    "sg:city":"Birmingham",
    "sg:classifiers":[
        {
            "category":"Professional",
            "subcategory":"Management & Consulting",
            "type":"Services"
        }
    ],
    "sg:phone":"+1 248 644 0749",
    "sg:postcode":"48009",
    "sg:province":"MI",
    "sg:tags":[
        "consultant",
        "educational",
        "business"
    ],
    "wof:name":"Lynn B Luckenbach Inc",
    "wof:placetype":"venue"
},
  "geometry": {"coordinates":[-83.21332,42.545814],"type":"Point"}
}