{
  "type": "Feature",
  "properties": {
    "iso:country":"US",
    "sg:address":"503 N State St",
    "sg:city":"Alma",
    "sg:classifiers":[
        {
            "category":"Health Services",
            "subcategory":"Doctor",
            "type":"Services"
        }
    ],
    "sg:phone":"+1 517 463 2779",
    "sg:postcode":"48801",
    "sg:province":"MI",
    "sg:tags":[
        "medical"
    ],
    "wof:name":"Sunil R Rangwani MD",
    "wof:placetype":"venue"
},
  "geometry": {"coordinates":[-84.661905,43.381578],"type":"Point"}
}