{
  "type": "Feature",
  "properties": {
    "iso:country":"US",
    "sg:address":"6401 Enola Ave",
    "sg:city":"Kalamazoo",
    "sg:classifiers":[
        {
            "category":"Building & Trades",
            "subcategory":"Construction",
            "type":"Services"
        }
    ],
    "sg:phone":"+1 269 349 7563",
    "sg:postcode":"49048",
    "sg:province":"MI",
    "sg:tags":[
        "house"
    ],
    "wof:name":"Joseph Reisterer Builder",
    "wof:placetype":"venue"
},
  "geometry": {"coordinates":[-85.505414,42.320597],"type":"Point"}
}