{
  "type": "Feature",
  "properties": {
    "iso:country":"US",
    "sg:address":"8380 M 60",
    "sg:city":"Union City",
    "sg:classifiers":[
        {
            "category":"Shopping",
            "subcategory":"Clothing, Apparel, & Fashions",
            "type":"Retail Goods"
        }
    ],
    "sg:phone":"+1 517 741 4651",
    "sg:postcode":"49094",
    "sg:province":"MI",
    "sg:tags":[
        "industrial",
        "glove"
    ],
    "wof:name":"Glove Coaters Inc",
    "wof:placetype":"venue"
},
  "geometry": {"coordinates":[-85.132927,42.078208],"type":"Point"}
}