{
  "type": "Feature",
  "properties": {
    "iso:country":"US",
    "sg:address":"11950 Andersonville Rd",
    "sg:city":"Davisburg",
    "sg:classifiers":[
        {
            "category":"Personal",
            "type":"Services"
        }
    ],
    "sg:phone":"+1 248 634 1617",
    "sg:postcode":"48350",
    "sg:province":"MI",
    "wof:name":"Kustom Design & Renovation LLC",
    "wof:placetype":"venue"
},
  "geometry": {"coordinates":[-83.529319,42.742717],"type":"Point"}
}