{
  "type": "Feature",
  "properties": {
    "iso:country":"US",
    "sg:address":"26300 Ford Rd Ste 131",
    "sg:city":"Dearborn Heights",
    "sg:classifiers":[
        {
            "category":"Building & Trades",
            "subcategory":"Electrical",
            "type":"Services"
        }
    ],
    "sg:phone":"+1 313 436 9200",
    "sg:postcode":"48127",
    "sg:province":"MI",
    "sg:tags":[
        "electrician"
    ],
    "sg:website":"www.citywideelectric.biz",
    "wof:name":"City Wide Electric",
    "wof:placetype":"venue"
},
  "geometry": {"coordinates":[-83.29817199999999,42.327284],"type":"Point"}
}