{
  "type": "Feature",
  "properties": {
    "iso:country":"US",
    "sg:address":"741 E Portage Ave",
    "sg:city":"Sault Ste Marie",
    "sg:classifiers":[
        {
            "category":"Manufacturing",
            "subcategory":"Aerospace",
            "type":"Manufacturing & Wholesale Goods"
        }
    ],
    "sg:phone":"+1 906 632 1542",
    "sg:postcode":"49783",
    "sg:province":"MI",
    "sg:tags":[
        "aircraft",
        "component"
    ],
    "sg:website":"www.rbesoo.com",
    "wof:name":"R & B Electronics Inc",
    "wof:placetype":"venue"
},
  "geometry": {"coordinates":[-84.32982199999999,46.495016],"type":"Point"}
}