{
  "type": "Feature",
  "properties": {
    "iso:country":"US",
    "sg:address":"733 N Fordney Rd",
    "sg:city":"Hemlock",
    "sg:classifiers":[
        {
            "category":"Shopping",
            "subcategory":"Hobbies, Toys, & Games",
            "type":"Retail Goods"
        }
    ],
    "sg:phone":"+1 989 642 5423",
    "sg:postcode":"48626",
    "sg:province":"MI",
    "sg:tags":[
        "craft"
    ],
    "wof:name":"Cindy's Creative Crafts",
    "wof:placetype":"venue"
},
  "geometry": {"coordinates":[-84.190577,43.428495],"type":"Point"}
}