{
  "type": "Feature",
  "properties": {
    "iso:country":"US",
    "sg:address":"26653 Simone St",
    "sg:city":"Dearborn Heights",
    "sg:classifiers":[
        {
            "category":"Professional",
            "subcategory":"Business Services",
            "type":"Services"
        }
    ],
    "sg:phone":"+1 313 274 7839",
    "sg:postcode":"48127",
    "sg:province":"MI",
    "sg:tags":[
        "notary",
        "republic"
    ],
    "wof:name":"Laura Harris",
    "wof:placetype":"venue"
},
  "geometry": {"coordinates":[-83.305941,42.322548],"type":"Point"}
}