{
  "type": "Feature",
  "properties": {
    "iso:country":"US",
    "sg:address":"313 E Maumee St",
    "sg:city":"Adrian",
    "sg:classifiers":[
        {
            "category":"Education",
            "subcategory":"Dance Studio",
            "type":"Public Place"
        }
    ],
    "sg:phone":"+1 517 263 9553",
    "sg:postcode":"49221",
    "sg:province":"MI",
    "sg:tags":[
        "instruction",
        "dancing"
    ],
    "wof:name":"Encore Dance Studio",
    "wof:placetype":"venue"
},
  "geometry": {"coordinates":[-84.032689,41.897653],"type":"Point"}
}