{
  "type": "Feature",
  "properties": {
    "iso:country":"US",
    "sg:address":"2628 Lake Lansing Rd",
    "sg:city":"Lansing",
    "sg:classifiers":[
        {
            "category":"Education",
            "subcategory":"College",
            "type":"Public Place"
        }
    ],
    "sg:phone":"+1 517 485 8980",
    "sg:postcode":"48912",
    "sg:province":"MI",
    "sg:website":"www.northwood.edu",
    "wof:name":"Northwood University",
    "wof:placetype":"venue"
},
  "geometry": {"coordinates":[-84.52104,42.760661],"type":"Point"}
}