{
  "type": "Feature",
  "properties": {
    "iso:country":"US",
    "sg:address":"1249 Pomona Ct",
    "sg:city":"Fenton",
    "sg:classifiers":[
        {
            "category":"Food & Beverages",
            "subcategory":"Bakery",
            "type":"Retail Goods"
        }
    ],
    "sg:phone":"+1 810 750 6420",
    "sg:postcode":"48430",
    "sg:province":"MI",
    "sg:tags":[
        "cookie",
        "cracker"
    ],
    "wof:name":"Pomona's Gourmet Turtles",
    "wof:placetype":"venue"
},
  "geometry": {"coordinates":[-83.698151,42.833529],"type":"Point"}
}