{
  "type": "Feature",
  "properties": {
    "iso:country":"US",
    "sg:address":"1873 Maple Shade Dr",
    "sg:city":"Williamston",
    "sg:classifiers":[
        {
            "category":"Shopping",
            "subcategory":"Discount & Variety Stores",
            "type":"Retail Goods"
        }
    ],
    "sg:phone":"+1 517 655 2421",
    "sg:postcode":"48895",
    "sg:province":"MI",
    "sg:tags":[
        "merchandise",
        "general"
    ],
    "wof:name":"Collegiate Sales-Herff Jones",
    "wof:placetype":"venue"
},
  "geometry": {"coordinates":[-84.293465,42.71415],"type":"Point"}
}