{
  "type": "Feature",
  "properties": {
    "iso:country":"US",
    "sg:address":"516 S Creyts Rd",
    "sg:city":"Lansing",
    "sg:classifiers":[
        {
            "category":"Organizations",
            "subcategory":"Non-profit Organization",
            "type":"Services"
        }
    ],
    "sg:phone":"+1 517 321 7500",
    "sg:postcode":"48917",
    "sg:province":"MI",
    "wof:name":"Michigan Community Action",
    "wof:placetype":"venue"
},
  "geometry": {"coordinates":[-84.64237300000001,42.729285],"type":"Point"}
}