{
  "type": "Feature",
  "properties": {
    "iso:country":"US",
    "sg:address":"922 Cesar E Chavez Ave",
    "sg:city":"Pontiac",
    "sg:classifiers":[
        {
            "category":"Building & Trades",
            "subcategory":"Construction",
            "type":"Services"
        }
    ],
    "sg:phone":"+1 248 335 4850",
    "sg:postcode":"48340",
    "sg:province":"MI",
    "sg:tags":[
        "masonry",
        "contractor"
    ],
    "wof:name":"Albaugh Masonry Stone & Tile",
    "wof:placetype":"venue"
},
  "geometry": {"coordinates":[-83.318641,42.658516],"type":"Point"}
}