{
  "type": "Feature",
  "properties": {
    "iso:country":"US",
    "sg:address":"3460 Tanglewood Trl",
    "sg:city":"Chelsea",
    "sg:classifiers":[
        {
            "category":"Banks & Credit Unions",
            "subcategory":"Financial Services",
            "type":"Services"
        }
    ],
    "sg:phone":"+1 734 424 9499",
    "sg:postcode":"48118",
    "sg:province":"MI",
    "sg:tags":[
        "investor"
    ],
    "wof:name":"Orchid Investments LLC",
    "wof:placetype":"venue"
},
  "geometry": {"coordinates":[-83.977581,42.350662],"type":"Point"}
}