{
  "type": "Feature",
  "properties": {
    "iso:country":"US",
    "sg:address":"1006 Benstein Rd",
    "sg:city":"Commerce Twp",
    "sg:classifiers":[
        {
            "category":"Home & Garden",
            "subcategory":"Furniture",
            "type":"Retail Goods"
        }
    ],
    "sg:phone":"+1 248 926 1777",
    "sg:postcode":"48390",
    "sg:province":"MI",
    "sg:tags":[
        "builder",
        "custom"
    ],
    "wof:name":"Denco Interiors",
    "wof:placetype":"venue"
},
  "geometry": {"coordinates":[-83.502375,42.538683],"type":"Point"}
}