{
  "type": "Feature",
  "properties": {
    "iso:country":"US",
    "sg:address":"250 Elizabeth Lake Rd",
    "sg:city":"Pontiac",
    "sg:classifiers":[
        {
            "category":"Organizations",
            "subcategory":"Non-profit Organization",
            "type":"Services"
        }
    ],
    "sg:phone":"+1 248 858 5200",
    "sg:postcode":"48341",
    "sg:province":"MI",
    "sg:tags":[
        "information",
        "alcoholism",
        "treatment"
    ],
    "wof:name":"Central Diagnosis & Referral",
    "wof:placetype":"venue"
},
  "geometry": {"coordinates":[-83.319142,42.640766],"type":"Point"}
}