{
  "type": "Feature",
  "properties": {
    "iso:country":"US",
    "sg:address":"10360 Homestead Ln",
    "sg:city":"Plymouth",
    "sg:classifiers":[
        {
            "category":"Building & Trades",
            "subcategory":"Construction",
            "type":"Services"
        }
    ],
    "sg:phone":"+1 734 453 4900",
    "sg:postcode":"48170",
    "sg:province":"MI",
    "sg:tags":[
        "contractor"
    ],
    "wof:name":"Great State Construction",
    "wof:placetype":"venue"
},
  "geometry": {"coordinates":[-83.561938,42.371737],"type":"Point"}
}