{
  "type": "Feature",
  "properties": {
    "iso:country":"US",
    "sg:address":"5829 E Deerfield Rd",
    "sg:city":"Mount Pleasant",
    "sg:phone":"+1 989 773 9222",
    "sg:postcode":"48858",
    "sg:province":"MI",
    "sg:tags":[
        "farm",
        "corn",
        "soybean"
    ],
    "wof:name":"Jim Cary",
    "wof:placetype":"venue"
},
  "geometry": {"coordinates":[-84.736279,43.568113],"type":"Point"}
}