{
  "type": "Feature",
  "properties": {
    "iso:country":"US",
    "sg:address":"5106 Marlowe Dr SE",
    "sg:city":"Grand Rapids",
    "sg:classifiers":[
        {
            "category":"Real Estate",
            "subcategory":"Real Estate Agent",
            "type":"Services"
        }
    ],
    "sg:phone":"+1 616 974 6252",
    "sg:postcode":"49548",
    "sg:province":"MI",
    "wof:name":"Lawrence Bergen Inc",
    "wof:placetype":"venue"
},
  "geometry": {"coordinates":[-85.653649,42.870464],"type":"Point"}
}