{
  "type": "Feature",
  "properties": {
    "iso:country":"US",
    "sg:address":"933 Lapeer Ave",
    "sg:city":"Port Huron",
    "sg:classifiers":[
        {
            "category":"Organizations",
            "subcategory":"Community Association",
            "type":"Services"
        }
    ],
    "sg:phone":"+1 810 985 9316",
    "sg:postcode":"48060",
    "sg:province":"MI",
    "sg:tags":[
        "club"
    ],
    "wof:name":"Michigan Automobile Club",
    "wof:placetype":"venue"
},
  "geometry": {"coordinates":[-82.431901,42.976202],"type":"Point"}
}