{
  "type": "Feature",
  "properties": {
    "iso:country":"US",
    "sg:address":"11194 Finley Rd",
    "sg:city":"Hawks",
    "sg:classifiers":[
        {
            "category":"Building & Trades",
            "subcategory":"Construction",
            "type":"Services"
        }
    ],
    "sg:phone":"+1 989 766 2208",
    "sg:postcode":"49743",
    "sg:province":"MI",
    "sg:tags":[
        "excavation",
        "work"
    ],
    "wof:name":"G W Excavating",
    "wof:placetype":"venue"
},
  "geometry": {"coordinates":[-83.861673,45.257031],"type":"Point"}
}