{
  "type": "Feature",
  "properties": {
    "iso:country":"US",
    "sg:address":"16020 W Peet Rd",
    "sg:city":"Oakley",
    "sg:classifiers":[
        {
            "category":"Social Services",
            "type":"Services"
        }
    ],
    "sg:phone":"+1 989 845 7200",
    "sg:postcode":"48649",
    "sg:province":"MI",
    "wof:name":"Brady Senior Center",
    "wof:placetype":"venue"
},
  "geometry": {"coordinates":[-84.233794,43.172455],"type":"Point"}
}