{
  "type": "Feature",
  "properties": {
    "iso:country":"US",
    "sg:address":"21412 Jewell St",
    "sg:city":"Saint Clair Shores",
    "sg:classifiers":[
        {
            "category":"Retail",
            "subcategory":"Car Wash",
            "type":"Services"
        }
    ],
    "sg:phone":"+1 586 873 9274",
    "sg:postcode":"48082",
    "sg:province":"MI",
    "sg:tags":[
        "carwash"
    ],
    "wof:name":"Keep It Kleen Power Washing",
    "wof:placetype":"venue"
},
  "geometry": {"coordinates":[-82.89878899999999,42.517775],"type":"Point"}
}