{
  "type": "Feature",
  "properties": {
    "iso:country":"US",
    "sg:address":"13380 S Waldron Rd",
    "sg:city":"Waldron",
    "sg:classifiers":[
        {
            "category":"Social Services",
            "subcategory":"Child Care",
            "type":"Services"
        }
    ],
    "sg:phone":"+1 517 286 6268",
    "sg:postcode":"49288",
    "sg:province":"MI",
    "sg:tags":[
        "kindergarten",
        "academic",
        "school"
    ],
    "wof:name":"Waldron Head Start & Family",
    "wof:placetype":"venue"
},
  "geometry": {"coordinates":[-84.41897400000001,41.734336],"type":"Point"}
}