{
  "type": "Feature",
  "properties": {
    "iso:country":"US",
    "sg:address":"132 W South St",
    "sg:city":"Kalamazoo",
    "sg:classifiers":[
        {
            "category":"Personal",
            "type":"Services"
        }
    ],
    "sg:phone":"+1 269 330 0786",
    "sg:postcode":"49007",
    "sg:province":"MI",
    "sg:tags":[
        "therapist",
        "massage"
    ],
    "wof:name":"Melissa Spamer",
    "wof:placetype":"venue"
},
  "geometry": {"coordinates":[-85.584329,42.289866],"type":"Point"}
}