{
  "type": "Feature",
  "properties": {
    "iso:country":"US",
    "sg:address":"1301 S Main St",
    "sg:city":"Adrian",
    "sg:classifiers":[
        {
            "category":"Cinema",
            "subcategory":"Movie Rental",
            "type":"Entertainment"
        }
    ],
    "sg:phone":"+1 517 264 2066",
    "sg:postcode":"49221",
    "sg:province":"MI",
    "sg:tags":[
        "leasing",
        "video",
        "disc",
        "tape"
    ],
    "wof:name":"R & J Discount Outlet",
    "wof:placetype":"venue"
},
  "geometry": {"coordinates":[-84.043307,41.881828],"type":"Point"}
}