{
  "type": "Feature",
  "properties": {
    "iso:country":"US",
    "sg:address":"873 N Blacks Corners Rd",
    "sg:city":"Imlay City",
    "sg:classifiers":[
        {
            "category":"Retail",
            "subcategory":"Animal Services",
            "type":"Services"
        }
    ],
    "sg:phone":"+1 810 724 1912",
    "sg:postcode":"48444",
    "sg:province":"MI",
    "wof:name":"Larry Kennel",
    "wof:placetype":"venue"
},
  "geometry": {"coordinates":[-83.089158,43.057605],"type":"Point"}
}