{
  "type": "Feature",
  "properties": {
    "iso:country":"US",
    "sg:address":"17158 Brady",
    "sg:city":"Redford",
    "sg:classifiers":[
        {
            "category":"Professional",
            "subcategory":"Business Services",
            "type":"Services"
        }
    ],
    "sg:phone":"+1 313 532 1269",
    "sg:postcode":"48240",
    "sg:province":"MI",
    "wof:name":"Make Waves Media",
    "wof:placetype":"venue"
},
  "geometry": {"coordinates":[-83.28794000000001,42.416333],"type":"Point"}
}