{
  "type": "Feature",
  "properties": {
    "iso:country":"US",
    "sg:address":"131 E Summit St",
    "sg:city":"Breckenridge",
    "sg:classifiers":[
        {
            "category":"Government",
            "subcategory":"Office",
            "type":"Public Place"
        }
    ],
    "sg:phone":"+1 989 842 3137",
    "sg:postcode":"48615",
    "sg:province":"MI",
    "sg:tags":[
        "village"
    ],
    "wof:name":"Breckenridge Village Water",
    "wof:placetype":"venue"
},
  "geometry": {"coordinates":[-84.47881700000001,43.411316],"type":"Point"}
}