{
  "type": "Feature",
  "properties": {
    "iso:country":"US",
    "sg:address":"4866 Ridgewater Run",
    "sg:city":"Traverse City",
    "sg:classifiers":[
        {
            "category":"Professional",
            "subcategory":"Accounting & Tax Preparation",
            "type":"Services"
        }
    ],
    "sg:phone":"+1 231 946 8299",
    "sg:postcode":"49684",
    "sg:province":"MI",
    "sg:tags":[
        "accountant"
    ],
    "wof:name":"Nancy Smith Accounting Svc",
    "wof:placetype":"venue"
},
  "geometry": {"coordinates":[-85.747578,44.75816],"type":"Point"}
}