{
  "type": "Feature",
  "properties": {
    "iso:country":"US",
    "sg:address":"7000 Lakeview Blvd Ofc",
    "sg:city":"Westland",
    "sg:classifiers":[
        {
            "category":"Real Estate",
            "subcategory":"Real Estate Services",
            "type":"Services"
        },
        {
            "category":"Real Estate",
            "subcategory":"Real Estate Operator",
            "type":"Services"
        }
    ],
    "sg:phone":"+1 734 729 5650",
    "sg:postcode":"48185",
    "sg:province":"MI",
    "sg:tags":[
        "apartment",
        "property",
        "management"
    ],
    "wof:name":"Landings Apartments the",
    "wof:placetype":"venue"
},
  "geometry": {"coordinates":[-83.397598,42.335999],"type":"Point"}
}