{
  "type": "Feature",
  "properties": {
    "iso:country":"US",
    "sg:address":"208 N Lincoln Ave",
    "sg:city":"Lakeview",
    "sg:classifiers":[
        {
            "category":"Autos & Motor Vehicles",
            "subcategory":"Automobile Sales",
            "type":"Retail Goods"
        }
    ],
    "sg:phone":"+1 989 352 7251",
    "sg:postcode":"48850",
    "sg:province":"MI",
    "sg:tags":[
        "car",
        "dealer"
    ],
    "sg:website":"www.bollingers.net",
    "wof:name":"Bollinger's Inc",
    "wof:placetype":"venue"
},
  "geometry": {"coordinates":[-85.282071,43.445503],"type":"Point"}
}