{
  "type": "Feature",
  "properties": {
    "iso:country":"US",
    "sg:address":"1032 N Leroy St",
    "sg:city":"Fenton",
    "sg:classifiers":[
        {
            "category":"Real Estate",
            "subcategory":"Real Estate Agent",
            "type":"Services"
        }
    ],
    "sg:phone":"+1 810 750 4663",
    "sg:postcode":"48430",
    "sg:province":"MI",
    "sg:tags":[
        "agency"
    ],
    "sg:website":"www.tremainerealestate.com",
    "wof:name":"Tremaine Real Estate Co",
    "wof:placetype":"venue"
},
  "geometry": {"coordinates":[-83.707205,42.807896],"type":"Point"}
}