{
  "type": "Feature",
  "properties": {
    "iso:country":"US",
    "sg:address":"13329 Portage Rd",
    "sg:city":"Vicksburg",
    "sg:classifiers":[
        {
            "category":"Retail",
            "subcategory":"Animal Services",
            "type":"Services"
        }
    ],
    "sg:phone":"+1 269 649 5612",
    "sg:postcode":"49097",
    "sg:province":"MI",
    "sg:tags":[
        "pet",
        "boarding",
        "sitting"
    ],
    "wof:name":"Kitty Cat Bed-N-Breakfast",
    "wof:placetype":"venue"
},
  "geometry": {"coordinates":[-85.56956099999999,42.152648],"type":"Point"}
}