{
  "type": "Feature",
  "properties": {
    "iso:country":"US",
    "sg:address":"531 S Dexter Dr",
    "sg:city":"Lansing",
    "sg:classifiers":[
        {
            "category":"Professional",
            "type":"Services"
        }
    ],
    "sg:phone":"+1 517 394 6073",
    "sg:postcode":"48910",
    "sg:province":"MI",
    "wof:name":"Professional Admin Services So",
    "wof:placetype":"venue"
},
  "geometry": {"coordinates":[-84.54488600000001,42.69863],"type":"Point"}
}