{
  "type": "Feature",
  "properties": {
    "iso:country":"US",
    "sg:address":"5404 Sherwood Rd",
    "sg:city":"Oxford",
    "sg:classifiers":[
        {
            "category":"Building & Trades",
            "subcategory":"Construction",
            "type":"Services"
        }
    ],
    "sg:phone":"+1 248 628 4893",
    "sg:postcode":"48371",
    "sg:province":"MI",
    "sg:tags":[
        "layer",
        "carpet"
    ],
    "wof:name":"D & A Carpet & Tile",
    "wof:placetype":"venue"
},
  "geometry": {"coordinates":[-83.353623,42.82385],"type":"Point"}
}