{
  "type": "Feature",
  "properties": {
    "iso:country":"US",
    "sg:address":"5957 State St",
    "sg:city":"Kingston",
    "sg:classifiers":[
        {
            "category":"Restaurant",
            "type":"Food & Drink"
        }
    ],
    "sg:phone":"+1 989 683 2640",
    "sg:postcode":"48741",
    "sg:province":"MI",
    "wof:name":"Beagio's Pizza",
    "wof:placetype":"venue"
},
  "geometry": {"coordinates":[-83.188109,43.41292],"type":"Point"}
}