{
  "type": "Feature",
  "properties": {
    "iso:country":"US",
    "sg:address":"1 Monroe Ave NW",
    "sg:city":"Grand Rapids",
    "sg:classifiers":[
        {
            "category":"Professional",
            "type":"Services"
        }
    ],
    "sg:phone":"+1 616 456 4809",
    "sg:postcode":"49503",
    "sg:province":"MI",
    "wof:name":"Metropolitan Enf Tm Co",
    "wof:placetype":"venue"
},
  "geometry": {"coordinates":[-85.672759,42.964211],"type":"Point"}
}