{
  "type": "Feature",
  "properties": {
    "iso:country":"US",
    "sg:address":"3090 Main St",
    "sg:city":"Marlette",
    "sg:classifiers":[
        {
            "category":"Professional",
            "subcategory":"Management & Consulting",
            "type":"Services"
        }
    ],
    "sg:phone":"+1 989 635 3551",
    "sg:postcode":"48453",
    "sg:province":"MI",
    "wof:name":"Massoglia Financial Plg LLC",
    "wof:placetype":"venue"
},
  "geometry": {"coordinates":[-83.079939,43.326173],"type":"Point"}
}