{
  "type": "Feature",
  "properties": {
    "iso:country":"US",
    "sg:address":"4530 Alan Ln",
    "sg:city":"Lake Orion",
    "sg:classifiers":[
        {
            "category":"Real Estate",
            "subcategory":"Real Estate Agent",
            "type":"Services"
        }
    ],
    "sg:phone":"+1 248 393 2003",
    "sg:postcode":"48359",
    "sg:province":"MI",
    "wof:name":"Regina Appraisal Svc",
    "wof:placetype":"venue"
},
  "geometry": {"coordinates":[-83.314374,42.713626],"type":"Point"}
}