{
  "type": "Feature",
  "properties": {
    "iso:country":"US",
    "sg:address":"5225 Highland Rd",
    "sg:city":"Waterford",
    "sg:classifiers":[
        {
            "category":"Professional",
            "subcategory":"Computer Services",
            "type":"Services"
        }
    ],
    "sg:phone":"+1 248 674 7580",
    "sg:postcode":"48327",
    "sg:province":"MI",
    "sg:tags":[
        "repair"
    ],
    "sg:website":"www.data-link.com",
    "wof:name":"Datalinks",
    "wof:placetype":"venue"
},
  "geometry": {"coordinates":[-83.391848,42.660195],"type":"Point"}
}