{
  "type": "Feature",
  "properties": {
    "iso:country":"US",
    "sg:address":"4150 S Saginaw St",
    "sg:city":"Flint",
    "sg:classifiers":[
        {
            "category":"Health Services",
            "subcategory":"Chiropractor",
            "type":"Services"
        }
    ],
    "sg:phone":"+1 810 742 1880",
    "sg:postcode":"48507",
    "sg:province":"MI",
    "wof:name":"Healthquest of Burton",
    "wof:placetype":"venue"
},
  "geometry": {"coordinates":[-83.67559799999999,42.986301],"type":"Point"}
}