{
  "type": "Feature",
  "properties": {
    "iso:country":"US",
    "sg:address":"299 Grindstone Rd",
    "sg:city":"Port Austin",
    "sg:classifiers":[
        {
            "category":"Real Estate",
            "subcategory":"Real Estate Operator",
            "type":"Services"
        }
    ],
    "sg:phone":"+1 989 738 8545",
    "sg:postcode":"48467",
    "sg:province":"MI",
    "sg:tags":[
        "apartment"
    ],
    "wof:name":"Harbor Villa Apartments",
    "wof:placetype":"venue"
},
  "geometry": {"coordinates":[-82.98790700000001,44.040862],"type":"Point"}
}