{
  "type": "Feature",
  "properties": {
    "iso:country":"US",
    "sg:address":"419 Michigan St",
    "sg:city":"Algonac",
    "sg:classifiers":[
        {
            "category":"Food & Beverages",
            "subcategory":"Groceries & Convenience Stores",
            "type":"Retail Goods"
        }
    ],
    "sg:phone":"+1 810 794 7031",
    "sg:postcode":"48001",
    "sg:province":"MI",
    "sg:tags":[
        "grocer"
    ],
    "wof:name":"Kings IGA",
    "wof:placetype":"venue"
},
  "geometry": {"coordinates":[-82.53670099999999,42.614431],"type":"Point"}
}