{
  "type": "Feature",
  "properties": {
    "iso:country":"US",
    "sg:address":"121 Ashman St",
    "sg:city":"Midland",
    "sg:classifiers":[
        {
            "category":"Real Estate",
            "subcategory":"Real Estate Agent",
            "type":"Services"
        }
    ],
    "sg:phone":"+1 989 633 0123",
    "sg:postcode":"48640",
    "sg:province":"MI",
    "wof:name":"Darger & Assoc",
    "wof:placetype":"venue"
},
  "geometry": {"coordinates":[-84.244854,43.613745],"type":"Point"}
}