{
  "type": "Feature",
  "properties": {
    "iso:country":"US",
    "sg:address":"3140 N 3rd St",
    "sg:city":"Kalamazoo",
    "sg:classifiers":[
        {
            "category":"Organizations",
            "subcategory":"Religious Organization",
            "type":"Services"
        }
    ],
    "sg:phone":"+1 269 375 2700",
    "sg:postcode":"49009",
    "sg:province":"MI",
    "sg:tags":[
        "church"
    ],
    "wof:name":"Northwest United Methodist Chr",
    "wof:placetype":"venue"
},
  "geometry": {"coordinates":[-85.735491,42.310375],"type":"Point"}
}