{
  "type": "Feature",
  "properties": {
    "iso:country":"US",
    "sg:address":"115 W 27th St",
    "sg:city":"Holland",
    "sg:classifiers":[
        {
            "category":"Building & Trades",
            "subcategory":"Pest Control",
            "type":"Services"
        }
    ],
    "sg:phone":"+1 616 494 9660",
    "sg:postcode":"49423",
    "sg:province":"MI",
    "wof:name":"Stingers Pest Control Inc",
    "wof:placetype":"venue"
},
  "geometry": {"coordinates":[-86.113449,42.773128],"type":"Point"}
}