{
  "type": "Feature",
  "properties": {
    "iso:country":"US",
    "sg:address":"2866 Dowling Hwy",
    "sg:city":"Hudson",
    "sg:classifiers":[
        {
            "category":"Real Estate",
            "subcategory":"Real Estate Agent",
            "type":"Services"
        }
    ],
    "sg:phone":"+1 517 448 8529",
    "sg:postcode":"49247",
    "sg:province":"MI",
    "sg:tags":[
        "investment"
    ],
    "wof:name":"Sallows Sanborn Land Co",
    "wof:placetype":"venue"
},
  "geometry": {"coordinates":[-84.31473800000001,41.871968],"type":"Point"}
}