{
  "type": "Feature",
  "properties": {
    "iso:country":"US",
    "sg:address":"410 North St",
    "sg:city":"Otisville",
    "sg:classifiers":[
        {
            "category":"Personal",
            "subcategory":"Barber",
            "type":"Services"
        }
    ],
    "sg:phone":"+1 810 631 2333",
    "sg:postcode":"48463",
    "sg:province":"MI",
    "wof:name":"Family Barber Shop",
    "wof:placetype":"venue"
},
  "geometry": {"coordinates":[-83.524508,43.171432],"type":"Point"}
}