{
  "type": "Feature",
  "properties": {
    "iso:country":"US",
    "sg:address":"900 26th St",
    "sg:city":"Menominee",
    "sg:classifiers":[
        {
            "category":"Professional",
            "subcategory":"Accounting & Tax Preparation",
            "type":"Services"
        }
    ],
    "sg:phone":"+1 906 863 4457",
    "sg:postcode":"49858",
    "sg:province":"MI",
    "sg:tags":[
        "accountant"
    ],
    "wof:name":"Johnson & Rennie LLC",
    "wof:placetype":"venue"
},
  "geometry": {"coordinates":[-87.634852,45.108014],"type":"Point"}
}