{
  "type": "Feature",
  "properties": {
    "iso:country":"US",
    "sg:address":"718 W Buttles St",
    "sg:city":"Midland",
    "sg:classifiers":[
        {
            "category":"Autos & Motor Vehicles",
            "subcategory":"Automobile Sales",
            "type":"Retail Goods"
        }
    ],
    "sg:phone":"+1 989 835 6711",
    "sg:postcode":"48640",
    "sg:province":"MI",
    "sg:tags":[
        "car",
        "dealer"
    ],
    "sg:website":"www.dirkwaltz.com",
    "wof:name":"Dirk Waltz Buick-Oldsmobile",
    "wof:placetype":"venue"
},
  "geometry": {"coordinates":[-84.249089,43.619475],"type":"Point"}
}