{
  "type": "Feature",
  "properties": {
    "iso:country":"US",
    "sg:address":"27720 Woodward Ave",
    "sg:city":"Royal Oak",
    "sg:classifiers":[
        {
            "category":"Building & Trades",
            "subcategory":"Construction",
            "type":"Services"
        }
    ],
    "sg:phone":"+1 248 591 9780",
    "sg:postcode":"48067",
    "sg:province":"MI",
    "sg:tags":[
        "home",
        "improvement"
    ],
    "wof:name":"Lead Strategists",
    "wof:placetype":"venue"
},
  "geometry": {"coordinates":[-83.163798,42.494912],"type":"Point"}
}