{
  "type": "Feature",
  "properties": {
    "iso:country":"US",
    "sg:address":"544 E 8th St",
    "sg:city":"Traverse City",
    "sg:classifiers":[
        {
            "category":"Shopping",
            "subcategory":"Used Merchandise",
            "type":"Retail Goods"
        }
    ],
    "sg:phone":"+1 231 935 4700",
    "sg:postcode":"49686",
    "sg:province":"MI",
    "sg:tags":[
        "shop",
        "consignment"
    ],
    "wof:name":"Upscale Resale",
    "wof:placetype":"venue"
},
  "geometry": {"coordinates":[-85.61270500000001,44.759325],"type":"Point"}
}