{
  "type": "Feature",
  "properties": {
    "iso:country":"US",
    "sg:address":"16800 South Chandler",
    "sg:city":"East Lansing",
    "sg:classifiers":[
        {
            "category":"Restaurant",
            "type":"Food & Drink"
        }
    ],
    "sg:menulink":"http://www.allmenus.com/mi/bath/250030-average-joes-sports-grill/menu/",
    "sg:phone":"+1 517 203 4090",
    "sg:postcode":"48823",
    "sg:province":"MI",
    "sg:tags":[
        "wrap",
        "american",
        "sandwich"
    ],
    "wof:name":"Average Joe's Sports Grill",
    "wof:placetype":"venue"
},
  "geometry": {"coordinates":[-84.48364100000001,42.771882],"type":"Point"}
}