{
  "type": "Feature",
  "properties": {
    "iso:country":"US",
    "sg:address":"5069 Coldwater Rd",
    "sg:city":"Flint",
    "sg:classifiers":[
        {
            "category":"Building & Trades",
            "subcategory":"Cleaning & Sanitation",
            "type":"Services"
        }
    ],
    "sg:phone":"+1 810 720 1099",
    "sg:postcode":"48504",
    "sg:province":"MI",
    "sg:tags":[
        "maintenance"
    ],
    "wof:name":"Curlys Cleaning Service",
    "wof:placetype":"venue"
},
  "geometry": {"coordinates":[-83.78195100000001,43.089653],"type":"Point"}
}