{
  "type": "Feature",
  "properties": {
    "iso:country":"US",
    "sg:address":"240 Fogg Rd",
    "sg:city":"Leslie",
    "sg:classifiers":[
        {
            "category":"Recreation",
            "type":"Entertainment"
        }
    ],
    "sg:phone":"+1 517 589 0133",
    "sg:postcode":"49251",
    "sg:province":"MI",
    "sg:tags":[
        "archery",
        "range"
    ],
    "wof:name":"Whitetail Acres Archery Range",
    "wof:placetype":"venue"
},
  "geometry": {"coordinates":[-84.352256,42.471467],"type":"Point"}
}