{
  "type": "Feature",
  "properties": {
    "iso:country":"US",
    "sg:address":"699 Birch Ln",
    "sg:city":"Grosse Pointe",
    "sg:classifiers":[
        {
            "category":"Professional",
            "subcategory":"Management & Consulting",
            "type":"Services"
        }
    ],
    "sg:phone":"+1 313 647 0555",
    "sg:postcode":"48236",
    "sg:province":"MI",
    "sg:tags":[
        "marketing",
        "communication"
    ],
    "wof:name":"Wines Creative Services Inc",
    "wof:placetype":"venue"
},
  "geometry": {"coordinates":[-82.89254699999999,42.426233],"type":"Point"}
}