{
  "type": "Feature",
  "properties": {
    "iso:country":"US",
    "sg:address":"103 Lem Paul St",
    "sg:city":"Middleville",
    "sg:classifiers":[
        {
            "category":"Banks & Credit Unions",
            "subcategory":"Bank",
            "type":"Services"
        }
    ],
    "sg:phone":"+1 269 795 7633",
    "sg:postcode":"49333",
    "sg:province":"MI",
    "sg:tags":[
        "loan",
        "real estate"
    ],
    "wof:name":"Security Mortgage",
    "wof:placetype":"venue"
},
  "geometry": {"coordinates":[-85.472818,42.711961],"type":"Point"}
}