{
  "type": "Feature",
  "properties": {
    "iso:country":"US",
    "sg:address":"3631 Mann Rd",
    "sg:city":"Clarkston",
    "sg:classifiers":[
        {
            "category":"Building & Trades",
            "subcategory":"Landscaping Services",
            "type":"Services"
        }
    ],
    "sg:phone":"+1 248 673 8482",
    "sg:postcode":"48346",
    "sg:province":"MI",
    "sg:tags":[
        "landscape"
    ],
    "wof:name":"Cecil Property Services",
    "wof:placetype":"venue"
},
  "geometry": {"coordinates":[-83.355711,42.703704],"type":"Point"}
}