{
  "type": "Feature",
  "properties": {
    "iso:country":"US",
    "sg:address":"7320 Grand River Rd",
    "sg:city":"Bancroft",
    "sg:classifiers":[
        {
            "category":"Wholesale",
            "subcategory":"Motor Vehicles",
            "type":"Manufacturing & Wholesale Goods"
        }
    ],
    "sg:phone":"+1 989 634 5760",
    "sg:postcode":"48414",
    "sg:province":"MI",
    "wof:name":"R & L Enterprises Inc",
    "wof:placetype":"venue"
},
  "geometry": {"coordinates":[-84.03101599999999,42.830712],"type":"Point"}
}