{
  "type": "Feature",
  "properties": {
    "iso:country":"US",
    "sg:address":"2012 10th St",
    "sg:city":"Menominee",
    "sg:classifiers":[
        {
            "category":"Insurance",
            "subcategory":"Insurance Agent",
            "type":"Services"
        }
    ],
    "sg:phone":"+1 906 864 3424",
    "sg:postcode":"49858",
    "sg:province":"MI",
    "wof:name":"Hughes Financial Svc",
    "wof:placetype":"venue"
},
  "geometry": {"coordinates":[-87.61353,45.11954],"type":"Point"}
}