{
  "type": "Feature",
  "properties": {
    "iso:country":"US",
    "sg:address":"600 S Adams Rd",
    "sg:city":"Birmingham",
    "sg:classifiers":[
        {
            "category":"Health Services",
            "subcategory":"Clinic",
            "type":"Services"
        }
    ],
    "sg:phone":"+1 248 594 3867",
    "sg:postcode":"48009",
    "sg:province":"MI",
    "sg:tags":[
        "counseling",
        "mental"
    ],
    "wof:name":"Mazure Phyllis MA PC",
    "wof:placetype":"venue"
},
  "geometry": {"coordinates":[-83.205597,42.543201],"type":"Point"}
}