{
  "type": "Feature",
  "properties": {
    "iso:country":"US",
    "sg:address":"113 W Houghton Ave",
    "sg:city":"West Branch",
    "sg:classifiers":[
        {
            "category":"Banks & Credit Unions",
            "subcategory":"Bank",
            "type":"Services"
        }
    ],
    "sg:phone":"+1 989 345 2490",
    "sg:postcode":"48661",
    "sg:province":"MI",
    "wof:name":"National City Bank",
    "wof:placetype":"venue"
},
  "geometry": {"coordinates":[-84.23581,44.276346],"type":"Point"}
}