{
  "type": "Feature",
  "properties": {
    "iso:country":"US",
    "sg:address":"2801 Celery Ln",
    "sg:city":"North Muskegon",
    "sg:classifiers":[
        {
            "category":"Retail",
            "subcategory":"Auto Repair",
            "type":"Services"
        }
    ],
    "sg:phone":"+1 231 744 0469",
    "sg:postcode":"49445",
    "sg:province":"MI",
    "sg:tags":[
        "repairing",
        "automobile"
    ],
    "wof:name":"Harold's North Shore Svc",
    "wof:placetype":"venue"
},
  "geometry": {"coordinates":[-86.244533,43.268327],"type":"Point"}
}