{
  "type": "Feature",
  "properties": {
    "iso:country":"US",
    "sg:address":"7655 Ormes Rd",
    "sg:city":"Vassar",
    "sg:classifiers":[
        {
            "category":"Real Estate",
            "subcategory":"Real Estate Operator",
            "type":"Services"
        }
    ],
    "sg:phone":"+1 989 823 3294",
    "sg:postcode":"48768",
    "sg:province":"MI",
    "sg:tags":[
        "property",
        "lessor"
    ],
    "wof:name":"Robert Hohman",
    "wof:placetype":"venue"
},
  "geometry": {"coordinates":[-83.610803,43.32169],"type":"Point"}
}