{
  "type": "Feature",
  "properties": {
    "iso:country":"US",
    "sg:address":"3711 Rose Ann Dr",
    "sg:city":"Brighton",
    "sg:classifiers":[
        {
            "category":"Professional",
            "subcategory":"Accounting & Tax Preparation",
            "type":"Services"
        }
    ],
    "sg:phone":"+1 810 220 8801",
    "sg:postcode":"48114",
    "sg:province":"MI",
    "wof:name":"Brighten Imperial",
    "wof:placetype":"venue"
},
  "geometry": {"coordinates":[-83.737802,42.547902],"type":"Point"}
}