{
  "type": "Feature",
  "properties": {
    "iso:country":"US",
    "sg:address":"3215 Shattuck Rd",
    "sg:city":"Saginaw",
    "sg:classifiers":[
        {
            "category":"Personal",
            "subcategory":"Beauty Salon",
            "type":"Services"
        }
    ],
    "sg:phone":"+1 989 793 6815",
    "sg:postcode":"48603",
    "sg:province":"MI",
    "sg:tags":[
        "shop"
    ],
    "wof:name":"Belle Mains Nail Parlor",
    "wof:placetype":"venue"
},
  "geometry": {"coordinates":[-83.982237,43.45091],"type":"Point"}
}