{
  "type": "Feature",
  "properties": {
    "iso:country":"US",
    "sg:address":"4001 Mapleleaf Rd",
    "sg:city":"Waterford",
    "sg:classifiers":[
        {
            "category":"Real Estate",
            "subcategory":"Developer",
            "type":"Services"
        }
    ],
    "sg:phone":"+1 248 682 1129",
    "sg:postcode":"48328",
    "sg:province":"MI",
    "wof:name":"ALB Development Inc",
    "wof:placetype":"venue"
},
  "geometry": {"coordinates":[-83.365405,42.628546],"type":"Point"}
}