{
  "type": "Feature",
  "properties": {
    "iso:country":"US",
    "sg:address":"109 Evergreen Ave",
    "sg:city":"Oscoda",
    "sg:classifiers":[
        {
            "category":"Shopping",
            "type":"Retail Goods"
        }
    ],
    "sg:phone":"+1 989 739 5927",
    "sg:postcode":"48750",
    "sg:province":"MI",
    "sg:tags":[
        "limb",
        "artificial"
    ],
    "wof:name":"Teter Orthotics & Prosthetics",
    "wof:placetype":"venue"
},
  "geometry": {"coordinates":[-83.330161,44.424676],"type":"Point"}
}