{
  "type": "Feature",
  "properties": {
    "iso:country":"US",
    "sg:address":"419 Fulton St",
    "sg:city":"Buchanan",
    "sg:classifiers":[
        {
            "category":"Real Estate",
            "subcategory":"Real Estate Operator",
            "type":"Services"
        }
    ],
    "sg:phone":"+1 269 695 0287",
    "sg:postcode":"49107",
    "sg:province":"MI",
    "sg:tags":[
        "property",
        "lessor"
    ],
    "wof:name":"Manuel Moten",
    "wof:placetype":"venue"
},
  "geometry": {"coordinates":[-86.352453,41.835103],"type":"Point"}
}