{
  "type": "Feature",
  "properties": {
    "iso:country":"US",
    "sg:address":"1057 S State Rd",
    "sg:city":"Davison",
    "sg:classifiers":[
        {
            "category":"Shopping",
            "subcategory":"Florist",
            "type":"Retail Goods"
        }
    ],
    "sg:phone":"+1 810 653 8600",
    "sg:postcode":"48423",
    "sg:province":"MI",
    "wof:name":"Royal Gardens Flowers",
    "wof:placetype":"venue"
},
  "geometry": {"coordinates":[-83.517629,43.01983],"type":"Point"}
}