{
  "type": "Feature",
  "properties": {
    "iso:country":"US",
    "sg:address":"1541 Beechwood Dr",
    "sg:city":"Jenison",
    "sg:classifiers":[
        {
            "category":"Social Services",
            "subcategory":"Child Care",
            "type":"Services"
        }
    ],
    "sg:phone":"+1 616 457 3065",
    "sg:postcode":"49428",
    "sg:province":"MI",
    "sg:tags":[
        "day",
        "provider"
    ],
    "wof:name":"Dawn Marie Simpson",
    "wof:placetype":"venue"
},
  "geometry": {"coordinates":[-85.818223,42.918563],"type":"Point"}
}