{
  "type": "Feature",
  "properties": {
    "iso:country":"US",
    "sg:address":"19311 US Hwy 12",
    "sg:city":"Edwardsburg",
    "sg:classifiers":[
        {
            "category":"Real Estate",
            "subcategory":"Real Estate Operator",
            "type":"Services"
        }
    ],
    "sg:phone":"+1 269 641 7019",
    "sg:postcode":"49112",
    "sg:province":"MI",
    "sg:tags":[
        "mobile",
        "home",
        "site"
    ],
    "wof:name":"Simmons Mobile Home Park",
    "wof:placetype":"venue"
},
  "geometry": {"coordinates":[-85.939318,41.768871],"type":"Point"}
}