{
  "type": "Feature",
  "properties": {
    "iso:country":"US",
    "sg:address":"2523 Fairview Rd",
    "sg:city":"Eau Claire",
    "sg:classifiers":[
        {
            "category":"Retail",
            "subcategory":"Repair Shop",
            "type":"Services"
        }
    ],
    "sg:phone":"+1 269 944 1615",
    "sg:postcode":"49111",
    "sg:province":"MI",
    "wof:name":"Haystack Repair",
    "wof:placetype":"venue"
},
  "geometry": {"coordinates":[-86.339319,42.071897],"type":"Point"}
}