{
  "type": "Feature",
  "properties": {
    "iso:country":"US",
    "sg:address":"32985 Hamilton Ct",
    "sg:city":"Farmington Hills",
    "sg:classifiers":[
        {
            "category":"Insurance",
            "subcategory":"Insurance Agent",
            "type":"Services"
        }
    ],
    "sg:phone":"+1 248 553 3130",
    "sg:postcode":"48334",
    "sg:province":"MI",
    "wof:name":"Kleinschmit Insurance Inc",
    "wof:placetype":"venue"
},
  "geometry": {"coordinates":[-83.37344899999999,42.496688],"type":"Point"}
}