{
  "type": "Feature",
  "properties": {
    "iso:country":"US",
    "sg:address":"10945 W Grand River Hwy",
    "sg:city":"Grand Ledge",
    "sg:classifiers":[
        {
            "category":"Mining & Drilling",
            "type":"Manufacturing & Wholesale Goods"
        }
    ],
    "sg:phone":"+1 517 622 0770",
    "sg:postcode":"48837",
    "sg:province":"MI",
    "sg:tags":[
        "oil",
        "gas",
        "producer"
    ],
    "wof:name":"Pohl Oil Co",
    "wof:placetype":"venue"
},
  "geometry": {"coordinates":[-84.735551,42.797694],"type":"Point"}
}