{
  "type": "Feature",
  "properties": {
    "iso:country":"US",
    "sg:address":"2165 E Long Lake Rd",
    "sg:city":"Harrison",
    "sg:classifiers":[
        {
            "category":"Building & Trades",
            "subcategory":"Electrical",
            "type":"Services"
        }
    ],
    "sg:phone":"+1 989 539 5544",
    "sg:postcode":"48625",
    "sg:province":"MI",
    "sg:tags":[
        "electrical",
        "contractor"
    ],
    "wof:name":"Buyers Electric Inc",
    "wof:placetype":"venue"
},
  "geometry": {"coordinates":[-84.806263,44.103771],"type":"Point"}
}