{
  "type": "Feature",
  "properties": {
    "iso:country":"US",
    "sg:address":"22401 W 8 Mile Rd",
    "sg:city":"Detroit",
    "sg:classifiers":[
        {
            "category":"Education",
            "subcategory":"Kindergarten",
            "type":"Public Place"
        }
    ],
    "sg:phone":"+1 313 537 1882",
    "sg:postcode":"48219",
    "sg:province":"MI",
    "sg:tags":[
        "school",
        "driving"
    ],
    "sg:website":"www.schooldayzdrivingschool.com",
    "wof:name":"School Dayz Drving School",
    "wof:placetype":"venue"
},
  "geometry": {"coordinates":[-83.26376399999999,42.442969],"type":"Point"}
}