{
  "type": "Feature",
  "properties": {
    "iso:country":"US",
    "sg:address":"19700 Masonic Blvd",
    "sg:city":"Roseville",
    "sg:classifiers":[
        {
            "category":"Real Estate",
            "subcategory":"Real Estate Operator",
            "type":"Services"
        }
    ],
    "sg:phone":"+1 586 293 2500",
    "sg:postcode":"48066",
    "sg:province":"MI",
    "sg:tags":[
        "apartment"
    ],
    "wof:name":"Macomb Manor Apartments",
    "wof:placetype":"venue"
},
  "geometry": {"coordinates":[-82.9188,42.532101],"type":"Point"}
}