{
  "type": "Feature",
  "properties": {
    "iso:country":"US",
    "sg:address":"13776 172nd Ave",
    "sg:city":"Grand Haven",
    "sg:classifiers":[
        {
            "category":"Manufacturing",
            "subcategory":"Tools & Machinery",
            "type":"Manufacturing & Wholesale Goods"
        }
    ],
    "sg:phone":"+1 616 850 3002",
    "sg:postcode":"49417",
    "sg:province":"MI",
    "sg:tags":[
        "die",
        "maker"
    ],
    "wof:name":"Cobra Tooling Inc",
    "wof:placetype":"venue"
},
  "geometry": {"coordinates":[-86.210532,43.019113],"type":"Point"}
}