{
  "type": "Feature",
  "properties": {
    "iso:country":"US",
    "sg:address":"6179 S 220th Ave",
    "sg:city":"Reed City",
    "sg:classifiers":[
        {
            "category":"Home & Garden",
            "subcategory":"Mobile Homes",
            "type":"Retail Goods"
        }
    ],
    "sg:phone":"+1 231 832 2198",
    "sg:postcode":"49677",
    "sg:province":"MI",
    "wof:name":"Hodgers Mobile Home Setup",
    "wof:placetype":"venue"
},
  "geometry": {"coordinates":[-85.522852,43.908619],"type":"Point"}
}