{
  "type": "Feature",
  "properties": {
    "iso:country":"US",
    "sg:address":"28230 Elm St",
    "sg:city":"Dowagiac",
    "sg:classifiers":[
        {
            "category":"Real Estate",
            "subcategory":"Real Estate Operator",
            "type":"Services"
        }
    ],
    "sg:phone":"+1 269 782 8003",
    "sg:postcode":"49047",
    "sg:province":"MI",
    "sg:tags":[
        "farm",
        "land",
        "leasing"
    ],
    "wof:name":"Brook Barry Enterprise",
    "wof:placetype":"venue"
},
  "geometry": {"coordinates":[-86.115433,42.041783],"type":"Point"}
}