{
  "type": "Feature",
  "properties": {
    "iso:country":"US",
    "sg:address":"32486 Gratiot Ave",
    "sg:city":"Roseville",
    "sg:classifiers":[
        {
            "category":"Personal",
            "subcategory":"Beauty Salon",
            "type":"Services"
        }
    ],
    "sg:phone":"+1 586 294 2334",
    "sg:postcode":"48066",
    "sg:province":"MI",
    "sg:tags":[
        "shop",
        "barber"
    ],
    "wof:name":"Briles John Hair Technique",
    "wof:placetype":"venue"
},
  "geometry": {"coordinates":[-82.91130099999999,42.535599],"type":"Point"}
}