{
  "type": "Feature",
  "properties": {
    "iso:country":"US",
    "sg:address":"4100 Orchard Lake Rd",
    "sg:city":"Orchard Lake",
    "sg:classifiers":[
        {
            "category":"Farming",
            "subcategory":"Orchard",
            "type":"Manufacturing & Wholesale Goods"
        }
    ],
    "sg:phone":"+1 248 683 5771",
    "sg:postcode":"48323",
    "sg:province":"MI",
    "sg:tags":[
        "grove",
        "management"
    ],
    "wof:name":"Orchard Lake Sunoco",
    "wof:placetype":"venue"
},
  "geometry": {"coordinates":[-83.36235499999999,42.57897],"type":"Point"}
}