{
  "type": "Feature",
  "properties": {
    "iso:country":"US",
    "sg:address":"39660 Schoolcraft Rd",
    "sg:city":"Plymouth",
    "sg:classifiers":[
        {
            "category":"Retail",
            "subcategory":"Repair Shop",
            "type":"Services"
        }
    ],
    "sg:phone":"+1 734 420 9840",
    "sg:postcode":"48170",
    "sg:province":"MI",
    "sg:tags":[
        "equipment",
        "industrial",
        "electrical"
    ],
    "wof:name":"Group Industrial Service & Sls",
    "wof:placetype":"venue"
},
  "geometry": {"coordinates":[-83.434263,42.382719],"type":"Point"}
}