{
  "type": "Feature",
  "properties": {
    "iso:country":"US",
    "sg:address":"3200 S Airport Rd W",
    "sg:city":"Traverse City",
    "sg:classifiers":[
        {
            "category":"Personal",
            "subcategory":"Beauty Salon",
            "type":"Services"
        }
    ],
    "sg:phone":"+1 231 932 0621",
    "sg:postcode":"49684",
    "sg:province":"MI",
    "sg:tags":[
        "manicuring"
    ],
    "wof:name":"Nancy Nails",
    "wof:placetype":"venue"
},
  "geometry": {"coordinates":[-85.636004,44.723647],"type":"Point"}
}