{
  "type": "Feature",
  "properties": {
    "iso:country":"US",
    "sg:address":"19162 Banker St",
    "sg:city":"Constantine",
    "sg:phone":"+1 269 435 7513",
    "sg:postcode":"49042",
    "sg:province":"MI",
    "sg:tags":[
        "farm",
        "corn",
        "soybean"
    ],
    "wof:name":"Bill Younts",
    "wof:placetype":"venue"
},
  "geometry": {"coordinates":[-85.582545,41.86796],"type":"Point"}
}