{
  "type": "Feature",
  "properties": {
    "iso:country":"US",
    "sg:address":"705 Hart St",
    "sg:city":"Essexville",
    "sg:classifiers":[
        {
            "category":"Professional",
            "subcategory":"Management & Consulting",
            "type":"Services"
        }
    ],
    "sg:phone":"+1 989 892 6227",
    "sg:postcode":"48732",
    "sg:province":"MI",
    "sg:tags":[
        "consultant"
    ],
    "wof:name":"Bird Productions Consultant",
    "wof:placetype":"venue"
},
  "geometry": {"coordinates":[-83.843273,43.609752],"type":"Point"}
}