{
  "type": "Feature",
  "properties": {
    "iso:country":"US",
    "sg:address":"45735 Willis Rd",
    "sg:city":"Belleville",
    "sg:classifiers":[
        {
            "category":"Organizations",
            "subcategory":"Community Association",
            "type":"Services"
        }
    ],
    "sg:phone":"+1 734 697 4378",
    "sg:postcode":"48111",
    "sg:province":"MI",
    "wof:name":"International Order of Ra",
    "wof:placetype":"venue"
},
  "geometry": {"coordinates":[-83.485547,42.160322],"type":"Point"}
}