{
  "type": "Feature",
  "properties": {
    "iso:country":"US",
    "sg:address":"13286 S 42nd St",
    "sg:city":"Vicksburg",
    "sg:classifiers":[
        {
            "category":"Building & Trades",
            "subcategory":"Landscaping Services",
            "type":"Services"
        }
    ],
    "sg:phone":"+1 269 778 3577",
    "sg:postcode":"49097",
    "sg:province":"MI",
    "wof:name":"Walkers Lawn Care",
    "wof:placetype":"venue"
},
  "geometry": {"coordinates":[-85.353053,42.125441],"type":"Point"}
}