{
  "type": "Feature",
  "properties": {
    "iso:country":"US",
    "sg:address":"700 Austin Ave",
    "sg:city":"Albion",
    "sg:classifiers":[
        {
            "category":"Personal",
            "subcategory":"Beauty Salon",
            "type":"Services"
        }
    ],
    "sg:phone":"+1 517 629 8588",
    "sg:postcode":"49224",
    "sg:province":"MI",
    "wof:name":"Dunklin Beauty & Hair Products",
    "wof:placetype":"venue"
},
  "geometry": {"coordinates":[-84.76326299999999,42.253702],"type":"Point"}
}