{
  "type": "Feature",
  "properties": {
    "iso:country":"US",
    "sg:address":"1458 W Ryant Rd",
    "sg:city":"Maple City",
    "sg:classifiers":[
        {
            "category":"Farming",
            "subcategory":"Farm",
            "type":"Manufacturing & Wholesale Goods"
        }
    ],
    "sg:phone":"+1 231 228 5880",
    "sg:postcode":"49664",
    "sg:province":"MI",
    "wof:name":"Olsen Farms",
    "wof:placetype":"venue"
},
  "geometry": {"coordinates":[-85.874921,44.878509],"type":"Point"}
}