{
  "type": "Feature",
  "properties": {
    "iso:country":"US",
    "sg:address":"18104 E 10 Mile Rd",
    "sg:city":"Eastpointe",
    "sg:classifiers":[
        {
            "category":"Personal",
            "subcategory":"Tanning Parlor",
            "type":"Services"
        }
    ],
    "sg:phone":"+1 586 776 4147",
    "sg:postcode":"48021",
    "sg:province":"MI",
    "sg:tags":[
        "salon"
    ],
    "wof:name":"Wolski Enterprises",
    "wof:placetype":"venue"
},
  "geometry": {"coordinates":[-82.93395599999999,42.479949],"type":"Point"}
}