{
  "type": "Feature",
  "properties": {
    "iso:country":"US",
    "sg:address":"5970 Van Buren St",
    "sg:city":"Hudsonville",
    "sg:classifiers":[
        {
            "category":"Freight",
            "type":"Transportation"
        }
    ],
    "sg:phone":"+1 616 875 6055",
    "sg:postcode":"49426",
    "sg:province":"MI",
    "sg:tags":[
        "hauling",
        "trucking"
    ],
    "wof:name":"Ken Kamps Trucking",
    "wof:placetype":"venue"
},
  "geometry": {"coordinates":[-85.929271,42.870754],"type":"Point"}
}