{
  "type": "Feature",
  "properties": {
    "iso:country":"US",
    "sg:address":"2761 Peck St",
    "sg:city":"Muskegon",
    "sg:classifiers":[
        {
            "category":"Wholesale",
            "subcategory":"Machinery & Supplies",
            "type":"Manufacturing & Wholesale Goods"
        }
    ],
    "sg:phone":"+1 231 739 5557",
    "sg:postcode":"49444",
    "sg:province":"MI",
    "sg:tags":[
        "salon",
        "beauty"
    ],
    "wof:name":"Hair Plus Beauty Supply",
    "wof:placetype":"venue"
},
  "geometry": {"coordinates":[-86.24476900000001,43.201431],"type":"Point"}
}