{
  "type": "Feature",
  "properties": {
    "iso:country":"US",
    "sg:address":"3950 Supply Rd",
    "sg:city":"Traverse City",
    "sg:classifiers":[
        {
            "category":"Building & Trades",
            "subcategory":"Construction",
            "type":"Services"
        }
    ],
    "sg:phone":"+1 231 946 8195",
    "sg:postcode":"49686",
    "sg:province":"MI",
    "sg:tags":[
        "house"
    ],
    "wof:name":"Six Construction",
    "wof:placetype":"venue"
},
  "geometry": {"coordinates":[-85.49632099999999,44.707652],"type":"Point"}
}