{
  "type": "Feature",
  "properties": {
    "iso:country":"US",
    "sg:address":"11999 M 50",
    "sg:city":"Brooklyn",
    "sg:classifiers":[
        {
            "category":"Professional",
            "subcategory":"Engineering",
            "type":"Services"
        }
    ],
    "sg:phone":"+1 517 592 5642",
    "sg:postcode":"49230",
    "sg:province":"MI",
    "sg:tags":[
        "engineer"
    ],
    "wof:name":"Davis Design",
    "wof:placetype":"venue"
},
  "geometry": {"coordinates":[-84.22158399999999,42.060916],"type":"Point"}
}