{
  "type": "Feature",
  "properties": {
    "iso:country":"US",
    "sg:address":"20911 Inkster Rd",
    "sg:city":"Farmington",
    "sg:classifiers":[
        {
            "category":"Organizations",
            "subcategory":"Religious Organization",
            "type":"Services"
        }
    ],
    "sg:phone":"+1 248 477 0577",
    "sg:postcode":"48336",
    "sg:province":"MI",
    "wof:name":"True Light Pentecostal Apostol",
    "wof:placetype":"venue"
},
  "geometry": {"coordinates":[-83.317036,42.445545],"type":"Point"}
}