{
  "type": "Feature",
  "properties": {
    "iso:country":"US",
    "sg:address":"2404 E Michigan Ave",
    "sg:city":"Lansing",
    "sg:classifiers":[
        {
            "category":"Food & Beverages",
            "subcategory":"Specialty",
            "type":"Retail Goods"
        }
    ],
    "sg:phone":"+1 517 702 2635",
    "sg:postcode":"48912",
    "sg:province":"MI",
    "sg:tags":[
        "oriental"
    ],
    "wof:name":"Her's Oriental Market",
    "wof:placetype":"venue"
},
  "geometry": {"coordinates":[-84.516373,42.733557],"type":"Point"}
}