{
  "type": "Feature",
  "properties": {
    "iso:country":"US",
    "sg:address":"3556 Dubois St",
    "sg:city":"Detroit",
    "sg:classifiers":[
        {
            "category":"Organizations",
            "subcategory":"Religious Organization",
            "type":"Services"
        }
    ],
    "sg:phone":"+1 313 831 2770",
    "sg:postcode":"48207",
    "sg:province":"MI",
    "wof:name":"Church of Living God C W F F",
    "wof:placetype":"venue"
},
  "geometry": {"coordinates":[-83.036631,42.355776],"type":"Point"}
}