{
  "type": "Feature",
  "properties": {
    "iso:country":"US",
    "sg:address":"7003 Vicksburg Cir",
    "sg:city":"Shelby Twp",
    "sg:classifiers":[
        {
            "category":"Building & Trades",
            "subcategory":"Cleaning & Sanitation",
            "type":"Services"
        }
    ],
    "sg:phone":"+1 586 731 0878",
    "sg:postcode":"48317",
    "sg:province":"MI",
    "sg:tags":[
        "maintenance"
    ],
    "wof:name":"DNA Building Svc",
    "wof:placetype":"venue"
},
  "geometry": {"coordinates":[-83.041946,42.639909],"type":"Point"}
}