{
  "type": "Feature",
  "properties": {
    "iso:country":"US",
    "sg:address":"21504 Collingham Ave",
    "sg:city":"Farmington Hills",
    "sg:classifiers":[
        {
            "category":"Social Services",
            "subcategory":"Child Care",
            "type":"Services"
        }
    ],
    "sg:phone":"+1 248 477 2953",
    "sg:postcode":"48336",
    "sg:province":"MI",
    "sg:tags":[
        "day"
    ],
    "wof:name":"Kids On the Block",
    "wof:placetype":"venue"
},
  "geometry": {"coordinates":[-83.326256,42.449117],"type":"Point"}
}