{
  "type": "Feature",
  "properties": {
    "iso:country":"US",
    "sg:address":"265 Fremont St",
    "sg:city":"Battle Creek",
    "sg:classifiers":[
        {
            "category":"Health Services",
            "subcategory":"Health Practitioner",
            "type":"Services"
        }
    ],
    "sg:phone":"+1 269 966 6159",
    "sg:postcode":"49017",
    "sg:province":"MI",
    "sg:tags":[
        "occupational",
        "safety"
    ],
    "wof:name":"Battle Creek Health System",
    "wof:placetype":"venue"
},
  "geometry": {"coordinates":[-85.178049,42.333815],"type":"Point"}
}