{
  "type": "Feature",
  "properties": {
    "iso:country":"US",
    "sg:address":"521 Elmwood St",
    "sg:city":"Dearborn",
    "sg:classifiers":[
        {
            "category":"Professional",
            "subcategory":"Management & Consulting",
            "type":"Services"
        }
    ],
    "sg:phone":"+1 313 563 6836",
    "sg:postcode":"48124",
    "sg:province":"MI",
    "wof:name":"Elmwood Management Co LLC",
    "wof:placetype":"venue"
},
  "geometry": {"coordinates":[-83.266631,42.308462],"type":"Point"}
}