{
  "type": "Feature",
  "properties": {
    "iso:country":"US",
    "sg:address":"940 Dubay Dr",
    "sg:city":"West Branch",
    "sg:phone":"+1 989 345 5593",
    "sg:postcode":"48661",
    "sg:province":"MI",
    "sg:tags":[
        "farm",
        "soybean"
    ],
    "wof:name":"Al Wiltse",
    "wof:placetype":"venue"
},
  "geometry": {"coordinates":[-84.218851,44.363685],"type":"Point"}
}