{
  "type": "Feature",
  "properties": {
    "iso:country":"US",
    "sg:address":"18 Smith Ln",
    "sg:city":"Marquette",
    "sg:classifiers":[
        {
            "category":"Retail",
            "subcategory":"Auto Repair",
            "type":"Services"
        }
    ],
    "sg:phone":"+1 906 249 5309",
    "sg:postcode":"49855",
    "sg:province":"MI",
    "sg:tags":[
        "body"
    ],
    "wof:name":"Williams Door Service",
    "wof:placetype":"venue"
},
  "geometry": {"coordinates":[-87.37395600000001,46.485802],"type":"Point"}
}