{
  "type": "Feature",
  "properties": {
    "iso:country":"US",
    "sg:address":"1100 Boyne Ave",
    "sg:city":"Boyne City",
    "sg:classifiers":[
        {
            "category":"Shopping",
            "subcategory":"Florist",
            "type":"Retail Goods"
        }
    ],
    "sg:phone":"+1 231 582 0972",
    "sg:postcode":"49712",
    "sg:province":"MI",
    "wof:name":"Accents By Pamelanies",
    "wof:placetype":"venue"
},
  "geometry": {"coordinates":[-84.990123,45.204826],"type":"Point"}
}