{
  "type": "Feature",
  "properties": {
    "iso:country":"US",
    "sg:address":"71 Walnut Blvd",
    "sg:city":"Rochester",
    "sg:classifiers":[
        {
            "category":"Professional",
            "subcategory":"Lawyer & Legal Services",
            "type":"Services"
        }
    ],
    "sg:phone":"+1 248 608 1900",
    "sg:postcode":"48307",
    "sg:province":"MI",
    "sg:tags":[
        "attorney"
    ],
    "wof:name":"Johnson & Blankenship PC",
    "wof:placetype":"venue"
},
  "geometry": {"coordinates":[-83.135318,42.677712],"type":"Point"}
}