{
  "type": "Feature",
  "properties": {
    "iso:country":"US",
    "sg:address":"5684 W Saginaw Hwy",
    "sg:city":"Lansing",
    "sg:classifiers":[
        {
            "category":"Shopping",
            "subcategory":"Gifts & Souvenirs",
            "type":"Retail Goods"
        }
    ],
    "sg:phone":"+1 517 323 6223",
    "sg:postcode":"48917",
    "sg:province":"MI",
    "sg:tags":[
        "shop"
    ],
    "wof:name":"Creative Gift Gallery",
    "wof:placetype":"venue"
},
  "geometry": {"coordinates":[-84.630146,42.741187],"type":"Point"}
}