{
  "type": "Feature",
  "properties": {
    "iso:country":"US",
    "sg:address":"1146 Camelot",
    "sg:city":"Pinckney",
    "sg:classifiers":[
        {
            "category":"Building & Trades",
            "subcategory":"Electrical",
            "type":"Services"
        }
    ],
    "sg:phone":"+1 734 878 5947",
    "sg:postcode":"48169",
    "sg:province":"MI",
    "sg:tags":[
        "electric",
        "contractor"
    ],
    "wof:name":"Wiltse Electric Svc",
    "wof:placetype":"venue"
},
  "geometry": {"coordinates":[-83.921278,42.429392],"type":"Point"}
}