{
  "type": "Feature",
  "properties": {
    "iso:country":"US",
    "sg:address":"6280 E Deckerville Rd",
    "sg:city":"Deford",
    "sg:classifiers":[
        {
            "category":"Building & Trades",
            "subcategory":"Construction",
            "type":"Services"
        }
    ],
    "sg:phone":"+1 989 872 2717",
    "sg:postcode":"48729",
    "sg:province":"MI",
    "sg:tags":[
        "house"
    ],
    "wof:name":"Bee Builders",
    "wof:placetype":"venue"
},
  "geometry": {"coordinates":[-83.173204,43.513838],"type":"Point"}
}