{
  "type": "Feature",
  "properties": {
    "iso:country":"US",
    "sg:address":"6353 Andersonville Rd",
    "sg:city":"Waterford",
    "sg:classifiers":[
        {
            "category":"Health Services",
            "subcategory":"Clinic",
            "type":"Services"
        }
    ],
    "sg:phone":"+1 248 623 4918",
    "sg:postcode":"48329",
    "sg:province":"MI",
    "wof:name":"Hammonah Health Care",
    "wof:placetype":"venue"
},
  "geometry": {"coordinates":[-83.415198,42.701137],"type":"Point"}
}