{
  "type": "Feature",
  "properties": {
    "iso:country":"US",
    "sg:address":"3212 W Pratt Rd",
    "sg:city":"Dewitt",
    "sg:classifiers":[
        {
            "category":"Building & Trades",
            "subcategory":"Construction",
            "type":"Services"
        }
    ],
    "sg:phone":"+1 517 669 5911",
    "sg:postcode":"48820",
    "sg:province":"MI",
    "sg:tags":[
        "house"
    ],
    "wof:name":"Debois Construction",
    "wof:placetype":"venue"
},
  "geometry": {"coordinates":[-84.591504,42.900146],"type":"Point"}
}