{
  "type": "Feature",
  "properties": {
    "iso:country":"US",
    "sg:address":"4530 24th Ave",
    "sg:city":"Fort Gratiot",
    "sg:classifiers":[
        {
            "category":"Autos & Motor Vehicles",
            "subcategory":"Auto Supplies",
            "type":"Retail Goods"
        }
    ],
    "sg:phone":"+1 810 385 8460",
    "sg:postcode":"48059",
    "sg:province":"MI",
    "sg:tags":[
        "tire"
    ],
    "wof:name":"Discount Tire Co",
    "wof:placetype":"venue"
},
  "geometry": {"coordinates":[-82.45677499999999,43.041102],"type":"Point"}
}