{
  "type": "Feature",
  "properties": {
    "iso:country":"US",
    "sg:address":"16892 Robson St",
    "sg:city":"Detroit",
    "sg:classifiers":[
        {
            "category":"Local Transit",
            "type":"Transportation"
        }
    ],
    "sg:phone":"+1 313 836 7483",
    "sg:postcode":"48235",
    "sg:province":"MI",
    "sg:tags":[
        "passenger"
    ],
    "wof:name":"Courtesy Coach",
    "wof:placetype":"venue"
},
  "geometry": {"coordinates":[-83.193174,42.415516],"type":"Point"}
}