{
  "type": "Feature",
  "properties": {
    "iso:country":"US",
    "sg:address":"281 N Main St",
    "sg:city":"Plymouth",
    "sg:classifiers":[
        {
            "category":"Personal",
            "subcategory":"Beauty Salon",
            "type":"Services"
        }
    ],
    "sg:phone":"+1 734 459 7350",
    "sg:postcode":"48170",
    "sg:province":"MI",
    "sg:tags":[
        "shop"
    ],
    "wof:name":"Sante Fe Salon",
    "wof:placetype":"venue"
},
  "geometry": {"coordinates":[-83.46487999999999,42.374289],"type":"Point"}
}