{
  "type": "Feature",
  "properties": {
    "iso:country":"US",
    "sg:address":"29287 Mound Rd",
    "sg:city":"Warren",
    "sg:classifiers":[
        {
            "category":"Fast Food",
            "type":"Food & Drink"
        }
    ],
    "sg:phone":"+1 586 573 9164",
    "sg:postcode":"48092",
    "sg:province":"MI",
    "sg:tags":[
        "chicken",
        "wing"
    ],
    "sg:website":"www.buffalowildwings.com",
    "wof:name":"Buffalo Wild Wings",
    "wof:placetype":"venue"
},
  "geometry": {"coordinates":[-83.046744,42.505706],"type":"Point"}
}