{
  "type": "Feature",
  "properties": {
    "iso:country":"US",
    "sg:address":"1750 Vernier Rd",
    "sg:city":"Grosse Pointe",
    "sg:classifiers":[
        {
            "category":"Professional",
            "subcategory":"Management & Consulting",
            "type":"Services"
        }
    ],
    "sg:phone":"+1 313 886 7648",
    "sg:postcode":"48236",
    "sg:province":"MI",
    "wof:name":"M&S Consultants",
    "wof:placetype":"venue"
},
  "geometry": {"coordinates":[-82.905348,42.443372],"type":"Point"}
}