{
  "type": "Feature",
  "properties": {
    "iso:country":"US",
    "sg:address":"22255 Greenfield Rd",
    "sg:city":"Southfield",
    "sg:classifiers":[
        {
            "category":"Health Services",
            "subcategory":"Health Practitioner",
            "type":"Services"
        }
    ],
    "sg:phone":"+1 248 849 3195",
    "sg:postcode":"48075",
    "sg:province":"MI",
    "sg:tags":[
        "occupational",
        "safety"
    ],
    "wof:name":"Providence Occupational Health",
    "wof:placetype":"venue"
},
  "geometry": {"coordinates":[-83.201089,42.455559],"type":"Point"}
}