{
  "type": "Feature",
  "properties": {
    "iso:country":"US",
    "sg:address":"5143 Rushton Rd",
    "sg:city":"Central Lake",
    "sg:classifiers":[
        {
            "category":"Communications",
            "subcategory":"Film & Video Production",
            "type":"Services"
        },
        {
            "category":"Professional",
            "subcategory":"Advertising",
            "type":"Services"
        }
    ],
    "sg:phone":"+1 231 258 6178",
    "sg:postcode":"49622",
    "sg:province":"MI",
    "sg:tags":[
        "motion",
        "picture",
        "representative",
        "taping"
    ],
    "wof:name":"3 J's Video Productions",
    "wof:placetype":"venue"
},
  "geometry": {"coordinates":[-85.252047,45.109853],"type":"Point"}
}