{
  "type": "Feature",
  "properties": {
    "iso:country":"US",
    "sg:address":"170 N Paw Paw St",
    "sg:city":"Coloma",
    "sg:classifiers":[
        {
            "category":"Professional",
            "subcategory":"Lawyer & Legal Services",
            "type":"Services"
        }
    ],
    "sg:phone":"+1 269 468 3070",
    "sg:postcode":"49038",
    "sg:province":"MI",
    "sg:tags":[
        "attorney"
    ],
    "wof:name":"F Ronald Postelli Law Office",
    "wof:placetype":"venue"
},
  "geometry": {"coordinates":[-86.306288,42.187394],"type":"Point"}
}