{
  "type": "Feature",
  "properties": {
    "iso:country":"US",
    "sg:address":"4499 S Center Rd",
    "sg:city":"Burton",
    "sg:classifiers":[
        {
            "category":"Health Services",
            "subcategory":"Chiropractor",
            "type":"Services"
        }
    ],
    "sg:phone":"+1 810 743 8033",
    "sg:postcode":"48519",
    "sg:province":"MI",
    "wof:name":"Forr Chiropractic Clinic",
    "wof:placetype":"venue"
},
  "geometry": {"coordinates":[-83.632599,42.961399],"type":"Point"}
}