{
  "type": "Feature",
  "properties": {
    "iso:country":"US",
    "sg:address":"53 Chandler St",
    "sg:city":"Detroit",
    "sg:classifiers":[
        {
            "category":"Education",
            "subcategory":"School",
            "type":"Public Place"
        }
    ],
    "sg:phone":"+1 313 868 7502",
    "sg:postcode":"48202",
    "sg:province":"MI",
    "sg:tags":[
        "elementary"
    ],
    "wof:name":"St Benedict Grade School",
    "wof:placetype":"venue"
},
  "geometry": {"coordinates":[-83.074561,42.374495],"type":"Point"}
}