{
  "type": "Feature",
  "properties": {
    "iso:country":"US",
    "sg:address":"3015 Omena Point Rd",
    "sg:city":"Omena",
    "sg:classifiers":[
        {
            "category":"Food & Beverages",
            "subcategory":"Specialty",
            "type":"Retail Goods"
        }
    ],
    "sg:phone":"+1 231 386 9131",
    "sg:postcode":"49670",
    "sg:province":"MI",
    "sg:tags":[
        "herb"
    ],
    "wof:name":"Lavender Lane On The Bay",
    "wof:placetype":"venue"
},
  "geometry": {"coordinates":[-85.581946,45.056368],"type":"Point"}
}