{
  "type": "Feature",
  "properties": {
    "iso:country":"US",
    "sg:address":"37070 Amrhein Rd",
    "sg:city":"Livonia",
    "sg:phone":"+1 734 953 6991",
    "sg:postcode":"48150",
    "sg:province":"MI",
    "wof:name":"Appliance Doctor Service By Joe Gagnon & Sons",
    "wof:placetype":"venue"
},
  "geometry": {"coordinates":[-83.409802,42.374714],"type":"Point"}
}