{
  "type": "Feature",
  "properties": {
    "iso:country":"US",
    "sg:address":"14740 Country Club Dr",
    "sg:city":"Livonia",
    "sg:classifiers":[
        {
            "category":"Professional",
            "subcategory":"Management & Consulting",
            "type":"Services"
        }
    ],
    "sg:phone":"+1 734 464 6019",
    "sg:postcode":"48154",
    "sg:province":"MI",
    "sg:tags":[
        "retail",
        "direct",
        "sales"
    ],
    "wof:name":"Becky Diachun",
    "wof:placetype":"venue"
},
  "geometry": {"coordinates":[-83.395962,42.392726],"type":"Point"}
}