{
  "type": "Feature",
  "properties": {
    "iso:country":"US",
    "sg:address":"11925 60th Ave",
    "sg:city":"Allendale",
    "sg:classifiers":[
        {
            "category":"Building & Trades",
            "subcategory":"Construction",
            "type":"Services"
        }
    ],
    "sg:phone":"+1 616 450 6079",
    "sg:postcode":"49401",
    "sg:province":"MI",
    "sg:tags":[
        "house"
    ],
    "wof:name":"Meredith Custom Builders Inc",
    "wof:placetype":"venue"
},
  "geometry": {"coordinates":[-85.934696,42.985535],"type":"Point"}
}