{
  "type": "Feature",
  "properties": {
    "iso:country":"US",
    "sg:address":"2031 Golfcrest Dr",
    "sg:city":"Davison",
    "sg:classifiers":[
        {
            "category":"Professional",
            "subcategory":"Management & Consulting",
            "type":"Services"
        }
    ],
    "sg:phone":"+1 810 653 5954",
    "sg:postcode":"48423",
    "sg:province":"MI",
    "sg:tags":[
        "business"
    ],
    "wof:name":"Institute For Strtigic Studies",
    "wof:placetype":"venue"
},
  "geometry": {"coordinates":[-83.52230900000001,43.00333],"type":"Point"}
}