{
  "type": "Feature",
  "properties": {
    "iso:country":"US",
    "sg:address":"671 Century Dr",
    "sg:city":"Troy",
    "sg:classifiers":[
        {
            "category":"Professional",
            "subcategory":"Business Services",
            "type":"Services"
        }
    ],
    "sg:phone":"+1 248 619 9456",
    "sg:postcode":"48083",
    "sg:province":"MI",
    "wof:name":"Paper Dressing Inc",
    "wof:placetype":"venue"
},
  "geometry": {"coordinates":[-83.137422,42.559882],"type":"Point"}
}