{
  "type": "Feature",
  "properties": {
    "iso:country":"US",
    "sg:address":"22450 Milner St",
    "sg:city":"St Clair Shores",
    "sg:classifiers":[
        {
            "category":"Personal",
            "type":"Services"
        }
    ],
    "sg:phone":"+1 586 491 1160",
    "sg:postcode":"48081",
    "sg:province":"MI",
    "sg:tags":[
        "chair",
        "therapist",
        "provides",
        "massage",
        "workplace"
    ],
    "wof:name":"Business Bodyworks Inc",
    "wof:placetype":"venue"
},
  "geometry": {"coordinates":[-82.885745,42.494753],"type":"Point"}
}