{
  "type": "Feature",
  "properties": {
    "iso:country":"US",
    "sg:address":"11 E 8th St",
    "sg:city":"Holland",
    "sg:classifiers":[
        {
            "category":"Shopping",
            "type":"Retail Goods"
        }
    ],
    "sg:phone":"+1 616 546 3047",
    "sg:postcode":"49423",
    "sg:province":"MI",
    "sg:tags":[
        "picture",
        "frame"
    ],
    "wof:name":"Frame Works",
    "wof:placetype":"venue"
},
  "geometry": {"coordinates":[-86.104749,42.790413],"type":"Point"}
}