{
  "type": "Feature",
  "properties": {
    "iso:country":"US",
    "sg:address":"12505 Northland Dr",
    "sg:city":"Cedar Springs",
    "sg:classifiers":[
        {
            "category":"Shopping",
            "subcategory":"Hobbies, Toys, & Games",
            "type":"Retail Goods"
        }
    ],
    "sg:phone":"+1 616 696 9850",
    "sg:postcode":"49319",
    "sg:province":"MI",
    "sg:tags":[
        "model",
        "supply"
    ],
    "wof:name":"Cinderella Slipper Scrap Bkng",
    "wof:placetype":"venue"
},
  "geometry": {"coordinates":[-85.551175,43.195399],"type":"Point"}
}