{
  "type": "Feature",
  "properties": {
    "iso:country":"US",
    "sg:address":"18000 E Eight Mile Rd",
    "sg:city":"Harper Woods",
    "sg:classifiers":[
        {
            "category":"Shopping",
            "subcategory":"Shoes",
            "type":"Retail Goods"
        }
    ],
    "sg:phone":"+1 313 521 1300",
    "sg:postcode":"48225",
    "sg:province":"MI",
    "sg:tags":[
        "store"
    ],
    "sg:website":"www.footlocker.com",
    "wof:name":"Foot Locker",
    "wof:placetype":"venue"
},
  "geometry": {"coordinates":[-82.93413200000001,42.450526],"type":"Point"}
}