{
  "type": "Feature",
  "properties": {
    "iso:country":"US",
    "sg:address":"9598 Burning Tree Dr",
    "sg:city":"Grand Blanc",
    "sg:classifiers":[
        {
            "category":"Banks & Credit Unions",
            "subcategory":"Financial Services",
            "type":"Services"
        }
    ],
    "sg:phone":"+1 810 694 0220",
    "sg:postcode":"48439",
    "sg:province":"MI",
    "sg:tags":[
        "trust",
        "management"
    ],
    "wof:name":"Misra Family Trust Partnership",
    "wof:placetype":"venue"
},
  "geometry": {"coordinates":[-83.591685,42.896821],"type":"Point"}
}