{
  "type": "Feature",
  "properties": {
    "iso:country":"US",
    "sg:address":"3500 Gull Rd",
    "sg:city":"Kalamazoo",
    "sg:classifiers":[
        {
            "category":"Autos & Motor Vehicles",
            "subcategory":"Auto Supplies",
            "type":"Retail Goods"
        }
    ],
    "sg:phone":"+1 269 385 2666",
    "sg:postcode":"49048",
    "sg:province":"MI",
    "sg:tags":[
        "repair",
        "tire"
    ],
    "wof:name":"Mark Ransoms Tire Brks Svc Ctr",
    "wof:placetype":"venue"
},
  "geometry": {"coordinates":[-85.53633600000001,42.316467],"type":"Point"}
}