{
  "type": "Feature",
  "properties": {
    "iso:country":"US",
    "sg:address":"7400 Blackman Rd",
    "sg:city":"Jackson",
    "sg:classifiers":[
        {
            "category":"Building & Trades",
            "subcategory":"Construction",
            "type":"Services"
        }
    ],
    "sg:phone":"+1 517 782 3454",
    "sg:postcode":"49201",
    "sg:province":"MI",
    "sg:tags":[
        "house"
    ],
    "wof:name":"Gold Medal Home Repairs Inc",
    "wof:placetype":"venue"
},
  "geometry": {"coordinates":[-84.482749,42.342747],"type":"Point"}
}