{
  "type": "Feature",
  "properties": {
    "iso:country":"US",
    "sg:address":"66614 N Shore Dr",
    "sg:city":"Cassopolis",
    "sg:classifiers":[
        {
            "category":"Retail",
            "subcategory":"Animal Services",
            "type":"Services"
        }
    ],
    "sg:phone":"+1 269 699 5244",
    "sg:postcode":"49031",
    "sg:province":"MI",
    "wof:name":"Dark Horse Enterprise Ltd",
    "wof:placetype":"venue"
},
  "geometry": {"coordinates":[-85.991625,41.828873],"type":"Point"}
}