{
  "type": "Feature",
  "properties": {
    "iso:country":"US",
    "sg:address":"740 W 14 Mile Rd",
    "sg:city":"Clawson",
    "sg:classifiers":[
        {
            "category":"Personal",
            "subcategory":"Barber",
            "type":"Services"
        }
    ],
    "sg:phone":"+1 248 435 2697",
    "sg:postcode":"48017",
    "sg:province":"MI",
    "wof:name":"Marc Josephs",
    "wof:placetype":"venue"
},
  "geometry": {"coordinates":[-83.156502,42.533298],"type":"Point"}
}