{
  "type": "Feature",
  "properties": {
    "iso:country":"US",
    "sg:address":"3914 Highwood Pl",
    "sg:city":"Okemos",
    "sg:classifiers":[
        {
            "category":"Professional",
            "subcategory":"Engineering",
            "type":"Services"
        },
        {
            "category":"Building & Trades",
            "subcategory":"Construction",
            "type":"Services"
        }
    ],
    "sg:phone":"+1 517 349 4484",
    "sg:postcode":"48864",
    "sg:province":"MI",
    "sg:tags":[
        "designer",
        "business"
    ],
    "wof:name":"Quality Design Services Inc",
    "wof:placetype":"venue"
},
  "geometry": {"coordinates":[-84.420613,42.694941],"type":"Point"}
}