{
  "type": "Feature",
  "properties": {
    "iso:country":"US",
    "sg:address":"566 Ann St",
    "sg:city":"Birmingham",
    "sg:classifiers":[
        {
            "category":"Health Services",
            "subcategory":"Hospital",
            "type":"Services"
        }
    ],
    "sg:phone":"+1 248 644 8610",
    "sg:postcode":"48009",
    "sg:province":"MI",
    "sg:tags":[
        "mental"
    ],
    "wof:name":"Gretchen D Mosher",
    "wof:placetype":"venue"
},
  "geometry": {"coordinates":[-83.212197,42.543117],"type":"Point"}
}