{
  "type": "Feature",
  "properties": {
    "iso:country":"US",
    "sg:address":"6031 Spring Valley Ct",
    "sg:city":"Greenville",
    "sg:classifiers":[
        {
            "category":"Building & Trades",
            "subcategory":"Equipment Rental",
            "type":"Services"
        }
    ],
    "sg:phone":"+1 616 754 7357",
    "sg:postcode":"48838",
    "sg:province":"MI",
    "wof:name":"Highland Rentals",
    "wof:placetype":"venue"
},
  "geometry": {"coordinates":[-85.309118,43.202988],"type":"Point"}
}