{
  "type": "Feature",
  "properties": {
    "iso:country":"US",
    "sg:address":"4283 Cornith St",
    "sg:city":"Lake Orion",
    "sg:classifiers":[
        {
            "category":"Shopping",
            "type":"Retail Goods"
        }
    ],
    "sg:phone":"+1 248 391 4040",
    "sg:postcode":"48359",
    "sg:province":"MI",
    "sg:tags":[
        "equipment",
        "telephone",
        "supply"
    ],
    "wof:name":"Dewco Communications",
    "wof:placetype":"venue"
},
  "geometry": {"coordinates":[-83.277355,42.718489],"type":"Point"}
}