{
  "type": "Feature",
  "properties": {
    "iso:country":"US",
    "sg:address":"23855 Research Dr",
    "sg:city":"Farmington Hills",
    "sg:classifiers":[
        {
            "category":"Professional",
            "subcategory":"Engineering",
            "type":"Services"
        }
    ],
    "sg:phone":"+1 248 426 3908",
    "sg:postcode":"48335",
    "sg:province":"MI",
    "sg:tags":[
        "engineer"
    ],
    "wof:name":"TRW Automotive Electronics",
    "wof:placetype":"venue"
},
  "geometry": {"coordinates":[-83.428856,42.464268],"type":"Point"}
}