{
  "type": "Feature",
  "properties": {
    "iso:country":"US",
    "sg:address":"423 Barrett Ave",
    "sg:city":"Jackson",
    "sg:classifiers":[
        {
            "category":"Manufacturing",
            "subcategory":"Wood Products",
            "type":"Manufacturing & Wholesale Goods"
        }
    ],
    "sg:phone":"+1 517 784 1779",
    "sg:postcode":"49202",
    "sg:province":"MI",
    "sg:tags":[
        "pallet",
        "skid"
    ],
    "wof:name":"C & K Box Co Inc",
    "wof:placetype":"venue"
},
  "geometry": {"coordinates":[-84.44642399999999,42.25296],"type":"Point"}
}