{
  "type": "Feature",
  "properties": {
    "iso:country":"US",
    "sg:address":"1224 N Leroy St",
    "sg:city":"Fenton",
    "sg:classifiers":[
        {
            "category":"Home & Garden",
            "subcategory":"Hardware",
            "type":"Retail Goods"
        }
    ],
    "sg:phone":"+1 810 629 6307",
    "sg:postcode":"48430",
    "sg:province":"MI",
    "wof:name":"Taylor Hardware",
    "wof:placetype":"venue"
},
  "geometry": {"coordinates":[-83.707263,42.81143],"type":"Point"}
}