{
  "type": "Feature",
  "properties": {
    "iso:country":"US",
    "sg:address":"321 Bridge St",
    "sg:city":"Charlevoix",
    "sg:classifiers":[
        {
            "category":"Wholesale",
            "subcategory":"Durable Goods & Equipment",
            "type":"Manufacturing & Wholesale Goods"
        }
    ],
    "sg:phone":"+1 231 237 9237",
    "sg:postcode":"49720",
    "sg:province":"MI",
    "sg:tags":[
        "importer"
    ],
    "wof:name":"J C Marketing & Internet Dsgn",
    "wof:placetype":"venue"
},
  "geometry": {"coordinates":[-85.25874399999999,45.316841],"type":"Point"}
}