{
  "type": "Feature",
  "properties": {
    "iso:country":"US",
    "sg:address":"604 N Creyts Rd",
    "sg:city":"Lansing",
    "sg:classifiers":[
        {
            "category":"Wholesale",
            "subcategory":"Machinery & Supplies",
            "type":"Manufacturing & Wholesale Goods"
        }
    ],
    "sg:phone":"+1 517 321 6969",
    "sg:postcode":"48917",
    "sg:province":"MI",
    "sg:tags":[
        "carwash",
        "automotive",
        "industrial",
        "re"
    ],
    "wof:name":"Ziebart",
    "wof:placetype":"venue"
},
  "geometry": {"coordinates":[-84.642218,42.741011],"type":"Point"}
}