{
  "type": "Feature",
  "properties": {
    "iso:country":"US",
    "sg:address":"5530 Hickory Ln",
    "sg:city":"Bay City",
    "sg:classifiers":[
        {
            "category":"Professional",
            "type":"Services"
        }
    ],
    "sg:phone":"+1 989 686 7035",
    "sg:postcode":"48706",
    "sg:province":"MI",
    "sg:tags":[
        "establishment"
    ],
    "wof:name":"Spnp A A A",
    "wof:placetype":"venue"
},
  "geometry": {"coordinates":[-83.968909,43.579454],"type":"Point"}
}