{
  "type": "Feature",
  "properties": {
    "iso:country":"US",
    "sg:address":"3919 Oak Hills Cir",
    "sg:city":"Port Huron",
    "sg:classifiers":[
        {
            "category":"Professional",
            "subcategory":"Business Services",
            "type":"Services"
        }
    ],
    "sg:phone":"+1 810 982 4710",
    "sg:postcode":"48060",
    "sg:province":"MI",
    "sg:tags":[
        "interior",
        "consultant",
        "design",
        "decorator"
    ],
    "wof:name":"Joanne E Thomas Interior Dsgn",
    "wof:placetype":"venue"
},
  "geometry": {"coordinates":[-82.44950900000001,43.02003],"type":"Point"}
}