{
  "type": "Feature",
  "properties": {
    "iso:country":"US",
    "sg:address":"35135 Harper Ave",
    "sg:city":"Clinton Twp",
    "sg:classifiers":[
        {
            "category":"Retail",
            "subcategory":"Animal Services",
            "type":"Services"
        }
    ],
    "sg:phone":"+1 586 791 3710",
    "sg:postcode":"48035",
    "sg:province":"MI",
    "sg:tags":[
        "pet",
        "grooming",
        "washing"
    ],
    "wof:name":"Canine Castle",
    "wof:placetype":"venue"
},
  "geometry": {"coordinates":[-82.87025300000001,42.556672],"type":"Point"}
}