{
  "type": "Feature",
  "properties": {
    "iso:country":"US",
    "sg:address":"2140 Lake Grove Rd",
    "sg:city":"Petoskey",
    "sg:classifiers":[
        {
            "category":"Farming",
            "subcategory":"Dairy Farm",
            "type":"Manufacturing & Wholesale Goods"
        }
    ],
    "sg:phone":"+1 231 347 1468",
    "sg:postcode":"49770",
    "sg:province":"MI",
    "wof:name":"Beas Dairy",
    "wof:placetype":"venue"
},
  "geometry": {"coordinates":[-85.026847,45.343828],"type":"Point"}
}