{
  "type": "Feature",
  "properties": {
    "iso:country":"US",
    "sg:address":"102 W Main St",
    "sg:city":"Hale",
    "sg:classifiers":[
        {
            "category":"Real Estate",
            "subcategory":"Real Estate Agent",
            "type":"Services"
        }
    ],
    "sg:phone":"+1 989 728 2603",
    "sg:postcode":"48739",
    "sg:province":"MI",
    "sg:website":"www.scofieldrealestate.com",
    "wof:name":"Scofield Real Estate",
    "wof:placetype":"venue"
},
  "geometry": {"coordinates":[-83.806196,44.378052],"type":"Point"}
}