{
  "type": "Feature",
  "properties": {
    "iso:country":"US",
    "sg:address":"100 Library Ct",
    "sg:city":"Ionia",
    "sg:classifiers":[
        {
            "category":"Government",
            "subcategory":"Office",
            "type":"Public Place"
        }
    ],
    "sg:phone":"+1 616 527 8219",
    "sg:postcode":"48846",
    "sg:province":"MI",
    "wof:name":"Ionia County Resource Recovery",
    "wof:placetype":"venue"
},
  "geometry": {"coordinates":[-85.062562,42.983703],"type":"Point"}
}