{
  "type": "Feature",
  "properties": {
    "iso:country":"US",
    "sg:address":"900 W North St",
    "sg:city":"Jackson",
    "sg:classifiers":[
        {
            "category":"Real Estate",
            "subcategory":"Real Estate Agent",
            "type":"Services"
        }
    ],
    "sg:phone":"+1 517 796 1700",
    "sg:postcode":"49202",
    "sg:province":"MI",
    "sg:website":"www.coldwellbanker.com",
    "wof:name":"Archway Properties Inc",
    "wof:placetype":"venue"
},
  "geometry": {"coordinates":[-84.425797,42.258981],"type":"Point"}
}