{
  "type": "Feature",
  "properties": {
    "iso:country":"US",
    "sg:address":"3401 E Saginaw St",
    "sg:city":"Lansing",
    "sg:classifiers":[
        {
            "category":"Shopping",
            "subcategory":"Computers & Home Electronics",
            "type":"Retail Goods"
        }
    ],
    "sg:phone":"+1 517 324 4227",
    "sg:postcode":"48912",
    "sg:province":"MI",
    "sg:tags":[
        "software"
    ],
    "wof:name":"Site Objects",
    "wof:placetype":"venue"
},
  "geometry": {"coordinates":[-84.50605400000001,42.740922],"type":"Point"}
}