{
  "type": "Feature",
  "properties": {
    "iso:country":"US",
    "sg:address":"955 Canterbury St SW",
    "sg:city":"Grand Rapids",
    "sg:classifiers":[
        {
            "category":"Social Services",
            "subcategory":"Child Care",
            "type":"Services"
        }
    ],
    "sg:phone":"+1 616 530 9597",
    "sg:postcode":"49509",
    "sg:province":"MI",
    "sg:tags":[
        "day",
        "provider"
    ],
    "wof:name":"Cornelius Sandra",
    "wof:placetype":"venue"
},
  "geometry": {"coordinates":[-85.687067,42.911356],"type":"Point"}
}