{
  "type": "Feature",
  "properties": {
    "iso:country":"US",
    "sg:address":"23230 Inkster Rd",
    "sg:city":"New Boston",
    "sg:classifiers":[
        {
            "category":"Building & Trades",
            "subcategory":"Construction",
            "type":"Services"
        }
    ],
    "sg:phone":"+1 734 783 3422",
    "sg:postcode":"48164",
    "sg:province":"MI",
    "sg:tags":[
        "excavation",
        "contractor"
    ],
    "wof:name":"EDS Excavating",
    "wof:placetype":"venue"
},
  "geometry": {"coordinates":[-83.304711,42.131111],"type":"Point"}
}