{
  "type": "Feature",
  "properties": {
    "iso:country":"US",
    "sg:address":"226 W Michigan Ave",
    "sg:city":"Marshall",
    "sg:classifiers":[
        {
            "category":"Professional",
            "subcategory":"Computer Services",
            "type":"Services"
        }
    ],
    "sg:phone":"+1 269 781 6637",
    "sg:postcode":"49068",
    "sg:province":"MI",
    "sg:tags":[
        "website",
        "design"
    ],
    "wof:name":"Ebuisness Development Group",
    "wof:placetype":"venue"
},
  "geometry": {"coordinates":[-84.961511,42.272111],"type":"Point"}
}