{
  "type": "Feature",
  "properties": {
    "iso:country":"US",
    "sg:address":"15306 Falk Rd",
    "sg:city":"Holly",
    "sg:classifiers":[
        {
            "category":"Retail",
            "subcategory":"Repair Shop",
            "type":"Services"
        }
    ],
    "sg:phone":"+1 248 328 0900",
    "sg:postcode":"48442",
    "sg:province":"MI",
    "sg:tags":[
        "mobile",
        "body",
        "home",
        "auto"
    ],
    "wof:name":"Covered Wgon MBL HM Prts Srvic",
    "wof:placetype":"venue"
},
  "geometry": {"coordinates":[-83.603285,42.79254],"type":"Point"}
}