{
  "type": "Feature",
  "properties": {
    "iso:country":"US",
    "sg:address":"117 Cass Ave",
    "sg:city":"Mount Clemens",
    "sg:classifiers":[
        {
            "category":"Banks & Credit Unions",
            "subcategory":"Bank",
            "type":"Services"
        }
    ],
    "sg:phone":"+1 586 954 9235",
    "sg:postcode":"48043",
    "sg:province":"MI",
    "sg:tags":[
        "broker",
        "mortgage"
    ],
    "wof:name":"Michigan Mortgage Consultants",
    "wof:placetype":"venue"
},
  "geometry": {"coordinates":[-82.88273599999999,42.597175],"type":"Point"}
}