{
  "type": "Feature",
  "properties": {
    "iso:country":"US",
    "sg:address":"2391 Glen Valley Dr NW",
    "sg:city":"Grand Rapids",
    "sg:classifiers":[
        {
            "category":"Building & Trades",
            "subcategory":"Landscaping Services",
            "type":"Services"
        }
    ],
    "sg:phone":"+1 616 784 2357",
    "sg:postcode":"49544",
    "sg:province":"MI",
    "wof:name":"Thr Lawn Care",
    "wof:placetype":"venue"
},
  "geometry": {"coordinates":[-85.70044900000001,43.007425],"type":"Point"}
}