{
  "type": "Feature",
  "properties": {
    "iso:country":"US",
    "sg:address":"3015 Brown Rd",
    "sg:city":"Lake Odessa",
    "sg:phone":"+1 616 374 7666",
    "sg:postcode":"48849",
    "sg:province":"MI",
    "sg:tags":[
        "beef",
        "farm",
        "cash",
        "grain",
        "cattle",
        "feedlot"
    ],
    "wof:name":"Fred Ost",
    "wof:placetype":"venue"
},
  "geometry": {"coordinates":[-85.213915,42.755483],"type":"Point"}
}