{
  "type": "Feature",
  "properties": {
    "iso:country":"US",
    "sg:address":"1919 Corunna Rd",
    "sg:city":"Flint",
    "sg:classifiers":[
        {
            "category":"Autos & Motor Vehicles",
            "subcategory":"Fuel & Gas Station",
            "type":"Retail Goods"
        },
        {
            "category":"Personal",
            "type":"Services"
        },
        {
            "category":"Retail",
            "subcategory":"Auto Repair",
            "type":"Services"
        }
    ],
    "sg:phone":"+1 810 232 4511",
    "sg:postcode":"48503",
    "sg:province":"MI",
    "sg:tags":[
        "body",
        "shop",
        "towing"
    ],
    "wof:name":"Jim McFall's Collision & Frame Service",
    "wof:placetype":"venue"
},
  "geometry": {"coordinates":[-83.711304,43.0065],"type":"Point"}
}