{
  "type": "Feature",
  "properties": {
    "iso:country":"US",
    "sg:address":"2088 Riggs Ave",
    "sg:city":"Warren",
    "sg:classifiers":[
        {
            "category":"Building & Trades",
            "subcategory":"Construction",
            "type":"Services"
        }
    ],
    "sg:phone":"+1 586 759 6640",
    "sg:postcode":"48091",
    "sg:province":"MI",
    "sg:tags":[
        "painter"
    ],
    "wof:name":"Paintwork Inc",
    "wof:placetype":"venue"
},
  "geometry": {"coordinates":[-83.0821,42.478401],"type":"Point"}
}