{
  "type": "Feature",
  "properties": {
    "iso:country":"US",
    "sg:address":"914 S 3rd St",
    "sg:city":"Niles",
    "sg:classifiers":[
        {
            "category":"Retail",
            "subcategory":"Repair Shop",
            "type":"Services"
        }
    ],
    "sg:phone":"+1 269 684 6761",
    "sg:postcode":"49120",
    "sg:province":"MI",
    "sg:tags":[
        "motorcycle"
    ],
    "wof:name":"Doug Fattic Cycles",
    "wof:placetype":"venue"
},
  "geometry": {"coordinates":[-86.25230000000001,41.816546],"type":"Point"}
}