{
  "type": "Feature",
  "properties": {
    "iso:country":"US",
    "sg:address":"4671 Parker St",
    "sg:city":"Dearborn Heights",
    "sg:classifiers":[
        {
            "category":"Education",
            "subcategory":"School",
            "type":"Public Place"
        }
    ],
    "sg:phone":"+1 313 292 1144",
    "sg:postcode":"48125",
    "sg:province":"MI",
    "wof:name":"St Albert Great School",
    "wof:placetype":"venue"
},
  "geometry": {"coordinates":[-83.260527,42.275418],"type":"Point"}
}