{
  "type": "Feature",
  "properties": {
    "iso:country":"US",
    "sg:address":"3330 S Rochester Rd",
    "sg:city":"Rochester Hills",
    "sg:classifiers":[
        {
            "category":"Home & Garden",
            "subcategory":"Carpets & Floor Coverings",
            "type":"Retail Goods"
        }
    ],
    "sg:phone":"+1 248 852 8120",
    "sg:postcode":"48307",
    "sg:province":"MI",
    "sg:tags":[
        "mattress"
    ],
    "wof:name":"Beautiful Bedrooms At Waterbed Mart",
    "wof:placetype":"venue"
},
  "geometry": {"coordinates":[-83.131798,42.632999],"type":"Point"}
}