{
  "type": "Feature",
  "properties": {
    "iso:country":"US",
    "sg:address":"653 36th St SW",
    "sg:city":"Grand Rapids",
    "sg:classifiers":[
        {
            "category":"Health Services",
            "subcategory":"Chiropractor",
            "type":"Services"
        }
    ],
    "sg:phone":"+1 616 530 0085",
    "sg:postcode":"49509",
    "sg:province":"MI",
    "sg:tags":[
        "clinic"
    ],
    "wof:name":"Wyoming Chiropractic Clinic",
    "wof:placetype":"venue"
},
  "geometry": {"coordinates":[-85.682703,42.89885],"type":"Point"}
}