{
  "type": "Feature",
  "properties": {
    "iso:country":"US",
    "sg:address":"9835 Portage Rd",
    "sg:city":"Portage",
    "sg:classifiers":[
        {
            "category":"Real Estate",
            "subcategory":"Surveying",
            "type":"Services"
        }
    ],
    "sg:phone":"+1 269 327 3532",
    "sg:postcode":"49002",
    "sg:province":"MI",
    "wof:name":"Wightman Ward Inc",
    "wof:placetype":"venue"
},
  "geometry": {"coordinates":[-85.568262,42.173374],"type":"Point"}
}