{
  "type": "Feature",
  "properties": {
    "iso:country":"US",
    "sg:address":"4540 Meigs St",
    "sg:city":"Waterford",
    "sg:classifiers":[
        {
            "category":"Building & Trades",
            "subcategory":"Construction",
            "type":"Services"
        }
    ],
    "sg:phone":"+1 248 674 2597",
    "sg:postcode":"48329",
    "sg:province":"MI",
    "sg:tags":[
        "house",
        "contractor"
    ],
    "wof:name":"Complete Remodeling Co",
    "wof:placetype":"venue"
},
  "geometry": {"coordinates":[-83.376543,42.691688],"type":"Point"}
}