{
  "type": "Feature",
  "properties": {
    "iso:country":"US",
    "sg:address":"3801 Lynn Ct",
    "sg:city":"Flint",
    "sg:classifiers":[
        {
            "category":"Retail",
            "subcategory":"Repair Shop",
            "type":"Services"
        }
    ],
    "sg:phone":"+1 810 744 0187",
    "sg:postcode":"48503",
    "sg:province":"MI",
    "sg:tags":[
        "related"
    ],
    "wof:name":"Drum Doctor",
    "wof:placetype":"venue"
},
  "geometry": {"coordinates":[-83.636167,43.005593],"type":"Point"}
}