{
  "type": "Feature",
  "properties": {
    "iso:country":"US",
    "sg:address":"29205 Dequindre Rd",
    "sg:city":"Madison Heights",
    "sg:classifiers":[
        {
            "category":"Restaurant",
            "type":"Food & Drink"
        }
    ],
    "sg:menulink":"http://www.allmenus.com/mi/warren/86860-little-caesars-pizza/menu/",
    "sg:phone":"+1 248 548 9191",
    "sg:postcode":"48071",
    "sg:province":"MI",
    "sg:tags":[
        "american",
        "pizza"
    ],
    "wof:name":"Little Caesar's Pizza",
    "wof:placetype":"venue"
},
  "geometry": {"coordinates":[-83.085705,42.50716],"type":"Point"}
}