{
  "type": "Feature",
  "properties": {
    "iso:country":"US",
    "sg:address":"1900 Yeager St",
    "sg:city":"Port Huron",
    "sg:classifiers":[
        {
            "category":"Retail",
            "subcategory":"Auto Rental",
            "type":"Services"
        }
    ],
    "sg:phone":"+1 810 987 4880",
    "sg:postcode":"48060",
    "sg:province":"MI",
    "sg:tags":[
        "renting",
        "truck",
        "leasing"
    ],
    "wof:name":"Budget Truck Rental",
    "wof:placetype":"venue"
},
  "geometry": {"coordinates":[-82.45208599999999,42.989438],"type":"Point"}
}