{
  "type": "Feature",
  "properties": {
    "iso:country":"US",
    "sg:address":"982 Riverview Ct",
    "sg:city":"Williamston",
    "sg:classifiers":[
        {
            "category":"Professional",
            "subcategory":"Engineering",
            "type":"Services"
        }
    ],
    "sg:phone":"+1 517 655 5682",
    "sg:postcode":"48895",
    "sg:province":"MI",
    "wof:name":"Lgdi Engineering",
    "wof:placetype":"venue"
},
  "geometry": {"coordinates":[-84.27387400000001,42.689947],"type":"Point"}
}