{
  "type": "Feature",
  "properties": {
    "iso:country":"US",
    "sg:address":"25657 Southfield Rd",
    "sg:city":"Southfield",
    "sg:classifiers":[
        {
            "category":"Wholesale",
            "subcategory":"Office Equipment",
            "type":"Manufacturing & Wholesale Goods"
        }
    ],
    "sg:phone":"+1 248 569 6440",
    "sg:postcode":"48075",
    "sg:province":"MI",
    "sg:tags":[
        "repair",
        "electrical"
    ],
    "wof:name":"Dss",
    "wof:placetype":"venue"
},
  "geometry": {"coordinates":[-83.221468,42.47836],"type":"Point"}
}