{
  "type": "Feature",
  "properties": {
    "iso:country":"US",
    "sg:address":"24787 Van Horn Rd",
    "sg:city":"Flat Rock",
    "sg:classifiers":[
        {
            "category":"Education",
            "subcategory":"School",
            "type":"Public Place"
        }
    ],
    "sg:phone":"+1 734 783 3333",
    "sg:postcode":"48134",
    "sg:province":"MI",
    "sg:tags":[
        "high",
        "middle",
        "elementary"
    ],
    "wof:name":"Woodhaven Brownstown School District",
    "wof:placetype":"venue"
},
  "geometry": {"coordinates":[-83.273079,42.12352],"type":"Point"}
}