{
  "type": "Feature",
  "properties": {
    "iso:country":"US",
    "sg:address":"56200 Grand River Ave",
    "sg:city":"New Hudson",
    "sg:classifiers":[
        {
            "category":"Autos & Motor Vehicles",
            "subcategory":"Auto Supplies",
            "type":"Retail Goods"
        }
    ],
    "sg:phone":"+1 248 486 8334",
    "sg:postcode":"48165",
    "sg:province":"MI",
    "sg:tags":[
        "automobile",
        "remote",
        "starter"
    ],
    "wof:name":"Hilltop Sounds & Security",
    "wof:placetype":"venue"
},
  "geometry": {"coordinates":[-83.611936,42.510873],"type":"Point"}
}