{
  "type": "Feature",
  "properties": {
    "iso:country":"US",
    "sg:address":"1348 Front Ave NW",
    "sg:city":"Grand Rapids",
    "sg:classifiers":[
        {
            "category":"Social Services",
            "type":"Services"
        }
    ],
    "sg:phone":"+1 616 454 7077",
    "sg:postcode":"49504",
    "sg:province":"MI",
    "sg:tags":[
        "organization",
        "welfare"
    ],
    "wof:name":"Spectrum Community Svc",
    "wof:placetype":"venue"
},
  "geometry": {"coordinates":[-85.675394,42.987503],"type":"Point"}
}