{
  "type": "Feature",
  "properties": {
    "iso:country":"US",
    "sg:address":"725 Barclay Cir",
    "sg:city":"Rochester Hills",
    "sg:classifiers":[
        {
            "category":"Professional",
            "subcategory":"Lawyer & Legal Services",
            "type":"Services"
        }
    ],
    "sg:phone":"+1 248 299 9999",
    "sg:postcode":"48307",
    "sg:province":"MI",
    "sg:tags":[
        "attorney"
    ],
    "wof:name":"Mark S Kopson PLC",
    "wof:placetype":"venue"
},
  "geometry": {"coordinates":[-83.12968100000001,42.642713],"type":"Point"}
}