{
  "type": "Feature",
  "properties": {
    "iso:country":"US",
    "sg:address":"2306 Eastways Rd",
    "sg:city":"Bloomfield Hills",
    "sg:classifiers":[
        {
            "category":"Insurance",
            "subcategory":"Insurance Agent",
            "type":"Services"
        }
    ],
    "sg:phone":"+1 248 644 1215",
    "sg:postcode":"48304",
    "sg:province":"MI",
    "wof:name":"Equisport Agency Inc",
    "wof:placetype":"venue"
},
  "geometry": {"coordinates":[-83.230338,42.603442],"type":"Point"}
}