{
  "type": "Feature",
  "properties": {
    "iso:country":"US",
    "sg:address":"206 S Canal St",
    "sg:city":"Chesaning",
    "sg:classifiers":[
        {
            "category":"Retail",
            "subcategory":"Repair Shop",
            "type":"Services"
        }
    ],
    "sg:phone":"+1 989 845 2645",
    "sg:postcode":"48616",
    "sg:province":"MI",
    "wof:name":"Take 5 Cleaning",
    "wof:placetype":"venue"
},
  "geometry": {"coordinates":[-84.113783,43.182067],"type":"Point"}
}