{
  "type": "Feature",
  "properties": {
    "iso:country":"US",
    "sg:address":"1218 Pontaluna Rd",
    "sg:city":"Spring Lake",
    "sg:classifiers":[
        {
            "category":"Banks & Credit Unions",
            "subcategory":"Financial Services",
            "type":"Services"
        }
    ],
    "sg:phone":"+1 231 799 6240",
    "sg:postcode":"49456",
    "sg:province":"MI",
    "sg:tags":[
        "company",
        "holding"
    ],
    "wof:name":"Hines Corp",
    "wof:placetype":"venue"
},
  "geometry": {"coordinates":[-86.21426700000001,43.132472],"type":"Point"}
}