{
  "type": "Feature",
  "properties": {
    "iso:country":"US",
    "sg:address":"2000 E 10 Mile Rd",
    "sg:city":"Warren",
    "sg:classifiers":[
        {
            "category":"Restaurant",
            "type":"Food & Drink"
        }
    ],
    "sg:menulink":"http://www.allmenus.com/mi/warren/86995-little-caesars-pizza/menu/",
    "sg:phone":"+1 586 757 4922",
    "sg:postcode":"48091",
    "sg:province":"MI",
    "sg:tags":[
        "american",
        "pizza"
    ],
    "wof:name":"Little Caesar's Pizza",
    "wof:placetype":"venue"
},
  "geometry": {"coordinates":[-83.082972,42.476391],"type":"Point"}
}