{
  "type": "Feature",
  "properties": {
    "iso:country":"US",
    "sg:address":"480 Olds St",
    "sg:city":"Jonesville",
    "sg:classifiers":[
        {
            "category":"Real Estate",
            "subcategory":"Real Estate Agent",
            "type":"Services"
        }
    ],
    "sg:phone":"+1 517 849 3111",
    "sg:postcode":"49250",
    "sg:province":"MI",
    "sg:tags":[
        "agency",
        "rental"
    ],
    "wof:name":"Eagle Rentals",
    "wof:placetype":"venue"
},
  "geometry": {"coordinates":[-84.67111800000001,41.968593],"type":"Point"}
}