{
  "type": "Feature",
  "properties": {
    "iso:country":"US",
    "sg:address":"32051 Howard Ave",
    "sg:city":"Madison Heights",
    "sg:classifiers":[
        {
            "category":"Manufacturing",
            "subcategory":"Glass & Minerals",
            "type":"Manufacturing & Wholesale Goods"
        }
    ],
    "sg:phone":"+1 248 585 2330",
    "sg:postcode":"48071",
    "sg:province":"MI",
    "sg:tags":[
        "abrasive",
        "product"
    ],
    "sg:website":"www.inlanddiamond.com",
    "wof:name":"Inland Diamond Products",
    "wof:placetype":"venue"
},
  "geometry": {"coordinates":[-83.09948799999999,42.530329],"type":"Point"}
}