{
  "type": "Feature",
  "properties": {
    "iso:country":"US",
    "sg:address":"123 E Washington St",
    "sg:city":"Howell",
    "sg:classifiers":[
        {
            "category":"Organizations",
            "subcategory":"Professional Association",
            "type":"Services"
        }
    ],
    "sg:phone":"+1 517 546 3920",
    "sg:postcode":"48843",
    "sg:province":"MI",
    "sg:tags":[
        "chambers",
        "business",
        "commerce"
    ],
    "wof:name":"Howell Area Chamber Commerce",
    "wof:placetype":"venue"
},
  "geometry": {"coordinates":[-83.930547,42.60532],"type":"Point"}
}