{
  "type": "Feature",
  "properties": {
    "iso:country":"US",
    "sg:address":"2260 Jolly Oak Rd",
    "sg:city":"Okemos",
    "sg:classifiers":[
        {
            "category":"Banks & Credit Unions",
            "subcategory":"Bank",
            "type":"Services"
        }
    ],
    "sg:phone":"+1 517 334 1725",
    "sg:postcode":"48864",
    "sg:province":"MI",
    "sg:tags":[
        "national"
    ],
    "wof:name":"National City Bank",
    "wof:placetype":"venue"
},
  "geometry": {"coordinates":[-84.433267,42.685286],"type":"Point"}
}