{
  "type": "Feature",
  "properties": {
    "iso:country":"US",
    "sg:address":"22884 66th Ave",
    "sg:city":"Mattawan",
    "sg:classifiers":[
        {
            "category":"Building & Trades",
            "subcategory":"Landscaping Services",
            "type":"Services"
        }
    ],
    "sg:phone":"+1 269 668 3474",
    "sg:postcode":"49071",
    "sg:province":"MI",
    "wof:name":"Van Niman Wood Sales",
    "wof:placetype":"venue"
},
  "geometry": {"coordinates":[-85.780362,42.179027],"type":"Point"}
}