{
  "type": "Feature",
  "properties": {
    "iso:country":"US",
    "sg:address":"10944 Reeck Rd",
    "sg:city":"Allen Park",
    "sg:classifiers":[
        {
            "category":"Organizations",
            "subcategory":"Religious Organization",
            "type":"Services"
        }
    ],
    "sg:phone":"+1 313 383 7610",
    "sg:postcode":"48101",
    "sg:province":"MI",
    "wof:name":"Allen Park Church of the Nazarene",
    "wof:placetype":"venue"
},
  "geometry": {"coordinates":[-83.21970399999999,42.2285],"type":"Point"}
}