{
  "type": "Feature",
  "properties": {
    "iso:country":"US",
    "sg:address":"6299 Chapin Rd",
    "sg:city":"Deford",
    "sg:classifiers":[
        {
            "category":"Organizations",
            "subcategory":"Religious Organization",
            "type":"Services"
        }
    ],
    "sg:phone":"+1 989 683 2381",
    "sg:postcode":"48729",
    "sg:province":"MI",
    "sg:tags":[
        "church"
    ],
    "wof:name":"Watertown Missionary Church",
    "wof:placetype":"venue"
},
  "geometry": {"coordinates":[-83.174071,43.470854],"type":"Point"}
}