{
  "type": "Feature",
  "properties": {
    "iso:country":"US",
    "sg:address":"1007 Clear St",
    "sg:city":"Lansing",
    "sg:classifiers":[
        {
            "category":"Organizations",
            "subcategory":"Religious Organization",
            "type":"Services"
        }
    ],
    "sg:phone":"+1 517 316 1279",
    "sg:postcode":"48910",
    "sg:province":"MI",
    "wof:name":"Men's Family Ministry",
    "wof:placetype":"venue"
},
  "geometry": {"coordinates":[-84.549646,42.721982],"type":"Point"}
}