{
  "type": "Feature",
  "properties": {
    "iso:country":"US",
    "sg:address":"2675 Dixie Hwy ",
    "sg:city":"Waterford",
    "sg:classifiers":[
        {
            "category":"Restaurant",
            "type":"Food & Drink"
        }
    ],
    "sg:menulink":"http://www.allmenus.com/mi/waterford/289652-ricos-restaurant/menu/",
    "sg:phone":"+1 248 618 0122",
    "sg:postcode":"48328",
    "sg:province":"MI",
    "sg:tags":[
        "mexican"
    ],
    "wof:name":"Rico's Restaurant",
    "wof:placetype":"venue"
},
  "geometry": {"coordinates":[-83.341319,42.67404],"type":"Point"}
}