{
  "type": "Feature",
  "properties": {
    "iso:country":"US",
    "sg:address":"10830 Ramsdell Dr NE",
    "sg:city":"Rockford",
    "sg:classifiers":[
        {
            "category":"Freight",
            "type":"Transportation"
        }
    ],
    "sg:phone":"+1 616 863 9202",
    "sg:postcode":"49341",
    "sg:province":"MI",
    "sg:tags":[
        "operator",
        "trucking"
    ],
    "wof:name":"Woodys Trucking",
    "wof:placetype":"venue"
},
  "geometry": {"coordinates":[-85.43122200000001,43.16503],"type":"Point"}
}