{
  "type": "Feature",
  "properties": {
    "iso:country":"US",
    "sg:address":"2870 Hilton Rd",
    "sg:city":"Ferndale",
    "sg:classifiers":[
        {
            "category":"Professional",
            "type":"Services"
        }
    ],
    "sg:phone":"+1 248 548 7424",
    "sg:postcode":"48220",
    "sg:province":"MI",
    "wof:name":"United Bg Svc",
    "wof:placetype":"venue"
},
  "geometry": {"coordinates":[-83.12348,42.471776],"type":"Point"}
}