{
  "type": "Feature",
  "properties": {
    "iso:country":"US",
    "sg:address":"6001 Miller Rd",
    "sg:city":"Dearborn",
    "sg:classifiers":[
        {
            "category":"Personal",
            "subcategory":"Beauty Salon",
            "type":"Services"
        }
    ],
    "sg:phone":"+1 313 584 5290",
    "sg:postcode":"48126",
    "sg:province":"MI",
    "sg:tags":[
        "shop"
    ],
    "wof:name":"Eves Air Salon",
    "wof:placetype":"venue"
},
  "geometry": {"coordinates":[-83.16668199999999,42.335138],"type":"Point"}
}