{
  "type": "Feature",
  "properties": {
    "iso:country":"US",
    "sg:address":"6655 Pine Rd",
    "sg:city":"Benton Harbor",
    "sg:phone":"+1 269 468 3691",
    "sg:postcode":"49022",
    "sg:province":"MI",
    "sg:tags":[
        "farm"
    ],
    "wof:name":"Terry Molter",
    "wof:placetype":"venue"
},
  "geometry": {"coordinates":[-86.29048400000001,42.123219],"type":"Point"}
}