{
  "type": "Feature",
  "properties": {
    "iso:country":"US",
    "sg:address":"45710 Spring Ln",
    "sg:city":"Shelby Township",
    "sg:classifiers":[
        {
            "category":"Real Estate",
            "subcategory":"Real Estate Operator",
            "type":"Services"
        }
    ],
    "sg:phone":"+1 586 739 6611",
    "sg:postcode":"48317",
    "sg:province":"MI",
    "sg:tags":[
        "apartment"
    ],
    "wof:name":"Spring Hill Apartments",
    "wof:placetype":"venue"
},
  "geometry": {"coordinates":[-83.068901,42.6301],"type":"Point"}
}