{
  "type": "Feature",
  "properties": {
    "iso:country":"US",
    "sg:address":"4391 Dixie Hwy",
    "sg:city":"Waterford",
    "sg:classifiers":[
        {
            "category":"Personal",
            "subcategory":"Barber",
            "type":"Services"
        }
    ],
    "sg:phone":"+1 248 674 1210",
    "sg:postcode":"48329",
    "sg:province":"MI",
    "sg:tags":[
        "shop"
    ],
    "wof:name":"Burleson Art Barber Shop",
    "wof:placetype":"venue"
},
  "geometry": {"coordinates":[-83.375005,42.681834],"type":"Point"}
}