{
  "type": "Feature",
  "properties": {
    "iso:country":"US",
    "sg:address":"17903 Dice Rd",
    "sg:city":"Hemlock",
    "sg:classifiers":[
        {
            "category":"Education",
            "subcategory":"School",
            "type":"Public Place"
        }
    ],
    "sg:phone":"+1 989 642 2147",
    "sg:postcode":"48626",
    "sg:province":"MI",
    "sg:tags":[
        "organization",
        "religious"
    ],
    "wof:name":"Zion Lutheran School",
    "wof:placetype":"venue"
},
  "geometry": {"coordinates":[-84.26310599999999,43.463386],"type":"Point"}
}