{
  "type": "Feature",
  "properties": {
    "iso:country":"US",
    "sg:address":"1302 US Hwy 41",
    "sg:city":"Bark River",
    "sg:classifiers":[
        {
            "category":"Food & Beverages",
            "subcategory":"Groceries & Convenience Stores",
            "type":"Retail Goods"
        }
    ],
    "sg:phone":"+1 906 466 9961",
    "sg:postcode":"49807",
    "sg:province":"MI",
    "sg:tags":[
        "grocer"
    ],
    "wof:name":"Adams Grocery",
    "wof:placetype":"venue"
},
  "geometry": {"coordinates":[-87.301163,45.711652],"type":"Point"}
}