{
  "type": "Feature",
  "properties": {
    "iso:country":"US",
    "sg:address":"36536 Jefferson Ct",
    "sg:city":"Farmington",
    "sg:classifiers":[
        {
            "category":"Education",
            "subcategory":"Vocational School",
            "type":"Public Place"
        }
    ],
    "sg:phone":"+1 248 476 4407",
    "sg:postcode":"48335",
    "sg:province":"MI",
    "sg:tags":[
        "processing",
        "datum"
    ],
    "wof:name":"Intellitech Inc",
    "wof:placetype":"venue"
},
  "geometry": {"coordinates":[-83.411511,42.473641],"type":"Point"}
}