{
  "type": "Feature",
  "properties": {
    "iso:country":"US",
    "sg:address":"27135 Van Dyke Ave",
    "sg:city":"Warren",
    "sg:classifiers":[
        {
            "category":"Shopping",
            "subcategory":"Mobile Phones",
            "type":"Retail Goods"
        }
    ],
    "sg:phone":"+1 586 393 6900",
    "sg:postcode":"48093",
    "sg:province":"MI",
    "wof:name":"Proz Wireless",
    "wof:placetype":"venue"
},
  "geometry": {"coordinates":[-83.02798799999999,42.492974],"type":"Point"}
}