{
  "type": "Feature",
  "properties": {
    "iso:country":"US",
    "sg:address":"200 Diversion St",
    "sg:city":"Rochester Hills",
    "sg:classifiers":[
        {
            "category":"Health Services",
            "subcategory":"Health Practitioner",
            "type":"Services"
        }
    ],
    "sg:phone":"+1 248 608 9020",
    "sg:postcode":"48307",
    "sg:province":"MI",
    "sg:tags":[
        "psychologist"
    ],
    "wof:name":"Pillow & Yurik",
    "wof:placetype":"venue"
},
  "geometry": {"coordinates":[-83.13426800000001,42.675509],"type":"Point"}
}