{
  "type": "Feature",
  "properties": {
    "iso:country":"US",
    "sg:address":"41240 Hayes Rd",
    "sg:city":"Clinton Twp",
    "sg:classifiers":[
        {
            "category":"Restaurant",
            "type":"Food & Drink"
        }
    ],
    "sg:phone":"+1 586 412 2233",
    "sg:postcode":"48038",
    "sg:province":"MI",
    "wof:name":"Andiamo Pizza Pie",
    "wof:placetype":"venue"
},
  "geometry": {"coordinates":[-82.972003,42.5978],"type":"Point"}
}