{
  "type": "Feature",
  "properties": {
    "iso:country":"US",
    "sg:address":"1316 S Rochester Rd",
    "sg:city":"Rochester Hills",
    "sg:classifiers":[
        {
            "category":"Home & Garden",
            "subcategory":"Furniture",
            "type":"Retail Goods"
        }
    ],
    "sg:phone":"+1 248 651 9300",
    "sg:postcode":"48307",
    "sg:province":"MI",
    "sg:website":"www.costplusworldmarket.com",
    "wof:name":"Cost Plus World Market",
    "wof:placetype":"venue"
},
  "geometry": {"coordinates":[-83.13323800000001,42.665995],"type":"Point"}
}