{
  "type": "Feature",
  "properties": {
    "iso:country":"US",
    "sg:address":"5351 Boland Dr",
    "sg:city":"Grand Blanc",
    "sg:classifiers":[
        {
            "category":"Shopping",
            "subcategory":"Used Merchandise",
            "type":"Retail Goods"
        }
    ],
    "sg:phone":"+1 810 694 1219",
    "sg:postcode":"48439",
    "sg:province":"MI",
    "wof:name":"Lilahs Antiques & Collectibles",
    "wof:placetype":"venue"
},
  "geometry": {"coordinates":[-83.67049900000001,42.946739],"type":"Point"}
}