{
  "type": "Feature",
  "properties": {
    "iso:country":"US",
    "sg:address":"1251 Fort St",
    "sg:city":"Trenton",
    "sg:classifiers":[
        {
            "category":"Real Estate",
            "subcategory":"Developer",
            "type":"Services"
        }
    ],
    "sg:phone":"+1 734 479 2345",
    "sg:postcode":"48183",
    "sg:province":"MI",
    "sg:tags":[
        "development",
        "a",
        "manages",
        "export",
        "import",
        "trading"
    ],
    "wof:name":"Danou Enterprises Inc",
    "wof:placetype":"venue"
},
  "geometry": {"coordinates":[-83.18843200000001,42.165654],"type":"Point"}
}