{
  "type": "Feature",
  "properties": {
    "iso:country":"US",
    "sg:address":"354 Reitman Ct",
    "sg:city":"Rochester",
    "sg:classifiers":[
        {
            "category":"Organizations",
            "subcategory":"Professional Association",
            "type":"Services"
        }
    ],
    "sg:phone":"+1 248 651 5036",
    "sg:postcode":"48307",
    "sg:province":"MI",
    "wof:name":"Questers",
    "wof:placetype":"venue"
},
  "geometry": {"coordinates":[-83.13868100000001,42.693876],"type":"Point"}
}