{
  "type": "Feature",
  "properties": {
    "iso:country":"US",
    "sg:address":"397 W Aurora St",
    "sg:city":"Ironwood",
    "sg:classifiers":[
        {
            "category":"Autos & Motor Vehicles",
            "subcategory":"Automobile Sales",
            "type":"Retail Goods"
        }
    ],
    "sg:phone":"+1 906 932 6239",
    "sg:postcode":"49938",
    "sg:province":"MI",
    "sg:tags":[
        "car",
        "dealer"
    ],
    "wof:name":"Quality Used Cars",
    "wof:placetype":"venue"
},
  "geometry": {"coordinates":[-90.173158,46.451743],"type":"Point"}
}