{
  "type": "Feature",
  "properties": {
    "iso:country":"US",
    "sg:address":"620 S Ripley Blvd",
    "sg:city":"Alpena",
    "sg:classifiers":[
        {
            "category":"Professional",
            "type":"Services"
        }
    ],
    "sg:phone":"+1 989 354 9413",
    "sg:postcode":"49707",
    "sg:province":"MI",
    "sg:tags":[
        "establishment"
    ],
    "wof:name":"NCI Kurven Inc",
    "wof:placetype":"venue"
},
  "geometry": {"coordinates":[-83.453018,45.046621],"type":"Point"}
}