{
  "type": "Feature",
  "properties": {
    "iso:country":"US",
    "sg:address":"365 Broken Hills Rd",
    "sg:city":"Mason",
    "sg:classifiers":[
        {
            "category":"Professional",
            "subcategory":"Management & Consulting",
            "type":"Services"
        }
    ],
    "sg:phone":"+1 517 623 6850",
    "sg:postcode":"48854",
    "sg:province":"MI",
    "sg:tags":[
        "financial"
    ],
    "wof:name":"Aci Finance Inc",
    "wof:placetype":"venue"
},
  "geometry": {"coordinates":[-84.34863300000001,42.539867],"type":"Point"}
}