{
  "type": "Feature",
  "properties": {
    "iso:country":"US",
    "sg:address":"2964 Dixie Hwy",
    "sg:city":"Waterford",
    "sg:classifiers":[
        {
            "category":"Professional",
            "type":"Services"
        }
    ],
    "sg:phone":"+1 248 673 8790",
    "sg:postcode":"48328",
    "sg:province":"MI",
    "wof:name":"J&T Safety Service",
    "wof:placetype":"venue"
},
  "geometry": {"coordinates":[-83.345122,42.675159],"type":"Point"}
}