{
  "type": "Feature",
  "properties": {
    "iso:country":"US",
    "sg:address":"8135 Allen Rd",
    "sg:city":"Fenwick",
    "sg:classifiers":[
        {
            "category":"Social Services",
            "subcategory":"Job Training",
            "type":"Services"
        }
    ],
    "sg:phone":"+1 800 532 7579",
    "sg:postcode":"48834",
    "sg:province":"MI",
    "sg:tags":[
        "career",
        "educational",
        "planning"
    ],
    "wof:name":"Careerplanonlinecom",
    "wof:placetype":"venue"
},
  "geometry": {"coordinates":[-85.045023,43.108643],"type":"Point"}
}