{
  "type": "Feature",
  "properties": {
    "iso:country":"US",
    "sg:address":"220 Bagley St Ste 1015",
    "sg:city":"Detroit",
    "sg:classifiers":[
        {
            "category":"Professional",
            "subcategory":"Lawyer & Legal Services",
            "type":"Services"
        }
    ],
    "sg:phone":"+1 313 965 6050",
    "sg:postcode":"48226",
    "sg:province":"MI",
    "wof:name":"Kostovski Suzanna Law Office of",
    "wof:placetype":"venue"
},
  "geometry": {"coordinates":[-83.053324,42.334809],"type":"Point"}
}