{
  "type": "Feature",
  "properties": {
    "iso:country":"US",
    "sg:address":"29508 Northwestern Hwy",
    "sg:city":"Southfield",
    "sg:classifiers":[
        {
            "category":"Food & Beverages",
            "subcategory":"Ethnic Foods",
            "type":"Retail Goods"
        }
    ],
    "sg:phone":"+1 248 208 1680",
    "sg:postcode":"48034",
    "sg:province":"MI",
    "sg:tags":[
        "soul"
    ],
    "sg:website":"www.beanscornbread.com",
    "wof:name":"Beans & Cornbread",
    "wof:placetype":"venue"
},
  "geometry": {"coordinates":[-83.314598,42.504601],"type":"Point"}
}