{
  "type": "Feature",
  "properties": {
    "iso:country":"US",
    "sg:address":"250 N Hadley Rd",
    "sg:city":"Ortonville",
    "sg:classifiers":[
        {
            "category":"Professional",
            "subcategory":"Engineering",
            "type":"Services"
        }
    ],
    "sg:phone":"+1 248 627 5320",
    "sg:postcode":"48462",
    "sg:province":"MI",
    "sg:tags":[
        "consulting",
        "industrial",
        "mechanical"
    ],
    "wof:name":"Detroit Racing Components Inc",
    "wof:placetype":"venue"
},
  "geometry": {"coordinates":[-83.404715,42.855116],"type":"Point"}
}