{
  "type": "Feature",
  "properties": {
    "iso:country":"US",
    "sg:address":"526 Townsend St",
    "sg:city":"Lansing",
    "sg:classifiers":[
        {
            "category":"Professional",
            "subcategory":"Management & Consulting",
            "type":"Services"
        }
    ],
    "sg:phone":"+1 517 372 0860",
    "sg:postcode":"48933",
    "sg:province":"MI",
    "sg:tags":[
        "lobbyist",
        "public",
        "relations"
    ],
    "sg:website":"www.capitolservices.org",
    "wof:name":"Capitol Services Corp",
    "wof:placetype":"venue"
},
  "geometry": {"coordinates":[-84.555565,42.727762],"type":"Point"}
}