{
  "type": "Feature",
  "properties": {
    "iso:country":"US",
    "sg:address":"434 Pine Creek Ct",
    "sg:city":"Waterford",
    "sg:classifiers":[
        {
            "category":"Building & Trades",
            "subcategory":"Landscaping Services",
            "type":"Services"
        }
    ],
    "sg:phone":"+1 248 698 1404",
    "sg:postcode":"48327",
    "sg:province":"MI",
    "sg:tags":[
        "landscape",
        "contractor"
    ],
    "wof:name":"Grand View Landscape",
    "wof:placetype":"venue"
},
  "geometry": {"coordinates":[-83.43170600000001,42.650613],"type":"Point"}
}