{
  "type": "Feature",
  "properties": {
    "iso:country":"US",
    "sg:address":"12153 N Woodbridge Ave",
    "sg:city":"Bitely",
    "sg:classifiers":[
        {
            "category":"Home & Garden",
            "subcategory":"Building Materials",
            "type":"Retail Goods"
        }
    ],
    "sg:phone":"+1 231 745 7132",
    "sg:postcode":"49309",
    "sg:province":"MI",
    "sg:tags":[
        "insulation",
        "heat"
    ],
    "wof:name":"Foam Plus LLC",
    "wof:placetype":"venue"
},
  "geometry": {"coordinates":[-85.850273,43.783406],"type":"Point"}
}