{
  "type": "Feature",
  "properties": {
    "iso:country":"US",
    "sg:address":"1795 W Stadium Blvd",
    "sg:city":"Ann Arbor",
    "sg:classifiers":[
        {
            "category":"Health Services",
            "subcategory":"Doctor",
            "type":"Services"
        }
    ],
    "sg:phone":"+1 734 769 4121",
    "sg:postcode":"48103",
    "sg:province":"MI",
    "wof:name":"Richard Han DDS",
    "wof:placetype":"venue"
},
  "geometry": {"coordinates":[-83.769193,42.265634],"type":"Point"}
}