{
  "type": "Feature",
  "properties": {
    "iso:country":"US",
    "sg:address":"3802 Holiday Rd",
    "sg:city":"Traverse City",
    "sg:classifiers":[
        {
            "category":"Shopping",
            "subcategory":"Computers & Home Electronics",
            "type":"Retail Goods"
        }
    ],
    "sg:phone":"+1 231 938 2265",
    "sg:postcode":"49686",
    "sg:province":"MI",
    "sg:tags":[
        "software"
    ],
    "wof:name":"Integrated Custom Software",
    "wof:placetype":"venue"
},
  "geometry": {"coordinates":[-85.50393099999999,44.741009],"type":"Point"}
}