{
  "type": "Feature",
  "properties": {
    "iso:country":"US",
    "sg:address":"7084 Highland Rd",
    "sg:city":"Waterford",
    "sg:classifiers":[
        {
            "category":"Professional",
            "subcategory":"Testing Lab",
            "type":"Services"
        }
    ],
    "sg:phone":"+1 248 886 1001",
    "sg:postcode":"48327",
    "sg:province":"MI",
    "sg:tags":[
        "consulting",
        "plastic"
    ],
    "wof:name":"JHM Technologies",
    "wof:placetype":"venue"
},
  "geometry": {"coordinates":[-83.42349400000001,42.659453],"type":"Point"}
}