{
  "type": "Feature",
  "properties": {
    "iso:country":"US",
    "sg:address":"3377 Elizabeth Lake Rd",
    "sg:city":"Waterford",
    "sg:classifiers":[
        {
            "category":"Restaurant",
            "type":"Food & Drink"
        }
    ],
    "sg:phone":"+1 248 738 3802",
    "sg:postcode":"48328",
    "sg:province":"MI",
    "wof:name":"Cabana Cafe",
    "wof:placetype":"venue"
},
  "geometry": {"coordinates":[-83.352093,42.639305],"type":"Point"}
}