{
  "type": "Feature",
  "properties": {
    "iso:country":"US",
    "sg:address":"1380 Rankin Dr",
    "sg:city":"Troy",
    "sg:classifiers":[
        {
            "category":"Professional",
            "subcategory":"Management & Consulting",
            "type":"Services"
        }
    ],
    "sg:phone":"+1 248 307 0388",
    "sg:postcode":"48083",
    "sg:province":"MI",
    "sg:tags":[
        "business"
    ],
    "wof:name":"Twin Star Trading",
    "wof:placetype":"venue"
},
  "geometry": {"coordinates":[-83.128112,42.542816],"type":"Point"}
}