{
  "type": "Feature",
  "properties": {
    "iso:country":"US",
    "sg:address":"1710 E Marshall St",
    "sg:city":"Ferndale",
    "sg:classifiers":[
        {
            "category":"Building & Trades",
            "subcategory":"Construction",
            "type":"Services"
        }
    ],
    "sg:phone":"+1 248 398 1019",
    "sg:postcode":"48220",
    "sg:province":"MI",
    "sg:tags":[
        "builder",
        "patio",
        "deck"
    ],
    "wof:name":"Kapasetic Decks & More",
    "wof:placetype":"venue"
},
  "geometry": {"coordinates":[-83.110629,42.454332],"type":"Point"}
}