{
  "type": "Feature",
  "properties": {
    "iso:country":"US",
    "sg:address":"1600 S Beacon Blvd",
    "sg:city":"Grand Haven",
    "sg:classifiers":[
        {
            "category":"Real Estate",
            "subcategory":"Developer",
            "type":"Services"
        }
    ],
    "sg:phone":"+1 616 846 6900",
    "sg:postcode":"49417",
    "sg:province":"MI",
    "wof:name":"Investment Property Assoc Inc",
    "wof:placetype":"venue"
},
  "geometry": {"coordinates":[-86.220063,43.048526],"type":"Point"}
}