{
  "type": "Feature",
  "properties": {
    "iso:country":"US",
    "sg:address":"7551 Auburn Rd",
    "sg:city":"Utica",
    "sg:classifiers":[
        {
            "category":"Retail",
            "subcategory":"Auto Repair",
            "type":"Services"
        }
    ],
    "sg:phone":"+1 586 323 0516",
    "sg:postcode":"48317",
    "sg:province":"MI",
    "sg:tags":[
        "automobile",
        "co",
        "drive",
        "transporter"
    ],
    "wof:name":"Shelby Utica Automotive",
    "wof:placetype":"venue"
},
  "geometry": {"coordinates":[-83.034858,42.626085],"type":"Point"}
}