{
  "type": "Feature",
  "properties": {
    "iso:country":"US",
    "sg:address":"1491 N Leroy St",
    "sg:city":"Fenton",
    "sg:classifiers":[
        {
            "category":"Restaurant",
            "type":"Food & Drink"
        }
    ],
    "sg:phone":"+1 810 714 0351",
    "sg:postcode":"48430",
    "sg:province":"MI",
    "sg:tags":[
        "shop",
        "coffee"
    ],
    "wof:name":"Perky's Java & Juice",
    "wof:placetype":"venue"
},
  "geometry": {"coordinates":[-83.70759,42.8175],"type":"Point"}
}