{
  "type": "Feature",
  "properties": {
    "iso:country":"US",
    "sg:address":"5875 New King Ct",
    "sg:city":"Troy",
    "sg:classifiers":[
        {
            "category":"Manufacturing",
            "subcategory":"Chemicals & Compounds",
            "type":"Manufacturing & Wholesale Goods"
        }
    ],
    "sg:phone":"+1 248 641 2000",
    "sg:postcode":"48098",
    "sg:province":"MI",
    "sg:tags":[
        "paint",
        "varnish",
        "allied",
        "product"
    ],
    "sg:website":"www.ppg.com",
    "wof:name":"PPG Industries Inc",
    "wof:placetype":"venue"
},
  "geometry": {"coordinates":[-83.17198399999999,42.602888],"type":"Point"}
}