{
  "type": "Feature",
  "properties": {
    "iso:country":"US",
    "sg:address":"4060 Leonard St NE",
    "sg:city":"Grand Rapids",
    "sg:classifiers":[
        {
            "category":"Building & Trades",
            "subcategory":"Equipment Rental",
            "type":"Services"
        }
    ],
    "sg:phone":"+1 616 813 5374",
    "sg:postcode":"49525",
    "sg:province":"MI",
    "sg:tags":[
        "leasing"
    ],
    "wof:name":"Davco Capital & Leasing",
    "wof:placetype":"venue"
},
  "geometry": {"coordinates":[-85.574815,42.984468],"type":"Point"}
}