{
  "type": "Feature",
  "properties": {
    "iso:country":"US",
    "sg:address":"720 E Main St",
    "sg:city":"Benton Harbor",
    "sg:classifiers":[
        {
            "category":"Organizations",
            "subcategory":"Religious Organization",
            "type":"Services"
        }
    ],
    "sg:phone":"+1 269 926 9742",
    "sg:postcode":"49022",
    "sg:province":"MI",
    "wof:name":"Full Gospel Tabernacle",
    "wof:placetype":"venue"
},
  "geometry": {"coordinates":[-86.440862,42.117739],"type":"Point"}
}