{
  "type": "Feature",
  "properties": {
    "iso:country":"US",
    "sg:address":"19401 E 10 Mile Rd",
    "sg:city":"Roseville",
    "sg:classifiers":[
        {
            "category":"Restaurant",
            "type":"Food & Drink"
        }
    ],
    "sg:phone":"+1 586 777 4474",
    "sg:postcode":"48066",
    "sg:province":"MI",
    "wof:name":"Our Daily Bread Sub Shop",
    "wof:placetype":"venue"
},
  "geometry": {"coordinates":[-82.91996399999999,42.480457],"type":"Point"}
}