{
  "type": "Feature",
  "properties": {
    "iso:country":"US",
    "sg:address":"396 N State St",
    "sg:city":"St Ignace",
    "sg:classifiers":[
        {
            "category":"Government",
            "subcategory":"Office",
            "type":"Public Place"
        }
    ],
    "sg:phone":"+1 906 643 8131",
    "sg:postcode":"49781",
    "sg:province":"MI",
    "sg:tags":[
        "village"
    ],
    "wof:name":"St Ignace Marina",
    "wof:placetype":"venue"
},
  "geometry": {"coordinates":[-84.728065,45.868693],"type":"Point"}
}