{
  "type": "Feature",
  "properties": {
    "iso:country":"US",
    "sg:address":"1166 N Macomb St",
    "sg:city":"Monroe",
    "sg:classifiers":[
        {
            "category":"Real Estate",
            "subcategory":"Real Estate Operator",
            "type":"Services"
        }
    ],
    "sg:phone":"+1 734 243 6767",
    "sg:postcode":"48162",
    "sg:province":"MI",
    "sg:tags":[
        "owner",
        "apartment"
    ],
    "wof:name":"Charlotte Arms Apartments",
    "wof:placetype":"venue"
},
  "geometry": {"coordinates":[-83.38628199999999,41.930188],"type":"Point"}
}