{
  "type": "Feature",
  "properties": {
    "iso:country":"US",
    "sg:address":"2270 Union Lake Rd",
    "sg:city":"Commerce Twp",
    "sg:classifiers":[
        {
            "category":"Shopping",
            "subcategory":"Computers & Home Electronics",
            "type":"Retail Goods"
        }
    ],
    "sg:phone":"+1 248 360 5356",
    "sg:postcode":"48382",
    "sg:province":"MI",
    "sg:tags":[
        "equipment",
        "satellite",
        "system"
    ],
    "wof:name":"Satellite Receivers LTD",
    "wof:placetype":"venue"
},
  "geometry": {"coordinates":[-83.44660500000001,42.605102],"type":"Point"}
}