{
  "type": "Feature",
  "properties": {
    "iso:country":"US",
    "sg:address":"2505 Dexter Rd",
    "sg:city":"Ann Arbor",
    "sg:classifiers":[
        {
            "category":"Deli",
            "type":"Food & Drink"
        }
    ],
    "sg:menulink":"http://www.allmenus.com/mi/ann-arbor/260802-ahmos-gyros--deli/menu/",
    "sg:phone":"+1 734 998 4445",
    "sg:postcode":"48103",
    "sg:province":"MI",
    "sg:tags":[
        "pita",
        "american",
        "sandwich"
    ],
    "wof:name":"Ahmo's Gyros & Deli",
    "wof:placetype":"venue"
},
  "geometry": {"coordinates":[-83.78081,42.285403],"type":"Point"}
}