{
  "type": "Feature",
  "properties": {
    "iso:country":"US",
    "sg:address":"2411 Central St",
    "sg:city":"Detroit",
    "sg:classifiers":[
        {
            "category":"Food & Beverages",
            "subcategory":"Groceries & Convenience Stores",
            "type":"Retail Goods"
        }
    ],
    "sg:phone":"+1 313 843 0500",
    "sg:postcode":"48209",
    "sg:province":"MI",
    "wof:name":"Farmers Food Center",
    "wof:placetype":"venue"
},
  "geometry": {"coordinates":[-83.12522,42.313621],"type":"Point"}
}