{
  "type": "Feature",
  "properties": {
    "iso:country":"US",
    "sg:address":"918 Inkster Rd",
    "sg:city":"Dearborn Heights",
    "sg:classifiers":[
        {
            "category":"Building & Trades",
            "subcategory":"Landscaping Services",
            "type":"Services"
        }
    ],
    "sg:phone":"+1 313 562 0777",
    "sg:postcode":"48127",
    "sg:province":"MI",
    "sg:tags":[
        "landscape"
    ],
    "wof:name":"Ray Cole Landscape & Service",
    "wof:placetype":"venue"
},
  "geometry": {"coordinates":[-83.31107299999999,42.318414],"type":"Point"}
}