{
  "type": "Feature",
  "properties": {
    "iso:country":"US",
    "sg:address":"12074 N Genesee Rd",
    "sg:city":"Clio",
    "sg:classifiers":[
        {
            "category":"Manufacturing",
            "subcategory":"Metals",
            "type":"Manufacturing & Wholesale Goods"
        }
    ],
    "sg:phone":"+1 810 687 0740",
    "sg:postcode":"48420",
    "sg:province":"MI",
    "wof:name":"Hi-Vacs",
    "wof:placetype":"venue"
},
  "geometry": {"coordinates":[-83.62036999999999,43.185096],"type":"Point"}
}