{
  "type": "Feature",
  "properties": {
    "iso:country":"US",
    "sg:address":"812 Campbell Dr",
    "sg:city":"Owosso",
    "sg:classifiers":[
        {
            "category":"Professional",
            "subcategory":"Management & Consulting",
            "type":"Services"
        }
    ],
    "sg:phone":"+1 989 723 8008",
    "sg:postcode":"48867",
    "sg:province":"MI",
    "wof:name":"Keating Marketing Plus Inc",
    "wof:placetype":"venue"
},
  "geometry": {"coordinates":[-84.179385,43.008001],"type":"Point"}
}