{
  "type": "Feature",
  "properties": {
    "iso:country":"US",
    "sg:address":"8676 W W Ave",
    "sg:city":"Schoolcraft",
    "sg:classifiers":[
        {
            "category":"Manufacturing",
            "subcategory":"Tools & Machinery",
            "type":"Manufacturing & Wholesale Goods"
        }
    ],
    "sg:phone":"+1 269 679 3160",
    "sg:postcode":"49087",
    "sg:province":"MI",
    "sg:tags":[
        "devices",
        "mfg"
    ],
    "wof:name":"Swantech",
    "wof:placetype":"venue"
},
  "geometry": {"coordinates":[-85.71749699999999,42.113351],"type":"Point"}
}