{
  "type": "Feature",
  "properties": {
    "iso:country":"US",
    "sg:address":"400 E Division., Ste 3",
    "sg:city":"Rockford",
    "sg:classifiers":[
        {
            "category":"Personal",
            "subcategory":"Beauty Salon",
            "type":"Services"
        }
    ],
    "sg:phone":"+1 616 863 2887",
    "sg:postcode":"49341",
    "sg:province":"MI",
    "sg:tags":[
        "hair"
    ],
    "wof:name":"A Cut Ahead Salon Inc",
    "wof:placetype":"venue"
},
  "geometry": {"coordinates":[-85.550487,43.117392],"type":"Point"}
}