{
  "type": "Feature",
  "properties": {
    "iso:country":"US",
    "sg:address":"19500 S Mackinac Trl",
    "sg:city":"Rudyard",
    "sg:phone":"+1 906 478 3331",
    "sg:postcode":"49780",
    "sg:province":"MI",
    "sg:tags":[
        "farm",
        "field",
        "crop"
    ],
    "wof:name":"Ross Hay Co",
    "wof:placetype":"venue"
},
  "geometry": {"coordinates":[-84.592451,46.223663],"type":"Point"}
}