{
  "type": "Feature",
  "properties": {
    "iso:country":"US",
    "sg:address":"1955 Axtell Dr",
    "sg:city":"Troy",
    "sg:classifiers":[
        {
            "category":"Health Services",
            "subcategory":"Nursing And Care Facility",
            "type":"Services"
        }
    ],
    "sg:phone":"+1 248 458 1537",
    "sg:postcode":"48084",
    "sg:province":"MI",
    "sg:tags":[
        "hospice"
    ],
    "wof:name":"Brenda Spencer Hospice-Mi",
    "wof:placetype":"venue"
},
  "geometry": {"coordinates":[-83.18315,42.547996],"type":"Point"}
}