{
  "type": "Feature",
  "properties": {
    "iso:country":"US",
    "sg:address":"29555 Northwestern Hwy",
    "sg:city":"Southfield",
    "sg:classifiers":[
        {
            "category":"Restaurant",
            "type":"Food & Drink"
        }
    ],
    "sg:phone":"+1 248 355 1882",
    "sg:postcode":"48075",
    "sg:province":"MI",
    "sg:tags":[
        "japanese"
    ],
    "wof:name":"ISSA Japanese Kushi Restaurant",
    "wof:placetype":"venue"
},
  "geometry": {"coordinates":[-83.313481,42.503388],"type":"Point"}
}