{
  "type": "Feature",
  "properties": {
    "iso:country":"US",
    "sg:address":"414 Prospect Ave",
    "sg:city":"Alma",
    "sg:classifiers":[
        {
            "category":"Personal",
            "subcategory":"Beauty Salon",
            "type":"Services"
        }
    ],
    "sg:phone":"+1 989 463 5129",
    "sg:postcode":"48801",
    "sg:province":"MI",
    "sg:tags":[
        "shop"
    ],
    "wof:name":"Reflections Hairstyling Inc",
    "wof:placetype":"venue"
},
  "geometry": {"coordinates":[-84.663338,43.379977],"type":"Point"}
}