{
  "type": "Feature",
  "properties": {
    "iso:country":"US",
    "sg:address":"815 Maplegrove Ave",
    "sg:city":"Royal Oak",
    "sg:classifiers":[
        {
            "category":"Building & Trades",
            "subcategory":"Construction",
            "type":"Services"
        }
    ],
    "sg:phone":"+1 248 399 5436",
    "sg:postcode":"48067",
    "sg:province":"MI",
    "sg:tags":[
        "blind",
        "installation",
        "drapery",
        "contractor"
    ],
    "wof:name":"Installation Services",
    "wof:placetype":"venue"
},
  "geometry": {"coordinates":[-83.160605,42.495722],"type":"Point"}
}