{
  "type": "Feature",
  "properties": {
    "iso:country":"US",
    "sg:address":"23717 Kean St",
    "sg:city":"Dearborn",
    "sg:classifiers":[
        {
            "category":"Autos & Motor Vehicles",
            "subcategory":"Automobile Sales",
            "type":"Retail Goods"
        }
    ],
    "sg:phone":"+1 313 561 4400",
    "sg:postcode":"48124",
    "sg:province":"MI",
    "sg:tags":[
        "limo"
    ],
    "wof:name":"Black Tie Limousine Llc",
    "wof:placetype":"venue"
},
  "geometry": {"coordinates":[-83.267082,42.299606],"type":"Point"}
}