{
  "type": "Feature",
  "properties": {
    "iso:country":"US",
    "sg:address":"3918 W Saint Joseph Hwy",
    "sg:city":"Lansing",
    "sg:classifiers":[
        {
            "category":"Professional",
            "subcategory":"Employment Agencies",
            "type":"Services"
        }
    ],
    "sg:phone":"+1 517 886 4806",
    "sg:postcode":"48917",
    "sg:province":"MI",
    "sg:tags":[
        "opportunity"
    ],
    "sg:website":"www.gocss.com",
    "wof:name":"Css Health Force Inc",
    "wof:placetype":"venue"
},
  "geometry": {"coordinates":[-84.604039,42.72666],"type":"Point"}
}