{
  "type": "Feature",
  "properties": {
    "iso:country":"US",
    "sg:address":"25294 Sullivan Ln",
    "sg:city":"Novi",
    "sg:classifiers":[
        {
            "category":"Professional",
            "subcategory":"Engineering",
            "type":"Services"
        }
    ],
    "sg:phone":"+1 248 380 9301",
    "sg:postcode":"48375",
    "sg:province":"MI",
    "wof:name":"Peak Engineering Consultants",
    "wof:placetype":"venue"
},
  "geometry": {"coordinates":[-83.489581,42.476374],"type":"Point"}
}