{
  "type": "Feature",
  "properties": {
    "iso:country":"US",
    "sg:address":"1521 Blossom St SE",
    "sg:city":"Grand Rapids",
    "sg:classifiers":[
        {
            "category":"Retail",
            "subcategory":"Auto Repair",
            "type":"Services"
        }
    ],
    "sg:phone":"+1 616 281 5051",
    "sg:postcode":"49508",
    "sg:province":"MI",
    "sg:tags":[
        "automobile",
        "customizing"
    ],
    "wof:name":"Signature Soundz & Performance",
    "wof:placetype":"venue"
},
  "geometry": {"coordinates":[-85.62756,42.890516],"type":"Point"}
}