{
  "type": "Feature",
  "properties": {
    "iso:country":"US",
    "sg:address":"35475 S Gratiot Ave",
    "sg:city":"Clinton Township",
    "sg:classifiers":[
        {
            "category":"Restaurant",
            "type":"Food & Drink"
        }
    ],
    "sg:phone":"+1 586 792 9600",
    "sg:postcode":"48035",
    "sg:province":"MI",
    "sg:tags":[
        "chinese"
    ],
    "wof:name":"China Kitchen",
    "wof:placetype":"venue"
},
  "geometry": {"coordinates":[-82.898201,42.558201],"type":"Point"}
}