{
  "type": "Feature",
  "properties": {
    "iso:country":"US",
    "sg:address":"5943 Chase Rd",
    "sg:city":"Dearborn",
    "sg:classifiers":[
        {
            "category":"Manufacturing",
            "subcategory":"Tools & Machinery",
            "type":"Manufacturing & Wholesale Goods"
        }
    ],
    "sg:phone":"+1 313 846 8900",
    "sg:postcode":"48126",
    "sg:province":"MI",
    "sg:tags":[
        "control",
        "engineering",
        "mfg"
    ],
    "wof:name":"Kilo Process Control Systems",
    "wof:placetype":"venue"
},
  "geometry": {"coordinates":[-83.18612299999999,42.331613],"type":"Point"}
}