{
  "type": "Feature",
  "properties": {
    "iso:country":"US",
    "sg:address":"402 Center St",
    "sg:city":"Muskegon",
    "sg:classifiers":[
        {
            "category":"Personal",
            "subcategory":"Beauty Salon",
            "type":"Services"
        }
    ],
    "sg:phone":"+1 231 744 1732",
    "sg:postcode":"49445",
    "sg:province":"MI",
    "sg:tags":[
        "shop"
    ],
    "wof:name":"Designers Touch",
    "wof:placetype":"venue"
},
  "geometry": {"coordinates":[-86.26167100000001,43.262426],"type":"Point"}
}