{
  "type": "Feature",
  "properties": {
    "iso:country":"US",
    "sg:address":"812 S Main St",
    "sg:city":"Royal Oak",
    "sg:classifiers":[
        {
            "category":"Professional",
            "subcategory":"Lawyer & Legal Services",
            "type":"Services"
        }
    ],
    "sg:phone":"+1 248 543 1920",
    "sg:postcode":"48067",
    "sg:province":"MI",
    "wof:name":"Bereznoff Gregory M",
    "wof:placetype":"venue"
},
  "geometry": {"coordinates":[-83.144096,42.483398],"type":"Point"}
}