{
  "type": "Feature",
  "properties": {
    "iso:country":"US",
    "sg:address":"18457 Magnolia Ave",
    "sg:city":"Southfield",
    "sg:classifiers":[
        {
            "category":"Building & Trades",
            "subcategory":"Construction",
            "type":"Services"
        }
    ],
    "sg:phone":"+1 248 552 1036",
    "sg:postcode":"48075",
    "sg:province":"MI",
    "sg:tags":[
        "house"
    ],
    "wof:name":"Eames Const",
    "wof:placetype":"venue"
},
  "geometry": {"coordinates":[-83.224583,42.449691],"type":"Point"}
}