{
  "type": "Feature",
  "properties": {
    "iso:country":"US",
    "sg:address":"19331 Rainbow Dr",
    "sg:city":"Southfield",
    "sg:classifiers":[
        {
            "category":"Health Services",
            "subcategory":"Nursing And Care Facility",
            "type":"Services"
        }
    ],
    "sg:phone":"+1 248 569 8289",
    "sg:postcode":"48076",
    "sg:province":"MI",
    "wof:name":"Rainbow Home The",
    "wof:placetype":"venue"
},
  "geometry": {"coordinates":[-83.2364,42.491788],"type":"Point"}
}