{
  "type": "Feature",
  "properties": {
    "iso:country":"US",
    "sg:address":"119 N Edgeworth Ave",
    "sg:city":"Royal Oak",
    "sg:classifiers":[
        {
            "category":"Arts & Performance",
            "subcategory":"Theater",
            "type":"Entertainment"
        }
    ],
    "sg:phone":"+1 248 541 0250",
    "sg:postcode":"48067",
    "sg:province":"MI",
    "sg:tags":[
        "live",
        "music"
    ],
    "wof:name":"Boogie Brothers Game Shows",
    "wof:placetype":"venue"
},
  "geometry": {"coordinates":[-83.12033599999999,42.492474],"type":"Point"}
}