{
  "type": "Feature",
  "properties": {
    "iso:country":"US",
    "sg:address":"3035 N Connecticut Ave",
    "sg:city":"Royal Oak",
    "sg:classifiers":[
        {
            "category":"Professional",
            "subcategory":"Management & Consulting",
            "type":"Services"
        }
    ],
    "sg:phone":"+1 248 588 4630",
    "sg:postcode":"48073",
    "sg:province":"MI",
    "sg:tags":[
        "consultant"
    ],
    "wof:name":"MEW Consultants",
    "wof:placetype":"venue"
},
  "geometry": {"coordinates":[-83.12836799999999,42.515989],"type":"Point"}
}