{
  "type": "Feature",
  "properties": {
    "iso:country":"US",
    "sg:address":"1950 W Columbia Ave",
    "sg:city":"Battle Creek",
    "sg:classifiers":[
        {
            "category":"Retail",
            "subcategory":"Repair Shop",
            "type":"Services"
        }
    ],
    "sg:phone":"+1 269 962 7221",
    "sg:postcode":"49015",
    "sg:province":"MI",
    "sg:tags":[
        "cleaners",
        "vacuum"
    ],
    "wof:name":"Davis Sweeper and Supply Co",
    "wof:placetype":"venue"
},
  "geometry": {"coordinates":[-85.230615,42.297459],"type":"Point"}
}