{
  "type": "Feature",
  "properties": {
    "iso:country":"US",
    "sg:address":"9677 E Remus Rd",
    "sg:city":"Mount Pleasant",
    "sg:classifiers":[
        {
            "category":"Arts & Performance",
            "subcategory":"Theater",
            "type":"Entertainment"
        }
    ],
    "sg:phone":"+1 989 772 3691",
    "sg:postcode":"48858",
    "sg:province":"MI",
    "sg:tags":[
        "group"
    ],
    "wof:name":"Digital Knights Inc",
    "wof:placetype":"venue"
},
  "geometry": {"coordinates":[-84.660403,43.597319],"type":"Point"}
}