{
  "type": "Feature",
  "properties": {
    "iso:country":"US",
    "sg:address":"55647 Giddings Ct",
    "sg:city":"Mattawan",
    "sg:classifiers":[
        {
            "category":"Organizations",
            "subcategory":"Labor Organization",
            "type":"Services"
        }
    ],
    "sg:phone":"+1 269 668 2263",
    "sg:postcode":"49071",
    "sg:province":"MI",
    "wof:name":"Brotherhood of Maintenance",
    "wof:placetype":"venue"
},
  "geometry": {"coordinates":[-85.78792799999999,42.216238],"type":"Point"}
}