{
  "type": "Feature",
  "properties": {
    "iso:country":"US",
    "sg:address":"30540 Glenwood Cir",
    "sg:city":"Warren",
    "sg:classifiers":[
        {
            "category":"Health Services",
            "subcategory":"Clinic",
            "type":"Services"
        }
    ],
    "sg:phone":"+1 586 778 6414",
    "sg:postcode":"48088",
    "sg:province":"MI",
    "sg:tags":[
        "info",
        "optometrist",
        "referral"
    ],
    "wof:name":"Advanced Vision Svc",
    "wof:placetype":"venue"
},
  "geometry": {"coordinates":[-82.970941,42.521622],"type":"Point"}
}