{
  "type": "Feature",
  "properties": {
    "iso:country":"US",
    "sg:address":"21500 Northwestern Hwy Ste 340",
    "sg:city":"Southfield",
    "sg:classifiers":[
        {
            "category":"Shopping",
            "subcategory":"Jewelry",
            "type":"Retail Goods"
        }
    ],
    "sg:phone":"+1 248 423 6669",
    "sg:postcode":"48075",
    "sg:province":"MI",
    "wof:name":"Jewel Box the",
    "wof:placetype":"venue"
},
  "geometry": {"coordinates":[-83.207629,42.449622],"type":"Point"}
}