{
  "type": "Feature",
  "properties": {
    "iso:country":"US",
    "sg:address":"155 E Siena Heights Dr",
    "sg:city":"Adrian",
    "sg:classifiers":[
        {
            "category":"Social Services",
            "subcategory":"Child Care",
            "type":"Services"
        }
    ],
    "sg:phone":"+1 517 265 8979",
    "sg:postcode":"49221",
    "sg:province":"MI",
    "sg:tags":[
        "day"
    ],
    "wof:name":"Fannies Daycare",
    "wof:placetype":"venue"
},
  "geometry": {"coordinates":[-84.03044300000001,41.906785],"type":"Point"}
}