{
  "type": "Feature",
  "properties": {
    "iso:country":"US",
    "sg:address":"802 S Main St",
    "sg:city":"Cheboygan",
    "sg:classifiers":[
        {
            "category":"Health Services",
            "subcategory":"Doctor",
            "type":"Services"
        }
    ],
    "sg:phone":"+1 231 627 1493",
    "sg:postcode":"49721",
    "sg:province":"MI",
    "sg:tags":[
        "medical"
    ],
    "wof:name":"Thomas A Fasbender Do Ob/Gyn",
    "wof:placetype":"venue"
},
  "geometry": {"coordinates":[-84.479388,45.629534],"type":"Point"}
}