{
  "type": "Feature",
  "properties": {
    "iso:country":"US",
    "sg:address":"29670 Haggerty Rd",
    "sg:city":"Farmington",
    "sg:classifiers":[
        {
            "category":"Professional",
            "subcategory":"Advertising",
            "type":"Services"
        }
    ],
    "sg:phone":"+1 248 553 4566",
    "sg:postcode":"48331",
    "sg:province":"MI",
    "sg:tags":[
        "marketing",
        "communications"
    ],
    "wof:name":"Competition Graphics",
    "wof:placetype":"venue"
},
  "geometry": {"coordinates":[-83.436871,42.513143],"type":"Point"}
}