{
  "type": "Feature",
  "properties": {
    "iso:country":"US",
    "sg:address":"5301 Saginaw St",
    "sg:city":"Grand Blanc",
    "sg:classifiers":[
        {
            "category":"Sports & Exercise",
            "subcategory":"Bowling",
            "type":"Entertainment"
        }
    ],
    "sg:phone":"+1 810 742 7752",
    "sg:postcode":"48439",
    "sg:province":"MI",
    "wof:name":"Galaxy Bowling Center",
    "wof:placetype":"venue"
},
  "geometry": {"coordinates":[-83.66056,42.953862],"type":"Point"}
}