{
  "type": "Feature",
  "properties": {
    "iso:country":"US",
    "sg:address":"20500 Eureka Rd Ste 107",
    "sg:city":"Taylor",
    "sg:classifiers":[
        {
            "category":"Professional",
            "subcategory":"Lawyer & Legal Services",
            "type":"Services"
        }
    ],
    "sg:phone":"+1 734 246 7128",
    "sg:postcode":"48180",
    "sg:province":"MI",
    "wof:name":"Zamler Mellen & Shiffman PC",
    "wof:placetype":"venue"
},
  "geometry": {"coordinates":[-83.23490099999999,42.198399],"type":"Point"}
}