{
  "type": "Feature",
  "properties": {
    "iso:country":"US",
    "sg:address":"7509 E Burnside Rd",
    "sg:city":"Brown City",
    "sg:classifiers":[
        {
            "category":"Autos & Motor Vehicles",
            "subcategory":"Automobile Sales",
            "type":"Retail Goods"
        }
    ],
    "sg:phone":"+1 810 346 2971",
    "sg:postcode":"48416",
    "sg:province":"MI",
    "sg:tags":[
        "car",
        "used",
        "parts"
    ],
    "wof:name":"M-90 Used Cars",
    "wof:placetype":"venue"
},
  "geometry": {"coordinates":[-83.051524,43.211242],"type":"Point"}
}