{
  "type": "Feature",
  "properties": {
    "iso:country":"US",
    "sg:address":"2304 E 11 Mile Rd",
    "sg:city":"Royal Oak",
    "sg:classifiers":[
        {
            "category":"Professional",
            "subcategory":"Lawyer & Legal Services",
            "type":"Services"
        }
    ],
    "sg:phone":"+1 248 541 3400",
    "sg:postcode":"48067",
    "sg:province":"MI",
    "wof:name":"Melder Sanford J",
    "wof:placetype":"venue"
},
  "geometry": {"coordinates":[-83.11750000000001,42.490398],"type":"Point"}
}