{
  "type": "Feature",
  "properties": {
    "iso:country":"US",
    "sg:address":"24301 Telegraph Rd",
    "sg:city":"Southfield",
    "sg:classifiers":[
        {
            "category":"Health Services",
            "subcategory":"Clinic",
            "type":"Services"
        }
    ],
    "sg:phone":"+1 248 354 2127",
    "sg:postcode":"48033",
    "sg:province":"MI",
    "sg:tags":[
        "home"
    ],
    "wof:name":"Homes Services & Stafafing Grp",
    "wof:placetype":"venue"
},
  "geometry": {"coordinates":[-83.281942,42.4719],"type":"Point"}
}