{
  "type": "Feature",
  "properties": {
    "iso:country":"US",
    "sg:address":"918 Inkster Rd",
    "sg:city":"Dearborn Heights",
    "sg:classifiers":[
        {
            "category":"Professional",
            "subcategory":"Detective & Security Services",
            "type":"Services"
        }
    ],
    "sg:phone":"+1 734 502 1884",
    "sg:postcode":"48127",
    "sg:province":"MI",
    "sg:tags":[
        "personal",
        "protection"
    ],
    "wof:name":"Ronin Worldwide Executive Prot",
    "wof:placetype":"venue"
},
  "geometry": {"coordinates":[-83.31107299999999,42.318414],"type":"Point"}
}