{
  "type": "Feature",
  "properties": {
    "iso:country":"US",
    "sg:address":"32123 Gratiot Ave",
    "sg:city":"Roseville",
    "sg:classifiers":[
        {
            "category":"Personal",
            "subcategory":"Beauty Salon",
            "type":"Services"
        }
    ],
    "sg:phone":"+1 586 296 2590",
    "sg:postcode":"48066",
    "sg:province":"MI",
    "sg:tags":[
        "shop"
    ],
    "wof:name":"Premier Salon 22653",
    "wof:placetype":"venue"
},
  "geometry": {"coordinates":[-82.912285,42.534932],"type":"Point"}
}