{
  "type": "Feature",
  "properties": {
    "iso:country":"US",
    "sg:address":"4275 Airwest Dr SE",
    "sg:city":"Kentwood",
    "sg:classifiers":[
        {
            "category":"Manufacturing",
            "subcategory":"Motor Vehicles & Parts",
            "type":"Manufacturing & Wholesale Goods"
        }
    ],
    "sg:phone":"+1 616 554 7888",
    "sg:postcode":"49512",
    "sg:province":"MI",
    "sg:tags":[
        "automobile",
        "supply"
    ],
    "wof:name":"Lacks Enterprises Inc",
    "wof:placetype":"venue"
},
  "geometry": {"coordinates":[-85.571473,42.884524],"type":"Point"}
}