{
  "type": "Feature",
  "properties": {
    "iso:country":"US",
    "sg:address":"9315 Hillcrest",
    "sg:city":"Clarkston",
    "sg:classifiers":[
        {
            "category":"Freight",
            "type":"Transportation"
        }
    ],
    "sg:phone":"+1 248 625 3632",
    "sg:postcode":"48348",
    "sg:province":"MI",
    "sg:tags":[
        "trucking"
    ],
    "sg:website":"www.getransport.com",
    "wof:name":"G & E Transport",
    "wof:placetype":"venue"
},
  "geometry": {"coordinates":[-83.471254,42.749448],"type":"Point"}
}