{
  "type": "Feature",
  "properties": {
    "iso:country":"US",
    "sg:address":"133 E State Rd",
    "sg:city":"West Branch",
    "sg:classifiers":[
        {
            "category":"Personal",
            "subcategory":"Beauty Salon",
            "type":"Services"
        }
    ],
    "sg:phone":"+1 989 345 0847",
    "sg:postcode":"48661",
    "sg:province":"MI",
    "sg:tags":[
        "shop"
    ],
    "wof:name":"Lady Gay Salon",
    "wof:placetype":"venue"
},
  "geometry": {"coordinates":[-84.110634,44.313097],"type":"Point"}
}