{
  "type": "Feature",
  "properties": {
    "iso:country":"US",
    "sg:address":"33216 Grand River Ave",
    "sg:city":"Farmington",
    "sg:classifiers":[
        {
            "category":"Shopping",
            "subcategory":"Jewelry",
            "type":"Retail Goods"
        }
    ],
    "sg:phone":"+1 248 471 1113",
    "sg:postcode":"48336",
    "sg:province":"MI",
    "wof:name":"United Jewelers Inc",
    "wof:placetype":"venue"
},
  "geometry": {"coordinates":[-83.374702,42.464298],"type":"Point"}
}