{
  "type": "Feature",
  "properties": {
    "iso:country":"US",
    "sg:address":"14114 Brethren Hwy",
    "sg:city":"Brethren",
    "sg:classifiers":[
        {
            "category":"Organizations",
            "subcategory":"Religious Organization",
            "type":"Services"
        }
    ],
    "sg:phone":"+1 231 477 5486",
    "sg:postcode":"49619",
    "sg:province":"MI",
    "wof:name":"Epworth United Methodist",
    "wof:placetype":"venue"
},
  "geometry": {"coordinates":[-86.019549,44.304377],"type":"Point"}
}