{
  "type": "Feature",
  "properties": {
    "iso:country":"US",
    "sg:address":"6535 Evergreen St",
    "sg:city":"Portage",
    "sg:classifiers":[
        {
            "category":"Professional",
            "subcategory":"Printing & Photocopies",
            "type":"Services"
        }
    ],
    "sg:phone":"+1 269 327 6155",
    "sg:postcode":"49024",
    "sg:province":"MI",
    "sg:tags":[
        "copy",
        "center"
    ],
    "wof:name":"Copy Desk",
    "wof:placetype":"venue"
},
  "geometry": {"coordinates":[-85.619325,42.220233],"type":"Point"}
}