{
  "type": "Feature",
  "properties": {
    "iso:country":"US",
    "sg:address":"1157 Pine Rd",
    "sg:city":"Alpena",
    "sg:classifiers":[
        {
            "category":"Social Services",
            "subcategory":"Child Care",
            "type":"Services"
        }
    ],
    "sg:phone":"+1 989 354 8958",
    "sg:postcode":"49707",
    "sg:province":"MI",
    "sg:tags":[
        "day"
    ],
    "wof:name":"Szymanski Day Care Services",
    "wof:placetype":"venue"
},
  "geometry": {"coordinates":[-83.464446,45.029182],"type":"Point"}
}