{
  "type": "Feature",
  "properties": {
    "iso:country":"US",
    "sg:address":"1305 Gratiot Blvd",
    "sg:city":"Marysville",
    "sg:classifiers":[
        {
            "category":"Personal",
            "subcategory":"Beauty Salon",
            "type":"Services"
        }
    ],
    "sg:phone":"+1 810 364 5344",
    "sg:postcode":"48040",
    "sg:province":"MI",
    "wof:name":"Styles By J & S",
    "wof:placetype":"venue"
},
  "geometry": {"coordinates":[-82.475115,42.920575],"type":"Point"}
}