{
  "type": "Feature",
  "properties": {
    "iso:country":"US",
    "sg:address":"32805 Northwestern Hwy",
    "sg:city":"Farmington Hills",
    "sg:classifiers":[
        {
            "category":"Retail",
            "subcategory":"Auto Rental",
            "type":"Services"
        }
    ],
    "sg:phone":"+1 248 865 8647",
    "sg:postcode":"48334",
    "sg:province":"MI",
    "sg:tags":[
        "car"
    ],
    "sg:website":"www.enterprise.com",
    "wof:name":"Enterprise Rent-A-Car",
    "wof:placetype":"venue"
},
  "geometry": {"coordinates":[-83.355023,42.526723],"type":"Point"}
}