{
  "type": "Feature",
  "properties": {
    "iso:country":"US",
    "sg:address":"4179 Flamingo Ave SW",
    "sg:city":"Grand Rapids",
    "sg:classifiers":[
        {
            "category":"Professional",
            "subcategory":"Business Services",
            "type":"Services"
        }
    ],
    "sg:phone":"+1 616 249 8554",
    "sg:postcode":"49509",
    "sg:province":"MI",
    "wof:name":"CT Las Express",
    "wof:placetype":"venue"
},
  "geometry": {"coordinates":[-85.696556,42.891206],"type":"Point"}
}