{
  "type": "Feature",
  "properties": {
    "iso:country":"US",
    "sg:address":"5200 W River Dr NE",
    "sg:city":"Comstock Park",
    "sg:classifiers":[
        {
            "category":"Manufacturing",
            "subcategory":"Tools & Machinery",
            "type":"Manufacturing & Wholesale Goods"
        }
    ],
    "sg:phone":"+1 616 784 6868",
    "sg:postcode":"49321",
    "sg:province":"MI",
    "sg:tags":[
        "machine",
        "shop"
    ],
    "wof:name":"RNB Machine & Tool Inc",
    "wof:placetype":"venue"
},
  "geometry": {"coordinates":[-85.642675,43.057756],"type":"Point"}
}