{
  "type": "Feature",
  "properties": {
    "iso:country":"US",
    "sg:address":"49088 Jefferson Ave",
    "sg:city":"Chesterfield",
    "sg:classifiers":[
        {
            "category":"Autos & Motor Vehicles",
            "subcategory":"Boat Sales",
            "type":"Retail Goods"
        }
    ],
    "sg:phone":"+1 586 716 3960",
    "sg:postcode":"48047",
    "sg:province":"MI",
    "sg:tags":[
        "top",
        "upholstery",
        "cover"
    ],
    "wof:name":"Raber's Canvass & Cushions",
    "wof:placetype":"venue"
},
  "geometry": {"coordinates":[-82.782005,42.65768],"type":"Point"}
}