{
  "type": "Feature",
  "properties": {
    "iso:country":"US",
    "sg:address":"42550 Garfield Rd",
    "sg:city":"Clinton Township",
    "sg:classifiers":[
        {
            "category":"Health Services",
            "subcategory":"Podiatrist",
            "type":"Services"
        }
    ],
    "sg:phone":"+1 586 263 4270",
    "sg:postcode":"48038",
    "sg:province":"MI",
    "wof:name":"Hosey Thomas C DPM PC",
    "wof:placetype":"venue"
},
  "geometry": {"coordinates":[-82.95274000000001,42.609557],"type":"Point"}
}