{
  "type": "Feature",
  "properties": {
    "iso:country":"US",
    "sg:address":"943 W Polk Rd",
    "sg:city":"Hart",
    "sg:classifiers":[
        {
            "category":"Retail",
            "subcategory":"Auto Repair",
            "type":"Services"
        }
    ],
    "sg:phone":"+1 231 873 4868",
    "sg:postcode":"49420",
    "sg:province":"MI",
    "sg:tags":[
        "towing",
        "wrecker"
    ],
    "wof:name":"McGhans Towing",
    "wof:placetype":"venue"
},
  "geometry": {"coordinates":[-86.30140299999999,43.687211],"type":"Point"}
}