{
  "type": "Feature",
  "properties": {
    "iso:country":"US",
    "sg:address":"17910 Van Dyke St",
    "sg:city":"Detroit",
    "sg:classifiers":[
        {
            "category":"Social Services",
            "subcategory":"Job Training",
            "type":"Services"
        }
    ],
    "sg:phone":"+1 313 368 5200",
    "sg:postcode":"48234",
    "sg:province":"MI",
    "wof:name":"Services To Enhance Potentials",
    "wof:placetype":"venue"
},
  "geometry": {"coordinates":[-83.02390699999999,42.426656],"type":"Point"}
}