{
  "type": "Feature",
  "properties": {
    "iso:country":"US",
    "sg:address":"7483 N Seymour Rd",
    "sg:city":"Flushing",
    "sg:classifiers":[
        {
            "category":"Building & Trades",
            "subcategory":"Cleaning & Sanitation",
            "type":"Services"
        }
    ],
    "sg:phone":"+1 810 659 6673",
    "sg:postcode":"48433",
    "sg:province":"MI",
    "sg:tags":[
        "maintenance"
    ],
    "wof:name":"A1 Commercial Cleaning",
    "wof:placetype":"venue"
},
  "geometry": {"coordinates":[-83.87285,43.117232],"type":"Point"}
}