{
  "type": "Feature",
  "properties": {
    "iso:country":"US",
    "sg:address":"237 N River Rd",
    "sg:city":"Mount Clemens",
    "sg:classifiers":[
        {
            "category":"Cinema",
            "subcategory":"Movie Rental",
            "type":"Entertainment"
        }
    ],
    "sg:phone":"+1 586 307 3776",
    "sg:postcode":"48043",
    "sg:province":"MI",
    "sg:tags":[
        "game",
        "video"
    ],
    "wof:name":"Game Punk Inc",
    "wof:placetype":"venue"
},
  "geometry": {"coordinates":[-82.86246199999999,42.597882],"type":"Point"}
}