{
  "type": "Feature",
  "properties": {
    "iso:country":"US",
    "sg:address":"704 N Saginaw St",
    "sg:city":"Saint Charles",
    "sg:classifiers":[
        {
            "category":"Social Services",
            "subcategory":"Child Care",
            "type":"Services"
        }
    ],
    "sg:phone":"+1 989 865 6325",
    "sg:postcode":"48655",
    "sg:province":"MI",
    "sg:tags":[
        "day"
    ],
    "wof:name":"Profector Cleaning",
    "wof:placetype":"venue"
},
  "geometry": {"coordinates":[-84.143815,43.301965],"type":"Point"}
}