{
  "type": "Feature",
  "properties": {
    "iso:country":"US",
    "sg:address":"1800 Paw Paw Ave",
    "sg:city":"Benton Harbor",
    "sg:classifiers":[
        {
            "category":"Professional",
            "type":"Services"
        }
    ],
    "sg:phone":"+1 269 923 7400",
    "sg:postcode":"49022",
    "sg:province":"MI",
    "sg:tags":[
        "establishment"
    ],
    "wof:name":"Center For Partner Dev",
    "wof:placetype":"venue"
},
  "geometry": {"coordinates":[-86.437251,42.146649],"type":"Point"}
}