{
  "type": "Feature",
  "properties": {
    "iso:country":"US",
    "sg:address":"20524 W Warren Ave",
    "sg:city":"Detroit",
    "sg:classifiers":[
        {
            "category":"Health Services",
            "subcategory":"Doctor",
            "type":"Services"
        }
    ],
    "sg:phone":"+1 313 271 6660",
    "sg:postcode":"48228",
    "sg:province":"MI",
    "wof:name":"Jboor Nidal MD",
    "wof:placetype":"venue"
},
  "geometry": {"coordinates":[-83.24046,42.343172],"type":"Point"}
}