{
  "type": "Feature",
  "properties": {
    "iso:country":"US",
    "sg:address":"7271 W Bay Shore Dr",
    "sg:city":"Northport",
    "sg:classifiers":[
        {
            "category":"Farming",
            "subcategory":"Orchard",
            "type":"Manufacturing & Wholesale Goods"
        }
    ],
    "sg:phone":"+1 231 386 5104",
    "sg:postcode":"49670",
    "sg:province":"MI",
    "sg:tags":[
        "fruit",
        "tree"
    ],
    "wof:name":"Mitco Cherry Farm",
    "wof:placetype":"venue"
},
  "geometry": {"coordinates":[-85.603471,45.090766],"type":"Point"}
}