{
  "type": "Feature",
  "properties": {
    "iso:country":"US",
    "sg:address":"1155 Pintail Way Cir",
    "sg:city":"Sanford",
    "sg:classifiers":[
        {
            "category":"Banks & Credit Unions",
            "subcategory":"Investment Brokerage",
            "type":"Services"
        }
    ],
    "sg:phone":"+1 989 687 5513",
    "sg:postcode":"48657",
    "sg:province":"MI",
    "sg:tags":[
        "advisory",
        "financial"
    ],
    "wof:name":"Nash Investments",
    "wof:placetype":"venue"
},
  "geometry": {"coordinates":[-84.324179,43.661231],"type":"Point"}
}