{
  "type": "Feature",
  "properties": {
    "iso:country":"US",
    "sg:address":"24595 Groesbeck Hwy",
    "sg:city":"Warren",
    "sg:classifiers":[
        {
            "category":"Real Estate",
            "subcategory":"Real Estate Agent",
            "type":"Services"
        }
    ],
    "sg:phone":"+1 586 775 8206",
    "sg:postcode":"48089",
    "sg:province":"MI",
    "sg:tags":[
        "finding",
        "apartment",
        "rental"
    ],
    "wof:name":"Nalco Management Inc",
    "wof:placetype":"venue"
},
  "geometry": {"coordinates":[-82.98273500000001,42.474901],"type":"Point"}
}