{
  "type": "Feature",
  "properties": {
    "iso:country":"US",
    "sg:address":"1444 Gratiot Blvd",
    "sg:city":"Marysville",
    "sg:classifiers":[
        {
            "category":"Wholesale",
            "subcategory":"Construction Materials",
            "type":"Manufacturing & Wholesale Goods"
        }
    ],
    "sg:phone":"+1 810 364 7132",
    "sg:postcode":"48040",
    "sg:province":"MI",
    "sg:tags":[
        "brick",
        "common",
        "face"
    ],
    "wof:name":"Theut Products",
    "wof:placetype":"venue"
},
  "geometry": {"coordinates":[-82.476749,42.920061],"type":"Point"}
}