{
  "type": "Feature",
  "properties": {
    "iso:country":"US",
    "sg:address":"1030 Decker Rd",
    "sg:city":"Walled Lake",
    "sg:classifiers":[
        {
            "category":"Retail",
            "subcategory":"Auto Repair",
            "type":"Services"
        }
    ],
    "sg:phone":"+1 248 926 9373",
    "sg:postcode":"48390",
    "sg:province":"MI",
    "sg:tags":[
        "body",
        "automobile",
        "painting"
    ],
    "wof:name":"GEB Collision Inc",
    "wof:placetype":"venue"
},
  "geometry": {"coordinates":[-83.467876,42.540132],"type":"Point"}
}