{
  "type": "Feature",
  "properties": {
    "iso:country":"US",
    "sg:address":"6698 W Houghton Lake Dr",
    "sg:city":"Houghton Lake",
    "sg:classifiers":[
        {
            "category":"Travel",
            "subcategory":"Hotels & Motels",
            "type":"Entertainment"
        }
    ],
    "sg:phone":"+1 989 422 3641",
    "sg:postcode":"48629",
    "sg:province":"MI",
    "sg:tags":[
        "operation"
    ],
    "wof:name":"Stowell Lake Wood Motel",
    "wof:placetype":"venue"
},
  "geometry": {"coordinates":[-84.764881,44.314989],"type":"Point"}
}