{
  "type": "Feature",
  "properties": {
    "iso:country":"US",
    "sg:address":"204 State Ave",
    "sg:city":"Baraga",
    "sg:classifiers":[
        {
            "category":"Professional",
            "subcategory":"Business Services",
            "type":"Services"
        }
    ],
    "sg:phone":"+1 906 353 7411",
    "sg:postcode":"49908",
    "sg:province":"MI",
    "wof:name":"Superior Spectrum",
    "wof:placetype":"venue"
},
  "geometry": {"coordinates":[-88.49210600000001,46.779076],"type":"Point"}
}