{
  "type": "Feature",
  "properties": {
    "iso:country":"US",
    "sg:address":"3909 Dwight Dr",
    "sg:city":"Warren",
    "sg:classifiers":[
        {
            "category":"Professional",
            "subcategory":"Computer Services",
            "type":"Services"
        }
    ],
    "sg:phone":"+1 586 573 3991",
    "sg:postcode":"48092",
    "sg:province":"MI",
    "sg:tags":[
        "datum"
    ],
    "wof:name":"Entry Solutions Inc",
    "wof:placetype":"venue"
},
  "geometry": {"coordinates":[-83.0677,42.493519],"type":"Point"}
}