{
  "type": "Feature",
  "properties": {
    "iso:country":"US",
    "sg:address":"5610 N Sundell Rd",
    "sg:city":"Skandia",
    "sg:classifiers":[
        {
            "category":"Shopping",
            "subcategory":"Hobbies, Toys, & Games",
            "type":"Retail Goods"
        }
    ],
    "sg:phone":"+1 906 439 5225",
    "sg:postcode":"49885",
    "sg:province":"MI",
    "wof:name":"Samples of Country",
    "wof:placetype":"venue"
},
  "geometry": {"coordinates":[-87.08505599999999,46.365504],"type":"Point"}
}