{
  "type": "Feature",
  "properties": {
    "iso:country":"US",
    "sg:address":"8306 E 12 Mile Rd",
    "sg:city":"Warren",
    "sg:classifiers":[
        {
            "category":"Health Services",
            "subcategory":"Podiatrist",
            "type":"Services"
        }
    ],
    "sg:phone":"+1 586 573 4880",
    "sg:postcode":"48093",
    "sg:province":"MI",
    "sg:tags":[
        "medicine",
        "sport"
    ],
    "wof:name":"Silver Joseph E DPM PC",
    "wof:placetype":"venue"
},
  "geometry": {"coordinates":[-83.02419999999999,42.5065],"type":"Point"}
}