{
  "type": "Feature",
  "properties": {
    "iso:country":"US",
    "sg:address":"10321 Grand River Rd",
    "sg:city":"Brighton",
    "sg:classifiers":[
        {
            "category":"Government",
            "subcategory":"Office",
            "type":"Public Place"
        }
    ],
    "sg:phone":"+1 810 227 4681",
    "sg:postcode":"48116",
    "sg:province":"MI",
    "sg:tags":[
        "state",
        "program"
    ],
    "sg:website":"www.michigan.gov",
    "wof:name":"Transportation Dept",
    "wof:placetype":"venue"
},
  "geometry": {"coordinates":[-83.751352,42.519326],"type":"Point"}
}