{
  "type": "Feature",
  "properties": {
    "iso:country":"US",
    "sg:address":"8825 Robson St",
    "sg:city":"Detroit",
    "sg:classifiers":[
        {
            "category":"Real Estate",
            "subcategory":"Real Estate Operator",
            "type":"Services"
        }
    ],
    "sg:phone":"+1 313 272 3632",
    "sg:postcode":"48228",
    "sg:province":"MI",
    "sg:tags":[
        "building",
        "apartment"
    ],
    "wof:name":"Vernor J & Fannie W Jacob",
    "wof:placetype":"venue"
},
  "geometry": {"coordinates":[-83.191743,42.360362],"type":"Point"}
}