{
  "type": "Feature",
  "properties": {
    "iso:country":"US",
    "sg:address":"6625 Dyke Rd",
    "sg:city":"Clay",
    "sg:classifiers":[
        {
            "category":"Real Estate",
            "subcategory":"Real Estate Agent",
            "type":"Services"
        }
    ],
    "sg:phone":"+1 810 794 3150",
    "sg:postcode":"48001",
    "sg:province":"MI",
    "wof:name":"Isles Realty",
    "wof:placetype":"venue"
},
  "geometry": {"coordinates":[-82.618846,42.653797],"type":"Point"}
}