{
  "type": "Feature",
  "properties": {
    "iso:country":"US",
    "sg:address":"999 Republic Dr",
    "sg:city":"Allen Park",
    "sg:classifiers":[
        {
            "category":"Retail",
            "subcategory":"Auto Repair",
            "type":"Services"
        }
    ],
    "sg:phone":"+1 313 749 1030",
    "sg:postcode":"48101",
    "sg:province":"MI",
    "wof:name":"Meridian Automative Services",
    "wof:placetype":"venue"
},
  "geometry": {"coordinates":[-83.19961499999999,42.298172],"type":"Point"}
}