{
  "type": "Feature",
  "properties": {
    "iso:country":"US",
    "sg:address":"22950 Hall Rd",
    "sg:city":"Clinton Twp",
    "sg:classifiers":[
        {
            "category":"Retail",
            "subcategory":"Auto Repair",
            "type":"Services"
        }
    ],
    "sg:phone":"+1 586 463 1431",
    "sg:postcode":"48036",
    "sg:province":"MI",
    "sg:tags":[
        "automobile",
        "lubrication"
    ],
    "sg:website":"www.afautowash.com",
    "wof:name":"Valvoline Express Care",
    "wof:placetype":"venue"
},
  "geometry": {"coordinates":[-82.881051,42.629013],"type":"Point"}
}