{
  "type": "Feature",
  "properties": {
    "iso:country":"US",
    "sg:address":"6390 Deans Hill Rd",
    "sg:city":"Berrien Center",
    "sg:classifiers":[
        {
            "category":"Health Services",
            "subcategory":"Doctor",
            "type":"Services"
        }
    ],
    "sg:phone":"+1 269 471 1496",
    "sg:postcode":"49102",
    "sg:province":"MI",
    "sg:tags":[
        "medical"
    ],
    "wof:name":"Froggart John W III MD",
    "wof:placetype":"venue"
},
  "geometry": {"coordinates":[-86.30483099999999,41.957164],"type":"Point"}
}