{
  "type": "Feature",
  "properties": {
    "iso:country":"US",
    "sg:address":"621 Main St",
    "sg:city":"East Jordan",
    "sg:classifiers":[
        {
            "category":"Retail",
            "subcategory":"Funeral Services",
            "type":"Services"
        }
    ],
    "sg:phone":"+1 231 536 7031",
    "sg:postcode":"49727",
    "sg:province":"MI",
    "sg:tags":[
        "director"
    ],
    "wof:name":"Penzien Funeral Homes Inc",
    "wof:placetype":"venue"
},
  "geometry": {"coordinates":[-85.12715300000001,45.161184],"type":"Point"}
}