{
  "type": "Feature",
  "properties": {
    "iso:country":"US",
    "sg:address":"28600 Grand River Ave",
    "sg:city":"Farmington Hills",
    "sg:classifiers":[
        {
            "category":"Freight",
            "type":"Transportation"
        }
    ],
    "sg:phone":"+1 248 473 9303",
    "sg:postcode":"48336",
    "sg:province":"MI",
    "sg:tags":[
        "commercial",
        "storage"
    ],
    "wof:name":"Shurgard Storage Ctr",
    "wof:placetype":"venue"
},
  "geometry": {"coordinates":[-83.328868,42.445315],"type":"Point"}
}