{
  "type": "Feature",
  "properties": {
    "iso:country":"US",
    "sg:address":"6059 Bay Rd",
    "sg:city":"Saginaw",
    "sg:classifiers":[
        {
            "category":"Autos & Motor Vehicles",
            "subcategory":"Automobile Sales",
            "type":"Retail Goods"
        }
    ],
    "sg:phone":"+1 989 797 0311",
    "sg:postcode":"48604",
    "sg:province":"MI",
    "sg:tags":[
        "car",
        "dealer"
    ],
    "wof:name":"Bay Cars",
    "wof:placetype":"venue"
},
  "geometry": {"coordinates":[-83.973444,43.496207],"type":"Point"}
}