{
  "type": "Feature",
  "properties": {
    "iso:country":"US",
    "sg:address":"4318 Gratiot Ave",
    "sg:city":"Port Huron",
    "sg:classifiers":[
        {
            "category":"Professional",
            "subcategory":"Detective & Security Services",
            "type":"Services"
        }
    ],
    "sg:phone":"+1 810 385 7544",
    "sg:postcode":"48060",
    "sg:province":"MI",
    "wof:name":"Lakeshore Investigations Inc",
    "wof:placetype":"venue"
},
  "geometry": {"coordinates":[-82.44249000000001,43.035612],"type":"Point"}
}