{
  "type": "Feature",
  "properties": {
    "iso:country":"US",
    "sg:address":"524 E William St",
    "sg:city":"Ann Arbor",
    "sg:classifiers":[
        {
            "category":"Personal",
            "subcategory":"Barber",
            "type":"Services"
        }
    ],
    "sg:phone":"+1 734 741 0869",
    "sg:postcode":"48104",
    "sg:province":"MI",
    "sg:tags":[
        "shop",
        "beauty"
    ],
    "wof:name":"Campus Barber & Beauty Salon",
    "wof:placetype":"venue"
},
  "geometry": {"coordinates":[-83.742193,42.277778],"type":"Point"}
}