{
  "type": "Feature",
  "properties": {
    "iso:country":"US",
    "sg:address":"26 Peterboro St",
    "sg:city":"Detroit",
    "sg:classifiers":[
        {
            "category":"Social Services",
            "type":"Services"
        }
    ],
    "sg:phone":"+1 313 831 3777",
    "sg:postcode":"48201",
    "sg:province":"MI",
    "wof:name":"Cots",
    "wof:placetype":"venue"
},
  "geometry": {"coordinates":[-83.05825900000001,42.344843],"type":"Point"}
}