{
  "type": "Feature",
  "properties": {
    "iso:country":"US",
    "sg:address":"1960 Crystal Lake Ct W",
    "sg:city":"Shelby Twp",
    "sg:classifiers":[
        {
            "category":"Professional",
            "subcategory":"Computer Services",
            "type":"Services"
        }
    ],
    "sg:phone":"+1 248 229 0593",
    "sg:postcode":"48316",
    "sg:province":"MI",
    "sg:tags":[
        "hardware",
        "provider",
        "internet",
        "software"
    ],
    "wof:name":"1st Place Cyber Space",
    "wof:placetype":"venue"
},
  "geometry": {"coordinates":[-83.09299300000001,42.676321],"type":"Point"}
}