{
  "type": "Feature",
  "properties": {
    "iso:country":"US",
    "sg:address":"57365 M 51 S",
    "sg:city":"Dowagiac",
    "sg:classifiers":[
        {
            "category":"Health Services",
            "subcategory":"Chiropractor",
            "type":"Services"
        }
    ],
    "sg:phone":"+1 269 782 3855",
    "sg:postcode":"49047",
    "sg:province":"MI",
    "wof:name":"Mc Canse Chiropractic",
    "wof:placetype":"venue"
},
  "geometry": {"coordinates":[-86.139326,41.969055],"type":"Point"}
}