{
  "type": "Feature",
  "properties": {
    "iso:country":"US",
    "sg:address":"1655 Hallmark Dr",
    "sg:city":"Troy",
    "sg:classifiers":[
        {
            "category":"Professional",
            "type":"Services"
        }
    ],
    "sg:phone":"+1 248 641 7459",
    "sg:postcode":"48098",
    "sg:province":"MI",
    "wof:name":"Prep Services",
    "wof:placetype":"venue"
},
  "geometry": {"coordinates":[-83.18123,42.582753],"type":"Point"}
}