{
  "type": "Feature",
  "properties": {
    "iso:country":"US",
    "sg:address":"6180 Murray Rd",
    "sg:city":"Whitehall",
    "sg:classifiers":[
        {
            "category":"Travel",
            "subcategory":"Hotels & Motels",
            "type":"Entertainment"
        }
    ],
    "sg:phone":"+1 231 893 7035",
    "sg:postcode":"49461",
    "sg:province":"MI",
    "sg:tags":[
        "lodge"
    ],
    "wof:name":"Driftwood Resort",
    "wof:placetype":"venue"
},
  "geometry": {"coordinates":[-86.422938,43.374365],"type":"Point"}
}