{
  "type": "Feature",
  "properties": {
    "iso:country":"US",
    "sg:address":"20 S Main St",
    "sg:city":"Yale",
    "sg:classifiers":[
        {
            "category":"Autos & Motor Vehicles",
            "subcategory":"Auto Supplies",
            "type":"Retail Goods"
        }
    ],
    "sg:phone":"+1 810 387 3776",
    "sg:postcode":"48097",
    "sg:province":"MI",
    "sg:tags":[
        "automobile",
        "parts"
    ],
    "wof:name":"Thumb Auto Parts",
    "wof:placetype":"venue"
},
  "geometry": {"coordinates":[-82.79821200000001,43.129791],"type":"Point"}
}