{
  "type": "Feature",
  "properties": {
    "iso:country":"US",
    "sg:address":"531 Common St",
    "sg:city":"Walled Lake",
    "sg:classifiers":[
        {
            "category":"Organizations",
            "subcategory":"Religious Organization",
            "type":"Services"
        }
    ],
    "sg:phone":"+1 248 624 1421",
    "sg:postcode":"48390",
    "sg:province":"MI",
    "sg:tags":[
        "catholic",
        "church"
    ],
    "sg:website":"www.stwilliam.com",
    "wof:name":"St Williams Catholic Church",
    "wof:placetype":"venue"
},
  "geometry": {"coordinates":[-83.48537899999999,42.535018],"type":"Point"}
}