{
  "type": "Feature",
  "properties": {
    "iso:country":"US",
    "sg:address":"6390 28th St SE",
    "sg:city":"Grand Rapids",
    "sg:classifiers":[
        {
            "category":"Restaurant",
            "type":"Food & Drink"
        }
    ],
    "sg:menulink":"http://www.allmenus.com/mi/cascade/56574-pizza-hut/menu/",
    "sg:phone":"+1 616 942 6255",
    "sg:postcode":"49546",
    "sg:province":"MI",
    "sg:tags":[
        "american",
        "pizza"
    ],
    "wof:name":"Pizza Hut",
    "wof:placetype":"venue"
},
  "geometry": {"coordinates":[-85.511043,42.913091],"type":"Point"}
}