{
  "type": "Feature",
  "properties": {
    "iso:country":"US",
    "sg:address":"10531 Puritan Rd",
    "sg:city":"Bessemer",
    "sg:classifiers":[
        {
            "category":"Retail",
            "subcategory":"Auto Repair",
            "type":"Services"
        }
    ],
    "sg:phone":"+1 906 663 0349",
    "sg:postcode":"49911",
    "sg:province":"MI",
    "sg:tags":[
        "repairing",
        "automobile"
    ],
    "wof:name":"Mark's Car Care",
    "wof:placetype":"venue"
},
  "geometry": {"coordinates":[-90.08381300000001,46.479839],"type":"Point"}
}