{
  "type": "Feature",
  "properties": {
    "iso:country":"US",
    "sg:address":"251 E Merrill St",
    "sg:city":"Birmingham",
    "sg:classifiers":[
        {
            "category":"Shopping",
            "subcategory":"Used Merchandise",
            "type":"Retail Goods"
        }
    ],
    "sg:phone":"+1 248 594 8330",
    "sg:postcode":"48009",
    "sg:province":"MI",
    "sg:tags":[
        "antique"
    ],
    "wof:name":"Dede & Jim Taylor Antiques",
    "wof:placetype":"venue"
},
  "geometry": {"coordinates":[-83.21379899999999,42.545502],"type":"Point"}
}