{
  "type": "Feature",
  "properties": {
    "iso:country":"US",
    "sg:address":"20735 Van Dyke Ave",
    "sg:city":"Warren",
    "sg:classifiers":[
        {
            "category":"Personal",
            "subcategory":"Beauty Salon",
            "type":"Services"
        }
    ],
    "sg:phone":"+1 586 758 6869",
    "sg:postcode":"48089",
    "sg:province":"MI",
    "sg:tags":[
        "nail",
        "manicuring"
    ],
    "wof:name":"Tv Nails",
    "wof:placetype":"venue"
},
  "geometry": {"coordinates":[-83.02498300000001,42.448674],"type":"Point"}
}