{
  "type": "Feature",
  "properties": {
    "iso:country":"US",
    "sg:address":"5700 Georgia Dr",
    "sg:city":"Oscoda",
    "sg:classifiers":[
        {
            "category":"Government",
            "subcategory":"Office",
            "type":"Public Place"
        }
    ],
    "sg:phone":"+1 989 739 6999",
    "sg:postcode":"48750",
    "sg:province":"MI",
    "sg:tags":[
        "city",
        "program",
        "adm"
    ],
    "wof:name":"Economic Adjustment Office",
    "wof:placetype":"venue"
},
  "geometry": {"coordinates":[-83.35217799999999,44.44604],"type":"Point"}
}