{
  "type": "Feature",
  "properties": {
    "iso:country":"US",
    "sg:address":"16001 Ford Rd",
    "sg:city":"Dearborn",
    "sg:classifiers":[
        {
            "category":"Shopping",
            "subcategory":"Discount & Variety Stores",
            "type":"Retail Goods"
        }
    ],
    "sg:phone":"+1 313 271 4887",
    "sg:postcode":"48126",
    "sg:province":"MI",
    "wof:name":"Dollar Palace",
    "wof:placetype":"venue"
},
  "geometry": {"coordinates":[-83.200126,42.329028],"type":"Point"}
}