{
  "type": "Feature",
  "properties": {
    "iso:country":"US",
    "sg:address":"13546 Summer Ln",
    "sg:city":"Grand Ledge",
    "sg:classifiers":[
        {
            "category":"Personal",
            "subcategory":"Beauty Salon",
            "type":"Services"
        }
    ],
    "sg:phone":"+1 517 626 6200",
    "sg:postcode":"48837",
    "sg:province":"MI",
    "sg:tags":[
        "shop"
    ],
    "wof:name":"Looking Glass Embroidery",
    "wof:placetype":"venue"
},
  "geometry": {"coordinates":[-84.675895,42.823074],"type":"Point"}
}