{
  "type": "Feature",
  "properties": {
    "iso:country":"US",
    "sg:address":"26977 Grand River Ave",
    "sg:city":"Redford",
    "sg:classifiers":[
        {
            "category":"Professional",
            "subcategory":"Testing Lab",
            "type":"Services"
        },
        {
            "category":"Health Services",
            "subcategory":"Medical Lab",
            "type":"Services"
        },
        {
            "category":"Health Services",
            "subcategory":"Dentist",
            "type":"Services"
        }
    ],
    "sg:phone":"+1 313 794 7072",
    "sg:postcode":"48240",
    "sg:province":"MI",
    "sg:tags":[
        "laboratory",
        "dental",
        "clinic"
    ],
    "wof:name":"Levson Dental",
    "wof:placetype":"venue"
},
  "geometry": {"coordinates":[-83.31155200000001,42.437963],"type":"Point"}
}