{
  "type": "Feature",
  "properties": {
    "iso:country":"US",
    "sg:address":"20080 White Oaks Dr",
    "sg:city":"Clinton Township",
    "sg:classifiers":[
        {
            "category":"Retail",
            "subcategory":"Auto Repair",
            "type":"Services"
        }
    ],
    "sg:phone":"+1 586 463 3130",
    "sg:postcode":"48036",
    "sg:province":"MI",
    "sg:tags":[
        "exhaust"
    ],
    "wof:name":"Wright Way Auto Service Center",
    "wof:placetype":"venue"
},
  "geometry": {"coordinates":[-82.918886,42.586075],"type":"Point"}
}