{
  "type": "Feature",
  "properties": {
    "iso:country":"US",
    "sg:address":"215 Hesse St",
    "sg:city":"Howell",
    "sg:classifiers":[
        {
            "category":"Arts & Performance",
            "subcategory":"Theater",
            "type":"Entertainment"
        }
    ],
    "sg:phone":"+1 517 552 9519",
    "sg:postcode":"48843",
    "sg:province":"MI",
    "sg:tags":[
        "group"
    ],
    "wof:name":"CK Entertainment",
    "wof:placetype":"venue"
},
  "geometry": {"coordinates":[-83.92332399999999,42.606809],"type":"Point"}
}