{
  "type": "Feature",
  "properties": {
    "iso:country":"US",
    "sg:address":"537 W 14th St",
    "sg:city":"Traverse City",
    "sg:classifiers":[
        {
            "category":"Professional",
            "subcategory":"Computer Services",
            "type":"Services"
        }
    ],
    "sg:phone":"+1 231 933 9910",
    "sg:postcode":"49684",
    "sg:province":"MI",
    "sg:tags":[
        "repair"
    ],
    "wof:name":"Northland Computers Inc",
    "wof:placetype":"venue"
},
  "geometry": {"coordinates":[-85.632515,44.751609],"type":"Point"}
}