{
  "type": "Feature",
  "properties": {
    "iso:country":"US",
    "sg:address":"3544 Plainfield Ave NE",
    "sg:city":"Grand Rapids",
    "sg:classifiers":[
        {
            "category":"Retail",
            "subcategory":"Auto Rental",
            "type":"Services"
        }
    ],
    "sg:phone":"+1 616 363 0615",
    "sg:postcode":"49525",
    "sg:province":"MI",
    "sg:tags":[
        "renting",
        "automobile"
    ],
    "wof:name":"Avis Rent A Car",
    "wof:placetype":"venue"
},
  "geometry": {"coordinates":[-85.63173500000001,43.027573],"type":"Point"}
}