{
  "type": "Feature",
  "properties": {
    "iso:country":"US",
    "sg:address":"101 W Porter St",
    "sg:city":"Albion",
    "sg:classifiers":[
        {
            "category":"Personal",
            "subcategory":"Barber",
            "type":"Services"
        }
    ],
    "sg:phone":"+1 517 629 2410",
    "sg:postcode":"49224",
    "sg:province":"MI",
    "wof:name":"Snug Barber Shop",
    "wof:placetype":"venue"
},
  "geometry": {"coordinates":[-84.75456699999999,42.243775],"type":"Point"}
}