{
  "type": "Feature",
  "properties": {
    "iso:country":"US",
    "sg:address":"3060 Bc East Jordan Rd",
    "sg:city":"Boyne City",
    "sg:classifiers":[
        {
            "category":"Professional",
            "subcategory":"Business Services",
            "type":"Services"
        }
    ],
    "sg:phone":"+1 231 582 2254",
    "sg:postcode":"49712",
    "sg:province":"MI",
    "wof:name":"Amerispec Home Inspection S",
    "wof:placetype":"venue"
},
  "geometry": {"coordinates":[-84.98334699999999,45.160699],"type":"Point"}
}