{
  "type": "Feature",
  "properties": {
    "iso:country":"US",
    "sg:address":"11686 Blueridge St",
    "sg:city":"Schoolcraft",
    "sg:classifiers":[
        {
            "category":"Social Services",
            "subcategory":"Child Care",
            "type":"Services"
        }
    ],
    "sg:phone":"+1 269 679 5911",
    "sg:postcode":"49087",
    "sg:province":"MI",
    "sg:tags":[
        "day"
    ],
    "wof:name":"Laurie J Morch",
    "wof:placetype":"venue"
},
  "geometry": {"coordinates":[-85.61739,42.14564],"type":"Point"}
}