{
  "type": "Feature",
  "properties": {
    "iso:country":"US",
    "sg:address":"2656 Northvale Dr NE",
    "sg:city":"Grand Rapids",
    "sg:classifiers":[
        {
            "category":"Building & Trades",
            "subcategory":"Construction",
            "type":"Services"
        }
    ],
    "sg:phone":"+1 616 363 2791",
    "sg:postcode":"49525",
    "sg:province":"MI",
    "sg:tags":[
        "maintenance",
        "contractor"
    ],
    "wof:name":"Mark's Maintenance",
    "wof:placetype":"venue"
},
  "geometry": {"coordinates":[-85.603219,43.0409],"type":"Point"}
}