{
  "type": "Feature",
  "properties": {
    "iso:country":"US",
    "sg:address":"535 Griswold St Ste 800",
    "sg:city":"Detroit",
    "sg:classifiers":[
        {
            "category":"Professional",
            "subcategory":"Lawyer & Legal Services",
            "type":"Services"
        }
    ],
    "sg:phone":"+1 313 963 1970",
    "sg:postcode":"48226",
    "sg:province":"MI",
    "wof:name":"Miller Arthur W PC Atty",
    "wof:placetype":"venue"
},
  "geometry": {"coordinates":[-83.04630299999999,42.3293],"type":"Point"}
}