{
  "type": "Feature",
  "properties": {
    "iso:country":"US",
    "sg:address":"5811 US Hwy 31 N",
    "sg:city":"Levering",
    "sg:classifiers":[
        {
            "category":"Shopping",
            "subcategory":"Bicycles & Sporting Goods",
            "type":"Retail Goods"
        }
    ],
    "sg:phone":"+1 231 537 4737",
    "sg:postcode":"49755",
    "sg:province":"MI",
    "wof:name":"Levering Sports",
    "wof:placetype":"venue"
},
  "geometry": {"coordinates":[-84.782511,45.634721],"type":"Point"}
}