{
  "type": "Feature",
  "properties": {
    "iso:country":"US",
    "sg:address":"8275 W Hyde Rd",
    "sg:city":"St Johns",
    "sg:classifiers":[
        {
            "category":"Autos & Motor Vehicles",
            "subcategory":"Auto Supplies",
            "type":"Retail Goods"
        }
    ],
    "sg:phone":"+1 989 682 4714",
    "sg:postcode":"48879",
    "sg:province":"MI",
    "sg:tags":[
        "automobile",
        "parts"
    ],
    "wof:name":"Maple Rapids Auto Parts",
    "wof:placetype":"venue"
},
  "geometry": {"coordinates":[-84.687991,43.097344],"type":"Point"}
}