{
  "type": "Feature",
  "properties": {
    "iso:country":"US",
    "sg:address":"575 E Michigan St",
    "sg:city":"Marquette",
    "sg:classifiers":[
        {
            "category":"Home & Garden",
            "subcategory":"Furniture",
            "type":"Retail Goods"
        }
    ],
    "sg:phone":"+1 906 226 2228",
    "sg:postcode":"49855",
    "sg:province":"MI",
    "sg:tags":[
        "builder",
        "custom"
    ],
    "wof:name":"Rustico",
    "wof:placetype":"venue"
},
  "geometry": {"coordinates":[-87.38011400000001,46.547314],"type":"Point"}
}