{
  "type": "Feature",
  "properties": {
    "iso:country":"US",
    "sg:address":"19900 E 10 Mile Rd",
    "sg:city":"Saint Clair Shores",
    "sg:classifiers":[
        {
            "category":"Professional",
            "subcategory":"Accounting & Tax Preparation",
            "type":"Services"
        }
    ],
    "sg:phone":"+1 586 773 7720",
    "sg:postcode":"48080",
    "sg:province":"MI",
    "wof:name":"Robert F Ricci CPA Inc",
    "wof:placetype":"venue"
},
  "geometry": {"coordinates":[-82.91562500000001,42.480397],"type":"Point"}
}