{
  "type": "Feature",
  "properties": {
    "iso:country":"US",
    "sg:address":"8231 St Johns Dr",
    "sg:city":"Westland",
    "sg:classifiers":[
        {
            "category":"Personal",
            "subcategory":"Beauty Salon",
            "type":"Services"
        }
    ],
    "sg:phone":"+1 734 416 8342",
    "sg:postcode":"48185",
    "sg:province":"MI",
    "sg:tags":[
        "shop"
    ],
    "wof:name":"Total Design Solutions In",
    "wof:placetype":"venue"
},
  "geometry": {"coordinates":[-83.427683,42.346803],"type":"Point"}
}