{
  "type": "Feature",
  "properties": {
    "iso:country":"US",
    "sg:address":"9631 Silberhorn Hwy",
    "sg:city":"Riga",
    "sg:classifiers":[
        {
            "category":"Building & Trades",
            "subcategory":"Landscaping Services",
            "type":"Services"
        }
    ],
    "sg:phone":"+1 517 486 2350",
    "sg:postcode":"49276",
    "sg:province":"MI",
    "wof:name":"Ranger Bobs Tree Service",
    "wof:placetype":"venue"
},
  "geometry": {"coordinates":[-83.842838,41.779833],"type":"Point"}
}