{
  "type": "Feature",
  "properties": {
    "iso:country":"US",
    "sg:address":"4416 Chandy Dr NE",
    "sg:city":"Grand Rapids",
    "sg:classifiers":[
        {
            "category":"Shopping",
            "subcategory":"Gifts & Souvenirs",
            "type":"Retail Goods"
        }
    ],
    "sg:phone":"+1 616 364 9290",
    "sg:postcode":"49525",
    "sg:province":"MI",
    "sg:tags":[
        "basket",
        "parcel"
    ],
    "wof:name":"Creative Gift Baskets",
    "wof:placetype":"venue"
},
  "geometry": {"coordinates":[-85.594205,43.043369],"type":"Point"}
}