{
  "type": "Feature",
  "properties": {
    "iso:country":"US",
    "sg:address":"108 Brooklyn Rd",
    "sg:city":"Jackson",
    "sg:classifiers":[
        {
            "category":"Restaurant",
            "type":"Food & Drink"
        }
    ],
    "sg:phone":"+1 517 536 8383",
    "sg:postcode":"49201",
    "sg:province":"MI",
    "wof:name":"Aggies",
    "wof:placetype":"venue"
},
  "geometry": {"coordinates":[-84.248391,42.161984],"type":"Point"}
}