{
  "type": "Feature",
  "properties": {
    "iso:country":"US",
    "sg:address":"22170 W 9 Mile Rd",
    "sg:city":"Southfield",
    "sg:classifiers":[
        {
            "category":"Government",
            "subcategory":"Office",
            "type":"Public Place"
        }
    ],
    "sg:phone":"+1 248 350 3429",
    "sg:postcode":"48033",
    "sg:province":"MI",
    "sg:tags":[
        "state",
        "program"
    ],
    "wof:name":"Transportation Dept",
    "wof:placetype":"venue"
},
  "geometry": {"coordinates":[-83.26008299999999,42.457857],"type":"Point"}
}