{
  "type": "Feature",
  "properties": {
    "iso:country":"US",
    "sg:address":"7050 S Cedar St",
    "sg:city":"Lansing",
    "sg:classifiers":[
        {
            "category":"Restaurant",
            "type":"Food & Drink"
        }
    ],
    "sg:menulink":"http://www.allmenus.com/mi/lansing/251296-china-east-buffet/menu/",
    "sg:phone":"+1 517 694 6688",
    "sg:postcode":"48911",
    "sg:province":"MI",
    "sg:tags":[
        "asian",
        "chinese"
    ],
    "wof:name":"China East Buffet",
    "wof:placetype":"venue"
},
  "geometry": {"coordinates":[-84.533525,42.655613],"type":"Point"}
}