{
  "type": "Feature",
  "properties": {
    "iso:country":"US",
    "sg:address":"7021 Wyoming St",
    "sg:city":"Dearborn",
    "sg:classifiers":[
        {
            "category":"Fast Food",
            "type":"Food & Drink"
        }
    ],
    "sg:phone":"+1 313 846 5592",
    "sg:postcode":"48126",
    "sg:province":"MI",
    "sg:tags":[
        "burger"
    ],
    "sg:website":"www.burgerking.com",
    "wof:name":"Burger King",
    "wof:placetype":"venue"
},
  "geometry": {"coordinates":[-83.157303,42.3428],"type":"Point"}
}