{
  "type": "Feature",
  "properties": {
    "iso:country":"US",
    "sg:address":"5250 S Old US Highway 23",
    "sg:city":"Brighton",
    "sg:classifiers":[
        {
            "category":"Retail",
            "subcategory":"Car Wash",
            "type":"Services"
        }
    ],
    "sg:phone":"+1 810 225 7184",
    "sg:postcode":"48114",
    "sg:province":"MI",
    "sg:tags":[
        "polishing",
        "washing"
    ],
    "wof:name":"Blue Water Car Wash",
    "wof:placetype":"venue"
},
  "geometry": {"coordinates":[-83.759022,42.528352],"type":"Point"}
}