{
  "type": "Feature",
  "properties": {
    "iso:country":"US",
    "sg:address":"3572 Flushing Rd",
    "sg:city":"Flint",
    "sg:classifiers":[
        {
            "category":"Food & Beverages",
            "subcategory":"Liquor & Beverages",
            "type":"Retail Goods"
        }
    ],
    "sg:phone":"+1 810 732 5181",
    "sg:postcode":"48504",
    "sg:province":"MI",
    "sg:tags":[
        "beer",
        "ale"
    ],
    "wof:name":"Happy Boy Market",
    "wof:placetype":"venue"
},
  "geometry": {"coordinates":[-83.740483,43.026965],"type":"Point"}
}