{
  "type": "Feature",
  "properties": {
    "iso:country":"US",
    "sg:address":"708 N Brady Rd",
    "sg:city":"Dearborn",
    "sg:classifiers":[
        {
            "category":"Freight",
            "type":"Transportation"
        }
    ],
    "sg:phone":"+1 313 562 7847",
    "sg:postcode":"48124",
    "sg:province":"MI",
    "sg:tags":[
        "water"
    ],
    "wof:name":"Bhopak",
    "wof:placetype":"venue"
},
  "geometry": {"coordinates":[-83.24374,42.318426],"type":"Point"}
}