{
  "type": "Feature",
  "properties": {
    "iso:country":"US",
    "sg:address":"2814 Glenwood Rd",
    "sg:city":"Royal Oak",
    "sg:classifiers":[
        {
            "category":"Education",
            "subcategory":"Special Training",
            "type":"Public Place"
        }
    ],
    "sg:phone":"+1 248 546 4456",
    "sg:postcode":"48073",
    "sg:province":"MI",
    "sg:tags":[
        "program"
    ],
    "wof:name":"Promotional Training Aids",
    "wof:placetype":"venue"
},
  "geometry": {"coordinates":[-83.178791,42.512662],"type":"Point"}
}