{
  "type": "Feature",
  "properties": {
    "iso:country":"US",
    "sg:address":"1 Heritage Dr",
    "sg:city":"Southgate",
    "sg:classifiers":[
        {
            "category":"Professional",
            "subcategory":"Lawyer & Legal Services",
            "type":"Services"
        }
    ],
    "sg:phone":"+1 734 284 9282",
    "sg:postcode":"48195",
    "sg:province":"MI",
    "wof:name":"Pendracki & Burke",
    "wof:placetype":"venue"
},
  "geometry": {"coordinates":[-83.224765,42.209296],"type":"Point"}
}