{
  "type": "Feature",
  "properties": {
    "iso:country":"US",
    "sg:address":"8101 Byron Rd",
    "sg:city":"Howell",
    "sg:classifiers":[
        {
            "category":"Sports & Exercise",
            "subcategory":"Golf",
            "type":"Entertainment"
        }
    ],
    "sg:phone":"+1 517 545 4653",
    "sg:postcode":"48855",
    "sg:province":"MI",
    "sg:tags":[
        "course",
        "public"
    ],
    "wof:name":"Hunters Ridge Golf Course",
    "wof:placetype":"venue"
},
  "geometry": {"coordinates":[-83.968085,42.717843],"type":"Point"}
}