{
  "type": "Feature",
  "properties": {
    "iso:country":"US",
    "sg:address":"2368 Ridgefield Dr NE",
    "sg:city":"Grand Rapids",
    "sg:classifiers":[
        {
            "category":"Professional",
            "subcategory":"Art Services",
            "type":"Services"
        }
    ],
    "sg:phone":"+1 616 774 0050",
    "sg:postcode":"49505",
    "sg:province":"MI",
    "sg:tags":[
        "graphic",
        "design"
    ],
    "wof:name":"Morning Glory Greetings",
    "wof:placetype":"venue"
},
  "geometry": {"coordinates":[-85.61285700000001,42.987776],"type":"Point"}
}