{
  "type": "Feature",
  "properties": {
    "iso:country":"US",
    "sg:address":"56 Grand Ave",
    "sg:city":"Mount Clemens",
    "sg:classifiers":[
        {
            "category":"Real Estate",
            "subcategory":"Developer",
            "type":"Services"
        }
    ],
    "sg:phone":"+1 586 822 0173",
    "sg:postcode":"48043",
    "sg:province":"MI",
    "wof:name":"Omniware Development",
    "wof:placetype":"venue"
},
  "geometry": {"coordinates":[-82.882029,42.600027],"type":"Point"}
}