{
  "type": "Feature",
  "properties": {
    "iso:country":"US",
    "sg:address":"555 Townsend St",
    "sg:city":"Birmingham",
    "sg:classifiers":[
        {
            "category":"Real Estate",
            "subcategory":"Real Estate Agent",
            "type":"Services"
        }
    ],
    "sg:phone":"+1 248 644 8929",
    "sg:postcode":"48009",
    "sg:province":"MI",
    "wof:name":"McKeon Co Real Estate",
    "wof:placetype":"venue"
},
  "geometry": {"coordinates":[-83.220114,42.544283],"type":"Point"}
}