{
  "type": "Feature",
  "properties": {
    "iso:country":"US",
    "sg:address":"7779 E Mitchell Rd",
    "sg:city":"Petoskey",
    "sg:classifiers":[
        {
            "category":"Restaurant",
            "type":"Food & Drink"
        }
    ],
    "sg:phone":"+1 231 439 6915",
    "sg:postcode":"49770",
    "sg:province":"MI",
    "wof:name":"Epsilon General Store",
    "wof:placetype":"venue"
},
  "geometry": {"coordinates":[-84.812028,45.362871],"type":"Point"}
}