{
  "type": "Feature",
  "properties": {
    "iso:country":"US",
    "sg:address":"318 Green St",
    "sg:city":"Roscommon",
    "sg:classifiers":[
        {
            "category":"Arts & Performance",
            "subcategory":"Theater",
            "type":"Entertainment"
        }
    ],
    "sg:phone":"+1 989 821 3015",
    "sg:postcode":"48653",
    "sg:province":"MI",
    "sg:tags":[
        "group"
    ],
    "wof:name":"Angelas Piano Styles",
    "wof:placetype":"venue"
},
  "geometry": {"coordinates":[-84.66556300000001,44.456001],"type":"Point"}
}