{
  "type": "Feature",
  "properties": {
    "iso:country":"US",
    "sg:address":"1201 E Houghton Ave",
    "sg:city":"Houghton",
    "sg:classifiers":[
        {
            "category":"Travel",
            "subcategory":"Hotels & Motels",
            "type":"Entertainment"
        }
    ],
    "sg:phone":"+1 906 482 4503",
    "sg:postcode":"49931",
    "sg:province":"MI",
    "sg:tags":[
        "membership",
        "lodging"
    ],
    "wof:name":"Alpha Xi Zeta",
    "wof:placetype":"venue"
},
  "geometry": {"coordinates":[-88.556051,47.119484],"type":"Point"}
}