{
  "type": "Feature",
  "properties": {
    "iso:country":"US",
    "sg:address":"1890 E Stoney Corners Rd",
    "sg:city":"Mc Bain",
    "sg:classifiers":[
        {
            "category":"Professional",
            "subcategory":"Business Services",
            "type":"Services"
        }
    ],
    "sg:phone":"+1 231 825 2628",
    "sg:postcode":"49657",
    "sg:province":"MI",
    "sg:tags":[
        "embroidery"
    ],
    "wof:name":"B & D Classic Sewn",
    "wof:placetype":"venue"
},
  "geometry": {"coordinates":[-85.05551800000001,44.192444],"type":"Point"}
}