{
  "type": "Feature",
  "properties": {
    "iso:country":"US",
    "sg:address":"120 S Main St",
    "sg:city":"Scottville",
    "sg:classifiers":[
        {
            "category":"Shopping",
            "subcategory":"Used Merchandise",
            "type":"Retail Goods"
        }
    ],
    "sg:phone":"+1 231 757 4708",
    "sg:postcode":"49454",
    "sg:province":"MI",
    "wof:name":"Fricks Old Country Store",
    "wof:placetype":"venue"
},
  "geometry": {"coordinates":[-86.279521,43.954258],"type":"Point"}
}