{
  "type": "Feature",
  "properties": {
    "iso:country":"US",
    "sg:address":"3965 N Big Spring Dr SW",
    "sg:city":"Grandville",
    "sg:classifiers":[
        {
            "category":"Professional",
            "subcategory":"Management & Consulting",
            "type":"Services"
        }
    ],
    "sg:phone":"+1 616 534 3330",
    "sg:postcode":"49418",
    "sg:province":"MI",
    "wof:name":"ICI International Consultants",
    "wof:placetype":"venue"
},
  "geometry": {"coordinates":[-85.75927799999999,42.900235],"type":"Point"}
}