{
  "type": "Feature",
  "properties": {
    "iso:country":"US",
    "sg:address":"21 W Chicago St",
    "sg:city":"Coldwater",
    "sg:classifiers":[
        {
            "category":"Shopping",
            "subcategory":"Books",
            "type":"Retail Goods"
        }
    ],
    "sg:phone":"+1 517 278 6575",
    "sg:postcode":"49036",
    "sg:province":"MI",
    "sg:tags":[
        "dealer"
    ],
    "wof:name":"Lamp Post Christian Bookstore",
    "wof:placetype":"venue"
},
  "geometry": {"coordinates":[-85.00074600000001,41.94063],"type":"Point"}
}