{
  "type": "Feature",
  "properties": {
    "iso:country":"US",
    "sg:address":"430 US Hwy 23",
    "sg:city":"Oscoda",
    "sg:classifiers":[
        {
            "category":"Recreation",
            "type":"Entertainment"
        }
    ],
    "sg:phone":"+1 989 739 7502",
    "sg:postcode":"48750",
    "sg:province":"MI",
    "sg:tags":[
        "club",
        "membership"
    ],
    "wof:name":"Oscoda Yacht Club",
    "wof:placetype":"venue"
},
  "geometry": {"coordinates":[-83.32474000000001,44.408726],"type":"Point"}
}