{
  "type": "Feature",
  "properties": {
    "iso:country":"US",
    "sg:address":"18350 Blue Heron Dr W",
    "sg:city":"Northville",
    "sg:classifiers":[
        {
            "category":"Professional",
            "type":"Services"
        }
    ],
    "sg:phone":"+1 248 380 0380",
    "sg:postcode":"48168",
    "sg:province":"MI",
    "sg:tags":[
        "supply"
    ],
    "wof:name":"Tod Sales Assoc Inc",
    "wof:placetype":"venue"
},
  "geometry": {"coordinates":[-83.51509,42.417085],"type":"Point"}
}