{
  "type": "Feature",
  "properties": {
    "iso:country":"US",
    "sg:address":"5253 S Harvey St",
    "sg:city":"Muskegon",
    "sg:classifiers":[
        {
            "category":"Shopping",
            "subcategory":"Clothing, Apparel, & Fashions",
            "type":"Retail Goods"
        }
    ],
    "sg:phone":"+1 231 798 8485",
    "sg:postcode":"49444",
    "sg:province":"MI",
    "sg:tags":[
        "furnishing"
    ],
    "sg:website":"www.skmenswear.com",
    "wof:name":"S&K Famous Brand Menswear",
    "wof:placetype":"venue"
},
  "geometry": {"coordinates":[-86.20578,43.158804],"type":"Point"}
}