{
  "type": "Feature",
  "properties": {
    "iso:country":"US",
    "sg:address":"25882 Shirley Ln",
    "sg:city":"Dearborn Heights",
    "sg:classifiers":[
        {
            "category":"Personal",
            "type":"Services"
        }
    ],
    "sg:phone":"+1 313 562 1641",
    "sg:postcode":"48127",
    "sg:province":"MI",
    "wof:name":"Good Work",
    "wof:placetype":"venue"
},
  "geometry": {"coordinates":[-83.293491,42.312933],"type":"Point"}
}