{
  "type": "Feature",
  "properties": {
    "iso:country":"US",
    "sg:address":"Detroit Metropolitan Airport 6810 Metroplex Dr",
    "sg:city":"Romulus",
    "sg:classifiers":[
        {
            "category":"Fast Food",
            "type":"Food & Drink"
        }
    ],
    "sg:phone":"+1 734 727 0055",
    "sg:postcode":"48242",
    "sg:province":"MI",
    "sg:tags":[
        "burger"
    ],
    "sg:website":"www.cheeburger.com/",
    "wof:name":"Cheeburger Cheeburger",
    "wof:placetype":"venue"
},
  "geometry": {"coordinates":[-83.33187,42.257563],"type":"Point"}
}