{
  "type": "Feature",
  "properties": {
    "iso:country":"US",
    "sg:address":"329 South St",
    "sg:city":"Cadillac",
    "sg:classifiers":[
        {
            "category":"Real Estate",
            "subcategory":"Real Estate Operator",
            "type":"Services"
        }
    ],
    "sg:phone":"+1 231 775 0831",
    "sg:postcode":"49601",
    "sg:province":"MI",
    "sg:tags":[
        "apartment"
    ],
    "wof:name":"Harbor View Apartments",
    "wof:placetype":"venue"
},
  "geometry": {"coordinates":[-85.398135,44.245038],"type":"Point"}
}