{
  "type": "Feature",
  "properties": {
    "iso:country":"US",
    "sg:address":"37493 Schoolcraft Rd",
    "sg:city":"Livonia",
    "sg:classifiers":[
        {
            "category":"Home & Garden",
            "subcategory":"Carpets & Floor Coverings",
            "type":"Retail Goods"
        }
    ],
    "sg:phone":"+1 734 462 8750",
    "sg:postcode":"48150",
    "sg:province":"MI",
    "sg:tags":[
        "flooring"
    ],
    "wof:name":"Total Floors",
    "wof:placetype":"venue"
},
  "geometry": {"coordinates":[-83.415114,42.381016],"type":"Point"}
}