{
  "type": "Feature",
  "properties": {
    "iso:country":"US",
    "sg:address":"489 W Feather Valley Rd",
    "sg:city":"Fremont",
    "sg:classifiers":[
        {
            "category":"Travel",
            "subcategory":"Campground",
            "type":"Entertainment"
        }
    ],
    "sg:phone":"+1 260 495 0164",
    "sg:postcode":"46737",
    "sg:province":"MI",
    "wof:name":"Oak Family Campground",
    "wof:placetype":"venue"
},
  "geometry": {"coordinates":[-85.00274400000001,41.715345],"type":"Point"}
}