{
  "type": "Feature",
  "properties": {
    "iso:country":"US",
    "sg:address":"64541 Van Dyke Rd",
    "sg:city":"Washington",
    "sg:classifiers":[
        {
            "category":"Real Estate",
            "subcategory":"Real Estate Agent",
            "type":"Services"
        }
    ],
    "sg:phone":"+1 586 992 1500",
    "sg:postcode":"48095",
    "sg:province":"MI",
    "wof:name":"Sunset Real Estate",
    "wof:placetype":"venue"
},
  "geometry": {"coordinates":[-83.018405,42.768667],"type":"Point"}
}