{
  "type": "Feature",
  "properties": {
    "iso:country":"US",
    "sg:address":"582 W Hamlin Rd",
    "sg:city":"Rochester Hills",
    "sg:classifiers":[
        {
            "category":"Building & Trades",
            "subcategory":"Construction",
            "type":"Services"
        }
    ],
    "sg:phone":"+1 248 652 2233",
    "sg:postcode":"48307",
    "sg:province":"MI",
    "sg:tags":[
        "general",
        "contractor"
    ],
    "wof:name":"Remington Homes Inc",
    "wof:placetype":"venue"
},
  "geometry": {"coordinates":[-83.143829,42.652265],"type":"Point"}
}