{
  "type": "Feature",
  "properties": {
    "iso:country":"US",
    "sg:address":"2237 Puritan St",
    "sg:city":"Detroit",
    "sg:classifiers":[
        {
            "category":"Personal",
            "subcategory":"Barber",
            "type":"Services"
        }
    ],
    "sg:phone":"+1 313 270 5709",
    "sg:postcode":"48238",
    "sg:province":"MI",
    "sg:tags":[
        "shop"
    ],
    "wof:name":"Eureka Barber Shop",
    "wof:placetype":"venue"
},
  "geometry": {"coordinates":[-83.12190200000001,42.410198],"type":"Point"}
}