{
  "type": "Feature",
  "properties": {
    "iso:country":"US",
    "sg:address":"2336 Beard St",
    "sg:city":"Port Huron",
    "sg:classifiers":[
        {
            "category":"Building & Trades",
            "subcategory":"Construction",
            "type":"Services"
        }
    ],
    "sg:phone":"+1 810 985 8049",
    "sg:postcode":"48060",
    "sg:province":"MI",
    "sg:tags":[
        "general",
        "contractor"
    ],
    "wof:name":"Phoenix Contracting",
    "wof:placetype":"venue"
},
  "geometry": {"coordinates":[-82.45163599999999,42.958158],"type":"Point"}
}