{
  "type": "Feature",
  "properties": {
    "iso:country":"US",
    "sg:address":"9954 N Long Lake Rd",
    "sg:city":"Traverse City",
    "sg:classifiers":[
        {
            "category":"Retail",
            "subcategory":"Repair Shop",
            "type":"Services"
        },
        {
            "category":"Manufacturing",
            "subcategory":"Motor Vehicles & Parts",
            "type":"Manufacturing & Wholesale Goods"
        }
    ],
    "sg:phone":"+1 231 947 6557",
    "sg:postcode":"49684",
    "sg:province":"MI",
    "sg:tags":[
        "body",
        "welding",
        "truck",
        "mfg"
    ],
    "wof:name":"Wheelock & Sons Welding Inc",
    "wof:placetype":"venue"
},
  "geometry": {"coordinates":[-85.776538,44.734948],"type":"Point"}
}