{
  "type": "Feature",
  "properties": {
    "iso:country":"US",
    "sg:address":"9792 Red Arrow Hwy",
    "sg:city":"Bridgman",
    "sg:classifiers":[
        {
            "category":"Utilities",
            "subcategory":"Mobile Phone",
            "type":"Services"
        }
    ],
    "sg:phone":"+1 269 465 3735",
    "sg:postcode":"49106",
    "sg:province":"MI",
    "sg:tags":[
        "telephone",
        "cellular"
    ],
    "wof:name":"Cellular Choices",
    "wof:placetype":"venue"
},
  "geometry": {"coordinates":[-86.56437200000001,41.941415],"type":"Point"}
}