{
  "type": "Feature",
  "properties": {
    "iso:country":"US",
    "sg:address":"14251 Princeton Dr",
    "sg:city":"Plymouth",
    "sg:classifiers":[
        {
            "category":"Real Estate",
            "subcategory":"Real Estate Operator",
            "type":"Services"
        }
    ],
    "sg:phone":"+1 734 459 6640",
    "sg:postcode":"48170",
    "sg:province":"MI",
    "sg:tags":[
        "apartment"
    ],
    "wof:name":"Princeton Court Apts",
    "wof:placetype":"venue"
},
  "geometry": {"coordinates":[-83.45059999999999,42.385399],"type":"Point"}
}