{
  "type": "Feature",
  "properties": {
    "iso:country":"US",
    "sg:address":"69421 Union Rd",
    "sg:city":"Union",
    "sg:classifiers":[
        {
            "category":"Wholesale",
            "subcategory":"Machinery & Supplies",
            "type":"Manufacturing & Wholesale Goods"
        }
    ],
    "sg:phone":"+1 269 641 7938",
    "sg:postcode":"49130",
    "sg:province":"MI",
    "sg:tags":[
        "glass",
        "product",
        "fiber"
    ],
    "wof:name":"Class Glas Inc",
    "wof:placetype":"venue"
},
  "geometry": {"coordinates":[-85.866995,41.788607],"type":"Point"}
}