{
  "type": "Feature",
  "properties": {
    "iso:country":"US",
    "sg:address":"226 S Main St",
    "sg:city":"Concord",
    "sg:classifiers":[
        {
            "category":"Building & Trades",
            "subcategory":"Electrical",
            "type":"Services"
        }
    ],
    "sg:phone":"+1 517 524 6742",
    "sg:postcode":"49237",
    "sg:province":"MI",
    "sg:tags":[
        "electric",
        "contractor"
    ],
    "wof:name":"Brigham Electric",
    "wof:placetype":"venue"
},
  "geometry": {"coordinates":[-84.644626,42.174985],"type":"Point"}
}