{
  "type": "Feature",
  "properties": {
    "iso:country":"US",
    "sg:address":"345 S Main St",
    "sg:city":"Frankenmuth",
    "sg:classifiers":[
        {
            "category":"Museum",
            "type":"Entertainment"
        }
    ],
    "sg:phone":"+1 989 652 8271",
    "sg:postcode":"48734",
    "sg:province":"MI",
    "sg:tags":[
        "gallery",
        "merchandise"
    ],
    "wof:name":"Artist Studio",
    "wof:placetype":"venue"
},
  "geometry": {"coordinates":[-83.73813699999999,43.33234],"type":"Point"}
}