{
  "type": "Feature",
  "properties": {
    "iso:country":"US",
    "sg:address":"949 Sheridan Ave",
    "sg:city":"Ypsilanti",
    "sg:classifiers":[
        {
            "category":"Professional",
            "subcategory":"Business Services",
            "type":"Services"
        }
    ],
    "sg:phone":"+1 734 487 1377",
    "sg:postcode":"48197",
    "sg:province":"MI",
    "wof:name":"Data V Solutions",
    "wof:placetype":"venue"
},
  "geometry": {"coordinates":[-83.62892600000001,42.244627],"type":"Point"}
}