{
  "type": "Feature",
  "properties": {
    "iso:country":"US",
    "sg:address":"14811 Poplar St",
    "sg:city":"Southgate",
    "sg:classifiers":[
        {
            "category":"Personal",
            "type":"Services"
        }
    ],
    "sg:phone":"+1 734 284 3559",
    "sg:postcode":"48195",
    "sg:province":"MI",
    "wof:name":"Home & Garden Party Rep",
    "wof:placetype":"venue"
},
  "geometry": {"coordinates":[-83.20075300000001,42.200028],"type":"Point"}
}