{
  "type": "Feature",
  "properties": {
    "iso:country":"US",
    "sg:address":"27610 Harvard Rd",
    "sg:city":"Southfield",
    "sg:classifiers":[
        {
            "category":"Professional",
            "subcategory":"Business Services",
            "type":"Services"
        }
    ],
    "sg:phone":"+1 248 352 8173",
    "sg:postcode":"48076",
    "sg:province":"MI",
    "wof:name":"Richardson Group",
    "wof:placetype":"venue"
},
  "geometry": {"coordinates":[-83.250405,42.491741],"type":"Point"}
}