{
  "type": "Feature",
  "properties": {
    "iso:country":"US",
    "sg:address":"1057 Rogers Plz SW",
    "sg:city":"Wyoming",
    "sg:classifiers":[
        {
            "category":"Shopping",
            "subcategory":"Gifts & Souvenirs",
            "type":"Retail Goods"
        }
    ],
    "sg:phone":"+1 616 249 3544",
    "sg:postcode":"49509",
    "sg:province":"MI",
    "sg:tags":[
        "shop"
    ],
    "wof:name":"Cool Holographics",
    "wof:placetype":"venue"
},
  "geometry": {"coordinates":[-85.692463,42.91247],"type":"Point"}
}