{
  "type": "Feature",
  "properties": {
    "iso:country":"US",
    "sg:address":"3368 W Wilson Rd",
    "sg:city":"Clio",
    "sg:classifiers":[
        {
            "category":"Professional",
            "subcategory":"Computer Services",
            "type":"Services"
        }
    ],
    "sg:phone":"+1 810 686 5143",
    "sg:postcode":"48420",
    "sg:province":"MI",
    "sg:tags":[
        "prepackaged",
        "software"
    ],
    "wof:name":"Alto Software Inc",
    "wof:placetype":"venue"
},
  "geometry": {"coordinates":[-83.748997,43.162999],"type":"Point"}
}