{
  "type": "Feature",
  "properties": {
    "iso:country":"US",
    "sg:address":"9653 E S Ave",
    "sg:city":"Vicksburg",
    "sg:classifiers":[
        {
            "category":"Building & Trades",
            "subcategory":"Construction",
            "type":"Services"
        }
    ],
    "sg:phone":"+1 269 626 8814",
    "sg:postcode":"49097",
    "sg:province":"MI",
    "sg:tags":[
        "excavation",
        "contractor"
    ],
    "wof:name":"Becker Escavating",
    "wof:placetype":"venue"
},
  "geometry": {"coordinates":[-85.432301,42.172461],"type":"Point"}
}