{
  "type": "Feature",
  "properties": {
    "iso:country":"US",
    "sg:address":"17600 Clinton River Rd",
    "sg:city":"Clinton Township",
    "sg:classifiers":[
        {
            "category":"Sports & Exercise",
            "subcategory":"Bowling",
            "type":"Entertainment"
        }
    ],
    "sg:phone":"+1 586 286 5060",
    "sg:postcode":"48038",
    "sg:province":"MI",
    "wof:name":"Fern Hill Lanes",
    "wof:placetype":"venue"
},
  "geometry": {"coordinates":[-82.94270299999999,42.582298],"type":"Point"}
}