{
  "type": "Feature",
  "properties": {
    "iso:country":"US",
    "sg:address":"17423 Hiawatha Dr",
    "sg:city":"Spring Lake",
    "sg:classifiers":[
        {
            "category":"Food & Beverages",
            "subcategory":"Specialty",
            "type":"Retail Goods"
        }
    ],
    "sg:phone":"+1 616 847 6135",
    "sg:postcode":"49456",
    "sg:province":"MI",
    "wof:name":"Bosse Beef",
    "wof:placetype":"venue"
},
  "geometry": {"coordinates":[-86.229446,43.089564],"type":"Point"}
}