{
  "type": "Feature",
  "properties": {
    "iso:country":"US",
    "sg:address":"2695 Henry St",
    "sg:city":"Muskegon",
    "sg:classifiers":[
        {
            "category":"Building & Trades",
            "subcategory":"Equipment Rental",
            "type":"Services"
        }
    ],
    "sg:phone":"+1 231 755 2227",
    "sg:postcode":"49441",
    "sg:province":"MI",
    "sg:tags":[
        "yard"
    ],
    "wof:name":"Color Tyme",
    "wof:placetype":"venue"
},
  "geometry": {"coordinates":[-86.263165,43.205156],"type":"Point"}
}