{
  "type": "Feature",
  "properties": {
    "iso:country":"US",
    "sg:address":"471 W South St",
    "sg:city":"Kalamazoo",
    "sg:classifiers":[
        {
            "category":"Social Services",
            "type":"Services"
        }
    ],
    "sg:phone":"+1 269 384 3212",
    "sg:postcode":"49007",
    "sg:province":"MI",
    "sg:tags":[
        "counselor",
        "marriage",
        "family"
    ],
    "wof:name":"Susan Weaver Acsw",
    "wof:placetype":"venue"
},
  "geometry": {"coordinates":[-85.588391,42.289636],"type":"Point"}
}