{
  "type": "Feature",
  "properties": {
    "iso:country":"US",
    "sg:address":"520 13th St",
    "sg:city":"Three Rivers",
    "sg:classifiers":[
        {
            "category":"Home & Garden",
            "subcategory":"Mobile Homes",
            "type":"Retail Goods"
        }
    ],
    "sg:phone":"+1 269 278 8086",
    "sg:postcode":"49093",
    "sg:province":"MI",
    "wof:name":"New Generation Homes",
    "wof:placetype":"venue"
},
  "geometry": {"coordinates":[-85.618567,41.93814],"type":"Point"}
}