{
  "type": "Feature",
  "properties": {
    "iso:country":"US",
    "sg:address":"2359 W Shiawassee Ave",
    "sg:city":"Fenton",
    "sg:classifiers":[
        {
            "category":"Real Estate",
            "subcategory":"Real Estate Agent",
            "type":"Services"
        }
    ],
    "sg:phone":"+1 810 629 0680",
    "sg:postcode":"48430",
    "sg:province":"MI",
    "wof:name":"Prudential Chamberlain-Stiehl",
    "wof:placetype":"venue"
},
  "geometry": {"coordinates":[-83.72402200000001,42.787918],"type":"Point"}
}