{
  "type": "Feature",
  "properties": {
    "iso:country":"US",
    "sg:address":"3308 S Blissfield Hwy",
    "sg:city":"Blissfield",
    "sg:classifiers":[
        {
            "category":"Farming",
            "subcategory":"Farm",
            "type":"Manufacturing & Wholesale Goods"
        }
    ],
    "sg:phone":"+1 517 486 3627",
    "sg:postcode":"49228",
    "sg:province":"MI",
    "wof:name":"Eisenmann's Golden Acres",
    "wof:placetype":"venue"
},
  "geometry": {"coordinates":[-83.866338,41.871292],"type":"Point"}
}