{
  "type": "Feature",
  "properties": {
    "iso:country":"US",
    "sg:address":"800 Crystal Lake Blvd",
    "sg:city":"Iron Mountain",
    "sg:classifiers":[
        {
            "category":"Social Services",
            "type":"Services"
        }
    ],
    "sg:phone":"+1 906 774 8032",
    "sg:postcode":"49801",
    "sg:province":"MI",
    "sg:tags":[
        "senior",
        "citizen"
    ],
    "wof:name":"Family Ties Adult Day Care",
    "wof:placetype":"venue"
},
  "geometry": {"coordinates":[-88.07966399999999,45.814887],"type":"Point"}
}