{
  "type": "Feature",
  "properties": {
    "iso:country":"US",
    "sg:address":"517 Division Ave S",
    "sg:city":"Grand Rapids",
    "sg:classifiers":[
        {
            "category":"Local Transit",
            "type":"Transportation"
        }
    ],
    "sg:phone":"+1 616 392 7064",
    "sg:postcode":"49503",
    "sg:province":"MI",
    "sg:tags":[
        "ambulance"
    ],
    "wof:name":"American Medical Response",
    "wof:placetype":"venue"
},
  "geometry": {"coordinates":[-85.66768,42.95355],"type":"Point"}
}