{
  "type": "Feature",
  "properties": {
    "iso:country":"US",
    "sg:address":"8630 Stout St",
    "sg:city":"Detroit",
    "sg:classifiers":[
        {
            "category":"Banks & Credit Unions",
            "subcategory":"Financial Services",
            "type":"Services"
        }
    ],
    "sg:phone":"+1 313 945 5707",
    "sg:postcode":"48228",
    "sg:province":"MI",
    "sg:tags":[
        "broker",
        "mortgage"
    ],
    "wof:name":"First Chicago Home Equit",
    "wof:placetype":"venue"
},
  "geometry": {"coordinates":[-83.23936,42.356106],"type":"Point"}
}