{
  "type": "Feature",
  "properties": {
    "iso:country":"US",
    "sg:address":"29777 Telegraph Rd",
    "sg:city":"Southfield",
    "sg:classifiers":[
        {
            "category":"Government",
            "subcategory":"Office",
            "type":"Public Place"
        }
    ],
    "sg:phone":"+1 248 353 1003",
    "sg:postcode":"48034",
    "sg:province":"MI",
    "sg:tags":[
        "program",
        "administrative"
    ],
    "wof:name":"Frick Co The",
    "wof:placetype":"venue"
},
  "geometry": {"coordinates":[-83.2856,42.504591],"type":"Point"}
}