{
  "type": "Feature",
  "properties": {
    "iso:country":"US",
    "sg:address":"108 N Saginaw St",
    "sg:city":"Pontiac",
    "sg:classifiers":[
        {
            "category":"Shopping",
            "subcategory":"Hobbies, Toys, & Games",
            "type":"Retail Goods"
        }
    ],
    "sg:phone":"+1 248 334 8521",
    "sg:postcode":"48342",
    "sg:province":"MI",
    "sg:tags":[
        "equipment",
        "ceramic",
        "supply"
    ],
    "wof:name":"Ceramics By Bob & Hazel",
    "wof:placetype":"venue"
},
  "geometry": {"coordinates":[-83.29297099999999,42.639824],"type":"Point"}
}