{
  "type": "Feature",
  "properties": {
    "iso:country":"US",
    "sg:address":"39475 Lewis Dr Ste 150",
    "sg:city":"Novi",
    "sg:classifiers":[
        {
            "category":"Health Services",
            "subcategory":"Doctor",
            "type":"Services"
        }
    ],
    "sg:phone":"+1 248 324 2222",
    "sg:postcode":"48377",
    "sg:province":"MI",
    "sg:tags":[
        "dermatologist"
    ],
    "wof:name":"Great Lakes Dermatology",
    "wof:placetype":"venue"
},
  "geometry": {"coordinates":[-83.438356,42.506978],"type":"Point"}
}