{
  "type": "Feature",
  "properties": {
    "iso:country":"US",
    "sg:address":"9620 Wolven Ave NE",
    "sg:city":"Rockford",
    "sg:classifiers":[
        {
            "category":"Building & Trades",
            "subcategory":"Landscaping Services",
            "type":"Services"
        }
    ],
    "sg:phone":"+1 616 866 3611",
    "sg:postcode":"49341",
    "sg:province":"MI",
    "wof:name":"T and T Lawn Specialist",
    "wof:placetype":"venue"
},
  "geometry": {"coordinates":[-85.585857,43.13448],"type":"Point"}
}