{
  "type": "Feature",
  "properties": {
    "iso:country":"US",
    "sg:address":"31395 Fairfax Ave",
    "sg:city":"Beverly Hills",
    "sg:classifiers":[
        {
            "category":"Building & Trades",
            "subcategory":"Construction",
            "type":"Services"
        }
    ],
    "sg:phone":"+1 248 203 6654",
    "sg:postcode":"48025",
    "sg:province":"MI",
    "sg:tags":[
        "painter"
    ],
    "wof:name":"JDP Painting Inc",
    "wof:placetype":"venue"
},
  "geometry": {"coordinates":[-83.20717999999999,42.518783],"type":"Point"}
}