{
  "type": "Feature",
  "properties": {
    "iso:country":"US",
    "sg:address":"161 Ottawa Ave NW",
    "sg:city":"Grand Rapids",
    "sg:classifiers":[
        {
            "category":"Recreation",
            "type":"Entertainment"
        }
    ],
    "sg:phone":"+1 616 459 1300",
    "sg:postcode":"49503",
    "sg:province":"MI",
    "sg:tags":[
        "carnival"
    ],
    "sg:website":"www.festival-gr.org",
    "wof:name":"Festival",
    "wof:placetype":"venue"
},
  "geometry": {"coordinates":[-85.67011100000001,42.967049],"type":"Point"}
}