{
  "type": "Feature",
  "properties": {
    "iso:country":"US",
    "sg:address":"3767 S Evergreen Dr",
    "sg:city":"White Cloud",
    "sg:classifiers":[
        {
            "category":"Autos & Motor Vehicles",
            "subcategory":"Automobile Sales",
            "type":"Retail Goods"
        }
    ],
    "sg:phone":"+1 231 689 5303",
    "sg:postcode":"49349",
    "sg:province":"MI",
    "sg:tags":[
        "car",
        "dealer"
    ],
    "wof:name":"Q's Classic Preowned Autos",
    "wof:placetype":"venue"
},
  "geometry": {"coordinates":[-85.773445,43.487129],"type":"Point"}
}