{
  "type": "Feature",
  "properties": {
    "iso:country":"US",
    "sg:address":"27424 Harper Ave",
    "sg:city":"St Clair Shores",
    "sg:classifiers":[
        {
            "category":"Home & Garden",
            "subcategory":"Building Materials",
            "type":"Retail Goods"
        }
    ],
    "sg:phone":"+1 586 777 3222",
    "sg:postcode":"48081",
    "sg:province":"MI",
    "sg:tags":[
        "glass",
        "window",
        "plate"
    ],
    "wof:name":"A Touch Of Glass & Trim",
    "wof:placetype":"venue"
},
  "geometry": {"coordinates":[-82.89743300000001,42.49389],"type":"Point"}
}