{
  "type": "Feature",
  "properties": {
    "iso:country":"US",
    "sg:address":"1800 Pipestone Rd",
    "sg:city":"Benton Harbor",
    "sg:classifiers":[
        {
            "category":"Restaurant",
            "type":"Food & Drink"
        }
    ],
    "sg:phone":"+1 269 926 4260",
    "sg:postcode":"49022",
    "sg:province":"MI",
    "wof:name":"Subway Sandwiches & Salads",
    "wof:placetype":"venue"
},
  "geometry": {"coordinates":[-86.420851,42.08727],"type":"Point"}
}