{
  "type": "Feature",
  "properties": {
    "iso:country":"US",
    "sg:address":"549 Ottawa Ave NW",
    "sg:city":"Grand Rapids",
    "sg:classifiers":[
        {
            "category":"Professional",
            "subcategory":"Management & Consulting",
            "type":"Services"
        }
    ],
    "sg:phone":"+1 616 459 1752",
    "sg:postcode":"49503",
    "sg:province":"MI",
    "sg:tags":[
        "consultant",
        "educational"
    ],
    "wof:name":"Michigan Epic",
    "wof:placetype":"venue"
},
  "geometry": {"coordinates":[-85.67025,42.973034],"type":"Point"}
}