{
  "type": "Feature",
  "properties": {
    "iso:country":"US",
    "sg:address":"510 Apple Tree Dr",
    "sg:city":"Ionia",
    "sg:classifiers":[
        {
            "category":"Manufacturing",
            "subcategory":"Metals",
            "type":"Manufacturing & Wholesale Goods"
        }
    ],
    "sg:phone":"+1 616 527 5555",
    "sg:postcode":"48846",
    "sg:province":"MI",
    "sg:tags":[
        "coating"
    ],
    "sg:website":"www.volcor.com",
    "wof:name":"Volcor Finishing Inc",
    "wof:placetype":"venue"
},
  "geometry": {"coordinates":[-85.072254,42.997256],"type":"Point"}
}