{
  "type": "Feature",
  "properties": {
    "iso:country":"US",
    "sg:address":"1965 Devonshire Dr",
    "sg:city":"Wixom",
    "sg:classifiers":[
        {
            "category":"Professional",
            "type":"Services"
        }
    ],
    "sg:phone":"+1 248 669 9872",
    "sg:postcode":"48393",
    "sg:province":"MI",
    "wof:name":"J Comm Inc",
    "wof:placetype":"venue"
},
  "geometry": {"coordinates":[-83.55467899999999,42.550146],"type":"Point"}
}