{
  "type": "Feature",
  "properties": {
    "iso:country":"US",
    "sg:address":"4695 Indianwood Ct",
    "sg:city":"Clarkston",
    "sg:classifiers":[
        {
            "category":"Building & Trades",
            "subcategory":"Construction",
            "type":"Services"
        }
    ],
    "sg:phone":"+1 248 969 0315",
    "sg:postcode":"48348",
    "sg:province":"MI",
    "sg:tags":[
        "home",
        "builder",
        "custom"
    ],
    "wof:name":"Riviera Construction Inc",
    "wof:placetype":"venue"
},
  "geometry": {"coordinates":[-83.340186,42.787875],"type":"Point"}
}