{
  "type": "Feature",
  "properties": {
    "iso:country":"US",
    "sg:address":"3949 Country Way",
    "sg:city":"Hartland",
    "sg:classifiers":[
        {
            "category":"Building & Trades",
            "subcategory":"Cleaning & Sanitation",
            "type":"Services"
        }
    ],
    "sg:phone":"+1 810 632 5098",
    "sg:postcode":"48353",
    "sg:province":"MI",
    "sg:tags":[
        "maintenance"
    ],
    "wof:name":"Thunder Mop Maintenance Co",
    "wof:placetype":"venue"
},
  "geometry": {"coordinates":[-83.74228599999999,42.66246],"type":"Point"}
}