{
  "type": "Feature",
  "properties": {
    "iso:country":"US",
    "sg:address":"25890 Hudson St",
    "sg:city":"Roseville",
    "sg:classifiers":[
        {
            "category":"Real Estate",
            "subcategory":"Real Estate Agent",
            "type":"Services"
        }
    ],
    "sg:phone":"+1 586 598 8191",
    "sg:postcode":"48066",
    "sg:province":"MI",
    "wof:name":"American United Realty",
    "wof:placetype":"venue"
},
  "geometry": {"coordinates":[-82.950948,42.486199],"type":"Point"}
}