{
  "type": "Feature",
  "properties": {
    "iso:country":"US",
    "sg:address":"2100 Plank Rd",
    "sg:city":"Cottrellville",
    "sg:classifiers":[
        {
            "category":"Retail",
            "subcategory":"Auto Repair",
            "type":"Services"
        }
    ],
    "sg:phone":"+1 810 765 1899",
    "sg:postcode":"48039",
    "sg:province":"MI",
    "sg:tags":[
        "transmission"
    ],
    "wof:name":"Transmission Physicians Inc",
    "wof:placetype":"venue"
},
  "geometry": {"coordinates":[-82.51023000000001,42.720488],"type":"Point"}
}