{
  "type": "Feature",
  "properties": {
    "iso:country":"US",
    "sg:address":"850 Green Hills Dr",
    "sg:city":"Ann Arbor",
    "sg:classifiers":[
        {
            "category":"Education",
            "subcategory":"School",
            "type":"Public Place"
        }
    ],
    "sg:phone":"+1 734 769 4010",
    "sg:postcode":"48105",
    "sg:province":"MI",
    "wof:name":"Greenhills School",
    "wof:placetype":"venue"
},
  "geometry": {"coordinates":[-83.68051699999999,42.284383],"type":"Point"}
}