{
  "type": "Feature",
  "properties": {
    "iso:country":"US",
    "sg:address":"8775 Hall Rd",
    "sg:city":"Utica",
    "sg:classifiers":[
        {
            "category":"Shopping",
            "subcategory":"Tobacco",
            "type":"Retail Goods"
        }
    ],
    "sg:phone":"+1 586 739 1370",
    "sg:postcode":"48317",
    "sg:province":"MI",
    "sg:tags":[
        "shop"
    ],
    "wof:name":"My Smoker",
    "wof:placetype":"venue"
},
  "geometry": {"coordinates":[-83.024041,42.626078],"type":"Point"}
}