{
  "type": "Feature",
  "properties": {
    "iso:country":"US",
    "sg:address":"15321 Archdale St",
    "sg:city":"Detroit",
    "sg:classifiers":[
        {
            "category":"Real Estate",
            "subcategory":"Real Estate Operator",
            "type":"Services"
        }
    ],
    "sg:phone":"+1 313 273 1208",
    "sg:postcode":"48227",
    "sg:province":"MI",
    "sg:tags":[
        "building",
        "apartment"
    ],
    "wof:name":"Faith Manor Apartments",
    "wof:placetype":"venue"
},
  "geometry": {"coordinates":[-83.216342,42.402589],"type":"Point"}
}