{
  "type": "Feature",
  "properties": {
    "iso:country":"US",
    "sg:address":"2959 Leyton Ct",
    "sg:city":"Rochester Hills",
    "sg:classifiers":[
        {
            "category":"Professional",
            "subcategory":"Engineering",
            "type":"Services"
        }
    ],
    "sg:phone":"+1 248 651 7929",
    "sg:postcode":"48306",
    "sg:province":"MI",
    "sg:tags":[
        "engineer"
    ],
    "wof:name":"Crawford Technologies Inc",
    "wof:placetype":"venue"
},
  "geometry": {"coordinates":[-83.193349,42.702582],"type":"Point"}
}