{
  "type": "Feature",
  "properties": {
    "iso:country":"US",
    "sg:address":"118 N Lake St",
    "sg:city":"Rogers City",
    "sg:classifiers":[
        {
            "category":"Government",
            "subcategory":"Office",
            "type":"Public Place"
        }
    ],
    "sg:phone":"+1 989 734 2928",
    "sg:postcode":"49779",
    "sg:province":"MI",
    "sg:tags":[
        "village"
    ],
    "wof:name":"Rogers City Pump House 4",
    "wof:placetype":"venue"
},
  "geometry": {"coordinates":[-83.81361800000001,45.422038],"type":"Point"}
}