{
  "type": "Feature",
  "properties": {
    "iso:country":"US",
    "sg:address":"634 Island Rd",
    "sg:city":"Grass Lake",
    "sg:classifiers":[
        {
            "category":"Professional",
            "subcategory":"Computer Services",
            "type":"Services"
        }
    ],
    "sg:phone":"+1 517 522 6005",
    "sg:postcode":"49240",
    "sg:province":"MI",
    "sg:tags":[
        "related"
    ],
    "wof:name":"Rogan Associates LTD",
    "wof:placetype":"venue"
},
  "geometry": {"coordinates":[-84.21688899999999,42.266664],"type":"Point"}
}