{
  "type": "Feature",
  "properties": {
    "iso:country":"US",
    "sg:address":"201 E Washington St",
    "sg:city":"Hale",
    "sg:classifiers":[
        {
            "category":"Shopping",
            "subcategory":"Used Merchandise",
            "type":"Retail Goods"
        }
    ],
    "sg:phone":"+1 989 728 2538",
    "sg:postcode":"48730",
    "sg:province":"MI",
    "sg:tags":[
        "antique"
    ],
    "wof:name":"Elsie's Hale Creek Antiques",
    "wof:placetype":"venue"
},
  "geometry": {"coordinates":[-83.489301,44.284667],"type":"Point"}
}