{
  "type": "Feature",
  "properties": {
    "iso:country":"US",
    "sg:address":"2793 University Dr",
    "sg:city":"Rochester",
    "sg:classifiers":[
        {
            "category":"Professional",
            "subcategory":"Computer Services",
            "type":"Services"
        }
    ],
    "sg:phone":"+1 248 475 0811",
    "sg:postcode":"48326",
    "sg:province":"MI",
    "sg:tags":[
        "datum"
    ],
    "wof:name":"Data Whiz",
    "wof:placetype":"venue"
},
  "geometry": {"coordinates":[-83.232866,42.669857],"type":"Point"}
}