{
  "type": "Feature",
  "properties": {
    "iso:country":"US",
    "sg:address":"10650 E Maple Rd",
    "sg:city":"Pewamo",
    "sg:classifiers":[
        {
            "category":"Farming",
            "subcategory":"Dairy Farm",
            "type":"Manufacturing & Wholesale Goods"
        }
    ],
    "sg:phone":"+1 989 587 6735",
    "sg:postcode":"48873",
    "sg:province":"MI",
    "wof:name":"Diary Farms",
    "wof:placetype":"venue"
},
  "geometry": {"coordinates":[-84.86548999999999,42.943641],"type":"Point"}
}