{
  "type": "Feature",
  "properties": {
    "iso:country":"US",
    "sg:address":"33111 Schoenherr Rd",
    "sg:city":"Sterling Heights",
    "sg:classifiers":[
        {
            "category":"Shopping",
            "subcategory":"Party Supplies",
            "type":"Retail Goods"
        },
        {
            "category":"Personal",
            "type":"Services"
        }
    ],
    "sg:phone":"+1 586 939 4320",
    "sg:postcode":"48312",
    "sg:province":"MI",
    "sg:tags":[
        "planning",
        "event"
    ],
    "wof:name":"Frank's Liquor",
    "wof:placetype":"venue"
},
  "geometry": {"coordinates":[-82.98896999999999,42.538942],"type":"Point"}
}