{
  "type": "Feature",
  "properties": {
    "iso:country":"US",
    "sg:address":"2300 E 8 Mile Rd",
    "sg:city":"Detroit",
    "sg:classifiers":[
        {
            "category":"Banks & Credit Unions",
            "subcategory":"Bank",
            "type":"Services"
        }
    ],
    "sg:phone":"+1 313 366 9524",
    "sg:postcode":"48234",
    "sg:province":"MI",
    "wof:name":"Standard Federal Bank",
    "wof:placetype":"venue"
},
  "geometry": {"coordinates":[-83.078598,42.446999],"type":"Point"}
}