{
  "type": "Feature",
  "properties": {
    "iso:country":"US",
    "sg:address":"65 S Airport Rd W",
    "sg:city":"Traverse City",
    "sg:classifiers":[
        {
            "category":"Retail",
            "subcategory":"Repair Shop",
            "type":"Services"
        }
    ],
    "sg:phone":"+1 231 941 1719",
    "sg:postcode":"49686",
    "sg:province":"MI",
    "sg:tags":[
        "upholsterer"
    ],
    "wof:name":"Stuff It Upholstery",
    "wof:placetype":"venue"
},
  "geometry": {"coordinates":[-85.581858,44.733147],"type":"Point"}
}