{
  "type": "Feature",
  "properties": {
    "iso:country":"US",
    "sg:address":"2215 Oak Industrial Dr NE",
    "sg:city":"Grand Rapids",
    "sg:classifiers":[
        {
            "category":"Professional",
            "subcategory":"Employment Agencies",
            "type":"Services"
        }
    ],
    "sg:phone":"+1 616 776 6866",
    "sg:postcode":"49505",
    "sg:province":"MI",
    "sg:tags":[
        "opportunity"
    ],
    "wof:name":"Foodservice Careers LLC",
    "wof:placetype":"venue"
},
  "geometry": {"coordinates":[-85.61051500000001,42.974774],"type":"Point"}
}