{
  "type": "Feature",
  "properties": {
    "iso:country":"US",
    "sg:address":"2459 Mayfair Dr",
    "sg:city":"White Lake",
    "sg:classifiers":[
        {
            "category":"Professional",
            "subcategory":"Lawyer & Legal Services",
            "type":"Services"
        }
    ],
    "sg:phone":"+1 248 685 3008",
    "sg:postcode":"48383",
    "sg:province":"MI",
    "wof:name":"Eads John T Lll P C",
    "wof:placetype":"venue"
},
  "geometry": {"coordinates":[-83.522346,42.618306],"type":"Point"}
}