{
  "type": "Feature",
  "properties": {
    "iso:country":"US",
    "sg:address":"10246 S West-Bay Shore Dr",
    "sg:city":"Traverse City",
    "sg:classifiers":[
        {
            "category":"Building & Trades",
            "subcategory":"Construction",
            "type":"Services"
        }
    ],
    "sg:phone":"+1 231 922 0669",
    "sg:postcode":"49684",
    "sg:province":"MI",
    "sg:tags":[
        "concrete",
        "contractor"
    ],
    "wof:name":"Americrete",
    "wof:placetype":"venue"
},
  "geometry": {"coordinates":[-85.651495,44.830936],"type":"Point"}
}