{
  "type": "Feature",
  "properties": {
    "iso:country":"US",
    "sg:address":"700 Washington Ave",
    "sg:city":"Grand Haven",
    "sg:classifiers":[
        {
            "category":"Health Services",
            "subcategory":"Doctor",
            "type":"Services"
        }
    ],
    "sg:phone":"+1 616 844 4026",
    "sg:postcode":"49417",
    "sg:province":"MI",
    "sg:tags":[
        "medical"
    ],
    "wof:name":"Robin Hood Nursing Home",
    "wof:placetype":"venue"
},
  "geometry": {"coordinates":[-86.221418,43.061091],"type":"Point"}
}