{
  "type": "Feature",
  "properties": {
    "iso:country":"US",
    "sg:address":"1453 S Washington Ave",
    "sg:city":"Royal Oak",
    "sg:classifiers":[
        {
            "category":"Education",
            "subcategory":"Special Training",
            "type":"Public Place"
        }
    ],
    "sg:phone":"+1 248 320 7616",
    "sg:postcode":"48067",
    "sg:province":"MI",
    "sg:tags":[
        "reading",
        "instruction",
        "improvement"
    ],
    "wof:name":"Tutoring Services Inc",
    "wof:placetype":"venue"
},
  "geometry": {"coordinates":[-83.146079,42.477501],"type":"Point"}
}