{
  "type": "Feature",
  "properties": {
    "iso:country":"US",
    "sg:address":"21740 W Cannonsville Rd",
    "sg:city":"Pierson",
    "sg:classifiers":[
        {
            "category":"Wholesale",
            "subcategory":"Machinery & Supplies",
            "type":"Manufacturing & Wholesale Goods"
        }
    ],
    "sg:phone":"+1 616 636 4740",
    "sg:postcode":"49339",
    "sg:province":"MI",
    "sg:tags":[
        "contractor"
    ],
    "sg:website":"www.midmichiganequip.com",
    "wof:name":"Mid Michigan Equipment Sales",
    "wof:placetype":"venue"
},
  "geometry": {"coordinates":[-85.51411,43.337742],"type":"Point"}
}