{
  "type": "Feature",
  "properties": {
    "iso:country":"US",
    "sg:address":"37694 W 12 Mile Rd",
    "sg:city":"Farmington Hills",
    "sg:classifiers":[
        {
            "category":"Shopping",
            "subcategory":"Party Supplies",
            "type":"Retail Goods"
        },
        {
            "category":"Personal",
            "type":"Services"
        }
    ],
    "sg:phone":"+1 248 324 1795",
    "sg:postcode":"48331",
    "sg:province":"MI",
    "sg:tags":[
        "planning",
        "event"
    ],
    "wof:name":"Fabulous Party Cards & Gifts",
    "wof:placetype":"venue"
},
  "geometry": {"coordinates":[-83.419026,42.497883],"type":"Point"}
}