{
  "type": "Feature",
  "properties": {
    "iso:country":"US",
    "sg:address":"440 Erie St",
    "sg:city":"Adrian",
    "sg:classifiers":[
        {
            "category":"Food & Beverages",
            "subcategory":"Groceries & Convenience Stores",
            "type":"Retail Goods"
        }
    ],
    "sg:phone":"+1 517 265 8730",
    "sg:postcode":"49221",
    "sg:province":"MI",
    "sg:tags":[
        "grocer"
    ],
    "wof:name":"Diana Market",
    "wof:placetype":"venue"
},
  "geometry": {"coordinates":[-84.02973900000001,41.894532],"type":"Point"}
}