{
  "type": "Feature",
  "properties": {
    "iso:country":"US",
    "sg:address":"1170 W Oakley Park Rd",
    "sg:city":"Commerce Twp",
    "sg:classifiers":[
        {
            "category":"Shopping",
            "type":"Retail Goods"
        },
        {
            "category":"Professional",
            "subcategory":"Management & Consulting",
            "type":"Services"
        }
    ],
    "sg:phone":"+1 248 624 5360",
    "sg:postcode":"48390",
    "sg:province":"MI",
    "sg:tags":[
        "consultant",
        "training",
        "merchandise"
    ],
    "wof:name":"Cross Training Inc",
    "wof:placetype":"venue"
},
  "geometry": {"coordinates":[-83.49635000000001,42.569131],"type":"Point"}
}