{
  "type": "Feature",
  "properties": {
    "iso:country":"US",
    "sg:address":"10580 N Dr N",
    "sg:city":"Battle Creek",
    "sg:classifiers":[
        {
            "category":"Recreation",
            "type":"Entertainment"
        }
    ],
    "sg:phone":"+1 269 963 3925",
    "sg:postcode":"49014",
    "sg:province":"MI",
    "sg:tags":[
        "paint",
        "ball",
        "sport"
    ],
    "sg:website":"www.bcsplat.com",
    "wof:name":"Excalibur Paintball",
    "wof:placetype":"venue"
},
  "geometry": {"coordinates":[-85.090653,42.34799],"type":"Point"}
}