{
  "type": "Feature",
  "properties": {
    "iso:country":"US",
    "sg:address":"76 Wood Rd",
    "sg:city":"Marlette",
    "sg:classifiers":[
        {
            "category":"Health Services",
            "subcategory":"Clinic",
            "type":"Services"
        }
    ],
    "sg:phone":"+1 989 635 3051",
    "sg:postcode":"48453",
    "sg:province":"MI",
    "wof:name":"Custom Medical Service",
    "wof:placetype":"venue"
},
  "geometry": {"coordinates":[-83.027855,43.413676],"type":"Point"}
}