{
  "type": "Feature",
  "properties": {
    "iso:country":"US",
    "sg:address":"7555 Byron Center Ave SW",
    "sg:city":"Byron Center",
    "sg:classifiers":[
        {
            "category":"Education",
            "subcategory":"Special Training",
            "type":"Public Place"
        }
    ],
    "sg:phone":"+1 616 878 9472",
    "sg:postcode":"49315",
    "sg:province":"MI",
    "wof:name":"Zion Christian School",
    "wof:placetype":"venue"
},
  "geometry": {"coordinates":[-85.723067,42.829778],"type":"Point"}
}