{
  "type": "Feature",
  "properties": {
    "iso:country":"US",
    "sg:address":"1505 N Monroe St",
    "sg:city":"Monroe",
    "sg:classifiers":[
        {
            "category":"Shopping",
            "subcategory":"Clothing, Apparel, & Fashions",
            "type":"Retail Goods"
        }
    ],
    "sg:phone":"+1 734 242 7571",
    "sg:postcode":"48162",
    "sg:province":"MI",
    "wof:name":"Beauty Aisle",
    "wof:placetype":"venue"
},
  "geometry": {"coordinates":[-83.38995799999999,41.935528],"type":"Point"}
}