{
  "type": "Feature",
  "properties": {
    "iso:country":"US",
    "sg:address":"36395 Co Rd 687",
    "sg:city":"Bangor",
    "sg:classifiers":[
        {
            "category":"Retail",
            "subcategory":"Repair Shop",
            "type":"Services"
        }
    ],
    "sg:phone":"+1 269 926 2825",
    "sg:postcode":"49013",
    "sg:province":"MI",
    "sg:tags":[
        "plumbing",
        "drain",
        "cleaning",
        "sewer"
    ],
    "wof:name":"Harold Ballard Sewer Cleaning",
    "wof:placetype":"venue"
},
  "geometry": {"coordinates":[-86.167095,42.285761],"type":"Point"}
}