{
  "type": "Feature",
  "properties": {
    "iso:country":"US",
    "sg:address":"6150 Division Ave S",
    "sg:city":"Grand Rapids",
    "sg:classifiers":[
        {
            "category":"Building & Trades",
            "subcategory":"Construction",
            "type":"Services"
        }
    ],
    "sg:phone":"+1 616 534 4967",
    "sg:postcode":"49548",
    "sg:province":"MI",
    "wof:name":"Southwest Housing",
    "wof:placetype":"venue"
},
  "geometry": {"coordinates":[-85.66372200000001,42.851931],"type":"Point"}
}