{
  "type": "Feature",
  "properties": {
    "iso:country":"US",
    "sg:address":"2242 N Hilltop Dr",
    "sg:city":"Muskegon",
    "sg:classifiers":[
        {
            "category":"Professional",
            "subcategory":"Business Services",
            "type":"Services"
        }
    ],
    "sg:phone":"+1 231 755 1421",
    "sg:postcode":"49441",
    "sg:province":"MI",
    "wof:name":"Demos Unlimited Corp",
    "wof:placetype":"venue"
},
  "geometry": {"coordinates":[-86.30054199999999,43.18173],"type":"Point"}
}