{
  "type": "Feature",
  "properties": {
    "iso:country":"US",
    "sg:address":"721 E 9 Mile Rd",
    "sg:city":"Ferndale",
    "sg:classifiers":[
        {
            "category":"Restaurant",
            "type":"Food & Drink"
        }
    ],
    "sg:phone":"+1 248 542 6860",
    "sg:postcode":"48220",
    "sg:province":"MI",
    "sg:tags":[
        "thai"
    ],
    "wof:name":"Thai Garden Restaurant",
    "wof:placetype":"venue"
},
  "geometry": {"coordinates":[-83.1241,42.460999],"type":"Point"}
}