{
  "type": "Feature",
  "properties": {
    "iso:country":"US",
    "sg:address":"9460 Central St",
    "sg:city":"Detroit",
    "sg:classifiers":[
        {
            "category":"Utilities",
            "subcategory":"Refuse",
            "type":"Services"
        },
        {
            "category":"Transit Center",
            "subcategory":"Freight",
            "type":"Transportation"
        },
        {
            "category":"Freight",
            "type":"Transportation"
        }
    ],
    "sg:phone":"+1 313 933 0728",
    "sg:postcode":"48204",
    "sg:province":"MI",
    "sg:tags":[
        "local",
        "truck",
        "trucking-motor",
        "dump",
        "trucking"
    ],
    "wof:name":"Gipson Brothers Trucking",
    "wof:placetype":"venue"
},
  "geometry": {"coordinates":[-83.146512,42.366271],"type":"Point"}
}