{
  "type": "Feature",
  "properties": {
    "iso:country":"US",
    "sg:address":"1395 Folkstone Ct",
    "sg:city":"Ann Arbor",
    "sg:classifiers":[
        {
            "category":"Building & Trades",
            "subcategory":"Construction",
            "type":"Services"
        }
    ],
    "sg:phone":"+1 734 994 0680",
    "sg:postcode":"48105",
    "sg:province":"MI",
    "sg:tags":[
        "residential"
    ],
    "wof:name":"D K Woolley LLC",
    "wof:placetype":"venue"
},
  "geometry": {"coordinates":[-83.68588699999999,42.292206],"type":"Point"}
}