{
  "type": "Feature",
  "properties": {
    "iso:country":"US",
    "sg:address":"413 Wildwood Cir",
    "sg:city":"Tecumseh",
    "sg:classifiers":[
        {
            "category":"Professional",
            "type":"Services"
        }
    ],
    "sg:phone":"+1 517 423 8942",
    "sg:postcode":"49286",
    "sg:province":"MI",
    "wof:name":"Crystal Clear Public",
    "wof:placetype":"venue"
},
  "geometry": {"coordinates":[-83.970353,42.018549],"type":"Point"}
}