{
  "type": "Feature",
  "properties": {
    "iso:country":"US",
    "sg:address":"189 S Maple St",
    "sg:city":"Grant",
    "sg:classifiers":[
        {
            "category":"Bars & Pubs",
            "type":"Food & Drink"
        }
    ],
    "sg:phone":"+1 231 834 5535",
    "sg:postcode":"49327",
    "sg:province":"MI",
    "wof:name":"Tin Lizzy's",
    "wof:placetype":"venue"
},
  "geometry": {"coordinates":[-85.810632,43.333101],"type":"Point"}
}