{
  "type": "Feature",
  "properties": {
    "iso:country":"US",
    "sg:address":"2638 Browning Dr",
    "sg:city":"Lake Orion",
    "sg:classifiers":[
        {
            "category":"Education",
            "subcategory":"Special Training",
            "type":"Public Place"
        }
    ],
    "sg:phone":"+1 248 391 5957",
    "sg:postcode":"48360",
    "sg:province":"MI",
    "wof:name":"Personal Growth Institute",
    "wof:placetype":"venue"
},
  "geometry": {"coordinates":[-83.301337,42.743945],"type":"Point"}
}