{
  "type": "Feature",
  "properties": {
    "iso:country":"US",
    "sg:address":"615 E University Ave",
    "sg:city":"Ann Arbor",
    "sg:classifiers":[
        {
            "category":"Restaurant",
            "type":"Food & Drink"
        }
    ],
    "sg:menulink":"http://www.allmenus.com/mi/ann-arbor/247979-zas-custom-pastas/menu/",
    "sg:phone":"+1 734 555 1211",
    "sg:postcode":"48104",
    "sg:province":"MI",
    "sg:tags":[
        "italian"
    ],
    "wof:name":"Za's Custom Pastas",
    "wof:placetype":"venue"
},
  "geometry": {"coordinates":[-83.735749,42.273812],"type":"Point"}
}