{
  "type": "Feature",
  "properties": {
    "iso:country":"US",
    "sg:address":"714 E Apple Ave",
    "sg:city":"Muskegon",
    "sg:classifiers":[
        {
            "category":"Health Services",
            "subcategory":"Chiropractor",
            "type":"Services"
        }
    ],
    "sg:phone":"+1 231 726 6185",
    "sg:postcode":"49442",
    "sg:province":"MI",
    "wof:name":"Muskegon Chiropractic Ctr",
    "wof:placetype":"venue"
},
  "geometry": {"coordinates":[-86.226789,43.23425],"type":"Point"}
}