{
  "type": "Feature",
  "properties": {
    "iso:country":"US",
    "sg:address":"12918 Michigan Ave",
    "sg:city":"Dearborn",
    "sg:classifiers":[
        {
            "category":"Restaurant",
            "type":"Food & Drink"
        }
    ],
    "sg:menulink":"http://www.allmenus.com/mi/dearborn/10545-la-shish/menu/",
    "sg:phone":"+1 313 584 4477",
    "sg:postcode":"48126",
    "sg:province":"MI",
    "sg:tags":[
        "mediterranean"
    ],
    "wof:name":"La Shish",
    "wof:placetype":"venue"
},
  "geometry": {"coordinates":[-83.169141,42.324294],"type":"Point"}
}