{
  "type": "Feature",
  "properties": {
    "iso:country":"US",
    "sg:address":"2335 Glen Valley Dr NW",
    "sg:city":"Grand Rapids",
    "sg:classifiers":[
        {
            "category":"Building & Trades",
            "subcategory":"Construction",
            "type":"Services"
        }
    ],
    "sg:phone":"+1 616 784 2420",
    "sg:postcode":"49544",
    "sg:province":"MI",
    "sg:tags":[
        "home",
        "builder"
    ],
    "wof:name":"Ron Vandenbrand Builder",
    "wof:placetype":"venue"
},
  "geometry": {"coordinates":[-85.700659,43.008411],"type":"Point"}
}