{
  "type": "Feature",
  "properties": {
    "iso:country":"US",
    "sg:address":"2150 Chevrolet St",
    "sg:city":"Ypsilanti",
    "sg:classifiers":[
        {
            "category":"Professional",
            "subcategory":"Business Services",
            "type":"Services"
        }
    ],
    "sg:phone":"+1 734 320 8648",
    "sg:postcode":"48198",
    "sg:province":"MI",
    "sg:tags":[
        "support"
    ],
    "wof:name":"Virtual Consulting Associates",
    "wof:placetype":"venue"
},
  "geometry": {"coordinates":[-83.569453,42.22853],"type":"Point"}
}