{
  "type": "Feature",
  "properties": {
    "iso:country":"US",
    "sg:address":"9413 Woodland Ct",
    "sg:city":"Davison",
    "sg:classifiers":[
        {
            "category":"Manufacturing",
            "subcategory":"Apparel",
            "type":"Manufacturing & Wholesale Goods"
        }
    ],
    "sg:phone":"+1 810 653 0994",
    "sg:postcode":"48423",
    "sg:province":"MI",
    "sg:tags":[
        "sewing",
        "contractor"
    ],
    "wof:name":"Carol's Creative Stitchery",
    "wof:placetype":"venue"
},
  "geometry": {"coordinates":[-83.520083,43.058595],"type":"Point"}
}