{
  "type": "Feature",
  "properties": {
    "iso:country":"US",
    "sg:address":"72 W Maple Rd",
    "sg:city":"Troy",
    "sg:classifiers":[
        {
            "category":"Restaurant",
            "type":"Food & Drink"
        }
    ],
    "sg:menulink":"http://www.allmenus.com/mi/troy/48459-priya-indian-cuisine/menu/",
    "sg:phone":"+1 248 269 0100",
    "sg:postcode":"48084",
    "sg:province":"MI",
    "sg:tags":[
        "indian",
        "asian"
    ],
    "wof:name":"Priya Indian Cuisine",
    "wof:placetype":"venue"
},
  "geometry": {"coordinates":[-83.150053,42.548269],"type":"Point"}
}