{
  "type": "Feature",
  "properties": {
    "iso:country":"US",
    "sg:address":"2510 Old US Hwy 23",
    "sg:city":"Howell",
    "sg:classifiers":[
        {
            "category":"Building & Trades",
            "subcategory":"Plumbing",
            "type":"Services"
        }
    ],
    "sg:phone":"+1 810 632 9722",
    "sg:postcode":"48843",
    "sg:province":"MI",
    "sg:tags":[
        "contractor"
    ],
    "wof:name":"Kenneth W Kanitz",
    "wof:placetype":"venue"
},
  "geometry": {"coordinates":[-83.75558599999999,42.647681],"type":"Point"}
}