{
  "type": "Feature",
  "properties": {
    "iso:country":"US",
    "sg:address":"760 E Spruce St",
    "sg:city":"Sault Ste Marie",
    "sg:classifiers":[
        {
            "category":"Building & Trades",
            "subcategory":"Plumbing",
            "type":"Services"
        }
    ],
    "sg:phone":"+1 906 632 0760",
    "sg:postcode":"49783",
    "sg:province":"MI",
    "sg:tags":[
        "heating",
        "contractor"
    ],
    "wof:name":"Don Earl Heating & Air Cond",
    "wof:placetype":"venue"
},
  "geometry": {"coordinates":[-84.333033,46.492539],"type":"Point"}
}