{
  "type": "Feature",
  "properties": {
    "iso:country":"US",
    "sg:address":"3744 Eaton Gate Ln",
    "sg:city":"Auburn Hills",
    "sg:classifiers":[
        {
            "category":"Home & Garden",
            "subcategory":"Home Furnishings",
            "type":"Retail Goods"
        }
    ],
    "sg:phone":"+1 248 852 0634",
    "sg:postcode":"48326",
    "sg:province":"MI",
    "sg:tags":[
        "window",
        "covering"
    ],
    "wof:name":"Windows Of Opportunity Inc",
    "wof:placetype":"venue"
},
  "geometry": {"coordinates":[-83.21366,42.623662],"type":"Point"}
}