{
  "type": "Feature",
  "properties": {
    "iso:country":"US",
    "sg:address":"38365 Lowell Dr",
    "sg:city":"Farmington Hills",
    "sg:classifiers":[
        {
            "category":"Wholesale",
            "subcategory":"Durable Goods & Equipment",
            "type":"Manufacturing & Wholesale Goods"
        }
    ],
    "sg:phone":"+1 248 788 8108",
    "sg:postcode":"48331",
    "sg:province":"MI",
    "sg:tags":[
        "importer"
    ],
    "wof:name":"Judaica Imports Intl Inc",
    "wof:placetype":"venue"
},
  "geometry": {"coordinates":[-83.427217,42.524663],"type":"Point"}
}