{
  "type": "Feature",
  "properties": {
    "iso:country":"US",
    "sg:address":"34427 Jefferson Ave",
    "sg:city":"Harrison Township",
    "sg:classifiers":[
        {
            "category":"Food & Beverages",
            "subcategory":"Meat & Fish",
            "type":"Retail Goods"
        }
    ],
    "sg:phone":"+1 586 792 1820",
    "sg:postcode":"48045",
    "sg:province":"MI",
    "sg:tags":[
        "shop"
    ],
    "wof:name":"Durocs Quality Meat",
    "wof:placetype":"venue"
},
  "geometry": {"coordinates":[-82.858299,42.544399],"type":"Point"}
}