{
  "type": "Feature",
  "properties": {
    "iso:country":"US",
    "sg:address":"1380 E Jefferson",
    "sg:city":"Detroit",
    "sg:classifiers":[
        {
            "category":"Professional",
            "subcategory":"Art Services",
            "type":"Services"
        },
        {
            "category":"Communications",
            "type":"Services"
        }
    ],
    "sg:phone":"+1 313 259 3458",
    "sg:postcode":"48207",
    "sg:province":"MI",
    "sg:tags":[
        "web",
        "graphic",
        "design"
    ],
    "sg:website":"www.marketwithpandora.com",
    "wof:name":"Pandora Outside the Box Marketing",
    "wof:placetype":"venue"
},
  "geometry": {"coordinates":[-83.03246300000001,42.333454],"type":"Point"}
}