{
  "type": "Feature",
  "properties": {
    "iso:country":"US",
    "sg:address":"3301 N Pontiac Trl",
    "sg:city":"Commerce Twp",
    "sg:classifiers":[
        {
            "category":"Utilities",
            "subcategory":"Mobile Phone",
            "type":"Services"
        }
    ],
    "sg:phone":"+1 248 538 9900",
    "sg:postcode":"48390",
    "sg:province":"MI",
    "sg:tags":[
        "telephone",
        "cellular"
    ],
    "wof:name":"Verizon Wireless",
    "wof:placetype":"venue"
},
  "geometry": {"coordinates":[-83.440862,42.558568],"type":"Point"}
}