{
  "type": "Feature",
  "properties": {
    "iso:country":"US",
    "sg:address":"2300 E Michigan Ave",
    "sg:city":"Lansing",
    "sg:classifiers":[
        {
            "category":"Shopping",
            "subcategory":"Clothing, Apparel, & Fashions",
            "type":"Retail Goods"
        }
    ],
    "sg:phone":"+1 517 484 9199",
    "sg:postcode":"48912",
    "sg:province":"MI",
    "sg:tags":[
        "theatrical",
        "costume"
    ],
    "wof:name":"Costumes By Lansing Civic",
    "wof:placetype":"venue"
},
  "geometry": {"coordinates":[-84.517544,42.733639],"type":"Point"}
}