{
  "type": "Feature",
  "properties": {
    "iso:country":"US",
    "sg:address":"1507 W Lake Dr",
    "sg:city":"Novi",
    "sg:classifiers":[
        {
            "category":"Building & Trades",
            "subcategory":"Construction",
            "type":"Services"
        }
    ],
    "sg:phone":"+1 248 624 6499",
    "sg:postcode":"48377",
    "sg:province":"MI",
    "sg:tags":[
        "project"
    ],
    "wof:name":"Compass Construction Co",
    "wof:placetype":"venue"
},
  "geometry": {"coordinates":[-83.488164,42.522441],"type":"Point"}
}