{
  "type": "Feature",
  "properties": {
    "iso:country":"US",
    "sg:address":"2134 E Walton Blvd",
    "sg:city":"Auburn Hills",
    "sg:classifiers":[
        {
            "category":"Retail",
            "subcategory":"Car Wash",
            "type":"Services"
        }
    ],
    "sg:phone":"+1 248 373 3530",
    "sg:postcode":"48326",
    "sg:province":"MI",
    "sg:tags":[
        "polishing",
        "washing"
    ],
    "wof:name":"Grand Prix Auto Wash",
    "wof:placetype":"venue"
},
  "geometry": {"coordinates":[-83.246669,42.678265],"type":"Point"}
}