{
  "type": "Feature",
  "properties": {
    "iso:country":"US",
    "sg:address":"47834 Van Dyke Ave",
    "sg:city":"Utica",
    "sg:classifiers":[
        {
            "category":"Banks & Credit Unions",
            "subcategory":"Bank",
            "type":"Services"
        }
    ],
    "sg:phone":"+1 586 323 2920",
    "sg:postcode":"48317",
    "sg:province":"MI",
    "sg:tags":[
        "broker",
        "mortgage"
    ],
    "wof:name":"Smart Rate Mortgage Corp",
    "wof:placetype":"venue"
},
  "geometry": {"coordinates":[-83.033035,42.645541],"type":"Point"}
}