{
  "type": "Feature",
  "properties": {
    "iso:country":"US",
    "sg:address":"19771 James Couzens Fwy",
    "sg:city":"Detroit",
    "sg:classifiers":[
        {
            "category":"Professional",
            "subcategory":"Lawyer & Legal Services",
            "type":"Services"
        }
    ],
    "sg:phone":"+1 313 864 0663",
    "sg:postcode":"48235",
    "sg:province":"MI",
    "sg:tags":[
        "personal",
        "injury"
    ],
    "wof:name":"Karega Chui Atty",
    "wof:placetype":"venue"
},
  "geometry": {"coordinates":[-83.193703,42.436798],"type":"Point"}
}