{
  "type": "Feature",
  "properties": {
    "iso:country":"US",
    "sg:address":"5530 Adrian St",
    "sg:city":"Saginaw",
    "sg:classifiers":[
        {
            "category":"Building & Trades",
            "subcategory":"Construction",
            "type":"Services"
        }
    ],
    "sg:phone":"+1 989 793 6136",
    "sg:postcode":"48603",
    "sg:province":"MI",
    "sg:tags":[
        "house"
    ],
    "wof:name":"Maday Builders",
    "wof:placetype":"venue"
},
  "geometry": {"coordinates":[-84.027051,43.43915],"type":"Point"}
}