{
  "type": "Feature",
  "properties": {
    "iso:country":"US",
    "sg:address":"50481 Peggy Ln",
    "sg:city":"New Baltimore",
    "sg:classifiers":[
        {
            "category":"Professional",
            "subcategory":"Business Services",
            "type":"Services"
        }
    ],
    "sg:phone":"+1 586 598 8355",
    "sg:postcode":"48047",
    "sg:province":"MI",
    "wof:name":"Chaircovers Etc Inc",
    "wof:placetype":"venue"
},
  "geometry": {"coordinates":[-82.801014,42.671794],"type":"Point"}
}