{
  "type": "Feature",
  "properties": {
    "iso:country":"US",
    "sg:address":"100 W Townsend Rd",
    "sg:city":"St Johns",
    "sg:classifiers":[
        {
            "category":"Communications",
            "subcategory":"Radio Station",
            "type":"Services"
        }
    ],
    "sg:phone":"+1 248 988 8588",
    "sg:postcode":"48879",
    "sg:province":"MI",
    "sg:tags":[
        "company",
        "broadcasting"
    ],
    "wof:name":"WJBK",
    "wof:placetype":"venue"
},
  "geometry": {"coordinates":[-84.56242399999999,42.986925],"type":"Point"}
}