{
  "type": "Feature",
  "properties": {
    "iso:country":"US",
    "sg:address":"7072 State Hwy 37",
    "sg:city":"Kingsley",
    "sg:classifiers":[
        {
            "category":"Food & Beverages",
            "subcategory":"Groceries & Convenience Stores",
            "type":"Retail Goods"
        }
    ],
    "sg:phone":"+1 231 263 5525",
    "sg:postcode":"49637",
    "sg:province":"MI",
    "wof:name":"Wesso's Superette & Total Svc",
    "wof:placetype":"venue"
},
  "geometry": {"coordinates":[-85.656035,44.58362],"type":"Point"}
}