{
  "type": "Feature",
  "properties": {
    "iso:country":"US",
    "sg:address":"33550 N Hampshire St",
    "sg:city":"Livonia",
    "sg:classifiers":[
        {
            "category":"Building & Trades",
            "subcategory":"Construction",
            "type":"Services"
        }
    ],
    "sg:phone":"+1 734 522 0224",
    "sg:postcode":"48154",
    "sg:province":"MI",
    "sg:tags":[
        "contractor"
    ],
    "wof:name":"Johnson Building Company",
    "wof:placetype":"venue"
},
  "geometry": {"coordinates":[-83.36869799999999,42.3974],"type":"Point"}
}