{
  "type": "Feature",
  "properties": {
    "iso:country":"US",
    "sg:address":"204 Huron Ave",
    "sg:city":"Port Huron",
    "sg:classifiers":[
        {
            "category":"Wholesale",
            "subcategory":"Groceries",
            "type":"Manufacturing & Wholesale Goods"
        }
    ],
    "sg:phone":"+1 810 987 7779",
    "sg:postcode":"48060",
    "sg:province":"MI",
    "sg:tags":[
        "cocoa",
        "chocolate"
    ],
    "wof:name":"Chocolate Harbor",
    "wof:placetype":"venue"
},
  "geometry": {"coordinates":[-82.424136,42.977378],"type":"Point"}
}