{
  "type": "Feature",
  "properties": {
    "iso:country":"US",
    "sg:address":"437 Butternut Dr",
    "sg:city":"Holland",
    "sg:classifiers":[
        {
            "category":"Home & Garden",
            "subcategory":"Garden Supply",
            "type":"Retail Goods"
        }
    ],
    "sg:phone":"+1 616 392 8211",
    "sg:postcode":"49424",
    "sg:province":"MI",
    "sg:tags":[
        "house",
        "bird",
        "feeder"
    ],
    "wof:name":"Wild Birds Unlimited",
    "wof:placetype":"venue"
},
  "geometry": {"coordinates":[-86.121235,42.811594],"type":"Point"}
}