{
  "type": "Feature",
  "properties": {
    "iso:country":"US",
    "sg:address":"23100 Providence Dr",
    "sg:city":"Southfield",
    "sg:classifiers":[
        {
            "category":"Insurance",
            "subcategory":"Insurance Agent",
            "type":"Services"
        }
    ],
    "sg:phone":"+1 248 331 1133",
    "sg:postcode":"48075",
    "sg:province":"MI",
    "sg:tags":[
        "processing"
    ],
    "wof:name":"Maxcis Inc",
    "wof:placetype":"venue"
},
  "geometry": {"coordinates":[-83.20684300000001,42.459994],"type":"Point"}
}