{
  "type": "Feature",
  "properties": {
    "iso:country":"US",
    "sg:address":"1720 Hancock St",
    "sg:city":"Port Huron",
    "sg:classifiers":[
        {
            "category":"Travel",
            "subcategory":"Hotels & Motels",
            "type":"Entertainment"
        }
    ],
    "sg:phone":"+1 810 987 5999",
    "sg:postcode":"48060",
    "sg:province":"MI",
    "wof:name":"Holiday Inn Express Port Huron",
    "wof:placetype":"venue"
},
  "geometry": {"coordinates":[-82.441194,43.001397],"type":"Point"}
}