{
  "type": "Feature",
  "properties": {
    "iso:country":"US",
    "sg:address":"25300 Michigan Ave",
    "sg:city":"Dearborn",
    "sg:classifiers":[
        {
            "category":"Fast Food",
            "type":"Food & Drink"
        }
    ],
    "sg:phone":"+1 313 563 3504",
    "sg:postcode":"48124",
    "sg:province":"MI",
    "sg:tags":[
        "burger"
    ],
    "sg:website":"www.burgerking.com",
    "wof:name":"Burger King",
    "wof:placetype":"venue"
},
  "geometry": {"coordinates":[-83.283699,42.2981],"type":"Point"}
}