{
  "type": "Feature",
  "properties": {
    "iso:country":"US",
    "sg:address":"4515 9th St",
    "sg:city":"Ecorse",
    "sg:classifiers":[
        {
            "category":"Professional",
            "subcategory":"Employment Agencies",
            "type":"Services"
        }
    ],
    "sg:phone":"+1 313 389 5173",
    "sg:postcode":"48229",
    "sg:province":"MI",
    "sg:tags":[
        "help",
        "supply"
    ],
    "wof:name":"Salvador Hernandez",
    "wof:placetype":"venue"
},
  "geometry": {"coordinates":[-83.157674,42.24368],"type":"Point"}
}