{
  "type": "Feature",
  "properties": {
    "iso:country":"US",
    "sg:address":"5604 Swede Ave",
    "sg:city":"Midland",
    "sg:classifiers":[
        {
            "category":"Social Services",
            "subcategory":"Child Care",
            "type":"Services"
        }
    ],
    "sg:phone":"+1 989 835 4993",
    "sg:postcode":"48642",
    "sg:province":"MI",
    "sg:tags":[
        "day"
    ],
    "wof:name":"Almost Home Daycare",
    "wof:placetype":"venue"
},
  "geometry": {"coordinates":[-84.206833,43.647825],"type":"Point"}
}