{
  "type": "Feature",
  "properties": {
    "iso:country":"US",
    "sg:address":"33120 Ryan Rd",
    "sg:city":"Sterling Heights",
    "sg:classifiers":[
        {
            "category":"Restaurant",
            "type":"Food & Drink"
        }
    ],
    "sg:menulink":"http://www.allmenus.com/mi/sterling-heights/114054-marcus-hamburgers/menu/",
    "sg:phone":"+1 586 977 0760",
    "sg:postcode":"48310",
    "sg:province":"MI",
    "sg:tags":[
        "burger",
        "american"
    ],
    "wof:name":"Marcus Hamburgers",
    "wof:placetype":"venue"
},
  "geometry": {"coordinates":[-83.068595,42.536313],"type":"Point"}
}