{
  "type": "Feature",
  "properties": {
    "iso:country":"US",
    "sg:address":"1035 E Saginaw St",
    "sg:city":"Lansing",
    "sg:classifiers":[
        {
            "category":"Professional",
            "subcategory":"Management & Consulting",
            "type":"Services"
        }
    ],
    "sg:phone":"+1 517 485 3333",
    "sg:postcode":"48906",
    "sg:province":"MI",
    "sg:tags":[
        "environmental"
    ],
    "wof:name":"P M Environmental Inc",
    "wof:placetype":"venue"
},
  "geometry": {"coordinates":[-84.536584,42.741012],"type":"Point"}
}