{
  "type": "Feature",
  "properties": {
    "iso:country":"US",
    "sg:address":"4936 Lakeshore Rd",
    "sg:city":"Fort Gratiot",
    "sg:classifiers":[
        {
            "category":"Health Services",
            "subcategory":"Health Practitioner",
            "type":"Services"
        }
    ],
    "sg:phone":"+1 810 385 6255",
    "sg:postcode":"48059",
    "sg:province":"MI",
    "wof:name":"Lakeshore Therapeutic Massage",
    "wof:placetype":"venue"
},
  "geometry": {"coordinates":[-82.453401,43.050531],"type":"Point"}
}