{
  "type": "Feature",
  "properties": {
    "iso:country":"US",
    "sg:address":"411 S Clay St",
    "sg:city":"Greenville",
    "sg:classifiers":[
        {
            "category":"Banks & Credit Unions",
            "subcategory":"Investment Brokerage",
            "type":"Services"
        }
    ],
    "sg:phone":"+1 616 225 8633",
    "sg:postcode":"48838",
    "sg:province":"MI",
    "sg:tags":[
        "stock",
        "bond"
    ],
    "wof:name":"Raymond James Financial Svc",
    "wof:placetype":"venue"
},
  "geometry": {"coordinates":[-85.25172999999999,43.177346],"type":"Point"}
}