{
  "type": "Feature",
  "properties": {
    "iso:country":"US",
    "sg:address":"49821 Leona Dr",
    "sg:city":"Chesterfield",
    "sg:classifiers":[
        {
            "category":"Professional",
            "subcategory":"Management & Consulting",
            "type":"Services"
        }
    ],
    "sg:phone":"+1 586 294 6759",
    "sg:postcode":"48051",
    "sg:province":"MI",
    "sg:tags":[
        "fire",
        "consultant",
        "protection"
    ],
    "wof:name":"ASIC",
    "wof:placetype":"venue"
},
  "geometry": {"coordinates":[-82.84318399999999,42.665533],"type":"Point"}
}