{
  "type": "Feature",
  "properties": {
    "iso:country":"US",
    "sg:address":"133 Johnson St",
    "sg:city":"Alpena",
    "sg:classifiers":[
        {
            "category":"Recreation",
            "type":"Entertainment"
        }
    ],
    "sg:phone":"+1 989 356 0608",
    "sg:postcode":"49707",
    "sg:province":"MI",
    "sg:tags":[
        "hall",
        "auditorium"
    ],
    "wof:name":"Alpena Civic & Community Ctr",
    "wof:placetype":"venue"
},
  "geometry": {"coordinates":[-83.45210299999999,45.079889],"type":"Point"}
}