{
  "type": "Feature",
  "properties": {
    "iso:country":"US",
    "sg:address":"11970 Devereaux Rd",
    "sg:city":"Parma",
    "sg:classifiers":[
        {
            "category":"Organizations",
            "subcategory":"Religious Organization",
            "type":"Services"
        }
    ],
    "sg:phone":"+1 517 531 4054",
    "sg:postcode":"49269",
    "sg:province":"MI",
    "sg:tags":[
        "church"
    ],
    "wof:name":"North Parma United Methodist",
    "wof:placetype":"venue"
},
  "geometry": {"coordinates":[-84.617774,42.313305],"type":"Point"}
}