{
  "type": "Feature",
  "properties": {
    "iso:country":"US",
    "sg:address":"1400 Division St",
    "sg:city":"Marquette",
    "sg:classifiers":[
        {
            "category":"Freight",
            "type":"Transportation"
        }
    ],
    "sg:phone":"+1 906 226 8101",
    "sg:postcode":"49855",
    "sg:province":"MI",
    "sg:tags":[
        "operator",
        "local",
        "trucking"
    ],
    "wof:name":"Milk Marketing",
    "wof:placetype":"venue"
},
  "geometry": {"coordinates":[-87.39872099999999,46.532492],"type":"Point"}
}