{
  "type": "Feature",
  "properties": {
    "iso:country":"US",
    "sg:address":"1600 Buttrick Ave SE",
    "sg:city":"Ada",
    "sg:classifiers":[
        {
            "category":"Professional",
            "subcategory":"Business Services",
            "type":"Services"
        }
    ],
    "sg:phone":"+1 616 676 1829",
    "sg:postcode":"49301",
    "sg:province":"MI",
    "sg:tags":[
        "notary",
        "public"
    ],
    "wof:name":"Charles F Justian",
    "wof:placetype":"venue"
},
  "geometry": {"coordinates":[-85.47632,42.935711],"type":"Point"}
}