{
  "type": "Feature",
  "properties": {
    "iso:country":"US",
    "sg:address":"125 Gerald Ave",
    "sg:city":"Clawson",
    "sg:classifiers":[
        {
            "category":"Building & Trades",
            "subcategory":"Construction",
            "type":"Services"
        }
    ],
    "sg:phone":"+1 248 435 6569",
    "sg:postcode":"48017",
    "sg:province":"MI",
    "sg:tags":[
        "demolition",
        "contractor"
    ],
    "wof:name":"Double JJ Constr & Demolition",
    "wof:placetype":"venue"
},
  "geometry": {"coordinates":[-83.15136,42.531973],"type":"Point"}
}