{
  "type": "Feature",
  "properties": {
    "iso:country":"US",
    "sg:address":"1700 Atlantic Blvd",
    "sg:city":"Auburn Hills",
    "sg:classifiers":[
        {
            "category":"Professional",
            "subcategory":"Engineering",
            "type":"Services"
        }
    ],
    "sg:phone":"+1 248 373 1749",
    "sg:postcode":"48326",
    "sg:province":"MI",
    "sg:tags":[
        "administration"
    ],
    "wof:name":"Grupo Antolin North American",
    "wof:placetype":"venue"
},
  "geometry": {"coordinates":[-83.267906,42.697632],"type":"Point"}
}