{
  "type": "Feature",
  "properties": {
    "iso:country":"US",
    "sg:address":"15345 W 7 Mile Rd",
    "sg:city":"Detroit",
    "sg:classifiers":[
        {
            "category":"Personal",
            "subcategory":"Beauty Salon",
            "type":"Services"
        }
    ],
    "sg:phone":"+1 313 273 2265",
    "sg:postcode":"48235",
    "sg:province":"MI",
    "sg:tags":[
        "shop"
    ],
    "wof:name":"Camara Hair Braiding",
    "wof:placetype":"venue"
},
  "geometry": {"coordinates":[-83.198263,42.430388],"type":"Point"}
}