{
  "type": "Feature",
  "properties": {
    "iso:country":"US",
    "sg:address":"4677 S Geneva Rd",
    "sg:city":"Saint Louis",
    "sg:classifiers":[
        {
            "category":"Social Services",
            "subcategory":"Child Care",
            "type":"Services"
        }
    ],
    "sg:phone":"+1 989 681 5878",
    "sg:postcode":"48880",
    "sg:province":"MI",
    "sg:tags":[
        "day",
        "provider"
    ],
    "wof:name":"Corinne Anne Lerg",
    "wof:placetype":"venue"
},
  "geometry": {"coordinates":[-84.54853,43.475292],"type":"Point"}
}