{
  "type": "Feature",
  "properties": {
    "iso:country":"US",
    "sg:address":"925 Edenhill Rd",
    "sg:city":"Beulah",
    "sg:classifiers":[
        {
            "category":"Retail",
            "subcategory":"Repair Shop",
            "type":"Services"
        }
    ],
    "sg:phone":"+1 231 882 7206",
    "sg:postcode":"49617",
    "sg:province":"MI",
    "sg:tags":[
        "repairing",
        "lawn",
        "mower"
    ],
    "wof:name":"Ballard's Repair Svc",
    "wof:placetype":"venue"
},
  "geometry": {"coordinates":[-86.079865,44.646606],"type":"Point"}
}