{
  "type": "Feature",
  "properties": {
    "iso:country":"US",
    "sg:address":"21024 Vreeland Rd",
    "sg:city":"Woodhaven",
    "sg:classifiers":[
        {
            "category":"Professional",
            "subcategory":"Computer Services",
            "type":"Services"
        }
    ],
    "sg:phone":"+1 734 675 7111",
    "sg:postcode":"48183",
    "sg:province":"MI",
    "sg:website":"www.ecsinc1.com",
    "wof:name":"Electronic Computer Services Inc",
    "wof:placetype":"venue"
},
  "geometry": {"coordinates":[-83.236369,42.109914],"type":"Point"}
}