{
  "type": "Feature",
  "properties": {
    "iso:country":"US",
    "sg:address":"30785 Grand River Ave",
    "sg:city":"Farmington Hills",
    "sg:classifiers":[
        {
            "category":"Professional",
            "subcategory":"Engineering",
            "type":"Services"
        }
    ],
    "sg:phone":"+1 248 888 0900",
    "sg:postcode":"48336",
    "sg:province":"MI",
    "sg:tags":[
        "electrical",
        "engineer"
    ],
    "wof:name":"Weber Engineering Inc",
    "wof:placetype":"venue"
},
  "geometry": {"coordinates":[-83.35292,42.454774],"type":"Point"}
}