{
  "type": "Feature",
  "properties": {
    "iso:country":"US",
    "sg:address":"11275 Cady Rd",
    "sg:city":"Grass Lake",
    "sg:classifiers":[
        {
            "category":"Building & Trades",
            "subcategory":"Plumbing",
            "type":"Services"
        }
    ],
    "sg:phone":"+1 517 536 2222",
    "sg:postcode":"49240",
    "sg:province":"MI",
    "sg:tags":[
        "excavation",
        "contractor"
    ],
    "wof:name":"Boyer Excavating",
    "wof:placetype":"venue"
},
  "geometry": {"coordinates":[-84.207058,42.176006],"type":"Point"}
}