{
  "type": "Feature",
  "properties": {
    "iso:country":"US",
    "sg:address":"148 W Michigan Ave",
    "sg:city":"Jackson",
    "sg:classifiers":[
        {
            "category":"Shopping",
            "type":"Retail Goods"
        }
    ],
    "sg:phone":"+1 517 783 5370",
    "sg:postcode":"49201",
    "sg:province":"MI",
    "sg:tags":[
        "candle"
    ],
    "wof:name":"Swan Creek Candle",
    "wof:placetype":"venue"
},
  "geometry": {"coordinates":[-84.407723,42.247561],"type":"Point"}
}