{
  "type": "Feature",
  "properties": {
    "iso:country":"US",
    "sg:address":"1434 Colfax Ave",
    "sg:city":"Grand Haven",
    "sg:classifiers":[
        {
            "category":"Manufacturing",
            "subcategory":"Signs",
            "type":"Manufacturing & Wholesale Goods"
        }
    ],
    "sg:phone":"+1 616 842 2633",
    "sg:postcode":"49417",
    "sg:province":"MI",
    "wof:name":"Kammeraad Sign Svc",
    "wof:placetype":"venue"
},
  "geometry": {"coordinates":[-86.20766,43.056578],"type":"Point"}
}