{
  "type": "Feature",
  "properties": {
    "iso:country":"US",
    "sg:address":"14614 State St",
    "sg:city":"Marne",
    "sg:classifiers":[
        {
            "category":"Government",
            "subcategory":"Post Office",
            "type":"Public Place"
        }
    ],
    "sg:phone":"+1 800 275 8777",
    "sg:postcode":"49435",
    "sg:province":"MI",
    "sg:website":"http://www.usps.com",
    "wof:name":"USPS - United States Post Office - Marne Main Office",
    "wof:placetype":"venue"
},
  "geometry": {"coordinates":[-85.826904,43.034621],"type":"Point"}
}