{
  "type": "Feature",
  "properties": {
    "iso:country":"US",
    "sg:address":"33600 Mound Rd",
    "sg:city":"Sterling Heights",
    "sg:classifiers":[
        {
            "category":"Shopping",
            "subcategory":"Bicycles & Sporting Goods",
            "type":"Retail Goods"
        }
    ],
    "sg:phone":"+1 586 977 8380",
    "sg:postcode":"48310",
    "sg:province":"MI",
    "wof:name":"Michigan Usssa",
    "wof:placetype":"venue"
},
  "geometry": {"coordinates":[-83.047501,42.539902],"type":"Point"}
}