{
  "type": "Feature",
  "properties": {
    "iso:country":"US",
    "sg:address":"20965 Grange Rd",
    "sg:city":"Wyandotte",
    "sg:classifiers":[
        {
            "category":"Health Services",
            "subcategory":"Doctor",
            "type":"Services"
        }
    ],
    "sg:phone":"+1 734 479 1888",
    "sg:postcode":"48193",
    "sg:province":"MI",
    "wof:name":"Shalhoub Deeb MD Facog",
    "wof:placetype":"venue"
},
  "geometry": {"coordinates":[-83.211905,42.155359],"type":"Point"}
}