{
  "type": "Feature",
  "properties": {
    "iso:country":"US",
    "sg:address":"1170 Panama St",
    "sg:city":"Portage",
    "sg:classifiers":[
        {
            "category":"Professional",
            "subcategory":"Accounting & Tax Preparation",
            "type":"Services"
        }
    ],
    "sg:phone":"+1 269 323 8224",
    "sg:postcode":"49002",
    "sg:province":"MI",
    "wof:name":"National Accounting Service",
    "wof:placetype":"venue"
},
  "geometry": {"coordinates":[-85.574043,42.153973],"type":"Point"}
}