{
  "type": "Feature",
  "properties": {
    "iso:country":"US",
    "sg:address":"1969 E 9 Mile Rd",
    "sg:city":"Dafter",
    "sg:classifiers":[
        {
            "category":"Organizations",
            "subcategory":"Religious Organization",
            "type":"Services"
        }
    ],
    "sg:phone":"+1 906 632 4422",
    "sg:postcode":"49724",
    "sg:province":"MI",
    "sg:tags":[
        "church"
    ],
    "wof:name":"Rosedale Community Church",
    "wof:placetype":"venue"
},
  "geometry": {"coordinates":[-84.326155,46.375909],"type":"Point"}
}