{
  "type": "Feature",
  "properties": {
    "iso:country":"US",
    "sg:address":"3225 S Telegraph Rd",
    "sg:city":"Dearborn",
    "sg:classifiers":[
        {
            "category":"Retail",
            "subcategory":"Veterinary Services",
            "type":"Services"
        }
    ],
    "sg:phone":"+1 313 565 5566",
    "sg:postcode":"48124",
    "sg:province":"MI",
    "sg:tags":[
        "veterinarian"
    ],
    "wof:name":"Vetselect Animal Hospital of Dearborn",
    "wof:placetype":"venue"
},
  "geometry": {"coordinates":[-83.27069899999999,42.287701],"type":"Point"}
}