{
  "type": "Feature",
  "properties": {
    "iso:country":"US",
    "sg:address":"9564 Jericho Rd",
    "sg:city":"Bridgman",
    "sg:classifiers":[
        {
            "category":"Professional",
            "subcategory":"Management & Consulting",
            "type":"Services"
        }
    ],
    "sg:phone":"+1 269 465 9431",
    "sg:postcode":"49106",
    "sg:province":"MI",
    "sg:tags":[
        "marketing",
        "program"
    ],
    "wof:name":"Smith & Smith",
    "wof:placetype":"venue"
},
  "geometry": {"coordinates":[-86.533478,41.945498],"type":"Point"}
}