{
  "type": "Feature",
  "properties": {
    "iso:country":"US",
    "sg:address":"1017 S Washington Ave",
    "sg:city":"Royal Oak",
    "sg:classifiers":[
        {
            "category":"Sports & Exercise",
            "subcategory":"Bowling",
            "type":"Entertainment"
        }
    ],
    "sg:phone":"+1 248 541 7060",
    "sg:postcode":"48067",
    "sg:province":"MI",
    "sg:tags":[
        "drinking",
        "center"
    ],
    "wof:name":"Royal Oak Lanes",
    "wof:placetype":"venue"
},
  "geometry": {"coordinates":[-83.14625700000001,42.480767],"type":"Point"}
}