{
  "type": "Feature",
  "properties": {
    "iso:country":"US",
    "sg:address":"25718 John R Rd",
    "sg:city":"Madison Heights",
    "sg:classifiers":[
        {
            "category":"Retail",
            "subcategory":"Auto Repair",
            "type":"Services"
        }
    ],
    "sg:phone":"+1 248 543 7832",
    "sg:postcode":"48071",
    "sg:province":"MI",
    "sg:tags":[
        "transmission"
    ],
    "wof:name":"Transmission Clinic",
    "wof:placetype":"venue"
},
  "geometry": {"coordinates":[-83.104797,42.481499],"type":"Point"}
}