{
  "type": "Feature",
  "properties": {
    "iso:country":"US",
    "sg:address":"13765 Lakeside Ave",
    "sg:city":"Bear Lake",
    "sg:classifiers":[
        {
            "category":"Professional",
            "subcategory":"Accounting & Tax Preparation",
            "type":"Services"
        }
    ],
    "sg:phone":"+1 231 864 2622",
    "sg:postcode":"49614",
    "sg:province":"MI",
    "wof:name":"Jacque Wallace CPA PC",
    "wof:placetype":"venue"
},
  "geometry": {"coordinates":[-86.12968600000001,44.430889],"type":"Point"}
}