{
  "type": "Feature",
  "properties": {
    "iso:country":"US",
    "sg:address":"3289 US Hwy 23 N",
    "sg:city":"Alpena",
    "sg:classifiers":[
        {
            "category":"Organizations",
            "subcategory":"Religious Organization",
            "type":"Services"
        }
    ],
    "sg:phone":"+1 989 356 2718",
    "sg:postcode":"49707",
    "sg:province":"MI",
    "sg:tags":[
        "church"
    ],
    "wof:name":"Church Of God Of Prophecy",
    "wof:placetype":"venue"
},
  "geometry": {"coordinates":[-83.455063,45.098896],"type":"Point"}
}