{
  "type": "Feature",
  "properties": {
    "iso:country":"US",
    "sg:address":"210 S Front St",
    "sg:city":"Dowagiac",
    "sg:classifiers":[
        {
            "category":"Personal",
            "type":"Services"
        }
    ],
    "sg:phone":"+1 269 782 0800",
    "sg:postcode":"49047",
    "sg:province":"MI",
    "wof:name":"Darker Side Tanning",
    "wof:placetype":"venue"
},
  "geometry": {"coordinates":[-86.109011,41.982361],"type":"Point"}
}