{
  "type": "Feature",
  "properties": {
    "iso:country":"US",
    "sg:address":"29433 Southfield Rd",
    "sg:city":"Southfield",
    "sg:classifiers":[
        {
            "category":"Real Estate",
            "subcategory":"Real Estate Agent",
            "type":"Services"
        }
    ],
    "sg:phone":"+1 248 443 9000",
    "sg:postcode":"48076",
    "sg:province":"MI",
    "sg:website":"www.griffinproperties.com",
    "wof:name":"Griffin Properties",
    "wof:placetype":"venue"
},
  "geometry": {"coordinates":[-83.222846,42.506439],"type":"Point"}
}