{
  "type": "Feature",
  "properties": {
    "iso:country":"US",
    "sg:address":"3470 Division Ave S",
    "sg:city":"Grand Rapids",
    "sg:classifiers":[
        {
            "category":"Autos & Motor Vehicles",
            "subcategory":"Fuel & Gas Station",
            "type":"Retail Goods"
        }
    ],
    "sg:phone":"+1 616 243 9238",
    "sg:postcode":"49548",
    "sg:province":"MI",
    "sg:tags":[
        "oil"
    ],
    "wof:name":"Value Market Express",
    "wof:placetype":"venue"
},
  "geometry": {"coordinates":[-85.665351,42.901101],"type":"Point"}
}