{
  "type": "Feature",
  "properties": {
    "iso:country":"US",
    "sg:address":"440 W Congress St",
    "sg:city":"Detroit",
    "sg:classifiers":[
        {
            "category":"Professional",
            "type":"Services"
        }
    ],
    "sg:phone":"+1 313 963 9441",
    "sg:postcode":"48226",
    "sg:province":"MI",
    "sg:tags":[
        "personal"
    ],
    "wof:name":"Transition Team- Detroit The",
    "wof:placetype":"venue"
},
  "geometry": {"coordinates":[-83.051002,42.32813],"type":"Point"}
}