{
  "type": "Feature",
  "properties": {
    "iso:country":"US",
    "sg:address":"16996 Pasanen Rd",
    "sg:city":"Kaleva",
    "sg:classifiers":[
        {
            "category":"Building & Trades",
            "subcategory":"Construction",
            "type":"Services"
        }
    ],
    "sg:phone":"+1 231 362 3822",
    "sg:postcode":"49645",
    "sg:province":"MI",
    "sg:tags":[
        "roofing",
        "contractor"
    ],
    "wof:name":"Let George Do It",
    "wof:placetype":"venue"
},
  "geometry": {"coordinates":[-85.961303,44.361133],"type":"Point"}
}