{
  "type": "Feature",
  "properties": {
    "iso:country":"US",
    "sg:address":"2085 Winston Dr",
    "sg:city":"Commerce Township",
    "sg:classifiers":[
        {
            "category":"Retail",
            "subcategory":"Repair Shop",
            "type":"Services"
        }
    ],
    "sg:phone":"+1 248 626 4080",
    "sg:postcode":"48382",
    "sg:province":"MI",
    "wof:name":"International Watch Repair",
    "wof:placetype":"venue"
},
  "geometry": {"coordinates":[-83.518573,42.608736],"type":"Point"}
}