{
  "type": "Feature",
  "properties": {
    "iso:country":"US",
    "sg:address":"1701 N Woodward",
    "sg:city":"Bloomfield Hills",
    "sg:classifiers":[
        {
            "category":"Professional",
            "subcategory":"Lawyer & Legal Services",
            "type":"Services"
        }
    ],
    "sg:phone":"+1 248 645 9300",
    "sg:postcode":"48301",
    "sg:province":"MI",
    "wof:name":"Colombo Frederick Atty",
    "wof:placetype":"venue"
},
  "geometry": {"coordinates":[-83.285202,42.5448],"type":"Point"}
}