{
  "type": "Feature",
  "properties": {
    "iso:country":"US",
    "sg:address":"12086 S West-Bay Shore Dr",
    "sg:city":"Traverse City",
    "sg:classifiers":[
        {
            "category":"Home & Garden",
            "subcategory":"Garden Supply",
            "type":"Retail Goods"
        }
    ],
    "sg:phone":"+1 231 947 5639",
    "sg:postcode":"49684",
    "sg:province":"MI",
    "sg:tags":[
        "center"
    ],
    "wof:name":"Manitou Gardens",
    "wof:placetype":"venue"
},
  "geometry": {"coordinates":[-85.63750899999999,44.804063],"type":"Point"}
}