{
  "type": "Feature",
  "properties": {
    "iso:country":"US",
    "sg:address":"13439 Wilshire Dr",
    "sg:city":"Detroit",
    "sg:classifiers":[
        {
            "category":"Social Services",
            "subcategory":"Adult Care",
            "type":"Services"
        }
    ],
    "sg:phone":"+1 313 526 5481",
    "sg:postcode":"48213",
    "sg:province":"MI",
    "sg:tags":[
        "foster",
        "provider"
    ],
    "wof:name":"Florence Ransburg",
    "wof:placetype":"venue"
},
  "geometry": {"coordinates":[-82.972959,42.412101],"type":"Point"}
}