{
  "type": "Feature",
  "properties": {
    "iso:country":"US",
    "sg:address":"1820 Lakewood Dr",
    "sg:city":"Crystal",
    "sg:classifiers":[
        {
            "category":"Social Services",
            "subcategory":"Child Care",
            "type":"Services"
        }
    ],
    "sg:phone":"+1 989 235 4075",
    "sg:postcode":"48818",
    "sg:province":"MI",
    "wof:name":"Lakewood Day Care",
    "wof:placetype":"venue"
},
  "geometry": {"coordinates":[-84.891572,43.267817],"type":"Point"}
}