{
  "type": "Feature",
  "properties": {
    "iso:country":"US",
    "sg:address":"21250 W 7 Mile Rd",
    "sg:city":"Detroit",
    "sg:classifiers":[
        {
            "category":"Commercial Area",
            "type":"Public Place"
        },
        {
            "category":"Manufacturing",
            "subcategory":"Glass & Minerals",
            "type":"Manufacturing & Wholesale Goods"
        },
        {
            "category":"Manufacturing",
            "subcategory":"Apparel",
            "type":"Manufacturing & Wholesale Goods"
        },
        {
            "category":"Building & Trades",
            "subcategory":"Construction",
            "type":"Services"
        }
    ],
    "sg:phone":"+1 313 538 2746",
    "sg:postcode":"48219",
    "sg:province":"MI",
    "sg:tags":[
        "plate",
        "repair",
        "window",
        "glass-auto",
        "board",
        "front",
        "glass-broken",
        "store",
        "replacement"
    ],
    "sg:website":"http://www.danielsglassinc.com",
    "wof:name":"Daniels Glass Inc",
    "wof:placetype":"venue"
},
  "geometry": {"coordinates":[-83.25155599999999,42.429275],"type":"Point"}
}