{
  "type": "Feature",
  "properties": {
    "iso:country":"US",
    "sg:address":"1580 Seaman Rd",
    "sg:city":"Wellston",
    "sg:classifiers":[
        {
            "category":"Shopping",
            "subcategory":"Computers & Home Electronics",
            "type":"Retail Goods"
        }
    ],
    "sg:phone":"+1 231 848 4830",
    "sg:postcode":"49689",
    "sg:province":"MI",
    "sg:tags":[
        "equipment",
        "dealer"
    ],
    "wof:name":"Little Mary's Computer",
    "wof:placetype":"venue"
},
  "geometry": {"coordinates":[-85.95792899999999,44.216191],"type":"Point"}
}