{
  "type": "Feature",
  "properties": {
    "iso:country":"US",
    "sg:address":"4407 State St",
    "sg:city":"Saginaw",
    "sg:classifiers":[
        {
            "category":"Professional",
            "subcategory":"Lawyer & Legal Services",
            "type":"Services"
        }
    ],
    "sg:phone":"+1 989 792 4395",
    "sg:postcode":"48603",
    "sg:province":"MI",
    "sg:tags":[
        "attorney"
    ],
    "wof:name":"Russell J Perry Jr Law Office",
    "wof:placetype":"venue"
},
  "geometry": {"coordinates":[-84.004485,43.436663],"type":"Point"}
}