{
  "type": "Feature",
  "properties": {
    "iso:country":"US",
    "sg:address":"16060 Peach Ridge Ave",
    "sg:city":"Kent City",
    "sg:classifiers":[
        {
            "category":"Retail",
            "subcategory":"Animal Services",
            "type":"Services"
        }
    ],
    "sg:phone":"+1 616 890 3982",
    "sg:postcode":"49330",
    "sg:province":"MI",
    "sg:tags":[
        "pet",
        "grooming",
        "washing"
    ],
    "wof:name":"Scissor Wizard Mobile Pet",
    "wof:placetype":"venue"
},
  "geometry": {"coordinates":[-85.751651,43.257402],"type":"Point"}
}