{
  "type": "Feature",
  "properties": {
    "iso:country":"US",
    "sg:address":"201 N Mitchell St",
    "sg:city":"Cadillac",
    "sg:classifiers":[
        {
            "category":"Real Estate",
            "subcategory":"Real Estate Agent",
            "type":"Services"
        }
    ],
    "sg:phone":"+1 231 775 2600",
    "sg:postcode":"49601",
    "sg:province":"MI",
    "sg:website":"www.cadillac-realty.com",
    "wof:name":"Cadillac Realty By Fagerman",
    "wof:placetype":"venue"
},
  "geometry": {"coordinates":[-85.40093899999999,44.252137],"type":"Point"}
}