{
  "type": "Feature",
  "properties": {
    "iso:country":"US",
    "sg:address":"17604 Gray Ln",
    "sg:city":"Interlochen",
    "sg:classifiers":[
        {
            "category":"Building & Trades",
            "subcategory":"Construction",
            "type":"Services"
        }
    ],
    "sg:phone":"+1 231 275 7200",
    "sg:postcode":"49643",
    "sg:province":"MI",
    "sg:tags":[
        "house"
    ],
    "wof:name":"Inland Pines Construction LLC",
    "wof:placetype":"venue"
},
  "geometry": {"coordinates":[-85.88604599999999,44.677101],"type":"Point"}
}