{
  "type": "Feature",
  "properties": {
    "iso:country":"US",
    "sg:address":"7292 N Genesee Rd",
    "sg:city":"Genesee",
    "sg:classifiers":[
        {
            "category":"Personal",
            "subcategory":"Beauty Salon",
            "type":"Services"
        }
    ],
    "sg:phone":"+1 810 640 2482",
    "sg:postcode":"48437",
    "sg:province":"MI",
    "sg:tags":[
        "shop"
    ],
    "wof:name":"Hair Doktors M D",
    "wof:placetype":"venue"
},
  "geometry": {"coordinates":[-83.61749399999999,43.112662],"type":"Point"}
}