{
  "type": "Feature",
  "properties": {
    "iso:country":"US",
    "sg:address":"18979 Livernois Ave",
    "sg:city":"Detroit",
    "sg:classifiers":[
        {
            "category":"Personal",
            "subcategory":"Nail Salon",
            "type":"Services"
        }
    ],
    "sg:phone":"+1 313 864 8212",
    "sg:postcode":"48221",
    "sg:province":"MI",
    "wof:name":"Ok Nail",
    "wof:placetype":"venue"
},
  "geometry": {"coordinates":[-83.14160200000001,42.431499],"type":"Point"}
}