{
  "type": "Feature",
  "properties": {
    "iso:country":"US",
    "sg:address":"18680 Bungalow Dr",
    "sg:city":"Lathrup Village",
    "sg:classifiers":[
        {
            "category":"Professional",
            "subcategory":"Accounting & Tax Preparation",
            "type":"Services"
        }
    ],
    "sg:phone":"+1 248 559 6728",
    "sg:postcode":"48076",
    "sg:province":"MI",
    "sg:tags":[
        "bookkeeping",
        "general"
    ],
    "wof:name":"Hillary C Morris Accounting",
    "wof:placetype":"venue"
},
  "geometry": {"coordinates":[-83.225103,42.49073],"type":"Point"}
}