{
  "type": "Feature",
  "properties": {
    "iso:country":"US",
    "sg:address":"4323 W Michigan Ave",
    "sg:city":"Kalamazoo",
    "sg:classifiers":[
        {
            "category":"Social Services",
            "subcategory":"Child Care",
            "type":"Services"
        }
    ],
    "sg:phone":"+1 269 375 0051",
    "sg:postcode":"49006",
    "sg:province":"MI",
    "wof:name":"Katie's Korner Daycare",
    "wof:placetype":"venue"
},
  "geometry": {"coordinates":[-85.64274899999999,42.277043],"type":"Point"}
}