{
  "type": "Feature",
  "properties": {
    "iso:country":"US",
    "sg:address":"424 Riverside Dr",
    "sg:city":"Battle Creek",
    "sg:classifiers":[
        {
            "category":"Health Services",
            "subcategory":"Doctor",
            "type":"Services"
        }
    ],
    "sg:phone":"+1 269 964 7113",
    "sg:postcode":"49015",
    "sg:province":"MI",
    "sg:tags":[
        "dentist",
        "dental"
    ],
    "wof:name":"Riverside Dental PC",
    "wof:placetype":"venue"
},
  "geometry": {"coordinates":[-85.18963100000001,42.299604],"type":"Point"}
}