{
  "type": "Feature",
  "properties": {
    "iso:country":"US",
    "sg:address":"8145 Southshore Dr",
    "sg:city":"Brighton",
    "sg:classifiers":[
        {
            "category":"Professional",
            "subcategory":"Employment Agencies",
            "type":"Services"
        }
    ],
    "sg:phone":"+1 810 220 2107",
    "sg:postcode":"48114",
    "sg:province":"MI",
    "sg:tags":[
        "help",
        "supply"
    ],
    "wof:name":"Lor Ventures LLC",
    "wof:placetype":"venue"
},
  "geometry": {"coordinates":[-83.787976,42.568221],"type":"Point"}
}