{
  "type": "Feature",
  "properties": {
    "iso:country":"US",
    "sg:address":"2760 Port Sheldon St",
    "sg:city":"Jenison",
    "sg:classifiers":[
        {
            "category":"Retail",
            "subcategory":"Car Wash",
            "type":"Services"
        }
    ],
    "sg:phone":"+1 616 669 0610",
    "sg:postcode":"49428",
    "sg:province":"MI",
    "sg:website":"www.stayclean.com",
    "wof:name":"Georgetown Village Car Wash",
    "wof:placetype":"venue"
},
  "geometry": {"coordinates":[-85.85062600000001,42.887593],"type":"Point"}
}