{
  "type": "Feature",
  "properties": {
    "iso:country":"US",
    "sg:address":"91 S Tilden Ave",
    "sg:city":"Waterford",
    "sg:classifiers":[
        {
            "category":"Retail",
            "subcategory":"Auto Repair",
            "type":"Services"
        }
    ],
    "sg:phone":"+1 248 683 9655",
    "sg:postcode":"48328",
    "sg:province":"MI",
    "sg:tags":[
        "body"
    ],
    "wof:name":"Dent Doctor",
    "wof:placetype":"venue"
},
  "geometry": {"coordinates":[-83.32825800000001,42.631429],"type":"Point"}
}