{
  "type": "Feature",
  "properties": {
    "iso:country":"US",
    "sg:address":"750 W Eisenhower Pkwy",
    "sg:city":"Ann Arbor",
    "sg:classifiers":[
        {
            "category":"Health Services",
            "subcategory":"Nursing And Care Facility",
            "type":"Services"
        }
    ],
    "sg:phone":"+1 734 213 1708",
    "sg:postcode":"48103",
    "sg:province":"MI",
    "sg:tags":[
        "skilled"
    ],
    "wof:name":"Clare Bridge of Ann Arbor",
    "wof:placetype":"venue"
},
  "geometry": {"coordinates":[-83.750784,42.243688],"type":"Point"}
}