{
  "type": "Feature",
  "properties": {
    "iso:country":"US",
    "sg:address":"1510 W Grand Blvd",
    "sg:city":"Detroit",
    "sg:classifiers":[
        {
            "category":"Organizations",
            "subcategory":"Religious Organization",
            "type":"Services"
        }
    ],
    "sg:phone":"+1 313 895 6744",
    "sg:postcode":"48208",
    "sg:province":"MI",
    "wof:name":"Carter Metrpltn Chrstn Meth",
    "wof:placetype":"venue"
},
  "geometry": {"coordinates":[-83.105726,42.342315],"type":"Point"}
}