{
  "type": "Feature",
  "properties": {
    "iso:country":"US",
    "sg:address":"110 Calhoun St",
    "sg:city":"Battle Creek",
    "sg:classifiers":[
        {
            "category":"Retail",
            "subcategory":"Self-service Laundry",
            "type":"Services"
        }
    ],
    "sg:phone":"+1 269 963 0786",
    "sg:postcode":"49017",
    "sg:province":"MI",
    "wof:name":"Calhoun Laundry",
    "wof:placetype":"venue"
},
  "geometry": {"coordinates":[-85.17698,42.324071],"type":"Point"}
}