{
  "type": "Feature",
  "properties": {
    "iso:country":"US",
    "sg:address":"29151 Dequindre",
    "sg:city":"Warren",
    "sg:classifiers":[
        {
            "category":"Food & Beverages",
            "subcategory":"Bakery",
            "type":"Retail Goods"
        }
    ],
    "sg:phone":"+1 248 399 5355",
    "sg:postcode":"48092",
    "sg:province":"MI",
    "sg:tags":[
        "sandwich"
    ],
    "sg:website":"www.5crunch.com",
    "wof:name":"$5 Crunch",
    "wof:placetype":"venue"
},
  "geometry": {"coordinates":[-83.085714,42.506897],"type":"Point"}
}