{
  "type": "Feature",
  "properties": {
    "iso:country":"US",
    "sg:address":"101 W Sanborn Ave",
    "sg:city":"Croswell",
    "sg:classifiers":[
        {
            "category":"Banks & Credit Unions",
            "subcategory":"Bank",
            "type":"Services"
        }
    ],
    "sg:phone":"+1 810 679 3590",
    "sg:postcode":"48422",
    "sg:province":"MI",
    "wof:name":"St Patrick Credit Union",
    "wof:placetype":"venue"
},
  "geometry": {"coordinates":[-82.62555,43.271498],"type":"Point"}
}