{
  "type": "Feature",
  "properties": {
    "iso:country":"US",
    "sg:address":"528 Riley St",
    "sg:city":"Dundee",
    "sg:classifiers":[
        {
            "category":"Building & Trades",
            "subcategory":"Construction",
            "type":"Services"
        }
    ],
    "sg:phone":"+1 734 529 2243",
    "sg:postcode":"48131",
    "sg:province":"MI",
    "sg:tags":[
        "house"
    ],
    "wof:name":"Stoianowski Construction",
    "wof:placetype":"venue"
},
  "geometry": {"coordinates":[-83.66605,41.952061],"type":"Point"}
}