{
  "type": "Feature",
  "properties": {
    "iso:country":"US",
    "sg:address":"3060 Pine St SW",
    "sg:city":"Grandville",
    "sg:classifiers":[
        {
            "category":"Building & Trades",
            "subcategory":"Construction",
            "type":"Services"
        }
    ],
    "sg:phone":"+1 616 530 9880",
    "sg:postcode":"49418",
    "sg:province":"MI",
    "sg:tags":[
        "house",
        "builder",
        "home"
    ],
    "wof:name":"Grand Concept Homes Ltd",
    "wof:placetype":"venue"
},
  "geometry": {"coordinates":[-85.770449,42.907587],"type":"Point"}
}