{
  "type": "Feature",
  "properties": {
    "iso:country":"US",
    "sg:address":"628 N Maple Hill Dr",
    "sg:city":"Gwinn",
    "sg:classifiers":[
        {
            "category":"Organizations",
            "subcategory":"Labor Organization",
            "type":"Services"
        }
    ],
    "sg:phone":"+1 906 346 7335",
    "sg:postcode":"49841",
    "sg:province":"MI",
    "wof:name":"International Assoc Heat/Frost",
    "wof:placetype":"venue"
},
  "geometry": {"coordinates":[-87.457764,46.303359],"type":"Point"}
}