{
  "type": "Feature",
  "properties": {
    "iso:country":"US",
    "sg:address":"425 Bryn Mawr St",
    "sg:city":"Birmingham",
    "sg:classifiers":[
        {
            "category":"Health Services",
            "subcategory":"Doctor",
            "type":"Services"
        }
    ],
    "sg:phone":"+1 248 647 1663",
    "sg:postcode":"48009",
    "sg:province":"MI",
    "sg:tags":[
        "physician",
        "surgeon"
    ],
    "wof:name":"Phyllis J Yates MD",
    "wof:placetype":"venue"
},
  "geometry": {"coordinates":[-83.24464999999999,42.542699],"type":"Point"}
}