{
  "type": "Feature",
  "properties": {
    "iso:country":"US",
    "sg:address":"937 Leonard St NW",
    "sg:city":"Grand Rapids",
    "sg:classifiers":[
        {
            "category":"Personal",
            "type":"Services"
        }
    ],
    "sg:phone":"+1 616 454 5561",
    "sg:postcode":"49504",
    "sg:province":"MI",
    "sg:tags":[
        "therapist",
        "massage"
    ],
    "wof:name":"Touch Of Health",
    "wof:placetype":"venue"
},
  "geometry": {"coordinates":[-85.692939,42.985459],"type":"Point"}
}