{
  "type": "Feature",
  "properties": {
    "iso:country":"US",
    "sg:address":"5815 S M-66 Hwy",
    "sg:city":"Nashville",
    "sg:classifiers":[
        {
            "category":"Farming",
            "subcategory":"Dairy Farm",
            "type":"Manufacturing & Wholesale Goods"
        }
    ],
    "sg:phone":"+1 517 852 2121",
    "sg:postcode":"49073",
    "sg:province":"MI",
    "wof:name":"Douglas Westendorp",
    "wof:placetype":"venue"
},
  "geometry": {"coordinates":[-85.094127,42.570589],"type":"Point"}
}