{
  "type": "Feature",
  "properties": {
    "iso:country":"US",
    "sg:address":"15882 Flanders St",
    "sg:city":"Southgate",
    "sg:classifiers":[
        {
            "category":"Real Estate",
            "subcategory":"Real Estate Agent",
            "type":"Services"
        }
    ],
    "sg:phone":"+1 734 283 5986",
    "sg:postcode":"48195",
    "sg:province":"MI",
    "wof:name":"Glasser Investments",
    "wof:placetype":"venue"
},
  "geometry": {"coordinates":[-83.226167,42.193426],"type":"Point"}
}