{
  "type": "Feature",
  "properties": {
    "iso:country":"US",
    "sg:address":"15371 Merriman Rd",
    "sg:city":"Livonia",
    "sg:classifiers":[
        {
            "category":"Personal",
            "subcategory":"Beauty Salon",
            "type":"Services"
        }
    ],
    "sg:phone":"+1 734 367 0401",
    "sg:postcode":"48154",
    "sg:province":"MI",
    "sg:tags":[
        "nail",
        "shop"
    ],
    "wof:name":"Cosmic Nails",
    "wof:placetype":"venue"
},
  "geometry": {"coordinates":[-83.354293,42.399084],"type":"Point"}
}