{
  "type": "Feature",
  "properties": {
    "iso:country":"US",
    "sg:address":"1706 Division Ave S",
    "sg:city":"Grand Rapids",
    "sg:classifiers":[
        {
            "category":"Professional",
            "subcategory":"Business Services",
            "type":"Services"
        }
    ],
    "sg:phone":"+1 616 245 4346",
    "sg:postcode":"49507",
    "sg:province":"MI",
    "sg:tags":[
        "house",
        "adult",
        "way",
        "half"
    ],
    "sg:website":"www.altdir.org",
    "wof:name":"Alternative Directions",
    "wof:placetype":"venue"
},
  "geometry": {"coordinates":[-85.666813,42.932363],"type":"Point"}
}