{
  "type": "Feature",
  "properties": {
    "iso:country":"US",
    "sg:address":"700 Degroff St",
    "sg:city":"Grand Ledge",
    "sg:classifiers":[
        {
            "category":"Professional",
            "subcategory":"Business Services",
            "type":"Services"
        }
    ],
    "sg:phone":"+1 517 627 0747",
    "sg:postcode":"48837",
    "sg:province":"MI",
    "wof:name":"A Plus Home Inspection Svcs",
    "wof:placetype":"venue"
},
  "geometry": {"coordinates":[-84.74458199999999,42.748518],"type":"Point"}
}