{
  "type": "Feature",
  "properties": {
    "iso:country":"US",
    "sg:address":"12343 Stark Rd",
    "sg:city":"Livonia",
    "sg:classifiers":[
        {
            "category":"Building & Trades",
            "subcategory":"Landscaping Services",
            "type":"Services"
        }
    ],
    "sg:phone":"+1 734 522 4620",
    "sg:postcode":"48150",
    "sg:province":"MI",
    "sg:tags":[
        "consultant",
        "designer",
        "landscape",
        "contractor"
    ],
    "wof:name":"Images In Landscaping",
    "wof:placetype":"venue"
},
  "geometry": {"coordinates":[-83.380414,42.374181],"type":"Point"}
}