{
  "type": "Feature",
  "properties": {
    "iso:country":"US",
    "sg:address":"2759 Valley Heights Dr",
    "sg:city":"Adrian",
    "sg:classifiers":[
        {
            "category":"Real Estate",
            "subcategory":"Developer",
            "type":"Services"
        }
    ],
    "sg:phone":"+1 517 265 2414",
    "sg:postcode":"49221",
    "sg:province":"MI",
    "sg:tags":[
        "land",
        "subdivider"
    ],
    "wof:name":"Wendt Developments LLC",
    "wof:placetype":"venue"
},
  "geometry": {"coordinates":[-83.98316699999999,41.932222],"type":"Point"}
}