{
  "type": "Feature",
  "properties": {
    "iso:country":"US",
    "sg:address":"1654 Livernois Rd",
    "sg:city":"Troy",
    "sg:classifiers":[
        {
            "category":"Autos & Motor Vehicles",
            "subcategory":"Fuel & Gas Station",
            "type":"Retail Goods"
        }
    ],
    "sg:phone":"+1 248 250 9750",
    "sg:postcode":"48083",
    "sg:province":"MI",
    "wof:name":"Citgo Clark Gas Station",
    "wof:placetype":"venue"
},
  "geometry": {"coordinates":[-83.147009,42.548827],"type":"Point"}
}