{
  "type": "Feature",
  "properties": {
    "iso:country":"US",
    "sg:address":"21 21st St",
    "sg:city":"Battle Creek",
    "sg:classifiers":[
        {
            "category":"Real Estate",
            "subcategory":"Architect",
            "type":"Services"
        }
    ],
    "sg:phone":"+1 269 968 1110",
    "sg:postcode":"49015",
    "sg:province":"MI",
    "sg:tags":[
        "architectural"
    ],
    "wof:name":"G E Harris & Affiliates Inc",
    "wof:placetype":"venue"
},
  "geometry": {"coordinates":[-85.22036199999999,42.307624],"type":"Point"}
}