{
  "type": "Feature",
  "properties": {
    "iso:country":"US",
    "sg:address":"850 Williamsbury Ct",
    "sg:city":"Waterford",
    "sg:classifiers":[
        {
            "category":"Real Estate",
            "subcategory":"Real Estate Operator",
            "type":"Services"
        }
    ],
    "sg:phone":"+1 248 683 2010",
    "sg:postcode":"48328",
    "sg:province":"MI",
    "sg:tags":[
        "apartment"
    ],
    "wof:name":"Glengary Park Apartments",
    "wof:placetype":"venue"
},
  "geometry": {"coordinates":[-83.364034,42.653557],"type":"Point"}
}