{
  "type": "Feature",
  "properties": {
    "iso:country":"US",
    "sg:address":"5950 Rochester Rd",
    "sg:city":"Troy",
    "sg:classifiers":[
        {
            "category":"Banks & Credit Unions",
            "subcategory":"Bank",
            "type":"Services"
        }
    ],
    "sg:phone":"+1 248 828 3737",
    "sg:postcode":"48085",
    "sg:province":"MI",
    "wof:name":"Midwest Guaranty Bank",
    "wof:placetype":"venue"
},
  "geometry": {"coordinates":[-83.12960099999999,42.6059],"type":"Point"}
}