{
  "type": "Feature",
  "properties": {
    "iso:country":"US",
    "sg:address":"3476 Snow Ave SE",
    "sg:city":"Lowell",
    "sg:classifiers":[
        {
            "category":"Shopping",
            "subcategory":"Clothing, Apparel, & Fashions",
            "type":"Retail Goods"
        }
    ],
    "sg:phone":"+1 616 897 1121",
    "sg:postcode":"49331",
    "sg:province":"MI",
    "sg:tags":[
        "wear"
    ],
    "wof:name":"Pigtails and Pollywogs",
    "wof:placetype":"venue"
},
  "geometry": {"coordinates":[-85.430272,42.901993],"type":"Point"}
}