{
  "type": "Feature",
  "properties": {
    "iso:country":"US",
    "sg:address":"17985 E 14 Mile Rd",
    "sg:city":"Fraser",
    "sg:classifiers":[
        {
            "category":"Professional",
            "subcategory":"Accounting & Tax Preparation",
            "type":"Services"
        }
    ],
    "sg:phone":"+1 586 731 4097",
    "sg:postcode":"48026",
    "sg:province":"MI",
    "wof:name":"David K Lavoie Accounting Svcs",
    "wof:placetype":"venue"
},
  "geometry": {"coordinates":[-82.93554,42.53927],"type":"Point"}
}