{
  "type": "Feature",
  "properties": {
    "iso:country":"US",
    "sg:address":"23068 Middlebelt Rd",
    "sg:city":"New Boston",
    "sg:classifiers":[
        {
            "category":"Retail",
            "subcategory":"Auto Repair",
            "type":"Services"
        }
    ],
    "sg:phone":"+1 734 782 3425",
    "sg:postcode":"48164",
    "sg:province":"MI",
    "sg:tags":[
        "automotive"
    ],
    "wof:name":"Scarry Larrys",
    "wof:placetype":"venue"
},
  "geometry": {"coordinates":[-83.32404099999999,42.130826],"type":"Point"}
}