{
  "type": "Feature",
  "properties": {
    "iso:country":"US",
    "sg:address":"46548 Erb Dr",
    "sg:city":"Macomb",
    "sg:classifiers":[
        {
            "category":"Professional",
            "subcategory":"Advertising",
            "type":"Services"
        }
    ],
    "sg:phone":"+1 586 598 8591",
    "sg:postcode":"48042",
    "sg:province":"MI",
    "sg:tags":[
        "distribution"
    ],
    "wof:name":"Composite Systems & Supplies",
    "wof:placetype":"venue"
},
  "geometry": {"coordinates":[-82.857815,42.642626],"type":"Point"}
}