{
  "type": "Feature",
  "properties": {
    "iso:country":"US",
    "sg:address":"1910 Industrial Pkwy",
    "sg:city":"Marquette",
    "sg:classifiers":[
        {
            "category":"Real Estate",
            "subcategory":"Developer",
            "type":"Services"
        }
    ],
    "sg:phone":"+1 906 228 2632",
    "sg:postcode":"49855",
    "sg:province":"MI",
    "wof:name":"Cornerstone Development Corp",
    "wof:placetype":"venue"
},
  "geometry": {"coordinates":[-87.416079,46.566079],"type":"Point"}
}