{
  "type": "Feature",
  "properties": {
    "iso:country":"US",
    "sg:address":"350 N Telegraph Rd",
    "sg:city":"Pontiac",
    "sg:classifiers":[
        {
            "category":"Shopping",
            "subcategory":"Department Store",
            "type":"Retail Goods"
        }
    ],
    "sg:phone":"+1 248 332 9370",
    "sg:postcode":"48341",
    "sg:province":"MI",
    "wof:name":"A J Wright",
    "wof:placetype":"venue"
},
  "geometry": {"coordinates":[-83.326043,42.64293],"type":"Point"}
}