{
  "type": "Feature",
  "properties": {
    "iso:country":"US",
    "sg:address":"20726 Harper Ave",
    "sg:city":"Harper Woods",
    "sg:classifiers":[
        {
            "category":"Restaurant",
            "type":"Food & Drink"
        }
    ],
    "sg:phone":"+1 313 881 7790",
    "sg:postcode":"48225",
    "sg:province":"MI",
    "sg:website":"www.tacobell.com",
    "wof:name":"Taco Bell No 2937",
    "wof:placetype":"venue"
},
  "geometry": {"coordinates":[-82.916298,42.4464],"type":"Point"}
}