{
  "type": "Feature",
  "properties": {
    "iso:country":"US",
    "sg:address":"415 Goodrich Rd",
    "sg:city":"Fostoria",
    "sg:classifiers":[
        {
            "category":"Education",
            "subcategory":"Library",
            "type":"Public Place"
        }
    ],
    "sg:phone":"+1 989 795 2794",
    "sg:postcode":"48435",
    "sg:province":"MI",
    "sg:tags":[
        "executive"
    ],
    "wof:name":"Watertown Township Library",
    "wof:placetype":"venue"
},
  "geometry": {"coordinates":[-83.370695,43.249134],"type":"Point"}
}