{
  "type": "Feature",
  "properties": {
    "iso:country":"US",
    "sg:address":"7878 Brighton Rd",
    "sg:city":"Brighton",
    "sg:classifiers":[
        {
            "category":"Education",
            "subcategory":"College",
            "type":"Public Place"
        }
    ],
    "sg:phone":"+1 810 299 4195",
    "sg:postcode":"48116",
    "sg:province":"MI",
    "sg:tags":[
        "academic",
        "school"
    ],
    "sg:website":"www.wccnet.edu",
    "wof:name":"Washtenaw Community College",
    "wof:placetype":"venue"
},
  "geometry": {"coordinates":[-83.795292,42.529128],"type":"Point"}
}