{
  "type": "Feature",
  "properties": {
    "iso:country":"US",
    "sg:address":"125 N 2nd Ave",
    "sg:city":"Alpena",
    "sg:classifiers":[
        {
            "category":"Organizations",
            "subcategory":"Membership Organization",
            "type":"Services"
        },
        {
            "category":"Banks & Credit Unions",
            "subcategory":"Financial Services",
            "type":"Services"
        }
    ],
    "sg:phone":"+1 989 354 4722",
    "sg:postcode":"49707",
    "sg:province":"MI",
    "sg:tags":[
        "trust",
        "nonprofit",
        "management"
    ],
    "wof:name":"Besser Foundation",
    "wof:placetype":"venue"
},
  "geometry": {"coordinates":[-83.43257199999999,45.062805],"type":"Point"}
}