{
  "type": "Feature",
  "properties": {
    "iso:country":"US",
    "sg:address":"11720 Susan Ave",
    "sg:city":"Warren",
    "sg:classifiers":[
        {
            "category":"Arts & Performance",
            "subcategory":"Theater",
            "type":"Entertainment"
        }
    ],
    "sg:phone":"+1 586 754 0014",
    "sg:postcode":"48093",
    "sg:province":"MI",
    "sg:tags":[
        "group"
    ],
    "wof:name":"Daniel Bergen Ministries Inc",
    "wof:placetype":"venue"
},
  "geometry": {"coordinates":[-83.00578400000001,42.496386],"type":"Point"}
}