{
  "type": "Feature",
  "properties": {
    "iso:country":"US",
    "sg:address":"4499 Potomac Ave SW",
    "sg:city":"Grandville",
    "sg:classifiers":[
        {
            "category":"Restaurant",
            "type":"Food & Drink"
        }
    ],
    "sg:menulink":"http://www.allmenus.com/mi/grandville/13999-olive-garden-italian-restaurant/menu/",
    "sg:phone":"+1 616 406 0852",
    "sg:postcode":"49418",
    "sg:province":"MI",
    "sg:tags":[
        "italian"
    ],
    "wof:name":"Olive Garden Italian Restaurant",
    "wof:placetype":"venue"
},
  "geometry": {"coordinates":[-85.75282900000001,42.881411],"type":"Point"}
}