{
  "type": "Feature",
  "properties": {
    "iso:country":"US",
    "sg:address":"28401 Hoover Rd",
    "sg:city":"Warren",
    "sg:classifiers":[
        {
            "category":"Health Services",
            "subcategory":"Doctor",
            "type":"Services"
        }
    ],
    "sg:phone":"+1 586 574 9255",
    "sg:postcode":"48093",
    "sg:province":"MI",
    "sg:tags":[
        "clinic"
    ],
    "wof:name":"Health Medical Clinic",
    "wof:placetype":"venue"
},
  "geometry": {"coordinates":[-83.006623,42.500429],"type":"Point"}
}