{
  "type": "Feature",
  "properties": {
    "iso:country":"US",
    "sg:address":"780 W Western Ave",
    "sg:city":"Muskegon",
    "sg:classifiers":[
        {
            "category":"Professional",
            "type":"Services"
        }
    ],
    "sg:phone":"+1 231 722 6353",
    "sg:postcode":"49441",
    "sg:province":"MI",
    "sg:tags":[
        "establishment"
    ],
    "wof:name":"Inland Lakes Management",
    "wof:placetype":"venue"
},
  "geometry": {"coordinates":[-86.261214,43.230137],"type":"Point"}
}