{
  "type": "Feature",
  "properties": {
    "iso:country":"US",
    "sg:address":"3181 Orchard Lake Rd",
    "sg:city":"Keego Harbor",
    "sg:classifiers":[
        {
            "category":"Manufacturing",
            "subcategory":"Printing",
            "type":"Manufacturing & Wholesale Goods"
        }
    ],
    "sg:phone":"+1 248 681 9933",
    "sg:postcode":"48320",
    "sg:province":"MI",
    "sg:tags":[
        "screen"
    ],
    "wof:name":"Maitiki",
    "wof:placetype":"venue"
},
  "geometry": {"coordinates":[-83.348302,42.604023],"type":"Point"}
}