{
  "type": "Feature",
  "properties": {
    "iso:country":"US",
    "sg:address":"42974 Christina Dr",
    "sg:city":"Sterling Heights",
    "sg:classifiers":[
        {
            "category":"Building & Trades",
            "subcategory":"Construction",
            "type":"Services"
        }
    ],
    "sg:phone":"+1 586 726 5346",
    "sg:postcode":"48313",
    "sg:province":"MI",
    "sg:tags":[
        "home",
        "improvement"
    ],
    "wof:name":"Gary's Construction Svc",
    "wof:placetype":"venue"
},
  "geometry": {"coordinates":[-82.99612399999999,42.609708],"type":"Point"}
}