{
  "type": "Feature",
  "properties": {
    "iso:country":"US",
    "sg:address":"16333 Lulu Rd",
    "sg:city":"Petersburg",
    "sg:classifiers":[
        {
            "category":"Travel",
            "subcategory":"Campground",
            "type":"Entertainment"
        }
    ],
    "sg:phone":"+1 734 279 2110",
    "sg:postcode":"49270",
    "sg:province":"MI",
    "sg:tags":[
        "camp",
        "grounds"
    ],
    "wof:name":"Totem Pole Park LLC",
    "wof:placetype":"venue"
},
  "geometry": {"coordinates":[-83.67811500000001,41.880465],"type":"Point"}
}