{
  "type": "Feature",
  "properties": {
    "iso:country":"US",
    "sg:address":"29299 Franklin Rd",
    "sg:city":"Southfield",
    "sg:classifiers":[
        {
            "category":"Professional",
            "subcategory":"Accounting & Tax Preparation",
            "type":"Services"
        }
    ],
    "sg:phone":"+1 248 353 7128",
    "sg:postcode":"48034",
    "sg:province":"MI",
    "sg:tags":[
        "billing"
    ],
    "sg:website":"www.per-se.com",
    "wof:name":"Computer Terminal Svc",
    "wof:placetype":"venue"
},
  "geometry": {"coordinates":[-83.309822,42.501754],"type":"Point"}
}