{
  "type": "Feature",
  "properties": {
    "iso:country":"US",
    "sg:address":"1301 Hollywood Ave",
    "sg:city":"Grosse Pointe",
    "sg:classifiers":[
        {
            "category":"Professional",
            "type":"Services"
        }
    ],
    "sg:phone":"+1 313 884 2995",
    "sg:postcode":"48236",
    "sg:province":"MI",
    "sg:tags":[
        "consultant",
        "freelance",
        "writer"
    ],
    "wof:name":"Lewis J Alden",
    "wof:placetype":"venue"
},
  "geometry": {"coordinates":[-82.89864,42.444847],"type":"Point"}
}