{
  "type": "Feature",
  "properties": {
    "iso:country":"US",
    "sg:address":"9326 Crafton Dr",
    "sg:city":"Swartz Creek",
    "sg:classifiers":[
        {
            "category":"Professional",
            "subcategory":"Business Services",
            "type":"Services"
        }
    ],
    "sg:phone":"+1 810 635 9852",
    "sg:postcode":"48473",
    "sg:province":"MI",
    "wof:name":"Red Creek Sales",
    "wof:placetype":"venue"
},
  "geometry": {"coordinates":[-83.86464100000001,43.007252],"type":"Point"}
}