{
  "type": "Feature",
  "properties": {
    "iso:country":"US",
    "sg:address":"1905 W Main St",
    "sg:city":"Lansing",
    "sg:classifiers":[
        {
            "category":"Building & Trades",
            "subcategory":"Construction",
            "type":"Services"
        }
    ],
    "sg:phone":"+1 517 372 5142",
    "sg:postcode":"48915",
    "sg:province":"MI",
    "sg:tags":[
        "house"
    ],
    "wof:name":"Purchase Construction Co",
    "wof:placetype":"venue"
},
  "geometry": {"coordinates":[-84.579561,42.725503],"type":"Point"}
}