{
  "type": "Feature",
  "properties": {
    "iso:country":"US",
    "sg:address":"4800 Curtis Rd",
    "sg:city":"Plymouth",
    "sg:classifiers":[
        {
            "category":"Real Estate",
            "subcategory":"Developer",
            "type":"Services"
        }
    ],
    "sg:phone":"+1 734 454 9903",
    "sg:postcode":"48170",
    "sg:province":"MI",
    "sg:tags":[
        "cemetery"
    ],
    "wof:name":"Meadco LLC",
    "wof:placetype":"venue"
},
  "geometry": {"coordinates":[-83.606092,42.343787],"type":"Point"}
}