{
  "type": "Feature",
  "properties": {
    "iso:country":"US",
    "sg:address":"607 Shelby St",
    "sg:city":"Detroit",
    "sg:classifiers":[
        {
            "category":"Professional",
            "subcategory":"Lawyer & Legal Services",
            "type":"Services"
        }
    ],
    "sg:phone":"+1 313 964 0903",
    "sg:postcode":"48226",
    "sg:province":"MI",
    "wof:name":"Hogan Charlene Glover Atty",
    "wof:placetype":"venue"
},
  "geometry": {"coordinates":[-83.048203,42.329201],"type":"Point"}
}