{
  "type": "Feature",
  "properties": {
    "iso:country":"US",
    "sg:address":"1439 60th St SE",
    "sg:city":"Kentwood",
    "sg:classifiers":[
        {
            "category":"Restaurant",
            "type":"Food & Drink"
        }
    ],
    "sg:phone":"+1 616 971 4560",
    "sg:postcode":"49508",
    "sg:province":"MI",
    "sg:tags":[
        "shop",
        "coffee"
    ],
    "wof:name":"Kava House",
    "wof:placetype":"venue"
},
  "geometry": {"coordinates":[-85.62565499999999,42.854762],"type":"Point"}
}