{
  "type": "Feature",
  "properties": {
    "iso:country":"US",
    "sg:address":"3060 Westbay Dr",
    "sg:city":"Saginaw",
    "sg:classifiers":[
        {
            "category":"Insurance",
            "subcategory":"Insurance Agent",
            "type":"Services"
        }
    ],
    "sg:phone":"+1 989 791 1039",
    "sg:postcode":"48604",
    "sg:province":"MI",
    "wof:name":"Mac Donald Insurance Agency",
    "wof:placetype":"venue"
},
  "geometry": {"coordinates":[-83.977125,43.477595],"type":"Point"}
}