{
  "type": "Feature",
  "properties": {
    "iso:country":"US",
    "sg:address":"9219 Blackburn Dr",
    "sg:city":"Traverse City",
    "sg:classifiers":[
        {
            "category":"Building & Trades",
            "subcategory":"Landscaping Services",
            "type":"Services"
        }
    ],
    "sg:phone":"+1 231 929 3578",
    "sg:postcode":"49684",
    "sg:province":"MI",
    "wof:name":"Earth Friendly Lawn Care",
    "wof:placetype":"venue"
},
  "geometry": {"coordinates":[-85.760508,44.752439],"type":"Point"}
}