{
  "type": "Feature",
  "properties": {
    "iso:country":"US",
    "sg:address":"24501 Jefferson At Fresard 9 1/2",
    "sg:city":"Roseville",
    "sg:classifiers":[
        {
            "category":"Retail",
            "subcategory":"Auto Repair",
            "type":"Services"
        }
    ],
    "sg:phone":"+1 586 773 3330",
    "sg:postcode":"48066",
    "sg:province":"MI",
    "wof:name":"S & K Muffler",
    "wof:placetype":"venue"
},
  "geometry": {"coordinates":[-82.88898,42.47227],"type":"Point"}
}