{
  "type": "Feature",
  "properties": {
    "iso:country":"US",
    "sg:address":"809 Crystal Ave",
    "sg:city":"Crystal Falls",
    "sg:classifiers":[
        {
            "category":"Organizations",
            "subcategory":"Religious Organization",
            "type":"Services"
        }
    ],
    "sg:phone":"+1 906 875 3921",
    "sg:postcode":"49920",
    "sg:province":"MI",
    "sg:tags":[
        "church"
    ],
    "wof:name":"St Mark S Episcopal Church",
    "wof:placetype":"venue"
},
  "geometry": {"coordinates":[-88.339843,46.097682],"type":"Point"}
}