{
  "type": "Feature",
  "properties": {
    "iso:country":"US",
    "sg:address":"45049 W Pontiac Trl",
    "sg:city":"Novi",
    "sg:classifiers":[
        {
            "category":"Restaurant",
            "type":"Food & Drink"
        }
    ],
    "sg:phone":"+1 248 669 3333",
    "sg:postcode":"48377",
    "sg:province":"MI",
    "wof:name":"Dolly's Pizza",
    "wof:placetype":"venue"
},
  "geometry": {"coordinates":[-83.492953,42.525558],"type":"Point"}
}