{
  "type": "Feature",
  "properties": {
    "iso:country":"US",
    "sg:address":"1900 Edgewood Blvd",
    "sg:city":"Berkley",
    "sg:classifiers":[
        {
            "category":"Professional",
            "subcategory":"Business Services",
            "type":"Services"
        }
    ],
    "sg:phone":"+1 248 548 7844",
    "sg:postcode":"48072",
    "sg:province":"MI",
    "wof:name":"Rypat Enterprises",
    "wof:placetype":"venue"
},
  "geometry": {"coordinates":[-83.177899,42.499796],"type":"Point"}
}