{
  "type": "Feature",
  "properties": {
    "iso:country":"US",
    "sg:address":"2190 N Park Dr",
    "sg:city":"Holland",
    "sg:classifiers":[
        {
            "category":"Banks & Credit Unions",
            "subcategory":"Bank",
            "type":"Services"
        }
    ],
    "sg:phone":"+1 616 355 4367",
    "sg:postcode":"49424",
    "sg:province":"MI",
    "wof:name":"Bank Of America",
    "wof:placetype":"venue"
},
  "geometry": {"coordinates":[-86.09003199999999,42.811341],"type":"Point"}
}