{
  "type": "Feature",
  "properties": {
    "iso:country":"US",
    "sg:address":"3300 Packard St",
    "sg:city":"Ann Arbor",
    "sg:classifiers":[
        {
            "category":"Retail",
            "subcategory":"Car Wash",
            "type":"Services"
        }
    ],
    "sg:phone":"+1 734 973 2240",
    "sg:postcode":"48108",
    "sg:province":"MI",
    "sg:tags":[
        "carwash"
    ],
    "wof:name":"Classy Chassie Auto Wash Inc",
    "wof:placetype":"venue"
},
  "geometry": {"coordinates":[-83.695514,42.245074],"type":"Point"}
}