{
  "type": "Feature",
  "properties": {
    "iso:country":"US",
    "sg:address":"21225 Kelly Rd",
    "sg:city":"Eastpointe",
    "sg:classifiers":[
        {
            "category":"Health Services",
            "subcategory":"Doctor",
            "type":"Services"
        }
    ],
    "sg:phone":"+1 586 776 4185",
    "sg:postcode":"48021",
    "sg:province":"MI",
    "sg:tags":[
        "physician",
        "surgeon"
    ],
    "wof:name":"Health One Medical Centers",
    "wof:placetype":"venue"
},
  "geometry": {"coordinates":[-82.9375,42.453999],"type":"Point"}
}