{
  "type": "Feature",
  "properties": {
    "iso:country":"US",
    "sg:address":"343 W Cedar Ave",
    "sg:city":"Gladwin",
    "sg:classifiers":[
        {
            "category":"Health Services",
            "subcategory":"Hospital",
            "type":"Services"
        },
        {
            "category":"Social Services",
            "type":"Services"
        }
    ],
    "sg:phone":"+1 989 426 5471",
    "sg:postcode":"48624",
    "sg:province":"MI",
    "sg:tags":[
        "disabled",
        "for",
        "developmentally",
        "mental"
    ],
    "wof:name":"Community Mental Health Svc",
    "wof:placetype":"venue"
},
  "geometry": {"coordinates":[-84.49011,43.980619],"type":"Point"}
}