{
  "type": "Feature",
  "properties": {
    "iso:country":"US",
    "sg:address":"1133 Michigan St NE",
    "sg:city":"Grand Rapids",
    "sg:classifiers":[
        {
            "category":"Utilities",
            "subcategory":"Telephone",
            "type":"Services"
        }
    ],
    "sg:phone":"+1 616 458 5485",
    "sg:postcode":"49503",
    "sg:province":"MI",
    "sg:tags":[
        "telecommunication"
    ],
    "wof:name":"Marceco LTD",
    "wof:placetype":"venue"
},
  "geometry": {"coordinates":[-85.63985099999999,42.970056],"type":"Point"}
}