{
  "type": "Feature",
  "properties": {
    "iso:country":"US",
    "sg:address":"18316 Middlebelt Rd",
    "sg:city":"Livonia",
    "sg:classifiers":[
        {
            "category":"Health Services",
            "subcategory":"Clinic",
            "type":"Services"
        }
    ],
    "sg:phone":"+1 248 615 9730",
    "sg:postcode":"48152",
    "sg:province":"MI",
    "sg:tags":[
        "specialty",
        "outpatient"
    ],
    "wof:name":"Lifespan Family Service",
    "wof:placetype":"venue"
},
  "geometry": {"coordinates":[-83.335587,42.422356],"type":"Point"}
}