{
  "type": "Feature",
  "properties": {
    "iso:country":"US",
    "sg:address":"1028 Shire Ave",
    "sg:city":"Petoskey",
    "sg:classifiers":[
        {
            "category":"Building & Trades",
            "subcategory":"Cleaning & Sanitation",
            "type":"Services"
        }
    ],
    "sg:phone":"+1 231 348 9628",
    "sg:postcode":"49770",
    "sg:province":"MI",
    "sg:tags":[
        "maintenance"
    ],
    "wof:name":"Little Bay Maintenance & Repr",
    "wof:placetype":"venue"
},
  "geometry": {"coordinates":[-84.924604,45.388146],"type":"Point"}
}