{
  "type": "Feature",
  "properties": {
    "iso:country":"US",
    "sg:address":"2407 Peale Dr",
    "sg:city":"Saginaw",
    "sg:classifiers":[
        {
            "category":"Professional",
            "subcategory":"Lawyer & Legal Services",
            "type":"Services"
        }
    ],
    "sg:phone":"+1 989 790 0480",
    "sg:postcode":"48602",
    "sg:province":"MI",
    "sg:tags":[
        "attorney"
    ],
    "wof:name":"Mertz & Mertz",
    "wof:placetype":"venue"
},
  "geometry": {"coordinates":[-83.985929,43.441367],"type":"Point"}
}