{
  "type": "Feature",
  "properties": {
    "iso:country":"US",
    "sg:address":"426 S Walnut St",
    "sg:city":"Lansing",
    "sg:classifiers":[
        {
            "category":"Health Services",
            "subcategory":"Clinic",
            "type":"Services"
        }
    ],
    "sg:phone":"+1 517 485 9033",
    "sg:postcode":"48933",
    "sg:province":"MI",
    "sg:tags":[
        "agency",
        "welfare"
    ],
    "wof:name":"Michigan Environmental Health",
    "wof:placetype":"venue"
},
  "geometry": {"coordinates":[-84.557087,42.729068],"type":"Point"}
}