{
  "type": "Feature",
  "properties": {
    "iso:country":"US",
    "sg:address":"27 N Washington St",
    "sg:city":"Oxford",
    "sg:classifiers":[
        {
            "category":"Shopping",
            "subcategory":"Gifts & Souvenirs",
            "type":"Retail Goods"
        }
    ],
    "sg:phone":"+1 248 628 6933",
    "sg:postcode":"48371",
    "sg:province":"MI",
    "sg:tags":[
        "party",
        "supply"
    ],
    "wof:name":"Heckle & Jeckle's Party Stop",
    "wof:placetype":"venue"
},
  "geometry": {"coordinates":[-83.26600500000001,42.825862],"type":"Point"}
}