{
  "type": "Feature",
  "properties": {
    "iso:country":"US",
    "sg:address":"2034 Lawndale St",
    "sg:city":"Detroit",
    "sg:classifiers":[
        {
            "category":"Organizations",
            "subcategory":"Community Association",
            "type":"Services"
        }
    ],
    "sg:phone":"+1 313 841 7103",
    "sg:postcode":"48209",
    "sg:province":"MI",
    "wof:name":"Lodge 1870 - Suthwest Detroit",
    "wof:placetype":"venue"
},
  "geometry": {"coordinates":[-83.131473,42.30775],"type":"Point"}
}