{
  "type": "Feature",
  "properties": {
    "iso:country":"US",
    "sg:address":"2030 N Graham Rd",
    "sg:city":"Freeland",
    "sg:classifiers":[
        {
            "category":"Professional",
            "subcategory":"Management & Consulting",
            "type":"Services"
        }
    ],
    "sg:phone":"+1 989 781 9935",
    "sg:postcode":"48623",
    "sg:province":"MI",
    "sg:tags":[
        "business"
    ],
    "wof:name":"A T C",
    "wof:placetype":"venue"
},
  "geometry": {"coordinates":[-84.130927,43.438373],"type":"Point"}
}