{
  "type": "Feature",
  "properties": {
    "iso:country":"US",
    "sg:address":"128 S Lafayette St",
    "sg:city":"Greenville",
    "sg:classifiers":[
        {
            "category":"Personal",
            "subcategory":"Hair Removal",
            "type":"Services"
        }
    ],
    "sg:phone":"+1 616 225 8633",
    "sg:postcode":"48838",
    "sg:province":"MI",
    "sg:tags":[
        "advisory",
        "financial"
    ],
    "wof:name":"Raymond James",
    "wof:placetype":"venue"
},
  "geometry": {"coordinates":[-85.253062,43.180377],"type":"Point"}
}