{
  "type": "Feature",
  "properties": {
    "iso:country":"US",
    "sg:address":"16836 Marsh Rd",
    "sg:city":"Haslett",
    "sg:classifiers":[
        {
            "category":"Retail",
            "subcategory":"Auto Repair",
            "type":"Services"
        }
    ],
    "sg:phone":"+1 517 339 8888",
    "sg:postcode":"48840",
    "sg:province":"MI",
    "sg:tags":[
        "automotive"
    ],
    "wof:name":"Ex Valvoline Care & Carwash",
    "wof:placetype":"venue"
},
  "geometry": {"coordinates":[-84.41315,42.773145],"type":"Point"}
}