{
  "type": "Feature",
  "properties": {
    "iso:country":"US",
    "sg:address":"25620 Van Born Rd",
    "sg:city":"Dearborn Heights",
    "sg:classifiers":[
        {
            "category":"Retail",
            "subcategory":"Event Space",
            "type":"Services"
        }
    ],
    "sg:phone":"+1 313 292 6531",
    "sg:postcode":"48125",
    "sg:province":"MI",
    "sg:tags":[
        "venue"
    ],
    "wof:name":"Donovan Vfw Hall",
    "wof:placetype":"venue"
},
  "geometry": {"coordinates":[-83.287498,42.268799],"type":"Point"}
}