{
  "type": "Feature",
  "properties": {
    "iso:country":"US",
    "sg:address":"6211 W Willow Hwy",
    "sg:city":"Lansing",
    "sg:classifiers":[
        {
            "category":"Education",
            "subcategory":"College",
            "type":"Public Place"
        }
    ],
    "sg:phone":"+1 517 321 0242",
    "sg:postcode":"48917",
    "sg:province":"MI",
    "sg:tags":[
        "christian"
    ],
    "wof:name":"Great Lakes Christian College",
    "wof:placetype":"venue"
},
  "geometry": {"coordinates":[-84.63704,42.755439],"type":"Point"}
}