{
  "type": "Feature",
  "properties": {
    "iso:country":"US",
    "sg:address":"111 N Hanchett St",
    "sg:city":"Coldwater",
    "sg:classifiers":[
        {
            "category":"Education",
            "subcategory":"Dance Studio",
            "type":"Public Place"
        }
    ],
    "sg:phone":"+1 517 279 9426",
    "sg:postcode":"49036",
    "sg:province":"MI",
    "sg:tags":[
        "instruction",
        "dancing"
    ],
    "wof:name":"Kathy's School Of Dance",
    "wof:placetype":"venue"
},
  "geometry": {"coordinates":[-85.003337,41.944611],"type":"Point"}
}