{
  "type": "Feature",
  "properties": {
    "iso:country":"US",
    "sg:address":"10977 Hoffman Rd",
    "sg:city":"Maybee",
    "sg:classifiers":[
        {
            "category":"Retail",
            "subcategory":"Repair Shop",
            "type":"Services"
        }
    ],
    "sg:phone":"+1 734 439 0672",
    "sg:postcode":"48159",
    "sg:province":"MI",
    "sg:tags":[
        "welding"
    ],
    "wof:name":"B M F Welding & Fabricating",
    "wof:placetype":"venue"
},
  "geometry": {"coordinates":[-83.579403,42.028044],"type":"Point"}
}