{
  "type": "Feature",
  "properties": {
    "iso:country":"US",
    "sg:address":"1900 W Houghton Lake Dr",
    "sg:city":"Houghton Lake",
    "sg:classifiers":[
        {
            "category":"Autos & Motor Vehicles",
            "subcategory":"Automobile Sales",
            "type":"Retail Goods"
        }
    ],
    "sg:phone":"+1 989 366 7100",
    "sg:postcode":"48629",
    "sg:province":"MI",
    "sg:tags":[
        "used"
    ],
    "wof:name":"Perrin Automotive North",
    "wof:placetype":"venue"
},
  "geometry": {"coordinates":[-84.77063800000001,44.326701],"type":"Point"}
}