{
  "type": "Feature",
  "properties": {
    "iso:country":"US",
    "sg:address":"519 W Elm St",
    "sg:city":"Reading",
    "sg:classifiers":[
        {
            "category":"Education",
            "subcategory":"School",
            "type":"Public Place"
        }
    ],
    "sg:phone":"+1 517 283 2166",
    "sg:postcode":"49274",
    "sg:province":"MI",
    "sg:website":"www.rcsk12.org",
    "wof:name":"Reading Community School Dist",
    "wof:placetype":"venue"
},
  "geometry": {"coordinates":[-84.754153,41.836042],"type":"Point"}
}