{
  "type": "Feature",
  "properties": {
    "iso:country":"US",
    "sg:address":"2338 US Hwy 23 N",
    "sg:city":"Alpena",
    "sg:classifiers":[
        {
            "category":"Shopping",
            "subcategory":"Department Store",
            "type":"Retail Goods"
        }
    ],
    "sg:phone":"+1 989 354 3124",
    "sg:postcode":"49707",
    "sg:province":"MI",
    "wof:name":"J C Penney Co",
    "wof:placetype":"venue"
},
  "geometry": {"coordinates":[-83.456513,45.095462],"type":"Point"}
}