{
  "type": "Feature",
  "properties": {
    "iso:country":"US",
    "sg:address":"150 S Stewart Ave",
    "sg:city":"Big Rapids",
    "sg:classifiers":[
        {
            "category":"Professional",
            "subcategory":"Lawyer & Legal Services",
            "type":"Services"
        }
    ],
    "sg:phone":"+1 231 796 3525",
    "sg:postcode":"49307",
    "sg:province":"MI",
    "wof:name":"Hults & Helder",
    "wof:placetype":"venue"
},
  "geometry": {"coordinates":[-85.479004,43.697697],"type":"Point"}
}