{
  "type": "Feature",
  "properties": {
    "iso:country":"US",
    "sg:address":"3281 Cummings Ave",
    "sg:city":"Berkley",
    "sg:classifiers":[
        {
            "category":"Building & Trades",
            "subcategory":"Construction",
            "type":"Services"
        }
    ],
    "sg:phone":"+1 248 399 9131",
    "sg:postcode":"48072",
    "sg:province":"MI",
    "sg:tags":[
        "concrete",
        "contractor"
    ],
    "wof:name":"Bill Elwood Inc",
    "wof:placetype":"venue"
},
  "geometry": {"coordinates":[-83.199586,42.502188],"type":"Point"}
}