{
  "type": "Feature",
  "properties": {
    "iso:country":"US",
    "sg:address":"4399 108th Ave",
    "sg:city":"Allegan",
    "sg:classifiers":[
        {
            "category":"Shopping",
            "type":"Retail Goods"
        }
    ],
    "sg:phone":"+1 269 521 6560",
    "sg:postcode":"49010",
    "sg:province":"MI",
    "sg:tags":[
        "church",
        "supply"
    ],
    "wof:name":"Chicora Country Chapel",
    "wof:placetype":"venue"
},
  "geometry": {"coordinates":[-85.97405999999999,42.476816],"type":"Point"}
}