{
  "type": "Feature",
  "properties": {
    "iso:country":"US",
    "sg:address":"324 Crystal Ave",
    "sg:city":"Crystal Falls",
    "sg:classifiers":[
        {
            "category":"Insurance",
            "subcategory":"Insurance Agent",
            "type":"Services"
        }
    ],
    "sg:phone":"+1 906 875 6626",
    "sg:postcode":"49920",
    "sg:province":"MI",
    "sg:website":"www.ludstooragency.com",
    "wof:name":"Lud Stoor Insurance",
    "wof:placetype":"venue"
},
  "geometry": {"coordinates":[-88.331537,46.097883],"type":"Point"}
}