{
  "type": "Feature",
  "properties": {
    "iso:country":"US",
    "sg:address":"626 W Division St",
    "sg:city":"Ishpeming",
    "sg:classifiers":[
        {
            "category":"Building & Trades",
            "subcategory":"Construction",
            "type":"Services"
        }
    ],
    "sg:phone":"+1 906 485 1598",
    "sg:postcode":"49849",
    "sg:province":"MI",
    "sg:tags":[
        "general",
        "contractor"
    ],
    "wof:name":"R E Holappa Construction",
    "wof:placetype":"venue"
},
  "geometry": {"coordinates":[-87.68065,46.488898],"type":"Point"}
}