{
  "type": "Feature",
  "properties": {
    "iso:country":"US",
    "sg:address":"7531 Dixie Hwy",
    "sg:city":"Bridgeport",
    "sg:classifiers":[
        {
            "category":"Retail",
            "subcategory":"Auto Repair",
            "type":"Services"
        }
    ],
    "sg:phone":"+1 989 777 7204",
    "sg:postcode":"48722",
    "sg:province":"MI",
    "sg:tags":[
        "body",
        "automobile",
        "painting"
    ],
    "wof:name":"Kranz's Collision",
    "wof:placetype":"venue"
},
  "geometry": {"coordinates":[-83.822844,43.321275],"type":"Point"}
}