{
  "type": "Feature",
  "properties": {
    "iso:country":"US",
    "sg:address":"5300 Pickerel Lake Rd",
    "sg:city":"Petoskey",
    "sg:classifiers":[
        {
            "category":"Building & Trades",
            "subcategory":"Landscaping Services",
            "type":"Services"
        }
    ],
    "sg:phone":"+1 231 347 9699",
    "sg:postcode":"49770",
    "sg:province":"MI",
    "sg:tags":[
        "lawn",
        "maintenance",
        "grounds"
    ],
    "wof:name":"All Season's Maintenance",
    "wof:placetype":"venue"
},
  "geometry": {"coordinates":[-84.857484,45.391589],"type":"Point"}
}