{
  "type": "Feature",
  "properties": {
    "iso:country":"US",
    "sg:address":"14600 Lakeside Cir",
    "sg:city":"Sterling Heights",
    "sg:classifiers":[
        {
            "category":"Shopping",
            "subcategory":"Clothing, Apparel, & Fashions",
            "type":"Retail Goods"
        }
    ],
    "sg:phone":"+1 586 247 8589",
    "sg:postcode":"48313",
    "sg:province":"MI",
    "sg:tags":[
        "children's",
        "clothing"
    ],
    "sg:website":"www.gymboree.com",
    "wof:name":"Gymboree Store",
    "wof:placetype":"venue"
},
  "geometry": {"coordinates":[-82.9813,42.621799],"type":"Point"}
}