{
  "type": "Feature",
  "properties": {
    "iso:country":"US",
    "sg:address":"3026 W Saginaw Rd",
    "sg:city":"Vassar",
    "sg:classifiers":[
        {
            "category":"Food & Beverages",
            "subcategory":"Groceries & Convenience Stores",
            "type":"Retail Goods"
        }
    ],
    "sg:phone":"+1 989 843 5910",
    "sg:postcode":"48768",
    "sg:province":"MI",
    "sg:tags":[
        "alcoholic"
    ],
    "wof:name":"Coloskys Market",
    "wof:placetype":"venue"
},
  "geometry": {"coordinates":[-83.466217,43.35036],"type":"Point"}
}