{
  "type": "Feature",
  "properties": {
    "iso:country":"US",
    "sg:address":"416 W Hudson Ave",
    "sg:city":"Royal Oak",
    "sg:classifiers":[
        {
            "category":"Retail",
            "subcategory":"Portrait Studio",
            "type":"Services"
        }
    ],
    "sg:phone":"+1 248 543 5566",
    "sg:postcode":"48067",
    "sg:province":"MI",
    "sg:tags":[
        "photo"
    ],
    "wof:name":"Mark Trupiano Photo-Graphic",
    "wof:placetype":"venue"
},
  "geometry": {"coordinates":[-83.15098500000001,42.481542],"type":"Point"}
}