{
  "type": "Feature",
  "properties": {
    "iso:country":"US",
    "sg:address":"20743 Van Born Rd",
    "sg:city":"Taylor",
    "sg:classifiers":[
        {
            "category":"Retail",
            "subcategory":"Auto Repair",
            "type":"Services"
        }
    ],
    "sg:phone":"+1 313 278 3265",
    "sg:postcode":"48180",
    "sg:province":"MI",
    "sg:tags":[
        "automotive"
    ],
    "wof:name":"Robert Burton",
    "wof:placetype":"venue"
},
  "geometry": {"coordinates":[-83.23973599999999,42.269625],"type":"Point"}
}