{
  "type": "Feature",
  "properties": {
    "iso:country":"US",
    "sg:address":"100 Grandville Ave SW",
    "sg:city":"Grand Rapids",
    "sg:classifiers":[
        {
            "category":"Professional",
            "subcategory":"Management & Consulting",
            "type":"Services"
        }
    ],
    "sg:phone":"+1 616 235 9580",
    "sg:postcode":"49503",
    "sg:province":"MI",
    "sg:tags":[
        "public",
        "relations"
    ],
    "wof:name":"North Star Public Relations",
    "wof:placetype":"venue"
},
  "geometry": {"coordinates":[-85.673484,42.960443],"type":"Point"}
}