{
  "type": "Feature",
  "properties": {
    "iso:country":"US",
    "sg:address":"2345 Lapeer Rd",
    "sg:city":"Flint",
    "sg:classifiers":[
        {
            "category":"Organizations",
            "subcategory":"Labor Organization",
            "type":"Services"
        }
    ],
    "sg:phone":"+1 810 239 0931",
    "sg:postcode":"48503",
    "sg:province":"MI",
    "wof:name":"Flint Area Local American",
    "wof:placetype":"venue"
},
  "geometry": {"coordinates":[-83.66502199999999,43.009447],"type":"Point"}
}