{
  "type": "Feature",
  "properties": {
    "iso:country":"US",
    "sg:address":"161 Ottawa Ave NW",
    "sg:city":"Grand Rapids",
    "sg:classifiers":[
        {
            "category":"Insurance",
            "subcategory":"Insurance Agent",
            "type":"Services"
        }
    ],
    "sg:phone":"+1 616 454 8257",
    "sg:postcode":"49503",
    "sg:province":"MI",
    "sg:tags":[
        "broker"
    ],
    "wof:name":"Paul Goebel Group",
    "wof:placetype":"venue"
},
  "geometry": {"coordinates":[-85.67011100000001,42.967049],"type":"Point"}
}