{
  "type": "Feature",
  "properties": {
    "iso:country":"US",
    "sg:address":"16815 James Couzens Fwy",
    "sg:city":"Detroit",
    "sg:classifiers":[
        {
            "category":"Organizations",
            "subcategory":"Community Association",
            "type":"Services"
        }
    ],
    "sg:phone":"+1 313 862 0600",
    "sg:postcode":"48235",
    "sg:province":"MI",
    "wof:name":"Eta PHI Beta Sorority Fdtn Inc",
    "wof:placetype":"venue"
},
  "geometry": {"coordinates":[-83.17075699999999,42.414641],"type":"Point"}
}