{
  "type": "Feature",
  "properties": {
    "iso:country":"US",
    "sg:address":"23153 Michigan Ave",
    "sg:city":"Dearborn",
    "sg:classifiers":[
        {
            "category":"Banks & Credit Unions",
            "subcategory":"Bank",
            "type":"Services"
        }
    ],
    "sg:phone":"+1 313 562 6910",
    "sg:postcode":"48124",
    "sg:province":"MI",
    "sg:website":"www.nationalcity.com",
    "wof:name":"National City",
    "wof:placetype":"venue"
},
  "geometry": {"coordinates":[-83.26039900000001,42.302299],"type":"Point"}
}