{
  "type": "Feature",
  "properties": {
    "iso:country":"US",
    "sg:address":"3196 Burkley Rd",
    "sg:city":"Williamston",
    "sg:classifiers":[
        {
            "category":"Manufacturing",
            "subcategory":"Printing",
            "type":"Manufacturing & Wholesale Goods"
        }
    ],
    "sg:phone":"+1 517 655 5899",
    "sg:postcode":"48895",
    "sg:province":"MI",
    "sg:tags":[
        "printer"
    ],
    "wof:name":"Above & Beyond Labels",
    "wof:placetype":"venue"
},
  "geometry": {"coordinates":[-84.34193,42.681507],"type":"Point"}
}