{
  "type": "Feature",
  "properties": {
    "iso:country":"US",
    "sg:address":"512 Pilgrim Dr E",
    "sg:city":"Saginaw",
    "sg:classifiers":[
        {
            "category":"Real Estate",
            "subcategory":"Real Estate Agent",
            "type":"Services"
        }
    ],
    "sg:phone":"+1 989 793 3449",
    "sg:postcode":"48638",
    "sg:province":"MI",
    "wof:name":"Court Centre Complex",
    "wof:placetype":"venue"
},
  "geometry": {"coordinates":[-84.02037199999999,43.418984],"type":"Point"}
}