{
  "type": "Feature",
  "properties": {
    "iso:country":"US",
    "sg:address":"1515 Ridge Rd",
    "sg:city":"Ypsilanti",
    "sg:classifiers":[
        {
            "category":"Shopping",
            "subcategory":"Gifts & Souvenirs",
            "type":"Retail Goods"
        }
    ],
    "sg:phone":"+1 734 340 2305",
    "sg:postcode":"48198",
    "sg:province":"MI",
    "wof:name":"Gifts For Every Occasion",
    "wof:placetype":"venue"
},
  "geometry": {"coordinates":[-83.554168,42.275215],"type":"Point"}
}