{
  "type": "Feature",
  "properties": {
    "iso:country":"US",
    "sg:address":"33215 Grand River Ave",
    "sg:city":"Farmington",
    "sg:classifiers":[
        {
            "category":"Insurance",
            "subcategory":"Hazard Insurance",
            "type":"Services"
        }
    ],
    "sg:phone":"+1 248 478 7760",
    "sg:postcode":"48336",
    "sg:province":"MI",
    "sg:tags":[
        "fidelity",
        "bond"
    ],
    "wof:name":"Swales Agency",
    "wof:placetype":"venue"
},
  "geometry": {"coordinates":[-83.37524000000001,42.464311],"type":"Point"}
}