{
  "type": "Feature",
  "properties": {
    "iso:country":"US",
    "sg:address":"5675 Palms Rd",
    "sg:city":"Casco",
    "sg:classifiers":[
        {
            "category":"Insurance",
            "subcategory":"Insurance Agent",
            "type":"Services"
        }
    ],
    "sg:phone":"+1 810 765 4858",
    "sg:postcode":"48064",
    "sg:province":"MI",
    "wof:name":"Thrivent Fincl For Lutherans",
    "wof:placetype":"venue"
},
  "geometry": {"coordinates":[-82.630717,42.729369],"type":"Point"}
}