{
  "type": "Feature",
  "properties": {
    "iso:country":"US",
    "sg:address":"1046 Estey Rd",
    "sg:city":"Beaverton",
    "sg:classifiers":[
        {
            "category":"Building & Trades",
            "subcategory":"Cleaning & Sanitation",
            "type":"Services"
        }
    ],
    "sg:phone":"+1 865 548 1965",
    "sg:postcode":"48612",
    "sg:province":"MI",
    "sg:tags":[
        "maintenance"
    ],
    "wof:name":"Trident Resource Corporation",
    "wof:placetype":"venue"
},
  "geometry": {"coordinates":[-84.327004,43.871549],"type":"Point"}
}