{
  "type": "Feature",
  "properties": {
    "iso:country":"US",
    "sg:address":"2005 Parkwood Ave",
    "sg:city":"Saginaw",
    "sg:classifiers":[
        {
            "category":"Social Services",
            "subcategory":"Adult Care",
            "type":"Services"
        }
    ],
    "sg:phone":"+1 989 752 0883",
    "sg:postcode":"48601",
    "sg:province":"MI",
    "sg:tags":[
        "foster",
        "provider"
    ],
    "wof:name":"McDonald Zeola",
    "wof:placetype":"venue"
},
  "geometry": {"coordinates":[-83.939933,43.408929],"type":"Point"}
}