{
  "type": "Feature",
  "properties": {
    "iso:country":"US",
    "sg:address":"1761 Schoenith Ln",
    "sg:city":"Bloomfield Hills",
    "sg:classifiers":[
        {
            "category":"Health Services",
            "subcategory":"Doctor",
            "type":"Services"
        }
    ],
    "sg:phone":"+1 248 626 3727",
    "sg:postcode":"48302",
    "sg:province":"MI",
    "sg:tags":[
        "medical"
    ],
    "wof:name":"Garcia M D Michael",
    "wof:placetype":"venue"
},
  "geometry": {"coordinates":[-83.311412,42.564226],"type":"Point"}
}