{
  "type": "Feature",
  "properties": {
    "iso:country":"US",
    "sg:address":"637 S Connecticut Ave",
    "sg:city":"Royal Oak",
    "sg:classifiers":[
        {
            "category":"Building & Trades",
            "subcategory":"Construction",
            "type":"Services"
        }
    ],
    "sg:phone":"+1 248 545 5518",
    "sg:postcode":"48067",
    "sg:province":"MI",
    "sg:tags":[
        "paving",
        "asphalt",
        "contractor"
    ],
    "wof:name":"Baldwin Asphalt Seal Coating",
    "wof:placetype":"venue"
},
  "geometry": {"coordinates":[-83.126538,42.483754],"type":"Point"}
}