{
  "type": "Feature",
  "properties": {
    "iso:country":"US",
    "sg:address":"566 W Long Lake Rd",
    "sg:city":"Traverse City",
    "sg:classifiers":[
        {
            "category":"Real Estate",
            "subcategory":"Real Estate Agent",
            "type":"Services"
        }
    ],
    "sg:phone":"+1 231 943 3234",
    "sg:postcode":"49684",
    "sg:province":"MI",
    "wof:name":"Hearth Stone Land & Homes",
    "wof:placetype":"venue"
},
  "geometry": {"coordinates":[-85.76330299999999,44.699462],"type":"Point"}
}