{
  "type": "Feature",
  "properties": {
    "iso:country":"US",
    "sg:address":"412 Prospect Ave",
    "sg:city":"Alma",
    "sg:classifiers":[
        {
            "category":"Professional",
            "subcategory":"Business Services",
            "type":"Services"
        }
    ],
    "sg:phone":"+1 989 463 2120",
    "sg:postcode":"48801",
    "sg:province":"MI",
    "sg:tags":[
        "transcribing",
        "disc"
    ],
    "wof:name":"Mid-Michigan Braille",
    "wof:placetype":"venue"
},
  "geometry": {"coordinates":[-84.663337,43.380001],"type":"Point"}
}