{
  "type": "Feature",
  "properties": {
    "iso:country":"US",
    "sg:address":"1351 Rowe Rd",
    "sg:city":"Milford",
    "sg:classifiers":[
        {
            "category":"Building & Trades",
            "subcategory":"Landscaping Services",
            "type":"Services"
        }
    ],
    "sg:phone":"+1 248 684 7947",
    "sg:postcode":"48380",
    "sg:province":"MI",
    "wof:name":"Stouts Lawn Care",
    "wof:placetype":"venue"
},
  "geometry": {"coordinates":[-83.631883,42.608153],"type":"Point"}
}