{
  "type": "Feature",
  "properties": {
    "iso:country":"US",
    "sg:address":"1070 S Haven Pl",
    "sg:city":"South Haven",
    "sg:classifiers":[
        {
            "category":"Organizations",
            "subcategory":"Professional Association",
            "type":"Services"
        }
    ],
    "sg:phone":"+1 269 637 2304",
    "sg:postcode":"49090",
    "sg:province":"MI",
    "sg:tags":[
        "business"
    ],
    "wof:name":"Sgt George S Monroe",
    "wof:placetype":"venue"
},
  "geometry": {"coordinates":[-86.25959400000001,42.396242],"type":"Point"}
}