{
  "type": "Feature",
  "properties": {
    "iso:country":"US",
    "sg:address":"47255 Northgate Dr",
    "sg:city":"Canton",
    "sg:classifiers":[
        {
            "category":"Education",
            "subcategory":"School",
            "type":"Public Place"
        }
    ],
    "sg:phone":"+1 734 495 1903",
    "sg:postcode":"48188",
    "sg:province":"MI",
    "wof:name":"Great Lakes Education Center",
    "wof:placetype":"venue"
},
  "geometry": {"coordinates":[-83.50160200000001,42.2869],"type":"Point"}
}