{
  "type": "Feature",
  "properties": {
    "iso:country":"US",
    "sg:address":"5119 N Shore Dr",
    "sg:city":"Clarklake",
    "sg:classifiers":[
        {
            "category":"Personal",
            "subcategory":"Beauty Salon",
            "type":"Services"
        }
    ],
    "sg:phone":"+1 517 529 4587",
    "sg:postcode":"49234",
    "sg:province":"MI",
    "sg:tags":[
        "shop",
        "transportation"
    ],
    "wof:name":"Door To Door Trnsp Svc",
    "wof:placetype":"venue"
},
  "geometry": {"coordinates":[-84.31703899999999,42.124863],"type":"Point"}
}