{
  "type": "Feature",
  "properties": {
    "iso:country":"US",
    "sg:address":"13950 Meyers Rd",
    "sg:city":"Detroit",
    "sg:classifiers":[
        {
            "category":"Organizations",
            "subcategory":"Religious Organization",
            "type":"Services"
        }
    ],
    "sg:phone":"+1 313 491 2475",
    "sg:postcode":"48227",
    "sg:province":"MI",
    "wof:name":"Westside Bibleway Baptist Church",
    "wof:placetype":"venue"
},
  "geometry": {"coordinates":[-83.16860200000001,42.3895],"type":"Point"}
}