{
  "type": "Feature",
  "properties": {
    "iso:country":"US",
    "sg:address":"17550 Floral St",
    "sg:city":"Livonia",
    "sg:classifiers":[
        {
            "category":"Building & Trades",
            "subcategory":"Construction",
            "type":"Services"
        }
    ],
    "sg:phone":"+1 734 421 9258",
    "sg:postcode":"48152",
    "sg:province":"MI",
    "sg:tags":[
        "home",
        "remodeling",
        "contractor"
    ],
    "wof:name":"Jordan Restorations",
    "wof:placetype":"venue"
},
  "geometry": {"coordinates":[-83.322542,42.416311],"type":"Point"}
}