{
  "type": "Feature",
  "properties": {
    "iso:country":"US",
    "sg:address":"29 Riverview Dr",
    "sg:city":"Lapeer",
    "sg:classifiers":[
        {
            "category":"Freight",
            "type":"Transportation"
        }
    ],
    "sg:phone":"+1 810 245 3652",
    "sg:postcode":"48446",
    "sg:province":"MI",
    "sg:tags":[
        "operator",
        "local",
        "trucking"
    ],
    "wof:name":"MCB Trucking LLC",
    "wof:placetype":"venue"
},
  "geometry": {"coordinates":[-83.305026,43.075973],"type":"Point"}
}