{
  "type": "Feature",
  "properties": {
    "iso:country":"US",
    "sg:address":"3478 Pointe Tremble Rd",
    "sg:city":"Algonac",
    "sg:classifiers":[
        {
            "category":"Home & Garden",
            "subcategory":"Building Materials",
            "type":"Retail Goods"
        }
    ],
    "sg:phone":"+1 810 794 3172",
    "sg:postcode":"48001",
    "sg:province":"MI",
    "sg:tags":[
        "plumbing",
        "fixture",
        "supply"
    ],
    "wof:name":"Prior Plumbing & Heating Inc",
    "wof:placetype":"venue"
},
  "geometry": {"coordinates":[-82.56019999999999,42.618616],"type":"Point"}
}