{
  "type": "Feature",
  "properties": {
    "iso:country":"US",
    "sg:address":"2164 Oak St",
    "sg:city":"Niles",
    "sg:classifiers":[
        {
            "category":"Retail",
            "subcategory":"Veterinary Services",
            "type":"Services"
        }
    ],
    "sg:phone":"+1 269 683 6511",
    "sg:postcode":"49120",
    "sg:province":"MI",
    "sg:tags":[
        "veterinarian"
    ],
    "wof:name":"County Line Animal Clinic",
    "wof:placetype":"venue"
},
  "geometry": {"coordinates":[-86.228762,41.826583],"type":"Point"}
}