{
  "type": "Feature",
  "properties": {
    "iso:country":"US",
    "sg:address":"19332 Forrer St",
    "sg:city":"Detroit",
    "sg:classifiers":[
        {
            "category":"Building & Trades",
            "subcategory":"Cleaning & Sanitation",
            "type":"Services"
        }
    ],
    "sg:phone":"+1 313 272 8791",
    "sg:postcode":"48235",
    "sg:province":"MI",
    "sg:tags":[
        "maintenance"
    ],
    "wof:name":"E&W Cleaning Services Inc",
    "wof:placetype":"venue"
},
  "geometry": {"coordinates":[-83.203185,42.433383],"type":"Point"}
}