{
  "type": "Feature",
  "properties": {
    "iso:country":"US",
    "sg:address":"228 48th St SE",
    "sg:city":"Grand Rapids",
    "sg:classifiers":[
        {
            "category":"Social Services",
            "subcategory":"Child Care",
            "type":"Services"
        }
    ],
    "sg:phone":"+1 616 534 9347",
    "sg:postcode":"49548",
    "sg:province":"MI",
    "sg:tags":[
        "day",
        "provider"
    ],
    "wof:name":"Linda Boot",
    "wof:placetype":"venue"
},
  "geometry": {"coordinates":[-85.657083,42.876602],"type":"Point"}
}