{
  "type": "Feature",
  "properties": {
    "iso:country":"US",
    "sg:address":"625 Harrison St",
    "sg:city":"Kalamazoo",
    "sg:classifiers":[
        {
            "category":"Professional",
            "subcategory":"Engineering",
            "type":"Services"
        }
    ],
    "sg:phone":"+1 269 373 8000",
    "sg:postcode":"49007",
    "sg:province":"MI",
    "sg:tags":[
        "engineer"
    ],
    "wof:name":"West Tech Design Inc",
    "wof:placetype":"venue"
},
  "geometry": {"coordinates":[-85.57485699999999,42.298163],"type":"Point"}
}