{
  "type": "Feature",
  "properties": {
    "iso:country":"US",
    "sg:address":"222 Howard St",
    "sg:city":"Cadillac",
    "sg:classifiers":[
        {
            "category":"Professional",
            "subcategory":"Accounting & Tax Preparation",
            "type":"Services"
        }
    ],
    "sg:phone":"+1 231 775 0174",
    "sg:postcode":"49601",
    "sg:province":"MI",
    "sg:tags":[
        "accountant"
    ],
    "sg:website":"www.thedriftwoodlodge.com",
    "wof:name":"Jay K Thiebaut CPA",
    "wof:placetype":"venue"
},
  "geometry": {"coordinates":[-85.39408299999999,44.247545],"type":"Point"}
}