{
  "type": "Feature",
  "properties": {
    "iso:country":"US",
    "sg:address":"3555 Alpine Ave NW",
    "sg:city":"Grand Rapids",
    "sg:classifiers":[
        {
            "category":"Restaurant",
            "type":"Food & Drink"
        }
    ],
    "sg:menulink":"http://www.allmenus.com/mi/walker/122002-quiznos-sub/menu/",
    "sg:phone":"+1 616 988 7721",
    "sg:postcode":"49544",
    "sg:province":"MI",
    "sg:tags":[
        "wrap",
        "american",
        "sandwich"
    ],
    "wof:name":"Quiznos Sub",
    "wof:placetype":"venue"
},
  "geometry": {"coordinates":[-85.689314,43.027955],"type":"Point"}
}