{
  "type": "Feature",
  "properties": {
    "iso:country":"US",
    "sg:address":"17467 Brill Dr",
    "sg:city":"Clinton Twp",
    "sg:classifiers":[
        {
            "category":"Wholesale",
            "subcategory":"Computers",
            "type":"Manufacturing & Wholesale Goods"
        }
    ],
    "sg:phone":"+1 586 790 7909",
    "sg:postcode":"48035",
    "sg:province":"MI",
    "sg:tags":[
        "communications",
        "datum"
    ],
    "wof:name":"Black Box Network Svc",
    "wof:placetype":"venue"
},
  "geometry": {"coordinates":[-82.94141399999999,42.557713],"type":"Point"}
}