{
  "type": "Feature",
  "properties": {
    "iso:country":"US",
    "sg:address":"29208 Hoover Rd",
    "sg:city":"Warren",
    "sg:classifiers":[
        {
            "category":"Personal",
            "type":"Services"
        }
    ],
    "sg:phone":"+1 586 751 3430",
    "sg:postcode":"48093",
    "sg:province":"MI",
    "sg:tags":[
        "program",
        "physical",
        "exercise",
        "fitness"
    ],
    "wof:name":"Fit For Eternity",
    "wof:placetype":"venue"
},
  "geometry": {"coordinates":[-83.006861,42.507616],"type":"Point"}
}