{
  "type": "Feature",
  "properties": {
    "iso:country":"US",
    "sg:address":"2709 S Telegraph Rd",
    "sg:city":"Bloomfield Hills",
    "sg:classifiers":[
        {
            "category":"Real Estate",
            "subcategory":"Architect",
            "type":"Services"
        }
    ],
    "sg:phone":"+1 248 418 0990",
    "sg:postcode":"48302",
    "sg:province":"MI",
    "sg:website":"www.redstonearchitects.com",
    "wof:name":"Redstone Architects",
    "wof:placetype":"venue"
},
  "geometry": {"coordinates":[-83.285312,42.600594],"type":"Point"}
}