{
  "type": "Feature",
  "properties": {
    "iso:country":"US",
    "sg:address":"14551 Southfield Rd",
    "sg:city":"Allen Park",
    "sg:classifiers":[
        {
            "category":"Health Services",
            "subcategory":"Doctor",
            "type":"Services"
        }
    ],
    "sg:phone":"+1 313 388 0910",
    "sg:postcode":"48101",
    "sg:province":"MI",
    "wof:name":"Haque Rafia MD Ofc",
    "wof:placetype":"venue"
},
  "geometry": {"coordinates":[-83.19760100000001,42.256199],"type":"Point"}
}