{
  "type": "Feature",
  "properties": {
    "iso:country":"US",
    "sg:address":"7115 Davis Rd",
    "sg:city":"Buckley",
    "sg:classifiers":[
        {
            "category":"Wholesale",
            "subcategory":"Farm Supplies",
            "type":"Manufacturing & Wholesale Goods"
        }
    ],
    "sg:phone":"+1 231 263 7130",
    "sg:postcode":"49620",
    "sg:province":"MI",
    "sg:tags":[
        "grain"
    ],
    "wof:name":"George's Grainery",
    "wof:placetype":"venue"
},
  "geometry": {"coordinates":[-85.720069,44.556062],"type":"Point"}
}