{
  "type": "Feature",
  "properties": {
    "iso:country":"US",
    "sg:address":"1212 107th Ave",
    "sg:city":"Otsego",
    "sg:classifiers":[
        {
            "category":"Shopping",
            "subcategory":"Gifts & Souvenirs",
            "type":"Retail Goods"
        }
    ],
    "sg:phone":"+1 269 685 5347",
    "sg:postcode":"49078",
    "sg:province":"MI",
    "wof:name":"Cookies Gifts",
    "wof:placetype":"venue"
},
  "geometry": {"coordinates":[-85.661969,42.471595],"type":"Point"}
}