{
  "type": "Feature",
  "properties": {
    "iso:country":"US",
    "sg:address":"34343 Glouster Cir",
    "sg:city":"Farmington",
    "sg:classifiers":[
        {
            "category":"Professional",
            "subcategory":"Business Services",
            "type":"Services"
        }
    ],
    "sg:phone":"+1 248 661 2016",
    "sg:postcode":"48331",
    "sg:province":"MI",
    "wof:name":"Engraving By Paul LLC",
    "wof:placetype":"venue"
},
  "geometry": {"coordinates":[-83.384531,42.523417],"type":"Point"}
}