{
  "type": "Feature",
  "properties": {
    "iso:country":"US",
    "sg:address":"132 N State St",
    "sg:city":"Saint Ignace",
    "sg:classifiers":[
        {
            "category":"Professional",
            "subcategory":"Lawyer & Legal Services",
            "type":"Services"
        }
    ],
    "sg:phone":"+1 906 643 7800",
    "sg:postcode":"49781",
    "sg:province":"MI",
    "sg:tags":[
        "law"
    ],
    "wof:name":"Brown & Brown Law Offices",
    "wof:placetype":"venue"
},
  "geometry": {"coordinates":[-84.725016,45.868011],"type":"Point"}
}