{
  "type": "Feature",
  "properties": {
    "iso:country":"US",
    "sg:address":"920 S University Ave",
    "sg:city":"Ann Arbor",
    "sg:classifiers":[
        {
            "category":"Education",
            "subcategory":"Library",
            "type":"Public Place"
        }
    ],
    "sg:phone":"+1 734 764 0406",
    "sg:postcode":"48104",
    "sg:province":"MI",
    "wof:name":"University Library",
    "wof:placetype":"venue"
},
  "geometry": {"coordinates":[-83.74068699999999,42.274947],"type":"Point"}
}