{
  "type": "Feature",
  "properties": {
    "iso:country":"US",
    "sg:address":"311 Cherry Ln",
    "sg:city":"Oakland",
    "sg:classifiers":[
        {
            "category":"Building & Trades",
            "subcategory":"Landscaping Services",
            "type":"Services"
        }
    ],
    "sg:phone":"+1 248 814 0846",
    "sg:postcode":"48363",
    "sg:province":"MI",
    "sg:tags":[
        "lawn",
        "maintenance",
        "grounds"
    ],
    "wof:name":"A & G Lawncare",
    "wof:placetype":"venue"
},
  "geometry": {"coordinates":[-83.166606,42.795372],"type":"Point"}
}