{
  "type": "Feature",
  "properties": {
    "iso:country":"US",
    "sg:address":"7276 Kessling St",
    "sg:city":"Davison",
    "sg:classifiers":[
        {
            "category":"Home & Garden",
            "subcategory":"Furniture",
            "type":"Retail Goods"
        }
    ],
    "sg:phone":"+1 810 653 2516",
    "sg:postcode":"48423",
    "sg:province":"MI",
    "wof:name":"Always On Time",
    "wof:placetype":"venue"
},
  "geometry": {"coordinates":[-83.563507,42.985017],"type":"Point"}
}