{
  "type": "Feature",
  "properties": {
    "iso:country":"US",
    "sg:address":"1294 W Lakewood Blvd",
    "sg:city":"Holland",
    "sg:classifiers":[
        {
            "category":"Education",
            "subcategory":"School",
            "type":"Public Place"
        }
    ],
    "sg:phone":"+1 616 786 1800",
    "sg:postcode":"49424",
    "sg:province":"MI",
    "wof:name":"Waukazoo Elementary School",
    "wof:placetype":"venue"
},
  "geometry": {"coordinates":[-86.162268,42.804414],"type":"Point"}
}