{
  "type": "Feature",
  "properties": {
    "iso:country":"US",
    "sg:address":"28490 Utica Rd",
    "sg:city":"Roseville",
    "sg:classifiers":[
        {
            "category":"Autos & Motor Vehicles",
            "subcategory":"Automobile Sales",
            "type":"Retail Goods"
        }
    ],
    "sg:phone":"+1 586 777 0909",
    "sg:postcode":"48066",
    "sg:province":"MI",
    "sg:tags":[
        "limo"
    ],
    "wof:name":"V I P Services",
    "wof:placetype":"venue"
},
  "geometry": {"coordinates":[-82.933998,42.506199],"type":"Point"}
}