{
  "type": "Feature",
  "properties": {
    "iso:country":"US",
    "sg:address":"21400 Perry Ave",
    "sg:city":"Big Rapids",
    "sg:classifiers":[
        {
            "category":"Professional",
            "subcategory":"Accounting & Tax Preparation",
            "type":"Services"
        }
    ],
    "sg:phone":"+1 231 796 1211",
    "sg:postcode":"49307",
    "sg:province":"MI",
    "sg:tags":[
        "return",
        "filing"
    ],
    "wof:name":"H & R Block Tax Svc",
    "wof:placetype":"venue"
},
  "geometry": {"coordinates":[-85.516212,43.687856],"type":"Point"}
}