{
  "type": "Feature",
  "properties": {
    "iso:country":"US",
    "sg:address":"8000 Ora Lake Rd",
    "sg:city":"Hale",
    "sg:classifiers":[
        {
            "category":"Real Estate",
            "subcategory":"Real Estate Agent",
            "type":"Services"
        }
    ],
    "sg:phone":"+1 989 728 2540",
    "sg:postcode":"48739",
    "sg:province":"MI",
    "wof:name":"Real Estate Masters",
    "wof:placetype":"venue"
},
  "geometry": {"coordinates":[-83.844843,44.384821],"type":"Point"}
}