{
  "type": "Feature",
  "properties": {
    "iso:country":"US",
    "sg:address":"3556 Avon St",
    "sg:city":"Hartland",
    "sg:classifiers":[
        {
            "category":"Retail",
            "subcategory":"Portrait Studio",
            "type":"Services"
        }
    ],
    "sg:phone":"+1 810 632 6500",
    "sg:postcode":"48353",
    "sg:province":"MI",
    "sg:tags":[
        "photo"
    ],
    "wof:name":"Herff Jones Inc",
    "wof:placetype":"venue"
},
  "geometry": {"coordinates":[-83.75419100000001,42.655523],"type":"Point"}
}