{
  "type": "Feature",
  "properties": {
    "iso:country":"US",
    "sg:address":"1323 Springdale Dr SE",
    "sg:city":"Grand Rapids",
    "sg:classifiers":[
        {
            "category":"Professional",
            "subcategory":"Business Services",
            "type":"Services"
        }
    ],
    "sg:phone":"+1 616 248 4676",
    "sg:postcode":"49508",
    "sg:province":"MI",
    "wof:name":"German Translation Service",
    "wof:placetype":"venue"
},
  "geometry": {"coordinates":[-85.63392,42.893399],"type":"Point"}
}