{
  "type": "Feature",
  "properties": {
    "iso:country":"US",
    "sg:address":"3860 State Street Rd",
    "sg:city":"Bay City",
    "sg:classifiers":[
        {
            "category":"Home & Garden",
            "subcategory":"Building Materials",
            "type":"Retail Goods"
        }
    ],
    "sg:phone":"+1 989 671 9402",
    "sg:postcode":"48706",
    "sg:province":"MI",
    "sg:tags":[
        "center"
    ],
    "sg:website":"www.homedepot.com",
    "wof:name":"Home Depot",
    "wof:placetype":"venue"
},
  "geometry": {"coordinates":[-83.894184,43.627207],"type":"Point"}
}