{
  "type": "Feature",
  "properties": {
    "iso:country":"US",
    "sg:address":"4215 S Beech Daly St",
    "sg:city":"Dearborn Heights",
    "sg:classifiers":[
        {
            "category":"Health Services",
            "subcategory":"Doctor",
            "type":"Services"
        }
    ],
    "sg:phone":"+1 313 278 7750",
    "sg:postcode":"48125",
    "sg:province":"MI",
    "sg:website":"www.beechdalymedicalcenter.com",
    "wof:name":"Beech Daly Medical Center",
    "wof:placetype":"venue"
},
  "geometry": {"coordinates":[-83.289703,42.278301],"type":"Point"}
}