{
  "type": "Feature",
  "properties": {
    "iso:country":"US",
    "sg:address":"1980 S College Rd",
    "sg:city":"Mason",
    "sg:classifiers":[
        {
            "category":"Professional",
            "subcategory":"Research",
            "type":"Services"
        }
    ],
    "sg:phone":"+1 517 333 4617",
    "sg:postcode":"48854",
    "sg:province":"MI",
    "sg:tags":[
        "foundation",
        "philanthropic"
    ],
    "sg:website":"www.bpfi.org",
    "wof:name":"Bedding Plant Foundation Inc",
    "wof:placetype":"venue"
},
  "geometry": {"coordinates":[-84.48310600000001,42.530758],"type":"Point"}
}