{
  "type": "Feature",
  "properties": {
    "iso:country":"US",
    "sg:address":"21 Ecorse Rd",
    "sg:city":"Ypsilanti",
    "sg:classifiers":[
        {
            "category":"Retail",
            "subcategory":"Auto Repair",
            "type":"Services"
        }
    ],
    "sg:phone":"+1 734 483 1066",
    "sg:postcode":"48198",
    "sg:province":"MI",
    "sg:tags":[
        "body",
        "automobile",
        "painting",
        "repairing"
    ],
    "wof:name":"Sheets Collision Inc",
    "wof:placetype":"venue"
},
  "geometry": {"coordinates":[-83.598404,42.240914],"type":"Point"}
}