{
  "type": "Feature",
  "properties": {
    "iso:country":"US",
    "sg:address":"37020 Garfield Rd",
    "sg:city":"Clinton Township",
    "sg:classifiers":[
        {
            "category":"Banks & Credit Unions",
            "subcategory":"Bank",
            "type":"Services"
        }
    ],
    "sg:phone":"+1 586 286 7480",
    "sg:postcode":"48036",
    "sg:province":"MI",
    "sg:tags":[
        "national",
        "commercial"
    ],
    "wof:name":"Standard Federal Bank 219",
    "wof:placetype":"venue"
},
  "geometry": {"coordinates":[-82.950942,42.568206],"type":"Point"}
}