{
  "type": "Feature",
  "properties": {
    "iso:country":"US",
    "sg:address":"1819 E Big Beaver Rd Ste 211",
    "sg:city":"Troy",
    "sg:classifiers":[
        {
            "category":"Sports & Exercise",
            "subcategory":"Gym",
            "type":"Entertainment"
        }
    ],
    "sg:phone":"+1 248 619 0900",
    "sg:postcode":"48083",
    "sg:province":"MI",
    "sg:tags":[
        "trainer"
    ],
    "sg:website":"www.coresportsfitness.com",
    "wof:name":"Core",
    "wof:placetype":"venue"
},
  "geometry": {"coordinates":[-83.11089800000001,42.563792],"type":"Point"}
}