{
  "type": "Feature",
  "properties": {
    "iso:country":"US",
    "sg:address":"3824 E 13 Mile Rd",
    "sg:city":"Warren",
    "sg:classifiers":[
        {
            "category":"Health Services",
            "subcategory":"Optometrist",
            "type":"Services"
        }
    ],
    "sg:phone":"+1 586 751 2600",
    "sg:postcode":"48092",
    "sg:province":"MI",
    "sg:website":"www.fortney-eyecare.com",
    "wof:name":"Fortney Eyecare Associates",
    "wof:placetype":"venue"
},
  "geometry": {"coordinates":[-83.069801,42.520199],"type":"Point"}
}