{
  "type": "Feature",
  "properties": {
    "iso:country":"US",
    "sg:address":"17534 E 9 Mile Rd",
    "sg:city":"Eastpointe",
    "sg:classifiers":[
        {
            "category":"Personal",
            "subcategory":"Shoe Repair & Shine",
            "type":"Services"
        }
    ],
    "sg:phone":"+1 586 778 8260",
    "sg:postcode":"48021",
    "sg:province":"MI",
    "sg:tags":[
        "repairing",
        "parlor",
        "boot"
    ],
    "wof:name":"Hank's Shoe Repair",
    "wof:placetype":"venue"
},
  "geometry": {"coordinates":[-82.94025600000001,42.464968],"type":"Point"}
}