{
  "type": "Feature",
  "properties": {
    "iso:country":"US",
    "sg:address":"216 Rust Ave",
    "sg:city":"Big Rapids",
    "sg:classifiers":[
        {
            "category":"Professional",
            "subcategory":"Research",
            "type":"Services"
        }
    ],
    "sg:phone":"+1 231 796 5155",
    "sg:postcode":"49307",
    "sg:province":"MI",
    "sg:tags":[
        "organization",
        "noncommercial"
    ],
    "wof:name":"Institute For The Study of Eco",
    "wof:placetype":"venue"
},
  "geometry": {"coordinates":[-85.485114,43.697048],"type":"Point"}
}