{
  "type": "Feature",
  "properties": {
    "iso:country":"US",
    "sg:address":"50 Gratiot Blvd",
    "sg:city":"Marysville",
    "sg:classifiers":[
        {
            "category":"Manufacturing",
            "subcategory":"Chemicals & Compounds",
            "type":"Manufacturing & Wholesale Goods"
        }
    ],
    "sg:phone":"+1 810 364 6521",
    "sg:postcode":"48040",
    "sg:province":"MI",
    "sg:tags":[
        "industrial",
        "mfg",
        "supply",
        "gas",
        "equipment",
        "welding"
    ],
    "wof:name":"South Park Welding Supplies",
    "wof:placetype":"venue"
},
  "geometry": {"coordinates":[-82.46064,42.928394],"type":"Point"}
}