{
  "type": "Feature",
  "properties": {
    "iso:country":"US",
    "sg:address":"4029 N Mission Rd",
    "sg:city":"Rosebush",
    "sg:classifiers":[
        {
            "category":"Government",
            "subcategory":"Office",
            "type":"Public Place"
        }
    ],
    "sg:phone":"+1 989 433 2980",
    "sg:postcode":"48878",
    "sg:province":"MI",
    "sg:tags":[
        "village"
    ],
    "wof:name":"Rosebush Municipal Building",
    "wof:placetype":"venue"
},
  "geometry": {"coordinates":[-84.76800799999999,43.699975],"type":"Point"}
}