{
  "type": "Feature",
  "properties": {
    "iso:country":"US",
    "sg:address":"1200 W Willow St",
    "sg:city":"Lansing",
    "sg:classifiers":[
        {
            "category":"Food & Beverages",
            "subcategory":"Groceries & Convenience Stores",
            "type":"Retail Goods"
        }
    ],
    "sg:phone":"+1 517 319 4107",
    "sg:postcode":"48915",
    "sg:province":"MI",
    "sg:tags":[
        "grocer"
    ],
    "wof:name":"Quality Dairy Co",
    "wof:placetype":"venue"
},
  "geometry": {"coordinates":[-84.57011799999999,42.748298],"type":"Point"}
}