{
  "type": "Feature",
  "properties": {
    "iso:country":"US",
    "sg:address":"136 Imperial St",
    "sg:city":"Kalamazoo",
    "sg:classifiers":[
        {
            "category":"Professional",
            "subcategory":"Secretarial Services",
            "type":"Services"
        }
    ],
    "sg:phone":"+1 269 226 9464",
    "sg:postcode":"49001",
    "sg:province":"MI",
    "sg:tags":[
        "reporting",
        "computer",
        "related"
    ],
    "wof:name":"Images & Creations",
    "wof:placetype":"venue"
},
  "geometry": {"coordinates":[-85.58475,42.26095],"type":"Point"}
}