{
  "type": "Feature",
  "properties": {
    "iso:country":"US",
    "sg:address":"1603 Woodside Ave",
    "sg:city":"Bay City",
    "sg:classifiers":[
        {
            "category":"Wholesale",
            "subcategory":"Machinery & Supplies",
            "type":"Manufacturing & Wholesale Goods"
        }
    ],
    "sg:phone":"+1 989 893 6519",
    "sg:postcode":"48708",
    "sg:province":"MI",
    "sg:tags":[
        "engine",
        "repair",
        "parts",
        "gas",
        "automotive"
    ],
    "wof:name":"Star Sales & Service Inc",
    "wof:placetype":"venue"
},
  "geometry": {"coordinates":[-83.871543,43.604067],"type":"Point"}
}