{
  "type": "Feature",
  "properties": {
    "iso:country":"US",
    "sg:address":"27575 Harper Ave",
    "sg:city":"St Clair Shores",
    "sg:classifiers":[
        {
            "category":"Organizations",
            "subcategory":"Non-profit Organization",
            "type":"Services"
        }
    ],
    "sg:phone":"+1 586 779 7676",
    "sg:postcode":"48081",
    "sg:province":"MI",
    "sg:tags":[
        "medical",
        "management"
    ],
    "sg:website":"www.ngsamerican.com",
    "wof:name":"NGS American Inc",
    "wof:placetype":"venue"
},
  "geometry": {"coordinates":[-82.897721,42.495694],"type":"Point"}
}