{
  "type": "Feature",
  "properties": {
    "iso:country":"US",
    "sg:address":"4410 Wilfors Dr",
    "sg:city":"Williamston",
    "sg:classifiers":[
        {
            "category":"Retail",
            "subcategory":"Repair Shop",
            "type":"Services"
        }
    ],
    "sg:phone":"+1 517 706 0646",
    "sg:postcode":"48895",
    "sg:province":"MI",
    "wof:name":"Your Handyman Can",
    "wof:placetype":"venue"
},
  "geometry": {"coordinates":[-84.362821,42.712645],"type":"Point"}
}