{
  "type": "Feature",
  "properties": {
    "iso:country":"US",
    "sg:address":"4529 Grove St",
    "sg:city":"Holt",
    "sg:classifiers":[
        {
            "category":"Wholesale",
            "subcategory":"Vending Machines",
            "type":"Manufacturing & Wholesale Goods"
        }
    ],
    "sg:phone":"+1 517 694 0372",
    "sg:postcode":"48842",
    "sg:province":"MI",
    "wof:name":"Telecard Vending",
    "wof:placetype":"venue"
},
  "geometry": {"coordinates":[-84.52402600000001,42.638158],"type":"Point"}
}