{
  "type": "Feature",
  "properties": {
    "iso:country":"US",
    "sg:address":"15342 24th Ave",
    "sg:city":"Marne",
    "sg:classifiers":[
        {
            "category":"Utilities",
            "subcategory":"Refuse",
            "type":"Services"
        }
    ],
    "sg:phone":"+1 616 677 3488",
    "sg:postcode":"49435",
    "sg:province":"MI",
    "sg:tags":[
        "disposal",
        "waste"
    ],
    "wof:name":"Waste Trends LLC",
    "wof:placetype":"venue"
},
  "geometry": {"coordinates":[-85.847508,43.058886],"type":"Point"}
}