{
  "type": "Feature",
  "properties": {
    "iso:country":"US",
    "sg:address":"7550 S Saginaw St",
    "sg:city":"Grand Blanc",
    "sg:classifiers":[
        {
            "category":"Professional",
            "subcategory":"Lawyer & Legal Services",
            "type":"Services"
        }
    ],
    "sg:phone":"+1 810 603 3491",
    "sg:postcode":"48439",
    "sg:province":"MI",
    "sg:tags":[
        "attorney"
    ],
    "wof:name":"Jeffrey D Mitchell Law Office",
    "wof:placetype":"venue"
},
  "geometry": {"coordinates":[-83.616355,42.917366],"type":"Point"}
}