{
  "type": "Feature",
  "properties": {
    "iso:country":"US",
    "sg:address":"1314 Crescent Lake Rd",
    "sg:city":"Waterford",
    "sg:classifiers":[
        {
            "category":"Manufacturing",
            "subcategory":"Metals",
            "type":"Manufacturing & Wholesale Goods"
        }
    ],
    "sg:phone":"+1 248 674 3131",
    "sg:postcode":"48327",
    "sg:province":"MI",
    "sg:tags":[
        "tube",
        "fabricating"
    ],
    "sg:website":"www.tubefabricators.com",
    "wof:name":"Tru-Val Tubing Co",
    "wof:placetype":"venue"
},
  "geometry": {"coordinates":[-83.3861,42.659201],"type":"Point"}
}