{
  "type": "Feature",
  "properties": {
    "iso:country":"US",
    "sg:address":"4840 Delemere Ave",
    "sg:city":"Royal Oak",
    "sg:classifiers":[
        {
            "category":"Shopping",
            "subcategory":"Clothing, Apparel, & Fashions",
            "type":"Retail Goods"
        }
    ],
    "sg:phone":"+1 248 435 2391",
    "sg:postcode":"48073",
    "sg:province":"MI",
    "sg:tags":[
        "baby",
        "accessory"
    ],
    "wof:name":"D & D Millwork",
    "wof:placetype":"venue"
},
  "geometry": {"coordinates":[-83.176976,42.535074],"type":"Point"}
}