{
  "type": "Feature",
  "properties": {
    "iso:country":"US",
    "sg:address":"3000 W Beecher Rd",
    "sg:city":"Adrian",
    "sg:classifiers":[
        {
            "category":"Organizations",
            "subcategory":"Religious Organization",
            "type":"Services"
        }
    ],
    "sg:phone":"+1 517 265 3864",
    "sg:postcode":"49221",
    "sg:province":"MI",
    "sg:tags":[
        "church"
    ],
    "wof:name":"Jesus Is Lord Ministries",
    "wof:placetype":"venue"
},
  "geometry": {"coordinates":[-84.08253999999999,41.88865],"type":"Point"}
}