{
  "type": "Feature",
  "properties": {
    "iso:country":"US",
    "sg:address":"12989 Ferry Rd",
    "sg:city":"Charlevoix",
    "sg:classifiers":[
        {
            "category":"Building & Trades",
            "subcategory":"Cleaning & Sanitation",
            "type":"Services"
        }
    ],
    "sg:phone":"+1 231 547 0116",
    "sg:postcode":"49720",
    "sg:province":"MI",
    "sg:tags":[
        "maintenance"
    ],
    "wof:name":"A & J Maintenance Property",
    "wof:placetype":"venue"
},
  "geometry": {"coordinates":[-85.246848,45.257108],"type":"Point"}
}