{
  "type": "Feature",
  "properties": {
    "iso:country":"US",
    "sg:address":"4251 W Saginaw Hwy",
    "sg:city":"Lansing",
    "sg:classifiers":[
        {
            "category":"Shopping",
            "subcategory":"Florist",
            "type":"Retail Goods"
        }
    ],
    "sg:phone":"+1 517 455 0611",
    "sg:postcode":"48917",
    "sg:province":"MI",
    "sg:website":"http://www.addysfloral.com",
    "wof:name":"Addy's Floral And Gifts",
    "wof:placetype":"venue"
},
  "geometry": {"coordinates":[-84.60794799999999,42.741046],"type":"Point"}
}