{
  "type": "Feature",
  "properties": {
    "iso:country":"US",
    "sg:address":"5680 Marsh Rd",
    "sg:city":"Haslett",
    "sg:classifiers":[
        {
            "category":"Health Services",
            "subcategory":"Doctor",
            "type":"Services"
        }
    ],
    "sg:phone":"+1 517 339 8251",
    "sg:postcode":"48840",
    "sg:province":"MI",
    "sg:tags":[
        "physician",
        "surgeon"
    ],
    "wof:name":"Linda P Coniglio DO",
    "wof:placetype":"venue"
},
  "geometry": {"coordinates":[-84.40843,42.748163],"type":"Point"}
}