{
  "type": "Feature",
  "properties": {
    "iso:country":"US",
    "sg:address":"700 Shelden Ave",
    "sg:city":"Houghton",
    "sg:classifiers":[
        {
            "category":"Restaurant",
            "type":"Food & Drink"
        }
    ],
    "sg:menulink":"http://www.allmenus.com/mi/houghton/142363-subway/menu/",
    "sg:phone":"+1 906 487 9524",
    "sg:postcode":"49931",
    "sg:province":"MI",
    "sg:tags":[
        "american",
        "sandwich"
    ],
    "wof:name":"Subway",
    "wof:placetype":"venue"
},
  "geometry": {"coordinates":[-88.565663,47.121919],"type":"Point"}
}