{
  "type": "Feature",
  "properties": {
    "iso:country":"US",
    "sg:address":"8750 Clinton Rd",
    "sg:city":"Jackson",
    "sg:classifiers":[
        {
            "category":"Building & Trades",
            "subcategory":"Construction",
            "type":"Services"
        }
    ],
    "sg:phone":"+1 517 784 2562",
    "sg:postcode":"49201",
    "sg:province":"MI",
    "sg:tags":[
        "contractor"
    ],
    "wof:name":"Chris Piotrowski Builders",
    "wof:placetype":"venue"
},
  "geometry": {"coordinates":[-84.508303,42.348037],"type":"Point"}
}