{
  "type": "Feature",
  "properties": {
    "iso:country":"US",
    "sg:address":"1521 N Elms Rd",
    "sg:city":"Flint",
    "sg:classifiers":[
        {
            "category":"Organizations",
            "subcategory":"Religious Organization",
            "type":"Services"
        }
    ],
    "sg:phone":"+1 810 230 9544",
    "sg:postcode":"48532",
    "sg:province":"MI",
    "sg:tags":[
        "church"
    ],
    "sg:website":"www.ppcflint.org",
    "wof:name":"Peace Presbyterian Church",
    "wof:placetype":"venue"
},
  "geometry": {"coordinates":[-83.812718,43.028408],"type":"Point"}
}