{
  "type": "Feature",
  "properties": {
    "iso:country":"US",
    "sg:address":"23047 M 78",
    "sg:city":"Battle Creek",
    "sg:classifiers":[
        {
            "category":"Shopping",
            "subcategory":"Bicycles & Sporting Goods",
            "type":"Retail Goods"
        }
    ],
    "sg:phone":"+1 269 441 2453",
    "sg:postcode":"49017",
    "sg:province":"MI",
    "wof:name":"E Bike World Battle Creek LLC",
    "wof:placetype":"venue"
},
  "geometry": {"coordinates":[-85.12345000000001,42.406179],"type":"Point"}
}