{
  "type": "Feature",
  "properties": {
    "iso:country":"US",
    "sg:address":"4185 Windiate Park Dr",
    "sg:city":"Waterford",
    "sg:classifiers":[
        {
            "category":"Building & Trades",
            "subcategory":"Electrical",
            "type":"Services"
        }
    ],
    "sg:phone":"+1 248 623 4702",
    "sg:postcode":"48329",
    "sg:province":"MI",
    "sg:tags":[
        "electrical",
        "contractor"
    ],
    "wof:name":"Hoffman Electric LLC",
    "wof:placetype":"venue"
},
  "geometry": {"coordinates":[-83.426897,42.701771],"type":"Point"}
}