{
  "type": "Feature",
  "properties": {
    "iso:country":"US",
    "sg:address":"20027 Alcoy St",
    "sg:city":"Detroit",
    "sg:classifiers":[
        {
            "category":"Arts & Performance",
            "subcategory":"Theater",
            "type":"Entertainment"
        }
    ],
    "sg:phone":"+1 313 372 0196",
    "sg:postcode":"48205",
    "sg:province":"MI",
    "sg:tags":[
        "group"
    ],
    "wof:name":"Taylor Boy Entertainment",
    "wof:placetype":"venue"
},
  "geometry": {"coordinates":[-82.98925300000001,42.445484],"type":"Point"}
}