{
  "type": "Feature",
  "properties": {
    "iso:country":"US",
    "sg:address":"2310 Green Rd",
    "sg:city":"Ann Arbor",
    "sg:classifiers":[
        {
            "category":"Restaurant",
            "type":"Food & Drink"
        }
    ],
    "sg:menulink":"http://www.allmenus.com/mi/ann-arbor/88661-applebees/menu/",
    "sg:phone":"+1 734 741 1870",
    "sg:postcode":"48105",
    "sg:province":"MI",
    "sg:tags":[
        "burger",
        "american",
        "sandwich",
        "soup"
    ],
    "wof:name":"Applebee's",
    "wof:placetype":"venue"
},
  "geometry": {"coordinates":[-83.692736,42.307781],"type":"Point"}
}