{
  "type": "Feature",
  "properties": {
    "iso:country":"US",
    "sg:address":"280 S Main St",
    "sg:city":"Plymouth",
    "sg:classifiers":[
        {
            "category":"Retail",
            "subcategory":"Funeral Services",
            "type":"Services"
        }
    ],
    "sg:phone":"+1 734 453 3333",
    "sg:postcode":"48170",
    "sg:province":"MI",
    "sg:tags":[
        "cemetery"
    ],
    "sg:website":"www.schrader-howell.com",
    "wof:name":"Schrader-Howell Funeral Home",
    "wof:placetype":"venue"
},
  "geometry": {"coordinates":[-83.469002,42.371101],"type":"Point"}
}