{
  "type": "Feature",
  "properties": {
    "iso:country":"US",
    "sg:address":"2121 Shetland Dr NE",
    "sg:city":"Grand Rapids",
    "sg:classifiers":[
        {
            "category":"Professional",
            "subcategory":"Business Services",
            "type":"Services"
        }
    ],
    "sg:phone":"+1 616 363 4651",
    "sg:postcode":"49505",
    "sg:province":"MI",
    "wof:name":"Ruth Rooks Interiors",
    "wof:placetype":"venue"
},
  "geometry": {"coordinates":[-85.621962,43.002986],"type":"Point"}
}