{
  "type": "Feature",
  "properties": {
    "iso:country":"US",
    "sg:address":"7980 Paradise Trl",
    "sg:city":"Carp Lake",
    "sg:classifiers":[
        {
            "category":"Professional",
            "type":"Services"
        }
    ],
    "sg:phone":"+1 231 537 4767",
    "sg:postcode":"49718",
    "sg:province":"MI",
    "wof:name":"E&M Hall Inc",
    "wof:placetype":"venue"
},
  "geometry": {"coordinates":[-84.75102699999999,45.697385],"type":"Point"}
}