{
  "type": "Feature",
  "properties": {
    "iso:country":"US",
    "sg:address":"135 E Lakewood Rd",
    "sg:city":"Twin Lake",
    "sg:classifiers":[
        {
            "category":"Building & Trades",
            "subcategory":"Landscaping Services",
            "type":"Services"
        }
    ],
    "sg:phone":"+1 231 893 1384",
    "sg:postcode":"49457",
    "sg:province":"MI",
    "wof:name":"Terrys Lawn Service",
    "wof:placetype":"venue"
},
  "geometry": {"coordinates":[-86.239204,43.3683],"type":"Point"}
}