{
  "type": "Feature",
  "properties": {
    "iso:country":"US",
    "sg:address":"3921 Rochester Rd",
    "sg:city":"Troy",
    "sg:classifiers":[
        {
            "category":"Real Estate",
            "subcategory":"Real Estate Agent",
            "type":"Services"
        }
    ],
    "sg:phone":"+1 248 528 1019",
    "sg:postcode":"48083",
    "sg:province":"MI",
    "sg:tags":[
        "finding",
        "apartment",
        "rental"
    ],
    "wof:name":"Relocation Central",
    "wof:placetype":"venue"
},
  "geometry": {"coordinates":[-83.12836799999999,42.575066],"type":"Point"}
}