{
  "type": "Feature",
  "properties": {
    "iso:country":"US",
    "sg:address":"1339 N Johnson St",
    "sg:city":"Bay City",
    "sg:classifiers":[
        {
            "category":"Building & Trades",
            "subcategory":"Plumbing",
            "type":"Services"
        }
    ],
    "sg:phone":"+1 989 893 2669",
    "sg:postcode":"48708",
    "sg:province":"MI",
    "sg:tags":[
        "conditioning",
        "air",
        "system",
        "contractor"
    ],
    "wof:name":"Gledhill Heating & Cooling Co",
    "wof:placetype":"venue"
},
  "geometry": {"coordinates":[-83.871578,43.603319],"type":"Point"}
}