{
  "type": "Feature",
  "properties": {
    "iso:country":"US",
    "sg:address":"110 W Norrie St",
    "sg:city":"Ironwood",
    "sg:classifiers":[
        {
            "category":"Personal",
            "type":"Services"
        }
    ],
    "sg:phone":"+1 906 932 6044",
    "sg:postcode":"49938",
    "sg:province":"MI",
    "wof:name":"Quilters Finsihing Touch",
    "wof:placetype":"venue"
},
  "geometry": {"coordinates":[-90.173019,46.455953],"type":"Point"}
}