{
  "type": "Feature",
  "properties": {
    "iso:country":"US",
    "sg:address":"6764 River Rd",
    "sg:city":"Cottrellville",
    "sg:classifiers":[
        {
            "category":"Food & Beverages",
            "subcategory":"Groceries & Convenience Stores",
            "type":"Retail Goods"
        }
    ],
    "sg:phone":"+1 810 765 4061",
    "sg:postcode":"48039",
    "sg:province":"MI",
    "sg:tags":[
        "grocer"
    ],
    "sg:website":"www.vgsfood.com",
    "wof:name":"V G's Food Ctr & Pharmacy",
    "wof:placetype":"venue"
},
  "geometry": {"coordinates":[-82.506349,42.695121],"type":"Point"}
}