{
  "type": "Feature",
  "properties": {
    "iso:country":"US",
    "sg:address":"64580 Van Dyke Rd",
    "sg:city":"Washington",
    "sg:classifiers":[
        {
            "category":"Health Services",
            "subcategory":"Health Practitioner",
            "type":"Services"
        }
    ],
    "sg:phone":"+1 586 752 9629",
    "sg:postcode":"48095",
    "sg:province":"MI",
    "wof:name":"Curtis P Craig MD",
    "wof:placetype":"venue"
},
  "geometry": {"coordinates":[-83.018263,42.768978],"type":"Point"}
}