{
  "type": "Feature",
  "properties": {
    "iso:country":"US",
    "sg:address":"1109 Ives Rd",
    "sg:city":"Tecumseh",
    "sg:classifiers":[
        {
            "category":"Building & Trades",
            "subcategory":"Construction",
            "type":"Services"
        }
    ],
    "sg:phone":"+1 517 423 5990",
    "sg:postcode":"49286",
    "sg:province":"MI",
    "wof:name":"Kruse Construction",
    "wof:placetype":"venue"
},
  "geometry": {"coordinates":[-83.99420600000001,41.977582],"type":"Point"}
}