{
  "type": "Feature",
  "properties": {
    "iso:country":"US",
    "sg:address":"11703 Pentecost Hwy",
    "sg:city":"Onsted",
    "sg:classifiers":[
        {
            "category":"Autos & Motor Vehicles",
            "subcategory":"Auto Supplies",
            "type":"Retail Goods"
        }
    ],
    "sg:phone":"+1 517 467 7974",
    "sg:postcode":"49265",
    "sg:province":"MI",
    "sg:tags":[
        "automobile",
        "accessory",
        "equipment",
        "parts",
        "car",
        "racing"
    ],
    "wof:name":"Roumell Enterprises Inc",
    "wof:placetype":"venue"
},
  "geometry": {"coordinates":[-84.12687699999999,42.059591],"type":"Point"}
}