{
  "type": "Feature",
  "properties": {
    "iso:country":"US",
    "sg:address":"3400 Pickerel Lake Rd",
    "sg:city":"Petoskey",
    "sg:classifiers":[
        {
            "category":"Building & Trades",
            "subcategory":"Landscaping Services",
            "type":"Services"
        }
    ],
    "sg:phone":"+1 231 348 0031",
    "sg:postcode":"49770",
    "sg:province":"MI",
    "sg:tags":[
        "lawn",
        "maintenance",
        "grounds"
    ],
    "wof:name":"Wilson's Up North",
    "wof:placetype":"venue"
},
  "geometry": {"coordinates":[-84.90198599999999,45.391631],"type":"Point"}
}