{
  "type": "Feature",
  "properties": {
    "iso:country":"US",
    "sg:address":"13301 Lake Shore Dr",
    "sg:city":"Fenton",
    "sg:classifiers":[
        {
            "category":"Restaurant",
            "type":"Food & Drink"
        }
    ],
    "sg:phone":"+1 810 714 1136",
    "sg:postcode":"48430",
    "sg:province":"MI",
    "sg:tags":[
        "eating"
    ],
    "wof:name":"Anrad Restaurants",
    "wof:placetype":"venue"
},
  "geometry": {"coordinates":[-83.718322,42.833405],"type":"Point"}
}