{
  "type": "Feature",
  "properties": {
    "iso:country":"US",
    "sg:address":"28780 Graham Dr",
    "sg:city":"New Baltimore",
    "sg:classifiers":[
        {
            "category":"Building & Trades",
            "subcategory":"Construction",
            "type":"Services"
        }
    ],
    "sg:phone":"+1 586 949 0537",
    "sg:postcode":"48047",
    "sg:province":"MI",
    "sg:tags":[
        "residential"
    ],
    "wof:name":"M J Construction",
    "wof:placetype":"venue"
},
  "geometry": {"coordinates":[-82.820335,42.651783],"type":"Point"}
}