{
  "type": "Feature",
  "properties": {
    "iso:country":"US",
    "sg:address":"1829 Valley Ln",
    "sg:city":"Flint",
    "sg:classifiers":[
        {
            "category":"Banks & Credit Unions",
            "subcategory":"Bank",
            "type":"Services"
        }
    ],
    "sg:phone":"+1 810 743 5254",
    "sg:postcode":"48503",
    "sg:province":"MI",
    "sg:tags":[
        "mortgage"
    ],
    "wof:name":"Branch Metropolitan Mortgage",
    "wof:placetype":"venue"
},
  "geometry": {"coordinates":[-83.640102,43.008521],"type":"Point"}
}