{
  "type": "Feature",
  "properties": {
    "iso:country":"US",
    "sg:address":"551 Linn St",
    "sg:city":"Allegan",
    "sg:classifiers":[
        {
            "category":"Health Services",
            "subcategory":"Podiatrist",
            "type":"Services"
        }
    ],
    "sg:phone":"+1 269 673 8757",
    "sg:postcode":"49010",
    "sg:province":"MI",
    "wof:name":"Redmond Thomas D DPM",
    "wof:placetype":"venue"
},
  "geometry": {"coordinates":[-85.857327,42.518511],"type":"Point"}
}