{
  "type": "Feature",
  "properties": {
    "iso:country":"US",
    "sg:address":"1051 W White Rd",
    "sg:city":"Free Soil",
    "sg:classifiers":[
        {
            "category":"Retail",
            "subcategory":"Repair Shop",
            "type":"Services"
        }
    ],
    "sg:phone":"+1 231 464 5038",
    "sg:postcode":"49411",
    "sg:province":"MI",
    "sg:tags":[
        "scooter",
        "motorcycle",
        "motor"
    ],
    "wof:name":"White Road Motorcycle Repair",
    "wof:placetype":"venue"
},
  "geometry": {"coordinates":[-86.311464,44.11251],"type":"Point"}
}