{
  "type": "Feature",
  "properties": {
    "iso:country":"US",
    "sg:address":"750 Ball Ave NE",
    "sg:city":"Grand Rapids",
    "sg:classifiers":[
        {
            "category":"Building & Trades",
            "subcategory":"Electrical",
            "type":"Services"
        }
    ],
    "sg:phone":"+1 616 458 7210",
    "sg:postcode":"49503",
    "sg:province":"MI",
    "sg:tags":[
        "electric",
        "contractor"
    ],
    "wof:name":"Bazen Electric",
    "wof:placetype":"venue"
},
  "geometry": {"coordinates":[-85.62995100000001,42.977046],"type":"Point"}
}