{
  "type": "Feature",
  "properties": {
    "iso:country":"US",
    "sg:address":"8260 Cleveland Ave",
    "sg:city":"Baroda",
    "sg:classifiers":[
        {
            "category":"Farming",
            "subcategory":"Farm",
            "type":"Manufacturing & Wholesale Goods"
        }
    ],
    "sg:phone":"+1 269 422 1225",
    "sg:postcode":"49101",
    "sg:province":"MI",
    "sg:tags":[
        "crop",
        "general"
    ],
    "wof:name":"Ashbys Tired Hands Farm",
    "wof:placetype":"venue"
},
  "geometry": {"coordinates":[-86.49469000000001,41.969041],"type":"Point"}
}