{
  "type": "Feature",
  "properties": {
    "iso:country":"US",
    "sg:address":"2128 Laura Dr",
    "sg:city":"Traverse City",
    "sg:classifiers":[
        {
            "category":"Health Services",
            "subcategory":"Medical Lab",
            "type":"Services"
        }
    ],
    "sg:phone":"+1 231 935 1845",
    "sg:postcode":"49686",
    "sg:province":"MI",
    "sg:tags":[
        "laboratory"
    ],
    "wof:name":"Holstein Julian Curtis",
    "wof:placetype":"venue"
},
  "geometry": {"coordinates":[-85.618246,44.70963],"type":"Point"}
}