{
  "type": "Feature",
  "properties": {
    "iso:country":"US",
    "sg:address":"211 S Suffolk St",
    "sg:city":"Ironwood",
    "sg:classifiers":[
        {
            "category":"Professional",
            "subcategory":"Employment Agencies",
            "type":"Services"
        }
    ],
    "sg:phone":"+1 906 265 9705",
    "sg:postcode":"49938",
    "sg:province":"MI",
    "sg:tags":[
        "help",
        "contractor"
    ],
    "wof:name":"Nustar Temporary Svc",
    "wof:placetype":"venue"
},
  "geometry": {"coordinates":[-90.16839400000001,46.454442],"type":"Point"}
}