{
  "type": "Feature",
  "properties": {
    "iso:country":"US",
    "sg:address":"115 W Main St",
    "sg:city":"Ionia",
    "sg:classifiers":[
        {
            "category":"Insurance",
            "subcategory":"Insurance Agent",
            "type":"Services"
        }
    ],
    "sg:phone":"+1 616 527 1200",
    "sg:postcode":"48846",
    "sg:province":"MI",
    "sg:tags":[
        "i",
        "life",
        "real estate"
    ],
    "wof:name":"Speerstra-Carr Agency",
    "wof:placetype":"venue"
},
  "geometry": {"coordinates":[-85.063373,42.982652],"type":"Point"}
}