{
  "type": "Feature",
  "properties": {
    "iso:country":"US",
    "sg:address":"38363 Palmer Rd",
    "sg:city":"Westland",
    "sg:classifiers":[
        {
            "category":"Professional",
            "subcategory":"Computer Services",
            "type":"Services"
        }
    ],
    "sg:phone":"+1 734 721 6076",
    "sg:postcode":"48186",
    "sg:province":"MI",
    "sg:tags":[
        "related"
    ],
    "wof:name":"Jnt Enterprise",
    "wof:placetype":"venue"
},
  "geometry": {"coordinates":[-83.41627,42.294783],"type":"Point"}
}