{
  "type": "Feature",
  "properties": {
    "iso:country":"US",
    "sg:address":"454 S Main St",
    "sg:city":"Lapeer",
    "sg:classifiers":[
        {
            "category":"Professional",
            "subcategory":"Business Services",
            "type":"Services"
        }
    ],
    "sg:phone":"+1 810 245 2600",
    "sg:postcode":"48446",
    "sg:province":"MI",
    "sg:website":"www.exitrealtygroup.net",
    "wof:name":"Exit Realty Group",
    "wof:placetype":"venue"
},
  "geometry": {"coordinates":[-83.31940400000001,43.045516],"type":"Point"}
}