{
  "type": "Feature",
  "properties": {
    "iso:country":"US",
    "sg:address":"360 E Sanilac Rd",
    "sg:city":"Sandusky",
    "sg:classifiers":[
        {
            "category":"Home & Garden",
            "subcategory":"Building Materials",
            "type":"Retail Goods"
        }
    ],
    "sg:phone":"+1 810 648 5881",
    "sg:postcode":"48471",
    "sg:province":"MI",
    "sg:tags":[
        "glass",
        "window",
        "plate"
    ],
    "wof:name":"Northeastern Auto Glass",
    "wof:placetype":"venue"
},
  "geometry": {"coordinates":[-82.82257799999999,43.42137],"type":"Point"}
}