{
  "type": "Feature",
  "properties": {
    "iso:country":"US",
    "sg:address":"7683 Cottonwood Dr",
    "sg:city":"Jenison",
    "sg:classifiers":[
        {
            "category":"Health Services",
            "subcategory":"Hospital",
            "type":"Services"
        }
    ],
    "sg:phone":"+1 616 667 1284",
    "sg:postcode":"49428",
    "sg:province":"MI",
    "wof:name":"Holland Home",
    "wof:placetype":"venue"
},
  "geometry": {"coordinates":[-85.79329799999999,42.908191],"type":"Point"}
}