{
  "type": "Feature",
  "properties": {
    "iso:country":"US",
    "sg:address":"1006 S Main St",
    "sg:city":"Cheboygan",
    "sg:classifiers":[
        {
            "category":"Personal",
            "subcategory":"Beauty Salon",
            "type":"Services"
        }
    ],
    "sg:phone":"+1 231 627 6665",
    "sg:postcode":"49721",
    "sg:province":"MI",
    "sg:tags":[
        "shop"
    ],
    "wof:name":"Shear Magic Hair Salon Inc",
    "wof:placetype":"venue"
},
  "geometry": {"coordinates":[-84.478469,45.62804],"type":"Point"}
}