{
  "type": "Feature",
  "properties": {
    "iso:country":"US",
    "sg:address":"36 E Maple St NE",
    "sg:city":"Cedar Springs",
    "sg:classifiers":[
        {
            "category":"Manufacturing",
            "subcategory":"Printing",
            "type":"Manufacturing & Wholesale Goods"
        }
    ],
    "sg:phone":"+1 616 696 3655",
    "sg:postcode":"49319",
    "sg:province":"MI",
    "sg:tags":[
        "newspaper"
    ],
    "sg:website":"www.cedarspringspost.com",
    "wof:name":"Cedar Springs Post Newspaper",
    "wof:placetype":"venue"
},
  "geometry": {"coordinates":[-85.551028,43.225412],"type":"Point"}
}