{
  "type": "Feature",
  "properties": {
    "iso:country":"US",
    "sg:address":"3645 Inkster Rd",
    "sg:city":"Inkster",
    "sg:classifiers":[
        {
            "category":"Retail",
            "subcategory":"Car Wash",
            "type":"Services"
        }
    ],
    "sg:phone":"+1 313 730 0999",
    "sg:postcode":"48141",
    "sg:province":"MI",
    "sg:tags":[
        "carwash"
    ],
    "wof:name":"Owens Auto Hand Wash",
    "wof:placetype":"venue"
},
  "geometry": {"coordinates":[-83.30940200000001,42.283199],"type":"Point"}
}