{
  "type": "Feature",
  "properties": {
    "iso:country":"US",
    "sg:address":"11668 N Begole Rd",
    "sg:city":"Saint Louis",
    "sg:classifiers":[
        {
            "category":"Social Services",
            "subcategory":"Child Care",
            "type":"Services"
        }
    ],
    "sg:phone":"+1 989 681 2892",
    "sg:postcode":"48880",
    "sg:province":"MI",
    "sg:tags":[
        "day"
    ],
    "wof:name":"Carol Ann Lantzer",
    "wof:placetype":"venue"
},
  "geometry": {"coordinates":[-84.64696000000001,43.464894],"type":"Point"}
}