{
  "type": "Feature",
  "properties": {
    "iso:country":"US",
    "sg:address":"1093 S Benton Center Rd",
    "sg:city":"Benton Harbor",
    "sg:classifiers":[
        {
            "category":"Food & Beverages",
            "subcategory":"Fruits & Vegetables",
            "type":"Retail Goods"
        }
    ],
    "sg:phone":"+1 269 926 6959",
    "sg:postcode":"49022",
    "sg:province":"MI",
    "sg:tags":[
        "produce"
    ],
    "wof:name":"Sommer Fresh Farms",
    "wof:placetype":"venue"
},
  "geometry": {"coordinates":[-86.378406,42.097981],"type":"Point"}
}