{
  "type": "Feature",
  "properties": {
    "iso:country":"US",
    "sg:address":"10090 Bennett Lake Rd",
    "sg:city":"Fenton",
    "sg:classifiers":[
        {
            "category":"Banks & Credit Unions",
            "subcategory":"Bank",
            "type":"Services"
        }
    ],
    "sg:phone":"+1 810 714 7700",
    "sg:postcode":"48430",
    "sg:province":"MI",
    "sg:tags":[
        "assistance",
        "foreclosure"
    ],
    "wof:name":"R T Enterprises",
    "wof:placetype":"venue"
},
  "geometry": {"coordinates":[-83.758467,42.781836],"type":"Point"}
}