{
  "type": "Feature",
  "properties": {
    "iso:country":"US",
    "sg:address":"29753 Hoover Rd",
    "sg:city":"Warren",
    "sg:classifiers":[
        {
            "category":"Health Services",
            "subcategory":"Doctor",
            "type":"Services"
        }
    ],
    "sg:phone":"+1 586 573 3880",
    "sg:postcode":"48093",
    "sg:province":"MI",
    "sg:tags":[
        "physician",
        "surgeon"
    ],
    "wof:name":"Optical Associates Inc",
    "wof:placetype":"venue"
},
  "geometry": {"coordinates":[-83.007311,42.513242],"type":"Point"}
}