{
  "type": "Feature",
  "properties": {
    "iso:country":"US",
    "sg:address":"1606 Leonard St NW",
    "sg:city":"Grand Rapids",
    "sg:classifiers":[
        {
            "category":"Professional",
            "subcategory":"Business Services",
            "type":"Services"
        }
    ],
    "sg:phone":"+1 616 453 7490",
    "sg:postcode":"49504",
    "sg:province":"MI",
    "wof:name":"Jahangir Parirokh",
    "wof:placetype":"venue"
},
  "geometry": {"coordinates":[-85.70851399999999,42.985862],"type":"Point"}
}