{
  "type": "Feature",
  "properties": {
    "iso:country":"US",
    "sg:address":"210 W Highland Rd",
    "sg:city":"Highland",
    "sg:classifiers":[
        {
            "category":"Real Estate",
            "subcategory":"Architect",
            "type":"Services"
        }
    ],
    "sg:phone":"+1 248 887 6477",
    "sg:postcode":"48357",
    "sg:province":"MI",
    "sg:tags":[
        "home",
        "planning",
        "design"
    ],
    "wof:name":"Mark B Koppelo & Assoc",
    "wof:placetype":"venue"
},
  "geometry": {"coordinates":[-83.63129000000001,42.640146],"type":"Point"}
}