{
  "type": "Feature",
  "properties": {
    "iso:country":"US",
    "sg:address":"537 2nd St",
    "sg:city":"Manistee",
    "sg:classifiers":[
        {
            "category":"Farming",
            "subcategory":"Farm",
            "type":"Manufacturing & Wholesale Goods"
        }
    ],
    "sg:phone":"+1 231 723 7522",
    "sg:postcode":"49660",
    "sg:province":"MI",
    "sg:tags":[
        "crop",
        "general"
    ],
    "wof:name":"Hargreaves Farms",
    "wof:placetype":"venue"
},
  "geometry": {"coordinates":[-86.33361499999999,44.245258],"type":"Point"}
}