{
  "type": "Feature",
  "properties": {
    "iso:country":"US",
    "sg:address":"6801 Belmont Ave NE",
    "sg:city":"Belmont",
    "sg:classifiers":[
        {
            "category":"Organizations",
            "subcategory":"Religious Organization",
            "type":"Services"
        }
    ],
    "sg:phone":"+1 616 361 9609",
    "sg:postcode":"49306",
    "sg:province":"MI",
    "sg:tags":[
        "monastery",
        "convent"
    ],
    "sg:website":"www.consolatasisters.org",
    "wof:name":"Consolata Missionary Sisters",
    "wof:placetype":"venue"
},
  "geometry": {"coordinates":[-85.607204,43.087182],"type":"Point"}
}