{
  "type": "Feature",
  "properties": {
    "iso:country":"US",
    "sg:address":"13728 Commonwealth St",
    "sg:city":"Southgate",
    "sg:classifiers":[
        {
            "category":"Freight",
            "type":"Transportation"
        }
    ],
    "sg:phone":"+1 734 284 3807",
    "sg:postcode":"48195",
    "sg:province":"MI",
    "sg:tags":[
        "operator",
        "local",
        "trucking"
    ],
    "wof:name":"Able Piano & Organ Moving",
    "wof:placetype":"venue"
},
  "geometry": {"coordinates":[-83.19233800000001,42.205781],"type":"Point"}
}