{
  "type": "Feature",
  "properties": {
    "iso:country":"US",
    "sg:address":"4158 Brammer Rd",
    "sg:city":"Traverse City",
    "sg:classifiers":[
        {
            "category":"Restaurant",
            "type":"Food & Drink"
        }
    ],
    "sg:phone":"+1 231 943 9683",
    "sg:postcode":"49684",
    "sg:province":"MI",
    "sg:tags":[
        "caterer"
    ],
    "wof:name":"Chef's Pride Catering",
    "wof:placetype":"venue"
},
  "geometry": {"coordinates":[-85.66093100000001,44.660626],"type":"Point"}
}