{
  "type": "Feature",
  "properties": {
    "iso:country":"US",
    "sg:address":"8280 Neff Rd NE",
    "sg:city":"Edmore",
    "sg:classifiers":[
        {
            "category":"Social Services",
            "subcategory":"Adult Care",
            "type":"Services"
        }
    ],
    "sg:phone":"+1 989 427 5245",
    "sg:postcode":"48829",
    "sg:province":"MI",
    "sg:tags":[
        "foster"
    ],
    "wof:name":"Kilchermann AFC",
    "wof:placetype":"venue"
},
  "geometry": {"coordinates":[-85.024272,43.410831],"type":"Point"}
}