{
  "type": "Feature",
  "properties": {
    "iso:country":"US",
    "sg:address":"7180 Duffield Rd",
    "sg:city":"Durand",
    "sg:classifiers":[
        {
            "category":"Organizations",
            "subcategory":"Religious Organization",
            "type":"Services"
        }
    ],
    "sg:phone":"+1 989 271 8460",
    "sg:postcode":"48429",
    "sg:province":"MI",
    "wof:name":"Duffield United Meth Chur",
    "wof:placetype":"venue"
},
  "geometry": {"coordinates":[-83.909982,42.922542],"type":"Point"}
}