{
  "type": "Feature",
  "properties": {
    "iso:country":"US",
    "sg:address":"3600 S Dort Hwy Ste 4",
    "sg:city":"Flint",
    "sg:classifiers":[
        {
            "category":"Personal",
            "subcategory":"Nail Salon",
            "type":"Services"
        }
    ],
    "sg:phone":"+1 810 742 4398",
    "sg:postcode":"48507",
    "sg:province":"MI",
    "wof:name":"Rumors Nail Salon",
    "wof:placetype":"venue"
},
  "geometry": {"coordinates":[-83.653503,42.990799],"type":"Point"}
}