{
  "type": "Feature",
  "properties": {
    "iso:country":"US",
    "sg:address":"47922 Royal Pointe Dr",
    "sg:city":"Canton",
    "sg:classifiers":[
        {
            "category":"Real Estate",
            "subcategory":"Real Estate Services",
            "type":"Services"
        }
    ],
    "sg:phone":"+1 734 664 5853",
    "sg:postcode":"48187",
    "sg:province":"MI",
    "sg:website":"www.InnovativeHomeInspection.com",
    "wof:name":"Innovative Home Inspection, LLC",
    "wof:placetype":"venue"
},
  "geometry": {"coordinates":[-83.51299899999999,42.333733],"type":"Point"}
}