{
  "type": "Feature",
  "properties": {
    "iso:country":"US",
    "sg:address":"436 N Park St",
    "sg:city":"Kalamazoo",
    "sg:classifiers":[
        {
            "category":"Manufacturing",
            "subcategory":"Glass & Minerals",
            "type":"Manufacturing & Wholesale Goods"
        }
    ],
    "sg:phone":"+1 269 349 1958",
    "sg:postcode":"49007",
    "sg:province":"MI",
    "wof:name":"Meints Glass Blowing",
    "wof:placetype":"venue"
},
  "geometry": {"coordinates":[-85.587413,42.29537],"type":"Point"}
}