{
  "type": "Feature",
  "properties": {
    "iso:country":"US",
    "sg:address":"145 Spruce Ave",
    "sg:city":"Holland",
    "sg:classifiers":[
        {
            "category":"Freight",
            "type":"Transportation"
        }
    ],
    "sg:phone":"+1 616 392 5883",
    "sg:postcode":"49423",
    "sg:province":"MI",
    "sg:tags":[
        "operator",
        "refuse",
        "local",
        "system",
        "trucking"
    ],
    "wof:name":"Dales Junk Hauling Pick Up Lo",
    "wof:placetype":"venue"
},
  "geometry": {"coordinates":[-86.0857,42.792118],"type":"Point"}
}