{
  "type": "Feature",
  "properties": {
    "iso:country":"US",
    "sg:address":"4294 Laurel Dr",
    "sg:city":"Lake Odessa",
    "sg:classifiers":[
        {
            "category":"Health Services",
            "subcategory":"Health Practitioner",
            "type":"Services"
        }
    ],
    "sg:phone":"+1 616 374 0099",
    "sg:postcode":"48849",
    "sg:province":"MI",
    "sg:tags":[
        "therapist",
        "physical"
    ],
    "wof:name":"Total Health Ctr",
    "wof:placetype":"venue"
},
  "geometry": {"coordinates":[-85.161016,42.784225],"type":"Point"}
}