{
  "type": "Feature",
  "properties": {
    "iso:country":"US",
    "sg:address":"496 E Avon Rd",
    "sg:city":"Rochester Hills",
    "sg:classifiers":[
        {
            "category":"Home & Garden",
            "subcategory":"Garden Supply",
            "type":"Retail Goods"
        }
    ],
    "sg:phone":"+1 248 651 1620",
    "sg:postcode":"48307",
    "sg:province":"MI",
    "sg:tags":[
        "mulch"
    ],
    "sg:website":"www.shadesofgreennursery.com",
    "wof:name":"Shades Of Green Nursery",
    "wof:placetype":"venue"
},
  "geometry": {"coordinates":[-83.127498,42.666415],"type":"Point"}
}