{
  "type": "Feature",
  "properties": {
    "iso:country":"US",
    "sg:address":"46186 Vineyard Ave",
    "sg:city":"Shelby Twp",
    "sg:classifiers":[
        {
            "category":"Building & Trades",
            "subcategory":"Plumbing",
            "type":"Services"
        }
    ],
    "sg:phone":"+1 586 803 1391",
    "sg:postcode":"48317",
    "sg:province":"MI",
    "sg:tags":[
        "plumbing",
        "contractor"
    ],
    "wof:name":"Fantastic Plumbing",
    "wof:placetype":"venue"
},
  "geometry": {"coordinates":[-83.078579,42.632736],"type":"Point"}
}