{
  "type": "Feature",
  "properties": {
    "iso:country":"US",
    "sg:address":"6336 Fox Ave",
    "sg:city":"Allen Park",
    "sg:classifiers":[
        {
            "category":"Professional",
            "subcategory":"Lawyer & Legal Services",
            "type":"Services"
        }
    ],
    "sg:phone":"+1 313 389 2860",
    "sg:postcode":"48101",
    "sg:province":"MI",
    "wof:name":"Theisz Jacqueline Atty",
    "wof:placetype":"venue"
},
  "geometry": {"coordinates":[-83.201401,42.257301],"type":"Point"}
}