{
  "type": "Feature",
  "properties": {
    "iso:country":"US",
    "sg:address":"3963 Westrick Rd",
    "sg:city":"China",
    "sg:classifiers":[
        {
            "category":"Professional",
            "subcategory":"Lawyer & Legal Services",
            "type":"Services"
        }
    ],
    "sg:phone":"+1 810 326 1880",
    "sg:postcode":"48054",
    "sg:province":"MI",
    "sg:tags":[
        "attorney"
    ],
    "wof:name":"David L Smith Law Office",
    "wof:placetype":"venue"
},
  "geometry": {"coordinates":[-82.588228,42.786421],"type":"Point"}
}