{
  "type": "Feature",
  "properties": {
    "iso:country":"US",
    "sg:address":"25142 Muerland Rd",
    "sg:city":"Southfield",
    "sg:classifiers":[
        {
            "category":"Personal",
            "subcategory":"Beauty Salon",
            "type":"Services"
        }
    ],
    "sg:phone":"+1 248 350 8107",
    "sg:postcode":"48033",
    "sg:province":"MI",
    "wof:name":"Sylvias Salon Success",
    "wof:placetype":"venue"
},
  "geometry": {"coordinates":[-83.287125,42.481483],"type":"Point"}
}