{
  "type": "Feature",
  "properties": {
    "iso:country":"US",
    "sg:address":"1900 S Lincoln Rd",
    "sg:city":"Escanaba",
    "sg:classifiers":[
        {
            "category":"Building & Trades",
            "subcategory":"Construction",
            "type":"Services"
        }
    ],
    "sg:phone":"+1 906 786 8080",
    "sg:postcode":"49829",
    "sg:province":"MI",
    "sg:tags":[
        "contractor"
    ],
    "wof:name":"Degrave Quality Homes Inc",
    "wof:placetype":"venue"
},
  "geometry": {"coordinates":[-87.07993399999999,45.722242],"type":"Point"}
}