{
  "type": "Feature",
  "properties": {
    "iso:country":"US",
    "sg:address":"4728 Garfield Rd",
    "sg:city":"Auburn",
    "sg:classifiers":[
        {
            "category":"Professional",
            "subcategory":"Engineering",
            "type":"Services"
        }
    ],
    "sg:phone":"+1 989 662 7230",
    "sg:postcode":"48611",
    "sg:province":"MI",
    "sg:tags":[
        "engineer"
    ],
    "wof:name":"Bay Engineering",
    "wof:placetype":"venue"
},
  "geometry": {"coordinates":[-84.089483,43.605762],"type":"Point"}
}