{
  "type": "Feature",
  "properties": {
    "iso:country":"US",
    "sg:address":"808 N Blackstone St",
    "sg:city":"Jackson",
    "sg:classifiers":[
        {
            "category":"Professional",
            "subcategory":"Credit Reporting & Collection",
            "type":"Services"
        }
    ],
    "sg:phone":"+1 517 782 0863",
    "sg:postcode":"49202",
    "sg:province":"MI",
    "sg:tags":[
        "agency"
    ],
    "wof:name":"JCB Judgment Collections",
    "wof:placetype":"venue"
},
  "geometry": {"coordinates":[-84.411986,42.258854],"type":"Point"}
}