{
  "type": "Feature",
  "properties": {
    "iso:country":"US",
    "sg:address":"54014 Co Rd 388",
    "sg:city":"Grand Junction",
    "sg:classifiers":[
        {
            "category":"Government",
            "subcategory":"Post Office",
            "type":"Public Place"
        }
    ],
    "sg:phone":"+1 269 000 1111",
    "sg:postcode":"49056",
    "sg:province":"MI",
    "wof:name":"US Post Office",
    "wof:placetype":"venue"
},
  "geometry": {"coordinates":[-86.072503,42.404485],"type":"Point"}
}