{
  "type": "Feature",
  "properties": {
    "iso:country":"US",
    "sg:address":"67200 Van Dyke Rd",
    "sg:city":"Washington",
    "sg:classifiers":[
        {
            "category":"Health Services",
            "subcategory":"Doctor",
            "type":"Services"
        }
    ],
    "sg:phone":"+1 586 752 7575",
    "sg:postcode":"48095",
    "sg:province":"MI",
    "sg:tags":[
        "medical"
    ],
    "wof:name":"Romeo Heart Clinic",
    "wof:placetype":"venue"
},
  "geometry": {"coordinates":[-83.013132,42.786929],"type":"Point"}
}