{
  "type": "Feature",
  "properties": {
    "iso:country":"US",
    "sg:address":"201 Haynes St",
    "sg:city":"Cadillac",
    "sg:classifiers":[
        {
            "category":"Wholesale",
            "subcategory":"Construction Materials",
            "type":"Manufacturing & Wholesale Goods"
        }
    ],
    "sg:phone":"+1 231 779 8800",
    "sg:postcode":"49601",
    "sg:province":"MI",
    "sg:tags":[
        "pallet",
        "skid"
    ],
    "sg:website":"www.aarcorp.com",
    "wof:name":"AAR Mobility Systems",
    "wof:placetype":"venue"
},
  "geometry": {"coordinates":[-85.405233,44.25383],"type":"Point"}
}