{
  "type": "Feature",
  "properties": {
    "iso:country":"US",
    "sg:address":"3633 Hollow Pine Ct",
    "sg:city":"Almont",
    "sg:classifiers":[
        {
            "category":"Building & Trades",
            "subcategory":"Construction",
            "type":"Services"
        }
    ],
    "sg:phone":"+1 810 706 0048",
    "sg:postcode":"48003",
    "sg:province":"MI",
    "sg:tags":[
        "equipment",
        "installation"
    ],
    "wof:name":"Brayboy Enginnering",
    "wof:placetype":"venue"
},
  "geometry": {"coordinates":[-83.014792,42.964284],"type":"Point"}
}