{
  "type": "Feature",
  "properties": {
    "iso:country":"US",
    "sg:address":"2237 Annesley St",
    "sg:city":"Saginaw",
    "sg:classifiers":[
        {
            "category":"Food & Beverages",
            "subcategory":"Groceries & Convenience Stores",
            "type":"Retail Goods"
        }
    ],
    "sg:phone":"+1 989 771 9448",
    "sg:postcode":"48601",
    "sg:province":"MI",
    "sg:tags":[
        "grocer"
    ],
    "wof:name":"Hogan's Grocery",
    "wof:placetype":"venue"
},
  "geometry": {"coordinates":[-83.915758,43.420384],"type":"Point"}
}