{
  "type": "Feature",
  "properties": {
    "iso:country":"US",
    "sg:address":"2960 W Walton Blvd",
    "sg:city":"Waterford",
    "sg:classifiers":[
        {
            "category":"Professional",
            "subcategory":"Accounting & Tax Preparation",
            "type":"Services"
        }
    ],
    "sg:phone":"+1 248 673 8724",
    "sg:postcode":"48329",
    "sg:province":"MI",
    "sg:tags":[
        "return"
    ],
    "wof:name":"Walton Tax Center",
    "wof:placetype":"venue"
},
  "geometry": {"coordinates":[-83.34958899999999,42.687813],"type":"Point"}
}