{
  "type": "Feature",
  "properties": {
    "iso:country":"US",
    "sg:address":"17160 Catherine Ct",
    "sg:city":"Livonia",
    "sg:classifiers":[
        {
            "category":"Professional",
            "subcategory":"Management & Consulting",
            "type":"Services"
        }
    ],
    "sg:phone":"+1 734 422 6065",
    "sg:postcode":"48152",
    "sg:province":"MI",
    "wof:name":"Dynamic Management Partner",
    "wof:placetype":"venue"
},
  "geometry": {"coordinates":[-83.34451300000001,42.412932],"type":"Point"}
}