{
  "type": "Feature",
  "properties": {
    "iso:country":"US",
    "sg:address":"908 Nagold St NW",
    "sg:city":"Grand Rapids",
    "sg:classifiers":[
        {
            "category":"Social Services",
            "subcategory":"Child Care",
            "type":"Services"
        }
    ],
    "sg:phone":"+1 616 454 3230",
    "sg:postcode":"49504",
    "sg:province":"MI",
    "sg:tags":[
        "day"
    ],
    "wof:name":"Kerrys Kids",
    "wof:placetype":"venue"
},
  "geometry": {"coordinates":[-85.69251800000001,42.975653],"type":"Point"}
}