{
  "type": "Feature",
  "properties": {
    "iso:country":"US",
    "sg:address":"2726 Detroit Rd",
    "sg:city":"Niles",
    "sg:classifiers":[
        {
            "category":"Retail",
            "subcategory":"Auto Repair",
            "type":"Services"
        }
    ],
    "sg:phone":"+1 269 683 7740",
    "sg:postcode":"49120",
    "sg:province":"MI",
    "sg:tags":[
        "general"
    ],
    "wof:name":"Marks Place",
    "wof:placetype":"venue"
},
  "geometry": {"coordinates":[-86.170469,41.840523],"type":"Point"}
}