{
  "type": "Feature",
  "properties": {
    "iso:country":"US",
    "sg:address":"17421 Beech Rd",
    "sg:city":"Hersey",
    "sg:classifiers":[
        {
            "category":"Farming",
            "subcategory":"Dairy Farm",
            "type":"Manufacturing & Wholesale Goods"
        }
    ],
    "sg:phone":"+1 231 832 9423",
    "sg:postcode":"49639",
    "sg:province":"MI",
    "wof:name":"Dale Owens",
    "wof:placetype":"venue"
},
  "geometry": {"coordinates":[-85.43432900000001,43.804253],"type":"Point"}
}