{
  "type": "Feature",
  "properties": {
    "iso:country":"US",
    "sg:address":"1150 Stephenson Hwy",
    "sg:city":"Troy",
    "sg:classifiers":[
        {
            "category":"Professional",
            "subcategory":"Engineering",
            "type":"Services"
        }
    ],
    "sg:phone":"+1 248 588 7670",
    "sg:postcode":"48083",
    "sg:province":"MI",
    "sg:tags":[
        "engineer"
    ],
    "wof:name":"Hantech",
    "wof:placetype":"venue"
},
  "geometry": {"coordinates":[-83.12027399999999,42.544365],"type":"Point"}
}