{
  "type": "Feature",
  "properties": {
    "iso:country":"US",
    "sg:address":"6302 King Hwy",
    "sg:city":"Kalamazoo",
    "sg:classifiers":[
        {
            "category":"Travel",
            "subcategory":"Hotels & Motels",
            "type":"Entertainment"
        }
    ],
    "sg:phone":"+1 269 349 4353",
    "sg:postcode":"49048",
    "sg:province":"MI",
    "wof:name":"Comstock Motor Court Motel",
    "wof:placetype":"venue"
},
  "geometry": {"coordinates":[-85.504419,42.288388],"type":"Point"}
}