{
  "type": "Feature",
  "properties": {
    "iso:country":"US",
    "sg:address":"14342 Ironwood Dr NW",
    "sg:city":"Grand Rapids",
    "sg:classifiers":[
        {
            "category":"Real Estate",
            "subcategory":"Real Estate Agent",
            "type":"Services"
        }
    ],
    "sg:phone":"+1 616 677 2546",
    "sg:postcode":"49534",
    "sg:province":"MI",
    "sg:website":"www.reedsrealty.com",
    "wof:name":"Reeds Realty",
    "wof:placetype":"venue"
},
  "geometry": {"coordinates":[-85.805391,43.02925],"type":"Point"}
}