{
  "type": "Feature",
  "properties": {
    "iso:country":"US",
    "sg:address":"6230 Hackett Rd",
    "sg:city":"Freeland",
    "sg:classifiers":[
        {
            "category":"Building & Trades",
            "subcategory":"Construction",
            "type":"Services"
        }
    ],
    "sg:phone":"+1 989 695 2300",
    "sg:postcode":"48623",
    "sg:province":"MI",
    "sg:tags":[
        "contractor"
    ],
    "wof:name":"Sheldon Building Co",
    "wof:placetype":"venue"
},
  "geometry": {"coordinates":[-84.07135100000001,43.498863],"type":"Point"}
}