{
  "type": "Feature",
  "properties": {
    "iso:country":"US",
    "sg:address":"111 Broadus St",
    "sg:city":"Sturgis",
    "sg:classifiers":[
        {
            "category":"Professional",
            "subcategory":"Employment Agencies",
            "type":"Services"
        }
    ],
    "sg:phone":"+1 269 651 5030",
    "sg:postcode":"49091",
    "sg:province":"MI",
    "sg:tags":[
        "help",
        "supply"
    ],
    "wof:name":"Perry Personnel Plus Inc",
    "wof:placetype":"venue"
},
  "geometry": {"coordinates":[-85.43315200000001,41.799027],"type":"Point"}
}