{
  "type": "Feature",
  "properties": {
    "iso:country":"US",
    "sg:address":"420 S 17th St",
    "sg:city":"Saginaw",
    "sg:classifiers":[
        {
            "category":"Organizations",
            "subcategory":"Religious Organization",
            "type":"Services"
        }
    ],
    "sg:phone":"+1 989 753 1383",
    "sg:postcode":"48601",
    "sg:province":"MI",
    "sg:tags":[
        "church"
    ],
    "wof:name":"New Jerusalem Baptist Church",
    "wof:placetype":"venue"
},
  "geometry": {"coordinates":[-83.91360400000001,43.425889],"type":"Point"}
}