{
  "type": "Feature",
  "properties": {
    "iso:country":"US",
    "sg:address":"7375 Noffke Dr",
    "sg:city":"Caledonia",
    "sg:classifiers":[
        {
            "category":"Building & Trades",
            "subcategory":"Construction",
            "type":"Services"
        }
    ],
    "sg:phone":"+1 616 891 1859",
    "sg:postcode":"49316",
    "sg:province":"MI",
    "sg:tags":[
        "housing"
    ],
    "wof:name":"Paradigm Homes Inc",
    "wof:placetype":"venue"
},
  "geometry": {"coordinates":[-85.523111,42.767679],"type":"Point"}
}