{
  "type": "Feature",
  "properties": {
    "iso:country":"US",
    "sg:address":"3464 Fairlane Dr",
    "sg:city":"Allen Park",
    "sg:classifiers":[
        {
            "category":"Shopping Center",
            "type":"Public Place"
        }
    ],
    "sg:postcode":"48101",
    "sg:province":"MI",
    "wof:name":"Fairlane Green",
    "wof:placetype":"venue"
},
  "geometry": {"coordinates":[-83.20785600000001,42.279769],"type":"Point"}
}