{
  "type": "Feature",
  "properties": {
    "iso:country":"US",
    "sg:address":"342 Glen Arbor Dr NE",
    "sg:city":"Rockford",
    "sg:classifiers":[
        {
            "category":"Building & Trades",
            "subcategory":"Landscaping Services",
            "type":"Services"
        }
    ],
    "sg:phone":"+1 616 307 2526",
    "sg:postcode":"49341",
    "sg:province":"MI",
    "wof:name":"A & M Lawn Care",
    "wof:placetype":"venue"
},
  "geometry": {"coordinates":[-85.5737,43.127767],"type":"Point"}
}