{
  "type": "Feature",
  "properties": {
    "iso:country":"US",
    "sg:address":"7481 Chesaning Rd",
    "sg:city":"Chesaning",
    "sg:classifiers":[
        {
            "category":"Building & Trades",
            "subcategory":"Construction",
            "type":"Services"
        }
    ],
    "sg:phone":"+1 989 845 6365",
    "sg:postcode":"48616",
    "sg:province":"MI",
    "sg:tags":[
        "general",
        "contractor"
    ],
    "wof:name":"Streng Construction",
    "wof:placetype":"venue"
},
  "geometry": {"coordinates":[-84.059825,43.203826],"type":"Point"}
}