{
  "type": "Feature",
  "properties": {
    "iso:country":"US",
    "sg:address":"3185 N Broadway St",
    "sg:city":"Hastings",
    "sg:classifiers":[
        {
            "category":"Organizations",
            "subcategory":"Religious Organization",
            "type":"Services"
        }
    ],
    "sg:phone":"+1 269 945 2654",
    "sg:postcode":"49058",
    "sg:province":"MI",
    "sg:tags":[
        "church"
    ],
    "wof:name":"Welcome Corners United Meth",
    "wof:placetype":"venue"
},
  "geometry": {"coordinates":[-85.29089,42.698471],"type":"Point"}
}