{
  "type": "Feature",
  "properties": {
    "iso:country":"US",
    "sg:address":"4156 Morrison St",
    "sg:city":"Burton",
    "sg:classifiers":[
        {
            "category":"Building & Trades",
            "subcategory":"Construction",
            "type":"Services"
        }
    ],
    "sg:phone":"+1 810 743 6679",
    "sg:postcode":"48529",
    "sg:province":"MI",
    "sg:tags":[
        "home",
        "improvement"
    ],
    "wof:name":"Timbercrest Home Improvement",
    "wof:placetype":"venue"
},
  "geometry": {"coordinates":[-83.67585699999999,42.969308],"type":"Point"}
}