{
  "type": "Feature",
  "properties": {
    "iso:country":"US",
    "sg:address":"25062 Plymouth Rd",
    "sg:city":"Redford",
    "sg:classifiers":[
        {
            "category":"Retail",
            "subcategory":"Funeral Services",
            "type":"Services"
        }
    ],
    "sg:phone":"+1 313 533 1302",
    "sg:postcode":"48239",
    "sg:province":"MI",
    "sg:tags":[
        "cemetery"
    ],
    "wof:name":"Detroit Memorial Park Association Inc",
    "wof:placetype":"venue"
},
  "geometry": {"coordinates":[-83.2911,42.370998],"type":"Point"}
}