{
  "type": "Feature",
  "properties": {
    "iso:country":"US",
    "sg:address":"10585 Vasold Rd",
    "sg:city":"Freeland",
    "sg:classifiers":[
        {
            "category":"Building & Trades",
            "subcategory":"Landscaping Services",
            "type":"Services"
        }
    ],
    "sg:phone":"+1 989 799 5723",
    "sg:postcode":"48623",
    "sg:province":"MI",
    "sg:tags":[
        "landscape",
        "contractor"
    ],
    "wof:name":"KWIK Kerb",
    "wof:placetype":"venue"
},
  "geometry": {"coordinates":[-84.116744,43.495897],"type":"Point"}
}