{
  "type": "Feature",
  "properties": {
    "iso:country":"US",
    "sg:address":"11028 Arnold Hwy",
    "sg:city":"Jasper",
    "sg:classifiers":[
        {
            "category":"Organizations",
            "subcategory":"Religious Organization",
            "type":"Services"
        }
    ],
    "sg:phone":"+1 517 436 3165",
    "sg:postcode":"49248",
    "sg:province":"MI",
    "sg:tags":[
        "church"
    ],
    "wof:name":"Ridgeville Bible Church",
    "wof:placetype":"venue"
},
  "geometry": {"coordinates":[-84.02165100000001,41.756746],"type":"Point"}
}