{
  "type": "Feature",
  "properties": {
    "iso:country":"US",
    "sg:address":"2726 Kensington Dr",
    "sg:city":"Saginaw",
    "sg:classifiers":[
        {
            "category":"Organizations",
            "subcategory":"Religious Organization",
            "type":"Services"
        }
    ],
    "sg:phone":"+1 989 753 7885",
    "sg:postcode":"48601",
    "sg:province":"MI",
    "sg:tags":[
        "clergy"
    ],
    "wof:name":"Thomas Brown",
    "wof:placetype":"venue"
},
  "geometry": {"coordinates":[-83.92827200000001,43.394525],"type":"Point"}
}