{
  "type": "Feature",
  "properties": {
    "iso:country":"US",
    "sg:address":"315 N Lincoln Rd",
    "sg:city":"Escanaba",
    "sg:classifiers":[
        {
            "category":"Shopping",
            "subcategory":"Optical Goods",
            "type":"Retail Goods"
        }
    ],
    "sg:phone":"+1 906 789 0668",
    "sg:postcode":"49829",
    "sg:province":"MI",
    "wof:name":"Exact Eye Care",
    "wof:placetype":"venue"
},
  "geometry": {"coordinates":[-87.07976499999999,45.748639],"type":"Point"}
}