{
  "type": "Feature",
  "properties": {
    "iso:country":"US",
    "sg:address":"67 College St",
    "sg:city":"Battle Creek",
    "sg:classifiers":[
        {
            "category":"Social Services",
            "subcategory":"Adult Care",
            "type":"Services"
        }
    ],
    "sg:phone":"+1 269 969 0435",
    "sg:postcode":"49037",
    "sg:province":"MI",
    "sg:tags":[
        "home"
    ],
    "wof:name":"Mainstay AFC",
    "wof:placetype":"venue"
},
  "geometry": {"coordinates":[-85.839862,43.807322],"type":"Point"}
}