{
  "type": "Feature",
  "properties": {
    "iso:country":"US",
    "sg:address":"3231 Boyer Rd",
    "sg:city":"Coloma",
    "sg:classifiers":[
        {
            "category":"Organizations",
            "subcategory":"Religious Organization",
            "type":"Services"
        }
    ],
    "sg:phone":"+1 269 468 9323",
    "sg:postcode":"49038",
    "sg:province":"MI",
    "wof:name":"Kingdom Hall Jhovahs Witnesses",
    "wof:placetype":"venue"
},
  "geometry": {"coordinates":[-86.32995,42.182993],"type":"Point"}
}