{
  "type": "Feature",
  "properties": {
    "iso:country":"US",
    "sg:address":"239 Orchard St",
    "sg:city":"Saranac",
    "sg:classifiers":[
        {
            "category":"Professional",
            "subcategory":"Business Services",
            "type":"Services"
        }
    ],
    "sg:phone":"+1 616 642 9888",
    "sg:postcode":"48881",
    "sg:province":"MI",
    "wof:name":"Target Solutions",
    "wof:placetype":"venue"
},
  "geometry": {"coordinates":[-85.207189,42.927861],"type":"Point"}
}