{
  "type": "Feature",
  "properties": {
    "iso:country":"US",
    "sg:address":"2966 Shorewood Blvd",
    "sg:city":"Fort Gratiot",
    "sg:classifiers":[
        {
            "category":"Health Services",
            "subcategory":"Doctor",
            "type":"Services"
        }
    ],
    "sg:phone":"+1 810 985 9681",
    "sg:postcode":"48059",
    "sg:province":"MI",
    "sg:tags":[
        "physician",
        "surgeon"
    ],
    "wof:name":"Babu Doddapaneni MD",
    "wof:placetype":"venue"
},
  "geometry": {"coordinates":[-82.463971,43.063203],"type":"Point"}
}