{
  "type": "Feature",
  "properties": {
    "iso:country":"US",
    "sg:address":"55 S Morse St",
    "sg:city":"Sandusky",
    "sg:classifiers":[
        {
            "category":"Government",
            "subcategory":"Post Office",
            "type":"Public Place"
        }
    ],
    "sg:phone":"+1 810 648 2362",
    "sg:postcode":"48471",
    "sg:province":"MI",
    "wof:name":"US Post Office",
    "wof:placetype":"venue"
},
  "geometry": {"coordinates":[-82.828328,43.420129],"type":"Point"}
}