{
  "type": "Feature",
  "properties": {
    "iso:country":"US",
    "sg:address":"4210 Pontiac Lake Rd",
    "sg:city":"Waterford",
    "sg:classifiers":[
        {
            "category":"Health Services",
            "subcategory":"Doctor",
            "type":"Services"
        }
    ],
    "sg:phone":"+1 248 673 1520",
    "sg:postcode":"48328",
    "sg:province":"MI",
    "sg:tags":[
        "physician",
        "surgeon"
    ],
    "wof:name":"Waterford Pediatrics",
    "wof:placetype":"venue"
},
  "geometry": {"coordinates":[-83.371405,42.654977],"type":"Point"}
}