{
  "type": "Feature",
  "properties": {
    "iso:country":"US",
    "sg:address":"2040 Cedar St",
    "sg:city":"Holt",
    "sg:classifiers":[
        {
            "category":"Retail",
            "subcategory":"Auto Repair",
            "type":"Services"
        }
    ],
    "sg:phone":"+1 517 694 8519",
    "sg:postcode":"48842",
    "sg:province":"MI",
    "sg:tags":[
        "general"
    ],
    "wof:name":"Holt Auto Clinic",
    "wof:placetype":"venue"
},
  "geometry": {"coordinates":[-84.517072,42.64198],"type":"Point"}
}