{
  "type": "Feature",
  "properties": {
    "iso:country":"US",
    "sg:address":"100 Main St",
    "sg:city":"East Jordan",
    "sg:classifiers":[
        {
            "category":"Insurance",
            "subcategory":"Insurance Agent",
            "type":"Services"
        }
    ],
    "sg:phone":"+1 231 536 2268",
    "sg:postcode":"49727",
    "sg:province":"MI",
    "wof:name":"Korthase Insurance & Financial",
    "wof:placetype":"venue"
},
  "geometry": {"coordinates":[-85.12759800000001,45.155381],"type":"Point"}
}