{
  "type": "Feature",
  "properties": {
    "iso:country":"US",
    "sg:address":"212 Woodward Ave",
    "sg:city":"Iron Mountain",
    "sg:classifiers":[
        {
            "category":"Home & Garden",
            "subcategory":"Building Materials",
            "type":"Retail Goods"
        }
    ],
    "sg:phone":"+1 906 779 0590",
    "sg:postcode":"49801",
    "sg:province":"MI",
    "sg:tags":[
        "glass",
        "window",
        "plate"
    ],
    "wof:name":"Superior Auto Glass Ctr",
    "wof:placetype":"venue"
},
  "geometry": {"coordinates":[-88.069923,45.80787],"type":"Point"}
}