{
  "type": "Feature",
  "properties": {
    "iso:country":"US",
    "sg:address":"870 Polaris Crescent Dr",
    "sg:city":"Traverse City",
    "sg:classifiers":[
        {
            "category":"Home & Garden",
            "subcategory":"Home Furnishings",
            "type":"Retail Goods"
        }
    ],
    "sg:phone":"+1 231 933 9913",
    "sg:postcode":"49684",
    "sg:province":"MI",
    "sg:tags":[
        "beveled",
        "glass",
        "ornamental"
    ],
    "wof:name":"Traverse Bay Beveled Glass",
    "wof:placetype":"venue"
},
  "geometry": {"coordinates":[-85.654387,44.700529],"type":"Point"}
}