{
  "type": "Feature",
  "properties": {
    "iso:country":"US",
    "sg:address":"621 Mason St",
    "sg:city":"Flint",
    "sg:classifiers":[
        {
            "category":"Banks & Credit Unions",
            "subcategory":"Financial Services",
            "type":"Services"
        }
    ],
    "sg:phone":"+1 810 239 8473",
    "sg:postcode":"48503",
    "sg:province":"MI",
    "sg:tags":[
        "investor"
    ],
    "wof:name":"Magnum Investments",
    "wof:placetype":"venue"
},
  "geometry": {"coordinates":[-83.698955,43.020341],"type":"Point"}
}