{
  "type": "Feature",
  "properties": {
    "iso:country":"US",
    "sg:address":"1209 Cove Rd",
    "sg:city":"Wales",
    "sg:classifiers":[
        {
            "category":"Organizations",
            "subcategory":"Religious Organization",
            "type":"Services"
        }
    ],
    "sg:phone":"+1 810 392 2294",
    "sg:postcode":"48027",
    "sg:province":"MI",
    "sg:tags":[
        "church"
    ],
    "wof:name":"Lamb United Methodist Church",
    "wof:placetype":"venue"
},
  "geometry": {"coordinates":[-82.708105,42.934864],"type":"Point"}
}