{
  "type": "Feature",
  "properties": {
    "iso:country":"US",
    "sg:address":"22124 Averhill St",
    "sg:city":"Farmington Hills",
    "sg:classifiers":[
        {
            "category":"Building & Trades",
            "subcategory":"Landscaping Services",
            "type":"Services"
        }
    ],
    "sg:phone":"+1 248 888 0082",
    "sg:postcode":"48336",
    "sg:province":"MI",
    "sg:tags":[
        "lawn",
        "maintenance",
        "grounds"
    ],
    "wof:name":"Sir Edward Landscaping",
    "wof:placetype":"venue"
},
  "geometry": {"coordinates":[-83.327179,42.456022],"type":"Point"}
}