{
  "type": "Feature",
  "properties": {
    "iso:country":"US",
    "sg:address":"1171 N Queensway Dr",
    "sg:city":"Weidman",
    "sg:classifiers":[
        {
            "category":"Professional",
            "subcategory":"Accounting & Tax Preparation",
            "type":"Services"
        }
    ],
    "sg:phone":"+1 989 644 5890",
    "sg:postcode":"48893",
    "sg:province":"MI",
    "sg:tags":[
        "accountant"
    ],
    "wof:name":"R G & G ACCOUNTING PC",
    "wof:placetype":"venue"
},
  "geometry": {"coordinates":[-85.010009,43.645548],"type":"Point"}
}