{
  "type": "Feature",
  "properties": {
    "iso:country":"US",
    "sg:address":"210 Dunlap St",
    "sg:city":"Lansing",
    "sg:classifiers":[
        {
            "category":"Building & Trades",
            "subcategory":"Construction",
            "type":"Services"
        }
    ],
    "sg:phone":"+1 517 853 1061",
    "sg:postcode":"48910",
    "sg:province":"MI",
    "sg:tags":[
        "hanging",
        "contractor"
    ],
    "wof:name":"Brad J King",
    "wof:placetype":"venue"
},
  "geometry": {"coordinates":[-84.554411,42.70233],"type":"Point"}
}