{
  "type": "Feature",
  "properties": {
    "iso:country":"US",
    "sg:address":"873 Iroquois St",
    "sg:city":"Detroit",
    "sg:classifiers":[
        {
            "category":"Personal",
            "type":"Services"
        }
    ],
    "sg:phone":"+1 313 824 8019",
    "sg:postcode":"48214",
    "sg:province":"MI",
    "wof:name":"Magik Touch",
    "wof:placetype":"venue"
},
  "geometry": {"coordinates":[-82.991878,42.35446],"type":"Point"}
}