{
  "type": "Feature",
  "properties": {
    "iso:country":"US",
    "sg:address":"2030 S Airport Rd W",
    "sg:city":"Traverse City",
    "sg:classifiers":[
        {
            "category":"Restaurant",
            "type":"Food & Drink"
        }
    ],
    "sg:phone":"+1 231 941 8147",
    "sg:postcode":"49684",
    "sg:province":"MI",
    "wof:name":"Auntie Pasta's",
    "wof:placetype":"venue"
},
  "geometry": {"coordinates":[-85.61740399999999,44.733225],"type":"Point"}
}