{
  "type": "Feature",
  "properties": {
    "iso:country":"US",
    "sg:address":"6333 Thornhills Ct SE",
    "sg:city":"Grand Rapids",
    "sg:classifiers":[
        {
            "category":"Professional",
            "type":"Services"
        }
    ],
    "sg:phone":"+1 616 942 8732",
    "sg:postcode":"49546",
    "sg:province":"MI",
    "wof:name":"Bylenga Family Ltd Partne",
    "wof:placetype":"venue"
},
  "geometry": {"coordinates":[-85.510192,42.905726],"type":"Point"}
}