{
  "type": "Feature",
  "properties": {
    "iso:country":"US",
    "sg:address":"5555 Gatewood Dr",
    "sg:city":"Sterling Heights",
    "sg:classifiers":[
        {
            "category":"Wholesale",
            "subcategory":"Hardware",
            "type":"Manufacturing & Wholesale Goods"
        }
    ],
    "sg:phone":"+1 586 268 5130",
    "sg:postcode":"48310",
    "sg:province":"MI",
    "sg:tags":[
        "tool"
    ],
    "wof:name":"Quality Tool & Abrasive",
    "wof:placetype":"venue"
},
  "geometry": {"coordinates":[-83.051174,42.587962],"type":"Point"}
}