{
  "type": "Feature",
  "properties": {
    "iso:country":"US",
    "sg:address":"5277 Dixie Hwy",
    "sg:city":"Saginaw",
    "sg:classifiers":[
        {
            "category":"Building & Trades",
            "subcategory":"Construction",
            "type":"Services"
        }
    ],
    "sg:phone":"+1 989 777 5680",
    "sg:postcode":"48601",
    "sg:province":"MI",
    "sg:tags":[
        "excavating",
        "contractor"
    ],
    "wof:name":"Hemerline Excavating",
    "wof:placetype":"venue"
},
  "geometry": {"coordinates":[-83.90021400000001,43.38464],"type":"Point"}
}