{
  "type": "Feature",
  "properties": {
    "iso:country":"US",
    "sg:address":"2446 E 12 Mile Rd",
    "sg:city":"Warren",
    "sg:classifiers":[
        {
            "category":"Autos & Motor Vehicles",
            "subcategory":"Automobile Sales",
            "type":"Retail Goods"
        }
    ],
    "sg:phone":"+1 586 751 6100",
    "sg:postcode":"48092",
    "sg:province":"MI",
    "sg:tags":[
        "car"
    ],
    "wof:name":"Nissan-Key Nissan Sales & Service",
    "wof:placetype":"venue"
},
  "geometry": {"coordinates":[-83.080299,42.505501],"type":"Point"}
}