{
  "type": "Feature",
  "properties": {
    "iso:country":"US",
    "sg:address":"350 Karen Rd",
    "sg:city":"Marquette",
    "sg:classifiers":[
        {
            "category":"Freight",
            "type":"Transportation"
        }
    ],
    "sg:phone":"+1 906 249 9500",
    "sg:postcode":"49855",
    "sg:province":"MI",
    "sg:tags":[
        "operator",
        "local",
        "trucking"
    ],
    "wof:name":"Boyer Trucking",
    "wof:placetype":"venue"
},
  "geometry": {"coordinates":[-87.32775100000001,46.428758],"type":"Point"}
}