{
  "type": "Feature",
  "properties": {
    "iso:country":"US",
    "sg:address":"26235 Gibraltar Rd",
    "sg:city":"Flat Rock",
    "sg:classifiers":[
        {
            "category":"Personal",
            "subcategory":"Beauty Salon",
            "type":"Services"
        }
    ],
    "sg:phone":"+1 734 782 2700",
    "sg:postcode":"48134",
    "sg:province":"MI",
    "sg:tags":[
        "shop"
    ],
    "wof:name":"Shear Illusions",
    "wof:placetype":"venue"
},
  "geometry": {"coordinates":[-83.288758,42.094317],"type":"Point"}
}