{
  "type": "Feature",
  "properties": {
    "iso:country":"US",
    "sg:address":"50 Ottawa Ave NW",
    "sg:city":"Grand Rapids",
    "sg:classifiers":[
        {
            "category":"Government",
            "subcategory":"Office",
            "type":"Public Place"
        }
    ],
    "sg:phone":"+1 616 456 3290",
    "sg:postcode":"49503",
    "sg:province":"MI",
    "sg:tags":[
        "village"
    ],
    "sg:website":"www.ci.grand-rapids.mi.us",
    "wof:name":"Grand Rapids Parking Svc",
    "wof:placetype":"venue"
},
  "geometry": {"coordinates":[-85.67146200000001,42.963653],"type":"Point"}
}