{
  "type": "Feature",
  "properties": {
    "iso:country":"US",
    "sg:address":"1995 US Hwy 31",
    "sg:city":"Traverse City",
    "sg:classifiers":[
        {
            "category":"Organizations",
            "subcategory":"Community Association",
            "type":"Services"
        }
    ],
    "sg:phone":"+1 231 938 2228",
    "sg:postcode":"49686",
    "sg:province":"MI",
    "sg:tags":[
        "condominium"
    ],
    "wof:name":"Beach Condominiums Association",
    "wof:placetype":"venue"
},
  "geometry": {"coordinates":[-85.53759599999999,44.745918],"type":"Point"}
}