{
  "type": "Feature",
  "properties": {
    "iso:country":"US",
    "sg:address":"15800 Providence Dr",
    "sg:city":"Southfield",
    "sg:classifiers":[
        {
            "category":"Banks & Credit Unions",
            "subcategory":"Investment Brokerage",
            "type":"Services"
        }
    ],
    "sg:phone":"+1 248 443 2521",
    "sg:postcode":"48075",
    "sg:province":"MI",
    "sg:tags":[
        "advisory"
    ],
    "wof:name":"Freedmon Financial Services",
    "wof:placetype":"venue"
},
  "geometry": {"coordinates":[-83.206656,42.455985],"type":"Point"}
}