{
  "type": "Feature",
  "properties": {
    "iso:country":"US",
    "sg:address":"3196 N Dancer Rd",
    "sg:city":"Dexter",
    "sg:classifiers":[
        {
            "category":"Manufacturing",
            "subcategory":"Electronics",
            "type":"Manufacturing & Wholesale Goods"
        }
    ],
    "sg:phone":"+1 734 426 9390",
    "sg:postcode":"48130",
    "sg:province":"MI",
    "sg:tags":[
        "semiconductor",
        "mfg"
    ],
    "wof:name":"Allegro Microsystems Inc",
    "wof:placetype":"venue"
},
  "geometry": {"coordinates":[-83.924271,42.342984],"type":"Point"}
}