{
  "type": "Feature",
  "properties": {
    "iso:country":"US",
    "sg:address":"363 E Grand Blanc Rd",
    "sg:city":"Grand Blanc",
    "sg:classifiers":[
        {
            "category":"Social Services",
            "subcategory":"Child Care",
            "type":"Services"
        }
    ],
    "sg:phone":"+1 810 694 9710",
    "sg:postcode":"48439",
    "sg:province":"MI",
    "sg:tags":[
        "kindergarten",
        "academic",
        "school",
        "day"
    ],
    "wof:name":"Gingerbread House",
    "wof:placetype":"venue"
},
  "geometry": {"coordinates":[-83.632831,42.925429],"type":"Point"}
}