{
  "type": "Feature",
  "properties": {
    "iso:country":"US",
    "sg:address":"8758 Mercedes Ave",
    "sg:city":"Dearborn Heights",
    "sg:classifiers":[
        {
            "category":"Professional",
            "subcategory":"Business Services",
            "type":"Services"
        }
    ],
    "sg:phone":"+1 313 563 3102",
    "sg:postcode":"48127",
    "sg:province":"MI",
    "sg:tags":[
        "notary",
        "republic"
    ],
    "wof:name":"Beck Bookkeeping",
    "wof:placetype":"venue"
},
  "geometry": {"coordinates":[-83.309731,42.354585],"type":"Point"}
}