{
  "type": "Feature",
  "properties": {
    "iso:country":"US",
    "sg:address":"914 Ottawa Ave",
    "sg:city":"Ypsilanti",
    "sg:classifiers":[
        {
            "category":"Building & Trades",
            "subcategory":"Landscaping Services",
            "type":"Services"
        }
    ],
    "sg:phone":"+1 734 340 4667",
    "sg:postcode":"48198",
    "sg:province":"MI",
    "sg:tags":[
        "landscape"
    ],
    "wof:name":"Cdl Landscaping LLC",
    "wof:placetype":"venue"
},
  "geometry": {"coordinates":[-83.592449,42.233313],"type":"Point"}
}