{
  "type": "Feature",
  "properties": {
    "iso:country":"US",
    "sg:address":"22904 W Industrial Dr",
    "sg:city":"Saint Clair Shores",
    "sg:classifiers":[
        {
            "category":"Building & Trades",
            "subcategory":"Construction",
            "type":"Services"
        }
    ],
    "sg:phone":"+1 586 772 1310",
    "sg:postcode":"48080",
    "sg:province":"MI",
    "sg:tags":[
        "em",
        "equipment",
        "installation",
        "help",
        "supply"
    ],
    "wof:name":"St Clair Development Co",
    "wof:placetype":"venue"
},
  "geometry": {"coordinates":[-82.91878199999999,42.466354],"type":"Point"}
}