{
  "type": "Feature",
  "properties": {
    "iso:country":"US",
    "sg:address":"181 S Division St",
    "sg:city":"Hesperia",
    "sg:classifiers":[
        {
            "category":"Restaurant",
            "type":"Food & Drink"
        }
    ],
    "sg:menulink":"http://www.allmenus.com/mi/denver/146061-subway/menu/",
    "sg:phone":"+1 231 854 5400",
    "sg:postcode":"49421",
    "sg:province":"MI",
    "sg:tags":[
        "american",
        "sandwich"
    ],
    "wof:name":"Subway",
    "wof:placetype":"venue"
},
  "geometry": {"coordinates":[-86.039601,43.566997],"type":"Point"}
}