{
  "type": "Feature",
  "properties": {
    "iso:country":"US",
    "sg:address":"1787 Allen Rd",
    "sg:city":"Smiths Creek",
    "sg:classifiers":[
        {
            "category":"Manufacturing",
            "subcategory":"Wood Products",
            "type":"Manufacturing & Wholesale Goods"
        }
    ],
    "sg:phone":"+1 810 985 9583",
    "sg:postcode":"48074",
    "sg:province":"MI",
    "sg:tags":[
        "mill",
        "mfg"
    ],
    "wof:name":"G and G Woodworking",
    "wof:placetype":"venue"
},
  "geometry": {"coordinates":[-82.522966,42.959782],"type":"Point"}
}