{
  "type": "Feature",
  "properties": {
    "iso:country":"US",
    "sg:address":"22811 Greater Mack Ave",
    "sg:city":"St Clair Shores",
    "sg:classifiers":[
        {
            "category":"Professional",
            "type":"Services"
        }
    ],
    "sg:phone":"+1 586 447 4746",
    "sg:postcode":"48080",
    "sg:province":"MI",
    "sg:tags":[
        "establishment"
    ],
    "wof:name":"Vocis It Inc",
    "wof:placetype":"venue"
},
  "geometry": {"coordinates":[-82.899503,42.462624],"type":"Point"}
}