{
  "type": "Feature",
  "properties": {
    "iso:country":"US",
    "sg:address":"22000 Garrison St",
    "sg:city":"Dearborn",
    "sg:classifiers":[
        {
            "category":"Professional",
            "subcategory":"Employment Agencies",
            "type":"Services"
        }
    ],
    "sg:phone":"+1 313 791 8140",
    "sg:postcode":"48124",
    "sg:province":"MI",
    "wof:name":"Heritage Human Tech MGT LLC",
    "wof:placetype":"venue"
},
  "geometry": {"coordinates":[-83.246504,42.306819],"type":"Point"}
}