{
  "type": "Feature",
  "properties": {
    "iso:country":"US",
    "sg:address":"10985 Woodbury Rd",
    "sg:city":"Laingsburg",
    "sg:classifiers":[
        {
            "category":"Building & Trades",
            "subcategory":"Construction",
            "type":"Services"
        }
    ],
    "sg:phone":"+1 517 651 2970",
    "sg:postcode":"48848",
    "sg:province":"MI",
    "sg:tags":[
        "concrete",
        "contractor"
    ],
    "wof:name":"Arlus Concrete & Construction",
    "wof:placetype":"venue"
},
  "geometry": {"coordinates":[-84.343361,42.833923],"type":"Point"}
}