{
  "type": "Feature",
  "properties": {
    "iso:country":"US",
    "sg:address":"190 Uran St",
    "sg:city":"Hillsdale",
    "sg:classifiers":[
        {
            "category":"Manufacturing",
            "subcategory":"Chemicals & Compounds",
            "type":"Manufacturing & Wholesale Goods"
        }
    ],
    "sg:phone":"+1 517 439 4400",
    "sg:postcode":"49242",
    "sg:province":"MI",
    "sg:tags":[
        "adhesive",
        "sealant"
    ],
    "sg:website":"www.dow.com",
    "wof:name":"Dow Automotive",
    "wof:placetype":"venue"
},
  "geometry": {"coordinates":[-84.65835800000001,41.937622],"type":"Point"}
}