{
  "type": "Feature",
  "properties": {
    "iso:country":"US",
    "sg:address":"17515 W 9 Mile Rd Ste 150",
    "sg:city":"Southfield",
    "sg:classifiers":[
        {
            "category":"Personal",
            "subcategory":"Barber",
            "type":"Services"
        }
    ],
    "sg:phone":"+1 248 424 8466",
    "sg:postcode":"48075",
    "sg:province":"MI",
    "wof:name":"Hair Explore",
    "wof:placetype":"venue"
},
  "geometry": {"coordinates":[-83.21790300000001,42.4589],"type":"Point"}
}