{
  "type": "Feature",
  "properties": {
    "iso:country":"US",
    "sg:address":"18560 W 9 Mile Rd",
    "sg:city":"Southfield",
    "sg:classifiers":[
        {
            "category":"Building & Trades",
            "subcategory":"Cleaning & Sanitation",
            "type":"Services"
        }
    ],
    "sg:phone":"+1 248 358 3430",
    "sg:postcode":"48075",
    "sg:province":"MI",
    "sg:tags":[
        "maintenance"
    ],
    "wof:name":"Houge Building Services",
    "wof:placetype":"venue"
},
  "geometry": {"coordinates":[-83.230356,42.458626],"type":"Point"}
}