{
  "type": "Feature",
  "properties": {
    "iso:country":"US",
    "sg:address":"1813 S Getty St",
    "sg:city":"Muskegon",
    "sg:classifiers":[
        {
            "category":"Food & Beverages",
            "subcategory":"Groceries & Convenience Stores",
            "type":"Retail Goods"
        }
    ],
    "sg:phone":"+1 231 722 6652",
    "sg:postcode":"49442",
    "sg:province":"MI",
    "wof:name":"Antoo Of Muskegon",
    "wof:placetype":"venue"
},
  "geometry": {"coordinates":[-86.22448,43.217887],"type":"Point"}
}