{
  "type": "Feature",
  "properties": {
    "iso:country":"US",
    "sg:address":"17800 Kennebec St",
    "sg:city":"Wyandotte",
    "sg:classifiers":[
        {
            "category":"Social Services",
            "subcategory":"Child Care",
            "type":"Services"
        }
    ],
    "sg:phone":"+1 734 284 9160",
    "sg:postcode":"48193",
    "sg:province":"MI",
    "sg:tags":[
        "day"
    ],
    "wof:name":"Camp Fire Latchkey Program",
    "wof:placetype":"venue"
},
  "geometry": {"coordinates":[-83.203121,42.179073],"type":"Point"}
}