{
  "type": "Feature",
  "properties": {
    "iso:country":"US",
    "sg:address":"6375 Bridgeport Village Square Dr",
    "sg:city":"Bridgeport",
    "sg:classifiers":[
        {
            "category":"Manufacturing",
            "subcategory":"Printing",
            "type":"Manufacturing & Wholesale Goods"
        }
    ],
    "sg:phone":"+1 989 777 9850",
    "sg:postcode":"48722",
    "sg:province":"MI",
    "sg:tags":[
        "commercial"
    ],
    "wof:name":"Multicopy Printing Inc",
    "wof:placetype":"venue"
},
  "geometry": {"coordinates":[-83.871635,43.353277],"type":"Point"}
}