{
  "type": "Feature",
  "properties": {
    "iso:country":"US",
    "sg:address":"124 W Allegan St",
    "sg:city":"Lansing",
    "sg:classifiers":[
        {
            "category":"Government",
            "subcategory":"Office",
            "type":"Public Place"
        }
    ],
    "sg:phone":"+1 517 373 2518",
    "sg:postcode":"48915",
    "sg:province":"MI",
    "sg:tags":[
        "administrative",
        "program",
        "economic",
        "finance",
        "general"
    ],
    "wof:name":"Department of State Michigan",
    "wof:placetype":"venue"
},
  "geometry": {"coordinates":[-84.55361600000001,42.73273],"type":"Point"}
}