{
  "type": "Feature",
  "properties": {
    "iso:country":"US",
    "sg:address":"3328 Burnside St",
    "sg:city":"Detroit",
    "sg:classifiers":[
        {
            "category":"Building & Trades",
            "subcategory":"Construction",
            "type":"Services"
        }
    ],
    "sg:phone":"+1 313 893 2767",
    "sg:postcode":"48212",
    "sg:province":"MI",
    "sg:tags":[
        "floor",
        "laying",
        "contractor"
    ],
    "wof:name":"Unique Flooring",
    "wof:placetype":"venue"
},
  "geometry": {"coordinates":[-83.0599,42.409493],"type":"Point"}
}