{
  "type": "Feature",
  "properties": {
    "iso:country":"US",
    "sg:address":"4710 Melanie Ln",
    "sg:city":"White Lake",
    "sg:classifiers":[
        {
            "category":"Building & Trades",
            "subcategory":"Construction",
            "type":"Services"
        }
    ],
    "sg:phone":"+1 248 889 2384",
    "sg:postcode":"48383",
    "sg:province":"MI",
    "sg:tags":[
        "residential"
    ],
    "wof:name":"Capstone Residential Cnstr",
    "wof:placetype":"venue"
},
  "geometry": {"coordinates":[-83.53236699999999,42.68138],"type":"Point"}
}