{
  "type": "Feature",
  "properties": {
    "iso:country":"US",
    "sg:address":"516 S Creyts Rd",
    "sg:city":"Lansing",
    "sg:classifiers":[
        {
            "category":"Banks & Credit Unions",
            "subcategory":"Investment Brokerage",
            "type":"Services"
        }
    ],
    "sg:phone":"+1 517 323 4877",
    "sg:postcode":"48917",
    "sg:province":"MI",
    "sg:tags":[
        "consultant",
        "planning",
        "financial"
    ],
    "wof:name":"American Express Financial Adv",
    "wof:placetype":"venue"
},
  "geometry": {"coordinates":[-84.64237300000001,42.729285],"type":"Point"}
}