{
  "type": "Feature",
  "properties": {
    "iso:country":"US",
    "sg:address":"12368 W Corunna Rd",
    "sg:city":"Lennon",
    "sg:classifiers":[
        {
            "category":"Shopping",
            "subcategory":"Discount & Variety Stores",
            "type":"Retail Goods"
        }
    ],
    "sg:phone":"+1 810 621 4505",
    "sg:postcode":"48449",
    "sg:province":"MI",
    "sg:tags":[
        "merchandise",
        "general"
    ],
    "wof:name":"Eagle Sales",
    "wof:placetype":"venue"
},
  "geometry": {"coordinates":[-83.919985,43.00031],"type":"Point"}
}