{
  "type": "Feature",
  "properties": {
    "iso:country":"US",
    "sg:address":"48181 Ryan Rd",
    "sg:city":"Shelby Twp",
    "sg:classifiers":[
        {
            "category":"Manufacturing",
            "subcategory":"Electronics",
            "type":"Manufacturing & Wholesale Goods"
        }
    ],
    "sg:phone":"+1 810 695 7516",
    "sg:postcode":"48317",
    "sg:province":"MI",
    "wof:name":"Action Traffic Maintenance",
    "wof:placetype":"venue"
},
  "geometry": {"coordinates":[-83.073081,42.650434],"type":"Point"}
}