{
  "type": "Feature",
  "properties": {
    "iso:country":"US",
    "sg:address":"439 Butler St",
    "sg:city":"Saugatuck",
    "sg:classifiers":[
        {
            "category":"Home & Garden",
            "subcategory":"Hardware",
            "type":"Retail Goods"
        }
    ],
    "sg:phone":"+1 269 857 7501",
    "sg:postcode":"49453",
    "sg:province":"MI",
    "wof:name":"Wilkins Hardware Co",
    "wof:placetype":"venue"
},
  "geometry": {"coordinates":[-86.20406199999999,42.658049],"type":"Point"}
}