{
  "type": "Feature",
  "properties": {
    "iso:country":"US",
    "sg:address":"820 Monroe Ave NW",
    "sg:city":"Grand Rapids",
    "sg:classifiers":[
        {
            "category":"Wholesale",
            "subcategory":"Books, Periodicals, & Newspapers",
            "type":"Manufacturing & Wholesale Goods"
        }
    ],
    "sg:phone":"+1 616 458 2121",
    "sg:postcode":"49503",
    "sg:province":"MI",
    "sg:tags":[
        "magazine"
    ],
    "wof:name":"Women's Lifestyle Inc",
    "wof:placetype":"venue"
},
  "geometry": {"coordinates":[-85.672439,42.977886],"type":"Point"}
}