{
  "type": "Feature",
  "properties": {
    "iso:country":"US",
    "sg:address":"19401 W McNichols Rd",
    "sg:city":"Detroit",
    "sg:classifiers":[
        {
            "category":"Social Services",
            "type":"Services"
        }
    ],
    "sg:phone":"+1 313 537 8202",
    "sg:postcode":"48219",
    "sg:province":"MI",
    "wof:name":"Greater Detroit Michigan Chapt",
    "wof:placetype":"venue"
},
  "geometry": {"coordinates":[-83.233904,42.415256],"type":"Point"}
}