{
  "type": "Feature",
  "properties": {
    "iso:country":"US",
    "sg:address":"36100 Harper Ave",
    "sg:city":"Clinton Township",
    "sg:classifiers":[
        {
            "category":"Building & Trades",
            "subcategory":"Electrical",
            "type":"Services"
        }
    ],
    "sg:phone":"+1 586 463 9266",
    "sg:postcode":"48035",
    "sg:province":"MI",
    "sg:tags":[
        "electrician"
    ],
    "sg:website":"www.clean-air-specialties.com",
    "wof:name":"Multi-Phase Contracting",
    "wof:placetype":"venue"
},
  "geometry": {"coordinates":[-82.870544,42.563186],"type":"Point"}
}