{
  "type": "Feature",
  "properties": {
    "iso:country":"US",
    "sg:address":"19251 Mack Ave Ste 220",
    "sg:city":"Grosse Pointe Woods",
    "sg:classifiers":[
        {
            "category":"Health Services",
            "subcategory":"Dentist",
            "type":"Services"
        }
    ],
    "sg:phone":"+1 313 343 8790",
    "sg:postcode":"48236",
    "sg:province":"MI",
    "wof:name":"Harvey Dawn DDS",
    "wof:placetype":"venue"
},
  "geometry": {"coordinates":[-82.910461,42.419974],"type":"Point"}
}