{
  "type": "Feature",
  "properties": {
    "iso:country":"US",
    "sg:address":"118 N 22nd St",
    "sg:city":"Escanaba",
    "sg:classifiers":[
        {
            "category":"Real Estate",
            "subcategory":"Real Estate Agent",
            "type":"Services"
        }
    ],
    "sg:phone":"+1 906 786 5030",
    "sg:postcode":"49829",
    "sg:province":"MI",
    "sg:website":"www.premierrealestate.org",
    "wof:name":"Premier Real Estate Inc",
    "wof:placetype":"venue"
},
  "geometry": {"coordinates":[-87.078142,45.746639],"type":"Point"}
}