{
  "type": "Feature",
  "properties": {
    "iso:country":"US",
    "sg:address":"1435 N Oakland Blvd",
    "sg:city":"Waterford",
    "sg:classifiers":[
        {
            "category":"Social Services",
            "subcategory":"Job Training",
            "type":"Services"
        }
    ],
    "sg:phone":"+1 248 666 2720",
    "sg:postcode":"48327",
    "sg:province":"MI",
    "sg:tags":[
        "rehabilitation"
    ],
    "sg:website":"www.communityprograms.com",
    "wof:name":"Community Programs Inc",
    "wof:placetype":"venue"
},
  "geometry": {"coordinates":[-83.43245899999999,42.65492],"type":"Point"}
}