{
  "type": "Feature",
  "properties": {
    "iso:country":"US",
    "sg:address":"38455 Albert Blvd",
    "sg:city":"Clinton Twp",
    "sg:classifiers":[
        {
            "category":"Building & Trades",
            "subcategory":"Construction",
            "type":"Services"
        }
    ],
    "sg:phone":"+1 586 350 6071",
    "sg:postcode":"48036",
    "sg:province":"MI",
    "sg:tags":[
        "painter"
    ],
    "wof:name":"Scott Frank Painting",
    "wof:placetype":"venue"
},
  "geometry": {"coordinates":[-82.86448799999999,42.58376],"type":"Point"}
}