{
  "type": "Feature",
  "properties": {
    "iso:country":"US",
    "sg:address":"4390 Mushbach Rd",
    "sg:city":"Chelsea",
    "sg:classifiers":[
        {
            "category":"Farming",
            "subcategory":"Farm",
            "type":"Manufacturing & Wholesale Goods"
        }
    ],
    "sg:phone":"+1 734 475 7662",
    "sg:postcode":"48118",
    "sg:province":"MI",
    "sg:tags":[
        "crop",
        "general"
    ],
    "wof:name":"Coyote Ridge Farms",
    "wof:placetype":"venue"
},
  "geometry": {"coordinates":[-84.11413400000001,42.296188],"type":"Point"}
}