{
  "type": "Feature",
  "properties": {
    "iso:country":"US",
    "sg:address":"15500 Lundy Pkwy",
    "sg:city":"Dearborn",
    "sg:classifiers":[
        {
            "category":"Professional",
            "subcategory":"Computer Services",
            "type":"Services"
        }
    ],
    "sg:phone":"+1 313 583 5192",
    "sg:postcode":"48126",
    "sg:province":"MI",
    "sg:tags":[
        "design",
        "elect",
        "system",
        "related"
    ],
    "wof:name":"HP",
    "wof:placetype":"venue"
},
  "geometry": {"coordinates":[-83.20333599999999,42.332153],"type":"Point"}
}