{
  "type": "Feature",
  "properties": {
    "iso:country":"US",
    "sg:address":"6054 Kalamazoo Ave SE",
    "sg:city":"Grand Rapids",
    "sg:classifiers":[
        {
            "category":"Retail",
            "subcategory":"Laundry & Dry Cleaning",
            "type":"Services"
        }
    ],
    "sg:phone":"+1 616 554 7263",
    "sg:postcode":"49508",
    "sg:province":"MI",
    "sg:tags":[
        "drycleaning",
        "plant",
        "cleaners"
    ],
    "wof:name":"Peachtree Cleaners",
    "wof:placetype":"venue"
},
  "geometry": {"coordinates":[-85.62476100000001,42.850831],"type":"Point"}
}