{
  "type": "Feature",
  "properties": {
    "iso:country":"US",
    "sg:address":"2413 Burdette",
    "sg:city":"Ferndale",
    "sg:classifiers":[
        {
            "category":"Personal",
            "subcategory":"Massage",
            "type":"Services"
        }
    ],
    "sg:phone":"+1 248 229 7812",
    "sg:postcode":"48220",
    "sg:province":"MI",
    "sg:website":"soothingrhythm.massagetherapy.com",
    "wof:name":"Soothing Rhythm Massage",
    "wof:placetype":"venue"
},
  "geometry": {"coordinates":[-83.126138,42.465227],"type":"Point"}
}