{
  "type": "Feature",
  "properties": {
    "iso:country":"US",
    "sg:address":"1746 Sheffield Dr",
    "sg:city":"Ypsilanti",
    "sg:classifiers":[
        {
            "category":"Wholesale",
            "subcategory":"Vending Machines",
            "type":"Manufacturing & Wholesale Goods"
        }
    ],
    "sg:phone":"+1 734 485 7136",
    "sg:postcode":"48198",
    "sg:province":"MI",
    "sg:tags":[
        "operator"
    ],
    "wof:name":"M T Vending",
    "wof:placetype":"venue"
},
  "geometry": {"coordinates":[-83.594229,42.266239],"type":"Point"}
}