{
  "type": "Feature",
  "properties": {
    "iso:country":"US",
    "sg:address":"42841 Lombardy Dr",
    "sg:city":"Canton",
    "sg:classifiers":[
        {
            "category":"Organizations",
            "subcategory":"Community Association",
            "type":"Services"
        }
    ],
    "sg:phone":"+1 734 453 3257",
    "sg:postcode":"48187",
    "sg:province":"MI",
    "wof:name":"Ancient Order of Hibernians",
    "wof:placetype":"venue"
},
  "geometry": {"coordinates":[-83.466949,42.341866],"type":"Point"}
}