{
  "type": "Feature",
  "properties": {
    "iso:country":"US",
    "sg:address":"1328 S Rochester Rd",
    "sg:city":"Rochester Hills",
    "sg:classifiers":[
        {
            "category":"Shopping",
            "subcategory":"Gifts & Souvenirs",
            "type":"Retail Goods"
        }
    ],
    "sg:phone":"+1 248 650 1700",
    "sg:postcode":"48307",
    "sg:province":"MI",
    "sg:tags":[
        "party",
        "supply"
    ],
    "wof:name":"Party City",
    "wof:placetype":"venue"
},
  "geometry": {"coordinates":[-83.13324299999999,42.666159],"type":"Point"}
}