{
  "type": "Feature",
  "properties": {
    "iso:country":"US",
    "sg:address":"245 Glenbrooke St",
    "sg:city":"Waterford",
    "sg:classifiers":[
        {
            "category":"Organizations",
            "subcategory":"Religious Organization",
            "type":"Services"
        }
    ],
    "sg:phone":"+1 248 683 1284",
    "sg:postcode":"48327",
    "sg:province":"MI",
    "wof:name":"God Efficient Care",
    "wof:placetype":"venue"
},
  "geometry": {"coordinates":[-83.402214,42.650879],"type":"Point"}
}