{
  "type": "Feature",
  "properties": {
    "iso:country":"US",
    "sg:address":"3922 Cherry Hills Pl",
    "sg:city":"Traverse City",
    "sg:classifiers":[
        {
            "category":"Home & Garden",
            "subcategory":"Home Furnishings",
            "type":"Retail Goods"
        }
    ],
    "sg:phone":"+1 231 946 5787",
    "sg:postcode":"49684",
    "sg:province":"MI",
    "wof:name":"Northern Needles",
    "wof:placetype":"venue"
},
  "geometry": {"coordinates":[-85.654946,44.740644],"type":"Point"}
}