{
  "type": "Feature",
  "properties": {
    "iso:country":"US",
    "sg:address":"5084 Tyler Dr",
    "sg:city":"Troy",
    "sg:classifiers":[
        {
            "category":"Shopping",
            "subcategory":"Computers & Home Electronics",
            "type":"Retail Goods"
        }
    ],
    "sg:phone":"+1 248 524 2942",
    "sg:postcode":"48085",
    "sg:province":"MI",
    "sg:tags":[
        "equipment",
        "dealer"
    ],
    "wof:name":"Computer Exchange Intl Inc",
    "wof:placetype":"venue"
},
  "geometry": {"coordinates":[-83.119615,42.593925],"type":"Point"}
}