{
  "type": "Feature",
  "properties": {
    "iso:country":"US",
    "sg:address":"17100 W 12 Mile Rd",
    "sg:city":"Southfield",
    "sg:classifiers":[
        {
            "category":"Professional",
            "subcategory":"Research",
            "type":"Services"
        }
    ],
    "sg:phone":"+1 248 443 2156",
    "sg:postcode":"48076",
    "sg:province":"MI",
    "sg:tags":[
        "laboratory"
    ],
    "wof:name":"Our Lab",
    "wof:placetype":"venue"
},
  "geometry": {"coordinates":[-83.21566799999999,42.502725],"type":"Point"}
}