{
  "type": "Feature",
  "properties": {
    "iso:country":"US",
    "sg:address":"18900 Greenfield Rd",
    "sg:city":"Detroit",
    "sg:classifiers":[
        {
            "category":"Autos & Motor Vehicles",
            "subcategory":"Fuel & Gas Station",
            "type":"Retail Goods"
        }
    ],
    "sg:phone":"+1 313 270 4910",
    "sg:postcode":"48235",
    "sg:province":"MI",
    "wof:name":"A & M Petro",
    "wof:placetype":"venue"
},
  "geometry": {"coordinates":[-83.199699,42.429401],"type":"Point"}
}