{
  "type": "Feature",
  "properties": {
    "iso:country":"US",
    "sg:address":"29940 Orchard Lake Rd",
    "sg:city":"Farmington Hills",
    "sg:classifiers":[
        {
            "category":"Professional",
            "subcategory":"Business Services",
            "type":"Services"
        }
    ],
    "sg:phone":"+1 248 855 5557",
    "sg:postcode":"48334",
    "sg:province":"MI",
    "wof:name":"Business Group LLC",
    "wof:placetype":"venue"
},
  "geometry": {"coordinates":[-83.35954,42.518128],"type":"Point"}
}