{
  "type": "Feature",
  "properties": {
    "iso:country":"US",
    "sg:address":"1307 Country Ln",
    "sg:city":"Dewitt",
    "sg:classifiers":[
        {
            "category":"Professional",
            "type":"Services"
        }
    ],
    "sg:phone":"+1 517 668 9200",
    "sg:postcode":"48820",
    "sg:province":"MI",
    "sg:tags":[
        "establishment"
    ],
    "wof:name":"MTO & Assoc",
    "wof:placetype":"venue"
},
  "geometry": {"coordinates":[-84.56586799999999,42.827908],"type":"Point"}
}