{
  "type": "Feature",
  "properties": {
    "iso:country":"US",
    "sg:address":"12250 Belden Ct",
    "sg:city":"Livonia",
    "sg:classifiers":[
        {
            "category":"Manufacturing",
            "subcategory":"Apparel",
            "type":"Manufacturing & Wholesale Goods"
        }
    ],
    "sg:phone":"+1 734 425 3360",
    "sg:postcode":"48150",
    "sg:province":"MI",
    "sg:tags":[
        "commercial",
        "desi"
    ],
    "wof:name":"Flying Colors",
    "wof:placetype":"venue"
},
  "geometry": {"coordinates":[-83.389264,42.37207],"type":"Point"}
}