{
  "type": "Feature",
  "properties": {
    "iso:country":"US",
    "sg:address":"62539 N M 66",
    "sg:city":"Sturgis",
    "sg:phone":"+1 269 651 7396",
    "sg:postcode":"49091",
    "sg:province":"MI",
    "sg:tags":[
        "farm",
        "corn"
    ],
    "wof:name":"Yoder Lowayne",
    "wof:placetype":"venue"
},
  "geometry": {"coordinates":[-85.41868100000001,41.816006],"type":"Point"}
}