{
  "type": "Feature",
  "properties": {
    "iso:country":"US",
    "sg:address":"715 S James St",
    "sg:city":"Ludington",
    "sg:classifiers":[
        {
            "category":"Manufacturing",
            "subcategory":"Furniture",
            "type":"Manufacturing & Wholesale Goods"
        }
    ],
    "sg:phone":"+1 231 843 2430",
    "sg:postcode":"49431",
    "sg:province":"MI",
    "sg:tags":[
        "upholstered",
        "wood"
    ],
    "wof:name":"Brill Manufacturing Co",
    "wof:placetype":"venue"
},
  "geometry": {"coordinates":[-86.44765200000001,43.949334],"type":"Point"}
}