{
  "type": "Feature",
  "properties": {
    "iso:country":"US",
    "sg:address":"1918 N Dort Hwy",
    "sg:city":"Flint",
    "sg:classifiers":[
        {
            "category":"Food & Beverages",
            "subcategory":"Groceries & Convenience Stores",
            "type":"Retail Goods"
        }
    ],
    "sg:phone":"+1 810 238 1972",
    "sg:postcode":"48506",
    "sg:province":"MI",
    "sg:tags":[
        "grocer"
    ],
    "sg:website":"www.save-a-lot.com",
    "wof:name":"Save-A-Lot",
    "wof:placetype":"venue"
},
  "geometry": {"coordinates":[-83.655197,43.0336],"type":"Point"}
}