{
  "type": "Feature",
  "properties": {
    "iso:country":"US",
    "sg:address":"1101 E Hunt St",
    "sg:city":"Adrian",
    "sg:classifiers":[
        {
            "category":"Building & Trades",
            "subcategory":"Cleaning & Sanitation",
            "type":"Services"
        }
    ],
    "sg:phone":"+1 517 265 2689",
    "sg:postcode":"49221",
    "sg:province":"MI",
    "sg:tags":[
        "maintenance"
    ],
    "wof:name":"Sns Cleaning Service",
    "wof:placetype":"venue"
},
  "geometry": {"coordinates":[-84.020601,41.899448],"type":"Point"}
}