{
  "type": "Feature",
  "properties": {
    "iso:country":"US",
    "sg:address":"27800 Franklin Rd",
    "sg:city":"Southfield",
    "sg:classifiers":[
        {
            "category":"Communications",
            "subcategory":"Television Station",
            "type":"Services"
        }
    ],
    "sg:phone":"+1 248 350 0102",
    "sg:postcode":"48034",
    "sg:province":"MI",
    "sg:tags":[
        "satellite",
        "cable"
    ],
    "wof:name":"Comcast",
    "wof:placetype":"venue"
},
  "geometry": {"coordinates":[-83.296773,42.491159],"type":"Point"}
}