{
  "type": "Feature",
  "properties": {
    "iso:country":"US",
    "sg:address":"24882 Wilmot Ave",
    "sg:city":"Eastpointe",
    "sg:classifiers":[
        {
            "category":"Building & Trades",
            "subcategory":"Construction",
            "type":"Services"
        }
    ],
    "sg:phone":"+1 586 447 0690",
    "sg:postcode":"48021",
    "sg:province":"MI",
    "sg:tags":[
        "painter"
    ],
    "wof:name":"Brushworks Painting",
    "wof:placetype":"venue"
},
  "geometry": {"coordinates":[-82.93589799999999,42.478802],"type":"Point"}
}