{
  "type": "Feature",
  "properties": {
    "iso:country":"US",
    "sg:address":"2981 Armstrong Dr",
    "sg:city":"Lake Orion",
    "sg:classifiers":[
        {
            "category":"Building & Trades",
            "subcategory":"Construction",
            "type":"Services"
        }
    ],
    "sg:phone":"+1 248 391 4781",
    "sg:postcode":"48360",
    "sg:province":"MI",
    "sg:tags":[
        "house"
    ],
    "wof:name":"Game Day Landscape & Const",
    "wof:placetype":"venue"
},
  "geometry": {"coordinates":[-83.29899899999999,42.736833],"type":"Point"}
}