{
  "type": "Feature",
  "properties": {
    "iso:country":"US",
    "sg:address":"3235 W Thompson Rd",
    "sg:city":"Fenton",
    "sg:classifiers":[
        {
            "category":"Restaurant",
            "type":"Food & Drink"
        }
    ],
    "sg:phone":"+1 810 629 5554",
    "sg:postcode":"48430",
    "sg:province":"MI",
    "wof:name":"LA Marina Family Restaurant",
    "wof:placetype":"venue"
},
  "geometry": {"coordinates":[-83.741378,42.862948],"type":"Point"}
}