{
  "type": "Feature",
  "properties": {
    "iso:country":"US",
    "sg:address":"3250 W Big Beaver Rd",
    "sg:city":"Troy",
    "sg:classifiers":[
        {
            "category":"Wholesale",
            "subcategory":"Stationery",
            "type":"Manufacturing & Wholesale Goods"
        }
    ],
    "sg:phone":"+1 248 357 7100",
    "sg:postcode":"48084",
    "sg:province":"MI",
    "sg:tags":[
        "business",
        "form",
        "system"
    ],
    "wof:name":"Wallace Computer Svc Inc",
    "wof:placetype":"venue"
},
  "geometry": {"coordinates":[-83.187832,42.561277],"type":"Point"}
}