{
  "type": "Feature",
  "properties": {
    "iso:country":"US",
    "sg:address":"12990 Bradshaw St NE",
    "sg:city":"Gowen",
    "sg:classifiers":[
        {
            "category":"Sports & Exercise",
            "subcategory":"Golf",
            "type":"Entertainment"
        }
    ],
    "sg:phone":"+1 616 984 9916",
    "sg:postcode":"49326",
    "sg:province":"MI",
    "sg:tags":[
        "course"
    ],
    "sg:website":"www.golfbowenlake.com",
    "wof:name":"Bowen Lake Links",
    "wof:placetype":"venue"
},
  "geometry": {"coordinates":[-85.345551,43.239034],"type":"Point"}
}