{
  "type": "Feature",
  "properties": {
    "iso:country":"US",
    "sg:address":"4612 Ivanrest Ave SW",
    "sg:city":"Grandville",
    "sg:classifiers":[
        {
            "category":"Farming",
            "subcategory":"Nursery",
            "type":"Manufacturing & Wholesale Goods"
        }
    ],
    "sg:phone":"+1 616 534 6668",
    "sg:postcode":"49418",
    "sg:province":"MI",
    "sg:tags":[
        "greenhouse"
    ],
    "wof:name":"Westview Greenhouse",
    "wof:placetype":"venue"
},
  "geometry": {"coordinates":[-85.743161,42.88025],"type":"Point"}
}