{
  "type": "Feature",
  "properties": {
    "iso:country":"US",
    "sg:address":"606 Desoto Ave",
    "sg:city":"Ypsilanti",
    "sg:classifiers":[
        {
            "category":"Building & Trades",
            "subcategory":"Cleaning & Sanitation",
            "type":"Services"
        }
    ],
    "sg:phone":"+1 734 340 4157",
    "sg:postcode":"48198",
    "sg:province":"MI",
    "sg:tags":[
        "maintenance"
    ],
    "wof:name":"Clinton & Diane Cleaning",
    "wof:placetype":"venue"
},
  "geometry": {"coordinates":[-83.566704,42.236428],"type":"Point"}
}