{
  "type": "Feature",
  "properties": {
    "iso:country":"US",
    "sg:address":"321 S Telegraph Rd",
    "sg:city":"Monroe",
    "sg:classifiers":[
        {
            "category":"Education",
            "subcategory":"Vocational School",
            "type":"Public Place"
        }
    ],
    "sg:phone":"+1 734 241 3777",
    "sg:postcode":"48161",
    "sg:province":"MI",
    "sg:tags":[
        "secretarial"
    ],
    "wof:name":"H & R Block Tax Svc",
    "wof:placetype":"venue"
},
  "geometry": {"coordinates":[-83.41708199999999,41.918592],"type":"Point"}
}