{
  "type": "Feature",
  "properties": {
    "iso:country":"US",
    "sg:address":"2987 Hunters Pl",
    "sg:city":"Kalamazoo",
    "sg:classifiers":[
        {
            "category":"Shopping",
            "subcategory":"Jewelry",
            "type":"Retail Goods"
        }
    ],
    "sg:phone":"+1 269 345 8416",
    "sg:postcode":"49048",
    "sg:province":"MI",
    "sg:tags":[
        "jeweler"
    ],
    "wof:name":"Advincula Enterprises",
    "wof:placetype":"venue"
},
  "geometry": {"coordinates":[-85.498414,42.315855],"type":"Point"}
}