{
  "type": "Feature",
  "properties": {
    "iso:country":"US",
    "sg:address":"315 Chippewa St",
    "sg:city":"Clawson",
    "sg:classifiers":[
        {
            "category":"Building & Trades",
            "subcategory":"Construction",
            "type":"Services"
        }
    ],
    "sg:phone":"+1 248 879 0330",
    "sg:postcode":"48017",
    "sg:province":"MI",
    "sg:tags":[
        "house"
    ],
    "wof:name":"John Marson Ceramic Tile Svc",
    "wof:placetype":"venue"
},
  "geometry": {"coordinates":[-83.151768,42.527009],"type":"Point"}
}