{
  "type": "Feature",
  "properties": {
    "iso:country":"US",
    "sg:address":"115 E Grand River Ave",
    "sg:city":"Lansing",
    "sg:classifiers":[
        {
            "category":"Professional",
            "subcategory":"Art Services",
            "type":"Services"
        }
    ],
    "sg:phone":"+1 517 267 3540",
    "sg:postcode":"48906",
    "sg:province":"MI",
    "sg:tags":[
        "graphic",
        "designer"
    ],
    "wof:name":"Image Creative Group",
    "wof:placetype":"venue"
},
  "geometry": {"coordinates":[-84.55105399999999,42.747534],"type":"Point"}
}