{
  "type": "Feature",
  "properties": {
    "iso:country":"US",
    "sg:address":"34820 Harper Ave",
    "sg:city":"Clinton Township",
    "sg:classifiers":[
        {
            "category":"Insurance",
            "subcategory":"Health Insurance",
            "type":"Services"
        }
    ],
    "sg:phone":"+1 586 792 6355",
    "sg:postcode":"48035",
    "sg:province":"MI",
    "sg:tags":[
        "ac",
        "plan"
    ],
    "wof:name":"Cambrdge Integrated Svcs Group",
    "wof:placetype":"venue"
},
  "geometry": {"coordinates":[-82.870619,42.554194],"type":"Point"}
}