{
  "type": "Feature",
  "properties": {
    "iso:country":"US",
    "sg:address":"830 Shoregrove Cir",
    "sg:city":"Auburn Hills",
    "sg:classifiers":[
        {
            "category":"Professional",
            "subcategory":"Management & Consulting",
            "type":"Services"
        }
    ],
    "sg:phone":"+1 248 370 9121",
    "sg:postcode":"48326",
    "sg:province":"MI",
    "sg:tags":[
        "business"
    ],
    "wof:name":"Creative Otsrcing Partnerships",
    "wof:placetype":"venue"
},
  "geometry": {"coordinates":[-83.324265,42.704386],"type":"Point"}
}