{
  "type": "Feature",
  "properties": {
    "iso:country":"US",
    "sg:address":"808 S Old Woodward Ave",
    "sg:city":"Birmingham",
    "sg:classifiers":[
        {
            "category":"Home & Garden",
            "subcategory":"Carpets & Floor Coverings",
            "type":"Retail Goods"
        }
    ],
    "sg:phone":"+1 248 644 7750",
    "sg:postcode":"48009",
    "sg:province":"MI",
    "sg:tags":[
        "cleaning"
    ],
    "wof:name":"Nigosians Oriental Rug Co",
    "wof:placetype":"venue"
},
  "geometry": {"coordinates":[-83.208674,42.540936],"type":"Point"}
}