{
  "type": "Feature",
  "properties": {
    "iso:country":"US",
    "sg:address":"12037 N Saginaw Rd",
    "sg:city":"Clio",
    "sg:classifiers":[
        {
            "category":"Retail",
            "subcategory":"Auto Repair",
            "type":"Services"
        }
    ],
    "sg:phone":"+1 810 686 5454",
    "sg:postcode":"48420",
    "sg:province":"MI",
    "sg:tags":[
        "automotive"
    ],
    "wof:name":"Clio Towing Inc",
    "wof:placetype":"venue"
},
  "geometry": {"coordinates":[-83.715816,43.178737],"type":"Point"}
}