{
  "type": "Feature",
  "properties": {
    "iso:country":"US",
    "sg:address":"244 N Rose St",
    "sg:city":"Kalamazoo",
    "sg:classifiers":[
        {
            "category":"Professional",
            "subcategory":"Management & Consulting",
            "type":"Services"
        }
    ],
    "sg:phone":"+1 269 552 3221",
    "sg:postcode":"49007",
    "sg:province":"MI",
    "wof:name":"Sdm & G",
    "wof:placetype":"venue"
},
  "geometry": {"coordinates":[-85.58474,42.293112],"type":"Point"}
}