{
  "type": "Feature",
  "properties": {
    "iso:country":"US",
    "sg:address":"500 W 8 Mile Rd",
    "sg:city":"Ferndale",
    "sg:classifiers":[
        {
            "category":"Retail",
            "subcategory":"Auto Repair",
            "type":"Services"
        }
    ],
    "sg:phone":"+1 248 545 4002",
    "sg:postcode":"48220",
    "sg:province":"MI",
    "sg:tags":[
        "repairing",
        "automobile"
    ],
    "wof:name":"Finzi Auto Repair",
    "wof:placetype":"venue"
},
  "geometry": {"coordinates":[-83.13176,42.446557],"type":"Point"}
}