{
  "type": "Feature",
  "properties": {
    "iso:country":"US",
    "sg:address":"310 S Bradley Rd",
    "sg:city":"Mount Pleasant",
    "sg:classifiers":[
        {
            "category":"Real Estate",
            "subcategory":"Real Estate Operator",
            "type":"Services"
        }
    ],
    "sg:phone":"+1 989 773 7274",
    "sg:postcode":"48858",
    "sg:province":"MI",
    "sg:tags":[
        "building",
        "apartment"
    ],
    "wof:name":"Immanuel Village",
    "wof:placetype":"venue"
},
  "geometry": {"coordinates":[-84.797847,43.601918],"type":"Point"}
}