{
  "type": "Feature",
  "properties": {
    "iso:country":"US",
    "sg:address":"3664 Sweeter Rd",
    "sg:city":"Twin Lake",
    "sg:classifiers":[
        {
            "category":"Retail",
            "subcategory":"Repair Shop",
            "type":"Services"
        }
    ],
    "sg:phone":"+1 231 744 5170",
    "sg:postcode":"49457",
    "sg:province":"MI",
    "wof:name":"PH Repair",
    "wof:placetype":"venue"
},
  "geometry": {"coordinates":[-86.153881,43.331097],"type":"Point"}
}