{
  "type": "Feature",
  "properties": {
    "iso:country":"US",
    "sg:address":"5883 S Warner Ave",
    "sg:city":"Fremont",
    "sg:classifiers":[
        {
            "category":"Restaurant",
            "type":"Food & Drink"
        }
    ],
    "sg:phone":"+1 231 924 5500",
    "sg:postcode":"49412",
    "sg:province":"MI",
    "wof:name":"Seasons Restaurant",
    "wof:placetype":"venue"
},
  "geometry": {"coordinates":[-85.94001900000001,43.447409],"type":"Point"}
}