{
  "type": "Feature",
  "properties": {
    "iso:country":"US",
    "sg:address":"2621 Mallery St",
    "sg:city":"Flint",
    "sg:classifiers":[
        {
            "category":"Professional",
            "subcategory":"Business Services",
            "type":"Services"
        }
    ],
    "sg:phone":"+1 810 233 0762",
    "sg:postcode":"48504",
    "sg:province":"MI",
    "wof:name":"From Ground Up",
    "wof:placetype":"venue"
},
  "geometry": {"coordinates":[-83.72432999999999,43.031257],"type":"Point"}
}