{
  "type": "Feature",
  "properties": {
    "iso:country":"US",
    "sg:address":"70164 Carolyn Ave",
    "sg:city":"Sturgis",
    "sg:classifiers":[
        {
            "category":"Organizations",
            "subcategory":"Religious Organization",
            "type":"Services"
        }
    ],
    "sg:phone":"+1 269 651 9561",
    "sg:postcode":"49091",
    "sg:province":"MI",
    "wof:name":"Gary Bond Ministries",
    "wof:placetype":"venue"
},
  "geometry": {"coordinates":[-85.44356999999999,41.77896],"type":"Point"}
}