{
  "type": "Feature",
  "properties": {
    "iso:country":"US",
    "sg:address":"13427 15 Mile Rd",
    "sg:city":"Sterling Heights",
    "sg:classifiers":[
        {
            "category":"Banks & Credit Unions",
            "subcategory":"Bank",
            "type":"Services"
        }
    ],
    "sg:phone":"+1 586 939 5447",
    "sg:postcode":"48312",
    "sg:province":"MI",
    "wof:name":"Flagstar Bank",
    "wof:placetype":"venue"
},
  "geometry": {"coordinates":[-82.989502,42.552299],"type":"Point"}
}