{
  "type": "Feature",
  "properties": {
    "iso:country":"US",
    "sg:address":"2899 E 1st St",
    "sg:city":"Custer",
    "sg:classifiers":[
        {
            "category":"Retail",
            "subcategory":"Repair Shop",
            "type":"Services"
        }
    ],
    "sg:phone":"+1 231 757 2665",
    "sg:postcode":"49405",
    "sg:province":"MI",
    "sg:tags":[
        "welding"
    ],
    "wof:name":"Wolf Welding",
    "wof:placetype":"venue"
},
  "geometry": {"coordinates":[-86.205834,43.94703],"type":"Point"}
}