{
  "type": "Feature",
  "properties": {
    "iso:country":"US",
    "sg:address":"1397 Piedmont Dr",
    "sg:city":"Troy",
    "sg:classifiers":[
        {
            "category":"Manufacturing",
            "subcategory":"Printing",
            "type":"Manufacturing & Wholesale Goods"
        }
    ],
    "sg:phone":"+1 248 689 0227",
    "sg:postcode":"48083",
    "sg:province":"MI",
    "sg:tags":[
        "publisher"
    ],
    "wof:name":"Wall Street Journal",
    "wof:placetype":"venue"
},
  "geometry": {"coordinates":[-83.12602,42.556535],"type":"Point"}
}