{
  "type": "Feature",
  "properties": {
    "iso:country":"US",
    "sg:address":"3757 Lansing Ave",
    "sg:city":"Jackson",
    "sg:classifiers":[
        {
            "category":"Education",
            "subcategory":"School",
            "type":"Public Place"
        }
    ],
    "sg:phone":"+1 517 789 6159",
    "sg:postcode":"49202",
    "sg:province":"MI",
    "wof:name":"Northwest Elementary School",
    "wof:placetype":"venue"
},
  "geometry": {"coordinates":[-84.41353700000001,42.294588],"type":"Point"}
}