{
  "type": "Feature",
  "properties": {
    "iso:country":"US",
    "sg:address":"42860 Mound Rd",
    "sg:city":"Sterling Heights",
    "sg:classifiers":[
        {
            "category":"Manufacturing",
            "subcategory":"Tools & Machinery",
            "type":"Manufacturing & Wholesale Goods"
        }
    ],
    "sg:phone":"+1 586 731 7632",
    "sg:postcode":"48314",
    "sg:province":"MI",
    "sg:tags":[
        "machine",
        "shop"
    ],
    "wof:name":"Titan Tool",
    "wof:placetype":"venue"
},
  "geometry": {"coordinates":[-83.051033,42.608235],"type":"Point"}
}