{
  "type": "Feature",
  "properties": {
    "iso:country":"US",
    "sg:address":"737 E Cork St",
    "sg:city":"Kalamazoo",
    "sg:classifiers":[
        {
            "category":"Retail",
            "subcategory":"Car Wash",
            "type":"Services"
        }
    ],
    "sg:phone":"+1 269 345 9206",
    "sg:postcode":"49001",
    "sg:province":"MI",
    "sg:tags":[
        "carwash"
    ],
    "wof:name":"Specialty Car Wash",
    "wof:placetype":"venue"
},
  "geometry": {"coordinates":[-85.572174,42.259655],"type":"Point"}
}