{
  "type": "Feature",
  "properties": {
    "iso:country":"US",
    "sg:address":"1114 W Pasadena Ave",
    "sg:city":"Flint",
    "sg:classifiers":[
        {
            "category":"Retail",
            "subcategory":"Car Wash",
            "type":"Services"
        }
    ],
    "sg:phone":"+1 800 219 3219",
    "sg:postcode":"48504",
    "sg:province":"MI",
    "sg:tags":[
        "carwash"
    ],
    "wof:name":"Family Auto Care Center",
    "wof:placetype":"venue"
},
  "geometry": {"coordinates":[-83.71880299999999,43.046398],"type":"Point"}
}