{
  "type": "Feature",
  "properties": {
    "iso:country":"US",
    "sg:address":"1502 Barlow St",
    "sg:city":"Traverse City",
    "sg:classifiers":[
        {
            "category":"Real Estate",
            "subcategory":"Real Estate Agent",
            "type":"Services"
        }
    ],
    "sg:phone":"+1 231 929 1745",
    "sg:postcode":"49686",
    "sg:province":"MI",
    "wof:name":"Manitou Properties",
    "wof:placetype":"venue"
},
  "geometry": {"coordinates":[-85.605588,44.742232],"type":"Point"}
}