{
  "type": "Feature",
  "properties": {
    "iso:country":"US",
    "sg:address":"17719 Red Pine Dr",
    "sg:city":"Kent City",
    "sg:classifiers":[
        {
            "category":"Professional",
            "subcategory":"Business Services",
            "type":"Services"
        }
    ],
    "sg:phone":"+1 616 675 4609",
    "sg:postcode":"49330",
    "sg:province":"MI",
    "wof:name":"Outside Lines Design Co",
    "wof:placetype":"venue"
},
  "geometry": {"coordinates":[-85.68072100000001,43.292483],"type":"Point"}
}