{
  "type": "Feature",
  "properties": {
    "iso:country":"US",
    "sg:address":"3580 W Vassar Rd",
    "sg:city":"Reese",
    "sg:classifiers":[
        {
            "category":"Retail",
            "subcategory":"Auto Repair",
            "type":"Services"
        }
    ],
    "sg:phone":"+1 989 868 9878",
    "sg:postcode":"48757",
    "sg:province":"MI",
    "sg:tags":[
        "body"
    ],
    "wof:name":"Dietzel Auto Body",
    "wof:placetype":"venue"
},
  "geometry": {"coordinates":[-83.759556,43.459539],"type":"Point"}
}