{
  "type": "Feature",
  "properties": {
    "iso:country":"US",
    "sg:address":"844 N Wayne Rd",
    "sg:city":"Westland",
    "sg:classifiers":[
        {
            "category":"Bakery",
            "type":"Food & Drink"
        }
    ],
    "sg:phone":"+1 734 326 4151",
    "sg:postcode":"48185",
    "sg:province":"MI",
    "wof:name":"Le'cakery Bake Shop",
    "wof:placetype":"venue"
},
  "geometry": {"coordinates":[-83.38870199999999,42.3153],"type":"Point"}
}