{
  "type": "Feature",
  "properties": {
    "iso:country":"US",
    "sg:address":"1639 E 14 Mile Rd",
    "sg:city":"Troy",
    "sg:classifiers":[
        {
            "category":"Sports & Exercise",
            "subcategory":"Bowling",
            "type":"Entertainment"
        }
    ],
    "sg:phone":"+1 248 588 4850",
    "sg:postcode":"48083",
    "sg:province":"MI",
    "sg:website":"www.bowldetroit.com/center-info....",
    "wof:name":"Bowl One Lanes",
    "wof:placetype":"venue"
},
  "geometry": {"coordinates":[-83.091301,42.534801],"type":"Point"}
}