{
  "type": "Feature",
  "properties": {
    "iso:country":"US",
    "sg:address":"1305 S Washington Ave",
    "sg:city":"Lansing",
    "sg:classifiers":[
        {
            "category":"Professional",
            "subcategory":"Lawyer & Legal Services",
            "type":"Services"
        }
    ],
    "sg:phone":"+1 517 482 4890",
    "sg:postcode":"48910",
    "sg:province":"MI",
    "sg:tags":[
        "attorney"
    ],
    "sg:website":"www.mcclelland-anderson.com",
    "wof:name":"Mc Clelland & Anderson",
    "wof:placetype":"venue"
},
  "geometry": {"coordinates":[-84.552272,42.718238],"type":"Point"}
}