{
  "type": "Feature",
  "properties": {
    "iso:country":"US",
    "sg:address":"3809 Chilson Rd",
    "sg:city":"Howell",
    "sg:classifiers":[
        {
            "category":"Building & Trades",
            "subcategory":"Construction",
            "type":"Services"
        }
    ],
    "sg:phone":"+1 517 548 5798",
    "sg:postcode":"48843",
    "sg:province":"MI",
    "sg:tags":[
        "painter"
    ],
    "wof:name":"In A White Room",
    "wof:placetype":"venue"
},
  "geometry": {"coordinates":[-83.876321,42.543328],"type":"Point"}
}