{
  "type": "Feature",
  "properties": {
    "iso:country":"US",
    "sg:address":"5515 Davison Rd Ste 11",
    "sg:city":"Burton",
    "sg:classifiers":[
        {
            "category":"Personal",
            "subcategory":"Barber",
            "type":"Services"
        }
    ],
    "sg:phone":"+1 810 744 9224",
    "sg:postcode":"48509",
    "sg:province":"MI",
    "wof:name":"Hair Cutz",
    "wof:placetype":"venue"
},
  "geometry": {"coordinates":[-83.597319,43.033666],"type":"Point"}
}