{
  "type": "Feature",
  "properties": {
    "iso:country":"US",
    "sg:address":"34505 W 12 Mile Rd",
    "sg:city":"Farmington Hills",
    "sg:classifiers":[
        {
            "category":"Insurance",
            "subcategory":"Insurance Agent",
            "type":"Services"
        }
    ],
    "sg:phone":"+1 248 489 2800",
    "sg:postcode":"48331",
    "sg:province":"MI",
    "wof:name":"Liberty Mutual Insurance",
    "wof:placetype":"venue"
},
  "geometry": {"coordinates":[-83.386599,42.498304],"type":"Point"}
}