{
  "type": "Feature",
  "properties": {
    "iso:country":"US",
    "sg:address":"31471 Northwestern Hwy",
    "sg:city":"Farmington Hills",
    "sg:classifiers":[
        {
            "category":"Personal",
            "subcategory":"Tanning Parlor",
            "type":"Services"
        }
    ],
    "sg:phone":"+1 248 932 3826",
    "sg:postcode":"48334",
    "sg:province":"MI",
    "sg:tags":[
        "salon"
    ],
    "wof:name":"Resort Tan",
    "wof:placetype":"venue"
},
  "geometry": {"coordinates":[-83.33984700000001,42.519082],"type":"Point"}
}