{
  "type": "Feature",
  "properties": {
    "iso:country":"US",
    "sg:address":"2507 W Hibbard Rd",
    "sg:city":"Owosso",
    "sg:classifiers":[
        {
            "category":"Retail",
            "subcategory":"Auto Repair",
            "type":"Services"
        }
    ],
    "sg:phone":"+1 989 725 8104",
    "sg:postcode":"48867",
    "sg:province":"MI",
    "sg:tags":[
        "body",
        "automobile",
        "painting"
    ],
    "wof:name":"Bogg's Pro Street",
    "wof:placetype":"venue"
},
  "geometry": {"coordinates":[-84.231697,42.953308],"type":"Point"}
}