{
  "type": "Feature",
  "properties": {
    "iso:country":"US",
    "sg:address":"1425 Alloy Pkwy",
    "sg:city":"Highland",
    "sg:classifiers":[
        {
            "category":"Wholesale",
            "subcategory":"Hardware",
            "type":"Manufacturing & Wholesale Goods"
        }
    ],
    "sg:phone":"+1 248 889 0064",
    "sg:postcode":"48356",
    "sg:province":"MI",
    "sg:tags":[
        "robot"
    ],
    "sg:website":"www.roboticconcepts.com",
    "wof:name":"Robotic Concepts Inc",
    "wof:placetype":"venue"
},
  "geometry": {"coordinates":[-83.61529400000001,42.651137],"type":"Point"}
}