{
  "type": "Feature",
  "properties": {
    "iso:country":"US",
    "sg:address":"3215 Eastern Ave SE",
    "sg:city":"Grand Rapids",
    "sg:classifiers":[
        {
            "category":"Retail",
            "subcategory":"Repair Shop",
            "type":"Services"
        }
    ],
    "sg:phone":"+1 616 452 9528",
    "sg:postcode":"49508",
    "sg:province":"MI",
    "wof:name":"Eastern Avenue Clock Shop",
    "wof:placetype":"venue"
},
  "geometry": {"coordinates":[-85.646694,42.904029],"type":"Point"}
}