{
  "type": "Feature",
  "properties": {
    "iso:country":"US",
    "sg:address":"9019 Yorkshire Dr",
    "sg:city":"Saline",
    "sg:classifiers":[
        {
            "category":"Social Services",
            "subcategory":"Child Care",
            "type":"Services"
        }
    ],
    "sg:phone":"+1 734 944 7403",
    "sg:postcode":"48176",
    "sg:province":"MI",
    "sg:tags":[
        "day"
    ],
    "wof:name":"Diane Newberry",
    "wof:placetype":"venue"
},
  "geometry": {"coordinates":[-83.740166,42.153593],"type":"Point"}
}