{
  "type": "Feature",
  "properties": {
    "iso:country":"US",
    "sg:address":"238 W 15th St",
    "sg:city":"Holland",
    "sg:classifiers":[
        {
            "category":"Organizations",
            "subcategory":"Religious Organization",
            "type":"Services"
        }
    ],
    "sg:phone":"+1 616 392 2590",
    "sg:postcode":"49423",
    "sg:province":"MI",
    "wof:name":"Fourth Reformed Church",
    "wof:placetype":"venue"
},
  "geometry": {"coordinates":[-86.120249,42.783754],"type":"Point"}
}