{
  "type": "Feature",
  "properties": {
    "iso:country":"US",
    "sg:address":"508 Elm",
    "sg:city":"Elk Rapids",
    "sg:classifiers":[
        {
            "category":"Organizations",
            "subcategory":"Religious Organization",
            "type":"Services"
        }
    ],
    "sg:phone":"+1 231 264 6584",
    "sg:postcode":"49629",
    "sg:province":"MI",
    "sg:tags":[
        "church"
    ],
    "wof:name":"Presbyterian First Church",
    "wof:placetype":"venue"
},
  "geometry": {"coordinates":[-85.417663,44.893919],"type":"Point"}
}