{
  "type": "Feature",
  "properties": {
    "iso:country":"US",
    "sg:address":"4800 W Huron River Dr",
    "sg:city":"Ann Arbor",
    "sg:classifiers":[
        {
            "category":"Social Services",
            "subcategory":"Child Care",
            "type":"Services"
        }
    ],
    "sg:phone":"+1 734 973 3538",
    "sg:postcode":"48103",
    "sg:province":"MI",
    "sg:tags":[
        "center",
        "day"
    ],
    "wof:name":"Childrens Center",
    "wof:placetype":"venue"
},
  "geometry": {"coordinates":[-83.824192,42.330294],"type":"Point"}
}