{
  "type": "Feature",
  "properties": {
    "iso:country":"US",
    "sg:address":"1706 Fair St",
    "sg:city":"Ann Arbor",
    "sg:classifiers":[
        {
            "category":"Professional",
            "subcategory":"Business Services",
            "type":"Services"
        }
    ],
    "sg:phone":"+1 734 662 3321",
    "sg:postcode":"48103",
    "sg:province":"MI",
    "sg:tags":[
        "notary",
        "public"
    ],
    "wof:name":"Susan A Perry",
    "wof:placetype":"venue"
},
  "geometry": {"coordinates":[-83.76790200000001,42.278321],"type":"Point"}
}