{
  "type": "Feature",
  "properties": {
    "iso:country":"US",
    "sg:address":"22040 Mac Arthur Blvd",
    "sg:city":"Warren",
    "sg:classifiers":[
        {
            "category":"Retail",
            "subcategory":"Repair Shop",
            "type":"Services"
        }
    ],
    "sg:phone":"+1 586 758 6168",
    "sg:postcode":"48089",
    "sg:province":"MI",
    "sg:tags":[
        "lock",
        "industrial",
        "locksmiths-commercial"
    ],
    "wof:name":"B & D Lock Rekey Service",
    "wof:placetype":"venue"
},
  "geometry": {"coordinates":[-83.01830699999999,42.45773],"type":"Point"}
}