{
  "type": "Feature",
  "properties": {
    "iso:country":"US",
    "sg:address":"700 Hawksbridge Cir",
    "sg:city":"Temperance",
    "sg:classifiers":[
        {
            "category":"Retail",
            "subcategory":"Auto Repair",
            "type":"Services"
        }
    ],
    "sg:phone":"+1 734 692 1350",
    "sg:postcode":"48182",
    "sg:province":"MI",
    "sg:tags":[
        "automotive",
        "general"
    ],
    "wof:name":"Professional Auto Body Inc",
    "wof:placetype":"venue"
},
  "geometry": {"coordinates":[-83.56240099999999,41.774916],"type":"Point"}
}