{
  "type": "Feature",
  "properties": {
    "iso:country":"US",
    "sg:address":"631 E Big Beaver Rd",
    "sg:city":"Troy",
    "sg:classifiers":[
        {
            "category":"Wholesale",
            "subcategory":"Auto Parts",
            "type":"Manufacturing & Wholesale Goods"
        }
    ],
    "sg:phone":"+1 248 680 9020",
    "sg:postcode":"48083",
    "sg:province":"MI",
    "sg:tags":[
        "automobile"
    ],
    "sg:website":"www.polytechnet.com",
    "wof:name":"Polytech Netting Industries",
    "wof:placetype":"venue"
},
  "geometry": {"coordinates":[-83.12904899999999,42.563089],"type":"Point"}
}