{
  "type": "Feature",
  "properties": {
    "iso:country":"US",
    "sg:address":"12669 Schleweis Rd",
    "sg:city":"Manchester",
    "sg:classifiers":[
        {
            "category":"Retail",
            "subcategory":"Repair Shop",
            "type":"Services"
        }
    ],
    "sg:phone":"+1 734 428 9028",
    "sg:postcode":"48158",
    "sg:province":"MI",
    "sg:tags":[
        "television",
        "radio"
    ],
    "wof:name":"R 2 Electronics",
    "wof:placetype":"venue"
},
  "geometry": {"coordinates":[-84.040177,42.136551],"type":"Point"}
}