{
  "type": "Feature",
  "properties": {
    "iso:country":"US",
    "sg:address":"606 N 4th St",
    "sg:city":"Chesaning",
    "sg:classifiers":[
        {
            "category":"Real Estate",
            "subcategory":"Real Estate Operator",
            "type":"Services"
        }
    ],
    "sg:phone":"+1 989 845 4389",
    "sg:postcode":"48616",
    "sg:province":"MI",
    "sg:tags":[
        "apartment"
    ],
    "wof:name":"Lone Rock Apartments",
    "wof:placetype":"venue"
},
  "geometry": {"coordinates":[-84.129113,43.1913],"type":"Point"}
}