{
  "type": "Feature",
  "properties": {
    "iso:country":"US",
    "sg:address":"3996 Chicago Dr SW",
    "sg:city":"Grandville",
    "sg:classifiers":[
        {
            "category":"Professional",
            "subcategory":"Lawyer & Legal Services",
            "type":"Services"
        }
    ],
    "sg:phone":"+1 616 531 7714",
    "sg:postcode":"49418",
    "sg:province":"MI",
    "sg:tags":[
        "attorney"
    ],
    "wof:name":"Biker's Resource",
    "wof:placetype":"venue"
},
  "geometry": {"coordinates":[-85.76194700000001,42.910057],"type":"Point"}
}