{
  "type": "Feature",
  "properties": {
    "iso:country":"US",
    "sg:address":"2415 Wildwood Ave",
    "sg:city":"Jackson",
    "sg:classifiers":[
        {
            "category":"Home & Garden",
            "subcategory":"Home Furnishings",
            "type":"Retail Goods"
        }
    ],
    "sg:phone":"+1 517 784 4608",
    "sg:postcode":"49202",
    "sg:province":"MI",
    "sg:tags":[
        "glassware",
        "chinaware"
    ],
    "sg:website":"www.taylorrental.com",
    "wof:name":"Taylor Rental Ctr",
    "wof:placetype":"venue"
},
  "geometry": {"coordinates":[-84.444047,42.254617],"type":"Point"}
}