{
  "type": "Feature",
  "properties": {
    "iso:country":"US",
    "sg:address":"61800 Romeo Plank Rd",
    "sg:city":"Washington",
    "sg:classifiers":[
        {
            "category":"Real Estate",
            "subcategory":"Real Estate Agent",
            "type":"Services"
        }
    ],
    "sg:phone":"+1 586 781 2116",
    "sg:postcode":"48096",
    "sg:province":"MI",
    "sg:tags":[
        "broker"
    ],
    "wof:name":"Sir Realty Inc",
    "wof:placetype":"venue"
},
  "geometry": {"coordinates":[-82.960662,42.750987],"type":"Point"}
}