{
  "type": "Feature",
  "properties": {
    "iso:country":"US",
    "sg:address":"10561 Potters Rd",
    "sg:city":"Lowell",
    "sg:classifiers":[
        {
            "category":"Home & Garden",
            "subcategory":"Home Furnishings",
            "type":"Retail Goods"
        }
    ],
    "sg:phone":"+1 616 987 9437",
    "sg:postcode":"49331",
    "sg:province":"MI",
    "sg:tags":[
        "stove",
        "wood",
        "burning"
    ],
    "wof:name":"Whites Bridge Wood Heat WDMN",
    "wof:placetype":"venue"
},
  "geometry": {"coordinates":[-85.283468,42.98016],"type":"Point"}
}