{
  "type": "Feature",
  "properties": {
    "iso:country":"US",
    "sg:address":"42480 Cherry Hill Road.",
    "sg:city":"Canton",
    "sg:classifiers":[
        {
            "category":"Food & Beverages",
            "subcategory":"Candy",
            "type":"Retail Goods"
        },
        {
            "category":"Coffee & Tea",
            "type":"Food & Drink"
        }
    ],
    "sg:phone":"+1 734 983 0334",
    "sg:postcode":"48187",
    "sg:province":"MI",
    "sg:tags":[
        "dessert"
    ],
    "sg:website":"www.swirlscafe.com",
    "wof:name":"Swirls Cafe",
    "wof:placetype":"venue"
},
  "geometry": {"coordinates":[-83.45878,42.308074],"type":"Point"}
}