{
  "type": "Feature",
  "properties": {
    "iso:country":"US",
    "sg:address":"720 E Michigan Ave",
    "sg:city":"Lansing",
    "sg:classifiers":[
        {
            "category":"Wholesale",
            "subcategory":"Construction Materials",
            "type":"Manufacturing & Wholesale Goods"
        }
    ],
    "sg:phone":"+1 517 484 5431",
    "sg:postcode":"48912",
    "sg:province":"MI",
    "sg:tags":[
        "brick",
        "common",
        "face"
    ],
    "wof:name":"Young Brothers & Daley Inc",
    "wof:placetype":"venue"
},
  "geometry": {"coordinates":[-84.542337,42.733506],"type":"Point"}
}