{
  "type": "Feature",
  "properties": {
    "iso:country":"US",
    "sg:address":"853 E Auburn Rd",
    "sg:city":"Rochester Hills",
    "sg:classifiers":[
        {
            "category":"Personal",
            "subcategory":"Beauty Salon",
            "type":"Services"
        }
    ],
    "sg:phone":"+1 248 853 0010",
    "sg:postcode":"48307",
    "sg:province":"MI",
    "sg:tags":[
        "shop"
    ],
    "wof:name":"Impressions Salon",
    "wof:placetype":"venue"
},
  "geometry": {"coordinates":[-83.112723,42.63675],"type":"Point"}
}