{
  "type": "Feature",
  "properties": {
    "iso:country":"US",
    "sg:address":"1804 W 18th St",
    "sg:city":"Sault Ste Marie",
    "sg:classifiers":[
        {
            "category":"Real Estate",
            "subcategory":"Real Estate Operator",
            "type":"Services"
        }
    ],
    "sg:phone":"+1 906 632 2851",
    "sg:postcode":"49783",
    "sg:province":"MI",
    "sg:tags":[
        "mobile",
        "home",
        "site",
        "community"
    ],
    "wof:name":"L & M Homes",
    "wof:placetype":"venue"
},
  "geometry": {"coordinates":[-84.40042099999999,46.483617],"type":"Point"}
}