{
  "type": "Feature",
  "properties": {
    "iso:country":"US",
    "sg:address":"30423 Aston Ct",
    "sg:city":"Farmington",
    "sg:classifiers":[
        {
            "category":"Education",
            "subcategory":"Special Training",
            "type":"Public Place"
        }
    ],
    "sg:phone":"+1 248 661 6684",
    "sg:postcode":"48331",
    "sg:province":"MI",
    "wof:name":"Piano Lesson-Classical",
    "wof:placetype":"venue"
},
  "geometry": {"coordinates":[-83.429363,42.517874],"type":"Point"}
}