{
  "type": "Feature",
  "properties": {
    "iso:country":"US",
    "sg:address":"207 N Main St",
    "sg:city":"Brooklyn",
    "sg:classifiers":[
        {
            "category":"Education",
            "subcategory":"Library",
            "type":"Public Place"
        }
    ],
    "sg:phone":"+1 517 592 3406",
    "sg:postcode":"49230",
    "sg:province":"MI",
    "wof:name":"Jackson District Library",
    "wof:placetype":"venue"
},
  "geometry": {"coordinates":[-84.24784099999999,42.107442],"type":"Point"}
}