{
  "type": "Feature",
  "properties": {
    "iso:country":"US",
    "sg:address":"2125 Washington Ave",
    "sg:city":"St Joseph",
    "sg:classifiers":[
        {
            "category":"Retail",
            "subcategory":"Repair Shop",
            "type":"Services"
        }
    ],
    "sg:phone":"+1 269 982 1113",
    "sg:postcode":"49085",
    "sg:province":"MI",
    "sg:tags":[
        "jewelry"
    ],
    "wof:name":"Werdowatz Jewelry",
    "wof:placetype":"venue"
},
  "geometry": {"coordinates":[-86.48545799999999,42.078207],"type":"Point"}
}