{
  "type": "Feature",
  "properties": {
    "iso:country":"US",
    "sg:address":"5089 M 66",
    "sg:city":"Athens",
    "sg:classifiers":[
        {
            "category":"Retail",
            "subcategory":"Photofinishing",
            "type":"Services"
        }
    ],
    "sg:phone":"+1 269 729 4250",
    "sg:postcode":"49011",
    "sg:province":"MI",
    "sg:tags":[
        "laboratory"
    ],
    "wof:name":"Wild West Photo",
    "wof:placetype":"venue"
},
  "geometry": {"coordinates":[-85.207756,42.151116],"type":"Point"}
}