{
  "type": "Feature",
  "properties": {
    "iso:country":"US",
    "sg:address":"2525 E Jolly Rd",
    "sg:city":"Lansing",
    "sg:classifiers":[
        {
            "category":"Restaurant",
            "type":"Food & Drink"
        }
    ],
    "sg:menulink":"http://www.allmenus.com/mi/lansing/249711-leos-lodge/menu/",
    "sg:phone":"+1 517 882 3850",
    "sg:postcode":"48910",
    "sg:province":"MI",
    "sg:tags":[
        "burger",
        "american"
    ],
    "wof:name":"Leo's Lodge",
    "wof:placetype":"venue"
},
  "geometry": {"coordinates":[-84.51593699999999,42.682932],"type":"Point"}
}