{
  "type": "Feature",
  "properties": {
    "iso:country":"US",
    "sg:address":"4400 Pond View Dr",
    "sg:city":"White Lake",
    "sg:classifiers":[
        {
            "category":"Professional",
            "type":"Services"
        }
    ],
    "sg:phone":"+1 248 889 0748",
    "sg:postcode":"48383",
    "sg:province":"MI",
    "wof:name":"Erins Services",
    "wof:placetype":"venue"
},
  "geometry": {"coordinates":[-83.556134,42.689347],"type":"Point"}
}