{
  "type": "Feature",
  "properties": {
    "iso:country":"US",
    "sg:address":"3777 Indian Trl",
    "sg:city":"Orchard Lake",
    "sg:classifiers":[
        {
            "category":"Building & Trades",
            "subcategory":"Construction",
            "type":"Services"
        }
    ],
    "sg:phone":"+1 248 706 2000",
    "sg:postcode":"48324",
    "sg:province":"MI",
    "sg:tags":[
        "contractor"
    ],
    "wof:name":"21st Century Building Co",
    "wof:placetype":"venue"
},
  "geometry": {"coordinates":[-83.35663,42.590757],"type":"Point"}
}