{
  "type": "Feature",
  "properties": {
    "iso:country":"US",
    "sg:address":"1794 W Bear Lake Rd NE",
    "sg:city":"Kalkaska",
    "sg:classifiers":[
        {
            "category":"Organizations",
            "subcategory":"Religious Organization",
            "type":"Services"
        }
    ],
    "sg:phone":"+1 231 258 4359",
    "sg:postcode":"49646",
    "sg:province":"MI",
    "wof:name":"End Time Ministries",
    "wof:placetype":"venue"
},
  "geometry": {"coordinates":[-84.950272,44.734631],"type":"Point"}
}