{
  "type": "Feature",
  "properties": {
    "iso:country":"US",
    "sg:address":"119 Clinton Ave",
    "sg:city":"St Clair",
    "sg:classifiers":[
        {
            "category":"Restaurant",
            "type":"Food & Drink"
        }
    ],
    "sg:phone":"+1 810 326 1710",
    "sg:postcode":"48079",
    "sg:province":"MI",
    "wof:name":"Pepper Joe's",
    "wof:placetype":"venue"
},
  "geometry": {"coordinates":[-82.48809900000001,42.821073],"type":"Point"}
}