{
  "type": "Feature",
  "properties": {
    "iso:country":"US",
    "sg:address":"8433 Renee",
    "sg:city":"Newport",
    "sg:classifiers":[
        {
            "category":"Recreation",
            "type":"Entertainment"
        }
    ],
    "sg:phone":"+1 734 586 3812",
    "sg:postcode":"48166",
    "sg:province":"MI",
    "sg:tags":[
        "amusement"
    ],
    "wof:name":"Arrowhead Fishing Charters",
    "wof:placetype":"venue"
},
  "geometry": {"coordinates":[-83.354426,42.00328],"type":"Point"}
}