{
  "type": "Feature",
  "properties": {
    "iso:country":"US",
    "sg:address":"206 Lariat Dr",
    "sg:city":"Lapeer",
    "sg:classifiers":[
        {
            "category":"Professional",
            "subcategory":"Art Services",
            "type":"Services"
        }
    ],
    "sg:phone":"+1 810 664 1542",
    "sg:postcode":"48446",
    "sg:province":"MI",
    "sg:tags":[
        "photographer"
    ],
    "wof:name":"Mapley's Photography",
    "wof:placetype":"venue"
},
  "geometry": {"coordinates":[-83.302038,43.129695],"type":"Point"}
}