{
  "type": "Feature",
  "properties": {
    "iso:country":"US",
    "sg:address":"36912 Van Born Rd",
    "sg:city":"Wayne",
    "sg:classifiers":[
        {
            "category":"Retail",
            "subcategory":"Veterinary Services",
            "type":"Services"
        }
    ],
    "sg:phone":"+1 734 721 8844",
    "sg:postcode":"48184",
    "sg:province":"MI",
    "sg:tags":[
        "veterinarian"
    ],
    "wof:name":"Nichols Veterinary Clinic",
    "wof:placetype":"venue"
},
  "geometry": {"coordinates":[-83.403702,42.266399],"type":"Point"}
}