{
  "type": "Feature",
  "properties": {
    "iso:country":"US",
    "sg:address":"1191 N Milford Rd",
    "sg:city":"Milford",
    "sg:classifiers":[
        {
            "category":"Shopping",
            "subcategory":"Pharmacy",
            "type":"Retail Goods"
        }
    ],
    "sg:phone":"+1 248 685 8363",
    "sg:postcode":"48381",
    "sg:province":"MI",
    "wof:name":"Milford Pharmacy",
    "wof:placetype":"venue"
},
  "geometry": {"coordinates":[-83.608949,42.598916],"type":"Point"}
}