{
  "type": "Feature",
  "properties": {
    "iso:country":"US",
    "sg:address":"1309 Commercial St",
    "sg:city":"Munising",
    "sg:classifiers":[
        {
            "category":"Retail",
            "subcategory":"Auto Repair",
            "type":"Services"
        }
    ],
    "sg:phone":"+1 906 387 3091",
    "sg:postcode":"49862",
    "sg:province":"MI",
    "sg:tags":[
        "repairing",
        "automobile"
    ],
    "wof:name":"Lare Auto Repair",
    "wof:placetype":"venue"
},
  "geometry": {"coordinates":[-86.657996,46.426931],"type":"Point"}
}