{
  "type": "Feature",
  "properties": {
    "iso:country":"US",
    "sg:address":"747 Clark St",
    "sg:city":"Detroit",
    "sg:classifiers":[
        {
            "category":"Food & Beverages",
            "subcategory":"Groceries & Convenience Stores",
            "type":"Retail Goods"
        }
    ],
    "sg:phone":"+1 313 842 5422",
    "sg:postcode":"48209",
    "sg:province":"MI",
    "wof:name":"Kavalos & Son's Inc",
    "wof:placetype":"venue"
},
  "geometry": {"coordinates":[-83.09079699999999,42.313],"type":"Point"}
}