{
  "type": "Feature",
  "properties": {
    "iso:country":"US",
    "sg:address":"401 W Broadway Ave",
    "sg:city":"Muskegon",
    "sg:classifiers":[
        {
            "category":"Shopping",
            "subcategory":"Clothing, Apparel, & Fashions",
            "type":"Retail Goods"
        }
    ],
    "sg:phone":"+1 231 733 2068",
    "sg:postcode":"49444",
    "sg:province":"MI",
    "sg:tags":[
        "dry",
        "cleaners",
        "tailor"
    ],
    "wof:name":"Remwolt Cleaners & Tailors",
    "wof:placetype":"venue"
},
  "geometry": {"coordinates":[-86.25593000000001,43.201149],"type":"Point"}
}