{
  "type": "Feature",
  "properties": {
    "iso:country":"US",
    "sg:address":"6061 Rolling Green Dr",
    "sg:city":"Grand Blanc",
    "sg:classifiers":[
        {
            "category":"Shopping",
            "subcategory":"Hobbies, Toys, & Games",
            "type":"Retail Goods"
        }
    ],
    "sg:phone":"+1 734 854 5511",
    "sg:postcode":"48439",
    "sg:province":"MI",
    "sg:tags":[
        "basket"
    ],
    "wof:name":"Gift Cellar",
    "wof:placetype":"venue"
},
  "geometry": {"coordinates":[-83.589315,42.896664],"type":"Point"}
}