{
  "type": "Feature",
  "properties": {
    "iso:country":"US",
    "sg:address":"28100 Farmington Rd",
    "sg:city":"Farmington Hills",
    "sg:classifiers":[
        {
            "category":"Social Services",
            "type":"Services"
        }
    ],
    "sg:phone":"+1 248 553 4020",
    "sg:postcode":"48334",
    "sg:province":"MI",
    "sg:tags":[
        "organization",
        "welfare"
    ],
    "sg:website":"www.ymcadetroit.org",
    "wof:name":"YMCA",
    "wof:placetype":"venue"
},
  "geometry": {"coordinates":[-83.378247,42.500954],"type":"Point"}
}