{
  "type": "Feature",
  "properties": {
    "iso:country":"US",
    "sg:address":"8622 Telegraph Rd",
    "sg:city":"Dearborn Heights",
    "sg:classifiers":[
        {
            "category":"Retail",
            "subcategory":"Auto Repair",
            "type":"Services"
        }
    ],
    "sg:phone":"+1 313 274 6880",
    "sg:postcode":"48127",
    "sg:province":"MI",
    "sg:tags":[
        "general"
    ],
    "wof:name":"Brownies Muffler Service",
    "wof:placetype":"venue"
},
  "geometry": {"coordinates":[-83.274086,42.355341],"type":"Point"}
}