{
  "type": "Feature",
  "properties": {
    "iso:country":"US",
    "sg:address":"3535 Woodland Ave",
    "sg:city":"Royal Oak",
    "sg:classifiers":[
        {
            "category":"Personal",
            "type":"Services"
        }
    ],
    "sg:phone":"+1 248 549 7735",
    "sg:postcode":"48073",
    "sg:province":"MI",
    "wof:name":"Your Handyman",
    "wof:placetype":"venue"
},
  "geometry": {"coordinates":[-83.169631,42.520433],"type":"Point"}
}