{
  "type": "Feature",
  "properties": {
    "iso:country":"US",
    "sg:address":"6705 Green Rd",
    "sg:city":"Ottawa Lake",
    "sg:classifiers":[
        {
            "category":"Building & Trades",
            "subcategory":"Landscaping Services",
            "type":"Services"
        }
    ],
    "sg:phone":"+1 734 888 1305",
    "sg:postcode":"49267",
    "sg:province":"MI",
    "sg:tags":[
        "landscape",
        "contractor"
    ],
    "wof:name":"Wallace Landscape",
    "wof:placetype":"venue"
},
  "geometry": {"coordinates":[-83.70796799999999,41.726115],"type":"Point"}
}