{
  "type": "Feature",
  "properties": {
    "iso:country":"US",
    "sg:address":"274 Piper Blvd",
    "sg:city":"Detroit",
    "sg:classifiers":[
        {
            "category":"Social Services",
            "subcategory":"Child Care",
            "type":"Services"
        }
    ],
    "sg:phone":"+1 313 822 2199",
    "sg:postcode":"48215",
    "sg:province":"MI",
    "sg:tags":[
        "home",
        "day"
    ],
    "wof:name":"Hattie Lewis",
    "wof:placetype":"venue"
},
  "geometry": {"coordinates":[-82.941399,42.359618],"type":"Point"}
}