{
  "type": "Feature",
  "properties": {
    "iso:country":"US",
    "sg:address":"101 W Main St",
    "sg:city":"Harbor Springs",
    "sg:classifiers":[
        {
            "category":"Food & Beverages",
            "subcategory":"Candy",
            "type":"Retail Goods"
        }
    ],
    "sg:phone":"+1 231 526 2802",
    "sg:postcode":"49740",
    "sg:province":"MI",
    "sg:tags":[
        "confectionery"
    ],
    "sg:website":"www.kilwins.com",
    "wof:name":"Kilwin's Chocolates",
    "wof:placetype":"venue"
},
  "geometry": {"coordinates":[-84.98894199999999,45.429671],"type":"Point"}
}