{
  "type": "Feature",
  "properties": {
    "iso:country":"US",
    "sg:address":"1745 Hamilton Rd",
    "sg:city":"Okemos",
    "sg:classifiers":[
        {
            "category":"Professional",
            "subcategory":"Lawyer & Legal Services",
            "type":"Services"
        }
    ],
    "sg:phone":"+1 517 347 0246",
    "sg:postcode":"48864",
    "sg:province":"MI",
    "wof:name":"Tripp Pamela",
    "wof:placetype":"venue"
},
  "geometry": {"coordinates":[-84.41271999999999,42.716786],"type":"Point"}
}