{
  "type": "Feature",
  "properties": {
    "iso:country":"US",
    "sg:address":"717 S Gordon Rd",
    "sg:city":"Scottville",
    "sg:classifiers":[
        {
            "category":"Building & Trades",
            "subcategory":"Electrical",
            "type":"Services"
        }
    ],
    "sg:phone":"+1 231 757 9213",
    "sg:postcode":"49454",
    "sg:province":"MI",
    "sg:tags":[
        "electrical",
        "contractor"
    ],
    "wof:name":"Dougs Electric",
    "wof:placetype":"venue"
},
  "geometry": {"coordinates":[-86.30900800000001,43.942335],"type":"Point"}
}