{
  "type": "Feature",
  "properties": {
    "iso:country":"US",
    "sg:address":"105 Main St",
    "sg:city":"East Jordan",
    "sg:classifiers":[
        {
            "category":"Shopping",
            "subcategory":"Bicycles & Sporting Goods",
            "type":"Retail Goods"
        }
    ],
    "sg:phone":"+1 231 582 9950",
    "sg:postcode":"49727",
    "sg:province":"MI",
    "sg:tags":[
        "tackle",
        "fishing"
    ],
    "wof:name":"Jordan Rier Fly Shop",
    "wof:placetype":"venue"
},
  "geometry": {"coordinates":[-85.127673,45.155332],"type":"Point"}
}