{
  "type": "Feature",
  "properties": {
    "iso:country":"US",
    "sg:address":"600 N Old Woodward Ave",
    "sg:city":"Birmingham",
    "sg:classifiers":[
        {
            "category":"Real Estate",
            "subcategory":"Real Estate Services",
            "type":"Services"
        }
    ],
    "sg:phone":"+1 248 593 4899",
    "sg:postcode":"48009",
    "sg:province":"MI",
    "sg:tags":[
        "company",
        "title"
    ],
    "wof:name":"Anthem Title Agency",
    "wof:placetype":"venue"
},
  "geometry": {"coordinates":[-83.219585,42.553363],"type":"Point"}
}