{
  "type": "Feature",
  "properties": {
    "iso:country":"US",
    "sg:address":"112 Homer Rd",
    "sg:city":"Concord",
    "sg:classifiers":[
        {
            "category":"Government",
            "subcategory":"Post Office",
            "type":"Public Place"
        }
    ],
    "sg:phone":"+1 517 000 1111",
    "sg:postcode":"49237",
    "sg:province":"MI",
    "wof:name":"US Post Office",
    "wof:placetype":"venue"
},
  "geometry": {"coordinates":[-84.64502899999999,42.178064],"type":"Point"}
}