{
  "type": "Feature",
  "properties": {
    "iso:country":"US",
    "sg:address":"4252 S Van Dyke Rd",
    "sg:city":"Ubly",
    "sg:classifiers":[
        {
            "category":"Building & Trades",
            "subcategory":"Construction",
            "type":"Services"
        }
    ],
    "sg:phone":"+1 989 658 2204",
    "sg:postcode":"48475",
    "sg:province":"MI",
    "sg:tags":[
        "excavation",
        "contractor"
    ],
    "wof:name":"Lubescki & Son Excavating",
    "wof:placetype":"venue"
},
  "geometry": {"coordinates":[-83.09878,43.71758],"type":"Point"}
}