{
  "type": "Feature",
  "properties": {
    "iso:country":"US",
    "sg:address":"6045 Woodfield Dr SE",
    "sg:city":"Grand Rapids",
    "sg:classifiers":[
        {
            "category":"Building & Trades",
            "subcategory":"Landscaping Services",
            "type":"Services"
        }
    ],
    "sg:phone":"+1 616 827 9227",
    "sg:postcode":"49548",
    "sg:province":"MI",
    "sg:tags":[
        "lawn",
        "maintenance",
        "grounds"
    ],
    "wof:name":"Hale Lawn Maintenance",
    "wof:placetype":"venue"
},
  "geometry": {"coordinates":[-85.648985,42.853775],"type":"Point"}
}