{
  "type": "Feature",
  "properties": {
    "iso:country":"US",
    "sg:address":"1762 W Townline Rd",
    "sg:city":"Harbor Springs",
    "sg:classifiers":[
        {
            "category":"Home & Garden",
            "subcategory":"Home Furnishings",
            "type":"Retail Goods"
        }
    ],
    "sg:phone":"+1 231 632 9948",
    "sg:postcode":"49740",
    "sg:province":"MI",
    "wof:name":"Zoerners Woodstoves",
    "wof:placetype":"venue"
},
  "geometry": {"coordinates":[-85.097531,45.525518],"type":"Point"}
}