{
  "type": "Feature",
  "properties": {
    "iso:country":"US",
    "sg:address":"11555 Engleman Rd",
    "sg:city":"Warren",
    "sg:classifiers":[
        {
            "category":"Restaurant",
            "type":"Food & Drink"
        }
    ],
    "sg:menulink":"http://www.allmenus.com/mi/warren/86994-little-caesars-pizza/menu/",
    "sg:phone":"+1 586 754 8889",
    "sg:postcode":"48089",
    "sg:province":"MI",
    "sg:tags":[
        "american",
        "pizza"
    ],
    "wof:name":"Little Caesar's Pizza",
    "wof:placetype":"venue"
},
  "geometry": {"coordinates":[-83.006935,42.481467],"type":"Point"}
}