{
  "type": "Feature",
  "properties": {
    "iso:country":"US",
    "sg:address":"89105 Shorelane Dr",
    "sg:city":"Lawton",
    "sg:classifiers":[
        {
            "category":"Shopping",
            "subcategory":"Computers & Home Electronics",
            "type":"Retail Goods"
        }
    ],
    "sg:phone":"+1 269 624 6760",
    "sg:postcode":"49065",
    "sg:province":"MI",
    "wof:name":"PC Enterprises Inc",
    "wof:placetype":"venue"
},
  "geometry": {"coordinates":[-85.82687199999999,42.094537],"type":"Point"}
}