{
  "type": "Feature",
  "properties": {
    "iso:country":"US",
    "sg:address":"1450 Alloy Pkwy",
    "sg:city":"Highland",
    "sg:classifiers":[
        {
            "category":"Building & Trades",
            "subcategory":"Construction",
            "type":"Services"
        }
    ],
    "sg:phone":"+1 248 887 3718",
    "sg:postcode":"48356",
    "sg:province":"MI",
    "sg:tags":[
        "insulation",
        "heat",
        "contractor"
    ],
    "wof:name":"Brinker Mechanical",
    "wof:placetype":"venue"
},
  "geometry": {"coordinates":[-83.61626699999999,42.651406],"type":"Point"}
}