{
  "type": "Feature",
  "properties": {
    "iso:country":"US",
    "sg:address":"22550 Hall Rd",
    "sg:city":"Clinton Township",
    "sg:classifiers":[
        {
            "category":"Professional",
            "subcategory":"Engineering",
            "type":"Services"
        }
    ],
    "sg:phone":"+1 586 469 1001",
    "sg:postcode":"48036",
    "sg:province":"MI",
    "sg:tags":[
        "industrial",
        "design"
    ],
    "wof:name":"Ryco Engineering of Alabama",
    "wof:placetype":"venue"
},
  "geometry": {"coordinates":[-82.878345,42.629289],"type":"Point"}
}