{
  "type": "Feature",
  "properties": {
    "iso:country":"US",
    "sg:address":"27150 Ryan Rd",
    "sg:city":"Warren",
    "sg:classifiers":[
        {
            "category":"Health Services",
            "subcategory":"Doctor",
            "type":"Services"
        }
    ],
    "sg:phone":"+1 586 573 3079",
    "sg:postcode":"48092",
    "sg:province":"MI",
    "wof:name":"Northeast Surgical Associates",
    "wof:placetype":"venue"
},
  "geometry": {"coordinates":[-83.066771,42.492539],"type":"Point"}
}