{
  "type": "Feature",
  "properties": {
    "iso:country":"US",
    "sg:address":"39541 Mound Rd",
    "sg:city":"Sterling Heights",
    "sg:classifiers":[
        {
            "category":"Personal",
            "type":"Services"
        },
        {
            "category":"Shopping",
            "subcategory":"Jewelry",
            "type":"Retail Goods"
        }
    ],
    "sg:phone":"+1 586 939 7772",
    "sg:postcode":"48310",
    "sg:province":"MI",
    "sg:tags":[
        "jeweler"
    ],
    "wof:name":"Sally's Fine Jewelry",
    "wof:placetype":"venue"
},
  "geometry": {"coordinates":[-83.049809,42.582931],"type":"Point"}
}