{
  "type": "Feature",
  "properties": {
    "iso:country":"US",
    "sg:address":"1604 116th Ave",
    "sg:city":"Otsego",
    "sg:classifiers":[
        {
            "category":"Shopping",
            "subcategory":"Hobbies, Toys, & Games",
            "type":"Retail Goods"
        }
    ],
    "sg:phone":"+1 269 672 7473",
    "sg:postcode":"49078",
    "sg:province":"MI",
    "wof:name":"Pee Wee S Hobby Shop",
    "wof:placetype":"venue"
},
  "geometry": {"coordinates":[-85.682727,42.536866],"type":"Point"}
}