{
  "type": "Feature",
  "properties": {
    "iso:country":"US",
    "sg:address":"4243 Remembrance Rd NW",
    "sg:city":"Grand Rapids",
    "sg:classifiers":[
        {
            "category":"Recreation",
            "type":"Entertainment"
        }
    ],
    "sg:phone":"+1 616 791 6890",
    "sg:postcode":"49504",
    "sg:province":"MI",
    "sg:tags":[
        "center"
    ],
    "wof:name":"Walker City Recreation Dept",
    "wof:placetype":"venue"
},
  "geometry": {"coordinates":[-85.77219100000001,43.00449],"type":"Point"}
}