{
  "type": "Feature",
  "properties": {
    "iso:country":"US",
    "sg:address":"8493 N 43rd St",
    "sg:city":"Augusta",
    "sg:classifiers":[
        {
            "category":"Building & Trades",
            "subcategory":"Construction",
            "type":"Services"
        }
    ],
    "sg:phone":"+1 269 731 4918",
    "sg:postcode":"49012",
    "sg:province":"MI",
    "sg:tags":[
        "contractor"
    ],
    "wof:name":"R B Baker Masonry",
    "wof:placetype":"venue"
},
  "geometry": {"coordinates":[-85.35010800000001,42.385703],"type":"Point"}
}