{
  "type": "Feature",
  "properties": {
    "iso:country":"US",
    "sg:address":"8809 Schoolcraft St",
    "sg:city":"Detroit",
    "sg:classifiers":[
        {
            "category":"Place Of Worship",
            "subcategory":"Church",
            "type":"Public Place"
        },
        {
            "category":"Place Of Worship",
            "type":"Public Place"
        }
    ],
    "sg:phone":"+1 313 491 1222",
    "sg:postcode":"48238",
    "sg:province":"MI",
    "sg:tags":[
        "churches-apostolic",
        "churches-pentecostal-apostolic"
    ],
    "wof:name":"J Ruth Haddon Ministries",
    "wof:placetype":"venue"
},
  "geometry": {"coordinates":[-83.157123,42.388537],"type":"Point"}
}