{
  "type": "Feature",
  "properties": {
    "iso:country":"US",
    "sg:address":"3940 Krouse Rd",
    "sg:city":"Owosso",
    "sg:classifiers":[
        {
            "category":"Building & Trades",
            "subcategory":"Construction",
            "type":"Services"
        }
    ],
    "sg:phone":"+1 517 723 8798",
    "sg:postcode":"48867",
    "sg:province":"MI",
    "sg:tags":[
        "house"
    ],
    "wof:name":"Robert Spencer Construction",
    "wof:placetype":"venue"
},
  "geometry": {"coordinates":[-84.237211,42.983494],"type":"Point"}
}