{
  "type": "Feature",
  "properties": {
    "iso:country":"US",
    "sg:address":"1033 S Wildwood St",
    "sg:city":"Westland",
    "sg:classifiers":[
        {
            "category":"Organizations",
            "subcategory":"Religious Organization",
            "type":"Services"
        }
    ],
    "sg:phone":"+1 734 721 8195",
    "sg:postcode":"48186",
    "sg:province":"MI",
    "wof:name":"First Baptist of Westland",
    "wof:placetype":"venue"
},
  "geometry": {"coordinates":[-83.378563,42.30188],"type":"Point"}
}