{
  "type": "Feature",
  "properties": {
    "iso:country":"US",
    "sg:address":"5971 Ravine Rd",
    "sg:city":"Kalamazoo",
    "sg:classifiers":[
        {
            "category":"Building & Trades",
            "subcategory":"Plumbing",
            "type":"Services"
        }
    ],
    "sg:phone":"+1 269 343 2798",
    "sg:postcode":"49009",
    "sg:province":"MI",
    "sg:tags":[
        "plumbing",
        "contractor"
    ],
    "wof:name":"Deurloo Plumbing Co",
    "wof:placetype":"venue"
},
  "geometry": {"coordinates":[-85.65796899999999,42.346882],"type":"Point"}
}