{
  "type": "Feature",
  "properties": {
    "iso:country":"US",
    "sg:address":"40610 Woodward Ave",
    "sg:city":"Bloomfield Hills",
    "sg:classifiers":[
        {
            "category":"Autos & Motor Vehicles",
            "subcategory":"Fuel & Gas Station",
            "type":"Retail Goods"
        }
    ],
    "sg:phone":"+1 248 258 9605",
    "sg:postcode":"48304",
    "sg:province":"MI",
    "wof:name":"Safiedine Long Lake",
    "wof:placetype":"venue"
},
  "geometry": {"coordinates":[-83.245153,42.584058],"type":"Point"}
}