{
  "type": "Feature",
  "properties": {
    "iso:country":"US",
    "sg:address":"4743 Moon Lake Rd",
    "sg:city":"Jackson",
    "sg:classifiers":[
        {
            "category":"Real Estate",
            "subcategory":"Real Estate Agent",
            "type":"Services"
        }
    ],
    "sg:phone":"+1 517 764 7745",
    "sg:postcode":"49201",
    "sg:province":"MI",
    "sg:tags":[
        "inspection"
    ],
    "wof:name":"All American Home & Building",
    "wof:placetype":"venue"
},
  "geometry": {"coordinates":[-84.306978,42.194727],"type":"Point"}
}