{
  "type": "Feature",
  "properties": {
    "iso:country":"US",
    "sg:address":"195 W Genesee St",
    "sg:city":"Lapeer",
    "sg:classifiers":[
        {
            "category":"Restaurant",
            "type":"Food & Drink"
        }
    ],
    "sg:phone":"+1 810 664 9929",
    "sg:postcode":"48446",
    "sg:province":"MI",
    "wof:name":"Country Cafe",
    "wof:placetype":"venue"
},
  "geometry": {"coordinates":[-83.304374,43.050847],"type":"Point"}
}