{
  "type": "Feature",
  "properties": {
    "iso:country":"US",
    "sg:address":"2994 28th St SE",
    "sg:city":"Kentwood",
    "sg:classifiers":[
        {
            "category":"Home & Garden",
            "subcategory":"Furniture",
            "type":"Retail Goods"
        }
    ],
    "sg:phone":"+1 616 464 3355",
    "sg:postcode":"49512",
    "sg:province":"MI",
    "sg:website":"www.thomasville.com",
    "wof:name":"Thomasville Home Furnishings",
    "wof:placetype":"venue"
},
  "geometry": {"coordinates":[-85.593653,42.912487],"type":"Point"}
}