{
  "type": "Feature",
  "properties": {
    "iso:country":"US",
    "sg:address":"45618 Van Dyke Ave",
    "sg:city":"Utica",
    "sg:classifiers":[
        {
            "category":"Retail",
            "subcategory":"Repair Shop",
            "type":"Services"
        }
    ],
    "sg:phone":"+1 586 726 9030",
    "sg:postcode":"48317",
    "sg:province":"MI",
    "sg:tags":[
        "appliance"
    ],
    "wof:name":"Doc's Appliance Svc",
    "wof:placetype":"venue"
},
  "geometry": {"coordinates":[-83.032481,42.629513],"type":"Point"}
}