{
  "type": "Feature",
  "properties": {
    "iso:country":"US",
    "sg:address":"5380 Snow Ave SE",
    "sg:city":"Alto",
    "sg:classifiers":[
        {
            "category":"Farming",
            "subcategory":"Farm",
            "type":"Manufacturing & Wholesale Goods"
        }
    ],
    "sg:phone":"+1 616 868 0673",
    "sg:postcode":"49302",
    "sg:province":"MI",
    "sg:tags":[
        "crop",
        "general"
    ],
    "wof:name":"Irish Lane Farm",
    "wof:placetype":"venue"
},
  "geometry": {"coordinates":[-85.429366,42.870023],"type":"Point"}
}