{
  "type": "Feature",
  "properties": {
    "iso:country":"US",
    "sg:address":"14403 Spring Garden St",
    "sg:city":"Detroit",
    "sg:classifiers":[
        {
            "category":"Retail",
            "subcategory":"Auto Repair",
            "type":"Services"
        }
    ],
    "sg:phone":"+1 313 527 5100",
    "sg:postcode":"48205",
    "sg:province":"MI",
    "sg:tags":[
        "body"
    ],
    "wof:name":"Wummel Collision",
    "wof:placetype":"venue"
},
  "geometry": {"coordinates":[-82.972618,42.428012],"type":"Point"}
}