{
  "type": "Feature",
  "properties": {
    "iso:country":"US",
    "sg:address":"116 N Mill St",
    "sg:city":"St Louis",
    "sg:classifiers":[
        {
            "category":"Shopping",
            "subcategory":"Pharmacy",
            "type":"Retail Goods"
        }
    ],
    "sg:phone":"+1 989 681 6633",
    "sg:postcode":"48880",
    "sg:province":"MI",
    "wof:name":"Evans Drug Store",
    "wof:placetype":"venue"
},
  "geometry": {"coordinates":[-84.608667,43.408994],"type":"Point"}
}