{
  "type": "Feature",
  "properties": {
    "iso:country":"US",
    "sg:address":"10411 Newburg Rd",
    "sg:city":"Durand",
    "sg:classifiers":[
        {
            "category":"Organizations",
            "subcategory":"Religious Organization",
            "type":"Services"
        }
    ],
    "sg:phone":"+1 989 288 2296",
    "sg:postcode":"48429",
    "sg:province":"MI",
    "wof:name":"Durand Church Of God",
    "wof:placetype":"venue"
},
  "geometry": {"coordinates":[-83.95384199999999,42.911445],"type":"Point"}
}