{
  "type": "Feature",
  "properties": {
    "iso:country":"US",
    "sg:address":"350 Holmes Rd",
    "sg:city":"Allenton",
    "sg:classifiers":[
        {
            "category":"Building & Trades",
            "subcategory":"Construction",
            "type":"Services"
        }
    ],
    "sg:phone":"+1 810 395 4843",
    "sg:postcode":"48002",
    "sg:province":"MI",
    "sg:tags":[
        "carpentry",
        "contractor"
    ],
    "wof:name":"Thom Ruthenburg Contg Svcs",
    "wof:placetype":"venue"
},
  "geometry": {"coordinates":[-82.955101,42.904718],"type":"Point"}
}