{
  "type": "Feature",
  "properties": {
    "iso:country":"US",
    "sg:address":"232 Dutton St",
    "sg:city":"Eaton Rapids",
    "sg:classifiers":[
        {
            "category":"Home & Garden",
            "subcategory":"Building Materials",
            "type":"Retail Goods"
        }
    ],
    "sg:phone":"+1 517 663 0062",
    "sg:postcode":"48827",
    "sg:province":"MI",
    "sg:tags":[
        "glass",
        "window",
        "plate"
    ],
    "wof:name":"Auto Glass Bailey's",
    "wof:placetype":"venue"
},
  "geometry": {"coordinates":[-84.65118099999999,42.508341],"type":"Point"}
}