{
  "type": "Feature",
  "properties": {
    "iso:country":"US",
    "sg:address":"55 Rockview Dr NE",
    "sg:city":"Rockford",
    "sg:classifiers":[
        {
            "category":"Building & Trades",
            "subcategory":"Construction",
            "type":"Services"
        }
    ],
    "sg:phone":"+1 616 866 8951",
    "sg:postcode":"49341",
    "sg:province":"MI",
    "sg:tags":[
        "house"
    ],
    "wof:name":"Fortier Construction",
    "wof:placetype":"venue"
},
  "geometry": {"coordinates":[-85.564757,43.128996],"type":"Point"}
}