{
  "type": "Feature",
  "properties": {
    "iso:country":"US",
    "sg:address":"23433 Plymouth Rd",
    "sg:city":"Redford",
    "sg:classifiers":[
        {
            "category":"Autos & Motor Vehicles",
            "subcategory":"Fuel & Gas Station",
            "type":"Retail Goods"
        }
    ],
    "sg:phone":"+1 313 538 6812",
    "sg:postcode":"48239",
    "sg:province":"MI",
    "wof:name":"Shebli Petrol Inc",
    "wof:placetype":"venue"
},
  "geometry": {"coordinates":[-83.26979799999999,42.3713],"type":"Point"}
}