{
  "type": "Feature",
  "properties": {
    "iso:country":"US",
    "sg:address":"8080 Vassar Rd",
    "sg:city":"Grand Blanc",
    "sg:classifiers":[
        {
            "category":"Recreation",
            "type":"Entertainment"
        }
    ],
    "sg:phone":"+1 810 695 6141",
    "sg:postcode":"48439",
    "sg:province":"MI",
    "sg:tags":[
        "stable"
    ],
    "wof:name":"Pine Hollow Farms",
    "wof:placetype":"venue"
},
  "geometry": {"coordinates":[-83.572292,42.911244],"type":"Point"}
}