{
  "type": "Feature",
  "properties": {
    "iso:country":"US",
    "sg:address":"2457 Sinclair Ave NE",
    "sg:city":"Grand Rapids",
    "sg:classifiers":[
        {
            "category":"Shopping",
            "subcategory":"Hobbies, Toys, & Games",
            "type":"Retail Goods"
        }
    ],
    "sg:phone":"+1 616 363 7395",
    "sg:postcode":"49505",
    "sg:province":"MI",
    "wof:name":"Unique Bowtique",
    "wof:placetype":"venue"
},
  "geometry": {"coordinates":[-85.658948,43.008468],"type":"Point"}
}