{
  "type": "Feature",
  "properties": {
    "iso:country":"US",
    "sg:address":"12192 Beecher Rd",
    "sg:city":"Flushing",
    "sg:classifiers":[
        {
            "category":"Farming",
            "subcategory":"Farm",
            "type":"Manufacturing & Wholesale Goods"
        }
    ],
    "sg:phone":"+1 810 659 6617",
    "sg:postcode":"48433",
    "sg:province":"MI",
    "sg:tags":[
        "crop",
        "general"
    ],
    "wof:name":"Koan Farms",
    "wof:placetype":"venue"
},
  "geometry": {"coordinates":[-83.914799,43.029825],"type":"Point"}
}