{
  "type": "Feature",
  "properties": {
    "iso:country":"US",
    "sg:address":"1800 Leonard St NW",
    "sg:city":"Grand Rapids",
    "sg:classifiers":[
        {
            "category":"Insurance",
            "subcategory":"Insurance Agent",
            "type":"Services"
        }
    ],
    "sg:phone":"+1 616 988 3380",
    "sg:postcode":"49504",
    "sg:province":"MI",
    "sg:tags":[
        "consultant"
    ],
    "wof:name":"TCI Group",
    "wof:placetype":"venue"
},
  "geometry": {"coordinates":[-85.713498,42.98598],"type":"Point"}
}