{
  "type": "Feature",
  "properties": {
    "iso:country":"US",
    "sg:address":"37370 Gregory Dr",
    "sg:city":"Sterling Heights",
    "sg:classifiers":[
        {
            "category":"Retail",
            "subcategory":"Portrait Studio",
            "type":"Services"
        }
    ],
    "sg:phone":"+1 586 264 6000",
    "sg:postcode":"48312",
    "sg:province":"MI",
    "sg:tags":[
        "photo"
    ],
    "wof:name":"Kellar Nrman L Art Photography",
    "wof:placetype":"venue"
},
  "geometry": {"coordinates":[-83.01926,42.568938],"type":"Point"}
}