{
  "type": "Feature",
  "properties": {
    "iso:country":"US",
    "sg:address":"116 W Cedar St",
    "sg:city":"Kalamazoo",
    "sg:classifiers":[
        {
            "category":"Government",
            "subcategory":"Office",
            "type":"Public Place"
        }
    ],
    "sg:phone":"+1 269 337 8101",
    "sg:postcode":"49007",
    "sg:province":"MI",
    "sg:tags":[
        "civil",
        "defense",
        "agency"
    ],
    "sg:website":"www.kalamazoocity.org",
    "wof:name":"Kalamazoo Public Safety Trng",
    "wof:placetype":"venue"
},
  "geometry": {"coordinates":[-85.583511,42.287528],"type":"Point"}
}