{
  "type": "Feature",
  "properties": {
    "iso:country":"US",
    "sg:address":"120 N Industrial Hwy",
    "sg:city":"Alpena",
    "sg:classifiers":[
        {
            "category":"Manufacturing",
            "subcategory":"Wood Products",
            "type":"Manufacturing & Wholesale Goods"
        }
    ],
    "sg:phone":"+1 989 356 9007",
    "sg:postcode":"49707",
    "sg:province":"MI",
    "sg:website":"www.panel.com",
    "wof:name":"Panel Processing Co",
    "wof:placetype":"venue"
},
  "geometry": {"coordinates":[-83.45896999999999,45.103607],"type":"Point"}
}