{
  "type": "Feature",
  "properties": {
    "iso:country":"US",
    "sg:address":"407 6th St",
    "sg:city":"Rochester",
    "sg:classifiers":[
        {
            "category":"Banks & Credit Unions",
            "subcategory":"Investment Brokerage",
            "type":"Services"
        }
    ],
    "sg:phone":"+1 248 601 1335",
    "sg:postcode":"48307",
    "sg:province":"MI",
    "sg:tags":[
        "advisory"
    ],
    "wof:name":"Comprehensive Inv & Svcs",
    "wof:placetype":"venue"
},
  "geometry": {"coordinates":[-83.139348,42.682883],"type":"Point"}
}