{
  "type": "Feature",
  "properties": {
    "iso:country":"US",
    "sg:address":"11641 Greenfield Rd",
    "sg:city":"Detroit",
    "sg:classifiers":[
        {
            "category":"Restaurant",
            "type":"Food & Drink"
        }
    ],
    "sg:menulink":"http://www.allmenus.com/mi/detroit/163043-rallys/menu/",
    "sg:phone":"+1 313 653 3103",
    "sg:postcode":"48227",
    "sg:province":"MI",
    "sg:tags":[
        "sandwich",
        "dog",
        "burger",
        "hot",
        "wrap",
        "american"
    ],
    "wof:name":"Rally's",
    "wof:placetype":"venue"
},
  "geometry": {"coordinates":[-83.197576,42.373173],"type":"Point"}
}