{
  "type": "Feature",
  "properties": {
    "iso:country":"US",
    "sg:address":"116 W Main St",
    "sg:city":"Dewitt",
    "sg:classifiers":[
        {
            "category":"Building & Trades",
            "subcategory":"Construction",
            "type":"Services"
        }
    ],
    "sg:phone":"+1 517 669 6187",
    "sg:postcode":"48820",
    "sg:province":"MI",
    "sg:tags":[
        "contractor"
    ],
    "wof:name":"Fred Motz Builders",
    "wof:placetype":"venue"
},
  "geometry": {"coordinates":[-84.570261,42.842295],"type":"Point"}
}