{
  "type": "Feature",
  "properties": {
    "iso:country":"US",
    "sg:address":"464 Stockford Dr",
    "sg:city":"Adrian",
    "sg:classifiers":[
        {
            "category":"Professional",
            "subcategory":"Computer Services",
            "type":"Services"
        }
    ],
    "sg:phone":"+1 517 263 9128",
    "sg:postcode":"49221",
    "sg:province":"MI",
    "wof:name":"John's PC Svc",
    "wof:placetype":"venue"
},
  "geometry": {"coordinates":[-84.046465,41.907482],"type":"Point"}
}