{
  "type": "Feature",
  "properties": {
    "iso:country":"US",
    "sg:address":"201 76th St SW",
    "sg:city":"Grand Rapids",
    "sg:classifiers":[
        {
            "category":"Autos & Motor Vehicles",
            "subcategory":"Recreational Vehicle Sales",
            "type":"Retail Goods"
        }
    ],
    "sg:phone":"+1 616 455 3250",
    "sg:postcode":"49548",
    "sg:province":"MI",
    "sg:website":"www.americanrv.com",
    "wof:name":"American RV Parts & Svc Drct",
    "wof:placetype":"venue"
},
  "geometry": {"coordinates":[-85.67184899999999,42.826249],"type":"Point"}
}