{
  "type": "Feature",
  "properties": {
    "iso:country":"US",
    "sg:address":"6405 B Dr N",
    "sg:city":"Battle Creek",
    "sg:classifiers":[
        {
            "category":"Shopping",
            "subcategory":"Pharmacy",
            "type":"Retail Goods"
        }
    ],
    "sg:phone":"+1 269 979 6610",
    "sg:postcode":"49014",
    "sg:province":"MI",
    "wof:name":"Meijer Pharmacy",
    "wof:placetype":"venue"
},
  "geometry": {"coordinates":[-85.17229,42.261135],"type":"Point"}
}