{
  "type": "Feature",
  "properties": {
    "iso:country":"US",
    "sg:address":"5252 Peekskill Dr",
    "sg:city":"Sterling Heights",
    "sg:classifiers":[
        {
            "category":"Professional",
            "subcategory":"Computer Services",
            "type":"Services"
        }
    ],
    "sg:phone":"+1 586 764 0256",
    "sg:postcode":"48310",
    "sg:province":"MI",
    "sg:tags":[
        "programing",
        "custom"
    ],
    "wof:name":"Joe Peplinkski",
    "wof:placetype":"venue"
},
  "geometry": {"coordinates":[-83.05558000000001,42.573055],"type":"Point"}
}