{
  "type": "Feature",
  "properties": {
    "iso:country":"US",
    "sg:address":"6059 Dort Hwy",
    "sg:city":"Grand Blanc",
    "sg:classifiers":[
        {
            "category":"Retail",
            "subcategory":"Car Wash",
            "type":"Services"
        }
    ],
    "sg:phone":"+1 810 606 1070",
    "sg:postcode":"48439",
    "sg:province":"MI",
    "wof:name":"Cyclone Grand Blanc Llc",
    "wof:placetype":"venue"
},
  "geometry": {"coordinates":[-83.65218400000001,42.943199],"type":"Point"}
}