{
  "type": "Feature",
  "properties": {
    "iso:country":"US",
    "sg:address":"890 Washington Ave",
    "sg:city":"Holland",
    "sg:classifiers":[
        {
            "category":"Health Services",
            "subcategory":"Doctor",
            "type":"Services"
        }
    ],
    "sg:phone":"+1 616 396 1907",
    "sg:postcode":"49423",
    "sg:province":"MI",
    "sg:tags":[
        "physician",
        "surgeon",
        "medical"
    ],
    "sg:website":"www.mmpc.com",
    "wof:name":"Michigan Medical PC",
    "wof:placetype":"venue"
},
  "geometry": {"coordinates":[-86.116716,42.765173],"type":"Point"}
}