{
  "type": "Feature",
  "properties": {
    "iso:country":"US",
    "sg:address":"505 Riverine Dr",
    "sg:city":"Traverse City",
    "sg:classifiers":[
        {
            "category":"Real Estate",
            "subcategory":"Real Estate Agent",
            "type":"Services"
        }
    ],
    "sg:phone":"+1 231 929 9337",
    "sg:postcode":"49684",
    "sg:province":"MI",
    "wof:name":"Kuschell-Belcrest Properties",
    "wof:placetype":"venue"
},
  "geometry": {"coordinates":[-85.61658199999999,44.758247],"type":"Point"}
}