{
  "type": "Feature",
  "properties": {
    "iso:country":"US",
    "sg:address":"25622 Napier Rd",
    "sg:city":"Novi",
    "sg:classifiers":[
        {
            "category":"Building & Trades",
            "subcategory":"Construction",
            "type":"Services"
        }
    ],
    "sg:phone":"+1 248 449 6889",
    "sg:postcode":"48374",
    "sg:province":"MI",
    "sg:tags":[
        "contractor"
    ],
    "wof:name":"Toll Brothers Inc",
    "wof:placetype":"venue"
},
  "geometry": {"coordinates":[-83.554125,42.475811],"type":"Point"}
}