{
  "type": "Feature",
  "properties": {
    "iso:country":"US",
    "sg:address":"13608 E Michigan Ave",
    "sg:city":"Galesburg",
    "sg:classifiers":[
        {
            "category":"Freight",
            "type":"Transportation"
        }
    ],
    "sg:phone":"+1 269 968 9900",
    "sg:postcode":"49053",
    "sg:province":"MI",
    "sg:tags":[
        "trucking"
    ],
    "wof:name":"Gertsen Interstate Systems",
    "wof:placetype":"venue"
},
  "geometry": {"coordinates":[-85.36636,42.281739],"type":"Point"}
}