{
  "type": "Feature",
  "properties": {
    "iso:country":"US",
    "sg:address":"20 E Remus Rd",
    "sg:city":"Mt Pleasant",
    "sg:classifiers":[
        {
            "category":"Restaurant",
            "type":"Food & Drink"
        }
    ],
    "sg:phone":"+1 989 773 3206",
    "sg:postcode":"48858",
    "sg:province":"MI",
    "wof:name":"Cracker Barrel General Store",
    "wof:placetype":"venue"
},
  "geometry": {"coordinates":[-84.834323,43.596813],"type":"Point"}
}