{
  "type": "Feature",
  "properties": {
    "iso:country":"US",
    "sg:address":"510 E Marengo Ave",
    "sg:city":"Flint",
    "sg:classifiers":[
        {
            "category":"Personal",
            "subcategory":"Beauty Salon",
            "type":"Services"
        }
    ],
    "sg:phone":"+1 810 249 0748",
    "sg:postcode":"48505",
    "sg:province":"MI",
    "sg:tags":[
        "hair",
        "supply",
        "accessory"
    ],
    "wof:name":"Kimberly Beauty And Barber",
    "wof:placetype":"venue"
},
  "geometry": {"coordinates":[-83.697121,43.059457],"type":"Point"}
}