{
  "type": "Feature",
  "properties": {
    "iso:country":"US",
    "sg:address":"2909 Birch Isle Rd",
    "sg:city":"Farwell",
    "sg:classifiers":[
        {
            "category":"Professional",
            "subcategory":"Secretarial Services",
            "type":"Services"
        }
    ],
    "sg:phone":"+1 989 588 4596",
    "sg:postcode":"48622",
    "sg:province":"MI",
    "sg:tags":[
        "reporting",
        "hearing"
    ],
    "wof:name":"Barbara J Duchene",
    "wof:placetype":"venue"
},
  "geometry": {"coordinates":[-84.90901700000001,43.85231],"type":"Point"}
}