{
  "type": "Feature",
  "properties": {
    "iso:country":"US",
    "sg:address":"23116 Marter Rd",
    "sg:city":"St Clair Shores",
    "sg:classifiers":[
        {
            "category":"Real Estate",
            "subcategory":"Real Estate Agent",
            "type":"Services"
        }
    ],
    "sg:phone":"+1 586 443 5042",
    "sg:postcode":"48080",
    "sg:province":"MI",
    "sg:tags":[
        "inspection"
    ],
    "wof:name":"Home Inspection Professionals",
    "wof:placetype":"venue"
},
  "geometry": {"coordinates":[-82.88364900000001,42.459445],"type":"Point"}
}