{
  "type": "Feature",
  "properties": {
    "iso:country":"US",
    "sg:address":"4701 S Chippewa Rd",
    "sg:city":"Shepherd",
    "sg:classifiers":[
        {
            "category":"Retail",
            "subcategory":"Car Wash",
            "type":"Services"
        }
    ],
    "sg:phone":"+1 989 772 7895",
    "sg:postcode":"48883",
    "sg:province":"MI",
    "sg:tags":[
        "carwash"
    ],
    "wof:name":"Rhynos Car Wash Inc",
    "wof:placetype":"venue"
},
  "geometry": {"coordinates":[-84.627776,43.572315],"type":"Point"}
}