{
  "type": "Feature",
  "properties": {
    "iso:country":"US",
    "sg:address":"2175 Lincoln St",
    "sg:city":"Marne",
    "sg:classifiers":[
        {
            "category":"Retail",
            "subcategory":"Repair Shop",
            "type":"Services"
        }
    ],
    "sg:phone":"+1 616 677 4868",
    "sg:postcode":"49435",
    "sg:province":"MI",
    "wof:name":"Life Like Rprdctions Taxidermy",
    "wof:placetype":"venue"
},
  "geometry": {"coordinates":[-85.83878,43.001883],"type":"Point"}
}