{
  "type": "Feature",
  "properties": {
    "iso:country":"US",
    "sg:address":"1750 Council Dr",
    "sg:city":"Benton Harbor",
    "sg:classifiers":[
        {
            "category":"Social Services",
            "subcategory":"Child Care",
            "type":"Services"
        }
    ],
    "sg:phone":"+1 269 926 2011",
    "sg:postcode":"49022",
    "sg:province":"MI",
    "wof:name":"Dudly's Day Care",
    "wof:placetype":"venue"
},
  "geometry": {"coordinates":[-86.416746,42.097377],"type":"Point"}
}