{
  "type": "Feature",
  "properties": {
    "iso:country":"US",
    "sg:address":"28175 Kingsberry St",
    "sg:city":"New Baltimore",
    "sg:classifiers":[
        {
            "category":"Social Services",
            "subcategory":"Adult Care",
            "type":"Services"
        }
    ],
    "sg:phone":"+1 586 949 2817",
    "sg:postcode":"48047",
    "sg:province":"MI",
    "sg:tags":[
        "residential"
    ],
    "wof:name":"Kingsberry Group Home",
    "wof:placetype":"venue"
},
  "geometry": {"coordinates":[-82.830399,42.641285],"type":"Point"}
}