{
  "type": "Feature",
  "properties": {
    "iso:country":"US",
    "sg:address":"20520 Alcoy St",
    "sg:city":"Detroit",
    "sg:classifiers":[
        {
            "category":"Retail",
            "subcategory":"Portrait Studio",
            "type":"Services"
        }
    ],
    "sg:phone":"+1 313 527 7041",
    "sg:postcode":"48205",
    "sg:province":"MI",
    "sg:tags":[
        "photo"
    ],
    "wof:name":"Face Off Photography",
    "wof:placetype":"venue"
},
  "geometry": {"coordinates":[-82.98921900000001,42.448894],"type":"Point"}
}