{
  "type": "Feature",
  "properties": {
    "iso:country":"US",
    "sg:address":"4666 Abrigador Trl NE",
    "sg:city":"Comstock Park",
    "sg:classifiers":[
        {
            "category":"Retail",
            "subcategory":"Repair Shop",
            "type":"Services"
        }
    ],
    "sg:phone":"+1 616 647 2105",
    "sg:postcode":"49321",
    "sg:province":"MI",
    "sg:tags":[
        "welding"
    ],
    "wof:name":"Michigan Welding Group",
    "wof:placetype":"venue"
},
  "geometry": {"coordinates":[-85.64902600000001,43.046779],"type":"Point"}
}