{
  "type": "Feature",
  "properties": {
    "iso:country":"US",
    "sg:address":"2721 S Fort St",
    "sg:city":"Detroit",
    "sg:classifiers":[
        {
            "category":"Personal",
            "subcategory":"Beauty Salon",
            "type":"Services"
        }
    ],
    "sg:phone":"+1 313 381 5230",
    "sg:postcode":"48217",
    "sg:province":"MI",
    "sg:tags":[
        "shop"
    ],
    "wof:name":"New ME",
    "wof:placetype":"venue"
},
  "geometry": {"coordinates":[-83.161446,42.268505],"type":"Point"}
}