{
  "type": "Feature",
  "properties": {
    "iso:country":"US",
    "sg:address":"60066 W Oak Dr",
    "sg:city":"Decatur",
    "sg:classifiers":[
        {
            "category":"Building & Trades",
            "subcategory":"Landscaping Services",
            "type":"Services"
        }
    ],
    "sg:phone":"+1 269 782 6130",
    "sg:postcode":"49045",
    "sg:province":"MI",
    "wof:name":"G&S Lawn Service",
    "wof:placetype":"venue"
},
  "geometry": {"coordinates":[-86.134818,42.106741],"type":"Point"}
}