{
  "type": "Feature",
  "properties": {
    "iso:country":"US",
    "sg:address":"19600 Woodward Ave",
    "sg:city":"Detroit",
    "sg:classifiers":[
        {
            "category":"Sports & Exercise",
            "subcategory":"Bowling",
            "type":"Entertainment"
        }
    ],
    "sg:phone":"+1 313 368 5123",
    "sg:postcode":"48203",
    "sg:province":"MI",
    "sg:website":"www.renaissancebowl.net",
    "wof:name":"Renaissance Bowling Center",
    "wof:placetype":"venue"
},
  "geometry": {"coordinates":[-83.11815,42.436793],"type":"Point"}
}