{
  "type": "Feature",
  "properties": {
    "iso:country":"US",
    "sg:address":"7110 Milford Rd",
    "sg:city":"Holly",
    "sg:classifiers":[
        {
            "category":"Education",
            "subcategory":"School",
            "type":"Public Place"
        }
    ],
    "sg:phone":"+1 248 328 3800",
    "sg:postcode":"48442",
    "sg:province":"MI",
    "sg:website":"www.hollyareaschools.com",
    "wof:name":"Rose Pioneer Elementary School",
    "wof:placetype":"venue"
},
  "geometry": {"coordinates":[-83.605321,42.701885],"type":"Point"}
}