{
  "type": "Feature",
  "properties": {
    "iso:country":"US",
    "sg:address":"23130 Elaine St",
    "sg:city":"Saint Clair Shores",
    "sg:classifiers":[
        {
            "category":"Professional",
            "subcategory":"Management & Consulting",
            "type":"Services"
        }
    ],
    "sg:phone":"+1 586 776 2626",
    "sg:postcode":"48080",
    "sg:province":"MI",
    "wof:name":"Personal & Professional Mgt",
    "wof:placetype":"venue"
},
  "geometry": {"coordinates":[-82.90949999999999,42.467709],"type":"Point"}
}