{
  "type": "Feature",
  "properties": {
    "iso:country":"US",
    "sg:address":"1363 Grandville Ave SW",
    "sg:city":"Grand Rapids",
    "sg:classifiers":[
        {
            "category":"Professional",
            "subcategory":"Management & Consulting",
            "type":"Services"
        }
    ],
    "sg:phone":"+1 616 245 3722",
    "sg:postcode":"49503",
    "sg:province":"MI",
    "sg:tags":[
        "consultant",
        "educational"
    ],
    "wof:name":"Short Books Inc",
    "wof:placetype":"venue"
},
  "geometry": {"coordinates":[-85.68454699999999,42.938482],"type":"Point"}
}