{
  "type": "Feature",
  "properties": {
    "iso:country":"US",
    "sg:address":"2073 Hiller Rd",
    "sg:city":"West Bloomfield",
    "sg:classifiers":[
        {
            "category":"Sports & Exercise",
            "subcategory":"Gym",
            "type":"Entertainment"
        }
    ],
    "sg:phone":"+1 248 738 9900",
    "sg:postcode":"48324",
    "sg:province":"MI",
    "sg:tags":[
        "club",
        "health",
        "studio",
        "gymnasium"
    ],
    "wof:name":"Curves For Women",
    "wof:placetype":"venue"
},
  "geometry": {"coordinates":[-83.398409,42.61173],"type":"Point"}
}