{
  "type": "Feature",
  "properties": {
    "iso:country":"US",
    "sg:address":"27270 Plymouth Rd",
    "sg:city":"Redford",
    "sg:classifiers":[
        {
            "category":"Professional",
            "type":"Services"
        }
    ],
    "sg:phone":"+1 313 937 0318",
    "sg:postcode":"48239",
    "sg:province":"MI",
    "wof:name":"New Redford Hall",
    "wof:placetype":"venue"
},
  "geometry": {"coordinates":[-83.311784,42.370158],"type":"Point"}
}