{
  "type": "Feature",
  "properties": {
    "iso:country":"US",
    "sg:address":"32455 Tareyton St",
    "sg:city":"Farmington Hills",
    "sg:classifiers":[
        {
            "category":"Travel",
            "subcategory":"Travel Agent",
            "type":"Entertainment"
        }
    ],
    "sg:phone":"+1 248 538 6887",
    "sg:postcode":"48334",
    "sg:province":"MI",
    "sg:tags":[
        "agency",
        "bureau"
    ],
    "wof:name":"Jubilee Travel & Tours",
    "wof:placetype":"venue"
},
  "geometry": {"coordinates":[-83.341809,42.523345],"type":"Point"}
}