{
  "type": "Feature",
  "properties": {
    "iso:country":"US",
    "sg:address":"38153 Utica Rd",
    "sg:city":"Sterling Heights",
    "sg:classifiers":[
        {
            "category":"Sports & Exercise",
            "subcategory":"Gym",
            "type":"Entertainment"
        }
    ],
    "sg:phone":"+1 586 977 5990",
    "sg:postcode":"48312",
    "sg:province":"MI",
    "sg:tags":[
        "club",
        "health",
        "studio",
        "gymnasium"
    ],
    "wof:name":"Curves For Women",
    "wof:placetype":"venue"
},
  "geometry": {"coordinates":[-82.98523400000001,42.575215],"type":"Point"}
}