{
  "type": "Feature",
  "properties": {
    "iso:country":"US",
    "sg:address":"2225 Luwanna Dr",
    "sg:city":"Lansing",
    "sg:classifiers":[
        {
            "category":"Professional",
            "subcategory":"Employment Agencies",
            "type":"Services"
        }
    ],
    "sg:phone":"+1 517 882 6283",
    "sg:postcode":"48910",
    "sg:province":"MI",
    "sg:tags":[
        "help",
        "supply"
    ],
    "wof:name":"Home Helpers",
    "wof:placetype":"venue"
},
  "geometry": {"coordinates":[-84.519685,42.693057],"type":"Point"}
}