{
  "type": "Feature",
  "properties": {
    "iso:country":"US",
    "sg:address":"6464 W B Ave",
    "sg:city":"Plainwell",
    "sg:classifiers":[
        {
            "category":"Personal",
            "subcategory":"Beauty Salon",
            "type":"Services"
        }
    ],
    "sg:phone":"+1 269 343 8190",
    "sg:postcode":"49080",
    "sg:province":"MI",
    "sg:tags":[
        "shop"
    ],
    "wof:name":"Lori's Country Boutique",
    "wof:placetype":"venue"
},
  "geometry": {"coordinates":[-85.677184,42.404705],"type":"Point"}
}