{
  "type": "Feature",
  "properties": {
    "iso:country":"US",
    "sg:address":"383 Fisher Rd",
    "sg:city":"Grosse Pointe",
    "sg:classifiers":[
        {
            "category":"Health Services",
            "subcategory":"Doctor",
            "type":"Services"
        }
    ],
    "sg:phone":"+1 313 881 5533",
    "sg:postcode":"48230",
    "sg:province":"MI",
    "sg:tags":[
        "psychiatrist"
    ],
    "wof:name":"Dorsey Edward C MD",
    "wof:placetype":"venue"
},
  "geometry": {"coordinates":[-82.90389999999999,42.390701],"type":"Point"}
}