{
  "type": "Feature",
  "properties": {
    "iso:country":"US",
    "sg:address":"38140 N Gratiot Ave",
    "sg:city":"Clinton Township",
    "sg:classifiers":[
        {
            "category":"Retail",
            "subcategory":"Auto Rental",
            "type":"Services"
        }
    ],
    "sg:phone":"+1 586 954 3700",
    "sg:postcode":"48036",
    "sg:province":"MI",
    "sg:tags":[
        "passenger",
        "car"
    ],
    "wof:name":"Enterprise Leasing Co Detroit",
    "wof:placetype":"venue"
},
  "geometry": {"coordinates":[-82.88901300000001,42.573718],"type":"Point"}
}