{
  "type": "Feature",
  "properties": {
    "iso:country":"US",
    "sg:address":"2528 S Lakeshore Rd",
    "sg:city":"Harbor Beach",
    "sg:classifiers":[
        {
            "category":"Health Services",
            "subcategory":"Clinic",
            "type":"Services"
        }
    ],
    "sg:phone":"+1 989 479 9771",
    "sg:postcode":"48441",
    "sg:province":"MI",
    "sg:tags":[
        "home",
        "care"
    ],
    "wof:name":"Devoted Home Care Inc",
    "wof:placetype":"venue"
},
  "geometry": {"coordinates":[-82.625499,43.776493],"type":"Point"}
}