{
  "type": "Feature",
  "properties": {
    "iso:country":"US",
    "sg:address":"23880 Woodward Ave",
    "sg:city":"Pleasant Ridge",
    "sg:classifiers":[
        {
            "category":"Professional",
            "subcategory":"Lawyer & Legal Services",
            "type":"Services"
        }
    ],
    "sg:phone":"+1 248 291 0500",
    "sg:postcode":"48069",
    "sg:province":"MI",
    "wof:name":"Mitchell William III",
    "wof:placetype":"venue"
},
  "geometry": {"coordinates":[-83.1408,42.4702],"type":"Point"}
}