{
  "type": "Feature",
  "properties": {
    "iso:country":"US",
    "sg:address":"1737 E Nine Mile Rd",
    "sg:city":"Ferndale",
    "sg:classifiers":[
        {
            "category":"Coffee & Tea",
            "type":"Food & Drink"
        }
    ],
    "sg:phone":"+1 248 691 4256",
    "sg:postcode":"48220",
    "sg:province":"MI",
    "sg:website":"www.chazzanocoffee.com",
    "wof:name":"Chazzano Coffee",
    "wof:placetype":"venue"
},
  "geometry": {"coordinates":[-83.11366200000001,42.461133],"type":"Point"}
}