{
  "type": "Feature",
  "properties": {
    "iso:country":"US",
    "sg:address":"490 Quarterline St",
    "sg:city":"Newaygo",
    "sg:classifiers":[
        {
            "category":"Government",
            "subcategory":"Office",
            "type":"Public Place"
        }
    ],
    "sg:phone":"+1 231 652 6763",
    "sg:postcode":"49337",
    "sg:province":"MI",
    "sg:tags":[
        "village"
    ],
    "wof:name":"Brooks Twp Office",
    "wof:placetype":"venue"
},
  "geometry": {"coordinates":[-85.788134,43.416597],"type":"Point"}
}