{
  "type": "Feature",
  "properties": {
    "iso:country":"US",
    "sg:address":"701 Main St",
    "sg:city":"St Joseph",
    "sg:classifiers":[
        {
            "category":"Government",
            "subcategory":"Office",
            "type":"Public Place"
        }
    ],
    "sg:phone":"+1 269 982 8617",
    "sg:postcode":"49085",
    "sg:province":"MI",
    "sg:website":"www.berriencounty.org",
    "wof:name":"Berrien County Planning",
    "wof:placetype":"venue"
},
  "geometry": {"coordinates":[-86.483886,42.105056],"type":"Point"}
}