{
  "type": "Feature",
  "properties": {
    "iso:country":"US",
    "sg:address":"474 W Taylor Rd",
    "sg:city":"Sanford",
    "sg:classifiers":[
        {
            "category":"Personal",
            "type":"Services"
        }
    ],
    "sg:phone":"+1 989 687 2951",
    "sg:postcode":"48657",
    "sg:province":"MI",
    "sg:tags":[
        "therapist",
        "massage"
    ],
    "wof:name":"Heidi's Healing Massage",
    "wof:placetype":"venue"
},
  "geometry": {"coordinates":[-84.386482,43.725436],"type":"Point"}
}