{
  "type": "Feature",
  "properties": {
    "iso:country":"US",
    "sg:address":"137 E Michigan Ave",
    "sg:city":"Saline",
    "sg:classifiers":[
        {
            "category":"Retail",
            "subcategory":"Portrait Studio",
            "type":"Services"
        }
    ],
    "sg:phone":"+1 734 429 5438",
    "sg:postcode":"48176",
    "sg:province":"MI",
    "sg:tags":[
        "photo"
    ],
    "wof:name":"Lifetouch",
    "wof:placetype":"venue"
},
  "geometry": {"coordinates":[-83.780973,42.166805],"type":"Point"}
}