{
  "type": "Feature",
  "properties": {
    "iso:country":"US",
    "sg:address":"76 W Adams Ave",
    "sg:city":"Detroit",
    "sg:classifiers":[
        {
            "category":"Real Estate",
            "subcategory":"Real Estate Operator",
            "type":"Services"
        }
    ],
    "sg:phone":"+1 313 963 7676",
    "sg:postcode":"48226",
    "sg:province":"MI",
    "sg:tags":[
        "apartment"
    ],
    "sg:website":"www.kales76.com",
    "wof:name":"The Kales Building",
    "wof:placetype":"venue"
},
  "geometry": {"coordinates":[-83.052291,42.336629],"type":"Point"}
}