{
  "type": "Feature",
  "properties": {
    "iso:country":"US",
    "sg:address":"1082 E Beaver Rd",
    "sg:city":"Kawkawlin",
    "sg:classifiers":[
        {
            "category":"Wholesale",
            "subcategory":"Groceries",
            "type":"Manufacturing & Wholesale Goods"
        }
    ],
    "sg:phone":"+1 989 686 7030",
    "sg:postcode":"48631",
    "sg:province":"MI",
    "sg:tags":[
        "food"
    ],
    "wof:name":"Beehive Products & More",
    "wof:placetype":"venue"
},
  "geometry": {"coordinates":[-84.005859,43.667394],"type":"Point"}
}