{
  "type": "Feature",
  "properties": {
    "iso:country":"US",
    "sg:address":"51214 Industrial Dr",
    "sg:city":"Macomb",
    "sg:classifiers":[
        {
            "category":"Professional",
            "type":"Services"
        }
    ],
    "sg:phone":"+1 586 677 7228",
    "sg:postcode":"48042",
    "sg:province":"MI",
    "sg:tags":[
        "establishment"
    ],
    "wof:name":"Krause & Mauser",
    "wof:placetype":"venue"
},
  "geometry": {"coordinates":[-82.96969300000001,42.673241],"type":"Point"}
}