{
  "type": "Feature",
  "properties": {
    "iso:country":"US",
    "sg:address":"1004 Woodward Ave",
    "sg:city":"Iron Mountain",
    "sg:classifiers":[
        {
            "category":"Professional",
            "type":"Services"
        }
    ],
    "sg:phone":"+1 906 774 0470",
    "sg:postcode":"49801",
    "sg:province":"MI",
    "wof:name":"Museum Services Inc",
    "wof:placetype":"venue"
},
  "geometry": {"coordinates":[-88.083721,45.80785],"type":"Point"}
}