{
  "type": "Feature",
  "properties": {
    "iso:country":"US",
    "sg:address":"14550 120th Ave",
    "sg:city":"Grand Haven",
    "sg:classifiers":[
        {
            "category":"Building & Trades",
            "subcategory":"Plumbing",
            "type":"Services"
        }
    ],
    "sg:phone":"+1 616 846 4070",
    "sg:postcode":"49417",
    "sg:province":"MI",
    "sg:tags":[
        "sheet",
        "work",
        "metal",
        "contractor"
    ],
    "wof:name":"Continental Installation Svc",
    "wof:placetype":"venue"
},
  "geometry": {"coordinates":[-86.086445,43.031709],"type":"Point"}
}