{
  "type": "Feature",
  "properties": {
    "iso:country":"US",
    "sg:address":"1344 US Hwy 2",
    "sg:city":"Crystal Falls",
    "sg:classifiers":[
        {
            "category":"Real Estate",
            "subcategory":"Real Estate Agent",
            "type":"Services"
        }
    ],
    "sg:phone":"+1 906 875 6331",
    "sg:postcode":"49920",
    "sg:province":"MI",
    "wof:name":"West Statewide Real Estate",
    "wof:placetype":"venue"
},
  "geometry": {"coordinates":[-88.35225199999999,46.097794],"type":"Point"}
}