{
  "type": "Feature",
  "properties": {
    "iso:country":"US",
    "sg:address":"22520 Fenkell St",
    "sg:city":"Detroit",
    "sg:classifiers":[
        {
            "category":"Autos & Motor Vehicles",
            "subcategory":"Auto Supplies",
            "type":"Retail Goods"
        }
    ],
    "sg:phone":"+1 313 535 0965",
    "sg:postcode":"48223",
    "sg:province":"MI",
    "sg:tags":[
        "tire"
    ],
    "wof:name":"Motor City Tire Service",
    "wof:placetype":"venue"
},
  "geometry": {"coordinates":[-83.26331999999999,42.400393],"type":"Point"}
}