{
  "type": "Feature",
  "properties": {
    "iso:country":"US",
    "sg:address":"3398 N Dixboro Rd",
    "sg:city":"Ann Arbor",
    "sg:classifiers":[
        {
            "category":"Building & Trades",
            "subcategory":"Construction",
            "type":"Services"
        }
    ],
    "sg:phone":"+1 734 994 8445",
    "sg:postcode":"48105",
    "sg:province":"MI",
    "sg:tags":[
        "floor",
        "laying",
        "contractor"
    ],
    "wof:name":"Expert Home Services",
    "wof:placetype":"venue"
},
  "geometry": {"coordinates":[-83.661254,42.31514],"type":"Point"}
}