{
  "type": "Feature",
  "properties": {
    "iso:country":"US",
    "sg:address":"4107 Corunna Rd",
    "sg:city":"Flint",
    "sg:classifiers":[
        {
            "category":"Autos & Motor Vehicles",
            "subcategory":"Fuel & Gas Station",
            "type":"Retail Goods"
        }
    ],
    "sg:phone":"+1 810 733 1279",
    "sg:postcode":"48532",
    "sg:province":"MI",
    "sg:tags":[
        "oil"
    ],
    "wof:name":"1 Stop Food Stores",
    "wof:placetype":"venue"
},
  "geometry": {"coordinates":[-83.741806,43.002109],"type":"Point"}
}