{
  "type": "Feature",
  "properties": {
    "iso:country":"US",
    "sg:address":"1540 Northwood St",
    "sg:city":"Ann Arbor",
    "sg:classifiers":[
        {
            "category":"Professional",
            "subcategory":"Art Services",
            "type":"Services"
        }
    ],
    "sg:phone":"+1 734 741 8081",
    "sg:postcode":"48103",
    "sg:province":"MI",
    "sg:tags":[
        "commercial",
        "design"
    ],
    "wof:name":"Patrick J Powers Design",
    "wof:placetype":"venue"
},
  "geometry": {"coordinates":[-83.76585799999999,42.27075],"type":"Point"}
}