{
  "type": "Feature",
  "properties": {
    "iso:country":"US",
    "sg:address":"1212 Wildwood Ave",
    "sg:city":"Jackson",
    "sg:classifiers":[
        {
            "category":"Personal",
            "subcategory":"Beauty Salon",
            "type":"Services"
        }
    ],
    "sg:phone":"+1 517 783 5886",
    "sg:postcode":"49202",
    "sg:province":"MI",
    "wof:name":"Melinda Creative Hair",
    "wof:placetype":"venue"
},
  "geometry": {"coordinates":[-84.429361,42.252031],"type":"Point"}
}