{
  "type": "Feature",
  "properties": {
    "iso:country":"US",
    "sg:address":"10995 Dixie Hwy",
    "sg:city":"South Rockwood",
    "sg:classifiers":[
        {
            "category":"Farming",
            "subcategory":"Livestock Farm",
            "type":"Manufacturing & Wholesale Goods"
        }
    ],
    "sg:phone":"+1 734 586 2973",
    "sg:postcode":"48179",
    "sg:province":"MI",
    "wof:name":"Robert Chapman",
    "wof:placetype":"venue"
},
  "geometry": {"coordinates":[-83.263744,42.053103],"type":"Point"}
}