{
  "type": "Feature",
  "properties": {
    "iso:country":"US",
    "sg:address":"7015 Cooley Lake Rd",
    "sg:city":"West Bloomfield",
    "sg:classifiers":[
        {
            "category":"Professional",
            "subcategory":"Printing & Photocopies",
            "type":"Services"
        }
    ],
    "sg:phone":"+1 248 360 2270",
    "sg:postcode":"48324",
    "sg:province":"MI",
    "wof:name":"Allegra Print & Imaging",
    "wof:placetype":"venue"
},
  "geometry": {"coordinates":[-83.423698,42.615398],"type":"Point"}
}