{
  "type": "Feature",
  "properties": {
    "iso:country":"US",
    "sg:address":"5695 Flinchbaugh Rd",
    "sg:city":"Kimball",
    "sg:classifiers":[
        {
            "category":"Building & Trades",
            "subcategory":"Construction",
            "type":"Services"
        }
    ],
    "sg:phone":"+1 810 982 5310",
    "sg:postcode":"48074",
    "sg:province":"MI",
    "sg:tags":[
        "hanging",
        "painter",
        "contractor"
    ],
    "wof:name":"Fretenborough Painting",
    "wof:placetype":"venue"
},
  "geometry": {"coordinates":[-82.550696,42.977986],"type":"Point"}
}