{
  "type": "Feature",
  "properties": {
    "iso:country":"US",
    "sg:address":"14441 W Warren Ave",
    "sg:city":"Dearborn",
    "sg:classifiers":[
        {
            "category":"Retail",
            "subcategory":"Auto Repair",
            "type":"Services"
        }
    ],
    "sg:phone":"+1 313 584 8770",
    "sg:postcode":"48126",
    "sg:province":"MI",
    "sg:tags":[
        "repairing",
        "automobile"
    ],
    "wof:name":"Puzzuoli's Auto Service Inc",
    "wof:placetype":"venue"
},
  "geometry": {"coordinates":[-83.184898,42.3437],"type":"Point"}
}