{
  "type": "Feature",
  "properties": {
    "iso:country":"US",
    "sg:address":"5901 Weber Rd",
    "sg:city":"Saline",
    "sg:classifiers":[
        {
            "category":"Professional",
            "type":"Services"
        }
    ],
    "sg:phone":"+1 734 429 4185",
    "sg:postcode":"48176",
    "sg:province":"MI",
    "wof:name":"Carry Dairy",
    "wof:placetype":"venue"
},
  "geometry": {"coordinates":[-83.87370199999999,42.189564],"type":"Point"}
}