{
  "type": "Feature",
  "properties": {
    "iso:country":"US",
    "sg:address":"12673 Sims Hwy",
    "sg:city":"Morenci",
    "sg:phone":"+1 517 458 7225",
    "sg:postcode":"49256",
    "sg:province":"MI",
    "sg:tags":[
        "farm",
        "corn",
        "soybean"
    ],
    "wof:name":"Arlan Murray",
    "wof:placetype":"venue"
},
  "geometry": {"coordinates":[-84.23115199999999,41.729884],"type":"Point"}
}