{
  "type": "Feature",
  "properties": {
    "iso:country":"US",
    "sg:address":"1401 S Huron St",
    "sg:city":"Ypsilanti",
    "sg:classifiers":[
        {
            "category":"Autos & Motor Vehicles",
            "subcategory":"Automobile Sales",
            "type":"Retail Goods"
        }
    ],
    "sg:phone":"+1 734 445 1212",
    "sg:postcode":"48197",
    "sg:province":"MI",
    "sg:tags":[
        "new",
        "car"
    ],
    "wof:name":"Agc Automotive Americas R&D, Inc.",
    "wof:placetype":"venue"
},
  "geometry": {"coordinates":[-83.61808000000001,42.222401],"type":"Point"}
}