{
  "type": "Feature",
  "properties": {
    "iso:country":"US",
    "sg:address":"2580 Craig Rd",
    "sg:city":"Ann Arbor",
    "sg:classifiers":[
        {
            "category":"Professional",
            "subcategory":"Lawyer & Legal Services",
            "type":"Services"
        }
    ],
    "sg:phone":"+1 734 302 3233",
    "sg:postcode":"48103",
    "sg:province":"MI",
    "wof:name":"Attorneys",
    "wof:placetype":"venue"
},
  "geometry": {"coordinates":[-83.78365100000001,42.30732],"type":"Point"}
}