{
  "type": "Feature",
  "properties": {
    "iso:country":"US",
    "sg:address":"9293 N 6th St",
    "sg:city":"Kalamazoo",
    "sg:classifiers":[
        {
            "category":"Building & Trades",
            "subcategory":"Landscaping Services",
            "type":"Services"
        }
    ],
    "sg:phone":"+1 269 720 4616",
    "sg:postcode":"49009",
    "sg:province":"MI",
    "sg:tags":[
        "landscape",
        "contractor"
    ],
    "wof:name":"Sibley & Woodhams Landscape",
    "wof:placetype":"venue"
},
  "geometry": {"coordinates":[-85.70880099999999,42.403219],"type":"Point"}
}