{
  "type": "Feature",
  "properties": {
    "iso:country":"US",
    "sg:address":"10279 River Rd",
    "sg:city":"Evart",
    "sg:classifiers":[
        {
            "category":"Organizations",
            "subcategory":"Community Association",
            "type":"Services"
        }
    ],
    "sg:phone":"+1 231 734 5950",
    "sg:postcode":"49631",
    "sg:province":"MI",
    "wof:name":"VFW Post 7979",
    "wof:placetype":"venue"
},
  "geometry": {"coordinates":[-85.324662,43.872124],"type":"Point"}
}