{
  "type": "Feature",
  "properties": {
    "iso:country":"US",
    "sg:address":"49900 Fairchild Rd",
    "sg:city":"Chesterfield",
    "sg:classifiers":[
        {
            "category":"Real Estate",
            "subcategory":"Real Estate Operator",
            "type":"Services"
        }
    ],
    "sg:phone":"+1 586 949 3970",
    "sg:postcode":"48051",
    "sg:province":"MI",
    "sg:tags":[
        "mobile",
        "home",
        "site",
        "community"
    ],
    "wof:name":"Chateau Chesterfield",
    "wof:placetype":"venue"
},
  "geometry": {"coordinates":[-82.85303399999999,42.67442],"type":"Point"}
}