{
  "type": "Feature",
  "properties": {
    "iso:country":"US",
    "sg:address":"3605 Oakville Waltz Rd",
    "sg:city":"Carleton",
    "sg:classifiers":[
        {
            "category":"Home & Garden",
            "subcategory":"Hardware",
            "type":"Retail Goods"
        }
    ],
    "sg:phone":"+1 734 654 2896",
    "sg:postcode":"48117",
    "sg:province":"MI",
    "sg:tags":[
        "tool",
        "used"
    ],
    "wof:name":"Tractors N Tools",
    "wof:placetype":"venue"
},
  "geometry": {"coordinates":[-83.43048,42.087579],"type":"Point"}
}