{
  "type": "Feature",
  "properties": {
    "iso:country":"US",
    "sg:address":"2162 Kewaunee Ct",
    "sg:city":"Traverse City",
    "sg:classifiers":[
        {
            "category":"Health Services",
            "subcategory":"Health Practitioner",
            "type":"Services"
        }
    ],
    "sg:phone":"+1 231 929 3575",
    "sg:postcode":"49686",
    "sg:province":"MI",
    "sg:tags":[
        "therapist",
        "physical"
    ],
    "wof:name":"Keenan Therapeutics",
    "wof:placetype":"venue"
},
  "geometry": {"coordinates":[-85.57455899999999,44.775071],"type":"Point"}
}