{
  "type": "Feature",
  "properties": {
    "iso:country":"US",
    "sg:address":"1907 Presque Isle Ave",
    "sg:city":"Marquette",
    "sg:classifiers":[
        {
            "category":"Restaurant",
            "type":"Food & Drink"
        }
    ],
    "sg:phone":"+1 906 228 6229",
    "sg:postcode":"49855",
    "sg:province":"MI",
    "wof:name":"Toarmina's Pizza",
    "wof:placetype":"venue"
},
  "geometry": {"coordinates":[-87.39616100000001,46.567573],"type":"Point"}
}