{
  "type": "Feature",
  "properties": {
    "iso:country":"US",
    "sg:address":"2528 Glenlord Rd",
    "sg:city":"Stevensville",
    "sg:classifiers":[
        {
            "category":"Restaurant",
            "type":"Food & Drink"
        }
    ],
    "sg:phone":"+1 269 429 5800",
    "sg:postcode":"49127",
    "sg:province":"MI",
    "wof:name":"Pedro's",
    "wof:placetype":"venue"
},
  "geometry": {"coordinates":[-86.516651,42.043351],"type":"Point"}
}