{
  "type": "Feature",
  "properties": {
    "iso:country":"US",
    "sg:address":"118 W Saginaw Rd",
    "sg:city":"Sanford",
    "sg:classifiers":[
        {
            "category":"Government",
            "subcategory":"Office",
            "type":"Public Place"
        }
    ],
    "sg:phone":"+1 989 687 7771",
    "sg:postcode":"48657",
    "sg:province":"MI",
    "sg:tags":[
        "state"
    ],
    "wof:name":"Natural Resources Dept",
    "wof:placetype":"venue"
},
  "geometry": {"coordinates":[-84.37235099999999,43.668802],"type":"Point"}
}