{
  "type": "Feature",
  "properties": {
    "iso:country":"US",
    "sg:address":"12954 8th Ave NW",
    "sg:city":"Grand Rapids",
    "sg:classifiers":[
        {
            "category":"Freight",
            "type":"Transportation"
        }
    ],
    "sg:phone":"+1 616 498 6090",
    "sg:postcode":"49544",
    "sg:province":"MI",
    "sg:tags":[
        "carriage"
    ],
    "wof:name":"Classic Carriage",
    "wof:placetype":"venue"
},
  "geometry": {"coordinates":[-85.806039,43.005948],"type":"Point"}
}