{
  "type": "Feature",
  "properties": {
    "iso:country":"US",
    "sg:address":"1034 Chester St SE",
    "sg:city":"Grand Rapids",
    "sg:classifiers":[
        {
            "category":"Building & Trades",
            "subcategory":"Construction",
            "type":"Services"
        }
    ],
    "sg:phone":"+1 616 742 0157",
    "sg:postcode":"49506",
    "sg:province":"MI",
    "sg:tags":[
        "house"
    ],
    "wof:name":"Kare Kraft Remodeling",
    "wof:placetype":"venue"
},
  "geometry": {"coordinates":[-85.643252,42.95856],"type":"Point"}
}