{
  "type": "Feature",
  "properties": {
    "iso:country":"US",
    "sg:address":"372 E Napier Ave",
    "sg:city":"Benton Harbor",
    "sg:classifiers":[
        {
            "category":"Building & Trades",
            "subcategory":"Construction",
            "type":"Services"
        }
    ],
    "sg:phone":"+1 269 926 8705",
    "sg:postcode":"49022",
    "sg:province":"MI",
    "sg:tags":[
        "house"
    ],
    "wof:name":"Premier Builders",
    "wof:placetype":"venue"
},
  "geometry": {"coordinates":[-86.44883299999999,42.087077],"type":"Point"}
}