{
  "type": "Feature",
  "properties": {
    "iso:country":"US",
    "sg:address":"16751 May Ave",
    "sg:city":"Eastpointe",
    "sg:classifiers":[
        {
            "category":"Professional",
            "subcategory":"Business Services",
            "type":"Services"
        }
    ],
    "sg:phone":"+1 586 778 5121",
    "sg:postcode":"48021",
    "sg:province":"MI",
    "wof:name":"Production Dock Solutions Inc",
    "wof:placetype":"venue"
},
  "geometry": {"coordinates":[-82.946792,42.476299],"type":"Point"}
}