{
  "type": "Feature",
  "properties": {
    "iso:country":"US",
    "sg:address":"520 S Michigan St",
    "sg:city":"Omer",
    "sg:classifiers":[
        {
            "category":"Professional",
            "subcategory":"Management & Consulting",
            "type":"Services"
        }
    ],
    "sg:phone":"+1 989 653 2583",
    "sg:postcode":"48749",
    "sg:province":"MI",
    "sg:tags":[
        "retail",
        "direct",
        "sales"
    ],
    "wof:name":"Richard Batko",
    "wof:placetype":"venue"
},
  "geometry": {"coordinates":[-83.857168,44.040534],"type":"Point"}
}