{
  "type": "Feature",
  "properties": {
    "iso:country":"US",
    "sg:address":"6603 Main St",
    "sg:city":"Caseville",
    "sg:classifiers":[
        {
            "category":"Shopping",
            "subcategory":"Gifts & Souvenirs",
            "type":"Retail Goods"
        }
    ],
    "sg:phone":"+1 989 856 4488",
    "sg:postcode":"48725",
    "sg:province":"MI",
    "sg:tags":[
        "shop"
    ],
    "wof:name":"Pigeon Hole",
    "wof:placetype":"venue"
},
  "geometry": {"coordinates":[-83.27240999999999,43.941431],"type":"Point"}
}