{
  "type": "Feature",
  "properties": {
    "iso:country":"US",
    "sg:address":"183 Washington St",
    "sg:city":"Sunfield",
    "sg:classifiers":[
        {
            "category":"Organizations",
            "subcategory":"Professional Association",
            "type":"Services"
        }
    ],
    "sg:phone":"+1 517 566 8599",
    "sg:postcode":"48890",
    "sg:province":"MI",
    "wof:name":"Steve Sharp National Wild Trky",
    "wof:placetype":"venue"
},
  "geometry": {"coordinates":[-84.993666,42.76156],"type":"Point"}
}