{
  "type": "Feature",
  "properties": {
    "iso:country":"US",
    "sg:address":"622 Theo Ave",
    "sg:city":"Lansing",
    "sg:classifiers":[
        {
            "category":"Retail",
            "subcategory":"Car Wash",
            "type":"Services"
        }
    ],
    "sg:phone":"+1 517 886 2169",
    "sg:postcode":"48917",
    "sg:province":"MI",
    "sg:tags":[
        "carwash"
    ],
    "wof:name":"His Auto Detailing",
    "wof:placetype":"venue"
},
  "geometry": {"coordinates":[-84.618168,42.738435],"type":"Point"}
}