{
  "type": "Feature",
  "properties": {
    "iso:country":"US",
    "sg:address":"2482 Orchard Lake Rd",
    "sg:city":"Keego Harbor",
    "sg:classifiers":[
        {
            "category":"Building & Trades",
            "subcategory":"Construction",
            "type":"Services"
        }
    ],
    "sg:phone":"+1 248 682 8375",
    "sg:postcode":"48320",
    "sg:province":"MI",
    "sg:tags":[
        "contractor"
    ],
    "wof:name":"Misieks Tile Inc",
    "wof:placetype":"venue"
},
  "geometry": {"coordinates":[-83.334524,42.609438],"type":"Point"}
}