{
  "type": "Feature",
  "properties": {
    "iso:country":"US",
    "sg:address":"30500 Northwestern Hwy",
    "sg:city":"Farmington Hills",
    "sg:classifiers":[
        {
            "category":"Banks & Credit Unions",
            "subcategory":"Bank",
            "type":"Services"
        }
    ],
    "sg:phone":"+1 248 324 1600",
    "sg:postcode":"48334",
    "sg:province":"MI",
    "sg:tags":[
        "factor"
    ],
    "wof:name":"Commission Express Of Michigan",
    "wof:placetype":"venue"
},
  "geometry": {"coordinates":[-83.331155,42.513843],"type":"Point"}
}