{
  "type": "Feature",
  "properties": {
    "iso:country":"US",
    "sg:address":"129 N Front St",
    "sg:city":"Lake City",
    "sg:classifiers":[
        {
            "category":"Personal",
            "subcategory":"Beauty Salon",
            "type":"Services"
        }
    ],
    "sg:phone":"+1 231 839 7587",
    "sg:postcode":"49651",
    "sg:province":"MI",
    "sg:tags":[
        "shop"
    ],
    "wof:name":"Dimensions Salon & Tanning",
    "wof:placetype":"venue"
},
  "geometry": {"coordinates":[-85.215834,44.335717],"type":"Point"}
}