{
  "type": "Feature",
  "properties": {
    "iso:country":"US",
    "sg:address":"5580 Main St",
    "sg:city":"Dryden",
    "sg:classifiers":[
        {
            "category":"Government",
            "subcategory":"Post Office",
            "type":"Public Place"
        }
    ],
    "sg:phone":"+1 810 796 3760",
    "sg:postcode":"48428",
    "sg:province":"MI",
    "wof:name":"US Post Office",
    "wof:placetype":"venue"
},
  "geometry": {"coordinates":[-83.12278999999999,42.945975],"type":"Point"}
}