{
  "type": "Feature",
  "properties": {
    "iso:country":"US",
    "sg:address":"17111 Farmington Rd",
    "sg:city":"Livonia",
    "sg:classifiers":[
        {
            "category":"Autos & Motor Vehicles",
            "subcategory":"Fuel & Gas Station",
            "type":"Retail Goods"
        }
    ],
    "sg:phone":"+1 734 522 4330",
    "sg:postcode":"48152",
    "sg:province":"MI",
    "wof:name":"Farmington and Six Mobilservice",
    "wof:placetype":"venue"
},
  "geometry": {"coordinates":[-83.3741,42.4119],"type":"Point"}
}