{
  "type": "Feature",
  "properties": {
    "iso:country":"US",
    "sg:address":"1133 Stokes St NE",
    "sg:city":"Grand Rapids",
    "sg:classifiers":[
        {
            "category":"Building & Trades",
            "subcategory":"Cleaning & Sanitation",
            "type":"Services"
        }
    ],
    "sg:phone":"+1 616 364 8953",
    "sg:postcode":"49505",
    "sg:province":"MI",
    "sg:tags":[
        "maintenance"
    ],
    "wof:name":"River City Cleaning & Maintena",
    "wof:placetype":"venue"
},
  "geometry": {"coordinates":[-85.640337,43.020115],"type":"Point"}
}