{
  "type": "Feature",
  "properties": {
    "iso:country":"US",
    "sg:address":"1809 23rd Ave",
    "sg:city":"Menominee",
    "sg:classifiers":[
        {
            "category":"Shopping",
            "subcategory":"Stationery & Office Supplies",
            "type":"Retail Goods"
        }
    ],
    "sg:phone":"+1 906 863 3848",
    "sg:postcode":"49858",
    "sg:province":"MI",
    "sg:tags":[
        "rubber",
        "stamp",
        "plastic"
    ],
    "wof:name":"J & G Rubber Stamps",
    "wof:placetype":"venue"
},
  "geometry": {"coordinates":[-87.62561599999999,45.119797],"type":"Point"}
}