{
  "type": "Feature",
  "properties": {
    "iso:country":"US",
    "sg:address":"15578 Warwick Ave",
    "sg:city":"Allen Park",
    "sg:classifiers":[
        {
            "category":"Shopping",
            "subcategory":"Computers & Home Electronics",
            "type":"Retail Goods"
        }
    ],
    "sg:phone":"+1 313 388 3426",
    "sg:postcode":"48101",
    "sg:province":"MI",
    "sg:tags":[
        "dish",
        "satellite"
    ],
    "wof:name":"Star Gazer",
    "wof:placetype":"venue"
},
  "geometry": {"coordinates":[-83.203722,42.264742],"type":"Point"}
}