{
  "type": "Feature",
  "properties": {
    "iso:country":"US",
    "sg:address":"1801 Howard St",
    "sg:city":"Detroit",
    "sg:classifiers":[
        {
            "category":"Manufacturing",
            "subcategory":"Tools & Machinery",
            "type":"Manufacturing & Wholesale Goods"
        }
    ],
    "sg:phone":"+1 313 963 6114",
    "sg:postcode":"48216",
    "sg:province":"MI",
    "sg:tags":[
        "manufacture",
        "bag",
        "air"
    ],
    "wof:name":"Aguirre Safety Tech LLC",
    "wof:placetype":"venue"
},
  "geometry": {"coordinates":[-83.066014,42.325142],"type":"Point"}
}