{
  "type": "Feature",
  "properties": {
    "iso:country":"US",
    "sg:address":"695 W Chicago Rd",
    "sg:city":"Coldwater",
    "sg:classifiers":[
        {
            "category":"Autos & Motor Vehicles",
            "subcategory":"Automobile Sales",
            "type":"Retail Goods"
        }
    ],
    "sg:phone":"+1 517 279 8300",
    "sg:postcode":"49028",
    "sg:province":"MI",
    "sg:tags":[
        "car",
        "dealer"
    ],
    "wof:name":"Fast Lane Auto Sales",
    "wof:placetype":"venue"
},
  "geometry": {"coordinates":[-85.174967,41.875433],"type":"Point"}
}