{
  "type": "Feature",
  "properties": {
    "iso:country":"US",
    "sg:address":"5170 Harrand Rd",
    "sg:city":"Buckley",
    "sg:classifiers":[
        {
            "category":"Farming",
            "subcategory":"Livestock Farm",
            "type":"Manufacturing & Wholesale Goods"
        }
    ],
    "sg:phone":"+1 231 263 7735",
    "sg:postcode":"49620",
    "sg:province":"MI",
    "sg:tags":[
        "beef",
        "feedlot",
        "cattle"
    ],
    "wof:name":"Joseph Yanska Farm",
    "wof:placetype":"venue"
},
  "geometry": {"coordinates":[-85.68915699999999,44.570444],"type":"Point"}
}