{
  "type": "Feature",
  "properties": {
    "iso:country":"US",
    "sg:address":"232 S Capitol Ave",
    "sg:city":"Lansing",
    "sg:classifiers":[
        {
            "category":"Government",
            "subcategory":"Office",
            "type":"Public Place"
        }
    ],
    "sg:phone":"+1 517 487 9360",
    "sg:postcode":"48933",
    "sg:province":"MI",
    "sg:tags":[
        "housing"
    ],
    "wof:name":"Michigan Housing Council",
    "wof:placetype":"venue"
},
  "geometry": {"coordinates":[-84.553972,42.731768],"type":"Point"}
}