{
  "type": "Feature",
  "properties": {
    "iso:country":"US",
    "sg:address":"23768 West Rd",
    "sg:city":"Brownstown Twp",
    "sg:classifiers":[
        {
            "category":"Shopping",
            "subcategory":"Optician",
            "type":"Retail Goods"
        }
    ],
    "sg:phone":"+1 734 692 7763",
    "sg:postcode":"48183",
    "sg:province":"MI",
    "sg:tags":[
        "eyewear"
    ],
    "sg:website":"www.redfordoptical.com",
    "wof:name":"Redford Optical",
    "wof:placetype":"venue"
},
  "geometry": {"coordinates":[-83.263293,42.13828],"type":"Point"}
}