{
  "type": "Feature",
  "properties": {
    "iso:country":"US",
    "sg:address":"31780 Telegraph Rd Ste 250",
    "sg:city":"Bingham Farms",
    "sg:classifiers":[
        {
            "category":"Professional",
            "subcategory":"Lawyer & Legal Services",
            "type":"Services"
        }
    ],
    "sg:phone":"+1 248 530 5544",
    "sg:postcode":"48025",
    "sg:province":"MI",
    "wof:name":"Law Offices of Ronald R Gold",
    "wof:placetype":"venue"
},
  "geometry": {"coordinates":[-83.285464,42.521205],"type":"Point"}
}