{
  "type": "Feature",
  "properties": {
    "iso:country":"US",
    "sg:address":"16560 Harper Ave",
    "sg:city":"Detroit",
    "sg:classifiers":[
        {
            "category":"Retail",
            "subcategory":"Auto Repair",
            "type":"Services"
        }
    ],
    "sg:phone":"+1 313 343 2800",
    "sg:postcode":"48224",
    "sg:province":"MI",
    "wof:name":"Alex's All Star Complete Auto Repair",
    "wof:placetype":"venue"
},
  "geometry": {"coordinates":[-82.94151599999999,42.412897],"type":"Point"}
}