{
  "type": "Feature",
  "properties": {
    "iso:country":"US",
    "sg:address":"5972 S Lake St",
    "sg:city":"Glen Arbor",
    "sg:classifiers":[
        {
            "category":"Food & Beverages",
            "subcategory":"Liquor & Beverages",
            "type":"Retail Goods"
        }
    ],
    "sg:phone":"+1 231 334 3024",
    "sg:postcode":"49636",
    "sg:province":"MI",
    "sg:tags":[
        "wine"
    ],
    "wof:name":"J & I Wine Shop",
    "wof:placetype":"venue"
},
  "geometry": {"coordinates":[-85.98880800000001,44.899216],"type":"Point"}
}