{
  "type": "Feature",
  "properties": {
    "iso:country":"US",
    "sg:address":"1795 Allen Rd",
    "sg:city":"Smiths Creek",
    "sg:classifiers":[
        {
            "category":"Retail",
            "subcategory":"Auto Repair",
            "type":"Services"
        }
    ],
    "sg:phone":"+1 810 985 7706",
    "sg:postcode":"48074",
    "sg:province":"MI",
    "sg:tags":[
        "body"
    ],
    "wof:name":"Kleeves Collision",
    "wof:placetype":"venue"
},
  "geometry": {"coordinates":[-82.52295599999999,42.959543],"type":"Point"}
}