{
  "type": "Feature",
  "properties": {
    "iso:country":"US",
    "sg:address":"5 Ransom Ave NE",
    "sg:city":"Grand Rapids",
    "sg:classifiers":[
        {
            "category":"Restaurant",
            "type":"Food & Drink"
        }
    ],
    "sg:phone":"+1 616 742 0801",
    "sg:postcode":"49503",
    "sg:province":"MI",
    "sg:tags":[
        "eating"
    ],
    "wof:name":"Liquid Room",
    "wof:placetype":"venue"
},
  "geometry": {"coordinates":[-85.665049,42.964159],"type":"Point"}
}