{
  "type": "Feature",
  "properties": {
    "iso:country":"US",
    "sg:address":"17496 Meadow Wood Rd",
    "sg:city":"Spring Lake",
    "sg:classifiers":[
        {
            "category":"Professional",
            "subcategory":"Employment Agencies",
            "type":"Services"
        }
    ],
    "sg:phone":"+1 616 846 3774",
    "sg:postcode":"49456",
    "sg:province":"MI",
    "wof:name":"Schwartz Consulting Service",
    "wof:placetype":"venue"
},
  "geometry": {"coordinates":[-86.222236,43.092366],"type":"Point"}
}