{
  "type": "Feature",
  "properties": {
    "iso:country":"US",
    "sg:address":"477 30th St",
    "sg:city":"Allegan",
    "sg:classifiers":[
        {
            "category":"Building & Trades",
            "subcategory":"Plumbing",
            "type":"Services"
        }
    ],
    "sg:phone":"+1 269 686 9425",
    "sg:postcode":"49010",
    "sg:province":"MI",
    "sg:tags":[
        "heating",
        "contractor"
    ],
    "wof:name":"Advantage Heating & Air Cond",
    "wof:placetype":"venue"
},
  "geometry": {"coordinates":[-85.83274,42.461399],"type":"Point"}
}