{
  "type": "Feature",
  "properties": {
    "iso:country":"US",
    "sg:address":"8515 Pontiac Lake Rd",
    "sg:city":"White Lake",
    "sg:classifiers":[
        {
            "category":"Social Services",
            "type":"Services"
        }
    ],
    "sg:phone":"+1 248 666 1785",
    "sg:postcode":"48386",
    "sg:province":"MI",
    "wof:name":"Pence & Sons Enterprises",
    "wof:placetype":"venue"
},
  "geometry": {"coordinates":[-83.45470899999999,42.661829],"type":"Point"}
}