{
  "type": "Feature",
  "properties": {
    "iso:country":"US",
    "sg:address":"3303 Grand Ridge Dr NE",
    "sg:city":"Grand Rapids",
    "sg:classifiers":[
        {
            "category":"Health Services",
            "subcategory":"Doctor",
            "type":"Services"
        }
    ],
    "sg:phone":"+1 616 363 3821",
    "sg:postcode":"49525",
    "sg:province":"MI",
    "sg:tags":[
        "dentist"
    ],
    "wof:name":"Professional Dental Care/Assoc",
    "wof:placetype":"venue"
},
  "geometry": {"coordinates":[-85.58743800000001,42.993187],"type":"Point"}
}