{
  "type": "Feature",
  "properties": {
    "iso:country":"US",
    "sg:address":"14020 S Telegraph",
    "sg:city":"Carleton",
    "sg:classifiers":[
        {
            "category":"Retail",
            "subcategory":"Auto Repair",
            "type":"Services"
        }
    ],
    "sg:phone":"+1 734 782 0575",
    "sg:postcode":"48117",
    "sg:province":"MI",
    "wof:name":"A & M Transmissions Inc",
    "wof:placetype":"venue"
},
  "geometry": {"coordinates":[-83.401901,42.049801],"type":"Point"}
}