{
  "type": "Feature",
  "properties": {
    "iso:country":"US",
    "sg:address":"20755 Greenfield Rd",
    "sg:city":"Southfield",
    "sg:classifiers":[
        {
            "category":"Health Services",
            "subcategory":"Doctor",
            "type":"Services"
        }
    ],
    "sg:phone":"+1 248 557 7546",
    "sg:postcode":"48075",
    "sg:province":"MI",
    "wof:name":"Richardson Peggy MD PC",
    "wof:placetype":"venue"
},
  "geometry": {"coordinates":[-83.20075799999999,42.445101],"type":"Point"}
}