{
  "type": "Feature",
  "properties": {
    "iso:country":"US",
    "sg:address":"213 Paw Paw St",
    "sg:city":"Coloma",
    "sg:classifiers":[
        {
            "category":"Health Services",
            "subcategory":"Doctor",
            "type":"Services"
        }
    ],
    "sg:phone":"+1 269 468 5741",
    "sg:postcode":"49038",
    "sg:province":"MI",
    "sg:tags":[
        "dentist"
    ],
    "wof:name":"Darlene S Getz DDS",
    "wof:placetype":"venue"
},
  "geometry": {"coordinates":[-86.302881,42.192711],"type":"Point"}
}