{
  "type": "Feature",
  "properties": {
    "iso:country":"US",
    "sg:address":"2828 Monticello Dr",
    "sg:city":"Port Huron",
    "sg:classifiers":[
        {
            "category":"Manufacturing",
            "subcategory":"Printing",
            "type":"Manufacturing & Wholesale Goods"
        }
    ],
    "sg:phone":"+1 810 985 5386",
    "sg:postcode":"48060",
    "sg:province":"MI",
    "sg:tags":[
        "screen"
    ],
    "wof:name":"Genie Screen Printing",
    "wof:placetype":"venue"
},
  "geometry": {"coordinates":[-82.45068499999999,43.005705],"type":"Point"}
}