{
  "type": "Feature",
  "properties": {
    "iso:country":"US",
    "sg:address":"1258 Oxford Rd",
    "sg:city":"Berkley",
    "sg:classifiers":[
        {
            "category":"Manufacturing",
            "subcategory":"Printing",
            "type":"Manufacturing & Wholesale Goods"
        }
    ],
    "sg:phone":"+1 248 658 6103",
    "sg:postcode":"48072",
    "sg:province":"MI",
    "sg:tags":[
        "publisher"
    ],
    "wof:name":"Conquest Corp",
    "wof:placetype":"venue"
},
  "geometry": {"coordinates":[-83.166296,42.49415],"type":"Point"}
}