{
  "type": "Feature",
  "properties": {
    "iso:country":"US",
    "sg:address":"1378 S Clark Rd",
    "sg:city":"Dansville",
    "sg:classifiers":[
        {
            "category":"Social Services",
            "subcategory":"Child Care",
            "type":"Services"
        }
    ],
    "sg:phone":"+1 517 623 6441",
    "sg:postcode":"48819",
    "sg:province":"MI",
    "sg:tags":[
        "day"
    ],
    "wof:name":"Sugarfoot Acers Daycare",
    "wof:placetype":"venue"
},
  "geometry": {"coordinates":[-84.324793,42.541421],"type":"Point"}
}