{
  "type": "Feature",
  "properties": {
    "iso:country":"US",
    "sg:address":"5950 W Dunbar Rd",
    "sg:city":"Monroe",
    "sg:classifiers":[
        {
            "category":"Retail",
            "subcategory":"Auto Repair",
            "type":"Services"
        }
    ],
    "sg:phone":"+1 734 242 6688",
    "sg:postcode":"48161",
    "sg:province":"MI",
    "sg:tags":[
        "body"
    ],
    "wof:name":"Macks Body Shop Inc",
    "wof:placetype":"venue"
},
  "geometry": {"coordinates":[-83.41420599999999,41.900012],"type":"Point"}
}