{
  "type": "Feature",
  "properties": {
    "iso:country":"US",
    "sg:address":"9930 Secor Rd",
    "sg:city":"Temperance",
    "sg:classifiers":[
        {
            "category":"Building & Trades",
            "subcategory":"Construction",
            "type":"Services"
        }
    ],
    "sg:phone":"+1 734 856 2242",
    "sg:postcode":"48182",
    "sg:province":"MI",
    "wof:name":"Brads Driveway Sealing Svc",
    "wof:placetype":"venue"
},
  "geometry": {"coordinates":[-83.627522,41.794845],"type":"Point"}
}