{
  "type": "Feature",
  "properties": {
    "iso:country":"US",
    "sg:address":"8140 N 32nd St",
    "sg:city":"Richland",
    "sg:classifiers":[
        {
            "category":"Shopping",
            "subcategory":"Jewelry",
            "type":"Retail Goods"
        }
    ],
    "sg:phone":"+1 269 629 0102",
    "sg:postcode":"49083",
    "sg:province":"MI",
    "sg:tags":[
        "jeweler"
    ],
    "wof:name":"Richland Jewel Gallery",
    "wof:placetype":"venue"
},
  "geometry": {"coordinates":[-85.455195,42.378571],"type":"Point"}
}