{
  "type": "Feature",
  "properties": {
    "iso:country":"US",
    "sg:address":"41650 Gardenbrook Rd",
    "sg:city":"Novi",
    "sg:classifiers":[
        {
            "category":"Professional",
            "subcategory":"Engineering",
            "type":"Services"
        },
        {
            "category":"Manufacturing",
            "subcategory":"Glass & Minerals",
            "type":"Manufacturing & Wholesale Goods"
        }
    ],
    "sg:phone":"+1 248 380 7878",
    "sg:postcode":"48375",
    "sg:province":"MI",
    "sg:tags":[
        "design",
        "mirror"
    ],
    "wof:name":"Ichikoh Manufacturing Inc",
    "wof:placetype":"venue"
},
  "geometry": {"coordinates":[-83.457054,42.483379],"type":"Point"}
}