{
  "type": "Feature",
  "properties": {
    "iso:country":"US",
    "sg:address":"18161 Shoreline Ct",
    "sg:city":"Northville",
    "sg:classifiers":[
        {
            "category":"Sports & Exercise",
            "subcategory":"Gym",
            "type":"Entertainment"
        }
    ],
    "sg:phone":"+1 734 458 4000",
    "sg:postcode":"48168",
    "sg:province":"MI",
    "sg:tags":[
        "health",
        "center",
        "fitness"
    ],
    "wof:name":"Fat Terminator",
    "wof:placetype":"venue"
},
  "geometry": {"coordinates":[-83.466089,42.417457],"type":"Point"}
}