{
  "type": "Feature",
  "properties": {
    "iso:country":"US",
    "sg:address":"11204 N Adrian Hwy",
    "sg:city":"Clinton",
    "sg:classifiers":[
        {
            "category":"Organizations",
            "subcategory":"Religious Organization",
            "type":"Services"
        }
    ],
    "sg:phone":"+1 517 456 7358",
    "sg:postcode":"49236",
    "sg:province":"MI",
    "sg:tags":[
        "church"
    ],
    "wof:name":"Church Of God",
    "wof:placetype":"venue"
},
  "geometry": {"coordinates":[-84.007035,42.046233],"type":"Point"}
}