{
  "type": "Feature",
  "properties": {
    "iso:country":"US",
    "sg:address":"4217 39th St",
    "sg:city":"Holland",
    "sg:classifiers":[
        {
            "category":"Farming",
            "subcategory":"Farm",
            "type":"Manufacturing & Wholesale Goods"
        }
    ],
    "sg:phone":"+1 616 688 5891",
    "sg:postcode":"49423",
    "sg:province":"MI",
    "sg:tags":[
        "crop",
        "general"
    ],
    "wof:name":"Duane Arendsen",
    "wof:placetype":"venue"
},
  "geometry": {"coordinates":[-85.929079,42.725313],"type":"Point"}
}