{
  "type": "Feature",
  "properties": {
    "iso:country":"US",
    "sg:address":"1400 Orion Rd",
    "sg:city":"Lake Orion",
    "sg:classifiers":[
        {
            "category":"Organizations",
            "subcategory":"Community Association",
            "type":"Services"
        }
    ],
    "sg:phone":"+1 248 693 9824",
    "sg:postcode":"48362",
    "sg:province":"MI",
    "sg:tags":[
        "fraternal"
    ],
    "wof:name":"Knights Of Columbus",
    "wof:placetype":"venue"
},
  "geometry": {"coordinates":[-83.217483,42.772886],"type":"Point"}
}