{
  "type": "Feature",
  "properties": {
    "iso:country":"US",
    "sg:address":"8008 US Hwy 2",
    "sg:city":"Rapid River",
    "sg:classifiers":[
        {
            "category":"Retail",
            "subcategory":"Auto Rental",
            "type":"Services"
        }
    ],
    "sg:phone":"+1 906 474 9657",
    "sg:postcode":"49878",
    "sg:province":"MI",
    "sg:tags":[
        "renting",
        "truck",
        "leasing"
    ],
    "wof:name":"U-Haul Co",
    "wof:placetype":"venue"
},
  "geometry": {"coordinates":[-86.962328,45.926654],"type":"Point"}
}