{
  "type": "Feature",
  "properties": {
    "iso:country":"US",
    "sg:address":"440 Lyon Ct",
    "sg:city":"South Lyon",
    "sg:classifiers":[
        {
            "category":"Restaurant",
            "type":"Food & Drink"
        }
    ],
    "sg:phone":"+1 248 446 0236",
    "sg:postcode":"48178",
    "sg:province":"MI",
    "wof:name":"Wendy's",
    "wof:placetype":"venue"
},
  "geometry": {"coordinates":[-83.64379599999999,42.463863],"type":"Point"}
}