{
  "type": "Feature",
  "properties": {
    "iso:country":"US",
    "sg:address":"5360 S Saginaw Rd",
    "sg:city":"Flint",
    "sg:classifiers":[
        {
            "category":"Retail",
            "subcategory":"Auto Repair",
            "type":"Services"
        }
    ],
    "sg:phone":"+1 810 694 4132",
    "sg:postcode":"48507",
    "sg:province":"MI",
    "sg:tags":[
        "repairing",
        "automobile"
    ],
    "wof:name":"Al's Radiator & Auto Svc",
    "wof:placetype":"venue"
},
  "geometry": {"coordinates":[-83.65832,42.951779],"type":"Point"}
}