{
  "type": "Feature",
  "properties": {
    "iso:country":"US",
    "sg:address":"6981 M 221",
    "sg:city":"Brimley",
    "sg:classifiers":[
        {
            "category":"Government",
            "subcategory":"Post Office",
            "type":"Public Place"
        }
    ],
    "sg:phone":"+1 906 248 3221",
    "sg:postcode":"49715",
    "sg:province":"MI",
    "wof:name":"US Post Office",
    "wof:placetype":"venue"
},
  "geometry": {"coordinates":[-84.572163,46.404352],"type":"Point"}
}