{
  "type": "Feature",
  "properties": {
    "iso:country":"US",
    "sg:address":"2820 E Delhi Rd",
    "sg:city":"Ann Arbor",
    "sg:classifiers":[
        {
            "category":"Health Services",
            "subcategory":"Doctor",
            "type":"Services"
        }
    ],
    "sg:phone":"+1 734 913 4806",
    "sg:postcode":"48103",
    "sg:province":"MI",
    "sg:tags":[
        "medical"
    ],
    "wof:name":"Kim A Eagle MD",
    "wof:placetype":"venue"
},
  "geometry": {"coordinates":[-83.81234499999999,42.323899],"type":"Point"}
}