{
  "type": "Feature",
  "properties": {
    "iso:country":"US",
    "sg:address":"4140 W Coon Lake Rd",
    "sg:city":"Howell",
    "sg:classifiers":[
        {
            "category":"Manufacturing",
            "subcategory":"Tools & Machinery",
            "type":"Manufacturing & Wholesale Goods"
        }
    ],
    "sg:phone":"+1 517 552 1249",
    "sg:postcode":"48843",
    "sg:province":"MI",
    "sg:tags":[
        "equipment",
        "sauna",
        "supply"
    ],
    "sg:website":"www.heattherapyprod.com",
    "wof:name":"Heat Therapy Products",
    "wof:placetype":"venue"
},
  "geometry": {"coordinates":[-83.990323,42.546113],"type":"Point"}
}