{
  "type": "Feature",
  "properties": {
    "iso:country":"US",
    "sg:address":"381 I- 75 Bus",
    "sg:city":"Grayling",
    "sg:classifiers":[
        {
            "category":"Banks & Credit Unions",
            "subcategory":"Bank",
            "type":"Services"
        }
    ],
    "sg:phone":"+1 989 348 5435",
    "sg:postcode":"49738",
    "sg:province":"MI",
    "wof:name":"Fifth Third Bank",
    "wof:placetype":"venue"
},
  "geometry": {"coordinates":[-84.717814,44.679377],"type":"Point"}
}