{
  "type": "Feature",
  "properties": {
    "iso:country":"US",
    "sg:address":"1203 S Centerville Rd",
    "sg:city":"Sturgis",
    "sg:classifiers":[
        {
            "category":"Social Services",
            "subcategory":"Job Training",
            "type":"Services"
        }
    ],
    "sg:phone":"+1 269 659 6339",
    "sg:postcode":"49091",
    "sg:province":"MI",
    "wof:name":"Goodwill Ind Southwestern MI",
    "wof:placetype":"venue"
},
  "geometry": {"coordinates":[-85.428229,41.788801],"type":"Point"}
}