{
  "type": "Feature",
  "properties": {
    "iso:country":"US",
    "sg:address":"9999 Pebble Creek Ct",
    "sg:city":"Davisburg",
    "sg:classifiers":[
        {
            "category":"Building & Trades",
            "subcategory":"Construction",
            "type":"Services"
        }
    ],
    "sg:phone":"+1 248 922 1094",
    "sg:postcode":"48350",
    "sg:province":"MI",
    "sg:tags":[
        "house",
        "nonresidential"
    ],
    "wof:name":"Doson Inc",
    "wof:placetype":"venue"
},
  "geometry": {"coordinates":[-83.486217,42.75467],"type":"Point"}
}