{
  "type": "Feature",
  "properties": {
    "iso:country":"US",
    "sg:address":"7202 Division Ave S",
    "sg:city":"Grand Rapids",
    "sg:classifiers":[
        {
            "category":"Autos & Motor Vehicles",
            "subcategory":"Automobile Sales",
            "type":"Retail Goods"
        }
    ],
    "sg:phone":"+1 616 281 2340",
    "sg:postcode":"49548",
    "sg:province":"MI",
    "sg:tags":[
        "car",
        "dealer"
    ],
    "wof:name":"Jeff's Motor Sales",
    "wof:placetype":"venue"
},
  "geometry": {"coordinates":[-85.663545,42.832646],"type":"Point"}
}