{
  "type": "Feature",
  "properties": {
    "iso:country":"US",
    "sg:address":"1065 Peck St",
    "sg:city":"Muskegon",
    "sg:classifiers":[
        {
            "category":"Professional",
            "subcategory":"Lawyer & Legal Services",
            "type":"Services"
        }
    ],
    "sg:phone":"+1 231 728 6160",
    "sg:postcode":"49441",
    "sg:province":"MI",
    "wof:name":"West Jffrey P Attorney At Law",
    "wof:placetype":"venue"
},
  "geometry": {"coordinates":[-86.244145,43.233409],"type":"Point"}
}