{
  "type": "Feature",
  "properties": {
    "iso:country":"US",
    "sg:address":"15401 Mack Ave",
    "sg:city":"Detroit",
    "sg:classifiers":[
        {
            "category":"Restaurant",
            "type":"Food & Drink"
        }
    ],
    "sg:phone":"+1 313 886 6050",
    "sg:postcode":"48224",
    "sg:province":"MI",
    "wof:name":"Chinatown Carry-Out",
    "wof:placetype":"venue"
},
  "geometry": {"coordinates":[-82.94259599999999,42.388302],"type":"Point"}
}