{
  "type": "Feature",
  "properties": {
    "iso:country":"US",
    "sg:address":"6193 Miller Rd",
    "sg:city":"Swartz Creek",
    "sg:classifiers":[
        {
            "category":"Health Services",
            "subcategory":"Doctor",
            "type":"Services"
        }
    ],
    "sg:phone":"+1 810 630 1937",
    "sg:postcode":"48473",
    "sg:province":"MI",
    "sg:tags":[
        "medical"
    ],
    "wof:name":"Brown A Errol DC",
    "wof:placetype":"venue"
},
  "geometry": {"coordinates":[-83.80165100000001,42.969076],"type":"Point"}
}