{
  "type": "Feature",
  "properties": {
    "iso:country":"US",
    "sg:address":"840 Belknap St",
    "sg:city":"Grand Ledge",
    "sg:classifiers":[
        {
            "category":"Professional",
            "subcategory":"Engineering",
            "type":"Services"
        }
    ],
    "sg:phone":"+1 517 627 5821",
    "sg:postcode":"48837",
    "sg:province":"MI",
    "wof:name":"Ledges Enterprises Inc",
    "wof:placetype":"venue"
},
  "geometry": {"coordinates":[-84.74316,42.747033],"type":"Point"}
}