{
  "type": "Feature",
  "properties": {
    "iso:country":"US",
    "sg:address":"955 Ken O Sha Ind Park Dr SE",
    "sg:city":"Grand Rapids",
    "sg:classifiers":[
        {
            "category":"Wholesale",
            "subcategory":"Machinery & Supplies",
            "type":"Manufacturing & Wholesale Goods"
        }
    ],
    "sg:phone":"+1 616 475 8130",
    "sg:postcode":"49508",
    "sg:province":"MI",
    "sg:tags":[
        "concrete",
        "mixer"
    ],
    "wof:name":"CEPI",
    "wof:placetype":"venue"
},
  "geometry": {"coordinates":[-85.640649,42.908053],"type":"Point"}
}