{
  "type": "Feature",
  "properties": {
    "iso:country":"US",
    "sg:address":"1741 Sensabaugh Rd",
    "sg:city":"Lupton",
    "sg:classifiers":[
        {
            "category":"Farming",
            "subcategory":"Farm",
            "type":"Manufacturing & Wholesale Goods"
        }
    ],
    "sg:phone":"+1 989 473 2034",
    "sg:postcode":"48635",
    "sg:province":"MI",
    "sg:tags":[
        "crop",
        "general"
    ],
    "wof:name":"Herman Sensabaugh",
    "wof:placetype":"venue"
},
  "geometry": {"coordinates":[-84.01498599999999,44.368936],"type":"Point"}
}