{
  "type": "Feature",
  "properties": {
    "iso:country":"US",
    "sg:address":"3950 S Rochester Rd",
    "sg:city":"Rochester",
    "sg:classifiers":[
        {
            "category":"Health Services",
            "subcategory":"Doctor",
            "type":"Services"
        }
    ],
    "sg:phone":"+1 248 844 8845",
    "sg:postcode":"48307",
    "sg:province":"MI",
    "sg:tags":[
        "reproductive"
    ],
    "wof:name":"Center For Rprductive Medicine",
    "wof:placetype":"venue"
},
  "geometry": {"coordinates":[-83.130859,42.624029],"type":"Point"}
}