{
  "type": "Feature",
  "properties": {
    "iso:country":"US",
    "sg:address":"580 Frederick St",
    "sg:city":"Detroit",
    "sg:classifiers":[
        {
            "category":"Landmark",
            "subcategory":"Historic",
            "type":"Public Place"
        }
    ],
    "sg:postcode":"48218",
    "sg:province":"MI",
    "sg:tags":[
        "building",
        "historical"
    ],
    "wof:name":"Dunbar Hospital",
    "wof:placetype":"venue"
},
  "geometry": {"coordinates":[-83.05876600000001,42.361896],"type":"Point"}
}