{
  "type": "Feature",
  "properties": {
    "iso:country":"US",
    "sg:address":"14372 Northland Dr",
    "sg:city":"Big Rapids",
    "sg:classifiers":[
        {
            "category":"Sports & Exercise",
            "subcategory":"Bowling",
            "type":"Entertainment"
        }
    ],
    "sg:phone":"+1 231 796 5713",
    "sg:postcode":"49307",
    "sg:province":"MI",
    "sg:tags":[
        "center"
    ],
    "wof:name":"Bleachers",
    "wof:placetype":"venue"
},
  "geometry": {"coordinates":[-85.48339199999999,43.674839],"type":"Point"}
}