{
  "type": "Feature",
  "properties": {
    "iso:country":"US",
    "sg:address":"2080 River Rd",
    "sg:city":"Marysville",
    "sg:classifiers":[
        {
            "category":"Sports & Exercise",
            "subcategory":"Golf",
            "type":"Entertainment"
        }
    ],
    "sg:phone":"+1 810 364 4653",
    "sg:postcode":"48040",
    "sg:province":"MI",
    "sg:tags":[
        "course"
    ],
    "wof:name":"Marysville Golf Course",
    "wof:placetype":"venue"
},
  "geometry": {"coordinates":[-82.47530999999999,42.889654],"type":"Point"}
}