{
  "type": "Feature",
  "properties": {
    "iso:country":"US",
    "sg:address":"21114 Walton St",
    "sg:city":"St Clair Shores",
    "sg:classifiers":[
        {
            "category":"Manufacturing",
            "subcategory":"Printing",
            "type":"Manufacturing & Wholesale Goods"
        }
    ],
    "sg:phone":"+1 586 465 4138",
    "sg:postcode":"48081",
    "sg:province":"MI",
    "sg:tags":[
        "bookbinder"
    ],
    "wof:name":"IMG Book Bindery",
    "wof:placetype":"venue"
},
  "geometry": {"coordinates":[-82.90518400000001,42.490845],"type":"Point"}
}