{
  "type": "Feature",
  "properties": {
    "iso:country":"US",
    "sg:address":"1807 Vanderbilt Ave",
    "sg:city":"Portage",
    "sg:classifiers":[
        {
            "category":"Retail",
            "subcategory":"Repair Shop",
            "type":"Services"
        }
    ],
    "sg:phone":"+1 269 323 2254",
    "sg:postcode":"49024",
    "sg:province":"MI",
    "sg:tags":[
        "appliance"
    ],
    "wof:name":"Nelson's Appliance Svc",
    "wof:placetype":"venue"
},
  "geometry": {"coordinates":[-85.613158,42.182801],"type":"Point"}
}