{
  "type": "Feature",
  "properties": {
    "iso:country":"US",
    "sg:address":"199 N Main St Ste 204",
    "sg:city":"Plymouth",
    "sg:classifiers":[
        {
            "category":"Personal",
            "subcategory":"Massage",
            "type":"Services"
        }
    ],
    "sg:phone":"+1 734 451 7880",
    "sg:postcode":"48170",
    "sg:province":"MI",
    "wof:name":"Certified Massage Therapy",
    "wof:placetype":"venue"
},
  "geometry": {"coordinates":[-83.46520200000001,42.3741],"type":"Point"}
}