{
  "type": "Feature",
  "properties": {
    "iso:country":"US",
    "sg:address":"11390 Culver Rd",
    "sg:city":"Cement City",
    "sg:classifiers":[
        {
            "category":"Building & Trades",
            "subcategory":"Cleaning & Sanitation",
            "type":"Services"
        }
    ],
    "sg:phone":"+1 517 529 4467",
    "sg:postcode":"49233",
    "sg:province":"MI",
    "sg:tags":[
        "maintenance"
    ],
    "wof:name":"Grime Busters",
    "wof:placetype":"venue"
},
  "geometry": {"coordinates":[-84.387984,42.094784],"type":"Point"}
}