{
  "type": "Feature",
  "properties": {
    "iso:country":"US",
    "sg:address":"9488 Adams St",
    "sg:city":"Zeeland",
    "sg:classifiers":[
        {
            "category":"Building & Trades",
            "subcategory":"Plumbing",
            "type":"Services"
        }
    ],
    "sg:phone":"+1 616 772 1963",
    "sg:postcode":"49464",
    "sg:province":"MI",
    "sg:tags":[
        "plumbing",
        "contractor"
    ],
    "wof:name":"Van Rhee Plumbing",
    "wof:placetype":"venue"
},
  "geometry": {"coordinates":[-86.015102,42.783368],"type":"Point"}
}