{
  "type": "Feature",
  "properties": {
    "iso:country":"US",
    "sg:address":"5649 Dixie Hwy",
    "sg:city":"Waterford",
    "sg:classifiers":[
        {
            "category":"Shopping",
            "subcategory":"Jewelry",
            "type":"Retail Goods"
        }
    ],
    "sg:phone":"+1 248 623 9422",
    "sg:postcode":"48329",
    "sg:province":"MI",
    "sg:tags":[
        "repair",
        "precious",
        "watch",
        "performs"
    ],
    "sg:website":"www.awaterfall.com",
    "wof:name":"Waterfall Jewelers",
    "wof:placetype":"venue"
},
  "geometry": {"coordinates":[-83.400182,42.700184],"type":"Point"}
}