{
  "type": "Feature",
  "properties": {
    "iso:country":"US",
    "sg:address":"4645 Cains Dr",
    "sg:city":"Houghton Lake",
    "sg:classifiers":[
        {
            "category":"Retail",
            "subcategory":"Auto Repair",
            "type":"Services"
        }
    ],
    "sg:phone":"+1 989 422 4241",
    "sg:postcode":"48629",
    "sg:province":"MI",
    "sg:tags":[
        "general",
        "wrecker",
        "welding"
    ],
    "wof:name":"Meadows Welding & Auto Repr",
    "wof:placetype":"venue"
},
  "geometry": {"coordinates":[-84.78926199999999,44.40079],"type":"Point"}
}