{
  "type": "Feature",
  "properties": {
    "iso:country":"US",
    "sg:address":"2797 E Arbor Rd",
    "sg:city":"Ann Arbor",
    "sg:classifiers":[
        {
            "category":"Building & Trades",
            "subcategory":"Landscaping Services",
            "type":"Services"
        }
    ],
    "sg:phone":"+1 734 741 0886",
    "sg:postcode":"48103",
    "sg:province":"MI",
    "wof:name":"AA Landscaping & Lawn Care",
    "wof:placetype":"venue"
},
  "geometry": {"coordinates":[-83.781786,42.244364],"type":"Point"}
}