{
  "type": "Feature",
  "properties": {
    "iso:country":"US",
    "sg:address":"2151 N Cochran Rd",
    "sg:city":"Charlotte",
    "sg:phone":"+1 517 543 4579",
    "sg:postcode":"48813",
    "sg:province":"MI",
    "sg:tags":[
        "farm",
        "field",
        "crop"
    ],
    "wof:name":"Joe White",
    "wof:placetype":"venue"
},
  "geometry": {"coordinates":[-84.836319,42.604475],"type":"Point"}
}