{
  "type": "Feature",
  "properties": {
    "iso:country":"US",
    "sg:address":"712 Ashmun St",
    "sg:city":"Sault Ste Marie",
    "sg:classifiers":[
        {
            "category":"Restaurant",
            "type":"Food & Drink"
        }
    ],
    "sg:phone":"+1 906 632 0800",
    "sg:postcode":"49783",
    "sg:province":"MI",
    "wof:name":"Domino's Pizza",
    "wof:placetype":"venue"
},
  "geometry": {"coordinates":[-84.349936,46.494683],"type":"Point"}
}