{
  "type": "Feature",
  "properties": {
    "iso:country":"US",
    "sg:address":"12365 US Hwy 23",
    "sg:city":"Ossineke",
    "sg:classifiers":[
        {
            "category":"Organizations",
            "subcategory":"Religious Organization",
            "type":"Services"
        }
    ],
    "sg:phone":"+1 989 471 5428",
    "sg:postcode":"49766",
    "sg:province":"MI",
    "sg:tags":[
        "church"
    ],
    "wof:name":"Good Shepherd Lutheran Church",
    "wof:placetype":"venue"
},
  "geometry": {"coordinates":[-83.441164,44.898885],"type":"Point"}
}