{
  "type": "Feature",
  "properties": {
    "iso:country":"US",
    "sg:address":"10565 Grandview Ln",
    "sg:city":"Ironwood",
    "sg:classifiers":[
        {
            "category":"Health Services",
            "subcategory":"Clinic",
            "type":"Services"
        },
        {
            "category":"Health Services",
            "subcategory":"Doctor",
            "type":"Services"
        }
    ],
    "sg:phone":"+1 906 932 5080",
    "sg:postcode":"49938",
    "sg:province":"MI",
    "sg:tags":[
        "physician",
        "medical",
        "specialty",
        "outpatient",
        "ambulatory",
        "surgeon"
    ],
    "wof:name":"Grand View Hospital Clinic",
    "wof:placetype":"venue"
},
  "geometry": {"coordinates":[-90.104709,46.477955],"type":"Point"}
}