{
  "type": "Feature",
  "properties": {
    "iso:country":"US",
    "sg:address":"18404 Greenwald Dr",
    "sg:city":"Southfield",
    "sg:classifiers":[
        {
            "category":"Personal",
            "subcategory":"Beauty Salon",
            "type":"Services"
        }
    ],
    "sg:phone":"+1 313 862 8104",
    "sg:postcode":"48075",
    "sg:province":"MI",
    "sg:tags":[
        "shop"
    ],
    "wof:name":"Larry Swygert Hair Studio",
    "wof:placetype":"venue"
},
  "geometry": {"coordinates":[-83.22300199999999,42.453969],"type":"Point"}
}