{
  "type": "Feature",
  "properties": {
    "iso:country":"US",
    "sg:address":"627 Prospect St",
    "sg:city":"Ionia",
    "sg:classifiers":[
        {
            "category":"Real Estate",
            "subcategory":"Real Estate Agent",
            "type":"Services"
        }
    ],
    "sg:phone":"+1 616 527 1966",
    "sg:postcode":"48846",
    "sg:province":"MI",
    "wof:name":"Gregmark Place LLC",
    "wof:placetype":"venue"
},
  "geometry": {"coordinates":[-85.049161,42.989393],"type":"Point"}
}