{
  "type": "Feature",
  "properties": {
    "iso:country":"US",
    "sg:address":"9320 Old US Hwy 223",
    "sg:city":"Ottawa Lake",
    "sg:classifiers":[
        {
            "category":"Building & Trades",
            "subcategory":"Construction",
            "type":"Services"
        }
    ],
    "sg:phone":"+1 734 856 5477",
    "sg:postcode":"49267",
    "sg:province":"MI",
    "sg:tags":[
        "hanging",
        "contractor"
    ],
    "wof:name":"Wallppring By Angie Chrstensen",
    "wof:placetype":"venue"
},
  "geometry": {"coordinates":[-83.75187200000001,41.78722],"type":"Point"}
}