{
  "type": "Feature",
  "properties": {
    "iso:country":"US",
    "sg:address":"2719 Courier Dr NW",
    "sg:city":"Grand Rapids",
    "sg:classifiers":[
        {
            "category":"Manufacturing",
            "subcategory":"Paper Products",
            "type":"Manufacturing & Wholesale Goods"
        }
    ],
    "sg:phone":"+1 616 791 7222",
    "sg:postcode":"49534",
    "sg:province":"MI",
    "sg:tags":[
        "bag"
    ],
    "sg:website":"www.polybags.com",
    "wof:name":"Apac Manufacturing",
    "wof:placetype":"venue"
},
  "geometry": {"coordinates":[-85.760203,43.014996],"type":"Point"}
}