{
  "type": "Feature",
  "properties": {
    "iso:country":"US",
    "sg:address":"53318 Ruann Dr",
    "sg:city":"Utica",
    "sg:classifiers":[
        {
            "category":"Restaurant",
            "type":"Food & Drink"
        }
    ],
    "sg:phone":"+1 586 677 4503",
    "sg:postcode":"48316",
    "sg:province":"MI",
    "sg:tags":[
        "eating"
    ],
    "wof:name":"Great Lakes Coffee House Inc",
    "wof:placetype":"venue"
},
  "geometry": {"coordinates":[-83.039942,42.687877],"type":"Point"}
}