{
  "type": "Feature",
  "properties": {
    "iso:country":"US",
    "sg:address":"15700 W 10 Mile Rd",
    "sg:city":"Southfield",
    "sg:classifiers":[
        {
            "category":"Real Estate",
            "subcategory":"Real Estate Agent",
            "type":"Services"
        }
    ],
    "sg:phone":"+1 248 354 3700",
    "sg:postcode":"48075",
    "sg:province":"MI",
    "wof:name":"Dowdell Realty Inc",
    "wof:placetype":"venue"
},
  "geometry": {"coordinates":[-83.20410200000001,42.473869],"type":"Point"}
}