{
  "type": "Feature",
  "properties": {
    "iso:country":"US",
    "sg:address":"915 Harmon St",
    "sg:city":"Birmingham",
    "sg:classifiers":[
        {
            "category":"Shopping",
            "subcategory":"Clothing, Apparel, & Fashions",
            "type":"Retail Goods"
        }
    ],
    "sg:phone":"+1 248 203 6928",
    "sg:postcode":"48009",
    "sg:province":"MI",
    "wof:name":"Frosting Fashions",
    "wof:placetype":"venue"
},
  "geometry": {"coordinates":[-83.22661100000001,42.549554],"type":"Point"}
}