{
  "type": "Feature",
  "properties": {
    "iso:country":"US",
    "sg:address":"17576 Parkside St",
    "sg:city":"Detroit",
    "sg:classifiers":[
        {
            "category":"Professional",
            "subcategory":"Management & Consulting",
            "type":"Services"
        }
    ],
    "sg:phone":"+1 313 610 6436",
    "sg:postcode":"48221",
    "sg:province":"MI",
    "sg:tags":[
        "review",
        "consultation",
        "grant",
        "writing"
    ],
    "wof:name":"En-Jay Enterprises",
    "wof:placetype":"venue"
},
  "geometry": {"coordinates":[-83.13181299999999,42.42247],"type":"Point"}
}