{
  "type": "Feature",
  "properties": {
    "iso:country":"US",
    "sg:address":"360 E Allegan St",
    "sg:city":"Otsego",
    "sg:classifiers":[
        {
            "category":"Shopping",
            "subcategory":"Gifts & Souvenirs",
            "type":"Retail Goods"
        }
    ],
    "sg:phone":"+1 269 692 2220",
    "sg:postcode":"49078",
    "sg:province":"MI",
    "sg:tags":[
        "party",
        "supply"
    ],
    "wof:name":"R P M's",
    "wof:placetype":"venue"
},
  "geometry": {"coordinates":[-85.691509,42.459314],"type":"Point"}
}