{
  "type": "Feature",
  "properties": {
    "iso:country":"US",
    "sg:address":"339 Walnut Blvd",
    "sg:city":"Rochester",
    "sg:classifiers":[
        {
            "category":"Retail",
            "subcategory":"Funeral Services",
            "type":"Services"
        }
    ],
    "sg:phone":"+1 248 651 5956",
    "sg:postcode":"48307",
    "sg:province":"MI",
    "sg:tags":[
        "director"
    ],
    "wof:name":"Silverbell Chapel Modetz Family",
    "wof:placetype":"venue"
},
  "geometry": {"coordinates":[-83.135295,42.679864],"type":"Point"}
}