{
  "type": "Feature",
  "properties": {
    "iso:country":"US",
    "sg:address":"6149 N Wayne Rd",
    "sg:city":"Westland",
    "sg:classifiers":[
        {
            "category":"Health Services",
            "subcategory":"Doctor",
            "type":"Services"
        }
    ],
    "sg:phone":"+1 734 728 4141",
    "sg:postcode":"48185",
    "sg:province":"MI",
    "sg:tags":[
        "medicine",
        "internal"
    ],
    "wof:name":"Raminick William DO",
    "wof:placetype":"venue"
},
  "geometry": {"coordinates":[-83.387703,42.329399],"type":"Point"}
}