{
  "type": "Feature",
  "properties": {
    "iso:country":"US",
    "sg:address":"750 Rickett Rd",
    "sg:city":"Brighton",
    "sg:classifiers":[
        {
            "category":"Manufacturing",
            "subcategory":"Tools & Machinery",
            "type":"Manufacturing & Wholesale Goods"
        }
    ],
    "sg:phone":"+1 810 229 9521",
    "sg:postcode":"48116",
    "sg:province":"MI",
    "sg:website":"www.weldmold.com",
    "wof:name":"Weld Mold Co",
    "wof:placetype":"venue"
},
  "geometry": {"coordinates":[-83.777018,42.523235],"type":"Point"}
}