{
  "type": "Feature",
  "properties": {
    "iso:country":"US",
    "sg:address":"4417 W Wackerly St",
    "sg:city":"Midland",
    "sg:classifiers":[
        {
            "category":"Education",
            "subcategory":"School",
            "type":"Public Place"
        }
    ],
    "sg:phone":"+1 517 835 9881",
    "sg:postcode":"48640",
    "sg:province":"MI",
    "wof:name":"Midland Christian School Assn",
    "wof:placetype":"venue"
},
  "geometry": {"coordinates":[-84.28075200000001,43.654962],"type":"Point"}
}