{
  "type": "Feature",
  "properties": {
    "iso:country":"US",
    "sg:address":"201 Broadus St",
    "sg:city":"Sturgis",
    "sg:classifiers":[
        {
            "category":"Professional",
            "subcategory":"Accounting & Tax Preparation",
            "type":"Services"
        }
    ],
    "sg:phone":"+1 269 651 8978",
    "sg:postcode":"49091",
    "sg:province":"MI",
    "wof:name":"Medical Insurance Aid Services",
    "wof:placetype":"venue"
},
  "geometry": {"coordinates":[-85.433239,41.801173],"type":"Point"}
}