{
  "type": "Feature",
  "properties": {
    "iso:country":"US",
    "sg:address":"9222 McKinley Rd",
    "sg:city":"Montrose",
    "sg:classifiers":[
        {
            "category":"Social Services",
            "subcategory":"Adult Care",
            "type":"Services"
        }
    ],
    "sg:phone":"+1 810 639 7994",
    "sg:postcode":"48457",
    "sg:province":"MI",
    "sg:tags":[
        "home",
        "residential"
    ],
    "wof:name":"Leineke Foster Care Home",
    "wof:placetype":"venue"
},
  "geometry": {"coordinates":[-83.85969299999999,43.138294],"type":"Point"}
}