{
  "type": "Feature",
  "properties": {
    "iso:country":"US",
    "sg:address":"925 Hampton Ave",
    "sg:city":"Owosso",
    "sg:classifiers":[
        {
            "category":"Education",
            "subcategory":"School",
            "type":"Public Place"
        }
    ],
    "sg:phone":"+1 989 723 4355",
    "sg:postcode":"48867",
    "sg:province":"MI",
    "wof:name":"Bryant Elementary School",
    "wof:placetype":"venue"
},
  "geometry": {"coordinates":[-84.18361299999999,42.986693],"type":"Point"}
}