{
  "type": "Feature",
  "properties": {
    "iso:country":"US",
    "sg:address":"4180 Fort St",
    "sg:city":"Lincoln Park",
    "sg:classifiers":[
        {
            "category":"Restaurant",
            "type":"Food & Drink"
        }
    ],
    "sg:menulink":"http://www.allmenus.com/mi/lincoln-park/185989-mcdonalds/menu/",
    "sg:postcode":"48146",
    "sg:province":"MI",
    "sg:tags":[
        "burger",
        "american"
    ],
    "wof:name":"McDonald's",
    "wof:placetype":"venue"
},
  "geometry": {"coordinates":[-83.181445,42.222748],"type":"Point"}
}