{
  "type": "Feature",
  "properties": {
    "iso:country":"US",
    "sg:address":"215 N Kalamazoo St",
    "sg:city":"Paw Paw",
    "sg:classifiers":[
        {
            "category":"Real Estate",
            "subcategory":"Real Estate Agent",
            "type":"Services"
        }
    ],
    "sg:phone":"+1 269 657 6002",
    "sg:postcode":"49079",
    "sg:province":"MI",
    "sg:tags":[
        "title",
        "agency",
        "insurance",
        "escrow"
    ],
    "wof:name":"Chicago Title",
    "wof:placetype":"venue"
},
  "geometry": {"coordinates":[-85.890832,42.2194],"type":"Point"}
}