{
  "type": "Feature",
  "properties": {
    "iso:country":"US",
    "sg:address":"3776 Hollywood Rd",
    "sg:city":"St Joseph",
    "sg:classifiers":[
        {
            "category":"Health Services",
            "subcategory":"Doctor",
            "type":"Services"
        }
    ],
    "sg:phone":"+1 269 556 0523",
    "sg:postcode":"49085",
    "sg:province":"MI",
    "sg:tags":[
        "physician",
        "surgeon"
    ],
    "wof:name":"Lakeland Medical Ctr",
    "wof:placetype":"venue"
},
  "geometry": {"coordinates":[-86.45589699999999,42.04419],"type":"Point"}
}