{
  "type": "Feature",
  "properties": {
    "iso:country":"US",
    "sg:address":"716 E Front St",
    "sg:city":"Buchanan",
    "sg:classifiers":[
        {
            "category":"Manufacturing",
            "subcategory":"Food",
            "type":"Manufacturing & Wholesale Goods"
        }
    ],
    "sg:phone":"+1 269 695 8000",
    "sg:postcode":"49107",
    "sg:province":"MI",
    "sg:tags":[
        "winery"
    ],
    "wof:name":"Wyncroft",
    "wof:placetype":"venue"
},
  "geometry": {"coordinates":[-86.353011,41.827278],"type":"Point"}
}