{
  "type": "Feature",
  "properties": {
    "iso:country":"US",
    "sg:address":"13114 W Warren Ave",
    "sg:city":"Dearborn",
    "sg:classifiers":[
        {
            "category":"Food & Beverages",
            "subcategory":"Groceries & Convenience Stores",
            "type":"Retail Goods"
        }
    ],
    "sg:phone":"+1 313 581 0525",
    "sg:postcode":"48126",
    "sg:province":"MI",
    "wof:name":"Harb's Imports",
    "wof:placetype":"venue"
},
  "geometry": {"coordinates":[-83.1726,42.3442],"type":"Point"}
}