{
  "type": "Feature",
  "properties": {
    "iso:country":"US",
    "sg:address":"2301 W Lotan Rd",
    "sg:city":"Mc Bain",
    "sg:classifiers":[
        {
            "category":"Retail",
            "subcategory":"Repair Shop",
            "type":"Services"
        }
    ],
    "sg:phone":"+1 231 826 4438",
    "sg:postcode":"49657",
    "sg:province":"MI",
    "sg:tags":[
        "refrigeration",
        "refrigerator",
        "freezer"
    ],
    "wof:name":"Jerry's Refrigeration & Air",
    "wof:placetype":"venue"
},
  "geometry": {"coordinates":[-85.14982500000001,44.280514],"type":"Point"}
}