{
  "type": "Feature",
  "properties": {
    "iso:country":"US",
    "sg:address":"503 Livernois St",
    "sg:city":"Ferndale",
    "sg:classifiers":[
        {
            "category":"Building & Trades",
            "subcategory":"Construction",
            "type":"Services"
        }
    ],
    "sg:phone":"+1 248 543 6575",
    "sg:postcode":"48220",
    "sg:province":"MI",
    "sg:tags":[
        "dry wall",
        "contractor"
    ],
    "wof:name":"Russell Plastering Co",
    "wof:placetype":"venue"
},
  "geometry": {"coordinates":[-83.142701,42.452131],"type":"Point"}
}