{
  "type": "Feature",
  "properties": {
    "iso:country":"US",
    "sg:address":"22109 West Rd",
    "sg:city":"Trenton",
    "sg:classifiers":[
        {
            "category":"Banks & Credit Unions",
            "subcategory":"Bank",
            "type":"Services"
        }
    ],
    "sg:phone":"+1 734 675 9600",
    "sg:postcode":"48183",
    "sg:province":"MI",
    "sg:tags":[
        "federal",
        "personal",
        "institution"
    ],
    "wof:name":"Rouge Employees Credit Union",
    "wof:placetype":"venue"
},
  "geometry": {"coordinates":[-83.24725100000001,42.138316],"type":"Point"}
}