{
  "type": "Feature",
  "properties": {
    "iso:country":"US",
    "sg:address":"8328 Sierra Madre Trl",
    "sg:city":"Kalamazoo",
    "sg:classifiers":[
        {
            "category":"Professional",
            "subcategory":"Business Services",
            "type":"Services"
        }
    ],
    "sg:phone":"+1 269 372 5613",
    "sg:postcode":"49009",
    "sg:province":"MI",
    "wof:name":"6th Street Limited Partnership",
    "wof:placetype":"venue"
},
  "geometry": {"coordinates":[-85.71267,42.241869],"type":"Point"}
}