{
  "type": "Feature",
  "properties": {
    "iso:country":"US",
    "sg:address":"120 Delaware St",
    "sg:city":"Sandusky",
    "sg:classifiers":[
        {
            "category":"Professional",
            "subcategory":"Research",
            "type":"Services"
        }
    ],
    "sg:phone":"+1 810 648 5490",
    "sg:postcode":"48471",
    "sg:province":"MI",
    "sg:tags":[
        "laboratory"
    ],
    "wof:name":"Laboratory Corp Of America",
    "wof:placetype":"venue"
},
  "geometry": {"coordinates":[-82.832989,43.424488],"type":"Point"}
}