{
  "type": "Feature",
  "properties": {
    "iso:country":"US",
    "sg:address":"60261 State Hwy 43",
    "sg:city":"Bangor",
    "sg:classifiers":[
        {
            "category":"Organizations",
            "subcategory":"Religious Organization",
            "type":"Services"
        }
    ],
    "sg:phone":"+1 269 427 5298",
    "sg:postcode":"49013",
    "sg:province":"MI",
    "sg:tags":[
        "church"
    ],
    "wof:name":"Seventh-Day Adventist Church",
    "wof:placetype":"venue"
},
  "geometry": {"coordinates":[-86.12993899999999,42.320137],"type":"Point"}
}