{
  "type": "Feature",
  "properties": {
    "iso:country":"US",
    "sg:address":"218 Blanche St",
    "sg:city":"Houghton",
    "sg:classifiers":[
        {
            "category":"Organizations",
            "subcategory":"Community Association",
            "type":"Services"
        }
    ],
    "sg:phone":"+1 906 482 0375",
    "sg:postcode":"49931",
    "sg:province":"MI",
    "sg:tags":[
        "sorority",
        "fraternity"
    ],
    "wof:name":"Sigma Phi Epsilon",
    "wof:placetype":"venue"
},
  "geometry": {"coordinates":[-88.549009,47.117819],"type":"Point"}
}