{
  "type": "Feature",
  "properties": {
    "iso:country":"US",
    "sg:address":"3656 Farren Ln",
    "sg:city":"Grayling",
    "sg:classifiers":[
        {
            "category":"Government",
            "subcategory":"Office",
            "type":"Public Place"
        }
    ],
    "sg:phone":"+1 989 348 2347",
    "sg:postcode":"49738",
    "sg:province":"MI",
    "sg:tags":[
        "conservation"
    ],
    "wof:name":"Tohlands Inc",
    "wof:placetype":"venue"
},
  "geometry": {"coordinates":[-84.536507,44.634348],"type":"Point"}
}