{
  "type": "Feature",
  "properties": {
    "iso:country":"US",
    "sg:address":"321 4th St",
    "sg:city":"St Ignace",
    "sg:classifiers":[
        {
            "category":"Building & Trades",
            "subcategory":"Construction",
            "type":"Services"
        }
    ],
    "sg:phone":"+1 906 643 8946",
    "sg:postcode":"49781",
    "sg:province":"MI",
    "sg:tags":[
        "general",
        "contractor"
    ],
    "wof:name":"G & D Construction Co",
    "wof:placetype":"venue"
},
  "geometry": {"coordinates":[-84.739983,45.867009],"type":"Point"}
}