{
  "type": "Feature",
  "properties": {
    "iso:country":"US",
    "sg:address":"11739 Dart Dr",
    "sg:city":"Sterling Heights",
    "sg:classifiers":[
        {
            "category":"Building & Trades",
            "subcategory":"Construction",
            "type":"Services"
        }
    ],
    "sg:phone":"+1 586 979 9942",
    "sg:postcode":"48313",
    "sg:province":"MI",
    "sg:tags":[
        "house"
    ],
    "wof:name":"Wargo Construction",
    "wof:placetype":"venue"
},
  "geometry": {"coordinates":[-83.009597,42.586835],"type":"Point"}
}