{
  "type": "Feature",
  "properties": {
    "iso:country":"US",
    "sg:address":"4700 Cathro Rd",
    "sg:city":"Alpena",
    "sg:classifiers":[
        {
            "category":"Retail",
            "subcategory":"Repair Shop",
            "type":"Services"
        }
    ],
    "sg:phone":"+1 989 356 6070",
    "sg:postcode":"49707",
    "sg:province":"MI",
    "sg:tags":[
        "trade",
        "welding",
        "contractor"
    ],
    "wof:name":"Cubilo Heliarc & Welding Repr",
    "wof:placetype":"venue"
},
  "geometry": {"coordinates":[-83.53286900000001,45.112856],"type":"Point"}
}