{
  "type": "Feature",
  "properties": {
    "iso:country":"US",
    "sg:address":"43690 N Gratiot Ave",
    "sg:city":"Clinton Twp",
    "sg:classifiers":[
        {
            "category":"Home & Garden",
            "subcategory":"Furniture",
            "type":"Retail Goods"
        }
    ],
    "sg:phone":"+1 586 783 7174",
    "sg:postcode":"48036",
    "sg:province":"MI",
    "sg:tags":[
        "top",
        "counter"
    ],
    "wof:name":"Countertop Connection",
    "wof:placetype":"venue"
},
  "geometry": {"coordinates":[-82.868056,42.615328],"type":"Point"}
}