{
  "type": "Feature",
  "properties": {
    "iso:country":"US",
    "sg:address":"3897 Rector Ave NE",
    "sg:city":"Rockford",
    "sg:classifiers":[
        {
            "category":"Wholesale",
            "subcategory":"Auto Parts",
            "type":"Manufacturing & Wholesale Goods"
        }
    ],
    "sg:phone":"+1 616 866 9800",
    "sg:postcode":"49341",
    "sg:province":"MI",
    "sg:tags":[
        "equipment",
        "truck"
    ],
    "wof:name":"J & K Diesel Supply",
    "wof:placetype":"venue"
},
  "geometry": {"coordinates":[-85.576311,43.153764],"type":"Point"}
}