{
  "type": "Feature",
  "properties": {
    "iso:country":"US",
    "sg:address":"2525 W 14 Mile Rd",
    "sg:city":"Royal Oak",
    "sg:classifiers":[
        {
            "category":"Wholesale",
            "subcategory":"Machinery & Supplies",
            "type":"Manufacturing & Wholesale Goods"
        }
    ],
    "sg:phone":"+1 248 549 0077",
    "sg:postcode":"48073",
    "sg:province":"MI",
    "sg:tags":[
        "tool"
    ],
    "wof:name":"Tool-Craft Co",
    "wof:placetype":"venue"
},
  "geometry": {"coordinates":[-83.175754,42.532644],"type":"Point"}
}