{
  "type": "Feature",
  "properties": {
    "iso:country":"US",
    "sg:address":"30232 Bradner Dr",
    "sg:city":"Warren",
    "sg:classifiers":[
        {
            "category":"Sports & Exercise",
            "subcategory":"Gym",
            "type":"Entertainment"
        }
    ],
    "sg:phone":"+1 586 719 9132",
    "sg:postcode":"48088",
    "sg:province":"MI",
    "sg:tags":[
        "trainer"
    ],
    "sg:website":"www.healthfitnesstrainerbodybyde...",
    "wof:name":"Health & Fitness Trainers Body By Design",
    "wof:placetype":"venue"
},
  "geometry": {"coordinates":[-82.98528399999999,42.517282],"type":"Point"}
}