{
  "type": "Feature",
  "properties": {
    "iso:country":"US",
    "sg:address":"1284 E Cottage Grove Rd",
    "sg:city":"Linwood",
    "sg:classifiers":[
        {
            "category":"Building & Trades",
            "subcategory":"Plumbing",
            "type":"Services"
        }
    ],
    "sg:phone":"+1 989 697 5566",
    "sg:postcode":"48634",
    "sg:province":"MI",
    "sg:tags":[
        "plumbing",
        "contractor"
    ],
    "wof:name":"R & R Heating & Cooling",
    "wof:placetype":"venue"
},
  "geometry": {"coordinates":[-83.989099,43.724426],"type":"Point"}
}