{
  "type": "Feature",
  "properties": {
    "iso:country":"US",
    "sg:address":"530 S Main St",
    "sg:city":"Royal Oak",
    "sg:classifiers":[
        {
            "category":"Bars & Pubs",
            "type":"Food & Drink"
        },
        {
            "category":"Restaurant",
            "type":"Food & Drink"
        }
    ],
    "sg:phone":"+1 248 582 9460",
    "sg:postcode":"48067",
    "sg:province":"MI",
    "sg:tags":[
        "traditional",
        "new",
        "american"
    ],
    "sg:website":"blackfinnroyaloak.com",
    "wof:name":"BlackFinn American Saloon",
    "wof:placetype":"venue"
},
  "geometry": {"coordinates":[-83.144081,42.485385],"type":"Point"}
}