{
  "type": "Feature",
  "properties": {
    "iso:country":"US",
    "sg:address":"1111 Hecla St",
    "sg:city":"Hancock",
    "sg:classifiers":[
        {
            "category":"Health Services",
            "subcategory":"Doctor",
            "type":"Services"
        }
    ],
    "sg:phone":"+1 906 482 8602",
    "sg:postcode":"49930",
    "sg:province":"MI",
    "sg:tags":[
        "dentist"
    ],
    "wof:name":"Beesley Leonard W DDS",
    "wof:placetype":"venue"
},
  "geometry": {"coordinates":[-88.609545,47.131922],"type":"Point"}
}