{
  "type": "Feature",
  "properties": {
    "iso:country":"US",
    "sg:address":"6338 N Elms Rd",
    "sg:city":"Flushing",
    "sg:classifiers":[
        {
            "category":"Arena",
            "subcategory":"Sports Club",
            "type":"Entertainment"
        }
    ],
    "sg:phone":"+1 810 659 1204",
    "sg:postcode":"48433",
    "sg:province":"MI",
    "wof:name":"Championship Sports Production",
    "wof:placetype":"venue"
},
  "geometry": {"coordinates":[-83.813492,43.098614],"type":"Point"}
}