{
  "type": "Feature",
  "properties": {
    "iso:country":"US",
    "sg:address":"1 E State Rd 120",
    "sg:city":"Fremont",
    "sg:classifiers":[
        {
            "category":"Autos & Motor Vehicles",
            "subcategory":"Automobile Sales",
            "type":"Retail Goods"
        }
    ],
    "sg:phone":"+1 260 495 0244",
    "sg:postcode":"46737",
    "sg:province":"MI",
    "sg:tags":[
        "car",
        "dealer"
    ],
    "wof:name":"Fulton Auto Sales",
    "wof:placetype":"venue"
},
  "geometry": {"coordinates":[-85.000429,41.729796],"type":"Point"}
}