{
  "type": "Feature",
  "properties": {
    "iso:country":"US",
    "sg:address":"766 E Tuttle Rd",
    "sg:city":"Ionia",
    "sg:classifiers":[
        {
            "category":"Professional",
            "type":"Services"
        }
    ],
    "sg:phone":"+1 616 527 7151",
    "sg:postcode":"48846",
    "sg:province":"MI",
    "wof:name":"Diversified Services",
    "wof:placetype":"venue"
},
  "geometry": {"coordinates":[-85.05713299999999,42.95106],"type":"Point"}
}