{
  "type": "Feature",
  "properties": {
    "iso:country":"US",
    "sg:address":"1218 S 13th St",
    "sg:city":"Niles",
    "sg:classifiers":[
        {
            "category":"Building & Trades",
            "subcategory":"Cleaning & Sanitation",
            "type":"Services"
        }
    ],
    "sg:phone":"+1 269 684 6762",
    "sg:postcode":"49120",
    "sg:province":"MI",
    "sg:tags":[
        "maintenance"
    ],
    "wof:name":"Malott Cleaning Service",
    "wof:placetype":"venue"
},
  "geometry": {"coordinates":[-86.245147,41.814914],"type":"Point"}
}