{
  "type": "Feature",
  "properties": {
    "iso:country":"US",
    "sg:address":"5429 Kenicott Trl",
    "sg:city":"Brighton",
    "sg:classifiers":[
        {
            "category":"Banks & Credit Unions",
            "subcategory":"Investment Brokerage",
            "type":"Services"
        }
    ],
    "sg:phone":"+1 810 225 9876",
    "sg:postcode":"48114",
    "sg:province":"MI",
    "sg:tags":[
        "advisory",
        "financial"
    ],
    "wof:name":"Financial Group LLC",
    "wof:placetype":"venue"
},
  "geometry": {"coordinates":[-83.73963000000001,42.524297],"type":"Point"}
}