{
  "type": "Feature",
  "properties": {
    "iso:country":"US",
    "sg:address":"1457 Griggs St SE",
    "sg:city":"Grand Rapids",
    "sg:classifiers":[
        {
            "category":"Professional",
            "subcategory":"Business Services",
            "type":"Services"
        }
    ],
    "sg:phone":"+1 616 452 6154",
    "sg:postcode":"49507",
    "sg:province":"MI",
    "wof:name":"Patricia L Goudzwaard",
    "wof:placetype":"venue"
},
  "geometry": {"coordinates":[-85.63134100000001,42.93082],"type":"Point"}
}