{
  "type": "Feature",
  "properties": {
    "iso:country":"US",
    "sg:address":"856 E 8th St",
    "sg:city":"Traverse City",
    "sg:classifiers":[
        {
            "category":"Professional",
            "type":"Services"
        }
    ],
    "sg:phone":"+1 231 929 2852",
    "sg:postcode":"49686",
    "sg:province":"MI",
    "sg:tags":[
        "establishment"
    ],
    "wof:name":"Grand Travers Equities",
    "wof:placetype":"venue"
},
  "geometry": {"coordinates":[-85.60214499999999,44.758942],"type":"Point"}
}