{
  "type": "Feature",
  "properties": {
    "iso:country":"US",
    "sg:address":"528 W Centre Ave",
    "sg:city":"Portage",
    "sg:classifiers":[
        {
            "category":"Health Services",
            "subcategory":"Doctor",
            "type":"Services"
        }
    ],
    "sg:phone":"+1 800 695 8600",
    "sg:postcode":"49024",
    "sg:province":"MI",
    "sg:tags":[
        "physician",
        "surgeon"
    ],
    "wof:name":"Advantage Healthcare Inc.",
    "wof:placetype":"venue"
},
  "geometry": {"coordinates":[-85.595229,42.200989],"type":"Point"}
}