{
  "type": "Feature",
  "properties": {
    "iso:country":"US",
    "sg:address":"2861 E Grand River Ave",
    "sg:city":"Howell",
    "sg:classifiers":[
        {
            "category":"Retail",
            "subcategory":"Auto Repair",
            "type":"Services"
        }
    ],
    "sg:phone":"+1 517 546 1113",
    "sg:postcode":"48843",
    "sg:province":"MI",
    "sg:tags":[
        "automobile",
        "lubrication",
        "automotive"
    ],
    "wof:name":"Cruz-N Oil Change Center",
    "wof:placetype":"venue"
},
  "geometry": {"coordinates":[-83.896771,42.594993],"type":"Point"}
}