{
  "type": "Feature",
  "properties": {
    "iso:country":"US",
    "sg:address":"300 S Main St",
    "sg:city":"Brooklyn",
    "sg:classifiers":[
        {
            "category":"Real Estate",
            "subcategory":"Real Estate Agent",
            "type":"Services"
        }
    ],
    "sg:phone":"+1 517 592 0000",
    "sg:postcode":"49230",
    "sg:province":"MI",
    "wof:name":"Brooklyn Realty Inc",
    "wof:placetype":"venue"
},
  "geometry": {"coordinates":[-84.24786899999999,42.101648],"type":"Point"}
}