{
  "type": "Feature",
  "properties": {
    "iso:country":"US",
    "sg:address":"17259 Hickory St",
    "sg:city":"Spring Lake",
    "sg:classifiers":[
        {
            "category":"Manufacturing",
            "subcategory":"Rubber & Plastics",
            "type":"Manufacturing & Wholesale Goods"
        }
    ],
    "sg:phone":"+1 616 846 0820",
    "sg:postcode":"49456",
    "sg:province":"MI",
    "wof:name":"SAC Plastics Inc",
    "wof:placetype":"venue"
},
  "geometry": {"coordinates":[-86.21538099999999,43.110318],"type":"Point"}
}