{
  "type": "Feature",
  "properties": {
    "iso:country":"US",
    "sg:address":"12493 Shall Rd",
    "sg:city":"Cheboygan",
    "sg:classifiers":[
        {
            "category":"Building & Trades",
            "subcategory":"Landscaping Services",
            "type":"Services"
        }
    ],
    "sg:phone":"+1 231 627 6850",
    "sg:postcode":"49721",
    "sg:province":"MI",
    "wof:name":"Northern Lawn Care Snow Rmoval",
    "wof:placetype":"venue"
},
  "geometry": {"coordinates":[-84.53947700000001,45.644622],"type":"Point"}
}