{
  "type": "Feature",
  "properties": {
    "iso:country":"US",
    "sg:address":"2 S 6th St",
    "sg:city":"Crystal Falls",
    "sg:classifiers":[
        {
            "category":"Government",
            "subcategory":"Office",
            "type":"Public Place"
        }
    ],
    "sg:phone":"+1 906 875 6502",
    "sg:postcode":"49920",
    "sg:province":"MI",
    "wof:name":"Iron County Equalization Dept",
    "wof:placetype":"venue"
},
  "geometry": {"coordinates":[-88.334738,46.09674],"type":"Point"}
}