{
  "type": "Feature",
  "properties": {
    "iso:country":"US",
    "sg:address":"908 Gull Rd",
    "sg:city":"Kalamazoo",
    "sg:classifiers":[
        {
            "category":"Organizations",
            "subcategory":"Religious Organization",
            "type":"Services"
        }
    ],
    "sg:phone":"+1 269 382 0141",
    "sg:postcode":"49048",
    "sg:province":"MI",
    "wof:name":"Saints Praise Worshp Ctr Churc",
    "wof:placetype":"venue"
},
  "geometry": {"coordinates":[-85.569371,42.300862],"type":"Point"}
}