{
  "type": "Feature",
  "properties": {
    "iso:country":"US",
    "sg:address":"104 E Munising Ave",
    "sg:city":"Munising",
    "sg:classifiers":[
        {
            "category":"Bars & Pubs",
            "type":"Food & Drink"
        }
    ],
    "sg:phone":"+1 906 387 5232",
    "sg:postcode":"49862",
    "sg:province":"MI",
    "wof:name":"Sylvester's",
    "wof:placetype":"venue"
},
  "geometry": {"coordinates":[-86.655002,46.411476],"type":"Point"}
}