{
  "type": "Feature",
  "properties": {
    "iso:country":"US",
    "sg:address":"309 S Front St",
    "sg:city":"Marquette",
    "sg:classifiers":[
        {
            "category":"Professional",
            "subcategory":"Accounting & Tax Preparation",
            "type":"Services"
        }
    ],
    "sg:phone":"+1 906 228 4620",
    "sg:postcode":"49855",
    "sg:province":"MI",
    "sg:tags":[
        "accountant"
    ],
    "wof:name":"Houle & Assoc PC",
    "wof:placetype":"venue"
},
  "geometry": {"coordinates":[-87.393286,46.541499],"type":"Point"}
}