{
  "type": "Feature",
  "properties": {
    "iso:country":"US",
    "sg:address":"732 Randall St W",
    "sg:city":"Coopersville",
    "sg:classifiers":[
        {
            "category":"Retail",
            "subcategory":"Auto Repair",
            "type":"Services"
        }
    ],
    "sg:phone":"+1 616 837 9447",
    "sg:postcode":"49404",
    "sg:province":"MI",
    "sg:tags":[
        "repairing",
        "automobile"
    ],
    "wof:name":"Auto Source Of West Michigan",
    "wof:placetype":"venue"
},
  "geometry": {"coordinates":[-85.951615,43.059788],"type":"Point"}
}