{
  "type": "Feature",
  "properties": {
    "iso:country":"US",
    "sg:address":"15571 Hickory Ln",
    "sg:city":"Southgate",
    "sg:classifiers":[
        {
            "category":"Professional",
            "subcategory":"Computer Services",
            "type":"Services"
        }
    ],
    "sg:phone":"+1 734 283 7766",
    "sg:postcode":"48195",
    "sg:province":"MI",
    "sg:tags":[
        "related"
    ],
    "wof:name":"Thomas Bateman",
    "wof:placetype":"venue"
},
  "geometry": {"coordinates":[-83.223274,42.19472],"type":"Point"}
}