{
  "type": "Feature",
  "properties": {
    "iso:country":"US",
    "sg:address":"315 N Front St",
    "sg:city":"Marquette",
    "sg:classifiers":[
        {
            "category":"Professional",
            "subcategory":"Credit Reporting & Collection",
            "type":"Services"
        }
    ],
    "sg:phone":"+1 906 228 6960",
    "sg:postcode":"49855",
    "sg:province":"MI",
    "sg:website":"www.creditcheckup.com",
    "wof:name":"Credit Check",
    "wof:placetype":"venue"
},
  "geometry": {"coordinates":[-87.392301,46.546023],"type":"Point"}
}