{
  "type": "Feature",
  "properties": {
    "iso:country":"US",
    "sg:address":"1484 N Leroy St",
    "sg:city":"Fenton",
    "sg:classifiers":[
        {
            "category":"Restaurant",
            "type":"Food & Drink"
        }
    ],
    "sg:phone":"+1 810 750 6833",
    "sg:postcode":"48430",
    "sg:province":"MI",
    "sg:tags":[
        "chinese"
    ],
    "wof:name":"Bamboo Asian Grill",
    "wof:placetype":"venue"
},
  "geometry": {"coordinates":[-83.70760300000001,42.817813],"type":"Point"}
}