{
  "type": "Feature",
  "properties": {
    "iso:country":"US",
    "sg:address":"6351 E H Ave",
    "sg:city":"Kalamazoo",
    "sg:classifiers":[
        {
            "category":"Social Services",
            "subcategory":"Adult Care",
            "type":"Services"
        }
    ],
    "sg:phone":"+1 269 381 9622",
    "sg:postcode":"49048",
    "sg:province":"MI",
    "sg:tags":[
        "home"
    ],
    "wof:name":"Country Haven AFC",
    "wof:placetype":"venue"
},
  "geometry": {"coordinates":[-85.506539,42.317461],"type":"Point"}
}