{
  "type": "Feature",
  "properties": {
    "iso:country":"US",
    "sg:address":"1591 S Graham Rd",
    "sg:city":"Flint",
    "sg:classifiers":[
        {
            "category":"Ice Cream",
            "type":"Food & Drink"
        }
    ],
    "sg:menulink":"http://www.allmenus.com/mi/flint/217738-ben--jerrys/menu/",
    "sg:postcode":"48532",
    "sg:province":"MI",
    "sg:tags":[
        "american"
    ],
    "wof:name":"Ben & Jerry's",
    "wof:placetype":"venue"
},
  "geometry": {"coordinates":[-83.753006,43.003062],"type":"Point"}
}