{
  "type": "Feature",
  "properties": {
    "iso:country":"US",
    "sg:address":"2883 US Hwy 23",
    "sg:city":"Cheboygan",
    "sg:classifiers":[
        {
            "category":"Personal",
            "subcategory":"Beauty Salon",
            "type":"Services"
        }
    ],
    "sg:phone":"+1 231 627 7979",
    "sg:postcode":"49721",
    "sg:province":"MI",
    "sg:tags":[
        "shop"
    ],
    "wof:name":"Victorian Salon",
    "wof:placetype":"venue"
},
  "geometry": {"coordinates":[-84.547579,45.692636],"type":"Point"}
}