{
  "type": "Feature",
  "properties": {
    "iso:country":"US",
    "sg:address":"29816 Marshall St",
    "sg:city":"Southfield",
    "sg:classifiers":[
        {
            "category":"Professional",
            "subcategory":"Management & Consulting",
            "type":"Services"
        }
    ],
    "sg:phone":"+1 248 569 7938",
    "sg:postcode":"48076",
    "sg:province":"MI",
    "sg:tags":[
        "business"
    ],
    "wof:name":"Resource Services Network",
    "wof:placetype":"venue"
},
  "geometry": {"coordinates":[-83.20546400000001,42.509369],"type":"Point"}
}