{
  "type": "Feature",
  "properties": {
    "iso:country":"US",
    "sg:address":"1156 Saskatoon Trl",
    "sg:city":"Wayland",
    "sg:classifiers":[
        {
            "category":"Shopping",
            "subcategory":"Gifts & Souvenirs",
            "type":"Retail Goods"
        }
    ],
    "sg:phone":"+1 269 792 9497",
    "sg:postcode":"49348",
    "sg:province":"MI",
    "sg:tags":[
        "shop"
    ],
    "wof:name":"Streit Gifts",
    "wof:placetype":"venue"
},
  "geometry": {"coordinates":[-85.65837999999999,42.680581],"type":"Point"}
}