{
  "type": "Feature",
  "properties": {
    "iso:country":"US",
    "sg:address":"4221 Livesay Rd",
    "sg:city":"Sand Creek",
    "sg:classifiers":[
        {
            "category":"Shopping",
            "subcategory":"Bicycles & Sporting Goods",
            "type":"Retail Goods"
        }
    ],
    "sg:phone":"+1 517 436 6245",
    "sg:postcode":"49279",
    "sg:province":"MI",
    "sg:tags":[
        "tent"
    ],
    "sg:website":"www.tentmasters.com",
    "wof:name":"Four Seasons Tentmasters",
    "wof:placetype":"venue"
},
  "geometry": {"coordinates":[-84.102452,41.827602],"type":"Point"}
}