{
  "type": "Feature",
  "properties": {
    "iso:country":"US",
    "sg:address":"200 Prospect Ave",
    "sg:city":"Alma",
    "sg:classifiers":[
        {
            "category":"Shopping",
            "type":"Retail Goods"
        }
    ],
    "sg:phone":"+1 989 463 4121",
    "sg:postcode":"48801",
    "sg:province":"MI",
    "sg:tags":[
        "equipment",
        "care",
        "health",
        "home"
    ],
    "wof:name":"Gratiot Home Medical Equipment",
    "wof:placetype":"venue"
},
  "geometry": {"coordinates":[-84.66346900000001,43.376695],"type":"Point"}
}