{
  "type": "Feature",
  "properties": {
    "iso:country":"US",
    "sg:address":"2031 S Dort Hwy",
    "sg:city":"Flint",
    "sg:classifiers":[
        {
            "category":"Organizations",
            "subcategory":"Community Association",
            "type":"Services"
        },
        {
            "category":"Recreation",
            "type":"Entertainment"
        }
    ],
    "sg:phone":"+1 810 234 9441",
    "sg:postcode":"48503",
    "sg:province":"MI",
    "sg:tags":[
        "club",
        "membership",
        "nightlife"
    ],
    "wof:name":"J B Night Club",
    "wof:placetype":"venue"
},
  "geometry": {"coordinates":[-83.653999,43.005901],"type":"Point"}
}