{
  "type": "Feature",
  "properties": {
    "iso:country":"US",
    "sg:address":"934 Pinckney Rd",
    "sg:city":"Howell",
    "sg:classifiers":[
        {
            "category":"Restaurant",
            "type":"Food & Drink"
        }
    ],
    "sg:phone":"+1 517 552 2722",
    "sg:postcode":"48843",
    "sg:province":"MI",
    "wof:name":"All Star Coney Island",
    "wof:placetype":"venue"
},
  "geometry": {"coordinates":[-83.933346,42.582966],"type":"Point"}
}