{
  "type": "Feature",
  "properties": {
    "iso:country":"US",
    "sg:address":"745 N Oxford Rd",
    "sg:city":"Oxford",
    "sg:classifiers":[
        {
            "category":"Education",
            "subcategory":"School",
            "type":"Public Place"
        }
    ],
    "sg:phone":"+1 248 969 5100",
    "sg:postcode":"48371",
    "sg:province":"MI",
    "sg:website":"www.oxford.k12.mi.us",
    "wof:name":"Oxford High School",
    "wof:placetype":"venue"
},
  "geometry": {"coordinates":[-83.255467,42.842352],"type":"Point"}
}