{
  "type": "Feature",
  "properties": {
    "iso:country":"US",
    "sg:address":"50375 Central Industrial Dr",
    "sg:city":"Shelby Twp",
    "sg:classifiers":[
        {
            "category":"Manufacturing",
            "subcategory":"Tools & Machinery",
            "type":"Manufacturing & Wholesale Goods"
        }
    ],
    "sg:phone":"+1 586 803 9500",
    "sg:postcode":"48315",
    "sg:province":"MI",
    "sg:tags":[
        "machine",
        "shop"
    ],
    "wof:name":"Rassey Industries Inc",
    "wof:placetype":"venue"
},
  "geometry": {"coordinates":[-83.001053,42.66604],"type":"Point"}
}