{
  "type": "Feature",
  "properties": {
    "iso:country":"US",
    "sg:address":"10651 Parkwood Dr",
    "sg:city":"Montague",
    "sg:classifiers":[
        {
            "category":"Building & Trades",
            "subcategory":"Landscaping Services",
            "type":"Services"
        }
    ],
    "sg:phone":"+1 231 893 1166",
    "sg:postcode":"49437",
    "sg:province":"MI",
    "sg:tags":[
        "tree"
    ],
    "wof:name":"Top Notch Tree Svc",
    "wof:placetype":"venue"
},
  "geometry": {"coordinates":[-86.30632199999999,43.456399],"type":"Point"}
}