{
  "type": "Feature",
  "properties": {
    "iso:country":"US",
    "sg:address":"811 W Michigan Ave",
    "sg:city":"Kalamazoo",
    "sg:classifiers":[
        {
            "category":"Fast Food",
            "type":"Food & Drink"
        },
        {
            "category":"Restaurant",
            "type":"Food & Drink"
        }
    ],
    "sg:phone":"+1 269 388 6083",
    "sg:postcode":"49007",
    "sg:province":"MI",
    "sg:tags":[
        "pan",
        "asian",
        "chinese",
        "take"
    ],
    "wof:name":"Rice Kitchen",
    "wof:placetype":"venue"
},
  "geometry": {"coordinates":[-85.595432,42.290072],"type":"Point"}
}