{
  "type": "Feature",
  "properties": {
    "iso:country":"US",
    "sg:address":"4000 Harold St",
    "sg:city":"Saginaw",
    "sg:classifiers":[
        {
            "category":"Real Estate",
            "subcategory":"Real Estate Operator",
            "type":"Services"
        }
    ],
    "sg:phone":"+1 989 753 0061",
    "sg:postcode":"48601",
    "sg:province":"MI",
    "sg:tags":[
        "building",
        "apartment"
    ],
    "wof:name":"Essex Manor Inc",
    "wof:placetype":"venue"
},
  "geometry": {"coordinates":[-83.910464,43.409058],"type":"Point"}
}