{
  "type": "Feature",
  "properties": {
    "iso:country":"US",
    "sg:address":"29206 Orchard Lake Rd",
    "sg:city":"Farmington",
    "sg:classifiers":[
        {
            "category":"Restaurant",
            "type":"Food & Drink"
        }
    ],
    "sg:menulink":"http://www.allmenus.com/mi/farmington-hills/196782-burger-king/menu/",
    "sg:phone":"+1 248 851 7473",
    "sg:postcode":"48334",
    "sg:province":"MI",
    "sg:tags":[
        "burger",
        "american"
    ],
    "wof:name":"Burger King",
    "wof:placetype":"venue"
},
  "geometry": {"coordinates":[-83.35841499999999,42.511097],"type":"Point"}
}