{
  "type": "Feature",
  "properties": {
    "iso:country":"US",
    "sg:address":"1600 S Drake Rd",
    "sg:city":"Kalamazoo",
    "sg:classifiers":[
        {
            "category":"Autos & Motor Vehicles",
            "subcategory":"Automobile Sales",
            "type":"Retail Goods"
        }
    ],
    "sg:phone":"+1 269 375 7008",
    "sg:postcode":"49006",
    "sg:province":"MI",
    "sg:tags":[
        "car",
        "dealer"
    ],
    "sg:website":"www.waltersautos.com",
    "wof:name":"Bud & Doug Walters Auto Sales",
    "wof:placetype":"venue"
},
  "geometry": {"coordinates":[-85.64836099999999,42.275695],"type":"Point"}
}