{
  "type": "Feature",
  "properties": {
    "iso:country":"US",
    "sg:address":"5343 N Adams Rd",
    "sg:city":"Bloomfield Hills",
    "sg:classifiers":[
        {
            "category":"Professional",
            "subcategory":"Art Services",
            "type":"Services"
        }
    ],
    "sg:phone":"+1 248 646 9233",
    "sg:postcode":"48304",
    "sg:province":"MI",
    "sg:tags":[
        "photography",
        "commercial"
    ],
    "wof:name":"Ron Strong Incorporated",
    "wof:placetype":"venue"
},
  "geometry": {"coordinates":[-83.208145,42.594755],"type":"Point"}
}