{
  "type": "Feature",
  "properties": {
    "iso:country":"US",
    "sg:address":"119 Almyra Ave",
    "sg:city":"Monroe",
    "sg:classifiers":[
        {
            "category":"Organizations",
            "subcategory":"Religious Organization",
            "type":"Services"
        }
    ],
    "sg:phone":"+1 734 457 0723",
    "sg:postcode":"48161",
    "sg:province":"MI",
    "wof:name":"Careys Chapel A M E Church",
    "wof:placetype":"venue"
},
  "geometry": {"coordinates":[-83.38175099999999,41.907721],"type":"Point"}
}