{
  "type": "Feature",
  "properties": {
    "iso:country":"US",
    "sg:address":"1147 32nd St",
    "sg:city":"Allegan",
    "sg:classifiers":[
        {
            "category":"Professional",
            "subcategory":"Accounting & Tax Preparation",
            "type":"Services"
        }
    ],
    "sg:phone":"+1 269 673 4310",
    "sg:postcode":"49010",
    "sg:province":"MI",
    "wof:name":"Sanger Tax & Acctg Svc",
    "wof:placetype":"venue"
},
  "geometry": {"coordinates":[-85.861211,42.506488],"type":"Point"}
}