{
  "type": "Feature",
  "properties": {
    "iso:country":"US",
    "sg:address":"5580 Waldon Rd",
    "sg:city":"Clarkston",
    "sg:classifiers":[
        {
            "category":"Restaurant",
            "type":"Food & Drink"
        }
    ],
    "sg:phone":"+1 248 625 0700",
    "sg:postcode":"48348",
    "sg:province":"MI",
    "sg:tags":[
        "banquet",
        "rooms"
    ],
    "sg:website":"www.pineknobmansion.com",
    "wof:name":"Pine Knob Mansion",
    "wof:placetype":"venue"
},
  "geometry": {"coordinates":[-83.373395,42.733928],"type":"Point"}
}