{
  "type": "Feature",
  "properties": {
    "iso:country":"US",
    "sg:address":"1034 Innes St NE",
    "sg:city":"Grand Rapids",
    "sg:classifiers":[
        {
            "category":"Utilities",
            "subcategory":"Cable",
            "type":"Services"
        }
    ],
    "sg:phone":"+1 616 459 3768",
    "sg:postcode":"49503",
    "sg:province":"MI",
    "sg:tags":[
        "television"
    ],
    "wof:name":"Mdcb Inc",
    "wof:placetype":"venue"
},
  "geometry": {"coordinates":[-85.642253,42.967803],"type":"Point"}
}