{
  "type": "Feature",
  "properties": {
    "iso:country":"US",
    "sg:address":"4009 Atherton Dr",
    "sg:city":"Coloma",
    "sg:classifiers":[
        {
            "category":"Wholesale",
            "subcategory":"Sporting Goods",
            "type":"Manufacturing & Wholesale Goods"
        }
    ],
    "sg:phone":"+1 269 468 4029",
    "sg:postcode":"49038",
    "sg:province":"MI",
    "wof:name":"Bo Jacs Sports Crew",
    "wof:placetype":"venue"
},
  "geometry": {"coordinates":[-86.330034,42.18346],"type":"Point"}
}