{
  "type": "Feature",
  "properties": {
    "iso:country":"US",
    "sg:address":"9491 Wise Rd",
    "sg:city":"Commerce Twp",
    "sg:classifiers":[
        {
            "category":"Travel",
            "subcategory":"Campground",
            "type":"Entertainment"
        }
    ],
    "sg:phone":"+1 248 363 7059",
    "sg:postcode":"48382",
    "sg:province":"MI",
    "sg:tags":[
        "camp"
    ],
    "wof:name":"Crossroads For Youth",
    "wof:placetype":"venue"
},
  "geometry": {"coordinates":[-83.473951,42.598795],"type":"Point"}
}