{
  "type": "Feature",
  "properties": {
    "iso:country":"US",
    "sg:address":"3687 Erie Dr",
    "sg:city":"Orchard Lake",
    "sg:classifiers":[
        {
            "category":"Organizations",
            "subcategory":"Religious Organization",
            "type":"Services"
        }
    ],
    "sg:phone":"+1 248 681 4452",
    "sg:postcode":"48324",
    "sg:province":"MI",
    "sg:tags":[
        "church"
    ],
    "wof:name":"Our Lady Of Refuge Family Life",
    "wof:placetype":"venue"
},
  "geometry": {"coordinates":[-83.358767,42.596747],"type":"Point"}
}