{
  "type": "Feature",
  "properties": {
    "iso:country":"US",
    "sg:address":"923 N Wattles Rd",
    "sg:city":"Battle Creek",
    "sg:classifiers":[
        {
            "category":"Professional",
            "subcategory":"Management & Consulting",
            "type":"Services"
        }
    ],
    "sg:phone":"+1 269 968 8214",
    "sg:postcode":"49014",
    "sg:province":"MI",
    "sg:tags":[
        "manufacturing"
    ],
    "wof:name":"Scot Schira",
    "wof:placetype":"venue"
},
  "geometry": {"coordinates":[-85.11170199999999,42.326873],"type":"Point"}
}