{
  "type": "Feature",
  "properties": {
    "iso:country":"US",
    "sg:address":"19894 Kelly Rd",
    "sg:city":"Harper Woods",
    "sg:classifiers":[
        {
            "category":"Personal",
            "subcategory":"Beauty Salon",
            "type":"Services"
        }
    ],
    "sg:phone":"+1 313 521 7900",
    "sg:postcode":"48225",
    "sg:province":"MI",
    "sg:tags":[
        "shop"
    ],
    "wof:name":"Sandras Hair Design Unlimited",
    "wof:placetype":"venue"
},
  "geometry": {"coordinates":[-82.946473,42.442899],"type":"Point"}
}