{
  "type": "Feature",
  "properties": {
    "iso:country":"US",
    "sg:address":"5691 Cooley Village Dr",
    "sg:city":"Waterford",
    "sg:classifiers":[
        {
            "category":"Professional",
            "type":"Services"
        }
    ],
    "sg:phone":"+1 248 738 8347",
    "sg:postcode":"48327",
    "sg:province":"MI",
    "sg:tags":[
        "establishment"
    ],
    "wof:name":"CRS Svc Inc",
    "wof:placetype":"venue"
},
  "geometry": {"coordinates":[-83.396,42.624748],"type":"Point"}
}