{
  "type": "Feature",
  "properties": {
    "iso:country":"US",
    "sg:address":"10002 Highland Rd",
    "sg:city":"Hartland",
    "sg:classifiers":[
        {
            "category":"Real Estate",
            "subcategory":"Real Estate Agent",
            "type":"Services"
        }
    ],
    "sg:phone":"+1 810 632 0222",
    "sg:postcode":"48353",
    "sg:province":"MI",
    "wof:name":"Real Estate One Hartland",
    "wof:placetype":"venue"
},
  "geometry": {"coordinates":[-83.75295699999999,42.633011],"type":"Point"}
}