{
  "type": "Feature",
  "properties": {
    "iso:country":"US",
    "sg:address":"3003 Gannon Rd",
    "sg:city":"Howell",
    "sg:classifiers":[
        {
            "category":"Manufacturing",
            "subcategory":"Signs",
            "type":"Manufacturing & Wholesale Goods"
        }
    ],
    "sg:phone":"+1 517 545 8260",
    "sg:postcode":"48855",
    "sg:province":"MI",
    "sg:website":"www.fowlervillesigns.com",
    "wof:name":"Fowlerville Signs",
    "wof:placetype":"venue"
},
  "geometry": {"coordinates":[-83.98262699999999,42.740733],"type":"Point"}
}