{
  "type": "Feature",
  "properties": {
    "iso:country":"US",
    "sg:address":"950 E Bridge St",
    "sg:city":"Portland",
    "sg:classifiers":[
        {
            "category":"Government",
            "subcategory":"Office",
            "type":"Public Place"
        }
    ],
    "sg:phone":"+1 517 647 7291",
    "sg:postcode":"48875",
    "sg:province":"MI",
    "sg:tags":[
        "village"
    ],
    "wof:name":"Portland City Cemetery",
    "wof:placetype":"venue"
},
  "geometry": {"coordinates":[-84.895747,42.865457],"type":"Point"}
}