{
  "type": "Feature",
  "properties": {
    "iso:country":"US",
    "sg:address":"12941 Oak Park Blvd",
    "sg:city":"Oak Park",
    "sg:classifiers":[
        {
            "category":"Wholesale",
            "subcategory":"Motor Vehicles",
            "type":"Manufacturing & Wholesale Goods"
        }
    ],
    "sg:phone":"+1 248 981 3610",
    "sg:postcode":"48237",
    "sg:province":"MI",
    "wof:name":"Tommy Investments",
    "wof:placetype":"venue"
},
  "geometry": {"coordinates":[-83.175321,42.465934],"type":"Point"}
}