{
  "type": "Feature",
  "properties": {
    "iso:country":"US",
    "sg:address":"718 N Mc Ewan St",
    "sg:city":"Clare",
    "sg:classifiers":[
        {
            "category":"Food & Beverages",
            "subcategory":"Groceries & Convenience Stores",
            "type":"Retail Goods"
        }
    ],
    "sg:phone":"+1 989 386 9611",
    "sg:postcode":"48617",
    "sg:province":"MI",
    "wof:name":"Clare Shop N Go",
    "wof:placetype":"venue"
},
  "geometry": {"coordinates":[-84.768264,43.821821],"type":"Point"}
}