{
  "type": "Feature",
  "properties": {
    "iso:country":"US",
    "sg:address":"708 Sherman Ln",
    "sg:city":"Cassopolis",
    "sg:classifiers":[
        {
            "category":"Government",
            "subcategory":"Office",
            "type":"Public Place"
        }
    ],
    "sg:phone":"+1 269 445 2520",
    "sg:postcode":"49031",
    "sg:province":"MI",
    "sg:tags":[
        "administrative",
        "program",
        "economic",
        "general"
    ],
    "wof:name":"Edward Lowe Business Dev Ctr",
    "wof:placetype":"venue"
},
  "geometry": {"coordinates":[-86.000288,41.905522],"type":"Point"}
}