{
  "type": "Feature",
  "properties": {
    "iso:country":"US",
    "sg:address":"201 Crosby Dr",
    "sg:city":"Battle Creek",
    "sg:classifiers":[
        {
            "category":"Building & Trades",
            "subcategory":"Electrical",
            "type":"Services"
        }
    ],
    "sg:phone":"+1 269 660 0004",
    "sg:postcode":"49014",
    "sg:province":"MI",
    "sg:tags":[
        "electric",
        "contractor"
    ],
    "wof:name":"Battle Creek Electrical Jatc",
    "wof:placetype":"venue"
},
  "geometry": {"coordinates":[-85.120091,42.300556],"type":"Point"}
}