{
  "type": "Feature",
  "properties": {
    "iso:country":"US",
    "sg:address":"3080 Orchard Lake Rd",
    "sg:city":"Keego Harbor",
    "sg:classifiers":[
        {
            "category":"Sports & Exercise",
            "subcategory":"Gym",
            "type":"Entertainment"
        }
    ],
    "sg:phone":"+1 248 681 4323",
    "sg:postcode":"48320",
    "sg:province":"MI",
    "sg:tags":[
        "fitness",
        "physical",
        "facility"
    ],
    "wof:name":"Get A Grip Fitness",
    "wof:placetype":"venue"
},
  "geometry": {"coordinates":[-83.34646100000001,42.604872],"type":"Point"}
}