{
  "type": "Feature",
  "properties": {
    "iso:country":"US",
    "sg:address":"19345 Winthrop St",
    "sg:city":"Detroit",
    "sg:classifiers":[
        {
            "category":"Professional",
            "subcategory":"Detective & Security Services",
            "type":"Services"
        }
    ],
    "sg:phone":"+1 313 580 0392",
    "sg:postcode":"48235",
    "sg:province":"MI",
    "sg:tags":[
        "car",
        "armored",
        "private",
        "investigator"
    ],
    "wof:name":"Apex Information Services",
    "wof:placetype":"venue"
},
  "geometry": {"coordinates":[-83.201026,42.433002],"type":"Point"}
}