{
  "type": "Feature",
  "properties": {
    "iso:country":"US",
    "sg:address":"2743 Sparta Dr",
    "sg:city":"Troy",
    "sg:classifiers":[
        {
            "category":"Insurance",
            "subcategory":"Insurance Agent",
            "type":"Services"
        }
    ],
    "sg:phone":"+1 248 457 9439",
    "sg:postcode":"48083",
    "sg:province":"MI",
    "wof:name":"Allied Insurance",
    "wof:placetype":"venue"
},
  "geometry": {"coordinates":[-83.09440499999999,42.563512],"type":"Point"}
}