{
  "type": "Feature",
  "properties": {
    "iso:country":"US",
    "sg:address":"320 S Walnut St",
    "sg:city":"Lansing",
    "sg:classifiers":[
        {
            "category":"Social Services",
            "type":"Services"
        }
    ],
    "sg:phone":"+1 517 373 4700",
    "sg:postcode":"48933",
    "sg:province":"MI",
    "wof:name":"O D C P",
    "wof:placetype":"venue"
},
  "geometry": {"coordinates":[-84.557085,42.730293],"type":"Point"}
}