{
  "type": "Feature",
  "properties": {
    "iso:country":"US",
    "sg:address":"1040 26th St SW",
    "sg:city":"Grand Rapids",
    "sg:classifiers":[
        {
            "category":"Organizations",
            "subcategory":"Religious Organization",
            "type":"Services"
        }
    ],
    "sg:phone":"+1 616 531 1100",
    "sg:postcode":"49509",
    "sg:province":"MI",
    "wof:name":"South Side Vineyard",
    "wof:placetype":"venue"
},
  "geometry": {"coordinates":[-85.692285,42.916956],"type":"Point"}
}