{
  "type": "Feature",
  "properties": {
    "iso:country":"US",
    "sg:address":"991 Cedar Oaks Trl",
    "sg:city":"White Lake",
    "sg:classifiers":[
        {
            "category":"Professional",
            "subcategory":"Business Services",
            "type":"Services"
        }
    ],
    "sg:phone":"+1 248 360 8945",
    "sg:postcode":"48386",
    "sg:province":"MI",
    "wof:name":"Dreamtime Enterprise Inc",
    "wof:placetype":"venue"
},
  "geometry": {"coordinates":[-83.457821,42.62156],"type":"Point"}
}