{
  "type": "Feature",
  "properties": {
    "iso:country":"US",
    "sg:address":"149 South St",
    "sg:city":"Belleville",
    "sg:classifiers":[
        {
            "category":"Retail",
            "subcategory":"Auto Repair",
            "type":"Services"
        }
    ],
    "sg:phone":"+1 734 697 2140",
    "sg:postcode":"48111",
    "sg:province":"MI",
    "sg:tags":[
        "glass",
        "replacement"
    ],
    "wof:name":"Glass Ranch Inc",
    "wof:placetype":"venue"
},
  "geometry": {"coordinates":[-83.485169,42.203714],"type":"Point"}
}