{
  "type": "Feature",
  "properties": {
    "iso:country":"US",
    "sg:address":"4406 134th Ave",
    "sg:city":"Hamilton",
    "sg:classifiers":[
        {
            "category":"Farming",
            "subcategory":"Farm",
            "type":"Manufacturing & Wholesale Goods"
        }
    ],
    "sg:phone":"+1 269 751 8780",
    "sg:postcode":"49419",
    "sg:province":"MI",
    "wof:name":"Poll Farms Inc",
    "wof:placetype":"venue"
},
  "geometry": {"coordinates":[-85.98913,42.66639],"type":"Point"}
}