{
  "type": "Feature",
  "properties": {
    "iso:country":"US",
    "sg:address":"2322 Cass Rd",
    "sg:city":"Traverse City",
    "sg:classifiers":[
        {
            "category":"Manufacturing",
            "subcategory":"Apparel",
            "type":"Manufacturing & Wholesale Goods"
        }
    ],
    "sg:phone":"+1 231 941 8200",
    "sg:postcode":"49684",
    "sg:province":"MI",
    "sg:tags":[
        "flag",
        "banner"
    ],
    "sg:website":"www.brittenmedia.com",
    "wof:name":"Britten Media Inc",
    "wof:placetype":"venue"
},
  "geometry": {"coordinates":[-85.625787,44.717835],"type":"Point"}
}