{
  "type": "Feature",
  "properties": {
    "iso:country":"US",
    "sg:address":"590 W Columbia Ave",
    "sg:city":"Battle Creek",
    "sg:classifiers":[
        {
            "category":"Shopping",
            "type":"Retail Goods"
        }
    ],
    "sg:phone":"+1 269 965 7083",
    "sg:postcode":"49015",
    "sg:province":"MI",
    "sg:tags":[
        "telephone",
        "cellular"
    ],
    "wof:name":"Clear Communications Inc",
    "wof:placetype":"venue"
},
  "geometry": {"coordinates":[-85.211015,42.298631],"type":"Point"}
}