{
  "type": "Feature",
  "properties": {
    "iso:country":"US",
    "sg:address":"10444 S 27th St",
    "sg:city":"Vicksburg",
    "sg:classifiers":[
        {
            "category":"Building & Trades",
            "subcategory":"Construction",
            "type":"Services"
        }
    ],
    "sg:phone":"+1 269 327 2842",
    "sg:postcode":"49097",
    "sg:province":"MI",
    "sg:tags":[
        "house"
    ],
    "wof:name":"Daves Home Repair & Mtc",
    "wof:placetype":"venue"
},
  "geometry": {"coordinates":[-85.500885,42.164044],"type":"Point"}
}