{
  "type": "Feature",
  "properties": {
    "iso:country":"US",
    "sg:address":"8801 Macomb St",
    "sg:city":"Grosse Ile",
    "sg:classifiers":[
        {
            "category":"Personal",
            "subcategory":"Beauty Salon",
            "type":"Services"
        }
    ],
    "sg:phone":"+1 734 675 3450",
    "sg:postcode":"48138",
    "sg:province":"MI",
    "sg:tags":[
        "shop"
    ],
    "wof:name":"Salon Sigrid Inc",
    "wof:placetype":"venue"
},
  "geometry": {"coordinates":[-83.158148,42.130618],"type":"Point"}
}