{
  "type": "Feature",
  "properties": {
    "iso:country":"US",
    "sg:address":"933 Western Ave",
    "sg:city":"Monroe",
    "sg:classifiers":[
        {
            "category":"Organizations",
            "subcategory":"Religious Organization",
            "type":"Services"
        }
    ],
    "sg:phone":"+1 734 241 2752",
    "sg:postcode":"48161",
    "sg:province":"MI",
    "sg:tags":[
        "monastery",
        "convent"
    ],
    "wof:name":"Sisters IHM",
    "wof:placetype":"venue"
},
  "geometry": {"coordinates":[-83.42722000000001,41.917421],"type":"Point"}
}