{
  "type": "Feature",
  "properties": {
    "iso:country":"US",
    "sg:address":"37866 Tralee Trl",
    "sg:city":"Northville",
    "sg:classifiers":[
        {
            "category":"Sports & Exercise",
            "subcategory":"Gym",
            "type":"Entertainment"
        }
    ],
    "sg:phone":"+1 248 442 0090",
    "sg:postcode":"48167",
    "sg:province":"MI",
    "sg:tags":[
        "trainer"
    ],
    "wof:name":"American Health & Fitness",
    "wof:placetype":"venue"
},
  "geometry": {"coordinates":[-83.420411,42.44355],"type":"Point"}
}