{
  "type": "Feature",
  "properties": {
    "iso:country":"US",
    "sg:address":"21719 Harper Ave",
    "sg:city":"St Clair Shores",
    "sg:classifiers":[
        {
            "category":"Insurance",
            "subcategory":"Insurance Agent",
            "type":"Services"
        }
    ],
    "sg:phone":"+1 586 773 7950",
    "sg:postcode":"48080",
    "sg:province":"MI",
    "wof:name":"State Farm Insurance",
    "wof:placetype":"venue"
},
  "geometry": {"coordinates":[-82.912296,42.455985],"type":"Point"}
}