{
  "type": "Feature",
  "properties": {
    "iso:country":"US",
    "sg:address":"12170 Conant St",
    "sg:city":"Detroit",
    "sg:classifiers":[
        {
            "category":"Shopping",
            "subcategory":"Used Merchandise",
            "type":"Retail Goods"
        }
    ],
    "sg:phone":"+1 313 368 9857",
    "sg:postcode":"48212",
    "sg:province":"MI",
    "sg:tags":[
        "vintage",
        "consignment"
    ],
    "sg:website":"www.malonchofashion.com",
    "wof:name":"Maloncho Fashion Inc",
    "wof:placetype":"venue"
},
  "geometry": {"coordinates":[-83.056489,42.408441],"type":"Point"}
}