{
  "type": "Feature",
  "properties": {
    "iso:country":"US",
    "sg:address":"420 S Main St",
    "sg:city":"Clawson",
    "sg:classifiers":[
        {
            "category":"Manufacturing",
            "subcategory":"Printing",
            "type":"Manufacturing & Wholesale Goods"
        }
    ],
    "sg:phone":"+1 248 288 6008",
    "sg:postcode":"48017",
    "sg:province":"MI",
    "sg:tags":[
        "commercial"
    ],
    "wof:name":"Clawson Printing Co",
    "wof:placetype":"venue"
},
  "geometry": {"coordinates":[-83.146091,42.529774],"type":"Point"}
}