{
  "type": "Feature",
  "properties": {
    "iso:country":"US",
    "sg:address":"9532 Joseph Campau St",
    "sg:city":"Hamtramck",
    "sg:classifiers":[
        {
            "category":"Shopping",
            "subcategory":"Clothing, Apparel, & Fashions",
            "type":"Retail Goods"
        }
    ],
    "sg:phone":"+1 313 871 2515",
    "sg:postcode":"48212",
    "sg:province":"MI",
    "sg:tags":[
        "children's",
        "clothing"
    ],
    "sg:website":"www.treehousekidsclothing.com/",
    "wof:name":"The Treehouse",
    "wof:placetype":"venue"
},
  "geometry": {"coordinates":[-83.056702,42.395401],"type":"Point"}
}