{
  "type": "Feature",
  "properties": {
    "iso:country":"US",
    "sg:address":"1726 Leonard St NE",
    "sg:city":"Grand Rapids",
    "sg:classifiers":[
        {
            "category":"Health Services",
            "subcategory":"Doctor",
            "type":"Services"
        }
    ],
    "sg:phone":"+1 616 459 0478",
    "sg:postcode":"49505",
    "sg:province":"MI",
    "sg:tags":[
        "dentist"
    ],
    "wof:name":"Beckwith Family Dental Care",
    "wof:placetype":"venue"
},
  "geometry": {"coordinates":[-85.625705,42.984361],"type":"Point"}
}