{
  "type": "Feature",
  "properties": {
    "iso:country":"US",
    "sg:address":"35111 Grand River Ave",
    "sg:city":"Farmington",
    "sg:classifiers":[
        {
            "category":"Insurance",
            "subcategory":"Insurance Agent",
            "type":"Services"
        }
    ],
    "sg:phone":"+1 248 478 7010",
    "sg:postcode":"48335",
    "sg:province":"MI",
    "wof:name":"State Farm Insurance",
    "wof:placetype":"venue"
},
  "geometry": {"coordinates":[-83.395786,42.46899],"type":"Point"}
}