{
  "type": "Feature",
  "properties": {
    "iso:country":"US",
    "sg:address":"548 Lincoln Ave",
    "sg:city":"Lansing",
    "sg:classifiers":[
        {
            "category":"Building & Trades",
            "subcategory":"Cleaning & Sanitation",
            "type":"Services"
        }
    ],
    "sg:phone":"+1 517 485 6272",
    "sg:postcode":"48910",
    "sg:province":"MI",
    "sg:tags":[
        "maintenance"
    ],
    "wof:name":"E B Cleaning",
    "wof:placetype":"venue"
},
  "geometry": {"coordinates":[-84.544904,42.705928],"type":"Point"}
}