{
  "type": "Feature",
  "properties": {
    "iso:country":"US",
    "sg:address":"49952 Sandra",
    "sg:city":"Shelby Twp",
    "sg:classifiers":[
        {
            "category":"Building & Trades",
            "subcategory":"Construction",
            "type":"Services"
        }
    ],
    "sg:phone":"+1 586 323 1188",
    "sg:postcode":"48315",
    "sg:province":"MI",
    "sg:tags":[
        "roofing",
        "contractor"
    ],
    "wof:name":"Weatherseal Home Improvements",
    "wof:placetype":"venue"
},
  "geometry": {"coordinates":[-82.99668699999999,42.662168],"type":"Point"}
}