{
  "type": "Feature",
  "properties": {
    "iso:country":"US",
    "sg:address":"3519 W Bradford Dr",
    "sg:city":"Bloomfield Hills",
    "sg:classifiers":[
        {
            "category":"Professional",
            "subcategory":"Employment Agencies",
            "type":"Services"
        }
    ],
    "sg:phone":"+1 248 644 0809",
    "sg:postcode":"48301",
    "sg:province":"MI",
    "wof:name":"A To Z Odd Jobs Inc",
    "wof:placetype":"venue"
},
  "geometry": {"coordinates":[-83.262694,42.538508],"type":"Point"}
}