{
  "type": "Feature",
  "properties": {
    "iso:country":"US",
    "sg:address":"25755 Southfield Rd",
    "sg:city":"Southfield",
    "sg:classifiers":[
        {
            "category":"Recreation",
            "type":"Entertainment"
        }
    ],
    "sg:phone":"+1 248 398 8288",
    "sg:postcode":"48075",
    "sg:province":"MI",
    "wof:name":"International Career Academy",
    "wof:placetype":"venue"
},
  "geometry": {"coordinates":[-83.221514,42.479207],"type":"Point"}
}