{
  "type": "Feature",
  "properties": {
    "iso:country":"US",
    "sg:address":"7941 Cribbins Rd",
    "sg:city":"Croswell",
    "sg:classifiers":[
        {
            "category":"Freight",
            "type":"Transportation"
        }
    ],
    "sg:phone":"+1 810 679 4724",
    "sg:postcode":"48422",
    "sg:province":"MI",
    "wof:name":"Assessor Trucking",
    "wof:placetype":"venue"
},
  "geometry": {"coordinates":[-82.645065,43.194765],"type":"Point"}
}