{
  "type": "Feature",
  "properties": {
    "iso:country":"US",
    "sg:address":"5227 Riley St",
    "sg:city":"Hudsonville",
    "sg:classifiers":[
        {
            "category":"Farming",
            "subcategory":"Livestock Farm",
            "type":"Manufacturing & Wholesale Goods"
        }
    ],
    "sg:phone":"+1 616 896 9034",
    "sg:postcode":"49426",
    "sg:province":"MI",
    "sg:tags":[
        "beef",
        "feedlot",
        "cattle"
    ],
    "wof:name":"Donald Hoppen",
    "wof:placetype":"venue"
},
  "geometry": {"coordinates":[-85.917292,42.826136],"type":"Point"}
}