{
  "type": "Feature",
  "properties": {
    "iso:country":"US",
    "sg:address":"984 N Park",
    "sg:city":"Highland",
    "sg:classifiers":[
        {
            "category":"Manufacturing",
            "subcategory":"Metals",
            "type":"Manufacturing & Wholesale Goods"
        }
    ],
    "sg:phone":"+1 248 887 3640",
    "sg:postcode":"48356",
    "sg:province":"MI",
    "sg:tags":[
        "fabricator",
        "sheet"
    ],
    "wof:name":"Advantage Laser Inc",
    "wof:placetype":"venue"
},
  "geometry": {"coordinates":[-83.60593299999999,42.652497],"type":"Point"}
}