{
  "type": "Feature",
  "properties": {
    "iso:country":"US",
    "sg:address":"205 E Montezuma Ave",
    "sg:city":"Houghton",
    "sg:classifiers":[
        {
            "category":"Organizations",
            "subcategory":"Religious Organization",
            "type":"Services"
        }
    ],
    "sg:phone":"+1 906 482 2010",
    "sg:postcode":"49931",
    "sg:province":"MI",
    "sg:tags":[
        "episcopal",
        "church"
    ],
    "wof:name":"Trinity Episcopal Church Inc",
    "wof:placetype":"venue"
},
  "geometry": {"coordinates":[-88.571856,47.121064],"type":"Point"}
}