{
  "type": "Feature",
  "properties": {
    "iso:country":"US",
    "sg:address":"20087 Caldwell St",
    "sg:city":"Northville",
    "sg:classifiers":[
        {
            "category":"Real Estate",
            "subcategory":"Real Estate Agent",
            "type":"Services"
        }
    ],
    "sg:phone":"+1 248 349 1556",
    "sg:postcode":"48167",
    "sg:province":"MI",
    "sg:tags":[
        "house",
        "construct"
    ],
    "wof:name":"Anthony V Rizzo",
    "wof:placetype":"venue"
},
  "geometry": {"coordinates":[-83.493621,42.431816],"type":"Point"}
}