{
  "type": "Feature",
  "properties": {
    "iso:country":"US",
    "sg:address":"2080 S Huron Rd",
    "sg:city":"Kawkawlin",
    "sg:classifiers":[
        {
            "category":"Real Estate",
            "subcategory":"Real Estate Operator",
            "type":"Services"
        }
    ],
    "sg:phone":"+1 989 684 3792",
    "sg:postcode":"48631",
    "sg:province":"MI",
    "sg:tags":[
        "mobile",
        "home",
        "park"
    ],
    "wof:name":"Pines Trailer Parks",
    "wof:placetype":"venue"
},
  "geometry": {"coordinates":[-83.959642,43.680154],"type":"Point"}
}