{
  "type": "Feature",
  "properties": {
    "iso:country":"US",
    "sg:address":"10151 Burton Ave",
    "sg:city":"Oak Park",
    "sg:classifiers":[
        {
            "category":"Real Estate",
            "subcategory":"Real Estate Operator",
            "type":"Services"
        }
    ],
    "sg:phone":"+1 248 543 5428",
    "sg:postcode":"48237",
    "sg:province":"MI",
    "sg:tags":[
        "building",
        "apartment"
    ],
    "wof:name":"Arlington Manor Apartments LLP",
    "wof:placetype":"venue"
},
  "geometry": {"coordinates":[-83.166719,42.472251],"type":"Point"}
}