{
  "type": "Feature",
  "properties": {
    "iso:country":"US",
    "sg:address":"300 N State St",
    "sg:city":"Stanton",
    "sg:classifiers":[
        {
            "category":"Health Services",
            "subcategory":"Clinic",
            "type":"Services"
        }
    ],
    "sg:phone":"+1 989 831 5045",
    "sg:postcode":"48888",
    "sg:province":"MI",
    "sg:tags":[
        "home"
    ],
    "wof:name":"Gratiot Home Care & Hospice",
    "wof:placetype":"venue"
},
  "geometry": {"coordinates":[-85.08480299999999,43.295916],"type":"Point"}
}