{
  "type": "Feature",
  "properties": {
    "iso:country":"US",
    "sg:address":"1713 Gardenia Ave",
    "sg:city":"Royal Oak",
    "sg:classifiers":[
        {
            "category":"Organizations",
            "subcategory":"Professional Association",
            "type":"Services"
        }
    ],
    "sg:phone":"+1 248 584 3303",
    "sg:postcode":"48067",
    "sg:province":"MI",
    "sg:tags":[
        "business"
    ],
    "wof:name":"Cornerstone Project Inc",
    "wof:placetype":"venue"
},
  "geometry": {"coordinates":[-83.123527,42.498547],"type":"Point"}
}