{
  "type": "Feature",
  "properties": {
    "iso:country":"US",
    "sg:address":"2289 Parmalee Ln",
    "sg:city":"Brighton",
    "sg:classifiers":[
        {
            "category":"Manufacturing",
            "subcategory":"Metals",
            "type":"Manufacturing & Wholesale Goods"
        }
    ],
    "sg:phone":"+1 810 229 4930",
    "sg:postcode":"48114",
    "sg:province":"MI",
    "sg:tags":[
        "mfg",
        "automotive",
        "stampings",
        "supply"
    ],
    "wof:name":"Spridgetech Inc",
    "wof:placetype":"venue"
},
  "geometry": {"coordinates":[-83.721039,42.570268],"type":"Point"}
}