{
  "type": "Feature",
  "properties": {
    "iso:country":"US",
    "sg:address":"51996 Monaco Dr",
    "sg:city":"Macomb",
    "sg:classifiers":[
        {
            "category":"Wholesale",
            "subcategory":"Auto Parts",
            "type":"Manufacturing & Wholesale Goods"
        }
    ],
    "sg:phone":"+1 586 677 6524",
    "sg:postcode":"48042",
    "sg:province":"MI",
    "wof:name":"A & E Performance",
    "wof:placetype":"venue"
},
  "geometry": {"coordinates":[-82.932069,42.679219],"type":"Point"}
}