{
  "type": "Feature",
  "properties": {
    "iso:country":"US",
    "sg:address":"4356 Chicago Dr SW",
    "sg:city":"Grandville",
    "sg:classifiers":[
        {
            "category":"Personal",
            "subcategory":"Beauty Salon",
            "type":"Services"
        }
    ],
    "sg:phone":"+1 616 532 3226",
    "sg:postcode":"49418",
    "sg:province":"MI",
    "wof:name":"Hairport",
    "wof:placetype":"venue"
},
  "geometry": {"coordinates":[-85.771326,42.906779],"type":"Point"}
}