{
  "type": "Feature",
  "properties": {
    "iso:country":"US",
    "sg:address":"2219 Manchester Dr",
    "sg:city":"Saginaw",
    "sg:classifiers":[
        {
            "category":"Professional",
            "subcategory":"Management & Consulting",
            "type":"Services"
        }
    ],
    "sg:phone":"+1 989 781 4947",
    "sg:postcode":"48609",
    "sg:province":"MI",
    "sg:tags":[
        "datum",
        "m",
        "public",
        "relations"
    ],
    "wof:name":"Fortune II Internet Market",
    "wof:placetype":"venue"
},
  "geometry": {"coordinates":[-84.070695,43.441463],"type":"Point"}
}