{
  "type": "Feature",
  "properties": {
    "iso:country":"US",
    "sg:address":"3085 Palm Aire Dr",
    "sg:city":"Rochester",
    "sg:classifiers":[
        {
            "category":"Manufacturing",
            "subcategory":"Retail Goods",
            "type":"Manufacturing & Wholesale Goods"
        }
    ],
    "sg:phone":"+1 248 375 1087",
    "sg:postcode":"48309",
    "sg:province":"MI",
    "sg:tags":[
        "product",
        "mfg"
    ],
    "wof:name":"Kowality Pole & Flag",
    "wof:placetype":"venue"
},
  "geometry": {"coordinates":[-83.196011,42.692945],"type":"Point"}
}