{
  "type": "Feature",
  "properties": {
    "iso:country":"US",
    "sg:address":"200 Hyne St",
    "sg:city":"Brighton",
    "sg:classifiers":[
        {
            "category":"Shopping",
            "subcategory":"Gifts & Souvenirs",
            "type":"Retail Goods"
        }
    ],
    "sg:phone":"+1 810 227 2837",
    "sg:postcode":"48116",
    "sg:province":"MI",
    "sg:tags":[
        "shop"
    ],
    "wof:name":"Wood N Things Inc",
    "wof:placetype":"venue"
},
  "geometry": {"coordinates":[-83.783964,42.528624],"type":"Point"}
}