{
  "type": "Feature",
  "properties": {
    "iso:country":"US",
    "sg:address":"2495 Crescent Lake Rd",
    "sg:city":"Waterford",
    "sg:classifiers":[
        {
            "category":"Government",
            "subcategory":"Fire Station",
            "type":"Public Place"
        }
    ],
    "sg:phone":"+1 248 673 0405",
    "sg:postcode":"48329",
    "sg:province":"MI",
    "sg:tags":[
        "department"
    ],
    "wof:name":"Water Township Fire Dept",
    "wof:placetype":"venue"
},
  "geometry": {"coordinates":[-83.386842,42.672253],"type":"Point"}
}