{
  "type": "Feature",
  "properties": {
    "iso:country":"US",
    "sg:address":"855 Cliffs Dr",
    "sg:city":"Ypsilanti",
    "sg:classifiers":[
        {
            "category":"Professional",
            "subcategory":"Management & Consulting",
            "type":"Services"
        }
    ],
    "sg:phone":"+1 734 482 3833",
    "sg:postcode":"48198",
    "sg:province":"MI",
    "sg:tags":[
        "business"
    ],
    "wof:name":"McM Consultants",
    "wof:placetype":"venue"
},
  "geometry": {"coordinates":[-83.596574,42.223253],"type":"Point"}
}