{
  "type": "Feature",
  "properties": {
    "iso:country":"US",
    "sg:address":"10712 Mac Arthur Rd",
    "sg:city":"Levering",
    "sg:classifiers":[
        {
            "category":"Retail",
            "subcategory":"Laundry & Dry Cleaning",
            "type":"Services"
        }
    ],
    "sg:phone":"+1 231 537 2677",
    "sg:postcode":"49755",
    "sg:province":"MI",
    "wof:name":"Shawn Garments & Alterati",
    "wof:placetype":"venue"
},
  "geometry": {"coordinates":[-84.702708,45.615903],"type":"Point"}
}