{
  "type": "Feature",
  "properties": {
    "iso:country":"US",
    "sg:address":"120 E Newark St",
    "sg:city":"Ithaca",
    "sg:classifiers":[
        {
            "category":"Retail",
            "subcategory":"Veterinary Services",
            "type":"Services"
        }
    ],
    "sg:phone":"+1 989 875 3185",
    "sg:postcode":"48847",
    "sg:province":"MI",
    "sg:tags":[
        "veterinarian"
    ],
    "wof:name":"Ithaca Animal Hospital",
    "wof:placetype":"venue"
},
  "geometry": {"coordinates":[-84.607299,43.290436],"type":"Point"}
}