{
  "type": "Feature",
  "properties": {
    "iso:country":"US",
    "sg:address":"210 E Surrey Rd",
    "sg:city":"Farwell",
    "sg:classifiers":[
        {
            "category":"Retail",
            "subcategory":"Repair Shop",
            "type":"Services"
        }
    ],
    "sg:phone":"+1 989 588 8995",
    "sg:postcode":"48622",
    "sg:province":"MI",
    "sg:tags":[
        "welding"
    ],
    "wof:name":"Bruce & Kelee",
    "wof:placetype":"venue"
},
  "geometry": {"coordinates":[-84.84883600000001,43.857524],"type":"Point"}
}