{
  "type": "Feature",
  "properties": {
    "iso:country":"US",
    "sg:address":"12245 Alpena Rd",
    "sg:city":"Posen",
    "sg:classifiers":[
        {
            "category":"Utilities",
            "subcategory":"Electric",
            "type":"Services"
        }
    ],
    "sg:phone":"+1 989 766 2579",
    "sg:postcode":"49776",
    "sg:province":"MI",
    "sg:tags":[
        "company"
    ],
    "wof:name":"Wolverine Power Supply",
    "wof:placetype":"venue"
},
  "geometry": {"coordinates":[-83.65185700000001,45.250493],"type":"Point"}
}