{
  "type": "Feature",
  "properties": {
    "iso:country":"US",
    "sg:address":"1025 S Payne Lake Rd",
    "sg:city":"Wayland",
    "sg:classifiers":[
        {
            "category":"Home & Garden",
            "subcategory":"Building Materials",
            "type":"Retail Goods"
        }
    ],
    "sg:phone":"+1 269 795 7549",
    "sg:postcode":"49348",
    "sg:province":"MI",
    "sg:tags":[
        "modular"
    ],
    "wof:name":"First Choice Modular Homes",
    "wof:placetype":"venue"
},
  "geometry": {"coordinates":[-85.525972,42.638529],"type":"Point"}
}