{
  "type": "Feature",
  "properties": {
    "iso:country":"US",
    "sg:address":"3110 Ogden Hwy",
    "sg:city":"Adrian",
    "sg:classifiers":[
        {
            "category":"Autos & Motor Vehicles",
            "subcategory":"Automobile Sales",
            "type":"Retail Goods"
        }
    ],
    "sg:phone":"+1 517 263 1377",
    "sg:postcode":"49221",
    "sg:province":"MI",
    "sg:tags":[
        "truck"
    ],
    "wof:name":"Lenawee Truck Sales and Svc",
    "wof:placetype":"venue"
},
  "geometry": {"coordinates":[-83.99226,41.874455],"type":"Point"}
}