{
  "type": "Feature",
  "properties": {
    "iso:country":"US",
    "sg:address":"18145 Mack Ave",
    "sg:city":"Detroit",
    "sg:classifiers":[
        {
            "category":"Social Services",
            "type":"Services"
        }
    ],
    "sg:phone":"+1 313 647 9620",
    "sg:postcode":"48224",
    "sg:province":"MI",
    "sg:tags":[
        "for",
        "family",
        "assistance",
        "tax",
        "low",
        "income"
    ],
    "wof:name":"Accounting Aid Society Inc",
    "wof:placetype":"venue"
},
  "geometry": {"coordinates":[-82.915317,42.406656],"type":"Point"}
}