{
  "type": "Feature",
  "properties": {
    "iso:country":"US",
    "sg:address":"10750 Capital St",
    "sg:city":"Oak Park",
    "sg:classifiers":[
        {
            "category":"Manufacturing",
            "subcategory":"Food",
            "type":"Manufacturing & Wholesale Goods"
        }
    ],
    "sg:phone":"+1 248 544 4574",
    "sg:postcode":"48237",
    "sg:province":"MI",
    "sg:tags":[
        "vegetable",
        "fruit"
    ],
    "sg:website":"www.midasfoods.com",
    "wof:name":"Michigan Desserts",
    "wof:placetype":"venue"
},
  "geometry": {"coordinates":[-83.16954800000001,42.455553],"type":"Point"}
}