{
  "type": "Feature",
  "properties": {
    "iso:country":"US",
    "sg:address":"4011 E Rosebush Rd",
    "sg:city":"Rosebush",
    "sg:classifiers":[
        {
            "category":"Banks & Credit Unions",
            "subcategory":"Bank",
            "type":"Services"
        }
    ],
    "sg:phone":"+1 989 433 2976",
    "sg:postcode":"48878",
    "sg:province":"MI",
    "wof:name":"Chemical Bank & Trust Co",
    "wof:placetype":"venue"
},
  "geometry": {"coordinates":[-84.766852,43.698549],"type":"Point"}
}