{
  "type": "Feature",
  "properties": {
    "iso:country":"US",
    "sg:address":"549 E Chicago St",
    "sg:city":"Bronson",
    "sg:classifiers":[
        {
            "category":"Shopping",
            "subcategory":"Computers & Home Electronics",
            "type":"Retail Goods"
        }
    ],
    "sg:phone":"+1 517 369 6035",
    "sg:postcode":"49028",
    "sg:province":"MI",
    "sg:tags":[
        "software"
    ],
    "wof:name":"Power Bible Tech Help",
    "wof:placetype":"venue"
},
  "geometry": {"coordinates":[-85.188138,41.873419],"type":"Point"}
}