{
  "type": "Feature",
  "properties": {
    "iso:country":"US",
    "sg:address":"2232 N Benson Rd",
    "sg:city":"Fountain",
    "sg:classifiers":[
        {
            "category":"Autos & Motor Vehicles",
            "subcategory":"Automobile Sales",
            "type":"Retail Goods"
        }
    ],
    "sg:phone":"+1 231 462 3336",
    "sg:postcode":"49410",
    "sg:province":"MI",
    "sg:tags":[
        "car",
        "used",
        "dealer"
    ],
    "wof:name":"Vander Haag Used Car Sales",
    "wof:placetype":"venue"
},
  "geometry": {"coordinates":[-86.12060700000001,43.997386],"type":"Point"}
}