{
  "type": "Feature",
  "properties": {
    "iso:country":"US",
    "sg:address":"3580 S Van Dyke Rd",
    "sg:city":"Marlette",
    "sg:classifiers":[
        {
            "category":"Real Estate",
            "subcategory":"Developer",
            "type":"Services"
        }
    ],
    "sg:phone":"+1 989 635 7325",
    "sg:postcode":"48453",
    "sg:province":"MI",
    "sg:tags":[
        "cemetery"
    ],
    "wof:name":"Marlette Cemetery",
    "wof:placetype":"venue"
},
  "geometry": {"coordinates":[-83.07986699999999,43.313598],"type":"Point"}
}