{
  "type": "Feature",
  "properties": {
    "iso:country":"US",
    "sg:address":"441 Gumwood Rd",
    "sg:city":"Niles",
    "sg:classifiers":[
        {
            "category":"Building & Trades",
            "subcategory":"Cleaning & Sanitation",
            "type":"Services"
        }
    ],
    "sg:phone":"+1 269 683 4349",
    "sg:postcode":"49120",
    "sg:province":"MI",
    "sg:tags":[
        "janitor"
    ],
    "wof:name":"Aim Cleaning Svc",
    "wof:placetype":"venue"
},
  "geometry": {"coordinates":[-86.186156,41.786241],"type":"Point"}
}