{
  "type": "Feature",
  "properties": {
    "iso:country":"US",
    "sg:address":"889 Twin Towers St",
    "sg:city":"Ypsilanti",
    "sg:classifiers":[
        {
            "category":"Building & Trades",
            "subcategory":"Construction",
            "type":"Services"
        }
    ],
    "sg:phone":"+1 734 485 7893",
    "sg:postcode":"48198",
    "sg:province":"MI",
    "sg:tags":[
        "house"
    ],
    "wof:name":"McCully Construction",
    "wof:placetype":"venue"
},
  "geometry": {"coordinates":[-83.59737699999999,42.252439],"type":"Point"}
}