{
  "type": "Feature",
  "properties": {
    "iso:country":"US",
    "sg:address":"852 S Hooper St",
    "sg:city":"Caro",
    "sg:classifiers":[
        {
            "category":"Sports & Exercise",
            "subcategory":"Gym",
            "type":"Entertainment"
        }
    ],
    "sg:phone":"+1 989 673 4888",
    "sg:postcode":"48723",
    "sg:province":"MI",
    "sg:tags":[
        "club",
        "health",
        "studio",
        "gymnasium"
    ],
    "wof:name":"Curves For Women",
    "wof:placetype":"venue"
},
  "geometry": {"coordinates":[-83.406297,43.48178],"type":"Point"}
}