{
  "type": "Feature",
  "properties": {
    "iso:country":"US",
    "sg:address":"5186 N Lake Sanford Rd",
    "sg:city":"Sanford",
    "sg:classifiers":[
        {
            "category":"Shopping",
            "subcategory":"Crafts & Fabrics",
            "type":"Retail Goods"
        }
    ],
    "sg:phone":"+1 989 689 6275",
    "sg:postcode":"48657",
    "sg:province":"MI",
    "sg:tags":[
        "sewing"
    ],
    "wof:name":"Sew Fine Designs",
    "wof:placetype":"venue"
},
  "geometry": {"coordinates":[-84.407515,43.756984],"type":"Point"}
}