{
  "type": "Feature",
  "properties": {
    "iso:country":"US",
    "sg:address":"6257 Orchard Lake Rd",
    "sg:city":"West Bloomfield",
    "sg:classifiers":[
        {
            "category":"Restaurant",
            "type":"Food & Drink"
        }
    ],
    "sg:phone":"+1 248 855 3570",
    "sg:postcode":"48322",
    "sg:province":"MI",
    "wof:name":"Golden Phoenix",
    "wof:placetype":"venue"
},
  "geometry": {"coordinates":[-83.360703,42.544998],"type":"Point"}
}