{
  "type": "Feature",
  "properties": {
    "iso:country":"US",
    "sg:address":"120 Ionia Ave SW",
    "sg:city":"Grand Rapids",
    "sg:classifiers":[
        {
            "category":"Shopping",
            "subcategory":"Clothing, Apparel, & Fashions",
            "type":"Retail Goods"
        }
    ],
    "sg:phone":"+1 616 454 2380",
    "sg:postcode":"49503",
    "sg:province":"MI",
    "sg:tags":[
        "accessory"
    ],
    "sg:website":"www.ljbullian.com",
    "wof:name":"L J Bullian Clothier L L C",
    "wof:placetype":"venue"
},
  "geometry": {"coordinates":[-85.670092,42.959948],"type":"Point"}
}