{
  "type": "Feature",
  "properties": {
    "iso:country":"US",
    "sg:address":"11950 Hall Rd",
    "sg:city":"Sterling Heights",
    "sg:classifiers":[
        {
            "category":"Shopping",
            "subcategory":"Bicycles & Sporting Goods",
            "type":"Retail Goods"
        }
    ],
    "sg:phone":"+1 586 997 1600",
    "sg:postcode":"48313",
    "sg:province":"MI",
    "sg:website":"www.dunhams.com",
    "wof:name":"Dunham's Sports",
    "wof:placetype":"venue"
},
  "geometry": {"coordinates":[-83.00511299999999,42.626373],"type":"Point"}
}