{
  "type": "Feature",
  "properties": {
    "iso:country":"US",
    "sg:address":"10520 Rathbun Way",
    "sg:city":"Birch Run",
    "sg:classifiers":[
        {
            "category":"Building & Trades",
            "subcategory":"Construction",
            "type":"Services"
        }
    ],
    "sg:phone":"+1 989 624 9963",
    "sg:postcode":"48415",
    "sg:province":"MI",
    "sg:tags":[
        "house"
    ],
    "wof:name":"Thomas A Purman Builder",
    "wof:placetype":"venue"
},
  "geometry": {"coordinates":[-83.795489,43.269071],"type":"Point"}
}