{
  "type": "Feature",
  "properties": {
    "iso:country":"US",
    "sg:address":"5108 Jackson Rd",
    "sg:city":"Ironwood",
    "sg:classifiers":[
        {
            "category":"Home & Garden",
            "subcategory":"Building Materials",
            "type":"Retail Goods"
        }
    ],
    "sg:phone":"+1 906 932 2311",
    "sg:postcode":"49938",
    "sg:province":"MI",
    "sg:tags":[
        "lumber"
    ],
    "sg:website":"www.forslund.com",
    "wof:name":"Forslund Building Supply Inc",
    "wof:placetype":"venue"
},
  "geometry": {"coordinates":[-90.153048,46.470622],"type":"Point"}
}