{
  "type": "Feature",
  "properties": {
    "iso:country":"US",
    "sg:address":"6023 Litchfield Ln",
    "sg:city":"Kalamazoo",
    "sg:classifiers":[
        {
            "category":"Social Services",
            "subcategory":"Adult Care",
            "type":"Services"
        }
    ],
    "sg:phone":"+1 269 375 0438",
    "sg:postcode":"49009",
    "sg:province":"MI",
    "sg:tags":[
        "residential"
    ],
    "wof:name":"Tls Litchfield LLC",
    "wof:placetype":"venue"
},
  "geometry": {"coordinates":[-85.66996,42.304615],"type":"Point"}
}