{
  "type": "Feature",
  "properties": {
    "iso:country":"US",
    "sg:address":"721 E Main St",
    "sg:city":"Niles",
    "sg:classifiers":[
        {
            "category":"Insurance",
            "subcategory":"Insurance Agent",
            "type":"Services"
        }
    ],
    "sg:phone":"+1 269 684 3500",
    "sg:postcode":"49120",
    "sg:province":"MI",
    "wof:name":"Talon The Group",
    "wof:placetype":"venue"
},
  "geometry": {"coordinates":[-86.251166,41.829415],"type":"Point"}
}