{
  "type": "Feature",
  "properties": {
    "iso:country":"US",
    "sg:address":"5916 S Main St",
    "sg:city":"Clarkston",
    "sg:classifiers":[
        {
            "category":"Retail",
            "subcategory":"Laundry & Dry Cleaning",
            "type":"Services"
        }
    ],
    "sg:phone":"+1 248 625 0135",
    "sg:postcode":"48346",
    "sg:province":"MI",
    "sg:tags":[
        "drycleaning",
        "plant"
    ],
    "wof:name":"Clarkston Dry Cleaners",
    "wof:placetype":"venue"
},
  "geometry": {"coordinates":[-83.418633,42.725263],"type":"Point"}
}