{
  "type": "Feature",
  "properties": {
    "iso:country":"US",
    "sg:address":"211 E Main St",
    "sg:city":"Niles",
    "sg:classifiers":[
        {
            "category":"Shopping",
            "subcategory":"Hobbies, Toys, & Games",
            "type":"Retail Goods"
        }
    ],
    "sg:phone":"+1 269 687 8550",
    "sg:postcode":"49120",
    "sg:province":"MI",
    "sg:tags":[
        "model",
        "supply"
    ],
    "wof:name":"Action Hobbies",
    "wof:placetype":"venue"
},
  "geometry": {"coordinates":[-86.257304,41.829988],"type":"Point"}
}