{
  "type": "Feature",
  "properties": {
    "iso:country":"US",
    "sg:address":"10200 Highland Rd",
    "sg:city":"White Lake",
    "sg:classifiers":[
        {
            "category":"Building & Trades",
            "subcategory":"Construction",
            "type":"Services"
        }
    ],
    "sg:phone":"+1 248 698 1504",
    "sg:postcode":"48386",
    "sg:province":"MI",
    "sg:tags":[
        "general",
        "contractor"
    ],
    "wof:name":"Hugh Loyer Inc",
    "wof:placetype":"venue"
},
  "geometry": {"coordinates":[-83.48751900000001,42.651847],"type":"Point"}
}