{
  "type": "Feature",
  "properties": {
    "iso:country":"US",
    "sg:address":"4025 Owen Rd",
    "sg:city":"Fenton",
    "sg:classifiers":[
        {
            "category":"Retail",
            "subcategory":"Laundry & Dry Cleaning",
            "type":"Services"
        }
    ],
    "sg:phone":"+1 810 750 4530",
    "sg:postcode":"48430",
    "sg:province":"MI",
    "sg:tags":[
        "cleaners"
    ],
    "wof:name":"Brenda's Best Dry Cleaners",
    "wof:placetype":"venue"
},
  "geometry": {"coordinates":[-83.750243,42.789458],"type":"Point"}
}