{
  "type": "Feature",
  "properties": {
    "iso:country":"US",
    "sg:address":"6691 Boca Vista Dr NE",
    "sg:city":"Rockford",
    "sg:classifiers":[
        {
            "category":"Professional",
            "subcategory":"Business Services",
            "type":"Services"
        }
    ],
    "sg:phone":"+1 616 874 3019",
    "sg:postcode":"49341",
    "sg:province":"MI",
    "wof:name":"Boatlifts Express",
    "wof:placetype":"venue"
},
  "geometry": {"coordinates":[-85.504824,43.089793],"type":"Point"}
}