{
  "type": "Feature",
  "properties": {
    "iso:country":"US",
    "sg:address":"111 Ellen Dr",
    "sg:city":"Lake Orion",
    "sg:classifiers":[
        {
            "category":"Wholesale",
            "subcategory":"Machinery & Supplies",
            "type":"Manufacturing & Wholesale Goods"
        }
    ],
    "sg:phone":"+1 248 340 8600",
    "sg:postcode":"48359",
    "sg:province":"MI",
    "sg:website":"www.campbellsorensen.com",
    "wof:name":"Campbell Sorensen Co Inc",
    "wof:placetype":"venue"
},
  "geometry": {"coordinates":[-83.237798,42.71188],"type":"Point"}
}