{
  "type": "Feature",
  "properties": {
    "iso:country":"US",
    "sg:address":"1126 Edgeorge Dr",
    "sg:city":"Waterford",
    "sg:classifiers":[
        {
            "category":"Manufacturing",
            "subcategory":"Tools & Machinery",
            "type":"Manufacturing & Wholesale Goods"
        }
    ],
    "sg:phone":"+1 248 673 3759",
    "sg:postcode":"48327",
    "sg:province":"MI",
    "wof:name":"Michigan Machine Mntnnc Inc",
    "wof:placetype":"venue"
},
  "geometry": {"coordinates":[-83.39483300000001,42.653914],"type":"Point"}
}