{
  "type": "Feature",
  "properties": {
    "iso:country":"US",
    "sg:address":"222 S Whittaker St",
    "sg:city":"New Buffalo",
    "sg:classifiers":[
        {
            "category":"Building & Trades",
            "subcategory":"Construction",
            "type":"Services"
        }
    ],
    "sg:phone":"+1 269 469 6859",
    "sg:postcode":"49117",
    "sg:province":"MI",
    "sg:tags":[
        "general",
        "contractor"
    ],
    "wof:name":"Shelton Construction",
    "wof:placetype":"venue"
},
  "geometry": {"coordinates":[-86.741863,41.79157],"type":"Point"}
}