{
  "type": "Feature",
  "properties": {
    "iso:country":"US",
    "sg:address":"7501 US Hwy 31",
    "sg:city":"Alanson",
    "sg:classifiers":[
        {
            "category":"Home & Garden",
            "subcategory":"Furniture",
            "type":"Retail Goods"
        }
    ],
    "sg:phone":"+1 231 548 2726",
    "sg:postcode":"49706",
    "sg:province":"MI",
    "wof:name":"Northern Lodge Interiors",
    "wof:placetype":"venue"
},
  "geometry": {"coordinates":[-84.78810300000001,45.441991],"type":"Point"}
}