{
  "type": "Feature",
  "properties": {
    "iso:country":"US",
    "sg:address":"25010 Harper Ave",
    "sg:city":"Saint Clair Shores",
    "sg:classifiers":[
        {
            "category":"Bars & Pubs",
            "type":"Food & Drink"
        }
    ],
    "sg:phone":"+1 586 771 5121",
    "sg:postcode":"48080",
    "sg:province":"MI",
    "sg:tags":[
        "burger"
    ],
    "wof:name":"Sabby's Bar",
    "wof:placetype":"venue"
},
  "geometry": {"coordinates":[-82.90160400000001,42.48],"type":"Point"}
}