{
  "type": "Feature",
  "properties": {
    "iso:country":"US",
    "sg:address":"129 S Kalamazoo St",
    "sg:city":"Paw Paw",
    "sg:classifiers":[
        {
            "category":"Organizations",
            "subcategory":"Non-profit Organization",
            "type":"Services"
        }
    ],
    "sg:phone":"+1 269 657 7919",
    "sg:postcode":"49079",
    "sg:province":"MI",
    "sg:tags":[
        "action",
        "agency",
        "community"
    ],
    "wof:name":"Carnegie Community Ctr",
    "wof:placetype":"venue"
},
  "geometry": {"coordinates":[-85.890891,42.217393],"type":"Point"}
}