{
  "type": "Feature",
  "properties": {
    "iso:country":"US",
    "sg:address":"14515 Ford Rd",
    "sg:city":"Dearborn",
    "sg:classifiers":[
        {
            "category":"Health Services",
            "subcategory":"Doctor",
            "type":"Services"
        }
    ],
    "sg:phone":"+1 313 581 4511",
    "sg:postcode":"48126",
    "sg:province":"MI",
    "wof:name":"Berri Ziad MD",
    "wof:placetype":"venue"
},
  "geometry": {"coordinates":[-83.18499799999999,42.329201],"type":"Point"}
}