{
  "type": "Feature",
  "properties": {
    "iso:country":"US",
    "sg:address":"5696 Shady Oak Ln",
    "sg:city":"Jackson",
    "sg:classifiers":[
        {
            "category":"Recreation",
            "type":"Entertainment"
        }
    ],
    "sg:phone":"+1 517 764 7767",
    "sg:postcode":"49201",
    "sg:province":"MI",
    "sg:tags":[
        "animal"
    ],
    "sg:website":"www.dcstables.com",
    "wof:name":"Dream Catcher Stables",
    "wof:placetype":"venue"
},
  "geometry": {"coordinates":[-84.314584,42.279771],"type":"Point"}
}