{
  "type": "Feature",
  "properties": {
    "iso:country":"US",
    "sg:address":"318 Houston Ave",
    "sg:city":"Muskegon",
    "sg:classifiers":[
        {
            "category":"Banks & Credit Unions",
            "subcategory":"Investment Brokerage",
            "type":"Services"
        }
    ],
    "sg:phone":"+1 231 722 3206",
    "sg:postcode":"49441",
    "sg:province":"MI",
    "sg:tags":[
        "security"
    ],
    "wof:name":"Linsco Private Ledger Fncl Svc",
    "wof:placetype":"venue"
},
  "geometry": {"coordinates":[-86.252213,43.230933],"type":"Point"}
}