{
  "type": "Feature",
  "properties": {
    "iso:country":"US",
    "sg:address":"41143 Westfield Cir",
    "sg:city":"Canton",
    "sg:classifiers":[
        {
            "category":"Health Services",
            "subcategory":"Clinic",
            "type":"Services"
        }
    ],
    "sg:phone":"+1 734 397 9706",
    "sg:postcode":"48188",
    "sg:province":"MI",
    "wof:name":"Progressive Medical Equipment",
    "wof:placetype":"venue"
},
  "geometry": {"coordinates":[-83.447076,42.3027],"type":"Point"}
}