{
  "type": "Feature",
  "properties": {
    "iso:country":"US",
    "sg:address":"21960 Northland Dr",
    "sg:city":"Paris",
    "sg:classifiers":[
        {
            "category":"Education",
            "subcategory":"Dance Studio",
            "type":"Public Place"
        }
    ],
    "sg:phone":"+1 231 527 1553",
    "sg:postcode":"49338",
    "sg:province":"MI",
    "sg:tags":[
        "fitness",
        "physical",
        "facility"
    ],
    "wof:name":"Rhythmic Sky Studios",
    "wof:placetype":"venue"
},
  "geometry": {"coordinates":[-85.502833,43.781667],"type":"Point"}
}