{
  "type": "Feature",
  "properties": {
    "iso:country":"US",
    "sg:address":"3925 E Seymour Lake Rd",
    "sg:city":"Ortonville",
    "sg:classifiers":[
        {
            "category":"Food & Beverages",
            "subcategory":"Fruits & Vegetables",
            "type":"Retail Goods"
        }
    ],
    "sg:phone":"+1 248 627 6671",
    "sg:postcode":"48462",
    "sg:province":"MI",
    "sg:tags":[
        "farm",
        "market"
    ],
    "wof:name":"Ashton Orchards",
    "wof:placetype":"venue"
},
  "geometry": {"coordinates":[-83.382777,42.809235],"type":"Point"}
}