{
  "type": "Feature",
  "properties": {
    "iso:country":"US",
    "sg:address":"6034 Airborne St",
    "sg:city":"Romulus",
    "sg:classifiers":[
        {
            "category":"Building & Trades",
            "subcategory":"Construction",
            "type":"Services"
        }
    ],
    "sg:phone":"+1 734 231 0109",
    "sg:postcode":"48174",
    "sg:province":"MI",
    "sg:tags":[
        "sealcoating",
        "asphalt",
        "paving"
    ],
    "wof:name":"Advanced Asphalt",
    "wof:placetype":"venue"
},
  "geometry": {"coordinates":[-83.31782699999999,42.265207],"type":"Point"}
}