{
  "type": "Feature",
  "properties": {
    "iso:country":"US",
    "sg:address":"24285 Red Arrow Hwy",
    "sg:city":"Mattawan",
    "sg:classifiers":[
        {
            "category":"Personal",
            "subcategory":"Tanning Parlor",
            "type":"Services"
        },
        {
            "category":"Personal",
            "type":"Services"
        }
    ],
    "sg:phone":"+1 269 668 4370",
    "sg:postcode":"49071",
    "sg:province":"MI",
    "sg:tags":[
        "equipment",
        "salon"
    ],
    "wof:name":"Tan-Fast-N-Splash Inc",
    "wof:placetype":"venue"
},
  "geometry": {"coordinates":[-85.78823199999999,42.236505],"type":"Point"}
}