{
  "type": "Feature",
  "properties": {
    "iso:country":"US",
    "sg:address":"710 Salzburg Ave",
    "sg:city":"Bay City",
    "sg:classifiers":[
        {
            "category":"Shopping",
            "subcategory":"Florist",
            "type":"Retail Goods"
        }
    ],
    "sg:phone":"+1 989 893 3322",
    "sg:postcode":"48706",
    "sg:province":"MI",
    "wof:name":"M & M Flowers & Gifts",
    "wof:placetype":"venue"
},
  "geometry": {"coordinates":[-83.911467,43.580375],"type":"Point"}
}