{
  "type": "Feature",
  "properties": {
    "iso:country":"US",
    "sg:address":"12325 McPherson St NE",
    "sg:city":"Lowell",
    "sg:classifiers":[
        {
            "category":"Building & Trades",
            "subcategory":"Construction",
            "type":"Services"
        }
    ],
    "sg:phone":"+1 616 897 4330",
    "sg:postcode":"49331",
    "sg:province":"MI",
    "sg:tags":[
        "mobile",
        "home"
    ],
    "wof:name":"Dreamsetters Mobile Home Setup",
    "wof:placetype":"venue"
},
  "geometry": {"coordinates":[-85.370046,42.987393],"type":"Point"}
}