{
  "type": "Feature",
  "properties": {
    "iso:country":"US",
    "sg:address":"2373 E 8 Mile Rd",
    "sg:city":"Warren",
    "sg:classifiers":[
        {
            "category":"Home & Garden",
            "subcategory":"Building Materials",
            "type":"Retail Goods"
        }
    ],
    "sg:phone":"+1 586 759 1004",
    "sg:postcode":"48091",
    "sg:province":"MI",
    "sg:tags":[
        "glass",
        "window",
        "plate"
    ],
    "wof:name":"All Star Auto Glass",
    "wof:placetype":"venue"
},
  "geometry": {"coordinates":[-83.079469,42.447147],"type":"Point"}
}