{
  "type": "Feature",
  "properties": {
    "iso:country":"US",
    "sg:address":"208 Courtland St",
    "sg:city":"Dowagiac",
    "sg:classifiers":[
        {
            "category":"Social Services",
            "subcategory":"Child Care",
            "type":"Services"
        }
    ],
    "sg:phone":"+1 269 782 2930",
    "sg:postcode":"49047",
    "sg:province":"MI",
    "sg:tags":[
        "day"
    ],
    "wof:name":"Catherine Lamb",
    "wof:placetype":"venue"
},
  "geometry": {"coordinates":[-86.10906,41.984702],"type":"Point"}
}