{
  "type": "Feature",
  "properties": {
    "iso:country":"US",
    "sg:address":"2461 Tandy Dr",
    "sg:city":"Flint",
    "sg:classifiers":[
        {
            "category":"Freight",
            "type":"Transportation"
        }
    ],
    "sg:phone":"+1 810 733 8615",
    "sg:postcode":"48532",
    "sg:province":"MI",
    "sg:tags":[
        "operator",
        "local",
        "trucking"
    ],
    "wof:name":"Cde Turner Light Hauling",
    "wof:placetype":"venue"
},
  "geometry": {"coordinates":[-83.756304,42.992224],"type":"Point"}
}