{
  "type": "Feature",
  "properties": {
    "iso:country":"US",
    "sg:address":"300 W Wardlow Rd",
    "sg:city":"Highland",
    "sg:classifiers":[
        {
            "category":"Building & Trades",
            "subcategory":"Construction",
            "type":"Services"
        }
    ],
    "sg:phone":"+1 248 889 0169",
    "sg:postcode":"48357",
    "sg:province":"MI",
    "sg:tags":[
        "concrete",
        "contractor"
    ],
    "wof:name":"Custom Poured Walls",
    "wof:placetype":"venue"
},
  "geometry": {"coordinates":[-83.620324,42.652492],"type":"Point"}
}