{
  "type": "Feature",
  "properties": {
    "iso:country":"US",
    "sg:address":"23010 E Main St",
    "sg:city":"Armada",
    "sg:classifiers":[
        {
            "category":"Restaurant",
            "type":"Food & Drink"
        }
    ],
    "sg:phone":"+1 586 784 8484",
    "sg:postcode":"48005",
    "sg:province":"MI",
    "wof:name":"Pizza X-Press",
    "wof:placetype":"venue"
},
  "geometry": {"coordinates":[-82.884281,42.844111],"type":"Point"}
}