{
  "type": "Feature",
  "properties": {
    "iso:country":"US",
    "sg:address":"8811 Chicago Rd",
    "sg:city":"Warren",
    "sg:classifiers":[
        {
            "category":"Social Services",
            "subcategory":"Adult Care",
            "type":"Services"
        }
    ],
    "sg:phone":"+1 586 979 8095",
    "sg:postcode":"48093",
    "sg:province":"MI",
    "sg:tags":[
        "foster"
    ],
    "wof:name":"Silver Knoll",
    "wof:placetype":"venue"
},
  "geometry": {"coordinates":[-83.017883,42.528424],"type":"Point"}
}