{
  "type": "Feature",
  "properties": {
    "iso:country":"US",
    "sg:address":"1500 E Saginaw St",
    "sg:city":"Lansing",
    "sg:classifiers":[
        {
            "category":"Social Services",
            "type":"Services"
        }
    ],
    "sg:phone":"+1 517 482 9529",
    "sg:postcode":"48906",
    "sg:province":"MI",
    "wof:name":"Project Rachel",
    "wof:placetype":"venue"
},
  "geometry": {"coordinates":[-84.52764999999999,42.740902],"type":"Point"}
}