{
  "type": "Feature",
  "properties": {
    "iso:country":"US",
    "sg:address":"771 Arbor St",
    "sg:city":"Ann Arbor",
    "sg:classifiers":[
        {
            "category":"Shopping",
            "subcategory":"Gifts & Souvenirs",
            "type":"Retail Goods"
        }
    ],
    "sg:phone":"+1 734 222 9093",
    "sg:postcode":"48104",
    "sg:province":"MI",
    "wof:name":"Detailsartcom",
    "wof:placetype":"venue"
},
  "geometry": {"coordinates":[-83.739822,42.27107],"type":"Point"}
}