{
  "type": "Feature",
  "properties": {
    "iso:country":"US",
    "sg:address":"2070 N Elba Rd",
    "sg:city":"Lapeer",
    "sg:classifiers":[
        {
            "category":"Wholesale",
            "subcategory":"Machinery & Supplies",
            "type":"Manufacturing & Wholesale Goods"
        }
    ],
    "sg:phone":"+1 810 245 7695",
    "sg:postcode":"48446",
    "sg:province":"MI",
    "sg:tags":[
        "gage"
    ],
    "wof:name":"Quality Gauge Co",
    "wof:placetype":"venue"
},
  "geometry": {"coordinates":[-83.442757,43.084041],"type":"Point"}
}