{
  "type": "Feature",
  "properties": {
    "iso:country":"US",
    "sg:address":"3060 W F Ave",
    "sg:city":"Kalamazoo",
    "sg:classifiers":[
        {
            "category":"Shopping",
            "subcategory":"Gifts & Souvenirs",
            "type":"Retail Goods"
        }
    ],
    "sg:phone":"+1 269 343 8099",
    "sg:postcode":"49009",
    "sg:province":"MI",
    "wof:name":"Blooming Baskets",
    "wof:placetype":"venue"
},
  "geometry": {"coordinates":[-85.615709,42.347497],"type":"Point"}
}