{
  "type": "Feature",
  "properties": {
    "iso:country":"US",
    "sg:address":"4250 Fulton St E",
    "sg:city":"Grand Rapids",
    "sg:classifiers":[
        {
            "category":"Professional",
            "subcategory":"Art Services",
            "type":"Services"
        }
    ],
    "sg:phone":"+1 616 977 9817",
    "sg:postcode":"49546",
    "sg:province":"MI",
    "sg:tags":[
        "commercial",
        "design"
    ],
    "wof:name":"Hu Xiao",
    "wof:placetype":"venue"
},
  "geometry": {"coordinates":[-85.564955,42.960925],"type":"Point"}
}