{
  "type": "Feature",
  "properties": {
    "iso:country":"US",
    "sg:address":"425 Biltmore St",
    "sg:city":"Inkster",
    "sg:classifiers":[
        {
            "category":"Personal",
            "subcategory":"Barber",
            "type":"Services"
        }
    ],
    "sg:phone":"+1 313 565 1830",
    "sg:postcode":"48141",
    "sg:province":"MI",
    "sg:tags":[
        "shop"
    ],
    "wof:name":"Rams Head",
    "wof:placetype":"venue"
},
  "geometry": {"coordinates":[-83.296539,42.307925],"type":"Point"}
}