{
  "type": "Feature",
  "properties": {
    "iso:country":"US",
    "sg:address":"33644 Farmview Ln",
    "sg:city":"Fraser",
    "sg:classifiers":[
        {
            "category":"Autos & Motor Vehicles",
            "subcategory":"Automobile Sales",
            "type":"Retail Goods"
        }
    ],
    "sg:phone":"+1 586 415 0033",
    "sg:postcode":"48026",
    "sg:province":"MI",
    "sg:tags":[
        "limo"
    ],
    "wof:name":"Anthony's Limousine Service Inc",
    "wof:placetype":"venue"
},
  "geometry": {"coordinates":[-82.964203,42.543999],"type":"Point"}
}