{
  "type": "Feature",
  "properties": {
    "iso:country":"US",
    "sg:address":"995 S Main St",
    "sg:city":"Plymouth",
    "sg:classifiers":[
        {
            "category":"Personal",
            "type":"Services"
        }
    ],
    "sg:phone":"+1 734 254 9160",
    "sg:postcode":"48170",
    "sg:province":"MI",
    "sg:tags":[
        "handyman"
    ],
    "wof:name":"Home Advantage Handyman Svc",
    "wof:placetype":"venue"
},
  "geometry": {"coordinates":[-83.46972100000001,42.364119],"type":"Point"}
}