{
  "type": "Feature",
  "properties": {
    "iso:country":"US",
    "sg:address":"1783 Oakgrove Ave",
    "sg:city":"Hazel Park",
    "sg:classifiers":[
        {
            "category":"Building & Trades",
            "subcategory":"Plumbing",
            "type":"Services"
        }
    ],
    "sg:phone":"+1 248 547 6490",
    "sg:postcode":"48030",
    "sg:province":"MI",
    "sg:tags":[
        "plumbing",
        "contractor"
    ],
    "wof:name":"Pipecon Plumbing & Piping",
    "wof:placetype":"venue"
},
  "geometry": {"coordinates":[-83.085949,42.470873],"type":"Point"}
}