{
  "type": "Feature",
  "properties": {
    "iso:country":"US",
    "sg:address":"4230 Beeline Rd",
    "sg:city":"Holland",
    "sg:classifiers":[
        {
            "category":"Farming",
            "subcategory":"Nursery",
            "type":"Manufacturing & Wholesale Goods"
        }
    ],
    "sg:phone":"+1 616 335 8127",
    "sg:postcode":"49423",
    "sg:province":"MI",
    "sg:tags":[
        "greenhouse"
    ],
    "wof:name":"Laketown Greenhouse",
    "wof:placetype":"venue"
},
  "geometry": {"coordinates":[-86.160605,42.725189],"type":"Point"}
}