{
  "type": "Feature",
  "properties": {
    "iso:country":"US",
    "sg:address":"2345 S Venoy Rd",
    "sg:city":"Westland",
    "sg:classifiers":[
        {
            "category":"Manufacturing",
            "subcategory":"Food",
            "type":"Manufacturing & Wholesale Goods"
        }
    ],
    "sg:phone":"+1 734 729 0466",
    "sg:postcode":"48186",
    "sg:province":"MI",
    "sg:tags":[
        "merchandise",
        "mfg"
    ],
    "wof:name":"Chocolate Drop Shop",
    "wof:placetype":"venue"
},
  "geometry": {"coordinates":[-83.363506,42.289475],"type":"Point"}
}