{
  "type": "Feature",
  "properties": {
    "iso:country":"US",
    "sg:address":"650 Riley St",
    "sg:city":"Holland",
    "sg:classifiers":[
        {
            "category":"Shopping",
            "subcategory":"Used Merchandise",
            "type":"Retail Goods"
        }
    ],
    "sg:phone":"+1 616 399 0686",
    "sg:postcode":"49424",
    "sg:province":"MI",
    "wof:name":"Kidz Junction",
    "wof:placetype":"venue"
},
  "geometry": {"coordinates":[-86.13600700000001,42.826717],"type":"Point"}
}