{
  "type": "Feature",
  "properties": {
    "iso:country":"US",
    "sg:address":"108 W Gaston Ave",
    "sg:city":"Harrietta",
    "sg:classifiers":[
        {
            "category":"Government",
            "subcategory":"Fire Station",
            "type":"Public Place"
        }
    ],
    "sg:phone":"+1 231 389 2631",
    "sg:postcode":"49638",
    "sg:province":"MI",
    "sg:tags":[
        "protection"
    ],
    "wof:name":"S&H Fire Hall",
    "wof:placetype":"venue"
},
  "geometry": {"coordinates":[-85.699241,44.309714],"type":"Point"}
}