{
  "type": "Feature",
  "properties": {
    "iso:country":"US",
    "sg:address":"8367 Dixie Hwy",
    "sg:city":"Ira",
    "sg:classifiers":[
        {
            "category":"Restaurant",
            "type":"Food & Drink"
        }
    ],
    "sg:phone":"+1 586 725 4644",
    "sg:postcode":"48023",
    "sg:province":"MI",
    "wof:name":"Jiggers Bar & Grill",
    "wof:placetype":"venue"
},
  "geometry": {"coordinates":[-82.64096600000001,42.676276],"type":"Point"}
}