{
  "type": "Feature",
  "properties": {
    "iso:country":"US",
    "sg:address":"4447 Eastern Ave SE",
    "sg:city":"Kentwood",
    "sg:classifiers":[
        {
            "category":"Education",
            "subcategory":"Special Training",
            "type":"Public Place"
        }
    ],
    "sg:phone":"+1 616 531 5033",
    "sg:postcode":"49508",
    "sg:province":"MI",
    "sg:tags":[
        "program",
        "student",
        "exchange"
    ],
    "wof:name":"Global World Intl",
    "wof:placetype":"venue"
},
  "geometry": {"coordinates":[-85.64565399999999,42.882849],"type":"Point"}
}