{
  "type": "Feature",
  "properties": {
    "iso:country":"US",
    "sg:address":"20700 Ecorse Rd",
    "sg:city":"Taylor",
    "sg:classifiers":[
        {
            "category":"Health Services",
            "subcategory":"Chiropractor",
            "type":"Services"
        }
    ],
    "sg:phone":"+1 313 294 6000",
    "sg:postcode":"48180",
    "sg:province":"MI",
    "wof:name":"Bader C J Chiropractic & Kinesiology",
    "wof:placetype":"venue"
},
  "geometry": {"coordinates":[-83.2397,42.256401],"type":"Point"}
}