{
  "type": "Feature",
  "properties": {
    "iso:country":"US",
    "sg:address":"3184 Alpine Rd",
    "sg:city":"Troy",
    "sg:classifiers":[
        {
            "category":"Professional",
            "subcategory":"Business Services",
            "type":"Services"
        }
    ],
    "sg:phone":"+1 248 649 4948",
    "sg:postcode":"48084",
    "sg:province":"MI",
    "wof:name":"Samurai Industries",
    "wof:placetype":"venue"
},
  "geometry": {"coordinates":[-83.175999,42.565321],"type":"Point"}
}