{
  "type": "Feature",
  "properties": {
    "iso:country":"US",
    "sg:address":"120 W Antoine St",
    "sg:city":"Iron Mountain",
    "sg:classifiers":[
        {
            "category":"Wholesale",
            "subcategory":"Machinery & Supplies",
            "type":"Manufacturing & Wholesale Goods"
        }
    ],
    "sg:phone":"+1 906 774 1558",
    "sg:postcode":"49801",
    "sg:province":"MI",
    "sg:tags":[
        "equipment",
        "printing"
    ],
    "wof:name":"Black Hole LTD",
    "wof:placetype":"venue"
},
  "geometry": {"coordinates":[-88.062471,45.836881],"type":"Point"}
}