{
  "type": "Feature",
  "properties": {
    "iso:country":"US",
    "sg:address":"4645 N M 37",
    "sg:city":"Mesick",
    "sg:classifiers":[
        {
            "category":"Shopping",
            "subcategory":"Gifts & Souvenirs",
            "type":"Retail Goods"
        }
    ],
    "sg:phone":"+1 231 885 2870",
    "sg:postcode":"49668",
    "sg:province":"MI",
    "sg:tags":[
        "shop"
    ],
    "wof:name":"T & L Gifts",
    "wof:placetype":"venue"
},
  "geometry": {"coordinates":[-85.69946899999999,44.404621],"type":"Point"}
}