{
  "type": "Feature",
  "properties": {
    "iso:country":"US",
    "sg:address":"1241 Rosewood St",
    "sg:city":"Ann Arbor",
    "sg:classifiers":[
        {
            "category":"Shopping",
            "subcategory":"Used Merchandise",
            "type":"Retail Goods"
        }
    ],
    "sg:phone":"+1 734 994 1206",
    "sg:postcode":"48104",
    "sg:province":"MI",
    "wof:name":"Woman In The Shoe Inc",
    "wof:placetype":"venue"
},
  "geometry": {"coordinates":[-83.73389299999999,42.255033],"type":"Point"}
}