{
  "type": "Feature",
  "properties": {
    "iso:country":"US",
    "sg:address":"1696 E Clear Lake Rd",
    "sg:city":"Buchanan",
    "sg:classifiers":[
        {
            "category":"Travel",
            "subcategory":"Campground",
            "type":"Entertainment"
        }
    ],
    "sg:phone":"+1 269 695 2191",
    "sg:postcode":"49107",
    "sg:province":"MI",
    "sg:tags":[
        "camp"
    ],
    "wof:name":"Life Action Retreat & Cnfrnc",
    "wof:placetype":"venue"
},
  "geometry": {"coordinates":[-86.414541,41.834323],"type":"Point"}
}