{
  "type": "Feature",
  "properties": {
    "iso:country":"US",
    "sg:address":"4540 Bridgeville Ct",
    "sg:city":"Hudsonville",
    "sg:classifiers":[
        {
            "category":"Wholesale",
            "subcategory":"Sporting Goods",
            "type":"Manufacturing & Wholesale Goods"
        }
    ],
    "sg:phone":"+1 616 662 1980",
    "sg:postcode":"49426",
    "sg:province":"MI",
    "wof:name":"Clear Source One LLC",
    "wof:placetype":"venue"
},
  "geometry": {"coordinates":[-85.89456,42.897712],"type":"Point"}
}