{
  "type": "Feature",
  "properties": {
    "iso:country":"US",
    "sg:address":"1 W Main St",
    "sg:city":"Milan",
    "sg:classifiers":[
        {
            "category":"Shopping",
            "subcategory":"Computers & Home Electronics",
            "type":"Retail Goods"
        }
    ],
    "sg:phone":"+1 734 439 7908",
    "sg:postcode":"48160",
    "sg:province":"MI",
    "sg:tags":[
        "repair"
    ],
    "wof:name":"Collins Center",
    "wof:placetype":"venue"
},
  "geometry": {"coordinates":[-83.685862,42.085943],"type":"Point"}
}