{
  "type": "Feature",
  "properties": {
    "iso:country":"US",
    "sg:address":"1771 Dix Hwy",
    "sg:city":"Lincoln Park",
    "sg:classifiers":[
        {
            "category":"Professional",
            "subcategory":"Management & Consulting",
            "type":"Services"
        }
    ],
    "sg:phone":"+1 313 381 6600",
    "sg:postcode":"48146",
    "sg:province":"MI",
    "sg:tags":[
        "consultant",
        "balancing",
        "air"
    ],
    "wof:name":"Barmatic Inspecting Company",
    "wof:placetype":"venue"
},
  "geometry": {"coordinates":[-83.190848,42.257996],"type":"Point"}
}