{
  "type": "Feature",
  "properties": {
    "iso:country":"US",
    "sg:address":"4200 Martin St",
    "sg:city":"Detroit",
    "sg:classifiers":[
        {
            "category":"Organizations",
            "subcategory":"Religious Organization",
            "type":"Services"
        }
    ],
    "sg:phone":"+1 313 897 8160",
    "sg:postcode":"48210",
    "sg:province":"MI",
    "wof:name":"Our Lady Queen Angels Church",
    "wof:placetype":"venue"
},
  "geometry": {"coordinates":[-83.12682,42.33018],"type":"Point"}
}