{
  "type": "Feature",
  "properties": {
    "iso:country":"US",
    "sg:address":"50 2nd St",
    "sg:city":"Pentwater",
    "sg:classifiers":[
        {
            "category":"Shopping",
            "subcategory":"Used Merchandise",
            "type":"Retail Goods"
        }
    ],
    "sg:phone":"+1 231 869 0222",
    "sg:postcode":"49449",
    "sg:province":"MI",
    "sg:tags":[
        "antique"
    ],
    "wof:name":"Carriage House Antique Mall",
    "wof:placetype":"venue"
},
  "geometry": {"coordinates":[-86.432545,43.780042],"type":"Point"}
}