{
  "type": "Feature",
  "properties": {
    "iso:country":"US",
    "sg:address":"1211 East Lincoln Avenue Ste 200",
    "sg:city":"Royal Oak",
    "sg:classifiers":[
        {
            "category":"Professional",
            "subcategory":"Art Services",
            "type":"Services"
        }
    ],
    "sg:phone":"+1 248 850 8589",
    "sg:postcode":"48067",
    "sg:province":"MI",
    "sg:tags":[
        "photographer"
    ],
    "sg:website":"www.jeffreymcintyre.com",
    "wof:name":"Jeffrey McIntyre",
    "wof:placetype":"venue"
},
  "geometry": {"coordinates":[-83.12984400000001,42.483322],"type":"Point"}
}