{
  "type": "Feature",
  "properties": {
    "iso:country":"US",
    "sg:address":"1970 N Evergreen Dr",
    "sg:city":"White Cloud",
    "sg:classifiers":[
        {
            "category":"Professional",
            "type":"Services"
        }
    ],
    "sg:phone":"+1 231 689 0010",
    "sg:postcode":"49349",
    "sg:province":"MI",
    "sg:tags":[
        "establishment"
    ],
    "wof:name":"Old Farm Girl",
    "wof:placetype":"venue"
},
  "geometry": {"coordinates":[-85.771281,43.583635],"type":"Point"}
}