{
  "type": "Feature",
  "properties": {
    "iso:country":"US",
    "sg:address":"1034 Bell Rd",
    "sg:city":"Niles",
    "sg:classifiers":[
        {
            "category":"Personal",
            "subcategory":"Tanning Parlor",
            "type":"Services"
        }
    ],
    "sg:phone":"+1 269 687 9866",
    "sg:postcode":"49120",
    "sg:province":"MI",
    "sg:tags":[
        "salon"
    ],
    "wof:name":"Tan Unique",
    "wof:placetype":"venue"
},
  "geometry": {"coordinates":[-86.251403,41.797886],"type":"Point"}
}