{
  "type": "Feature",
  "properties": {
    "iso:country":"US",
    "sg:address":"212 S Washington St",
    "sg:city":"Owosso",
    "sg:classifiers":[
        {
            "category":"Personal",
            "subcategory":"Barber",
            "type":"Services"
        }
    ],
    "sg:phone":"+1 989 723 2220",
    "sg:postcode":"48867",
    "sg:province":"MI",
    "sg:tags":[
        "shop"
    ],
    "wof:name":"Pete & Ivan's Barber Shop",
    "wof:placetype":"venue"
},
  "geometry": {"coordinates":[-84.170739,42.996443],"type":"Point"}
}