{
  "type": "Feature",
  "properties": {
    "iso:country":"US",
    "sg:address":"28860 7 Mile Rd",
    "sg:city":"Livonia",
    "sg:classifiers":[
        {
            "category":"Food & Beverages",
            "subcategory":"Groceries & Convenience Stores",
            "type":"Retail Goods"
        }
    ],
    "sg:phone":"+1 248 426 9798",
    "sg:postcode":"48152",
    "sg:province":"MI",
    "wof:name":"Da-Zhong Oriental Food Market Inc",
    "wof:placetype":"venue"
},
  "geometry": {"coordinates":[-83.330563,42.427393],"type":"Point"}
}