{
  "type": "Feature",
  "properties": {
    "iso:country":"US",
    "sg:address":"220 N Jackson St",
    "sg:city":"Sandusky",
    "sg:classifiers":[
        {
            "category":"Wholesale",
            "subcategory":"Farm Supplies",
            "type":"Manufacturing & Wholesale Goods"
        }
    ],
    "sg:phone":"+1 810 648 2299",
    "sg:postcode":"48471",
    "sg:province":"MI",
    "sg:tags":[
        "fertilizer"
    ],
    "wof:name":"Crop Production Svc Inc",
    "wof:placetype":"venue"
},
  "geometry": {"coordinates":[-82.825596,43.425089],"type":"Point"}
}