{
  "type": "Feature",
  "properties": {
    "iso:country":"US",
    "sg:address":"5306 M-72",
    "sg:city":"Harrisville",
    "sg:classifiers":[
        {
            "category":"Manufacturing",
            "subcategory":"Glass & Minerals",
            "type":"Manufacturing & Wholesale Goods"
        }
    ],
    "sg:phone":"+1 989 724 6446",
    "sg:postcode":"48740",
    "sg:province":"MI",
    "sg:tags":[
        "ready"
    ],
    "wof:name":"Northeast Redi-Mix Inc",
    "wof:placetype":"venue"
},
  "geometry": {"coordinates":[-83.30249999999999,44.656327],"type":"Point"}
}