{
  "type": "Feature",
  "properties": {
    "iso:country":"US",
    "sg:address":"21533 Ecorse Rd",
    "sg:city":"Taylor",
    "sg:classifiers":[
        {
            "category":"Cinema",
            "subcategory":"Movie Rental",
            "type":"Entertainment"
        }
    ],
    "sg:phone":"+1 313 292 0990",
    "sg:postcode":"48180",
    "sg:province":"MI",
    "sg:tags":[
        "game",
        "video"
    ],
    "sg:website":"www.familyvideo.com",
    "wof:name":"Family Video Store #444",
    "wof:placetype":"venue"
},
  "geometry": {"coordinates":[-83.246754,42.25599],"type":"Point"}
}