{
  "type": "Feature",
  "properties": {
    "iso:country":"US",
    "sg:address":"24822 John R Rd",
    "sg:city":"Hazel Park",
    "sg:classifiers":[
        {
            "category":"Food & Beverages",
            "subcategory":"Groceries & Convenience Stores",
            "type":"Retail Goods"
        }
    ],
    "sg:phone":"+1 248 399 5537",
    "sg:postcode":"48030",
    "sg:province":"MI",
    "wof:name":"Hazel Park Food & Fuel",
    "wof:placetype":"venue"
},
  "geometry": {"coordinates":[-83.10453800000001,42.475242],"type":"Point"}
}