{
  "type": "Feature",
  "properties": {
    "iso:country":"US",
    "sg:address":"502 Pine St",
    "sg:city":"Marquette",
    "sg:classifiers":[
        {
            "category":"Banks & Credit Unions",
            "subcategory":"Bank",
            "type":"Services"
        }
    ],
    "sg:phone":"+1 906 228 2539",
    "sg:postcode":"49855",
    "sg:province":"MI",
    "sg:tags":[
        "loan",
        "real estate"
    ],
    "wof:name":"Nolan Mortgage",
    "wof:placetype":"venue"
},
  "geometry": {"coordinates":[-87.38911899999999,46.547566],"type":"Point"}
}