{
  "type": "Feature",
  "properties": {
    "iso:country":"US",
    "sg:address":"32900 W 13 Mile Rd",
    "sg:city":"Farmington Hills",
    "sg:classifiers":[
        {
            "category":"Education",
            "subcategory":"Preschool",
            "type":"Public Place"
        },
        {
            "category":"Education",
            "subcategory":"School",
            "type":"Public Place"
        }
    ],
    "sg:phone":"+1 248 785 2005",
    "sg:postcode":"48334",
    "sg:province":"MI",
    "sg:tags":[
        "elementary"
    ],
    "wof:name":"Farmington Public Schools",
    "wof:placetype":"venue"
},
  "geometry": {"coordinates":[-83.375013,42.513428],"type":"Point"}
}