{
  "type": "Feature",
  "properties": {
    "iso:country":"US",
    "sg:address":"225 College Ave",
    "sg:city":"Holland",
    "sg:classifiers":[
        {
            "category":"Professional",
            "subcategory":"Business Services",
            "type":"Services"
        }
    ],
    "sg:phone":"+1 616 395 7200",
    "sg:postcode":"49423",
    "sg:province":"MI",
    "sg:tags":[
        "conference",
        "center"
    ],
    "sg:website":"www.haworthinn.com",
    "wof:name":"Haworth Inn & Conference Ctr",
    "wof:placetype":"venue"
},
  "geometry": {"coordinates":[-86.10432,42.789085],"type":"Point"}
}