{
  "type": "Feature",
  "properties": {
    "iso:country":"US",
    "sg:address":"8906 1st St",
    "sg:city":"Baroda",
    "sg:classifiers":[
        {
            "category":"Restaurant",
            "type":"Food & Drink"
        }
    ],
    "sg:phone":"+1 269 422 1141",
    "sg:postcode":"49101",
    "sg:province":"MI",
    "sg:website":"www.billstap.com",
    "wof:name":"Bill's Tap & Restaurant",
    "wof:placetype":"venue"
},
  "geometry": {"coordinates":[-86.485737,41.957234],"type":"Point"}
}