{
  "type": "Feature",
  "properties": {
    "iso:country":"US",
    "sg:address":"28456 Aberdeen St",
    "sg:city":"Southfield",
    "sg:classifiers":[
        {
            "category":"Professional",
            "subcategory":"Accounting & Tax Preparation",
            "type":"Services"
        }
    ],
    "sg:phone":"+1 248 557 8652",
    "sg:postcode":"48076",
    "sg:province":"MI",
    "wof:name":"Seymour Rabotnick & Associates",
    "wof:placetype":"venue"
},
  "geometry": {"coordinates":[-83.209574,42.500421],"type":"Point"}
}