{
  "type": "Feature",
  "properties": {
    "iso:country":"US",
    "sg:address":"4174 Cedar Ave",
    "sg:city":"West Bloomfield",
    "sg:classifiers":[
        {
            "category":"Professional",
            "subcategory":"Business Services",
            "type":"Services"
        }
    ],
    "sg:phone":"+1 248 366 3124",
    "sg:postcode":"48323",
    "sg:province":"MI",
    "sg:tags":[
        "embroidery"
    ],
    "wof:name":"Embrodiery Artist",
    "wof:placetype":"venue"
},
  "geometry": {"coordinates":[-83.422348,42.575714],"type":"Point"}
}