{
  "type": "Feature",
  "properties": {
    "iso:country":"US",
    "sg:address":"121 Avery St",
    "sg:city":"Clinton Township",
    "sg:classifiers":[
        {
            "category":"Building & Trades",
            "subcategory":"Plumbing",
            "type":"Services"
        }
    ],
    "sg:phone":"+1 586 465 6666",
    "sg:postcode":"48036",
    "sg:province":"MI",
    "wof:name":"Youngs Plumbing",
    "wof:placetype":"venue"
},
  "geometry": {"coordinates":[-82.865196,42.585899],"type":"Point"}
}