{
  "type": "Feature",
  "properties": {
    "iso:country":"US",
    "sg:address":"35600 E Michigan Ave",
    "sg:city":"Wayne",
    "sg:classifiers":[
        {
            "category":"Autos & Motor Vehicles",
            "subcategory":"Fuel & Gas Station",
            "type":"Retail Goods"
        }
    ],
    "sg:phone":"+1 734 467 2210",
    "sg:postcode":"48184",
    "sg:province":"MI",
    "wof:name":"Wayne Bp",
    "wof:placetype":"venue"
},
  "geometry": {"coordinates":[-83.38968,42.280037],"type":"Point"}
}