{
  "type": "Feature",
  "properties": {
    "iso:country":"US",
    "sg:address":"4470 S Forthill Dr",
    "sg:city":"Suttons Bay",
    "sg:classifiers":[
        {
            "category":"Social Services",
            "subcategory":"Adult Care",
            "type":"Services"
        }
    ],
    "sg:phone":"+1 231 271 6038",
    "sg:postcode":"49682",
    "sg:province":"MI",
    "sg:tags":[
        "home"
    ],
    "wof:name":"Suttons Bay Adult Foster",
    "wof:placetype":"venue"
},
  "geometry": {"coordinates":[-85.63178000000001,44.917299],"type":"Point"}
}