{
  "type": "Feature",
  "properties": {
    "iso:country":"US",
    "sg:address":"10344 Gratiot Ave",
    "sg:city":"Columbus",
    "sg:classifiers":[
        {
            "category":"Education",
            "subcategory":"Dance Studio",
            "type":"Public Place"
        }
    ],
    "sg:phone":"+1 586 727 4165",
    "sg:postcode":"48063",
    "sg:province":"MI",
    "wof:name":"Dance Connection",
    "wof:placetype":"venue"
},
  "geometry": {"coordinates":[-82.723071,42.812057],"type":"Point"}
}