{
  "type": "Feature",
  "properties": {
    "iso:country":"US",
    "sg:address":"3780 Maybee Rd",
    "sg:city":"Lake Orion",
    "sg:classifiers":[
        {
            "category":"Retail",
            "subcategory":"Animal Services",
            "type":"Services"
        }
    ],
    "sg:phone":"+1 248 391 2126",
    "sg:postcode":"48359",
    "sg:province":"MI",
    "wof:name":"Allen Salo",
    "wof:placetype":"venue"
},
  "geometry": {"coordinates":[-83.316348,42.728815],"type":"Point"}
}