{
  "type": "Feature",
  "properties": {
    "iso:country":"US",
    "sg:address":"715 E Van Buren Rd",
    "sg:city":"Alma",
    "sg:classifiers":[
        {
            "category":"Professional",
            "subcategory":"Management & Consulting",
            "type":"Services"
        }
    ],
    "sg:phone":"+1 989 463 5630",
    "sg:postcode":"48801",
    "sg:province":"MI",
    "sg:tags":[
        "business"
    ],
    "wof:name":"Serenity Farms",
    "wof:placetype":"venue"
},
  "geometry": {"coordinates":[-84.59313899999999,43.364192],"type":"Point"}
}