{
  "type": "Feature",
  "properties": {
    "iso:country":"US",
    "sg:address":"1336 Audubon Rd",
    "sg:city":"Grosse Pointe",
    "sg:classifiers":[
        {
            "category":"Professional",
            "subcategory":"Management & Consulting",
            "type":"Services"
        }
    ],
    "sg:phone":"+1 313 886 2437",
    "sg:postcode":"48230",
    "sg:province":"MI",
    "sg:tags":[
        "retail",
        "direct",
        "sales"
    ],
    "wof:name":"J Campagna",
    "wof:placetype":"venue"
},
  "geometry": {"coordinates":[-82.929039,42.389635],"type":"Point"}
}