{
  "type": "Feature",
  "properties": {
    "iso:country":"US",
    "sg:address":"4864 Hillcrest Ave",
    "sg:city":"Okemos",
    "sg:classifiers":[
        {
            "category":"Building & Trades",
            "subcategory":"Plumbing",
            "type":"Services"
        }
    ],
    "sg:phone":"+1 517 349 1753",
    "sg:postcode":"48864",
    "sg:province":"MI",
    "sg:tags":[
        "mechanical",
        "contractor"
    ],
    "wof:name":"Nova",
    "wof:placetype":"venue"
},
  "geometry": {"coordinates":[-84.431174,42.721535],"type":"Point"}
}