{
  "type": "Feature",
  "properties": {
    "iso:country":"US",
    "sg:address":"1045 142nd Ave",
    "sg:city":"Wayland",
    "sg:classifiers":[
        {
            "category":"Retail",
            "subcategory":"Animal Services",
            "type":"Services"
        }
    ],
    "sg:phone":"+1 616 877 0254",
    "sg:postcode":"49348",
    "sg:province":"MI",
    "wof:name":"Pet Expressions",
    "wof:placetype":"venue"
},
  "geometry": {"coordinates":[-85.646404,42.72485],"type":"Point"}
}