{
  "type": "Feature",
  "properties": {
    "iso:country":"US",
    "sg:address":"4092 Bayview Cir",
    "sg:city":"Newport",
    "sg:classifiers":[
        {
            "category":"Real Estate",
            "subcategory":"Developer",
            "type":"Services"
        }
    ],
    "sg:phone":"+1 734 289 1540",
    "sg:postcode":"48166",
    "sg:province":"MI",
    "wof:name":"Davis and Bodenmiller LLC",
    "wof:placetype":"venue"
},
  "geometry": {"coordinates":[-83.298717,41.94629],"type":"Point"}
}