{
  "type": "Feature",
  "properties": {
    "iso:country":"US",
    "sg:address":"51735 Fairchild Rd",
    "sg:city":"New Baltimore",
    "sg:classifiers":[
        {
            "category":"Organizations",
            "subcategory":"Religious Organization",
            "type":"Services"
        }
    ],
    "sg:phone":"+1 586 949 9099",
    "sg:postcode":"48051",
    "sg:province":"MI",
    "wof:name":"Church of Jesus Christ",
    "wof:placetype":"venue"
},
  "geometry": {"coordinates":[-82.85318599999999,42.67858],"type":"Point"}
}