{
  "type": "Feature",
  "properties": {
    "iso:country":"US",
    "sg:address":"505 Beechwood St",
    "sg:city":"River Rouge",
    "sg:classifiers":[
        {
            "category":"Organizations",
            "subcategory":"Religious Organization",
            "type":"Services"
        }
    ],
    "sg:phone":"+1 313 386 2288",
    "sg:postcode":"48218",
    "sg:province":"MI",
    "sg:tags":[
        "episcopal",
        "african",
        "methodist",
        "church"
    ],
    "wof:name":"Saint John AME Church",
    "wof:placetype":"venue"
},
  "geometry": {"coordinates":[-83.147971,42.267141],"type":"Point"}
}