{
  "type": "Feature",
  "properties": {
    "iso:country":"US",
    "sg:address":"45166 Lakeview Dr",
    "sg:city":"Macomb",
    "sg:classifiers":[
        {
            "category":"Professional",
            "type":"Services"
        }
    ],
    "sg:phone":"+1 586 412 6613",
    "sg:postcode":"48044",
    "sg:province":"MI",
    "wof:name":"Karam Distribution Services",
    "wof:placetype":"venue"
},
  "geometry": {"coordinates":[-82.952686,42.628926],"type":"Point"}
}