{
  "type": "Feature",
  "properties": {
    "iso:country":"US",
    "sg:address":"46671 Summertime Dr",
    "sg:city":"Chesterfield",
    "sg:classifiers":[
        {
            "category":"Travel",
            "subcategory":"Travel Agent",
            "type":"Entertainment"
        }
    ],
    "sg:phone":"+1 586 598 9770",
    "sg:postcode":"48047",
    "sg:province":"MI",
    "sg:tags":[
        "cruise"
    ],
    "wof:name":"Global Travel",
    "wof:placetype":"venue"
},
  "geometry": {"coordinates":[-82.814161,42.642643],"type":"Point"}
}