{
  "type": "Feature",
  "properties": {
    "iso:country":"US",
    "sg:address":"2601 Birchwood Dr",
    "sg:city":"Howell",
    "sg:classifiers":[
        {
            "category":"Shopping",
            "type":"Retail Goods"
        }
    ],
    "sg:phone":"+1 517 545 0272",
    "sg:postcode":"48855",
    "sg:province":"MI",
    "sg:tags":[
        "wedding",
        "supply"
    ],
    "wof:name":"Sensible Wedding Solutions",
    "wof:placetype":"venue"
},
  "geometry": {"coordinates":[-83.900257,42.627219],"type":"Point"}
}