{
  "type": "Feature",
  "properties": {
    "iso:country":"US",
    "sg:address":"791 W 26th St",
    "sg:city":"Holland",
    "sg:classifiers":[
        {
            "category":"Building & Trades",
            "subcategory":"Landscaping Services",
            "type":"Services"
        }
    ],
    "sg:phone":"+1 616 335 8879",
    "sg:postcode":"49423",
    "sg:province":"MI",
    "wof:name":"Southshore Maintenance Service",
    "wof:placetype":"venue"
},
  "geometry": {"coordinates":[-86.140815,42.773848],"type":"Point"}
}