{
  "type": "Feature",
  "properties": {
    "iso:country":"US",
    "sg:address":"6777 W. Maple Road",
    "sg:city":"West Bloomfield",
    "sg:classifiers":[
        {
            "category":"Health Services",
            "subcategory":"Clinic",
            "type":"Services"
        }
    ],
    "sg:phone":"+1 248 661 4100",
    "sg:postcode":"48322",
    "sg:province":"MI",
    "sg:tags":[
        "medical"
    ],
    "wof:name":"Henry Ford West Bloomfield Hospital",
    "wof:placetype":"venue"
},
  "geometry": {"coordinates":[-83.40706900000001,42.538653],"type":"Point"}
}