{
  "type": "Feature",
  "properties": {
    "iso:country":"US",
    "sg:address":"325 S Fairview Rd",
    "sg:city":"West Branch",
    "sg:classifiers":[
        {
            "category":"Building & Trades",
            "subcategory":"Construction",
            "type":"Services"
        }
    ],
    "sg:phone":"+1 989 345 4520",
    "sg:postcode":"48661",
    "sg:province":"MI",
    "sg:tags":[
        "paving",
        "contractor"
    ],
    "wof:name":"Pyramid Paving & Contracting",
    "wof:placetype":"venue"
},
  "geometry": {"coordinates":[-84.22583299999999,44.278183],"type":"Point"}
}