{
  "type": "Feature",
  "properties": {
    "iso:country":"US",
    "sg:address":"23746 Brest",
    "sg:city":"Taylor",
    "sg:classifiers":[
        {
            "category":"Building & Trades",
            "subcategory":"Electrical",
            "type":"Services"
        }
    ],
    "sg:phone":"+1 734 287 7368",
    "sg:postcode":"48180",
    "sg:province":"MI",
    "sg:tags":[
        "electrician"
    ],
    "wof:name":"All Current Electrical Services",
    "wof:placetype":"venue"
},
  "geometry": {"coordinates":[-83.266098,42.219501],"type":"Point"}
}