{
  "type": "Feature",
  "properties": {
    "iso:country":"US",
    "sg:address":"542 State Rd",
    "sg:city":"Vassar",
    "sg:classifiers":[
        {
            "category":"Restaurant",
            "type":"Food & Drink"
        }
    ],
    "sg:phone":"+1 989 823 3577",
    "sg:postcode":"48768",
    "sg:province":"MI",
    "wof:name":"Dragon Palace",
    "wof:placetype":"venue"
},
  "geometry": {"coordinates":[-83.580229,43.362094],"type":"Point"}
}