{
  "type": "Feature",
  "properties": {
    "iso:country":"US",
    "sg:address":"3234 Associates Dr",
    "sg:city":"Burton",
    "sg:classifiers":[
        {
            "category":"Autos & Motor Vehicles",
            "subcategory":"Automobile Sales",
            "type":"Retail Goods"
        }
    ],
    "sg:phone":"+1 810 742 6444",
    "sg:postcode":"48529",
    "sg:province":"MI",
    "sg:tags":[
        "car",
        "dealer"
    ],
    "wof:name":"Larson Auto Group",
    "wof:placetype":"venue"
},
  "geometry": {"coordinates":[-83.66782000000001,42.978992],"type":"Point"}
}