{
  "type": "Feature",
  "properties": {
    "iso:country":"US",
    "sg:address":"3001 W Big Beaver Rd Ste 116",
    "sg:city":"Troy",
    "sg:classifiers":[
        {
            "category":"Real Estate",
            "subcategory":"Real Estate Services",
            "type":"Services"
        }
    ],
    "sg:phone":"+1 248 649 1996",
    "sg:postcode":"48084",
    "sg:province":"MI",
    "sg:tags":[
        "management",
        "property"
    ],
    "wof:name":"Nemer Management Co Inc",
    "wof:placetype":"venue"
},
  "geometry": {"coordinates":[-83.17590300000001,42.557301],"type":"Point"}
}