{
  "type": "Feature",
  "properties": {
    "iso:country":"US",
    "sg:address":"29780 Milford Rd",
    "sg:city":"New Hudson",
    "sg:classifiers":[
        {
            "category":"Building & Trades",
            "subcategory":"Construction",
            "type":"Services"
        }
    ],
    "sg:phone":"+1 248 486 3053",
    "sg:postcode":"48165",
    "sg:province":"MI",
    "sg:tags":[
        "hanging",
        "contractor"
    ],
    "wof:name":"Neighborhood Painting & Job Sv",
    "wof:placetype":"venue"
},
  "geometry": {"coordinates":[-83.615427,42.507704],"type":"Point"}
}