{
  "type": "Feature",
  "properties": {
    "iso:country":"US",
    "sg:address":"1295 Milan Oakville Rd",
    "sg:city":"Milan",
    "sg:classifiers":[
        {
            "category":"Building & Trades",
            "subcategory":"Construction",
            "type":"Services"
        }
    ],
    "sg:phone":"+1 734 439 5626",
    "sg:postcode":"48160",
    "sg:province":"MI",
    "sg:tags":[
        "hanging",
        "contractor"
    ],
    "wof:name":"Phillips Painting & Renovation",
    "wof:placetype":"venue"
},
  "geometry": {"coordinates":[-83.659554,42.084626],"type":"Point"}
}