{
  "type": "Feature",
  "properties": {
    "iso:country":"US",
    "sg:address":"113 Lydia St",
    "sg:city":"Jackson",
    "sg:classifiers":[
        {
            "category":"Health Services",
            "subcategory":"Hospital",
            "type":"Services"
        }
    ],
    "sg:phone":"+1 517 782 1722",
    "sg:postcode":"49201",
    "sg:province":"MI",
    "sg:tags":[
        "clinic",
        "specialty",
        "outpatient"
    ],
    "wof:name":"Reflection Otptient Counseling",
    "wof:placetype":"venue"
},
  "geometry": {"coordinates":[-84.41716599999999,42.248313],"type":"Point"}
}