{
  "type": "Feature",
  "properties": {
    "iso:country":"US",
    "sg:address":"5644 Arborview Ct",
    "sg:city":"West Bloomfield",
    "sg:classifiers":[
        {
            "category":"Wholesale",
            "subcategory":"Scrap",
            "type":"Manufacturing & Wholesale Goods"
        }
    ],
    "sg:phone":"+1 248 592 3000",
    "sg:postcode":"48322",
    "sg:province":"MI",
    "sg:tags":[
        "metal",
        "iron"
    ],
    "wof:name":"Weintraub Alloys Co",
    "wof:placetype":"venue"
},
  "geometry": {"coordinates":[-83.405089,42.551921],"type":"Point"}
}