{
  "type": "Feature",
  "properties": {
    "iso:country":"US",
    "sg:address":"2106 Lapeer Ave",
    "sg:city":"Saginaw",
    "sg:classifiers":[
        {
            "category":"Professional",
            "type":"Services"
        }
    ],
    "sg:phone":"+1 989 714 4340",
    "sg:postcode":"48601",
    "sg:province":"MI",
    "wof:name":"Just Write Services",
    "wof:placetype":"venue"
},
  "geometry": {"coordinates":[-83.915482,43.431747],"type":"Point"}
}