{
  "type": "Feature",
  "properties": {
    "iso:country":"US",
    "sg:address":"10886 Minx Rd",
    "sg:city":"Erie",
    "sg:classifiers":[
        {
            "category":"Wholesale",
            "subcategory":"Groceries",
            "type":"Manufacturing & Wholesale Goods"
        }
    ],
    "sg:phone":"+1 734 856 3894",
    "sg:postcode":"48133",
    "sg:province":"MI",
    "sg:tags":[
        "confectionery"
    ],
    "wof:name":"Interstate Snack Company",
    "wof:placetype":"venue"
},
  "geometry": {"coordinates":[-83.531131,41.81981],"type":"Point"}
}