{
  "type": "Feature",
  "properties": {
    "iso:country":"US",
    "sg:address":"57910 Apple Ln",
    "sg:city":"New Hudson",
    "sg:classifiers":[
        {
            "category":"Professional",
            "subcategory":"Computer Services",
            "type":"Services"
        }
    ],
    "sg:phone":"+1 248 437 3481",
    "sg:postcode":"48165",
    "sg:province":"MI",
    "sg:tags":[
        "datum"
    ],
    "wof:name":"Graphic Knight",
    "wof:placetype":"venue"
},
  "geometry": {"coordinates":[-83.621225,42.484895],"type":"Point"}
}