{
  "type": "Feature",
  "properties": {
    "iso:country":"US",
    "sg:address":"30420 Groesbeck Hwy",
    "sg:city":"Roseville",
    "sg:classifiers":[
        {
            "category":"Health Services",
            "subcategory":"Health Practitioner",
            "type":"Services"
        }
    ],
    "sg:phone":"+1 586 775 8400",
    "sg:postcode":"48066",
    "sg:province":"MI",
    "sg:tags":[
        "occupational",
        "safety"
    ],
    "wof:name":"Groesbeck Occupational Med",
    "wof:placetype":"venue"
},
  "geometry": {"coordinates":[-82.950817,42.517282],"type":"Point"}
}