{
  "type": "Feature",
  "properties": {
    "iso:country":"US",
    "sg:address":"1430 Old US Hwy 31",
    "sg:city":"Niles",
    "sg:classifiers":[
        {
            "category":"Building & Trades",
            "subcategory":"Construction",
            "type":"Services"
        }
    ],
    "sg:phone":"+1 269 689 8900",
    "sg:postcode":"49120",
    "sg:province":"MI",
    "sg:tags":[
        "concrete",
        "contractor"
    ],
    "wof:name":"Szucs Concrete & Asphalt Rcycl",
    "wof:placetype":"venue"
},
  "geometry": {"coordinates":[-86.280798,41.870435],"type":"Point"}
}