{
  "type": "Feature",
  "properties": {
    "iso:country":"US",
    "sg:address":"500 S 8th St",
    "sg:city":"Escanaba",
    "sg:classifiers":[
        {
            "category":"Real Estate",
            "subcategory":"Real Estate Agent",
            "type":"Services"
        }
    ],
    "sg:phone":"+1 906 786 5681",
    "sg:postcode":"49829",
    "sg:province":"MI",
    "wof:name":"Precise Home Inspections",
    "wof:placetype":"venue"
},
  "geometry": {"coordinates":[-87.058196,45.740908],"type":"Point"}
}