{
  "type": "Feature",
  "properties": {
    "iso:country":"US",
    "sg:address":"1785 Creston St",
    "sg:city":"Muskegon",
    "sg:classifiers":[
        {
            "category":"Restaurant",
            "type":"Food & Drink"
        }
    ],
    "sg:phone":"+1 231 777 7567",
    "sg:postcode":"49442",
    "sg:province":"MI",
    "wof:name":"Hot 'n Now Hamburgers",
    "wof:placetype":"venue"
},
  "geometry": {"coordinates":[-86.209506,43.219502],"type":"Point"}
}