{
  "type": "Feature",
  "properties": {
    "iso:country":"US",
    "sg:address":"4926 Chilson Rd",
    "sg:city":"Howell",
    "sg:classifiers":[
        {
            "category":"Restaurant",
            "type":"Food & Drink"
        }
    ],
    "sg:phone":"+1 810 494 1800",
    "sg:postcode":"48843",
    "sg:province":"MI",
    "wof:name":"Fat Guy Pizza Pie",
    "wof:placetype":"venue"
},
  "geometry": {"coordinates":[-83.862773,42.527808],"type":"Point"}
}