{
  "type": "Feature",
  "properties": {
    "iso:country":"US",
    "sg:address":"68365 S Main St",
    "sg:city":"Richmond",
    "sg:classifiers":[
        {
            "category":"Professional",
            "subcategory":"Lawyer & Legal Services",
            "type":"Services"
        }
    ],
    "sg:phone":"+1 586 727 2227",
    "sg:postcode":"48062",
    "sg:province":"MI",
    "wof:name":"McGovern & Bucci PC",
    "wof:placetype":"venue"
},
  "geometry": {"coordinates":[-82.74989100000001,42.802844],"type":"Point"}
}