{
  "type": "Feature",
  "properties": {
    "iso:country":"US",
    "sg:address":"283 Taras Dr",
    "sg:city":"Highland",
    "sg:classifiers":[
        {
            "category":"Building & Trades",
            "subcategory":"Construction",
            "type":"Services"
        }
    ],
    "sg:phone":"+1 248 736 1695",
    "sg:postcode":"48356",
    "sg:province":"MI",
    "sg:tags":[
        "house"
    ],
    "wof:name":"American Made Construction LLC",
    "wof:placetype":"venue"
},
  "geometry": {"coordinates":[-83.6151,42.654754],"type":"Point"}
}