{
  "type": "Feature",
  "properties": {
    "iso:country":"US",
    "sg:address":"25 Arthur St",
    "sg:city":"Manistee",
    "sg:classifiers":[
        {
            "category":"Utilities",
            "subcategory":"Electric",
            "type":"Services"
        },
        {
            "category":"Utilities",
            "type":"Services"
        }
    ],
    "sg:phone":"+1 231 723 0251",
    "sg:postcode":"49660",
    "sg:province":"MI",
    "wof:name":"Consumers Energy Company",
    "wof:placetype":"venue"
},
  "geometry": {"coordinates":[-86.319242,44.255131],"type":"Point"}
}