{
  "type": "Feature",
  "properties": {
    "iso:country":"US",
    "sg:address":"5228 S Westnedge Ave",
    "sg:city":"Portage",
    "sg:classifiers":[
        {
            "category":"Restaurant",
            "type":"Food & Drink"
        }
    ],
    "sg:menulink":"http://www.allmenus.com/mi/portage/47221-kazoopys-eatery/menu/",
    "sg:phone":"+1 269 488 3232",
    "sg:postcode":"49002",
    "sg:province":"MI",
    "sg:tags":[
        "wrap",
        "american",
        "sandwich"
    ],
    "wof:name":"Kazoopy's Eatery",
    "wof:placetype":"venue"
},
  "geometry": {"coordinates":[-85.58957100000001,42.241785],"type":"Point"}
}