{
  "type": "Feature",
  "properties": {
    "iso:country":"US",
    "sg:address":"5757 W Hickory Hollow St",
    "sg:city":"Wayne",
    "sg:classifiers":[
        {
            "category":"Real Estate",
            "subcategory":"Real Estate Operator",
            "type":"Services"
        }
    ],
    "sg:phone":"+1 734 729 7262",
    "sg:postcode":"48184",
    "sg:province":"MI",
    "sg:tags":[
        "housing",
        "apartment",
        "complex",
        "cooperative"
    ],
    "wof:name":"Hickory Hollow Cooperative",
    "wof:placetype":"venue"
},
  "geometry": {"coordinates":[-83.356201,42.2682],"type":"Point"}
}