{
  "type": "Feature",
  "properties": {
    "iso:country":"US",
    "sg:address":"189 Gerald St",
    "sg:city":"Detroit",
    "sg:classifiers":[
        {
            "category":"Shopping",
            "type":"Retail Goods"
        }
    ],
    "sg:phone":"+1 313 865 4351",
    "sg:postcode":"48203",
    "sg:province":"MI",
    "sg:tags":[
        "merchandise"
    ],
    "wof:name":"Publishing By Candle Light",
    "wof:placetype":"venue"
},
  "geometry": {"coordinates":[-83.08945,42.408259],"type":"Point"}
}