{
  "type": "Feature",
  "properties": {
    "iso:country":"US",
    "sg:address":"235 S Bradley Rd",
    "sg:city":"Charlotte",
    "sg:classifiers":[
        {
            "category":"Professional",
            "subcategory":"Business Services",
            "type":"Services"
        }
    ],
    "sg:phone":"+1 517 543 4045",
    "sg:postcode":"48813",
    "sg:province":"MI",
    "wof:name":"Butters Auction Service",
    "wof:placetype":"venue"
},
  "geometry": {"coordinates":[-84.95508599999999,42.564418],"type":"Point"}
}