{
  "type": "Feature",
  "properties": {
    "iso:country":"US",
    "sg:address":"912 S Washington St",
    "sg:city":"Owosso",
    "sg:classifiers":[
        {
            "category":"Social Services",
            "subcategory":"Child Care",
            "type":"Services"
        }
    ],
    "sg:phone":"+1 989 723 5251",
    "sg:postcode":"48867",
    "sg:province":"MI",
    "sg:tags":[
        "day"
    ],
    "wof:name":"Baker College Chld Dev Ctr",
    "wof:placetype":"venue"
},
  "geometry": {"coordinates":[-84.17088699999999,42.988814],"type":"Point"}
}