{
  "type": "Feature",
  "properties": {
    "iso:country":"US",
    "sg:address":"24605 John R Rd",
    "sg:city":"Hazel Park",
    "sg:classifiers":[
        {
            "category":"Building & Trades",
            "subcategory":"Plumbing",
            "type":"Services"
        }
    ],
    "sg:phone":"+1 248 547 6490",
    "sg:postcode":"48030",
    "sg:province":"MI",
    "wof:name":"Pipecon Plumbing & Piping",
    "wof:placetype":"venue"
},
  "geometry": {"coordinates":[-83.104499,42.473248],"type":"Point"}
}