{
  "type": "Feature",
  "properties": {
    "iso:country":"US",
    "sg:address":"13211 W State Rd",
    "sg:city":"Grand Ledge",
    "sg:classifiers":[
        {
            "category":"Building & Trades",
            "subcategory":"Construction",
            "type":"Services"
        }
    ],
    "sg:phone":"+1 517 627 7152",
    "sg:postcode":"48837",
    "sg:province":"MI",
    "sg:tags":[
        "house"
    ],
    "wof:name":"J L Kebler Construction",
    "wof:placetype":"venue"
},
  "geometry": {"coordinates":[-84.794606,42.784867],"type":"Point"}
}