{
  "type": "Feature",
  "properties": {
    "iso:country":"US",
    "sg:address":"1115 Kettering St",
    "sg:city":"Burton",
    "sg:classifiers":[
        {
            "category":"Manufacturing",
            "subcategory":"Tools & Machinery",
            "type":"Manufacturing & Wholesale Goods"
        }
    ],
    "sg:phone":"+1 810 744 0059",
    "sg:postcode":"48509",
    "sg:province":"MI",
    "sg:tags":[
        "industrial",
        "mfg"
    ],
    "wof:name":"Vac Form Tooling",
    "wof:placetype":"venue"
},
  "geometry": {"coordinates":[-83.58830500000001,43.01634],"type":"Point"}
}