{
  "type": "Feature",
  "properties": {
    "iso:country":"US",
    "sg:address":"1621 Oak Ter",
    "sg:city":"Saint Joseph",
    "sg:classifiers":[
        {
            "category":"Professional",
            "subcategory":"Management & Consulting",
            "type":"Services"
        }
    ],
    "sg:phone":"+1 269 429 7875",
    "sg:postcode":"49085",
    "sg:province":"MI",
    "wof:name":"Nmac",
    "wof:placetype":"venue"
},
  "geometry": {"coordinates":[-86.49152100000001,42.030332],"type":"Point"}
}