{
  "type": "Feature",
  "properties": {
    "iso:country":"US",
    "sg:address":"9326 Torrey Rd",
    "sg:city":"Grand Blanc",
    "sg:classifiers":[
        {
            "category":"Building & Trades",
            "subcategory":"Construction",
            "type":"Services"
        }
    ],
    "sg:phone":"+1 810 655 2015",
    "sg:postcode":"48439",
    "sg:province":"MI",
    "sg:tags":[
        "layer",
        "carpet"
    ],
    "wof:name":"BEA Carpet Svc",
    "wof:placetype":"venue"
},
  "geometry": {"coordinates":[-83.72963900000001,42.888802],"type":"Point"}
}