{
  "type": "Feature",
  "properties": {
    "iso:country":"US",
    "sg:address":"1003 W Main St",
    "sg:city":"Fremont",
    "sg:classifiers":[
        {
            "category":"Wholesale",
            "subcategory":"Non-durable Goods",
            "type":"Manufacturing & Wholesale Goods"
        }
    ],
    "sg:phone":"+1 231 924 4540",
    "sg:postcode":"49412",
    "sg:province":"MI",
    "sg:tags":[
        "advertising"
    ],
    "wof:name":"T S Silk Screen",
    "wof:placetype":"venue"
},
  "geometry": {"coordinates":[-85.962761,43.467265],"type":"Point"}
}