{
  "type": "Feature",
  "properties": {
    "iso:country":"US",
    "sg:address":"5166 Grand River Ave",
    "sg:city":"Detroit",
    "sg:classifiers":[
        {
            "category":"Autos & Motor Vehicles",
            "subcategory":"Auto Supplies",
            "type":"Retail Goods"
        }
    ],
    "sg:phone":"+1 313 898 2332",
    "sg:postcode":"48208",
    "sg:province":"MI",
    "sg:tags":[
        "automobile",
        "rebuilt",
        "part",
        "supplies-used"
    ],
    "wof:name":"John's Auto Salvage",
    "wof:placetype":"venue"
},
  "geometry": {"coordinates":[-83.092061,42.349816],"type":"Point"}
}