{
  "type": "Feature",
  "properties": {
    "iso:country":"US",
    "sg:address":"6858 Belmont Ave NE",
    "sg:city":"Belmont",
    "sg:classifiers":[
        {
            "category":"Building & Trades",
            "subcategory":"Cleaning & Sanitation",
            "type":"Services"
        }
    ],
    "sg:phone":"+1 616 866 4056",
    "sg:postcode":"49306",
    "sg:province":"MI",
    "sg:tags":[
        "maintenance"
    ],
    "wof:name":"Vaness Building Maintainence",
    "wof:placetype":"venue"
},
  "geometry": {"coordinates":[-85.606995,43.087367],"type":"Point"}
}