{
  "type": "Feature",
  "properties": {
    "iso:country":"US",
    "sg:address":"7162 Sheridan Rd",
    "sg:city":"Flushing",
    "sg:classifiers":[
        {
            "category":"Manufacturing",
            "subcategory":"Tools & Machinery",
            "type":"Manufacturing & Wholesale Goods"
        }
    ],
    "sg:phone":"+1 810 638 5388",
    "sg:postcode":"48433",
    "sg:province":"MI",
    "sg:tags":[
        "die",
        "maker"
    ],
    "sg:website":"www.ultradexusa.com",
    "wof:name":"Ultra-Dex Tooling Systems",
    "wof:placetype":"venue"
},
  "geometry": {"coordinates":[-83.928945,43.106108],"type":"Point"}
}