{
  "type": "Feature",
  "properties": {
    "iso:country":"US",
    "sg:address":"222 el Centro Blvd SE",
    "sg:city":"Grand Rapids",
    "sg:classifiers":[
        {
            "category":"Professional",
            "subcategory":"Art Services",
            "type":"Services"
        }
    ],
    "sg:phone":"+1 616 957 0900",
    "sg:postcode":"49506",
    "sg:province":"MI",
    "sg:tags":[
        "commercial",
        "design"
    ],
    "wof:name":"Ad Design Inc",
    "wof:placetype":"venue"
},
  "geometry": {"coordinates":[-85.604739,42.960445],"type":"Point"}
}