{
  "type": "Feature",
  "properties": {
    "iso:country":"US",
    "sg:address":"5135 E Mount Morris Rd",
    "sg:city":"Mount Morris",
    "sg:classifiers":[
        {
            "category":"Social Services",
            "subcategory":"Adult Care",
            "type":"Services"
        }
    ],
    "sg:phone":"+1 810 640 2302",
    "sg:postcode":"48458",
    "sg:province":"MI",
    "sg:tags":[
        "foster"
    ],
    "wof:name":"McShens Adult Foster Care Home",
    "wof:placetype":"venue"
},
  "geometry": {"coordinates":[-83.617766,43.120537],"type":"Point"}
}