{
  "type": "Feature",
  "properties": {
    "iso:country":"US",
    "sg:address":"875 York St",
    "sg:city":"Plymouth",
    "sg:classifiers":[
        {
            "category":"Manufacturing",
            "subcategory":"Glass & Minerals",
            "type":"Manufacturing & Wholesale Goods"
        }
    ],
    "sg:phone":"+1 734 459 6419",
    "sg:postcode":"48170",
    "sg:province":"MI",
    "sg:tags":[
        "mfg"
    ],
    "wof:name":"York Street Glass",
    "wof:placetype":"venue"
},
  "geometry": {"coordinates":[-83.45843600000001,42.379612],"type":"Point"}
}