{
  "type": "Feature",
  "properties": {
    "iso:country":"US",
    "sg:address":"21041 John R Rd",
    "sg:city":"Hazel Park",
    "sg:classifiers":[
        {
            "category":"Professional",
            "type":"Services"
        }
    ],
    "sg:phone":"+1 248 541 6230",
    "sg:postcode":"48030",
    "sg:province":"MI",
    "sg:tags":[
        "establishment"
    ],
    "wof:name":"Granito Inc",
    "wof:placetype":"venue"
},
  "geometry": {"coordinates":[-83.103146,42.449798],"type":"Point"}
}