{
  "type": "Feature",
  "properties": {
    "iso:country":"US",
    "sg:address":"229 S Benzie Blvd",
    "sg:city":"Beulah",
    "sg:classifiers":[
        {
            "category":"Sports & Exercise",
            "subcategory":"Bowling",
            "type":"Entertainment"
        }
    ],
    "sg:phone":"+1 231 882 4121",
    "sg:postcode":"49617",
    "sg:province":"MI",
    "sg:tags":[
        "center"
    ],
    "wof:name":"Beulah Bowling Ctr",
    "wof:placetype":"venue"
},
  "geometry": {"coordinates":[-86.09550900000001,44.628674],"type":"Point"}
}