{
  "type": "Feature",
  "properties": {
    "iso:country":"US",
    "sg:address":"6326 N Seymour Rd",
    "sg:city":"Flushing",
    "sg:classifiers":[
        {
            "category":"Real Estate",
            "subcategory":"Real Estate Operator",
            "type":"Services"
        }
    ],
    "sg:phone":"+1 810 659 1947",
    "sg:postcode":"48433",
    "sg:province":"MI",
    "sg:tags":[
        "building",
        "apartment"
    ],
    "wof:name":"Matousek Ken",
    "wof:placetype":"venue"
},
  "geometry": {"coordinates":[-83.866775,43.099116],"type":"Point"}
}