{
  "type": "Feature",
  "properties": {
    "iso:country":"US",
    "sg:address":"515 Plymouth Dr",
    "sg:city":"Davison",
    "sg:classifiers":[
        {
            "category":"Retail",
            "subcategory":"Repair Shop",
            "type":"Services"
        }
    ],
    "sg:phone":"+1 810 652 0051",
    "sg:postcode":"48423",
    "sg:province":"MI",
    "sg:tags":[
        "reupholstery",
        "upholsterer",
        "furniture"
    ],
    "wof:name":"The Upholstery Shop",
    "wof:placetype":"venue"
},
  "geometry": {"coordinates":[-83.524002,43.021198],"type":"Point"}
}