{
  "type": "Feature",
  "properties": {
    "iso:country":"US",
    "sg:address":"3940 Fenkell St",
    "sg:city":"Detroit",
    "sg:classifiers":[
        {
            "category":"Real Estate",
            "subcategory":"Real Estate Operator",
            "type":"Services"
        }
    ],
    "sg:phone":"+1 313 864 8727",
    "sg:postcode":"48238",
    "sg:province":"MI",
    "sg:tags":[
        "building",
        "nonresidential"
    ],
    "wof:name":"G&C Assoc",
    "wof:placetype":"venue"
},
  "geometry": {"coordinates":[-83.13761700000001,42.402802],"type":"Point"}
}