{
  "type": "Feature",
  "properties": {
    "iso:country":"US",
    "sg:address":"11505 E Mount Morris Rd",
    "sg:city":"Davison",
    "sg:classifiers":[
        {
            "category":"Professional",
            "subcategory":"Accounting & Tax Preparation",
            "type":"Services"
        }
    ],
    "sg:phone":"+1 810 631 6457",
    "sg:postcode":"48423",
    "sg:province":"MI",
    "sg:tags":[
        "return"
    ],
    "wof:name":"A W Income Tax",
    "wof:placetype":"venue"
},
  "geometry": {"coordinates":[-83.48941000000001,43.127355],"type":"Point"}
}