{
  "type": "Feature",
  "properties": {
    "iso:country":"US",
    "sg:address":"8059 Hill Rd",
    "sg:city":"Swartz Creek",
    "sg:classifiers":[
        {
            "category":"Building & Trades",
            "subcategory":"Construction",
            "type":"Services"
        }
    ],
    "sg:phone":"+1 810 635 4212",
    "sg:postcode":"48473",
    "sg:province":"MI",
    "sg:tags":[
        "hanging",
        "contractor"
    ],
    "wof:name":"Aztec Painting & Power Wash",
    "wof:placetype":"venue"
},
  "geometry": {"coordinates":[-83.844387,42.941766],"type":"Point"}
}