{
  "type": "Feature",
  "properties": {
    "iso:country":"US",
    "sg:address":"1094 Nautical Dr",
    "sg:city":"Okemos",
    "sg:classifiers":[
        {
            "category":"Insurance",
            "subcategory":"Insurance Agent",
            "type":"Services"
        }
    ],
    "sg:phone":"+1 517 347 7343",
    "sg:postcode":"48864",
    "sg:province":"MI",
    "sg:tags":[
        "agency"
    ],
    "wof:name":"William & Associates Inc",
    "wof:placetype":"venue"
},
  "geometry": {"coordinates":[-84.38676700000001,42.69919],"type":"Point"}
}