{
  "type": "Feature",
  "properties": {
    "iso:country":"US",
    "sg:address":"2454 Golfbury Dr SW",
    "sg:city":"Wyoming",
    "sg:classifiers":[
        {
            "category":"Arts & Performance",
            "subcategory":"Theater",
            "type":"Entertainment"
        }
    ],
    "sg:phone":"+1 616 534 8176",
    "sg:postcode":"49519",
    "sg:province":"MI",
    "sg:tags":[
        "magician"
    ],
    "wof:name":"Menu Magic Foods Inc",
    "wof:placetype":"venue"
},
  "geometry": {"coordinates":[-85.725283,42.871627],"type":"Point"}
}