{
  "type": "Feature",
  "properties": {
    "iso:country":"US",
    "sg:address":"201 W Central Ave",
    "sg:city":"Mackinaw City",
    "sg:classifiers":[
        {
            "category":"Ice Cream",
            "type":"Food & Drink"
        }
    ],
    "sg:menulink":"http://www.allmenus.com/mi/wawatam/168591-dairy-queen/menu/",
    "sg:phone":"+1 231 436 7841",
    "sg:postcode":"49701",
    "sg:province":"MI",
    "sg:tags":[
        "burger",
        "american"
    ],
    "wof:name":"Dairy Queen",
    "wof:placetype":"venue"
},
  "geometry": {"coordinates":[-84.73457999999999,45.781576],"type":"Point"}
}