{
  "type": "Feature",
  "properties": {
    "iso:country":"US",
    "sg:address":"325 Watts Rd",
    "sg:city":"Jackson",
    "sg:classifiers":[
        {
            "category":"Manufacturing",
            "subcategory":"Tools & Machinery",
            "type":"Manufacturing & Wholesale Goods"
        }
    ],
    "sg:phone":"+1 517 764 0470",
    "sg:postcode":"49203",
    "sg:province":"MI",
    "sg:tags":[
        "machine",
        "shop"
    ],
    "wof:name":"Yo Manufacturing Co",
    "wof:placetype":"venue"
},
  "geometry": {"coordinates":[-84.355526,42.250575],"type":"Point"}
}