{
  "type": "Feature",
  "properties": {
    "iso:country":"US",
    "sg:address":"2355 M 99 S",
    "sg:city":"Homer",
    "sg:classifiers":[
        {
            "category":"Freight",
            "type":"Transportation"
        }
    ],
    "sg:phone":"+1 517 568 3573",
    "sg:postcode":"49245",
    "sg:province":"MI",
    "sg:tags":[
        "operator",
        "local",
        "trucking"
    ],
    "wof:name":"Ralph Odell Jr Trucking",
    "wof:placetype":"venue"
},
  "geometry": {"coordinates":[-84.80828700000001,42.115815],"type":"Point"}
}