{
  "type": "Feature",
  "properties": {
    "iso:country":"US",
    "sg:address":"1887 Holton Rd",
    "sg:city":"Muskegon",
    "sg:classifiers":[
        {
            "category":"Cinema",
            "subcategory":"Movie Rental",
            "type":"Entertainment"
        }
    ],
    "sg:phone":"+1 231 719 1952",
    "sg:postcode":"49445",
    "sg:province":"MI",
    "sg:tags":[
        "video",
        "tape"
    ],
    "wof:name":"Grand Video",
    "wof:placetype":"venue"
},
  "geometry": {"coordinates":[-86.221484,43.285993],"type":"Point"}
}