{
  "type": "Feature",
  "properties": {
    "iso:country":"US",
    "sg:address":"115 E Exchange St",
    "sg:city":"Gobles",
    "sg:classifiers":[
        {
            "category":"Building & Trades",
            "subcategory":"Construction",
            "type":"Services"
        }
    ],
    "sg:phone":"+1 269 628 6500",
    "sg:postcode":"49055",
    "sg:province":"MI",
    "sg:tags":[
        "home",
        "improvement"
    ],
    "wof:name":"Earwood Construction",
    "wof:placetype":"venue"
},
  "geometry": {"coordinates":[-85.878835,42.359559],"type":"Point"}
}