{
  "type": "Feature",
  "properties": {
    "iso:country":"US",
    "sg:address":"9901 State Hwy 46",
    "sg:city":"Vestaburg",
    "sg:classifiers":[
        {
            "category":"Building & Trades",
            "subcategory":"Construction",
            "type":"Services"
        }
    ],
    "sg:phone":"+1 989 268 5237",
    "sg:postcode":"48891",
    "sg:province":"MI",
    "sg:tags":[
        "water",
        "well",
        "drilling"
    ],
    "wof:name":"Trayer Water Wells",
    "wof:placetype":"venue"
},
  "geometry": {"coordinates":[-84.89303700000001,43.408331],"type":"Point"}
}