{
  "type": "Feature",
  "properties": {
    "iso:country":"US",
    "sg:address":"2020 N Meridian Rd",
    "sg:city":"Hudson",
    "sg:classifiers":[
        {
            "category":"Wholesale",
            "subcategory":"Construction Materials",
            "type":"Manufacturing & Wholesale Goods"
        }
    ],
    "sg:phone":"+1 517 547 5801",
    "sg:postcode":"49247",
    "sg:province":"MI",
    "sg:tags":[
        "pallet",
        "skid"
    ],
    "wof:name":"Snyder's Pallets",
    "wof:placetype":"venue"
},
  "geometry": {"coordinates":[-84.367035,41.932181],"type":"Point"}
}