{
  "type": "Feature",
  "properties": {
    "iso:country":"US",
    "sg:address":"812 Columbus Ave",
    "sg:city":"Bay City",
    "sg:classifiers":[
        {
            "category":"Shopping",
            "type":"Retail Goods"
        }
    ],
    "sg:phone":"+1 989 895 5363",
    "sg:postcode":"48708",
    "sg:province":"MI",
    "sg:tags":[
        "merchandise"
    ],
    "wof:name":"Columbus Coin & Jewelry",
    "wof:placetype":"venue"
},
  "geometry": {"coordinates":[-83.882634,43.589343],"type":"Point"}
}