{
  "type": "Feature",
  "properties": {
    "iso:country":"US",
    "sg:address":"5603 Byron Center Ave SW",
    "sg:city":"Wyoming",
    "sg:classifiers":[
        {
            "category":"Organizations",
            "subcategory":"Religious Organization",
            "type":"Services"
        }
    ],
    "sg:phone":"+1 616 532 0131",
    "sg:postcode":"49519",
    "sg:province":"MI",
    "sg:tags":[
        "church"
    ],
    "wof:name":"South Wyoming United Methodist",
    "wof:placetype":"venue"
},
  "geometry": {"coordinates":[-85.723118,42.858291],"type":"Point"}
}