{
  "type": "Feature",
  "properties": {
    "iso:country":"US",
    "sg:address":"555 S 5th Ave",
    "sg:city":"Alpena",
    "sg:classifiers":[
        {
            "category":"Organizations",
            "subcategory":"Religious Organization",
            "type":"Services"
        }
    ],
    "sg:phone":"+1 989 354 8487",
    "sg:postcode":"49707",
    "sg:province":"MI",
    "wof:name":"Cornerstone Ministries",
    "wof:placetype":"venue"
},
  "geometry": {"coordinates":[-83.441598,45.062311],"type":"Point"}
}