{
  "type": "Feature",
  "properties": {
    "iso:country":"US",
    "sg:address":"4676 32nd Ave",
    "sg:city":"Hudsonville",
    "sg:classifiers":[
        {
            "category":"Restaurant",
            "type":"Food & Drink"
        }
    ],
    "sg:phone":"+1 616 662 2244",
    "sg:postcode":"49426",
    "sg:province":"MI",
    "sg:tags":[
        "pizza"
    ],
    "wof:name":"Maurizio's Pizza",
    "wof:placetype":"venue"
},
  "geometry": {"coordinates":[-85.860935,42.855786],"type":"Point"}
}