{
  "type": "Feature",
  "properties": {
    "iso:country":"US",
    "sg:address":"1343 E Duck Lake Rd",
    "sg:city":"Grawn",
    "sg:classifiers":[
        {
            "category":"Building & Trades",
            "subcategory":"Construction",
            "type":"Services"
        }
    ],
    "sg:phone":"+1 231 883 3849",
    "sg:postcode":"49637",
    "sg:province":"MI",
    "sg:tags":[
        "downspouts",
        "gutter"
    ],
    "wof:name":"Rainwater Control Systems",
    "wof:placetype":"venue"
},
  "geometry": {"coordinates":[-85.73197,44.658369],"type":"Point"}
}