{
  "type": "Feature",
  "properties": {
    "iso:country":"US",
    "sg:address":"1902 Water St",
    "sg:city":"Port Huron",
    "sg:classifiers":[
        {
            "category":"Shopping",
            "subcategory":"Florist",
            "type":"Retail Goods"
        }
    ],
    "sg:phone":"+1 810 982 9902",
    "sg:postcode":"48060",
    "sg:province":"MI",
    "wof:name":"Flower Niche",
    "wof:placetype":"venue"
},
  "geometry": {"coordinates":[-82.446423,42.98726],"type":"Point"}
}