{
  "type": "Feature",
  "properties": {
    "iso:country":"US",
    "sg:address":"23900 Ryan Rd",
    "sg:city":"Warren",
    "sg:classifiers":[
        {
            "category":"Manufacturing",
            "subcategory":"Tools & Machinery",
            "type":"Manufacturing & Wholesale Goods"
        }
    ],
    "sg:phone":"+1 586 757 2713",
    "sg:postcode":"48091",
    "sg:province":"MI",
    "sg:tags":[
        "machine",
        "shop"
    ],
    "wof:name":"J C Mfg Co",
    "wof:placetype":"venue"
},
  "geometry": {"coordinates":[-83.06483900000001,42.469355],"type":"Point"}
}