{
  "type": "Feature",
  "properties": {
    "iso:country":"US",
    "sg:address":"618 N Riverview Dr",
    "sg:city":"Parchment",
    "sg:classifiers":[
        {
            "category":"Food & Beverages",
            "subcategory":"Groceries & Convenience Stores",
            "type":"Retail Goods"
        }
    ],
    "sg:phone":"+1 269 342 5998",
    "sg:postcode":"49004",
    "sg:province":"MI",
    "sg:tags":[
        "grocer"
    ],
    "wof:name":"Harding's Friendly Market",
    "wof:placetype":"venue"
},
  "geometry": {"coordinates":[-85.56539100000001,42.332433],"type":"Point"}
}