{
  "type": "Feature",
  "properties": {
    "iso:country":"US",
    "sg:address":"681 Wintersun Pl",
    "sg:city":"Holland",
    "sg:classifiers":[
        {
            "category":"Organizations",
            "subcategory":"Membership Organization",
            "type":"Services"
        }
    ],
    "sg:phone":"+1 616 355 6698",
    "sg:postcode":"49424",
    "sg:province":"MI",
    "sg:tags":[
        "noncommercial",
        "research"
    ],
    "wof:name":"Alliance For Cultural and Ethn",
    "wof:placetype":"venue"
},
  "geometry": {"coordinates":[-86.137618,42.796223],"type":"Point"}
}