{
  "type": "Feature",
  "properties": {
    "iso:country":"US",
    "sg:address":"20252 Ecorse Rd",
    "sg:city":"Taylor",
    "sg:classifiers":[
        {
            "category":"Banks & Credit Unions",
            "subcategory":"Bank",
            "type":"Services"
        }
    ],
    "sg:phone":"+1 313 382 6533",
    "sg:postcode":"48180",
    "sg:province":"MI",
    "sg:tags":[
        "federal",
        "state"
    ],
    "sg:website":"www.unitedchurchescu.org",
    "wof:name":"United Churches Credit Union",
    "wof:placetype":"venue"
},
  "geometry": {"coordinates":[-83.234596,42.256401],"type":"Point"}
}