{
  "type": "Feature",
  "properties": {
    "iso:country":"US",
    "sg:address":"32669 Warren Rd",
    "sg:city":"Garden City",
    "sg:classifiers":[
        {
            "category":"Personal",
            "subcategory":"Beauty Salon",
            "type":"Services"
        }
    ],
    "sg:phone":"+1 734 422 6420",
    "sg:postcode":"48135",
    "sg:province":"MI",
    "sg:tags":[
        "shop"
    ],
    "wof:name":"Style Masters Salon",
    "wof:placetype":"venue"
},
  "geometry": {"coordinates":[-83.361474,42.339348],"type":"Point"}
}