{
  "type": "Feature",
  "properties": {
    "iso:country":"US",
    "sg:address":"1452 N Monroe St",
    "sg:city":"Monroe",
    "sg:classifiers":[
        {
            "category":"Insurance",
            "subcategory":"Insurance Agent",
            "type":"Services"
        }
    ],
    "sg:phone":"+1 734 457 0800",
    "sg:postcode":"48162",
    "sg:province":"MI",
    "wof:name":"Allstate",
    "wof:placetype":"venue"
},
  "geometry": {"coordinates":[-83.389611,41.935811],"type":"Point"}
}