{
  "type": "Feature",
  "properties": {
    "iso:country":"US",
    "sg:address":"8293 Officepark Dr",
    "sg:city":"Grand Blanc",
    "sg:classifiers":[
        {
            "category":"Shopping",
            "subcategory":"Computers & Home Electronics",
            "type":"Retail Goods"
        }
    ],
    "sg:phone":"+1 810 694 7477",
    "sg:postcode":"48439",
    "sg:province":"MI",
    "sg:tags":[
        "consultant",
        "system",
        "software"
    ],
    "wof:name":"Bit By Bit Computing",
    "wof:placetype":"venue"
},
  "geometry": {"coordinates":[-83.604342,42.907482],"type":"Point"}
}