{
  "type": "Feature",
  "properties": {
    "iso:country":"US",
    "sg:address":"27950 Drake Rd",
    "sg:city":"Farmington Hills",
    "sg:classifiers":[
        {
            "category":"Social Services",
            "subcategory":"Adult Care",
            "type":"Services"
        }
    ],
    "sg:phone":"+1 248 489 9362",
    "sg:postcode":"48331",
    "sg:province":"MI",
    "sg:tags":[
        "home",
        "residential"
    ],
    "sg:website":"www.assisted.com",
    "wof:name":"Alterra Clare Bridge",
    "wof:placetype":"venue"
},
  "geometry": {"coordinates":[-83.39779299999999,42.50021],"type":"Point"}
}