{
  "type": "Feature",
  "properties": {
    "iso:country":"US",
    "sg:address":"7550 Myers Lake Ave NE",
    "sg:city":"Rockford",
    "sg:classifiers":[
        {
            "category":"Food & Beverages",
            "subcategory":"Specialty",
            "type":"Retail Goods"
        }
    ],
    "sg:phone":"+1 616 874 7279",
    "sg:postcode":"49341",
    "sg:province":"MI",
    "wof:name":"Shaklee Independent Distrs",
    "wof:placetype":"venue"
},
  "geometry": {"coordinates":[-85.500275,43.099361],"type":"Point"}
}