{
  "type": "Feature",
  "properties": {
    "iso:country":"US",
    "sg:address":"49495 Gratiot Ave",
    "sg:city":"Chesterfield",
    "sg:classifiers":[
        {
            "category":"Manufacturing",
            "subcategory":"Metals",
            "type":"Manufacturing & Wholesale Goods"
        }
    ],
    "sg:phone":"+1 586 949 6000",
    "sg:postcode":"48051",
    "sg:province":"MI",
    "sg:tags":[
        "stamping"
    ],
    "sg:website":"www.schallergroup.com",
    "wof:name":"Schaller Corp",
    "wof:placetype":"venue"
},
  "geometry": {"coordinates":[-82.843431,42.661796],"type":"Point"}
}