{
  "type": "Feature",
  "properties": {
    "iso:country":"US",
    "sg:address":"22946 Katzman St",
    "sg:city":"Clinton Township",
    "sg:classifiers":[
        {
            "category":"Building & Trades",
            "subcategory":"Construction",
            "type":"Services"
        }
    ],
    "sg:phone":"+1 586 868 6600",
    "sg:postcode":"48035",
    "sg:province":"MI",
    "sg:tags":[
        "contractor"
    ],
    "wof:name":"Sps Construction Llc",
    "wof:placetype":"venue"
},
  "geometry": {"coordinates":[-82.884598,42.567501],"type":"Point"}
}