{
  "type": "Feature",
  "properties": {
    "iso:country":"US",
    "sg:address":"7688 Van Geisen Rd",
    "sg:city":"Reese",
    "sg:classifiers":[
        {
            "category":"Farming",
            "subcategory":"Farm",
            "type":"Manufacturing & Wholesale Goods"
        }
    ],
    "sg:phone":"+1 989 868 3188",
    "sg:postcode":"48757",
    "sg:province":"MI",
    "sg:tags":[
        "crop",
        "general"
    ],
    "wof:name":"Dennis Ackerman",
    "wof:placetype":"venue"
},
  "geometry": {"coordinates":[-83.61075099999999,43.479753],"type":"Point"}
}