{
  "type": "Feature",
  "properties": {
    "iso:country":"US",
    "sg:address":"501 N 3rd St",
    "sg:city":"Grand Haven",
    "sg:classifiers":[
        {
            "category":"Recreation",
            "subcategory":"Marina",
            "type":"Entertainment"
        }
    ],
    "sg:phone":"+1 616 842 5370",
    "sg:postcode":"49417",
    "sg:province":"MI",
    "wof:name":"Wharf Marina Inc",
    "wof:placetype":"venue"
},
  "geometry": {"coordinates":[-86.22752800000001,43.066885],"type":"Point"}
}