{
  "type": "Feature",
  "properties": {
    "iso:country":"US",
    "sg:address":"11200 Lesure Dr",
    "sg:city":"Sterling Heights",
    "sg:classifiers":[
        {
            "category":"Professional",
            "subcategory":"Computer Services",
            "type":"Services"
        }
    ],
    "sg:phone":"+1 586 264 2661",
    "sg:postcode":"48312",
    "sg:province":"MI",
    "sg:tags":[
        "consulting"
    ],
    "wof:name":"Mega Byte Engineering Services",
    "wof:placetype":"venue"
},
  "geometry": {"coordinates":[-83.016441,42.57798],"type":"Point"}
}