{
  "type": "Feature",
  "properties": {
    "iso:country":"US",
    "sg:address":"661 S 220th Ave",
    "sg:city":"Reed City",
    "sg:classifiers":[
        {
            "category":"Professional",
            "type":"Services"
        }
    ],
    "sg:phone":"+1 231 832 4005",
    "sg:postcode":"49677",
    "sg:province":"MI",
    "wof:name":"Richard Heilman",
    "wof:placetype":"venue"
},
  "geometry": {"coordinates":[-85.523118,43.822519],"type":"Point"}
}