{
  "type": "Feature",
  "properties": {
    "iso:country":"US",
    "sg:address":"718 Daniel St",
    "sg:city":"Ann Arbor",
    "sg:classifiers":[
        {
            "category":"Social Services",
            "type":"Services"
        }
    ],
    "sg:phone":"+1 734 662 3509",
    "sg:postcode":"48103",
    "sg:province":"MI",
    "wof:name":"L Sanders",
    "wof:placetype":"venue"
},
  "geometry": {"coordinates":[-83.750851,42.288796],"type":"Point"}
}