{
  "type": "Feature",
  "properties": {
    "iso:country":"US",
    "sg:address":"4111 County Farm Rd",
    "sg:city":"Jackson",
    "sg:classifiers":[
        {
            "category":"Professional",
            "subcategory":"Employment Agencies",
            "type":"Services"
        }
    ],
    "sg:phone":"+1 517 796 1319",
    "sg:postcode":"49201",
    "sg:province":"MI",
    "sg:tags":[
        "help",
        "contractor"
    ],
    "wof:name":"Kelly Services Inc",
    "wof:placetype":"venue"
},
  "geometry": {"coordinates":[-84.47453400000001,42.276473],"type":"Point"}
}