{
  "type": "Feature",
  "properties": {
    "iso:country":"US",
    "sg:address":"5321 Ferris Rd",
    "sg:city":"Eaton Rapids",
    "sg:classifiers":[
        {
            "category":"Real Estate",
            "subcategory":"Real Estate Agent",
            "type":"Services"
        }
    ],
    "sg:phone":"+1 517 663 3380",
    "sg:postcode":"48827",
    "sg:province":"MI",
    "wof:name":"Cheney- Wells LLC",
    "wof:placetype":"venue"
},
  "geometry": {"coordinates":[-84.55913700000001,42.494728],"type":"Point"}
}