{
  "type": "Feature",
  "properties": {
    "iso:country":"US",
    "sg:address":"5033 Parman Rd",
    "sg:city":"Stockbridge",
    "sg:classifiers":[
        {
            "category":"Farming",
            "subcategory":"Farm",
            "type":"Manufacturing & Wholesale Goods"
        }
    ],
    "sg:phone":"+1 517 565 3103",
    "sg:postcode":"49285",
    "sg:province":"MI",
    "wof:name":"Greenamyer Farms",
    "wof:placetype":"venue"
},
  "geometry": {"coordinates":[-84.25827200000001,42.436744],"type":"Point"}
}