{
  "type": "Feature",
  "properties": {
    "iso:country":"US",
    "sg:address":"17 Metroview Ct",
    "sg:city":"Ann Arbor",
    "sg:classifiers":[
        {
            "category":"Social Services",
            "subcategory":"Child Care",
            "type":"Services"
        }
    ],
    "sg:phone":"+1 734 973 6620",
    "sg:postcode":"48108",
    "sg:province":"MI",
    "sg:tags":[
        "day"
    ],
    "wof:name":"Marys Lil Lamb Day Care Home",
    "wof:placetype":"venue"
},
  "geometry": {"coordinates":[-83.715735,42.23676],"type":"Point"}
}