{
  "type": "Feature",
  "properties": {
    "iso:country":"US",
    "sg:address":"50250 Dennis Ct",
    "sg:city":"Wixom",
    "sg:classifiers":[
        {
            "category":"Autos & Motor Vehicles",
            "subcategory":"Auto Supplies",
            "type":"Retail Goods"
        }
    ],
    "sg:phone":"+1 248 669 6946",
    "sg:postcode":"48393",
    "sg:province":"MI",
    "sg:tags":[
        "equipment",
        "racing",
        "car",
        "automobile"
    ],
    "wof:name":"Motor City Performance Racing",
    "wof:placetype":"venue"
},
  "geometry": {"coordinates":[-83.54677599999999,42.524682],"type":"Point"}
}