{
  "type": "Feature",
  "properties": {
    "iso:country":"US",
    "sg:address":"12230 Wormer",
    "sg:city":"Redford",
    "sg:classifiers":[
        {
            "category":"Retail",
            "subcategory":"Repair Shop",
            "type":"Services"
        }
    ],
    "sg:phone":"+1 313 533 2457",
    "sg:postcode":"48239",
    "sg:province":"MI",
    "sg:tags":[
        "glass",
        "mfg"
    ],
    "wof:name":"Preform Resources",
    "wof:placetype":"venue"
},
  "geometry": {"coordinates":[-83.278058,42.377005],"type":"Point"}
}