{
  "type": "Feature",
  "properties": {
    "iso:country":"US",
    "sg:address":"8430 Maurice Ct",
    "sg:city":"Newport",
    "sg:classifiers":[
        {
            "category":"Building & Trades",
            "subcategory":"Construction",
            "type":"Services"
        }
    ],
    "sg:phone":"+1 734 457 5027",
    "sg:postcode":"48166",
    "sg:province":"MI",
    "sg:tags":[
        "contractor"
    ],
    "wof:name":"Ceramic Tile By Joseph Bert",
    "wof:placetype":"venue"
},
  "geometry": {"coordinates":[-83.35184599999999,42.004428],"type":"Point"}
}