{
  "type": "Feature",
  "properties": {
    "iso:country":"US",
    "sg:address":"1090 N 10th St",
    "sg:city":"Kalamazoo",
    "sg:classifiers":[
        {
            "category":"Professional",
            "subcategory":"Lawyer & Legal Services",
            "type":"Services"
        }
    ],
    "sg:phone":"+1 269 372 9075",
    "sg:postcode":"49009",
    "sg:province":"MI",
    "sg:tags":[
        "attorney"
    ],
    "wof:name":"Samuel K Silverman Law Ofc",
    "wof:placetype":"venue"
},
  "geometry": {"coordinates":[-85.667514,42.296928],"type":"Point"}
}