{
  "type": "Feature",
  "properties": {
    "iso:country":"US",
    "sg:address":"1006 Washington Ave",
    "sg:city":"Holland",
    "sg:classifiers":[
        {
            "category":"Shopping",
            "subcategory":"Department Store",
            "type":"Retail Goods"
        }
    ],
    "sg:phone":"+1 616 393 8476",
    "sg:postcode":"49423",
    "sg:province":"MI",
    "sg:tags":[
        "variety"
    ],
    "sg:website":"http://www.familydollar.com",
    "wof:name":"Family Dollar Stores",
    "wof:placetype":"venue"
},
  "geometry": {"coordinates":[-86.11662200000001,42.761424],"type":"Point"}
}