{
  "type": "Feature",
  "properties": {
    "iso:country":"US",
    "sg:address":"9348 Silver Lake Rd",
    "sg:city":"Linden",
    "sg:classifiers":[
        {
            "category":"Real Estate",
            "subcategory":"Real Estate Operator",
            "type":"Services"
        }
    ],
    "sg:phone":"+1 810 735 9422",
    "sg:postcode":"48451",
    "sg:province":"MI",
    "sg:tags":[
        "mobile",
        "home",
        "site"
    ],
    "wof:name":"Pine Ridge Mobile Home Park",
    "wof:placetype":"venue"
},
  "geometry": {"coordinates":[-83.849853,42.792258],"type":"Point"}
}