{
  "type": "Feature",
  "properties": {
    "iso:country":"US",
    "sg:address":"14275 S Custer Rd",
    "sg:city":"Dundee",
    "sg:classifiers":[
        {
            "category":"Health Services",
            "subcategory":"Chiropractor",
            "type":"Services"
        }
    ],
    "sg:phone":"+1 734 529 3530",
    "sg:postcode":"48131",
    "sg:province":"MI",
    "wof:name":"Dundee Chiropractic Clinic PC",
    "wof:placetype":"venue"
},
  "geometry": {"coordinates":[-83.641079,41.951919],"type":"Point"}
}