{
  "type": "Feature",
  "properties": {
    "iso:country":"US",
    "sg:address":"5270 Lakeview Ave",
    "sg:city":"Mercer",
    "sg:classifiers":[
        {
            "category":"Bars & Pubs",
            "type":"Food & Drink"
        }
    ],
    "sg:phone":"+1 715 476 2214",
    "sg:postcode":"54547",
    "sg:province":"WI",
    "sg:tags":[
        "drinking"
    ],
    "wof:name":"Antlers Inc",
    "wof:placetype":"venue"
},
  "geometry": {"coordinates":[-90.06317,46.1656],"type":"Point"}
}