{
  "type": "Feature",
  "properties": {
    "iso:country":"US",
    "sg:address":"356 Schaffer Ct",
    "sg:city":"Manchester",
    "sg:classifiers":[
        {
            "category":"Social Services",
            "type":"Services"
        }
    ],
    "sg:phone":"+1 734 428 8852",
    "sg:postcode":"48158",
    "sg:province":"MI",
    "wof:name":"Manchester Family Services",
    "wof:placetype":"venue"
},
  "geometry": {"coordinates":[-84.04573600000001,42.145463],"type":"Point"}
}