{
  "type": "Feature",
  "properties": {
    "iso:country":"US",
    "sg:address":"18981 Telegraph Rd",
    "sg:city":"Detroit",
    "sg:classifiers":[
        {
            "category":"Personal",
            "subcategory":"Nail Salon",
            "type":"Services"
        }
    ],
    "sg:phone":"+1 313 538 1600",
    "sg:postcode":"48219",
    "sg:province":"MI",
    "wof:name":"24 7 Nails",
    "wof:placetype":"venue"
},
  "geometry": {"coordinates":[-83.278125,42.427657],"type":"Point"}
}