{
  "type": "Feature",
  "properties": {
    "iso:country":"US",
    "sg:address":"108 Main St",
    "sg:city":"Gregory",
    "sg:classifiers":[
        {
            "category":"Utilities",
            "subcategory":"Cable",
            "type":"Services"
        }
    ],
    "sg:phone":"+1 734 498 3366",
    "sg:postcode":"48137",
    "sg:province":"MI",
    "sg:tags":[
        "television"
    ],
    "wof:name":"Specialty Satellite & Antenna",
    "wof:placetype":"venue"
},
  "geometry": {"coordinates":[-84.084245,42.45826],"type":"Point"}
}