{
  "type": "Feature",
  "properties": {
    "iso:country":"US",
    "sg:address":"500 E Washington Ave",
    "sg:city":"Zeeland",
    "sg:classifiers":[
        {
            "category":"Retail",
            "subcategory":"Repair Shop",
            "type":"Services"
        }
    ],
    "sg:phone":"+1 616 931 0036",
    "sg:postcode":"49464",
    "sg:province":"MI",
    "sg:tags":[
        "refinishing",
        "furniture"
    ],
    "wof:name":"Vandermeulen Fine Finishers",
    "wof:placetype":"venue"
},
  "geometry": {"coordinates":[-86.00617699999999,42.815186],"type":"Point"}
}