{
  "type": "Feature",
  "properties": {
    "iso:country":"US",
    "sg:address":"3901 Cuthbertson St",
    "sg:city":"Flint",
    "sg:classifiers":[
        {
            "category":"Wholesale",
            "subcategory":"Machinery & Supplies",
            "type":"Manufacturing & Wholesale Goods"
        }
    ],
    "sg:phone":"+1 810 235 0248",
    "sg:postcode":"48507",
    "sg:province":"MI",
    "sg:tags":[
        "equipment",
        "hydraulic"
    ],
    "wof:name":"Tom's Enterprises",
    "wof:placetype":"venue"
},
  "geometry": {"coordinates":[-83.680497,42.987414],"type":"Point"}
}