{
  "type": "Feature",
  "properties": {
    "iso:country":"US",
    "sg:address":"24005 Telegraph Rd",
    "sg:city":"Flat Rock",
    "sg:classifiers":[
        {
            "category":"Retail",
            "subcategory":"Car Wash",
            "type":"Services"
        }
    ],
    "sg:phone":"+1 734 782 5920",
    "sg:postcode":"48134",
    "sg:province":"MI",
    "wof:name":"Huzzy's Car Wash",
    "wof:placetype":"venue"
},
  "geometry": {"coordinates":[-83.271103,42.1306],"type":"Point"}
}