{
  "type": "Feature",
  "properties": {
    "iso:country":"US",
    "sg:address":"3632 W US Hwy 10",
    "sg:city":"Ludington",
    "sg:classifiers":[
        {
            "category":"Retail",
            "subcategory":"Auto Rental",
            "type":"Services"
        }
    ],
    "sg:phone":"+1 231 845 5111",
    "sg:postcode":"49431",
    "sg:province":"MI",
    "sg:tags":[
        "passenger",
        "car"
    ],
    "wof:name":"Ford Rental System",
    "wof:placetype":"venue"
},
  "geometry": {"coordinates":[-86.37874100000001,43.95623],"type":"Point"}
}