{
  "type": "Feature",
  "properties": {
    "iso:country":"US",
    "sg:address":"3128 Fairlane Dr",
    "sg:city":"Allen Park",
    "sg:classifiers":[
        {
            "category":"Shopping",
            "subcategory":"Mobile Phones",
            "type":"Retail Goods"
        }
    ],
    "sg:phone":"+1 313 271 9255",
    "sg:postcode":"48101",
    "sg:province":"MI",
    "sg:website":"www.verizonwireless.com",
    "wof:name":"Verizon Wireless",
    "wof:placetype":"venue"
},
  "geometry": {"coordinates":[-83.20419099999999,42.283572],"type":"Point"}
}