{
  "type": "Feature",
  "properties": {
    "iso:country":"US",
    "sg:address":"45215 Labelle Dr",
    "sg:city":"Macomb",
    "sg:classifiers":[
        {
            "category":"Professional",
            "subcategory":"Business Services",
            "type":"Services"
        }
    ],
    "sg:phone":"+1 586 493 1835",
    "sg:postcode":"48044",
    "sg:province":"MI",
    "wof:name":"General Solutions Inc",
    "wof:placetype":"venue"
},
  "geometry": {"coordinates":[-82.899511,42.631631],"type":"Point"}
}