{
  "type": "Feature",
  "properties": {
    "iso:country":"US",
    "sg:address":"5224 S Cedar St",
    "sg:city":"Lansing",
    "sg:classifiers":[
        {
            "category":"Shopping",
            "subcategory":"Optical Goods",
            "type":"Retail Goods"
        }
    ],
    "sg:phone":"+1 517 882 0202",
    "sg:postcode":"48911",
    "sg:province":"MI",
    "wof:name":"DOC Optics Ctr",
    "wof:placetype":"venue"
},
  "geometry": {"coordinates":[-84.548129,42.679529],"type":"Point"}
}