{
  "type": "Feature",
  "properties": {
    "iso:country":"US",
    "sg:address":"23 Mill Rd",
    "sg:city":"Shelby Twp",
    "sg:classifiers":[
        {
            "category":"Home & Garden",
            "subcategory":"Furniture",
            "type":"Retail Goods"
        }
    ],
    "sg:phone":"+1 586 566 9814",
    "sg:postcode":"48386",
    "sg:province":"MI",
    "sg:tags":[
        "top",
        "counter"
    ],
    "wof:name":"BFD Surfaces",
    "wof:placetype":"venue"
},
  "geometry": {"coordinates":[-83.48759800000001,42.638901],"type":"Point"}
}