{
  "type": "Feature",
  "properties": {
    "iso:country":"US",
    "sg:address":"17 Mill Rd",
    "sg:city":"Marshall",
    "sg:classifiers":[
        {
            "category":"Restaurant",
            "type":"Food & Drink"
        }
    ],
    "sg:phone":"+1 269 789 0058",
    "sg:postcode":"49014",
    "sg:province":"MI",
    "wof:name":"Moonraker Lounge & Restaurant",
    "wof:placetype":"venue"
},
  "geometry": {"coordinates":[-85.14958900000001,42.332351],"type":"Point"}
}