{
  "type": "Feature",
  "properties": {
    "iso:country":"US",
    "sg:address":"2817 Van Alstyne St",
    "sg:city":"Wyandotte",
    "sg:classifiers":[
        {
            "category":"Organizations",
            "subcategory":"Community Association",
            "type":"Services"
        }
    ],
    "sg:phone":"+1 734 281 9514",
    "sg:postcode":"48192",
    "sg:province":"MI",
    "wof:name":"American Legion Post 217",
    "wof:placetype":"venue"
},
  "geometry": {"coordinates":[-83.14742099999999,42.204173],"type":"Point"}
}