{
  "type": "Feature",
  "properties": {
    "iso:country":"US",
    "sg:address":"7808 Thornapple Way SE",
    "sg:city":"Ada",
    "sg:classifiers":[
        {
            "category":"Banks & Credit Unions",
            "subcategory":"Financial Services",
            "type":"Services"
        }
    ],
    "sg:phone":"+1 616 676 9156",
    "sg:postcode":"49301",
    "sg:province":"MI",
    "sg:tags":[
        "trust",
        "investment",
        "real estate"
    ],
    "wof:name":"Emerald Shores Getaway LLC",
    "wof:placetype":"venue"
},
  "geometry": {"coordinates":[-85.476979,42.927843],"type":"Point"}
}