{
  "type": "Feature",
  "properties": {
    "iso:country":"US",
    "sg:address":"53109 N Main St",
    "sg:city":"Mattawan",
    "sg:classifiers":[
        {
            "category":"Home & Garden",
            "subcategory":"Carpets & Floor Coverings",
            "type":"Retail Goods"
        }
    ],
    "sg:phone":"+1 269 668 5378",
    "sg:postcode":"49071",
    "sg:province":"MI",
    "sg:tags":[
        "dealer",
        "rug"
    ],
    "wof:name":"West Michigan Carpet Brokers",
    "wof:placetype":"venue"
},
  "geometry": {"coordinates":[-85.785307,42.223609],"type":"Point"}
}