{
  "type": "Feature",
  "properties": {
    "iso:country":"US",
    "sg:address":"2799 Birchdale Dr",
    "sg:city":"Troy",
    "sg:classifiers":[
        {
            "category":"Professional",
            "subcategory":"Lawyer & Legal Services",
            "type":"Services"
        }
    ],
    "sg:phone":"+1 248 307 0700",
    "sg:postcode":"48083",
    "sg:province":"MI",
    "sg:tags":[
        "attorney"
    ],
    "wof:name":"Suchowski & Suchowski Plc",
    "wof:placetype":"venue"
},
  "geometry": {"coordinates":[-83.092845,42.577374],"type":"Point"}
}