{
  "type": "Feature",
  "properties": {
    "iso:country":"US",
    "sg:address":"4832 North St",
    "sg:city":"Benton Harbor",
    "sg:classifiers":[
        {
            "category":"Manufacturing",
            "subcategory":"Furniture",
            "type":"Manufacturing & Wholesale Goods"
        }
    ],
    "sg:phone":"+1 269 944 4135",
    "sg:postcode":"49022",
    "sg:province":"MI",
    "sg:tags":[
        "household",
        "wood",
        "mfg"
    ],
    "wof:name":"Beam Joe Woodworking",
    "wof:placetype":"venue"
},
  "geometry": {"coordinates":[-86.340923,42.123207],"type":"Point"}
}