{
  "type": "Feature",
  "properties": {
    "iso:country":"US",
    "sg:address":"52070 Van Dyke Ave",
    "sg:city":"Shelby Twp",
    "sg:classifiers":[
        {
            "category":"Shopping",
            "subcategory":"Florist",
            "type":"Retail Goods"
        }
    ],
    "sg:phone":"+1 586 731 4161",
    "sg:postcode":"48316",
    "sg:province":"MI",
    "wof:name":"Flowers By Us",
    "wof:placetype":"venue"
},
  "geometry": {"coordinates":[-83.03415800000001,42.678293],"type":"Point"}
}