{
  "type": "Feature",
  "properties": {
    "iso:country":"US",
    "sg:address":"72 Sheldon Blvd SE",
    "sg:city":"Grand Rapids",
    "sg:classifiers":[
        {
            "category":"Real Estate",
            "subcategory":"Real Estate Operator",
            "type":"Services"
        }
    ],
    "sg:phone":"+1 616 988 2101",
    "sg:postcode":"49503",
    "sg:province":"MI",
    "sg:tags":[
        "apartment"
    ],
    "wof:name":"Ferguson Apartment",
    "wof:placetype":"venue"
},
  "geometry": {"coordinates":[-85.666577,42.961541],"type":"Point"}
}