{
  "type": "Feature",
  "properties": {
    "iso:country":"US",
    "sg:address":"31440 Northwestern Hwy Ste 110",
    "sg:city":"Farmington Hills",
    "sg:classifiers":[
        {
            "category":"Banks & Credit Unions",
            "subcategory":"Bank",
            "type":"Services"
        }
    ],
    "sg:phone":"+1 248 539 5810",
    "sg:postcode":"48334",
    "sg:province":"MI",
    "wof:name":"Wachovia Securities",
    "wof:placetype":"venue"
},
  "geometry": {"coordinates":[-83.338252,42.518253],"type":"Point"}
}