{
  "type": "Feature",
  "properties": {
    "iso:country":"US",
    "sg:address":"1531 Main St",
    "sg:city":"Snover",
    "sg:classifiers":[
        {
            "category":"Manufacturing",
            "subcategory":"Metals",
            "type":"Manufacturing & Wholesale Goods"
        }
    ],
    "sg:phone":"+1 810 672 9283",
    "sg:postcode":"48472",
    "sg:province":"MI",
    "sg:tags":[
        "fabrication",
        "structural"
    ],
    "wof:name":"Kreative Metal Works",
    "wof:placetype":"venue"
},
  "geometry": {"coordinates":[-82.970777,43.461521],"type":"Point"}
}