{
  "type": "Feature",
  "properties": {
    "iso:country":"US",
    "sg:address":"43252 Woodward Ave Ste 202",
    "sg:city":"Bloomfield Hills",
    "sg:classifiers":[
        {
            "category":"Banks & Credit Unions",
            "subcategory":"Financial Services",
            "type":"Services"
        }
    ],
    "sg:phone":"+1 248 334 9400",
    "sg:postcode":"48302",
    "sg:province":"MI",
    "wof:name":"Golden Mortgage Corporation",
    "wof:placetype":"venue"
},
  "geometry": {"coordinates":[-83.265064,42.606103],"type":"Point"}
}