{
  "type": "Feature",
  "properties": {
    "iso:country":"US",
    "sg:address":"4498 N Bailey Rd",
    "sg:city":"Coral",
    "sg:classifiers":[
        {
            "category":"Personal",
            "type":"Services"
        }
    ],
    "sg:phone":"+1 231 354 6461",
    "sg:postcode":"49322",
    "sg:province":"MI",
    "wof:name":"Footprints",
    "wof:placetype":"venue"
},
  "geometry": {"coordinates":[-85.402871,43.356366],"type":"Point"}
}