{
  "type": "Feature",
  "properties": {
    "iso:country":"US",
    "sg:address":"2703 State St",
    "sg:city":"Saginaw",
    "sg:classifiers":[
        {
            "category":"Retail",
            "subcategory":"Auto Repair",
            "type":"Services"
        }
    ],
    "sg:phone":"+1 989 792 3000",
    "sg:postcode":"48602",
    "sg:province":"MI",
    "sg:tags":[
        "repairing",
        "automobile"
    ],
    "wof:name":"State & Bay Automotive",
    "wof:placetype":"venue"
},
  "geometry": {"coordinates":[-83.979248,43.43655],"type":"Point"}
}