{
  "type": "Feature",
  "properties": {
    "iso:country":"US",
    "sg:address":"21520 Violet St",
    "sg:city":"Saint Clair Shores",
    "sg:classifiers":[
        {
            "category":"Retail",
            "subcategory":"Repair Shop",
            "type":"Services"
        }
    ],
    "sg:phone":"+1 586 294 4186",
    "sg:postcode":"48082",
    "sg:province":"MI",
    "wof:name":"XYZ Cleaning",
    "wof:placetype":"venue"
},
  "geometry": {"coordinates":[-82.888943,42.521427],"type":"Point"}
}