{
  "type": "Feature",
  "properties": {
    "iso:country":"US",
    "sg:address":"235 E Ferry Ave",
    "sg:city":"Detroit",
    "sg:classifiers":[
        {
            "category":"Travel",
            "subcategory":"Hotels & Motels",
            "type":"Entertainment"
        }
    ],
    "sg:phone":"+1 313 872 1646",
    "sg:postcode":"48202",
    "sg:province":"MI",
    "sg:tags":[
        "membership",
        "lodging"
    ],
    "wof:name":"Omega PSI PHI Fraterniey House",
    "wof:placetype":"venue"
},
  "geometry": {"coordinates":[-83.062659,42.362922],"type":"Point"}
}