{
  "type": "Feature",
  "properties": {
    "iso:country":"US",
    "sg:address":"11375 E Casperson Rd",
    "sg:city":"Northport",
    "sg:classifiers":[
        {
            "category":"Building & Trades",
            "subcategory":"Plumbing",
            "type":"Services"
        }
    ],
    "sg:phone":"+1 231 386 5170",
    "sg:postcode":"49670",
    "sg:province":"MI",
    "sg:tags":[
        "plumbing",
        "contractor"
    ],
    "wof:name":"Morgan Contractor Inc",
    "wof:placetype":"venue"
},
  "geometry": {"coordinates":[-85.62025199999999,45.11345],"type":"Point"}
}