{
  "type": "Feature",
  "properties": {
    "iso:country":"US",
    "sg:address":"2000 Leonard St NW",
    "sg:city":"Grand Rapids",
    "sg:classifiers":[
        {
            "category":"Shopping",
            "subcategory":"Gifts & Souvenirs",
            "type":"Retail Goods"
        }
    ],
    "sg:phone":"+1 616 453 8131",
    "sg:postcode":"49504",
    "sg:province":"MI",
    "sg:tags":[
        "party",
        "supply"
    ],
    "wof:name":"Charlie's",
    "wof:placetype":"venue"
},
  "geometry": {"coordinates":[-85.71978799999999,42.986041],"type":"Point"}
}