{
  "type": "Feature",
  "properties": {
    "iso:country":"US",
    "sg:address":"2756 Merelus Dr",
    "sg:city":"Waterford",
    "sg:classifiers":[
        {
            "category":"Insurance",
            "subcategory":"Insurance Agent",
            "type":"Services"
        }
    ],
    "sg:phone":"+1 248 618 8233",
    "sg:postcode":"48329",
    "sg:province":"MI",
    "wof:name":"EHTI",
    "wof:placetype":"venue"
},
  "geometry": {"coordinates":[-83.338922,42.687304],"type":"Point"}
}