{
  "type": "Feature",
  "properties": {
    "iso:country":"US",
    "sg:address":"5058 Cisne Ave SW",
    "sg:city":"Grand Rapids",
    "sg:classifiers":[
        {
            "category":"Building & Trades",
            "subcategory":"Construction",
            "type":"Services"
        }
    ],
    "sg:phone":"+1 616 723 1872",
    "sg:postcode":"49548",
    "sg:province":"MI",
    "sg:tags":[
        "concrete",
        "contractor"
    ],
    "wof:name":"R & L Concrete",
    "wof:placetype":"venue"
},
  "geometry": {"coordinates":[-85.67175,42.872463],"type":"Point"}
}