{
  "type": "Feature",
  "properties": {
    "iso:country":"US",
    "sg:address":"12911 W 8 Mile Rd",
    "sg:city":"Detroit",
    "sg:classifiers":[
        {
            "category":"Building & Trades",
            "subcategory":"Locksmith",
            "type":"Services"
        }
    ],
    "sg:phone":"+1 313 342 6775",
    "sg:postcode":"48235",
    "sg:province":"MI",
    "sg:tags":[
        "key"
    ],
    "wof:name":"Solomon Hugo & Son Inc",
    "wof:placetype":"venue"
},
  "geometry": {"coordinates":[-83.173698,42.445202],"type":"Point"}
}