{
  "type": "Feature",
  "properties": {
    "iso:country":"US",
    "sg:address":"24483 Sorrentino Ct",
    "sg:city":"Clinton Township",
    "sg:classifiers":[
        {
            "category":"Manufacturing",
            "subcategory":"Tools & Machinery",
            "type":"Manufacturing & Wholesale Goods"
        }
    ],
    "sg:phone":"+1 586 791 3160",
    "sg:postcode":"48035",
    "sg:province":"MI",
    "sg:tags":[
        "manufacture",
        "repair",
        "industrial"
    ],
    "wof:name":"Heating Induction Services",
    "wof:placetype":"venue"
},
  "geometry": {"coordinates":[-82.864915,42.554658],"type":"Point"}
}