{
  "type": "Feature",
  "properties": {
    "iso:country":"US",
    "sg:address":"465 Main St",
    "sg:city":"Belleville",
    "sg:classifiers":[
        {
            "category":"Banks & Credit Unions",
            "subcategory":"Bank",
            "type":"Services"
        }
    ],
    "sg:phone":"+1 734 697 9111",
    "sg:postcode":"48111",
    "sg:province":"MI",
    "wof:name":"Bank One",
    "wof:placetype":"venue"
},
  "geometry": {"coordinates":[-83.492057,42.209243],"type":"Point"}
}