{
  "type": "Feature",
  "properties": {
    "iso:country":"US",
    "sg:address":"412 Wonder Ln",
    "sg:city":"Romeo",
    "sg:classifiers":[
        {
            "category":"Personal",
            "type":"Services"
        }
    ],
    "sg:phone":"+1 586 336 0669",
    "sg:postcode":"48065",
    "sg:province":"MI",
    "wof:name":"Resting Place",
    "wof:placetype":"venue"
},
  "geometry": {"coordinates":[-83.020359,42.808593],"type":"Point"}
}