{
  "type": "Feature",
  "properties": {
    "iso:country":"US",
    "sg:address":"8824 Douglas Ave",
    "sg:city":"Kalamazoo",
    "sg:classifiers":[
        {
            "category":"Organizations",
            "subcategory":"Religious Organization",
            "type":"Services"
        }
    ],
    "sg:phone":"+1 269 385 4378",
    "sg:postcode":"49009",
    "sg:province":"MI",
    "wof:name":"Cooper Baptist Church",
    "wof:placetype":"venue"
},
  "geometry": {"coordinates":[-85.61032400000001,42.388554],"type":"Point"}
}