{
  "type": "Feature",
  "properties": {
    "iso:country":"US",
    "sg:address":"25913 Coolidge Hwy",
    "sg:city":"Oak Park",
    "sg:classifiers":[
        {
            "category":"Shopping",
            "subcategory":"Clothing, Apparel, & Fashions",
            "type":"Retail Goods"
        }
    ],
    "sg:phone":"+1 248 547 5794",
    "sg:postcode":"48237",
    "sg:province":"MI",
    "sg:tags":[
        "tailor"
    ],
    "wof:name":"Cambridge Tailors",
    "wof:placetype":"venue"
},
  "geometry": {"coordinates":[-83.183031,42.482178],"type":"Point"}
}