{
  "type": "Feature",
  "properties": {
    "iso:country":"US",
    "sg:address":"1875 E Grand River Ave",
    "sg:city":"Portland",
    "sg:classifiers":[
        {
            "category":"Retail",
            "subcategory":"Repair Shop",
            "type":"Services"
        }
    ],
    "sg:phone":"+1 517 647 6801",
    "sg:postcode":"48875",
    "sg:province":"MI",
    "sg:tags":[
        "tractor"
    ],
    "wof:name":"Tom's Auto Body",
    "wof:placetype":"venue"
},
  "geometry": {"coordinates":[-85.037025,42.886014],"type":"Point"}
}