{
  "type": "Feature",
  "properties": {
    "iso:country":"US",
    "sg:address":"44750 Ford Rd",
    "sg:city":"Canton",
    "sg:classifiers":[
        {
            "category":"Health Services",
            "subcategory":"Optometrist",
            "type":"Services"
        },
        {
            "category":"Shopping",
            "subcategory":"Optician",
            "type":"Retail Goods"
        }
    ],
    "sg:phone":"+1 734 455 3190",
    "sg:postcode":"48187",
    "sg:province":"MI",
    "sg:tags":[
        "eyewear"
    ],
    "wof:name":"Elite Eyecare Center Canton",
    "wof:placetype":"venue"
},
  "geometry": {"coordinates":[-83.481903,42.322201],"type":"Point"}
}