{
  "type": "Feature",
  "properties": {
    "iso:country":"US",
    "sg:address":"21527 Avalon St",
    "sg:city":"St Clair Shores",
    "sg:classifiers":[
        {
            "category":"Retail",
            "subcategory":"Repair Shop",
            "type":"Services"
        },
        {
            "category":"Building & Trades",
            "subcategory":"Plumbing",
            "type":"Services"
        }
    ],
    "sg:phone":"+1 586 776 6993",
    "sg:postcode":"48080",
    "sg:province":"MI",
    "sg:tags":[
        "plumbing",
        "contractor"
    ],
    "wof:name":"At-Less Plumbing & Drain Clean",
    "wof:placetype":"venue"
},
  "geometry": {"coordinates":[-82.90749,42.456275],"type":"Point"}
}