{
  "type": "Feature",
  "properties": {
    "iso:country":"US",
    "sg:address":"736 Stocking Ave NW",
    "sg:city":"Grand Rapids",
    "sg:classifiers":[
        {
            "category":"Professional",
            "type":"Services"
        }
    ],
    "sg:phone":"+1 616 954 0993",
    "sg:postcode":"49504",
    "sg:province":"MI",
    "sg:tags":[
        "establishment"
    ],
    "wof:name":"Aegis Benifits",
    "wof:placetype":"venue"
},
  "geometry": {"coordinates":[-85.688939,42.976698],"type":"Point"}
}