{
  "type": "Feature",
  "properties": {
    "iso:country":"US",
    "sg:address":"2201 Dixie Hwy",
    "sg:city":"Waterford",
    "sg:classifiers":[
        {
            "category":"Travel",
            "subcategory":"Hotels & Motels",
            "type":"Entertainment"
        }
    ],
    "sg:phone":"+1 248 338 4061",
    "sg:postcode":"48328",
    "sg:province":"MI",
    "sg:tags":[
        "operation"
    ],
    "wof:name":"Highlander Motel",
    "wof:placetype":"venue"
},
  "geometry": {"coordinates":[-83.33385199999999,42.668689],"type":"Point"}
}