{
  "type": "Feature",
  "properties": {
    "iso:country":"US",
    "sg:address":"801 E Maumee St",
    "sg:city":"Adrian",
    "sg:classifiers":[
        {
            "category":"Social Services",
            "subcategory":"Child Care",
            "type":"Services"
        }
    ],
    "sg:phone":"+1 517 266 0229",
    "sg:postcode":"49221",
    "sg:province":"MI",
    "sg:tags":[
        "kindergarten",
        "academic",
        "school"
    ],
    "wof:name":"Adrian Head Start",
    "wof:placetype":"venue"
},
  "geometry": {"coordinates":[-84.02585000000001,41.897036],"type":"Point"}
}