{
  "type": "Feature",
  "properties": {
    "iso:country":"US",
    "sg:address":"4665 Rohr Rd",
    "sg:city":"Lake Orion",
    "sg:classifiers":[
        {
            "category":"Building & Trades",
            "subcategory":"Construction",
            "type":"Services"
        }
    ],
    "sg:phone":"+1 248 391 0450",
    "sg:postcode":"48359",
    "sg:province":"MI",
    "sg:tags":[
        "builder",
        "patio",
        "deck"
    ],
    "wof:name":"Rustic Outdoors Landscaping Co",
    "wof:placetype":"venue"
},
  "geometry": {"coordinates":[-83.329149,42.712976],"type":"Point"}
}