{
  "type": "Feature",
  "properties": {
    "iso:country":"US",
    "sg:address":"3990 2nd St",
    "sg:city":"Wayne",
    "sg:classifiers":[
        {
            "category":"Retail",
            "subcategory":"Auto Repair",
            "type":"Services"
        }
    ],
    "sg:phone":"+1 734 595 4400",
    "sg:postcode":"48184",
    "sg:province":"MI",
    "sg:tags":[
        "disabled",
        "outfitter",
        "complete",
        "for",
        "mobility"
    ],
    "wof:name":"Advantage Mobility Outfitters",
    "wof:placetype":"venue"
},
  "geometry": {"coordinates":[-83.38067100000001,42.277716],"type":"Point"}
}