{
  "type": "Feature",
  "properties": {
    "iso:country":"US",
    "sg:address":"3146 S Dye Rd",
    "sg:city":"Flint",
    "sg:classifiers":[
        {
            "category":"Building & Trades",
            "subcategory":"Construction",
            "type":"Services"
        }
    ],
    "sg:phone":"+1 810 232 2121",
    "sg:postcode":"48507",
    "sg:province":"MI",
    "sg:tags":[
        "marking",
        "maintenance",
        "parking"
    ],
    "wof:name":"Curbco",
    "wof:placetype":"venue"
},
  "geometry": {"coordinates":[-83.782033,42.978761],"type":"Point"}
}