{
  "type": "Feature",
  "properties": {
    "iso:country":"US",
    "sg:address":"5351 Moore Rd",
    "sg:city":"Williamsburg",
    "sg:classifiers":[
        {
            "category":"Insurance",
            "subcategory":"Insurance Agent",
            "type":"Services"
        }
    ],
    "sg:phone":"+1 231 267 9477",
    "sg:postcode":"49690",
    "sg:province":"MI",
    "wof:name":"Michigan Risk Assessment",
    "wof:placetype":"venue"
},
  "geometry": {"coordinates":[-85.414143,44.760217],"type":"Point"}
}