{
  "type": "Feature",
  "properties": {
    "iso:country":"US",
    "sg:address":"17920 Farmington Rd",
    "sg:city":"Livonia",
    "sg:classifiers":[
        {
            "category":"Health Services",
            "subcategory":"Doctor",
            "type":"Services"
        }
    ],
    "sg:phone":"+1 734 425 5200",
    "sg:postcode":"48152",
    "sg:province":"MI",
    "wof:name":"Ajluni Roger MD",
    "wof:placetype":"venue"
},
  "geometry": {"coordinates":[-83.374393,42.418306],"type":"Point"}
}