{
  "type": "Feature",
  "properties": {
    "iso:country":"US",
    "sg:address":"2002 Stephenson Hwy",
    "sg:city":"Troy",
    "sg:classifiers":[
        {
            "category":"Manufacturing",
            "subcategory":"Tools & Machinery",
            "type":"Manufacturing & Wholesale Goods"
        }
    ],
    "sg:phone":"+1 248 689 0404",
    "sg:postcode":"48083",
    "sg:province":"MI",
    "sg:tags":[
        "process",
        "control",
        "c",
        "mfg",
        "instrument"
    ],
    "wof:name":"Smarteye Corporation",
    "wof:placetype":"venue"
},
  "geometry": {"coordinates":[-83.125817,42.55383],"type":"Point"}
}