{
  "type": "Feature",
  "properties": {
    "iso:country":"US",
    "sg:address":"868 Woods Ln",
    "sg:city":"Grosse Pointe",
    "sg:classifiers":[
        {
            "category":"Professional",
            "subcategory":"Computer Services",
            "type":"Services"
        }
    ],
    "sg:phone":"+1 313 886 0183",
    "sg:postcode":"48236",
    "sg:province":"MI",
    "wof:name":"Dicomp Inc",
    "wof:placetype":"venue"
},
  "geometry": {"coordinates":[-82.88685599999999,42.448844],"type":"Point"}
}