{
  "type": "Feature",
  "properties": {
    "iso:country":"US",
    "sg:address":"1279 N Saginaw Rd",
    "sg:city":"Midland",
    "sg:classifiers":[
        {
            "category":"Banks & Credit Unions",
            "subcategory":"Investment Brokerage",
            "type":"Services"
        }
    ],
    "sg:phone":"+1 989 837 8389",
    "sg:postcode":"48640",
    "sg:province":"MI",
    "sg:tags":[
        "advisory",
        "financial"
    ],
    "wof:name":"Advantage Financial Svc",
    "wof:placetype":"venue"
},
  "geometry": {"coordinates":[-84.240509,43.63976],"type":"Point"}
}