{
  "type": "Feature",
  "properties": {
    "iso:country":"US",
    "sg:address":"9291 Airport Dr",
    "sg:city":"Lakeview",
    "sg:classifiers":[
        {
            "category":"Airport",
            "type":"Transportation"
        }
    ],
    "sg:phone":"+1 989 352 7220",
    "sg:postcode":"48850",
    "sg:province":"MI",
    "sg:tags":[
        "aircraft",
        "maintenance"
    ],
    "wof:name":"T & W Electrical Svc Inc",
    "wof:placetype":"venue"
},
  "geometry": {"coordinates":[-85.26545400000001,43.449329],"type":"Point"}
}