{
  "type": "Feature",
  "properties": {
    "iso:country":"US",
    "sg:address":"5455 Squire Ln",
    "sg:city":"Flint",
    "sg:classifiers":[
        {
            "category":"Home & Garden",
            "subcategory":"Carpets & Floor Coverings",
            "type":"Retail Goods"
        }
    ],
    "sg:phone":"+1 810 736 8974",
    "sg:postcode":"48506",
    "sg:province":"MI",
    "wof:name":"Martins Floor Covering Svc",
    "wof:placetype":"venue"
},
  "geometry": {"coordinates":[-83.597979,43.060562],"type":"Point"}
}