{
  "type": "Feature",
  "properties": {
    "iso:country":"US",
    "sg:address":"514 N Grand St",
    "sg:city":"Fowlerville",
    "sg:classifiers":[
        {
            "category":"Shopping",
            "subcategory":"Discount & Variety Stores",
            "type":"Retail Goods"
        }
    ],
    "sg:phone":"+1 517 223 7253",
    "sg:postcode":"48836",
    "sg:province":"MI",
    "wof:name":"Dollar Dazzle",
    "wof:placetype":"venue"
},
  "geometry": {"coordinates":[-84.073386,42.665561],"type":"Point"}
}