{
  "type": "Feature",
  "properties": {
    "iso:country":"US",
    "sg:address":"490 N Ortonville Rd",
    "sg:city":"Ortonville",
    "sg:classifiers":[
        {
            "category":"Home & Garden",
            "subcategory":"Furniture",
            "type":"Retail Goods"
        }
    ],
    "sg:phone":"+1 248 627 4670",
    "sg:postcode":"48462",
    "sg:province":"MI",
    "sg:tags":[
        "top",
        "counter"
    ],
    "wof:name":"Country Counter Top Co",
    "wof:placetype":"venue"
},
  "geometry": {"coordinates":[-83.45622299999999,42.8573],"type":"Point"}
}