{
  "type": "Feature",
  "properties": {
    "iso:country":"US",
    "sg:address":"276 Visger Rd",
    "sg:city":"River Rouge",
    "sg:classifiers":[
        {
            "category":"Autos & Motor Vehicles",
            "subcategory":"Fuel & Gas Station",
            "type":"Retail Goods"
        }
    ],
    "sg:phone":"+1 313 381 6464",
    "sg:postcode":"48218",
    "sg:province":"MI",
    "wof:name":"Visgar Enterprises",
    "wof:placetype":"venue"
},
  "geometry": {"coordinates":[-83.14980300000001,42.263],"type":"Point"}
}