{
  "type": "Feature",
  "properties": {
    "iso:country":"US",
    "sg:address":"28044 Center Oaks Ct",
    "sg:city":"Wixom",
    "sg:classifiers":[
        {
            "category":"Wholesale",
            "subcategory":"Electrical",
            "type":"Manufacturing & Wholesale Goods"
        }
    ],
    "sg:phone":"+1 248 348 8100",
    "sg:postcode":"48393",
    "sg:province":"MI",
    "sg:tags":[
        "video",
        "disc",
        "tape"
    ],
    "sg:website":"www.avd.com",
    "wof:name":"AVD",
    "wof:placetype":"venue"
},
  "geometry": {"coordinates":[-83.546646,42.498217],"type":"Point"}
}