{
  "type": "Feature",
  "properties": {
    "iso:country":"US",
    "sg:address":"2295 W Bertrand Rd",
    "sg:city":"Niles",
    "sg:classifiers":[
        {
            "category":"Personal",
            "subcategory":"Beauty Salon",
            "type":"Services"
        }
    ],
    "sg:phone":"+1 269 684 7005",
    "sg:postcode":"49120",
    "sg:province":"MI",
    "sg:tags":[
        "shop"
    ],
    "wof:name":"A Cut Above",
    "wof:placetype":"venue"
},
  "geometry": {"coordinates":[-86.305646,41.773346],"type":"Point"}
}