{
  "type": "Feature",
  "properties": {
    "iso:country":"US",
    "sg:address":"18325 E 10 Mile Rd",
    "sg:city":"Roseville",
    "sg:classifiers":[
        {
            "category":"Health Services",
            "subcategory":"Doctor",
            "type":"Services"
        }
    ],
    "sg:phone":"+1 586 773 6300",
    "sg:postcode":"48066",
    "sg:province":"MI",
    "sg:tags":[
        "medical"
    ],
    "wof:name":"Todd G Campbell MD",
    "wof:placetype":"venue"
},
  "geometry": {"coordinates":[-82.94793799999999,42.479673],"type":"Point"}
}