{
  "type": "Feature",
  "properties": {
    "iso:country":"US",
    "sg:address":"3972 Scott St",
    "sg:city":"Calumet",
    "sg:classifiers":[
        {
            "category":"Personal",
            "subcategory":"Beauty Salon",
            "type":"Services"
        }
    ],
    "sg:phone":"+1 906 337 3232",
    "sg:postcode":"49913",
    "sg:province":"MI",
    "sg:tags":[
        "shop",
        "barber"
    ],
    "wof:name":"Northern Cuts",
    "wof:placetype":"venue"
},
  "geometry": {"coordinates":[-88.45372999999999,47.24445],"type":"Point"}
}