{
  "type": "Feature",
  "properties": {
    "iso:country":"US",
    "sg:address":"5695 Midland Rd",
    "sg:city":"Freeland",
    "sg:classifiers":[
        {
            "category":"Social Services",
            "subcategory":"Adult Care",
            "type":"Services"
        }
    ],
    "sg:phone":"+1 989 642 5504",
    "sg:postcode":"48623",
    "sg:province":"MI",
    "sg:tags":[
        "residential"
    ],
    "wof:name":"Customer Accountant",
    "wof:placetype":"venue"
},
  "geometry": {"coordinates":[-84.096808,43.491392],"type":"Point"}
}