{
  "type": "Feature",
  "properties": {
    "iso:country":"US",
    "sg:address":"400 Fuller St",
    "sg:city":"Clio",
    "sg:classifiers":[
        {
            "category":"Real Estate",
            "subcategory":"Real Estate Operator",
            "type":"Services"
        }
    ],
    "sg:phone":"+1 810 687 2030",
    "sg:postcode":"48420",
    "sg:province":"MI",
    "sg:tags":[
        "building",
        "apartment"
    ],
    "wof:name":"Four Hundred Fuller Apartments",
    "wof:placetype":"venue"
},
  "geometry": {"coordinates":[-83.72591,43.178442],"type":"Point"}
}