{
  "type": "Feature",
  "properties": {
    "iso:country":"US",
    "sg:address":"1157 Concord St",
    "sg:city":"Detroit",
    "sg:classifiers":[
        {
            "category":"Organizations",
            "subcategory":"Religious Organization",
            "type":"Services"
        }
    ],
    "sg:phone":"+1 313 267 1010",
    "sg:postcode":"48207",
    "sg:province":"MI",
    "wof:name":"Church of the Messiah Housing Corp",
    "wof:placetype":"venue"
},
  "geometry": {"coordinates":[-83.008454,42.350864],"type":"Point"}
}