{
  "type": "Feature",
  "properties": {
    "iso:country":"US",
    "sg:address":"752 W Grand River Ave",
    "sg:city":"Brighton",
    "sg:classifiers":[
        {
            "category":"Wholesale",
            "subcategory":"Hardware",
            "type":"Manufacturing & Wholesale Goods"
        }
    ],
    "sg:phone":"+1 810 220 2728",
    "sg:postcode":"48116",
    "sg:province":"MI",
    "sg:tags":[
        "robot"
    ],
    "sg:website":"www.destinyautomation.com",
    "wof:name":"Destiny Automation",
    "wof:placetype":"venue"
},
  "geometry": {"coordinates":[-83.783728,42.535786],"type":"Point"}
}