{
  "type": "Feature",
  "properties": {
    "iso:country":"US",
    "sg:address":"2221 Newman Rd",
    "sg:city":"West Branch",
    "sg:classifiers":[
        {
            "category":"Freight",
            "type":"Transportation"
        },
        {
            "category":"Retail",
            "subcategory":"Auto Rental",
            "type":"Services"
        }
    ],
    "sg:phone":"+1 989 345 1682",
    "sg:postcode":"48661",
    "sg:province":"MI",
    "sg:tags":[
        "truck",
        "leasing",
        "trucking"
    ],
    "wof:name":"A J Wangler Inc",
    "wof:placetype":"venue"
},
  "geometry": {"coordinates":[-84.114874,44.271072],"type":"Point"}
}