{
  "type": "Feature",
  "properties": {
    "iso:country":"US",
    "sg:address":"1571 S Lake Pleasant Rd",
    "sg:city":"Attica",
    "sg:classifiers":[
        {
            "category":"Retail",
            "subcategory":"Auto Repair",
            "type":"Services"
        }
    ],
    "sg:phone":"+1 810 724 3687",
    "sg:postcode":"48412",
    "sg:province":"MI",
    "sg:tags":[
        "body",
        "shop"
    ],
    "wof:name":"Mdt Enterprises Inc",
    "wof:placetype":"venue"
},
  "geometry": {"coordinates":[-83.16537,43.016394],"type":"Point"}
}