{
  "type": "Feature",
  "properties": {
    "iso:country":"US",
    "sg:address":"12053 Parkview",
    "sg:city":"Holland",
    "sg:classifiers":[
        {
            "category":"Real Estate",
            "subcategory":"Real Estate Operator",
            "type":"Services"
        }
    ],
    "sg:phone":"+1 616 399 5558",
    "sg:postcode":"49424",
    "sg:province":"MI",
    "sg:tags":[
        "apartment"
    ],
    "wof:name":"Clearview Apartments",
    "wof:placetype":"venue"
},
  "geometry": {"coordinates":[-86.079854,42.830032],"type":"Point"}
}