{
  "type": "Feature",
  "properties": {
    "iso:country":"US",
    "sg:address":"6175 Norton Center Dr",
    "sg:city":"Muskegon",
    "sg:classifiers":[
        {
            "category":"Home & Garden",
            "subcategory":"Furniture",
            "type":"Retail Goods"
        }
    ],
    "sg:phone":"+1 231 799 9032",
    "sg:postcode":"49441",
    "sg:province":"MI",
    "sg:tags":[
        "top",
        "counter"
    ],
    "wof:name":"Top It Off",
    "wof:placetype":"venue"
},
  "geometry": {"coordinates":[-86.21796999999999,43.143532],"type":"Point"}
}