{
  "type": "Feature",
  "properties": {
    "iso:country":"US",
    "sg:address":"32525 Mound Rd",
    "sg:city":"Warren",
    "sg:classifiers":[
        {
            "category":"Banks & Credit Unions",
            "subcategory":"Financial Services",
            "type":"Services"
        }
    ],
    "sg:phone":"+1 586 268 9292",
    "sg:postcode":"48092",
    "sg:province":"MI",
    "sg:tags":[
        "broker",
        "mortgage"
    ],
    "sg:website":"www.alliedmtgcapital.com",
    "wof:name":"Allied Home Mortgage Capita",
    "wof:placetype":"venue"
},
  "geometry": {"coordinates":[-83.048239,42.532638],"type":"Point"}
}