{
  "type": "Feature",
  "properties": {
    "iso:country":"US",
    "sg:address":"1030 Westend Ave NW",
    "sg:city":"Grand Rapids",
    "sg:classifiers":[
        {
            "category":"Real Estate",
            "subcategory":"Real Estate Agent",
            "type":"Services"
        }
    ],
    "sg:phone":"+1 616 485 2256",
    "sg:postcode":"49504",
    "sg:province":"MI",
    "sg:tags":[
        "inspection"
    ],
    "wof:name":"Andrew Starr LLC",
    "wof:placetype":"venue"
},
  "geometry": {"coordinates":[-85.719658,42.982578],"type":"Point"}
}