{
  "type": "Feature",
  "properties": {
    "iso:country":"US",
    "sg:address":"7800 Woodmont Ave",
    "sg:city":"Detroit",
    "sg:classifiers":[
        {
            "category":"Organizations",
            "subcategory":"Religious Organization",
            "type":"Services"
        }
    ],
    "sg:phone":"+1 313 584 7579",
    "sg:postcode":"48228",
    "sg:province":"MI",
    "wof:name":"Sisters of Holy Fmly Nazareth",
    "wof:placetype":"venue"
},
  "geometry": {"coordinates":[-83.20709600000001,42.349914],"type":"Point"}
}