{
  "type": "Feature",
  "properties": {
    "iso:country":"US",
    "sg:address":"1005 Forest Ave",
    "sg:city":"Manistee",
    "sg:classifiers":[
        {
            "category":"Travel",
            "subcategory":"Campground",
            "type":"Entertainment"
        }
    ],
    "sg:phone":"+1 231 723 0141",
    "sg:postcode":"49660",
    "sg:province":"MI",
    "wof:name":"Lake Michigan Recreation Area",
    "wof:placetype":"venue"
},
  "geometry": {"coordinates":[-86.306667,44.227556],"type":"Point"}
}