{
  "type": "Feature",
  "properties": {
    "iso:country":"US",
    "sg:address":"4100 Ann Arbor Rd",
    "sg:city":"Jackson",
    "sg:classifiers":[
        {
            "category":"Building & Trades",
            "subcategory":"Construction",
            "type":"Services"
        }
    ],
    "sg:phone":"+1 517 780 0904",
    "sg:postcode":"49202",
    "sg:province":"MI",
    "sg:tags":[
        "general",
        "contractor"
    ],
    "wof:name":"Better View Construction",
    "wof:placetype":"venue"
},
  "geometry": {"coordinates":[-84.342733,42.261226],"type":"Point"}
}