{
  "type": "Feature",
  "properties": {
    "iso:country":"US",
    "sg:address":"37671 6 Mile Rd",
    "sg:city":"Livonia",
    "sg:classifiers":[
        {
            "category":"Fast Food",
            "type":"Food & Drink"
        },
        {
            "category":"Food & Beverages",
            "subcategory":"Bakery",
            "type":"Retail Goods"
        }
    ],
    "sg:phone":"+1 734 462 3700",
    "sg:postcode":"48152",
    "sg:province":"MI",
    "sg:tags":[
        "sandwich"
    ],
    "sg:website":"www.jimmyjohns.com",
    "wof:name":"Jimmy John's Gourmet Sandwiches",
    "wof:placetype":"venue"
},
  "geometry": {"coordinates":[-83.417297,42.4105],"type":"Point"}
}