{
  "type": "Feature",
  "properties": {
    "iso:country":"US",
    "sg:address":"3727 Ivy Ln",
    "sg:city":"Dewitt",
    "sg:classifiers":[
        {
            "category":"Professional",
            "type":"Services"
        }
    ],
    "sg:phone":"+1 517 669 2254",
    "sg:postcode":"48820",
    "sg:province":"MI",
    "wof:name":"Kathleens Kreations",
    "wof:placetype":"venue"
},
  "geometry": {"coordinates":[-84.597928,42.831428],"type":"Point"}
}