{
  "type": "Feature",
  "properties": {
    "iso:country":"US",
    "sg:address":"1724 Stauch Dr",
    "sg:city":"West Bloomfield",
    "sg:classifiers":[
        {
            "category":"Shopping",
            "subcategory":"Catalog Store",
            "type":"Retail Goods"
        }
    ],
    "sg:phone":"+1 248 366 8889",
    "sg:postcode":"48324",
    "sg:province":"MI",
    "sg:tags":[
        "mail",
        "order"
    ],
    "sg:website":"www.tradingrooms.com",
    "wof:name":"Malibu International",
    "wof:placetype":"venue"
},
  "geometry": {"coordinates":[-83.40542600000001,42.612962],"type":"Point"}
}