{
  "type": "Feature",
  "properties": {
    "iso:country":"US",
    "sg:address":"1310 W Oliver St",
    "sg:city":"Owosso",
    "sg:classifiers":[
        {
            "category":"Social Services",
            "subcategory":"Adult Care",
            "type":"Services"
        }
    ],
    "sg:phone":"+1 989 729 6060",
    "sg:postcode":"48867",
    "sg:province":"MI",
    "sg:tags":[
        "home",
        "residential"
    ],
    "wof:name":"Oliver Woods Retirement Vlg",
    "wof:placetype":"venue"
},
  "geometry": {"coordinates":[-84.18807700000001,43.003263],"type":"Point"}
}