{
  "type": "Feature",
  "properties": {
    "iso:country":"US",
    "sg:address":"12729 E Washington Rd",
    "sg:city":"Reese",
    "sg:classifiers":[
        {
            "category":"Wholesale",
            "subcategory":"Hardware",
            "type":"Manufacturing & Wholesale Goods"
        }
    ],
    "sg:phone":"+1 989 868 4641",
    "sg:postcode":"48757",
    "sg:province":"MI",
    "sg:tags":[
        "furnace"
    ],
    "wof:name":"Reese Plumbing & Heating",
    "wof:placetype":"venue"
},
  "geometry": {"coordinates":[-83.702746,43.450531],"type":"Point"}
}