{
  "type": "Feature",
  "properties": {
    "iso:country":"US",
    "sg:address":"6343 W Freeland Rd",
    "sg:city":"Freeland",
    "sg:classifiers":[
        {
            "category":"Building & Trades",
            "subcategory":"Construction",
            "type":"Services"
        }
    ],
    "sg:phone":"+1 989 695 4724",
    "sg:postcode":"48623",
    "sg:province":"MI",
    "sg:tags":[
        "house"
    ],
    "wof:name":"Anderson Builder Dan",
    "wof:placetype":"venue"
},
  "geometry": {"coordinates":[-84.046862,43.52396],"type":"Point"}
}