{
  "type": "Feature",
  "properties": {
    "iso:country":"US",
    "sg:address":"2191 Harwood Rd",
    "sg:city":"Ionia",
    "sg:classifiers":[
        {
            "category":"Education",
            "subcategory":"School",
            "type":"Public Place"
        }
    ],
    "sg:phone":"+1 616 527 2921",
    "sg:postcode":"48846",
    "sg:province":"MI",
    "wof:name":"Freedom Acres School",
    "wof:placetype":"venue"
},
  "geometry": {"coordinates":[-85.09444000000001,42.955106],"type":"Point"}
}