{
  "type": "Feature",
  "properties": {
    "iso:country":"US",
    "sg:address":"5455 Rockridge Dr NE",
    "sg:city":"Comstock Park",
    "sg:classifiers":[
        {
            "category":"Building & Trades",
            "subcategory":"Construction",
            "type":"Services"
        }
    ],
    "sg:phone":"+1 616 785 1532",
    "sg:postcode":"49321",
    "sg:province":"MI",
    "sg:tags":[
        "contractor"
    ],
    "wof:name":"Garthe Tile",
    "wof:placetype":"venue"
},
  "geometry": {"coordinates":[-85.652675,43.062578],"type":"Point"}
}