{
  "type": "Feature",
  "properties": {
    "iso:country":"US",
    "sg:address":"37115 McKinney Ave Apt 104",
    "sg:city":"Westland",
    "sg:classifiers":[
        {
            "category":"Real Estate",
            "subcategory":"Real Estate Operator",
            "type":"Services"
        }
    ],
    "sg:phone":"+1 734 421 8200",
    "sg:postcode":"48185",
    "sg:province":"MI",
    "sg:tags":[
        "apartment"
    ],
    "sg:website":"www.warrisfarms.com",
    "wof:name":"Warris Farms Apartments",
    "wof:placetype":"venue"
},
  "geometry": {"coordinates":[-83.40920300000001,42.348598],"type":"Point"}
}