{
  "type": "Feature",
  "properties": {
    "iso:country":"US",
    "sg:address":"9284 E Mitchell Rd",
    "sg:city":"Petoskey",
    "sg:classifiers":[
        {
            "category":"Building & Trades",
            "subcategory":"Construction",
            "type":"Services"
        }
    ],
    "sg:phone":"+1 231 347 4322",
    "sg:postcode":"49770",
    "sg:province":"MI",
    "wof:name":"Blue Bay Builders",
    "wof:placetype":"venue"
},
  "geometry": {"coordinates":[-84.811173,45.362693],"type":"Point"}
}