{
  "type": "Feature",
  "properties": {
    "iso:country":"US",
    "sg:address":"8098 Edgewood Dr",
    "sg:city":"Birch Run",
    "sg:classifiers":[
        {
            "category":"Personal",
            "subcategory":"Beauty Salon",
            "type":"Services"
        }
    ],
    "sg:phone":"+1 989 624 4808",
    "sg:postcode":"48415",
    "sg:province":"MI",
    "sg:tags":[
        "shop"
    ],
    "wof:name":"Jodys Family Haircare",
    "wof:placetype":"venue"
},
  "geometry": {"coordinates":[-83.79279099999999,43.260389],"type":"Point"}
}