{
  "type": "Feature",
  "properties": {
    "iso:country":"US",
    "sg:address":"4200 Van Wagnen Rd",
    "sg:city":"Vassar",
    "sg:classifiers":[
        {
            "category":"Building & Trades",
            "subcategory":"Construction",
            "type":"Services"
        }
    ],
    "sg:phone":"+1 989 823 6001",
    "sg:postcode":"48768",
    "sg:province":"MI",
    "sg:tags":[
        "windows"
    ],
    "wof:name":"Windshields On Wheels",
    "wof:placetype":"venue"
},
  "geometry": {"coordinates":[-83.543526,43.384483],"type":"Point"}
}