{
  "type": "Feature",
  "properties": {
    "iso:country":"US",
    "sg:address":"7216 Division Ave S",
    "sg:city":"Grand Rapids",
    "sg:classifiers":[
        {
            "category":"Utilities",
            "subcategory":"Telephone",
            "type":"Services"
        }
    ],
    "sg:phone":"+1 616 455 6726",
    "sg:postcode":"49548",
    "sg:province":"MI",
    "sg:tags":[
        "telecommunication"
    ],
    "sg:website":"www.petersondatacom.com",
    "wof:name":"Peterson Datacom Group",
    "wof:placetype":"venue"
},
  "geometry": {"coordinates":[-85.663545,42.832848],"type":"Point"}
}