{
  "type": "Feature",
  "properties": {
    "iso:country":"US",
    "sg:address":"115 N Center St",
    "sg:city":"Northville",
    "sg:classifiers":[
        {
            "category":"Health Services",
            "subcategory":"Clinic",
            "type":"Services"
        }
    ],
    "sg:phone":"+1 248 347 3470",
    "sg:postcode":"48167",
    "sg:province":"MI",
    "sg:tags":[
        "specialty",
        "outpatient"
    ],
    "wof:name":"Hegira Programs Inc",
    "wof:placetype":"venue"
},
  "geometry": {"coordinates":[-83.48333,42.432026],"type":"Point"}
}