{
  "type": "Feature",
  "properties": {
    "iso:country":"US",
    "sg:address":"4130 Rochester Rd",
    "sg:city":"Royal Oak",
    "sg:classifiers":[
        {
            "category":"Professional",
            "type":"Services"
        }
    ],
    "sg:phone":"+1 248 588 2210",
    "sg:postcode":"48073",
    "sg:province":"MI",
    "sg:tags":[
        "caterer"
    ],
    "sg:website":"www.oasisgourmetcuisine.com/",
    "wof:name":"Oasis Gourmet Cuisine Llc",
    "wof:placetype":"venue"
},
  "geometry": {"coordinates":[-83.137497,42.526501],"type":"Point"}
}