{
  "type": "Feature",
  "properties": {
    "iso:country":"US",
    "sg:address":"46869 Garfield Rd",
    "sg:city":"Macomb",
    "sg:classifiers":[
        {
            "category":"Real Estate",
            "subcategory":"Architect",
            "type":"Services"
        }
    ],
    "sg:phone":"+1 586 532 9388",
    "sg:postcode":"48044",
    "sg:province":"MI",
    "wof:name":"Sauriol Bohde Wagner Arch",
    "wof:placetype":"venue"
},
  "geometry": {"coordinates":[-82.956317,42.639996],"type":"Point"}
}