{
  "type": "Feature",
  "properties": {
    "iso:country":"US",
    "sg:address":"639 Balboa Pl",
    "sg:city":"Pontiac",
    "sg:classifiers":[
        {
            "category":"Real Estate",
            "subcategory":"Real Estate Operator",
            "type":"Services"
        }
    ],
    "sg:phone":"+1 248 334 6262",
    "sg:postcode":"48342",
    "sg:province":"MI",
    "sg:tags":[
        "apartment",
        "management",
        "complex"
    ],
    "wof:name":"Woodcrest Commons Inc",
    "wof:placetype":"venue"
},
  "geometry": {"coordinates":[-83.27246,42.654927],"type":"Point"}
}