{
  "type": "Feature",
  "properties": {
    "iso:country":"US",
    "sg:address":"11335 Olive St",
    "sg:city":"Warren",
    "sg:classifiers":[
        {
            "category":"Professional",
            "subcategory":"Business Services",
            "type":"Services"
        }
    ],
    "sg:phone":"+1 586 558 8210",
    "sg:postcode":"48093",
    "sg:province":"MI",
    "sg:tags":[
        "embroidery"
    ],
    "wof:name":"Rainbow Images",
    "wof:placetype":"venue"
},
  "geometry": {"coordinates":[-83.012506,42.51779],"type":"Point"}
}