{
  "type": "Feature",
  "properties": {
    "iso:country":"US",
    "sg:address":"115 Bertram Rd",
    "sg:city":"Niles",
    "sg:classifiers":[
        {
            "category":"Building & Trades",
            "subcategory":"Cleaning & Sanitation",
            "type":"Services"
        }
    ],
    "sg:phone":"+1 269 683 2821",
    "sg:postcode":"49120",
    "sg:province":"MI",
    "sg:tags":[
        "maintenance"
    ],
    "wof:name":"A & S Chimney Service",
    "wof:placetype":"venue"
},
  "geometry": {"coordinates":[-86.26355,41.775879],"type":"Point"}
}