{
  "type": "Feature",
  "properties": {
    "iso:country":"US",
    "sg:address":"200 S Washington Ave",
    "sg:city":"Royal Oak",
    "sg:classifiers":[
        {
            "category":"Government",
            "subcategory":"City Hall",
            "type":"Public Place"
        }
    ],
    "sg:phone":"+1 248 547 4000",
    "sg:postcode":"48067",
    "sg:province":"MI",
    "sg:website":"www.royaloakchamber.com",
    "wof:name":"Royal Oak Chamber of Commerce",
    "wof:placetype":"venue"
},
  "geometry": {"coordinates":[-83.14673999999999,42.488865],"type":"Point"}
}