{
  "type": "Feature",
  "properties": {
    "iso:country":"US",
    "sg:address":"650 E Big Beaver Rd",
    "sg:city":"Troy",
    "sg:classifiers":[
        {
            "category":"Health Services",
            "subcategory":"Clinic",
            "type":"Services"
        }
    ],
    "sg:phone":"+1 248 519 1212",
    "sg:postcode":"48083",
    "sg:province":"MI",
    "sg:tags":[
        "counseling",
        "mental"
    ],
    "wof:name":"Woods Connie M Ms Llp",
    "wof:placetype":"venue"
},
  "geometry": {"coordinates":[-83.134598,42.562698],"type":"Point"}
}