{
  "type": "Feature",
  "properties": {
    "iso:country":"US",
    "sg:address":"29600 Fort St",
    "sg:city":"Rockwood",
    "sg:classifiers":[
        {
            "category":"Retail",
            "subcategory":"Auto Repair",
            "type":"Services"
        }
    ],
    "sg:phone":"+1 734 379 3137",
    "sg:postcode":"48173",
    "sg:province":"MI",
    "sg:tags":[
        "general"
    ],
    "wof:name":"Fishers Garage",
    "wof:placetype":"venue"
},
  "geometry": {"coordinates":[-83.230165,42.08864],"type":"Point"}
}