{
  "type": "Feature",
  "properties": {
    "iso:country":"US",
    "sg:address":"5053 Cram Rd",
    "sg:city":"Howell",
    "sg:classifiers":[
        {
            "category":"Professional",
            "subcategory":"Business Services",
            "type":"Services"
        }
    ],
    "sg:phone":"+1 517 545 3187",
    "sg:postcode":"48867",
    "sg:province":"MI",
    "wof:name":"RE Inspection Svcs",
    "wof:placetype":"venue"
},
  "geometry": {"coordinates":[-84.089338,43.073083],"type":"Point"}
}