{
  "type": "Feature",
  "properties": {
    "iso:country":"US",
    "sg:address":"10507 W Willard Rd",
    "sg:city":"Montrose",
    "sg:classifiers":[
        {
            "category":"Social Services",
            "subcategory":"Adult Care",
            "type":"Services"
        }
    ],
    "sg:phone":"+1 810 639 3088",
    "sg:postcode":"48457",
    "sg:province":"MI",
    "sg:tags":[
        "foster"
    ],
    "wof:name":"Sherwood Care Facilities Inc",
    "wof:placetype":"venue"
},
  "geometry": {"coordinates":[-83.90195300000001,43.220549],"type":"Point"}
}