{
  "type": "Feature",
  "properties": {
    "iso:country":"US",
    "sg:address":"509 Michigan Ave",
    "sg:city":"St Louis",
    "sg:classifiers":[
        {
            "category":"Real Estate",
            "subcategory":"Real Estate Agent",
            "type":"Services"
        }
    ],
    "sg:phone":"+1 989 681 2648",
    "sg:postcode":"48880",
    "sg:province":"MI",
    "wof:name":"Euclid Properties Corp",
    "wof:placetype":"venue"
},
  "geometry": {"coordinates":[-84.61193799999999,43.403185],"type":"Point"}
}