{
  "type": "Feature",
  "properties": {
    "iso:country":"US",
    "sg:address":"13660 Stansbury St",
    "sg:city":"Detroit",
    "sg:classifiers":[
        {
            "category":"Organizations",
            "subcategory":"Religious Organization",
            "type":"Services"
        }
    ],
    "sg:phone":"+1 313 836 7732",
    "sg:postcode":"48227",
    "sg:province":"MI",
    "wof:name":"Evangel Echos Church of Air",
    "wof:placetype":"venue"
},
  "geometry": {"coordinates":[-83.182011,42.38773],"type":"Point"}
}