{
  "type": "Feature",
  "properties": {
    "iso:country":"US",
    "sg:address":"20850 Coolidge Hwy",
    "sg:city":"Oak Park",
    "sg:classifiers":[
        {
            "category":"Building & Trades",
            "subcategory":"Cleaning & Sanitation",
            "type":"Services"
        }
    ],
    "sg:phone":"+1 800 773 9969",
    "sg:postcode":"48237",
    "sg:province":"MI",
    "sg:tags":[
        "carpet"
    ],
    "wof:name":"American Carpet Engineering Inc",
    "wof:placetype":"venue"
},
  "geometry": {"coordinates":[-83.180941,42.447103],"type":"Point"}
}