{
  "type": "Feature",
  "properties": {
    "iso:country":"US",
    "sg:address":"1744 Biddle St",
    "sg:city":"Wyandotte",
    "sg:classifiers":[
        {
            "category":"Restaurant",
            "type":"Food & Drink"
        }
    ],
    "sg:phone":"+1 734 283 3530",
    "sg:postcode":"48192",
    "sg:province":"MI",
    "sg:tags":[
        "polish"
    ],
    "sg:website":"polonusrestaurant.com",
    "wof:name":"Polonus Restaurant",
    "wof:placetype":"venue"
},
  "geometry": {"coordinates":[-83.150299,42.216202],"type":"Point"}
}