{
  "type": "Feature",
  "properties": {
    "iso:country":"US",
    "sg:address":"10220 Scott Rd",
    "sg:city":"Freeland",
    "sg:classifiers":[
        {
            "category":"Building & Trades",
            "subcategory":"Construction",
            "type":"Services"
        }
    ],
    "sg:phone":"+1 989 695 5178",
    "sg:postcode":"48623",
    "sg:province":"MI",
    "sg:tags":[
        "house"
    ],
    "wof:name":"Valley Builders",
    "wof:placetype":"venue"
},
  "geometry": {"coordinates":[-84.116851,43.532154],"type":"Point"}
}