{
  "type": "Feature",
  "properties": {
    "iso:country":"US",
    "sg:address":"108 E Main St",
    "sg:city":"Pewamo",
    "sg:classifiers":[
        {
            "category":"Restaurant",
            "type":"Food & Drink"
        }
    ],
    "sg:phone":"+1 989 593 2668",
    "sg:postcode":"48873",
    "sg:province":"MI",
    "wof:name":"Oakwood Lounge",
    "wof:placetype":"venue"
},
  "geometry": {"coordinates":[-84.845867,43.001355],"type":"Point"}
}