{
  "type": "Feature",
  "properties": {
    "iso:country":"US",
    "sg:address":"1581 Haslett Rd",
    "sg:city":"Haslett",
    "sg:classifiers":[
        {
            "category":"Home & Garden",
            "subcategory":"Hardware",
            "type":"Retail Goods"
        }
    ],
    "sg:phone":"+1 517 339 2829",
    "sg:postcode":"48840",
    "sg:province":"MI",
    "wof:name":"Haslett True Value Hardware",
    "wof:placetype":"venue"
},
  "geometry": {"coordinates":[-84.406868,42.747208],"type":"Point"}
}