{
  "type": "Feature",
  "properties": {
    "iso:country":"US",
    "sg:address":"8775 W 9 Mile Rd",
    "sg:city":"Oak Park",
    "sg:classifiers":[
        {
            "category":"Utilities",
            "subcategory":"Mobile Phone",
            "type":"Services"
        }
    ],
    "sg:phone":"+1 248 582 2222",
    "sg:postcode":"48237",
    "sg:province":"MI",
    "sg:tags":[
        "telephone",
        "cellular"
    ],
    "wof:name":"Wireless U Now",
    "wof:placetype":"venue"
},
  "geometry": {"coordinates":[-83.160982,42.460033],"type":"Point"}
}