{
  "type": "Feature",
  "properties": {
    "iso:country":"US",
    "sg:address":"4274 Treat Hwy",
    "sg:city":"Adrian",
    "sg:classifiers":[
        {
            "category":"Retail",
            "subcategory":"Repair Shop",
            "type":"Services"
        }
    ],
    "sg:phone":"+1 517 266 8034",
    "sg:postcode":"49221",
    "sg:province":"MI",
    "wof:name":"Miller Aviation of Michigan",
    "wof:placetype":"venue"
},
  "geometry": {"coordinates":[-84.018254,41.856946],"type":"Point"}
}