{
  "type": "Feature",
  "properties": {
    "iso:country":"US",
    "sg:address":"133 W 14 Mile Rd",
    "sg:city":"Clawson",
    "sg:classifiers":[
        {
            "category":"Shopping",
            "subcategory":"Florist",
            "type":"Retail Goods"
        }
    ],
    "sg:phone":"+1 248 288 7670",
    "sg:postcode":"48017",
    "sg:province":"MI",
    "wof:name":"Fougnie Floral",
    "wof:placetype":"venue"
},
  "geometry": {"coordinates":[-83.148715,42.533258],"type":"Point"}
}