{
  "type": "Feature",
  "properties": {
    "iso:country":"US",
    "sg:address":"5119 Highland Rd",
    "sg:city":"Waterford",
    "sg:classifiers":[
        {
            "category":"Real Estate",
            "subcategory":"Real Estate Agent",
            "type":"Services"
        }
    ],
    "sg:phone":"+1 248 736 3000",
    "sg:postcode":"48327",
    "sg:province":"MI",
    "sg:tags":[
        "residential",
        "commercial"
    ],
    "wof:name":"Amerivest",
    "wof:placetype":"venue"
},
  "geometry": {"coordinates":[-83.387902,42.660209],"type":"Point"}
}