{
  "type": "Feature",
  "properties": {
    "iso:country":"US",
    "sg:address":"201 W Bluff St",
    "sg:city":"Marquette",
    "sg:classifiers":[
        {
            "category":"Professional",
            "subcategory":"Accounting & Tax Preparation",
            "type":"Services"
        }
    ],
    "sg:phone":"+1 906 228 3600",
    "sg:postcode":"49855",
    "sg:province":"MI",
    "sg:tags":[
        "accountant"
    ],
    "sg:website":"www.mthn.com",
    "wof:name":"Makela Toutant Hill & Nardi",
    "wof:placetype":"venue"
},
  "geometry": {"coordinates":[-87.39729199999999,46.544869],"type":"Point"}
}