{
  "type": "Feature",
  "properties": {
    "iso:country":"US",
    "sg:address":"2370 Danforth St",
    "sg:city":"Detroit",
    "sg:classifiers":[
        {
            "category":"Professional",
            "type":"Services"
        }
    ],
    "sg:phone":"+1 313 872 5948",
    "sg:postcode":"48212",
    "sg:province":"MI",
    "wof:name":"Quazi Brothers",
    "wof:placetype":"venue"
},
  "geometry": {"coordinates":[-83.054328,42.388932],"type":"Point"}
}