{
  "type": "Feature",
  "properties": {
    "iso:country":"US",
    "sg:address":"3535 Forest Rd",
    "sg:city":"Lansing",
    "sg:classifiers":[
        {
            "category":"Education",
            "subcategory":"Special Training",
            "type":"Public Place"
        }
    ],
    "sg:phone":"+1 517 355 7603",
    "sg:postcode":"48910",
    "sg:province":"MI",
    "wof:name":"Weekend MBA Program",
    "wof:placetype":"venue"
},
  "geometry": {"coordinates":[-84.504057,42.704609],"type":"Point"}
}