{
  "type": "Feature",
  "properties": {
    "iso:country":"US",
    "sg:address":"26081 Hoover Rd",
    "sg:city":"Warren",
    "sg:classifiers":[
        {
            "category":"Shopping",
            "subcategory":"Pharmacy",
            "type":"Retail Goods"
        }
    ],
    "sg:phone":"+1 586 754 7080",
    "sg:postcode":"48089",
    "sg:province":"MI",
    "sg:tags":[
        "drugstore"
    ],
    "wof:name":"Cvs Pharmacy",
    "wof:placetype":"venue"
},
  "geometry": {"coordinates":[-83.006522,42.485791],"type":"Point"}
}