{
  "type": "Feature",
  "properties": {
    "iso:country":"US",
    "sg:address":"23100 Providence Dr",
    "sg:city":"Southfield",
    "sg:classifiers":[
        {
            "category":"Professional",
            "subcategory":"Lawyer & Legal Services",
            "type":"Services"
        }
    ],
    "sg:phone":"+1 248 539 7400",
    "sg:postcode":"48075",
    "sg:province":"MI",
    "sg:tags":[
        "attorney"
    ],
    "sg:website":"www.pmspc.com",
    "wof:name":"Peter M Schneiderman & Assoc",
    "wof:placetype":"venue"
},
  "geometry": {"coordinates":[-83.20684300000001,42.459994],"type":"Point"}
}