{
  "type": "Feature",
  "properties": {
    "iso:country":"US",
    "sg:address":"122 S Lafayette St",
    "sg:city":"Greenville",
    "sg:classifiers":[
        {
            "category":"Retail",
            "subcategory":"Portrait Studio",
            "type":"Services"
        }
    ],
    "sg:phone":"+1 616 754 1665",
    "sg:postcode":"48838",
    "sg:province":"MI",
    "sg:tags":[
        "photography"
    ],
    "wof:name":"Leonard's Photography",
    "wof:placetype":"venue"
},
  "geometry": {"coordinates":[-85.253062,43.180439],"type":"Point"}
}