{
  "type": "Feature",
  "properties": {
    "iso:country":"US",
    "sg:address":"26638 Telegraph Rd",
    "sg:city":"Flat Rock",
    "sg:classifiers":[
        {
            "category":"Personal",
            "subcategory":"Beauty Salon",
            "type":"Services"
        }
    ],
    "sg:phone":"+1 734 782 9656",
    "sg:postcode":"48134",
    "sg:province":"MI",
    "sg:tags":[
        "shop"
    ],
    "wof:name":"Hair Classics Ltd",
    "wof:placetype":"venue"
},
  "geometry": {"coordinates":[-83.28521499999999,42.109556],"type":"Point"}
}