{
  "type": "Feature",
  "properties": {
    "iso:country":"US",
    "sg:address":"7170 Simons St",
    "sg:city":"Lexington",
    "sg:classifiers":[
        {
            "category":"Building & Trades",
            "subcategory":"Construction",
            "type":"Services"
        }
    ],
    "sg:phone":"+1 810 359 8428",
    "sg:postcode":"48450",
    "sg:province":"MI",
    "sg:tags":[
        "home",
        "improvement"
    ],
    "wof:name":"Mc Callister Enterprises",
    "wof:placetype":"venue"
},
  "geometry": {"coordinates":[-82.531864,43.269335],"type":"Point"}
}