{
  "type": "Feature",
  "properties": {
    "iso:country":"US",
    "sg:address":"20051 Stamford Dr",
    "sg:city":"Livonia",
    "sg:classifiers":[
        {
            "category":"Manufacturing",
            "subcategory":"Rubber & Plastics",
            "type":"Manufacturing & Wholesale Goods"
        }
    ],
    "sg:phone":"+1 248 442 9380",
    "sg:postcode":"48152",
    "sg:province":"MI",
    "sg:tags":[
        "product",
        "mfg"
    ],
    "wof:name":"Avery Dennison Corporation",
    "wof:placetype":"venue"
},
  "geometry": {"coordinates":[-83.37809,42.432172],"type":"Point"}
}