{
  "type": "Feature",
  "properties": {
    "iso:country":"US",
    "sg:address":"3243 N 10th St",
    "sg:city":"Kalamazoo",
    "sg:classifiers":[
        {
            "category":"Manufacturing",
            "subcategory":"Tools & Machinery",
            "type":"Manufacturing & Wholesale Goods"
        }
    ],
    "sg:phone":"+1 269 375 0981",
    "sg:postcode":"49009",
    "sg:province":"MI",
    "sg:tags":[
        "trucking"
    ],
    "wof:name":"Cargo Transfer Inc",
    "wof:placetype":"venue"
},
  "geometry": {"coordinates":[-85.667795,42.324508],"type":"Point"}
}