{
  "type": "Feature",
  "properties": {
    "iso:country":"US",
    "sg:address":"19650 Cherry Hill St",
    "sg:city":"Southfield",
    "sg:classifiers":[
        {
            "category":"Health Services",
            "subcategory":"Doctor",
            "type":"Services"
        }
    ],
    "sg:phone":"+1 734 398 7899",
    "sg:postcode":"48076",
    "sg:province":"MI",
    "wof:name":"Ilsing Wendy MD",
    "wof:placetype":"venue"
},
  "geometry": {"coordinates":[-83.239064,42.509877],"type":"Point"}
}