{
  "type": "Feature",
  "properties": {
    "iso:country":"US",
    "sg:address":"4161 Madison Ave SE",
    "sg:city":"Wyoming",
    "sg:classifiers":[
        {
            "category":"Building & Trades",
            "subcategory":"Construction",
            "type":"Services"
        }
    ],
    "sg:phone":"+1 616 534 6000",
    "sg:postcode":"49548",
    "sg:province":"MI",
    "sg:tags":[
        "roofing",
        "contractor"
    ],
    "wof:name":"Otten's Custom Roofing Inc",
    "wof:placetype":"venue"
},
  "geometry": {"coordinates":[-85.65564999999999,42.887015],"type":"Point"}
}