{
  "type": "Feature",
  "properties": {
    "iso:country":"US",
    "sg:address":"742 E Roosevelt Rd",
    "sg:city":"Ashley",
    "sg:classifiers":[
        {
            "category":"Retail",
            "subcategory":"Repair Shop",
            "type":"Services"
        }
    ],
    "sg:phone":"+1 989 838 4483",
    "sg:postcode":"48806",
    "sg:province":"MI",
    "sg:tags":[
        "farm",
        "equipment",
        "parts"
    ],
    "wof:name":"Ken's Farm Shop",
    "wof:placetype":"venue"
},
  "geometry": {"coordinates":[-84.58900199999999,43.161332],"type":"Point"}
}