{
  "type": "Feature",
  "properties": {
    "iso:country":"US",
    "sg:address":"5255 Davis Rd",
    "sg:city":"Saginaw",
    "sg:classifiers":[
        {
            "category":"Professional",
            "subcategory":"Lawyer & Legal Services",
            "type":"Services"
        }
    ],
    "sg:phone":"+1 989 793 5080",
    "sg:postcode":"48604",
    "sg:province":"MI",
    "sg:tags":[
        "attorney"
    ],
    "wof:name":"Dwan Law Offices",
    "wof:placetype":"venue"
},
  "geometry": {"coordinates":[-83.95676400000001,43.482385],"type":"Point"}
}