{
  "type": "Feature",
  "properties": {
    "iso:country":"US",
    "sg:address":"46611 Darwood Ct",
    "sg:city":"Plymouth",
    "sg:classifiers":[
        {
            "category":"Professional",
            "subcategory":"Computer Services",
            "type":"Services"
        }
    ],
    "sg:phone":"+1 734 454 9010",
    "sg:postcode":"48170",
    "sg:province":"MI",
    "sg:tags":[
        "related",
        "programing",
        "custom"
    ],
    "wof:name":"Computer Solutions Inc",
    "wof:placetype":"venue"
},
  "geometry": {"coordinates":[-83.501588,42.363268],"type":"Point"}
}