{
  "type": "Feature",
  "properties": {
    "iso:country":"US",
    "sg:address":"4904 Elmgate Dr",
    "sg:city":"West Bloomfield",
    "sg:classifiers":[
        {
            "category":"Professional",
            "type":"Services"
        }
    ],
    "sg:phone":"+1 248 706 1425",
    "sg:postcode":"48324",
    "sg:province":"MI",
    "wof:name":"Class Chauffered Svc",
    "wof:placetype":"venue"
},
  "geometry": {"coordinates":[-83.38348999999999,42.582711],"type":"Point"}
}