{
  "type": "Feature",
  "properties": {
    "iso:country":"US",
    "sg:address":"10250 Tuttle Hill Rd",
    "sg:city":"Willis",
    "sg:phone":"+1 734 461 1655",
    "sg:postcode":"48191",
    "sg:province":"MI",
    "sg:tags":[
        "farm",
        "corn",
        "soybean"
    ],
    "wof:name":"Dj Farms",
    "wof:placetype":"venue"
},
  "geometry": {"coordinates":[-83.58837800000001,42.141159],"type":"Point"}
}