{
  "type": "Feature",
  "properties": {
    "iso:country":"US",
    "sg:address":"421 14th St",
    "sg:city":"Three Rivers",
    "sg:classifiers":[
        {
            "category":"Freight",
            "type":"Transportation"
        }
    ],
    "sg:phone":"+1 269 273 2779",
    "sg:postcode":"49093",
    "sg:province":"MI",
    "sg:tags":[
        "general"
    ],
    "wof:name":"Three Rivers Storage Center",
    "wof:placetype":"venue"
},
  "geometry": {"coordinates":[-85.617436,41.939829],"type":"Point"}
}