{
  "type": "Feature",
  "properties": {
    "iso:country":"US",
    "sg:address":"15107 Ardmore St",
    "sg:city":"Detroit",
    "sg:classifiers":[
        {
            "category":"Building & Trades",
            "subcategory":"Plumbing",
            "type":"Services"
        }
    ],
    "sg:phone":"+1 313 836 8058",
    "sg:postcode":"48227",
    "sg:province":"MI",
    "sg:tags":[
        "contractor"
    ],
    "wof:name":"Fortunes Heating & Cooling",
    "wof:placetype":"venue"
},
  "geometry": {"coordinates":[-83.184575,42.401152],"type":"Point"}
}