{
  "type": "Feature",
  "properties": {
    "iso:country":"US",
    "sg:address":"16801 Newburgh Rd",
    "sg:city":"Livonia",
    "sg:classifiers":[
        {
            "category":"Banks & Credit Unions",
            "subcategory":"Financial Services",
            "type":"Services"
        }
    ],
    "sg:phone":"+1 734 432 2030",
    "sg:postcode":"48154",
    "sg:province":"MI",
    "sg:tags":[
        "broker",
        "mortgage"
    ],
    "wof:name":"Vista Mortgage",
    "wof:placetype":"venue"
},
  "geometry": {"coordinates":[-83.41330000000001,42.4086],"type":"Point"}
}