{
  "type": "Feature",
  "properties": {
    "iso:country":"US",
    "sg:address":"10031 Mercedes",
    "sg:city":"Redford",
    "sg:classifiers":[
        {
            "category":"Professional",
            "subcategory":"Advertising",
            "type":"Services"
        }
    ],
    "sg:phone":"+1 313 937 0621",
    "sg:postcode":"48239",
    "sg:province":"MI",
    "wof:name":"Travel With K",
    "wof:placetype":"venue"
},
  "geometry": {"coordinates":[-83.31117999999999,42.367143],"type":"Point"}
}