{
  "type": "Feature",
  "properties": {
    "iso:country":"US",
    "sg:address":"4250 Normandy Ct",
    "sg:city":"Royal Oak",
    "sg:classifiers":[
        {
            "category":"Wholesale",
            "subcategory":"Machinery & Supplies",
            "type":"Manufacturing & Wholesale Goods"
        }
    ],
    "sg:phone":"+1 248 549 3350",
    "sg:postcode":"48073",
    "sg:province":"MI",
    "sg:tags":[
        "salon",
        "cosmetic",
        "beauty"
    ],
    "wof:name":"Richard Ravid Inc",
    "wof:placetype":"venue"
},
  "geometry": {"coordinates":[-83.18090100000001,42.526199],"type":"Point"}
}