{
  "type": "Feature",
  "properties": {
    "iso:country":"US",
    "sg:address":"208 N Main St",
    "sg:city":"Davison",
    "sg:classifiers":[
        {
            "category":"Shopping",
            "subcategory":"Stationery & Office Supplies",
            "type":"Retail Goods"
        }
    ],
    "sg:phone":"+1 810 658 1551",
    "sg:postcode":"48423",
    "sg:province":"MI",
    "sg:tags":[
        "equipment"
    ],
    "sg:website":"www.davisonoffice.com",
    "wof:name":"Davison Office Products",
    "wof:placetype":"venue"
},
  "geometry": {"coordinates":[-83.51660200000001,43.030998],"type":"Point"}
}