{
  "type": "Feature",
  "properties": {
    "iso:country":"US",
    "sg:address":"475 S Water St",
    "sg:city":"Marine City",
    "sg:classifiers":[
        {
            "category":"Restaurant",
            "type":"Food & Drink"
        }
    ],
    "sg:phone":"+1 810 765 9030",
    "sg:postcode":"48039",
    "sg:province":"MI",
    "wof:name":"Riviera Restaurant & Cocktail",
    "wof:placetype":"venue"
},
  "geometry": {"coordinates":[-82.492794,42.714791],"type":"Point"}
}