{
  "type": "Feature",
  "properties": {
    "iso:country":"US",
    "sg:address":"22832 Detour St",
    "sg:city":"Saint Clair Shores",
    "sg:classifiers":[
        {
            "category":"Communications",
            "subcategory":"Film & Video Production",
            "type":"Services"
        }
    ],
    "sg:phone":"+1 586 294 7912",
    "sg:postcode":"48082",
    "sg:province":"MI",
    "sg:tags":[
        "motion"
    ],
    "wof:name":"Filmlab Video Productions",
    "wof:placetype":"venue"
},
  "geometry": {"coordinates":[-82.887241,42.530369],"type":"Point"}
}