{
  "type": "Feature",
  "properties": {
    "iso:country":"US",
    "sg:address":"808 Terrace St",
    "sg:city":"Muskegon",
    "sg:classifiers":[
        {
            "category":"Organizations",
            "subcategory":"Non-profit Organization",
            "type":"Services"
        }
    ],
    "sg:phone":"+1 231 722 0345",
    "sg:postcode":"49440",
    "sg:province":"MI",
    "wof:name":"Optitions Assoc Of Michigan",
    "wof:placetype":"venue"
},
  "geometry": {"coordinates":[-86.24715399999999,43.237613],"type":"Point"}
}