{
  "type": "Feature",
  "properties": {
    "iso:country":"US",
    "sg:address":"6435 Davis Hwy",
    "sg:city":"Grand Ledge",
    "sg:classifiers":[
        {
            "category":"Wholesale",
            "subcategory":"Fruits & Vegetables",
            "type":"Manufacturing & Wholesale Goods"
        }
    ],
    "sg:phone":"+1 517 627 8457",
    "sg:postcode":"48837",
    "sg:province":"MI",
    "wof:name":"C & M Produce LTD",
    "wof:placetype":"venue"
},
  "geometry": {"coordinates":[-84.71714799999999,42.682865],"type":"Point"}
}