{
  "type": "Feature",
  "properties": {
    "iso:country":"US",
    "sg:address":"12677 S 36th St",
    "sg:city":"Vicksburg",
    "sg:classifiers":[
        {
            "category":"Building & Trades",
            "subcategory":"Construction",
            "type":"Services"
        }
    ],
    "sg:phone":"+1 269 649 4208",
    "sg:postcode":"49097",
    "sg:province":"MI",
    "sg:tags":[
        "contractor"
    ],
    "wof:name":"Parker's Subcontracting Svc",
    "wof:placetype":"venue"
},
  "geometry": {"coordinates":[-85.412114,42.142249],"type":"Point"}
}