{
  "type": "Feature",
  "properties": {
    "iso:country":"US",
    "sg:address":"239 E Michigan Ave",
    "sg:city":"Paw Paw",
    "sg:classifiers":[
        {
            "category":"Professional",
            "subcategory":"Business Services",
            "type":"Services"
        }
    ],
    "sg:phone":"+1 269 657 8080",
    "sg:postcode":"49079",
    "sg:province":"MI",
    "wof:name":"UPS Store",
    "wof:placetype":"venue"
},
  "geometry": {"coordinates":[-85.890421,42.217696],"type":"Point"}
}