{
  "type": "Feature",
  "properties": {
    "iso:country":"US",
    "sg:address":"5557 Tadworth Pl",
    "sg:city":"West Bloomfield",
    "sg:classifiers":[
        {
            "category":"Health Services",
            "subcategory":"Doctor",
            "type":"Services"
        }
    ],
    "sg:phone":"+1 248 737 0802",
    "sg:postcode":"48322",
    "sg:province":"MI",
    "sg:tags":[
        "podiatrist"
    ],
    "wof:name":"Wolf Cary S DPM",
    "wof:placetype":"venue"
},
  "geometry": {"coordinates":[-83.353798,42.530998],"type":"Point"}
}