{
  "type": "Feature",
  "properties": {
    "iso:country":"US",
    "sg:address":"2285 N Opdyke Rd",
    "sg:city":"Auburn Hills",
    "sg:classifiers":[
        {
            "category":"Professional",
            "subcategory":"Detective & Security Services",
            "type":"Services"
        },
        {
            "category":"Wholesale",
            "subcategory":"Electrical",
            "type":"Manufacturing & Wholesale Goods"
        }
    ],
    "sg:phone":"+1 248 373 3778",
    "sg:postcode":"48326",
    "sg:province":"MI",
    "sg:tags":[
        "control",
        "system"
    ],
    "sg:website":"www.lvctechnologies.com",
    "wof:name":"Lvc Technologies Inc",
    "wof:placetype":"venue"
},
  "geometry": {"coordinates":[-83.245994,42.675045],"type":"Point"}
}