{
  "type": "Feature",
  "properties": {
    "iso:country":"US",
    "sg:address":"22882 Orchard Lake Rd",
    "sg:city":"Farmington",
    "sg:classifiers":[
        {
            "category":"Wholesale",
            "subcategory":"Medical Equipment & Supplies",
            "type":"Manufacturing & Wholesale Goods"
        }
    ],
    "sg:phone":"+1 248 427 9657",
    "sg:postcode":"48336",
    "sg:province":"MI",
    "sg:tags":[
        "hospital"
    ],
    "wof:name":"Medical Equipment Inc",
    "wof:placetype":"venue"
},
  "geometry": {"coordinates":[-83.35651,42.458551],"type":"Point"}
}