{
  "type": "Feature",
  "properties": {
    "iso:country":"US",
    "sg:address":"702 W Corunna Ave",
    "sg:city":"Corunna",
    "sg:classifiers":[
        {
            "category":"Organizations",
            "subcategory":"Professional Association",
            "type":"Services"
        }
    ],
    "sg:phone":"+1 989 743 6227",
    "sg:postcode":"48817",
    "sg:province":"MI",
    "wof:name":"American Red Cross",
    "wof:placetype":"venue"
},
  "geometry": {"coordinates":[-84.131733,42.983383],"type":"Point"}
}