{
  "type": "Feature",
  "properties": {
    "iso:country":"US",
    "sg:address":"35135 Grand River Ave",
    "sg:city":"Farmington Hills",
    "sg:classifiers":[
        {
            "category":"Restaurant",
            "type":"Food & Drink"
        }
    ],
    "sg:phone":"+1 248 476 9181",
    "sg:postcode":"48335",
    "sg:province":"MI",
    "wof:name":"Great Wall Of China",
    "wof:placetype":"venue"
},
  "geometry": {"coordinates":[-83.395408,42.468979],"type":"Point"}
}