{
  "type": "Feature",
  "properties": {
    "iso:country":"US",
    "sg:address":"6259 Norton Center Dr",
    "sg:city":"Muskegon",
    "sg:classifiers":[
        {
            "category":"Manufacturing",
            "subcategory":"Rubber & Plastics",
            "type":"Manufacturing & Wholesale Goods"
        }
    ],
    "sg:phone":"+1 231 798 7935",
    "sg:postcode":"49441",
    "sg:province":"MI",
    "sg:website":"www.pliantplastics.com",
    "wof:name":"Pliant Plastics Corp",
    "wof:placetype":"venue"
},
  "geometry": {"coordinates":[-86.217992,43.137221],"type":"Point"}
}