{
  "type": "Feature",
  "properties": {
    "iso:country":"US",
    "sg:address":"23365 Woodward Ave",
    "sg:city":"Ferndale",
    "sg:classifiers":[
        {
            "category":"Home & Garden",
            "subcategory":"Household Appliances",
            "type":"Retail Goods"
        }
    ],
    "sg:phone":"+1 248 545 2600",
    "sg:postcode":"48220",
    "sg:province":"MI",
    "sg:tags":[
        "repair"
    ],
    "wof:name":"Witbeck Household Appliances & Electronics",
    "wof:placetype":"venue"
},
  "geometry": {"coordinates":[-83.13870199999999,42.466],"type":"Point"}
}