{
  "type": "Feature",
  "properties": {
    "iso:country":"US",
    "sg:address":"8335 Church St",
    "sg:city":"Fenwick",
    "sg:classifiers":[
        {
            "category":"Social Services",
            "subcategory":"Adult Care",
            "type":"Services"
        }
    ],
    "sg:phone":"+1 989 637 4730",
    "sg:postcode":"48834",
    "sg:province":"MI",
    "sg:tags":[
        "foster"
    ],
    "wof:name":"Humes Family Home",
    "wof:placetype":"venue"
},
  "geometry": {"coordinates":[-84.98384299999999,43.110859],"type":"Point"}
}