{
  "type": "Feature",
  "properties": {
    "iso:country":"US",
    "sg:address":"399 Tiffany Shores Dr",
    "sg:city":"Holland",
    "sg:classifiers":[
        {
            "category":"Building & Trades",
            "subcategory":"Construction",
            "type":"Services"
        }
    ],
    "sg:phone":"+1 616 399 0923",
    "sg:postcode":"49424",
    "sg:province":"MI",
    "sg:tags":[
        "general",
        "contractor"
    ],
    "wof:name":"Timberstone Builders",
    "wof:placetype":"venue"
},
  "geometry": {"coordinates":[-86.18374300000001,42.805435],"type":"Point"}
}