{
  "type": "Feature",
  "properties": {
    "iso:country":"US",
    "sg:address":"1668 W Hibbard Rd",
    "sg:city":"Owosso",
    "sg:classifiers":[
        {
            "category":"Health Services",
            "subcategory":"Nursing And Care Facility",
            "type":"Services"
        }
    ],
    "sg:phone":"+1 989 723 6577",
    "sg:postcode":"48867",
    "sg:province":"MI",
    "sg:tags":[
        "adult"
    ],
    "wof:name":"Country View Adult Foster Care",
    "wof:placetype":"venue"
},
  "geometry": {"coordinates":[-84.198121,42.954164],"type":"Point"}
}