{
  "type": "Feature",
  "properties": {
    "iso:country":"US",
    "sg:address":"23556 Plymouth Rd",
    "sg:city":"Redford",
    "sg:classifiers":[
        {
            "category":"Bakery",
            "type":"Food & Drink"
        }
    ],
    "sg:phone":"+1 313 532 6527",
    "sg:postcode":"48239",
    "sg:province":"MI",
    "wof:name":"Francis Discount Food Market",
    "wof:placetype":"venue"
},
  "geometry": {"coordinates":[-83.27159899999999,42.371498],"type":"Point"}
}