{
  "type": "Feature",
  "properties": {
    "iso:country":"US",
    "sg:address":"11189 E Cd Ave",
    "sg:city":"Richland",
    "sg:classifiers":[
        {
            "category":"Professional",
            "type":"Services"
        }
    ],
    "sg:phone":"+1 269 629 0800",
    "sg:postcode":"49083",
    "sg:province":"MI",
    "wof:name":"Michael Kifer",
    "wof:placetype":"venue"
},
  "geometry": {"coordinates":[-85.407191,42.383904],"type":"Point"}
}