{
  "type": "Feature",
  "properties": {
    "iso:country":"US",
    "sg:address":"1899 Dracka Rd",
    "sg:city":"Traverse City",
    "sg:classifiers":[
        {
            "category":"Health Services",
            "subcategory":"Nursing And Care Facility",
            "type":"Services"
        }
    ],
    "sg:phone":"+1 231 946 2999",
    "sg:postcode":"49684",
    "sg:province":"MI",
    "sg:tags":[
        "home",
        "retirement",
        "community"
    ],
    "wof:name":"Traverse Manor Retirement Ctr",
    "wof:placetype":"venue"
},
  "geometry": {"coordinates":[-85.636056,44.71344],"type":"Point"}
}