{
  "type": "Feature",
  "properties": {
    "iso:country":"US",
    "sg:address":"4154 Van Slyke Rd",
    "sg:city":"Flint",
    "sg:classifiers":[
        {
            "category":"Real Estate",
            "subcategory":"Real Estate Operator",
            "type":"Services"
        }
    ],
    "sg:phone":"+1 810 767 0600",
    "sg:postcode":"48507",
    "sg:province":"MI",
    "sg:tags":[
        "building",
        "nonresidential"
    ],
    "wof:name":"Fisher Hall",
    "wof:placetype":"venue"
},
  "geometry": {"coordinates":[-83.712682,42.968435],"type":"Point"}
}