{
  "type": "Feature",
  "properties": {
    "iso:country":"US",
    "sg:address":"14530 Pearson St",
    "sg:city":"Oak Park",
    "sg:classifiers":[
        {
            "category":"Social Services",
            "subcategory":"Child Care",
            "type":"Services"
        }
    ],
    "sg:phone":"+1 248 691 4225",
    "sg:postcode":"48237",
    "sg:province":"MI",
    "wof:name":"Toddler Tech Child Care & Dev",
    "wof:placetype":"venue"
},
  "geometry": {"coordinates":[-83.19332300000001,42.454742],"type":"Point"}
}