{
  "type": "Feature",
  "properties": {
    "iso:country":"US",
    "sg:address":"51192 Milano Dr",
    "sg:city":"Macomb",
    "sg:classifiers":[
        {
            "category":"Retail",
            "subcategory":"Laundry & Dry Cleaning",
            "type":"Services"
        },
        {
            "category":"Building & Trades",
            "subcategory":"Cleaning & Sanitation",
            "type":"Services"
        }
    ],
    "sg:phone":"+1 586 992 8136",
    "sg:postcode":"48042",
    "sg:province":"MI",
    "sg:tags":[
        "cleaner",
        "upholstery",
        "rug",
        "carpet"
    ],
    "wof:name":"Rainbow Carpet and Restoration",
    "wof:placetype":"venue"
},
  "geometry": {"coordinates":[-82.966443,42.672188],"type":"Point"}
}