{
  "type": "Feature",
  "properties": {
    "iso:country":"US",
    "sg:address":"6340 E 14 Mile Rd",
    "sg:city":"Warren",
    "sg:classifiers":[
        {
            "category":"Home & Garden",
            "subcategory":"Furniture",
            "type":"Retail Goods"
        }
    ],
    "sg:phone":"+1 586 826 9450",
    "sg:postcode":"48092",
    "sg:province":"MI",
    "sg:tags":[
        "store"
    ],
    "wof:name":"Furniture Express",
    "wof:placetype":"venue"
},
  "geometry": {"coordinates":[-83.043297,42.536201],"type":"Point"}
}