{
  "type": "Feature",
  "properties": {
    "iso:country":"US",
    "sg:address":"110 School St",
    "sg:city":"Harbor Beach",
    "sg:classifiers":[
        {
            "category":"Government",
            "subcategory":"Post Office",
            "type":"Public Place"
        }
    ],
    "sg:phone":"+1 989 479 3429",
    "sg:postcode":"48441",
    "sg:province":"MI",
    "sg:tags":[
        "postal",
        "us"
    ],
    "wof:name":"US Post Office",
    "wof:placetype":"venue"
},
  "geometry": {"coordinates":[-82.65191900000001,43.847299],"type":"Point"}
}