{
  "type": "Feature",
  "properties": {
    "iso:country":"US",
    "sg:address":"4528 Wilkshire Ave SW",
    "sg:city":"Grand Rapids",
    "sg:classifiers":[
        {
            "category":"Social Services",
            "subcategory":"Child Care",
            "type":"Services"
        }
    ],
    "sg:phone":"+1 616 531 9215",
    "sg:postcode":"49548",
    "sg:province":"MI",
    "sg:tags":[
        "day"
    ],
    "wof:name":"Kids Retreat",
    "wof:placetype":"venue"
},
  "geometry": {"coordinates":[-85.66576000000001,42.881123],"type":"Point"}
}