{
  "type": "Feature",
  "properties": {
    "iso:country":"US",
    "sg:address":"211 N Bridge St",
    "sg:city":"Bellaire",
    "sg:classifiers":[
        {
            "category":"Health Services",
            "subcategory":"Optometrist",
            "type":"Services"
        }
    ],
    "sg:phone":"+1 231 533 6283",
    "sg:postcode":"49615",
    "sg:province":"MI",
    "wof:name":"Bellaire Eye Ctr",
    "wof:placetype":"venue"
},
  "geometry": {"coordinates":[-85.210075,44.977152],"type":"Point"}
}