{
  "type": "Feature",
  "properties": {
    "iso:country":"US",
    "sg:address":"12227 Sandborn Rd",
    "sg:city":"Portland",
    "sg:classifiers":[
        {
            "category":"Sports & Exercise",
            "subcategory":"Golf",
            "type":"Entertainment"
        }
    ],
    "sg:phone":"+1 517 647 1984",
    "sg:postcode":"48875",
    "sg:province":"MI",
    "sg:tags":[
        "course"
    ],
    "sg:website":"www.willowwoodcountryclub.com",
    "wof:name":"Willow Wood Country Club",
    "wof:placetype":"venue"
},
  "geometry": {"coordinates":[-84.886083,42.811946],"type":"Point"}
}