{
  "type": "Feature",
  "properties": {
    "iso:country":"US",
    "sg:address":"3330 Elderwood Ave",
    "sg:city":"Holland",
    "sg:classifiers":[
        {
            "category":"Professional",
            "subcategory":"Computer Services",
            "type":"Services"
        }
    ],
    "sg:phone":"+1 616 399 4902",
    "sg:postcode":"49424",
    "sg:province":"MI",
    "sg:tags":[
        "consultant",
        "designer"
    ],
    "wof:name":"Northstar Solutions Inc",
    "wof:placetype":"venue"
},
  "geometry": {"coordinates":[-86.20342599999999,42.827255],"type":"Point"}
}