{
  "type": "Feature",
  "properties": {
    "iso:country":"US",
    "sg:address":"2740 E Lansing Dr",
    "sg:city":"East Lansing",
    "sg:classifiers":[
        {
            "category":"Professional",
            "type":"Services"
        }
    ],
    "sg:phone":"+1 517 333 6915",
    "sg:postcode":"48823",
    "sg:province":"MI",
    "sg:tags":[
        "establishment"
    ],
    "wof:name":"PSP-Twa",
    "wof:placetype":"venue"
},
  "geometry": {"coordinates":[-84.450682,42.749612],"type":"Point"}
}