{
  "type": "Feature",
  "properties": {
    "iso:country":"US",
    "sg:address":"1955 Allen Rd",
    "sg:city":"Smiths Creek",
    "sg:classifiers":[
        {
            "category":"Education",
            "subcategory":"Library",
            "type":"Public Place"
        }
    ],
    "sg:phone":"+1 810 982 9171",
    "sg:postcode":"48074",
    "sg:province":"MI",
    "wof:name":"Campbell G Lynn Branch Library",
    "wof:placetype":"venue"
},
  "geometry": {"coordinates":[-82.522645,42.954765],"type":"Point"}
}