{
  "type": "Feature",
  "properties": {
    "iso:country":"US",
    "sg:address":"205 E Congress St",
    "sg:city":"Sturgis",
    "sg:classifiers":[
        {
            "category":"Retail",
            "subcategory":"Repair Shop",
            "type":"Services"
        }
    ],
    "sg:phone":"+1 269 651 2817",
    "sg:postcode":"49091",
    "sg:province":"MI",
    "wof:name":"Dougs Rod & Reel Repair",
    "wof:placetype":"venue"
},
  "geometry": {"coordinates":[-85.416884,41.796646],"type":"Point"}
}