{
  "type": "Feature",
  "properties": {
    "iso:country":"US",
    "sg:address":"27500 Novi Rd",
    "sg:city":"Novi",
    "sg:classifiers":[
        {
            "category":"Shopping",
            "type":"Retail Goods"
        }
    ],
    "sg:phone":"+1 248 735 3973",
    "sg:postcode":"48377",
    "sg:province":"MI",
    "sg:tags":[
        "telephone",
        "cellular"
    ],
    "wof:name":"Verizon Wireless",
    "wof:placetype":"venue"
},
  "geometry": {"coordinates":[-83.47605299999999,42.493275],"type":"Point"}
}