{
  "type": "Feature",
  "properties": {
    "iso:country":"US",
    "sg:address":"3119 Aurelius Rd",
    "sg:city":"Lansing",
    "sg:classifiers":[
        {
            "category":"Professional",
            "subcategory":"Management & Consulting",
            "type":"Services"
        }
    ],
    "sg:phone":"+1 517 272 6923",
    "sg:postcode":"48910",
    "sg:province":"MI",
    "wof:name":"Cheek To Cheek Baby Essentials",
    "wof:placetype":"venue"
},
  "geometry": {"coordinates":[-84.52329400000001,42.699617],"type":"Point"}
}