{
  "type": "Feature",
  "properties": {
    "iso:country":"US",
    "sg:address":"25340 Mc Allister St",
    "sg:city":"Southfield",
    "sg:classifiers":[
        {
            "category":"Professional",
            "type":"Services"
        }
    ],
    "sg:phone":"+1 248 350 3028",
    "sg:postcode":"48034",
    "sg:province":"MI",
    "wof:name":"Courgette Services Corp",
    "wof:placetype":"venue"
},
  "geometry": {"coordinates":[-83.295609,42.476364],"type":"Point"}
}