{
  "type": "Feature",
  "properties": {
    "iso:country":"US",
    "sg:address":"32117 Plymouth Rd",
    "sg:city":"Livonia",
    "sg:classifiers":[
        {
            "category":"Professional",
            "subcategory":"Advertising",
            "type":"Services"
        }
    ],
    "sg:phone":"+1 734 522 6884",
    "sg:postcode":"48150",
    "sg:province":"MI",
    "sg:tags":[
        "mail",
        "direct"
    ],
    "wof:name":"J&M Advertising",
    "wof:placetype":"venue"
},
  "geometry": {"coordinates":[-83.36100500000001,42.368424],"type":"Point"}
}