{
  "type": "Feature",
  "properties": {
    "iso:country":"US",
    "sg:address":"4777 Hillandale Rd",
    "sg:city":"Sodus",
    "sg:classifiers":[
        {
            "category":"Manufacturing",
            "subcategory":"Tools & Machinery",
            "type":"Manufacturing & Wholesale Goods"
        }
    ],
    "sg:phone":"+1 269 927 6886",
    "sg:postcode":"49126",
    "sg:province":"MI",
    "sg:tags":[
        "manufacture",
        "ordnance",
        "door",
        "arms",
        "devices",
        "garage",
        "small"
    ],
    "wof:name":"Hill N Dale Farms",
    "wof:placetype":"venue"
},
  "geometry": {"coordinates":[-86.35866300000001,42.030812],"type":"Point"}
}