{
  "type": "Feature",
  "properties": {
    "iso:country":"US",
    "sg:address":"1055 S Lapeer Rd",
    "sg:city":"Oxford",
    "sg:classifiers":[
        {
            "category":"Restaurant",
            "type":"Food & Drink"
        }
    ],
    "sg:phone":"+1 248 628 2503",
    "sg:postcode":"48371",
    "sg:province":"MI",
    "wof:name":"Nugget",
    "wof:placetype":"venue"
},
  "geometry": {"coordinates":[-83.254672,42.813964],"type":"Point"}
}