{
  "type": "Feature",
  "properties": {
    "iso:country":"US",
    "sg:address":"32417 Gratiot Ave Sp580",
    "sg:city":"Roseville",
    "sg:classifiers":[
        {
            "category":"Shopping",
            "subcategory":"Clothing, Apparel, & Fashions",
            "type":"Retail Goods"
        }
    ],
    "sg:phone":"+1 586 415 8481",
    "sg:postcode":"48066",
    "sg:province":"MI",
    "sg:tags":[
        "shop",
        "cap",
        "hat",
        "sportswear"
    ],
    "sg:website":"http://www.lids.com",
    "wof:name":"Lids",
    "wof:placetype":"venue"
},
  "geometry": {"coordinates":[-82.912181,42.535206],"type":"Point"}
}