{
  "type": "Feature",
  "properties": {
    "iso:country":"US",
    "sg:address":"311 Columbus Ave",
    "sg:city":"Bay City",
    "sg:classifiers":[
        {
            "category":"Wholesale",
            "subcategory":"Chemicals & Plastics",
            "type":"Manufacturing & Wholesale Goods"
        }
    ],
    "sg:phone":"+1 989 894 4101",
    "sg:postcode":"48708",
    "sg:province":"MI",
    "sg:tags":[
        "retail",
        "store"
    ],
    "wof:name":"Airgas",
    "wof:placetype":"venue"
},
  "geometry": {"coordinates":[-83.88858,43.589459],"type":"Point"}
}