{
  "type": "Feature",
  "properties": {
    "iso:country":"US",
    "sg:address":"2932 Chicago Dr SW",
    "sg:city":"Wyoming",
    "sg:classifiers":[
        {
            "category":"Professional",
            "subcategory":"Management & Consulting",
            "type":"Services"
        }
    ],
    "sg:phone":"+1 616 475 0401",
    "sg:postcode":"49418",
    "sg:province":"MI",
    "sg:tags":[
        "employment",
        "screening"
    ],
    "wof:name":"Great Lakes Employment Svc",
    "wof:placetype":"venue"
},
  "geometry": {"coordinates":[-85.736187,42.924011],"type":"Point"}
}