{
  "type": "Feature",
  "properties": {
    "iso:country":"US",
    "sg:address":"2205 Byron Rd",
    "sg:city":"Hudsonville",
    "sg:classifiers":[
        {
            "category":"Real Estate",
            "subcategory":"Real Estate Operator",
            "type":"Services"
        }
    ],
    "sg:phone":"+1 616 896 9710",
    "sg:postcode":"49426",
    "sg:province":"MI",
    "sg:tags":[
        "property",
        "lessor"
    ],
    "wof:name":"Elmer Poortenga",
    "wof:placetype":"venue"
},
  "geometry": {"coordinates":[-85.83216899999999,42.811351],"type":"Point"}
}