{
  "type": "Feature",
  "properties": {
    "iso:country":"US",
    "sg:address":"14500 Northline Rd",
    "sg:city":"Southgate",
    "sg:classifiers":[
        {
            "category":"Health Services",
            "subcategory":"Doctor",
            "type":"Services"
        }
    ],
    "sg:phone":"+1 734 281 4197",
    "sg:postcode":"48195",
    "sg:province":"MI",
    "sg:tags":[
        "throat",
        "ear",
        "nose"
    ],
    "wof:name":"Reddy Pavan G MD",
    "wof:placetype":"venue"
},
  "geometry": {"coordinates":[-83.20050000000001,42.213699],"type":"Point"}
}