{
  "type": "Feature",
  "properties": {
    "iso:country":"US",
    "sg:address":"10071 E Maple Ave",
    "sg:city":"Davison",
    "sg:classifiers":[
        {
            "category":"Real Estate",
            "subcategory":"Real Estate Operator",
            "type":"Services"
        }
    ],
    "sg:phone":"+1 810 653 4297",
    "sg:postcode":"48423",
    "sg:province":"MI",
    "sg:tags":[
        "building",
        "nonresidential"
    ],
    "wof:name":"J & J MI Properties Inc",
    "wof:placetype":"venue"
},
  "geometry": {"coordinates":[-83.51562800000001,42.962311],"type":"Point"}
}