{
  "type": "Feature",
  "properties": {
    "iso:country":"US",
    "sg:address":"29127 Forest Hill Ct",
    "sg:city":"Farmington",
    "sg:classifiers":[
        {
            "category":"Professional",
            "subcategory":"Advertising",
            "type":"Services"
        }
    ],
    "sg:phone":"+1 248 848 2614",
    "sg:postcode":"48331",
    "sg:province":"MI",
    "wof:name":"Rah Advertising Inc",
    "wof:placetype":"venue"
},
  "geometry": {"coordinates":[-83.41114899999999,42.507103],"type":"Point"}
}