{
  "type": "Feature",
  "properties": {
    "iso:country":"US",
    "sg:address":"118 N Clinton Ave",
    "sg:city":"St Johns",
    "sg:classifiers":[
        {
            "category":"Home & Garden",
            "subcategory":"Furniture",
            "type":"Retail Goods"
        }
    ],
    "sg:phone":"+1 989 224 6600",
    "sg:postcode":"48879",
    "sg:province":"MI",
    "wof:name":"Burlington Sofa-Mattress Fctry",
    "wof:placetype":"venue"
},
  "geometry": {"coordinates":[-84.558391,43.00224],"type":"Point"}
}