{
  "type": "Feature",
  "properties": {
    "iso:country":"US",
    "sg:address":"4500 W Saginaw Hwy",
    "sg:city":"Lansing",
    "sg:classifiers":[
        {
            "category":"Food & Beverages",
            "subcategory":"Groceries & Convenience Stores",
            "type":"Retail Goods"
        }
    ],
    "sg:phone":"+1 517 319 4113",
    "sg:postcode":"48917",
    "sg:province":"MI",
    "sg:tags":[
        "grocer"
    ],
    "wof:name":"Quality Dairy Co",
    "wof:placetype":"venue"
},
  "geometry": {"coordinates":[-84.614553,42.741057],"type":"Point"}
}