{
  "type": "Feature",
  "properties": {
    "iso:country":"US",
    "sg:address":"4145 Kalamazoo Ave SE",
    "sg:city":"Grand Rapids",
    "sg:classifiers":[
        {
            "category":"Professional",
            "subcategory":"Lawyer & Legal Services",
            "type":"Services"
        }
    ],
    "sg:phone":"+1 616 827 2326",
    "sg:postcode":"49508",
    "sg:province":"MI",
    "wof:name":"Adam",
    "wof:placetype":"venue"
},
  "geometry": {"coordinates":[-85.626254,42.887598],"type":"Point"}
}