{
  "type": "Feature",
  "properties": {
    "iso:country":"US",
    "sg:address":"14300 E 13 Mile Rd",
    "sg:city":"Warren",
    "sg:classifiers":[
        {
            "category":"Organizations",
            "subcategory":"Religious Organization",
            "type":"Services"
        }
    ],
    "sg:phone":"+1 586 771 4821",
    "sg:postcode":"48088",
    "sg:province":"MI",
    "wof:name":"Warren Woods Church of Nazarene",
    "wof:placetype":"venue"
},
  "geometry": {"coordinates":[-82.980301,42.5224],"type":"Point"}
}