{
  "type": "Feature",
  "properties": {
    "iso:country":"US",
    "sg:address":"16906 W 7 Mile Rd",
    "sg:city":"Detroit",
    "sg:classifiers":[
        {
            "category":"Personal",
            "subcategory":"Tattoo Parlor",
            "type":"Services"
        }
    ],
    "sg:phone":"+1 313 272 0123",
    "sg:postcode":"48235",
    "sg:province":"MI",
    "wof:name":"Gallery Tattoo",
    "wof:placetype":"venue"
},
  "geometry": {"coordinates":[-83.210678,42.430386],"type":"Point"}
}