{
  "type": "Feature",
  "properties": {
    "iso:country":"US",
    "sg:address":"7028 State Hwy 68",
    "sg:city":"Rogers City",
    "sg:classifiers":[
        {
            "category":"Government",
            "subcategory":"Office",
            "type":"Public Place"
        }
    ],
    "sg:phone":"+1 989 734 3585",
    "sg:postcode":"49779",
    "sg:province":"MI",
    "sg:tags":[
        "policy"
    ],
    "wof:name":"Preskio",
    "wof:placetype":"venue"
},
  "geometry": {"coordinates":[-83.94811900000001,45.39918],"type":"Point"}
}