{
  "type": "Feature",
  "properties": {
    "iso:country":"US",
    "sg:address":"4692 US Hwy 45",
    "sg:city":"Watersmeet",
    "sg:classifiers":[
        {
            "category":"Real Estate",
            "subcategory":"Real Estate Agent",
            "type":"Services"
        }
    ],
    "sg:phone":"+1 906 358 4045",
    "sg:postcode":"49969",
    "sg:province":"MI",
    "wof:name":"Four Seasons Realty Of Mi Inc",
    "wof:placetype":"venue"
},
  "geometry": {"coordinates":[-89.178139,46.268846],"type":"Point"}
}