{
  "type": "Feature",
  "properties": {
    "iso:country":"US",
    "sg:address":"2301 Woodward Ave",
    "sg:city":"Detroit",
    "sg:classifiers":[
        {
            "category":"Communications",
            "subcategory":"Radio Station",
            "type":"Services"
        }
    ],
    "sg:phone":"+1 313 964 1606",
    "sg:postcode":"48201",
    "sg:province":"MI",
    "sg:tags":[
        "broadcast"
    ],
    "sg:website":"http://www.hockeytown.com",
    "wof:name":"Hockytown Broadcasting",
    "wof:placetype":"venue"
},
  "geometry": {"coordinates":[-83.052177,42.338928],"type":"Point"}
}