{
  "type": "Feature",
  "properties": {
    "iso:country":"US",
    "sg:address":"5791 S McVety Rd",
    "sg:city":"Falmouth",
    "sg:classifiers":[
        {
            "category":"Building & Trades",
            "subcategory":"Construction",
            "type":"Services"
        }
    ],
    "sg:phone":"+1 231 328 4701",
    "sg:postcode":"49632",
    "sg:province":"MI",
    "sg:tags":[
        "excavating",
        "contractor"
    ],
    "wof:name":"Pete's Contracting",
    "wof:placetype":"venue"
},
  "geometry": {"coordinates":[-84.932681,44.251775],"type":"Point"}
}