{
  "type": "Feature",
  "properties": {
    "iso:country":"US",
    "sg:address":"4375 Country Way",
    "sg:city":"Hartland",
    "sg:classifiers":[
        {
            "category":"Building & Trades",
            "subcategory":"Landscaping Services",
            "type":"Services"
        }
    ],
    "sg:phone":"+1 810 632 9084",
    "sg:postcode":"48353",
    "sg:province":"MI",
    "sg:tags":[
        "landscape",
        "contractor"
    ],
    "wof:name":"R & G Landscaping & Perennials",
    "wof:placetype":"venue"
},
  "geometry": {"coordinates":[-83.742349,42.665822],"type":"Point"}
}