{
  "type": "Feature",
  "properties": {
    "iso:country":"US",
    "sg:address":"800 State St",
    "sg:city":"Owosso",
    "sg:classifiers":[
        {
            "category":"Building & Trades",
            "subcategory":"Cleaning & Sanitation",
            "type":"Services"
        }
    ],
    "sg:phone":"+1 989 725 1955",
    "sg:postcode":"48867",
    "sg:province":"MI",
    "sg:tags":[
        "snow",
        "removal"
    ],
    "wof:name":"Losey's Snow Removal",
    "wof:placetype":"venue"
},
  "geometry": {"coordinates":[-84.185298,42.990522],"type":"Point"}
}