{
  "type": "Feature",
  "properties": {
    "iso:country":"US",
    "sg:address":"1266 W 120th St",
    "sg:city":"Grant",
    "sg:classifiers":[
        {
            "category":"Banks & Credit Unions",
            "subcategory":"Investment Brokerage",
            "type":"Services"
        }
    ],
    "sg:phone":"+1 231 834 9825",
    "sg:postcode":"49327",
    "sg:province":"MI",
    "sg:tags":[
        "security"
    ],
    "wof:name":"American Express",
    "wof:placetype":"venue"
},
  "geometry": {"coordinates":[-85.834103,43.336499],"type":"Point"}
}