{
  "type": "Feature",
  "properties": {
    "iso:country":"US",
    "sg:address":"21110 Outer Dr",
    "sg:city":"Dearborn",
    "sg:classifiers":[
        {
            "category":"Place Of Worship",
            "subcategory":"Mosque",
            "type":"Public Place"
        }
    ],
    "sg:phone":"+1 313 565 9314",
    "sg:postcode":"48124",
    "sg:province":"MI",
    "wof:name":"American Muslim Center",
    "wof:placetype":"venue"
},
  "geometry": {"coordinates":[-83.246498,42.290501],"type":"Point"}
}