{
  "type": "Feature",
  "properties": {
    "iso:country":"US",
    "sg:address":"655 28th St SE",
    "sg:city":"Grand Rapids",
    "sg:classifiers":[
        {
            "category":"Food & Beverages",
            "subcategory":"Groceries & Convenience Stores",
            "type":"Retail Goods"
        }
    ],
    "sg:phone":"+1 616 245 5851",
    "sg:postcode":"49548",
    "sg:province":"MI",
    "sg:tags":[
        "grocer"
    ],
    "wof:name":"Saigon Market",
    "wof:placetype":"venue"
},
  "geometry": {"coordinates":[-85.65092199999999,42.912888],"type":"Point"}
}