{
  "type": "Feature",
  "properties": {
    "iso:country":"US",
    "sg:address":"200 N Gainsborough Ave",
    "sg:city":"Royal Oak",
    "sg:classifiers":[
        {
            "category":"Restaurant",
            "type":"Food & Drink"
        }
    ],
    "sg:phone":"+1 248 544 7799",
    "sg:postcode":"48067",
    "sg:province":"MI",
    "wof:name":"Papa Romano's",
    "wof:placetype":"venue"
},
  "geometry": {"coordinates":[-83.131698,42.491323],"type":"Point"}
}