{
  "type": "Feature",
  "properties": {
    "iso:country":"US",
    "sg:address":"13567 Hannan Rd",
    "sg:city":"Romulus",
    "sg:classifiers":[
        {
            "category":"Building & Trades",
            "subcategory":"Construction",
            "type":"Services"
        }
    ],
    "sg:phone":"+1 734 955 2394",
    "sg:postcode":"48174",
    "sg:province":"MI",
    "sg:tags":[
        "contractor"
    ],
    "wof:name":"Arcade Marble & Granite Co",
    "wof:placetype":"venue"
},
  "geometry": {"coordinates":[-83.423815,42.205713],"type":"Point"}
}