{
  "type": "Feature",
  "properties": {
    "iso:country":"US",
    "sg:address":"8080 Carriage Ln",
    "sg:city":"Stanwood",
    "sg:classifiers":[
        {
            "category":"Wholesale",
            "subcategory":"Non-durable Goods",
            "type":"Manufacturing & Wholesale Goods"
        }
    ],
    "sg:phone":"+1 231 972 5154",
    "sg:postcode":"49346",
    "sg:province":"MI",
    "wof:name":"Wynne Marketing",
    "wof:placetype":"venue"
},
  "geometry": {"coordinates":[-85.279527,43.582362],"type":"Point"}
}