{
  "type": "Feature",
  "properties": {
    "iso:country":"US",
    "sg:address":"110 State Hwy 15",
    "sg:city":"Ortonville",
    "sg:classifiers":[
        {
            "category":"Autos & Motor Vehicles",
            "subcategory":"Automobile Sales",
            "type":"Retail Goods"
        }
    ],
    "sg:phone":"+1 248 627 3660",
    "sg:postcode":"48462",
    "sg:province":"MI",
    "sg:tags":[
        "car",
        "dealer"
    ],
    "wof:name":"Simms Chevrolet Motor Inc",
    "wof:placetype":"venue"
},
  "geometry": {"coordinates":[-83.45119,42.851054],"type":"Point"}
}