{
  "type": "Feature",
  "properties": {
    "iso:country":"US",
    "sg:address":"8200 S Saginaw St",
    "sg:city":"Grand Blanc",
    "sg:classifiers":[
        {
            "category":"Professional",
            "subcategory":"Lawyer & Legal Services",
            "type":"Services"
        }
    ],
    "sg:phone":"+1 810 953 6600",
    "sg:postcode":"48439",
    "sg:province":"MI",
    "sg:tags":[
        "attorney"
    ],
    "wof:name":"Grossman & St John",
    "wof:placetype":"venue"
},
  "geometry": {"coordinates":[-83.60761599999999,42.911425],"type":"Point"}
}