{
  "type": "Feature",
  "properties": {
    "iso:country":"US",
    "sg:address":"50528 Schoenherr Rd",
    "sg:city":"Utica",
    "sg:classifiers":[
        {
            "category":"Restaurant",
            "type":"Food & Drink"
        }
    ],
    "sg:menulink":"http://www.allmenus.com/mi/shelby/40597-papa-romanos/menu/",
    "sg:phone":"+1 586 566 7272",
    "sg:postcode":"48315",
    "sg:province":"MI",
    "sg:tags":[
        "wrap",
        "american",
        "sandwich",
        "pizza"
    ],
    "wof:name":"Papa Romano's",
    "wof:placetype":"venue"
},
  "geometry": {"coordinates":[-82.994547,42.666829],"type":"Point"}
}