{
  "type": "Feature",
  "properties": {
    "iso:country":"US",
    "sg:address":"520 Butternut Dr",
    "sg:city":"Holland",
    "sg:classifiers":[
        {
            "category":"Banks & Credit Unions",
            "subcategory":"Bank",
            "type":"Services"
        }
    ],
    "sg:phone":"+1 616 399 1164",
    "sg:postcode":"49424",
    "sg:province":"MI",
    "sg:tags":[
        "cashing",
        "check"
    ],
    "wof:name":"Crusader Cash Advance",
    "wof:placetype":"venue"
},
  "geometry": {"coordinates":[-86.122164,42.812136],"type":"Point"}
}