{
  "type": "Feature",
  "properties": {
    "iso:country":"US",
    "sg:address":"1960 Warbler Ct",
    "sg:city":"Troy",
    "sg:classifiers":[
        {
            "category":"Professional",
            "subcategory":"Business Services",
            "type":"Services"
        }
    ],
    "sg:phone":"+1 248 649 0404",
    "sg:postcode":"48084",
    "sg:province":"MI",
    "wof:name":"Bk Financial",
    "wof:placetype":"venue"
},
  "geometry": {"coordinates":[-83.184893,42.57544],"type":"Point"}
}