{
  "type": "Feature",
  "properties": {
    "iso:country":"US",
    "sg:address":"28640 Utica Rd",
    "sg:city":"Roseville",
    "sg:classifiers":[
        {
            "category":"Autos & Motor Vehicles",
            "subcategory":"Automobile Sales",
            "type":"Retail Goods"
        }
    ],
    "sg:phone":"+1 586 772 9810",
    "sg:postcode":"48066",
    "sg:province":"MI",
    "sg:tags":[
        "car",
        "dealer"
    ],
    "wof:name":"Gregory J Auto Sales",
    "wof:placetype":"venue"
},
  "geometry": {"coordinates":[-82.932982,42.504359],"type":"Point"}
}