{
  "type": "Feature",
  "properties": {
    "iso:country":"US",
    "sg:address":"239 W Saginaw Rd",
    "sg:city":"Sanford",
    "sg:classifiers":[
        {
            "category":"Government",
            "subcategory":"Post Office",
            "type":"Public Place"
        }
    ],
    "sg:phone":"+1 989 687 2311",
    "sg:postcode":"48657",
    "sg:province":"MI",
    "wof:name":"US Post Office",
    "wof:placetype":"venue"
},
  "geometry": {"coordinates":[-84.376865,43.670166],"type":"Point"}
}