{
  "type": "Feature",
  "properties": {
    "iso:country":"US",
    "sg:address":"26665 Tom Allen Dr",
    "sg:city":"Warren",
    "sg:classifiers":[
        {
            "category":"Building & Trades",
            "subcategory":"Cleaning & Sanitation",
            "type":"Services"
        }
    ],
    "sg:phone":"+1 586 757 3866",
    "sg:postcode":"48089",
    "sg:province":"MI",
    "sg:tags":[
        "carpet"
    ],
    "wof:name":"Speedy Dry Carpet Cleaning",
    "wof:placetype":"venue"
},
  "geometry": {"coordinates":[-83.015602,42.489601],"type":"Point"}
}