{
  "type": "Feature",
  "properties": {
    "iso:country":"US",
    "sg:address":"2900 Airport Rd",
    "sg:city":"Jackson",
    "sg:classifiers":[
        {
            "category":"Food & Beverages",
            "subcategory":"Groceries & Convenience Stores",
            "type":"Retail Goods"
        }
    ],
    "sg:phone":"+1 517 789 6544",
    "sg:postcode":"49202",
    "sg:province":"MI",
    "wof:name":"7-Eleven",
    "wof:placetype":"venue"
},
  "geometry": {"coordinates":[-84.45305500000001,42.274869],"type":"Point"}
}