{
  "type": "Feature",
  "properties": {
    "iso:country":"US",
    "sg:address":"21733 Armada Ridge Rd",
    "sg:city":"Armada",
    "sg:classifiers":[
        {
            "category":"Education",
            "subcategory":"Special Training",
            "type":"Public Place"
        }
    ],
    "sg:phone":"+1 586 784 4044",
    "sg:postcode":"48005",
    "sg:province":"MI",
    "wof:name":"D & J Smith Assoc",
    "wof:placetype":"venue"
},
  "geometry": {"coordinates":[-82.905006,42.835747],"type":"Point"}
}