{
  "type": "Feature",
  "properties": {
    "iso:country":"US",
    "sg:address":"9303 Bankers Rd",
    "sg:city":"Reading",
    "sg:classifiers":[
        {
            "category":"Building & Trades",
            "subcategory":"Construction",
            "type":"Services"
        }
    ],
    "sg:phone":"+1 517 283 2601",
    "sg:postcode":"49274",
    "sg:province":"MI",
    "sg:tags":[
        "water",
        "well",
        "drilling"
    ],
    "wof:name":"Don's Water Well Svc",
    "wof:placetype":"venue"
},
  "geometry": {"coordinates":[-84.79260499999999,41.885229],"type":"Point"}
}