{
  "type": "Feature",
  "properties": {
    "iso:country":"US",
    "sg:address":"1455 Bristol Ave NW",
    "sg:city":"Grand Rapids",
    "sg:classifiers":[
        {
            "category":"Building & Trades",
            "subcategory":"Electrical",
            "type":"Services"
        }
    ],
    "sg:phone":"+1 616 245 2301",
    "sg:postcode":"49504",
    "sg:province":"MI",
    "sg:tags":[
        "electric",
        "contractor"
    ],
    "wof:name":"Remtema Electric",
    "wof:placetype":"venue"
},
  "geometry": {"coordinates":[-85.707825,42.989067],"type":"Point"}
}