{
  "type": "Feature",
  "properties": {
    "iso:country":"US",
    "sg:address":"2975 Fruit St",
    "sg:city":"Clay",
    "sg:classifiers":[
        {
            "category":"Manufacturing",
            "subcategory":"Rubber & Plastics",
            "type":"Manufacturing & Wholesale Goods"
        }
    ],
    "sg:phone":"+1 810 794 4440",
    "sg:postcode":"48001",
    "sg:province":"MI",
    "wof:name":"Ramm",
    "wof:placetype":"venue"
},
  "geometry": {"coordinates":[-82.552594,42.623123],"type":"Point"}
}