{
  "type": "Feature",
  "properties": {
    "iso:country":"US",
    "sg:address":"632 Capital Ave SW",
    "sg:city":"Battle Creek",
    "sg:classifiers":[
        {
            "category":"Manufacturing",
            "subcategory":"Printing",
            "type":"Manufacturing & Wholesale Goods"
        }
    ],
    "sg:phone":"+1 269 965 7200",
    "sg:postcode":"49015",
    "sg:province":"MI",
    "sg:tags":[
        "multimedia"
    ],
    "wof:name":"Today Center Of Battle Creek",
    "wof:placetype":"venue"
},
  "geometry": {"coordinates":[-85.19954,42.303802],"type":"Point"}
}