{
  "type": "Feature",
  "properties": {
    "iso:country":"US",
    "sg:address":"821 Industrial Rd",
    "sg:city":"Marshall",
    "sg:classifiers":[
        {
            "category":"Wholesale",
            "subcategory":"Stationery",
            "type":"Manufacturing & Wholesale Goods"
        }
    ],
    "sg:phone":"+1 269 781 8579",
    "sg:postcode":"49068",
    "sg:province":"MI",
    "sg:tags":[
        "equipment",
        "price",
        "marking"
    ],
    "wof:name":"J F Miller Sales Co",
    "wof:placetype":"venue"
},
  "geometry": {"coordinates":[-84.972289,42.266568],"type":"Point"}
}