{
  "type": "Feature",
  "properties": {
    "iso:country":"US",
    "sg:address":"1104 Baldwin Ave",
    "sg:city":"Pontiac",
    "sg:classifiers":[
        {
            "category":"Autos & Motor Vehicles",
            "subcategory":"Automobile Sales",
            "type":"Retail Goods"
        }
    ],
    "sg:phone":"+1 248 335 5900",
    "sg:postcode":"48340",
    "sg:province":"MI",
    "sg:tags":[
        "car",
        "dealer"
    ],
    "wof:name":"Bob Wolfe's Auto Sales",
    "wof:placetype":"venue"
},
  "geometry": {"coordinates":[-83.300281,42.667996],"type":"Point"}
}