{
  "type": "Feature",
  "properties": {
    "iso:country":"US",
    "sg:address":"304 S Pine River St",
    "sg:city":"Ithaca",
    "sg:classifiers":[
        {
            "category":"Freight",
            "type":"Transportation"
        }
    ],
    "sg:phone":"+1 989 875 6672",
    "sg:postcode":"48847",
    "sg:province":"MI",
    "sg:tags":[
        "grain",
        "elevator"
    ],
    "wof:name":"Mid Michigan Specialty Crops",
    "wof:placetype":"venue"
},
  "geometry": {"coordinates":[-84.607663,43.289193],"type":"Point"}
}