{
  "type": "Feature",
  "properties": {
    "iso:country":"US",
    "sg:address":"307 W Main St",
    "sg:city":"Brighton",
    "sg:classifiers":[
        {
            "category":"Professional",
            "subcategory":"Business Services",
            "type":"Services"
        }
    ],
    "sg:phone":"+1 810 227 4751",
    "sg:postcode":"48116",
    "sg:province":"MI",
    "sg:tags":[
        "interior",
        "consultant",
        "design",
        "decorator"
    ],
    "wof:name":"Heirloom Oriental Rugs",
    "wof:placetype":"venue"
},
  "geometry": {"coordinates":[-83.782929,42.529429],"type":"Point"}
}