{
  "type": "Feature",
  "properties": {
    "iso:country":"US",
    "sg:address":"47633 Avante Dr",
    "sg:city":"Wixom",
    "sg:classifiers":[
        {
            "category":"Wholesale",
            "subcategory":"Machinery & Supplies",
            "type":"Manufacturing & Wholesale Goods"
        }
    ],
    "sg:phone":"+1 248 449 1977",
    "sg:postcode":"48393",
    "sg:province":"MI",
    "sg:tags":[
        "gage"
    ],
    "wof:name":"Gretna Gage & Engineering",
    "wof:placetype":"venue"
},
  "geometry": {"coordinates":[-83.519623,42.503996],"type":"Point"}
}