{
  "type": "Feature",
  "properties": {
    "iso:country":"US",
    "sg:address":"1412 Center Ave",
    "sg:city":"Bay City",
    "sg:classifiers":[
        {
            "category":"Shopping",
            "subcategory":"Books",
            "type":"Retail Goods"
        }
    ],
    "sg:phone":"+1 989 892 0719",
    "sg:postcode":"48708",
    "sg:province":"MI",
    "wof:name":"Jett W Whitehead Rare Books",
    "wof:placetype":"venue"
},
  "geometry": {"coordinates":[-83.874769,43.596967],"type":"Point"}
}