{
  "type": "Feature",
  "properties": {
    "iso:country":"US",
    "sg:address":"3946 Division Ave S",
    "sg:city":"Grand Rapids",
    "sg:classifiers":[
        {
            "category":"Recreation",
            "type":"Entertainment"
        }
    ],
    "sg:phone":"+1 616 261 5685",
    "sg:postcode":"49548",
    "sg:province":"MI",
    "sg:tags":[
        "amusement"
    ],
    "wof:name":"Stedman Motorsports",
    "wof:placetype":"venue"
},
  "geometry": {"coordinates":[-85.66506,42.892641],"type":"Point"}
}