{
  "type": "Feature",
  "properties": {
    "iso:country":"US",
    "sg:address":"995 E Main St",
    "sg:city":"Benton Harbor",
    "sg:classifiers":[
        {
            "category":"Food & Beverages",
            "subcategory":"Groceries & Convenience Stores",
            "type":"Retail Goods"
        }
    ],
    "sg:phone":"+1 269 925 6637",
    "sg:postcode":"49022",
    "sg:province":"MI",
    "wof:name":"Tim's Minimart",
    "wof:placetype":"venue"
},
  "geometry": {"coordinates":[-86.43535,42.117866],"type":"Point"}
}