{
  "type": "Feature",
  "properties": {
    "iso:country":"US",
    "sg:address":"31 2nd St N",
    "sg:city":"Kent City",
    "sg:classifiers":[
        {
            "category":"Building & Trades",
            "subcategory":"Construction",
            "type":"Services"
        }
    ],
    "sg:phone":"+1 616 678 4317",
    "sg:postcode":"49330",
    "sg:province":"MI",
    "sg:tags":[
        "hanging",
        "contractor"
    ],
    "wof:name":"Color By Beck",
    "wof:placetype":"venue"
},
  "geometry": {"coordinates":[-85.752348,43.221881],"type":"Point"}
}