{
  "type": "Feature",
  "properties": {
    "iso:country":"US",
    "sg:address":"11400 S Hutchinson Rd",
    "sg:city":"Dowling",
    "sg:classifiers":[
        {
            "category":"Farming",
            "subcategory":"Farm",
            "type":"Manufacturing & Wholesale Goods"
        }
    ],
    "sg:phone":"+1 269 758 3586",
    "sg:postcode":"49050",
    "sg:province":"MI",
    "wof:name":"Robert Russell",
    "wof:placetype":"venue"
},
  "geometry": {"coordinates":[-85.22944200000001,42.482301],"type":"Point"}
}