{
  "type": "Feature",
  "properties": {
    "iso:country":"US",
    "sg:address":"224 Circle Dr",
    "sg:city":"Traverse City",
    "sg:classifiers":[
        {
            "category":"Health Services",
            "subcategory":"Doctor",
            "type":"Services"
        }
    ],
    "sg:phone":"+1 231 946 3900",
    "sg:postcode":"49684",
    "sg:province":"MI",
    "sg:tags":[
        "dentist"
    ],
    "wof:name":"Wesson Schulz DDS",
    "wof:placetype":"venue"
},
  "geometry": {"coordinates":[-85.64388,44.762263],"type":"Point"}
}