{
  "type": "Feature",
  "properties": {
    "iso:country":"US",
    "sg:address":"2035 Ontonagon Ave SE",
    "sg:city":"Grand Rapids",
    "sg:classifiers":[
        {
            "category":"Insurance",
            "subcategory":"Insurance Agent",
            "type":"Services"
        }
    ],
    "sg:phone":"+1 616 475 0941",
    "sg:postcode":"49506",
    "sg:province":"MI",
    "wof:name":"United States Fidelty Guaranty",
    "wof:placetype":"venue"
},
  "geometry": {"coordinates":[-85.61027900000001,42.924754],"type":"Point"}
}