{
  "type": "Feature",
  "properties": {
    "iso:country":"US",
    "sg:address":"4220 W Carson City Rd",
    "sg:city":"Greenville",
    "sg:classifiers":[
        {
            "category":"Manufacturing",
            "subcategory":"Textiles",
            "type":"Manufacturing & Wholesale Goods"
        },
        {
            "category":"Manufacturing",
            "subcategory":"Rubber & Plastics",
            "type":"Manufacturing & Wholesale Goods"
        }
    ],
    "sg:phone":"+1 616 225 8248",
    "sg:postcode":"48838",
    "sg:province":"MI",
    "sg:tags":[
        "mill",
        "fabric"
    ],
    "wof:name":"HI Grade Plastics",
    "wof:placetype":"venue"
},
  "geometry": {"coordinates":[-85.15691700000001,43.170424],"type":"Point"}
}