{
  "type": "Feature",
  "properties": {
    "iso:country":"US",
    "sg:address":"11444 Mound Rd",
    "sg:city":"Hamtramck",
    "sg:classifiers":[
        {
            "category":"Recreation",
            "subcategory":"Amusement Park",
            "type":"Entertainment"
        }
    ],
    "sg:phone":"+1 313 893 0044",
    "sg:postcode":"48212",
    "sg:province":"MI",
    "wof:name":"All Star Amusement",
    "wof:placetype":"venue"
},
  "geometry": {"coordinates":[-83.04239699999999,42.4081],"type":"Point"}
}