{
  "type": "Feature",
  "properties": {
    "iso:country":"US",
    "sg:address":"1545 Clay St",
    "sg:city":"Detroit",
    "sg:classifiers":[
        {
            "category":"Building & Trades",
            "subcategory":"Construction",
            "type":"Services"
        }
    ],
    "sg:phone":"+1 313 871 6276",
    "sg:postcode":"48211",
    "sg:province":"MI",
    "sg:tags":[
        "for"
    ],
    "wof:name":"Yorkshire East Incorporated",
    "wof:placetype":"venue"
},
  "geometry": {"coordinates":[-83.061003,42.379029],"type":"Point"}
}