{
  "type": "Feature",
  "properties": {
    "iso:country":"US",
    "sg:address":"209 Maple St",
    "sg:city":"Big Rapids",
    "sg:classifiers":[
        {
            "category":"Professional",
            "subcategory":"Computer Services",
            "type":"Services"
        }
    ],
    "sg:phone":"+1 231 796 8299",
    "sg:postcode":"49307",
    "sg:province":"MI",
    "sg:tags":[
        "internet"
    ],
    "wof:name":"West Michigan Internet Svc",
    "wof:placetype":"venue"
},
  "geometry": {"coordinates":[-85.481916,43.698449],"type":"Point"}
}