{
  "type": "Feature",
  "properties": {
    "iso:country":"US",
    "sg:address":"105 Lake Shore Rd",
    "sg:city":"Grosse Pointe",
    "sg:classifiers":[
        {
            "category":"Health Services",
            "subcategory":"Doctor",
            "type":"Services"
        }
    ],
    "sg:phone":"+1 586 751 5200",
    "sg:postcode":"48236",
    "sg:province":"MI",
    "sg:tags":[
        "medical"
    ],
    "wof:name":"Yb Bishai MD PC",
    "wof:placetype":"venue"
},
  "geometry": {"coordinates":[-82.892746,42.391662],"type":"Point"}
}