{
  "type": "Feature",
  "properties": {
    "iso:country":"US",
    "sg:address":"4388 W Kinsel Hwy",
    "sg:city":"Charlotte",
    "sg:phone":"+1 517 543 0590",
    "sg:postcode":"48813",
    "sg:province":"MI",
    "sg:tags":[
        "farm",
        "grain",
        "cash"
    ],
    "wof:name":"John Lewis Farm",
    "wof:placetype":"venue"
},
  "geometry": {"coordinates":[-84.929463,42.597322],"type":"Point"}
}