{
  "type": "Feature",
  "properties": {
    "iso:country":"US",
    "sg:address":"7426 Connies Dr",
    "sg:city":"Utica",
    "sg:classifiers":[
        {
            "category":"Professional",
            "subcategory":"Business Services",
            "type":"Services"
        }
    ],
    "sg:phone":"+1 586 786 1456",
    "sg:postcode":"48316",
    "sg:province":"MI",
    "wof:name":"Patsy Damico Sales",
    "wof:placetype":"venue"
},
  "geometry": {"coordinates":[-83.03748899999999,42.686682],"type":"Point"}
}