{
  "type": "Feature",
  "properties": {
    "iso:country":"US",
    "sg:address":"6363 Richfield Rd",
    "sg:city":"Flint",
    "sg:classifiers":[
        {
            "category":"Building & Trades",
            "subcategory":"Construction",
            "type":"Services"
        }
    ],
    "sg:phone":"+1 810 736 9054",
    "sg:postcode":"48506",
    "sg:province":"MI",
    "sg:tags":[
        "hanging",
        "contractor"
    ],
    "wof:name":"J T Marzonie",
    "wof:placetype":"venue"
},
  "geometry": {"coordinates":[-83.583431,43.058506],"type":"Point"}
}