{
  "type": "Feature",
  "properties": {
    "iso:country":"US",
    "sg:address":"344 M 40 S",
    "sg:city":"Allegan",
    "sg:classifiers":[
        {
            "category":"Travel",
            "subcategory":"Hotels & Motels",
            "type":"Entertainment"
        }
    ],
    "sg:phone":"+1 269 673 3903",
    "sg:postcode":"49010",
    "sg:province":"MI",
    "sg:tags":[
        "breakfast",
        "accommodation",
        "bed"
    ],
    "wof:name":"Froggy's The Inn At The Pond",
    "wof:placetype":"venue"
},
  "geometry": {"coordinates":[-85.85727,42.454331],"type":"Point"}
}