{
  "type": "Feature",
  "properties": {
    "iso:country":"US",
    "sg:address":"9769 Alpine Rd",
    "sg:city":"Goodells",
    "sg:phone":"+1 810 392 2297",
    "sg:postcode":"48027",
    "sg:province":"MI",
    "sg:tags":[
        "farm",
        "soybean"
    ],
    "wof:name":"Carl Fox",
    "wof:placetype":"venue"
},
  "geometry": {"coordinates":[-82.728604,42.905396],"type":"Point"}
}