{
  "type": "Feature",
  "properties": {
    "iso:country":"US",
    "sg:address":"15250 Eureka Rd",
    "sg:city":"Southgate",
    "sg:classifiers":[
        {
            "category":"Retail",
            "subcategory":"Veterinary Services",
            "type":"Services"
        }
    ],
    "sg:phone":"+1 734 281 6500",
    "sg:postcode":"48195",
    "sg:province":"MI",
    "sg:tags":[
        "veterinarian"
    ],
    "sg:website":"www.angelanimalhospital.com",
    "wof:name":"Angel Animal Hospital",
    "wof:placetype":"venue"
},
  "geometry": {"coordinates":[-83.208635,42.199157],"type":"Point"}
}