{
  "type": "Feature",
  "properties": {
    "iso:country":"US",
    "sg:address":"3615 E M-79 Hwy",
    "sg:city":"Hastings",
    "sg:classifiers":[
        {
            "category":"Retail",
            "subcategory":"Auto Repair",
            "type":"Services"
        }
    ],
    "sg:phone":"+1 269 945 3310",
    "sg:postcode":"49058",
    "sg:province":"MI",
    "sg:tags":[
        "machine",
        "automobile",
        "shop"
    ],
    "wof:name":"Doug's Auto Svc",
    "wof:placetype":"venue"
},
  "geometry": {"coordinates":[-85.212673,42.610607],"type":"Point"}
}