{
  "type": "Feature",
  "properties": {
    "iso:country":"US",
    "sg:address":"755 S 100 E",
    "sg:city":"Angola",
    "sg:classifiers":[
        {
            "category":"Education",
            "subcategory":"School",
            "type":"Public Place"
        }
    ],
    "sg:phone":"+1 260 665 2186",
    "sg:postcode":"46703",
    "sg:province":"MI",
    "wof:name":"Angola High School",
    "wof:placetype":"venue"
},
  "geometry": {"coordinates":[-84.97012700000001,41.629636],"type":"Point"}
}