{
  "type": "Feature",
  "properties": {
    "iso:country":"US",
    "sg:address":"4315 Allegheny Dr",
    "sg:city":"Troy",
    "sg:classifiers":[
        {
            "category":"Building & Trades",
            "subcategory":"Construction",
            "type":"Services"
        }
    ],
    "sg:phone":"+1 248 740 8461",
    "sg:postcode":"48085",
    "sg:province":"MI",
    "sg:tags":[
        "house"
    ],
    "wof:name":"W & J Construction",
    "wof:placetype":"venue"
},
  "geometry": {"coordinates":[-83.10706,42.580796],"type":"Point"}
}