{
  "type": "Feature",
  "properties": {
    "iso:country":"US",
    "sg:address":"11730 Merrill Rd",
    "sg:city":"Whitmore Lake",
    "sg:classifiers":[
        {
            "category":"Building & Trades",
            "subcategory":"Construction",
            "type":"Services"
        }
    ],
    "sg:phone":"+1 810 231 8739",
    "sg:postcode":"48189",
    "sg:province":"MI",
    "sg:tags":[
        "house"
    ],
    "wof:name":"Pro Style Construction",
    "wof:placetype":"venue"
},
  "geometry": {"coordinates":[-83.81912699999999,42.430025],"type":"Point"}
}