{
  "type": "Feature",
  "properties": {
    "iso:country":"US",
    "sg:address":"155 Nixon",
    "sg:city":"Battle Creek",
    "sg:classifiers":[
        {
            "category":"Manufacturing",
            "subcategory":"Metals",
            "type":"Manufacturing & Wholesale Goods"
        }
    ],
    "sg:phone":"+1 269 968 1458",
    "sg:postcode":"49014",
    "sg:province":"MI",
    "sg:tags":[
        "stampings",
        "mfg"
    ],
    "wof:name":"Fabrication Unlimited",
    "wof:placetype":"venue"
},
  "geometry": {"coordinates":[-85.116595,42.307459],"type":"Point"}
}