{
  "type": "Feature",
  "properties": {
    "iso:country":"US",
    "sg:address":"1237 Michigan Ave",
    "sg:city":"Alma",
    "sg:classifiers":[
        {
            "category":"Food & Beverages",
            "subcategory":"Liquor & Beverages",
            "type":"Retail Goods"
        }
    ],
    "sg:phone":"+1 989 463 0736",
    "sg:postcode":"48801",
    "sg:province":"MI",
    "wof:name":"Zak's Market",
    "wof:placetype":"venue"
},
  "geometry": {"coordinates":[-84.64293600000001,43.3834],"type":"Point"}
}