{
  "type": "Feature",
  "properties": {
    "iso:country":"US",
    "sg:address":"19330 Midway Rd",
    "sg:city":"Southfield",
    "sg:classifiers":[
        {
            "category":"Social Services",
            "subcategory":"Adult Care",
            "type":"Services"
        }
    ],
    "sg:phone":"+1 248 948 9644",
    "sg:postcode":"48075",
    "sg:province":"MI",
    "sg:tags":[
        "foster",
        "provider"
    ],
    "wof:name":"Raymond & Caroline Fair",
    "wof:placetype":"venue"
},
  "geometry": {"coordinates":[-83.230701,42.452404],"type":"Point"}
}