{
  "type": "Feature",
  "properties": {
    "iso:country":"US",
    "sg:address":"3600 O'Neil Dr",
    "sg:city":"Jackson",
    "sg:classifiers":[
        {
            "category":"Shopping",
            "subcategory":"Florist",
            "type":"Retail Goods"
        }
    ],
    "sg:phone":"+1 517 796 5973",
    "sg:postcode":"49202",
    "sg:province":"MI",
    "wof:name":"H S Floral",
    "wof:placetype":"venue"
},
  "geometry": {"coordinates":[-84.32925899999999,42.068351],"type":"Point"}
}