{
  "type": "Feature",
  "properties": {
    "iso:country":"US",
    "sg:address":"3416 Henry St",
    "sg:city":"Muskegon",
    "sg:classifiers":[
        {
            "category":"Autos & Motor Vehicles",
            "subcategory":"Fuel & Gas Station",
            "type":"Retail Goods"
        }
    ],
    "sg:phone":"+1 231 733 4222",
    "sg:postcode":"49441",
    "sg:province":"MI",
    "sg:tags":[
        "oil"
    ],
    "wof:name":"Norton Shores E-Z Mart",
    "wof:placetype":"venue"
},
  "geometry": {"coordinates":[-86.263435,43.187344],"type":"Point"}
}