{
  "type": "Feature",
  "properties": {
    "iso:country":"US",
    "sg:address":"400 Park Dr",
    "sg:city":"Troy",
    "sg:classifiers":[
        {
            "category":"Home & Garden",
            "subcategory":"Hardware",
            "type":"Retail Goods"
        }
    ],
    "sg:phone":"+1 248 583 0030",
    "sg:postcode":"48083",
    "sg:province":"MI",
    "sg:tags":[
        "piping",
        "contractor"
    ],
    "wof:name":"Industrial Piping Systems",
    "wof:placetype":"venue"
},
  "geometry": {"coordinates":[-83.13958100000001,42.543164],"type":"Point"}
}