{
  "type": "Feature",
  "properties": {
    "iso:country":"US",
    "sg:address":"3777 Van Dyke Rd",
    "sg:city":"Almont",
    "sg:classifiers":[
        {
            "category":"Home & Garden",
            "subcategory":"Building Materials",
            "type":"Retail Goods"
        }
    ],
    "sg:phone":"+1 810 798 2727",
    "sg:postcode":"48003",
    "sg:province":"MI",
    "sg:website":"www.square-deal.com",
    "wof:name":"Square Deal Building Supply",
    "wof:placetype":"venue"
},
  "geometry": {"coordinates":[-83.056483,42.949451],"type":"Point"}
}