{
  "type": "Feature",
  "properties": {
    "iso:country":"US",
    "sg:address":"11233 Duffield Rd",
    "sg:city":"Montrose",
    "sg:classifiers":[
        {
            "category":"Personal",
            "subcategory":"Beauty Salon",
            "type":"Services"
        }
    ],
    "sg:phone":"+1 810 639 2993",
    "sg:postcode":"48457",
    "sg:province":"MI",
    "wof:name":"Dave's Family Hair Care",
    "wof:placetype":"venue"
},
  "geometry": {"coordinates":[-83.91289500000001,43.163268],"type":"Point"}
}