{
  "type": "Feature",
  "properties": {
    "iso:country":"US",
    "sg:address":"26126 Westmeath St",
    "sg:city":"Farmington",
    "sg:classifiers":[
        {
            "category":"Building & Trades",
            "subcategory":"Construction",
            "type":"Services"
        }
    ],
    "sg:phone":"+1 248 476 7334",
    "sg:postcode":"48334",
    "sg:province":"MI",
    "sg:tags":[
        "hanging",
        "contractor"
    ],
    "wof:name":"H Stewart Decorating",
    "wof:placetype":"venue"
},
  "geometry": {"coordinates":[-83.347683,42.488332],"type":"Point"}
}