{
  "type": "Feature",
  "properties": {
    "iso:country":"US",
    "sg:address":"2909 W White Lake Dr",
    "sg:city":"Whitehall",
    "sg:classifiers":[
        {
            "category":"Farming",
            "subcategory":"Nursery",
            "type":"Manufacturing & Wholesale Goods"
        }
    ],
    "sg:phone":"+1 231 894 6341",
    "sg:postcode":"49461",
    "sg:province":"MI",
    "sg:tags":[
        "greenhouse"
    ],
    "wof:name":"Stibitz Farms",
    "wof:placetype":"venue"
},
  "geometry": {"coordinates":[-86.31511500000001,43.384671],"type":"Point"}
}