{
  "type": "Feature",
  "properties": {
    "iso:country":"US",
    "sg:address":"14881 Farmington Rd",
    "sg:city":"Livonia",
    "sg:classifiers":[
        {
            "category":"Professional",
            "subcategory":"Lawyer & Legal Services",
            "type":"Services"
        }
    ],
    "sg:phone":"+1 734 422 5900",
    "sg:postcode":"48154",
    "sg:province":"MI",
    "sg:tags":[
        "personal",
        "injury"
    ],
    "sg:website":"www.brasheartangora.com",
    "wof:name":"Brashear William R Atty",
    "wof:placetype":"venue"
},
  "geometry": {"coordinates":[-83.374725,42.392559],"type":"Point"}
}