{
  "type": "Feature",
  "properties": {
    "iso:country":"US",
    "sg:address":"1983 Klingensmith Rd",
    "sg:city":"Bloomfield Hills",
    "sg:classifiers":[
        {
            "category":"Real Estate",
            "subcategory":"Real Estate Agent",
            "type":"Services"
        },
        {
            "category":"Professional",
            "subcategory":"Business Services",
            "type":"Services"
        }
    ],
    "sg:phone":"+1 248 335 2636",
    "sg:postcode":"48302",
    "sg:province":"MI",
    "sg:tags":[
        "notary",
        "public"
    ],
    "wof:name":"Presidential Real Estate Rlty",
    "wof:placetype":"venue"
},
  "geometry": {"coordinates":[-83.307044,42.610374],"type":"Point"}
}