{
  "type": "Feature",
  "properties": {
    "iso:country":"US",
    "sg:address":"11575 Edgerton Ave NE",
    "sg:city":"Rockford",
    "sg:classifiers":[
        {
            "category":"Professional",
            "subcategory":"Management & Consulting",
            "type":"Services"
        }
    ],
    "sg:phone":"+1 616 866 0787",
    "sg:postcode":"49341",
    "sg:province":"MI",
    "sg:tags":[
        "construction"
    ],
    "sg:website":"www.sablehomes.com",
    "wof:name":"Sable Developing Inc",
    "wof:placetype":"venue"
},
  "geometry": {"coordinates":[-85.58112800000001,43.174755],"type":"Point"}
}