{
  "type": "Feature",
  "properties": {
    "iso:country":"US",
    "sg:address":"7980 Territorial Rd",
    "sg:city":"Watervliet",
    "sg:classifiers":[
        {
            "category":"Farming",
            "subcategory":"Orchard",
            "type":"Manufacturing & Wholesale Goods"
        }
    ],
    "sg:phone":"+1 269 463 3351",
    "sg:postcode":"49098",
    "sg:province":"MI",
    "sg:tags":[
        "grove",
        "management"
    ],
    "wof:name":"Baiers Orchards",
    "wof:placetype":"venue"
},
  "geometry": {"coordinates":[-86.26912799999999,42.115494],"type":"Point"}
}