{
  "type": "Feature",
  "properties": {
    "iso:country":"US",
    "sg:address":"17449 E Jefferson Ave",
    "sg:city":"Grosse Pointe",
    "sg:classifiers":[
        {
            "category":"Banks & Credit Unions",
            "subcategory":"Bank",
            "type":"Services"
        }
    ],
    "sg:phone":"+1 313 884 3200",
    "sg:postcode":"48230",
    "sg:province":"MI",
    "sg:website":"www.chase.com",
    "wof:name":"Chase",
    "wof:placetype":"venue"
},
  "geometry": {"coordinates":[-82.905975,42.384805],"type":"Point"}
}