{
  "type": "Feature",
  "properties": {
    "iso:country":"US",
    "sg:address":"6470 Robb Rd",
    "sg:city":"Fowlerville",
    "sg:classifiers":[
        {
            "category":"Building & Trades",
            "subcategory":"Construction",
            "type":"Services"
        }
    ],
    "sg:phone":"+1 517 223 4216",
    "sg:postcode":"48836",
    "sg:province":"MI",
    "sg:tags":[
        "designer",
        "dealer",
        "pool",
        "swimming"
    ],
    "wof:name":"Battjes Pools LLC",
    "wof:placetype":"venue"
},
  "geometry": {"coordinates":[-84.055308,42.6922],"type":"Point"}
}