{
  "type": "Feature",
  "properties": {
    "iso:country":"US",
    "sg:address":"7667 Walker Rd",
    "sg:city":"Ovid",
    "sg:phone":"+1 989 834 5827",
    "sg:postcode":"48866",
    "sg:province":"MI",
    "sg:tags":[
        "farm",
        "soybean",
        "beef",
        "feedlot",
        "cattle"
    ],
    "wof:name":"Dean Watson",
    "wof:placetype":"venue"
},
  "geometry": {"coordinates":[-84.421069,43.01563],"type":"Point"}
}