{
  "type": "Feature",
  "properties": {
    "iso:country":"US",
    "sg:address":"101 N Main St",
    "sg:city":"Onsted",
    "sg:classifiers":[
        {
            "category":"Shopping",
            "subcategory":"Florist",
            "type":"Retail Goods"
        }
    ],
    "sg:phone":"+1 517 467 2339",
    "sg:postcode":"49265",
    "sg:province":"MI",
    "wof:name":"Dubois Flower Shop",
    "wof:placetype":"venue"
},
  "geometry": {"coordinates":[-84.18957399999999,42.006316],"type":"Point"}
}