{
  "type": "Feature",
  "properties": {
    "iso:country":"US",
    "sg:address":"8859 N Lemon Creek Rd",
    "sg:city":"Berrien Springs",
    "sg:classifiers":[
        {
            "category":"Professional",
            "subcategory":"Business Services",
            "type":"Services"
        }
    ],
    "sg:phone":"+1 269 473 2394",
    "sg:postcode":"49103",
    "sg:province":"MI",
    "wof:name":"Kw Enterprise",
    "wof:placetype":"venue"
},
  "geometry": {"coordinates":[-86.371505,41.957709],"type":"Point"}
}