{
  "type": "Feature",
  "properties": {
    "iso:country":"US",
    "sg:address":"110 N Main St",
    "sg:city":"Waldron",
    "sg:classifiers":[
        {
            "category":"Restaurant",
            "type":"Food & Drink"
        }
    ],
    "sg:phone":"+1 517 286 6279",
    "sg:postcode":"49288",
    "sg:province":"MI",
    "wof:name":"Kandy's Restaurant",
    "wof:placetype":"venue"
},
  "geometry": {"coordinates":[-84.418937,41.728823],"type":"Point"}
}