{
  "type": "Feature",
  "properties": {
    "iso:country":"US",
    "sg:address":"2773 Armstrong Dr",
    "sg:city":"Lake Orion",
    "sg:classifiers":[
        {
            "category":"Professional",
            "subcategory":"Business Services",
            "type":"Services"
        }
    ],
    "sg:phone":"+1 248 393 3618",
    "sg:postcode":"48360",
    "sg:province":"MI",
    "wof:name":"Craig Thompson Design",
    "wof:placetype":"venue"
},
  "geometry": {"coordinates":[-83.298672,42.739979],"type":"Point"}
}