{
  "type": "Feature",
  "properties": {
    "iso:country":"US",
    "sg:address":"3652 Gratiot Ave",
    "sg:city":"Detroit",
    "sg:classifiers":[
        {
            "category":"Retail",
            "subcategory":"Auto Repair",
            "type":"Services"
        }
    ],
    "sg:phone":"+1 313 579 0446",
    "sg:postcode":"48207",
    "sg:province":"MI",
    "wof:name":"Gratiot Auto Repair",
    "wof:placetype":"venue"
},
  "geometry": {"coordinates":[-83.024101,42.3643],"type":"Point"}
}