{
  "type": "Feature",
  "properties": {
    "iso:country":"US",
    "sg:address":"3265 S Cleveland Ave",
    "sg:city":"Saint Joseph",
    "sg:classifiers":[
        {
            "category":"Organizations",
            "subcategory":"Religious Organization",
            "type":"Services"
        }
    ],
    "sg:phone":"+1 269 429 7576",
    "sg:postcode":"49085",
    "sg:province":"MI",
    "wof:name":"American Baptist Church",
    "wof:placetype":"venue"
},
  "geometry": {"coordinates":[-86.494726,42.058927],"type":"Point"}
}