{
  "type": "Feature",
  "properties": {
    "iso:country":"US",
    "sg:address":"28504 Lorna Ave",
    "sg:city":"Warren",
    "sg:classifiers":[
        {
            "category":"Organizations",
            "subcategory":"Labor Organization",
            "type":"Services"
        }
    ],
    "sg:phone":"+1 586 751 4474",
    "sg:postcode":"48092",
    "sg:province":"MI",
    "wof:name":"UAW Intl Union",
    "wof:placetype":"venue"
},
  "geometry": {"coordinates":[-83.03559300000001,42.506266],"type":"Point"}
}