{
  "type": "Feature",
  "properties": {
    "iso:country":"US",
    "sg:address":"11867 Burgoyne Rd",
    "sg:city":"Buchanan",
    "sg:classifiers":[
        {
            "category":"Social Services",
            "subcategory":"Adult Care",
            "type":"Services"
        }
    ],
    "sg:phone":"+1 269 471 2628",
    "sg:postcode":"49107",
    "sg:province":"MI",
    "sg:tags":[
        "residential"
    ],
    "wof:name":"Snyder Afc Home",
    "wof:placetype":"venue"
},
  "geometry": {"coordinates":[-86.417062,41.903759],"type":"Point"}
}