{
  "type": "Feature",
  "properties": {
    "iso:country":"US",
    "sg:address":"808 N Euclid Ave",
    "sg:city":"Benton Harbor",
    "sg:classifiers":[
        {
            "category":"Personal",
            "subcategory":"Tattoo Parlor",
            "type":"Services"
        }
    ],
    "sg:phone":"+1 989 667 5887",
    "sg:postcode":"49022",
    "sg:province":"MI",
    "sg:tags":[
        "tattooing"
    ],
    "wof:name":"Star Tattoo All",
    "wof:placetype":"venue"
},
  "geometry": {"coordinates":[-86.407893,42.129816],"type":"Point"}
}