{
  "type": "Feature",
  "properties": {
    "iso:country":"US",
    "sg:address":"108 E Main St",
    "sg:city":"Hartford",
    "sg:classifiers":[
        {
            "category":"Autos & Motor Vehicles",
            "subcategory":"Fuel & Gas Station",
            "type":"Retail Goods"
        }
    ],
    "sg:phone":"+1 269 621 6076",
    "sg:postcode":"49057",
    "sg:province":"MI",
    "sg:tags":[
        "oil"
    ],
    "wof:name":"Kwick 'n EZ Marathon Mart",
    "wof:placetype":"venue"
},
  "geometry": {"coordinates":[-86.164536,42.206962],"type":"Point"}
}