{
  "type": "Feature",
  "properties": {
    "iso:country":"US",
    "sg:address":"230 Alta Dale Ave SE",
    "sg:city":"Ada",
    "sg:classifiers":[
        {
            "category":"Manufacturing",
            "subcategory":"Metals",
            "type":"Manufacturing & Wholesale Goods"
        }
    ],
    "sg:phone":"+1 616 676 8119",
    "sg:postcode":"49301",
    "sg:province":"MI",
    "sg:tags":[
        "fabricator",
        "sheet"
    ],
    "sg:website":"www.waltzholst.com",
    "wof:name":"Waltz-Holst Blow Pipe Co Inc",
    "wof:placetype":"venue"
},
  "geometry": {"coordinates":[-85.522988,42.959432],"type":"Point"}
}