{
  "type": "Feature",
  "properties": {
    "iso:country":"US",
    "sg:address":"115 W Ludington Ave",
    "sg:city":"Ludington",
    "sg:classifiers":[
        {
            "category":"Shopping",
            "subcategory":"Clothing, Apparel, & Fashions",
            "type":"Retail Goods"
        }
    ],
    "sg:phone":"+1 231 843 3860",
    "sg:postcode":"49431",
    "sg:province":"MI",
    "sg:tags":[
        "salvage",
        "surplus",
        "merchandise"
    ],
    "wof:name":"Dean's Four In One",
    "wof:placetype":"venue"
},
  "geometry": {"coordinates":[-86.44656500000001,43.955677],"type":"Point"}
}