{
  "type": "Feature",
  "properties": {
    "iso:country":"US",
    "sg:address":"33950 Van Dyke Ave",
    "sg:city":"Sterling Heights",
    "sg:classifiers":[
        {
            "category":"Restaurant",
            "type":"Food & Drink"
        }
    ],
    "sg:phone":"+1 586 979 6700",
    "sg:postcode":"48312",
    "sg:province":"MI",
    "sg:website":"www.lonestarsteakhouse.com",
    "wof:name":"Lone Star Steakhouse & Saloon",
    "wof:placetype":"venue"
},
  "geometry": {"coordinates":[-83.02862500000001,42.544211],"type":"Point"}
}