{
  "type": "Feature",
  "properties": {
    "iso:country":"US",
    "sg:address":"26312 Farmington Rd",
    "sg:city":"Farmington",
    "sg:classifiers":[
        {
            "category":"Shopping",
            "subcategory":"Hobbies, Toys, & Games",
            "type":"Retail Goods"
        }
    ],
    "sg:phone":"+1 248 474 5943",
    "sg:postcode":"48334",
    "sg:province":"MI",
    "sg:tags":[
        "repair",
        "merchandise"
    ],
    "wof:name":"This N That",
    "wof:placetype":"venue"
},
  "geometry": {"coordinates":[-83.377549,42.48658],"type":"Point"}
}