{
  "type": "Feature",
  "properties": {
    "iso:country":"US",
    "sg:address":"4245 W Jolly Rd",
    "sg:city":"Lansing",
    "sg:classifiers":[
        {
            "category":"Building & Trades",
            "subcategory":"Plumbing",
            "type":"Services"
        }
    ],
    "sg:phone":"+1 517 646 9010",
    "sg:postcode":"48911",
    "sg:province":"MI",
    "sg:tags":[
        "contractor"
    ],
    "wof:name":"Weaver Mechanical Design",
    "wof:placetype":"venue"
},
  "geometry": {"coordinates":[-84.6073,42.68315],"type":"Point"}
}