{
  "type": "Feature",
  "properties": {
    "iso:country":"US",
    "sg:address":"6534 Conestoga Dr",
    "sg:city":"Lansing",
    "sg:classifiers":[
        {
            "category":"Social Services",
            "type":"Services"
        }
    ],
    "sg:phone":"+1 517 853 8720",
    "sg:postcode":"48917",
    "sg:province":"MI",
    "sg:tags":[
        "referral"
    ],
    "wof:name":"Guardian Angel Referral",
    "wof:placetype":"venue"
},
  "geometry": {"coordinates":[-84.64583399999999,42.74904],"type":"Point"}
}