{
  "type": "Feature",
  "properties": {
    "iso:country":"US",
    "sg:address":"13162 Torrey Rd",
    "sg:city":"Fenton",
    "sg:phone":"+1 810 732 5903",
    "sg:postcode":"48430",
    "sg:province":"MI",
    "sg:tags":[
        "bulk",
        "gas"
    ],
    "wof:name":"Praxair Inc",
    "wof:placetype":"venue"
},
  "geometry": {"coordinates":[-83.72837,42.836901],"type":"Point"}
}