{
  "type": "Feature",
  "properties": {
    "iso:country":"US",
    "sg:address":"1027 Church St",
    "sg:city":"Port Huron",
    "sg:classifiers":[
        {
            "category":"Insurance",
            "subcategory":"Hazard Insurance",
            "type":"Services"
        }
    ],
    "sg:phone":"+1 810 984 1725",
    "sg:postcode":"48060",
    "sg:province":"MI",
    "sg:tags":[
        "bond"
    ],
    "wof:name":"Budget Bail Bond LLC",
    "wof:placetype":"venue"
},
  "geometry": {"coordinates":[-82.430763,43.001362],"type":"Point"}
}