{
  "type": "Feature",
  "properties": {
    "iso:country":"US",
    "sg:address":"2330 West Rd",
    "sg:city":"Trenton",
    "sg:classifiers":[
        {
            "category":"Restaurant",
            "type":"Food & Drink"
        }
    ],
    "sg:phone":"+1 734 493 3020",
    "sg:postcode":"48183",
    "sg:province":"MI",
    "sg:tags":[
        "pizza"
    ],
    "wof:name":"Humble Pies Pizza Inc",
    "wof:placetype":"venue"
},
  "geometry": {"coordinates":[-83.19634000000001,42.141351],"type":"Point"}
}