{
  "type": "Feature",
  "properties": {
    "iso:country":"US",
    "sg:address":"17251 W 12 Mile Rd",
    "sg:city":"Southfield",
    "sg:classifiers":[
        {
            "category":"Building & Trades",
            "subcategory":"Cleaning & Sanitation",
            "type":"Services"
        }
    ],
    "sg:phone":"+1 248 569 8165",
    "sg:postcode":"48076",
    "sg:province":"MI",
    "sg:tags":[
        "janitor"
    ],
    "wof:name":"Corporate Cleaning Svc",
    "wof:placetype":"venue"
},
  "geometry": {"coordinates":[-83.21726200000001,42.502536],"type":"Point"}
}