{
  "type": "Feature",
  "properties": {
    "iso:country":"US",
    "sg:address":"336 W First St",
    "sg:city":"Flint",
    "sg:classifiers":[
        {
            "category":"Professional",
            "type":"Services"
        }
    ],
    "sg:phone":"+1 810 235 3493",
    "sg:postcode":"48502",
    "sg:province":"MI",
    "wof:name":"Bennett Table Pad Co",
    "wof:placetype":"venue"
},
  "geometry": {"coordinates":[-83.694209,43.014425],"type":"Point"}
}