{
  "type": "Feature",
  "properties": {
    "iso:country":"US",
    "sg:address":"11745 US Hwy 23",
    "sg:city":"Ossineke",
    "sg:classifiers":[
        {
            "category":"Shopping",
            "subcategory":"Pharmacy",
            "type":"Retail Goods"
        }
    ],
    "sg:phone":"+1 989 471 2339",
    "sg:postcode":"49766",
    "sg:province":"MI",
    "wof:name":"Ossineke Pharmacy",
    "wof:placetype":"venue"
},
  "geometry": {"coordinates":[-83.443162,44.906204],"type":"Point"}
}