{
  "type": "Feature",
  "properties": {
    "iso:country":"US",
    "sg:address":"2400 James Savage Rd",
    "sg:city":"Midland",
    "sg:classifiers":[
        {
            "category":"Professional",
            "subcategory":"Lawyer & Legal Services",
            "type":"Services"
        }
    ],
    "sg:phone":"+1 989 638 6990",
    "sg:postcode":"48642",
    "sg:province":"MI",
    "sg:tags":[
        "plan"
    ],
    "wof:name":"Case Data Corp",
    "wof:placetype":"venue"
},
  "geometry": {"coordinates":[-84.20017799999999,43.610934],"type":"Point"}
}