{
  "type": "Feature",
  "properties": {
    "iso:country":"US",
    "sg:address":"903 E Clinton St",
    "sg:city":"Howell",
    "sg:classifiers":[
        {
            "category":"Health Services",
            "subcategory":"Chiropractor",
            "type":"Services"
        }
    ],
    "sg:phone":"+1 517 552 0890",
    "sg:postcode":"48843",
    "sg:province":"MI",
    "wof:name":"Peter C Spathis DC",
    "wof:placetype":"venue"
},
  "geometry": {"coordinates":[-83.920067,42.604677],"type":"Point"}
}