{
  "type": "Feature",
  "properties": {
    "iso:country":"US",
    "sg:address":"20700 Civic Center Dr",
    "sg:city":"Southfield",
    "sg:classifiers":[
        {
            "category":"Restaurant",
            "type":"Food & Drink"
        }
    ],
    "sg:phone":"+1 248 663 2335",
    "sg:postcode":"48076",
    "sg:province":"MI",
    "wof:name":"Hang Z Hou Qian Jiang Spg USA",
    "wof:placetype":"venue"
},
  "geometry": {"coordinates":[-83.248869,42.479744],"type":"Point"}
}