{
  "type": "Feature",
  "properties": {
    "iso:country":"US",
    "sg:address":"1317 Court St",
    "sg:city":"Saginaw",
    "sg:classifiers":[
        {
            "category":"Retail",
            "subcategory":"Repair Shop",
            "type":"Services"
        }
    ],
    "sg:phone":"+1 989 793 6511",
    "sg:postcode":"48602",
    "sg:province":"MI",
    "sg:tags":[
        "leather",
        "cleaning"
    ],
    "wof:name":"Realgood Cleaners & Shirt",
    "wof:placetype":"venue"
},
  "geometry": {"coordinates":[-83.971552,43.422794],"type":"Point"}
}