{
  "type": "Feature",
  "properties": {
    "iso:country":"US",
    "sg:address":"501 4th Ave",
    "sg:city":"Menominee",
    "sg:classifiers":[
        {
            "category":"Freight",
            "type":"Transportation"
        }
    ],
    "sg:phone":"+1 906 863 7812",
    "sg:postcode":"49858",
    "sg:province":"MI",
    "sg:tags":[
        "commercial",
        "storage"
    ],
    "wof:name":"K & K Warehousing",
    "wof:placetype":"venue"
},
  "geometry": {"coordinates":[-87.610395,45.101953],"type":"Point"}
}