{
  "type": "Feature",
  "properties": {
    "iso:country":"US",
    "sg:address":"2061 Cameo Dr",
    "sg:city":"Troy",
    "sg:classifiers":[
        {
            "category":"Professional",
            "subcategory":"Management & Consulting",
            "type":"Services"
        }
    ],
    "sg:phone":"+1 248 952 5469",
    "sg:postcode":"48098",
    "sg:province":"MI",
    "sg:tags":[
        "business"
    ],
    "wof:name":"Schultz Quality Consultants",
    "wof:placetype":"venue"
},
  "geometry": {"coordinates":[-83.188993,42.594551],"type":"Point"}
}