{
  "type": "Feature",
  "properties": {
    "iso:country":"US",
    "sg:address":"16188 Jenny Dr",
    "sg:city":"Macomb",
    "sg:classifiers":[
        {
            "category":"Professional",
            "subcategory":"Lawyer & Legal Services",
            "type":"Services"
        }
    ],
    "sg:phone":"+1 810 963 7666",
    "sg:postcode":"48042",
    "sg:province":"MI",
    "sg:tags":[
        "attorney"
    ],
    "wof:name":"Frank Cusumano",
    "wof:placetype":"venue"
},
  "geometry": {"coordinates":[-82.963713,42.694626],"type":"Point"}
}