{
  "type": "Feature",
  "properties": {
    "iso:country":"US",
    "sg:address":"515 S Washington Ave",
    "sg:city":"Royal Oak",
    "sg:classifiers":[
        {
            "category":"Shopping",
            "subcategory":"Gifts & Souvenirs",
            "type":"Retail Goods"
        }
    ],
    "sg:phone":"+1 248 336 9779",
    "sg:postcode":"48067",
    "sg:province":"MI",
    "sg:tags":[
        "basket",
        "parcel"
    ],
    "wof:name":"Bogart's Baskets & Gifts Inc",
    "wof:placetype":"venue"
},
  "geometry": {"coordinates":[-83.146456,42.485655],"type":"Point"}
}