{
  "type": "Feature",
  "properties": {
    "iso:country":"US",
    "sg:address":"5961 Beebe Ave",
    "sg:city":"Warren",
    "sg:classifiers":[
        {
            "category":"Communications",
            "type":"Services"
        },
        {
            "category":"Government",
            "subcategory":"Office",
            "type":"Public Place"
        }
    ],
    "sg:phone":"+1 586 268 2222",
    "sg:postcode":"48092",
    "sg:province":"MI",
    "sg:tags":[
        "general"
    ],
    "wof:name":"Warren Crime Comm",
    "wof:placetype":"venue"
},
  "geometry": {"coordinates":[-83.049483,42.525074],"type":"Point"}
}