{
  "type": "Feature",
  "properties": {
    "iso:country":"US",
    "sg:address":"1155 Hastings St",
    "sg:city":"Traverse City",
    "sg:classifiers":[
        {
            "category":"Manufacturing",
            "subcategory":"Toys & Sporting Goods",
            "type":"Manufacturing & Wholesale Goods"
        }
    ],
    "sg:phone":"+1 231 929 0598",
    "sg:postcode":"49686",
    "sg:province":"MI",
    "sg:tags":[
        "consulting",
        "business",
        "mfg"
    ],
    "wof:name":"Baum Research and Dev Co Inc",
    "wof:placetype":"venue"
},
  "geometry": {"coordinates":[-85.592715,44.745977],"type":"Point"}
}