{
  "type": "Feature",
  "properties": {
    "iso:country":"US",
    "sg:address":"23354 Gratiot Ave",
    "sg:city":"Eastpointe",
    "sg:classifiers":[
        {
            "category":"Real Estate",
            "subcategory":"Real Estate Agent",
            "type":"Services"
        }
    ],
    "sg:phone":"+1 586 778 8555",
    "sg:postcode":"48021",
    "sg:province":"MI",
    "wof:name":"Commvest Realty",
    "wof:placetype":"venue"
},
  "geometry": {"coordinates":[-82.954663,42.469168],"type":"Point"}
}