{
  "type": "Feature",
  "properties": {
    "iso:country":"US",
    "sg:address":"164 Cherry St",
    "sg:city":"Battle Creek",
    "sg:classifiers":[
        {
            "category":"Health Services",
            "subcategory":"Nursing And Care Facility",
            "type":"Services"
        },
        {
            "category":"Social Services",
            "subcategory":"Adult Care",
            "type":"Services"
        }
    ],
    "sg:phone":"+1 269 968 2888",
    "sg:postcode":"49017",
    "sg:province":"MI",
    "sg:tags":[
        "foster",
        "convalescent",
        "home"
    ],
    "wof:name":"Colonial Manor A F C",
    "wof:placetype":"venue"
},
  "geometry": {"coordinates":[-85.170464,42.320431],"type":"Point"}
}