{
  "type": "Feature",
  "properties": {
    "iso:country":"US",
    "sg:address":"4674 State St",
    "sg:city":"Saginaw",
    "sg:classifiers":[
        {
            "category":"Home & Garden",
            "subcategory":"Home Furnishings",
            "type":"Retail Goods"
        }
    ],
    "sg:phone":"+1 989 249 0337",
    "sg:postcode":"48603",
    "sg:province":"MI",
    "sg:tags":[
        "lighting",
        "fixture"
    ],
    "wof:name":"Heritage Lighting Inc",
    "wof:placetype":"venue"
},
  "geometry": {"coordinates":[-84.008079,43.43686],"type":"Point"}
}