{
  "type": "Feature",
  "properties": {
    "iso:country":"US",
    "sg:address":"4500 Marseilles St",
    "sg:city":"Detroit",
    "sg:classifiers":[
        {
            "category":"Social Services",
            "subcategory":"Child Care",
            "type":"Services"
        }
    ],
    "sg:phone":"+1 313 885 3320",
    "sg:postcode":"48224",
    "sg:province":"MI",
    "sg:tags":[
        "day"
    ],
    "wof:name":"Sunshine Street Nursery",
    "wof:placetype":"venue"
},
  "geometry": {"coordinates":[-82.92019999999999,42.40753],"type":"Point"}
}