{
  "type": "Feature",
  "properties": {
    "iso:country":"US",
    "sg:address":"23900 Bell Rd",
    "sg:city":"New Boston",
    "sg:classifiers":[
        {
            "category":"Restaurant",
            "type":"Food & Drink"
        }
    ],
    "sg:phone":"+1 734 753 3663",
    "sg:postcode":"48164",
    "sg:province":"MI",
    "sg:tags":[
        "pizza"
    ],
    "wof:name":"Manufacturing Research Center",
    "wof:placetype":"venue"
},
  "geometry": {"coordinates":[-83.382599,42.133099],"type":"Point"}
}