{
  "type": "Feature",
  "properties": {
    "iso:country":"US",
    "sg:address":"950 E 10 Mile Rd",
    "sg:city":"Hazel Park",
    "sg:classifiers":[
        {
            "category":"Manufacturing",
            "subcategory":"Tools & Machinery",
            "type":"Manufacturing & Wholesale Goods"
        }
    ],
    "sg:phone":"+1 248 543 0062",
    "sg:postcode":"48030",
    "sg:province":"MI",
    "sg:tags":[
        "machine",
        "shop"
    ],
    "wof:name":"D & D Boring",
    "wof:placetype":"venue"
},
  "geometry": {"coordinates":[-83.09515399999999,42.476144],"type":"Point"}
}