{
  "type": "Feature",
  "properties": {
    "iso:country":"US",
    "sg:address":"119 E Dwight Ave",
    "sg:city":"Oscoda",
    "sg:classifiers":[
        {
            "category":"Sports & Exercise",
            "subcategory":"Gym",
            "type":"Entertainment"
        }
    ],
    "sg:phone":"+1 989 739 0464",
    "sg:postcode":"48750",
    "sg:province":"MI",
    "sg:tags":[
        "club",
        "health",
        "studio",
        "gymnasium"
    ],
    "wof:name":"Huron Sports & Fitness",
    "wof:placetype":"venue"
},
  "geometry": {"coordinates":[-83.330071,44.419457],"type":"Point"}
}