{
  "type": "Feature",
  "properties": {
    "iso:country":"US",
    "sg:address":"7228 Miller Rd",
    "sg:city":"Manistee",
    "sg:classifiers":[
        {
            "category":"Organizations",
            "subcategory":"Community Association",
            "type":"Services"
        }
    ],
    "sg:phone":"+1 231 889 4489",
    "sg:postcode":"49660",
    "sg:province":"MI",
    "sg:tags":[
        "club"
    ],
    "wof:name":"Tosebo Club House LLC",
    "wof:placetype":"venue"
},
  "geometry": {"coordinates":[-86.242605,44.349858],"type":"Point"}
}