{
  "type": "Feature",
  "properties": {
    "iso:country":"US",
    "sg:address":"696 E Giles Rd",
    "sg:city":"Muskegon",
    "sg:classifiers":[
        {
            "category":"Professional",
            "subcategory":"Secretarial Services",
            "type":"Services"
        }
    ],
    "sg:phone":"+1 231 744 3931",
    "sg:postcode":"49445",
    "sg:province":"MI",
    "sg:tags":[
        "reporting"
    ],
    "wof:name":"Double TS",
    "wof:placetype":"venue"
},
  "geometry": {"coordinates":[-86.226063,43.278047],"type":"Point"}
}