{
  "type": "Feature",
  "properties": {
    "iso:country":"US",
    "sg:address":"30400 Telegraph Rd",
    "sg:city":"Bingham Farms",
    "sg:classifiers":[
        {
            "category":"Health Services",
            "subcategory":"Dentist",
            "type":"Services"
        }
    ],
    "sg:phone":"+1 248 647 7550",
    "sg:postcode":"48025",
    "sg:province":"MI",
    "sg:website":"www.greatexpressions.com",
    "wof:name":"Great Expressions Dental Centers",
    "wof:placetype":"venue"
},
  "geometry": {"coordinates":[-83.285312,42.510623],"type":"Point"}
}