{
  "type": "Feature",
  "properties": {
    "iso:country":"US",
    "sg:address":"31500 W 13 Mile Rd",
    "sg:city":"Farmington Hills",
    "sg:classifiers":[
        {
            "category":"Health Services",
            "subcategory":"Doctor",
            "type":"Services"
        },
        {
            "category":"Health Services",
            "subcategory":"Clinic",
            "type":"Services"
        }
    ],
    "sg:phone":"+1 248 855 9220",
    "sg:postcode":"48334",
    "sg:province":"MI",
    "sg:tags":[
        "counseling",
        "mental"
    ],
    "wof:name":"Carroll John Bradley PHD",
    "wof:placetype":"venue"
},
  "geometry": {"coordinates":[-83.360665,42.513782],"type":"Point"}
}