{
  "type": "Feature",
  "properties": {
    "iso:country":"US",
    "sg:address":"340 S Ford Blvd",
    "sg:city":"Ypsilanti",
    "sg:classifiers":[
        {
            "category":"Building & Trades",
            "subcategory":"Construction",
            "type":"Services"
        }
    ],
    "sg:phone":"+1 800 382 1982",
    "sg:postcode":"48198",
    "sg:province":"MI",
    "sg:tags":[
        "contractor"
    ],
    "wof:name":"Midwest Maintenance Service Inc",
    "wof:placetype":"venue"
},
  "geometry": {"coordinates":[-83.580223,42.238612],"type":"Point"}
}