{
  "type": "Feature",
  "properties": {
    "iso:country":"US",
    "sg:address":"8080 Haggerty Rd",
    "sg:city":"Belleville",
    "sg:classifiers":[
        {
            "category":"Home & Garden",
            "subcategory":"Hardware",
            "type":"Retail Goods"
        }
    ],
    "sg:phone":"+1 734 957 8080",
    "sg:postcode":"48111",
    "sg:province":"MI",
    "sg:tags":[
        "store"
    ],
    "sg:website":"www.acehardware.com",
    "wof:name":"Ace Hardware",
    "wof:placetype":"venue"
},
  "geometry": {"coordinates":[-83.445702,42.2439],"type":"Point"}
}