{
  "type": "Feature",
  "properties": {
    "iso:country":"US",
    "sg:address":"1790 School Rd",
    "sg:city":"Rochester",
    "sg:classifiers":[
        {
            "category":"Building & Trades",
            "subcategory":"Construction",
            "type":"Services"
        }
    ],
    "sg:phone":"+1 248 656 0609",
    "sg:postcode":"48307",
    "sg:province":"MI",
    "sg:tags":[
        "hanging",
        "contractor"
    ],
    "wof:name":"All Star Painting Co",
    "wof:placetype":"venue"
},
  "geometry": {"coordinates":[-83.099469,42.660639],"type":"Point"}
}