{
  "type": "Feature",
  "properties": {
    "iso:country":"US",
    "sg:address":"5485 Leatonville Rd",
    "sg:city":"Gladwin",
    "sg:classifiers":[
        {
            "category":"Home & Garden",
            "subcategory":"Garden Supply",
            "type":"Retail Goods"
        }
    ],
    "sg:phone":"+1 989 246 0483",
    "sg:postcode":"48624",
    "sg:province":"MI",
    "sg:tags":[
        "nurseryman"
    ],
    "wof:name":"Leatonville Gardens",
    "wof:placetype":"venue"
},
  "geometry": {"coordinates":[-84.417078,44.1206],"type":"Point"}
}