{
  "type": "Feature",
  "properties": {
    "iso:country":"US",
    "sg:address":"7277 Simons St",
    "sg:city":"Lexington",
    "sg:classifiers":[
        {
            "category":"Travel",
            "subcategory":"Hotels & Motels",
            "type":"Entertainment"
        }
    ],
    "sg:phone":"+1 810 359 2196",
    "sg:postcode":"48450",
    "sg:province":"MI",
    "sg:tags":[
        "breakfast",
        "accommodation",
        "bed"
    ],
    "wof:name":"Captain's Quarters Inn",
    "wof:placetype":"venue"
},
  "geometry": {"coordinates":[-82.529928,43.269563],"type":"Point"}
}