{
  "type": "Feature",
  "properties": {
    "iso:country":"US",
    "sg:address":"405 Lake Forest Rd",
    "sg:city":"Rochester Hills",
    "sg:classifiers":[
        {
            "category":"Building & Trades",
            "subcategory":"Construction",
            "type":"Services"
        }
    ],
    "sg:phone":"+1 248 656 7253",
    "sg:postcode":"48309",
    "sg:province":"MI",
    "sg:tags":[
        "planning",
        "remodeling",
        "kitchen"
    ],
    "wof:name":"Modern Kitchen & Bath",
    "wof:placetype":"venue"
},
  "geometry": {"coordinates":[-83.166618,42.676727],"type":"Point"}
}