{
  "type": "Feature",
  "properties": {
    "iso:country":"US",
    "sg:address":"4829 Chatsworth St",
    "sg:city":"Detroit",
    "sg:classifiers":[
        {
            "category":"Professional",
            "type":"Services"
        }
    ],
    "sg:phone":"+1 313 882 6587",
    "sg:postcode":"48224",
    "sg:province":"MI",
    "wof:name":"Noteworthy Productions",
    "wof:placetype":"venue"
},
  "geometry": {"coordinates":[-82.945644,42.399985],"type":"Point"}
}