{
  "type": "Feature",
  "properties": {
    "iso:country":"US",
    "sg:address":"1822 Thunderbird Dr",
    "sg:city":"Troy",
    "sg:classifiers":[
        {
            "category":"Wholesale",
            "subcategory":"Stationery",
            "type":"Manufacturing & Wholesale Goods"
        }
    ],
    "sg:phone":"+1 248 362 1260",
    "sg:postcode":"48084",
    "sg:province":"MI",
    "sg:tags":[
        "box",
        "fiber"
    ],
    "wof:name":"Jet Box Co",
    "wof:placetype":"venue"
},
  "geometry": {"coordinates":[-83.153991,42.550785],"type":"Point"}
}