{
  "type": "Feature",
  "properties": {
    "iso:country":"US",
    "sg:address":"215 E Parkdale Ave",
    "sg:city":"Manistee",
    "sg:classifiers":[
        {
            "category":"Personal",
            "subcategory":"Barber",
            "type":"Services"
        }
    ],
    "sg:phone":"+1 231 398 9708",
    "sg:postcode":"49660",
    "sg:province":"MI",
    "wof:name":"Parkdale Quick Cuts",
    "wof:placetype":"venue"
},
  "geometry": {"coordinates":[-86.296582,44.268541],"type":"Point"}
}