{
  "type": "Feature",
  "properties": {
    "iso:country":"US",
    "sg:address":"432 Edgewater Ave",
    "sg:city":"Algonac",
    "sg:classifiers":[
        {
            "category":"Retail",
            "subcategory":"Portrait Studio",
            "type":"Services"
        }
    ],
    "sg:phone":"+1 810 794 9792",
    "sg:postcode":"48001",
    "sg:province":"MI",
    "sg:tags":[
        "photo"
    ],
    "wof:name":"McKenzie Photography & Imaging",
    "wof:placetype":"venue"
},
  "geometry": {"coordinates":[-82.53936400000001,42.609552],"type":"Point"}
}