{
  "type": "Feature",
  "properties": {
    "iso:country":"US",
    "sg:address":"346 E Front St",
    "sg:city":"Traverse City",
    "sg:classifiers":[
        {
            "category":"Health Services",
            "subcategory":"Chiropractor",
            "type":"Services"
        }
    ],
    "sg:phone":"+1 231 995 0990",
    "sg:postcode":"49684",
    "sg:province":"MI",
    "wof:name":"Piche Family Chiropractic",
    "wof:placetype":"venue"
},
  "geometry": {"coordinates":[-85.616634,44.763987],"type":"Point"}
}