{
  "type": "Feature",
  "properties": {
    "iso:country":"US",
    "sg:address":"20 Mill Rd",
    "sg:city":"Barryton",
    "sg:classifiers":[
        {
            "category":"Wholesale",
            "subcategory":"Machinery & Supplies",
            "type":"Manufacturing & Wholesale Goods"
        }
    ],
    "sg:phone":"+1 989 382 7290",
    "sg:postcode":"49318",
    "sg:province":"MI",
    "sg:tags":[
        "crane",
        "derrick"
    ],
    "wof:name":"Carroll Crane Svc",
    "wof:placetype":"venue"
},
  "geometry": {"coordinates":[-85.81037999999999,43.249192],"type":"Point"}
}