{
  "type": "Feature",
  "properties": {
    "iso:country":"US",
    "sg:address":"875 W Beecher St",
    "sg:city":"Adrian",
    "sg:classifiers":[
        {
            "category":"Retail",
            "subcategory":"Car Wash",
            "type":"Services"
        }
    ],
    "sg:phone":"+1 517 263 1133",
    "sg:postcode":"49221",
    "sg:province":"MI",
    "sg:tags":[
        "carwash"
    ],
    "wof:name":"Brighter Image Detailing",
    "wof:placetype":"venue"
},
  "geometry": {"coordinates":[-84.056296,41.889138],"type":"Point"}
}