{
  "type": "Feature",
  "properties": {
    "iso:country":"US",
    "sg:address":"23280 Forest St",
    "sg:city":"Oak Park",
    "sg:classifiers":[
        {
            "category":"Professional",
            "subcategory":"Management & Consulting",
            "type":"Services"
        }
    ],
    "sg:phone":"+1 313 399 4923",
    "sg:postcode":"48237",
    "sg:province":"MI",
    "sg:tags":[
        "business"
    ],
    "wof:name":"Professional Planning Svc",
    "wof:placetype":"venue"
},
  "geometry": {"coordinates":[-83.154788,42.462873],"type":"Point"}
}