{
  "type": "Feature",
  "properties": {
    "iso:country":"US",
    "sg:address":"1605 N Towerline Rd",
    "sg:city":"Saginaw",
    "sg:classifiers":[
        {
            "category":"Recreation",
            "type":"Entertainment"
        }
    ],
    "sg:phone":"+1 989 752 7413",
    "sg:postcode":"48601",
    "sg:province":"MI",
    "sg:tags":[
        "parks"
    ],
    "wof:name":"Buena Vista Kuffman Park",
    "wof:placetype":"venue"
},
  "geometry": {"coordinates":[-83.876103,43.43446],"type":"Point"}
}