{
  "type": "Feature",
  "properties": {
    "iso:country":"US",
    "sg:address":"1808 Hawthorne Ave",
    "sg:city":"St Joseph",
    "sg:classifiers":[
        {
            "category":"Manufacturing",
            "subcategory":"Tools & Machinery",
            "type":"Manufacturing & Wholesale Goods"
        }
    ],
    "sg:phone":"+1 269 983 3183",
    "sg:postcode":"49085",
    "sg:province":"MI",
    "sg:tags":[
        "machine",
        "shop"
    ],
    "wof:name":"Reschke Enterprise",
    "wof:placetype":"venue"
},
  "geometry": {"coordinates":[-86.495408,42.072606],"type":"Point"}
}