{
  "type": "Feature",
  "properties": {
    "iso:country":"US",
    "sg:address":"2259 Traversefield Dr",
    "sg:city":"Traverse City",
    "sg:classifiers":[
        {
            "category":"Wholesale",
            "subcategory":"Vending Machines",
            "type":"Manufacturing & Wholesale Goods"
        }
    ],
    "sg:phone":"+1 231 947 1500",
    "sg:postcode":"49686",
    "sg:province":"MI",
    "wof:name":"Canteen Service Co",
    "wof:placetype":"venue"
},
  "geometry": {"coordinates":[-85.587414,44.716622],"type":"Point"}
}