{
  "type": "Feature",
  "properties": {
    "iso:country":"US",
    "sg:address":"7068 US Hwy 41",
    "sg:city":"Champion",
    "sg:classifiers":[
        {
            "category":"Building & Trades",
            "subcategory":"Construction",
            "type":"Services"
        }
    ],
    "sg:phone":"+1 906 339 2440",
    "sg:postcode":"49814",
    "sg:province":"MI",
    "sg:tags":[
        "general",
        "contractor"
    ],
    "wof:name":"Fence Lake Construction Co",
    "wof:placetype":"venue"
},
  "geometry": {"coordinates":[-87.97535499999999,46.517646],"type":"Point"}
}