{
  "type": "Feature",
  "properties": {
    "iso:country":"US",
    "sg:address":"736 W Marshall St",
    "sg:city":"Ferndale",
    "sg:classifiers":[
        {
            "category":"Building & Trades",
            "subcategory":"Construction",
            "type":"Services"
        }
    ],
    "sg:phone":"+1 248 545 1443",
    "sg:postcode":"48220",
    "sg:province":"MI",
    "sg:tags":[
        "house"
    ],
    "wof:name":"Tektonia",
    "wof:placetype":"venue"
},
  "geometry": {"coordinates":[-83.14244100000001,42.454871],"type":"Point"}
}