{
  "type": "Feature",
  "properties": {
    "iso:country":"US",
    "sg:address":"1880 S College Rd",
    "sg:city":"Mason",
    "sg:classifiers":[
        {
            "category":"Retail",
            "subcategory":"Repair Shop",
            "type":"Services"
        }
    ],
    "sg:phone":"+1 517 628 3014",
    "sg:postcode":"48854",
    "sg:province":"MI",
    "wof:name":"A & H Repair",
    "wof:placetype":"venue"
},
  "geometry": {"coordinates":[-84.483087,42.527857],"type":"Point"}
}