{
  "type": "Feature",
  "properties": {
    "iso:country":"US",
    "sg:address":"721 Washington Ave",
    "sg:city":"Bay City",
    "sg:classifiers":[
        {
            "category":"Health Services",
            "subcategory":"Doctor",
            "type":"Services"
        }
    ],
    "sg:phone":"+1 989 895 8122",
    "sg:postcode":"48708",
    "sg:province":"MI",
    "sg:tags":[
        "dentist"
    ],
    "wof:name":"Kli-Anne J Shelegey DDS",
    "wof:placetype":"venue"
},
  "geometry": {"coordinates":[-83.88789199999999,43.59785],"type":"Point"}
}