{
  "type": "Feature",
  "properties": {
    "iso:country":"US",
    "sg:address":"102 State Rd",
    "sg:city":"Dowagiac",
    "sg:classifiers":[
        {
            "category":"Shopping",
            "subcategory":"Pharmacy",
            "type":"Retail Goods"
        }
    ],
    "sg:phone":"+1 269 782 2962",
    "sg:postcode":"49047",
    "sg:province":"MI",
    "wof:name":"Rite Aid Pharmacy",
    "wof:placetype":"venue"
},
  "geometry": {"coordinates":[-86.12401699999999,41.98426],"type":"Point"}
}