{
  "type": "Feature",
  "properties": {
    "iso:country":"US",
    "sg:address":"440 West Dr N",
    "sg:city":"Marshall",
    "sg:classifiers":[
        {
            "category":"Social Services",
            "subcategory":"Child Care",
            "type":"Services"
        }
    ],
    "sg:phone":"+1 269 781 5842",
    "sg:postcode":"49068",
    "sg:province":"MI",
    "sg:tags":[
        "organization",
        "religious",
        "day"
    ],
    "wof:name":"Christ Lutheran Preschool",
    "wof:placetype":"venue"
},
  "geometry": {"coordinates":[-84.98362899999999,42.287227],"type":"Point"}
}