{
  "type": "Feature",
  "properties": {
    "iso:country":"US",
    "sg:address":"19510 Nicke St",
    "sg:city":"Clinton Township",
    "sg:classifiers":[
        {
            "category":"Arts & Performance",
            "subcategory":"Theater",
            "type":"Entertainment"
        }
    ],
    "sg:phone":"+1 586 790 7429",
    "sg:postcode":"48035",
    "sg:province":"MI",
    "sg:tags":[
        "group"
    ],
    "wof:name":"Highest Praise",
    "wof:placetype":"venue"
},
  "geometry": {"coordinates":[-82.91976099999999,42.540184],"type":"Point"}
}