{
  "type": "Feature",
  "properties": {
    "iso:country":"US",
    "sg:address":"201 N Bridge St",
    "sg:city":"Bellaire",
    "sg:classifiers":[
        {
            "category":"Restaurant",
            "type":"Food & Drink"
        }
    ],
    "sg:phone":"+1 231 533 8538",
    "sg:postcode":"49615",
    "sg:province":"MI",
    "wof:name":"Ruthie's Chicken & Dairy Twist",
    "wof:placetype":"venue"
},
  "geometry": {"coordinates":[-85.210076,44.977223],"type":"Point"}
}