{
  "type": "Feature",
  "properties": {
    "iso:country":"US",
    "sg:address":"1715 Northfield Dr",
    "sg:city":"Rochester Hills",
    "sg:classifiers":[
        {
            "category":"Social Services",
            "type":"Services"
        }
    ],
    "sg:phone":"+1 248 852 0376",
    "sg:postcode":"48309",
    "sg:province":"MI",
    "sg:tags":[
        "instruction",
        "health",
        "care"
    ],
    "wof:name":"Guardian Angel",
    "wof:placetype":"venue"
},
  "geometry": {"coordinates":[-83.164703,42.638608],"type":"Point"}
}