{
  "type": "Feature",
  "properties": {
    "iso:country":"US",
    "sg:address":"2050 Port City Blvd",
    "sg:city":"Muskegon",
    "sg:classifiers":[
        {
            "category":"Manufacturing",
            "subcategory":"Rubber & Plastics",
            "type":"Manufacturing & Wholesale Goods"
        }
    ],
    "sg:phone":"+1 231 777 2645",
    "sg:postcode":"49442",
    "sg:province":"MI",
    "sg:website":"www.adacplastics.com",
    "wof:name":"Adac Plastics",
    "wof:placetype":"venue"
},
  "geometry": {"coordinates":[-86.195587,43.214362],"type":"Point"}
}