{
  "type": "Feature",
  "properties": {
    "iso:country":"US",
    "sg:address":"801 S Adams Rd",
    "sg:city":"Birmingham",
    "sg:classifiers":[
        {
            "category":"Communications",
            "subcategory":"Film & Video Production",
            "type":"Services"
        }
    ],
    "sg:phone":"+1 248 645 6336",
    "sg:postcode":"48009",
    "sg:province":"MI",
    "sg:tags":[
        "motion",
        "picture"
    ],
    "wof:name":"David Pennock",
    "wof:placetype":"venue"
},
  "geometry": {"coordinates":[-83.205439,42.540701],"type":"Point"}
}