{
  "type": "Feature",
  "properties": {
    "iso:country":"US",
    "sg:address":"5725 16th Ave",
    "sg:city":"Hudsonville",
    "sg:classifiers":[
        {
            "category":"Professional",
            "type":"Services"
        }
    ],
    "sg:phone":"+1 616 457 9445",
    "sg:postcode":"49426",
    "sg:province":"MI",
    "sg:tags":[
        "establishment"
    ],
    "wof:name":"RJG Inc",
    "wof:placetype":"venue"
},
  "geometry": {"coordinates":[-85.821602,42.874624],"type":"Point"}
}