{
  "type": "Feature",
  "properties": {
    "iso:country":"US",
    "sg:address":"626 Phillips Ave",
    "sg:city":"Clawson",
    "sg:classifiers":[
        {
            "category":"Social Services",
            "subcategory":"Child Care",
            "type":"Services"
        }
    ],
    "sg:phone":"+1 248 280 1380",
    "sg:postcode":"48017",
    "sg:province":"MI",
    "sg:tags":[
        "school",
        "nursery"
    ],
    "wof:name":"Sunny Skies Inc",
    "wof:placetype":"venue"
},
  "geometry": {"coordinates":[-83.15421600000001,42.537794],"type":"Point"}
}