{
  "type": "Feature",
  "properties": {
    "iso:country":"US",
    "sg:address":"411 E Genesee Ave",
    "sg:city":"Saginaw",
    "sg:classifiers":[
        {
            "category":"Government",
            "subcategory":"Fire Station",
            "type":"Public Place"
        }
    ],
    "sg:phone":"+1 989 758 1553",
    "sg:postcode":"48607",
    "sg:province":"MI",
    "sg:tags":[
        "protection"
    ],
    "wof:name":"Saginaw Region II Ofs",
    "wof:placetype":"venue"
},
  "geometry": {"coordinates":[-83.936205,43.432668],"type":"Point"}
}