{
  "type": "Feature",
  "properties": {
    "iso:country":"US",
    "sg:address":"21455 Melrose Ave",
    "sg:city":"Southfield",
    "sg:classifiers":[
        {
            "category":"Professional",
            "subcategory":"Detective & Security Services",
            "type":"Services"
        }
    ],
    "sg:phone":"+1 248 353 7617",
    "sg:postcode":"48075",
    "sg:province":"MI",
    "sg:tags":[
        "home",
        "electrical"
    ],
    "wof:name":"ADT Security Services Inc",
    "wof:placetype":"venue"
},
  "geometry": {"coordinates":[-83.259314,42.447899],"type":"Point"}
}