{
  "type": "Feature",
  "properties": {
    "iso:country":"US",
    "sg:address":"2112 US Hwy 41",
    "sg:city":"Marquette",
    "sg:classifiers":[
        {
            "category":"Health Services",
            "subcategory":"Clinic",
            "type":"Services"
        }
    ],
    "sg:phone":"+1 906 226 9924",
    "sg:postcode":"49855",
    "sg:province":"MI",
    "wof:name":"Feet First",
    "wof:placetype":"venue"
},
  "geometry": {"coordinates":[-87.37300500000001,46.509771],"type":"Point"}
}