{
  "type": "Feature",
  "properties": {
    "iso:country":"US",
    "sg:address":"8940 Dexter Pinckney Rd",
    "sg:city":"Pinckney",
    "sg:classifiers":[
        {
            "category":"Autos & Motor Vehicles",
            "subcategory":"Boat Sales",
            "type":"Retail Goods"
        }
    ],
    "sg:phone":"+1 734 426 2467",
    "sg:postcode":"48169",
    "sg:province":"MI",
    "sg:tags":[
        "dealer",
        "sales"
    ],
    "wof:name":"Thomas F Ehman",
    "wof:placetype":"venue"
},
  "geometry": {"coordinates":[-83.91816900000001,42.414324],"type":"Point"}
}