{
  "type": "Feature",
  "properties": {
    "iso:country":"US",
    "sg:address":"4130 Crawford Rd",
    "sg:city":"Dryden",
    "sg:classifiers":[
        {
            "category":"Professional",
            "subcategory":"Engineering",
            "type":"Services"
        }
    ],
    "sg:phone":"+1 810 796 3751",
    "sg:postcode":"48428",
    "sg:province":"MI",
    "wof:name":"Trillium Corporation",
    "wof:placetype":"venue"
},
  "geometry": {"coordinates":[-83.173625,42.93024],"type":"Point"}
}