{
  "type": "Feature",
  "properties": {
    "iso:country":"US",
    "sg:address":"43593 Nowland Dr",
    "sg:city":"Canton",
    "sg:classifiers":[
        {
            "category":"Professional",
            "subcategory":"Business Services",
            "type":"Services"
        }
    ],
    "sg:phone":"+1 734 331 2020",
    "sg:postcode":"48188",
    "sg:province":"MI",
    "wof:name":"Advantage Marketing Solutions",
    "wof:placetype":"venue"
},
  "geometry": {"coordinates":[-83.47254,42.295371],"type":"Point"}
}