{
  "type": "Feature",
  "properties": {
    "iso:country":"US",
    "sg:address":"44763 Charnwood Dr",
    "sg:city":"Plymouth",
    "sg:classifiers":[
        {
            "category":"Real Estate",
            "subcategory":"Real Estate Agent",
            "type":"Services"
        }
    ],
    "sg:phone":"+1 734 451 8620",
    "sg:postcode":"48170",
    "sg:province":"MI",
    "wof:name":"Prudential",
    "wof:placetype":"venue"
},
  "geometry": {"coordinates":[-83.48160900000001,42.364872],"type":"Point"}
}