{
  "type": "Feature",
  "properties": {
    "iso:country":"US",
    "sg:address":"810 W Bellevue St",
    "sg:city":"Leslie",
    "sg:classifiers":[
        {
            "category":"Banks & Credit Unions",
            "subcategory":"Bank",
            "type":"Services"
        }
    ],
    "sg:phone":"+1 517 589 0500",
    "sg:postcode":"49251",
    "sg:province":"MI",
    "wof:name":"Mason State Bank",
    "wof:placetype":"venue"
},
  "geometry": {"coordinates":[-84.440912,42.451235],"type":"Point"}
}