{
  "type": "Feature",
  "properties": {
    "iso:country":"US",
    "sg:address":"1075 Suncrest Dr",
    "sg:city":"Lapeer",
    "sg:classifiers":[
        {
            "category":"Government",
            "subcategory":"Office",
            "type":"Public Place"
        }
    ],
    "sg:phone":"+1 810 667 0420",
    "sg:postcode":"48446",
    "sg:province":"MI",
    "sg:tags":[
        "development"
    ],
    "wof:name":"Construction Code Authority",
    "wof:placetype":"venue"
},
  "geometry": {"coordinates":[-83.333339,43.060377],"type":"Point"}
}