{
  "type": "Feature",
  "properties": {
    "iso:country":"US",
    "sg:address":"2545 Spring Arbor Rd",
    "sg:city":"Jackson",
    "sg:classifiers":[
        {
            "category":"Banks & Credit Unions",
            "subcategory":"Bank",
            "type":"Services"
        }
    ],
    "sg:phone":"+1 517 784 5556",
    "sg:postcode":"49203",
    "sg:province":"MI",
    "sg:tags":[
        "small",
        "company",
        "finance",
        "business"
    ],
    "wof:name":"Horizon Bidco Investment Co",
    "wof:placetype":"venue"
},
  "geometry": {"coordinates":[-84.44867499999999,42.229644],"type":"Point"}
}