{
  "type": "Feature",
  "properties": {
    "iso:country":"US",
    "sg:address":"20671 Ecorse Rd",
    "sg:city":"Taylor",
    "sg:classifiers":[
        {
            "category":"Building & Trades",
            "subcategory":"Equipment Rental",
            "type":"Services"
        }
    ],
    "sg:phone":"+1 313 382 7484",
    "sg:postcode":"48180",
    "sg:province":"MI",
    "sg:tags":[
        "party",
        "supply"
    ],
    "wof:name":"Olsons Party Rental",
    "wof:placetype":"venue"
},
  "geometry": {"coordinates":[-83.23892499999999,42.256186],"type":"Point"}
}