{
  "type": "Feature",
  "properties": {
    "iso:country":"US",
    "sg:address":"346 S Main St",
    "sg:city":"Plymouth",
    "sg:classifiers":[
        {
            "category":"Professional",
            "subcategory":"Art Services",
            "type":"Services"
        }
    ],
    "sg:phone":"+1 734 414 8880",
    "sg:postcode":"48170",
    "sg:province":"MI",
    "sg:tags":[
        "commercial",
        "design"
    ],
    "wof:name":"Terran Design Inc",
    "wof:placetype":"venue"
},
  "geometry": {"coordinates":[-83.46938299999999,42.370252],"type":"Point"}
}