{
  "type": "Feature",
  "properties": {
    "iso:country":"US",
    "sg:address":"1300 S Wheeler St",
    "sg:city":"Saginaw",
    "sg:classifiers":[
        {
            "category":"Building & Trades",
            "subcategory":"Construction",
            "type":"Services"
        }
    ],
    "sg:phone":"+1 989 792 9489",
    "sg:postcode":"48602",
    "sg:province":"MI",
    "sg:tags":[
        "builder",
        "repairer",
        "chimney"
    ],
    "wof:name":"Tim's Chimney Svc",
    "wof:placetype":"venue"
},
  "geometry": {"coordinates":[-83.99146399999999,43.403414],"type":"Point"}
}