{
  "type": "Feature",
  "properties": {
    "iso:country":"US",
    "sg:address":"56 Macomb Pl",
    "sg:city":"Mount Clemens",
    "sg:classifiers":[
        {
            "category":"Professional",
            "subcategory":"Computer Services",
            "type":"Services"
        }
    ],
    "sg:phone":"+1 586 783 8000",
    "sg:postcode":"48043",
    "sg:province":"MI",
    "sg:tags":[
        "programing",
        "custom"
    ],
    "wof:name":"Robot Support Inc",
    "wof:placetype":"venue"
},
  "geometry": {"coordinates":[-82.878641,42.598515],"type":"Point"}
}