{
  "type": "Feature",
  "properties": {
    "iso:country":"US",
    "sg:address":"1900 Snedecker Rd",
    "sg:city":"Williamston",
    "sg:classifiers":[
        {
            "category":"Professional",
            "subcategory":"Management & Consulting",
            "type":"Services"
        }
    ],
    "sg:phone":"+1 517 655 9318",
    "sg:postcode":"48895",
    "sg:province":"MI",
    "sg:tags":[
        "marketing",
        "consultant"
    ],
    "wof:name":"Focus Inc",
    "wof:placetype":"venue"
},
  "geometry": {"coordinates":[-84.245867,42.637731],"type":"Point"}
}