{
  "type": "Feature",
  "properties": {
    "iso:country":"US",
    "sg:address":"2541 N M-65",
    "sg:city":"Curran",
    "sg:classifiers":[
        {
            "category":"Autos & Motor Vehicles",
            "subcategory":"Fuel & Gas Station",
            "type":"Retail Goods"
        }
    ],
    "sg:phone":"+1 989 848 2344",
    "sg:postcode":"48728",
    "sg:province":"MI",
    "sg:tags":[
        "oil"
    ],
    "wof:name":"Curran BP Inc",
    "wof:placetype":"venue"
},
  "geometry": {"coordinates":[-83.807348,44.731196],"type":"Point"}
}