{
  "type": "Feature",
  "properties": {
    "iso:country":"US",
    "sg:address":"10545 Whitby Ct",
    "sg:city":"Clarkston",
    "sg:classifiers":[
        {
            "category":"Manufacturing",
            "subcategory":"Metals",
            "type":"Manufacturing & Wholesale Goods"
        }
    ],
    "sg:phone":"+1 248 236 9376",
    "sg:postcode":"48348",
    "sg:province":"MI",
    "sg:tags":[
        "processing",
        "powder"
    ],
    "wof:name":"JTA Industries",
    "wof:placetype":"venue"
},
  "geometry": {"coordinates":[-83.370507,42.792413],"type":"Point"}
}