{
  "type": "Feature",
  "properties": {
    "iso:country":"US",
    "sg:address":"13775 Grandpoint Dr",
    "sg:city":"Cement City",
    "sg:classifiers":[
        {
            "category":"Professional",
            "subcategory":"Management & Consulting",
            "type":"Services"
        },
        {
            "category":"Wholesale",
            "subcategory":"Durable Goods & Equipment",
            "type":"Manufacturing & Wholesale Goods"
        }
    ],
    "sg:phone":"+1 517 688 3250",
    "sg:postcode":"49282",
    "sg:province":"MI",
    "sg:tags":[
        "representative",
        "business",
        "manufacturer"
    ],
    "wof:name":"Davison & Associates",
    "wof:placetype":"venue"
},
  "geometry": {"coordinates":[-84.385244,42.055981],"type":"Point"}
}