{
  "type": "Feature",
  "properties": {
    "iso:country":"US",
    "sg:address":"643 S Waverly Rd",
    "sg:city":"Holland",
    "sg:classifiers":[
        {
            "category":"Professional",
            "subcategory":"Management & Consulting",
            "type":"Services"
        }
    ],
    "sg:phone":"+1 616 395 4600",
    "sg:postcode":"49423",
    "sg:province":"MI",
    "wof:name":"Holland Campus",
    "wof:placetype":"venue"
},
  "geometry": {"coordinates":[-86.077338,42.773432],"type":"Point"}
}