{
  "type": "Feature",
  "properties": {
    "iso:country":"US",
    "sg:address":"2620 Cox Rd",
    "sg:city":"St Clair",
    "sg:classifiers":[
        {
            "category":"Building & Trades",
            "subcategory":"Construction",
            "type":"Services"
        }
    ],
    "sg:phone":"+1 810 329 8566",
    "sg:postcode":"48079",
    "sg:province":"MI",
    "sg:tags":[
        "home",
        "builder"
    ],
    "wof:name":"Christopher Building Inc",
    "wof:placetype":"venue"
},
  "geometry": {"coordinates":[-82.509264,42.827876],"type":"Point"}
}