{
  "type": "Feature",
  "properties": {
    "iso:country":"US",
    "sg:address":"3450 Pleasant Valley Ave",
    "sg:city":"Boyne City",
    "sg:classifiers":[
        {
            "category":"Home & Garden",
            "subcategory":"Garden Supply",
            "type":"Retail Goods"
        }
    ],
    "sg:phone":"+1 231 582 6460",
    "sg:postcode":"49712",
    "sg:province":"MI",
    "sg:tags":[
        "sprinkler"
    ],
    "wof:name":"Haley Sprinkler Systems",
    "wof:placetype":"venue"
},
  "geometry": {"coordinates":[-85.024034,45.159434],"type":"Point"}
}