{
  "type": "Feature",
  "properties": {
    "iso:country":"US",
    "sg:address":"248 Southbound Gratiot Ave",
    "sg:city":"Mount Clemens",
    "sg:classifiers":[
        {
            "category":"Personal",
            "subcategory":"Beauty Salon",
            "type":"Services"
        }
    ],
    "sg:phone":"+1 586 465 2395",
    "sg:postcode":"48043",
    "sg:province":"MI",
    "sg:tags":[
        "shop"
    ],
    "wof:name":"Best Nail",
    "wof:placetype":"venue"
},
  "geometry": {"coordinates":[-82.882119,42.58923],"type":"Point"}
}