{
  "type": "Feature",
  "properties": {
    "iso:country":"US",
    "sg:address":"935 W Chisholm St",
    "sg:city":"Alpena",
    "sg:classifiers":[
        {
            "category":"Shopping",
            "subcategory":"Discount & Variety Stores",
            "type":"Retail Goods"
        }
    ],
    "sg:phone":"+1 989 354 4620",
    "sg:postcode":"49707",
    "sg:province":"MI",
    "sg:tags":[
        "merchandise",
        "general"
    ],
    "wof:name":"Joseph S Zolnierek Inc",
    "wof:placetype":"venue"
},
  "geometry": {"coordinates":[-83.44358,45.070851],"type":"Point"}
}