{
  "type": "Feature",
  "properties": {
    "iso:country":"US",
    "sg:address":"1455 Fuller Ave SE",
    "sg:city":"Grand Rapids",
    "sg:classifiers":[
        {
            "category":"Wholesale",
            "subcategory":"Furniture",
            "type":"Manufacturing & Wholesale Goods"
        }
    ],
    "sg:phone":"+1 616 245 5447",
    "sg:postcode":"49507",
    "sg:province":"MI",
    "sg:website":"www.ridemotorcycle.com",
    "wof:name":"Source Distribution Inc",
    "wof:placetype":"venue"
},
  "geometry": {"coordinates":[-85.638683,42.937119],"type":"Point"}
}