{
  "type": "Feature",
  "properties": {
    "iso:country":"US",
    "sg:address":"7900 Ida St",
    "sg:city":"Ida",
    "sg:classifiers":[
        {
            "category":"Education",
            "subcategory":"School",
            "type":"Public Place"
        }
    ],
    "sg:phone":"+1 734 269 3875",
    "sg:postcode":"48140",
    "sg:province":"MI",
    "sg:tags":[
        "academic",
        "special"
    ],
    "wof:name":"Ida Schools Hearing Impaired",
    "wof:placetype":"venue"
},
  "geometry": {"coordinates":[-83.57074299999999,41.907606],"type":"Point"}
}