{
  "type": "Feature",
  "properties": {
    "iso:country":"US",
    "sg:address":"818 W State St",
    "sg:city":"Hastings",
    "sg:classifiers":[
        {
            "category":"Personal",
            "subcategory":"Beauty Salon",
            "type":"Services"
        }
    ],
    "sg:phone":"+1 269 948 9470",
    "sg:postcode":"49058",
    "sg:province":"MI",
    "sg:tags":[
        "shop"
    ],
    "wof:name":"Fiesta Hair & Tanning",
    "wof:placetype":"venue"
},
  "geometry": {"coordinates":[-85.300588,42.648581],"type":"Point"}
}