{
  "type": "Feature",
  "properties": {
    "iso:country":"US",
    "sg:address":"5045 W Jefferson Ave",
    "sg:city":"Trenton",
    "sg:classifiers":[
        {
            "category":"Manufacturing",
            "subcategory":"Chemicals & Compounds",
            "type":"Manufacturing & Wholesale Goods"
        }
    ],
    "sg:phone":"+1 734 671 4615",
    "sg:postcode":"48183",
    "sg:province":"MI",
    "sg:tags":[
        "fertilizer",
        "mfg"
    ],
    "wof:name":"Astaris LLC",
    "wof:placetype":"venue"
},
  "geometry": {"coordinates":[-83.186967,42.123416],"type":"Point"}
}