{
  "type": "Feature",
  "properties": {
    "iso:country":"US",
    "sg:address":"57868 Territorial Rd",
    "sg:city":"Lawrence",
    "sg:classifiers":[
        {
            "category":"Professional",
            "subcategory":"Computer Services",
            "type":"Services"
        }
    ],
    "sg:phone":"+1 269 657 2634",
    "sg:postcode":"49064",
    "sg:province":"MI",
    "sg:tags":[
        "datum"
    ],
    "wof:name":"Steven Areaux",
    "wof:placetype":"venue"
},
  "geometry": {"coordinates":[-85.995418,42.207659],"type":"Point"}
}