{
  "type": "Feature",
  "properties": {
    "iso:country":"US",
    "sg:address":"11 S 4th St",
    "sg:city":"L Anse",
    "sg:classifiers":[
        {
            "category":"Organizations",
            "subcategory":"Non-profit Organization",
            "type":"Services"
        },
        {
            "category":"Social Services",
            "type":"Services"
        }
    ],
    "sg:phone":"+1 906 524 5017",
    "sg:postcode":"49946",
    "sg:province":"MI",
    "wof:name":"Baraga County Shelter Home",
    "wof:placetype":"venue"
},
  "geometry": {"coordinates":[-88.452732,46.756343],"type":"Point"}
}