{
  "type": "Feature",
  "properties": {
    "iso:country":"US",
    "sg:address":"32389 John R Rd",
    "sg:city":"Madison Heights",
    "sg:classifiers":[
        {
            "category":"Shopping",
            "subcategory":"Clothing, Apparel, & Fashions",
            "type":"Retail Goods"
        }
    ],
    "sg:phone":"+1 248 588 1220",
    "sg:postcode":"48071",
    "sg:province":"MI",
    "sg:tags":[
        "lingerie"
    ],
    "wof:name":"Lingerie Etc",
    "wof:placetype":"venue"
},
  "geometry": {"coordinates":[-83.106979,42.531254],"type":"Point"}
}