{
  "type": "Feature",
  "properties": {
    "iso:country":"US",
    "sg:address":"4 Woodside Park Blvd",
    "sg:city":"Pleasant Ridge",
    "sg:classifiers":[
        {
            "category":"Freight",
            "type":"Transportation"
        }
    ],
    "sg:phone":"+1 248 546 7059",
    "sg:postcode":"48069",
    "sg:province":"MI",
    "sg:tags":[
        "special"
    ],
    "wof:name":"Designers Partner",
    "wof:placetype":"venue"
},
  "geometry": {"coordinates":[-83.15337100000001,42.473647],"type":"Point"}
}