{
  "type": "Feature",
  "properties": {
    "iso:country":"US",
    "sg:address":"301 S Michigan Ave",
    "sg:city":"Hastings",
    "sg:classifiers":[
        {
            "category":"Education",
            "subcategory":"Dance Studio",
            "type":"Public Place"
        }
    ],
    "sg:phone":"+1 269 945 0421",
    "sg:postcode":"49058",
    "sg:province":"MI",
    "sg:tags":[
        "instruction",
        "dancing"
    ],
    "wof:name":"Expressions Dance Ctr",
    "wof:placetype":"venue"
},
  "geometry": {"coordinates":[-85.286107,42.646861],"type":"Point"}
}