{
  "type": "Feature",
  "properties": {
    "iso:country":"US",
    "sg:address":"4322 Cooper Ave",
    "sg:city":"Royal Oak",
    "sg:classifiers":[
        {
            "category":"Building & Trades",
            "subcategory":"Construction",
            "type":"Services"
        }
    ],
    "sg:phone":"+1 248 554 9769",
    "sg:postcode":"48073",
    "sg:province":"MI",
    "sg:tags":[
        "house"
    ],
    "wof:name":"Remodeling 8 Scotty Const",
    "wof:placetype":"venue"
},
  "geometry": {"coordinates":[-83.194216,42.528031],"type":"Point"}
}