{
  "type": "Feature",
  "properties": {
    "iso:country":"US",
    "sg:address":"201 E Grand River Ave",
    "sg:city":"Brighton",
    "sg:classifiers":[
        {
            "category":"Real Estate",
            "subcategory":"Real Estate Agent",
            "type":"Services"
        }
    ],
    "sg:phone":"+1 810 227 1311",
    "sg:postcode":"48116",
    "sg:province":"MI",
    "wof:name":"Heritage/Better HMS & Gdn RE",
    "wof:placetype":"venue"
},
  "geometry": {"coordinates":[-83.77989599999999,42.528777],"type":"Point"}
}