{
  "type": "Feature",
  "properties": {
    "iso:country":"US",
    "sg:address":"550 W Western Ave",
    "sg:city":"Muskegon",
    "sg:classifiers":[
        {
            "category":"Real Estate",
            "subcategory":"Architect",
            "type":"Services"
        }
    ],
    "sg:phone":"+1 231 725 0003",
    "sg:postcode":"49440",
    "sg:province":"MI",
    "wof:name":"Richard C Borgeson",
    "wof:placetype":"venue"
},
  "geometry": {"coordinates":[-86.25588399999999,43.233695],"type":"Point"}
}