{
  "type": "Feature",
  "properties": {
    "iso:country":"US",
    "sg:address":"2293 S Porter Rd",
    "sg:city":"Breckenridge",
    "sg:classifiers":[
        {
            "category":"Building & Trades",
            "subcategory":"Construction",
            "type":"Services"
        }
    ],
    "sg:phone":"+1 989 842 1513",
    "sg:postcode":"48615",
    "sg:province":"MI",
    "sg:tags":[
        "house"
    ],
    "wof:name":"Young Construction",
    "wof:placetype":"venue"
},
  "geometry": {"coordinates":[-84.45922299999999,43.545907],"type":"Point"}
}