{
  "type": "Feature",
  "properties": {
    "iso:country":"US",
    "sg:address":"40480 Grand River Ave",
    "sg:city":"Novi",
    "sg:classifiers":[
        {
            "category":"Professional",
            "type":"Services"
        }
    ],
    "sg:phone":"+1 586 726 2500",
    "sg:postcode":"48375",
    "sg:province":"MI",
    "sg:tags":[
        "establishment"
    ],
    "wof:name":"Xermac",
    "wof:placetype":"venue"
},
  "geometry": {"coordinates":[-83.447115,42.474505],"type":"Point"}
}