{
  "type": "Feature",
  "properties": {
    "iso:country":"US",
    "sg:address":"25598 Telegraph Rd",
    "sg:city":"Flat Rock",
    "sg:classifiers":[
        {
            "category":"Freight",
            "type":"Transportation"
        }
    ],
    "sg:phone":"+1 734 782 3515",
    "sg:postcode":"48134",
    "sg:province":"MI",
    "sg:tags":[
        "special"
    ],
    "wof:name":"Wagon Wheel Trailer Storage",
    "wof:placetype":"venue"
},
  "geometry": {"coordinates":[-83.277316,42.122564],"type":"Point"}
}