{
  "type": "Feature",
  "properties": {
    "iso:country":"US",
    "sg:address":"320 Park St",
    "sg:city":"Coloma",
    "sg:classifiers":[
        {
            "category":"Manufacturing",
            "subcategory":"Tools & Machinery",
            "type":"Manufacturing & Wholesale Goods"
        }
    ],
    "sg:phone":"+1 269 468 3346",
    "sg:postcode":"49038",
    "sg:province":"MI",
    "sg:tags":[
        "mold"
    ],
    "wof:name":"Michigan Mold Polishing",
    "wof:placetype":"venue"
},
  "geometry": {"coordinates":[-86.310605,42.190403],"type":"Point"}
}