{
  "type": "Feature",
  "properties": {
    "iso:country":"US",
    "sg:address":"43368 Woodward Ave Ste 101",
    "sg:city":"Bloomfield Hills",
    "sg:classifiers":[
        {
            "category":"Health Services",
            "subcategory":"Doctor",
            "type":"Services"
        }
    ],
    "sg:phone":"+1 248 334 4535",
    "sg:postcode":"48302",
    "sg:province":"MI",
    "sg:tags":[
        "orthopedist"
    ],
    "wof:name":"Levine Robert S MD PC",
    "wof:placetype":"venue"
},
  "geometry": {"coordinates":[-83.266502,42.6064],"type":"Point"}
}