{
  "type": "Feature",
  "properties": {
    "iso:country":"US",
    "sg:address":"1341 Springwells St",
    "sg:city":"Detroit",
    "sg:classifiers":[
        {
            "category":"Restaurant",
            "type":"Food & Drink"
        }
    ],
    "sg:phone":"+1 313 842 4857",
    "sg:postcode":"48209",
    "sg:province":"MI",
    "sg:tags":[
        "pizza"
    ],
    "wof:name":"Perfili Vincenzo",
    "wof:placetype":"venue"
},
  "geometry": {"coordinates":[-83.122597,42.304798],"type":"Point"}
}