{
  "type": "Feature",
  "properties": {
    "iso:country":"US",
    "sg:address":"25511 Gratiot Ave",
    "sg:city":"Roseville",
    "sg:classifiers":[
        {
            "category":"Food & Beverages",
            "subcategory":"Bakery",
            "type":"Retail Goods"
        }
    ],
    "sg:phone":"+1 586 498 9270",
    "sg:postcode":"48066",
    "sg:province":"MI",
    "sg:tags":[
        "doughnut"
    ],
    "wof:name":"Tim Hortons",
    "wof:placetype":"venue"
},
  "geometry": {"coordinates":[-82.944188,42.48607],"type":"Point"}
}