{
  "type": "Feature",
  "properties": {
    "iso:country":"US",
    "sg:address":"4340 8th St",
    "sg:city":"Luna Pier",
    "sg:classifiers":[
        {
            "category":"Professional",
            "type":"Services"
        }
    ],
    "sg:phone":"+1 734 848 2779",
    "sg:postcode":"48157",
    "sg:province":"MI",
    "sg:tags":[
        "establishment"
    ],
    "wof:name":"Luna Pier Beacon",
    "wof:placetype":"venue"
},
  "geometry": {"coordinates":[-83.44367800000001,41.806657],"type":"Point"}
}