{
  "type": "Feature",
  "properties": {
    "iso:country":"US",
    "sg:address":"10461 Davison Rd",
    "sg:city":"Davison",
    "sg:classifiers":[
        {
            "category":"Professional",
            "subcategory":"Accounting & Tax Preparation",
            "type":"Services"
        }
    ],
    "sg:phone":"+1 810 653 5381",
    "sg:postcode":"48423",
    "sg:province":"MI",
    "sg:tags":[
        "accountant"
    ],
    "wof:name":"Michael H De Vries CPA",
    "wof:placetype":"venue"
},
  "geometry": {"coordinates":[-83.501751,43.03516],"type":"Point"}
}