{
  "type": "Feature",
  "properties": {
    "iso:country":"US",
    "sg:address":"210 N Bullock St",
    "sg:city":"Whittemore",
    "sg:classifiers":[
        {
            "category":"Organizations",
            "subcategory":"Religious Organization",
            "type":"Services"
        }
    ],
    "sg:phone":"+1 989 756 3382",
    "sg:postcode":"48770",
    "sg:province":"MI",
    "sg:tags":[
        "church"
    ],
    "wof:name":"Whittemore Baptist Church",
    "wof:placetype":"venue"
},
  "geometry": {"coordinates":[-83.803031,44.239624],"type":"Point"}
}