{
  "type": "Feature",
  "properties": {
    "iso:country":"US",
    "sg:address":"101 Mechanic St",
    "sg:city":"Pontiac",
    "sg:classifiers":[
        {
            "category":"Real Estate",
            "subcategory":"Real Estate Agent",
            "type":"Services"
        }
    ],
    "sg:phone":"+1 248 335 1917",
    "sg:postcode":"48342",
    "sg:province":"MI",
    "wof:name":"Bobbish Properties",
    "wof:placetype":"venue"
},
  "geometry": {"coordinates":[-83.28266600000001,42.638919],"type":"Point"}
}