{
  "type": "Feature",
  "properties": {
    "iso:country":"US",
    "sg:address":"19727 Mack Ave",
    "sg:city":"Grosse Pointe",
    "sg:classifiers":[
        {
            "category":"Coffee & Tea",
            "type":"Food & Drink"
        }
    ],
    "sg:phone":"+1 313 642 0136",
    "sg:postcode":"48236",
    "sg:province":"MI",
    "sg:website":"www.starbucks.com",
    "wof:name":"Starbucks Coffee",
    "wof:placetype":"venue"
},
  "geometry": {"coordinates":[-82.90979799999999,42.4272],"type":"Point"}
}