{
  "type": "Feature",
  "properties": {
    "iso:country":"US",
    "sg:address":"1129 Varney St",
    "sg:city":"Port Huron",
    "sg:classifiers":[
        {
            "category":"Building & Trades",
            "subcategory":"Construction",
            "type":"Services"
        }
    ],
    "sg:phone":"+1 810 966 9884",
    "sg:postcode":"48060",
    "sg:province":"MI",
    "sg:tags":[
        "hanging",
        "contractor"
    ],
    "wof:name":"J Koenig Painting and Dctg",
    "wof:placetype":"venue"
},
  "geometry": {"coordinates":[-82.435563,42.979534],"type":"Point"}
}