{
  "type": "Feature",
  "properties": {
    "iso:country":"US",
    "sg:address":"616 Ingalls Ave",
    "sg:city":"Petoskey",
    "sg:classifiers":[
        {
            "category":"Building & Trades",
            "subcategory":"Construction",
            "type":"Services"
        }
    ],
    "sg:phone":"+1 231 487 9223",
    "sg:postcode":"49770",
    "sg:province":"MI",
    "sg:tags":[
        "hanging",
        "contractor"
    ],
    "wof:name":"Harbor Painting Co",
    "wof:placetype":"venue"
},
  "geometry": {"coordinates":[-84.96597300000001,45.370605],"type":"Point"}
}