{
  "type": "Feature",
  "properties": {
    "iso:country":"US",
    "sg:address":"201 S Robinson St",
    "sg:city":"Lyons",
    "sg:classifiers":[
        {
            "category":"Building & Trades",
            "subcategory":"Construction",
            "type":"Services"
        }
    ],
    "sg:phone":"+1 989 236 7273",
    "sg:postcode":"48851",
    "sg:province":"MI",
    "sg:tags":[
        "general",
        "contractor"
    ],
    "wof:name":"Smith Construction Svc",
    "wof:placetype":"venue"
},
  "geometry": {"coordinates":[-84.94085699999999,42.981013],"type":"Point"}
}