{
  "type": "Feature",
  "properties": {
    "iso:country":"US",
    "sg:address":"4685 Investment Dr",
    "sg:city":"Troy",
    "sg:classifiers":[
        {
            "category":"Professional",
            "type":"Services"
        }
    ],
    "sg:phone":"+1 248 952 5318",
    "sg:postcode":"48098",
    "sg:province":"MI",
    "sg:tags":[
        "establishment"
    ],
    "wof:name":"Pauls Corp",
    "wof:placetype":"venue"
},
  "geometry": {"coordinates":[-83.173553,42.588378],"type":"Point"}
}