{
  "type": "Feature",
  "properties": {
    "iso:country":"US",
    "sg:address":"46628 Maidstone Rd",
    "sg:city":"Canton",
    "sg:classifiers":[
        {
            "category":"Professional",
            "subcategory":"Management & Consulting",
            "type":"Services"
        }
    ],
    "sg:phone":"+1 734 454 1888",
    "sg:postcode":"48187",
    "sg:province":"MI",
    "sg:tags":[
        "promotional"
    ],
    "wof:name":"Adventures In Advertising",
    "wof:placetype":"venue"
},
  "geometry": {"coordinates":[-83.502786,42.339995],"type":"Point"}
}