{
  "type": "Feature",
  "properties": {
    "iso:country":"US",
    "sg:address":"15 Mill Rd",
    "sg:city":"Sterling Heights",
    "sg:classifiers":[
        {
            "category":"Health Services",
            "subcategory":"Doctor",
            "type":"Services"
        }
    ],
    "sg:phone":"+1 586 268 0900",
    "sg:postcode":"48386",
    "sg:province":"MI",
    "sg:tags":[
        "dentist"
    ],
    "wof:name":"Metripolitan Dental Center",
    "wof:placetype":"venue"
},
  "geometry": {"coordinates":[-83.487602,42.638901],"type":"Point"}
}