{
  "type": "Feature",
  "properties": {
    "iso:country":"US",
    "sg:address":"2800 Blue Briar Trl",
    "sg:city":"Highland",
    "sg:classifiers":[
        {
            "category":"Professional",
            "subcategory":"Business Services",
            "type":"Services"
        }
    ],
    "sg:phone":"+1 248 887 9240",
    "sg:postcode":"48357",
    "sg:province":"MI",
    "wof:name":"South Albany Point Association",
    "wof:placetype":"venue"
},
  "geometry": {"coordinates":[-83.672319,42.661949],"type":"Point"}
}