{
  "type": "Feature",
  "properties": {
    "iso:country":"US",
    "sg:address":"6974 Port Austin Rd",
    "sg:city":"Caseville",
    "sg:classifiers":[
        {
            "category":"Real Estate",
            "subcategory":"Real Estate Agent",
            "type":"Services"
        }
    ],
    "sg:phone":"+1 989 856 2980",
    "sg:postcode":"48725",
    "sg:province":"MI",
    "wof:name":"Real Estate One-Power Assoc",
    "wof:placetype":"venue"
},
  "geometry": {"coordinates":[-83.265728,43.954748],"type":"Point"}
}