{
  "type": "Feature",
  "properties": {
    "iso:country":"US",
    "sg:address":"61811 New Haven Rd",
    "sg:city":"New Haven",
    "sg:classifiers":[
        {
            "category":"Manufacturing",
            "subcategory":"Tools & Machinery",
            "type":"Manufacturing & Wholesale Goods"
        }
    ],
    "sg:phone":"+1 586 749 7483",
    "sg:postcode":"48048",
    "sg:province":"MI",
    "sg:tags":[
        "computer",
        "electronic",
        "mfg"
    ],
    "wof:name":"Sundown Computers",
    "wof:placetype":"venue"
},
  "geometry": {"coordinates":[-82.85643399999999,42.753617],"type":"Point"}
}