{
  "type": "Feature",
  "properties": {
    "iso:country":"US",
    "sg:address":"8417 Harbortowne Dr",
    "sg:city":"Clarkston",
    "sg:classifiers":[
        {
            "category":"Building & Trades",
            "subcategory":"Electrical",
            "type":"Services"
        }
    ],
    "sg:phone":"+1 248 620 8930",
    "sg:postcode":"48348",
    "sg:province":"MI",
    "sg:tags":[
        "electric",
        "contractor"
    ],
    "wof:name":"Harvey Electric Inc",
    "wof:placetype":"venue"
},
  "geometry": {"coordinates":[-83.47523200000001,42.762562],"type":"Point"}
}