{
  "type": "Feature",
  "properties": {
    "iso:country":"US",
    "sg:address":"9191 SW Greenville Rd",
    "sg:city":"Greenville",
    "sg:classifiers":[
        {
            "category":"Retail",
            "subcategory":"Veterinary Services",
            "type":"Services"
        }
    ],
    "sg:phone":"+1 616 754 4992",
    "sg:postcode":"48838",
    "sg:province":"MI",
    "sg:tags":[
        "veterinarian"
    ],
    "sg:website":"www.tcanimalclinic.com",
    "wof:name":"Town & Country Animal Clinic",
    "wof:placetype":"venue"
},
  "geometry": {"coordinates":[-85.256269,43.15949],"type":"Point"}
}