{
  "type": "Feature",
  "properties": {
    "iso:country":"US",
    "sg:address":"5537 N Long Lake Rd",
    "sg:city":"Traverse City",
    "sg:classifiers":[
        {
            "category":"Building & Trades",
            "subcategory":"Construction",
            "type":"Services"
        }
    ],
    "sg:phone":"+1 231 947 2423",
    "sg:postcode":"49684",
    "sg:province":"MI",
    "sg:tags":[
        "house",
        "business"
    ],
    "wof:name":"Home Construction Services",
    "wof:placetype":"venue"
},
  "geometry": {"coordinates":[-85.69291,44.744742],"type":"Point"}
}