{
  "type": "Feature",
  "properties": {
    "iso:country":"US",
    "sg:address":"6700 Weiss St",
    "sg:city":"Saginaw",
    "sg:classifiers":[
        {
            "category":"Recreation",
            "type":"Entertainment"
        }
    ],
    "sg:phone":"+1 989 799 3040",
    "sg:postcode":"48603",
    "sg:province":"MI",
    "sg:tags":[
        "fitness",
        "physical",
        "facility"
    ],
    "wof:name":"Seung-Ni Tae Kwon Do Academy",
    "wof:placetype":"venue"
},
  "geometry": {"coordinates":[-84.048007,43.443114],"type":"Point"}
}