{
  "type": "Feature",
  "properties": {
    "iso:country":"US",
    "sg:address":"414 Townsend St",
    "sg:city":"Midland",
    "sg:classifiers":[
        {
            "category":"Professional",
            "subcategory":"Lawyer & Legal Services",
            "type":"Services"
        }
    ],
    "sg:phone":"+1 989 631 1027",
    "sg:postcode":"48640",
    "sg:province":"MI",
    "sg:tags":[
        "attorney"
    ],
    "wof:name":"Braun Kendrick & Finkbeiner",
    "wof:placetype":"venue"
},
  "geometry": {"coordinates":[-84.239807,43.613649],"type":"Point"}
}