{
  "type": "Feature",
  "properties": {
    "iso:country":"US",
    "sg:address":"1312 New Life Ln",
    "sg:city":"Rochester",
    "sg:classifiers":[
        {
            "category":"Building & Trades",
            "subcategory":"Cleaning & Sanitation",
            "type":"Services"
        }
    ],
    "sg:phone":"+1 248 652 8537",
    "sg:postcode":"48309",
    "sg:province":"MI",
    "sg:tags":[
        "maintenance"
    ],
    "wof:name":"Ben & Sons Chimney Service",
    "wof:placetype":"venue"
},
  "geometry": {"coordinates":[-83.15528500000001,42.683228],"type":"Point"}
}