{
  "type": "Feature",
  "properties": {
    "iso:country":"US",
    "sg:address":"449 N Fiske Rd",
    "sg:city":"Coldwater",
    "sg:classifiers":[
        {
            "category":"Social Services",
            "subcategory":"Child Care",
            "type":"Services"
        }
    ],
    "sg:phone":"+1 517 279 8558",
    "sg:postcode":"49036",
    "sg:province":"MI",
    "sg:tags":[
        "day"
    ],
    "wof:name":"Coco Chrisitine",
    "wof:placetype":"venue"
},
  "geometry": {"coordinates":[-84.96154900000001,41.949955],"type":"Point"}
}