{
  "type": "Feature",
  "properties": {
    "iso:country":"US",
    "sg:address":"7825 Cannonsburg Rd NE",
    "sg:city":"Rockford",
    "sg:classifiers":[
        {
            "category":"Government",
            "subcategory":"Post Office",
            "type":"Public Place"
        }
    ],
    "sg:phone":"+1 616 874 8270",
    "sg:postcode":"49341",
    "sg:province":"MI",
    "wof:name":"US Post Office",
    "wof:placetype":"venue"
},
  "geometry": {"coordinates":[-85.47453400000001,43.055926],"type":"Point"}
}