{
  "type": "Feature",
  "properties": {
    "iso:country":"US",
    "sg:address":"870 Beech St",
    "sg:city":"Baldwin",
    "sg:classifiers":[
        {
            "category":"Organizations",
            "subcategory":"Religious Organization",
            "type":"Services"
        }
    ],
    "sg:phone":"+1 231 745 3466",
    "sg:postcode":"49304",
    "sg:province":"MI",
    "wof:name":"Baldwin Congregational Ucc",
    "wof:placetype":"venue"
},
  "geometry": {"coordinates":[-85.854488,43.895668],"type":"Point"}
}