{
  "type": "Feature",
  "properties": {
    "iso:country":"US",
    "sg:address":"15216 Quincy St",
    "sg:city":"Holland",
    "sg:classifiers":[
        {
            "category":"Banks & Credit Unions",
            "subcategory":"Investment Brokerage",
            "type":"Services"
        }
    ],
    "sg:phone":"+1 616 994 6828",
    "sg:postcode":"49424",
    "sg:province":"MI",
    "sg:tags":[
        "advisory",
        "financial"
    ],
    "wof:name":"CPR Financial",
    "wof:placetype":"venue"
},
  "geometry": {"coordinates":[-86.158168,42.841031],"type":"Point"}
}