{
  "type": "Feature",
  "properties": {
    "iso:country":"US",
    "sg:address":"15106 Garfield Ave",
    "sg:city":"Allen Park",
    "sg:classifiers":[
        {
            "category":"Shopping",
            "subcategory":"Musical Instruments",
            "type":"Retail Goods"
        }
    ],
    "sg:phone":"+1 313 381 2817",
    "sg:postcode":"48101",
    "sg:province":"MI",
    "wof:name":"Zimnicki Guitars",
    "wof:placetype":"venue"
},
  "geometry": {"coordinates":[-83.20405100000001,42.254993],"type":"Point"}
}