{
  "type": "Feature",
  "properties": {
    "iso:country":"US",
    "sg:address":"30990 S Wixom Rd",
    "sg:city":"Wixom",
    "sg:classifiers":[
        {
            "category":"Arena",
            "subcategory":"Sports Club",
            "type":"Entertainment"
        }
    ],
    "sg:phone":"+1 248 669 9817",
    "sg:postcode":"48393",
    "sg:province":"MI",
    "wof:name":"Soccerteeze Inc",
    "wof:placetype":"venue"
},
  "geometry": {"coordinates":[-83.537356,42.523475],"type":"Point"}
}