{
  "type": "Feature",
  "properties": {
    "iso:country":"US",
    "sg:address":"2311 16th St",
    "sg:city":"Port Huron",
    "sg:classifiers":[
        {
            "category":"Retail",
            "subcategory":"Laundry & Dry Cleaning",
            "type":"Services"
        }
    ],
    "sg:phone":"+1 810 985 8778",
    "sg:postcode":"48060",
    "sg:province":"MI",
    "sg:tags":[
        "linen",
        "supply"
    ],
    "wof:name":"Midwest Linen",
    "wof:placetype":"venue"
},
  "geometry": {"coordinates":[-82.44219200000001,42.959424],"type":"Point"}
}