{
  "type": "Feature",
  "properties": {
    "iso:country":"US",
    "sg:address":"11653 Joseph Campau St",
    "sg:city":"Detroit",
    "sg:classifiers":[
        {
            "category":"Building & Trades",
            "subcategory":"Cleaning & Sanitation",
            "type":"Services"
        }
    ],
    "sg:phone":"+1 313 365 8936",
    "sg:postcode":"48212",
    "sg:province":"MI",
    "sg:tags":[
        "janitorial",
        "maintenance"
    ],
    "wof:name":"A Lilias Maintenance Inc",
    "wof:placetype":"venue"
},
  "geometry": {"coordinates":[-83.062102,42.402886],"type":"Point"}
}