{
  "type": "Feature",
  "properties": {
    "iso:country":"US",
    "sg:address":"329 Washington Sq N",
    "sg:city":"Lansing",
    "sg:classifiers":[
        {
            "category":"Shopping",
            "subcategory":"Florist",
            "type":"Retail Goods"
        }
    ],
    "sg:phone":"+1 517 267 0913",
    "sg:postcode":"48933",
    "sg:province":"MI",
    "wof:name":"Smith Floral Co",
    "wof:placetype":"venue"
},
  "geometry": {"coordinates":[-84.55235999999999,42.736915],"type":"Point"}
}