{
  "type": "Feature",
  "properties": {
    "iso:country":"US",
    "sg:address":"27000 Wick Rd",
    "sg:city":"Taylor",
    "sg:classifiers":[
        {
            "category":"Education",
            "subcategory":"Special Training",
            "type":"Public Place"
        }
    ],
    "sg:phone":"+1 734 946 4330",
    "sg:postcode":"48180",
    "sg:province":"MI",
    "sg:tags":[
        "school",
        "specialty"
    ],
    "wof:name":"Dawn Food Products",
    "wof:placetype":"venue"
},
  "geometry": {"coordinates":[-83.303596,42.239601],"type":"Point"}
}