{
  "type": "Feature",
  "properties": {
    "iso:country":"US",
    "sg:address":"4242 State Hwy 33",
    "sg:city":"Atlanta",
    "sg:classifiers":[
        {
            "category":"Personal",
            "subcategory":"Beauty Salon",
            "type":"Services"
        }
    ],
    "sg:phone":"+1 989 785 4887",
    "sg:postcode":"49709",
    "sg:province":"MI",
    "sg:tags":[
        "shop"
    ],
    "wof:name":"Renees Beauty Salon & Tanning",
    "wof:placetype":"venue"
},
  "geometry": {"coordinates":[-84.03155700000001,44.913597],"type":"Point"}
}