{
  "type": "Feature",
  "properties": {
    "iso:country":"US",
    "sg:address":"3661 Highland Rd",
    "sg:city":"Waterford",
    "sg:classifiers":[
        {
            "category":"Health Services",
            "subcategory":"Doctor",
            "type":"Services"
        }
    ],
    "sg:phone":"+1 313 682 6883",
    "sg:postcode":"48328",
    "sg:province":"MI",
    "sg:tags":[
        "dentist"
    ],
    "wof:name":"David Lieberman DDS",
    "wof:placetype":"venue"
},
  "geometry": {"coordinates":[-83.363888,42.64765],"type":"Point"}
}