{
  "type": "Feature",
  "properties": {
    "iso:country":"US",
    "sg:address":"1691 Cliff View Dr",
    "sg:city":"Rochester Hills",
    "sg:classifiers":[
        {
            "category":"Real Estate",
            "subcategory":"Real Estate Operator",
            "type":"Services"
        }
    ],
    "sg:phone":"+1 248 651 7665",
    "sg:postcode":"48306",
    "sg:province":"MI",
    "sg:tags":[
        "building",
        "apartment",
        "for",
        "subsidized",
        "citizen",
        "senior"
    ],
    "wof:name":"Cliffview Apartments",
    "wof:placetype":"venue"
},
  "geometry": {"coordinates":[-83.14451200000001,42.697465],"type":"Point"}
}