{
  "type": "Feature",
  "properties": {
    "iso:country":"US",
    "sg:address":"2400 2nd Avenue",
    "sg:city":"Detroit",
    "sg:classifiers":[
        {
            "category":"Building & Trades",
            "subcategory":"Locksmith",
            "type":"Services"
        }
    ],
    "sg:phone":"+1 313 651 7666",
    "sg:postcode":"48201",
    "sg:province":"MI",
    "sg:tags":[
        "key"
    ],
    "wof:name":"24-7 detroit-locksmith",
    "wof:placetype":"venue"
},
  "geometry": {"coordinates":[-83.05866399999999,42.337291],"type":"Point"}
}