{
  "type": "Feature",
  "properties": {
    "iso:country":"US",
    "sg:address":"302 E Austin Ave",
    "sg:city":"Flint",
    "sg:classifiers":[
        {
            "category":"Social Services",
            "subcategory":"Adult Care",
            "type":"Services"
        }
    ],
    "sg:phone":"+1 810 787 2957",
    "sg:postcode":"48505",
    "sg:province":"MI",
    "sg:tags":[
        "foster",
        "provider"
    ],
    "wof:name":"Oliver Samuel & Essie",
    "wof:placetype":"venue"
},
  "geometry": {"coordinates":[-83.698933,43.069403],"type":"Point"}
}