{
  "type": "Feature",
  "properties": {
    "iso:country":"US",
    "sg:address":"72 Louise St",
    "sg:city":"Croswell",
    "sg:classifiers":[
        {
            "category":"Manufacturing",
            "subcategory":"Metals",
            "type":"Manufacturing & Wholesale Goods"
        }
    ],
    "sg:phone":"+1 810 679 2333",
    "sg:postcode":"48422",
    "sg:province":"MI",
    "sg:tags":[
        "hardware"
    ],
    "wof:name":"Jay & Kay Mfg",
    "wof:placetype":"venue"
},
  "geometry": {"coordinates":[-82.612617,43.283939],"type":"Point"}
}