{
  "type": "Feature",
  "properties": {
    "iso:country":"US",
    "sg:address":"4510 132nd Ave",
    "sg:city":"Hamilton",
    "sg:classifiers":[
        {
            "category":"Manufacturing",
            "subcategory":"Glass & Minerals",
            "type":"Manufacturing & Wholesale Goods"
        }
    ],
    "sg:phone":"+1 269 751 5129",
    "sg:postcode":"49419",
    "sg:province":"MI",
    "sg:tags":[
        "ready"
    ],
    "wof:name":"Hamilton Block & Ready Mix",
    "wof:placetype":"venue"
},
  "geometry": {"coordinates":[-85.988725,42.651985],"type":"Point"}
}