{
  "type": "Feature",
  "properties": {
    "iso:country":"US",
    "sg:address":"46089 Grand River Ave",
    "sg:city":"Novi",
    "sg:classifiers":[
        {
            "category":"Manufacturing",
            "subcategory":"Tools & Machinery",
            "type":"Manufacturing & Wholesale Goods"
        }
    ],
    "sg:phone":"+1 248 449 9911",
    "sg:postcode":"48374",
    "sg:province":"MI",
    "sg:tags":[
        "machine",
        "shop"
    ],
    "wof:name":"Slaco Tool & Mfg",
    "wof:placetype":"venue"
},
  "geometry": {"coordinates":[-83.499921,42.486087],"type":"Point"}
}