{
  "type": "Feature",
  "properties": {
    "iso:country":"US",
    "sg:address":"425 E Main St",
    "sg:city":"Hartford",
    "sg:classifiers":[
        {
            "category":"Social Services",
            "type":"Services"
        }
    ],
    "sg:phone":"+1 269 621 4736",
    "sg:postcode":"49057",
    "sg:province":"MI",
    "sg:tags":[
        "organization",
        "individual",
        "family",
        "welfare"
    ],
    "wof:name":"Cooperating Ministries Inc",
    "wof:placetype":"venue"
},
  "geometry": {"coordinates":[-86.161331,42.207292],"type":"Point"}
}