{
  "type": "Feature",
  "properties": {
    "iso:country":"US",
    "sg:address":"5651 S Middlebelt Rd",
    "sg:city":"Westland",
    "sg:classifiers":[
        {
            "category":"Organizations",
            "subcategory":"Religious Organization",
            "type":"Services"
        }
    ],
    "sg:phone":"+1 734 595 6146",
    "sg:postcode":"48186",
    "sg:province":"MI",
    "wof:name":"Beulah Baptist Church",
    "wof:placetype":"venue"
},
  "geometry": {"coordinates":[-83.328598,42.2705],"type":"Point"}
}