{
  "type": "Feature",
  "properties": {
    "iso:country":"US",
    "sg:address":"1406 W Broadway St",
    "sg:city":"Mount Pleasant",
    "sg:classifiers":[
        {
            "category":"Recreation",
            "type":"Entertainment"
        }
    ],
    "sg:phone":"+1 989 772 3839",
    "sg:postcode":"48858",
    "sg:province":"MI",
    "sg:tags":[
        "club",
        "membership"
    ],
    "wof:name":"Womens International Bowl Assn",
    "wof:placetype":"venue"
},
  "geometry": {"coordinates":[-84.79357,43.604468],"type":"Point"}
}