{
  "type": "Feature",
  "properties": {
    "iso:country":"US",
    "sg:address":"7481 Westwood Dr",
    "sg:city":"Oscoda",
    "sg:classifiers":[
        {
            "category":"Professional",
            "subcategory":"Computer Services",
            "type":"Services"
        }
    ],
    "sg:phone":"+1 989 739 5779",
    "sg:postcode":"48750",
    "sg:province":"MI",
    "sg:tags":[
        "planning",
        "disaster"
    ],
    "wof:name":"Roger J Callens",
    "wof:placetype":"venue"
},
  "geometry": {"coordinates":[-83.35034,44.502903],"type":"Point"}
}