{
  "type": "Feature",
  "properties": {
    "iso:country":"US",
    "sg:address":"19797 Seminole",
    "sg:city":"Redford",
    "sg:classifiers":[
        {
            "category":"Building & Trades",
            "subcategory":"Construction",
            "type":"Services"
        }
    ],
    "sg:phone":"+1 313 535 9421",
    "sg:postcode":"48240",
    "sg:province":"MI",
    "sg:tags":[
        "carpentry",
        "contractor"
    ],
    "wof:name":"Handy Hands Handyman Service",
    "wof:placetype":"venue"
},
  "geometry": {"coordinates":[-83.315371,42.433942],"type":"Point"}
}