{
  "type": "Feature",
  "properties": {
    "iso:country":"US",
    "sg:address":"2611 Alpine Ave NW",
    "sg:city":"Grand Rapids",
    "sg:classifiers":[
        {
            "category":"Building & Trades",
            "subcategory":"Construction",
            "type":"Services"
        }
    ],
    "sg:phone":"+1 616 363 3264",
    "sg:postcode":"49544",
    "sg:province":"MI",
    "sg:tags":[
        "coping",
        "plastering",
        "tiling",
        "pool",
        "swimming"
    ],
    "wof:name":"Pool Service Co Inc",
    "wof:placetype":"venue"
},
  "geometry": {"coordinates":[-85.688817,43.011238],"type":"Point"}
}