{
  "type": "Feature",
  "properties": {
    "iso:country":"US",
    "sg:address":"1540 E Elm Ave",
    "sg:city":"Monroe",
    "sg:classifiers":[
        {
            "category":"Professional",
            "type":"Services"
        },
        {
            "category":"Restaurant",
            "type":"Food & Drink"
        }
    ],
    "sg:phone":"+1 734 240 0501",
    "sg:postcode":"48162",
    "sg:province":"MI",
    "sg:tags":[
        "establishment"
    ],
    "wof:name":"Claimdigger",
    "wof:placetype":"venue"
},
  "geometry": {"coordinates":[-83.376356,41.910023],"type":"Point"}
}