{
  "type": "Feature",
  "properties": {
    "iso:country":"US",
    "sg:address":"1430 E Bristol Rd",
    "sg:city":"Burton",
    "sg:classifiers":[
        {
            "category":"Organizations",
            "subcategory":"Religious Organization",
            "type":"Services"
        }
    ],
    "sg:phone":"+1 810 742 1677",
    "sg:postcode":"48529",
    "sg:province":"MI",
    "wof:name":"Flint Baptist Temple",
    "wof:placetype":"venue"
},
  "geometry": {"coordinates":[-83.68049600000001,42.974201],"type":"Point"}
}