{
  "type": "Feature",
  "properties": {
    "iso:country":"US",
    "sg:address":"212 Garfield Ave",
    "sg:city":"Bay City",
    "sg:classifiers":[
        {
            "category":"Real Estate",
            "subcategory":"Real Estate Operator",
            "type":"Services"
        }
    ],
    "sg:phone":"+1 989 892 5838",
    "sg:postcode":"48708",
    "sg:province":"MI",
    "sg:tags":[
        "building",
        "apartment"
    ],
    "wof:name":"Dishaw Apts",
    "wof:placetype":"venue"
},
  "geometry": {"coordinates":[-83.890659,43.588522],"type":"Point"}
}