{
  "type": "Feature",
  "properties": {
    "iso:country":"US",
    "sg:address":"12851 Durham Dr",
    "sg:city":"Warren",
    "sg:classifiers":[
        {
            "category":"Professional",
            "subcategory":"Computer Services",
            "type":"Services"
        }
    ],
    "sg:phone":"+1 586 264 8794",
    "sg:postcode":"48088",
    "sg:province":"MI",
    "sg:tags":[
        "design",
        "system"
    ],
    "wof:name":"Finalphasesoftwarecom",
    "wof:placetype":"venue"
},
  "geometry": {"coordinates":[-82.994373,42.529889],"type":"Point"}
}