{
  "type": "Feature",
  "properties": {
    "iso:country":"US",
    "sg:address":"42900 W 9 Mile Rd",
    "sg:city":"Novi",
    "sg:classifiers":[
        {
            "category":"Manufacturing",
            "subcategory":"Glass & Minerals",
            "type":"Manufacturing & Wholesale Goods"
        }
    ],
    "sg:phone":"+1 248 349 1211",
    "sg:postcode":"48375",
    "sg:province":"MI",
    "sg:tags":[
        "wheel",
        "grinding"
    ],
    "sg:website":"www.dicoat.com",
    "wof:name":"Di-Coat Corp",
    "wof:placetype":"venue"
},
  "geometry": {"coordinates":[-83.47350299999999,42.452168],"type":"Point"}
}