{
  "type": "Feature",
  "properties": {
    "iso:country":"US",
    "sg:address":"730 Watkins Rd",
    "sg:city":"Battle Creek",
    "sg:classifiers":[
        {
            "category":"Building & Trades",
            "subcategory":"Construction",
            "type":"Services"
        }
    ],
    "sg:phone":"+1 269 746 5745",
    "sg:postcode":"49015",
    "sg:province":"MI",
    "sg:tags":[
        "contractor"
    ],
    "wof:name":"Baron Builders",
    "wof:placetype":"venue"
},
  "geometry": {"coordinates":[-85.287873,42.268068],"type":"Point"}
}