{
  "type": "Feature",
  "properties": {
    "iso:country":"US",
    "sg:address":"5295 Barney Rd",
    "sg:city":"Traverse City",
    "sg:classifiers":[
        {
            "category":"Building & Trades",
            "subcategory":"Landscaping Services",
            "type":"Services"
        }
    ],
    "sg:phone":"+1 231 941 0532",
    "sg:postcode":"49684",
    "sg:province":"MI",
    "wof:name":"Green Space Professional Lawn",
    "wof:placetype":"venue"
},
  "geometry": {"coordinates":[-85.680758,44.766388],"type":"Point"}
}