{
  "type": "Feature",
  "properties": {
    "iso:country":"US",
    "sg:address":"25505 W 12 Mile Rd",
    "sg:city":"Southfield",
    "sg:classifiers":[
        {
            "category":"Professional",
            "subcategory":"Lawyer & Legal Services",
            "type":"Services"
        }
    ],
    "sg:phone":"+1 248 353 5595",
    "sg:postcode":"48034",
    "sg:province":"MI",
    "sg:tags":[
        "personal",
        "injury"
    ],
    "wof:name":"Ross Phillip D Atty",
    "wof:placetype":"venue"
},
  "geometry": {"coordinates":[-83.296997,42.500801],"type":"Point"}
}