{
  "type": "Feature",
  "properties": {
    "iso:country":"US",
    "sg:address":"1280 Daley Rd",
    "sg:city":"Lapeer",
    "sg:classifiers":[
        {
            "category":"Organizations",
            "subcategory":"Religious Organization",
            "type":"Services"
        }
    ],
    "sg:phone":"+1 810 664 8089",
    "sg:postcode":"48446",
    "sg:province":"MI",
    "sg:tags":[
        "church"
    ],
    "wof:name":"Lapeer Assembly Of God",
    "wof:placetype":"venue"
},
  "geometry": {"coordinates":[-83.29669800000001,43.087734],"type":"Point"}
}