{
  "type": "Feature",
  "properties": {
    "iso:country":"US",
    "sg:address":"732 Brookwood Ln E",
    "sg:city":"Rochester Hills",
    "sg:classifiers":[
        {
            "category":"Manufacturing",
            "subcategory":"Printing",
            "type":"Manufacturing & Wholesale Goods"
        }
    ],
    "sg:phone":"+1 248 601 1200",
    "sg:postcode":"48309",
    "sg:province":"MI",
    "sg:tags":[
        "printer"
    ],
    "wof:name":"American Solutions-Business",
    "wof:placetype":"venue"
},
  "geometry": {"coordinates":[-83.17265399999999,42.692552],"type":"Point"}
}