{
  "type": "Feature",
  "properties": {
    "iso:country":"US",
    "sg:address":"8234 Rapid City Rd NW",
    "sg:city":"Rapid City",
    "sg:classifiers":[
        {
            "category":"Building & Trades",
            "subcategory":"Construction",
            "type":"Services"
        }
    ],
    "sg:phone":"+1 231 331 4030",
    "sg:postcode":"49676",
    "sg:province":"MI",
    "sg:tags":[
        "excavating",
        "contractor"
    ],
    "wof:name":"Double D Excavating",
    "wof:placetype":"venue"
},
  "geometry": {"coordinates":[-85.282696,44.83372],"type":"Point"}
}