{
  "type": "Feature",
  "properties": {
    "iso:country":"US",
    "sg:address":"810 S Putnam St",
    "sg:city":"Williamston",
    "sg:classifiers":[
        {
            "category":"Social Services",
            "subcategory":"Adult Care",
            "type":"Services"
        }
    ],
    "sg:phone":"+1 517 655 1369",
    "sg:postcode":"48895",
    "sg:province":"MI",
    "sg:tags":[
        "residential"
    ],
    "wof:name":"Parker Manor Adult Care",
    "wof:placetype":"venue"
},
  "geometry": {"coordinates":[-84.282883,42.681878],"type":"Point"}
}