{
  "type": "Feature",
  "properties": {
    "iso:country":"US",
    "sg:address":"6776 34th Ave",
    "sg:city":"Hudsonville",
    "sg:classifiers":[
        {
            "category":"Real Estate",
            "subcategory":"Architect",
            "type":"Services"
        }
    ],
    "sg:phone":"+1 616 662 5444",
    "sg:postcode":"49426",
    "sg:province":"MI",
    "sg:tags":[
        "architectural"
    ],
    "wof:name":"Vanguard Services",
    "wof:placetype":"venue"
},
  "geometry": {"coordinates":[-85.866435,42.887685],"type":"Point"}
}