{
  "type": "Feature",
  "properties": {
    "iso:country":"US",
    "sg:address":"140 E University Dr",
    "sg:city":"Rochester",
    "sg:classifiers":[
        {
            "category":"Personal",
            "subcategory":"Beauty Salon",
            "type":"Services"
        }
    ],
    "sg:phone":"+1 248 656 4990",
    "sg:postcode":"48307",
    "sg:province":"MI",
    "sg:tags":[
        "shop"
    ],
    "wof:name":"Linda Via Salon",
    "wof:placetype":"venue"
},
  "geometry": {"coordinates":[-83.133532,42.681979],"type":"Point"}
}