{
  "type": "Feature",
  "properties": {
    "iso:country":"US",
    "sg:address":"10504 E Dexter Trl",
    "sg:city":"Pewamo",
    "sg:classifiers":[
        {
            "category":"Farming",
            "subcategory":"Livestock Farm",
            "type":"Manufacturing & Wholesale Goods"
        }
    ],
    "sg:phone":"+1 989 593 2279",
    "sg:postcode":"48873",
    "sg:province":"MI",
    "sg:tags":[
        "hog",
        "or",
        "feedlot"
    ],
    "wof:name":"Daniel Hafner",
    "wof:placetype":"venue"
},
  "geometry": {"coordinates":[-84.868165,42.969003],"type":"Point"}
}