{
  "type": "Feature",
  "properties": {
    "iso:country":"US",
    "sg:address":"28299 Kehrig St",
    "sg:city":"Chesterfield",
    "sg:classifiers":[
        {
            "category":"Building & Trades",
            "subcategory":"Construction",
            "type":"Services"
        }
    ],
    "sg:phone":"+1 586 949 4777",
    "sg:postcode":"48047",
    "sg:province":"MI",
    "sg:tags":[
        "contractor"
    ],
    "wof:name":"Schena Roofing & Sheet Metal Company Inc",
    "wof:placetype":"venue"
},
  "geometry": {"coordinates":[-82.827904,42.632301],"type":"Point"}
}