{
  "type": "Feature",
  "properties": {
    "iso:country":"US",
    "sg:address":"27737 Floral St",
    "sg:city":"Roseville",
    "sg:classifiers":[
        {
            "category":"Professional",
            "type":"Services"
        }
    ],
    "sg:phone":"+1 586 777 2489",
    "sg:postcode":"48066",
    "sg:province":"MI",
    "wof:name":"PS Expediting Service",
    "wof:placetype":"venue"
},
  "geometry": {"coordinates":[-82.949134,42.500078],"type":"Point"}
}