{
  "type": "Feature",
  "properties": {
    "iso:country":"US",
    "sg:address":"29815 John R Rd",
    "sg:city":"Madison Heights",
    "sg:classifiers":[
        {
            "category":"Wholesale",
            "subcategory":"Machinery & Supplies",
            "type":"Manufacturing & Wholesale Goods"
        }
    ],
    "sg:phone":"+1 248 544 6300",
    "sg:postcode":"48071",
    "sg:province":"MI",
    "sg:tags":[
        "machine",
        "floor"
    ],
    "sg:website":"www.americanlincoln.com",
    "wof:name":"Alto US Inc",
    "wof:placetype":"venue"
},
  "geometry": {"coordinates":[-83.105947,42.509516],"type":"Point"}
}