{
  "type": "Feature",
  "properties": {
    "iso:country":"US",
    "sg:address":"9880 E Grand River Ave",
    "sg:city":"Brighton",
    "sg:classifiers":[
        {
            "category":"Health Services",
            "subcategory":"Doctor",
            "type":"Services"
        }
    ],
    "sg:phone":"+1 810 227 2626",
    "sg:postcode":"48116",
    "sg:province":"MI",
    "sg:tags":[
        "dentist"
    ],
    "wof:name":"Oral & Facial Surgeons",
    "wof:placetype":"venue"
},
  "geometry": {"coordinates":[-83.761785,42.52144],"type":"Point"}
}