{
  "type": "Feature",
  "properties": {
    "iso:country":"US",
    "sg:address":"18900 Hall Rd",
    "sg:city":"Clinton Township",
    "sg:classifiers":[
        {
            "category":"Autos & Motor Vehicles",
            "subcategory":"Automobile Sales",
            "type":"Retail Goods"
        }
    ],
    "sg:phone":"+1 586 412 9600",
    "sg:postcode":"48038",
    "sg:province":"MI",
    "sg:tags":[
        "car"
    ],
    "sg:website":"Www.jimriehl.com",
    "wof:name":"Jim Riehls Friendly Cadillac Honda Hummer",
    "wof:placetype":"venue"
},
  "geometry": {"coordinates":[-82.93289900000001,42.628201],"type":"Point"}
}