{
  "type": "Feature",
  "properties": {
    "iso:country":"US",
    "sg:address":"3381 Gregory Rd",
    "sg:city":"Lake Orion",
    "sg:classifiers":[
        {
            "category":"Professional",
            "type":"Services"
        }
    ],
    "sg:phone":"+1 248 391 0892",
    "sg:postcode":"48359",
    "sg:province":"MI",
    "wof:name":"Mj Residential Services",
    "wof:placetype":"venue"
},
  "geometry": {"coordinates":[-83.310412,42.721524],"type":"Point"}
}