{
  "type": "Feature",
  "properties": {
    "iso:country":"US",
    "sg:address":"420 N State St",
    "sg:city":"Sparta",
    "sg:classifiers":[
        {
            "category":"Manufacturing",
            "subcategory":"Tools & Machinery",
            "type":"Manufacturing & Wholesale Goods"
        }
    ],
    "sg:phone":"+1 616 887 7994",
    "sg:postcode":"49345",
    "sg:province":"MI",
    "sg:tags":[
        "control"
    ],
    "sg:website":"www.storagecontrol.com",
    "wof:name":"Storage Control Systems Inc",
    "wof:placetype":"venue"
},
  "geometry": {"coordinates":[-85.710201,43.168118],"type":"Point"}
}