{
  "type": "Feature",
  "properties": {
    "iso:country":"US",
    "sg:address":"8814 Pemberton Dr",
    "sg:city":"Sterling Heights",
    "sg:classifiers":[
        {
            "category":"Professional",
            "subcategory":"Business Services",
            "type":"Services"
        }
    ],
    "sg:phone":"+1 586 604 3220",
    "sg:postcode":"48312",
    "sg:province":"MI",
    "wof:name":"Active Financial Solutions",
    "wof:placetype":"venue"
},
  "geometry": {"coordinates":[-83.02066600000001,42.570033],"type":"Point"}
}