{
  "type": "Feature",
  "properties": {
    "iso:country":"US",
    "sg:address":"25425 Tweed Dr",
    "sg:city":"Franklin",
    "sg:classifiers":[
        {
            "category":"Health Services",
            "subcategory":"Doctor",
            "type":"Services"
        }
    ],
    "sg:phone":"+1 248 626 0084",
    "sg:postcode":"48025",
    "sg:province":"MI",
    "wof:name":"Lester Melvin A MD",
    "wof:placetype":"venue"
},
  "geometry": {"coordinates":[-83.295601,42.5117],"type":"Point"}
}