{
  "type": "Feature",
  "properties": {
    "iso:country":"US",
    "sg:address":"200 S Main St",
    "sg:city":"Evart",
    "sg:classifiers":[
        {
            "category":"Government",
            "subcategory":"Office",
            "type":"Public Place"
        }
    ],
    "sg:phone":"+1 231 734 2181",
    "sg:postcode":"49631",
    "sg:province":"MI",
    "sg:tags":[
        "legislative",
        "body"
    ],
    "wof:name":"City of Evart Michigan",
    "wof:placetype":"venue"
},
  "geometry": {"coordinates":[-85.259393,43.899196],"type":"Point"}
}