{
  "type": "Feature",
  "properties": {
    "iso:country":"US",
    "sg:address":"36380 Ryan Rd",
    "sg:city":"Sterling Heights",
    "sg:classifiers":[
        {
            "category":"Shopping",
            "type":"Retail Goods"
        }
    ],
    "sg:phone":"+1 586 977 1990",
    "sg:postcode":"48310",
    "sg:province":"MI",
    "sg:tags":[
        "cosmetic",
        "perfume"
    ],
    "wof:name":"Matis",
    "wof:placetype":"venue"
},
  "geometry": {"coordinates":[-83.069694,42.560308],"type":"Point"}
}