{
  "type": "Feature",
  "properties": {
    "iso:country":"US",
    "sg:address":"20775 Reimanville Ave",
    "sg:city":"Ferndale",
    "sg:classifiers":[
        {
            "category":"Professional",
            "subcategory":"Computer Services",
            "type":"Services"
        }
    ],
    "sg:phone":"+1 248 691 1171",
    "sg:postcode":"48220",
    "sg:province":"MI",
    "sg:tags":[
        "development",
        "web",
        "design",
        "site"
    ],
    "wof:name":"Durand Laurent Micheau Inc",
    "wof:placetype":"venue"
},
  "geometry": {"coordinates":[-83.155581,42.447941],"type":"Point"}
}