{
  "type": "Feature",
  "properties": {
    "iso:country":"US",
    "sg:address":"691 Ottawa Beach Rd",
    "sg:city":"Holland",
    "sg:classifiers":[
        {
            "category":"Organizations",
            "subcategory":"Community Association",
            "type":"Services"
        }
    ],
    "sg:phone":"+1 616 393 9000",
    "sg:postcode":"49424",
    "sg:province":"MI",
    "wof:name":"Spyglass Condominium Sales Off",
    "wof:placetype":"venue"
},
  "geometry": {"coordinates":[-86.137517,42.797626],"type":"Point"}
}