{
  "type": "Feature",
  "properties": {
    "iso:country":"US",
    "sg:address":"5552 Saint Andrew Dr",
    "sg:city":"Clarkston",
    "sg:classifiers":[
        {
            "category":"Real Estate",
            "subcategory":"Real Estate Agent",
            "type":"Services"
        }
    ],
    "sg:phone":"+1 248 922 9797",
    "sg:postcode":"48348",
    "sg:province":"MI",
    "wof:name":"Hudson Donna Realty Co",
    "wof:placetype":"venue"
},
  "geometry": {"coordinates":[-83.365275,42.737889],"type":"Point"}
}