{
  "type": "Feature",
  "properties": {
    "iso:country":"US",
    "sg:address":"595 Arthur Ave",
    "sg:city":"Pontiac",
    "sg:classifiers":[
        {
            "category":"Social Services",
            "subcategory":"Child Care",
            "type":"Services"
        }
    ],
    "sg:phone":"+1 248 338 8706",
    "sg:postcode":"48341",
    "sg:province":"MI",
    "wof:name":"Missy",
    "wof:placetype":"venue"
},
  "geometry": {"coordinates":[-83.294262,42.613903],"type":"Point"}
}