{
  "type": "Feature",
  "properties": {
    "iso:country":"US",
    "sg:address":"5317 S Telegraph Rd",
    "sg:city":"Dearborn Heights",
    "sg:classifiers":[
        {
            "category":"Shopping",
            "subcategory":"Pets & Pet Supplies",
            "type":"Retail Goods"
        }
    ],
    "sg:phone":"+1 313 292 6343",
    "sg:postcode":"48125",
    "sg:province":"MI",
    "sg:tags":[
        "store"
    ],
    "wof:name":"Pet Station",
    "wof:placetype":"venue"
},
  "geometry": {"coordinates":[-83.27010300000001,42.272301],"type":"Point"}
}