{
  "type": "Feature",
  "properties": {
    "iso:country":"US",
    "sg:address":"238 W Summit St",
    "sg:city":"Milford",
    "sg:classifiers":[
        {
            "category":"Restaurant",
            "type":"Food & Drink"
        }
    ],
    "sg:phone":"+1 248 684 6303",
    "sg:postcode":"48381",
    "sg:province":"MI",
    "wof:name":"Hungry Howie's Pizza & Subs",
    "wof:placetype":"venue"
},
  "geometry": {"coordinates":[-83.60074400000001,42.594766],"type":"Point"}
}