{
  "type": "Feature",
  "properties": {
    "iso:country":"US",
    "sg:address":"3551 Merritt Lake Dr",
    "sg:city":"Metamora",
    "sg:classifiers":[
        {
            "category":"Education",
            "subcategory":"Special Training",
            "type":"Public Place"
        }
    ],
    "sg:phone":"+1 810 678 2542",
    "sg:postcode":"48455",
    "sg:province":"MI",
    "wof:name":"Boss E Tunes",
    "wof:placetype":"venue"
},
  "geometry": {"coordinates":[-83.328642,42.951815],"type":"Point"}
}