{
  "type": "Feature",
  "properties": {
    "iso:country":"US",
    "sg:address":"168 N Saginaw St",
    "sg:city":"Lapeer",
    "sg:classifiers":[
        {
            "category":"Insurance",
            "subcategory":"Insurance Agent",
            "type":"Services"
        }
    ],
    "sg:phone":"+1 810 664 1421",
    "sg:postcode":"48446",
    "sg:province":"MI",
    "wof:name":"Houghtaling Agency Inc",
    "wof:placetype":"venue"
},
  "geometry": {"coordinates":[-83.307709,43.05437],"type":"Point"}
}