{
  "type": "Feature",
  "properties": {
    "iso:country":"US",
    "sg:address":"34800 Ford Rd",
    "sg:city":"Westland",
    "sg:classifiers":[
        {
            "category":"Restaurant",
            "type":"Food & Drink"
        }
    ],
    "sg:menulink":"http://www.allmenus.com/mi/westland/24419-mr-pita/menu/",
    "sg:phone":"+1 734 721 8575",
    "sg:postcode":"48185",
    "sg:province":"MI",
    "sg:tags":[
        "wrap",
        "american",
        "sandwich",
        "mexican"
    ],
    "wof:name":"Mr. Pita",
    "wof:placetype":"venue"
},
  "geometry": {"coordinates":[-83.382761,42.324552],"type":"Point"}
}