{
  "type": "Feature",
  "properties": {
    "iso:country":"US",
    "sg:address":"46771 Riverwoods Dr",
    "sg:city":"Macomb",
    "sg:classifiers":[
        {
            "category":"Insurance",
            "subcategory":"Insurance Agent",
            "type":"Services"
        }
    ],
    "sg:phone":"+1 586 228 8800",
    "sg:postcode":"48044",
    "sg:province":"MI",
    "wof:name":"Horace Mann Co Insurance",
    "wof:placetype":"venue"
},
  "geometry": {"coordinates":[-82.926388,42.641807],"type":"Point"}
}