{
  "type": "Feature",
  "properties": {
    "iso:country":"US",
    "sg:address":"600 S Beacon Blvd",
    "sg:city":"Grand Haven",
    "sg:classifiers":[
        {
            "category":"Professional",
            "subcategory":"Employment Agencies",
            "type":"Services"
        }
    ],
    "sg:phone":"+1 616 847 2555",
    "sg:postcode":"49417",
    "sg:province":"MI",
    "wof:name":"Wise Temporaries Inc",
    "wof:placetype":"venue"
},
  "geometry": {"coordinates":[-86.220575,43.055385],"type":"Point"}
}