{
  "type": "Feature",
  "properties": {
    "iso:country":"US",
    "sg:address":"15222 E Jefferson Ave",
    "sg:city":"Grosse Pointe",
    "sg:classifiers":[
        {
            "category":"Real Estate",
            "subcategory":"Real Estate Agent",
            "type":"Services"
        }
    ],
    "sg:phone":"+1 313 884 6763",
    "sg:postcode":"48230",
    "sg:province":"MI",
    "sg:tags":[
        "management"
    ],
    "wof:name":"Forester Hills Management Inc",
    "wof:placetype":"venue"
},
  "geometry": {"coordinates":[-82.93628,42.376149],"type":"Point"}
}