{
  "type": "Feature",
  "properties": {
    "iso:country":"US",
    "sg:address":"508 Mohawk Rd",
    "sg:city":"Tecumseh",
    "sg:classifiers":[
        {
            "category":"Utilities",
            "type":"Services"
        }
    ],
    "sg:phone":"+1 517 424 6518",
    "sg:postcode":"49286",
    "sg:province":"MI",
    "sg:tags":[
        "locating"
    ],
    "wof:name":"Creek Enterprise Inc",
    "wof:placetype":"venue"
},
  "geometry": {"coordinates":[-83.93986599999999,41.997629],"type":"Point"}
}