{
  "type": "Feature",
  "properties": {
    "iso:country":"US",
    "sg:address":"578 Munson Ave",
    "sg:city":"Traverse City",
    "sg:classifiers":[
        {
            "category":"Restaurant",
            "type":"Food & Drink"
        }
    ],
    "sg:menulink":"http://www.allmenus.com/mi/traverse-city/141331-ponderosa-steakhouse/menu/",
    "sg:phone":"+1 231 929 9720",
    "sg:postcode":"49686",
    "sg:province":"MI",
    "sg:tags":[
        "american"
    ],
    "wof:name":"Ponderosa Steakhouse",
    "wof:placetype":"venue"
},
  "geometry": {"coordinates":[-85.576121,44.75689],"type":"Point"}
}