{
  "type": "Feature",
  "properties": {
    "iso:country":"US",
    "sg:address":"22225 Green Hill Rd",
    "sg:city":"Farmington Hills",
    "sg:classifiers":[
        {
            "category":"Communications",
            "subcategory":"Newspaper",
            "type":"Services"
        }
    ],
    "sg:phone":"+1 248 426 7381",
    "sg:postcode":"48335",
    "sg:province":"MI",
    "sg:tags":[
        "print",
        "medium"
    ],
    "wof:name":"Angle Press Inc",
    "wof:placetype":"venue"
},
  "geometry": {"coordinates":[-83.402888,42.444737],"type":"Point"}
}