{
  "type": "Feature",
  "properties": {
    "iso:country":"US",
    "sg:address":"227 S Main St",
    "sg:city":"Nashville",
    "sg:classifiers":[
        {
            "category":"Real Estate",
            "subcategory":"Real Estate Agent",
            "type":"Services"
        }
    ],
    "sg:phone":"+1 517 852 1915",
    "sg:postcode":"49073",
    "sg:province":"MI",
    "wof:name":"Maple Valley Real Estate",
    "wof:placetype":"venue"
},
  "geometry": {"coordinates":[-85.093531,42.601988],"type":"Point"}
}