{
  "type": "Feature",
  "properties": {
    "iso:country":"US",
    "sg:address":"27625 John R Rd",
    "sg:city":"Madison Heights",
    "sg:classifiers":[
        {
            "category":"Shopping",
            "subcategory":"Florist",
            "type":"Retail Goods"
        }
    ],
    "sg:phone":"+1 248 547 0373",
    "sg:postcode":"48071",
    "sg:province":"MI",
    "wof:name":"Flower Factory Inc",
    "wof:placetype":"venue"
},
  "geometry": {"coordinates":[-83.10545500000001,42.493359],"type":"Point"}
}