{
  "type": "Feature",
  "properties": {
    "iso:country":"US",
    "sg:address":"34250 Ford Rd",
    "sg:city":"Westland",
    "sg:classifiers":[
        {
            "category":"Personal",
            "subcategory":"Barber",
            "type":"Services"
        }
    ],
    "sg:phone":"+1 734 326 2280",
    "sg:postcode":"48185",
    "sg:province":"MI",
    "wof:name":"Sy's Barber Shop",
    "wof:placetype":"venue"
},
  "geometry": {"coordinates":[-83.37869999999999,42.324799],"type":"Point"}
}