{
  "type": "Feature",
  "properties": {
    "iso:country":"US",
    "sg:address":"2711 E Maumee St",
    "sg:city":"Adrian",
    "sg:classifiers":[
        {
            "category":"Organizations",
            "subcategory":"Labor Organization",
            "type":"Services"
        }
    ],
    "sg:phone":"+1 517 265 5033",
    "sg:postcode":"49221",
    "sg:province":"MI",
    "wof:name":"USWA 8874",
    "wof:placetype":"venue"
},
  "geometry": {"coordinates":[-84.00640300000001,41.892019],"type":"Point"}
}