{
  "type": "Feature",
  "properties": {
    "iso:country":"US",
    "sg:address":"16030 Michigan Ave",
    "sg:city":"Dearborn",
    "sg:classifiers":[
        {
            "category":"Real Estate",
            "subcategory":"Real Estate Agent",
            "type":"Services"
        }
    ],
    "sg:phone":"+1 313 584 0312",
    "sg:postcode":"48126",
    "sg:province":"MI",
    "sg:tags":[
        "brokerage",
        "developer"
    ],
    "wof:name":"BBA Associates",
    "wof:placetype":"venue"
},
  "geometry": {"coordinates":[-83.200756,42.315089],"type":"Point"}
}