{
  "type": "Feature",
  "properties": {
    "iso:country":"US",
    "sg:address":"8383 Airport Dr",
    "sg:city":"Watervliet",
    "sg:classifiers":[
        {
            "category":"Manufacturing",
            "subcategory":"Furniture",
            "type":"Manufacturing & Wholesale Goods"
        }
    ],
    "sg:phone":"+1 269 463 6443",
    "sg:postcode":"49098",
    "sg:province":"MI",
    "sg:tags":[
        "household",
        "wood",
        "mfg"
    ],
    "wof:name":"Creekside Furniture Co",
    "wof:placetype":"venue"
},
  "geometry": {"coordinates":[-86.256342,42.199483],"type":"Point"}
}