{
  "type": "Feature",
  "properties": {
    "iso:country":"US",
    "sg:address":"12001 Sears St",
    "sg:city":"Livonia",
    "sg:classifiers":[
        {
            "category":"Home & Garden",
            "subcategory":"Household Appliances",
            "type":"Retail Goods"
        }
    ],
    "sg:phone":"+1 734 422 5700",
    "sg:postcode":"48150",
    "sg:province":"MI",
    "wof:name":"Sears Outlet Stores Store #5230",
    "wof:placetype":"venue"
},
  "geometry": {"coordinates":[-83.346001,42.371201],"type":"Point"}
}