{
  "type": "Feature",
  "properties": {
    "iso:country":"US",
    "sg:address":"2422 Fort Park Blvd",
    "sg:city":"Lincoln Park",
    "sg:classifiers":[
        {
            "category":"Shopping",
            "subcategory":"Bicycles & Sporting Goods",
            "type":"Retail Goods"
        }
    ],
    "sg:phone":"+1 313 382 2629",
    "sg:postcode":"48146",
    "sg:province":"MI",
    "wof:name":"Dock The",
    "wof:placetype":"venue"
},
  "geometry": {"coordinates":[-83.18191899999999,42.244897],"type":"Point"}
}