{
  "type": "Feature",
  "properties": {
    "iso:country":"US",
    "sg:address":"4737 Dixie Hwy",
    "sg:city":"Waterford",
    "sg:classifiers":[
        {
            "category":"Restaurant",
            "type":"Food & Drink"
        }
    ],
    "sg:phone":"+1 248 674 8490",
    "sg:postcode":"48329",
    "sg:province":"MI",
    "wof:name":"Cooper's Family Dining",
    "wof:placetype":"venue"
},
  "geometry": {"coordinates":[-83.382841,42.687428],"type":"Point"}
}