{
  "type": "Feature",
  "properties": {
    "iso:country":"US",
    "sg:address":"14567 Goutz Rd",
    "sg:city":"Monroe",
    "sg:classifiers":[
        {
            "category":"Professional",
            "subcategory":"Accounting & Tax Preparation",
            "type":"Services"
        }
    ],
    "sg:phone":"+1 734 243 0886",
    "sg:postcode":"48161",
    "sg:province":"MI",
    "wof:name":"Judys Bookkeeping",
    "wof:placetype":"venue"
},
  "geometry": {"coordinates":[-83.48315100000001,41.885616],"type":"Point"}
}