{
  "type": "Feature",
  "properties": {
    "iso:country":"US",
    "sg:address":"200 E Bay St",
    "sg:city":"East Tawas",
    "sg:classifiers":[
        {
            "category":"Utilities",
            "subcategory":"Mobile Phone",
            "type":"Services"
        }
    ],
    "sg:phone":"+1 989 984 0005",
    "sg:postcode":"48730",
    "sg:province":"MI",
    "sg:tags":[
        "telephone",
        "cellular"
    ],
    "wof:name":"Cellular One",
    "wof:placetype":"venue"
},
  "geometry": {"coordinates":[-83.48792,44.279959],"type":"Point"}
}