{
  "type": "Feature",
  "properties": {
    "iso:country":"US",
    "sg:address":"26559 Berg Rd",
    "sg:city":"Southfield",
    "sg:classifiers":[
        {
            "category":"Professional",
            "type":"Services"
        }
    ],
    "sg:phone":"+1 248 358 2653",
    "sg:postcode":"48033",
    "sg:province":"MI",
    "wof:name":"Devabhaktuni Naga",
    "wof:placetype":"venue"
},
  "geometry": {"coordinates":[-83.279601,42.483082],"type":"Point"}
}