{
  "type": "Feature",
  "properties": {
    "iso:country":"US",
    "sg:address":"37080 Wahimund Ave",
    "sg:city":"Paw Paw",
    "sg:classifiers":[
        {
            "category":"Building & Trades",
            "subcategory":"Construction",
            "type":"Services"
        }
    ],
    "sg:phone":"+1 269 657 4246",
    "sg:postcode":"49079",
    "sg:province":"MI",
    "wof:name":"Dl Contracting",
    "wof:placetype":"venue"
},
  "geometry": {"coordinates":[-85.908473,42.241359],"type":"Point"}
}