{
  "type": "Feature",
  "properties": {
    "iso:country":"US",
    "sg:address":"26401 Harper Ave",
    "sg:city":"St Clair Shores",
    "sg:classifiers":[
        {
            "category":"Utilities",
            "subcategory":"Mobile Phone",
            "type":"Services"
        }
    ],
    "sg:phone":"+1 586 777 4010",
    "sg:postcode":"48081",
    "sg:province":"MI",
    "sg:tags":[
        "telephone",
        "cellular"
    ],
    "sg:website":"www.verizonwireless.com",
    "wof:name":"Verizon Wireless",
    "wof:placetype":"venue"
},
  "geometry": {"coordinates":[-82.89806,42.488448],"type":"Point"}
}