{
  "type": "Feature",
  "properties": {
    "iso:country":"US",
    "sg:address":"1035 Country Ln",
    "sg:city":"Ishpeming",
    "sg:classifiers":[
        {
            "category":"Shopping",
            "subcategory":"Stationery & Office Supplies",
            "type":"Retail Goods"
        }
    ],
    "sg:phone":"+1 906 486 9110",
    "sg:postcode":"49849",
    "sg:province":"MI",
    "wof:name":"Office Supplies N' Svc",
    "wof:placetype":"venue"
},
  "geometry": {"coordinates":[-87.67912699999999,46.501746],"type":"Point"}
}