{
  "type": "Feature",
  "properties": {
    "iso:country":"US",
    "sg:address":"5551 Heather Ln",
    "sg:city":"Dearborn Heights",
    "sg:classifiers":[
        {
            "category":"Social Services",
            "subcategory":"Child Care",
            "type":"Services"
        }
    ],
    "sg:phone":"+1 313 292 2354",
    "sg:postcode":"48125",
    "sg:province":"MI",
    "sg:tags":[
        "home",
        "day"
    ],
    "wof:name":"Marie Kolo Juile",
    "wof:placetype":"venue"
},
  "geometry": {"coordinates":[-83.26023600000001,42.272993],"type":"Point"}
}