{
  "type": "Feature",
  "properties": {
    "iso:country":"US",
    "sg:address":"1110 E Bay St",
    "sg:city":"East Tawas",
    "sg:classifiers":[
        {
            "category":"Travel",
            "subcategory":"Hotels & Motels",
            "type":"Entertainment"
        }
    ],
    "sg:phone":"+1 989 362 6562",
    "sg:postcode":"48730",
    "sg:province":"MI",
    "sg:tags":[
        "operation"
    ],
    "wof:name":"Riptide Motel & Cabins",
    "wof:placetype":"venue"
},
  "geometry": {"coordinates":[-83.47859099999999,44.281247],"type":"Point"}
}