{
  "type": "Feature",
  "properties": {
    "iso:country":"US",
    "sg:address":"9675 Fitzner Rd",
    "sg:city":"Lakeview",
    "sg:classifiers":[
        {
            "category":"Building & Trades",
            "subcategory":"Construction",
            "type":"Services"
        }
    ],
    "sg:phone":"+1 989 352 7285",
    "sg:postcode":"48850",
    "sg:province":"MI",
    "sg:tags":[
        "floor",
        "laying",
        "contractor"
    ],
    "wof:name":"Absolute Paint & Drywall Inc",
    "wof:placetype":"venue"
},
  "geometry": {"coordinates":[-85.233862,43.433115],"type":"Point"}
}