{
  "type": "Feature",
  "properties": {
    "iso:country":"US",
    "sg:address":"6331 120th Ave",
    "sg:city":"Fennville",
    "sg:classifiers":[
        {
            "category":"Farming",
            "subcategory":"Orchard",
            "type":"Manufacturing & Wholesale Goods"
        }
    ],
    "sg:phone":"+1 269 561 2594",
    "sg:postcode":"49408",
    "sg:province":"MI",
    "sg:tags":[
        "fruit",
        "tree"
    ],
    "wof:name":"Phelps Glenn",
    "wof:placetype":"venue"
},
  "geometry": {"coordinates":[-86.160318,42.563985],"type":"Point"}
}