{
  "type": "Feature",
  "properties": {
    "iso:country":"US",
    "sg:address":"405 Knapp St NE",
    "sg:city":"Grand Rapids",
    "sg:classifiers":[
        {
            "category":"Professional",
            "subcategory":"Business Services",
            "type":"Services"
        }
    ],
    "sg:phone":"+1 616 363 4993",
    "sg:postcode":"49505",
    "sg:province":"MI",
    "sg:tags":[
        "interior",
        "consultant",
        "design",
        "decorator"
    ],
    "wof:name":"K Studio",
    "wof:placetype":"venue"
},
  "geometry": {"coordinates":[-85.658354,42.999124],"type":"Point"}
}