{
  "type": "Feature",
  "properties": {
    "iso:country":"US",
    "sg:address":"5205 Highland Rd",
    "sg:city":"Waterford",
    "sg:classifiers":[
        {
            "category":"Health Services",
            "subcategory":"Doctor",
            "type":"Services"
        }
    ],
    "sg:phone":"+1 248 674 9880",
    "sg:postcode":"48327",
    "sg:province":"MI",
    "sg:tags":[
        "dentist"
    ],
    "wof:name":"Michigan Orthodontic Specs",
    "wof:placetype":"venue"
},
  "geometry": {"coordinates":[-83.392149,42.660185],"type":"Point"}
}