{
  "type": "Feature",
  "properties": {
    "iso:country":"US",
    "sg:address":"34190 S Gratiot Ave",
    "sg:city":"Clinton Township",
    "sg:classifiers":[
        {
            "category":"Shopping",
            "subcategory":"Pets & Pet Supplies",
            "type":"Retail Goods"
        }
    ],
    "sg:phone":"+1 586 791 6595",
    "sg:postcode":"48035",
    "sg:province":"MI",
    "sg:tags":[
        "store"
    ],
    "wof:name":"Tropical Treasures",
    "wof:placetype":"venue"
},
  "geometry": {"coordinates":[-82.90239699999999,42.549099],"type":"Point"}
}