{
  "type": "Feature",
  "properties": {
    "iso:country":"US",
    "sg:address":"2065 Hiller Rd",
    "sg:city":"West Bloomfield",
    "sg:classifiers":[
        {
            "category":"Food & Beverages",
            "subcategory":"Groceries & Convenience Stores",
            "type":"Retail Goods"
        }
    ],
    "sg:phone":"+1 248 682 7986",
    "sg:postcode":"48324",
    "sg:province":"MI",
    "wof:name":"Hiller Food Wine Basket",
    "wof:placetype":"venue"
},
  "geometry": {"coordinates":[-83.398003,42.6073],"type":"Point"}
}