{
  "type": "Feature",
  "properties": {
    "iso:country":"US",
    "sg:address":"924 Terminal Rd",
    "sg:city":"Lansing",
    "sg:classifiers":[
        {
            "category":"Professional",
            "subcategory":"Advertising",
            "type":"Services"
        }
    ],
    "sg:phone":"+1 517 321 0188",
    "sg:postcode":"48906",
    "sg:province":"MI",
    "sg:tags":[
        "counselor"
    ],
    "sg:website":"www.obriensagency.com",
    "wof:name":"O'Brien's Agency Inc",
    "wof:placetype":"venue"
},
  "geometry": {"coordinates":[-84.565704,42.765831],"type":"Point"}
}