{
  "type": "Feature",
  "properties": {
    "iso:country":"US",
    "sg:address":"32726 White Oaks Trl",
    "sg:city":"Beverly Hills",
    "sg:classifiers":[
        {
            "category":"Building & Trades",
            "subcategory":"Equipment Rental",
            "type":"Services"
        }
    ],
    "sg:phone":"+1 248 646 7170",
    "sg:postcode":"48025",
    "sg:province":"MI",
    "sg:tags":[
        "leasing"
    ],
    "sg:website":"www.bankersquote.com",
    "wof:name":"Bankers Leasing Svc",
    "wof:placetype":"venue"
},
  "geometry": {"coordinates":[-83.26901700000001,42.529007],"type":"Point"}
}