{
  "type": "Feature",
  "properties": {
    "iso:country":"US",
    "sg:address":"2018 Browntown Rd",
    "sg:city":"Buchanan",
    "sg:classifiers":[
        {
            "category":"Professional",
            "subcategory":"Accounting & Tax Preparation",
            "type":"Services"
        }
    ],
    "sg:phone":"+1 269 422 2482",
    "sg:postcode":"49107",
    "sg:province":"MI",
    "sg:tags":[
        "return"
    ],
    "wof:name":"A1 Tax Service",
    "wof:placetype":"venue"
},
  "geometry": {"coordinates":[-86.497051,41.899216],"type":"Point"}
}