{
  "type": "Feature",
  "properties": {
    "iso:country":"US",
    "sg:address":"1424 Straits Dr",
    "sg:city":"Bay City",
    "sg:classifiers":[
        {
            "category":"Railroad",
            "type":"Transportation"
        }
    ],
    "sg:phone":"+1 989 684 5088",
    "sg:postcode":"48706",
    "sg:province":"MI",
    "wof:name":"Straits Service Co",
    "wof:placetype":"venue"
},
  "geometry": {"coordinates":[-83.99540500000001,43.593731],"type":"Point"}
}