{
  "type": "Feature",
  "properties": {
    "iso:country":"US",
    "sg:address":"4855 Fox Creek",
    "sg:city":"Clarkston",
    "sg:classifiers":[
        {
            "category":"Real Estate",
            "subcategory":"Real Estate Operator",
            "type":"Services"
        }
    ],
    "sg:phone":"+1 248 618 8100",
    "sg:postcode":"48346",
    "sg:province":"MI",
    "sg:tags":[
        "apartment"
    ],
    "wof:name":"Village Of Fox Creek",
    "wof:placetype":"venue"
},
  "geometry": {"coordinates":[-83.346428,42.71401],"type":"Point"}
}