{
  "type": "Feature",
  "properties": {
    "iso:country":"US",
    "sg:address":"3107 N Custer Rd",
    "sg:city":"Monroe",
    "sg:classifiers":[
        {
            "category":"Building & Trades",
            "subcategory":"Construction",
            "type":"Services"
        }
    ],
    "sg:phone":"+1 734 243 5381",
    "sg:postcode":"48162",
    "sg:province":"MI",
    "sg:tags":[
        "roofing",
        "contractor"
    ],
    "wof:name":"Rocky's Roofing",
    "wof:placetype":"venue"
},
  "geometry": {"coordinates":[-83.450199,41.931463],"type":"Point"}
}