{
  "type": "Feature",
  "properties": {
    "iso:country":"US",
    "sg:address":"1000 N Washington Ave",
    "sg:city":"Lansing",
    "sg:classifiers":[
        {
            "category":"Personal",
            "type":"Services"
        }
    ],
    "sg:phone":"+1 517 487 3600",
    "sg:postcode":"48906",
    "sg:province":"MI",
    "sg:tags":[
        "health",
        "practitioner",
        "specialty",
        "outpatient"
    ],
    "wof:name":"Alternative Wellness Center",
    "wof:placetype":"venue"
},
  "geometry": {"coordinates":[-84.55211799999999,42.746108],"type":"Point"}
}