{
  "type": "Feature",
  "properties": {
    "iso:country":"US",
    "sg:address":"3129 Bolgos Cir",
    "sg:city":"Ann Arbor",
    "sg:classifiers":[
        {
            "category":"Professional",
            "subcategory":"Business Services",
            "type":"Services"
        }
    ],
    "sg:phone":"+1 734 663 9081",
    "sg:postcode":"48105",
    "sg:province":"MI",
    "wof:name":"R3 Solutions Inc",
    "wof:placetype":"venue"
},
  "geometry": {"coordinates":[-83.689294,42.312625],"type":"Point"}
}