{
  "type": "Feature",
  "properties": {
    "iso:country":"US",
    "sg:address":"1510 E Carpenter Rd",
    "sg:city":"Flint",
    "sg:classifiers":[
        {
            "category":"Food & Beverages",
            "subcategory":"Bakery",
            "type":"Retail Goods"
        }
    ],
    "sg:phone":"+1 810 785 4766",
    "sg:postcode":"48505",
    "sg:province":"MI",
    "sg:tags":[
        "baker"
    ],
    "wof:name":"Wonder Bread & Hostess Cakes",
    "wof:placetype":"venue"
},
  "geometry": {"coordinates":[-83.67664499999999,43.075748],"type":"Point"}
}