{
  "type": "Feature",
  "properties": {
    "iso:country":"US",
    "sg:address":"2437 Okemos Dr SE",
    "sg:city":"Grand Rapids",
    "sg:classifiers":[
        {
            "category":"Home & Garden",
            "subcategory":"Furniture",
            "type":"Retail Goods"
        }
    ],
    "sg:phone":"+1 616 988 1068",
    "sg:postcode":"49506",
    "sg:province":"MI",
    "sg:website":"www.arofurn.com",
    "wof:name":"ARO Furniture Group",
    "wof:placetype":"venue"
},
  "geometry": {"coordinates":[-85.61341299999999,42.919279],"type":"Point"}
}