{
  "type": "Feature",
  "properties": {
    "iso:country":"US",
    "sg:address":"400 Ashmun St",
    "sg:city":"Sault Ste Marie",
    "sg:classifiers":[
        {
            "category":"Shopping",
            "subcategory":"Jewelry",
            "type":"Retail Goods"
        }
    ],
    "sg:phone":"+1 906 635 9150",
    "sg:postcode":"49783",
    "sg:province":"MI",
    "sg:tags":[
        "jeweler"
    ],
    "wof:name":"Ryan's Jewelry",
    "wof:placetype":"venue"
},
  "geometry": {"coordinates":[-84.347003,46.498421],"type":"Point"}
}