{
  "type": "Feature",
  "properties": {
    "iso:country":"US",
    "sg:address":"11420 Wing Dr",
    "sg:city":"Clio",
    "sg:classifiers":[
        {
            "category":"Shopping",
            "subcategory":"Clothing, Apparel, & Fashions",
            "type":"Retail Goods"
        }
    ],
    "sg:phone":"+1 810 686 4835",
    "sg:postcode":"48420",
    "sg:province":"MI",
    "sg:tags":[
        "lingerie"
    ],
    "wof:name":"Undercover Wear Fashions",
    "wof:placetype":"venue"
},
  "geometry": {"coordinates":[-83.752472,43.175925],"type":"Point"}
}