{
  "type": "Feature",
  "properties": {
    "iso:country":"US",
    "sg:address":"1998 Jolly Rd",
    "sg:city":"Okemos",
    "sg:classifiers":[
        {
            "category":"Professional",
            "subcategory":"Lawyer & Legal Services",
            "type":"Services"
        }
    ],
    "sg:phone":"+1 517 381 1344",
    "sg:postcode":"48864",
    "sg:province":"MI",
    "sg:tags":[
        "security",
        "counselor",
        "rep",
        "social"
    ],
    "wof:name":"Social Security Disability",
    "wof:placetype":"venue"
},
  "geometry": {"coordinates":[-84.425062,42.682942],"type":"Point"}
}