{
  "type": "Feature",
  "properties": {
    "iso:country":"US",
    "sg:address":"6575 US Hwy 23",
    "sg:city":"Spruce",
    "sg:classifiers":[
        {
            "category":"Food & Beverages",
            "subcategory":"Groceries & Convenience Stores",
            "type":"Retail Goods"
        }
    ],
    "sg:phone":"+1 989 471 9159",
    "sg:postcode":"48762",
    "sg:province":"MI",
    "sg:tags":[
        "grocer"
    ],
    "wof:name":"Chippewa Point Grocery",
    "wof:placetype":"venue"
},
  "geometry": {"coordinates":[-83.40810999999999,44.846605],"type":"Point"}
}