{
  "type": "Feature",
  "properties": {
    "iso:country":"US",
    "sg:address":"16849 E 14 Mile Rd",
    "sg:city":"Fraser",
    "sg:classifiers":[
        {
            "category":"Professional",
            "subcategory":"Employment Agencies",
            "type":"Services"
        }
    ],
    "sg:phone":"+1 586 541 0416",
    "sg:postcode":"48026",
    "sg:province":"MI",
    "wof:name":"Reliance-One",
    "wof:placetype":"venue"
},
  "geometry": {"coordinates":[-82.94900800000001,42.539031],"type":"Point"}
}