{
  "type": "Feature",
  "properties": {
    "iso:country":"US",
    "sg:address":"744 Wing St.",
    "sg:city":"Plymouth",
    "sg:classifiers":[
        {
            "category":"Deli",
            "type":"Food & Drink"
        },
        {
            "category":"Restaurant",
            "type":"Food & Drink"
        }
    ],
    "sg:phone":"+1 734 207 7880",
    "sg:postcode":"48170",
    "sg:province":"MI",
    "sg:tags":[
        "italian"
    ],
    "sg:website":"wwww.nicoandvali.com",
    "wof:name":"Nico & Vali",
    "wof:placetype":"venue"
},
  "geometry": {"coordinates":[-83.468768,42.367683],"type":"Point"}
}