{
  "type": "Feature",
  "properties": {
    "iso:country":"US",
    "sg:address":"16733 Middlebelt Rd",
    "sg:city":"Livonia",
    "sg:classifiers":[
        {
            "category":"Personal",
            "subcategory":"Tanning Parlor",
            "type":"Services"
        }
    ],
    "sg:phone":"+1 734 524 9900",
    "sg:postcode":"48154",
    "sg:province":"MI",
    "wof:name":"Designer Tanning of Livonia",
    "wof:placetype":"venue"
},
  "geometry": {"coordinates":[-83.335249,42.409933],"type":"Point"}
}