{
  "type": "Feature",
  "properties": {
    "iso:country":"US",
    "sg:address":"4577 US Hwy 31",
    "sg:city":"Oden",
    "sg:classifiers":[
        {
            "category":"Restaurant",
            "type":"Food & Drink"
        }
    ],
    "sg:phone":"+1 231 348 7528",
    "sg:postcode":"49764",
    "sg:province":"MI",
    "sg:tags":[
        "pizza"
    ],
    "wof:name":"Tignanelli's",
    "wof:placetype":"venue"
},
  "geometry": {"coordinates":[-84.822613,45.421833],"type":"Point"}
}