{
  "type": "Feature",
  "properties": {
    "iso:country":"US",
    "sg:address":"103 Belvedere Ave",
    "sg:city":"Charlevoix",
    "sg:classifiers":[
        {
            "category":"Professional",
            "subcategory":"Lawyer & Legal Services",
            "type":"Services"
        }
    ],
    "sg:phone":"+1 231 547 9941",
    "sg:postcode":"49720",
    "sg:province":"MI",
    "sg:tags":[
        "attorney"
    ],
    "wof:name":"Hoffman & Hoffman",
    "wof:placetype":"venue"
},
  "geometry": {"coordinates":[-85.25548499999999,45.314809],"type":"Point"}
}