{
  "type": "Feature",
  "properties": {
    "iso:country":"US",
    "sg:address":"75 E Van Buren Rd",
    "sg:city":"Alma",
    "sg:classifiers":[
        {
            "category":"Retail",
            "subcategory":"Animal Services",
            "type":"Services"
        }
    ],
    "sg:phone":"+1 989 463 2008",
    "sg:postcode":"48801",
    "sg:province":"MI",
    "sg:tags":[
        "pet",
        "grooming",
        "washing"
    ],
    "wof:name":"Puppy Luv Boarding & Grooming",
    "wof:placetype":"venue"
},
  "geometry": {"coordinates":[-84.60265200000001,43.364184],"type":"Point"}
}