{
  "type": "Feature",
  "properties": {
    "iso:country":"US",
    "sg:address":"2336 Port Sheldon Ct",
    "sg:city":"Hudsonville",
    "sg:classifiers":[
        {
            "category":"Building & Trades",
            "subcategory":"Cleaning & Sanitation",
            "type":"Services"
        }
    ],
    "sg:phone":"+1 616 662 4266",
    "sg:postcode":"49426",
    "sg:province":"MI",
    "sg:tags":[
        "ventilating",
        "system"
    ],
    "wof:name":"Safety King Inc",
    "wof:placetype":"venue"
},
  "geometry": {"coordinates":[-85.840008,42.885664],"type":"Point"}
}