{
  "type": "Feature",
  "properties": {
    "iso:country":"US",
    "sg:address":"23709 Harper Ave",
    "sg:city":"St Clair Shores",
    "sg:classifiers":[
        {
            "category":"Retail",
            "subcategory":"Auto Rental",
            "type":"Services"
        }
    ],
    "sg:phone":"+1 586 773 1008",
    "sg:postcode":"48080",
    "sg:province":"MI",
    "sg:tags":[
        "renting",
        "automobile"
    ],
    "wof:name":"Hertz Rent A Car",
    "wof:placetype":"venue"
},
  "geometry": {"coordinates":[-82.90595999999999,42.470491],"type":"Point"}
}