{
  "type": "Feature",
  "properties": {
    "iso:country":"US",
    "sg:address":"2881 Orchard Lake Rd",
    "sg:city":"Keego Harbor",
    "sg:classifiers":[
        {
            "category":"Social Services",
            "type":"Services"
        }
    ],
    "sg:phone":"+1 248 681 6172",
    "sg:postcode":"48320",
    "sg:province":"MI",
    "wof:name":"Keego Harbr Snr Ctzn Nutrtn Si",
    "wof:placetype":"venue"
},
  "geometry": {"coordinates":[-83.341774,42.606516],"type":"Point"}
}