{
  "type": "Feature",
  "properties": {
    "iso:country":"US",
    "sg:address":"1001 S Lincoln Dr",
    "sg:city":"Hancock",
    "sg:classifiers":[
        {
            "category":"Organizations",
            "subcategory":"Religious Organization",
            "type":"Services"
        }
    ],
    "sg:phone":"+1 906 482 8704",
    "sg:postcode":"49930",
    "sg:province":"MI",
    "sg:tags":[
        "church"
    ],
    "sg:website":"www.coc.chartermi.net",
    "wof:name":"Church Of Christ",
    "wof:placetype":"venue"
},
  "geometry": {"coordinates":[-88.59923499999999,47.129453],"type":"Point"}
}