{
  "type": "Feature",
  "properties": {
    "iso:country":"US",
    "sg:address":"8810 Eldorado",
    "sg:city":"White Lake",
    "sg:classifiers":[
        {
            "category":"Home & Garden",
            "subcategory":"Building Materials",
            "type":"Retail Goods"
        }
    ],
    "sg:phone":"+1 248 762 1110",
    "sg:postcode":"48386",
    "sg:province":"MI",
    "sg:tags":[
        "urinal",
        "sales"
    ],
    "wof:name":"Falcon Waterfree Technologies",
    "wof:placetype":"venue"
},
  "geometry": {"coordinates":[-83.458814,42.640316],"type":"Point"}
}