{
  "type": "Feature",
  "properties": {
    "iso:country":"US",
    "sg:address":"908 Main St",
    "sg:city":"Saint Joseph",
    "sg:classifiers":[
        {
            "category":"Insurance",
            "subcategory":"Insurance Agent",
            "type":"Services"
        }
    ],
    "sg:phone":"+1 269 983 5447",
    "sg:postcode":"49085",
    "sg:province":"MI",
    "wof:name":"State Farm Insurance",
    "wof:placetype":"venue"
},
  "geometry": {"coordinates":[-86.485181,42.103607],"type":"Point"}
}