{
  "type": "Feature",
  "properties": {
    "iso:country":"US",
    "sg:address":"24333 Southfield Rd",
    "sg:city":"Southfield",
    "sg:classifiers":[
        {
            "category":"Professional",
            "subcategory":"Accounting & Tax Preparation",
            "type":"Services"
        }
    ],
    "sg:phone":"+1 248 905 5900",
    "sg:postcode":"48075",
    "sg:province":"MI",
    "sg:tags":[
        "accountant"
    ],
    "wof:name":"Mitchell Accounting & Consulting",
    "wof:placetype":"venue"
},
  "geometry": {"coordinates":[-83.220901,42.468201],"type":"Point"}
}