{
  "type": "Feature",
  "properties": {
    "iso:country":"US",
    "sg:address":"1149 Teakwood Cir",
    "sg:city":"Haslett",
    "sg:classifiers":[
        {
            "category":"Professional",
            "subcategory":"Management & Consulting",
            "type":"Services"
        }
    ],
    "sg:phone":"+1 517 339 1645",
    "sg:postcode":"48840",
    "sg:province":"MI",
    "sg:tags":[
        "consultant",
        "education"
    ],
    "wof:name":"Kratus John",
    "wof:placetype":"venue"
},
  "geometry": {"coordinates":[-84.38945699999999,42.742016],"type":"Point"}
}