{
  "type": "Feature",
  "properties": {
    "iso:country":"US",
    "sg:address":"2438 28th St SW",
    "sg:city":"Wyoming",
    "sg:classifiers":[
        {
            "category":"Building & Trades",
            "subcategory":"Plumbing",
            "type":"Services"
        }
    ],
    "sg:phone":"+1 616 532 3485",
    "sg:postcode":"49519",
    "sg:province":"MI",
    "sg:tags":[
        "plumbing",
        "contractor"
    ],
    "wof:name":"Mr Rooter",
    "wof:placetype":"venue"
},
  "geometry": {"coordinates":[-85.72648599999999,42.913848],"type":"Point"}
}