{
  "type": "Feature",
  "properties": {
    "iso:country":"US",
    "sg:address":"3396 Fairlane Dr",
    "sg:city":"Allen Park",
    "sg:classifiers":[
        {
            "category":"Shopping",
            "subcategory":"Shoes",
            "type":"Retail Goods"
        }
    ],
    "sg:phone":"+1 313 583 0885",
    "sg:postcode":"48101",
    "sg:province":"MI",
    "sg:tags":[
        "store"
    ],
    "sg:website":"www.theathletesfoot.com",
    "wof:name":"Athlete's Foot the",
    "wof:placetype":"venue"
},
  "geometry": {"coordinates":[-83.207275,42.280683],"type":"Point"}
}