{
  "type": "Feature",
  "properties": {
    "iso:country":"US",
    "sg:address":"7647 Ellens Way St",
    "sg:city":"Ann Arbor",
    "sg:classifiers":[
        {
            "category":"Professional",
            "subcategory":"Engineering",
            "type":"Services"
        }
    ],
    "sg:phone":"+1 734 340 4620",
    "sg:postcode":"48105",
    "sg:province":"MI",
    "sg:tags":[
        "consulting"
    ],
    "wof:name":"Webertech Inc",
    "wof:placetype":"venue"
},
  "geometry": {"coordinates":[-83.614266,42.325978],"type":"Point"}
}