{
  "type": "Feature",
  "properties": {
    "iso:country":"US",
    "sg:address":"3205 Bermuda St",
    "sg:city":"Ferndale",
    "sg:classifiers":[
        {
            "category":"Wholesale",
            "subcategory":"Machinery & Supplies",
            "type":"Manufacturing & Wholesale Goods"
        }
    ],
    "sg:phone":"+1 248 544 2982",
    "sg:postcode":"48220",
    "sg:province":"MI",
    "sg:tags":[
        "equipment",
        "industrial",
        "gas",
        "compressor"
    ],
    "wof:name":"Detroit Air Compressor Company",
    "wof:placetype":"venue"
},
  "geometry": {"coordinates":[-83.133047,42.474144],"type":"Point"}
}