{
  "type": "Feature",
  "properties": {
    "iso:country":"US",
    "sg:address":"3150 Plainfield Ave NE",
    "sg:city":"Grand Rapids",
    "sg:classifiers":[
        {
            "category":"Restaurant",
            "type":"Food & Drink"
        }
    ],
    "sg:phone":"+1 616 447 0080",
    "sg:postcode":"49525",
    "sg:province":"MI",
    "sg:tags":[
        "shop",
        "coffee"
    ],
    "wof:name":"Frenz Coffee House",
    "wof:placetype":"venue"
},
  "geometry": {"coordinates":[-85.634852,43.020025],"type":"Point"}
}