{
  "type": "Feature",
  "properties": {
    "iso:country":"US",
    "sg:address":"400 Green Acres Dr",
    "sg:city":"Sandusky",
    "sg:classifiers":[
        {
            "category":"Recreation",
            "type":"Entertainment"
        }
    ],
    "sg:phone":"+1 810 648 1313",
    "sg:postcode":"48471",
    "sg:province":"MI",
    "sg:tags":[
        "hall",
        "auditorium"
    ],
    "wof:name":"Thumb Memorial Disabled Vets",
    "wof:placetype":"venue"
},
  "geometry": {"coordinates":[-82.84254799999999,43.427757],"type":"Point"}
}