{
  "type": "Feature",
  "properties": {
    "iso:country":"US",
    "sg:address":"10598 Sperry Rd SW",
    "sg:city":"Fife Lake",
    "sg:classifiers":[
        {
            "category":"Retail",
            "subcategory":"Repair Shop",
            "type":"Services"
        }
    ],
    "sg:phone":"+1 231 879 4227",
    "sg:postcode":"49633",
    "sg:province":"MI",
    "sg:tags":[
        "welding"
    ],
    "wof:name":"Witeks Welding",
    "wof:placetype":"venue"
},
  "geometry": {"coordinates":[-85.303106,44.560612],"type":"Point"}
}