{
  "type": "Feature",
  "properties": {
    "iso:country":"US",
    "sg:address":"19195 Livernois Ave",
    "sg:city":"Detroit",
    "sg:classifiers":[
        {
            "category":"Food & Beverages",
            "subcategory":"Groceries & Convenience Stores",
            "type":"Retail Goods"
        }
    ],
    "sg:phone":"+1 313 345 4711",
    "sg:postcode":"48221",
    "sg:province":"MI",
    "wof:name":"MIke's Fresh Market",
    "wof:placetype":"venue"
},
  "geometry": {"coordinates":[-83.141516,42.432426],"type":"Point"}
}