{
  "type": "Feature",
  "properties": {
    "iso:country":"US",
    "sg:address":"14953 E 9 Mile Rd",
    "sg:city":"Eastpointe",
    "sg:classifiers":[
        {
            "category":"Personal",
            "subcategory":"Beauty Salon",
            "type":"Services"
        }
    ],
    "sg:phone":"+1 586 771 5660",
    "sg:postcode":"48021",
    "sg:province":"MI",
    "sg:tags":[
        "shop"
    ],
    "wof:name":"Fantastic Sam's",
    "wof:placetype":"venue"
},
  "geometry": {"coordinates":[-82.967631,42.464736],"type":"Point"}
}