{
  "type": "Feature",
  "properties": {
    "iso:country":"US",
    "sg:address":"15264 Michigan Ave.",
    "sg:city":"Dearborn",
    "sg:classifiers":[
        {
            "category":"Restaurant",
            "type":"Food & Drink"
        }
    ],
    "sg:phone":"+1 313 582 8500",
    "sg:postcode":"48126",
    "sg:province":"MI",
    "sg:tags":[
        "pizza"
    ],
    "sg:website":"www.pizzakitchendearborn.com/",
    "wof:name":"Pizza Kitchen",
    "wof:placetype":"venue"
},
  "geometry": {"coordinates":[-83.19274299999999,42.317402],"type":"Point"}
}