{
  "type": "Feature",
  "properties": {
    "iso:country":"US",
    "sg:address":"201 Elm St",
    "sg:city":"Big Rapids",
    "sg:classifiers":[
        {
            "category":"Building & Trades",
            "subcategory":"Equipment Rental",
            "type":"Services"
        }
    ],
    "sg:phone":"+1 231 592 0834",
    "sg:postcode":"49307",
    "sg:province":"MI",
    "sg:tags":[
        "own",
        "leasing",
        "to",
        "rent",
        "store",
        "furniture"
    ],
    "wof:name":"Universal Rent To Own Inc",
    "wof:placetype":"venue"
},
  "geometry": {"coordinates":[-85.481938,43.697027],"type":"Point"}
}