{
  "type": "Feature",
  "properties": {
    "iso:country":"US",
    "sg:address":"9014 56th Ave",
    "sg:city":"Hudsonville",
    "sg:classifiers":[
        {
            "category":"Banks & Credit Unions",
            "subcategory":"Financial Services",
            "type":"Services"
        }
    ],
    "sg:phone":"+1 616 669 9198",
    "sg:postcode":"49426",
    "sg:province":"MI",
    "sg:tags":[
        "trust",
        "management"
    ],
    "wof:name":"John B Blythe",
    "wof:placetype":"venue"
},
  "geometry": {"coordinates":[-85.922656,42.932155],"type":"Point"}
}