{
  "type": "Feature",
  "properties": {
    "iso:country":"US",
    "sg:address":"258 Green St",
    "sg:city":"Springport",
    "sg:classifiers":[
        {
            "category":"Organizations",
            "subcategory":"Religious Organization",
            "type":"Services"
        }
    ],
    "sg:phone":"+1 517 857 3922",
    "sg:postcode":"49284",
    "sg:province":"MI",
    "sg:tags":[
        "church"
    ],
    "wof:name":"United Methodist Church",
    "wof:placetype":"venue"
},
  "geometry": {"coordinates":[-84.68912,42.375336],"type":"Point"}
}