{
  "type": "Feature",
  "properties": {
    "iso:country":"US",
    "sg:address":"9002 W 30 Rd",
    "sg:city":"Harrietta",
    "sg:classifiers":[
        {
            "category":"Food & Beverages",
            "subcategory":"Groceries & Convenience Stores",
            "type":"Retail Goods"
        }
    ],
    "sg:phone":"+1 231 389 2511",
    "sg:postcode":"49638",
    "sg:province":"MI",
    "wof:name":"Bill's Pit Stop",
    "wof:placetype":"venue"
},
  "geometry": {"coordinates":[-85.76532,44.309278],"type":"Point"}
}