{
  "type": "Feature",
  "properties": {
    "iso:country":"US",
    "sg:address":"2613 Lakeview Ave",
    "sg:city":"St Joseph",
    "sg:classifiers":[
        {
            "category":"Arts & Performance",
            "subcategory":"Theater",
            "type":"Entertainment"
        }
    ],
    "sg:phone":"+1 269 934 7918",
    "sg:postcode":"49085",
    "sg:province":"MI",
    "sg:tags":[
        "musician",
        "group"
    ],
    "wof:name":"Musicians Union Local 232",
    "wof:placetype":"venue"
},
  "geometry": {"coordinates":[-86.49031100000001,42.08882],"type":"Point"}
}