{
  "type": "Feature",
  "properties": {
    "iso:country":"US",
    "sg:address":"3750 Woodward Ave",
    "sg:city":"Detroit",
    "sg:classifiers":[
        {
            "category":"Banks & Credit Unions",
            "subcategory":"Bank",
            "type":"Services"
        }
    ],
    "sg:phone":"+1 313 833 3340",
    "sg:postcode":"48201",
    "sg:province":"MI",
    "sg:tags":[
        "state",
        "commercial"
    ],
    "wof:name":"Comerica",
    "wof:placetype":"venue"
},
  "geometry": {"coordinates":[-83.05865799999999,42.348546],"type":"Point"}
}