{
  "type": "Feature",
  "properties": {
    "iso:country":"US",
    "sg:address":"215 S Washington Ave",
    "sg:city":"Royal Oak",
    "sg:classifiers":[
        {
            "category":"Restaurant",
            "type":"Food & Drink"
        }
    ],
    "sg:phone":"+1 248 545 2700",
    "sg:postcode":"48067",
    "sg:province":"MI",
    "sg:tags":[
        "chinese"
    ],
    "sg:website":"pekinghousero.com",
    "wof:name":"Peking House",
    "wof:placetype":"venue"
},
  "geometry": {"coordinates":[-83.146236,42.488416],"type":"Point"}
}