{
  "type": "Feature",
  "properties": {
    "iso:country":"US",
    "sg:address":"4176 Pontiac Lake Rd",
    "sg:city":"Waterford",
    "sg:classifiers":[
        {
            "category":"Restaurant",
            "type":"Food & Drink"
        }
    ],
    "sg:phone":"+1 248 673 1347",
    "sg:postcode":"48328",
    "sg:province":"MI",
    "sg:tags":[
        "eating"
    ],
    "wof:name":"Honey Tree Restaurant",
    "wof:placetype":"venue"
},
  "geometry": {"coordinates":[-83.368334,42.654966],"type":"Point"}
}