{
  "type": "Feature",
  "properties": {
    "iso:country":"US",
    "sg:address":"108 Deens Ln",
    "sg:city":"Bay City",
    "sg:classifiers":[
        {
            "category":"Organizations",
            "subcategory":"Religious Organization",
            "type":"Services"
        }
    ],
    "sg:phone":"+1 989 686 5087",
    "sg:postcode":"48706",
    "sg:province":"MI",
    "wof:name":"Helen Janz Ministries",
    "wof:placetype":"venue"
},
  "geometry": {"coordinates":[-83.90370799999999,43.621994],"type":"Point"}
}