{
  "type": "Feature",
  "properties": {
    "iso:country":"US",
    "sg:address":"23053 Dequindre Rd",
    "sg:city":"Hazel Park",
    "sg:classifiers":[
        {
            "category":"Building & Trades",
            "subcategory":"Construction",
            "type":"Services"
        }
    ],
    "sg:phone":"+1 248 544 4051",
    "sg:postcode":"48030",
    "sg:province":"MI",
    "sg:tags":[
        "interior",
        "design"
    ],
    "wof:name":"Magic Blinds",
    "wof:placetype":"venue"
},
  "geometry": {"coordinates":[-83.084187,42.462785],"type":"Point"}
}