{
  "type": "Feature",
  "properties": {
    "iso:country":"US",
    "sg:address":"3385 Main St",
    "sg:city":"Ravenna",
    "sg:classifiers":[
        {
            "category":"Autos & Motor Vehicles",
            "subcategory":"Fuel & Gas Station",
            "type":"Retail Goods"
        }
    ],
    "sg:phone":"+1 231 853 2520",
    "sg:postcode":"49451",
    "sg:province":"MI",
    "sg:tags":[
        "oil"
    ],
    "wof:name":"Speedway",
    "wof:placetype":"venue"
},
  "geometry": {"coordinates":[-85.936689,43.191502],"type":"Point"}
}