{
  "type": "Feature",
  "properties": {
    "iso:country":"US",
    "sg:address":"2727 Kensington Dr",
    "sg:city":"Kalamazoo",
    "sg:classifiers":[
        {
            "category":"Professional",
            "type":"Services"
        }
    ],
    "sg:phone":"+1 269 552 4216",
    "sg:postcode":"49008",
    "sg:province":"MI",
    "sg:tags":[
        "establishment"
    ],
    "wof:name":"Point Foundation",
    "wof:placetype":"venue"
},
  "geometry": {"coordinates":[-85.62645500000001,42.260738],"type":"Point"}
}