{
  "type": "Feature",
  "properties": {
    "iso:country":"US",
    "sg:address":"117 W Broad St",
    "sg:city":"Linden",
    "sg:classifiers":[
        {
            "category":"Retail",
            "subcategory":"Auto Repair",
            "type":"Services"
        }
    ],
    "sg:phone":"+1 810 735 7350",
    "sg:postcode":"48451",
    "sg:province":"MI",
    "sg:tags":[
        "wrecker"
    ],
    "wof:name":"Linden City Towing",
    "wof:placetype":"venue"
},
  "geometry": {"coordinates":[-83.782524,42.814631],"type":"Point"}
}