{
  "type": "Feature",
  "properties": {
    "iso:country":"US",
    "sg:address":"1183 Parkway Dr",
    "sg:city":"Howell",
    "sg:classifiers":[
        {
            "category":"Building & Trades",
            "subcategory":"Plumbing",
            "type":"Services"
        }
    ],
    "sg:phone":"+1 517 552 1025",
    "sg:postcode":"48843",
    "sg:province":"MI",
    "sg:tags":[
        "heating",
        "contractor"
    ],
    "wof:name":"Four Seasons Cooling & Heating",
    "wof:placetype":"venue"
},
  "geometry": {"coordinates":[-83.859472,42.580875],"type":"Point"}
}