{
  "type": "Feature",
  "properties": {
    "iso:country":"US",
    "sg:address":"1441 Leonard St NE",
    "sg:city":"Grand Rapids",
    "sg:classifiers":[
        {
            "category":"Organizations",
            "subcategory":"Religious Organization",
            "type":"Services"
        }
    ],
    "sg:phone":"+1 616 454 1694",
    "sg:postcode":"49505",
    "sg:province":"MI",
    "sg:tags":[
        "church"
    ],
    "sg:website":"www.gracepentecostal.com",
    "wof:name":"Grace Pentecostal Church-God",
    "wof:placetype":"venue"
},
  "geometry": {"coordinates":[-85.632637,42.98451],"type":"Point"}
}