{
  "type": "Feature",
  "properties": {
    "iso:country":"US",
    "sg:address":"35275 Plymouth Rd",
    "sg:city":"Livonia",
    "sg:classifiers":[
        {
            "category":"Building & Trades",
            "subcategory":"Cleaning & Sanitation",
            "type":"Services"
        }
    ],
    "sg:phone":"+1 734 466 4000",
    "sg:postcode":"48150",
    "sg:province":"MI",
    "sg:tags":[
        "janitor",
        "maintenance"
    ],
    "wof:name":"Friske Building Maintenance Co",
    "wof:placetype":"venue"
},
  "geometry": {"coordinates":[-83.391186,42.36785],"type":"Point"}
}