{
  "type": "Feature",
  "properties": {
    "iso:country":"US",
    "sg:address":"117 Decatur Dr",
    "sg:city":"Cement City",
    "sg:classifiers":[
        {
            "category":"Social Services",
            "subcategory":"Child Care",
            "type":"Services"
        }
    ],
    "sg:phone":"+1 517 592 2427",
    "sg:postcode":"49233",
    "sg:province":"MI",
    "sg:tags":[
        "day"
    ],
    "wof:name":"Karen Hackett",
    "wof:placetype":"venue"
},
  "geometry": {"coordinates":[-84.313011,42.075972],"type":"Point"}
}