{
  "type": "Feature",
  "properties": {
    "iso:country":"US",
    "sg:address":"802 Jerome Ave",
    "sg:city":"Ypsilanti",
    "sg:classifiers":[
        {
            "category":"Building & Trades",
            "subcategory":"Construction",
            "type":"Services"
        }
    ],
    "sg:phone":"+1 734 480 2544",
    "sg:postcode":"48198",
    "sg:province":"MI",
    "sg:tags":[
        "hanging",
        "contractor"
    ],
    "wof:name":"Jayway Painting",
    "wof:placetype":"venue"
},
  "geometry": {"coordinates":[-83.578006,42.253763],"type":"Point"}
}