{
  "type": "Feature",
  "properties": {
    "iso:country":"US",
    "sg:address":"27318 Sparrow Ct",
    "sg:city":"New Baltimore",
    "sg:classifiers":[
        {
            "category":"Building & Trades",
            "subcategory":"Construction",
            "type":"Services"
        }
    ],
    "sg:phone":"+1 586 949 8021",
    "sg:postcode":"48051",
    "sg:province":"MI",
    "sg:tags":[
        "house"
    ],
    "wof:name":"Accurate One Construction Inc",
    "wof:placetype":"venue"
},
  "geometry": {"coordinates":[-82.83412300000001,42.663921],"type":"Point"}
}