{
  "type": "Feature",
  "properties": {
    "iso:country":"US",
    "sg:address":"902 S 7 Mile Rd",
    "sg:city":"Lake City",
    "sg:classifiers":[
        {
            "category":"Government",
            "subcategory":"Office",
            "type":"Public Place"
        }
    ],
    "sg:phone":"+1 231 328 4824",
    "sg:postcode":"49651",
    "sg:province":"MI",
    "sg:tags":[
        "village"
    ],
    "wof:name":"Inspection Control Co",
    "wof:placetype":"venue"
},
  "geometry": {"coordinates":[-85.07510600000001,44.324353],"type":"Point"}
}