{
  "type": "Feature",
  "properties": {
    "iso:country":"US",
    "sg:address":"16921 Harper Ave",
    "sg:city":"Detroit",
    "sg:classifiers":[
        {
            "category":"Bars & Pubs",
            "type":"Food & Drink"
        }
    ],
    "sg:phone":"+1 313 885 0109",
    "sg:postcode":"48224",
    "sg:province":"MI",
    "sg:tags":[
        "lounge",
        "cocktail"
    ],
    "wof:name":"First Place Lounge",
    "wof:placetype":"venue"
},
  "geometry": {"coordinates":[-82.93774999999999,42.415721],"type":"Point"}
}