{
  "type": "Feature",
  "properties": {
    "iso:country":"US",
    "sg:address":"9660 Kilmanagh Rd",
    "sg:city":"Sebewaing",
    "sg:classifiers":[
        {
            "category":"Farming",
            "subcategory":"Farm",
            "type":"Manufacturing & Wholesale Goods"
        }
    ],
    "sg:phone":"+1 989 883 9715",
    "sg:postcode":"48759",
    "sg:province":"MI",
    "sg:tags":[
        "crop",
        "general"
    ],
    "wof:name":"Darrin Lutz Farms Inc",
    "wof:placetype":"venue"
},
  "geometry": {"coordinates":[-83.36162,43.756087],"type":"Point"}
}