{
  "type": "Feature",
  "properties": {
    "iso:country":"US",
    "sg:address":"901 Garfield Rd S",
    "sg:city":"Traverse City",
    "sg:classifiers":[
        {
            "category":"Professional",
            "subcategory":"Advertising",
            "type":"Services"
        }
    ],
    "sg:phone":"+1 231 947 0241",
    "sg:postcode":"49686",
    "sg:province":"MI",
    "sg:website":"www.cablemichigan.com",
    "wof:name":"Charter Media",
    "wof:placetype":"venue"
},
  "geometry": {"coordinates":[-85.57049499999999,44.676824],"type":"Point"}
}