{
  "type": "Feature",
  "properties": {
    "iso:country":"US",
    "sg:address":"7701 Way Rd",
    "sg:city":"Honor",
    "sg:classifiers":[
        {
            "category":"Building & Trades",
            "subcategory":"Construction",
            "type":"Services"
        }
    ],
    "sg:phone":"+1 231 325 2348",
    "sg:postcode":"49640",
    "sg:province":"MI",
    "sg:tags":[
        "general",
        "contractor"
    ],
    "wof:name":"Benzie Builders & Maintenance",
    "wof:placetype":"venue"
},
  "geometry": {"coordinates":[-86.018653,44.742641],"type":"Point"}
}