{
  "type": "Feature",
  "properties": {
    "iso:country":"US",
    "sg:address":"2627 E Kimmel Rd",
    "sg:city":"Jackson",
    "sg:classifiers":[
        {
            "category":"Building & Trades",
            "subcategory":"Construction",
            "type":"Services"
        }
    ],
    "sg:phone":"+1 517 784 4359",
    "sg:postcode":"49201",
    "sg:province":"MI",
    "sg:tags":[
        "heavy"
    ],
    "wof:name":"Trac Tremching",
    "wof:placetype":"venue"
},
  "geometry": {"coordinates":[-84.388711,42.160372],"type":"Point"}
}