{
  "type": "Feature",
  "properties": {
    "iso:country":"US",
    "sg:address":"1001 N Irving St",
    "sg:city":"Greenville",
    "sg:classifiers":[
        {
            "category":"Social Services",
            "subcategory":"Child Care",
            "type":"Services"
        }
    ],
    "sg:phone":"+1 616 754 1478",
    "sg:postcode":"48838",
    "sg:province":"MI",
    "sg:tags":[
        "day"
    ],
    "wof:name":"Shirley Cotten",
    "wof:placetype":"venue"
},
  "geometry": {"coordinates":[-85.25800700000001,43.189633],"type":"Point"}
}