{
  "type": "Feature",
  "properties": {
    "iso:country":"US",
    "sg:address":"2700 Kinney Rd",
    "sg:city":"Riley",
    "sg:classifiers":[
        {
            "category":"Food & Beverages",
            "subcategory":"Groceries & Convenience Stores",
            "type":"Retail Goods"
        }
    ],
    "sg:phone":"+1 810 384 6919",
    "sg:postcode":"48041",
    "sg:province":"MI",
    "wof:name":"Sunrise Convenience Store Inc",
    "wof:placetype":"venue"
},
  "geometry": {"coordinates":[-82.764394,42.977439],"type":"Point"}
}