{
  "type": "Feature",
  "properties": {
    "iso:country":"US",
    "sg:address":"21285 Woodhill Dr",
    "sg:city":"Northville",
    "sg:classifiers":[
        {
            "category":"Professional",
            "subcategory":"Business Services",
            "type":"Services"
        }
    ],
    "sg:phone":"+1 248 476 4763",
    "sg:postcode":"48167",
    "sg:province":"MI",
    "wof:name":"Zlotucha Sales Representative",
    "wof:placetype":"venue"
},
  "geometry": {"coordinates":[-83.427142,42.444995],"type":"Point"}
}