{
  "type": "Feature",
  "properties": {
    "iso:country":"US",
    "sg:address":"2723 Kathleen Dr",
    "sg:city":"Brighton",
    "sg:classifiers":[
        {
            "category":"Retail",
            "subcategory":"Repair Shop",
            "type":"Services"
        }
    ],
    "sg:phone":"+1 810 220 8350",
    "sg:postcode":"48114",
    "sg:province":"MI",
    "wof:name":"Enforcement Gunsmithing",
    "wof:placetype":"venue"
},
  "geometry": {"coordinates":[-83.77570799999999,42.563639],"type":"Point"}
}