{
  "type": "Feature",
  "properties": {
    "iso:country":"US",
    "sg:address":"237 W Main St",
    "sg:city":"Morenci",
    "sg:classifiers":[
        {
            "category":"Shopping",
            "subcategory":"Florist",
            "type":"Retail Goods"
        }
    ],
    "sg:phone":"+1 517 458 6868",
    "sg:postcode":"49256",
    "sg:province":"MI",
    "wof:name":"Morenci Flower Shop",
    "wof:placetype":"venue"
},
  "geometry": {"coordinates":[-84.21819499999999,41.7195],"type":"Point"}
}