{
  "type": "Feature",
  "properties": {
    "iso:country":"US",
    "sg:address":"4508 Cramer Hwy",
    "sg:city":"Hudson",
    "sg:classifiers":[
        {
            "category":"Professional",
            "subcategory":"Business Services",
            "type":"Services"
        }
    ],
    "sg:phone":"+1 517 448 8307",
    "sg:postcode":"49247",
    "sg:province":"MI",
    "wof:name":"R & R Cargo",
    "wof:placetype":"venue"
},
  "geometry": {"coordinates":[-84.354974,41.845506],"type":"Point"}
}