{
  "type": "Feature",
  "properties": {
    "iso:country":"US",
    "sg:address":"28011 Rollcrest Rd",
    "sg:city":"Farmington Hills",
    "sg:classifiers":[
        {
            "category":"Retail",
            "subcategory":"Pet Boarding",
            "type":"Services"
        }
    ],
    "sg:phone":"+1 248 851 2191",
    "sg:postcode":"48334",
    "sg:province":"MI",
    "sg:tags":[
        "boarding/pet",
        "sitting"
    ],
    "wof:name":"Siesta Kennels",
    "wof:placetype":"venue"
},
  "geometry": {"coordinates":[-83.346603,42.499901],"type":"Point"}
}