{
  "type": "Feature",
  "properties": {
    "iso:country":"US",
    "sg:address":"5658 Division Ave S",
    "sg:city":"Kentwood",
    "sg:classifiers":[
        {
            "category":"Food & Beverages",
            "subcategory":"Groceries & Convenience Stores",
            "type":"Retail Goods"
        }
    ],
    "sg:phone":"+1 616 530 9519",
    "sg:postcode":"49548",
    "sg:province":"MI",
    "wof:name":"YNK",
    "wof:placetype":"venue"
},
  "geometry": {"coordinates":[-85.663838,42.860533],"type":"Point"}
}