{
  "type": "Feature",
  "properties": {
    "iso:country":"US",
    "sg:address":"3360 E Clarice Ave",
    "sg:city":"Highland",
    "sg:classifiers":[
        {
            "category":"Professional",
            "subcategory":"Business Services",
            "type":"Services"
        }
    ],
    "sg:phone":"+1 248 889 0397",
    "sg:postcode":"48356",
    "sg:province":"MI",
    "sg:tags":[
        "interior",
        "consultant",
        "design",
        "decorator"
    ],
    "wof:name":"Szent Gyorgyi Designs LTD",
    "wof:placetype":"venue"
},
  "geometry": {"coordinates":[-83.57059099999999,42.671175],"type":"Point"}
}