{
  "type": "Feature",
  "properties": {
    "iso:country":"US",
    "sg:address":"4751 Walnut Ridge St",
    "sg:city":"Battle Creek",
    "sg:classifiers":[
        {
            "category":"Building & Trades",
            "subcategory":"Construction",
            "type":"Services"
        }
    ],
    "sg:phone":"+1 269 721 8760",
    "sg:postcode":"49017",
    "sg:province":"MI",
    "sg:tags":[
        "house"
    ],
    "wof:name":"New Dimensions Bldg & Rmdlg",
    "wof:placetype":"venue"
},
  "geometry": {"coordinates":[-85.28820399999999,42.449811],"type":"Point"}
}