{
  "type": "Feature",
  "properties": {
    "iso:country":"US",
    "sg:address":"5685 Arden Ave",
    "sg:city":"Warren",
    "sg:classifiers":[
        {
            "category":"Professional",
            "subcategory":"Accounting & Tax Preparation",
            "type":"Services"
        }
    ],
    "sg:phone":"+1 586 365 2327",
    "sg:postcode":"48092",
    "sg:province":"MI",
    "sg:tags":[
        "accountant"
    ],
    "wof:name":"Kelley Rochelle J CPA PC",
    "wof:placetype":"venue"
},
  "geometry": {"coordinates":[-83.04940000000001,42.531399],"type":"Point"}
}