{
  "type": "Feature",
  "properties": {
    "iso:country":"US",
    "sg:address":"206 S Broadway St",
    "sg:city":"Hastings",
    "sg:classifiers":[
        {
            "category":"Professional",
            "subcategory":"Lawyer & Legal Services",
            "type":"Services"
        }
    ],
    "sg:phone":"+1 269 945 9585",
    "sg:postcode":"49058",
    "sg:province":"MI",
    "wof:name":"David H Tripp PC",
    "wof:placetype":"venue"
},
  "geometry": {"coordinates":[-85.29063600000001,42.647728],"type":"Point"}
}