{
  "type": "Feature",
  "properties": {
    "iso:country":"US",
    "sg:address":"114 S Cochran Ave",
    "sg:city":"Charlotte",
    "sg:classifiers":[
        {
            "category":"Shopping",
            "type":"Retail Goods"
        }
    ],
    "sg:phone":"+1 517 543 6677",
    "sg:postcode":"48813",
    "sg:province":"MI",
    "sg:tags":[
        "gallery",
        "merchandise"
    ],
    "sg:website":"www.mapleleafgallery.com",
    "wof:name":"Maple Leaf Gallery",
    "wof:placetype":"venue"
},
  "geometry": {"coordinates":[-84.83595699999999,42.563737],"type":"Point"}
}