{
  "type": "Feature",
  "properties": {
    "iso:country":"US",
    "sg:address":"7320 S Huron River Dr",
    "sg:city":"South Rockwood",
    "sg:classifiers":[
        {
            "category":"Freight",
            "type":"Transportation"
        }
    ],
    "sg:phone":"+1 734 379 5829",
    "sg:postcode":"48179",
    "sg:province":"MI",
    "wof:name":"B & D Transport Inc",
    "wof:placetype":"venue"
},
  "geometry": {"coordinates":[-83.238972,42.057301],"type":"Point"}
}