{
  "type": "Feature",
  "properties": {
    "iso:country":"US",
    "sg:address":"900 Cook Rd",
    "sg:city":"Grosse Pointe",
    "sg:classifiers":[
        {
            "category":"Social Services",
            "subcategory":"Adult Care",
            "type":"Services"
        }
    ],
    "sg:phone":"+1 313 886 0800",
    "sg:postcode":"48236",
    "sg:province":"MI",
    "sg:tags":[
        "residential"
    ],
    "wof:name":"Childrens Home of Detroit",
    "wof:placetype":"venue"
},
  "geometry": {"coordinates":[-82.895544,42.42254],"type":"Point"}
}