{
  "type": "Feature",
  "properties": {
    "iso:country":"US",
    "sg:address":"743 S Centerville Rd",
    "sg:city":"Sturgis",
    "sg:classifiers":[
        {
            "category":"Personal",
            "subcategory":"Beauty Salon",
            "type":"Services"
        }
    ],
    "sg:phone":"+1 269 651 2295",
    "sg:postcode":"49091",
    "sg:province":"MI",
    "sg:tags":[
        "shop"
    ],
    "wof:name":"Modern Images",
    "wof:placetype":"venue"
},
  "geometry": {"coordinates":[-85.42837,41.790086],"type":"Point"}
}