{
  "type": "Feature",
  "properties": {
    "iso:country":"US",
    "sg:address":"1556 E Parmeter Rd",
    "sg:city":"Ionia",
    "sg:classifiers":[
        {
            "category":"Farming",
            "subcategory":"Farm",
            "type":"Manufacturing & Wholesale Goods"
        }
    ],
    "sg:phone":"+1 616 527 3358",
    "sg:postcode":"48846",
    "sg:province":"MI",
    "sg:tags":[
        "crop",
        "general"
    ],
    "wof:name":"Ross Cox",
    "wof:placetype":"venue"
},
  "geometry": {"coordinates":[-85.044273,43.023621],"type":"Point"}
}