{
  "type": "Feature",
  "properties": {
    "iso:country":"US",
    "sg:address":"5279 Flushing Rd",
    "sg:city":"Flushing",
    "sg:classifiers":[
        {
            "category":"Building & Trades",
            "subcategory":"Plumbing",
            "type":"Services"
        }
    ],
    "sg:phone":"+1 810 230 8070",
    "sg:postcode":"48433",
    "sg:province":"MI",
    "sg:tags":[
        "plumbing",
        "contractor"
    ],
    "wof:name":"Dennis Cook Plumbing Inc",
    "wof:placetype":"venue"
},
  "geometry": {"coordinates":[-83.785203,43.040171],"type":"Point"}
}