{
  "type": "Feature",
  "properties": {
    "iso:country":"US",
    "sg:address":"27177 Lahser Rd Ste 205",
    "sg:city":"Southfield",
    "sg:classifiers":[
        {
            "category":"Health Services",
            "subcategory":"Doctor",
            "type":"Services"
        }
    ],
    "sg:phone":"+1 248 353 9817",
    "sg:postcode":"48034",
    "sg:province":"MI",
    "wof:name":"Desai Chandrankant MD",
    "wof:placetype":"venue"
},
  "geometry": {"coordinates":[-83.26149700000001,42.4884],"type":"Point"}
}