{
  "type": "Feature",
  "properties": {
    "iso:country":"US",
    "sg:address":"4171 E 124th St",
    "sg:city":"Grant",
    "sg:classifiers":[
        {
            "category":"Restaurant",
            "type":"Food & Drink"
        }
    ],
    "sg:phone":"+1 231 834 9563",
    "sg:postcode":"49327",
    "sg:province":"MI",
    "sg:tags":[
        "eating"
    ],
    "wof:name":"City Limits Restaurant",
    "wof:placetype":"venue"
},
  "geometry": {"coordinates":[-85.69539,43.329951],"type":"Point"}
}