{
  "type": "Feature",
  "properties": {
    "iso:country":"US",
    "sg:address":"32621 Northwestern Hwy",
    "sg:city":"Farmington",
    "sg:classifiers":[
        {
            "category":"Restaurant",
            "type":"Food & Drink"
        }
    ],
    "sg:menulink":"http://www.allmenus.com/mi/farmington-hills/48393-noodles--company/menu/",
    "sg:phone":"+1 248 626 8886",
    "sg:postcode":"48334",
    "sg:province":"MI",
    "sg:tags":[
        "noodle",
        "bar",
        "salad",
        "chinese",
        "japanese",
        "soup",
        "american",
        "asian",
        "thai",
        "italian"
    ],
    "wof:name":"Noodles & Company",
    "wof:placetype":"venue"
},
  "geometry": {"coordinates":[-83.352515,42.525678],"type":"Point"}
}