{
  "type": "Feature",
  "properties": {
    "iso:country":"US",
    "sg:address":"5387 Roehrs Rd",
    "sg:city":"Beaverton",
    "sg:classifiers":[
        {
            "category":"Manufacturing",
            "subcategory":"Rubber & Plastics",
            "type":"Manufacturing & Wholesale Goods"
        }
    ],
    "sg:phone":"+1 989 435 4373",
    "sg:postcode":"48612",
    "sg:province":"MI",
    "sg:tags":[
        "forming"
    ],
    "sg:website":"www.thepetcasketshop.com",
    "wof:name":"Kinne Plastics Inc",
    "wof:placetype":"venue"
},
  "geometry": {"coordinates":[-84.505815,43.832305],"type":"Point"}
}