{
  "type": "Feature",
  "properties": {
    "iso:country":"US",
    "sg:address":"802 W Chisholm St",
    "sg:city":"Alpena",
    "sg:classifiers":[
        {
            "category":"Home & Garden",
            "subcategory":"Hardware",
            "type":"Retail Goods"
        }
    ],
    "sg:phone":"+1 989 354 8771",
    "sg:postcode":"49707",
    "sg:province":"MI",
    "wof:name":"Mike's Hardware",
    "wof:placetype":"venue"
},
  "geometry": {"coordinates":[-83.442674,45.069932],"type":"Point"}
}