{
  "type": "Feature",
  "properties": {
    "iso:country":"US",
    "sg:address":"51830 Grand River Ave",
    "sg:city":"Wixom",
    "sg:classifiers":[
        {
            "category":"Freight",
            "type":"Transportation"
        }
    ],
    "sg:phone":"+1 248 349 3038",
    "sg:postcode":"48393",
    "sg:province":"MI",
    "sg:tags":[
        "commercial",
        "storage"
    ],
    "wof:name":"Old Grand River Mini Storage",
    "wof:placetype":"venue"
},
  "geometry": {"coordinates":[-83.55694200000001,42.49889],"type":"Point"}
}