{
  "type": "Feature",
  "properties": {
    "iso:country":"US",
    "sg:address":"883 W Isabella Rd",
    "sg:city":"Midland",
    "sg:classifiers":[
        {
            "category":"Local Transit",
            "type":"Transportation"
        }
    ],
    "sg:phone":"+1 989 837 9540",
    "sg:postcode":"48640",
    "sg:province":"MI",
    "sg:tags":[
        "bus",
        "line"
    ],
    "sg:website":"www.etc-1.com",
    "wof:name":"County Connection LLC",
    "wof:placetype":"venue"
},
  "geometry": {"coordinates":[-84.403526,43.610861],"type":"Point"}
}