{
  "type": "Feature",
  "properties": {
    "iso:country":"US",
    "sg:address":"218 N Park St",
    "sg:city":"Owosso",
    "sg:classifiers":[
        {
            "category":"Banks & Credit Unions",
            "subcategory":"Investment Brokerage",
            "type":"Services"
        }
    ],
    "sg:phone":"+1 989 725 1116",
    "sg:postcode":"48867",
    "sg:province":"MI",
    "sg:tags":[
        "management"
    ],
    "wof:name":"Lifegoals Financial Group",
    "wof:placetype":"venue"
},
  "geometry": {"coordinates":[-84.16924400000001,42.999284],"type":"Point"}
}