{
  "type": "Feature",
  "properties": {
    "iso:country":"US",
    "sg:address":"4444 E Grand River Ave",
    "sg:city":"Howell",
    "sg:classifiers":[
        {
            "category":"Shopping",
            "subcategory":"Bicycles & Sporting Goods",
            "type":"Retail Goods"
        }
    ],
    "sg:phone":"+1 517 552 9830",
    "sg:postcode":"48843",
    "sg:province":"MI",
    "sg:tags":[
        "equipment",
        "golf",
        "supply"
    ],
    "wof:name":"Deaton's Golf Ctr",
    "wof:placetype":"venue"
},
  "geometry": {"coordinates":[-84.00362,42.637673],"type":"Point"}
}