{
  "type": "Feature",
  "properties": {
    "iso:country":"US",
    "sg:address":"701 N Washington St",
    "sg:city":"Owosso",
    "sg:classifiers":[
        {
            "category":"Food & Beverages",
            "subcategory":"Liquor & Beverages",
            "type":"Retail Goods"
        }
    ],
    "sg:phone":"+1 989 725 6767",
    "sg:postcode":"48867",
    "sg:province":"MI",
    "sg:tags":[
        "beer",
        "ale"
    ],
    "wof:name":"Paulee K's",
    "wof:placetype":"venue"
},
  "geometry": {"coordinates":[-84.17054,43.005776],"type":"Point"}
}