{
  "type": "Feature",
  "properties": {
    "iso:country":"US",
    "sg:address":"2102 S Dort Hwy",
    "sg:city":"Flint",
    "sg:classifiers":[
        {
            "category":"Food & Beverages",
            "subcategory":"Liquor & Beverages",
            "type":"Retail Goods"
        }
    ],
    "sg:phone":"+1 810 239 4445",
    "sg:postcode":"48507",
    "sg:province":"MI",
    "sg:tags":[
        "beer",
        "ale"
    ],
    "wof:name":"E-Z Stop Market",
    "wof:placetype":"venue"
},
  "geometry": {"coordinates":[-83.65401,43.001881],"type":"Point"}
}