{
  "type": "Feature",
  "properties": {
    "iso:country":"US",
    "sg:address":"2509 S Wellsville Hwy",
    "sg:city":"Blissfield",
    "sg:classifiers":[
        {
            "category":"Organizations",
            "subcategory":"Religious Organization",
            "type":"Services"
        }
    ],
    "sg:phone":"+1 517 486 4777",
    "sg:postcode":"49228",
    "sg:province":"MI",
    "wof:name":"Wellsville Untd Methdst Church",
    "wof:placetype":"venue"
},
  "geometry": {"coordinates":[-83.885452,41.887042],"type":"Point"}
}