{
  "type": "Feature",
  "properties": {
    "iso:country":"US",
    "sg:address":"46280 Van Dyke Ave",
    "sg:city":"Shelby Township",
    "sg:classifiers":[
        {
            "category":"Home & Garden",
            "subcategory":"Carpets & Floor Coverings",
            "type":"Retail Goods"
        }
    ],
    "sg:phone":"+1 586 726 7300",
    "sg:postcode":"48317",
    "sg:province":"MI",
    "sg:tags":[
        "carpeting"
    ],
    "sg:website":"www.carpetcenterfloors.com",
    "wof:name":"Carpet Center & Floors",
    "wof:placetype":"venue"
},
  "geometry": {"coordinates":[-83.0326,42.635601],"type":"Point"}
}