{
  "type": "Feature",
  "properties": {
    "iso:country":"US",
    "sg:address":"488 Lakeland St",
    "sg:city":"Grosse Pointe",
    "sg:classifiers":[
        {
            "category":"Professional",
            "subcategory":"Business Services",
            "type":"Services"
        }
    ],
    "sg:phone":"+1 313 885 7386",
    "sg:postcode":"48230",
    "sg:province":"MI",
    "wof:name":"Griffin Interiors",
    "wof:placetype":"venue"
},
  "geometry": {"coordinates":[-82.911646,42.389758],"type":"Point"}
}