{
  "type": "Feature",
  "properties": {
    "iso:country":"US",
    "sg:address":"11938 Big Lake Rd",
    "sg:city":"Davisburg",
    "sg:classifiers":[
        {
            "category":"Building & Trades",
            "subcategory":"Construction",
            "type":"Services"
        }
    ],
    "sg:phone":"+1 248 625 9118",
    "sg:postcode":"48350",
    "sg:province":"MI",
    "sg:tags":[
        "sun",
        "solarium",
        "rooms"
    ],
    "wof:name":"Sun Structures",
    "wof:placetype":"venue"
},
  "geometry": {"coordinates":[-83.533198,42.72185],"type":"Point"}
}