{
  "type": "Feature",
  "properties": {
    "iso:country":"US",
    "sg:address":"318 Vista Ter",
    "sg:city":"Muskegon",
    "sg:classifiers":[
        {
            "category":"Professional",
            "subcategory":"Accounting & Tax Preparation",
            "type":"Services"
        }
    ],
    "sg:phone":"+1 231 788 3980",
    "sg:postcode":"49442",
    "sg:province":"MI",
    "wof:name":"Balancing Act",
    "wof:placetype":"venue"
},
  "geometry": {"coordinates":[-86.11342500000001,43.257035],"type":"Point"}
}