{
  "type": "Feature",
  "properties": {
    "iso:country":"US",
    "sg:address":"40500 Grand River Ave Ste G",
    "sg:city":"Novi",
    "sg:classifiers":[
        {
            "category":"Arts & Performance",
            "subcategory":"Arts Center",
            "type":"Entertainment"
        }
    ],
    "sg:phone":"+1 248 473 1160",
    "sg:postcode":"48375",
    "sg:province":"MI",
    "sg:tags":[
        "performing"
    ],
    "sg:website":"www.sherylsdance.com",
    "wof:name":"Sheryl's School of Dance",
    "wof:placetype":"venue"
},
  "geometry": {"coordinates":[-83.44650300000001,42.4743],"type":"Point"}
}