{
  "type": "Feature",
  "properties": {
    "iso:country":"US",
    "sg:address":"547 E Washington St",
    "sg:city":"Dimondale",
    "sg:classifiers":[
        {
            "category":"Building & Trades",
            "subcategory":"Plumbing",
            "type":"Services"
        }
    ],
    "sg:phone":"+1 517 646 6269",
    "sg:postcode":"48821",
    "sg:province":"MI",
    "sg:tags":[
        "product",
        "management",
        "energy",
        "system"
    ],
    "wof:name":"Great Lakes Renewable Energy",
    "wof:placetype":"venue"
},
  "geometry": {"coordinates":[-84.643215,42.64251],"type":"Point"}
}