{
  "type": "Feature",
  "properties": {
    "iso:country":"US",
    "sg:address":"206 Tanglewood Dr",
    "sg:city":"Rochester Hills",
    "sg:classifiers":[
        {
            "category":"Shopping",
            "subcategory":"Computers & Home Electronics",
            "type":"Retail Goods"
        }
    ],
    "sg:phone":"+1 248 650 4973",
    "sg:postcode":"48309",
    "sg:province":"MI",
    "sg:tags":[
        "equipment",
        "dealer"
    ],
    "wof:name":"Amdahl Corp",
    "wof:placetype":"venue"
},
  "geometry": {"coordinates":[-83.167079,42.678585],"type":"Point"}
}