{
  "type": "Feature",
  "properties": {
    "iso:country":"US",
    "sg:address":"12550 Pardee Rd",
    "sg:city":"Taylor",
    "sg:classifiers":[
        {
            "category":"Place Of Worship",
            "subcategory":"Church",
            "type":"Public Place"
        },
        {
            "category":"Place Of Worship",
            "type":"Public Place"
        },
        {
            "category":"Organizations",
            "subcategory":"Religious Organization",
            "type":"Services"
        }
    ],
    "sg:phone":"+1 734 287 8630",
    "sg:postcode":"48180",
    "sg:province":"MI",
    "sg:tags":[
        "god",
        "god-cleveland",
        "churches-church",
        "churches-pentecostal"
    ],
    "wof:name":"Heritage Park Church Of God",
    "wof:placetype":"venue"
},
  "geometry": {"coordinates":[-83.254023,42.215874],"type":"Point"}
}