{
  "type": "Feature",
  "properties": {
    "iso:country":"US",
    "sg:address":"919 W Washington St",
    "sg:city":"Greenville",
    "sg:classifiers":[
        {
            "category":"Shopping",
            "type":"Retail Goods"
        }
    ],
    "sg:phone":"+1 616 754 3497",
    "sg:postcode":"48838",
    "sg:province":"MI",
    "sg:tags":[
        "equipment",
        "care",
        "health",
        "home"
    ],
    "wof:name":"Carelinc Medical",
    "wof:placetype":"venue"
},
  "geometry": {"coordinates":[-85.268761,43.177316],"type":"Point"}
}