{
  "type": "Feature",
  "properties": {
    "iso:country":"US",
    "sg:address":"13653 Mason Dr",
    "sg:city":"Grant",
    "sg:classifiers":[
        {
            "category":"Building & Trades",
            "subcategory":"Construction",
            "type":"Services"
        }
    ],
    "sg:phone":"+1 231 834 5750",
    "sg:postcode":"49327",
    "sg:province":"MI",
    "sg:tags":[
        "concrete",
        "contractor"
    ],
    "wof:name":"Bill Mc Kinley Masonry",
    "wof:placetype":"venue"
},
  "geometry": {"coordinates":[-85.810637,43.306538],"type":"Point"}
}