{
  "type": "Feature",
  "properties": {
    "iso:country":"US",
    "sg:address":"48403 Heartwood Dr",
    "sg:city":"Utica",
    "sg:classifiers":[
        {
            "category":"Building & Trades",
            "subcategory":"Construction",
            "type":"Services"
        }
    ],
    "sg:phone":"+1 586 323 9719",
    "sg:postcode":"48315",
    "sg:province":"MI",
    "sg:tags":[
        "hanging",
        "contractor"
    ],
    "wof:name":"Painting Authority Inc",
    "wof:placetype":"venue"
},
  "geometry": {"coordinates":[-83.011852,42.65103],"type":"Point"}
}