{
  "type": "Feature",
  "properties": {
    "iso:country":"US",
    "sg:address":"1010 US Hwy 41",
    "sg:city":"Trenary",
    "sg:classifiers":[
        {
            "category":"Restaurant",
            "type":"Food & Drink"
        }
    ],
    "sg:phone":"+1 906 446 3344",
    "sg:postcode":"49891",
    "sg:province":"MI",
    "wof:name":"Hub Restaurant",
    "wof:placetype":"venue"
},
  "geometry": {"coordinates":[-86.97879399999999,46.184912],"type":"Point"}
}