{
  "type": "Feature",
  "properties": {
    "iso:country":"US",
    "sg:address":"115 Ames St",
    "sg:city":"Elk Rapids",
    "sg:classifiers":[
        {
            "category":"Restaurant",
            "type":"Food & Drink"
        }
    ],
    "sg:phone":"+1 231 264 5461",
    "sg:postcode":"49629",
    "sg:province":"MI",
    "sg:tags":[
        "parlor",
        "ice",
        "cream"
    ],
    "wof:name":"Frost Food Factory",
    "wof:placetype":"venue"
},
  "geometry": {"coordinates":[-85.40903900000001,44.900833],"type":"Point"}
}