{
  "type": "Feature",
  "properties": {
    "iso:country":"US",
    "sg:address":"35572 Veronica St",
    "sg:city":"Livonia",
    "sg:classifiers":[
        {
            "category":"Professional",
            "subcategory":"Engineering",
            "type":"Services"
        }
    ],
    "sg:phone":"+1 734 402 2340",
    "sg:postcode":"48150",
    "sg:province":"MI",
    "wof:name":"Sky-Tek LLC - Fixture Shop",
    "wof:placetype":"venue"
},
  "geometry": {"coordinates":[-83.40125500000001,42.376592],"type":"Point"}
}