{
  "type": "Feature",
  "properties": {
    "iso:country":"US",
    "sg:address":"345 S Canton Center Rd",
    "sg:city":"Canton",
    "sg:classifiers":[
        {
            "category":"Retail",
            "subcategory":"Auto Repair",
            "type":"Services"
        }
    ],
    "sg:phone":"+1 734 844 2100",
    "sg:postcode":"48188",
    "sg:province":"MI",
    "sg:tags":[
        "general"
    ],
    "wof:name":"DNB Motor City",
    "wof:placetype":"venue"
},
  "geometry": {"coordinates":[-83.487199,42.307075],"type":"Point"}
}