{
  "type": "Feature",
  "properties": {
    "iso:country":"US",
    "sg:address":"200 S Henry St",
    "sg:city":"Bay City",
    "sg:classifiers":[
        {
            "category":"Retail",
            "subcategory":"Auto Repair",
            "type":"Services"
        }
    ],
    "sg:phone":"+1 989 892 1601",
    "sg:postcode":"48706",
    "sg:province":"MI",
    "sg:tags":[
        "automotive",
        "welding"
    ],
    "wof:name":"A & S Radiator",
    "wof:placetype":"venue"
},
  "geometry": {"coordinates":[-83.900221,43.599958],"type":"Point"}
}