{
  "type": "Feature",
  "properties": {
    "iso:country":"US",
    "sg:address":"3800 Division Ave S",
    "sg:city":"Wyoming",
    "sg:classifiers":[
        {
            "category":"Home & Garden",
            "subcategory":"Furniture",
            "type":"Retail Goods"
        }
    ],
    "sg:phone":"+1 616 243 4342",
    "sg:postcode":"49548",
    "sg:province":"MI",
    "sg:tags":[
        "mattress"
    ],
    "sg:website":"www.jonathanstevens.com",
    "wof:name":"Jonathan Stevens Mattress Co",
    "wof:placetype":"venue"
},
  "geometry": {"coordinates":[-85.665138,42.894462],"type":"Point"}
}