{
  "type": "Feature",
  "properties": {
    "iso:country":"US",
    "sg:address":"2211 Association Dr",
    "sg:city":"Okemos",
    "sg:classifiers":[
        {
            "category":"Health Services",
            "subcategory":"Doctor",
            "type":"Services"
        }
    ],
    "sg:phone":"+1 517 381 8900",
    "sg:postcode":"48864",
    "sg:province":"MI",
    "sg:tags":[
        "physician",
        "surgeon"
    ],
    "sg:website":"www.trilliumeye.com",
    "wof:name":"Trillium Laser Cosmetic Srgry",
    "wof:placetype":"venue"
},
  "geometry": {"coordinates":[-84.429925,42.685799],"type":"Point"}
}