{
  "type": "Feature",
  "properties": {
    "iso:country":"US",
    "sg:address":"8785 Portage Industrial Dr",
    "sg:city":"Portage",
    "sg:classifiers":[
        {
            "category":"Manufacturing",
            "subcategory":"Printing",
            "type":"Manufacturing & Wholesale Goods"
        }
    ],
    "sg:phone":"+1 269 327 7727",
    "sg:postcode":"49024",
    "sg:province":"MI",
    "sg:tags":[
        "printer"
    ],
    "sg:website":"www.businesscardsplus.com",
    "wof:name":"Business Cards Plus",
    "wof:placetype":"venue"
},
  "geometry": {"coordinates":[-85.59858,42.191111],"type":"Point"}
}