{
  "type": "Feature",
  "properties": {
    "iso:country":"US",
    "sg:address":"805 S Van Dyke Rd",
    "sg:city":"Bad Axe",
    "sg:classifiers":[
        {
            "category":"Home & Garden",
            "subcategory":"Building Materials",
            "type":"Retail Goods"
        }
    ],
    "sg:phone":"+1 989 269 9374",
    "sg:postcode":"48413",
    "sg:province":"MI",
    "sg:tags":[
        "glass",
        "window",
        "plate"
    ],
    "wof:name":"Northeastern Auto",
    "wof:placetype":"venue"
},
  "geometry": {"coordinates":[-83.01730499999999,43.801716],"type":"Point"}
}