{
  "type": "Feature",
  "properties": {
    "iso:country":"US",
    "sg:address":"103 S Bridge St",
    "sg:city":"Dewitt",
    "sg:classifiers":[
        {
            "category":"Professional",
            "subcategory":"Advertising",
            "type":"Services"
        }
    ],
    "sg:phone":"+1 517 669 8200",
    "sg:postcode":"48820",
    "sg:province":"MI",
    "sg:tags":[
        "distribution"
    ],
    "wof:name":"Touchstone Distributing Inc",
    "wof:placetype":"venue"
},
  "geometry": {"coordinates":[-84.569034,42.841344],"type":"Point"}
}