{
  "type": "Feature",
  "properties": {
    "iso:country":"US",
    "sg:address":"5986 Standish Rd",
    "sg:city":"Bentley",
    "sg:classifiers":[
        {
            "category":"Shopping",
            "subcategory":"Hobbies, Toys, & Games",
            "type":"Retail Goods"
        }
    ],
    "sg:phone":"+1 989 879 2664",
    "sg:postcode":"48613",
    "sg:province":"MI",
    "wof:name":"Konkrete Five",
    "wof:placetype":"venue"
},
  "geometry": {"coordinates":[-84.13414899999999,43.907746],"type":"Point"}
}