{
  "type": "Feature",
  "properties": {
    "iso:country":"US",
    "sg:address":"24492 Indoplex Cir",
    "sg:city":"Farmington",
    "sg:classifiers":[
        {
            "category":"Wholesale",
            "subcategory":"Construction Materials",
            "type":"Manufacturing & Wholesale Goods"
        }
    ],
    "sg:phone":"+1 248 478 9000",
    "sg:postcode":"48335",
    "sg:province":"MI",
    "wof:name":"Mont Granite Inc",
    "wof:placetype":"venue"
},
  "geometry": {"coordinates":[-83.391581,42.470911],"type":"Point"}
}