{
  "type": "Feature",
  "properties": {
    "iso:country":"US",
    "sg:address":"100 W South St",
    "sg:city":"Decatur",
    "sg:classifiers":[
        {
            "category":"Building & Trades",
            "subcategory":"Landscaping Services",
            "type":"Services"
        }
    ],
    "sg:phone":"+1 269 423 7614",
    "sg:postcode":"49045",
    "sg:province":"MI",
    "sg:tags":[
        "tree"
    ],
    "wof:name":"J C & Sons Inc",
    "wof:placetype":"venue"
},
  "geometry": {"coordinates":[-85.970141,42.103984],"type":"Point"}
}