{
  "type": "Feature",
  "properties": {
    "iso:country":"US",
    "sg:address":"2158 Avon Industrial Dr",
    "sg:city":"Rochester Hills",
    "sg:classifiers":[
        {
            "category":"Manufacturing",
            "subcategory":"Retail Goods",
            "type":"Manufacturing & Wholesale Goods"
        }
    ],
    "sg:phone":"+1 248 377 9015",
    "sg:postcode":"48309",
    "sg:province":"MI",
    "sg:tags":[
        "assembly",
        "fabricating"
    ],
    "wof:name":"Advanced Assembly Solutions",
    "wof:placetype":"venue"
},
  "geometry": {"coordinates":[-83.17829399999999,42.645882],"type":"Point"}
}