{
  "type": "Feature",
  "properties": {
    "iso:country":"US",
    "sg:address":"2280 W M 21",
    "sg:city":"Owosso",
    "sg:classifiers":[
        {
            "category":"Restaurant",
            "type":"Food & Drink"
        }
    ],
    "sg:phone":"+1 989 723 6741",
    "sg:postcode":"48867",
    "sg:province":"MI",
    "wof:name":"Eddie O'Flynns Inc",
    "wof:placetype":"venue"
},
  "geometry": {"coordinates":[-84.21051,42.997681],"type":"Point"}
}