{
  "type": "Feature",
  "properties": {
    "iso:country":"US",
    "sg:address":"314 N Lincoln Ave",
    "sg:city":"Lakeview",
    "sg:classifiers":[
        {
            "category":"Autos & Motor Vehicles",
            "subcategory":"Motorcycle Sales",
            "type":"Retail Goods"
        }
    ],
    "sg:phone":"+1 989 352 7091",
    "sg:postcode":"48850",
    "sg:province":"MI",
    "sg:tags":[
        "scooter"
    ],
    "wof:name":"Collins Custom Cycles",
    "wof:placetype":"venue"
},
  "geometry": {"coordinates":[-85.28229399999999,43.44694],"type":"Point"}
}