{
  "type": "Feature",
  "properties": {
    "iso:country":"US",
    "sg:address":"5407 Gratiot Ave",
    "sg:city":"St Clair",
    "sg:classifiers":[
        {
            "category":"Wholesale",
            "subcategory":"Beer",
            "type":"Manufacturing & Wholesale Goods"
        }
    ],
    "sg:phone":"+1 810 364 6011",
    "sg:postcode":"48079",
    "sg:province":"MI",
    "sg:tags":[
        "ale"
    ],
    "wof:name":"Lakeside Beverage Co",
    "wof:placetype":"venue"
},
  "geometry": {"coordinates":[-82.533857,42.894337],"type":"Point"}
}