{
  "type": "Feature",
  "properties": {
    "iso:country":"US",
    "sg:address":"18854 Michigan St",
    "sg:city":"Copemish",
    "sg:classifiers":[
        {
            "category":"Building & Trades",
            "subcategory":"Cleaning & Sanitation",
            "type":"Services"
        }
    ],
    "sg:phone":"+1 231 378 2115",
    "sg:postcode":"49625",
    "sg:province":"MI",
    "sg:tags":[
        "maintenance"
    ],
    "wof:name":"Mc Carthy Floor Maintenance",
    "wof:placetype":"venue"
},
  "geometry": {"coordinates":[-85.92166400000001,44.47912],"type":"Point"}
}