{
  "type": "Feature",
  "properties": {
    "iso:country":"US",
    "sg:address":"3218 Stonegate Dr",
    "sg:city":"Flint",
    "sg:classifiers":[
        {
            "category":"Home & Garden",
            "subcategory":"Carpets & Floor Coverings",
            "type":"Retail Goods"
        }
    ],
    "sg:phone":"+1 810 715 2662",
    "sg:postcode":"48507",
    "sg:province":"MI",
    "sg:tags":[
        "dealer",
        "rug"
    ],
    "wof:name":"Carpet & More",
    "wof:placetype":"venue"
},
  "geometry": {"coordinates":[-83.64494999999999,42.993737],"type":"Point"}
}