{
  "type": "Feature",
  "properties": {
    "iso:country":"US",
    "sg:address":"1415 N Dort Hwy",
    "sg:city":"Flint",
    "sg:classifiers":[
        {
            "category":"Building & Trades",
            "subcategory":"Construction",
            "type":"Services"
        }
    ],
    "sg:phone":"+1 810 767 8141",
    "sg:postcode":"48506",
    "sg:province":"MI",
    "sg:tags":[
        "commercial",
        "contractor"
    ],
    "sg:website":"www.willhhallandson.com",
    "wof:name":"Will H Hall & Son Inc",
    "wof:placetype":"venue"
},
  "geometry": {"coordinates":[-83.65540300000001,43.030102],"type":"Point"}
}