{
  "type": "Feature",
  "properties": {
    "iso:country":"US",
    "sg:address":"9810 N Straits Hwy",
    "sg:city":"Cheboygan",
    "sg:classifiers":[
        {
            "category":"Building & Trades",
            "subcategory":"Construction",
            "type":"Services"
        }
    ],
    "sg:phone":"+1 231 627 3191",
    "sg:postcode":"49721",
    "sg:province":"MI",
    "sg:tags":[
        "dry wall",
        "contractor"
    ],
    "wof:name":"L & L Interior Construction",
    "wof:placetype":"venue"
},
  "geometry": {"coordinates":[-84.473894,45.601841],"type":"Point"}
}