{
  "type": "Feature",
  "properties": {
    "iso:country":"US",
    "sg:address":"4076 Cranbrook Ct",
    "sg:city":"Bloomfield Hills",
    "sg:classifiers":[
        {
            "category":"Real Estate",
            "subcategory":"Real Estate Agent",
            "type":"Services"
        }
    ],
    "sg:phone":"+1 248 642 4291",
    "sg:postcode":"48301",
    "sg:province":"MI",
    "sg:tags":[
        "broker",
        "developer"
    ],
    "wof:name":"M E Arden Company",
    "wof:placetype":"venue"
},
  "geometry": {"coordinates":[-83.284544,42.549053],"type":"Point"}
}