{
  "type": "Feature",
  "properties": {
    "iso:country":"US",
    "sg:address":"2309 Parmenter Rd",
    "sg:city":"Corunna",
    "sg:phone":"+1 989 743 3915",
    "sg:postcode":"48817",
    "sg:province":"MI",
    "sg:tags":[
        "farm",
        "corn",
        "soybean"
    ],
    "wof:name":"Duane Dumond",
    "wof:placetype":"venue"
},
  "geometry": {"coordinates":[-84.095409,42.96466],"type":"Point"}
}