{
  "type": "Feature",
  "properties": {
    "iso:country":"US",
    "sg:address":"11059 90th Ave",
    "sg:city":"Mecosta",
    "sg:classifiers":[
        {
            "category":"Personal",
            "subcategory":"Beauty Salon",
            "type":"Services"
        }
    ],
    "sg:phone":"+1 231 972 2955",
    "sg:postcode":"49332",
    "sg:province":"MI",
    "sg:tags":[
        "shop"
    ],
    "wof:name":"K DS Family Hair Care",
    "wof:placetype":"venue"
},
  "geometry": {"coordinates":[-85.265041,43.630263],"type":"Point"}
}