{
  "type": "Feature",
  "properties": {
    "iso:country":"US",
    "sg:address":"5841 Whitmore Lake Rd",
    "sg:city":"Brighton",
    "sg:classifiers":[
        {
            "category":"Professional",
            "subcategory":"Employment Agencies",
            "type":"Services"
        }
    ],
    "sg:phone":"+1 810 227 0259",
    "sg:postcode":"48114",
    "sg:province":"MI",
    "sg:tags":[
        "supply",
        "help",
        "contractor"
    ],
    "wof:name":"Q-Temps",
    "wof:placetype":"venue"
},
  "geometry": {"coordinates":[-83.759124,42.518648],"type":"Point"}
}