{
  "type": "Feature",
  "properties": {
    "iso:country":"US",
    "sg:address":"4928 W US Hwy 10",
    "sg:city":"Ludington",
    "sg:classifiers":[
        {
            "category":"Banks & Credit Unions",
            "subcategory":"Bank",
            "type":"Services"
        }
    ],
    "sg:phone":"+1 231 843 1144",
    "sg:postcode":"49431",
    "sg:province":"MI",
    "sg:tags":[
        "cashing",
        "check"
    ],
    "wof:name":"Advance America",
    "wof:placetype":"venue"
},
  "geometry": {"coordinates":[-86.403685,43.955709],"type":"Point"}
}