{
  "type": "Feature",
  "properties": {
    "iso:country":"US",
    "sg:address":"315 S Superior St",
    "sg:city":"Albion",
    "sg:classifiers":[
        {
            "category":"Home & Garden",
            "subcategory":"Furniture",
            "type":"Retail Goods"
        }
    ],
    "sg:phone":"+1 517 629 2081",
    "sg:postcode":"49224",
    "sg:province":"MI",
    "wof:name":"Sanders Furniture",
    "wof:placetype":"venue"
},
  "geometry": {"coordinates":[-84.75312,42.243667],"type":"Point"}
}