{
  "type": "Feature",
  "properties": {
    "iso:country":"US",
    "sg:address":"4000 Baldwin Rd",
    "sg:city":"Auburn Hills",
    "sg:classifiers":[
        {
            "category":"Shopping",
            "subcategory":"Clothing, Apparel, & Fashions",
            "type":"Retail Goods"
        }
    ],
    "sg:phone":"+1 248 451 1472",
    "sg:postcode":"48326",
    "sg:province":"MI",
    "sg:tags":[
        "sportswear"
    ],
    "sg:website":"www.demo.com",
    "wof:name":"Demo",
    "wof:placetype":"venue"
},
  "geometry": {"coordinates":[-83.30677900000001,42.700485],"type":"Point"}
}