{
  "type": "Feature",
  "properties": {
    "iso:country":"US",
    "sg:address":"6410 Spring Arbor Rd",
    "sg:city":"Jackson",
    "sg:classifiers":[
        {
            "category":"Home & Garden",
            "subcategory":"Building Materials",
            "type":"Retail Goods"
        }
    ],
    "sg:phone":"+1 517 750 2071",
    "sg:postcode":"49201",
    "sg:province":"MI",
    "sg:tags":[
        "glass",
        "window",
        "plate"
    ],
    "wof:name":"Fas-Break Auto Glass Ctr",
    "wof:placetype":"venue"
},
  "geometry": {"coordinates":[-84.505312,42.221449],"type":"Point"}
}