{
  "type": "Feature",
  "properties": {
    "iso:country":"US",
    "sg:address":"909 S Main St",
    "sg:city":"Royal Oak",
    "sg:classifiers":[
        {
            "category":"Professional",
            "subcategory":"Management & Consulting",
            "type":"Services"
        }
    ],
    "sg:phone":"+1 248 542 4901",
    "sg:postcode":"48067",
    "sg:province":"MI",
    "sg:tags":[
        "marketing",
        "program"
    ],
    "wof:name":"O Two Creative Solutions",
    "wof:placetype":"venue"
},
  "geometry": {"coordinates":[-83.14396000000001,42.482688],"type":"Point"}
}