{
  "type": "Feature",
  "properties": {
    "iso:country":"US",
    "sg:address":"1610 Guenther Rd",
    "sg:city":"Chelsea",
    "sg:classifiers":[
        {
            "category":"Farming",
            "subcategory":"Livestock Farm",
            "type":"Manufacturing & Wholesale Goods"
        }
    ],
    "sg:phone":"+1 734 475 2967",
    "sg:postcode":"48118",
    "sg:province":"MI",
    "sg:tags":[
        "beef",
        "feedlot",
        "cattle"
    ],
    "wof:name":"Robert Heller",
    "wof:placetype":"venue"
},
  "geometry": {"coordinates":[-83.945374,42.255165],"type":"Point"}
}