{
  "type": "Feature",
  "properties": {
    "iso:country":"US",
    "sg:address":"2779 Ruth Rd",
    "sg:city":"Deckerville",
    "sg:classifiers":[
        {
            "category":"Farming",
            "subcategory":"Farm",
            "type":"Manufacturing & Wholesale Goods"
        }
    ],
    "sg:phone":"+1 810 376 8148",
    "sg:postcode":"48427",
    "sg:province":"MI",
    "wof:name":"Palmer Farms Inc",
    "wof:placetype":"venue"
},
  "geometry": {"coordinates":[-82.734145,43.504635],"type":"Point"}
}