{
  "type": "Feature",
  "properties": {
    "iso:country":"US",
    "sg:address":"4198 96th Ave",
    "sg:city":"Zeeland",
    "sg:classifiers":[
        {
            "category":"Wholesale",
            "subcategory":"Poultry",
            "type":"Manufacturing & Wholesale Goods"
        },
        {
            "category":"Farming",
            "subcategory":"Poultry Farm",
            "type":"Manufacturing & Wholesale Goods"
        }
    ],
    "sg:phone":"+1 888 605 9972",
    "sg:postcode":"49464",
    "sg:province":"MI",
    "sg:tags":[
        "hatcheries-poultry"
    ],
    "sg:website":"http://www.townlinehatchery.com",
    "wof:name":"Town Line Hatchery & Poultry Farm",
    "wof:placetype":"venue"
},
  "geometry": {"coordinates":[-86.019858,42.842927],"type":"Point"}
}