{
  "type": "Feature",
  "properties": {
    "iso:country":"US",
    "sg:address":"4953 N 168th Ave",
    "sg:city":"Holland",
    "sg:classifiers":[
        {
            "category":"Social Services",
            "subcategory":"Child Care",
            "type":"Services"
        }
    ],
    "sg:phone":"+1 616 399 0528",
    "sg:postcode":"49424",
    "sg:province":"MI",
    "sg:tags":[
        "day"
    ],
    "wof:name":"Fun Haven",
    "wof:placetype":"venue"
},
  "geometry": {"coordinates":[-86.197813,42.858193],"type":"Point"}
}