{
  "type": "Feature",
  "properties": {
    "iso:country":"US",
    "sg:address":"8850 Unionville Rd",
    "sg:city":"Sebewaing",
    "sg:classifiers":[
        {
            "category":"Restaurant",
            "type":"Food & Drink"
        }
    ],
    "sg:phone":"+1 989 883 9224",
    "sg:postcode":"48759",
    "sg:province":"MI",
    "wof:name":"Lamplighter",
    "wof:placetype":"venue"
},
  "geometry": {"coordinates":[-83.447824,43.718753],"type":"Point"}
}