{
  "type": "Feature",
  "properties": {
    "iso:country":"US",
    "sg:address":"2260 Ives Rd",
    "sg:city":"Leslie",
    "sg:classifiers":[
        {
            "category":"Building & Trades",
            "subcategory":"Equipment Rental",
            "type":"Services"
        }
    ],
    "sg:phone":"+1 517 337 7200",
    "sg:postcode":"49251",
    "sg:province":"MI",
    "sg:tags":[
        "leasing"
    ],
    "wof:name":"General Fleet Leasing & Stge",
    "wof:placetype":"venue"
},
  "geometry": {"coordinates":[-84.403634,42.516955],"type":"Point"}
}