{
  "type": "Feature",
  "properties": {
    "iso:country":"US",
    "sg:address":"7880 Northwind Dr",
    "sg:city":"Howell",
    "sg:classifiers":[
        {
            "category":"Building & Trades",
            "subcategory":"Construction",
            "type":"Services"
        }
    ],
    "sg:phone":"+1 517 545 5914",
    "sg:postcode":"48855",
    "sg:province":"MI",
    "sg:tags":[
        "concrete",
        "contractor"
    ],
    "wof:name":"Watson Concrete Construction",
    "wof:placetype":"venue"
},
  "geometry": {"coordinates":[-83.91125700000001,42.709934],"type":"Point"}
}