{
  "type": "Feature",
  "properties": {
    "iso:country":"US",
    "sg:address":"4415 Corunna Rd",
    "sg:city":"Flint",
    "sg:classifiers":[
        {
            "category":"Organizations",
            "subcategory":"Non-profit Organization",
            "type":"Services"
        }
    ],
    "sg:phone":"+1 810 733 0900",
    "sg:postcode":"48532",
    "sg:province":"MI",
    "sg:tags":[
        "information",
        "alcoholism",
        "treatment"
    ],
    "sg:website":"www.insightrecovery.org",
    "wof:name":"Insight Recovery Ctr",
    "wof:placetype":"venue"
},
  "geometry": {"coordinates":[-83.767139,43.002124],"type":"Point"}
}