{
  "type": "Feature",
  "properties": {
    "iso:country":"US",
    "sg:address":"2025 US Hwy 41",
    "sg:city":"Marquette",
    "sg:classifiers":[
        {
            "category":"Communications",
            "subcategory":"Radio Station",
            "type":"Services"
        }
    ],
    "sg:phone":"+1 906 227 7777",
    "sg:postcode":"49855",
    "sg:province":"MI",
    "sg:tags":[
        "broadcast"
    ],
    "wof:name":"Wkqs Sunny 102",
    "wof:placetype":"venue"
},
  "geometry": {"coordinates":[-87.377067,46.513277],"type":"Point"}
}