{
  "type": "Feature",
  "properties": {
    "iso:country":"US",
    "sg:address":"705 McLaughlin St",
    "sg:city":"Eaton Rapids",
    "sg:classifiers":[
        {
            "category":"Social Services",
            "subcategory":"Adult Care",
            "type":"Services"
        }
    ],
    "sg:phone":"+1 517 663 2164",
    "sg:postcode":"48827",
    "sg:province":"MI",
    "sg:tags":[
        "day",
        "provider"
    ],
    "wof:name":"Wee Kare",
    "wof:placetype":"venue"
},
  "geometry": {"coordinates":[-84.64304199999999,42.511069],"type":"Point"}
}