{
  "type": "Feature",
  "properties": {
    "iso:country":"US",
    "sg:address":"724 Superior St",
    "sg:city":"Benton Harbor",
    "sg:classifiers":[
        {
            "category":"Professional",
            "type":"Services"
        }
    ],
    "sg:phone":"+1 269 925 2421",
    "sg:postcode":"49022",
    "sg:province":"MI",
    "wof:name":"Victorious Lamb Ministrie",
    "wof:placetype":"venue"
},
  "geometry": {"coordinates":[-86.447824,42.103882],"type":"Point"}
}