{
  "type": "Feature",
  "properties": {
    "iso:country":"US",
    "sg:address":"36843 Garfield Rd",
    "sg:city":"Clinton Twp",
    "sg:classifiers":[
        {
            "category":"Restaurant",
            "type":"Food & Drink"
        }
    ],
    "sg:phone":"+1 586 792 5160",
    "sg:postcode":"48035",
    "sg:province":"MI",
    "sg:tags":[
        "shop",
        "coffee"
    ],
    "wof:name":"Ciao Coffee House",
    "wof:placetype":"venue"
},
  "geometry": {"coordinates":[-82.950942,42.565916],"type":"Point"}
}