{
  "type": "Feature",
  "properties": {
    "iso:country":"US",
    "sg:address":"4520 Boardwalk Rd",
    "sg:city":"Alpena",
    "sg:classifiers":[
        {
            "category":"Social Services",
            "subcategory":"Adult Care",
            "type":"Services"
        }
    ],
    "sg:phone":"+1 989 354 8033",
    "sg:postcode":"49707",
    "sg:province":"MI",
    "sg:tags":[
        "residential"
    ],
    "wof:name":"Kelly Kares Adult Foster Care",
    "wof:placetype":"venue"
},
  "geometry": {"coordinates":[-83.459532,45.108224],"type":"Point"}
}