{
  "type": "Feature",
  "properties": {
    "iso:country":"US",
    "sg:address":"2004 Mary Catherine St",
    "sg:city":"Ypsilanti",
    "sg:classifiers":[
        {
            "category":"Building & Trades",
            "subcategory":"Construction",
            "type":"Services"
        }
    ],
    "sg:phone":"+1 734 480 2652",
    "sg:postcode":"48198",
    "sg:province":"MI",
    "sg:tags":[
        "house"
    ],
    "wof:name":"Hammer & Nails Construction",
    "wof:placetype":"venue"
},
  "geometry": {"coordinates":[-83.568597,42.227767],"type":"Point"}
}