{
  "type": "Feature",
  "properties": {
    "iso:country":"US",
    "sg:address":"8381 Canboro Rd",
    "sg:city":"Owendale",
    "sg:phone":"+1 989 678 4483",
    "sg:postcode":"48754",
    "sg:province":"MI",
    "sg:tags":[
        "farm",
        "corn"
    ],
    "wof:name":"Todd Lutz",
    "wof:placetype":"venue"
},
  "geometry": {"coordinates":[-83.306196,43.742756],"type":"Point"}
}