{
  "type": "Feature",
  "properties": {
    "iso:country":"US",
    "sg:address":"1462 E Grand River Ave",
    "sg:city":"Portland",
    "sg:classifiers":[
        {
            "category":"Coffee & Tea",
            "type":"Food & Drink"
        }
    ],
    "sg:menulink":"http://www.allmenus.com/mi/portland/248965-beaners/menu/",
    "sg:phone":"+1 517 647 4861",
    "sg:postcode":"48875",
    "sg:province":"MI",
    "sg:tags":[
        "american"
    ],
    "wof:name":"Beaners",
    "wof:placetype":"venue"
},
  "geometry": {"coordinates":[-84.891154,42.866043],"type":"Point"}
}