{
  "type": "Feature",
  "properties": {
    "iso:country":"US",
    "sg:address":"25 Jefferson Ave SE",
    "sg:city":"Grand Rapids",
    "sg:classifiers":[
        {
            "category":"Real Estate",
            "subcategory":"Architect",
            "type":"Services"
        }
    ],
    "sg:phone":"+1 616 235 3311",
    "sg:postcode":"49503",
    "sg:province":"MI",
    "sg:tags":[
        "consulting",
        "management",
        "architectural"
    ],
    "wof:name":"Karczewski Architects",
    "wof:placetype":"venue"
},
  "geometry": {"coordinates":[-85.66426300000001,42.962824],"type":"Point"}
}