{
  "type": "Feature",
  "properties": {
    "iso:country":"US",
    "sg:address":"34726 Dequindre Rd",
    "sg:city":"Sterling Heights",
    "sg:classifiers":[
        {
            "category":"Restaurant",
            "type":"Food & Drink"
        }
    ],
    "sg:phone":"+1 586 825 2203",
    "sg:postcode":"48083",
    "sg:province":"MI",
    "sg:tags":[
        "middle",
        "eastern"
    ],
    "wof:name":"Yahala Cafe",
    "wof:placetype":"venue"
},
  "geometry": {"coordinates":[-83.088022,42.548115],"type":"Point"}
}