{
  "type": "Feature",
  "properties": {
    "iso:country":"US",
    "sg:address":"140 E Main St",
    "sg:city":"Mendon",
    "sg:classifiers":[
        {
            "category":"Food & Beverages",
            "subcategory":"Specialty",
            "type":"Retail Goods"
        },
        {
            "category":"Food & Beverages",
            "subcategory":"Groceries & Convenience Stores",
            "type":"Retail Goods"
        },
        {
            "category":"Food & Beverages",
            "subcategory":"Meat & Fish",
            "type":"Retail Goods"
        }
    ],
    "sg:phone":"+1 269 496 4655",
    "sg:postcode":"49072",
    "sg:province":"MI",
    "sg:tags":[
        "grocers-specialty",
        "market"
    ],
    "wof:name":"Ken's Foodland",
    "wof:placetype":"venue"
},
  "geometry": {"coordinates":[-85.44894600000001,42.006724],"type":"Point"}
}