{
  "type": "Feature",
  "properties": {
    "iso:country":"US",
    "sg:address":"1500 Brookmoor Ln",
    "sg:city":"Portage",
    "sg:classifiers":[
        {
            "category":"Professional",
            "subcategory":"Business Services",
            "type":"Services"
        }
    ],
    "sg:phone":"+1 269 323 8630",
    "sg:postcode":"49024",
    "sg:province":"MI",
    "wof:name":"McEvers Appraisal",
    "wof:placetype":"venue"
},
  "geometry": {"coordinates":[-85.606798,42.19571],"type":"Point"}
}