{
  "type": "Feature",
  "properties": {
    "iso:country":"US",
    "sg:address":"3570 28th St SE",
    "sg:city":"Kentwood",
    "sg:classifiers":[
        {
            "category":"Restaurant",
            "type":"Food & Drink"
        }
    ],
    "sg:phone":"+1 616 954 7960",
    "sg:postcode":"49512",
    "sg:province":"MI",
    "sg:website":"www.donpablos.com",
    "wof:name":"Don Pablo's Mexican Kitchen",
    "wof:placetype":"venue"
},
  "geometry": {"coordinates":[-85.576063,42.912449],"type":"Point"}
}