{
  "type": "Feature",
  "properties": {
    "iso:country":"US",
    "sg:address":"2380 Yorkshire Rd",
    "sg:city":"Birmingham",
    "sg:classifiers":[
        {
            "category":"Building & Trades",
            "subcategory":"Construction",
            "type":"Services"
        }
    ],
    "sg:phone":"+1 248 643 6062",
    "sg:postcode":"48009",
    "sg:province":"MI",
    "sg:tags":[
        "home",
        "builder"
    ],
    "wof:name":"Hentgen Building & Development",
    "wof:placetype":"venue"
},
  "geometry": {"coordinates":[-83.190214,42.548232],"type":"Point"}
}