{
  "type": "Feature",
  "properties": {
    "iso:country":"US",
    "sg:address":"46359 Huling St",
    "sg:city":"Utica",
    "sg:classifiers":[
        {
            "category":"Utilities",
            "type":"Services"
        }
    ],
    "sg:phone":"+1 586 254 9479",
    "sg:postcode":"48317",
    "sg:province":"MI",
    "sg:tags":[
        "sanitary"
    ],
    "wof:name":"J T Snowplowing",
    "wof:placetype":"venue"
},
  "geometry": {"coordinates":[-83.08693700000001,42.632641],"type":"Point"}
}