{
  "type": "Feature",
  "properties": {
    "iso:country":"US",
    "sg:address":"3515 N Euclid Ave",
    "sg:city":"Bay City",
    "sg:classifiers":[
        {
            "category":"Manufacturing",
            "subcategory":"Tools & Machinery",
            "type":"Manufacturing & Wholesale Goods"
        }
    ],
    "sg:phone":"+1 989 684 8051",
    "sg:postcode":"48706",
    "sg:province":"MI",
    "sg:tags":[
        "die",
        "maker"
    ],
    "wof:name":"Tri-City Tool & Die Inc",
    "wof:placetype":"venue"
},
  "geometry": {"coordinates":[-83.913596,43.637222],"type":"Point"}
}