{
  "type": "Feature",
  "properties": {
    "iso:country":"US",
    "sg:address":"24357 Indoplex Cir",
    "sg:city":"Farmington Hills",
    "sg:classifiers":[
        {
            "category":"Professional",
            "subcategory":"Business Services",
            "type":"Services"
        },
        {
            "category":"Home & Garden",
            "subcategory":"Home Furnishings",
            "type":"Retail Goods"
        }
    ],
    "sg:phone":"+1 248 426 9735",
    "sg:postcode":"48335",
    "sg:province":"MI",
    "sg:tags":[
        "curtain",
        "made",
        "drapery"
    ],
    "wof:name":"Signature Designs Inc",
    "wof:placetype":"venue"
},
  "geometry": {"coordinates":[-83.392702,42.473083],"type":"Point"}
}