{
  "type": "Feature",
  "properties": {
    "iso:country":"US",
    "sg:address":"196 Oakland Ave",
    "sg:city":"Pontiac",
    "sg:classifiers":[
        {
            "category":"Wholesale",
            "subcategory":"Durable Goods & Equipment",
            "type":"Manufacturing & Wholesale Goods"
        }
    ],
    "sg:phone":"+1 248 253 7300",
    "sg:postcode":"48342",
    "sg:province":"MI",
    "sg:tags":[
        "instrument",
        "musical"
    ],
    "wof:name":"Music Products Group",
    "wof:placetype":"venue"
},
  "geometry": {"coordinates":[-83.298704,42.644491],"type":"Point"}
}