{
  "type": "Feature",
  "properties": {
    "iso:country":"US",
    "sg:address":"24370 Northwestern Hwy",
    "sg:city":"Southfield",
    "sg:classifiers":[
        {
            "category":"Professional",
            "subcategory":"Management & Consulting",
            "type":"Services"
        }
    ],
    "sg:phone":"+1 248 358 9199",
    "sg:postcode":"48075",
    "sg:province":"MI",
    "sg:tags":[
        "consultant"
    ],
    "wof:name":"Part D Advisors",
    "wof:placetype":"venue"
},
  "geometry": {"coordinates":[-83.23424900000001,42.467861],"type":"Point"}
}