{
  "type": "Feature",
  "properties": {
    "iso:country":"US",
    "sg:address":"14644 Greenfield Rd",
    "sg:city":"Detroit",
    "sg:classifiers":[
        {
            "category":"Professional",
            "subcategory":"Business Services",
            "type":"Services"
        }
    ],
    "sg:phone":"+1 313 836 1000",
    "sg:postcode":"48227",
    "sg:province":"MI",
    "wof:name":"Instrument Repairs & Sales",
    "wof:placetype":"venue"
},
  "geometry": {"coordinates":[-83.19841599999999,42.395523],"type":"Point"}
}