{
  "type": "Feature",
  "properties": {
    "iso:country":"US",
    "sg:address":"1612 Marilyn Dr",
    "sg:city":"Ludington",
    "sg:classifiers":[
        {
            "category":"Building & Trades",
            "subcategory":"Construction",
            "type":"Services"
        }
    ],
    "sg:phone":"+1 231 843 1719",
    "sg:postcode":"49431",
    "sg:province":"MI",
    "sg:tags":[
        "tile",
        "dealer"
    ],
    "wof:name":"Mortensen & Coleman Constr",
    "wof:placetype":"venue"
},
  "geometry": {"coordinates":[-86.45107400000001,43.989806],"type":"Point"}
}