{
  "type": "Feature",
  "properties": {
    "iso:country":"US",
    "sg:address":"316 W Lewis St",
    "sg:city":"Alpena",
    "sg:classifiers":[
        {
            "category":"Professional",
            "subcategory":"Computer Services",
            "type":"Services"
        }
    ],
    "sg:phone":"+1 989 356 2229",
    "sg:postcode":"49707",
    "sg:province":"MI",
    "sg:tags":[
        "internet"
    ],
    "wof:name":"Freeway Internet",
    "wof:placetype":"venue"
},
  "geometry": {"coordinates":[-83.442154,45.060734],"type":"Point"}
}