{
  "type": "Feature",
  "properties": {
    "iso:country":"US",
    "sg:address":"995 Razorback Dr",
    "sg:city":"Houghton",
    "sg:classifiers":[
        {
            "category":"Shopping",
            "subcategory":"Department Store",
            "type":"Retail Goods"
        }
    ],
    "sg:phone":"+1 906 482 0639",
    "sg:postcode":"49931",
    "sg:province":"MI",
    "sg:tags":[
        "photofinishing",
        "laboratory"
    ],
    "sg:website":"www.wal-mart.com",
    "wof:name":"Wal-Mart",
    "wof:placetype":"venue"
},
  "geometry": {"coordinates":[-88.586586,47.113009],"type":"Point"}
}