{
  "type": "Feature",
  "properties": {
    "iso:country":"US",
    "sg:address":"8164 Rattalee Lake Rd",
    "sg:city":"Clarkston",
    "sg:classifiers":[
        {
            "category":"Professional",
            "subcategory":"Lawyer & Legal Services",
            "type":"Services"
        }
    ],
    "sg:phone":"+1 248 593 5710",
    "sg:postcode":"48348",
    "sg:province":"MI",
    "sg:tags":[
        "attorney"
    ],
    "wof:name":"Cheryl A Daly",
    "wof:placetype":"venue"
},
  "geometry": {"coordinates":[-83.451302,42.774711],"type":"Point"}
}