{
  "type": "Feature",
  "properties": {
    "iso:country":"US",
    "sg:address":"55 Lowell Ave NE",
    "sg:city":"Grand Rapids",
    "sg:classifiers":[
        {
            "category":"Food & Beverages",
            "subcategory":"Groceries & Convenience Stores",
            "type":"Retail Goods"
        }
    ],
    "sg:phone":"+1 616 233 9820",
    "sg:postcode":"49503",
    "sg:province":"MI",
    "sg:tags":[
        "product"
    ],
    "wof:name":"Mc Cain Foods Inc",
    "wof:placetype":"venue"
},
  "geometry": {"coordinates":[-85.633876,42.965369],"type":"Point"}
}