{
  "type": "Feature",
  "properties": {
    "iso:country":"US",
    "sg:address":"14384 Smigelski Rd",
    "sg:city":"Posen",
    "sg:phone":"+1 989 766 2584",
    "sg:postcode":"49776",
    "sg:province":"MI",
    "sg:tags":[
        "farm",
        "corn"
    ],
    "wof:name":"Edward Smigelski",
    "wof:placetype":"venue"
},
  "geometry": {"coordinates":[-83.61751700000001,45.213026],"type":"Point"}
}