{
  "type": "Feature",
  "properties": {
    "iso:country":"US",
    "sg:address":"10788 Gratiot Ave",
    "sg:city":"Casco",
    "sg:classifiers":[
        {
            "category":"Professional",
            "subcategory":"Business Services",
            "type":"Services"
        }
    ],
    "sg:phone":"+1 586 727 4114",
    "sg:postcode":"48064",
    "sg:province":"MI",
    "sg:tags":[
        "automobile",
        "auctioneer"
    ],
    "wof:name":"Richmond Auto Auction",
    "wof:placetype":"venue"
},
  "geometry": {"coordinates":[-82.73080899999999,42.800871],"type":"Point"}
}