{
  "type": "Feature",
  "properties": {
    "iso:country":"US",
    "sg:address":"224 N 17th St",
    "sg:city":"Gladstone",
    "sg:classifiers":[
        {
            "category":"Shopping",
            "subcategory":"Gifts & Souvenirs",
            "type":"Retail Goods"
        }
    ],
    "sg:phone":"+1 906 428 1213",
    "sg:postcode":"49837",
    "sg:province":"MI",
    "sg:tags":[
        "novelty"
    ],
    "wof:name":"Tysons Treasuries",
    "wof:placetype":"venue"
},
  "geometry": {"coordinates":[-87.032552,45.849271],"type":"Point"}
}