{
  "type": "Feature",
  "properties": {
    "iso:country":"US",
    "sg:address":"36515 Van Born Rd",
    "sg:city":"Romulus",
    "sg:classifiers":[
        {
            "category":"Manufacturing",
            "subcategory":"Motor Vehicles & Parts",
            "type":"Manufacturing & Wholesale Goods"
        }
    ],
    "sg:phone":"+1 734 595 7920",
    "sg:postcode":"48174",
    "sg:province":"MI",
    "sg:tags":[
        "transmission",
        "mfg"
    ],
    "wof:name":"General Motors",
    "wof:placetype":"venue"
},
  "geometry": {"coordinates":[-83.40128300000001,42.26627],"type":"Point"}
}