{
  "type": "Feature",
  "properties": {
    "iso:country":"US",
    "sg:address":"3874 E Manales Rd",
    "sg:city":"Fountain",
    "sg:classifiers":[
        {
            "category":"Home & Garden",
            "subcategory":"Hardware",
            "type":"Retail Goods"
        }
    ],
    "sg:phone":"+1 231 462 3934",
    "sg:postcode":"49410",
    "sg:province":"MI",
    "sg:tags":[
        "saw"
    ],
    "wof:name":"Backwoods Products Inc",
    "wof:placetype":"venue"
},
  "geometry": {"coordinates":[-86.184918,44.041176],"type":"Point"}
}