{
  "type": "Feature",
  "properties": {
    "iso:country":"US",
    "sg:address":"2754 Burlingame Ave SW",
    "sg:city":"Wyoming",
    "sg:classifiers":[
        {
            "category":"Retail",
            "subcategory":"Veterinary Services",
            "type":"Services"
        }
    ],
    "sg:phone":"+1 616 538 9700",
    "sg:postcode":"49509",
    "sg:province":"MI",
    "sg:tags":[
        "hospital",
        "animal"
    ],
    "wof:name":"VCA Wyoming Animal Hospital",
    "wof:placetype":"venue"
},
  "geometry": {"coordinates":[-85.7052,42.914005],"type":"Point"}
}