{
  "type": "Feature",
  "properties": {
    "iso:country":"US",
    "sg:address":"4590 Seaway Dr",
    "sg:city":"Lansing",
    "sg:classifiers":[
        {
            "category":"Real Estate",
            "subcategory":"Real Estate Operator",
            "type":"Services"
        }
    ],
    "sg:phone":"+1 517 394 0000",
    "sg:postcode":"48911",
    "sg:province":"MI",
    "sg:tags":[
        "apartment"
    ],
    "wof:name":"Arbor Pointe One LLC",
    "wof:placetype":"venue"
},
  "geometry": {"coordinates":[-84.60880899999999,42.688234],"type":"Point"}
}