{
  "type": "Feature",
  "properties": {
    "iso:country":"US",
    "sg:address":"3361 N Bagley Rd",
    "sg:city":"Alma",
    "sg:classifiers":[
        {
            "category":"Professional",
            "subcategory":"Business Services",
            "type":"Services"
        }
    ],
    "sg:phone":"+1 989 875 2205",
    "sg:postcode":"48801",
    "sg:province":"MI",
    "sg:tags":[
        "notary",
        "public"
    ],
    "wof:name":"Rosemary A Duckworth",
    "wof:placetype":"venue"
},
  "geometry": {"coordinates":[-84.567806,43.33934],"type":"Point"}
}