{
  "type": "Feature",
  "properties": {
    "iso:country":"US",
    "sg:address":"35080 Grand River Ave",
    "sg:city":"Farmington",
    "sg:classifiers":[
        {
            "category":"Autos & Motor Vehicles",
            "subcategory":"Automobile Sales",
            "type":"Retail Goods"
        }
    ],
    "sg:phone":"+1 248 699 7100",
    "sg:postcode":"48335",
    "sg:province":"MI",
    "sg:tags":[
        "car"
    ],
    "wof:name":"Bob Saks Toyota Inc",
    "wof:placetype":"venue"
},
  "geometry": {"coordinates":[-83.392403,42.469002],"type":"Point"}
}