{
  "type": "Feature",
  "properties": {
    "iso:country":"US",
    "sg:address":"23329 Scott Dr",
    "sg:city":"Farmington Hills",
    "sg:classifiers":[
        {
            "category":"Professional",
            "subcategory":"Management & Consulting",
            "type":"Services"
        }
    ],
    "sg:phone":"+1 248 888 0776",
    "sg:postcode":"48336",
    "sg:province":"MI",
    "sg:tags":[
        "consultant",
        "business"
    ],
    "wof:name":"Boss Inc",
    "wof:placetype":"venue"
},
  "geometry": {"coordinates":[-83.32965,42.46461],"type":"Point"}
}