{
  "type": "Feature",
  "properties": {
    "iso:country":"US",
    "sg:address":"2033 11th Ave",
    "sg:city":"Port Huron",
    "sg:classifiers":[
        {
            "category":"Health Services",
            "subcategory":"Clinic",
            "type":"Services"
        }
    ],
    "sg:phone":"+1 810 984 1002",
    "sg:postcode":"48060",
    "sg:province":"MI",
    "sg:tags":[
        "specialty",
        "outpatient"
    ],
    "wof:name":"John Sarcar MD",
    "wof:placetype":"venue"
},
  "geometry": {"coordinates":[-82.43627499999999,42.996295],"type":"Point"}
}