{
  "type": "Feature",
  "properties": {
    "iso:country":"US",
    "sg:address":"8838 Melinda Ct",
    "sg:city":"Milan",
    "sg:classifiers":[
        {
            "category":"Wholesale",
            "subcategory":"Furniture",
            "type":"Manufacturing & Wholesale Goods"
        }
    ],
    "sg:phone":"+1 734 528 0300",
    "sg:postcode":"48160",
    "sg:province":"MI",
    "sg:tags":[
        "preparation",
        "tax",
        "return"
    ],
    "wof:name":"Complete Tax Center Inc",
    "wof:placetype":"venue"
},
  "geometry": {"coordinates":[-83.67410599999999,42.159595],"type":"Point"}
}