{
  "type": "Feature",
  "properties": {
    "iso:country":"US",
    "sg:address":"21703 Hoover Rd",
    "sg:city":"Warren",
    "sg:classifiers":[
        {
            "category":"Freight",
            "type":"Transportation"
        }
    ],
    "sg:phone":"+1 586 754 5315",
    "sg:postcode":"48089",
    "sg:province":"MI",
    "sg:tags":[
        "hauling",
        "trucking"
    ],
    "sg:website":"www.ktg.com",
    "wof:name":"Key Cartage",
    "wof:placetype":"venue"
},
  "geometry": {"coordinates":[-83.005582,42.457874],"type":"Point"}
}