{
  "type": "Feature",
  "properties": {
    "iso:country":"US",
    "sg:address":"53 Green St",
    "sg:city":"Pontiac",
    "sg:classifiers":[
        {
            "category":"Building & Trades",
            "subcategory":"Landscaping Services",
            "type":"Services"
        }
    ],
    "sg:phone":"+1 248 454 0970",
    "sg:postcode":"48341",
    "sg:province":"MI",
    "sg:tags":[
        "designer",
        "landscape"
    ],
    "wof:name":"Rock's Landscape Design",
    "wof:placetype":"venue"
},
  "geometry": {"coordinates":[-83.307616,42.634801],"type":"Point"}
}