{
  "type": "Feature",
  "properties": {
    "iso:country":"US",
    "sg:address":"236 Culver St",
    "sg:city":"Saugatuck",
    "sg:classifiers":[
        {
            "category":"Restaurant",
            "type":"Food & Drink"
        }
    ],
    "sg:phone":"+1 269 857 3793",
    "sg:postcode":"49453",
    "sg:province":"MI",
    "wof:name":"Loaf & Mug Restaurant",
    "wof:placetype":"venue"
},
  "geometry": {"coordinates":[-86.203175,42.65486],"type":"Point"}
}