{
  "type": "Feature",
  "properties": {
    "iso:country":"US",
    "sg:address":"6565 N Telegraph Rd",
    "sg:city":"Dearborn Heights",
    "sg:classifiers":[
        {
            "category":"Restaurant",
            "type":"Food & Drink"
        }
    ],
    "sg:menulink":"http://www.allmenus.com/mi/dearborn-heights/93332-carieras/menu/",
    "sg:phone":"+1 313 278 4060",
    "sg:postcode":"48127",
    "sg:province":"MI",
    "sg:tags":[
        "italian"
    ],
    "wof:name":"Cariera's",
    "wof:placetype":"venue"
},
  "geometry": {"coordinates":[-83.273279,42.335778],"type":"Point"}
}