{
  "type": "Feature",
  "properties": {
    "iso:country":"US",
    "sg:address":"6686 N Lafayette St",
    "sg:city":"Greenville",
    "sg:classifiers":[
        {
            "category":"Wholesale",
            "subcategory":"Scrap",
            "type":"Manufacturing & Wholesale Goods"
        }
    ],
    "sg:phone":"+1 616 754 7116",
    "sg:postcode":"48838",
    "sg:province":"MI",
    "sg:tags":[
        "metal",
        "iron"
    ],
    "wof:name":"Greenville Steel Sales",
    "wof:placetype":"venue"
},
  "geometry": {"coordinates":[-85.253011,43.197115],"type":"Point"}
}