{
  "type": "Feature",
  "properties": {
    "iso:country":"US",
    "sg:address":"3835 Washington Ave",
    "sg:city":"Saint Joseph",
    "sg:classifiers":[
        {
            "category":"Organizations",
            "subcategory":"Religious Organization",
            "type":"Services"
        }
    ],
    "sg:phone":"+1 269 429 4537",
    "sg:postcode":"49085",
    "sg:province":"MI",
    "wof:name":"First Missionary Baptst Chapel",
    "wof:placetype":"venue"
},
  "geometry": {"coordinates":[-86.484976,42.047728],"type":"Point"}
}