{
  "type": "Feature",
  "properties": {
    "iso:country":"US",
    "sg:address":"4472 Breton Rd SE",
    "sg:city":"Kentwood",
    "sg:classifiers":[
        {
            "category":"Shopping",
            "subcategory":"Clothing, Apparel, & Fashions",
            "type":"Retail Goods"
        }
    ],
    "sg:phone":"+1 616 455 5544",
    "sg:postcode":"49508",
    "sg:province":"MI",
    "sg:tags":[
        "swimwear",
        "accessory"
    ],
    "wof:name":"Endless Summer",
    "wof:placetype":"venue"
},
  "geometry": {"coordinates":[-85.606262,42.88276],"type":"Point"}
}