{
  "type": "Feature",
  "properties": {
    "iso:country":"US",
    "sg:address":"94 N Park St",
    "sg:city":"Muskegon",
    "sg:classifiers":[
        {
            "category":"Building & Trades",
            "subcategory":"Landscaping Services",
            "type":"Services"
        }
    ],
    "sg:phone":"+1 231 788 2123",
    "sg:postcode":"49442",
    "sg:province":"MI",
    "sg:tags":[
        "tree"
    ],
    "wof:name":"Cut-Rite Tree Svc",
    "wof:placetype":"venue"
},
  "geometry": {"coordinates":[-86.11721900000001,43.257],"type":"Point"}
}