{
  "type": "Feature",
  "properties": {
    "iso:country":"US",
    "sg:address":"4202 S Creyts Rd",
    "sg:city":"Lansing",
    "sg:classifiers":[
        {
            "category":"Retail",
            "subcategory":"Auto Repair",
            "type":"Services"
        }
    ],
    "sg:phone":"+1 517 322 3228",
    "sg:postcode":"48917",
    "sg:province":"MI",
    "sg:tags":[
        "transmission"
    ],
    "wof:name":"ATC Distribution Group",
    "wof:placetype":"venue"
},
  "geometry": {"coordinates":[-84.642449,42.689063],"type":"Point"}
}