{
  "type": "Feature",
  "properties": {
    "iso:country":"US",
    "sg:address":"4379 Maplewood Meadows Ave",
    "sg:city":"Grand Blanc",
    "sg:classifiers":[
        {
            "category":"Social Services",
            "subcategory":"Child Care",
            "type":"Services"
        }
    ],
    "sg:phone":"+1 810 715 0040",
    "sg:postcode":"48439",
    "sg:province":"MI",
    "wof:name":"Lori Ann Day Care",
    "wof:placetype":"venue"
},
  "geometry": {"coordinates":[-83.60379,42.96362],"type":"Point"}
}