{
  "type": "Feature",
  "properties": {
    "iso:country":"US",
    "sg:address":"9178 E Bristol Rd",
    "sg:city":"Davison",
    "sg:classifiers":[
        {
            "category":"Social Services",
            "subcategory":"Adult Care",
            "type":"Services"
        }
    ],
    "sg:phone":"+1 810 744 2327",
    "sg:postcode":"48423",
    "sg:province":"MI",
    "sg:tags":[
        "home",
        "residential"
    ],
    "wof:name":"Kra-Nur Manor",
    "wof:placetype":"venue"
},
  "geometry": {"coordinates":[-83.53218099999999,42.976336],"type":"Point"}
}