{
  "type": "Feature",
  "properties": {
    "iso:country":"US",
    "sg:address":"4513 6th St",
    "sg:city":"Caledonia",
    "sg:classifiers":[
        {
            "category":"Social Services",
            "subcategory":"Child Care",
            "type":"Services"
        }
    ],
    "sg:phone":"+1 616 891 9931",
    "sg:postcode":"49316",
    "sg:province":"MI",
    "sg:tags":[
        "day"
    ],
    "wof:name":"Celena Johnson",
    "wof:placetype":"venue"
},
  "geometry": {"coordinates":[-85.603689,42.747552],"type":"Point"}
}