{
  "type": "Feature",
  "properties": {
    "iso:country":"US",
    "sg:address":"57258 Co Rd 388",
    "sg:city":"Grand Junction",
    "sg:classifiers":[
        {
            "category":"Retail",
            "subcategory":"Repair Shop",
            "type":"Services"
        }
    ],
    "sg:phone":"+1 269 434 6475",
    "sg:postcode":"49056",
    "sg:province":"MI",
    "sg:tags":[
        "television",
        "radio"
    ],
    "wof:name":"J & J Svc",
    "wof:placetype":"venue"
},
  "geometry": {"coordinates":[-86.107699,42.409456],"type":"Point"}
}