{
  "type": "Feature",
  "properties": {
    "iso:country":"US",
    "sg:address":"2240 Schimperle Dr NE",
    "sg:city":"Grand Rapids",
    "sg:classifiers":[
        {
            "category":"Social Services",
            "subcategory":"Adult Care",
            "type":"Services"
        }
    ],
    "sg:phone":"+1 616 365 0039",
    "sg:postcode":"49525",
    "sg:province":"MI",
    "sg:tags":[
        "foster",
        "provider"
    ],
    "wof:name":"Theodore Ndawillie",
    "wof:placetype":"venue"
},
  "geometry": {"coordinates":[-85.61432000000001,43.026705],"type":"Point"}
}