{
  "type": "Feature",
  "properties": {
    "iso:country":"US",
    "sg:address":"6408 Heron Park Way",
    "sg:city":"Clarkston",
    "sg:classifiers":[
        {
            "category":"Building & Trades",
            "subcategory":"Construction",
            "type":"Services"
        }
    ],
    "sg:phone":"+1 248 922 3386",
    "sg:postcode":"48346",
    "sg:province":"MI",
    "sg:tags":[
        "painter"
    ],
    "wof:name":"Bright Looks Painting",
    "wof:placetype":"venue"
},
  "geometry": {"coordinates":[-83.385149,42.731371],"type":"Point"}
}