{
  "type": "Feature",
  "properties": {
    "iso:country":"US",
    "sg:address":"33186 Ryan Rd",
    "sg:city":"Sterling Heights",
    "sg:classifiers":[
        {
            "category":"Social Services",
            "type":"Services"
        }
    ],
    "sg:phone":"+1 586 268 0088",
    "sg:postcode":"48310",
    "sg:province":"MI",
    "wof:name":"Maple Ridge Adult Day Services",
    "wof:placetype":"venue"
},
  "geometry": {"coordinates":[-83.068552,42.536522],"type":"Point"}
}