{
  "type": "Feature",
  "properties": {
    "iso:country":"US",
    "sg:address":"437 4th St",
    "sg:city":"Ann Arbor",
    "sg:classifiers":[
        {
            "category":"Professional",
            "subcategory":"Printing & Photocopies",
            "type":"Services"
        }
    ],
    "sg:phone":"+1 734 330 7679",
    "sg:postcode":"48103",
    "sg:province":"MI",
    "sg:tags":[
        "photocopying",
        "duplicating"
    ],
    "wof:name":"Photo Reprint Services",
    "wof:placetype":"venue"
},
  "geometry": {"coordinates":[-83.75470799999999,42.27672],"type":"Point"}
}