{
  "type": "Feature",
  "properties": {
    "iso:country":"US",
    "sg:address":"3171 Forrest Trl NE",
    "sg:city":"Rockford",
    "sg:classifiers":[
        {
            "category":"Wholesale",
            "subcategory":"Metals & Minerals",
            "type":"Manufacturing & Wholesale Goods"
        }
    ],
    "sg:phone":"+1 616 866 8467",
    "sg:postcode":"49341",
    "sg:province":"MI",
    "sg:tags":[
        "steel",
        "warehouse"
    ],
    "wof:name":"Continental Metals Inc",
    "wof:placetype":"venue"
},
  "geometry": {"coordinates":[-85.59302599999999,43.163116],"type":"Point"}
}