{
  "type": "Feature",
  "properties": {
    "iso:country":"US",
    "sg:address":"17731 E Warren Ave",
    "sg:city":"Detroit",
    "sg:classifiers":[
        {
            "category":"Shopping",
            "subcategory":"Pharmacy",
            "type":"Retail Goods"
        }
    ],
    "sg:phone":"+1 313 308 4151",
    "sg:postcode":"48224",
    "sg:province":"MI",
    "sg:tags":[
        "drugstore"
    ],
    "wof:name":"Excel Pharmacy",
    "wof:placetype":"venue"
},
  "geometry": {"coordinates":[-82.92211500000001,42.409024],"type":"Point"}
}