{
  "type": "Feature",
  "properties": {
    "iso:country":"US",
    "sg:address":"7572 E Melissa Dr",
    "sg:city":"Traverse City",
    "sg:classifiers":[
        {
            "category":"Building & Trades",
            "subcategory":"Plumbing",
            "type":"Services"
        }
    ],
    "sg:phone":"+1 231 932 8400",
    "sg:postcode":"49684",
    "sg:province":"MI",
    "sg:tags":[
        "tank",
        "septic"
    ],
    "wof:name":"Great Lakes Wastewater Systems",
    "wof:placetype":"venue"
},
  "geometry": {"coordinates":[-85.70190700000001,44.901641],"type":"Point"}
}