{
  "type": "Feature",
  "properties": {
    "iso:country":"US",
    "sg:address":"5392 N Meridian Rd",
    "sg:city":"Hope",
    "sg:classifiers":[
        {
            "category":"Retail",
            "subcategory":"Repair Shop",
            "type":"Services"
        },
        {
            "category":"Recreation",
            "subcategory":"Marina",
            "type":"Entertainment"
        }
    ],
    "sg:phone":"+1 989 689 3204",
    "sg:postcode":"48628",
    "sg:province":"MI",
    "sg:tags":[
        "repairing",
        "marine",
        "boat"
    ],
    "wof:name":"Erskine Marine Inc",
    "wof:placetype":"venue"
},
  "geometry": {"coordinates":[-84.367411,43.766005],"type":"Point"}
}