{
  "type": "Feature",
  "properties": {
    "iso:country":"US",
    "sg:address":"7335 W Carleton Rd",
    "sg:city":"Clayton",
    "sg:classifiers":[
        {
            "category":"Retail",
            "subcategory":"Auto Repair",
            "type":"Services"
        }
    ],
    "sg:phone":"+1 517 445 2970",
    "sg:postcode":"49235",
    "sg:province":"MI",
    "sg:tags":[
        "automotive"
    ],
    "wof:name":"Clayton Corners Auto Transport",
    "wof:placetype":"venue"
},
  "geometry": {"coordinates":[-84.166551,41.857797],"type":"Point"}
}