{
  "type": "Feature",
  "properties": {
    "iso:country":"US",
    "sg:address":"33057 Schoolcraft Rd",
    "sg:city":"Livonia",
    "sg:classifiers":[
        {
            "category":"Utilities",
            "subcategory":"Telephone",
            "type":"Services"
        }
    ],
    "sg:phone":"+1 734 421 2250",
    "sg:postcode":"48150",
    "sg:province":"MI",
    "sg:tags":[
        "communications"
    ],
    "wof:name":"TDS",
    "wof:placetype":"venue"
},
  "geometry": {"coordinates":[-83.367262,42.382203],"type":"Point"}
}