{
  "type": "Feature",
  "properties": {
    "iso:country":"US",
    "sg:address":"1340 S M 33",
    "sg:city":"West Branch",
    "sg:classifiers":[
        {
            "category":"Recreation",
            "type":"Entertainment"
        }
    ],
    "sg:phone":"+1 989 345 0426",
    "sg:postcode":"48661",
    "sg:province":"MI",
    "sg:tags":[
        "stable"
    ],
    "wof:name":"Four Seasons Stables",
    "wof:placetype":"venue"
},
  "geometry": {"coordinates":[-84.12576799999999,44.296484],"type":"Point"}
}