{
  "type": "Feature",
  "properties": {
    "iso:country":"US",
    "sg:address":"1026 S Union St",
    "sg:city":"Traverse City",
    "sg:classifiers":[
        {
            "category":"Building & Trades",
            "subcategory":"Construction",
            "type":"Services"
        }
    ],
    "sg:phone":"+1 231 929 4596",
    "sg:postcode":"49684",
    "sg:province":"MI",
    "sg:tags":[
        "general",
        "contractor"
    ],
    "wof:name":"Tarras Construction Inc",
    "wof:placetype":"venue"
},
  "geometry": {"coordinates":[-85.623761,44.753156],"type":"Point"}
}