{
  "type": "Feature",
  "properties": {
    "iso:country":"US",
    "sg:address":"275 Muskegon Mall",
    "sg:city":"Muskegon",
    "sg:classifiers":[
        {
            "category":"Government",
            "subcategory":"Office",
            "type":"Public Place"
        }
    ],
    "sg:phone":"+1 231 728 5154",
    "sg:postcode":"49440",
    "sg:province":"MI",
    "sg:tags":[
        "armed",
        "force",
        "recruiting"
    ],
    "wof:name":"US Marine Corps Recruiting",
    "wof:placetype":"venue"
},
  "geometry": {"coordinates":[-86.25232699999999,43.236499],"type":"Point"}
}