{
  "type": "Feature",
  "properties": {
    "iso:country":"US",
    "sg:address":"500 100th St SW",
    "sg:city":"Byron Center",
    "sg:classifiers":[
        {
            "category":"Shopping",
            "subcategory":"Bicycles & Sporting Goods",
            "type":"Retail Goods"
        }
    ],
    "sg:phone":"+1 616 878 1813",
    "sg:postcode":"49315",
    "sg:province":"MI",
    "sg:tags":[
        "equipment",
        "hockey"
    ],
    "wof:name":"Perani's Hockey Shop",
    "wof:placetype":"venue"
},
  "geometry": {"coordinates":[-85.67374700000001,42.7826],"type":"Point"}
}