{
  "type": "Feature",
  "properties": {
    "iso:country":"US",
    "sg:address":"1755 Livernois Rd",
    "sg:city":"Troy",
    "sg:classifiers":[
        {
            "category":"Retail",
            "subcategory":"Portrait Studio",
            "type":"Services"
        }
    ],
    "sg:phone":"+1 248 244 1717",
    "sg:postcode":"48083",
    "sg:province":"MI",
    "sg:tags":[
        "photographer"
    ],
    "wof:name":"I2I Studio",
    "wof:placetype":"venue"
},
  "geometry": {"coordinates":[-83.14712900000001,42.54929],"type":"Point"}
}