{
  "type": "Feature",
  "properties": {
    "iso:country":"US",
    "sg:address":"306 N State St",
    "sg:city":"Alma",
    "sg:classifiers":[
        {
            "category":"Health Services",
            "subcategory":"Doctor",
            "type":"Services"
        }
    ],
    "sg:phone":"+1 989 463 4036",
    "sg:postcode":"48801",
    "sg:province":"MI",
    "sg:tags":[
        "dentist"
    ],
    "wof:name":"William G Ryan DDS",
    "wof:placetype":"venue"
},
  "geometry": {"coordinates":[-84.661771,43.378902],"type":"Point"}
}