{
  "type": "Feature",
  "properties": {
    "iso:country":"US",
    "sg:address":"8766 M 50",
    "sg:city":"Onsted",
    "sg:classifiers":[
        {
            "category":"Organizations",
            "subcategory":"Religious Organization",
            "type":"Services"
        }
    ],
    "sg:phone":"+1 517 467 7087",
    "sg:postcode":"49265",
    "sg:province":"MI",
    "wof:name":"Souls Harbor",
    "wof:placetype":"venue"
},
  "geometry": {"coordinates":[-84.16576999999999,42.031051],"type":"Point"}
}