{
  "type": "Feature",
  "properties": {
    "iso:country":"US",
    "sg:address":"10301 Mount Hope Rd",
    "sg:city":"Munith",
    "sg:classifiers":[
        {
            "category":"Building & Trades",
            "subcategory":"Landscaping Services",
            "type":"Services"
        }
    ],
    "sg:phone":"+1 517 596 2405",
    "sg:postcode":"49259",
    "sg:province":"MI",
    "sg:tags":[
        "landscape",
        "contractor"
    ],
    "wof:name":"Prentice Landscape",
    "wof:placetype":"venue"
},
  "geometry": {"coordinates":[-84.20511,42.382618],"type":"Point"}
}