{
  "type": "Feature",
  "properties": {
    "iso:country":"US",
    "sg:address":"120 N Sheldon St",
    "sg:city":"Charlotte",
    "sg:classifiers":[
        {
            "category":"Organizations",
            "subcategory":"Religious Organization",
            "type":"Services"
        }
    ],
    "sg:phone":"+1 517 543 3953",
    "sg:postcode":"48813",
    "sg:province":"MI",
    "sg:tags":[
        "church"
    ],
    "wof:name":"Chaplain Outreach Ministries",
    "wof:placetype":"venue"
},
  "geometry": {"coordinates":[-84.838426,42.564737],"type":"Point"}
}