{
  "type": "Feature",
  "properties": {
    "iso:country":"US",
    "sg:address":"16940 Joy Rd",
    "sg:city":"Detroit",
    "sg:classifiers":[
        {
            "category":"Retail",
            "subcategory":"Laundry & Dry Cleaning",
            "type":"Services"
        }
    ],
    "sg:phone":"+1 313 272 0022",
    "sg:postcode":"48228",
    "sg:province":"MI",
    "sg:website":"www.giovannicleaners.com",
    "wof:name":"Giovanni Cleaners",
    "wof:placetype":"venue"
},
  "geometry": {"coordinates":[-83.212504,42.358042],"type":"Point"}
}