{
  "type": "Feature",
  "properties": {
    "iso:country":"US",
    "sg:address":"9311 104th St",
    "sg:city":"Howard City",
    "sg:classifiers":[
        {
            "category":"Farming",
            "subcategory":"Farm & Veterinary Services",
            "type":"Manufacturing & Wholesale Goods"
        }
    ],
    "sg:phone":"+1 231 937 5015",
    "sg:postcode":"49329",
    "sg:province":"MI",
    "sg:tags":[
        "harvesting",
        "crop",
        "general"
    ],
    "wof:name":"Kim Hackbardt",
    "wof:placetype":"venue"
},
  "geometry": {"coordinates":[-85.57090599999999,43.366865],"type":"Point"}
}