{
  "type": "Feature",
  "properties": {
    "iso:country":"US",
    "sg:address":"10790 Holton-Duck Lake Rd",
    "sg:city":"Holton",
    "sg:phone":"+1 231 821 2903",
    "sg:postcode":"49425",
    "sg:province":"MI",
    "sg:tags":[
        "farm",
        "field",
        "corn",
        "crop"
    ],
    "wof:name":"Lemieux Art",
    "wof:placetype":"venue"
},
  "geometry": {"coordinates":[-86.079182,43.452453],"type":"Point"}
}