{
  "type": "Feature",
  "properties": {
    "iso:country":"US",
    "sg:address":"159 S River Ave",
    "sg:city":"Holland",
    "sg:classifiers":[
        {
            "category":"Social Services",
            "type":"Services"
        }
    ],
    "sg:phone":"+1 616 392 1479",
    "sg:postcode":"49423",
    "sg:province":"MI",
    "sg:tags":[
        "youth",
        "organization",
        "center"
    ],
    "wof:name":"Greater Holland Youth",
    "wof:placetype":"venue"
},
  "geometry": {"coordinates":[-86.10892800000001,42.791524],"type":"Point"}
}