{
  "type": "Feature",
  "properties": {
    "iso:country":"US",
    "sg:address":"31700 Middlebelt Rd",
    "sg:city":"Farmington Hills",
    "sg:classifiers":[
        {
            "category":"Building & Trades",
            "subcategory":"Cleaning & Sanitation",
            "type":"Services"
        }
    ],
    "sg:phone":"+1 248 851 9246",
    "sg:postcode":"48334",
    "sg:province":"MI",
    "sg:tags":[
        "property",
        "maintenance"
    ],
    "wof:name":"Etkin Management Svc",
    "wof:placetype":"venue"
},
  "geometry": {"coordinates":[-83.340037,42.520068],"type":"Point"}
}