{
  "type": "Feature",
  "properties": {
    "iso:country":"US",
    "sg:address":"1492 S Sheldon Rd",
    "sg:city":"Plymouth",
    "sg:classifiers":[
        {
            "category":"Personal",
            "subcategory":"Tanning Parlor",
            "type":"Services"
        }
    ],
    "sg:phone":"+1 734 459 4001",
    "sg:postcode":"48170",
    "sg:province":"MI",
    "wof:name":"American Beauty Tanning and Nails",
    "wof:placetype":"venue"
},
  "geometry": {"coordinates":[-83.474602,42.360199],"type":"Point"}
}