{
  "type": "Feature",
  "properties": {
    "iso:country":"US",
    "sg:address":"411 E 3rd St",
    "sg:city":"Monroe",
    "sg:classifiers":[
        {
            "category":"Real Estate",
            "subcategory":"Real Estate Operator",
            "type":"Services"
        }
    ],
    "sg:phone":"+1 734 241 1934",
    "sg:postcode":"48161",
    "sg:province":"MI",
    "sg:tags":[
        "property",
        "lessor"
    ],
    "wof:name":"Cardinal Rental Properties",
    "wof:placetype":"venue"
},
  "geometry": {"coordinates":[-83.394637,41.911624],"type":"Point"}
}