{
  "type": "Feature",
  "properties": {
    "iso:country":"US",
    "sg:address":"45523 Addington Ln",
    "sg:city":"Novi",
    "sg:classifiers":[
        {
            "category":"Building & Trades",
            "subcategory":"Landscaping Services",
            "type":"Services"
        }
    ],
    "sg:phone":"+1 248 305 7200",
    "sg:postcode":"48374",
    "sg:province":"MI",
    "sg:tags":[
        "landscape",
        "contractor"
    ],
    "wof:name":"B T Lang Co",
    "wof:placetype":"venue"
},
  "geometry": {"coordinates":[-83.49780699999999,42.460865],"type":"Point"}
}