{
  "type": "Feature",
  "properties": {
    "iso:country":"US",
    "sg:address":"2569 Curdy Rd",
    "sg:city":"Howell",
    "sg:classifiers":[
        {
            "category":"Professional",
            "subcategory":"Computer Services",
            "type":"Services"
        }
    ],
    "sg:phone":"+1 517 861 9363",
    "sg:postcode":"48855",
    "sg:province":"MI",
    "sg:tags":[
        "internet"
    ],
    "wof:name":"Datasure LC",
    "wof:placetype":"venue"
},
  "geometry": {"coordinates":[-83.901556,42.658947],"type":"Point"}
}