{
  "type": "Feature",
  "properties": {
    "iso:country":"US",
    "sg:address":"12242 Wilfred St",
    "sg:city":"Detroit",
    "sg:classifiers":[
        {
            "category":"Organizations",
            "subcategory":"Religious Organization",
            "type":"Services"
        }
    ],
    "sg:phone":"+1 313 371 1950",
    "sg:postcode":"48213",
    "sg:province":"MI",
    "wof:name":"I AM Temple of God",
    "wof:placetype":"venue"
},
  "geometry": {"coordinates":[-82.987184,42.41345],"type":"Point"}
}