{
  "type": "Feature",
  "properties": {
    "iso:country":"US",
    "sg:address":"G 5430 Saginaw St S",
    "sg:city":"Grand Blanc",
    "sg:classifiers":[
        {
            "category":"Health Services",
            "subcategory":"Health Practitioner",
            "type":"Services"
        }
    ],
    "sg:phone":"+1 810 694 1037",
    "sg:postcode":"48439",
    "sg:province":"MI",
    "sg:tags":[
        "therapy",
        "physical"
    ],
    "sg:website":"www.hopeineverystorm.com",
    "wof:name":"Active Physical Therapy & Wellness",
    "wof:placetype":"venue"
},
  "geometry": {"coordinates":[-83.65729899999999,42.950728],"type":"Point"}
}