{
  "type": "Feature",
  "properties": {
    "iso:country":"US",
    "sg:address":"1127 Clear Lake Ave",
    "sg:city":"Battle Creek",
    "sg:classifiers":[
        {
            "category":"Organizations",
            "subcategory":"Religious Organization",
            "type":"Services"
        }
    ],
    "sg:phone":"+1 269 963 6907",
    "sg:postcode":"49014",
    "sg:province":"MI",
    "wof:name":"Shepherds Embrace",
    "wof:placetype":"venue"
},
  "geometry": {"coordinates":[-85.093262,42.386718],"type":"Point"}
}