{
  "type": "Feature",
  "properties": {
    "iso:country":"US",
    "sg:address":"5580 E 12 Mile Rd",
    "sg:city":"Warren",
    "sg:classifiers":[
        {
            "category":"Education",
            "subcategory":"Vocational School",
            "type":"Public Place"
        }
    ],
    "sg:phone":"+1 586 751 4000",
    "sg:postcode":"48092",
    "sg:province":"MI",
    "sg:tags":[
        "cosmetology"
    ],
    "wof:name":"Mr Bela's School of Cosmetology",
    "wof:placetype":"venue"
},
  "geometry": {"coordinates":[-83.05035599999999,42.505933],"type":"Point"}
}