{
  "type": "Feature",
  "properties": {
    "iso:country":"US",
    "sg:address":"2656 Pointe Tremble Rd",
    "sg:city":"Algonac",
    "sg:classifiers":[
        {
            "category":"Restaurant",
            "type":"Food & Drink"
        }
    ],
    "sg:menulink":"http://www.allmenus.com/mi/clay/146273-subway/menu/",
    "sg:phone":"+1 810 794 9470",
    "sg:postcode":"48001",
    "sg:province":"MI",
    "sg:tags":[
        "american",
        "sandwich"
    ],
    "wof:name":"Subway",
    "wof:placetype":"venue"
},
  "geometry": {"coordinates":[-82.568405,42.62107],"type":"Point"}
}