{
  "type": "Feature",
  "properties": {
    "iso:country":"US",
    "sg:address":"30055 Northwestern Hwy",
    "sg:city":"Farmington Hills",
    "sg:classifiers":[
        {
            "category":"Health Services",
            "subcategory":"Doctor",
            "type":"Services"
        }
    ],
    "sg:phone":"+1 248 865 3750",
    "sg:postcode":"48334",
    "sg:province":"MI",
    "sg:tags":[
        "physician",
        "surgeon"
    ],
    "wof:name":"Birmingham Menopause Institute",
    "wof:placetype":"venue"
},
  "geometry": {"coordinates":[-83.320697,42.507863],"type":"Point"}
}