{
  "type": "Feature",
  "properties": {
    "iso:country":"US",
    "sg:address":"24105 Orchard Lake Rd",
    "sg:city":"Farmington",
    "sg:classifiers":[
        {
            "category":"Recreation",
            "type":"Entertainment"
        }
    ],
    "sg:phone":"+1 248 474 0700",
    "sg:postcode":"48336",
    "sg:province":"MI",
    "sg:tags":[
        "trainer",
        "martial art",
        "instruction"
    ],
    "sg:website":"www.farmingtonmartialarts.com",
    "wof:name":"Farmington Martial Arts",
    "wof:placetype":"venue"
},
  "geometry": {"coordinates":[-83.3573,42.469601],"type":"Point"}
}