{
  "type": "Feature",
  "properties": {
    "iso:country":"US",
    "sg:address":"39303 Country Club Dr",
    "sg:city":"Farmington Hills",
    "sg:classifiers":[
        {
            "category":"Education",
            "subcategory":"Special Training",
            "type":"Public Place"
        }
    ],
    "sg:phone":"+1 248 848 1896",
    "sg:postcode":"48331",
    "sg:province":"MI",
    "sg:tags":[
        "center"
    ],
    "wof:name":"American Credit Edu & Conslnt",
    "wof:placetype":"venue"
},
  "geometry": {"coordinates":[-83.428946,42.494459],"type":"Point"}
}