{
  "type": "Feature",
  "properties": {
    "iso:country":"US",
    "sg:address":"133 S Main St",
    "sg:city":"Ovid",
    "sg:classifiers":[
        {
            "category":"Personal",
            "subcategory":"Beauty Salon",
            "type":"Services"
        }
    ],
    "sg:phone":"+1 989 834 2587",
    "sg:postcode":"48866",
    "sg:province":"MI",
    "wof:name":"Corner Carousel",
    "wof:placetype":"venue"
},
  "geometry": {"coordinates":[-84.371634,43.005174],"type":"Point"}
}