{
  "type": "Feature",
  "properties": {
    "iso:country":"US",
    "sg:address":"18560 Outer Dr",
    "sg:city":"Dearborn",
    "sg:classifiers":[
        {
            "category":"Professional",
            "subcategory":"Lawyer & Legal Services",
            "type":"Services"
        }
    ],
    "sg:phone":"+1 313 274 7377",
    "sg:postcode":"48128",
    "sg:province":"MI",
    "wof:name":"Stearns James R Atty",
    "wof:placetype":"venue"
},
  "geometry": {"coordinates":[-83.256699,42.319],"type":"Point"}
}