{
  "type": "Feature",
  "properties": {
    "iso:country":"US",
    "sg:address":"4307 S Commerce Rd",
    "sg:city":"Commerce Twp",
    "sg:classifiers":[
        {
            "category":"Building & Trades",
            "subcategory":"Plumbing",
            "type":"Services"
        }
    ],
    "sg:phone":"+1 248 363 4868",
    "sg:postcode":"48382",
    "sg:province":"MI",
    "sg:tags":[
        "heating",
        "contractor"
    ],
    "sg:website":"www.mathesonheating.com",
    "wof:name":"Matheson Heating & AC INC",
    "wof:placetype":"venue"
},
  "geometry": {"coordinates":[-83.48090000000001,42.586144],"type":"Point"}
}