{
  "type": "Feature",
  "properties": {
    "iso:country":"US",
    "sg:address":"660 Commerce Dr",
    "sg:city":"Reed City",
    "sg:classifiers":[
        {
            "category":"Professional",
            "type":"Services"
        }
    ],
    "sg:phone":"+1 231 832 5668",
    "sg:postcode":"49677",
    "sg:province":"MI",
    "sg:tags":[
        "establishment"
    ],
    "wof:name":"Banc Inc",
    "wof:placetype":"venue"
},
  "geometry": {"coordinates":[-85.49548299999999,43.873189],"type":"Point"}
}