{
  "type": "Feature",
  "properties": {
    "iso:country":"US",
    "sg:address":"4396 Bender Ct",
    "sg:city":"Troy",
    "sg:classifiers":[
        {
            "category":"Real Estate",
            "subcategory":"Real Estate Agent",
            "type":"Services"
        }
    ],
    "sg:phone":"+1 248 641 0641",
    "sg:postcode":"48098",
    "sg:province":"MI",
    "wof:name":"Billy H Burtt",
    "wof:placetype":"venue"
},
  "geometry": {"coordinates":[-83.174373,42.582806],"type":"Point"}
}