{
  "type": "Feature",
  "properties": {
    "iso:country":"US",
    "sg:address":"28541 Gratiot Ave",
    "sg:city":"Roseville",
    "sg:classifiers":[
        {
            "category":"Restaurant",
            "type":"Food & Drink"
        }
    ],
    "sg:menulink":"http://www.allmenus.com/mi/roseville/44974-canton-inn/menu/",
    "sg:phone":"+1 586 779 5111",
    "sg:postcode":"48066",
    "sg:province":"MI",
    "sg:tags":[
        "asian",
        "chinese"
    ],
    "wof:name":"Canton Inn",
    "wof:placetype":"venue"
},
  "geometry": {"coordinates":[-82.930954,42.506311],"type":"Point"}
}