{
  "type": "Feature",
  "properties": {
    "iso:country":"US",
    "sg:address":"33520 Crestwell Dr",
    "sg:city":"Sterling Heights",
    "sg:classifiers":[
        {
            "category":"Professional",
            "subcategory":"Business Services",
            "type":"Services"
        }
    ],
    "sg:phone":"+1 586 268 2812",
    "sg:postcode":"48310",
    "sg:province":"MI",
    "wof:name":"Stanley Industrial Sales Inc",
    "wof:placetype":"venue"
},
  "geometry": {"coordinates":[-83.077641,42.537593],"type":"Point"}
}