{
  "type": "Feature",
  "properties": {
    "iso:country":"US",
    "sg:address":"8744 W McNichols Rd",
    "sg:city":"Detroit",
    "sg:classifiers":[
        {
            "category":"Personal",
            "subcategory":"Beauty Salon",
            "type":"Services"
        }
    ],
    "sg:phone":"+1 313 864 7901",
    "sg:postcode":"48221",
    "sg:province":"MI",
    "sg:tags":[
        "shop"
    ],
    "wof:name":"Six Avenue Beauty Salon",
    "wof:placetype":"venue"
},
  "geometry": {"coordinates":[-83.157791,42.417055],"type":"Point"}
}