{
  "type": "Feature",
  "properties": {
    "iso:country":"US",
    "sg:address":"9400 Birch Run Rd",
    "sg:city":"Birch Run",
    "sg:classifiers":[
        {
            "category":"Autos & Motor Vehicles",
            "subcategory":"Auto Supplies",
            "type":"Retail Goods"
        }
    ],
    "sg:phone":"+1 989 624 9973",
    "sg:postcode":"48415",
    "sg:province":"MI",
    "sg:tags":[
        "tire"
    ],
    "wof:name":"Totten Tire Ctr",
    "wof:placetype":"venue"
},
  "geometry": {"coordinates":[-83.765512,43.250161],"type":"Point"}
}