{
  "type": "Feature",
  "properties": {
    "iso:country":"US",
    "sg:address":"3880 Red Arrow Hwy",
    "sg:city":"Benton Harbor",
    "sg:classifiers":[
        {
            "category":"Government",
            "subcategory":"Office",
            "type":"Public Place"
        }
    ],
    "sg:phone":"+1 269 849 1165",
    "sg:postcode":"49022",
    "sg:province":"MI",
    "sg:tags":[
        "state",
        "program",
        "transportation"
    ],
    "wof:name":"Transportation Michigan Dept",
    "wof:placetype":"venue"
},
  "geometry": {"coordinates":[-86.364171,42.150895],"type":"Point"}
}