{
  "type": "Feature",
  "properties": {
    "iso:country":"US",
    "sg:address":"33765 Groesbeck Hwy",
    "sg:city":"Fraser",
    "sg:classifiers":[
        {
            "category":"Home & Garden",
            "subcategory":"Hardware",
            "type":"Retail Goods"
        }
    ],
    "sg:phone":"+1 586 285 1329",
    "sg:postcode":"48035",
    "sg:province":"MI",
    "sg:tags":[
        "tool",
        "used"
    ],
    "wof:name":"J Tech Tool & Gage Inc",
    "wof:placetype":"venue"
},
  "geometry": {"coordinates":[-82.931551,42.543017],"type":"Point"}
}