{
  "type": "Feature",
  "properties": {
    "iso:country":"US",
    "sg:address":"3285 Martin Rd",
    "sg:city":"Commerce Twp",
    "sg:classifiers":[
        {
            "category":"Manufacturing",
            "subcategory":"Tools & Machinery",
            "type":"Manufacturing & Wholesale Goods"
        }
    ],
    "sg:phone":"+1 248 669 1130",
    "sg:postcode":"48390",
    "sg:province":"MI",
    "sg:tags":[
        "instrument",
        "optical",
        "lense"
    ],
    "sg:website":"www.vcmich.com",
    "wof:name":"Vision Craft Inc",
    "wof:placetype":"venue"
},
  "geometry": {"coordinates":[-83.449726,42.567108],"type":"Point"}
}