{
  "type": "Feature",
  "properties": {
    "iso:country":"US",
    "sg:address":"12129 23 Mile Rd",
    "sg:city":"Utica",
    "sg:classifiers":[
        {
            "category":"Coffee & Tea",
            "type":"Food & Drink"
        }
    ],
    "sg:menulink":"http://www.allmenus.com/mi/shelby/125690-starbucks-coffee/menu/",
    "sg:phone":"+1 586 726 5461",
    "sg:postcode":"48315",
    "sg:province":"MI",
    "sg:tags":[
        "american"
    ],
    "wof:name":"Starbucks Coffee",
    "wof:placetype":"venue"
},
  "geometry": {"coordinates":[-83.009258,42.669767],"type":"Point"}
}