{
  "type": "Feature",
  "properties": {
    "iso:country":"US",
    "sg:address":"1801 Arborview Blvd",
    "sg:city":"Ann Arbor",
    "sg:classifiers":[
        {
            "category":"Organizations",
            "subcategory":"Membership Organization",
            "type":"Services"
        }
    ],
    "sg:phone":"+1 734 668 7348",
    "sg:postcode":"48103",
    "sg:province":"MI",
    "wof:name":"Touchstone Co Housing",
    "wof:placetype":"venue"
},
  "geometry": {"coordinates":[-83.770979,42.286038],"type":"Point"}
}