{
  "type": "Feature",
  "properties": {
    "iso:country":"US",
    "sg:address":"24432 Crocker Blvd",
    "sg:city":"Clinton Twp",
    "sg:classifiers":[
        {
            "category":"Manufacturing",
            "subcategory":"Tools & Machinery",
            "type":"Manufacturing & Wholesale Goods"
        }
    ],
    "sg:phone":"+1 586 463 3600",
    "sg:postcode":"48036",
    "sg:province":"MI",
    "sg:tags":[
        "orthopedic"
    ],
    "wof:name":"Mt Clemens Orthopaedic Appls",
    "wof:placetype":"venue"
},
  "geometry": {"coordinates":[-82.864576,42.584455],"type":"Point"}
}