{
  "type": "Feature",
  "properties": {
    "iso:country":"US",
    "sg:address":"9611 Dundee St",
    "sg:city":"Detroit",
    "sg:classifiers":[
        {
            "category":"Real Estate",
            "subcategory":"Real Estate Services",
            "type":"Services"
        }
    ],
    "sg:phone":"+1 313 834 6586",
    "sg:postcode":"48204",
    "sg:province":"MI",
    "sg:tags":[
        "management",
        "property"
    ],
    "wof:name":"Okuns Venture Inc",
    "wof:placetype":"venue"
},
  "geometry": {"coordinates":[-83.135002,42.367401],"type":"Point"}
}