{
  "type": "Feature",
  "properties": {
    "iso:country":"US",
    "sg:address":"8695 State Hwy 119",
    "sg:city":"Harbor Springs",
    "sg:classifiers":[
        {
            "category":"Building & Trades",
            "subcategory":"Landscaping Services",
            "type":"Services"
        }
    ],
    "sg:phone":"+1 231 439 9000",
    "sg:postcode":"49740",
    "sg:province":"MI",
    "sg:tags":[
        "landscape",
        "contractor"
    ],
    "wof:name":"Polly's Planting & Plucking",
    "wof:placetype":"venue"
},
  "geometry": {"coordinates":[-84.904662,45.426701],"type":"Point"}
}