{
  "type": "Feature",
  "properties": {
    "iso:country":"US",
    "sg:address":"1010 S Main St",
    "sg:city":"Cheboygan",
    "sg:classifiers":[
        {
            "category":"Professional",
            "subcategory":"Lawyer & Legal Services",
            "type":"Services"
        }
    ],
    "sg:phone":"+1 231 627 2721",
    "sg:postcode":"49721",
    "sg:province":"MI",
    "sg:tags":[
        "attorney"
    ],
    "wof:name":"Bankruptcy Clinic Of Cheboygan",
    "wof:placetype":"venue"
},
  "geometry": {"coordinates":[-84.478459,45.628019],"type":"Point"}
}