{
  "type": "Feature",
  "properties": {
    "iso:country":"US",
    "sg:address":"69796 S River Rd",
    "sg:city":"White Pigeon",
    "sg:classifiers":[
        {
            "category":"Wholesale",
            "subcategory":"Durable Goods & Equipment",
            "type":"Manufacturing & Wholesale Goods"
        }
    ],
    "sg:phone":"+1 269 483 2496",
    "sg:postcode":"49099",
    "sg:province":"MI",
    "wof:name":"River Stone",
    "wof:placetype":"venue"
},
  "geometry": {"coordinates":[-85.78890199999999,41.778617],"type":"Point"}
}