{
  "type": "Feature",
  "properties": {
    "iso:country":"US",
    "sg:address":"704 E Lakewood Blvd",
    "sg:city":"Holland",
    "sg:classifiers":[
        {
            "category":"Autos & Motor Vehicles",
            "subcategory":"Automobile Sales",
            "type":"Retail Goods"
        }
    ],
    "sg:phone":"+1 616 396 0001",
    "sg:postcode":"49424",
    "sg:province":"MI",
    "sg:tags":[
        "car",
        "dealer"
    ],
    "sg:website":"www.europeanautohaus.com",
    "wof:name":"European Autohaus",
    "wof:placetype":"venue"
},
  "geometry": {"coordinates":[-86.07953500000001,42.804743],"type":"Point"}
}