{
  "type": "Feature",
  "properties": {
    "iso:country":"US",
    "sg:address":"1087 US Hwy 31",
    "sg:city":"Petoskey",
    "sg:classifiers":[
        {
            "category":"Food & Beverages",
            "subcategory":"Groceries & Convenience Stores",
            "type":"Retail Goods"
        }
    ],
    "sg:phone":"+1 231 347 6064",
    "sg:postcode":"49770",
    "sg:province":"MI",
    "wof:name":"Bay View EZ Mart",
    "wof:placetype":"venue"
},
  "geometry": {"coordinates":[-84.920861,45.388579],"type":"Point"}
}