{
  "type": "Feature",
  "properties": {
    "iso:country":"US",
    "sg:address":"24675 Telegraph Rd",
    "sg:city":"Flat Rock",
    "sg:classifiers":[
        {
            "category":"Building & Trades",
            "subcategory":"Construction",
            "type":"Services"
        }
    ],
    "sg:phone":"+1 734 782 3911",
    "sg:postcode":"48134",
    "sg:province":"MI",
    "sg:tags":[
        "contractor"
    ],
    "wof:name":"A To Z Manufacturing Corp",
    "wof:placetype":"venue"
},
  "geometry": {"coordinates":[-83.275398,42.124001],"type":"Point"}
}