{
  "type": "Feature",
  "properties": {
    "iso:country":"US",
    "sg:address":"6410 Alpine Ave NW",
    "sg:city":"Comstock Park",
    "sg:classifiers":[
        {
            "category":"Health Services",
            "subcategory":"Chiropractor",
            "type":"Services"
        }
    ],
    "sg:phone":"+1 616 785 7970",
    "sg:postcode":"49321",
    "sg:province":"MI",
    "wof:name":"Chiropractic Wellness Center",
    "wof:placetype":"venue"
},
  "geometry": {"coordinates":[-85.689882,43.078623],"type":"Point"}
}