{
  "type": "Feature",
  "properties": {
    "iso:country":"US",
    "sg:address":"216 Park Ave",
    "sg:city":"Charlevoix",
    "sg:classifiers":[
        {
            "category":"Building & Trades",
            "subcategory":"Construction",
            "type":"Services"
        }
    ],
    "sg:phone":"+1 231 547 1941",
    "sg:postcode":"49720",
    "sg:province":"MI",
    "sg:tags":[
        "house"
    ],
    "wof:name":"W L Decker Contractor",
    "wof:placetype":"venue"
},
  "geometry": {"coordinates":[-85.261062,45.318079],"type":"Point"}
}