{
  "type": "Feature",
  "properties": {
    "iso:country":"US",
    "sg:address":"5599 Amy School Rd",
    "sg:city":"Howard City",
    "sg:classifiers":[
        {
            "category":"Manufacturing",
            "subcategory":"Rubber & Plastics",
            "type":"Manufacturing & Wholesale Goods"
        }
    ],
    "sg:phone":"+1 231 937 6500",
    "sg:postcode":"49329",
    "sg:province":"MI",
    "wof:name":"Universal Products",
    "wof:placetype":"venue"
},
  "geometry": {"coordinates":[-85.502301,43.379284],"type":"Point"}
}