{
  "type": "Feature",
  "properties": {
    "iso:country":"US",
    "sg:address":"4431 N Chester Rd",
    "sg:city":"Charlotte",
    "sg:classifiers":[
        {
            "category":"Professional",
            "subcategory":"Business Services",
            "type":"Services"
        }
    ],
    "sg:phone":"+1 517 543 7113",
    "sg:postcode":"48813",
    "sg:province":"MI",
    "sg:tags":[
        "auctioneer"
    ],
    "wof:name":"Yutzy's Action Svc",
    "wof:placetype":"venue"
},
  "geometry": {"coordinates":[-84.91482999999999,42.626304],"type":"Point"}
}