{
  "type": "Feature",
  "properties": {
    "iso:country":"US",
    "sg:address":"4337 Ravinewood Dr",
    "sg:city":"Commerce Township",
    "sg:classifiers":[
        {
            "category":"Health Services",
            "subcategory":"Health Practitioner",
            "type":"Services"
        }
    ],
    "sg:phone":"+1 248 684 5080",
    "sg:postcode":"48382",
    "sg:province":"MI",
    "wof:name":"Robert J Kantor",
    "wof:placetype":"venue"
},
  "geometry": {"coordinates":[-83.547719,42.584896],"type":"Point"}
}