{
  "type": "Feature",
  "properties": {
    "iso:country":"US",
    "sg:address":"1224 S Lapeer Rd",
    "sg:city":"Lake Orion",
    "sg:classifiers":[
        {
            "category":"Sports & Exercise",
            "subcategory":"Gym",
            "type":"Entertainment"
        }
    ],
    "sg:phone":"+1 248 814 1030",
    "sg:postcode":"48360",
    "sg:province":"MI",
    "sg:tags":[
        "club",
        "health",
        "studio",
        "gymnasium"
    ],
    "wof:name":"Gym",
    "wof:placetype":"venue"
},
  "geometry": {"coordinates":[-83.24560200000001,42.757904],"type":"Point"}
}