{
  "type": "Feature",
  "properties": {
    "iso:country":"US",
    "sg:address":"577 E Shevlin Ave",
    "sg:city":"Hazel Park",
    "sg:classifiers":[
        {
            "category":"Professional",
            "subcategory":"Computer Services",
            "type":"Services"
        }
    ],
    "sg:phone":"+1 248 544 8863",
    "sg:postcode":"48030",
    "sg:province":"MI",
    "sg:tags":[
        "related"
    ],
    "wof:name":"Binary Digital Logic Inc",
    "wof:placetype":"venue"
},
  "geometry": {"coordinates":[-83.09783,42.473305],"type":"Point"}
}