{
  "type": "Feature",
  "properties": {
    "iso:country":"US",
    "sg:address":"14811 Plymouth Rd",
    "sg:city":"Detroit",
    "sg:classifiers":[
        {
            "category":"Education",
            "subcategory":"University",
            "type":"Public Place"
        }
    ],
    "sg:phone":"+1 313 273 5667",
    "sg:postcode":"48227",
    "sg:province":"MI",
    "sg:tags":[
        "college"
    ],
    "wof:name":"Jon's International Cosmotology Academy",
    "wof:placetype":"venue"
},
  "geometry": {"coordinates":[-83.190016,42.37264],"type":"Point"}
}