{
  "type": "Feature",
  "properties": {
    "iso:country":"US",
    "sg:address":"28828 Telegraph Rd",
    "sg:city":"Flat Rock",
    "sg:classifiers":[
        {
            "category":"Restaurant",
            "type":"Food & Drink"
        }
    ],
    "sg:phone":"+1 734 782 1401",
    "sg:postcode":"48134",
    "sg:province":"MI",
    "wof:name":"Michaels On the River",
    "wof:placetype":"venue"
},
  "geometry": {"coordinates":[-83.29409800000001,42.096001],"type":"Point"}
}