{
  "type": "Feature",
  "properties": {
    "iso:country":"US",
    "sg:address":"821 W Washington Ave",
    "sg:city":"Alpena",
    "sg:classifiers":[
        {
            "category":"Retail",
            "subcategory":"Auto Repair",
            "type":"Services"
        }
    ],
    "sg:phone":"+1 989 356 0335",
    "sg:postcode":"49707",
    "sg:province":"MI",
    "sg:tags":[
        "general"
    ],
    "wof:name":"Graham Motor Rebuilding",
    "wof:placetype":"venue"
},
  "geometry": {"coordinates":[-83.451797,45.061774],"type":"Point"}
}