{
  "type": "Feature",
  "properties": {
    "iso:country":"US",
    "sg:address":"2335 Walter Ave",
    "sg:city":"Warren",
    "sg:classifiers":[
        {
            "category":"Professional",
            "subcategory":"Computer Services",
            "type":"Services"
        }
    ],
    "sg:phone":"+1 586 558 8773",
    "sg:postcode":"48092",
    "sg:province":"MI",
    "sg:tags":[
        "datum"
    ],
    "wof:name":"L Enterprise",
    "wof:placetype":"venue"
},
  "geometry": {"coordinates":[-83.07984399999999,42.511836],"type":"Point"}
}