{
  "type": "Feature",
  "properties": {
    "iso:country":"US",
    "sg:address":"1750 Indian Garden Ln",
    "sg:city":"Milford",
    "sg:classifiers":[
        {
            "category":"Home & Garden",
            "subcategory":"Furniture",
            "type":"Retail Goods"
        }
    ],
    "sg:phone":"+1 248 685 7896",
    "sg:postcode":"48380",
    "sg:province":"MI",
    "sg:tags":[
        "equipment",
        "kitchen",
        "cabinet"
    ],
    "wof:name":"Redford Building Specialties",
    "wof:placetype":"venue"
},
  "geometry": {"coordinates":[-83.626294,42.605162],"type":"Point"}
}