{
  "type": "Feature",
  "properties": {
    "iso:country":"US",
    "sg:address":"240 E Church Ave",
    "sg:city":"Reed City",
    "sg:classifiers":[
        {
            "category":"Social Services",
            "subcategory":"Job Training",
            "type":"Services"
        }
    ],
    "sg:phone":"+1 231 832 3131",
    "sg:postcode":"49677",
    "sg:province":"MI",
    "sg:tags":[
        "employment"
    ],
    "wof:name":"Michigan Works West Centl Inc",
    "wof:placetype":"venue"
},
  "geometry": {"coordinates":[-85.507575,43.869623],"type":"Point"}
}