{
  "type": "Feature",
  "properties": {
    "iso:country":"US",
    "sg:address":"37341 Emery St",
    "sg:city":"Clinton Twp",
    "sg:classifiers":[
        {
            "category":"Building & Trades",
            "subcategory":"Construction",
            "type":"Services"
        }
    ],
    "sg:phone":"+1 586 465 7049",
    "sg:postcode":"48036",
    "sg:province":"MI",
    "sg:tags":[
        "carpenter"
    ],
    "wof:name":"Di Trapani Building Co",
    "wof:placetype":"venue"
},
  "geometry": {"coordinates":[-82.907087,42.573392],"type":"Point"}
}