{
  "type": "Feature",
  "properties": {
    "iso:country":"US",
    "sg:address":"2855 Coolidge Hwy",
    "sg:city":"Troy",
    "sg:classifiers":[
        {
            "category":"Wholesale",
            "subcategory":"Drugs",
            "type":"Manufacturing & Wholesale Goods"
        }
    ],
    "sg:phone":"+1 248 280 9394",
    "sg:postcode":"48084",
    "sg:province":"MI",
    "sg:tags":[
        "food",
        "supplement",
        "vitamin"
    ],
    "wof:name":"Rexall Sundown Inc",
    "wof:placetype":"venue"
},
  "geometry": {"coordinates":[-83.18690100000001,42.559359],"type":"Point"}
}