{
  "type": "Feature",
  "properties": {
    "iso:country":"US",
    "sg:address":"417 Brookfield St",
    "sg:city":"Niles",
    "sg:classifiers":[
        {
            "category":"Bars & Pubs",
            "type":"Food & Drink"
        }
    ],
    "sg:phone":"+1 269 683 1888",
    "sg:postcode":"49120",
    "sg:province":"MI",
    "wof:name":"Tavern Inc",
    "wof:placetype":"venue"
},
  "geometry": {"coordinates":[-86.262816,41.823543],"type":"Point"}
}