{
  "type": "Feature",
  "properties": {
    "iso:country":"US",
    "sg:address":"200 W Big Beaver Rd",
    "sg:city":"Troy",
    "sg:classifiers":[
        {
            "category":"Travel",
            "subcategory":"Hotels & Motels",
            "type":"Entertainment"
        },
        {
            "category":"Restaurant",
            "type":"Food & Drink"
        }
    ],
    "sg:phone":"+1 248 680 9797",
    "sg:postcode":"48084",
    "sg:province":"MI",
    "sg:tags":[
        "lodging"
    ],
    "sg:website":"http://ad.doubleclick.net/clk;227431036;51131009;n?http://www.marriott.com/hotels/travel/DTTTT",
    "wof:name":"Detroit Marriott Troy",
    "wof:placetype":"venue"
},
  "geometry": {"coordinates":[-83.152199,42.562599],"type":"Point"}
}