{
  "type": "Feature",
  "properties": {
    "iso:country":"US",
    "sg:address":"1901 Packard Hwy",
    "sg:city":"Charlotte",
    "sg:classifiers":[
        {
            "category":"Manufacturing",
            "subcategory":"Retail Goods",
            "type":"Manufacturing & Wholesale Goods"
        }
    ],
    "sg:phone":"+1 517 543 5526",
    "sg:postcode":"48813",
    "sg:province":"MI",
    "sg:tags":[
        "lead",
        "mfg"
    ],
    "wof:name":"Technical Press Ltd",
    "wof:placetype":"venue"
},
  "geometry": {"coordinates":[-84.80013599999999,42.582114],"type":"Point"}
}