{
  "type": "Feature",
  "properties": {
    "iso:country":"US",
    "sg:address":"G-2333 S Center Rd",
    "sg:city":"Burton",
    "sg:classifiers":[
        {
            "category":"Personal",
            "subcategory":"Barber",
            "type":"Services"
        }
    ],
    "sg:phone":"+1 810 742 7430",
    "sg:postcode":"48509",
    "sg:province":"MI",
    "wof:name":"Meijer Inc",
    "wof:placetype":"venue"
},
  "geometry": {"coordinates":[-83.631687,42.993358],"type":"Point"}
}