{
  "type": "Feature",
  "properties": {
    "iso:country":"US",
    "sg:address":"899 E Chicago Rd",
    "sg:city":"Quincy",
    "sg:classifiers":[
        {
            "category":"Autos & Motor Vehicles",
            "subcategory":"Boat Sales",
            "type":"Retail Goods"
        }
    ],
    "sg:phone":"+1 517 639 3300",
    "sg:postcode":"49082",
    "sg:province":"MI",
    "sg:tags":[
        "sales"
    ],
    "wof:name":"Boaters Marine",
    "wof:placetype":"venue"
},
  "geometry": {"coordinates":[-84.90713700000001,41.940442],"type":"Point"}
}