{
  "type": "Feature",
  "properties": {
    "iso:country":"US",
    "sg:address":"2032 E 8 Mile Rd",
    "sg:city":"Detroit",
    "sg:classifiers":[
        {
            "category":"Professional",
            "subcategory":"Accounting & Tax Preparation",
            "type":"Services"
        }
    ],
    "sg:phone":"+1 313 893 4984",
    "sg:postcode":"48234",
    "sg:province":"MI",
    "sg:tags":[
        "return"
    ],
    "wof:name":"H & R Block",
    "wof:placetype":"venue"
},
  "geometry": {"coordinates":[-83.080173,42.446991],"type":"Point"}
}