{
  "type": "Feature",
  "properties": {
    "iso:country":"US",
    "sg:address":"7718 Burrstone Dr SE",
    "sg:city":"Caledonia",
    "sg:classifiers":[
        {
            "category":"Wholesale",
            "subcategory":"Office Equipment",
            "type":"Manufacturing & Wholesale Goods"
        }
    ],
    "sg:phone":"+1 616 891 8083",
    "sg:postcode":"49316",
    "sg:province":"MI",
    "sg:tags":[
        "scanning",
        "code",
        "bar"
    ],
    "wof:name":"Stonehill Solutions LLC",
    "wof:placetype":"venue"
},
  "geometry": {"coordinates":[-85.475002,42.832315],"type":"Point"}
}