{
  "type": "Feature",
  "properties": {
    "iso:country":"US",
    "sg:address":"108 Washington Sq S",
    "sg:city":"Lansing",
    "sg:classifiers":[
        {
            "category":"Restaurant",
            "type":"Food & Drink"
        }
    ],
    "sg:phone":"+1 517 485 1917",
    "sg:postcode":"48933",
    "sg:province":"MI",
    "sg:tags":[
        "eating"
    ],
    "wof:name":"Arbys",
    "wof:placetype":"venue"
},
  "geometry": {"coordinates":[-84.55233699999999,42.732723],"type":"Point"}
}