{
  "type": "Feature",
  "properties": {
    "iso:country":"US",
    "sg:address":"515 S Eton St",
    "sg:city":"Birmingham",
    "sg:classifiers":[
        {
            "category":"Personal",
            "subcategory":"Beauty Salon",
            "type":"Services"
        }
    ],
    "sg:phone":"+1 248 644 5144",
    "sg:postcode":"48009",
    "sg:province":"MI",
    "sg:tags":[
        "shop"
    ],
    "wof:name":"Salon 515",
    "wof:placetype":"venue"
},
  "geometry": {"coordinates":[-83.195843,42.54405],"type":"Point"}
}