{
  "type": "Feature",
  "properties": {
    "iso:country":"US",
    "sg:address":"14460 E 9 Mile Rd",
    "sg:city":"Warren",
    "sg:classifiers":[
        {
            "category":"Manufacturing",
            "subcategory":"Printing",
            "type":"Manufacturing & Wholesale Goods"
        }
    ],
    "sg:phone":"+1 586 774 0874",
    "sg:postcode":"48089",
    "sg:province":"MI",
    "sg:tags":[
        "printer"
    ],
    "wof:name":"C & H Printing",
    "wof:placetype":"venue"
},
  "geometry": {"coordinates":[-82.97221399999999,42.464282],"type":"Point"}
}