{
  "type": "Feature",
  "properties": {
    "iso:country":"US",
    "sg:address":"111 M 66 N",
    "sg:city":"Charlevoix",
    "sg:classifiers":[
        {
            "category":"Food & Beverages",
            "subcategory":"Groceries & Convenience Stores",
            "type":"Retail Goods"
        }
    ],
    "sg:phone":"+1 231 547 4131",
    "sg:postcode":"49720",
    "sg:province":"MI",
    "sg:tags":[
        "grocer"
    ],
    "wof:name":"Glen's Markets",
    "wof:placetype":"venue"
},
  "geometry": {"coordinates":[-85.16515800000001,45.20139],"type":"Point"}
}