{
  "type": "Feature",
  "properties": {
    "iso:country":"US",
    "sg:address":"475 Applejack Ct",
    "sg:city":"Sparta",
    "sg:classifiers":[
        {
            "category":"Manufacturing",
            "subcategory":"Tools & Machinery",
            "type":"Manufacturing & Wholesale Goods"
        }
    ],
    "sg:phone":"+1 616 887 8201",
    "sg:postcode":"49345",
    "sg:province":"MI",
    "sg:tags":[
        "equipment",
        "system",
        "automation"
    ],
    "sg:website":"www.andasi.com",
    "wof:name":"ANDERSEN-Asi",
    "wof:placetype":"venue"
},
  "geometry": {"coordinates":[-85.723519,43.157722],"type":"Point"}
}