{
  "type": "Feature",
  "properties": {
    "iso:country":"US",
    "sg:address":"2140 State Rd",
    "sg:city":"Hillsdale",
    "sg:classifiers":[
        {
            "category":"Utilities",
            "subcategory":"Sewage",
            "type":"Services"
        }
    ],
    "sg:phone":"+1 517 437 7510",
    "sg:postcode":"49242",
    "sg:province":"MI",
    "sg:tags":[
        "disposal",
        "system"
    ],
    "wof:name":"Lapew Sanitation Svc",
    "wof:placetype":"venue"
},
  "geometry": {"coordinates":[-84.606934,41.927367],"type":"Point"}
}