{
  "type": "Feature",
  "properties": {
    "iso:country":"US",
    "sg:address":"1701 Terminal Rd",
    "sg:city":"Niles",
    "sg:classifiers":[
        {
            "category":"Manufacturing",
            "subcategory":"Metals",
            "type":"Manufacturing & Wholesale Goods"
        }
    ],
    "sg:phone":"+1 269 683 1910",
    "sg:postcode":"49120",
    "sg:province":"MI",
    "sg:tags":[
        "tank"
    ],
    "sg:website":"www.nilesst.com",
    "wof:name":"Niles Steel Tank Co",
    "wof:placetype":"venue"
},
  "geometry": {"coordinates":[-86.229124,41.850168],"type":"Point"}
}