{
  "type": "Feature",
  "properties": {
    "iso:country":"US",
    "sg:address":"378 W Division St",
    "sg:city":"Ishpeming",
    "sg:classifiers":[
        {
            "category":"Autos & Motor Vehicles",
            "subcategory":"Fuel & Gas Station",
            "type":"Retail Goods"
        }
    ],
    "sg:phone":"+1 906 486 4733",
    "sg:postcode":"49849",
    "sg:province":"MI",
    "sg:tags":[
        "oil"
    ],
    "wof:name":"Express Convenience Ctr",
    "wof:placetype":"venue"
},
  "geometry": {"coordinates":[-87.67385,46.488774],"type":"Point"}
}