{
  "type": "Feature",
  "properties": {
    "iso:country":"US",
    "sg:address":"23 E Pearl St",
    "sg:city":"Coldwater",
    "sg:classifiers":[
        {
            "category":"Government",
            "subcategory":"Office",
            "type":"Public Place"
        }
    ],
    "sg:phone":"+1 517 279 4311",
    "sg:postcode":"49036",
    "sg:province":"MI",
    "wof:name":"Cooperative Extension Svc",
    "wof:placetype":"venue"
},
  "geometry": {"coordinates":[-85.000328,41.939264],"type":"Point"}
}