{
  "type": "Feature",
  "properties": {
    "iso:country":"US",
    "sg:address":"4625 Beckley Rd",
    "sg:city":"Battle Creek",
    "sg:classifiers":[
        {
            "category":"Banks & Credit Unions",
            "subcategory":"Bank",
            "type":"Services"
        }
    ],
    "sg:phone":"+1 269 979 8780",
    "sg:postcode":"49015",
    "sg:province":"MI",
    "sg:tags":[
        "mortgage"
    ],
    "wof:name":"Wells Fargo",
    "wof:placetype":"venue"
},
  "geometry": {"coordinates":[-85.20409600000001,42.261131],"type":"Point"}
}