{
  "type": "Feature",
  "properties": {
    "iso:country":"US",
    "sg:address":"11000 W McNichols Rd",
    "sg:city":"Detroit",
    "sg:classifiers":[
        {
            "category":"Insurance",
            "subcategory":"Insurance Agent",
            "type":"Services"
        }
    ],
    "sg:phone":"+1 313 863 6667",
    "sg:postcode":"48221",
    "sg:province":"MI",
    "wof:name":"Shears Insurance",
    "wof:placetype":"venue"
},
  "geometry": {"coordinates":[-83.170045,42.416733],"type":"Point"}
}