{
  "type": "Feature",
  "properties": {
    "iso:country":"US",
    "sg:address":"881 N Van Dyke Rd",
    "sg:city":"Almont",
    "sg:classifiers":[
        {
            "category":"Organizations",
            "subcategory":"Religious Organization",
            "type":"Services"
        }
    ],
    "sg:phone":"+1 810 798 8888",
    "sg:postcode":"48003",
    "sg:province":"MI",
    "sg:tags":[
        "church"
    ],
    "wof:name":"First Baptist Church",
    "wof:placetype":"venue"
},
  "geometry": {"coordinates":[-83.04964099999999,42.928072],"type":"Point"}
}