{
  "type": "Feature",
  "properties": {
    "iso:country":"US",
    "sg:address":"2122 Whittaker Rd ",
    "sg:city":"Ypsilanti",
    "sg:classifiers":[
        {
            "category":"Restaurant",
            "type":"Food & Drink"
        }
    ],
    "sg:menulink":"http://www.allmenus.com/mi/ypsilanti/283683-aubrees-pizza/menu/",
    "sg:phone":"+1 734 483 1111",
    "sg:postcode":"48197",
    "sg:province":"MI",
    "sg:tags":[
        "american",
        "pizza"
    ],
    "wof:name":"Aubree's Pizza",
    "wof:placetype":"venue"
},
  "geometry": {"coordinates":[-83.619536,42.210791],"type":"Point"}
}