{
  "type": "Feature",
  "properties": {
    "iso:country":"US",
    "sg:address":"4002 E Chandler St",
    "sg:city":"Carsonville",
    "sg:classifiers":[
        {
            "category":"Food & Beverages",
            "subcategory":"Liquor & Beverages",
            "type":"Retail Goods"
        }
    ],
    "sg:phone":"+1 810 657 9565",
    "sg:postcode":"48419",
    "sg:province":"MI",
    "sg:tags":[
        "beer",
        "ale"
    ],
    "wof:name":"Carsonville Market Inc",
    "wof:placetype":"venue"
},
  "geometry": {"coordinates":[-82.670753,43.426835],"type":"Point"}
}