{
  "type": "Feature",
  "properties": {
    "iso:country":"US",
    "sg:address":"37082 Gary Dr",
    "sg:city":"Sterling Heights",
    "sg:classifiers":[
        {
            "category":"Shopping",
            "subcategory":"Hobbies, Toys, & Games",
            "type":"Retail Goods"
        }
    ],
    "sg:phone":"+1 248 693 0800",
    "sg:postcode":"48310",
    "sg:province":"MI",
    "wof:name":"Toyz Wireless",
    "wof:placetype":"venue"
},
  "geometry": {"coordinates":[-83.080996,42.565967],"type":"Point"}
}