{
  "type": "Feature",
  "properties": {
    "iso:country":"US",
    "sg:address":"39261 Grand River Ave",
    "sg:city":"Farmington",
    "sg:classifiers":[
        {
            "category":"Food & Beverages",
            "subcategory":"Groceries & Convenience Stores",
            "type":"Retail Goods"
        }
    ],
    "sg:phone":"+1 248 888 0821",
    "sg:postcode":"48335",
    "sg:province":"MI",
    "wof:name":"India Grocers",
    "wof:placetype":"venue"
},
  "geometry": {"coordinates":[-83.43467699999999,42.471517],"type":"Point"}
}