{
  "type": "Feature",
  "properties": {
    "iso:country":"US",
    "sg:address":"8158 Landstar Dr",
    "sg:city":"Byron Center",
    "sg:classifiers":[
        {
            "category":"Shopping",
            "subcategory":"Computers & Home Electronics",
            "type":"Retail Goods"
        }
    ],
    "sg:phone":"+1 616 583 1500",
    "sg:postcode":"49315",
    "sg:province":"MI",
    "sg:tags":[
        "equipment",
        "dealer"
    ],
    "wof:name":"Direct Electronics Plus",
    "wof:placetype":"venue"
},
  "geometry": {"coordinates":[-85.705586,42.816526],"type":"Point"}
}