{
  "type": "Feature",
  "properties": {
    "iso:country":"US",
    "sg:address":"426 Iron St",
    "sg:city":"Negaunee",
    "sg:classifiers":[
        {
            "category":"Building & Trades",
            "subcategory":"Construction",
            "type":"Services"
        }
    ],
    "sg:phone":"+1 906 475 6099",
    "sg:postcode":"49866",
    "sg:province":"MI",
    "sg:tags":[
        "contractor"
    ],
    "wof:name":"Woodrich Builders",
    "wof:placetype":"venue"
},
  "geometry": {"coordinates":[-87.61273799999999,46.499014],"type":"Point"}
}