{
  "type": "Feature",
  "properties": {
    "iso:country":"US",
    "sg:address":"1915 Plains Rd",
    "sg:city":"Brutus",
    "sg:classifiers":[
        {
            "category":"Professional",
            "type":"Services"
        }
    ],
    "sg:phone":"+1 231 539 8324",
    "sg:postcode":"49716",
    "sg:province":"MI",
    "sg:tags":[
        "establishment"
    ],
    "wof:name":"Brubacher & Brubacher",
    "wof:placetype":"venue"
},
  "geometry": {"coordinates":[-84.750997,45.523488],"type":"Point"}
}