{
  "type": "Feature",
  "properties": {
    "iso:country":"US",
    "sg:address":"2140 Glen Echo Dr SE",
    "sg:city":"Grand Rapids",
    "sg:classifiers":[
        {
            "category":"Restaurant",
            "type":"Food & Drink"
        }
    ],
    "sg:phone":"+1 616 940 4506",
    "sg:postcode":"49546",
    "sg:province":"MI",
    "sg:tags":[
        "eating"
    ],
    "wof:name":"Simply Elegant Catering",
    "wof:placetype":"venue"
},
  "geometry": {"coordinates":[-85.602114,42.924354],"type":"Point"}
}