{
  "type": "Feature",
  "properties": {
    "iso:country":"US",
    "sg:address":"2121 Beard St",
    "sg:city":"Port Huron",
    "sg:classifiers":[
        {
            "category":"Manufacturing",
            "subcategory":"Metals",
            "type":"Manufacturing & Wholesale Goods"
        }
    ],
    "sg:phone":"+1 810 987 2992",
    "sg:postcode":"48060",
    "sg:province":"MI",
    "sg:tags":[
        "spring"
    ],
    "sg:website":"www.pjws.com",
    "wof:name":"P J Wallbank Springs Inc",
    "wof:placetype":"venue"
},
  "geometry": {"coordinates":[-82.44816299999999,42.958376],"type":"Point"}
}