{
  "type": "Feature",
  "properties": {
    "iso:country":"US",
    "sg:address":"6400 N Dixie Hwy",
    "sg:city":"Newport",
    "sg:classifiers":[
        {
            "category":"Professional",
            "subcategory":"Detective & Security Services",
            "type":"Services"
        }
    ],
    "sg:phone":"+1 734 586 4207",
    "sg:postcode":"48166",
    "sg:province":"MI",
    "sg:tags":[
        "car",
        "system"
    ],
    "wof:name":"Initial Security",
    "wof:placetype":"venue"
},
  "geometry": {"coordinates":[-83.291276,41.962722],"type":"Point"}
}