{
  "type": "Feature",
  "properties": {
    "iso:country":"US",
    "sg:address":"308 Myrtle St",
    "sg:city":"Flushing",
    "sg:classifiers":[
        {
            "category":"Professional",
            "subcategory":"Business Services",
            "type":"Services"
        }
    ],
    "sg:phone":"+1 810 659 8961",
    "sg:postcode":"48433",
    "sg:province":"MI",
    "wof:name":"Blue Sky Title Agency LLC",
    "wof:placetype":"venue"
},
  "geometry": {"coordinates":[-83.85139700000001,43.067103],"type":"Point"}
}