{
  "type": "Feature",
  "properties": {
    "iso:country":"US",
    "sg:address":"320 N Main St",
    "sg:city":"Reading",
    "sg:classifiers":[
        {
            "category":"Local Transit",
            "type":"Transportation"
        }
    ],
    "sg:phone":"+1 517 283 2856",
    "sg:postcode":"49274",
    "sg:province":"MI",
    "sg:tags":[
        "ambulance"
    ],
    "wof:name":"Reading Emergency Unit",
    "wof:placetype":"venue"
},
  "geometry": {"coordinates":[-84.747938,41.843668],"type":"Point"}
}