{
  "type": "Feature",
  "properties": {
    "iso:country":"US",
    "sg:address":"143 W Van Nest St",
    "sg:city":"Dundee",
    "sg:classifiers":[
        {
            "category":"Social Services",
            "subcategory":"Job Training",
            "type":"Services"
        }
    ],
    "sg:phone":"+1 734 529 7815",
    "sg:postcode":"48131",
    "sg:province":"MI",
    "sg:tags":[
        "rehabilitation"
    ],
    "wof:name":"Total Rehab In Dundee",
    "wof:placetype":"venue"
},
  "geometry": {"coordinates":[-83.65997400000001,41.958208],"type":"Point"}
}