{
  "type": "Feature",
  "properties": {
    "iso:country":"US",
    "sg:address":"107 E 2nd St",
    "sg:city":"Rochester",
    "sg:classifiers":[
        {
            "category":"Professional",
            "type":"Services"
        }
    ],
    "sg:phone":"+1 248 650 2958",
    "sg:postcode":"48307",
    "sg:province":"MI",
    "sg:tags":[
        "establishment"
    ],
    "wof:name":"Furniture Classic Stone",
    "wof:placetype":"venue"
},
  "geometry": {"coordinates":[-83.13288,42.678321],"type":"Point"}
}