{
  "type": "Feature",
  "properties": {
    "iso:country":"US",
    "sg:address":"32201 Harper Ave",
    "sg:city":"St Clair Shores",
    "sg:classifiers":[
        {
            "category":"Shopping",
            "subcategory":"Pharmacy",
            "type":"Retail Goods"
        }
    ],
    "sg:phone":"+1 586 293 5151",
    "sg:postcode":"48082",
    "sg:province":"MI",
    "sg:website":"www.walgreens.com",
    "wof:name":"Walgreens",
    "wof:placetype":"venue"
},
  "geometry": {"coordinates":[-82.888429,42.532251],"type":"Point"}
}