{
  "type": "Feature",
  "properties": {
    "iso:country":"US",
    "sg:address":"1125 24th St",
    "sg:city":"Port Huron",
    "sg:classifiers":[
        {
            "category":"Restaurant",
            "type":"Food & Drink"
        }
    ],
    "sg:menulink":"http://www.allmenus.com/mi/port-huron/185728-mcdonalds/menu/",
    "sg:postcode":"48060",
    "sg:province":"MI",
    "sg:tags":[
        "burger",
        "american"
    ],
    "wof:name":"McDonald's",
    "wof:placetype":"venue"
},
  "geometry": {"coordinates":[-82.452665,42.971944],"type":"Point"}
}