{
  "type": "Feature",
  "properties": {
    "iso:country":"US",
    "sg:address":"1516 Peck St",
    "sg:city":"Muskegon",
    "sg:classifiers":[
        {
            "category":"Professional",
            "subcategory":"Employment Agencies",
            "type":"Services"
        }
    ],
    "sg:phone":"+1 231 726 2626",
    "sg:postcode":"49441",
    "sg:province":"MI",
    "sg:tags":[
        "opportunity"
    ],
    "wof:name":"Family Services Ctr Inc",
    "wof:placetype":"venue"
},
  "geometry": {"coordinates":[-86.244191,43.224805],"type":"Point"}
}