{
  "type": "Feature",
  "properties": {
    "iso:country":"US",
    "sg:address":"5070 28th St SE",
    "sg:city":"Grand Rapids",
    "sg:classifiers":[
        {
            "category":"Restaurant",
            "type":"Food & Drink"
        }
    ],
    "sg:menulink":"http://www.allmenus.com/mi/cascade/59150-noodles--company/menu/",
    "sg:phone":"+1 616 954 5800",
    "sg:postcode":"49512",
    "sg:province":"MI",
    "sg:tags":[
        "noodle",
        "bar",
        "salad",
        "chinese",
        "japanese",
        "soup",
        "american",
        "asian",
        "thai",
        "italian"
    ],
    "wof:name":"Noodles & Company",
    "wof:placetype":"venue"
},
  "geometry": {"coordinates":[-85.54285900000001,42.912674],"type":"Point"}
}