{
  "type": "Feature",
  "properties": {
    "iso:country":"US",
    "sg:address":"571 N Wixom Rd",
    "sg:city":"Wixom",
    "sg:classifiers":[
        {
            "category":"Professional",
            "type":"Services"
        }
    ],
    "sg:phone":"+1 248 669 9037",
    "sg:postcode":"48393",
    "sg:province":"MI",
    "sg:tags":[
        "establishment"
    ],
    "wof:name":"Jenlue Corp",
    "wof:placetype":"venue"
},
  "geometry": {"coordinates":[-83.536389,42.52974],"type":"Point"}
}