{
  "type": "Feature",
  "properties": {
    "iso:country":"US",
    "sg:address":"22808 Harmon St",
    "sg:city":"St Clair Shores",
    "sg:classifiers":[
        {
            "category":"Building & Trades",
            "subcategory":"Construction",
            "type":"Services"
        }
    ],
    "sg:phone":"+1 586 776 3126",
    "sg:postcode":"48080",
    "sg:province":"MI",
    "sg:tags":[
        "roofing",
        "contractor"
    ],
    "wof:name":"Van Becelaere Roofing & Home",
    "wof:placetype":"venue"
},
  "geometry": {"coordinates":[-82.911968,42.46444],"type":"Point"}
}