{
  "type": "Feature",
  "properties": {
    "iso:country":"US",
    "sg:address":"2689 Balmoral Ct",
    "sg:city":"Ann Arbor",
    "sg:classifiers":[
        {
            "category":"Real Estate",
            "subcategory":"Real Estate Agent",
            "type":"Services"
        }
    ],
    "sg:phone":"+1 734 662 0351",
    "sg:postcode":"48103",
    "sg:province":"MI",
    "sg:tags":[
        "management"
    ],
    "wof:name":"Nam Invest Co",
    "wof:placetype":"venue"
},
  "geometry": {"coordinates":[-83.76476700000001,42.310981],"type":"Point"}
}