{
  "type": "Feature",
  "properties": {
    "iso:country":"US",
    "sg:address":"8107 N Dort Hwy",
    "sg:city":"Mt Morris",
    "sg:classifiers":[
        {
            "category":"Building & Trades",
            "subcategory":"Construction",
            "type":"Services"
        }
    ],
    "sg:phone":"+1 810 686 3980",
    "sg:postcode":"48458",
    "sg:province":"MI",
    "sg:tags":[
        "water",
        "well",
        "drilling"
    ],
    "wof:name":"Lyons Well Drilling Inc",
    "wof:placetype":"venue"
},
  "geometry": {"coordinates":[-83.676278,43.123286],"type":"Point"}
}