{
  "type": "Feature",
  "properties": {
    "iso:country":"US",
    "sg:address":"5770 S Main St",
    "sg:city":"Clarkston",
    "sg:classifiers":[
        {
            "category":"Health Services",
            "subcategory":"Doctor",
            "type":"Services"
        }
    ],
    "sg:phone":"+1 248 625 5511",
    "sg:postcode":"48346",
    "sg:province":"MI",
    "wof:name":"Donald K Nanney DDS PC Inc",
    "wof:placetype":"venue"
},
  "geometry": {"coordinates":[-83.41846700000001,42.721359],"type":"Point"}
}