{
  "type": "Feature",
  "properties": {
    "iso:country":"US",
    "sg:address":"35110 Division Rd",
    "sg:city":"Richmond",
    "sg:classifiers":[
        {
            "category":"Organizations",
            "subcategory":"Religious Organization",
            "type":"Services"
        }
    ],
    "sg:phone":"+1 586 727 7270",
    "sg:postcode":"48062",
    "sg:province":"MI",
    "sg:tags":[
        "church"
    ],
    "wof:name":"Trinity Lutheran Church Elca",
    "wof:placetype":"venue"
},
  "geometry": {"coordinates":[-82.768238,42.80889],"type":"Point"}
}