{
  "type": "Feature",
  "properties": {
    "iso:country":"US",
    "sg:address":"4486 Braden Rd",
    "sg:city":"Byron",
    "sg:classifiers":[
        {
            "category":"Food & Beverages",
            "subcategory":"Groceries & Convenience Stores",
            "type":"Retail Goods"
        }
    ],
    "sg:phone":"+1 989 634 5945",
    "sg:postcode":"48418",
    "sg:province":"MI",
    "wof:name":"Walkerville Family Mart",
    "wof:placetype":"venue"
},
  "geometry": {"coordinates":[-84.076398,42.792217],"type":"Point"}
}