{
  "type": "Feature",
  "properties": {
    "iso:country":"US",
    "sg:address":"3143 24th St",
    "sg:city":"Hopkins",
    "sg:classifiers":[
        {
            "category":"Farming",
            "subcategory":"Dairy Farm",
            "type":"Manufacturing & Wholesale Goods"
        }
    ],
    "sg:phone":"+1 269 793 4141",
    "sg:postcode":"49328",
    "sg:province":"MI",
    "wof:name":"Ronald W Layton",
    "wof:placetype":"venue"
},
  "geometry": {"coordinates":[-85.780674,42.638843],"type":"Point"}
}