{
  "type": "Feature",
  "properties": {
    "iso:country":"US",
    "sg:address":"28627 Hoover Rd",
    "sg:city":"Warren",
    "sg:classifiers":[
        {
            "category":"Health Services",
            "subcategory":"Optometrist",
            "type":"Services"
        }
    ],
    "sg:phone":"+1 586 573 7555",
    "sg:postcode":"48093",
    "sg:province":"MI",
    "sg:tags":[
        "ophthalmologist"
    ],
    "wof:name":"Zucker Norman MD",
    "wof:placetype":"venue"
},
  "geometry": {"coordinates":[-83.006897,42.504101],"type":"Point"}
}