{
  "type": "Feature",
  "properties": {
    "iso:country":"US",
    "sg:address":"1453 Sioux Trl",
    "sg:city":"Niles",
    "sg:classifiers":[
        {
            "category":"Professional",
            "subcategory":"Business Services",
            "type":"Services"
        }
    ],
    "sg:phone":"+1 269 683 9517",
    "sg:postcode":"49120",
    "sg:province":"MI",
    "wof:name":"Denise Dicostanzo Interiors",
    "wof:placetype":"venue"
},
  "geometry": {"coordinates":[-86.276211,41.819625],"type":"Point"}
}