{
  "type": "Feature",
  "properties": {
    "iso:country":"US",
    "sg:address":"20307 W 12 Mile Rd Ste 106",
    "sg:city":"Southfield",
    "sg:classifiers":[
        {
            "category":"Health Services",
            "subcategory":"Doctor",
            "type":"Services"
        }
    ],
    "sg:phone":"+1 248 353 8860",
    "sg:postcode":"48076",
    "sg:province":"MI",
    "sg:tags":[
        "surgeon",
        "oral"
    ],
    "wof:name":"Watko Jane DDS",
    "wof:placetype":"venue"
},
  "geometry": {"coordinates":[-83.2453,42.501801],"type":"Point"}
}