{
  "type": "Feature",
  "properties": {
    "iso:country":"US",
    "sg:address":"6336 S Cedar St",
    "sg:city":"Lansing",
    "sg:classifiers":[
        {
            "category":"Banks & Credit Unions",
            "subcategory":"Bank",
            "type":"Services"
        }
    ],
    "sg:phone":"+1 517 334 1655",
    "sg:postcode":"48911",
    "sg:province":"MI",
    "sg:tags":[
        "national",
        "commercial"
    ],
    "wof:name":"National City Bank",
    "wof:placetype":"venue"
},
  "geometry": {"coordinates":[-84.539266,42.662235],"type":"Point"}
}