{
  "type": "Feature",
  "properties": {
    "iso:country":"US",
    "sg:address":"166 James Robertson Dr",
    "sg:city":"Gladwin",
    "sg:classifiers":[
        {
            "category":"Professional",
            "subcategory":"Accounting & Tax Preparation",
            "type":"Services"
        }
    ],
    "sg:phone":"+1 989 426 7198",
    "sg:postcode":"48624",
    "sg:province":"MI",
    "sg:tags":[
        "return",
        "filing"
    ],
    "wof:name":"H & R Block Tax Svc",
    "wof:placetype":"venue"
},
  "geometry": {"coordinates":[-84.470314,43.983476],"type":"Point"}
}