{
  "type": "Feature",
  "properties": {
    "iso:country":"US",
    "sg:address":"215 Durkee St",
    "sg:city":"Lawton",
    "sg:classifiers":[
        {
            "category":"Building & Trades",
            "subcategory":"Construction",
            "type":"Services"
        }
    ],
    "sg:phone":"+1 269 624 1608",
    "sg:postcode":"49065",
    "sg:province":"MI",
    "sg:tags":[
        "painting",
        "drywall",
        "contractor"
    ],
    "wof:name":"Spicketts Paint & Dry Wall",
    "wof:placetype":"venue"
},
  "geometry": {"coordinates":[-85.84744999999999,42.163145],"type":"Point"}
}