{
  "type": "Feature",
  "properties": {
    "iso:country":"US",
    "sg:address":"1623 Oakwood Dr",
    "sg:city":"Gladwin",
    "sg:classifiers":[
        {
            "category":"Social Services",
            "subcategory":"Child Care",
            "type":"Services"
        }
    ],
    "sg:phone":"+1 989 246 1349",
    "sg:postcode":"48624",
    "sg:province":"MI",
    "sg:tags":[
        "day"
    ],
    "wof:name":"Darrell Day",
    "wof:placetype":"venue"
},
  "geometry": {"coordinates":[-84.55533699999999,44.020438],"type":"Point"}
}