{
  "type": "Feature",
  "properties": {
    "iso:country":"US",
    "sg:address":"14241 W 11 Mile Rd",
    "sg:city":"Oak Park",
    "sg:classifiers":[
        {
            "category":"Wholesale",
            "subcategory":"Hardware",
            "type":"Manufacturing & Wholesale Goods"
        }
    ],
    "sg:phone":"+1 248 545 2525",
    "sg:postcode":"48237",
    "sg:province":"MI",
    "sg:tags":[
        "thermostat"
    ],
    "wof:name":"Uni-Gard Inc",
    "wof:placetype":"venue"
},
  "geometry": {"coordinates":[-83.189831,42.48862],"type":"Point"}
}