{
  "type": "Feature",
  "properties": {
    "iso:country":"US",
    "sg:address":"7375 Midland Rd",
    "sg:city":"Freeland",
    "sg:classifiers":[
        {
            "category":"Restaurant",
            "type":"Food & Drink"
        }
    ],
    "sg:menulink":"http://www.allmenus.com/mi/tittabawassee/142379-subway/menu/",
    "sg:phone":"+1 989 695 2105",
    "sg:postcode":"48623",
    "sg:province":"MI",
    "sg:tags":[
        "american",
        "sandwich"
    ],
    "wof:name":"Subway",
    "wof:placetype":"venue"
},
  "geometry": {"coordinates":[-84.119618,43.516863],"type":"Point"}
}