{
  "type": "Feature",
  "properties": {
    "iso:country":"US",
    "sg:address":"1400 N Henry St",
    "sg:city":"Bay City",
    "sg:classifiers":[
        {
            "category":"Travel",
            "subcategory":"Campground",
            "type":"Entertainment"
        }
    ],
    "sg:phone":"+1 989 671 1142",
    "sg:postcode":"48706",
    "sg:province":"MI",
    "sg:tags":[
        "operation",
        "trailer"
    ],
    "wof:name":"Outdoor Adventures",
    "wof:placetype":"venue"
},
  "geometry": {"coordinates":[-83.899537,43.617478],"type":"Point"}
}