{
  "type": "Feature",
  "properties": {
    "iso:country":"US",
    "sg:address":"1138 Pine Ave NW",
    "sg:city":"Grand Rapids",
    "sg:classifiers":[
        {
            "category":"Education",
            "subcategory":"School",
            "type":"Public Place"
        }
    ],
    "sg:phone":"+1 616 771 2702",
    "sg:postcode":"49504",
    "sg:province":"MI",
    "wof:name":"Pine St",
    "wof:placetype":"venue"
},
  "geometry": {"coordinates":[-85.69412699999999,42.984703],"type":"Point"}
}