{
  "type": "Feature",
  "properties": {
    "iso:country":"US",
    "sg:address":"13920 E 9 Mile Rd",
    "sg:city":"Warren",
    "sg:classifiers":[
        {
            "category":"Manufacturing",
            "subcategory":"Metals",
            "type":"Manufacturing & Wholesale Goods"
        }
    ],
    "sg:phone":"+1 586 774 3659",
    "sg:postcode":"48089",
    "sg:province":"MI",
    "sg:tags":[
        "steel",
        "stamp",
        "brass"
    ],
    "wof:name":"Engravers Inc",
    "wof:placetype":"venue"
},
  "geometry": {"coordinates":[-82.98160900000001,42.463848],"type":"Point"}
}