{
  "type": "Feature",
  "properties": {
    "iso:country":"US",
    "sg:address":"1020 W Cedar St",
    "sg:city":"Standish",
    "sg:classifiers":[
        {
            "category":"Health Services",
            "subcategory":"Clinic",
            "type":"Services"
        },
        {
            "category":"Health Services",
            "subcategory":"Medical Lab",
            "type":"Services"
        }
    ],
    "sg:phone":"+1 989 846 4187",
    "sg:postcode":"48658",
    "sg:province":"MI",
    "sg:tags":[
        "a",
        "facility",
        "specialty",
        "drug",
        "operates",
        "detection",
        "equipment",
        "as",
        "outpatient",
        "specialized"
    ],
    "wof:name":"Occupational Testing Center",
    "wof:placetype":"venue"
},
  "geometry": {"coordinates":[-83.968535,43.98288],"type":"Point"}
}