{
  "type": "Feature",
  "properties": {
    "iso:country":"US",
    "sg:address":"6314 Ingersoll Rd SW",
    "sg:city":"Fife Lake",
    "sg:classifiers":[
        {
            "category":"Organizations",
            "subcategory":"Community Association",
            "type":"Services"
        }
    ],
    "sg:phone":"+1 231 879 5323",
    "sg:postcode":"49633",
    "sg:province":"MI",
    "wof:name":"Crofton Storage Condo Assoc",
    "wof:placetype":"venue"
},
  "geometry": {"coordinates":[-85.298137,44.569901],"type":"Point"}
}