{
  "type": "Feature",
  "properties": {
    "iso:country":"US",
    "sg:address":"4153 S M 37",
    "sg:city":"Baldwin",
    "sg:classifiers":[
        {
            "category":"Government",
            "subcategory":"Office",
            "type":"Public Place"
        }
    ],
    "sg:phone":"+1 231 745 7784",
    "sg:postcode":"49304",
    "sg:province":"MI",
    "wof:name":"TRV Ctr",
    "wof:placetype":"venue"
},
  "geometry": {"coordinates":[-85.851575,43.904505],"type":"Point"}
}