{
  "type": "Feature",
  "properties": {
    "iso:country":"US",
    "sg:address":"17655 Cake Rd",
    "sg:city":"Dundee",
    "sg:phone":"+1 734 279 1445",
    "sg:postcode":"48131",
    "sg:province":"MI",
    "sg:tags":[
        "farm",
        "soybean"
    ],
    "wof:name":"Cilley Delmer",
    "wof:placetype":"venue"
},
  "geometry": {"coordinates":[-83.69195499999999,41.931226],"type":"Point"}
}