{
  "type": "Feature",
  "properties": {
    "iso:country":"US",
    "sg:address":"14855 Telegraph Rd",
    "sg:city":"Redford",
    "sg:classifiers":[
        {
            "category":"Bakery",
            "type":"Food & Drink"
        },
        {
            "category":"Coffee & Tea",
            "type":"Food & Drink"
        },
        {
            "category":"Bagels",
            "type":"Food & Drink"
        },
        {
            "category":"Donuts",
            "type":"Food & Drink"
        }
    ],
    "sg:menulink":"http://www.allmenus.com/mi/redford/133219-dunkin-donuts/menu/",
    "sg:phone":"+1 313 531 5903",
    "sg:postcode":"48239",
    "sg:province":"MI",
    "sg:tags":[
        "american",
        "pastry"
    ],
    "wof:name":"Dunkin' Donuts",
    "wof:placetype":"venue"
},
  "geometry": {"coordinates":[-83.27682799999999,42.397098],"type":"Point"}
}