{
  "type": "Feature",
  "properties": {
    "iso:country":"US",
    "sg:address":"530 Beacon Lake Dr",
    "sg:city":"Mason",
    "sg:classifiers":[
        {
            "category":"Professional",
            "subcategory":"Management & Consulting",
            "type":"Services"
        }
    ],
    "sg:phone":"+1 517 676 5837",
    "sg:postcode":"48854",
    "sg:province":"MI",
    "sg:tags":[
        "consultant",
        "bill",
        "utility"
    ],
    "wof:name":"Wright Service",
    "wof:placetype":"venue"
},
  "geometry": {"coordinates":[-84.45181700000001,42.572016],"type":"Point"}
}