{
  "type": "Feature",
  "properties": {
    "iso:country":"US",
    "sg:address":"9060 N Bayshore Dr",
    "sg:city":"Elk Rapids",
    "sg:classifiers":[
        {
            "category":"Manufacturing",
            "subcategory":"Printing",
            "type":"Manufacturing & Wholesale Goods"
        }
    ],
    "sg:phone":"+1 231 264 5851",
    "sg:postcode":"49629",
    "sg:province":"MI",
    "sg:tags":[
        "publisher"
    ],
    "wof:name":"Bookability Inc",
    "wof:placetype":"venue"
},
  "geometry": {"coordinates":[-85.40888699999999,44.903727],"type":"Point"}
}