{
  "type": "Feature",
  "properties": {
    "iso:country":"US",
    "sg:address":"4803 E 8 Mile Rd",
    "sg:city":"Warren",
    "sg:classifiers":[
        {
            "category":"Shopping",
            "subcategory":"Department Store",
            "type":"Retail Goods"
        }
    ],
    "sg:phone":"+1 586 427 5707",
    "sg:postcode":"48091",
    "sg:province":"MI",
    "sg:tags":[
        "shop"
    ],
    "wof:name":"Family Dollar Store",
    "wof:placetype":"venue"
},
  "geometry": {"coordinates":[-83.056928,42.447506],"type":"Point"}
}