{
  "type": "Feature",
  "properties": {
    "iso:country":"US",
    "sg:address":"1692 Southlawn St",
    "sg:city":"Jenison",
    "sg:classifiers":[
        {
            "category":"Health Services",
            "subcategory":"Health Practitioner",
            "type":"Services"
        }
    ],
    "sg:phone":"+1 616 457 1185",
    "sg:postcode":"49428",
    "sg:province":"MI",
    "wof:name":"Reeling & Healing of Michigan",
    "wof:placetype":"venue"
},
  "geometry": {"coordinates":[-85.824748,42.901246],"type":"Point"}
}