{
  "type": "Feature",
  "properties": {
    "iso:country":"US",
    "sg:address":"6785 Myers Lake Ave NE",
    "sg:city":"Rockford",
    "sg:classifiers":[
        {
            "category":"Health Services",
            "subcategory":"Doctor",
            "type":"Services"
        }
    ],
    "sg:phone":"+1 616 874 3270",
    "sg:postcode":"49341",
    "sg:province":"MI",
    "sg:tags":[
        "medical"
    ],
    "wof:name":"Spectrum Health United Mem",
    "wof:placetype":"venue"
},
  "geometry": {"coordinates":[-85.50033000000001,43.085994],"type":"Point"}
}