{
  "type": "Feature",
  "properties": {
    "iso:country":"US",
    "sg:address":"415 W Ohio St",
    "sg:city":"Marquette",
    "sg:classifiers":[
        {
            "category":"Insurance",
            "subcategory":"Insurance Agent",
            "type":"Services"
        }
    ],
    "sg:phone":"+1 906 226 9563",
    "sg:postcode":"49855",
    "sg:province":"MI",
    "wof:name":"David H Vallar Ins",
    "wof:placetype":"venue"
},
  "geometry": {"coordinates":[-87.39856899999999,46.54806],"type":"Point"}
}