{
  "type": "Feature",
  "properties": {
    "iso:country":"US",
    "sg:address":"1429 E Lansing Dr",
    "sg:city":"East Lansing",
    "sg:classifiers":[
        {
            "category":"Food & Beverages",
            "subcategory":"Specialty",
            "type":"Retail Goods"
        }
    ],
    "sg:phone":"+1 517 324 7007",
    "sg:postcode":"48823",
    "sg:province":"MI",
    "sg:tags":[
        "gourmet",
        "shop"
    ],
    "wof:name":"Beaners Gourmet Coffee",
    "wof:placetype":"venue"
},
  "geometry": {"coordinates":[-84.452395,42.748813],"type":"Point"}
}