{
  "type": "Feature",
  "properties": {
    "iso:country":"US",
    "sg:address":"1035 Comstock St",
    "sg:city":"Marne",
    "sg:classifiers":[
        {
            "category":"Building & Trades",
            "subcategory":"Construction",
            "type":"Services"
        }
    ],
    "sg:phone":"+1 616 677 1600",
    "sg:postcode":"49435",
    "sg:province":"MI",
    "sg:tags":[
        "concrete",
        "contractor"
    ],
    "wof:name":"Meyering Concrete Inc",
    "wof:placetype":"venue"
},
  "geometry": {"coordinates":[-85.812652,43.038273],"type":"Point"}
}