{
  "type": "Feature",
  "properties": {
    "iso:country":"US",
    "sg:address":"614 S Silverleaf St",
    "sg:city":"Gladwin",
    "sg:classifiers":[
        {
            "category":"Recreation",
            "type":"Entertainment"
        }
    ],
    "sg:phone":"+1 989 426 3104",
    "sg:postcode":"48624",
    "sg:province":"MI",
    "sg:tags":[
        "instruction",
        "golf"
    ],
    "wof:name":"Ogden Custom Golf",
    "wof:placetype":"venue"
},
  "geometry": {"coordinates":[-84.486784,43.975755],"type":"Point"}
}