{
  "type": "Feature",
  "properties": {
    "iso:country":"US",
    "sg:address":"1022 4th St",
    "sg:city":"Jackson",
    "sg:classifiers":[
        {
            "category":"Professional",
            "subcategory":"Computer Services",
            "type":"Services"
        }
    ],
    "sg:phone":"+1 517 788 8431",
    "sg:postcode":"49203",
    "sg:province":"MI",
    "sg:tags":[
        "datum"
    ],
    "wof:name":"Lily Pad Desk Top Pubg Grphics",
    "wof:placetype":"venue"
},
  "geometry": {"coordinates":[-84.418525,42.238146],"type":"Point"}
}