{
  "type": "Feature",
  "properties": {
    "iso:country":"US",
    "sg:address":"132 E Division St",
    "sg:city":"Sparta",
    "sg:classifiers":[
        {
            "category":"Banks & Credit Unions",
            "subcategory":"Investment Brokerage",
            "type":"Services"
        }
    ],
    "sg:phone":"+1 616 887 2584",
    "sg:postcode":"49345",
    "sg:province":"MI",
    "sg:tags":[
        "security"
    ],
    "wof:name":"Edward Jones Co",
    "wof:placetype":"venue"
},
  "geometry": {"coordinates":[-85.707082,43.160673],"type":"Point"}
}