{
  "type": "Feature",
  "properties": {
    "iso:country":"US",
    "sg:address":"669 E Cedar Ave",
    "sg:city":"Gladwin",
    "sg:classifiers":[
        {
            "category":"Government",
            "subcategory":"Office",
            "type":"Public Place"
        }
    ],
    "sg:phone":"+1 989 426 6914",
    "sg:postcode":"48624",
    "sg:province":"MI",
    "wof:name":"Gladwin Cnty Circuit Ct Prbtn",
    "wof:placetype":"venue"
},
  "geometry": {"coordinates":[-84.480131,43.980673],"type":"Point"}
}