{
  "type": "Feature",
  "properties": {
    "iso:country":"US",
    "sg:address":"28404 Harper Ave",
    "sg:city":"Saint Clair Shores",
    "sg:classifiers":[
        {
            "category":"Health Services",
            "subcategory":"Chiropractor",
            "type":"Services"
        }
    ],
    "sg:phone":"+1 586 775 6500",
    "sg:postcode":"48081",
    "sg:province":"MI",
    "wof:name":"Migliazzo John DC",
    "wof:placetype":"venue"
},
  "geometry": {"coordinates":[-82.89769699999999,42.5023],"type":"Point"}
}