{
  "type": "Feature",
  "properties": {
    "iso:country":"US",
    "sg:address":"318 Town Center Dr",
    "sg:city":"Troy",
    "sg:classifiers":[
        {
            "category":"Banks & Credit Unions",
            "subcategory":"Investment Brokerage",
            "type":"Services"
        }
    ],
    "sg:phone":"+1 248 457 9810",
    "sg:postcode":"48084",
    "sg:province":"MI",
    "sg:tags":[
        "advisory",
        "financial"
    ],
    "wof:name":"LTC Financial Partners",
    "wof:placetype":"venue"
},
  "geometry": {"coordinates":[-83.15494099999999,42.56721],"type":"Point"}
}