{
  "type": "Feature",
  "properties": {
    "iso:country":"US",
    "sg:address":"477 Michigan Ave",
    "sg:city":"Detroit",
    "sg:classifiers":[
        {
            "category":"Government",
            "subcategory":"Office",
            "type":"Public Place"
        }
    ],
    "sg:phone":"+1 313 226 4114",
    "sg:postcode":"48226",
    "sg:province":"MI",
    "sg:tags":[
        "affairs"
    ],
    "wof:name":"Veterans Administration Emps",
    "wof:placetype":"venue"
},
  "geometry": {"coordinates":[-83.052663,42.331672],"type":"Point"}
}