{
  "type": "Feature",
  "properties": {
    "iso:country":"US",
    "sg:address":"11637 Ellis Rd",
    "sg:city":"Belding",
    "sg:classifiers":[
        {
            "category":"Farming",
            "subcategory":"Orchard",
            "type":"Manufacturing & Wholesale Goods"
        }
    ],
    "sg:phone":"+1 616 794 3187",
    "sg:postcode":"48809",
    "sg:province":"MI",
    "sg:tags":[
        "fruit",
        "tree"
    ],
    "wof:name":"Frank Mason Farms",
    "wof:placetype":"venue"
},
  "geometry": {"coordinates":[-85.311549,43.102488],"type":"Point"}
}