{
  "type": "Feature",
  "properties": {
    "iso:country":"US",
    "sg:address":"2421 Monroe St Ste 102",
    "sg:city":"Dearborn",
    "sg:classifiers":[
        {
            "category":"Health Services",
            "subcategory":"Doctor",
            "type":"Services"
        }
    ],
    "sg:phone":"+1 313 561 1520",
    "sg:postcode":"48124",
    "sg:province":"MI",
    "sg:tags":[
        "cardiologist"
    ],
    "wof:name":"Heart Institute PC the",
    "wof:placetype":"venue"
},
  "geometry": {"coordinates":[-83.24770100000001,42.295018],"type":"Point"}
}