{
  "type": "Feature",
  "properties": {
    "iso:country":"US",
    "sg:address":"3850 Glenkerry Ct",
    "sg:city":"Portage",
    "sg:classifiers":[
        {
            "category":"Banks & Credit Unions",
            "subcategory":"Investment Brokerage",
            "type":"Services"
        }
    ],
    "sg:phone":"+1 269 323 8944",
    "sg:postcode":"49024",
    "sg:province":"MI",
    "sg:tags":[
        "advisory"
    ],
    "wof:name":"Waddell & Reed Inc",
    "wof:placetype":"venue"
},
  "geometry": {"coordinates":[-85.634255,42.203812],"type":"Point"}
}