{
  "type": "Feature",
  "properties": {
    "iso:country":"US",
    "sg:address":"4675 Pelton Rd",
    "sg:city":"Clarkston",
    "sg:classifiers":[
        {
            "category":"Building & Trades",
            "subcategory":"Construction",
            "type":"Services"
        }
    ],
    "sg:phone":"+1 248 674 8559",
    "sg:postcode":"48346",
    "sg:province":"MI",
    "sg:tags":[
        "contractor"
    ],
    "wof:name":"Horizon Building Co",
    "wof:placetype":"venue"
},
  "geometry": {"coordinates":[-83.382327,42.711655],"type":"Point"}
}