{
  "type": "Feature",
  "properties": {
    "iso:country":"US",
    "sg:address":"15476 S M-43 Hwy",
    "sg:city":"Hickory Corners",
    "sg:classifiers":[
        {
            "category":"Food & Beverages",
            "subcategory":"Groceries & Convenience Stores",
            "type":"Retail Goods"
        }
    ],
    "sg:phone":"+1 269 671 5750",
    "sg:postcode":"49060",
    "sg:province":"MI",
    "sg:tags":[
        "video",
        "t",
        "alcoholic"
    ],
    "wof:name":"Gull View Market",
    "wof:placetype":"venue"
},
  "geometry": {"coordinates":[-85.43810000000001,42.423989],"type":"Point"}
}