{
  "type": "Feature",
  "properties": {
    "iso:country":"US",
    "sg:address":"16827 Appoline St",
    "sg:city":"Detroit",
    "sg:classifiers":[
        {
            "category":"Social Services",
            "subcategory":"Child Care",
            "type":"Services"
        },
        {
            "category":"Education",
            "subcategory":"Preschool",
            "type":"Public Place"
        },
        {
            "category":"Education",
            "subcategory":"School",
            "type":"Public Place"
        }
    ],
    "sg:phone":"+1 313 341 4944",
    "sg:postcode":"48235",
    "sg:province":"MI",
    "sg:tags":[
        "elementary",
        "day"
    ],
    "wof:name":"Martin Luther King Jr Education Center",
    "wof:placetype":"venue"
},
  "geometry": {"coordinates":[-83.17089799999999,42.414501],"type":"Point"}
}