{
  "type": "Feature",
  "properties": {
    "iso:country":"US",
    "sg:address":"7070 County Farm Rd",
    "sg:city":"Lexington",
    "sg:classifiers":[
        {
            "category":"Manufacturing",
            "subcategory":"Signs",
            "type":"Manufacturing & Wholesale Goods"
        }
    ],
    "sg:phone":"+1 810 434 7372",
    "sg:postcode":"48450",
    "sg:province":"MI",
    "sg:tags":[
        "specialty",
        "mfg"
    ],
    "wof:name":"Precision Sign LLC",
    "wof:placetype":"venue"
},
  "geometry": {"coordinates":[-82.53479299999999,43.311457],"type":"Point"}
}