{
  "type": "Feature",
  "properties": {
    "iso:country":"US",
    "sg:address":"1980 S Lincoln Rd",
    "sg:city":"Mount Pleasant",
    "sg:classifiers":[
        {
            "category":"Organizations",
            "subcategory":"Religious Organization",
            "type":"Services"
        }
    ],
    "sg:phone":"+1 989 772 4330",
    "sg:postcode":"48858",
    "sg:province":"MI",
    "wof:name":"First Church of Nazarene",
    "wof:placetype":"venue"
},
  "geometry": {"coordinates":[-84.807939,43.611737],"type":"Point"}
}