{
  "type": "Feature",
  "properties": {
    "iso:country":"US",
    "sg:address":"1361 Corey Cove",
    "sg:city":"White Lake",
    "sg:classifiers":[
        {
            "category":"Professional",
            "subcategory":"Business Services",
            "type":"Services"
        }
    ],
    "sg:phone":"+1 248 889 7156",
    "sg:postcode":"48383",
    "sg:province":"MI",
    "wof:name":"Skc Enterprises LLC",
    "wof:placetype":"venue"
},
  "geometry": {"coordinates":[-83.514139,42.631957],"type":"Point"}
}