{
  "type": "Feature",
  "properties": {
    "iso:country":"US",
    "sg:address":"5322 Pinch Hwy",
    "sg:city":"Potterville",
    "sg:classifiers":[
        {
            "category":"Building & Trades",
            "subcategory":"Construction",
            "type":"Services"
        }
    ],
    "sg:phone":"+1 517 645 2329",
    "sg:postcode":"48876",
    "sg:province":"MI",
    "sg:tags":[
        "residential"
    ],
    "wof:name":"Edwards Co",
    "wof:placetype":"venue"
},
  "geometry": {"coordinates":[-84.733475,42.654561],"type":"Point"}
}