{
  "type": "Feature",
  "properties": {
    "iso:country":"US",
    "sg:address":"17 Williams St SW",
    "sg:city":"Grand Rapids",
    "sg:classifiers":[
        {
            "category":"Manufacturing",
            "subcategory":"Rubber & Plastics",
            "type":"Manufacturing & Wholesale Goods"
        }
    ],
    "sg:phone":"+1 616 459 0129",
    "sg:postcode":"49503",
    "sg:province":"MI",
    "sg:tags":[
        "tire"
    ],
    "wof:name":"Rhd Tire Wholesalers",
    "wof:placetype":"venue"
},
  "geometry": {"coordinates":[-85.668587,42.958825],"type":"Point"}
}