{
  "type": "Feature",
  "properties": {
    "iso:country":"US",
    "sg:address":"617 Michigan St",
    "sg:city":"Ontonagon",
    "sg:classifiers":[
        {
            "category":"Organizations",
            "subcategory":"Community Association",
            "type":"Services"
        }
    ],
    "sg:phone":"+1 906 884 2389",
    "sg:postcode":"49953",
    "sg:province":"MI",
    "wof:name":"International Assoc of Lions",
    "wof:placetype":"venue"
},
  "geometry": {"coordinates":[-89.318659,46.874055],"type":"Point"}
}