{
  "type": "Feature",
  "properties": {
    "iso:country":"US",
    "sg:address":"4116 Mahogany Dr",
    "sg:city":"Sterling Heights",
    "sg:classifiers":[
        {
            "category":"Building & Trades",
            "subcategory":"Construction",
            "type":"Services"
        }
    ],
    "sg:phone":"+1 586 979 5082",
    "sg:postcode":"48310",
    "sg:province":"MI",
    "sg:tags":[
        "roofing",
        "contractor"
    ],
    "wof:name":"Courtesy Roofing",
    "wof:placetype":"venue"
},
  "geometry": {"coordinates":[-83.065168,42.559232],"type":"Point"}
}