{
  "type": "Feature",
  "properties": {
    "iso:country":"US",
    "sg:address":"235 Adrian St",
    "sg:city":"Manchester",
    "sg:classifiers":[
        {
            "category":"Building & Trades",
            "subcategory":"Cleaning & Sanitation",
            "type":"Services"
        }
    ],
    "sg:phone":"+1 734 428 7160",
    "sg:postcode":"48158",
    "sg:province":"MI",
    "sg:tags":[
        "maintenance"
    ],
    "wof:name":"Bakers Janitorial",
    "wof:placetype":"venue"
},
  "geometry": {"coordinates":[-84.036384,42.146572],"type":"Point"}
}