{
  "type": "Feature",
  "properties": {
    "iso:country":"US",
    "sg:address":"340 State St SE",
    "sg:city":"Grand Rapids",
    "sg:classifiers":[
        {
            "category":"Restaurant",
            "type":"Food & Drink"
        }
    ],
    "sg:phone":"+1 616 458 8383",
    "sg:postcode":"49503",
    "sg:province":"MI",
    "wof:name":"Beijing Kitchen",
    "wof:placetype":"venue"
},
  "geometry": {"coordinates":[-85.659228,42.959424],"type":"Point"}
}