{
  "type": "Feature",
  "properties": {
    "iso:country":"US",
    "sg:address":"1120 US Hwy 23 N",
    "sg:city":"Alpena",
    "sg:classifiers":[
        {
            "category":"Recreation",
            "subcategory":"Arcade",
            "type":"Entertainment"
        },
        {
            "category":"Recreation",
            "type":"Entertainment"
        }
    ],
    "sg:phone":"+1 989 354 4414",
    "sg:postcode":"49707",
    "sg:province":"MI",
    "sg:tags":[
        "device",
        "course",
        "golf",
        "amusement",
        "operator"
    ],
    "wof:name":"J J's Awesome Acres",
    "wof:placetype":"venue"
},
  "geometry": {"coordinates":[-83.45719099999999,45.087394],"type":"Point"}
}