{
  "type": "Feature",
  "properties": {
    "iso:country":"US",
    "sg:address":"4234 N Adrian Hwy",
    "sg:city":"Adrian",
    "sg:classifiers":[
        {
            "category":"Building & Trades",
            "subcategory":"Construction",
            "type":"Services"
        }
    ],
    "sg:phone":"+1 517 264 0300",
    "sg:postcode":"49221",
    "sg:province":"MI",
    "sg:tags":[
        "dry wall",
        "contractor"
    ],
    "wof:name":"Rawson Drywall",
    "wof:placetype":"venue"
},
  "geometry": {"coordinates":[-84.004677,41.945234],"type":"Point"}
}