{
  "type": "Feature",
  "properties": {
    "iso:country":"US",
    "sg:address":"20323 Mack Ave",
    "sg:city":"Grosse Pointe",
    "sg:classifiers":[
        {
            "category":"Health Services",
            "subcategory":"Doctor",
            "type":"Services"
        }
    ],
    "sg:phone":"+1 313 881 0077",
    "sg:postcode":"48236",
    "sg:province":"MI",
    "wof:name":"Ben J Czerniawski DDS Ms",
    "wof:placetype":"venue"
},
  "geometry": {"coordinates":[-82.908108,42.437831],"type":"Point"}
}