{
  "type": "Feature",
  "properties": {
    "iso:country":"US",
    "sg:address":"29069 Greenfield Rd.",
    "sg:city":"Southfield",
    "sg:classifiers":[
        {
            "category":"Coffee & Tea",
            "type":"Food & Drink"
        },
        {
            "category":"Restaurant",
            "type":"Food & Drink"
        },
        {
            "category":"Food & Beverages",
            "subcategory":"Groceries & Convenience Stores",
            "type":"Retail Goods"
        }
    ],
    "sg:phone":"+1 248 552 0016",
    "sg:postcode":"48076",
    "sg:province":"MI",
    "sg:tags":[
        "shop",
        "sandwich",
        "espresso",
        "lunch",
        "brunch",
        "breakfast"
    ],
    "sg:website":"www.timhortons.com",
    "wof:name":"Tim Hortons",
    "wof:placetype":"venue"
},
  "geometry": {"coordinates":[-83.203175,42.503796],"type":"Point"}
}