{
  "type": "Feature",
  "properties": {
    "iso:country":"US",
    "sg:address":"1710 Dykhouse Ave",
    "sg:city":"Grand Haven",
    "sg:classifiers":[
        {
            "category":"Building & Trades",
            "subcategory":"Pest Control",
            "type":"Services"
        }
    ],
    "sg:phone":"+1 616 846 4015",
    "sg:postcode":"49417",
    "sg:province":"MI",
    "wof:name":"Drakos Extermination",
    "wof:placetype":"venue"
},
  "geometry": {"coordinates":[-86.19819099999999,43.045667],"type":"Point"}
}