{
  "type": "Feature",
  "properties": {
    "iso:country":"US",
    "sg:address":"1372 Scott Lake Rd",
    "sg:city":"Waterford",
    "sg:classifiers":[
        {
            "category":"Building & Trades",
            "subcategory":"Construction",
            "type":"Services"
        }
    ],
    "sg:phone":"+1 248 681 6140",
    "sg:postcode":"48328",
    "sg:province":"MI",
    "sg:tags":[
        "repairing",
        "remodeling",
        "contractor"
    ],
    "wof:name":"Public Building Renovations",
    "wof:placetype":"venue"
},
  "geometry": {"coordinates":[-83.34665200000001,42.659963],"type":"Point"}
}