{
  "type": "Feature",
  "properties": {
    "iso:country":"US",
    "sg:address":"3750 Mack Rd",
    "sg:city":"Saginaw",
    "sg:classifiers":[
        {
            "category":"Building & Trades",
            "subcategory":"Construction",
            "type":"Services"
        }
    ],
    "sg:phone":"+1 989 777 4334",
    "sg:postcode":"48601",
    "sg:province":"MI",
    "sg:tags":[
        "house",
        "business"
    ],
    "wof:name":"Ernie Friske Builders",
    "wof:placetype":"venue"
},
  "geometry": {"coordinates":[-83.88641,43.383249],"type":"Point"}
}