{
  "type": "Feature",
  "properties": {
    "iso:country":"US",
    "sg:address":"9345 Milford Rd",
    "sg:city":"Holly",
    "sg:classifiers":[
        {
            "category":"Social Services",
            "subcategory":"Adult Care",
            "type":"Services"
        }
    ],
    "sg:phone":"+1 248 634 8505",
    "sg:postcode":"48442",
    "sg:province":"MI",
    "sg:tags":[
        "foster"
    ],
    "wof:name":"Milford Home",
    "wof:placetype":"venue"
},
  "geometry": {"coordinates":[-83.621166,42.734362],"type":"Point"}
}