{
  "type": "Feature",
  "properties": {
    "iso:country":"US",
    "sg:address":"24070 W 9 Mile Rd",
    "sg:city":"Southfield",
    "sg:classifiers":[
        {
            "category":"Retail",
            "subcategory":"Veterinary Services",
            "type":"Services"
        }
    ],
    "sg:phone":"+1 248 352 4560",
    "sg:postcode":"48034",
    "sg:province":"MI",
    "sg:tags":[
        "veterinarian"
    ],
    "wof:name":"Vetselect Animal Hospital of Southfield",
    "wof:placetype":"venue"
},
  "geometry": {"coordinates":[-83.279701,42.4575],"type":"Point"}
}