{
  "type": "Feature",
  "properties": {
    "iso:country":"US",
    "sg:address":"3659 Hillcrest Rd",
    "sg:city":"Hudsonville",
    "sg:classifiers":[
        {
            "category":"Professional",
            "type":"Services"
        }
    ],
    "sg:phone":"+1 616 662 1066",
    "sg:postcode":"49426",
    "sg:province":"MI",
    "sg:tags":[
        "establishment"
    ],
    "wof:name":"Opti Tech",
    "wof:placetype":"venue"
},
  "geometry": {"coordinates":[-85.874388,42.874202],"type":"Point"}
}