{
  "type": "Feature",
  "properties": {
    "iso:country":"US",
    "sg:address":"8268 Lamplight Dr",
    "sg:city":"Jenison",
    "sg:classifiers":[
        {
            "category":"Wholesale",
            "subcategory":"Furniture",
            "type":"Manufacturing & Wholesale Goods"
        }
    ],
    "sg:phone":"+1 616 457 0115",
    "sg:postcode":"49428",
    "sg:province":"MI",
    "wof:name":"Bittner Filing Systems",
    "wof:placetype":"venue"
},
  "geometry": {"coordinates":[-85.840045,42.92097],"type":"Point"}
}