{
  "type": "Feature",
  "properties": {
    "iso:country":"US",
    "sg:address":"6939 Apache Trl",
    "sg:city":"Westland",
    "sg:classifiers":[
        {
            "category":"Building & Trades",
            "subcategory":"Electrical",
            "type":"Services"
        }
    ],
    "sg:phone":"+1 734 595 4608",
    "sg:postcode":"48185",
    "sg:province":"MI",
    "sg:tags":[
        "electrical",
        "contractor"
    ],
    "wof:name":"Charles Hammontree & Sigma Elc",
    "wof:placetype":"venue"
},
  "geometry": {"coordinates":[-83.37581400000001,42.336278],"type":"Point"}
}