{
  "type": "Feature",
  "properties": {
    "iso:country":"US",
    "sg:address":"718 W Saginaw St",
    "sg:city":"Lansing",
    "sg:classifiers":[
        {
            "category":"Autos & Motor Vehicles",
            "subcategory":"Auto Supplies",
            "type":"Retail Goods"
        }
    ],
    "sg:phone":"+1 517 482 2340",
    "sg:postcode":"48915",
    "sg:province":"MI",
    "sg:tags":[
        "automobile",
        "parts"
    ],
    "wof:name":"Lansing Auto Supply Co",
    "wof:placetype":"venue"
},
  "geometry": {"coordinates":[-84.562753,42.741031],"type":"Point"}
}