{
  "type": "Feature",
  "properties": {
    "iso:country":"US",
    "sg:address":"6234 Towar Ave",
    "sg:city":"East Lansing",
    "sg:classifiers":[
        {
            "category":"Travel",
            "subcategory":"Hotels & Motels",
            "type":"Entertainment"
        }
    ],
    "sg:phone":"+1 517 337 7152",
    "sg:postcode":"48823",
    "sg:province":"MI",
    "sg:tags":[
        "operation"
    ],
    "wof:name":"Home Health Aide Inn",
    "wof:placetype":"venue"
},
  "geometry": {"coordinates":[-84.47525,42.758607],"type":"Point"}
}