{
  "type": "Feature",
  "properties": {
    "iso:country":"US",
    "sg:address":"11250 Fulton St E",
    "sg:city":"Lowell",
    "sg:classifiers":[
        {
            "category":"Autos & Motor Vehicles",
            "subcategory":"Automobile Sales",
            "type":"Retail Goods"
        }
    ],
    "sg:phone":"+1 616 897 9700",
    "sg:postcode":"49331",
    "sg:province":"MI",
    "sg:tags":[
        "car",
        "dealer"
    ],
    "wof:name":"Classic Car Co",
    "wof:placetype":"venue"
},
  "geometry": {"coordinates":[-85.40602199999999,42.925349],"type":"Point"}
}