{
  "type": "Feature",
  "properties": {
    "iso:country":"US",
    "sg:address":"1400 S Stephenson Ave",
    "sg:city":"Iron Mountain",
    "sg:classifiers":[
        {
            "category":"Autos & Motor Vehicles",
            "subcategory":"Automobile Sales",
            "type":"Retail Goods"
        }
    ],
    "sg:phone":"+1 906 774 8900",
    "sg:postcode":"49801",
    "sg:province":"MI",
    "sg:tags":[
        "truck"
    ],
    "wof:name":"Schultz Equipment & Parts Co",
    "wof:placetype":"venue"
},
  "geometry": {"coordinates":[-88.05742499999999,45.810215],"type":"Point"}
}