{
  "type": "Feature",
  "properties": {
    "iso:country":"US",
    "sg:address":"8888 Lansing Rd",
    "sg:city":"Durand",
    "sg:classifiers":[
        {
            "category":"Real Estate",
            "subcategory":"Real Estate Operator",
            "type":"Services"
        }
    ],
    "sg:phone":"+1 989 288 6825",
    "sg:postcode":"48429",
    "sg:province":"MI",
    "sg:tags":[
        "building",
        "apartment"
    ],
    "wof:name":"Country Village Apartments",
    "wof:placetype":"venue"
},
  "geometry": {"coordinates":[-83.98967,42.92521],"type":"Point"}
}