{
  "type": "Feature",
  "properties": {
    "iso:country":"US",
    "sg:address":"25175 Code Rd",
    "sg:city":"Southfield",
    "sg:classifiers":[
        {
            "category":"Social Services",
            "subcategory":"Child Care",
            "type":"Services"
        },
        {
            "category":"Education",
            "subcategory":"Preschool",
            "type":"Public Place"
        },
        {
            "category":"Education",
            "subcategory":"School",
            "type":"Public Place"
        }
    ],
    "sg:phone":"+1 248 358 1677",
    "sg:postcode":"48034",
    "sg:province":"MI",
    "sg:tags":[
        "elementary",
        "day"
    ],
    "wof:name":"Waldorf Kinder House",
    "wof:placetype":"venue"
},
  "geometry": {"coordinates":[-83.2687,42.473999],"type":"Point"}
}