{
  "type": "Feature",
  "properties": {
    "iso:country":"US",
    "sg:address":"3017 Amherst Dr",
    "sg:city":"Lansing",
    "sg:classifiers":[
        {
            "category":"Social Services",
            "subcategory":"Child Care",
            "type":"Services"
        }
    ],
    "sg:phone":"+1 517 323 7386",
    "sg:postcode":"48906",
    "sg:province":"MI",
    "sg:tags":[
        "day",
        "provider"
    ],
    "wof:name":"Anna Brooks",
    "wof:placetype":"venue"
},
  "geometry": {"coordinates":[-84.59805799999999,42.764445],"type":"Point"}
}