{
  "type": "Feature",
  "properties": {
    "iso:country":"US",
    "sg:address":"139 Edmonds Rd",
    "sg:city":"Battle Creek",
    "sg:classifiers":[
        {
            "category":"Professional",
            "subcategory":"Art Services",
            "type":"Services"
        }
    ],
    "sg:phone":"+1 269 963 4533",
    "sg:postcode":"49017",
    "sg:province":"MI",
    "sg:tags":[
        "graphic",
        "designer"
    ],
    "wof:name":"Herr's Graphic & Design Studio",
    "wof:placetype":"venue"
},
  "geometry": {"coordinates":[-85.22943100000001,42.395202],"type":"Point"}
}