{
  "type": "Feature",
  "properties": {
    "iso:country":"US",
    "sg:address":"25882 Orchard Lake Rd",
    "sg:city":"Farmington Hills",
    "sg:classifiers":[
        {
            "category":"Health Services",
            "subcategory":"Health Practitioner",
            "type":"Services"
        },
        {
            "category":"Health Services",
            "subcategory":"Doctor",
            "type":"Services"
        }
    ],
    "sg:phone":"+1 248 442 6600",
    "sg:postcode":"48336",
    "sg:province":"MI",
    "sg:tags":[
        "dentist"
    ],
    "sg:website":"www.mobiledentists.com",
    "wof:name":"Mobile Dentists PC",
    "wof:placetype":"venue"
},
  "geometry": {"coordinates":[-83.357677,42.483505],"type":"Point"}
}