{
  "type": "Feature",
  "properties": {
    "iso:country":"US",
    "sg:address":"3263 Shadydale Ln",
    "sg:city":"West Bloomfield",
    "sg:classifiers":[
        {
            "category":"Retail",
            "subcategory":"Portrait Studio",
            "type":"Services"
        }
    ],
    "sg:phone":"+1 248 851 8950",
    "sg:postcode":"48323",
    "sg:province":"MI",
    "sg:tags":[
        "painted",
        "photography",
        "hand"
    ],
    "wof:name":"Picture This",
    "wof:placetype":"venue"
},
  "geometry": {"coordinates":[-83.34604400000001,42.579184],"type":"Point"}
}