{
  "type": "Feature",
  "properties": {
    "iso:country":"US",
    "sg:address":"805 Spruce St",
    "sg:city":"Ironwood",
    "sg:classifiers":[
        {
            "category":"Retail",
            "subcategory":"Auto Repair",
            "type":"Services"
        }
    ],
    "sg:phone":"+1 906 932 3995",
    "sg:postcode":"49938",
    "sg:province":"MI",
    "sg:tags":[
        "general"
    ],
    "wof:name":"Superior Diesel",
    "wof:placetype":"venue"
},
  "geometry": {"coordinates":[-90.170007,46.442588],"type":"Point"}
}