{
  "type": "Feature",
  "properties": {
    "iso:country":"US",
    "sg:address":"69 54th St SW",
    "sg:city":"Wyoming",
    "sg:classifiers":[
        {
            "category":"Personal",
            "subcategory":"Tanning Parlor",
            "type":"Services"
        }
    ],
    "sg:phone":"+1 616 531 8034",
    "sg:postcode":"49548",
    "sg:province":"MI",
    "sg:tags":[
        "salon"
    ],
    "wof:name":"Electric Beach",
    "wof:placetype":"venue"
},
  "geometry": {"coordinates":[-85.66696899999999,42.865942],"type":"Point"}
}