{
  "type": "Feature",
  "properties": {
    "iso:country":"US",
    "sg:address":"1405 E Isabella Ave",
    "sg:city":"Muskegon",
    "sg:classifiers":[
        {
            "category":"Manufacturing",
            "subcategory":"Signs",
            "type":"Manufacturing & Wholesale Goods"
        }
    ],
    "sg:phone":"+1 231 773 5575",
    "sg:postcode":"49442",
    "sg:province":"MI",
    "wof:name":"Muskegon Sign Art",
    "wof:placetype":"venue"
},
  "geometry": {"coordinates":[-86.207836,43.232294],"type":"Point"}
}