{
  "type": "Feature",
  "properties": {
    "iso:country":"US",
    "sg:address":"1535 Old US Hwy 23",
    "sg:city":"Howell",
    "sg:classifiers":[
        {
            "category":"Sports & Exercise",
            "subcategory":"Bowling",
            "type":"Entertainment"
        }
    ],
    "sg:phone":"+1 810 632 5241",
    "sg:postcode":"48843",
    "sg:province":"MI",
    "sg:tags":[
        "center"
    ],
    "wof:name":"Striking Lanes",
    "wof:placetype":"venue"
},
  "geometry": {"coordinates":[-83.752758,42.628633],"type":"Point"}
}