{
  "type": "Feature",
  "properties": {
    "iso:country":"US",
    "sg:address":"15303 Merriman Rd",
    "sg:city":"Livonia",
    "sg:classifiers":[
        {
            "category":"Food & Beverages",
            "subcategory":"Meat & Fish",
            "type":"Retail Goods"
        }
    ],
    "sg:phone":"+1 734 525 2994",
    "sg:postcode":"48154",
    "sg:province":"MI",
    "sg:tags":[
        "shop"
    ],
    "wof:name":"Honeybaked Ham Company the",
    "wof:placetype":"venue"
},
  "geometry": {"coordinates":[-83.354781,42.39832],"type":"Point"}
}