{
  "type": "Feature",
  "properties": {
    "iso:country":"US",
    "sg:address":"5832 Highland Rd",
    "sg:city":"Waterford",
    "sg:classifiers":[
        {
            "category":"Retail",
            "subcategory":"Laundry & Dry Cleaning",
            "type":"Services"
        }
    ],
    "sg:phone":"+1 248 673 3679",
    "sg:postcode":"48327",
    "sg:province":"MI",
    "sg:tags":[
        "drycleaning",
        "plant"
    ],
    "wof:name":"Sim Cleaners",
    "wof:placetype":"venue"
},
  "geometry": {"coordinates":[-83.403516,42.660042],"type":"Point"}
}