{
  "type": "Feature",
  "properties": {
    "iso:country":"US",
    "sg:address":"100 Belvedere Ave",
    "sg:city":"Charlevoix",
    "sg:classifiers":[
        {
            "category":"Professional",
            "type":"Services"
        }
    ],
    "sg:phone":"+1 231 547 2370",
    "sg:postcode":"49720",
    "sg:province":"MI",
    "sg:tags":[
        "establishment"
    ],
    "wof:name":"Access Cash Machine",
    "wof:placetype":"venue"
},
  "geometry": {"coordinates":[-85.25543999999999,45.314733],"type":"Point"}
}