{
  "type": "Feature",
  "properties": {
    "iso:country":"US",
    "sg:address":"29417 Hoover Rd",
    "sg:city":"Warren",
    "sg:classifiers":[
        {
            "category":"Professional",
            "subcategory":"Employment Agencies",
            "type":"Services"
        }
    ],
    "sg:phone":"+1 586 573 0400",
    "sg:postcode":"48093",
    "sg:province":"MI",
    "sg:tags":[
        "opportunity"
    ],
    "wof:name":"Employment One",
    "wof:placetype":"venue"
},
  "geometry": {"coordinates":[-83.00724200000001,42.510363],"type":"Point"}
}