{
  "type": "Feature",
  "properties": {
    "iso:country":"US",
    "sg:address":"20795 Mack Ave",
    "sg:city":"Grosse Pointe",
    "sg:classifiers":[
        {
            "category":"Bars & Pubs",
            "type":"Food & Drink"
        },
        {
            "category":"Restaurant",
            "type":"Food & Drink"
        }
    ],
    "sg:phone":"+1 313 881 3985",
    "sg:postcode":"48236",
    "sg:province":"MI",
    "sg:tags":[
        "new",
        "american"
    ],
    "wof:name":"Telly's Place",
    "wof:placetype":"venue"
},
  "geometry": {"coordinates":[-82.90679900000001,42.445599],"type":"Point"}
}