{
  "type": "Feature",
  "properties": {
    "iso:country":"US",
    "sg:address":"3086 W Pasadena Ave",
    "sg:city":"Flint",
    "sg:classifiers":[
        {
            "category":"Home & Garden",
            "subcategory":"Building Materials",
            "type":"Retail Goods"
        }
    ],
    "sg:phone":"+1 810 732 7020",
    "sg:postcode":"48504",
    "sg:province":"MI",
    "sg:tags":[
        "equipment",
        "electric",
        "supply"
    ],
    "wof:name":"Win's Electrical Supply",
    "wof:placetype":"venue"
},
  "geometry": {"coordinates":[-83.736638,43.046276],"type":"Point"}
}