{
  "type": "Feature",
  "properties": {
    "iso:country":"US",
    "sg:address":"26665 Townley St",
    "sg:city":"Madison Heights",
    "sg:classifiers":[
        {
            "category":"Manufacturing",
            "subcategory":"Apparel",
            "type":"Manufacturing & Wholesale Goods"
        }
    ],
    "sg:phone":"+1 248 591 7249",
    "sg:postcode":"48071",
    "sg:province":"MI",
    "wof:name":"Gr Stitch",
    "wof:placetype":"venue"
},
  "geometry": {"coordinates":[-83.10300599999999,42.488831],"type":"Point"}
}