{
  "type": "Feature",
  "properties": {
    "iso:country":"US",
    "sg:address":"2751 28th St SE",
    "sg:city":"Grand Rapids",
    "sg:classifiers":[
        {
            "category":"Personal",
            "subcategory":"Tanning Parlor",
            "type":"Services"
        }
    ],
    "sg:phone":"+1 616 285 2600",
    "sg:postcode":"49512",
    "sg:province":"MI",
    "sg:tags":[
        "salon"
    ],
    "wof:name":"Mirage Tanning Ctr",
    "wof:placetype":"venue"
},
  "geometry": {"coordinates":[-85.597661,42.912586],"type":"Point"}
}