{
  "type": "Feature",
  "properties": {
    "iso:country":"US",
    "sg:address":"1932 Portage St",
    "sg:city":"Kalamazoo",
    "sg:classifiers":[
        {
            "category":"Organizations",
            "subcategory":"Religious Organization",
            "type":"Services"
        }
    ],
    "sg:phone":"+1 269 342 2870",
    "sg:postcode":"49001",
    "sg:province":"MI",
    "sg:tags":[
        "church"
    ],
    "wof:name":"New Beginning Tabernacle",
    "wof:placetype":"venue"
},
  "geometry": {"coordinates":[-85.571977,42.272942],"type":"Point"}
}