{
  "type": "Feature",
  "properties": {
    "iso:country":"US",
    "sg:address":"6407 Gratiot Ave",
    "sg:city":"Detroit",
    "sg:classifiers":[
        {
            "category":"Food & Beverages",
            "subcategory":"Liquor & Beverages",
            "type":"Retail Goods"
        }
    ],
    "sg:phone":"+1 313 571 5416",
    "sg:postcode":"48207",
    "sg:province":"MI",
    "sg:tags":[
        "ticket",
        "lottery",
        "grocery"
    ],
    "wof:name":"Jazz Liquor Store Inc",
    "wof:placetype":"venue"
},
  "geometry": {"coordinates":[-83.022901,42.366555],"type":"Point"}
}