{
  "type": "Feature",
  "properties": {
    "iso:country":"US",
    "sg:address":"4353 Sawkaw Dr NE",
    "sg:city":"Grand Rapids",
    "sg:classifiers":[
        {
            "category":"Health Services",
            "subcategory":"Doctor",
            "type":"Services"
        }
    ],
    "sg:phone":"+1 616 363 9821",
    "sg:postcode":"49525",
    "sg:province":"MI",
    "sg:tags":[
        "orthodontist"
    ],
    "wof:name":"Ed Herremans DDS PC",
    "wof:placetype":"venue"
},
  "geometry": {"coordinates":[-85.60435099999999,43.041188],"type":"Point"}
}