{
  "type": "Feature",
  "properties": {
    "iso:country":"US",
    "sg:address":"953 Beaconsfield Ave",
    "sg:city":"Grosse Pointe",
    "sg:classifiers":[
        {
            "category":"Building & Trades",
            "subcategory":"Construction",
            "type":"Services"
        }
    ],
    "sg:phone":"+1 313 824 2425",
    "sg:postcode":"48230",
    "sg:province":"MI",
    "sg:tags":[
        "residential"
    ],
    "wof:name":"Nolan Ej & Co",
    "wof:placetype":"venue"
},
  "geometry": {"coordinates":[-82.934605,42.375224],"type":"Point"}
}