{
  "type": "Feature",
  "properties": {
    "iso:country":"US",
    "sg:address":"8346 Port Austin Rd",
    "sg:city":"Pigeon",
    "sg:classifiers":[
        {
            "category":"Autos & Motor Vehicles",
            "subcategory":"Boat Sales",
            "type":"Retail Goods"
        }
    ],
    "sg:phone":"+1 989 856 4873",
    "sg:postcode":"48755",
    "sg:province":"MI",
    "sg:tags":[
        "top",
        "upholstery",
        "cover"
    ],
    "wof:name":"Lenz Canvas & Vinyl Works",
    "wof:placetype":"venue"
},
  "geometry": {"coordinates":[-83.32233600000001,43.894175],"type":"Point"}
}