{
  "type": "Feature",
  "properties": {
    "iso:country":"US",
    "sg:address":"5900 N Lilley Rd Ste 115",
    "sg:city":"Canton",
    "sg:classifiers":[
        {
            "category":"Professional",
            "subcategory":"Employment Agencies",
            "type":"Services"
        }
    ],
    "sg:phone":"+1 734 981 3709",
    "sg:postcode":"48187",
    "sg:province":"MI",
    "wof:name":"Community Work Opportunities",
    "wof:placetype":"venue"
},
  "geometry": {"coordinates":[-83.458702,42.325199],"type":"Point"}
}