{
  "type": "Feature",
  "properties": {
    "iso:country":"US",
    "sg:address":"2245 Fort St",
    "sg:city":"Wyandotte",
    "sg:classifiers":[
        {
            "category":"Home & Garden",
            "subcategory":"Hardware",
            "type":"Retail Goods"
        }
    ],
    "sg:phone":"+1 734 282 9922",
    "sg:postcode":"48192",
    "sg:province":"MI",
    "sg:tags":[
        "store"
    ],
    "wof:name":"Ace Hardware",
    "wof:placetype":"venue"
},
  "geometry": {"coordinates":[-83.180397,42.2113],"type":"Point"}
}