{
  "type": "Feature",
  "properties": {
    "iso:country":"US",
    "sg:address":"328 Winter Ave NW",
    "sg:city":"Grand Rapids",
    "sg:classifiers":[
        {
            "category":"Professional",
            "type":"Services"
        }
    ],
    "sg:phone":"+1 616 459 8893",
    "sg:postcode":"49504",
    "sg:province":"MI",
    "sg:tags":[
        "establishment"
    ],
    "wof:name":"Huver & Huver Inc",
    "wof:placetype":"venue"
},
  "geometry": {"coordinates":[-85.681065,42.968708],"type":"Point"}
}