{
  "type": "Feature",
  "properties": {
    "iso:country":"US",
    "sg:address":"1540 E 12 Mile Rd",
    "sg:city":"Madison Heights",
    "sg:classifiers":[
        {
            "category":"Restaurant",
            "type":"Food & Drink"
        }
    ],
    "sg:menulink":"http://www.allmenus.com/mi/madison-heights/197211-burger-king/menu/",
    "sg:phone":"+1 248 398 7989",
    "sg:postcode":"48071",
    "sg:province":"MI",
    "sg:tags":[
        "burger",
        "american"
    ],
    "wof:name":"Burger King",
    "wof:placetype":"venue"
},
  "geometry": {"coordinates":[-83.088751,42.504718],"type":"Point"}
}