{
  "type": "Feature",
  "properties": {
    "iso:country":"US",
    "sg:address":"43700 Woodward Ave Ste 111",
    "sg:city":"Bloomfield Hills",
    "sg:classifiers":[
        {
            "category":"Health Services",
            "subcategory":"Dentist",
            "type":"Services"
        }
    ],
    "sg:phone":"+1 248 332 3388",
    "sg:postcode":"48302",
    "sg:province":"MI",
    "wof:name":"Huntington Group PC",
    "wof:placetype":"venue"
},
  "geometry": {"coordinates":[-83.2696,42.6096],"type":"Point"}
}