{
  "type": "Feature",
  "properties": {
    "iso:country":"US",
    "sg:address":"189 W Clarkston Rd",
    "sg:city":"Lake Orion",
    "sg:classifiers":[
        {
            "category":"Wholesale",
            "subcategory":"Home Furnishings",
            "type":"Manufacturing & Wholesale Goods"
        }
    ],
    "sg:phone":"+1 248 693 4778",
    "sg:postcode":"48362",
    "sg:province":"MI",
    "sg:tags":[
        "closet",
        "accessory"
    ],
    "wof:name":"AAA Building Supplies Inc",
    "wof:placetype":"venue"
},
  "geometry": {"coordinates":[-83.24346799999999,42.76735],"type":"Point"}
}