{
  "type": "Feature",
  "properties": {
    "iso:country":"US",
    "sg:address":"31610 W 8 Mile Rd",
    "sg:city":"Farmington Hills",
    "sg:classifiers":[
        {
            "category":"Manufacturing",
            "subcategory":"Metals",
            "type":"Manufacturing & Wholesale Goods"
        }
    ],
    "sg:phone":"+1 248 478 5900",
    "sg:postcode":"48152",
    "sg:province":"MI",
    "sg:tags":[
        "treating",
        "heat"
    ],
    "wof:name":"Specialty Steel Treating Inc",
    "wof:placetype":"venue"
},
  "geometry": {"coordinates":[-83.360657,42.440889],"type":"Point"}
}