{
  "type": "Feature",
  "properties": {
    "iso:country":"US",
    "sg:address":"221 N Monroe St",
    "sg:city":"Monroe",
    "sg:classifiers":[
        {
            "category":"Retail",
            "subcategory":"Repair Shop",
            "type":"Services"
        }
    ],
    "sg:phone":"+1 734 242 7474",
    "sg:postcode":"48162",
    "sg:province":"MI",
    "sg:tags":[
        "lock",
        "locksmith"
    ],
    "wof:name":"Monroe Lock & Safe Co",
    "wof:placetype":"venue"
},
  "geometry": {"coordinates":[-83.39536200000001,41.920502],"type":"Point"}
}