{
  "type": "Feature",
  "properties": {
    "iso:country":"US",
    "sg:address":"3704 Clyde Park Ave SW",
    "sg:city":"Wyoming",
    "sg:classifiers":[
        {
            "category":"Retail",
            "subcategory":"Laundry & Dry Cleaning",
            "type":"Services"
        }
    ],
    "sg:phone":"+1 616 534 0122",
    "sg:postcode":"49509",
    "sg:province":"MI",
    "sg:tags":[
        "cleaners"
    ],
    "wof:name":"Clyde Park Coin Laundry & Dry",
    "wof:placetype":"venue"
},
  "geometry": {"coordinates":[-85.68483999999999,42.895649],"type":"Point"}
}