{
  "type": "Feature",
  "properties": {
    "iso:country":"US",
    "sg:address":"4555 Pelton Rd",
    "sg:city":"Clarkston",
    "sg:classifiers":[
        {
            "category":"Shopping",
            "subcategory":"Bicycles & Sporting Goods",
            "type":"Retail Goods"
        }
    ],
    "sg:phone":"+1 248 673 8400",
    "sg:postcode":"48346",
    "sg:province":"MI",
    "wof:name":"Rage Sports Inc",
    "wof:placetype":"venue"
},
  "geometry": {"coordinates":[-83.37958500000001,42.711723],"type":"Point"}
}