{
  "type": "Feature",
  "properties": {
    "iso:country":"US",
    "sg:address":"12707 Birwood St",
    "sg:city":"Detroit",
    "sg:classifiers":[
        {
            "category":"Social Services",
            "subcategory":"Child Care",
            "type":"Services"
        }
    ],
    "sg:phone":"+1 313 491 6927",
    "sg:postcode":"48238",
    "sg:province":"MI",
    "sg:tags":[
        "day"
    ],
    "wof:name":"Mary Andrews",
    "wof:placetype":"venue"
},
  "geometry": {"coordinates":[-83.16324,42.382918],"type":"Point"}
}