{
  "type": "Feature",
  "properties": {
    "iso:country":"US",
    "sg:address":"78070 Capac Rd",
    "sg:city":"Armada",
    "sg:classifiers":[
        {
            "category":"Shopping",
            "subcategory":"Clothing, Apparel, & Fashions",
            "type":"Retail Goods"
        }
    ],
    "sg:phone":"+1 586 784 9093",
    "sg:postcode":"48005",
    "sg:province":"MI",
    "sg:tags":[
        "accessory"
    ],
    "wof:name":"Underwear Home Parties",
    "wof:placetype":"venue"
},
  "geometry": {"coordinates":[-82.94537,42.878545],"type":"Point"}
}