{
  "type": "Feature",
  "properties": {
    "iso:country":"US",
    "sg:address":"137 S Main St",
    "sg:city":"Adrian",
    "sg:classifiers":[
        {
            "category":"Sports & Exercise",
            "subcategory":"Gym",
            "type":"Entertainment"
        }
    ],
    "sg:phone":"+1 517 265 5533",
    "sg:postcode":"49221",
    "sg:province":"MI",
    "sg:tags":[
        "club",
        "health",
        "studio",
        "gymnasium"
    ],
    "wof:name":"Jeff Willet's Powerhouse Gym",
    "wof:placetype":"venue"
},
  "geometry": {"coordinates":[-84.03682499999999,41.898218],"type":"Point"}
}