{
  "type": "Feature",
  "properties": {
    "iso:country":"US",
    "sg:address":"29347 Ann Arbor Trl",
    "sg:city":"Westland",
    "sg:classifiers":[
        {
            "category":"Shopping",
            "subcategory":"Pharmacy",
            "type":"Retail Goods"
        }
    ],
    "sg:phone":"+1 734 522 5200",
    "sg:postcode":"48185",
    "sg:province":"MI",
    "sg:tags":[
        "drugstore"
    ],
    "sg:website":"www.cvs.com",
    "wof:name":"Cvs Pharmacy",
    "wof:placetype":"venue"
},
  "geometry": {"coordinates":[-83.332787,42.347038],"type":"Point"}
}