{
  "type": "Feature",
  "properties": {
    "iso:country":"US",
    "sg:address":"6645 Bentley Lake Rd",
    "sg:city":"Pinckney",
    "sg:classifiers":[
        {
            "category":"Building & Trades",
            "subcategory":"Construction",
            "type":"Services"
        }
    ],
    "sg:phone":"+1 734 878 1677",
    "sg:postcode":"48169",
    "sg:province":"MI",
    "sg:tags":[
        "contractor"
    ],
    "wof:name":"Quality Services Ceilings",
    "wof:placetype":"venue"
},
  "geometry": {"coordinates":[-83.96954100000001,42.499554],"type":"Point"}
}