{
  "type": "Feature",
  "properties": {
    "iso:country":"US",
    "sg:address":"236 Hubbard St",
    "sg:city":"Allegan",
    "sg:classifiers":[
        {
            "category":"Banks & Credit Unions",
            "subcategory":"Bank",
            "type":"Services"
        }
    ],
    "sg:phone":"+1 269 686 7167",
    "sg:postcode":"49010",
    "sg:province":"MI",
    "wof:name":"Chemical Bank Shoreline",
    "wof:placetype":"venue"
},
  "geometry": {"coordinates":[-85.85016,42.527726],"type":"Point"}
}