{
  "type": "Feature",
  "properties": {
    "iso:country":"US",
    "sg:address":"125 Howard St",
    "sg:city":"Big Rapids",
    "sg:classifiers":[
        {
            "category":"Home & Garden",
            "subcategory":"Building Materials",
            "type":"Retail Goods"
        }
    ],
    "sg:phone":"+1 231 796 5783",
    "sg:postcode":"49307",
    "sg:province":"MI",
    "sg:tags":[
        "glass",
        "window",
        "plate"
    ],
    "wof:name":"United Glass Of Big Rapids Inc",
    "wof:placetype":"venue"
},
  "geometry": {"coordinates":[-85.469673,43.701161],"type":"Point"}
}