{
  "type": "Feature",
  "properties": {
    "iso:country":"US",
    "sg:address":"6117 Crest Rd",
    "sg:city":"Jackson",
    "sg:classifiers":[
        {
            "category":"Manufacturing",
            "subcategory":"Apparel",
            "type":"Manufacturing & Wholesale Goods"
        }
    ],
    "sg:phone":"+1 517 796 9982",
    "sg:postcode":"49203",
    "sg:province":"MI",
    "wof:name":"Kathys Kreations",
    "wof:placetype":"venue"
},
  "geometry": {"coordinates":[-84.412592,42.186044],"type":"Point"}
}