{
  "type": "Feature",
  "properties": {
    "iso:country":"US",
    "sg:address":"9303 S Johnson Rd",
    "sg:city":"Blanchard",
    "sg:classifiers":[
        {
            "category":"Social Services",
            "subcategory":"Child Care",
            "type":"Services"
        }
    ],
    "sg:phone":"+1 989 866 2315",
    "sg:postcode":"49310",
    "sg:province":"MI",
    "sg:tags":[
        "day"
    ],
    "wof:name":"Christine A Eldred",
    "wof:placetype":"venue"
},
  "geometry": {"coordinates":[-84.956434,43.509966],"type":"Point"}
}