{
  "type": "Feature",
  "properties": {
    "iso:country":"US",
    "sg:address":"19611 Alcoy St",
    "sg:city":"Detroit",
    "sg:classifiers":[
        {
            "category":"Social Services",
            "type":"Services"
        }
    ],
    "sg:phone":"+1 313 371 4766",
    "sg:postcode":"48205",
    "sg:province":"MI",
    "sg:tags":[
        "youth",
        "center"
    ],
    "wof:name":"Wash Youth Athletic Center",
    "wof:placetype":"venue"
},
  "geometry": {"coordinates":[-82.989023,42.439372],"type":"Point"}
}