{
  "type": "Feature",
  "properties": {
    "iso:country":"US",
    "sg:address":"735 W Philadelphia St",
    "sg:city":"Detroit",
    "sg:classifiers":[
        {
            "category":"Arts & Performance",
            "subcategory":"Theater",
            "type":"Entertainment"
        }
    ],
    "sg:phone":"+1 313 875 5216",
    "sg:postcode":"48202",
    "sg:province":"MI",
    "sg:tags":[
        "group"
    ],
    "wof:name":"Vision Production",
    "wof:placetype":"venue"
},
  "geometry": {"coordinates":[-83.08295699999999,42.376449],"type":"Point"}
}