{
  "type": "Feature",
  "properties": {
    "iso:country":"US",
    "sg:address":"1925 Ford Ave",
    "sg:city":"Wyandotte",
    "sg:classifiers":[
        {
            "category":"Social Services",
            "subcategory":"Child Care",
            "type":"Services"
        }
    ],
    "sg:phone":"+1 734 281 7399",
    "sg:postcode":"48192",
    "sg:province":"MI",
    "sg:tags":[
        "elementary",
        "school",
        "day"
    ],
    "wof:name":"Wyandotte Co Operative Nursery School",
    "wof:placetype":"venue"
},
  "geometry": {"coordinates":[-83.175201,42.213799],"type":"Point"}
}