{
  "type": "Feature",
  "properties": {
    "iso:country":"US",
    "sg:address":"3701 Bangor Rd",
    "sg:city":"Bay City",
    "sg:classifiers":[
        {
            "category":"Retail",
            "subcategory":"Animal Services",
            "type":"Services"
        }
    ],
    "sg:phone":"+1 989 684 8413",
    "sg:postcode":"48706",
    "sg:province":"MI",
    "sg:tags":[
        "farm",
        "raw",
        "product",
        "material"
    ],
    "wof:name":"Mjs Paints & Quarter Horses",
    "wof:placetype":"venue"
},
  "geometry": {"coordinates":[-83.883871,43.629512],"type":"Point"}
}