{
  "type": "Feature",
  "properties": {
    "iso:country":"US",
    "sg:address":"1939 Adelaide St",
    "sg:city":"Detroit",
    "sg:classifiers":[
        {
            "category":"Food & Beverages",
            "subcategory":"Meat & Fish",
            "type":"Retail Goods"
        }
    ],
    "sg:phone":"+1 313 963 2900",
    "sg:postcode":"48207",
    "sg:province":"MI",
    "sg:tags":[
        "shop"
    ],
    "wof:name":"K D B Inc",
    "wof:placetype":"venue"
},
  "geometry": {"coordinates":[-83.035832,42.348477],"type":"Point"}
}