{
  "type": "Feature",
  "properties": {
    "iso:country":"US",
    "sg:address":"4285 Consear Rd",
    "sg:city":"Lambertville",
    "sg:classifiers":[
        {
            "category":"Shopping",
            "type":"Retail Goods"
        }
    ],
    "sg:phone":"+1 734 856 1258",
    "sg:postcode":"48144",
    "sg:province":"MI",
    "sg:tags":[
        "monument"
    ],
    "wof:name":"Le Clair Monuments",
    "wof:placetype":"venue"
},
  "geometry": {"coordinates":[-83.646699,41.770348],"type":"Point"}
}