{
  "type": "Feature",
  "properties": {
    "iso:country":"US",
    "sg:address":"2450 E Lansing Dr",
    "sg:city":"East Lansing",
    "sg:classifiers":[
        {
            "category":"Restaurant",
            "type":"Food & Drink"
        }
    ],
    "sg:phone":"+1 517 336 5926",
    "sg:postcode":"48823",
    "sg:province":"MI",
    "wof:name":"Applebee's Neighborhood Grill",
    "wof:placetype":"venue"
},
  "geometry": {"coordinates":[-84.449983,42.749248],"type":"Point"}
}