{
  "type": "Feature",
  "properties": {
    "iso:country":"US",
    "sg:address":"400 Orchard Ave",
    "sg:city":"Battle Creek",
    "sg:classifiers":[
        {
            "category":"Professional",
            "subcategory":"Management & Consulting",
            "type":"Services"
        }
    ],
    "sg:phone":"+1 269 962 7775",
    "sg:postcode":"49017",
    "sg:province":"MI",
    "sg:tags":[
        "consultant",
        "business"
    ],
    "wof:name":"Managing Decisions Inc",
    "wof:placetype":"venue"
},
  "geometry": {"coordinates":[-85.169963,42.334944],"type":"Point"}
}