{
  "type": "Feature",
  "properties": {
    "iso:country":"US",
    "sg:address":"6820 Angling Rd",
    "sg:city":"Cottrellville",
    "sg:classifiers":[
        {
            "category":"Building & Trades",
            "subcategory":"Landscaping Services",
            "type":"Services"
        }
    ],
    "sg:phone":"+1 810 765 9317",
    "sg:postcode":"48039",
    "sg:province":"MI",
    "sg:tags":[
        "landscape",
        "contractor"
    ],
    "wof:name":"Starville Landscape Co",
    "wof:placetype":"venue"
},
  "geometry": {"coordinates":[-82.579542,42.678805],"type":"Point"}
}