{
  "type": "Feature",
  "properties": {
    "iso:country":"US",
    "sg:address":"823 S Lake St",
    "sg:city":"Boyne City",
    "sg:classifiers":[
        {
            "category":"Real Estate",
            "subcategory":"Real Estate Agent",
            "type":"Services"
        }
    ],
    "sg:phone":"+1 231 582 3200",
    "sg:postcode":"49712",
    "sg:province":"MI",
    "sg:website":"www.accommodationsnorth.com",
    "wof:name":"Accomodations North",
    "wof:placetype":"venue"
},
  "geometry": {"coordinates":[-85.01518799999999,45.20568],"type":"Point"}
}