{
  "type": "Feature",
  "properties": {
    "iso:country":"US",
    "sg:address":"161 W Michigan Ave",
    "sg:city":"Jackson",
    "sg:classifiers":[
        {
            "category":"Government",
            "subcategory":"Office",
            "type":"Public Place"
        }
    ],
    "sg:phone":"+1 517 788 4044",
    "sg:postcode":"49201",
    "sg:province":"MI",
    "sg:tags":[
        "city",
        "taxation"
    ],
    "wof:name":"Jackson Income Tax Div",
    "wof:placetype":"venue"
},
  "geometry": {"coordinates":[-84.407447,42.247417],"type":"Point"}
}