{
  "type": "Feature",
  "properties": {
    "iso:country":"US",
    "sg:address":"1153 Oak Valley Dr",
    "sg:city":"Ann Arbor",
    "sg:classifiers":[
        {
            "category":"Wholesale",
            "subcategory":"Hardware",
            "type":"Manufacturing & Wholesale Goods"
        }
    ],
    "sg:phone":"+1 734 302 1100",
    "sg:postcode":"48108",
    "sg:province":"MI",
    "sg:tags":[
        "energy",
        "recovery",
        "system"
    ],
    "wof:name":"Gas Recovery Systems",
    "wof:placetype":"venue"
},
  "geometry": {"coordinates":[-83.773197,42.250773],"type":"Point"}
}