{
  "type": "Feature",
  "properties": {
    "iso:country":"US",
    "sg:address":"27777 Stansbury St",
    "sg:city":"Farmington",
    "sg:classifiers":[
        {
            "category":"Travel",
            "subcategory":"Hotels & Motels",
            "type":"Entertainment"
        }
    ],
    "sg:phone":"+1 248 442 9015",
    "sg:postcode":"48334",
    "sg:province":"MI",
    "sg:tags":[
        "operation"
    ],
    "wof:name":"Fairfield Inn",
    "wof:placetype":"venue"
},
  "geometry": {"coordinates":[-83.35423900000001,42.498451],"type":"Point"}
}