{
  "type": "Feature",
  "properties": {
    "iso:country":"US",
    "sg:address":"32487 Norfolk St",
    "sg:city":"Livonia",
    "sg:classifiers":[
        {
            "category":"Building & Trades",
            "subcategory":"Construction",
            "type":"Services"
        }
    ],
    "sg:phone":"+1 248 471 5769",
    "sg:postcode":"48152",
    "sg:province":"MI",
    "sg:tags":[
        "house"
    ],
    "wof:name":"Walters Installation",
    "wof:placetype":"venue"
},
  "geometry": {"coordinates":[-83.368323,42.437087],"type":"Point"}
}