{
  "type": "Feature",
  "properties": {
    "iso:country":"US",
    "sg:address":"9192 W Houghton Lake Dr",
    "sg:city":"Houghton Lake",
    "sg:classifiers":[
        {
            "category":"Travel",
            "subcategory":"Hotels & Motels",
            "type":"Entertainment"
        }
    ],
    "sg:phone":"+1 989 422 5295",
    "sg:postcode":"48629",
    "sg:province":"MI",
    "sg:tags":[
        "operation"
    ],
    "wof:name":"Sands Northern Exposure Inc",
    "wof:placetype":"venue"
},
  "geometry": {"coordinates":[-84.792292,44.335847],"type":"Point"}
}