{
  "type": "Feature",
  "properties": {
    "iso:country":"US",
    "sg:address":"49580 Gratiot Ave",
    "sg:city":"Chesterfield",
    "sg:classifiers":[
        {
            "category":"Home & Garden",
            "subcategory":"Carpets & Floor Coverings",
            "type":"Retail Goods"
        }
    ],
    "sg:phone":"+1 586 598 0000",
    "sg:postcode":"48051",
    "sg:province":"MI",
    "wof:name":"Gallery Floor Covering & Blnds",
    "wof:placetype":"venue"
},
  "geometry": {"coordinates":[-82.841635,42.663899],"type":"Point"}
}