{
  "type": "Feature",
  "properties": {
    "iso:country":"US",
    "sg:address":"7808 Crystal Dr",
    "sg:city":"Beulah",
    "sg:classifiers":[
        {
            "category":"Travel",
            "subcategory":"Hotels & Motels",
            "type":"Entertainment"
        }
    ],
    "sg:phone":"+1 231 882 9907",
    "sg:postcode":"49617",
    "sg:province":"MI",
    "sg:tags":[
        "resort"
    ],
    "wof:name":"Cozy Comfort Resort",
    "wof:placetype":"venue"
},
  "geometry": {"coordinates":[-86.08663199999999,44.639485],"type":"Point"}
}