{
  "type": "Feature",
  "properties": {
    "iso:country":"US",
    "sg:address":"1133 Latham St",
    "sg:city":"Birmingham",
    "sg:classifiers":[
        {
            "category":"Professional",
            "subcategory":"Management & Consulting",
            "type":"Services"
        }
    ],
    "sg:phone":"+1 248 258 8776",
    "sg:postcode":"48009",
    "sg:province":"MI",
    "sg:tags":[
        "counselor",
        "public",
        "relations"
    ],
    "wof:name":"Ramp Public Communication Spec",
    "wof:placetype":"venue"
},
  "geometry": {"coordinates":[-83.22667300000001,42.537392],"type":"Point"}
}