{
  "type": "Feature",
  "properties": {
    "iso:country":"US",
    "sg:address":"11650 Plumbrook Rd",
    "sg:city":"Sterling Heights",
    "sg:classifiers":[
        {
            "category":"Building & Trades",
            "subcategory":"Construction",
            "type":"Services"
        }
    ],
    "sg:phone":"+1 586 983 5415",
    "sg:postcode":"48312",
    "sg:province":"MI",
    "sg:tags":[
        "general",
        "contractor"
    ],
    "sg:website":"www.tadianhomes.com",
    "wof:name":"Tadian Homes",
    "wof:placetype":"venue"
},
  "geometry": {"coordinates":[-83.008486,42.576564],"type":"Point"}
}