{
  "type": "Feature",
  "properties": {
    "iso:country":"US",
    "sg:address":"2355 E Stadium Blvd",
    "sg:city":"Ann Arbor",
    "sg:classifiers":[
        {
            "category":"Personal",
            "subcategory":"Beauty Salon",
            "type":"Services"
        }
    ],
    "sg:phone":"+1 734 994 4441",
    "sg:postcode":"48104",
    "sg:province":"MI",
    "sg:tags":[
        "shop"
    ],
    "wof:name":"Sheilas Hair Studio",
    "wof:placetype":"venue"
},
  "geometry": {"coordinates":[-83.715264,42.260486],"type":"Point"}
}