{
  "type": "Feature",
  "properties": {
    "iso:country":"US",
    "sg:address":"855 Harsdale Rd",
    "sg:city":"Bloomfield Hills",
    "sg:classifiers":[
        {
            "category":"Banks & Credit Unions",
            "subcategory":"Financial Services",
            "type":"Services"
        }
    ],
    "sg:phone":"+1 248 644 1059",
    "sg:postcode":"48302",
    "sg:province":"MI",
    "sg:tags":[
        "company",
        "holding"
    ],
    "wof:name":"Sabretech Inc",
    "wof:placetype":"venue"
},
  "geometry": {"coordinates":[-83.267751,42.568766],"type":"Point"}
}