{
  "type": "Feature",
  "properties": {
    "iso:country":"US",
    "sg:address":"709 N Gunnell Rd",
    "sg:city":"Eaton Rapids",
    "sg:classifiers":[
        {
            "category":"Manufacturing",
            "subcategory":"Printing",
            "type":"Manufacturing & Wholesale Goods"
        }
    ],
    "sg:phone":"+1 517 663 0435",
    "sg:postcode":"48827",
    "sg:province":"MI",
    "sg:tags":[
        "publishing"
    ],
    "wof:name":"Michigan Racing Scene",
    "wof:placetype":"venue"
},
  "geometry": {"coordinates":[-84.68060800000001,42.571494],"type":"Point"}
}