{
  "type": "Feature",
  "properties": {
    "iso:country":"US",
    "sg:address":"2124 S Grove Rd",
    "sg:city":"St Johns",
    "sg:classifiers":[
        {
            "category":"Freight",
            "type":"Transportation"
        }
    ],
    "sg:phone":"+1 989 224 4515",
    "sg:postcode":"48879",
    "sg:province":"MI",
    "sg:tags":[
        "grain",
        "elevator"
    ],
    "wof:name":"Hicks Farm Svc",
    "wof:placetype":"venue"
},
  "geometry": {"coordinates":[-84.621618,42.985226],"type":"Point"}
}