{
  "type": "Feature",
  "properties": {
    "iso:country":"US",
    "sg:address":"9800 Springport Rd",
    "sg:city":"Parma",
    "sg:classifiers":[
        {
            "category":"Professional",
            "subcategory":"Management & Consulting",
            "type":"Services"
        }
    ],
    "sg:phone":"+1 517 569 3551",
    "sg:postcode":"49269",
    "sg:province":"MI",
    "sg:tags":[
        "business"
    ],
    "wof:name":"Brian Welton",
    "wof:placetype":"venue"
},
  "geometry": {"coordinates":[-84.571005,42.364095],"type":"Point"}
}