{
  "type": "Feature",
  "properties": {
    "iso:country":"US",
    "sg:address":"31220 Cline Dr",
    "sg:city":"Franklin",
    "sg:classifiers":[
        {
            "category":"Banks & Credit Unions",
            "subcategory":"Bank",
            "type":"Services"
        }
    ],
    "sg:phone":"+1 248 593 0575",
    "sg:postcode":"48025",
    "sg:province":"MI",
    "sg:tags":[
        "broker",
        "mortgage"
    ],
    "wof:name":"Greentree Financial Corp",
    "wof:placetype":"venue"
},
  "geometry": {"coordinates":[-83.22977,42.519878],"type":"Point"}
}