{
  "type": "Feature",
  "properties": {
    "iso:country":"US",
    "sg:address":"36580 Garfield Rd",
    "sg:city":"Clinton Twp",
    "sg:classifiers":[
        {
            "category":"Travel",
            "subcategory":"Travel Agent",
            "type":"Entertainment"
        }
    ],
    "sg:phone":"+1 586 791 4700",
    "sg:postcode":"48035",
    "sg:province":"MI",
    "sg:tags":[
        "agency",
        "bureau"
    ],
    "wof:name":"Travel Station",
    "wof:placetype":"venue"
},
  "geometry": {"coordinates":[-82.950833,42.567251],"type":"Point"}
}