{
  "type": "Feature",
  "properties": {
    "iso:country":"US",
    "sg:address":"206 E Colby St",
    "sg:city":"Whitehall",
    "sg:classifiers":[
        {
            "category":"Personal",
            "subcategory":"Beauty Salon",
            "type":"Services"
        }
    ],
    "sg:phone":"+1 231 893 0003",
    "sg:postcode":"49461",
    "sg:province":"MI",
    "wof:name":"Studio 20.6",
    "wof:placetype":"venue"
},
  "geometry": {"coordinates":[-86.345479,43.409742],"type":"Point"}
}