{
  "type": "Feature",
  "properties": {
    "iso:country":"US",
    "sg:address":"3738 Market St",
    "sg:city":"Kalamazoo",
    "sg:classifiers":[
        {
            "category":"Retail",
            "subcategory":"Photofinishing",
            "type":"Services"
        }
    ],
    "sg:phone":"+1 269 344 7228",
    "sg:postcode":"49048",
    "sg:province":"MI",
    "sg:tags":[
        "laboratory"
    ],
    "wof:name":"Quality 1 Construction",
    "wof:placetype":"venue"
},
  "geometry": {"coordinates":[-85.530918,42.277442],"type":"Point"}
}