{
  "type": "Feature",
  "properties": {
    "iso:country":"US",
    "sg:address":"1101 S State Ave",
    "sg:city":"Alpena",
    "sg:classifiers":[
        {
            "category":"Personal",
            "subcategory":"Tanning Parlor",
            "type":"Services"
        },
        {
            "category":"Personal",
            "type":"Services"
        }
    ],
    "sg:phone":"+1 989 356 8266",
    "sg:postcode":"49707",
    "sg:province":"MI",
    "sg:tags":[
        "salon"
    ],
    "wof:name":"Bayside Tanning Salons",
    "wof:placetype":"venue"
},
  "geometry": {"coordinates":[-83.44538300000001,45.049493],"type":"Point"}
}