{
  "type": "Feature",
  "properties": {
    "iso:country":"US",
    "sg:address":"659 Lakeview Dr",
    "sg:city":"White Lake",
    "sg:classifiers":[
        {
            "category":"Real Estate",
            "subcategory":"Real Estate Agent",
            "type":"Services"
        }
    ],
    "sg:phone":"+1 248 698 3290",
    "sg:postcode":"48386",
    "sg:province":"MI",
    "wof:name":"Edward J Dine",
    "wof:placetype":"venue"
},
  "geometry": {"coordinates":[-83.469785,42.630991],"type":"Point"}
}