{
  "type": "Feature",
  "properties": {
    "iso:country":"US",
    "sg:address":"4350 Clyde Park Ave SW",
    "sg:city":"Grand Rapids",
    "sg:classifiers":[
        {
            "category":"Wholesale",
            "subcategory":"Motor Vehicles",
            "type":"Manufacturing & Wholesale Goods"
        }
    ],
    "sg:phone":"+1 616 530 2100",
    "sg:postcode":"49509",
    "sg:province":"MI",
    "sg:tags":[
        "semi",
        "trailer"
    ],
    "wof:name":"Mid-Michigan Great Dane Inc",
    "wof:placetype":"venue"
},
  "geometry": {"coordinates":[-85.684478,42.885902],"type":"Point"}
}