{
  "type": "Feature",
  "properties": {
    "iso:country":"US",
    "sg:address":"11 N Merchant Ave",
    "sg:city":"Fremont",
    "sg:classifiers":[
        {
            "category":"Local Transit",
            "type":"Transportation"
        }
    ],
    "sg:phone":"+1 231 928 5433",
    "sg:postcode":"49412",
    "sg:province":"MI",
    "sg:tags":[
        "ambulance"
    ],
    "sg:website":"www.lifeems.com",
    "wof:name":"Life EMS Ambulance Svc",
    "wof:placetype":"venue"
},
  "geometry": {"coordinates":[-85.943245,43.467934],"type":"Point"}
}