{
  "type": "Feature",
  "properties": {
    "iso:country":"US",
    "sg:address":"1039 Turner Ave NW",
    "sg:city":"Grand Rapids",
    "sg:classifiers":[
        {
            "category":"Building & Trades",
            "subcategory":"Electrical",
            "type":"Services"
        }
    ],
    "sg:phone":"+1 616 550 4876",
    "sg:postcode":"49504",
    "sg:province":"MI",
    "sg:tags":[
        "electric",
        "contractor"
    ],
    "wof:name":"D & S Electric",
    "wof:placetype":"venue"
},
  "geometry": {"coordinates":[-85.677832,42.983188],"type":"Point"}
}