{
  "type": "Feature",
  "properties": {
    "iso:country":"US",
    "sg:address":"4374 F41",
    "sg:city":"Oscoda",
    "sg:classifiers":[
        {
            "category":"Retail",
            "subcategory":"Repair Shop",
            "type":"Services"
        }
    ],
    "sg:phone":"+1 989 747 5810",
    "sg:postcode":"48750",
    "sg:province":"MI",
    "sg:tags":[
        "repairing",
        "lawn",
        "mower"
    ],
    "wof:name":"Sunrise Toro & Small Engine",
    "wof:placetype":"venue"
},
  "geometry": {"coordinates":[-83.56853599999999,43.334711],"type":"Point"}
}