{
  "type": "Feature",
  "properties": {
    "iso:country":"US",
    "sg:address":"67855 Van Dyke Rd",
    "sg:city":"Washington",
    "sg:classifiers":[
        {
            "category":"Banks & Credit Unions",
            "subcategory":"Bank",
            "type":"Services"
        }
    ],
    "sg:phone":"+1 586 465 2400",
    "sg:postcode":"48095",
    "sg:province":"MI",
    "sg:tags":[
        "state",
        "commercial"
    ],
    "wof:name":"Fifth Third Bank",
    "wof:placetype":"venue"
},
  "geometry": {"coordinates":[-83.013436,42.792763],"type":"Point"}
}