{
  "type": "Feature",
  "properties": {
    "iso:country":"US",
    "sg:address":"46320 W 10 Mile Rd",
    "sg:city":"Novi",
    "sg:classifiers":[
        {
            "category":"Professional",
            "subcategory":"Business Services",
            "type":"Services"
        }
    ],
    "sg:phone":"+1 248 344 0909",
    "sg:postcode":"48374",
    "sg:province":"MI",
    "sg:tags":[
        "translator",
        "interpreter"
    ],
    "wof:name":"Suzuki Myers & Assoc LTD",
    "wof:placetype":"venue"
},
  "geometry": {"coordinates":[-83.504032,42.465838],"type":"Point"}
}