{
  "type": "Feature",
  "properties": {
    "iso:country":"US",
    "sg:address":"5007 Universal Dr",
    "sg:city":"Midland",
    "sg:classifiers":[
        {
            "category":"Health Services",
            "subcategory":"Nursing And Care Facility",
            "type":"Services"
        }
    ],
    "sg:phone":"+1 989 837 2694",
    "sg:postcode":"48640",
    "sg:province":"MI",
    "sg:tags":[
        "intermediate"
    ],
    "sg:website":"www.tendercare.net",
    "wof:name":"Colonial Villa",
    "wof:placetype":"venue"
},
  "geometry": {"coordinates":[-84.289812,43.642819],"type":"Point"}
}