{
  "type": "Feature",
  "properties": {
    "iso:country":"US",
    "sg:address":"652 Henry Ruff Rd",
    "sg:city":"Garden City",
    "sg:classifiers":[
        {
            "category":"Building & Trades",
            "subcategory":"Electrical",
            "type":"Services"
        }
    ],
    "sg:phone":"+1 734 458 9120",
    "sg:postcode":"48135",
    "sg:province":"MI",
    "sg:tags":[
        "electrical",
        "contractor"
    ],
    "wof:name":"Precision Power Electric",
    "wof:placetype":"venue"
},
  "geometry": {"coordinates":[-83.340086,42.31522],"type":"Point"}
}