{
  "type": "Feature",
  "properties": {
    "iso:country":"US",
    "sg:address":"7523 N Stoney Lake Rd",
    "sg:city":"Jackson",
    "sg:classifiers":[
        {
            "category":"Professional",
            "subcategory":"Computer Services",
            "type":"Services"
        }
    ],
    "sg:phone":"+1 517 937 3468",
    "sg:postcode":"49201",
    "sg:province":"MI",
    "sg:tags":[
        "repair"
    ],
    "wof:name":"PC Plus",
    "wof:placetype":"venue"
},
  "geometry": {"coordinates":[-84.27769000000001,42.162167],"type":"Point"}
}