{
  "type": "Feature",
  "properties": {
    "iso:country":"US",
    "sg:address":"5667 Pleasantview Rd",
    "sg:city":"Harbor Springs",
    "sg:classifiers":[
        {
            "category":"Shopping",
            "subcategory":"Gifts & Souvenirs",
            "type":"Retail Goods"
        }
    ],
    "sg:phone":"+1 231 526 8668",
    "sg:postcode":"49740",
    "sg:province":"MI",
    "sg:tags":[
        "party",
        "supply"
    ],
    "wof:name":"Pleasantview Easy Mart",
    "wof:placetype":"venue"
},
  "geometry": {"coordinates":[-84.912648,45.465483],"type":"Point"}
}