{
  "type": "Feature",
  "properties": {
    "iso:country":"US",
    "sg:address":"4300 S Manorwood Dr",
    "sg:city":"Traverse City",
    "sg:classifiers":[
        {
            "category":"Shopping",
            "subcategory":"Stationery & Office Supplies",
            "type":"Retail Goods"
        }
    ],
    "sg:phone":"+1 231 943 4265",
    "sg:postcode":"49684",
    "sg:province":"MI",
    "wof:name":"McQuade Enterprises",
    "wof:placetype":"venue"
},
  "geometry": {"coordinates":[-85.662487,44.647149],"type":"Point"}
}