{
  "type": "Feature",
  "properties": {
    "iso:country":"US",
    "sg:address":"213 Walnut",
    "sg:city":"Mt Pleasant",
    "sg:classifiers":[
        {
            "category":"Freight",
            "type":"Transportation"
        }
    ],
    "sg:phone":"+1 989 773 5437",
    "sg:postcode":"48858",
    "sg:province":"MI",
    "sg:tags":[
        "trucking"
    ],
    "wof:name":"Moravy Trucking Co",
    "wof:placetype":"venue"
},
  "geometry": {"coordinates":[-84.78129800000001,43.60317],"type":"Point"}
}