{
  "type": "Feature",
  "properties": {
    "iso:country":"US",
    "sg:address":"3242 Huntington Woods Dr SE",
    "sg:city":"Grand Rapids",
    "sg:classifiers":[
        {
            "category":"Real Estate",
            "subcategory":"Real Estate Operator",
            "type":"Services"
        }
    ],
    "sg:phone":"+1 616 957 4190",
    "sg:postcode":"49512",
    "sg:province":"MI",
    "sg:tags":[
        "building",
        "apartment"
    ],
    "wof:name":"Huntington Glen Apartments",
    "wof:placetype":"venue"
},
  "geometry": {"coordinates":[-85.58692000000001,42.90036],"type":"Point"}
}