{
  "type": "Feature",
  "properties": {
    "iso:country":"US",
    "sg:address":"44555 Woodward Ave Ste 203",
    "sg:city":"Pontiac",
    "sg:classifiers":[
        {
            "category":"Health Services",
            "subcategory":"Optometrist",
            "type":"Services"
        }
    ],
    "sg:phone":"+1 248 334 4931",
    "sg:postcode":"48341",
    "sg:province":"MI",
    "sg:tags":[
        "ophthalmologist"
    ],
    "sg:website":"www.wilkinsoneye.com/",
    "wof:name":"Wilkinson Eye Center Optical Shoppe",
    "wof:placetype":"venue"
},
  "geometry": {"coordinates":[-83.27570299999999,42.615601],"type":"Point"}
}