{
  "type": "Feature",
  "properties": {
    "iso:country":"US",
    "sg:address":"1534 Mason St",
    "sg:city":"Dansville",
    "sg:classifiers":[
        {
            "category":"Organizations",
            "subcategory":"Religious Organization",
            "type":"Services"
        }
    ],
    "sg:phone":"+1 517 623 6020",
    "sg:postcode":"48819",
    "sg:province":"MI",
    "wof:name":"Dansville Baptist Church",
    "wof:placetype":"venue"
},
  "geometry": {"coordinates":[-84.28393199999999,42.555839],"type":"Point"}
}