{
  "type": "Feature",
  "properties": {
    "iso:country":"US",
    "sg:address":"421 N Leroy St",
    "sg:city":"Fenton",
    "sg:classifiers":[
        {
            "category":"Retail",
            "subcategory":"Car Wash",
            "type":"Services"
        }
    ],
    "sg:phone":"+1 810 629 0161",
    "sg:postcode":"48430",
    "sg:province":"MI",
    "sg:tags":[
        "carwash"
    ],
    "wof:name":"National Pride",
    "wof:placetype":"venue"
},
  "geometry": {"coordinates":[-83.704988,42.799921],"type":"Point"}
}