{
  "type": "Feature",
  "properties": {
    "iso:country":"US",
    "sg:address":"1475 W Big Beaver Rd",
    "sg:city":"Troy",
    "sg:classifiers":[
        {
            "category":"Real Estate",
            "subcategory":"Real Estate Agent",
            "type":"Services"
        }
    ],
    "sg:phone":"+1 248 816 0420",
    "sg:postcode":"48084",
    "sg:province":"MI",
    "sg:website":"www.foreclosuresnationwide.com",
    "wof:name":"Jack Christenson Inc",
    "wof:placetype":"venue"
},
  "geometry": {"coordinates":[-83.17328000000001,42.561561],"type":"Point"}
}