{
  "type": "Feature",
  "properties": {
    "iso:country":"US",
    "sg:address":"2368 S Center Rd",
    "sg:city":"Burton",
    "sg:classifiers":[
        {
            "category":"Insurance",
            "subcategory":"Insurance Agent",
            "type":"Services"
        }
    ],
    "sg:phone":"+1 810 715 0745",
    "sg:postcode":"48519",
    "sg:province":"MI",
    "wof:name":"AAA Insurance",
    "wof:placetype":"venue"
},
  "geometry": {"coordinates":[-83.633967,42.993544],"type":"Point"}
}