{
  "type": "Feature",
  "properties": {
    "iso:country":"US",
    "sg:address":"9090 Lapeer Rd",
    "sg:city":"Davison",
    "sg:classifiers":[
        {
            "category":"Autos & Motor Vehicles",
            "subcategory":"Auto Supplies",
            "type":"Retail Goods"
        },
        {
            "category":"Retail",
            "subcategory":"Auto Repair",
            "type":"Services"
        }
    ],
    "sg:phone":"+1 810 653 4160",
    "sg:postcode":"48423",
    "sg:province":"MI",
    "sg:tags":[
        "tire"
    ],
    "wof:name":"Church and Sons Auto Repair",
    "wof:placetype":"venue"
},
  "geometry": {"coordinates":[-83.533096,43.012199],"type":"Point"}
}