{
  "type": "Feature",
  "properties": {
    "iso:country":"US",
    "sg:address":"2065 W Maple Rd",
    "sg:city":"Commerce Twp",
    "sg:classifiers":[
        {
            "category":"Health Services",
            "subcategory":"Doctor",
            "type":"Services"
        }
    ],
    "sg:phone":"+1 248 960 3400",
    "sg:postcode":"48390",
    "sg:province":"MI",
    "sg:tags":[
        "anesthetist"
    ],
    "wof:name":"Anesthesia Services",
    "wof:placetype":"venue"
},
  "geometry": {"coordinates":[-83.51104599999999,42.534446],"type":"Point"}
}