{
  "type": "Feature",
  "properties": {
    "iso:country":"US",
    "sg:address":"304 S Suffolk St",
    "sg:city":"Ironwood",
    "sg:classifiers":[
        {
            "category":"Bars & Pubs",
            "type":"Food & Drink"
        }
    ],
    "sg:phone":"+1 906 932 2703",
    "sg:postcode":"49938",
    "sg:province":"MI",
    "wof:name":"Olkie's Bar",
    "wof:placetype":"venue"
},
  "geometry": {"coordinates":[-90.167371,46.45385],"type":"Point"}
}