{
  "type": "Feature",
  "properties": {
    "iso:country":"US",
    "sg:address":"217 Joseph Campau St",
    "sg:city":"Detroit",
    "sg:classifiers":[
        {
            "category":"Retail",
            "subcategory":"Auto Repair",
            "type":"Services"
        }
    ],
    "sg:phone":"+1 313 259 4810",
    "sg:postcode":"48207",
    "sg:province":"MI",
    "wof:name":"Ren Cen Mechanical Service",
    "wof:placetype":"venue"
},
  "geometry": {"coordinates":[-83.018097,42.3367],"type":"Point"}
}