{
  "type": "Feature",
  "properties": {
    "iso:country":"US",
    "sg:address":"114 E Washington St",
    "sg:city":"Ann Arbor",
    "sg:classifiers":[
        {
            "category":"Restaurant",
            "type":"Food & Drink"
        }
    ],
    "sg:menulink":"http://www.allmenus.com/mi/ann-arbor/248000-arbor-brewing-company/menu/",
    "sg:phone":"+1 734 213 1393",
    "sg:postcode":"48104",
    "sg:province":"MI",
    "sg:tags":[
        "wrap",
        "american",
        "sandwich"
    ],
    "wof:name":"Arbor Brewing Company",
    "wof:placetype":"venue"
},
  "geometry": {"coordinates":[-83.748327,42.280471],"type":"Point"}
}