{
  "type": "Feature",
  "properties": {
    "iso:country":"US",
    "sg:address":"330 N Grove St",
    "sg:city":"Delton",
    "sg:classifiers":[
        {
            "category":"Education",
            "subcategory":"Library",
            "type":"Public Place"
        }
    ],
    "sg:phone":"+1 269 623 8040",
    "sg:postcode":"49046",
    "sg:province":"MI",
    "wof:name":"Delton District Library",
    "wof:placetype":"venue"
},
  "geometry": {"coordinates":[-85.4085,42.502977],"type":"Point"}
}