{
  "type": "Feature",
  "properties": {
    "iso:country":"US",
    "sg:address":"586 N Main St",
    "sg:city":"Olivet",
    "sg:classifiers":[
        {
            "category":"Wholesale",
            "subcategory":"Machinery & Supplies",
            "type":"Manufacturing & Wholesale Goods"
        }
    ],
    "sg:phone":"+1 269 749 2161",
    "sg:postcode":"49076",
    "sg:province":"MI",
    "sg:tags":[
        "fitting",
        "hose",
        "coupling"
    ],
    "sg:website":"www.air-way.com",
    "wof:name":"Air-Way Mfg Co",
    "wof:placetype":"venue"
},
  "geometry": {"coordinates":[-84.91771300000001,42.450449],"type":"Point"}
}