{
  "type": "Feature",
  "properties": {
    "iso:country":"US",
    "sg:address":"345 State St SE",
    "sg:city":"Grand Rapids",
    "sg:classifiers":[
        {
            "category":"Professional",
            "subcategory":"Engineering",
            "type":"Services"
        }
    ],
    "sg:phone":"+1 616 235 2960",
    "sg:postcode":"49503",
    "sg:province":"MI",
    "wof:name":"I E T Inc",
    "wof:placetype":"venue"
},
  "geometry": {"coordinates":[-85.659217,42.959521],"type":"Point"}
}