{
  "type": "Feature",
  "properties": {
    "iso:country":"US",
    "sg:address":"35563 Harper Ave",
    "sg:city":"Clinton Township",
    "sg:classifiers":[
        {
            "category":"Personal",
            "subcategory":"Barber",
            "type":"Services"
        }
    ],
    "sg:phone":"+1 586 792 2323",
    "sg:postcode":"48035",
    "sg:province":"MI",
    "wof:name":"Phil's Hair Stylists",
    "wof:placetype":"venue"
},
  "geometry": {"coordinates":[-82.87039900000001,42.559898],"type":"Point"}
}