{
  "type": "Feature",
  "properties": {
    "iso:country":"US",
    "sg:address":"27022 Arden Park Cir",
    "sg:city":"Farmington",
    "sg:classifiers":[
        {
            "category":"Building & Trades",
            "subcategory":"Landscaping Services",
            "type":"Services"
        }
    ],
    "sg:phone":"+1 248 476 3209",
    "sg:postcode":"48334",
    "sg:province":"MI",
    "sg:tags":[
        "landscape"
    ],
    "wof:name":"Accurate Landscaping",
    "wof:placetype":"venue"
},
  "geometry": {"coordinates":[-83.32322000000001,42.48625],"type":"Point"}
}