{
  "type": "Feature",
  "properties": {
    "iso:country":"US",
    "sg:address":"3401 E Court St",
    "sg:city":"Flint",
    "sg:classifiers":[
        {
            "category":"Home & Garden",
            "subcategory":"Building Materials",
            "type":"Retail Goods"
        }
    ],
    "sg:phone":"+1 810 742 8787",
    "sg:postcode":"48503",
    "sg:province":"MI",
    "sg:tags":[
        "truss"
    ],
    "wof:name":"Michigan Timber & Trust",
    "wof:placetype":"venue"
},
  "geometry": {"coordinates":[-83.639787,43.018619],"type":"Point"}
}