{
  "type": "Feature",
  "properties": {
    "iso:country":"US",
    "sg:address":"1373 E Linwood Rd",
    "sg:city":"Linwood",
    "sg:classifiers":[
        {
            "category":"Freight",
            "type":"Transportation"
        }
    ],
    "sg:phone":"+1 989 697 5575",
    "sg:postcode":"48634",
    "sg:province":"MI",
    "sg:tags":[
        "trucking"
    ],
    "wof:name":"Scott's Trucking",
    "wof:placetype":"venue"
},
  "geometry": {"coordinates":[-83.991314,43.738974],"type":"Point"}
}