{
  "type": "Feature",
  "properties": {
    "iso:country":"US",
    "sg:address":"51850 Dequindre Rd",
    "sg:city":"Shelby Twp",
    "sg:classifiers":[
        {
            "category":"Health Services",
            "subcategory":"Doctor",
            "type":"Services"
        }
    ],
    "sg:phone":"+1 586 726 8504",
    "sg:postcode":"48316",
    "sg:province":"MI",
    "sg:tags":[
        "physician",
        "surgeon"
    ],
    "wof:name":"Associations-Family Medicine",
    "wof:placetype":"venue"
},
  "geometry": {"coordinates":[-83.093768,42.675962],"type":"Point"}
}