{
  "type": "Feature",
  "properties": {
    "iso:country":"US",
    "sg:address":"7900 Golf Meadows Dr SE",
    "sg:city":"Caledonia",
    "sg:classifiers":[
        {
            "category":"Professional",
            "subcategory":"Accounting & Tax Preparation",
            "type":"Services"
        }
    ],
    "sg:phone":"+1 616 891 7100",
    "sg:postcode":"49316",
    "sg:province":"MI",
    "sg:tags":[
        "accountant"
    ],
    "wof:name":"Thomas P Soltys CPA",
    "wof:placetype":"venue"
},
  "geometry": {"coordinates":[-85.539039,42.822211],"type":"Point"}
}