{
  "type": "Feature",
  "properties": {
    "iso:country":"US",
    "sg:address":"15747 Grayfield St",
    "sg:city":"Detroit",
    "sg:classifiers":[
        {
            "category":"Retail",
            "subcategory":"Laundry & Dry Cleaning",
            "type":"Services"
        }
    ],
    "sg:phone":"+1 313 535 4545",
    "sg:postcode":"48223",
    "sg:province":"MI",
    "sg:tags":[
        "drycleaning",
        "plant"
    ],
    "wof:name":"Radiant Carpet & Uphl Clrs",
    "wof:placetype":"venue"
},
  "geometry": {"coordinates":[-83.269316,42.404778],"type":"Point"}
}