{
  "type": "Feature",
  "properties": {
    "iso:country":"US",
    "sg:address":"23121 Gratiot Ave",
    "sg:city":"Eastpointe",
    "sg:classifiers":[
        {
            "category":"Professional",
            "subcategory":"Lawyer & Legal Services",
            "type":"Services"
        }
    ],
    "sg:phone":"+1 586 775 1572",
    "sg:postcode":"48021",
    "sg:province":"MI",
    "wof:name":"Segesta Benedict Atty",
    "wof:placetype":"venue"
},
  "geometry": {"coordinates":[-82.966904,42.451801],"type":"Point"}
}