{
  "type": "Feature",
  "properties": {
    "iso:country":"US",
    "sg:address":"3431 Waltrous Rd",
    "sg:city":"Chelsea",
    "sg:classifiers":[
        {
            "category":"Retail",
            "subcategory":"Repair Shop",
            "type":"Services"
        }
    ],
    "sg:phone":"+1 734 475 2805",
    "sg:postcode":"48118",
    "sg:province":"MI",
    "wof:name":"Jim & Sons Taxidermy",
    "wof:placetype":"venue"
},
  "geometry": {"coordinates":[-84.014512,42.278851],"type":"Point"}
}