{
  "type": "Feature",
  "properties": {
    "iso:country":"US",
    "sg:address":"600 John R Rd",
    "sg:city":"Troy",
    "sg:classifiers":[
        {
            "category":"Shopping",
            "subcategory":"Shoes",
            "type":"Retail Goods"
        }
    ],
    "sg:phone":"+1 248 307 1428",
    "sg:postcode":"48083",
    "sg:province":"MI",
    "sg:tags":[
        "store"
    ],
    "wof:name":"Dsw Shoe Warehouse",
    "wof:placetype":"venue"
},
  "geometry": {"coordinates":[-83.106903,42.5401],"type":"Point"}
}