{
  "type": "Feature",
  "properties": {
    "iso:country":"US",
    "sg:address":"2540 Grey Tower Rd",
    "sg:city":"Jackson",
    "sg:classifiers":[
        {
            "category":"Organizations",
            "subcategory":"Professional Association",
            "type":"Services"
        }
    ],
    "sg:phone":"+1 517 522 8260",
    "sg:postcode":"49201",
    "sg:province":"MI",
    "sg:tags":[
        "business"
    ],
    "wof:name":"D Valerian Trifa Romanian",
    "wof:placetype":"venue"
},
  "geometry": {"coordinates":[-84.229308,42.226006],"type":"Point"}
}