{
  "type": "Feature",
  "properties": {
    "iso:country":"US",
    "sg:address":"2250 Chicago St",
    "sg:city":"Saginaw",
    "sg:classifiers":[
        {
            "category":"Shopping",
            "subcategory":"Bicycles & Sporting Goods",
            "type":"Retail Goods"
        }
    ],
    "sg:phone":"+1 989 777 2428",
    "sg:postcode":"48601",
    "sg:province":"MI",
    "wof:name":"Rainbow Sports & Trophies",
    "wof:placetype":"venue"
},
  "geometry": {"coordinates":[-83.910353,43.393223],"type":"Point"}
}