{
  "type": "Feature",
  "properties": {
    "iso:country":"US",
    "sg:address":"435 Stuart Ave Apt 1",
    "sg:city":"Kalamazoo",
    "sg:classifiers":[
        {
            "category":"Coffee & Tea",
            "type":"Food & Drink"
        },
        {
            "category":"Restaurant",
            "type":"Food & Drink"
        }
    ],
    "sg:phone":"+1 269 665 7660",
    "sg:postcode":"49007",
    "sg:province":"MI",
    "sg:tags":[
        "shop",
        "espresso"
    ],
    "wof:name":"Chaney's Coffee & Cafe",
    "wof:placetype":"venue"
},
  "geometry": {"coordinates":[-85.59774899999999,42.294613],"type":"Point"}
}