{
  "type": "Feature",
  "properties": {
    "iso:country":"US",
    "sg:address":"120 A St",
    "sg:city":"Cheboygan",
    "sg:classifiers":[
        {
            "category":"Recreation",
            "type":"Entertainment"
        }
    ],
    "sg:phone":"+1 231 627 9011",
    "sg:postcode":"49721",
    "sg:province":"MI",
    "sg:tags":[
        "parks"
    ],
    "wof:name":"Parks & Recreation Dept",
    "wof:placetype":"venue"
},
  "geometry": {"coordinates":[-84.471569,45.646706],"type":"Point"}
}