{
  "type": "Feature",
  "properties": {
    "iso:country":"US",
    "sg:address":"7290 E Michigan Ave",
    "sg:city":"Parma",
    "sg:classifiers":[
        {
            "category":"Farming",
            "subcategory":"Farm",
            "type":"Manufacturing & Wholesale Goods"
        }
    ],
    "sg:phone":"+1 517 750 3806",
    "sg:postcode":"49269",
    "sg:province":"MI",
    "sg:tags":[
        "crop",
        "general"
    ],
    "wof:name":"Chuck Wilcox",
    "wof:placetype":"venue"
},
  "geometry": {"coordinates":[-84.517686,42.252731],"type":"Point"}
}