{
  "type": "Feature",
  "properties": {
    "iso:country":"US",
    "sg:address":"3373 Applewood Ave",
    "sg:city":"Lincoln Park",
    "sg:classifiers":[
        {
            "category":"Building & Trades",
            "subcategory":"Construction",
            "type":"Services"
        }
    ],
    "sg:phone":"+1 313 382 5369",
    "sg:postcode":"48146",
    "sg:province":"MI",
    "sg:tags":[
        "contractor"
    ],
    "wof:name":"Jim Finn",
    "wof:placetype":"venue"
},
  "geometry": {"coordinates":[-83.16739200000001,42.237918],"type":"Point"}
}