{
  "type": "Feature",
  "properties": {
    "iso:country":"US",
    "sg:address":"6855 High Pine Dr",
    "sg:city":"Davisburg",
    "sg:classifiers":[
        {
            "category":"Building & Trades",
            "subcategory":"Construction",
            "type":"Services"
        }
    ],
    "sg:phone":"+1 248 634 9605",
    "sg:postcode":"48350",
    "sg:province":"MI",
    "sg:tags":[
        "house"
    ],
    "wof:name":"J&J Contracting",
    "wof:placetype":"venue"
},
  "geometry": {"coordinates":[-83.539293,42.733362],"type":"Point"}
}