{
  "type": "Feature",
  "properties": {
    "iso:country":"US",
    "sg:address":"2759 Millville Rd",
    "sg:city":"Lapeer",
    "sg:classifiers":[
        {
            "category":"Building & Trades",
            "subcategory":"Construction",
            "type":"Services"
        }
    ],
    "sg:phone":"+1 810 664 3056",
    "sg:postcode":"48446",
    "sg:province":"MI",
    "sg:tags":[
        "residential",
        "builder"
    ],
    "wof:name":"John R ONeill Rsidential Bldr",
    "wof:placetype":"venue"
},
  "geometry": {"coordinates":[-83.3463,43.110553],"type":"Point"}
}