{
  "type": "Feature",
  "properties": {
    "iso:country":"US",
    "sg:address":"10900 Tefft Ave NE",
    "sg:city":"Rockford",
    "sg:classifiers":[
        {
            "category":"Insurance",
            "subcategory":"Insurance Agent",
            "type":"Services"
        }
    ],
    "sg:phone":"+1 616 866 8400",
    "sg:postcode":"49341",
    "sg:province":"MI",
    "wof:name":"Astras Insurance",
    "wof:placetype":"venue"
},
  "geometry": {"coordinates":[-85.520456,43.162693],"type":"Point"}
}