{
  "type": "Feature",
  "properties": {
    "iso:country":"US",
    "sg:address":"2690 Crooks Rd",
    "sg:city":"Troy",
    "sg:classifiers":[
        {
            "category":"Recreation",
            "type":"Entertainment"
        }
    ],
    "sg:phone":"+1 248 269 9440",
    "sg:postcode":"48084",
    "sg:province":"MI",
    "sg:tags":[
        "instruction",
        "golf"
    ],
    "wof:name":"Body Balance For Performance",
    "wof:placetype":"venue"
},
  "geometry": {"coordinates":[-83.166967,42.557394],"type":"Point"}
}