{
  "type": "Feature",
  "properties": {
    "iso:country":"US",
    "sg:address":"22175 Sibley Rd",
    "sg:city":"Wyandotte",
    "sg:classifiers":[
        {
            "category":"Professional",
            "type":"Services"
        }
    ],
    "sg:phone":"+1 734 479 0468",
    "sg:postcode":"48193",
    "sg:province":"MI",
    "wof:name":"Ajc Services",
    "wof:placetype":"venue"
},
  "geometry": {"coordinates":[-83.245525,42.170473],"type":"Point"}
}