{
  "type": "Feature",
  "properties": {
    "iso:country":"US",
    "sg:address":"1535 N Telegraph Rd",
    "sg:city":"Monroe",
    "sg:classifiers":[
        {
            "category":"Banks & Credit Unions",
            "subcategory":"Bank",
            "type":"Services"
        }
    ],
    "sg:phone":"+1 734 457 4440",
    "sg:postcode":"48162",
    "sg:province":"MI",
    "wof:name":"Key Bank",
    "wof:placetype":"venue"
},
  "geometry": {"coordinates":[-83.405895,41.939502],"type":"Point"}
}