{
  "type": "Feature",
  "properties": {
    "iso:country":"US",
    "sg:address":"302 S Stephenson Ave",
    "sg:city":"Iron Mountain",
    "sg:classifiers":[
        {
            "category":"Restaurant",
            "type":"Food & Drink"
        }
    ],
    "sg:phone":"+1 906 776 3310",
    "sg:postcode":"49801",
    "sg:province":"MI",
    "wof:name":"Hot Dog Heaven",
    "wof:placetype":"venue"
},
  "geometry": {"coordinates":[-88.06561600000001,45.820286],"type":"Point"}
}