{
  "type": "Feature",
  "properties": {
    "iso:country":"US",
    "sg:address":"16846 Newburgh Rd",
    "sg:city":"Livonia",
    "sg:classifiers":[
        {
            "category":"Health Services",
            "subcategory":"Health Practitioner",
            "type":"Services"
        }
    ],
    "sg:phone":"+1 734 402 2335",
    "sg:postcode":"48154",
    "sg:province":"MI",
    "sg:tags":[
        "therapy",
        "physical"
    ],
    "wof:name":"Team Rehab. Physical Therapy",
    "wof:placetype":"venue"
},
  "geometry": {"coordinates":[-83.413202,42.409985],"type":"Point"}
}