{
  "type": "Feature",
  "properties": {
    "iso:country":"US",
    "sg:address":"2855 Union Lake Rd",
    "sg:city":"Commerce Twp",
    "sg:classifiers":[
        {
            "category":"Shopping",
            "subcategory":"Department Store",
            "type":"Retail Goods"
        }
    ],
    "sg:phone":"+1 248 366 6359",
    "sg:postcode":"48382",
    "sg:province":"MI",
    "sg:tags":[
        "shop"
    ],
    "wof:name":"Big Lots",
    "wof:placetype":"venue"
},
  "geometry": {"coordinates":[-83.445949,42.594348],"type":"Point"}
}