{
  "type": "Feature",
  "properties": {
    "iso:country":"US",
    "sg:address":"7045 Crane Rd",
    "sg:city":"Ypsilanti",
    "sg:classifiers":[
        {
            "category":"Organizations",
            "subcategory":"Professional Association",
            "type":"Services"
        }
    ],
    "sg:phone":"+1 734 572 0379",
    "sg:postcode":"48197",
    "sg:province":"MI",
    "wof:name":"Experimental Aircraft Assco",
    "wof:placetype":"venue"
},
  "geometry": {"coordinates":[-83.66922599999999,42.181903],"type":"Point"}
}