{
  "type": "Feature",
  "properties": {
    "iso:country":"US",
    "sg:address":"5510 E Napier Ave",
    "sg:city":"Benton Harbor",
    "sg:classifiers":[
        {
            "category":"Professional",
            "type":"Services"
        }
    ],
    "sg:phone":"+1 269 944 1353",
    "sg:postcode":"49022",
    "sg:province":"MI",
    "wof:name":"Nichols Iva",
    "wof:placetype":"venue"
},
  "geometry": {"coordinates":[-86.322306,42.093976],"type":"Point"}
}