{
  "type": "Feature",
  "properties": {
    "iso:country":"US",
    "sg:address":"210 E River St",
    "sg:city":"Grand Ledge",
    "sg:classifiers":[
        {
            "category":"Professional",
            "subcategory":"Lawyer & Legal Services",
            "type":"Services"
        }
    ],
    "sg:phone":"+1 517 627 8328",
    "sg:postcode":"48837",
    "sg:province":"MI",
    "sg:tags":[
        "attorney"
    ],
    "wof:name":"Robert J Robinson",
    "wof:placetype":"venue"
},
  "geometry": {"coordinates":[-84.744242,42.753317],"type":"Point"}
}