{
  "type": "Feature",
  "properties": {
    "iso:country":"US",
    "sg:address":"65 Cadillac Sq Ste 2100",
    "sg:city":"Detroit",
    "sg:classifiers":[
        {
            "category":"Professional",
            "subcategory":"Lawyer & Legal Services",
            "type":"Services"
        }
    ],
    "sg:phone":"+1 313 963 1121",
    "sg:postcode":"48226",
    "sg:province":"MI",
    "wof:name":"Metropolitan Law Center",
    "wof:placetype":"venue"
},
  "geometry": {"coordinates":[-83.04498700000001,42.331857],"type":"Point"}
}