{
  "type": "Feature",
  "properties": {
    "iso:country":"US",
    "sg:address":"15275 E 13 Mile Rd",
    "sg:city":"Fraser",
    "sg:classifiers":[
        {
            "category":"Health Services",
            "subcategory":"Doctor",
            "type":"Services"
        }
    ],
    "sg:phone":"+1 586 296 3230",
    "sg:postcode":"48026",
    "sg:province":"MI",
    "sg:tags":[
        "surgeon",
        "oral"
    ],
    "wof:name":"Steenbergh Omar DDS",
    "wof:placetype":"venue"
},
  "geometry": {"coordinates":[-82.96820099999999,42.5238],"type":"Point"}
}