{
  "type": "Feature",
  "properties": {
    "iso:country":"US",
    "sg:address":"22 Mill Rd",
    "sg:city":"Utica",
    "sg:classifiers":[
        {
            "category":"Building & Trades",
            "subcategory":"Construction",
            "type":"Services"
        }
    ],
    "sg:phone":"+1 586 323 4445",
    "sg:postcode":"48386",
    "sg:province":"MI",
    "sg:tags":[
        "family"
    ],
    "wof:name":"Lexus Homes Inc",
    "wof:placetype":"venue"
},
  "geometry": {"coordinates":[-83.487594,42.639051],"type":"Point"}
}