{
  "type": "Feature",
  "properties": {
    "iso:country":"US",
    "sg:address":"5738 Eagle Dr SE",
    "sg:city":"Grand Rapids",
    "sg:classifiers":[
        {
            "category":"Freight",
            "type":"Transportation"
        }
    ],
    "sg:phone":"+1 616 956 0430",
    "sg:postcode":"49512",
    "sg:province":"MI",
    "sg:tags":[
        "warehouse",
        "self",
        "storage"
    ],
    "wof:name":"Superior Storage Co",
    "wof:placetype":"venue"
},
  "geometry": {"coordinates":[-85.52713,42.90052],"type":"Point"}
}