{
  "type": "Feature",
  "properties": {
    "iso:country":"US",
    "sg:address":"12734 Fenkell St",
    "sg:city":"Detroit",
    "sg:classifiers":[
        {
            "category":"Shopping",
            "subcategory":"Mobile Phones",
            "type":"Retail Goods"
        }
    ],
    "sg:phone":"+1 313 862 4677",
    "sg:postcode":"48227",
    "sg:province":"MI",
    "wof:name":"Raw Image Communications",
    "wof:placetype":"venue"
},
  "geometry": {"coordinates":[-83.170097,42.402302],"type":"Point"}
}