{
  "type": "Feature",
  "properties": {
    "iso:country":"US",
    "sg:address":"3514 Plainfield Ave NE",
    "sg:city":"Grand Rapids",
    "sg:classifiers":[
        {
            "category":"Insurance",
            "subcategory":"Insurance Agent",
            "type":"Services"
        }
    ],
    "sg:phone":"+1 616 363 5665",
    "sg:postcode":"49525",
    "sg:province":"MI",
    "wof:name":"Look Insurance",
    "wof:placetype":"venue"
},
  "geometry": {"coordinates":[-85.631586,43.027917],"type":"Point"}
}