{
  "type": "Feature",
  "properties": {
    "iso:country":"US",
    "sg:address":"1715 S Lapeer Rd",
    "sg:city":"Lake Orion",
    "sg:classifiers":[
        {
            "category":"Organizations",
            "subcategory":"Religious Organization",
            "type":"Services"
        }
    ],
    "sg:phone":"+1 248 693 1676",
    "sg:postcode":"48360",
    "sg:province":"MI",
    "sg:tags":[
        "church"
    ],
    "wof:name":"King Of Kings Lutheran Church",
    "wof:placetype":"venue"
},
  "geometry": {"coordinates":[-83.246315,42.754008],"type":"Point"}
}