{
  "type": "Feature",
  "properties": {
    "iso:country":"US",
    "sg:address":"355 S Summers Rd",
    "sg:city":"Imlay City",
    "sg:classifiers":[
        {
            "category":"Building & Trades",
            "subcategory":"Electrical",
            "type":"Services"
        }
    ],
    "sg:phone":"+1 810 724 5825",
    "sg:postcode":"48444",
    "sg:province":"MI",
    "sg:tags":[
        "electric",
        "contractor"
    ],
    "wof:name":"S & S Electric",
    "wof:placetype":"venue"
},
  "geometry": {"coordinates":[-83.10748,43.0324],"type":"Point"}
}