{
  "type": "Feature",
  "properties": {
    "iso:country":"US",
    "sg:address":"418 S Cuyler St",
    "sg:city":"Cheboygan",
    "sg:classifiers":[
        {
            "category":"Wholesale",
            "subcategory":"Farm Supplies",
            "type":"Manufacturing & Wholesale Goods"
        }
    ],
    "sg:phone":"+1 231 627 4605",
    "sg:postcode":"49721",
    "sg:province":"MI",
    "sg:website":"www.cheboygancoop.com",
    "wof:name":"Cheboygan Co-Op Co",
    "wof:placetype":"venue"
},
  "geometry": {"coordinates":[-84.48418700000001,45.639196],"type":"Point"}
}