{
  "type": "Feature",
  "properties": {
    "iso:country":"US",
    "sg:address":"20145 Kentucky St",
    "sg:city":"Detroit",
    "sg:classifiers":[
        {
            "category":"Professional",
            "subcategory":"Business Services",
            "type":"Services"
        }
    ],
    "sg:phone":"+1 313 341 6029",
    "sg:postcode":"48221",
    "sg:province":"MI",
    "wof:name":"Final Solution Cleaning Co",
    "wof:placetype":"venue"
},
  "geometry": {"coordinates":[-83.16042299999999,42.442933],"type":"Point"}
}