{
  "type": "Feature",
  "properties": {
    "iso:country":"US",
    "sg:address":"225 W Upton Ave",
    "sg:city":"Reed City",
    "sg:classifiers":[
        {
            "category":"Retail",
            "subcategory":"Funeral Services",
            "type":"Services"
        }
    ],
    "sg:phone":"+1 231 832 2262",
    "sg:postcode":"49677",
    "sg:province":"MI",
    "sg:tags":[
        "director"
    ],
    "wof:name":"Pruitt-Livingston Funeral Home",
    "wof:placetype":"venue"
},
  "geometry": {"coordinates":[-85.512333,43.87588],"type":"Point"}
}