{
  "type": "Feature",
  "properties": {
    "iso:country":"US",
    "sg:address":"18010 Mack Ave",
    "sg:city":"Grosse Pointe",
    "sg:classifiers":[
        {
            "category":"Insurance",
            "subcategory":"Insurance Agent",
            "type":"Services"
        }
    ],
    "sg:phone":"+1 313 343 9616",
    "sg:postcode":"48230",
    "sg:province":"MI",
    "sg:tags":[
        "agency"
    ],
    "wof:name":"Interstate Excess",
    "wof:placetype":"venue"
},
  "geometry": {"coordinates":[-82.915639,42.405255],"type":"Point"}
}