{
  "type": "Feature",
  "properties": {
    "iso:country":"US",
    "sg:address":"2531 Essex Rd",
    "sg:city":"Ann Arbor",
    "sg:classifiers":[
        {
            "category":"Professional",
            "subcategory":"Management & Consulting",
            "type":"Services"
        }
    ],
    "sg:phone":"+1 734 761 3170",
    "sg:postcode":"48104",
    "sg:province":"MI",
    "wof:name":"Macdonald Group Inc",
    "wof:placetype":"venue"
},
  "geometry": {"coordinates":[-83.714343,42.251603],"type":"Point"}
}