{
  "type": "Feature",
  "properties": {
    "iso:country":"US",
    "sg:address":"4585 60th St",
    "sg:city":"Holland",
    "sg:classifiers":[
        {
            "category":"Shopping",
            "subcategory":"Used Merchandise",
            "type":"Retail Goods"
        }
    ],
    "sg:phone":"+1 616 392 1424",
    "sg:postcode":"49423",
    "sg:province":"MI",
    "sg:tags":[
        "antique"
    ],
    "wof:name":"Nob-Hill Antique Mall",
    "wof:placetype":"venue"
},
  "geometry": {"coordinates":[-86.136554,42.753477],"type":"Point"}
}