{
  "type": "Feature",
  "properties": {
    "iso:country":"US",
    "sg:address":"7580 Crystal Rd",
    "sg:city":"Vestaburg",
    "sg:classifiers":[
        {
            "category":"Retail",
            "subcategory":"Auto Repair",
            "type":"Services"
        }
    ],
    "sg:phone":"+1 989 268 5303",
    "sg:postcode":"48891",
    "sg:province":"MI",
    "sg:tags":[
        "general"
    ],
    "wof:name":"Total Service",
    "wof:placetype":"venue"
},
  "geometry": {"coordinates":[-84.90524000000001,43.401779],"type":"Point"}
}