{
  "type": "Feature",
  "properties": {
    "iso:country":"US",
    "sg:address":"735 W McMillan Rd",
    "sg:city":"Muskegon",
    "sg:classifiers":[
        {
            "category":"Building & Trades",
            "subcategory":"Plumbing",
            "type":"Services"
        }
    ],
    "sg:phone":"+1 231 766 3758",
    "sg:postcode":"49445",
    "sg:province":"MI",
    "sg:tags":[
        "sheet",
        "work",
        "metal",
        "contractor"
    ],
    "wof:name":"Midway Sheet Metal",
    "wof:placetype":"venue"
},
  "geometry": {"coordinates":[-86.260587,43.310606],"type":"Point"}
}