{
  "type": "Feature",
  "properties": {
    "iso:country":"US",
    "sg:address":"58011 M 51 S",
    "sg:city":"Dowagiac",
    "sg:classifiers":[
        {
            "category":"Wholesale",
            "subcategory":"Scrap",
            "type":"Manufacturing & Wholesale Goods"
        }
    ],
    "sg:phone":"+1 269 782 0959",
    "sg:postcode":"49047",
    "sg:province":"MI",
    "sg:tags":[
        "recycling",
        "center"
    ],
    "wof:name":"Fryman's Recycling",
    "wof:placetype":"venue"
},
  "geometry": {"coordinates":[-86.150702,41.955829],"type":"Point"}
}