{
  "type": "Feature",
  "properties": {
    "iso:country":"US",
    "sg:address":"39596 Baroque Blvd",
    "sg:city":"Clinton Township",
    "sg:classifiers":[
        {
            "category":"Building & Trades",
            "subcategory":"Construction",
            "type":"Services"
        }
    ],
    "sg:phone":"+1 586 263 4814",
    "sg:postcode":"48038",
    "sg:province":"MI",
    "sg:tags":[
        "house"
    ],
    "wof:name":"Workens Homes",
    "wof:placetype":"venue"
},
  "geometry": {"coordinates":[-82.968626,42.587867],"type":"Point"}
}