{
  "type": "Feature",
  "properties": {
    "iso:country":"US",
    "sg:address":"630 Chene St",
    "sg:city":"Detroit",
    "sg:classifiers":[
        {
            "category":"Government",
            "subcategory":"Police Station",
            "type":"Public Place"
        }
    ],
    "sg:phone":"+1 313 567 1609",
    "sg:postcode":"48207",
    "sg:province":"MI",
    "sg:tags":[
        "protection"
    ],
    "wof:name":"Detroit Safe Neighborhood Acti",
    "wof:placetype":"venue"
},
  "geometry": {"coordinates":[-83.024321,42.340771],"type":"Point"}
}