{
  "type": "Feature",
  "properties": {
    "iso:country":"US",
    "sg:address":"1538 Timber Trl",
    "sg:city":"Whitehall",
    "sg:classifiers":[
        {
            "category":"Professional",
            "subcategory":"Engineering",
            "type":"Services"
        }
    ],
    "sg:phone":"+1 231 893 4532",
    "sg:postcode":"49461",
    "sg:province":"MI",
    "wof:name":"James B Bolger & Assoc Ltd",
    "wof:placetype":"venue"
},
  "geometry": {"coordinates":[-86.27142600000001,43.396485],"type":"Point"}
}