{
  "type": "Feature",
  "properties": {
    "iso:country":"US",
    "sg:address":"2110 18th Ave S",
    "sg:city":"Escanaba",
    "sg:classifiers":[
        {
            "category":"Home & Garden",
            "subcategory":"Building Materials",
            "type":"Retail Goods"
        }
    ],
    "sg:phone":"+1 906 786 5151",
    "sg:postcode":"49829",
    "sg:province":"MI",
    "sg:tags":[
        "glass",
        "window",
        "plate"
    ],
    "wof:name":"Ness Glass Co",
    "wof:placetype":"venue"
},
  "geometry": {"coordinates":[-87.07664200000001,45.724783],"type":"Point"}
}