{
  "type": "Feature",
  "properties": {
    "iso:country":"US",
    "sg:address":"233 W Centre Ave",
    "sg:city":"Portage",
    "sg:classifiers":[
        {
            "category":"Restaurant",
            "type":"Food & Drink"
        }
    ],
    "sg:phone":"+1 269 327 0911",
    "sg:postcode":"49024",
    "sg:province":"MI",
    "wof:name":"Cheesesteak Grill Inc",
    "wof:placetype":"venue"
},
  "geometry": {"coordinates":[-85.590772,42.200981],"type":"Point"}
}