{
  "type": "Feature",
  "properties": {
    "iso:country":"US",
    "sg:address":"5418 Hess Rd",
    "sg:city":"Saginaw",
    "sg:classifiers":[
        {
            "category":"Building & Trades",
            "subcategory":"Landscaping Services",
            "type":"Services"
        }
    ],
    "sg:phone":"+1 989 754 2290",
    "sg:postcode":"48601",
    "sg:province":"MI",
    "sg:tags":[
        "landscape",
        "contractor"
    ],
    "wof:name":"Rohloff Nursery",
    "wof:placetype":"venue"
},
  "geometry": {"coordinates":[-83.85360799999999,43.400022],"type":"Point"}
}