{
  "type": "Feature",
  "properties": {
    "iso:country":"US",
    "sg:address":"161 Ottawa Ave NW",
    "sg:city":"Grand Rapids",
    "sg:classifiers":[
        {
            "category":"Organizations",
            "subcategory":"Professional Association",
            "type":"Services"
        }
    ],
    "sg:phone":"+1 616 459 4331",
    "sg:postcode":"49503",
    "sg:province":"MI",
    "sg:website":"www.mdausa.org",
    "wof:name":"Muscular Dystrophy Assn",
    "wof:placetype":"venue"
},
  "geometry": {"coordinates":[-85.67011100000001,42.967049],"type":"Point"}
}