{
  "type": "Feature",
  "properties": {
    "iso:country":"US",
    "sg:address":"1851 Grandview St",
    "sg:city":"Auburn Hills",
    "sg:classifiers":[
        {
            "category":"Building & Trades",
            "subcategory":"Landscaping Services",
            "type":"Services"
        }
    ],
    "sg:phone":"+1 248 332 0486",
    "sg:postcode":"48326",
    "sg:province":"MI",
    "sg:tags":[
        "landscape"
    ],
    "wof:name":"Rose Ow & Sons",
    "wof:placetype":"venue"
},
  "geometry": {"coordinates":[-83.326469,42.703331],"type":"Point"}
}