{
  "type": "Feature",
  "properties": {
    "iso:country":"US",
    "sg:address":"5515 Auburn Rd",
    "sg:city":"Utica",
    "sg:classifiers":[
        {
            "category":"Retail",
            "subcategory":"Auto Repair",
            "type":"Services"
        }
    ],
    "sg:phone":"+1 586 731 0490",
    "sg:postcode":"48317",
    "sg:province":"MI",
    "sg:tags":[
        "general"
    ],
    "wof:name":"Shelby Foreign Car Service",
    "wof:placetype":"venue"
},
  "geometry": {"coordinates":[-83.05533,42.635501],"type":"Point"}
}