{
  "type": "Feature",
  "properties": {
    "iso:country":"US",
    "sg:address":"2055 Branch Rd",
    "sg:city":"Flint",
    "sg:classifiers":[
        {
            "category":"Freight",
            "type":"Transportation"
        }
    ],
    "sg:phone":"+1 810 250 0079",
    "sg:postcode":"48506",
    "sg:province":"MI",
    "sg:tags":[
        "delivery"
    ],
    "wof:name":"Velocity Express Inc",
    "wof:placetype":"venue"
},
  "geometry": {"coordinates":[-83.649176,43.035092],"type":"Point"}
}