{
  "type": "Feature",
  "properties": {
    "iso:country":"US",
    "sg:address":"4395 Hoyt Rd",
    "sg:city":"Belding",
    "sg:classifiers":[
        {
            "category":"Social Services",
            "subcategory":"Adult Care",
            "type":"Services"
        }
    ],
    "sg:phone":"+1 616 761 3704",
    "sg:postcode":"48809",
    "sg:province":"MI",
    "sg:tags":[
        "foster"
    ],
    "wof:name":"Our Home",
    "wof:placetype":"venue"
},
  "geometry": {"coordinates":[-85.145065,43.068414],"type":"Point"}
}