{
  "type": "Feature",
  "properties": {
    "iso:country":"US",
    "sg:address":"3717 Lakecrest Dr",
    "sg:city":"Bloomfield Hills",
    "sg:classifiers":[
        {
            "category":"Professional",
            "subcategory":"Business Services",
            "type":"Services"
        }
    ],
    "sg:phone":"+1 248 593 9393",
    "sg:postcode":"48304",
    "sg:province":"MI",
    "sg:tags":[
        "interior",
        "design"
    ],
    "wof:name":"Charfoos Design Inc",
    "wof:placetype":"venue"
},
  "geometry": {"coordinates":[-83.225098,42.585499],"type":"Point"}
}