{
  "type": "Feature",
  "properties": {
    "iso:country":"US",
    "sg:address":"6531 N Wisner Rd",
    "sg:city":"Breckenridge",
    "sg:classifiers":[
        {
            "category":"Building & Trades",
            "subcategory":"Construction",
            "type":"Services"
        }
    ],
    "sg:phone":"+1 989 842 3971",
    "sg:postcode":"48615",
    "sg:province":"MI",
    "sg:tags":[
        "contractor"
    ],
    "wof:name":"Morris Industries",
    "wof:placetype":"venue"
},
  "geometry": {"coordinates":[-84.48848599999999,43.388794],"type":"Point"}
}