{
  "type": "Feature",
  "properties": {
    "iso:country":"US",
    "sg:address":"4418 Greensboro Dr",
    "sg:city":"Troy",
    "sg:classifiers":[
        {
            "category":"Health Services",
            "subcategory":"Health Practitioner",
            "type":"Services"
        },
        {
            "category":"Insurance",
            "subcategory":"Health Insurance",
            "type":"Services"
        }
    ],
    "sg:phone":"+1 248 619 9460",
    "sg:postcode":"48085",
    "sg:province":"MI",
    "sg:tags":[
        "nutritionist",
        "market"
    ],
    "wof:name":"Nutritional Metabolic Counseling",
    "wof:placetype":"venue"
},
  "geometry": {"coordinates":[-83.099813,42.584052],"type":"Point"}
}