{
  "type": "Feature",
  "properties": {
    "iso:country":"US",
    "sg:address":"1025 Lapeer Ave",
    "sg:city":"Port Huron",
    "sg:classifiers":[
        {
            "category":"Personal",
            "subcategory":"Beauty Salon",
            "type":"Services"
        }
    ],
    "sg:phone":"+1 810 985 6250",
    "sg:postcode":"48060",
    "sg:province":"MI",
    "sg:tags":[
        "shop"
    ],
    "wof:name":"Continental Cuts Styling Salon",
    "wof:placetype":"venue"
},
  "geometry": {"coordinates":[-82.43468900000001,42.976415],"type":"Point"}
}