{
  "type": "Feature",
  "properties": {
    "iso:country":"US",
    "sg:address":"101 E Adrian St",
    "sg:city":"Blissfield",
    "sg:classifiers":[
        {
            "category":"Real Estate",
            "subcategory":"Real Estate Agent",
            "type":"Services"
        }
    ],
    "sg:phone":"+1 517 486 3121",
    "sg:postcode":"49228",
    "sg:province":"MI",
    "wof:name":"Binns Realty Inc",
    "wof:placetype":"venue"
},
  "geometry": {"coordinates":[-83.86277699999999,41.832595],"type":"Point"}
}