{
  "type": "Feature",
  "properties": {
    "iso:country":"US",
    "sg:address":"350 Ottawa Ave NW",
    "sg:city":"Grand Rapids",
    "sg:classifiers":[
        {
            "category":"Government",
            "subcategory":"Office",
            "type":"Public Place"
        }
    ],
    "sg:phone":"+1 616 458 0323",
    "sg:postcode":"49503",
    "sg:province":"MI",
    "sg:tags":[
        "state",
        "taxation"
    ],
    "wof:name":"Management & Budget",
    "wof:placetype":"venue"
},
  "geometry": {"coordinates":[-85.669971,42.968022],"type":"Point"}
}