{
  "type": "Feature",
  "properties": {
    "iso:country":"US",
    "sg:address":"1177 S Milford Rd",
    "sg:city":"Milford",
    "sg:classifiers":[
        {
            "category":"Personal",
            "subcategory":"Barber",
            "type":"Services"
        }
    ],
    "sg:phone":"+1 248 887 4195",
    "sg:postcode":"48381",
    "sg:province":"MI",
    "wof:name":"Sisters Barber Shop",
    "wof:placetype":"venue"
},
  "geometry": {"coordinates":[-83.612898,42.573944],"type":"Point"}
}