{
  "type": "Feature",
  "properties": {
    "iso:country":"US",
    "sg:address":"12750 Escanaba Dr",
    "sg:city":"Dewitt",
    "sg:classifiers":[
        {
            "category":"Wholesale",
            "subcategory":"Non-durable Goods",
            "type":"Manufacturing & Wholesale Goods"
        }
    ],
    "sg:phone":"+1 517 669 4300",
    "sg:postcode":"48820",
    "sg:province":"MI",
    "sg:tags":[
        "advertising"
    ],
    "sg:website":"www.mahoneypromo.com",
    "wof:name":"Mahoney & Assoc",
    "wof:placetype":"venue"
},
  "geometry": {"coordinates":[-84.54493100000001,42.83107],"type":"Point"}
}