{
  "type": "Feature",
  "properties": {
    "iso:country":"US",
    "sg:address":"27200 Cotton Rd",
    "sg:city":"Chesterfield",
    "sg:classifiers":[
        {
            "category":"Building & Trades",
            "subcategory":"Pest Control",
            "type":"Services"
        }
    ],
    "sg:phone":"+1 586 791 2828",
    "sg:postcode":"48047",
    "sg:province":"MI",
    "wof:name":"Environmental Systems",
    "wof:placetype":"venue"
},
  "geometry": {"coordinates":[-82.83504000000001,42.668434],"type":"Point"}
}