{
  "type": "Feature",
  "properties": {
    "iso:country":"US",
    "sg:address":"1311 Chicago Dr SW",
    "sg:city":"Grand Rapids",
    "sg:classifiers":[
        {
            "category":"Retail",
            "subcategory":"Funeral Services",
            "type":"Services"
        }
    ],
    "sg:phone":"+1 616 243 2966",
    "sg:postcode":"49509",
    "sg:province":"MI",
    "sg:tags":[
        "home"
    ],
    "wof:name":"Kuiper Funeral Home",
    "wof:placetype":"venue"
},
  "geometry": {"coordinates":[-85.70093799999999,42.935469],"type":"Point"}
}