{
  "type": "Feature",
  "properties": {
    "iso:country":"US",
    "sg:address":"1530 Emerson Rd",
    "sg:city":"Goodells",
    "sg:classifiers":[
        {
            "category":"Organizations",
            "subcategory":"Religious Organization",
            "type":"Services"
        }
    ],
    "sg:phone":"+1 810 325 1343",
    "sg:postcode":"48027",
    "sg:province":"MI",
    "sg:tags":[
        "church"
    ],
    "wof:name":"Mount Pleasant Bible Church",
    "wof:placetype":"venue"
},
  "geometry": {"coordinates":[-82.649734,42.948784],"type":"Point"}
}