{
  "type": "Feature",
  "properties": {
    "iso:country":"US",
    "sg:address":"1420 Washington Blvd",
    "sg:city":"Detroit",
    "sg:classifiers":[
        {
            "category":"Home & Garden",
            "subcategory":"Carpets & Floor Coverings",
            "type":"Retail Goods"
        }
    ],
    "sg:phone":"+1 734 421 6028",
    "sg:postcode":"48226",
    "sg:province":"MI",
    "sg:tags":[
        "inspection",
        "rug"
    ],
    "wof:name":"Carpetology",
    "wof:placetype":"venue"
},
  "geometry": {"coordinates":[-83.05091400000001,42.333877],"type":"Point"}
}