{
  "type": "Feature",
  "properties": {
    "iso:country":"US",
    "sg:address":"5435 Corporate Dr",
    "sg:city":"Troy",
    "sg:classifiers":[
        {
            "category":"Professional",
            "subcategory":"Lawyer & Legal Services",
            "type":"Services"
        }
    ],
    "sg:phone":"+1 248 952 0400",
    "sg:postcode":"48098",
    "sg:province":"MI",
    "sg:tags":[
        "attorney"
    ],
    "sg:website":"www.fhwnlaw.com",
    "wof:name":"Frank Haron Weiner Navarro",
    "wof:placetype":"venue"
},
  "geometry": {"coordinates":[-83.17135399999999,42.597903],"type":"Point"}
}