{
  "type": "Feature",
  "properties": {
    "iso:country":"US",
    "sg:address":"28005 el Dorado Pl",
    "sg:city":"Lathrup Village",
    "sg:classifiers":[
        {
            "category":"Professional",
            "subcategory":"Computer Services",
            "type":"Services"
        }
    ],
    "sg:phone":"+1 248 552 8593",
    "sg:postcode":"48076",
    "sg:province":"MI",
    "sg:tags":[
        "consultant",
        "designer",
        "programing",
        "custom"
    ],
    "wof:name":"Networkspace Inc",
    "wof:placetype":"venue"
},
  "geometry": {"coordinates":[-83.224779,42.496291],"type":"Point"}
}