{
  "type": "Feature",
  "properties": {
    "iso:country":"US",
    "sg:address":"33901 Woodward Ave",
    "sg:city":"Birmingham",
    "sg:classifiers":[
        {
            "category":"Restaurant",
            "type":"Food & Drink"
        }
    ],
    "sg:phone":"+1 248 540 6040",
    "sg:postcode":"48009",
    "sg:province":"MI",
    "sg:tags":[
        "pizza"
    ],
    "sg:website":"www.hungryhowies.com",
    "wof:name":"Hungry Howie's Pizza & Subs",
    "wof:placetype":"venue"
},
  "geometry": {"coordinates":[-83.222702,42.5578],"type":"Point"}
}