{
  "type": "Feature",
  "properties": {
    "iso:country":"US",
    "sg:address":"4165 Summit Woods Dr NE",
    "sg:city":"Rockford",
    "sg:classifiers":[
        {
            "category":"Professional",
            "subcategory":"Management & Consulting",
            "type":"Services"
        }
    ],
    "sg:phone":"+1 616 866 6035",
    "sg:postcode":"49341",
    "sg:province":"MI",
    "wof:name":"Daniel E Male",
    "wof:placetype":"venue"
},
  "geometry": {"coordinates":[-85.566315,43.173818],"type":"Point"}
}