{
  "type": "Feature",
  "properties": {
    "iso:country":"US",
    "sg:address":"4100 Peet Rd",
    "sg:city":"Chesaning",
    "sg:classifiers":[
        {
            "category":"Building & Trades",
            "subcategory":"Plumbing",
            "type":"Services"
        }
    ],
    "sg:phone":"+1 989 845 3881",
    "sg:postcode":"48616",
    "sg:province":"MI",
    "sg:tags":[
        "heating",
        "contractor"
    ],
    "wof:name":"Alfred Bishop Plumbing & Htg",
    "wof:placetype":"venue"
},
  "geometry": {"coordinates":[-83.995105,43.175759],"type":"Point"}
}