{
  "type": "Feature",
  "properties": {
    "iso:country":"US",
    "sg:address":"1005 S Adelaide St",
    "sg:city":"Fenton",
    "sg:classifiers":[
        {
            "category":"Building & Trades",
            "subcategory":"Construction",
            "type":"Services"
        }
    ],
    "sg:phone":"+1 810 714 1105",
    "sg:postcode":"48430",
    "sg:province":"MI",
    "sg:tags":[
        "house"
    ],
    "wof:name":"Premier Construction Services",
    "wof:placetype":"venue"
},
  "geometry": {"coordinates":[-83.70649299999999,42.785787],"type":"Point"}
}