{
  "type": "Feature",
  "properties": {
    "iso:country":"US",
    "sg:address":"309 S Green Ave",
    "sg:city":"Fremont",
    "sg:classifiers":[
        {
            "category":"Farming",
            "subcategory":"Dairy Farm",
            "type":"Manufacturing & Wholesale Goods"
        }
    ],
    "sg:phone":"+1 231 924 2496",
    "sg:postcode":"49412",
    "sg:province":"MI",
    "wof:name":"Smith Farmer",
    "wof:placetype":"venue"
},
  "geometry": {"coordinates":[-85.979906,43.548454],"type":"Point"}
}