{
  "type": "Feature",
  "properties": {
    "iso:country":"US",
    "sg:address":"30210 W 8 Mile Rd",
    "sg:city":"Farmington Hills",
    "sg:classifiers":[
        {
            "category":"Retail",
            "subcategory":"Auto Repair",
            "type":"Services"
        }
    ],
    "sg:phone":"+1 248 476 2677",
    "sg:postcode":"48336",
    "sg:province":"MI",
    "sg:tags":[
        "automobile",
        "restoration",
        "classic"
    ],
    "wof:name":"Pro Street Creations",
    "wof:placetype":"venue"
},
  "geometry": {"coordinates":[-83.345972,42.441416],"type":"Point"}
}