{
  "type": "Feature",
  "properties": {
    "iso:country":"US",
    "sg:address":"105 E Nagonaba St",
    "sg:city":"Northport",
    "sg:classifiers":[
        {
            "category":"Food & Beverages",
            "subcategory":"Groceries & Convenience Stores",
            "type":"Retail Goods"
        }
    ],
    "sg:phone":"+1 231 386 5721",
    "sg:postcode":"49670",
    "sg:province":"MI",
    "sg:tags":[
        "grocer"
    ],
    "wof:name":"Tom's Food Market",
    "wof:placetype":"venue"
},
  "geometry": {"coordinates":[-85.615734,45.129809],"type":"Point"}
}