{
  "type": "Feature",
  "properties": {
    "iso:country":"US",
    "sg:address":"118 W Grand River Ave",
    "sg:city":"Howell",
    "sg:classifiers":[
        {
            "category":"Food & Beverages",
            "subcategory":"Groceries & Convenience Stores",
            "type":"Retail Goods"
        }
    ],
    "sg:phone":"+1 517 548 9060",
    "sg:postcode":"48843",
    "sg:province":"MI",
    "sg:tags":[
        "product"
    ],
    "wof:name":"Spags Specialties Inc",
    "wof:placetype":"venue"
},
  "geometry": {"coordinates":[-83.930516,42.607553],"type":"Point"}
}