{
  "type": "Feature",
  "properties": {
    "iso:country":"US",
    "sg:address":"1201 Fort St",
    "sg:city":"Wyandotte",
    "sg:classifiers":[
        {
            "category":"Insurance",
            "subcategory":"Insurance Agent",
            "type":"Services"
        }
    ],
    "sg:phone":"+1 734 284 5588",
    "sg:postcode":"48183",
    "sg:province":"MI",
    "wof:name":"State Farm Insurance",
    "wof:placetype":"venue"
},
  "geometry": {"coordinates":[-83.188433,42.165675],"type":"Point"}
}