{
  "type": "Feature",
  "properties": {
    "iso:country":"US",
    "sg:address":"15077 Glastonbury Ave",
    "sg:city":"Detroit",
    "sg:classifiers":[
        {
            "category":"Sports & Exercise",
            "subcategory":"Gym",
            "type":"Entertainment"
        }
    ],
    "sg:phone":"+1 313 272 6641",
    "sg:postcode":"48223",
    "sg:province":"MI",
    "sg:tags":[
        "fitness",
        "physical",
        "facility"
    ],
    "wof:name":"Urban Ftnes Klub Fmly Mgazines",
    "wof:placetype":"venue"
},
  "geometry": {"coordinates":[-83.22530500000001,42.400304],"type":"Point"}
}