{
  "type": "Feature",
  "properties": {
    "iso:country":"US",
    "sg:address":"2278 E US Hwy 10",
    "sg:city":"Custer",
    "sg:classifiers":[
        {
            "category":"Bars & Pubs",
            "type":"Food & Drink"
        }
    ],
    "sg:phone":"+1 231 757 9914",
    "sg:postcode":"49405",
    "sg:province":"MI",
    "sg:tags":[
        "lounge",
        "cocktail"
    ],
    "wof:name":"Johnny's",
    "wof:placetype":"venue"
},
  "geometry": {"coordinates":[-86.22068899999999,43.954671],"type":"Point"}
}