{
  "type": "Feature",
  "properties": {
    "iso:country":"US",
    "sg:address":"3911 Plainfield Ave NE",
    "sg:city":"Grand Rapids",
    "sg:classifiers":[
        {
            "category":"Shopping",
            "subcategory":"Clothing, Apparel, & Fashions",
            "type":"Retail Goods"
        }
    ],
    "sg:phone":"+1 616 364 8889",
    "sg:postcode":"49525",
    "sg:province":"MI",
    "sg:tags":[
        "tailor"
    ],
    "wof:name":"Rosa Alteration & Tailor",
    "wof:placetype":"venue"
},
  "geometry": {"coordinates":[-85.621706,43.033983],"type":"Point"}
}