{
  "type": "Feature",
  "properties": {
    "iso:country":"US",
    "sg:address":"192 S Main St",
    "sg:city":"Mount Clemens",
    "sg:classifiers":[
        {
            "category":"Food & Beverages",
            "subcategory":"Groceries & Convenience Stores",
            "type":"Retail Goods"
        }
    ],
    "sg:phone":"+1 586 469 8470",
    "sg:postcode":"48043",
    "sg:province":"MI",
    "wof:name":"Hikmet Humu",
    "wof:placetype":"venue"
},
  "geometry": {"coordinates":[-82.88134599999999,42.590475],"type":"Point"}
}