{
  "type": "Feature",
  "properties": {
    "iso:country":"US",
    "sg:address":"15899 W Saddlebag Lake Rd",
    "sg:city":"Decatur",
    "sg:classifiers":[
        {
            "category":"Manufacturing",
            "subcategory":"Rubber & Plastics",
            "type":"Manufacturing & Wholesale Goods"
        }
    ],
    "sg:phone":"+1 269 646 3388",
    "sg:postcode":"49045",
    "sg:province":"MI",
    "sg:tags":[
        "product",
        "mfg"
    ],
    "wof:name":"Plastics By Design Inc",
    "wof:placetype":"venue"
},
  "geometry": {"coordinates":[-85.874865,42.052429],"type":"Point"}
}