{
  "type": "Feature",
  "properties": {
    "iso:country":"US",
    "sg:address":"8026 Coyle St",
    "sg:city":"Detroit",
    "sg:classifiers":[
        {
            "category":"Building & Trades",
            "subcategory":"Cleaning & Sanitation",
            "type":"Services"
        }
    ],
    "sg:phone":"+1 313 584 6903",
    "sg:postcode":"48228",
    "sg:province":"MI",
    "sg:tags":[
        "cleaning-industrial",
        "contractor"
    ],
    "wof:name":"Right Way Commercial Cleaning",
    "wof:placetype":"venue"
},
  "geometry": {"coordinates":[-83.192307,42.351291],"type":"Point"}
}