{
  "type": "Feature",
  "properties": {
    "iso:country":"US",
    "sg:address":"1000 W Sharon Ave",
    "sg:city":"Houghton",
    "sg:classifiers":[
        {
            "category":"Food & Beverages",
            "subcategory":"Groceries & Convenience Stores",
            "type":"Retail Goods"
        }
    ],
    "sg:phone":"+1 906 487 9675",
    "sg:postcode":"49931",
    "sg:province":"MI",
    "sg:tags":[
        "grocer"
    ],
    "wof:name":"Econofoods",
    "wof:placetype":"venue"
},
  "geometry": {"coordinates":[-88.589939,47.113271],"type":"Point"}
}