{
  "type": "Feature",
  "properties": {
    "iso:country":"US",
    "sg:address":"22425 Alexander St",
    "sg:city":"Saint Clair Shores",
    "sg:classifiers":[
        {
            "category":"Professional",
            "subcategory":"Business Services",
            "type":"Services"
        }
    ],
    "sg:phone":"+1 586 776 5573",
    "sg:postcode":"48081",
    "sg:province":"MI",
    "wof:name":"Jt Design Inc",
    "wof:placetype":"venue"
},
  "geometry": {"coordinates":[-82.888563,42.492932],"type":"Point"}
}