{
  "type": "Feature",
  "properties": {
    "iso:country":"US",
    "sg:address":"382 Cranbrook Ct",
    "sg:city":"Bloomfield Hills",
    "sg:classifiers":[
        {
            "category":"Banks & Credit Unions",
            "subcategory":"Financial Services",
            "type":"Services"
        }
    ],
    "sg:phone":"+1 248 723 8070",
    "sg:postcode":"48304",
    "sg:province":"MI",
    "sg:tags":[
        "fund",
        "mutual",
        "investor"
    ],
    "wof:name":"York Company LLC",
    "wof:placetype":"venue"
},
  "geometry": {"coordinates":[-83.23845900000001,42.564474],"type":"Point"}
}