{
  "type": "Feature",
  "properties": {
    "iso:country":"US",
    "sg:address":"11931 US Hwy 23",
    "sg:city":"Ossineke",
    "sg:classifiers":[
        {
            "category":"Personal",
            "subcategory":"Barber",
            "type":"Services"
        }
    ],
    "sg:phone":"+1 989 471 5456",
    "sg:postcode":"49766",
    "sg:province":"MI",
    "wof:name":"Mc Guires Barber Shop",
    "wof:placetype":"venue"
},
  "geometry": {"coordinates":[-83.44297,44.903332],"type":"Point"}
}