{
  "type": "Feature",
  "properties": {
    "iso:country":"US",
    "sg:address":"3865 Lapeer Rd",
    "sg:city":"Flint",
    "sg:classifiers":[
        {
            "category":"Banks & Credit Unions",
            "subcategory":"Bank",
            "type":"Services"
        }
    ],
    "sg:phone":"+1 810 742 3640",
    "sg:postcode":"48506",
    "sg:province":"MI",
    "sg:tags":[
        "cashing",
        "check"
    ],
    "wof:name":"Cash Store",
    "wof:placetype":"venue"
},
  "geometry": {"coordinates":[-83.63534300000001,43.010152],"type":"Point"}
}