{
  "type": "Feature",
  "properties": {
    "iso:country":"US",
    "sg:address":"102 2nd",
    "sg:city":"Mohawk",
    "sg:classifiers":[
        {
            "category":"Government",
            "subcategory":"Office",
            "type":"Public Place"
        }
    ],
    "sg:phone":"+1 906 337 2302",
    "sg:postcode":"49950",
    "sg:province":"MI",
    "sg:tags":[
        "village"
    ],
    "wof:name":"Allouez Township Hall",
    "wof:placetype":"venue"
},
  "geometry": {"coordinates":[-88.359364,47.30598],"type":"Point"}
}