{
  "type": "Feature",
  "properties": {
    "iso:country":"US",
    "sg:address":"71 E State Rd",
    "sg:city":"West Branch",
    "sg:classifiers":[
        {
            "category":"Shopping",
            "subcategory":"Bicycles & Sporting Goods",
            "type":"Retail Goods"
        }
    ],
    "sg:phone":"+1 989 685 8811",
    "sg:postcode":"48661",
    "sg:province":"MI",
    "sg:tags":[
        "tackle",
        "fishing"
    ],
    "wof:name":"Bachelder's Spool & Fly",
    "wof:placetype":"venue"
},
  "geometry": {"coordinates":[-84.123265,44.313108],"type":"Point"}
}