{
  "type": "Feature",
  "properties": {
    "iso:country":"US",
    "sg:address":"43297 Garfield Rd",
    "sg:city":"Clinton Township",
    "sg:classifiers":[
        {
            "category":"Health Services",
            "subcategory":"Doctor",
            "type":"Services"
        }
    ],
    "sg:phone":"+1 586 263 5252",
    "sg:postcode":"48038",
    "sg:province":"MI",
    "wof:name":"Lafrenz Juergen DDS",
    "wof:placetype":"venue"
},
  "geometry": {"coordinates":[-82.953126,42.61516],"type":"Point"}
}