{
  "type": "Feature",
  "properties": {
    "iso:country":"US",
    "sg:address":"7500 Valhalla Dr SE",
    "sg:city":"Alto",
    "sg:classifiers":[
        {
            "category":"Professional",
            "subcategory":"Management & Consulting",
            "type":"Services"
        }
    ],
    "sg:phone":"+1 616 554 3533",
    "sg:postcode":"49302",
    "sg:province":"MI",
    "sg:tags":[
        "business"
    ],
    "wof:name":"Coordination Station",
    "wof:placetype":"venue"
},
  "geometry": {"coordinates":[-85.480375,42.845693],"type":"Point"}
}