{
  "type": "Feature",
  "properties": {
    "iso:country":"US",
    "sg:address":"129 Adelaide St",
    "sg:city":"Maple Rapids",
    "sg:classifiers":[
        {
            "category":"Health Services",
            "subcategory":"Doctor",
            "type":"Services"
        }
    ],
    "sg:phone":"+1 989 682 4311",
    "sg:postcode":"48853",
    "sg:province":"MI",
    "sg:tags":[
        "physician",
        "surgeon"
    ],
    "wof:name":"William M Steigerwald DO",
    "wof:placetype":"venue"
},
  "geometry": {"coordinates":[-84.692115,43.103867],"type":"Point"}
}