{
  "type": "Feature",
  "properties": {
    "iso:country":"US",
    "sg:address":"501 S Cedar St",
    "sg:city":"Greenville",
    "sg:classifiers":[
        {
            "category":"Manufacturing",
            "subcategory":"Rubber & Plastics",
            "type":"Manufacturing & Wholesale Goods"
        }
    ],
    "sg:phone":"+1 616 754 1199",
    "sg:postcode":"48838",
    "sg:province":"MI",
    "sg:website":"www.clariontechnologies.com",
    "wof:name":"Clarion Technologies",
    "wof:placetype":"venue"
},
  "geometry": {"coordinates":[-85.245332,43.177146],"type":"Point"}
}