{
  "type": "Feature",
  "properties": {
    "iso:country":"US",
    "sg:address":"1841 Scheifle Rd",
    "sg:city":"Walled Lake",
    "sg:classifiers":[
        {
            "category":"Shopping",
            "subcategory":"Jewelry",
            "type":"Retail Goods"
        }
    ],
    "sg:phone":"+1 248 960 5595",
    "sg:postcode":"48390",
    "sg:province":"MI",
    "wof:name":"Earthway",
    "wof:placetype":"venue"
},
  "geometry": {"coordinates":[-83.46445,42.544558],"type":"Point"}
}