{
  "type": "Feature",
  "properties": {
    "iso:country":"US",
    "sg:address":"20 E Main St",
    "sg:city":"Mayville",
    "sg:classifiers":[
        {
            "category":"Organizations",
            "subcategory":"Community Association",
            "type":"Services"
        }
    ],
    "sg:phone":"+1 989 843 5731",
    "sg:postcode":"48744",
    "sg:province":"MI",
    "sg:tags":[
        "fraternal"
    ],
    "wof:name":"Fraternal Order Of Eagles",
    "wof:placetype":"venue"
},
  "geometry": {"coordinates":[-83.352397,43.33687],"type":"Point"}
}