{
  "type": "Feature",
  "properties": {
    "iso:country":"US",
    "sg:address":"1387 E Larned St",
    "sg:city":"Detroit",
    "sg:classifiers":[
        {
            "category":"Real Estate",
            "subcategory":"Real Estate Operator",
            "type":"Services"
        }
    ],
    "sg:phone":"+1 313 567 2995",
    "sg:postcode":"48207",
    "sg:province":"MI",
    "sg:tags":[
        "apartment"
    ],
    "wof:name":"Carlton Apartments",
    "wof:placetype":"venue"
},
  "geometry": {"coordinates":[-83.03220399999999,42.3353],"type":"Point"}
}