{
  "type": "Feature",
  "properties": {
    "iso:country":"US",
    "sg:address":"1040 Chapin Ave",
    "sg:city":"Birmingham",
    "sg:classifiers":[
        {
            "category":"Real Estate",
            "subcategory":"Architect",
            "type":"Services"
        }
    ],
    "sg:phone":"+1 248 644 3001",
    "sg:postcode":"48009",
    "sg:province":"MI",
    "sg:tags":[
        "architectural"
    ],
    "wof:name":"Gretchen Maricak Archite",
    "wof:placetype":"venue"
},
  "geometry": {"coordinates":[-83.208281,42.535702],"type":"Point"}
}