{
  "type": "Feature",
  "properties": {
    "iso:country":"US",
    "sg:address":"6120 Campbell Rd",
    "sg:city":"Ann Arbor",
    "sg:classifiers":[
        {
            "category":"Retail",
            "subcategory":"Auto Repair",
            "type":"Services"
        }
    ],
    "sg:phone":"+1 734 429 3062",
    "sg:postcode":"48108",
    "sg:province":"MI",
    "sg:tags":[
        "body"
    ],
    "wof:name":"Alternative Auto Custom U",
    "wof:placetype":"venue"
},
  "geometry": {"coordinates":[-83.71417099999999,42.195779],"type":"Point"}
}