{
  "type": "Feature",
  "properties": {
    "iso:country":"US",
    "sg:address":"412 S Boundary Rd",
    "sg:city":"Ontonagon",
    "sg:classifiers":[
        {
            "category":"Government",
            "subcategory":"Office",
            "type":"Public Place"
        }
    ],
    "sg:phone":"+1 906 885 5275",
    "sg:postcode":"49953",
    "sg:province":"MI",
    "sg:tags":[
        "conservation"
    ],
    "wof:name":"Porcupine Mnt Wildenss State",
    "wof:placetype":"venue"
},
  "geometry": {"coordinates":[-89.62697900000001,46.794485],"type":"Point"}
}