{
  "type": "Feature",
  "properties": {
    "iso:country":"US",
    "sg:address":"10515 W Nelson Rd",
    "sg:city":"Carson City",
    "sg:classifiers":[
        {
            "category":"Professional",
            "subcategory":"Accounting & Tax Preparation",
            "type":"Services"
        }
    ],
    "sg:phone":"+1 989 584 2081",
    "sg:postcode":"48811",
    "sg:province":"MI",
    "sg:tags":[
        "bookkeeping",
        "general"
    ],
    "wof:name":"Debbie's Bookkeeping",
    "wof:placetype":"venue"
},
  "geometry": {"coordinates":[-84.80740400000001,43.21261],"type":"Point"}
}