{
  "type": "Feature",
  "properties": {
    "iso:country":"US",
    "sg:address":"304 Central Ave",
    "sg:city":"Pontiac",
    "sg:classifiers":[
        {
            "category":"Personal",
            "subcategory":"Beauty Salon",
            "type":"Services"
        }
    ],
    "sg:phone":"+1 248 332 3518",
    "sg:postcode":"48341",
    "sg:province":"MI",
    "sg:tags":[
        "shop"
    ],
    "wof:name":"More Hair Beauty Salon",
    "wof:placetype":"venue"
},
  "geometry": {"coordinates":[-83.27630600000001,42.621417],"type":"Point"}
}