{
  "type": "Feature",
  "properties": {
    "iso:country":"US",
    "sg:address":"16195 Jacob Rd",
    "sg:city":"Linden",
    "sg:classifiers":[
        {
            "category":"Real Estate",
            "subcategory":"Real Estate Agent",
            "type":"Services"
        }
    ],
    "sg:phone":"+1 810 629 9786",
    "sg:postcode":"48451",
    "sg:province":"MI",
    "wof:name":"B J Bidwell Inc",
    "wof:placetype":"venue"
},
  "geometry": {"coordinates":[-83.77028,42.790591],"type":"Point"}
}