{
  "type": "Feature",
  "properties": {
    "iso:country":"US",
    "sg:address":"560 S Dort Hwy",
    "sg:city":"Flint",
    "sg:classifiers":[
        {
            "category":"Restaurant",
            "type":"Food & Drink"
        }
    ],
    "sg:phone":"+1 810 244 9600",
    "sg:postcode":"48503",
    "sg:province":"MI",
    "wof:name":"Anna's Kitchen",
    "wof:placetype":"venue"
},
  "geometry": {"coordinates":[-83.654999,43.020401],"type":"Point"}
}