{
  "type": "Feature",
  "properties": {
    "iso:country":"US",
    "sg:address":"6712 Cascade Rd SE",
    "sg:city":"Grand Rapids",
    "sg:classifiers":[
        {
            "category":"Restaurant",
            "type":"Food & Drink"
        }
    ],
    "sg:phone":"+1 616 247 8838",
    "sg:postcode":"49546",
    "sg:province":"MI",
    "wof:name":"New Yorker Restaurant",
    "wof:placetype":"venue"
},
  "geometry": {"coordinates":[-85.501352,42.915489],"type":"Point"}
}