{
  "type": "Feature",
  "properties": {
    "iso:country":"US",
    "sg:address":"6536 Scio Church Rd",
    "sg:city":"Ann Arbor",
    "sg:classifiers":[
        {
            "category":"Social Services",
            "subcategory":"Child Care",
            "type":"Services"
        }
    ],
    "sg:phone":"+1 734 665 5175",
    "sg:postcode":"48103",
    "sg:province":"MI",
    "sg:tags":[
        "camp",
        "day"
    ],
    "wof:name":"Sunshine Special",
    "wof:placetype":"venue"
},
  "geometry": {"coordinates":[-83.855665,42.254366],"type":"Point"}
}