{
  "type": "Feature",
  "properties": {
    "iso:country":"US",
    "sg:address":"436 Myrtle St",
    "sg:city":"Petoskey",
    "sg:classifiers":[
        {
            "category":"Personal",
            "type":"Services"
        }
    ],
    "sg:phone":"+1 231 347 8440",
    "sg:postcode":"49770",
    "sg:province":"MI",
    "sg:tags":[
        "therapist",
        "massage"
    ],
    "wof:name":"Litle Traverse Clinical Messg",
    "wof:placetype":"venue"
},
  "geometry": {"coordinates":[-84.954976,45.364844],"type":"Point"}
}