{
  "type": "Feature",
  "properties": {
    "iso:country":"US",
    "sg:address":"13350 Capital St",
    "sg:city":"Oak Park",
    "sg:classifiers":[
        {
            "category":"Freight",
            "type":"Transportation"
        }
    ],
    "sg:phone":"+1 248 336 9799",
    "sg:postcode":"48237",
    "sg:province":"MI",
    "sg:tags":[
        "commercial",
        "storage"
    ],
    "wof:name":"Safety Mini-Storage",
    "wof:placetype":"venue"
},
  "geometry": {"coordinates":[-83.17947599999999,42.455051],"type":"Point"}
}