{
  "type": "Feature",
  "properties": {
    "iso:country":"US",
    "sg:address":"18164 Mack Ave",
    "sg:city":"Grosse Pointe",
    "sg:classifiers":[
        {
            "category":"Banks & Credit Unions",
            "subcategory":"Investment Brokerage",
            "type":"Services"
        }
    ],
    "sg:phone":"+1 313 343 0788",
    "sg:postcode":"48230",
    "sg:province":"MI",
    "sg:tags":[
        "security"
    ],
    "wof:name":"Raymond James Financial Svcs",
    "wof:placetype":"venue"
},
  "geometry": {"coordinates":[-82.915109,42.406251],"type":"Point"}
}