{
  "type": "Feature",
  "properties": {
    "iso:country":"US",
    "sg:address":"18600 S Beech Daly Rd",
    "sg:city":"Romulus",
    "sg:classifiers":[
        {
            "category":"Organizations",
            "subcategory":"Professional Association",
            "type":"Services"
        }
    ],
    "sg:phone":"+1 734 942 9474",
    "sg:postcode":"48174",
    "sg:province":"MI",
    "wof:name":"David Felder & Associates",
    "wof:placetype":"venue"
},
  "geometry": {"coordinates":[-83.286317,42.168287],"type":"Point"}
}