{
  "type": "Feature",
  "properties": {
    "iso:country":"US",
    "sg:address":"1845 Norfolk St",
    "sg:city":"Birmingham",
    "sg:classifiers":[
        {
            "category":"Banks & Credit Unions",
            "subcategory":"Financial Services",
            "type":"Services"
        }
    ],
    "sg:phone":"+1 248 642 1025",
    "sg:postcode":"48009",
    "sg:province":"MI",
    "sg:tags":[
        "trust",
        "management"
    ],
    "wof:name":"John M Karns",
    "wof:placetype":"venue"
},
  "geometry": {"coordinates":[-83.228719,42.53167],"type":"Point"}
}