{
  "type": "Feature",
  "properties": {
    "iso:country":"US",
    "sg:address":"10728 S Westnedge Ave",
    "sg:city":"Portage",
    "sg:classifiers":[
        {
            "category":"Social Services",
            "subcategory":"Child Care",
            "type":"Services"
        }
    ],
    "sg:phone":"+1 269 327 2624",
    "sg:postcode":"49002",
    "sg:province":"MI",
    "sg:tags":[
        "day"
    ],
    "wof:name":"Christine Macleay",
    "wof:placetype":"venue"
},
  "geometry": {"coordinates":[-85.588993,42.161225],"type":"Point"}
}