{
  "type": "Feature",
  "properties": {
    "iso:country":"US",
    "sg:address":"11191 Mills-Macon Hwy",
    "sg:city":"Tecumseh",
    "sg:classifiers":[
        {
            "category":"Banks & Credit Unions",
            "subcategory":"Financial Services",
            "type":"Services"
        }
    ],
    "sg:phone":"+1 517 423 7961",
    "sg:postcode":"49286",
    "sg:province":"MI",
    "sg:tags":[
        "trust",
        "management"
    ],
    "wof:name":"David Squires Trust",
    "wof:placetype":"venue"
},
  "geometry": {"coordinates":[-83.851046,42.052522],"type":"Point"}
}