{
  "type": "Feature",
  "properties": {
    "iso:country":"US",
    "sg:address":"7715 Trotters Ln",
    "sg:city":"Whitmore Lake",
    "sg:classifiers":[
        {
            "category":"Building & Trades",
            "subcategory":"Landscaping Services",
            "type":"Services"
        }
    ],
    "sg:phone":"+1 734 449 5318",
    "sg:postcode":"48189",
    "sg:province":"MI",
    "wof:name":"Js Tree Trimming & Removal",
    "wof:placetype":"venue"
},
  "geometry": {"coordinates":[-83.79428900000001,42.395829],"type":"Point"}
}