{
  "type": "Feature",
  "properties": {
    "iso:country":"US",
    "sg:address":"624 3rd St",
    "sg:city":"Detroit",
    "sg:classifiers":[
        {
            "category":"Bars & Pubs",
            "subcategory":"Dive Bar",
            "type":"Food & Drink"
        }
    ],
    "sg:phone":"+1 313 964 5047",
    "sg:postcode":"48226",
    "sg:province":"MI",
    "wof:name":"Mac's On Third",
    "wof:placetype":"venue"
},
  "geometry": {"coordinates":[-83.05356399999999,42.327308],"type":"Point"}
}