{
  "type": "Feature",
  "properties": {
    "iso:country":"US",
    "sg:address":"1200 Keystone Ave",
    "sg:city":"Lansing",
    "sg:classifiers":[
        {
            "category":"Wholesale",
            "subcategory":"Furniture",
            "type":"Manufacturing & Wholesale Goods"
        }
    ],
    "sg:phone":"+1 517 393 0440",
    "sg:postcode":"48911",
    "sg:province":"MI",
    "sg:tags":[
        "equipment",
        "school"
    ],
    "wof:name":"Teachers Store",
    "wof:placetype":"venue"
},
  "geometry": {"coordinates":[-84.53271599999999,42.675168],"type":"Point"}
}