{
  "type": "Feature",
  "properties": {
    "iso:country":"US",
    "sg:address":"1033 Knollside Ct",
    "sg:city":"Lake Orion",
    "sg:classifiers":[
        {
            "category":"Real Estate",
            "subcategory":"Real Estate Operator",
            "type":"Services"
        }
    ],
    "sg:phone":"+1 248 693 8648",
    "sg:postcode":"48362",
    "sg:province":"MI",
    "sg:tags":[
        "building",
        "nonresidential"
    ],
    "wof:name":"Amglo Properties LLC",
    "wof:placetype":"venue"
},
  "geometry": {"coordinates":[-83.229955,42.774419],"type":"Point"}
}