{
  "type": "Feature",
  "properties": {
    "iso:country":"US",
    "sg:address":"14478 3rd St",
    "sg:city":"Detroit",
    "sg:classifiers":[
        {
            "category":"Professional",
            "subcategory":"Computer Services",
            "type":"Services"
        }
    ],
    "sg:phone":"+1 313 869 7120",
    "sg:postcode":"48203",
    "sg:province":"MI",
    "sg:tags":[
        "development",
        "software"
    ],
    "wof:name":"Lanco Enterprise",
    "wof:placetype":"venue"
},
  "geometry": {"coordinates":[-83.10601800000001,42.4078],"type":"Point"}
}