{
  "type": "Feature",
  "properties": {
    "iso:country":"US",
    "sg:address":"41767 Joy Rd",
    "sg:city":"Canton",
    "sg:classifiers":[
        {
            "category":"Wholesale",
            "subcategory":"Machinery & Supplies",
            "type":"Manufacturing & Wholesale Goods"
        }
    ],
    "sg:phone":"+1 734 453 6797",
    "sg:postcode":"48187",
    "sg:province":"MI",
    "sg:tags":[
        "packaging",
        "equipment",
        "mater",
        "industrial"
    ],
    "wof:name":"C F Sales Co Inc",
    "wof:placetype":"venue"
},
  "geometry": {"coordinates":[-83.450898,42.351868],"type":"Point"}
}