{
  "type": "Feature",
  "properties": {
    "iso:country":"US",
    "sg:address":"1145 Wesley Ave",
    "sg:city":"Muskegon",
    "sg:classifiers":[
        {
            "category":"Social Services",
            "type":"Services"
        }
    ],
    "sg:phone":"+1 231 777 2006",
    "sg:postcode":"49442",
    "sg:province":"MI",
    "sg:tags":[
        "rehabilitation",
        "for",
        "retarded"
    ],
    "wof:name":"ARC Muskegon",
    "wof:placetype":"venue"
},
  "geometry": {"coordinates":[-86.216945,43.241375],"type":"Point"}
}