{
  "type": "Feature",
  "properties": {
    "iso:country":"US",
    "sg:address":"23830 36th Ave",
    "sg:city":"Ravenna",
    "sg:classifiers":[
        {
            "category":"Building & Trades",
            "subcategory":"Construction",
            "type":"Services"
        }
    ],
    "sg:phone":"+1 231 788 4504",
    "sg:postcode":"49451",
    "sg:province":"MI",
    "sg:tags":[
        "general",
        "contractor"
    ],
    "wof:name":"F Hornacek Construction",
    "wof:placetype":"venue"
},
  "geometry": {"coordinates":[-85.879284,43.202899],"type":"Point"}
}