{
  "type": "Feature",
  "properties": {
    "iso:country":"US",
    "sg:address":"1019 N Robert St",
    "sg:city":"Ludington",
    "sg:classifiers":[
        {
            "category":"Personal",
            "type":"Services"
        }
    ],
    "sg:phone":"+1 231 843 4406",
    "sg:postcode":"49431",
    "sg:province":"MI",
    "wof:name":"Tropical Suntan",
    "wof:placetype":"venue"
},
  "geometry": {"coordinates":[-86.4509,43.968559],"type":"Point"}
}