{
  "type": "Feature",
  "properties": {
    "iso:country":"US",
    "sg:address":"3750 W Centre Ave",
    "sg:city":"Portage",
    "sg:classifiers":[
        {
            "category":"Food & Beverages",
            "subcategory":"Groceries & Convenience Stores",
            "type":"Retail Goods"
        }
    ],
    "sg:phone":"+1 269 329 3041",
    "sg:postcode":"49024",
    "sg:province":"MI",
    "sg:tags":[
        "grocer"
    ],
    "wof:name":"Harding's Friendly Market",
    "wof:placetype":"venue"
},
  "geometry": {"coordinates":[-85.642843,42.198537],"type":"Point"}
}