{
  "type": "Feature",
  "properties": {
    "iso:country":"US",
    "sg:address":"1854 Vine St",
    "sg:city":"St Clair",
    "sg:classifiers":[
        {
            "category":"Insurance",
            "subcategory":"Insurance Agent",
            "type":"Services"
        }
    ],
    "sg:phone":"+1 810 329 3068",
    "sg:postcode":"48079",
    "sg:province":"MI",
    "wof:name":"Proctor Homer Warren Inc",
    "wof:placetype":"venue"
},
  "geometry": {"coordinates":[-82.506632,42.830063],"type":"Point"}
}