{
  "type": "Feature",
  "properties": {
    "iso:country":"US",
    "sg:address":"100 Cedar",
    "sg:city":"Elk Rapids",
    "sg:classifiers":[
        {
            "category":"Banks & Credit Unions",
            "subcategory":"Investment Brokerage",
            "type":"Services"
        }
    ],
    "sg:phone":"+1 231 264 6199",
    "sg:postcode":"49629",
    "sg:province":"MI",
    "sg:tags":[
        "consultant",
        "planning",
        "financial"
    ],
    "wof:name":"Harr C Dickson Cfp",
    "wof:placetype":"venue"
},
  "geometry": {"coordinates":[-85.41403699999999,44.897439],"type":"Point"}
}