{
  "type": "Feature",
  "properties": {
    "iso:country":"US",
    "sg:address":"14825 S 24th St",
    "sg:city":"Vicksburg",
    "sg:classifiers":[
        {
            "category":"Building & Trades",
            "subcategory":"Cleaning & Sanitation",
            "type":"Services"
        }
    ],
    "sg:phone":"+1 269 649 4630",
    "sg:postcode":"49097",
    "sg:province":"MI",
    "sg:tags":[
        "maintenance"
    ],
    "wof:name":"Barnes Window Cleaning",
    "wof:placetype":"venue"
},
  "geometry": {"coordinates":[-85.529601,42.101768],"type":"Point"}
}