{
  "type": "Feature",
  "properties": {
    "iso:country":"US",
    "sg:address":"1450 Marlborough Dr",
    "sg:city":"Ann Arbor",
    "sg:classifiers":[
        {
            "category":"Professional",
            "subcategory":"Printing & Photocopies",
            "type":"Services"
        }
    ],
    "sg:phone":"+1 734 971 7653",
    "sg:postcode":"48104",
    "sg:province":"MI",
    "sg:tags":[
        "broker"
    ],
    "wof:name":"Complete Supply Services",
    "wof:placetype":"venue"
},
  "geometry": {"coordinates":[-83.727163,42.252111],"type":"Point"}
}