{
  "type": "Feature",
  "properties": {
    "iso:country":"US",
    "sg:address":"301 N 3rd St",
    "sg:city":"Rogers City",
    "sg:classifiers":[
        {
            "category":"Shopping",
            "subcategory":"Bicycles & Sporting Goods",
            "type":"Retail Goods"
        }
    ],
    "sg:phone":"+1 989 734 7590",
    "sg:postcode":"49779",
    "sg:province":"MI",
    "sg:tags":[
        "equipment",
        "diver",
        "supply"
    ],
    "wof:name":"Great Lakes Divers",
    "wof:placetype":"venue"
},
  "geometry": {"coordinates":[-83.81850900000001,45.421994],"type":"Point"}
}