{
  "type": "Feature",
  "properties": {
    "iso:country":"US",
    "sg:address":"287 N Galbraith Rd",
    "sg:city":"Mio",
    "sg:classifiers":[
        {
            "category":"Wholesale",
            "subcategory":"Construction Materials",
            "type":"Manufacturing & Wholesale Goods"
        }
    ],
    "sg:phone":"+1 989 826 1511",
    "sg:postcode":"48647",
    "sg:province":"MI",
    "sg:tags":[
        "lumber"
    ],
    "wof:name":"Woodside Lumber Co",
    "wof:placetype":"venue"
},
  "geometry": {"coordinates":[-84.170962,44.681791],"type":"Point"}
}