{
  "type": "Feature",
  "properties": {
    "iso:country":"US",
    "sg:address":"26680 Dequindre Rd",
    "sg:city":"Warren",
    "sg:classifiers":[
        {
            "category":"Restaurant",
            "type":"Food & Drink"
        }
    ],
    "sg:menulink":"http://www.allmenus.com/mi/warren/44996-ponderosa/menu/",
    "sg:phone":"+1 586 574 1425",
    "sg:postcode":"48091",
    "sg:province":"MI",
    "sg:tags":[
        "american",
        "steakhouse"
    ],
    "wof:name":"Ponderosa",
    "wof:placetype":"venue"
},
  "geometry": {"coordinates":[-83.08503,42.489074],"type":"Point"}
}