{
  "type": "Feature",
  "properties": {
    "iso:country":"US",
    "sg:address":"4401 Conner St",
    "sg:city":"Detroit",
    "sg:classifiers":[
        {
            "category":"Health Services",
            "subcategory":"Doctor",
            "type":"Services"
        }
    ],
    "sg:phone":"+1 313 823 9803",
    "sg:postcode":"48215",
    "sg:province":"MI",
    "sg:tags":[
        "medical"
    ],
    "wof:name":"Uthappa N Seetha MD",
    "wof:placetype":"venue"
},
  "geometry": {"coordinates":[-82.97040800000001,42.386482],"type":"Point"}
}