{
  "type": "Feature",
  "properties": {
    "iso:country":"US",
    "sg:address":"407 W Wackerly St",
    "sg:city":"Midland",
    "sg:classifiers":[
        {
            "category":"Health Services",
            "subcategory":"Doctor",
            "type":"Services"
        }
    ],
    "sg:phone":"+1 989 631 5721",
    "sg:postcode":"48640",
    "sg:province":"MI",
    "sg:tags":[
        "gynecology",
        "obstetrics"
    ],
    "wof:name":"Midland Ob-Gyn Associates PC",
    "wof:placetype":"venue"
},
  "geometry": {"coordinates":[-84.228382,43.654713],"type":"Point"}
}