{
  "type": "Feature",
  "properties": {
    "iso:country":"US",
    "sg:address":"16135 Harper",
    "sg:city":"Detroit",
    "sg:classifiers":[
        {
            "category":"Shopping",
            "type":"Retail Goods"
        },
        {
            "category":"Museum",
            "type":"Entertainment"
        }
    ],
    "sg:phone":"+1 313 640 4411",
    "sg:postcode":"48224",
    "sg:province":"MI",
    "sg:website":"www.artsandscraps.org",
    "wof:name":"Arts & Scraps",
    "wof:placetype":"venue"
},
  "geometry": {"coordinates":[-82.94644,42.410013],"type":"Point"}
}