{
  "type": "Feature",
  "properties": {
    "iso:country":"US",
    "sg:address":"40727 Regency Dr",
    "sg:city":"Sterling Heights",
    "sg:classifiers":[
        {
            "category":"Building & Trades",
            "subcategory":"Construction",
            "type":"Services"
        }
    ],
    "sg:phone":"+1 586 978 8861",
    "sg:postcode":"48313",
    "sg:province":"MI",
    "sg:tags":[
        "restoration",
        "cleaning",
        "patio",
        "deck"
    ],
    "wof:name":"Right Way Power Washing",
    "wof:placetype":"venue"
},
  "geometry": {"coordinates":[-83.020456,42.592901],"type":"Point"}
}