{
  "type": "Feature",
  "properties": {
    "iso:country":"US",
    "sg:address":"5045 Breezefield Dr SE",
    "sg:city":"Grand Rapids",
    "sg:classifiers":[
        {
            "category":"Retail",
            "subcategory":"Repair Shop",
            "type":"Services"
        }
    ],
    "sg:phone":"+1 616 532 3619",
    "sg:postcode":"49512",
    "sg:province":"MI",
    "sg:tags":[
        "equipment",
        "conditioning",
        "air"
    ],
    "wof:name":"Consolidated Heating & AC",
    "wof:placetype":"venue"
},
  "geometry": {"coordinates":[-85.576775,42.873333],"type":"Point"}
}