{
  "type": "Feature",
  "properties": {
    "iso:country":"US",
    "sg:address":"108 W Chicago Blvd",
    "sg:city":"Tecumseh",
    "sg:classifiers":[
        {
            "category":"Organizations",
            "subcategory":"Non-profit Organization",
            "type":"Services"
        }
    ],
    "sg:phone":"+1 517 424 5438",
    "sg:postcode":"49286",
    "sg:province":"MI",
    "sg:tags":[
        "information",
        "alcoholism",
        "treatment"
    ],
    "wof:name":"Insight Counseling Of Tecumseh",
    "wof:placetype":"venue"
},
  "geometry": {"coordinates":[-83.945306,42.003974],"type":"Point"}
}