{
  "type": "Feature",
  "properties": {
    "iso:country":"US",
    "sg:address":"5265 S Graham Rd",
    "sg:city":"St Charles",
    "sg:classifiers":[
        {
            "category":"Retail",
            "subcategory":"Auto Repair",
            "type":"Services"
        }
    ],
    "sg:phone":"+1 989 865 9611",
    "sg:postcode":"48655",
    "sg:province":"MI",
    "sg:tags":[
        "truck"
    ],
    "wof:name":"Able Welding Inc",
    "wof:placetype":"venue"
},
  "geometry": {"coordinates":[-84.14122,43.347173],"type":"Point"}
}