{
  "type": "Feature",
  "properties": {
    "iso:country":"US",
    "sg:address":"1521 Manor Ln",
    "sg:city":"Mount Pleasant",
    "sg:classifiers":[
        {
            "category":"Health Services",
            "subcategory":"Nursing And Care Facility",
            "type":"Services"
        }
    ],
    "sg:phone":"+1 989 772 0198",
    "sg:postcode":"48858",
    "sg:province":"MI",
    "wof:name":"Manors",
    "wof:placetype":"venue"
},
  "geometry": {"coordinates":[-84.75606500000001,43.610114],"type":"Point"}
}