{
  "type": "Feature",
  "properties": {
    "iso:country":"US",
    "sg:address":"14473 Grafton Rd",
    "sg:city":"Carleton",
    "sg:classifiers":[
        {
            "category":"Building & Trades",
            "subcategory":"Construction",
            "type":"Services"
        }
    ],
    "sg:phone":"+1 734 654 2104",
    "sg:postcode":"48117",
    "sg:province":"MI",
    "sg:tags":[
        "excavation",
        "contractor"
    ],
    "wof:name":"Bob Damic Trucking & Excvtg",
    "wof:placetype":"venue"
},
  "geometry": {"coordinates":[-83.381094,42.081762],"type":"Point"}
}