{
  "type": "Feature",
  "properties": {
    "iso:country":"US",
    "sg:address":"3391 Pleasant Vw",
    "sg:city":"Highland",
    "sg:classifiers":[
        {
            "category":"Professional",
            "subcategory":"Advertising",
            "type":"Services"
        }
    ],
    "sg:phone":"+1 248 889 1690",
    "sg:postcode":"48356",
    "sg:province":"MI",
    "wof:name":"Rk Ind",
    "wof:placetype":"venue"
},
  "geometry": {"coordinates":[-83.56576099999999,42.684023],"type":"Point"}
}