{
  "type": "Feature",
  "properties": {
    "iso:country":"US",
    "sg:address":"27554 Warren Rd",
    "sg:city":"Westland",
    "sg:classifiers":[
        {
            "category":"Bars & Pubs",
            "subcategory":"Nightclub",
            "type":"Food & Drink"
        }
    ],
    "sg:phone":"+1 734 427 3980",
    "sg:postcode":"48185",
    "sg:province":"MI",
    "sg:tags":[
        "nightlife"
    ],
    "wof:name":"Sidelines",
    "wof:placetype":"venue"
},
  "geometry": {"coordinates":[-83.314081,42.340699],"type":"Point"}
}