{
  "type": "Feature",
  "properties": {
    "iso:country":"US",
    "sg:address":"2645 Beacon Hill Ct",
    "sg:city":"Auburn Hills",
    "sg:classifiers":[
        {
            "category":"Professional",
            "subcategory":"Computer Services",
            "type":"Services"
        }
    ],
    "sg:phone":"+1 248 475 9776",
    "sg:postcode":"48326",
    "sg:province":"MI",
    "sg:tags":[
        "datum"
    ],
    "wof:name":"Data Pro Outsorcer Svs",
    "wof:placetype":"venue"
},
  "geometry": {"coordinates":[-83.21762200000001,42.683708],"type":"Point"}
}