{
  "type": "Feature",
  "properties": {
    "iso:country":"US",
    "sg:address":"71 S Front St",
    "sg:city":"Grant",
    "sg:classifiers":[
        {
            "category":"Building & Trades",
            "subcategory":"Construction",
            "type":"Services"
        }
    ],
    "sg:phone":"+1 231 834 9101",
    "sg:postcode":"49327",
    "sg:province":"MI",
    "sg:tags":[
        "well",
        "drilling"
    ],
    "wof:name":"Thorton's Water Well Drilling",
    "wof:placetype":"venue"
},
  "geometry": {"coordinates":[-85.81171999999999,43.335525],"type":"Point"}
}