{
  "type": "Feature",
  "properties": {
    "iso:country":"US",
    "sg:address":"13172 N Red Bud Trl",
    "sg:city":"Buchanan",
    "sg:classifiers":[
        {
            "category":"Utilities",
            "subcategory":"Telephone",
            "type":"Services"
        }
    ],
    "sg:phone":"+1 269 695 0250",
    "sg:postcode":"49107",
    "sg:province":"MI",
    "sg:tags":[
        "telecommunication"
    ],
    "wof:name":"J & W Communications",
    "wof:placetype":"venue"
},
  "geometry": {"coordinates":[-86.363377,41.87992],"type":"Point"}
}