{
  "type": "Feature",
  "properties": {
    "iso:country":"US",
    "sg:address":"47441 Co Rd 358",
    "sg:city":"Decatur",
    "sg:classifiers":[
        {
            "category":"Building & Trades",
            "subcategory":"Construction",
            "type":"Services"
        }
    ],
    "sg:phone":"+1 269 423 8545",
    "sg:postcode":"49045",
    "sg:province":"MI",
    "sg:tags":[
        "cleaning"
    ],
    "wof:name":"Dan Wydick",
    "wof:placetype":"venue"
},
  "geometry": {"coordinates":[-86.009286,42.163924],"type":"Point"}
}