{
  "type": "Feature",
  "properties": {
    "iso:country":"US",
    "sg:address":"8317 Pettit Rd",
    "sg:city":"Birch Run",
    "sg:classifiers":[
        {
            "category":"Travel",
            "subcategory":"Travel Agent",
            "type":"Entertainment"
        }
    ],
    "sg:phone":"+1 989 777 3493",
    "sg:postcode":"48415",
    "sg:province":"MI",
    "sg:tags":[
        "agency",
        "bureau"
    ],
    "wof:name":"Miles Away Travel",
    "wof:placetype":"venue"
},
  "geometry": {"coordinates":[-83.87451799999999,43.304867],"type":"Point"}
}