{
  "type": "Feature",
  "properties": {
    "iso:country":"US",
    "sg:address":"3167 E Frances Rd",
    "sg:city":"Clio",
    "sg:classifiers":[
        {
            "category":"Social Services",
            "subcategory":"Child Care",
            "type":"Services"
        }
    ],
    "sg:phone":"+1 810 687 6155",
    "sg:postcode":"48420",
    "sg:province":"MI",
    "sg:tags":[
        "day"
    ],
    "wof:name":"Nans Daycare",
    "wof:placetype":"venue"
},
  "geometry": {"coordinates":[-83.638273,43.135467],"type":"Point"}
}