{
  "type": "Feature",
  "properties": {
    "iso:country":"US",
    "sg:address":"14960 Meddler Ave NE",
    "sg:city":"Gowen",
    "sg:classifiers":[
        {
            "category":"Education",
            "subcategory":"Library",
            "type":"Public Place"
        }
    ],
    "sg:phone":"+1 616 984 5680",
    "sg:postcode":"49326",
    "sg:province":"MI",
    "wof:name":"Spencer Township Library",
    "wof:placetype":"venue"
},
  "geometry": {"coordinates":[-85.369169,43.237128],"type":"Point"}
}