{
  "type": "Feature",
  "properties": {
    "iso:country":"US",
    "sg:address":"50720 Schoenherr Rd",
    "sg:city":"Shelby Twp",
    "sg:classifiers":[
        {
            "category":"Health Services",
            "subcategory":"Doctor",
            "type":"Services"
        }
    ],
    "sg:phone":"+1 586 566 2340",
    "sg:postcode":"48315",
    "sg:province":"MI",
    "sg:tags":[
        "physician",
        "surgeon"
    ],
    "wof:name":"Pediatric Consultants-Troy",
    "wof:placetype":"venue"
},
  "geometry": {"coordinates":[-82.994592,42.669563],"type":"Point"}
}