{
  "type": "Feature",
  "properties": {
    "iso:country":"US",
    "sg:address":"5676 Hillcrest Cir E",
    "sg:city":"West Bloomfield",
    "sg:classifiers":[
        {
            "category":"Health Services",
            "subcategory":"Doctor",
            "type":"Services"
        }
    ],
    "sg:phone":"+1 248 788 2315",
    "sg:postcode":"48322",
    "sg:province":"MI",
    "sg:tags":[
        "surgeon",
        "oral"
    ],
    "wof:name":"Toomajanian Simon J DDS",
    "wof:placetype":"venue"
},
  "geometry": {"coordinates":[-83.40239699999999,42.5536],"type":"Point"}
}