{
  "type": "Feature",
  "properties": {
    "iso:country":"US",
    "sg:address":"16211 Fairfield St",
    "sg:city":"Detroit",
    "sg:classifiers":[
        {
            "category":"Professional",
            "subcategory":"Business Services",
            "type":"Services"
        }
    ],
    "sg:phone":"+1 313 659 2003",
    "sg:postcode":"48221",
    "sg:province":"MI",
    "sg:tags":[
        "notary",
        "public"
    ],
    "wof:name":"Gordon L Montgomery",
    "wof:placetype":"venue"
},
  "geometry": {"coordinates":[-83.135139,42.411783],"type":"Point"}
}