{
  "type": "Feature",
  "properties": {
    "iso:country":"US",
    "sg:address":"4376 W Locke Rd",
    "sg:city":"Perry",
    "sg:classifiers":[
        {
            "category":"Farming",
            "subcategory":"Livestock Farm",
            "type":"Manufacturing & Wholesale Goods"
        }
    ],
    "sg:phone":"+1 517 625 7986",
    "sg:postcode":"48872",
    "sg:province":"MI",
    "sg:tags":[
        "beekeeper"
    ],
    "wof:name":"Dances With Bees",
    "wof:placetype":"venue"
},
  "geometry": {"coordinates":[-84.246212,42.783415],"type":"Point"}
}