{
  "type": "Feature",
  "properties": {
    "iso:country":"US",
    "sg:address":"41640 Ann Arbor Rd.",
    "sg:city":"Plymouth",
    "sg:classifiers":[
        {
            "category":"Food & Beverages",
            "subcategory":"Candy",
            "type":"Retail Goods"
        },
        {
            "category":"Bakery",
            "type":"Food & Drink"
        }
    ],
    "sg:phone":"+1 734 459 9200",
    "sg:postcode":"48170",
    "sg:province":"MI",
    "sg:tags":[
        "dessert"
    ],
    "wof:name":"Grand Traverse Pie",
    "wof:placetype":"venue"
},
  "geometry": {"coordinates":[-83.45218,42.359158],"type":"Point"}
}