{
  "type": "Feature",
  "properties": {
    "iso:country":"US",
    "sg:address":"22853 Heslip Dr",
    "sg:city":"Novi",
    "sg:classifiers":[
        {
            "category":"Building & Trades",
            "subcategory":"Construction",
            "type":"Services"
        }
    ],
    "sg:phone":"+1 248 347 0093",
    "sg:postcode":"48375",
    "sg:province":"MI",
    "sg:tags":[
        "dry wall",
        "contractor"
    ],
    "wof:name":"Great Lakes Drywall",
    "wof:placetype":"venue"
},
  "geometry": {"coordinates":[-83.46783000000001,42.457651],"type":"Point"}
}