{
  "type": "Feature",
  "properties": {
    "iso:country":"US",
    "sg:address":"4440 S Hillsdale Rd",
    "sg:city":"Hillsdale",
    "sg:classifiers":[
        {
            "category":"Retail",
            "subcategory":"Repair Shop",
            "type":"Services"
        }
    ],
    "sg:phone":"+1 517 437 7510",
    "sg:postcode":"49242",
    "sg:province":"MI",
    "wof:name":"La Pew Sanitation Service",
    "wof:placetype":"venue"
},
  "geometry": {"coordinates":[-84.631533,41.862529],"type":"Point"}
}