{
  "type": "Feature",
  "properties": {
    "iso:country":"US",
    "sg:address":"1130 S Garfield Ave",
    "sg:city":"Traverse City",
    "sg:classifiers":[
        {
            "category":"Restaurant",
            "type":"Food & Drink"
        }
    ],
    "sg:phone":"+1 231 933 9309",
    "sg:postcode":"49686",
    "sg:province":"MI",
    "wof:name":"Jet Pizza",
    "wof:placetype":"venue"
},
  "geometry": {"coordinates":[-85.59540200000001,44.747531],"type":"Point"}
}