{
  "type": "Feature",
  "properties": {
    "iso:country":"US",
    "sg:address":"6117 S Graham Rd",
    "sg:city":"St Charles",
    "sg:classifiers":[
        {
            "category":"Utilities",
            "type":"Services"
        },
        {
            "category":"Building & Trades",
            "subcategory":"Landscaping Services",
            "type":"Services"
        }
    ],
    "sg:phone":"+1 989 865 8815",
    "sg:postcode":"48655",
    "sg:province":"MI",
    "sg:tags":[
        "sanitary",
        "lawn",
        "maintenance",
        "grounds"
    ],
    "wof:name":"Fowler Lawncare & Snow Plowing",
    "wof:placetype":"venue"
},
  "geometry": {"coordinates":[-84.141346,43.335074],"type":"Point"}
}