{
  "type": "Feature",
  "properties": {
    "iso:country":"US",
    "sg:address":"3217 Comer St",
    "sg:city":"Flint",
    "sg:classifiers":[
        {
            "category":"Retail",
            "subcategory":"Repair Shop",
            "type":"Services"
        }
    ],
    "sg:phone":"+1 810 736 9190",
    "sg:postcode":"48506",
    "sg:province":"MI",
    "wof:name":"Dales Jewelry Repair",
    "wof:placetype":"venue"
},
  "geometry": {"coordinates":[-83.61972400000001,43.053241],"type":"Point"}
}