{
  "type": "Feature",
  "properties": {
    "iso:country":"US",
    "sg:address":"2102 Ontonagon Ave SE",
    "sg:city":"Grand Rapids",
    "sg:classifiers":[
        {
            "category":"Building & Trades",
            "subcategory":"Construction",
            "type":"Services"
        }
    ],
    "sg:phone":"+1 616 452 4385",
    "sg:postcode":"49506",
    "sg:province":"MI",
    "sg:tags":[
        "home",
        "improvement"
    ],
    "wof:name":"Evernu Home Improvement",
    "wof:placetype":"venue"
},
  "geometry": {"coordinates":[-85.61018300000001,42.925706],"type":"Point"}
}