{
  "type": "Feature",
  "properties": {
    "iso:country":"US",
    "sg:address":"3237 State Rd",
    "sg:city":"Glennie",
    "sg:classifiers":[
        {
            "category":"Building & Trades",
            "subcategory":"Electrical",
            "type":"Services"
        }
    ],
    "sg:phone":"+1 989 735 0046",
    "sg:postcode":"48737",
    "sg:province":"MI",
    "sg:tags":[
        "electric",
        "contractor"
    ],
    "wof:name":"C & M Electric",
    "wof:placetype":"venue"
},
  "geometry": {"coordinates":[-83.74482500000001,44.582118],"type":"Point"}
}