{
  "type": "Feature",
  "properties": {
    "iso:country":"US",
    "sg:address":"8122 E Lincoln Rd",
    "sg:city":"Cedar",
    "sg:classifiers":[
        {
            "category":"Health Services",
            "subcategory":"Nursing And Care Facility",
            "type":"Services"
        }
    ],
    "sg:phone":"+1 231 947 4733",
    "sg:postcode":"49621",
    "sg:province":"MI",
    "wof:name":"Lincoln A I F",
    "wof:placetype":"venue"
},
  "geometry": {"coordinates":[-85.691824,44.802847],"type":"Point"}
}