{
  "type": "Feature",
  "properties": {
    "iso:country":"US",
    "sg:address":"12173 E D Ave",
    "sg:city":"Richland",
    "sg:classifiers":[
        {
            "category":"Personal",
            "subcategory":"Beauty Salon",
            "type":"Services"
        }
    ],
    "sg:phone":"+1 269 629 4622",
    "sg:postcode":"49083",
    "sg:province":"MI",
    "sg:tags":[
        "shop"
    ],
    "wof:name":"Studio III Hair Salon",
    "wof:placetype":"venue"
},
  "geometry": {"coordinates":[-85.388735,42.370455],"type":"Point"}
}