{
  "type": "Feature",
  "properties": {
    "iso:country":"US",
    "sg:address":"2312 Wadhams Rd",
    "sg:city":"Kimball",
    "sg:classifiers":[
        {
            "category":"Retail",
            "subcategory":"Repair Shop",
            "type":"Services"
        },
        {
            "category":"Professional",
            "subcategory":"Computer Services",
            "type":"Services"
        }
    ],
    "sg:phone":"+1 810 985 0099",
    "sg:postcode":"48074",
    "sg:province":"MI",
    "wof:name":"Jnz Electronics",
    "wof:placetype":"venue"
},
  "geometry": {"coordinates":[-82.543627,42.972746],"type":"Point"}
}