{
  "type": "Feature",
  "properties": {
    "iso:country":"US",
    "sg:address":"2555 Treat St",
    "sg:city":"Adrian",
    "sg:classifiers":[
        {
            "category":"Building & Trades",
            "subcategory":"Construction",
            "type":"Services"
        }
    ],
    "sg:phone":"+1 517 265 4779",
    "sg:postcode":"49221",
    "sg:province":"MI",
    "sg:tags":[
        "fence",
        "contractor"
    ],
    "wof:name":"AAA Fence Works",
    "wof:placetype":"venue"
},
  "geometry": {"coordinates":[-84.01875,41.881847],"type":"Point"}
}