{
  "type": "Feature",
  "properties": {
    "iso:country":"US",
    "sg:address":"202 Morrell St",
    "sg:city":"Charlotte",
    "sg:classifiers":[
        {
            "category":"Manufacturing",
            "subcategory":"Metals",
            "type":"Manufacturing & Wholesale Goods"
        }
    ],
    "sg:phone":"+1 517 543 3430",
    "sg:postcode":"48813",
    "sg:province":"MI",
    "sg:tags":[
        "pipe",
        "fitting",
        "fabricated"
    ],
    "sg:website":"www.stregisculvert.com",
    "wof:name":"St Regis Culvert Inc",
    "wof:placetype":"venue"
},
  "geometry": {"coordinates":[-84.835971,42.573921],"type":"Point"}
}