{
  "type": "Feature",
  "properties": {
    "iso:country":"US",
    "sg:address":"148 Pierce St",
    "sg:city":"Birmingham",
    "sg:classifiers":[
        {
            "category":"Building & Trades",
            "subcategory":"Landscaping Services",
            "type":"Services"
        }
    ],
    "sg:phone":"+1 248 642 4800",
    "sg:postcode":"48009",
    "sg:province":"MI",
    "sg:tags":[
        "designer",
        "landscape"
    ],
    "wof:name":"Gibbs Planning Group",
    "wof:placetype":"venue"
},
  "geometry": {"coordinates":[-83.21502599999999,42.546307],"type":"Point"}
}