{
  "type": "Feature",
  "properties": {
    "iso:country":"US",
    "sg:address":"193 S Benzie Blvd",
    "sg:city":"Beulah",
    "sg:classifiers":[
        {
            "category":"Health Services",
            "subcategory":"Health Practitioner",
            "type":"Services"
        }
    ],
    "sg:phone":"+1 231 882 2374",
    "sg:postcode":"49617",
    "sg:province":"MI",
    "sg:tags":[
        "therapist",
        "physical"
    ],
    "wof:name":"Advanced Therapy Concepts Inc",
    "wof:placetype":"venue"
},
  "geometry": {"coordinates":[-86.09457,44.629303],"type":"Point"}
}