{
  "type": "Feature",
  "properties": {
    "iso:country":"US",
    "sg:address":"12845 W Warren Ave",
    "sg:city":"Dearborn",
    "sg:classifiers":[
        {
            "category":"Restaurant",
            "type":"Food & Drink"
        }
    ],
    "sg:phone":"+1 313 581 7450",
    "sg:postcode":"48126",
    "sg:province":"MI",
    "wof:name":"Fish N Shrimp House",
    "wof:placetype":"venue"
},
  "geometry": {"coordinates":[-83.168999,42.344101],"type":"Point"}
}