{
  "type": "Feature",
  "properties": {
    "iso:country":"US",
    "sg:address":"16465 Northway",
    "sg:city":"New Buffalo",
    "sg:classifiers":[
        {
            "category":"Professional",
            "subcategory":"Business Services",
            "type":"Services"
        }
    ],
    "sg:phone":"+1 269 469 3618",
    "sg:postcode":"49117",
    "sg:province":"MI",
    "wof:name":"Adamec Decorating",
    "wof:placetype":"venue"
},
  "geometry": {"coordinates":[-86.709136,41.821301],"type":"Point"}
}