{
  "type": "Feature",
  "properties": {
    "iso:country":"US",
    "sg:address":"2456 Utley Rd",
    "sg:city":"Flint",
    "sg:classifiers":[
        {
            "category":"Local Transit",
            "type":"Transportation"
        }
    ],
    "sg:phone":"+1 810 732 6692",
    "sg:postcode":"48532",
    "sg:province":"MI",
    "sg:tags":[
        "limousine"
    ],
    "wof:name":"Dynasty Limousines Inc",
    "wof:placetype":"venue"
},
  "geometry": {"coordinates":[-83.747783,42.9911],"type":"Point"}
}