{
  "type": "Feature",
  "properties": {
    "iso:country":"US",
    "sg:address":"5775 Old 27 S",
    "sg:city":"Marshall",
    "sg:classifiers":[
        {
            "category":"Travel",
            "subcategory":"Campground",
            "type":"Entertainment"
        }
    ],
    "sg:phone":"+1 517 767 4161",
    "sg:postcode":"49068",
    "sg:province":"MI",
    "sg:tags":[
        "trailer"
    ],
    "wof:name":"Quality Camping Inc",
    "wof:placetype":"venue"
},
  "geometry": {"coordinates":[-84.96287100000001,42.158478],"type":"Point"}
}