{
  "type": "Feature",
  "properties": {
    "iso:country":"US",
    "sg:address":"5438 W Polk Rd",
    "sg:city":"Hart",
    "sg:classifiers":[
        {
            "category":"Building & Trades",
            "subcategory":"Construction",
            "type":"Services"
        }
    ],
    "sg:phone":"+1 231 873 8056",
    "sg:postcode":"49420",
    "sg:province":"MI",
    "sg:tags":[
        "general",
        "contractor"
    ],
    "wof:name":"Lakeside Design & Construction",
    "wof:placetype":"venue"
},
  "geometry": {"coordinates":[-86.41426199999999,43.689406],"type":"Point"}
}