{
  "type": "Feature",
  "properties": {
    "iso:country":"US",
    "sg:address":"Westland Shopping Ce",
    "sg:city":"Westland",
    "sg:classifiers":[
        {
            "category":"Shopping",
            "subcategory":"Department Store",
            "type":"Retail Goods"
        },
        {
            "category":"Shopping Center",
            "type":"Public Place"
        }
    ],
    "sg:phone":"+1 734 425 4260",
    "sg:postcode":"48185",
    "sg:province":"MI",
    "wof:name":"Penney J C Co Inc",
    "wof:placetype":"venue"
},
  "geometry": {"coordinates":[-83.375702,42.335899],"type":"Point"}
}