{
  "type": "Feature",
  "properties": {
    "iso:country":"US",
    "sg:address":"1587 Lake Dr",
    "sg:city":"Traverse City",
    "sg:classifiers":[
        {
            "category":"Manufacturing",
            "subcategory":"Printing",
            "type":"Manufacturing & Wholesale Goods"
        }
    ],
    "sg:phone":"+1 231 946 7680",
    "sg:postcode":"49684",
    "sg:province":"MI",
    "sg:tags":[
        "commercial"
    ],
    "wof:name":"Canoe Press",
    "wof:placetype":"venue"
},
  "geometry": {"coordinates":[-85.683645,44.710229],"type":"Point"}
}