{
  "type": "Feature",
  "properties": {
    "iso:country":"US",
    "sg:address":"1147 Pilgrim Hwy",
    "sg:city":"Frankfort",
    "sg:classifiers":[
        {
            "category":"Food & Beverages",
            "subcategory":"Bakery",
            "type":"Retail Goods"
        }
    ],
    "sg:phone":"+1 231 352 9881",
    "sg:postcode":"49635",
    "sg:province":"MI",
    "sg:tags":[
        "baker"
    ],
    "wof:name":"Country Oven",
    "wof:placetype":"venue"
},
  "geometry": {"coordinates":[-86.24431,44.657301],"type":"Point"}
}