{
  "type": "Feature",
  "properties": {
    "iso:country":"US",
    "sg:address":"131 S Milford Rd",
    "sg:city":"Milford",
    "sg:classifiers":[
        {
            "category":"Personal",
            "subcategory":"Beauty Salon",
            "type":"Services"
        }
    ],
    "sg:phone":"+1 248 684 4016",
    "sg:postcode":"48381",
    "sg:province":"MI",
    "wof:name":"Fantastic Sams",
    "wof:placetype":"venue"
},
  "geometry": {"coordinates":[-83.610877,42.580531],"type":"Point"}
}