{
  "type": "Feature",
  "properties": {
    "iso:country":"US",
    "sg:address":"2562 Mapleview Ct SE",
    "sg:city":"Kentwood",
    "sg:classifiers":[
        {
            "category":"Professional",
            "subcategory":"Business Services",
            "type":"Services"
        }
    ],
    "sg:phone":"+1 616 656 9091",
    "sg:postcode":"49508",
    "sg:province":"MI",
    "sg:tags":[
        "packaging"
    ],
    "wof:name":"Aldelano Corp",
    "wof:placetype":"venue"
},
  "geometry": {"coordinates":[-85.60353600000001,42.873674],"type":"Point"}
}