{
  "type": "Feature",
  "properties": {
    "iso:country":"US",
    "sg:address":"1216 Selma St",
    "sg:city":"Westland",
    "sg:classifiers":[
        {
            "category":"Professional",
            "subcategory":"Business Services",
            "type":"Services"
        }
    ],
    "sg:phone":"+1 734 728 0515",
    "sg:postcode":"48186",
    "sg:province":"MI",
    "wof:name":"Auto Solutions East Inc",
    "wof:placetype":"venue"
},
  "geometry": {"coordinates":[-83.40028,42.300745],"type":"Point"}
}