{
  "type": "Feature",
  "properties": {
    "iso:country":"US",
    "sg:address":"3100 Webber St",
    "sg:city":"Saginaw",
    "sg:classifiers":[
        {
            "category":"Education",
            "subcategory":"School",
            "type":"Public Place"
        }
    ],
    "sg:phone":"+1 989 759 3577",
    "sg:postcode":"48601",
    "sg:province":"MI",
    "sg:tags":[
        "high"
    ],
    "wof:name":"Saginaw High School",
    "wof:placetype":"venue"
},
  "geometry": {"coordinates":[-83.924612,43.407403],"type":"Point"}
}