{
  "type": "Feature",
  "properties": {
    "iso:country":"US",
    "sg:address":"3855 Sparks Dr SE",
    "sg:city":"Grand Rapids",
    "sg:classifiers":[
        {
            "category":"Banks & Credit Unions",
            "subcategory":"Financial Services",
            "type":"Services"
        }
    ],
    "sg:phone":"+1 616 956 3053",
    "sg:postcode":"49546",
    "sg:province":"MI",
    "sg:tags":[
        "company",
        "holding"
    ],
    "wof:name":"Batts Group",
    "wof:placetype":"venue"
},
  "geometry": {"coordinates":[-85.571821,42.915917],"type":"Point"}
}