{
  "type": "Feature",
  "properties": {
    "iso:country":"US",
    "sg:address":"109 N Railway St",
    "sg:city":"Clio",
    "sg:classifiers":[
        {
            "category":"Real Estate",
            "subcategory":"Real Estate Agent",
            "type":"Services"
        }
    ],
    "sg:phone":"+1 810 687 6767",
    "sg:postcode":"48420",
    "sg:province":"MI",
    "wof:name":"Century 21",
    "wof:placetype":"venue"
},
  "geometry": {"coordinates":[-83.737531,43.177943],"type":"Point"}
}