{
  "type": "Feature",
  "properties": {
    "iso:country":"US",
    "sg:address":"350 S Miller Dr",
    "sg:city":"Eaton Rapids",
    "sg:classifiers":[
        {
            "category":"Real Estate",
            "subcategory":"Real Estate Operator",
            "type":"Services"
        }
    ],
    "sg:phone":"+1 517 663 8660",
    "sg:postcode":"48827",
    "sg:province":"MI",
    "sg:tags":[
        "apartment"
    ],
    "wof:name":"Evergreen Apartments",
    "wof:placetype":"venue"
},
  "geometry": {"coordinates":[-84.640743,42.511806],"type":"Point"}
}