{
  "type": "Feature",
  "properties": {
    "iso:country":"US",
    "sg:address":"210 N Mc Ewan St",
    "sg:city":"Clare",
    "sg:classifiers":[
        {
            "category":"Wholesale",
            "subcategory":"Auto Parts",
            "type":"Manufacturing & Wholesale Goods"
        }
    ],
    "sg:phone":"+1 989 386 3089",
    "sg:postcode":"48617",
    "sg:province":"MI",
    "sg:tags":[
        "tire"
    ],
    "wof:name":"Cole Tire Co",
    "wof:placetype":"venue"
},
  "geometry": {"coordinates":[-84.768275,43.816512],"type":"Point"}
}