{
  "type": "Feature",
  "properties": {
    "iso:country":"US",
    "sg:address":"614 Lafayette St",
    "sg:city":"Lowell",
    "sg:classifiers":[
        {
            "category":"Building & Trades",
            "subcategory":"Construction",
            "type":"Services"
        }
    ],
    "sg:phone":"+1 616 897 1721",
    "sg:postcode":"49331",
    "sg:province":"MI",
    "sg:tags":[
        "housing"
    ],
    "wof:name":"Larry Botsford Construction",
    "wof:placetype":"venue"
},
  "geometry": {"coordinates":[-85.34029200000001,42.939968],"type":"Point"}
}