{
  "type": "Feature",
  "properties": {
    "iso:country":"US",
    "sg:address":"2605 Dixie Hwy",
    "sg:city":"Waterford",
    "sg:classifiers":[
        {
            "category":"Retail",
            "subcategory":"Auto Repair",
            "type":"Services"
        }
    ],
    "sg:phone":"+1 248 674 4187",
    "sg:postcode":"48328",
    "sg:province":"MI",
    "sg:tags":[
        "repairing",
        "automobile"
    ],
    "wof:name":"G M Svc Specialists Inc",
    "wof:placetype":"venue"
},
  "geometry": {"coordinates":[-83.339528,42.672907],"type":"Point"}
}