{
  "type": "Feature",
  "properties": {
    "iso:country":"US",
    "sg:address":"2560 E Highland Rd",
    "sg:city":"Highland",
    "sg:classifiers":[
        {
            "category":"Retail",
            "subcategory":"Car Wash",
            "type":"Services"
        }
    ],
    "sg:phone":"+1 248 889 0640",
    "sg:postcode":"48356",
    "sg:province":"MI",
    "sg:tags":[
        "polishing",
        "washing"
    ],
    "wof:name":"Buggy Bath Car Wash",
    "wof:placetype":"venue"
},
  "geometry": {"coordinates":[-83.57848,42.653844],"type":"Point"}
}