{
  "type": "Feature",
  "properties": {
    "iso:country":"US",
    "sg:address":"937 W Main St",
    "sg:city":"Fremont",
    "sg:classifiers":[
        {
            "category":"Sports & Exercise",
            "subcategory":"Gym",
            "type":"Entertainment"
        }
    ],
    "sg:phone":"+1 231 924 5619",
    "sg:postcode":"49412",
    "sg:province":"MI",
    "sg:tags":[
        "fitness",
        "physical",
        "facility"
    ],
    "wof:name":"Feel Good Fitness",
    "wof:placetype":"venue"
},
  "geometry": {"coordinates":[-85.96123799999999,43.467256],"type":"Point"}
}