{
  "type": "Feature",
  "properties": {
    "iso:country":"US",
    "sg:address":"2385 S Sheridan Rd",
    "sg:city":"Muskegon",
    "sg:classifiers":[
        {
            "category":"Manufacturing",
            "subcategory":"Metals",
            "type":"Manufacturing & Wholesale Goods"
        }
    ],
    "sg:phone":"+1 231 777 5809",
    "sg:postcode":"49442",
    "sg:province":"MI",
    "sg:tags":[
        "die",
        "nonferrous",
        "casting",
        "alum"
    ],
    "wof:name":"Port City Metal Products",
    "wof:placetype":"venue"
},
  "geometry": {"coordinates":[-86.18471700000001,43.209238],"type":"Point"}
}