{
  "type": "Feature",
  "properties": {
    "iso:country":"US",
    "sg:address":"836 Georgia St",
    "sg:city":"Williamston",
    "sg:classifiers":[
        {
            "category":"Building & Trades",
            "subcategory":"Cleaning & Sanitation",
            "type":"Services"
        }
    ],
    "sg:phone":"+1 517 655 1341",
    "sg:postcode":"48895",
    "sg:province":"MI",
    "sg:tags":[
        "janitor"
    ],
    "wof:name":"Capitol City Cleaning",
    "wof:placetype":"venue"
},
  "geometry": {"coordinates":[-84.28420800000001,42.682637],"type":"Point"}
}