{
  "type": "Feature",
  "properties": {
    "iso:country":"US",
    "sg:address":"2664 Windsor",
    "sg:city":"Troy",
    "sg:classifiers":[
        {
            "category":"Building & Trades",
            "subcategory":"Construction",
            "type":"Services"
        }
    ],
    "sg:phone":"+1 248 524 1217",
    "sg:postcode":"48085",
    "sg:province":"MI",
    "sg:tags":[
        "painter"
    ],
    "wof:name":"LAMA",
    "wof:placetype":"venue"
},
  "geometry": {"coordinates":[-83.095337,42.588942],"type":"Point"}
}