{
  "type": "Feature",
  "properties": {
    "iso:country":"US",
    "sg:address":"26075 W 6 Mile Rd",
    "sg:city":"Redford",
    "sg:classifiers":[
        {
            "category":"Professional",
            "subcategory":"Management & Consulting",
            "type":"Services"
        }
    ],
    "sg:phone":"+1 313 538 9411",
    "sg:postcode":"48240",
    "sg:province":"MI",
    "wof:name":"Successful Phone Marketing",
    "wof:placetype":"venue"
},
  "geometry": {"coordinates":[-83.29944500000001,42.41381],"type":"Point"}
}