{
  "type": "Feature",
  "properties": {
    "iso:country":"US",
    "sg:address":"615 S Waverly Rd",
    "sg:city":"Lansing",
    "sg:classifiers":[
        {
            "category":"Real Estate",
            "subcategory":"Real Estate Agent",
            "type":"Services"
        }
    ],
    "sg:phone":"+1 517 321 4920",
    "sg:postcode":"48917",
    "sg:province":"MI",
    "wof:name":"Tzoumakas Real Estate LLC",
    "wof:placetype":"venue"
},
  "geometry": {"coordinates":[-84.60291599999999,42.727932],"type":"Point"}
}