{
  "type": "Feature",
  "properties": {
    "iso:country":"US",
    "sg:address":"25005 Van Dyke Ave",
    "sg:city":"Center Line",
    "sg:classifiers":[
        {
            "category":"Shopping",
            "subcategory":"Discount & Variety Stores",
            "type":"Retail Goods"
        }
    ],
    "sg:phone":"+1 586 757 2132",
    "sg:postcode":"48015",
    "sg:province":"MI",
    "wof:name":"Castle Dollar",
    "wof:placetype":"venue"
},
  "geometry": {"coordinates":[-83.027368,42.478721],"type":"Point"}
}