{
  "type": "Feature",
  "properties": {
    "iso:country":"US",
    "sg:address":"18931 Allen Rd",
    "sg:city":"Melvindale",
    "sg:classifiers":[
        {
            "category":"Organizations",
            "subcategory":"Community Association",
            "type":"Services"
        }
    ],
    "sg:phone":"+1 313 386 7583",
    "sg:postcode":"48122",
    "sg:province":"MI",
    "wof:name":"Lodge 1911 - Melvindale",
    "wof:placetype":"venue"
},
  "geometry": {"coordinates":[-83.19067,42.278306],"type":"Point"}
}