{
  "type": "Feature",
  "properties": {
    "iso:country":"US",
    "sg:address":"1731 E 7 Mile Rd",
    "sg:city":"Detroit",
    "sg:classifiers":[
        {
            "category":"Retail",
            "subcategory":"Car Wash",
            "type":"Services"
        }
    ],
    "sg:phone":"+1 313 893 1227",
    "sg:postcode":"48203",
    "sg:province":"MI",
    "sg:tags":[
        "carwash"
    ],
    "wof:name":"Tone Capones Detailing",
    "wof:placetype":"venue"
},
  "geometry": {"coordinates":[-83.08589600000001,42.432869],"type":"Point"}
}