{
  "type": "Feature",
  "properties": {
    "iso:country":"US",
    "sg:address":"1812 E Pine River Rd",
    "sg:city":"Midland",
    "sg:classifiers":[
        {
            "category":"Shopping",
            "subcategory":"Clothing, Apparel, & Fashions",
            "type":"Retail Goods"
        }
    ],
    "sg:phone":"+1 989 631 3847",
    "sg:postcode":"48640",
    "sg:province":"MI",
    "wof:name":"Ephods",
    "wof:placetype":"venue"
},
  "geometry": {"coordinates":[-84.298913,43.59745],"type":"Point"}
}