{
  "type": "Feature",
  "properties": {
    "iso:country":"US",
    "sg:address":"6460 Sims Dr",
    "sg:city":"Sterling Heights",
    "sg:classifiers":[
        {
            "category":"Retail",
            "subcategory":"Repair Shop",
            "type":"Services"
        }
    ],
    "sg:phone":"+1 586 977 6900",
    "sg:postcode":"48313",
    "sg:province":"MI",
    "sg:tags":[
        "equipment",
        "hydraulic"
    ],
    "wof:name":"Sunsource",
    "wof:placetype":"venue"
},
  "geometry": {"coordinates":[-83.04509,42.588837],"type":"Point"}
}