{
  "type": "Feature",
  "properties": {
    "iso:country":"US",
    "sg:address":"910 N 3rd St",
    "sg:city":"Marquette",
    "sg:classifiers":[
        {
            "category":"Food & Beverages",
            "subcategory":"Bakery",
            "type":"Retail Goods"
        }
    ],
    "sg:phone":"+1 906 228 8284",
    "sg:postcode":"49855",
    "sg:province":"MI",
    "sg:tags":[
        "baker"
    ],
    "wof:name":"Cakeworks",
    "wof:placetype":"venue"
},
  "geometry": {"coordinates":[-87.39466,46.552097],"type":"Point"}
}