{
  "type": "Feature",
  "properties": {
    "iso:country":"US",
    "sg:address":"704 Palmyra St",
    "sg:city":"Cheboygan",
    "sg:classifiers":[
        {
            "category":"Social Services",
            "subcategory":"Child Care",
            "type":"Services"
        }
    ],
    "sg:phone":"+1 231 627 9556",
    "sg:postcode":"49721",
    "sg:province":"MI",
    "sg:tags":[
        "day"
    ],
    "wof:name":"Rebecca Phillips",
    "wof:placetype":"venue"
},
  "geometry": {"coordinates":[-84.490447,45.639569],"type":"Point"}
}