{
  "type": "Feature",
  "properties": {
    "iso:country":"US",
    "sg:address":"4633 Wood Valley Ct NE",
    "sg:city":"Rockford",
    "sg:classifiers":[
        {
            "category":"Health Services",
            "subcategory":"Optometrist",
            "type":"Services"
        }
    ],
    "sg:phone":"+1 616 866 0367",
    "sg:postcode":"49341",
    "sg:province":"MI",
    "wof:name":"Alpine Family Eye Care",
    "wof:placetype":"venue"
},
  "geometry": {"coordinates":[-85.552696,43.176714],"type":"Point"}
}