{
  "type": "Feature",
  "properties": {
    "iso:country":"US",
    "sg:address":"10865 S Enzian Rd",
    "sg:city":"Delton",
    "sg:classifiers":[
        {
            "category":"Building & Trades",
            "subcategory":"Construction",
            "type":"Services"
        }
    ],
    "sg:phone":"+1 269 343 1694",
    "sg:postcode":"49046",
    "sg:province":"MI",
    "sg:tags":[
        "home",
        "improvement"
    ],
    "wof:name":"Kingsley Seamless Gutters",
    "wof:placetype":"venue"
},
  "geometry": {"coordinates":[-85.493849,42.494589],"type":"Point"}
}