{
  "type": "Feature",
  "properties": {
    "iso:country":"US",
    "sg:address":"520 Pleasant St",
    "sg:city":"St Joseph",
    "sg:classifiers":[
        {
            "category":"Organizations",
            "subcategory":"Professional Association",
            "type":"Services"
        }
    ],
    "sg:phone":"+1 269 983 5411",
    "sg:postcode":"49085",
    "sg:province":"MI",
    "wof:name":"Heavy Duty Representatives",
    "wof:placetype":"venue"
},
  "geometry": {"coordinates":[-86.481999,42.109548],"type":"Point"}
}