{
  "type": "Feature",
  "properties": {
    "iso:country":"US",
    "sg:address":"1301 Washington St",
    "sg:city":"Midland",
    "sg:classifiers":[
        {
            "category":"Restaurant",
            "type":"Food & Drink"
        }
    ],
    "sg:menulink":"http://www.allmenus.com/mi/midland/122031-quiznos-sub/menu/",
    "sg:phone":"+1 989 631 7849",
    "sg:postcode":"48640",
    "sg:province":"MI",
    "sg:tags":[
        "wrap",
        "american",
        "sandwich"
    ],
    "wof:name":"Quiznos Sub",
    "wof:placetype":"venue"
},
  "geometry": {"coordinates":[-84.21733999999999,43.612228],"type":"Point"}
}