{
  "type": "Feature",
  "properties": {
    "iso:country":"US",
    "sg:address":"23936 Industrial Park Dr",
    "sg:city":"Farmington Hills",
    "sg:classifiers":[
        {
            "category":"Manufacturing",
            "subcategory":"Metals",
            "type":"Manufacturing & Wholesale Goods"
        }
    ],
    "sg:phone":"+1 248 477 6700",
    "sg:postcode":"48335",
    "sg:province":"MI",
    "sg:tags":[
        "coating"
    ],
    "sg:website":"www.volkcorp.com",
    "wof:name":"Volk Corp",
    "wof:placetype":"venue"
},
  "geometry": {"coordinates":[-83.42364999999999,42.464922],"type":"Point"}
}