{
  "type": "Feature",
  "properties": {
    "iso:country":"US",
    "sg:address":"1150 E Territorial Rd",
    "sg:city":"Rives Junction",
    "sg:classifiers":[
        {
            "category":"Professional",
            "subcategory":"Business Services",
            "type":"Services"
        }
    ],
    "sg:phone":"+1 517 589 5545",
    "sg:postcode":"49277",
    "sg:province":"MI",
    "wof:name":"Steve Shelhart Productions",
    "wof:placetype":"venue"
},
  "geometry": {"coordinates":[-84.40942200000001,42.411408],"type":"Point"}
}