{
  "type": "Feature",
  "properties": {
    "iso:country":"US",
    "sg:address":"165 W Fourteen Mile Rd",
    "sg:city":"Clawson",
    "sg:classifiers":[
        {
            "category":"Retail",
            "subcategory":"Auto Repair",
            "type":"Services"
        }
    ],
    "sg:phone":"+1 248 435 5850",
    "sg:postcode":"48017",
    "sg:province":"MI",
    "sg:website":"www.collexcollision.com",
    "wof:name":"Collex Collision Experts",
    "wof:placetype":"venue"
},
  "geometry": {"coordinates":[-83.14896299999999,42.533356],"type":"Point"}
}