{
  "type": "Feature",
  "properties": {
    "iso:country":"US",
    "sg:address":"3715 Hutchins Hill",
    "sg:city":"Orchard Lake",
    "sg:classifiers":[
        {
            "category":"Banks & Credit Unions",
            "subcategory":"Bank",
            "type":"Services"
        }
    ],
    "sg:phone":"+1 248 626 0066",
    "sg:postcode":"48323",
    "sg:province":"MI",
    "sg:tags":[
        "loan",
        "real estate"
    ],
    "wof:name":"R H Crimmins Assoc",
    "wof:placetype":"venue"
},
  "geometry": {"coordinates":[-83.35546100000001,42.578015],"type":"Point"}
}