{
  "type": "Feature",
  "properties": {
    "iso:country":"US",
    "sg:address":"310 Mary St",
    "sg:city":"Yale",
    "sg:classifiers":[
        {
            "category":"Wholesale",
            "subcategory":"Hardware",
            "type":"Manufacturing & Wholesale Goods"
        }
    ],
    "sg:phone":"+1 810 387 2474",
    "sg:postcode":"48097",
    "sg:province":"MI",
    "sg:tags":[
        "plumbing",
        "merchandise"
    ],
    "wof:name":"Higgins Water Softener",
    "wof:placetype":"venue"
},
  "geometry": {"coordinates":[-82.793815,43.125725],"type":"Point"}
}