{
  "type": "Feature",
  "properties": {
    "iso:country":"US",
    "sg:address":"44199 Manitou Dr",
    "sg:city":"Clinton Twp",
    "sg:classifiers":[
        {
            "category":"Manufacturing",
            "subcategory":"Electronics",
            "type":"Manufacturing & Wholesale Goods"
        }
    ],
    "sg:phone":"+1 586 412 8444",
    "sg:postcode":"48038",
    "sg:province":"MI",
    "sg:tags":[
        "equipment",
        "electronic",
        "supply"
    ],
    "wof:name":"Soundbase Corp",
    "wof:placetype":"venue"
},
  "geometry": {"coordinates":[-82.924679,42.621273],"type":"Point"}
}