{
  "type": "Feature",
  "properties": {
    "iso:country":"US",
    "sg:address":"3587 Euclid Dr",
    "sg:city":"Troy",
    "sg:classifiers":[
        {
            "category":"Professional",
            "type":"Services"
        }
    ],
    "sg:phone":"+1 248 740 8409",
    "sg:postcode":"48083",
    "sg:province":"MI",
    "sg:tags":[
        "establishment"
    ],
    "wof:name":"Lear Corp",
    "wof:placetype":"venue"
},
  "geometry": {"coordinates":[-83.092454,42.571471],"type":"Point"}
}