{
  "type": "Feature",
  "properties": {
    "iso:country":"US",
    "sg:address":"1215 W Division St",
    "sg:city":"Cadillac",
    "sg:classifiers":[
        {
            "category":"Restaurant",
            "type":"Food & Drink"
        }
    ],
    "sg:phone":"+1 231 779 3774",
    "sg:postcode":"49601",
    "sg:province":"MI",
    "sg:tags":[
        "eating"
    ],
    "wof:name":"Clam River Gardens",
    "wof:placetype":"venue"
},
  "geometry": {"coordinates":[-85.42353900000001,44.252449],"type":"Point"}
}