{
  "type": "Feature",
  "properties": {
    "iso:country":"US",
    "sg:address":"21235 John R Rd",
    "sg:city":"Hazel Park",
    "sg:classifiers":[
        {
            "category":"Professional",
            "subcategory":"Employment Agencies",
            "type":"Services"
        }
    ],
    "sg:phone":"+1 248 542 0100",
    "sg:postcode":"48030",
    "sg:province":"MI",
    "wof:name":"Somerset Sales Inc",
    "wof:placetype":"venue"
},
  "geometry": {"coordinates":[-83.103343,42.451095],"type":"Point"}
}