{
  "type": "Feature",
  "properties": {
    "iso:country":"US",
    "sg:address":"36510 Goddard Rd",
    "sg:city":"Romulus",
    "sg:classifiers":[
        {
            "category":"Professional",
            "subcategory":"Lawyer & Legal Services",
            "type":"Services"
        }
    ],
    "sg:phone":"+1 734 955 9088",
    "sg:postcode":"48174",
    "sg:province":"MI",
    "wof:name":"Douglas R Swatosh P C",
    "wof:placetype":"venue"
},
  "geometry": {"coordinates":[-83.39623899999999,42.222105],"type":"Point"}
}