{
  "type": "Feature",
  "properties": {
    "iso:country":"US",
    "sg:address":"25840 W 9 Mile Rd",
    "sg:city":"Southfield",
    "sg:classifiers":[
        {
            "category":"Food & Beverages",
            "subcategory":"Groceries & Convenience Stores",
            "type":"Retail Goods"
        }
    ],
    "sg:phone":"+1 248 357 3636",
    "sg:postcode":"48034",
    "sg:province":"MI",
    "wof:name":"Seoul Oriental Market",
    "wof:placetype":"venue"
},
  "geometry": {"coordinates":[-83.29879800000001,42.4571],"type":"Point"}
}