{
  "type": "Feature",
  "properties": {
    "iso:country":"US",
    "sg:address":"25801 Plymouth Rd",
    "sg:city":"Redford",
    "sg:classifiers":[
        {
            "category":"Shopping",
            "subcategory":"Mobile Phones",
            "type":"Retail Goods"
        }
    ],
    "sg:phone":"+1 313 937 0800",
    "sg:postcode":"48239",
    "sg:province":"MI",
    "sg:website":"www.t-mobile.com",
    "wof:name":"T-Mobile",
    "wof:placetype":"venue"
},
  "geometry": {"coordinates":[-83.294884,42.370653],"type":"Point"}
}