{
  "type": "Feature",
  "properties": {
    "iso:country":"US",
    "sg:address":"20611 Lockwood St",
    "sg:city":"Taylor",
    "sg:classifiers":[
        {
            "category":"Organizations",
            "subcategory":"Religious Organization",
            "type":"Services"
        }
    ],
    "sg:phone":"+1 313 292 0381",
    "sg:postcode":"48180",
    "sg:province":"MI",
    "wof:name":"Open Door Fellowship Church",
    "wof:placetype":"venue"
},
  "geometry": {"coordinates":[-83.240779,42.244898],"type":"Point"}
}