{
  "type": "Feature",
  "properties": {
    "iso:country":"US",
    "sg:address":"30200 Groesbeck Hwy",
    "sg:city":"Roseville",
    "sg:classifiers":[
        {
            "category":"Autos & Motor Vehicles",
            "subcategory":"Automobile Sales",
            "type":"Retail Goods"
        }
    ],
    "sg:phone":"+1 586 771 5500",
    "sg:postcode":"48066",
    "sg:province":"MI",
    "sg:tags":[
        "classic"
    ],
    "wof:name":"New Classy Chassis",
    "wof:placetype":"venue"
},
  "geometry": {"coordinates":[-82.949742,42.519227],"type":"Point"}
}