{
  "type": "Feature",
  "properties": {
    "iso:country":"US",
    "sg:address":"109 S 6th St",
    "sg:city":"Escanaba",
    "sg:classifiers":[
        {
            "category":"Professional",
            "subcategory":"Lawyer & Legal Services",
            "type":"Services"
        }
    ],
    "sg:phone":"+1 906 786 1223",
    "sg:postcode":"49829",
    "sg:province":"MI",
    "wof:name":"Vader & Vader",
    "wof:placetype":"venue"
},
  "geometry": {"coordinates":[-87.055161,45.745673],"type":"Point"}
}