{
  "type": "Feature",
  "properties": {
    "iso:country":"US",
    "sg:address":"320 Washington St",
    "sg:city":"Traverse City",
    "sg:classifiers":[
        {
            "category":"Government",
            "subcategory":"Police Station",
            "type":"Public Place"
        }
    ],
    "sg:phone":"+1 231 922 4510",
    "sg:postcode":"49684",
    "sg:province":"MI",
    "sg:tags":[
        "sheriff"
    ],
    "wof:name":"Grand Traverse Patrol Div",
    "wof:placetype":"venue"
},
  "geometry": {"coordinates":[-85.617394,44.761665],"type":"Point"}
}