{
  "type": "Feature",
  "properties": {
    "iso:country":"US",
    "sg:address":"5851 W Vernor Hwy",
    "sg:city":"Detroit",
    "sg:classifiers":[
        {
            "category":"Shopping",
            "subcategory":"Pharmacy",
            "type":"Retail Goods"
        }
    ],
    "sg:phone":"+1 313 841 9350",
    "sg:postcode":"48209",
    "sg:province":"MI",
    "sg:tags":[
        "drugstore"
    ],
    "sg:website":"www.southwestdiscountpharmacy.com",
    "wof:name":"Southwest Discount Pharmacy",
    "wof:placetype":"venue"
},
  "geometry": {"coordinates":[-83.104647,42.316479],"type":"Point"}
}