{
  "type": "Feature",
  "properties": {
    "iso:country":"US",
    "sg:address":"294 W Wardlow Rd",
    "sg:city":"Highland",
    "sg:classifiers":[
        {
            "category":"Shopping",
            "subcategory":"Computers & Home Electronics",
            "type":"Retail Goods"
        }
    ],
    "sg:phone":"+1 248 889 6342",
    "sg:postcode":"48357",
    "sg:province":"MI",
    "sg:tags":[
        "software"
    ],
    "wof:name":"Megatechnologies Inc",
    "wof:placetype":"venue"
},
  "geometry": {"coordinates":[-83.620271,42.652495],"type":"Point"}
}