{
  "type": "Feature",
  "properties": {
    "iso:country":"US",
    "sg:address":"8937 Asbury Park",
    "sg:city":"Detroit",
    "sg:classifiers":[
        {
            "category":"Social Services",
            "subcategory":"Child Care",
            "type":"Services"
        }
    ],
    "sg:phone":"+1 313 272 3121",
    "sg:postcode":"48228",
    "sg:province":"MI",
    "sg:tags":[
        "day"
    ],
    "wof:name":"Direct Daycare",
    "wof:placetype":"venue"
},
  "geometry": {"coordinates":[-83.206976,42.359687],"type":"Point"}
}