{
  "type": "Feature",
  "properties": {
    "iso:country":"US",
    "sg:address":"1164 S Cummings Rd",
    "sg:city":"Davison",
    "sg:classifiers":[
        {
            "category":"Arts & Performance",
            "subcategory":"Theater",
            "type":"Entertainment"
        }
    ],
    "sg:phone":"+1 810 653 8469",
    "sg:postcode":"48423",
    "sg:province":"MI",
    "sg:tags":[
        "group"
    ],
    "wof:name":"Davisons Compact Disc Jockey",
    "wof:placetype":"venue"
},
  "geometry": {"coordinates":[-83.488139,43.018488],"type":"Point"}
}