{
  "type": "Feature",
  "properties": {
    "iso:country":"US",
    "sg:address":"5270 E Apple Ave",
    "sg:city":"Muskegon",
    "sg:classifiers":[
        {
            "category":"Retail",
            "subcategory":"Repair Shop",
            "type":"Services"
        },
        {
            "category":"Retail",
            "subcategory":"Auto Repair",
            "type":"Services"
        }
    ],
    "sg:phone":"+1 231 788 2434",
    "sg:postcode":"49442",
    "sg:province":"MI",
    "sg:tags":[
        "engine",
        "repairing",
        "lawn",
        "small",
        "mower"
    ],
    "wof:name":"Norton Small Engine Repair LLC",
    "wof:placetype":"venue"
},
  "geometry": {"coordinates":[-86.115246,43.234817],"type":"Point"}
}