{
  "type": "Feature",
  "properties": {
    "iso:country":"US",
    "sg:address":"1006 S Main St",
    "sg:city":"Cheboygan",
    "sg:classifiers":[
        {
            "category":"Shopping",
            "subcategory":"Tobacco",
            "type":"Retail Goods"
        }
    ],
    "sg:phone":"+1 231 627 5255",
    "sg:postcode":"49721",
    "sg:province":"MI",
    "sg:tags":[
        "cigarette",
        "cigar",
        "dealer"
    ],
    "wof:name":"Matches Discount Cigarettes",
    "wof:placetype":"venue"
},
  "geometry": {"coordinates":[-84.478469,45.62804],"type":"Point"}
}