{
  "type": "Feature",
  "properties": {
    "iso:country":"US",
    "sg:address":"6047 Davis Rd",
    "sg:city":"Saginaw",
    "sg:classifiers":[
        {
            "category":"Health Services",
            "subcategory":"Nursing And Care Facility",
            "type":"Services"
        }
    ],
    "sg:phone":"+1 989 754 6125",
    "sg:postcode":"48604",
    "sg:province":"MI",
    "sg:tags":[
        "home",
        "convalescent"
    ],
    "wof:name":"Country Lane Senior Assisted",
    "wof:placetype":"venue"
},
  "geometry": {"coordinates":[-83.956014,43.494229],"type":"Point"}
}