{
  "type": "Feature",
  "properties": {
    "iso:country":"US",
    "sg:address":"6585 Dixie Hwy",
    "sg:city":"Clarkston",
    "sg:classifiers":[
        {
            "category":"Autos & Motor Vehicles",
            "subcategory":"Automobile Sales",
            "type":"Retail Goods"
        }
    ],
    "sg:phone":"+1 248 922 0172",
    "sg:postcode":"48346",
    "sg:province":"MI",
    "sg:tags":[
        "car",
        "dealer"
    ],
    "wof:name":"Randy Hosler Pontiac",
    "wof:placetype":"venue"
},
  "geometry": {"coordinates":[-83.41183700000001,42.714566],"type":"Point"}
}