{
  "type": "Feature",
  "properties": {
    "iso:country":"US",
    "sg:address":"7600 Packard Ave",
    "sg:city":"Warren",
    "sg:classifiers":[
        {
            "category":"Organizations",
            "subcategory":"Religious Organization",
            "type":"Services"
        }
    ],
    "sg:phone":"+1 586 758 7740",
    "sg:postcode":"48091",
    "sg:province":"MI",
    "sg:tags":[
        "church"
    ],
    "wof:name":"First Church of Jesus Christ",
    "wof:placetype":"venue"
},
  "geometry": {"coordinates":[-83.02687400000001,42.458568],"type":"Point"}
}