{
  "type": "Feature",
  "properties": {
    "iso:country":"US",
    "sg:address":"10515 N Latson Rd",
    "sg:city":"Howell",
    "sg:classifiers":[
        {
            "category":"Organizations",
            "subcategory":"Religious Organization",
            "type":"Services"
        }
    ],
    "sg:phone":"+1 517 545 7559",
    "sg:postcode":"48855",
    "sg:province":"MI",
    "wof:name":"Americana Buddhist Temple",
    "wof:placetype":"venue"
},
  "geometry": {"coordinates":[-83.888616,42.760972],"type":"Point"}
}