{
  "type": "Feature",
  "properties": {
    "iso:country":"US",
    "sg:address":"25353 Trowbridge St",
    "sg:city":"Dearborn",
    "sg:classifiers":[
        {
            "category":"Professional",
            "subcategory":"Business Services",
            "type":"Services"
        }
    ],
    "sg:phone":"+1 313 791 6100",
    "sg:postcode":"48124",
    "sg:province":"MI",
    "sg:tags":[
        "auto",
        "repair"
    ],
    "wof:name":"Collision Craftsmen Inc",
    "wof:placetype":"venue"
},
  "geometry": {"coordinates":[-83.28510300000001,42.2957],"type":"Point"}
}