{
  "type": "Feature",
  "properties": {
    "iso:country":"US",
    "sg:address":"24155 Drake Rd",
    "sg:city":"Farmington Hills",
    "sg:classifiers":[
        {
            "category":"Government",
            "subcategory":"Office",
            "type":"Public Place"
        },
        {
            "category":"Organizations",
            "subcategory":"Labor Organization",
            "type":"Services"
        }
    ],
    "sg:phone":"+1 248 888 8777",
    "sg:postcode":"48335",
    "sg:province":"MI",
    "wof:name":"Labor & Economic Growth Dept",
    "wof:placetype":"venue"
},
  "geometry": {"coordinates":[-83.396191,42.467532],"type":"Point"}
}