{
  "type": "Feature",
  "properties": {
    "iso:country":"US",
    "sg:address":"405 N Harrison St",
    "sg:city":"Ludington",
    "sg:classifiers":[
        {
            "category":"Real Estate",
            "subcategory":"Real Estate Agent",
            "type":"Services"
        }
    ],
    "sg:phone":"+1 231 845 0068",
    "sg:postcode":"49431",
    "sg:province":"MI",
    "wof:name":"Gene R Butler",
    "wof:placetype":"venue"
},
  "geometry": {"coordinates":[-86.446566,43.960675],"type":"Point"}
}