{
  "type": "Feature",
  "properties": {
    "iso:country":"US",
    "sg:address":"482 Cedar Ridge Dr",
    "sg:city":"Grand Rapids",
    "sg:classifiers":[
        {
            "category":"Professional",
            "subcategory":"Business Services",
            "type":"Services"
        }
    ],
    "sg:phone":"+1 616 696 5784",
    "sg:postcode":"49544",
    "sg:province":"MI",
    "wof:name":"Bollinger Dynamics",
    "wof:placetype":"venue"
},
  "geometry": {"coordinates":[-85.681847,43.023611],"type":"Point"}
}