{
  "type": "Feature",
  "properties": {
    "iso:country":"US",
    "sg:address":"653 S Madison St",
    "sg:city":"Adrian",
    "sg:classifiers":[
        {
            "category":"Real Estate",
            "subcategory":"Real Estate Operator",
            "type":"Services"
        }
    ],
    "sg:phone":"+1 517 263 7162",
    "sg:postcode":"49221",
    "sg:province":"MI",
    "sg:tags":[
        "building",
        "apartment"
    ],
    "wof:name":"Brookside Estates",
    "wof:placetype":"venue"
},
  "geometry": {"coordinates":[-84.058036,41.889836],"type":"Point"}
}