{
  "type": "Feature",
  "properties": {
    "iso:country":"US",
    "sg:address":"708 Cambridge Dr",
    "sg:city":"Battle Creek",
    "sg:classifiers":[
        {
            "category":"Food & Beverages",
            "subcategory":"Liquor & Beverages",
            "type":"Retail Goods"
        }
    ],
    "sg:phone":"+1 269 964 1651",
    "sg:postcode":"49015",
    "sg:province":"MI",
    "sg:tags":[
        "alcoholic"
    ],
    "wof:name":"Van Marz Distribution Inc",
    "wof:placetype":"venue"
},
  "geometry": {"coordinates":[-85.181529,42.284234],"type":"Point"}
}