{
  "type": "Feature",
  "properties": {
    "iso:country":"US",
    "sg:address":"1645 E Lansing Dr",
    "sg:city":"East Lansing",
    "sg:classifiers":[
        {
            "category":"Manufacturing",
            "subcategory":"Metals",
            "type":"Manufacturing & Wholesale Goods"
        }
    ],
    "sg:phone":"+1 517 351 2358",
    "sg:postcode":"48823",
    "sg:province":"MI",
    "sg:tags":[
        "hardware",
        "mfg"
    ],
    "wof:name":"Hays Sales Company",
    "wof:placetype":"venue"
},
  "geometry": {"coordinates":[-84.452393,42.748211],"type":"Point"}
}