{
  "type": "Feature",
  "properties": {
    "iso:country":"US",
    "sg:address":"3129 Christner St",
    "sg:city":"Burton",
    "sg:classifiers":[
        {
            "category":"Professional",
            "subcategory":"Business Services",
            "type":"Services"
        }
    ],
    "sg:phone":"+1 810 744 4299",
    "sg:postcode":"48529",
    "sg:province":"MI",
    "wof:name":"Eastern Michigan Golden Grub",
    "wof:placetype":"venue"
},
  "geometry": {"coordinates":[-83.639557,42.986722],"type":"Point"}
}