{
  "type": "Feature",
  "properties": {
    "iso:country":"US",
    "sg:address":"4205 Dunbar Ave SW",
    "sg:city":"Grand Rapids",
    "sg:classifiers":[
        {
            "category":"Professional",
            "subcategory":"Management & Consulting",
            "type":"Services"
        }
    ],
    "sg:phone":"+1 616 532 1147",
    "sg:postcode":"49509",
    "sg:province":"MI",
    "sg:tags":[
        "consultant",
        "business"
    ],
    "wof:name":"Invest In People LLC",
    "wof:placetype":"venue"
},
  "geometry": {"coordinates":[-85.690269,42.886985],"type":"Point"}
}