{
  "type": "Feature",
  "properties": {
    "iso:country":"US",
    "sg:address":"4175 Highland Rd",
    "sg:city":"Waterford",
    "sg:classifiers":[
        {
            "category":"Organizations",
            "subcategory":"Community Association",
            "type":"Services"
        }
    ],
    "sg:phone":"+1 248 683 9590",
    "sg:postcode":"48328",
    "sg:province":"MI",
    "wof:name":"Waterford Lions Community Club",
    "wof:placetype":"venue"
},
  "geometry": {"coordinates":[-83.36795100000001,42.650343],"type":"Point"}
}