{
  "type": "Feature",
  "properties": {
    "iso:country":"US",
    "sg:address":"7714 Harper Ave",
    "sg:city":"Detroit",
    "sg:classifiers":[
        {
            "category":"Professional",
            "subcategory":"Accounting & Tax Preparation",
            "type":"Services"
        }
    ],
    "sg:phone":"+1 313 925 5111",
    "sg:postcode":"48213",
    "sg:province":"MI",
    "sg:tags":[
        "accountant"
    ],
    "wof:name":"Brooks Bookkeeping & Tax Service",
    "wof:placetype":"venue"
},
  "geometry": {"coordinates":[-83.021004,42.388],"type":"Point"}
}