{
  "type": "Feature",
  "properties": {
    "iso:country":"US",
    "sg:address":"5151 Conway Rd",
    "sg:city":"Chelsea",
    "sg:classifiers":[
        {
            "category":"Professional",
            "type":"Services"
        }
    ],
    "sg:phone":"+1 734 475 2189",
    "sg:postcode":"48118",
    "sg:province":"MI",
    "wof:name":"Parker & Sons Outdoor Services",
    "wof:placetype":"venue"
},
  "geometry": {"coordinates":[-84.0539,42.310749],"type":"Point"}
}