{
  "type": "Feature",
  "properties": {
    "iso:country":"US",
    "sg:address":"259 W Grand Traverse St",
    "sg:city":"Commerce Twp",
    "sg:classifiers":[
        {
            "category":"Home & Garden",
            "subcategory":"Carpets & Floor Coverings",
            "type":"Retail Goods"
        }
    ],
    "sg:phone":"+1 248 360 0454",
    "sg:postcode":"48382",
    "sg:province":"MI",
    "sg:tags":[
        "dealer",
        "rug"
    ],
    "wof:name":"Steamaster Carpet & Upholstery",
    "wof:placetype":"venue"
},
  "geometry": {"coordinates":[-83.48226,42.605514],"type":"Point"}
}