{
  "type": "Feature",
  "properties": {
    "iso:country":"US",
    "sg:address":"1341 E Pine Hill Ave",
    "sg:city":"White Cloud",
    "sg:classifiers":[
        {
            "category":"Manufacturing",
            "subcategory":"Metals",
            "type":"Manufacturing & Wholesale Goods"
        }
    ],
    "sg:phone":"+1 231 689 9993",
    "sg:postcode":"49349",
    "sg:province":"MI",
    "sg:tags":[
        "coating"
    ],
    "wof:name":"Advanced Powder Coating",
    "wof:placetype":"venue"
},
  "geometry": {"coordinates":[-85.767402,43.553992],"type":"Point"}
}