{
  "type": "Feature",
  "properties": {
    "iso:country":"US",
    "sg:address":"703 E Peck Lake Rd",
    "sg:city":"Ionia",
    "sg:classifiers":[
        {
            "category":"Wholesale",
            "subcategory":"Meat",
            "type":"Manufacturing & Wholesale Goods"
        }
    ],
    "sg:phone":"+1 616 527 6280",
    "sg:postcode":"48846",
    "sg:province":"MI",
    "sg:tags":[
        "packer"
    ],
    "wof:name":"Country Packing Custom Butcher",
    "wof:placetype":"venue"
},
  "geometry": {"coordinates":[-85.074946,42.900506],"type":"Point"}
}