{
  "type": "Feature",
  "properties": {
    "iso:country":"US",
    "sg:address":"209 W Mill St",
    "sg:city":"Hastings",
    "sg:classifiers":[
        {
            "category":"Government",
            "subcategory":"Post Office",
            "type":"Public Place"
        }
    ],
    "sg:phone":"+1 269 945 4273",
    "sg:postcode":"49058",
    "sg:province":"MI",
    "wof:name":"US Post Office",
    "wof:placetype":"venue"
},
  "geometry": {"coordinates":[-85.290583,42.650622],"type":"Point"}
}