{
  "type": "Feature",
  "properties": {
    "iso:country":"US",
    "sg:address":"19246 Newburgh Rd",
    "sg:city":"Livonia",
    "sg:classifiers":[
        {
            "category":"Health Services",
            "subcategory":"Doctor",
            "type":"Services"
        },
        {
            "category":"Health Services",
            "subcategory":"Clinic",
            "type":"Services"
        },
        {
            "category":"Health Services",
            "subcategory":"Health Practitioner",
            "type":"Services"
        }
    ],
    "sg:phone":"+1 734 838 6669",
    "sg:postcode":"48152",
    "sg:province":"MI",
    "sg:tags":[
        "control",
        "physician",
        "surgeon",
        "reducing",
        "weight"
    ],
    "wof:name":"Physicians Weight Loss Centers",
    "wof:placetype":"venue"
},
  "geometry": {"coordinates":[-83.414063,42.426171],"type":"Point"}
}