{
  "type": "Feature",
  "properties": {
    "iso:country":"US",
    "sg:address":"1539 Ridgewood Ave SE",
    "sg:city":"Grand Rapids",
    "sg:classifiers":[
        {
            "category":"Professional",
            "subcategory":"Management & Consulting",
            "type":"Services"
        }
    ],
    "sg:phone":"+1 616 942 4040",
    "sg:postcode":"49506",
    "sg:province":"MI",
    "sg:tags":[
        "education"
    ],
    "wof:name":"William Southworth",
    "wof:placetype":"venue"
},
  "geometry": {"coordinates":[-85.596752,42.934849],"type":"Point"}
}