{
  "type": "Feature",
  "properties": {
    "iso:country":"US",
    "sg:address":"137 124th Ave",
    "sg:city":"Shelbyville",
    "sg:classifiers":[
        {
            "category":"Autos & Motor Vehicles",
            "subcategory":"Automobile Sales",
            "type":"Retail Goods"
        }
    ],
    "sg:phone":"+1 269 672 9182",
    "sg:postcode":"49344",
    "sg:province":"MI",
    "sg:tags":[
        "used"
    ],
    "wof:name":"Lakeview Sales of Gunlake Inc",
    "wof:placetype":"venue"
},
  "geometry": {"coordinates":[-85.552571,42.594817],"type":"Point"}
}