{
  "type": "Feature",
  "properties": {
    "iso:country":"US",
    "sg:address":"545 Ashmun St",
    "sg:city":"Sault Ste Marie",
    "sg:classifiers":[
        {
            "category":"Insurance",
            "subcategory":"Insurance Agent",
            "type":"Services"
        }
    ],
    "sg:phone":"+1 906 635 5981",
    "sg:postcode":"49783",
    "sg:province":"MI",
    "wof:name":"Sutter Meemic Insurance",
    "wof:placetype":"venue"
},
  "geometry": {"coordinates":[-84.348681,46.496232],"type":"Point"}
}