{
  "type": "Feature",
  "properties": {
    "iso:country":"US",
    "sg:address":"1747 W Milham Rd",
    "sg:city":"Portage",
    "sg:classifiers":[
        {
            "category":"Organizations",
            "subcategory":"Religious Organization",
            "type":"Services"
        }
    ],
    "sg:phone":"+1 269 343 3453",
    "sg:postcode":"49024",
    "sg:province":"MI",
    "sg:tags":[
        "lutheran",
        "church"
    ],
    "wof:name":"Prince Peace Lutheran Church",
    "wof:placetype":"venue"
},
  "geometry": {"coordinates":[-85.609872,42.230028],"type":"Point"}
}