{
  "type": "Feature",
  "properties": {
    "iso:country":"US",
    "sg:address":"28600 Eleven Mile Rd.",
    "sg:city":"Farmington Hills",
    "sg:classifiers":[
        {
            "category":"Organizations",
            "subcategory":"Non-profit Organization",
            "type":"Services"
        }
    ],
    "sg:phone":"+1 248 473 1800",
    "sg:postcode":"48336",
    "sg:province":"MI",
    "sg:tags":[
        "service/non-profit",
        "community"
    ],
    "sg:website":"www.ci.farmington-hills.mi.us/Co...",
    "wof:name":"William M. Costick Activities Center",
    "wof:placetype":"venue"
},
  "geometry": {"coordinates":[-83.33046400000001,42.485359],"type":"Point"}
}