{
  "type": "Feature",
  "properties": {
    "iso:country":"US",
    "sg:address":"2190 Brooklyn Rd",
    "sg:city":"Jackson",
    "sg:classifiers":[
        {
            "category":"Retail",
            "subcategory":"Repair Shop",
            "type":"Services"
        }
    ],
    "sg:phone":"+1 517 780 0140",
    "sg:postcode":"49203",
    "sg:province":"MI",
    "sg:tags":[
        "welding"
    ],
    "wof:name":"Eagle Production Welding",
    "wof:placetype":"venue"
},
  "geometry": {"coordinates":[-84.380464,42.218269],"type":"Point"}
}