{
  "type": "Feature",
  "properties": {
    "iso:country":"US",
    "sg:address":"2786 E Lansing Dr",
    "sg:city":"East Lansing",
    "sg:classifiers":[
        {
            "category":"Cinema",
            "subcategory":"Movie Rental",
            "type":"Entertainment"
        }
    ],
    "sg:phone":"+1 517 336 6900",
    "sg:postcode":"48823",
    "sg:province":"MI",
    "sg:tags":[
        "video",
        "tape"
    ],
    "sg:website":"www.hollywoodvideo.com",
    "wof:name":"Hollywood Video",
    "wof:placetype":"venue"
},
  "geometry": {"coordinates":[-84.45081,42.74961],"type":"Point"}
}