{
  "type": "Feature",
  "properties": {
    "iso:country":"US",
    "sg:address":"4450 Fashion Square Blvd",
    "sg:city":"Saginaw",
    "sg:classifiers":[
        {
            "category":"Health Services",
            "subcategory":"Doctor",
            "type":"Services"
        }
    ],
    "sg:phone":"+1 989 792 4090",
    "sg:postcode":"48603",
    "sg:province":"MI",
    "sg:tags":[
        "physician",
        "surgeon"
    ],
    "wof:name":"Matrix Pain Management",
    "wof:placetype":"venue"
},
  "geometry": {"coordinates":[-83.969463,43.471866],"type":"Point"}
}