{
  "type": "Feature",
  "properties": {
    "iso:country":"US",
    "sg:address":"5600 Crooks Rd",
    "sg:city":"Troy",
    "sg:classifiers":[
        {
            "category":"Professional",
            "type":"Services"
        }
    ],
    "sg:phone":"+1 248 879 7614",
    "sg:postcode":"48098",
    "sg:province":"MI",
    "wof:name":"Service Centers Corp",
    "wof:placetype":"venue"
},
  "geometry": {"coordinates":[-83.169083,42.601665],"type":"Point"}
}