{
  "type": "Feature",
  "properties": {
    "iso:country":"US",
    "sg:address":"29928 Rock Creek Dr",
    "sg:city":"Southfield",
    "sg:classifiers":[
        {
            "category":"Social Services",
            "subcategory":"Adult Care",
            "type":"Services"
        }
    ],
    "sg:phone":"+1 248 569 0145",
    "sg:postcode":"48076",
    "sg:province":"MI",
    "sg:tags":[
        "foster",
        "provider"
    ],
    "wof:name":"Jeffery & Carol Mosley",
    "wof:placetype":"venue"
},
  "geometry": {"coordinates":[-83.235196,42.509267],"type":"Point"}
}