{
  "type": "Feature",
  "properties": {
    "iso:country":"US",
    "sg:address":"5199 Farwell Lake Rd",
    "sg:city":"Horton",
    "sg:classifiers":[
        {
            "category":"Building & Trades",
            "subcategory":"Construction",
            "type":"Services"
        }
    ],
    "sg:phone":"+1 517 688 4705",
    "sg:postcode":"49246",
    "sg:province":"MI",
    "sg:tags":[
        "carpenter"
    ],
    "wof:name":"Unlimited Carpentry LLC",
    "wof:placetype":"venue"
},
  "geometry": {"coordinates":[-84.502038,42.076044],"type":"Point"}
}