{
  "type": "Feature",
  "properties": {
    "iso:country":"US",
    "sg:address":"1605 Bonner St",
    "sg:city":"Ferndale",
    "sg:classifiers":[
        {
            "category":"Manufacturing",
            "subcategory":"Electronics",
            "type":"Manufacturing & Wholesale Goods"
        }
    ],
    "sg:phone":"+1 248 399 4300",
    "sg:postcode":"48220",
    "sg:province":"MI",
    "sg:tags":[
        "coil",
        "transformer",
        "electronic"
    ],
    "wof:name":"Powertran Corp",
    "wof:placetype":"venue"
},
  "geometry": {"coordinates":[-83.120148,42.459751],"type":"Point"}
}