{
  "type": "Feature",
  "properties": {
    "iso:country":"US",
    "sg:address":"32 Oakridge Dr",
    "sg:city":"Marquette",
    "sg:classifiers":[
        {
            "category":"Recreation",
            "type":"Entertainment"
        }
    ],
    "sg:phone":"+1 906 249 1577",
    "sg:postcode":"49855",
    "sg:province":"MI",
    "sg:tags":[
        "martial",
        "arts",
        "instruction"
    ],
    "wof:name":"Dawe Martial Arts Inc",
    "wof:placetype":"venue"
},
  "geometry": {"coordinates":[-87.42221600000001,46.466049],"type":"Point"}
}