{
  "type": "Feature",
  "properties": {
    "iso:country":"US",
    "sg:address":"13265 E 8 Mile Rd",
    "sg:city":"Warren",
    "sg:classifiers":[
        {
            "category":"Manufacturing",
            "subcategory":"Tools & Machinery",
            "type":"Manufacturing & Wholesale Goods"
        }
    ],
    "sg:phone":"+1 586 771 6700",
    "sg:postcode":"48205",
    "sg:province":"MI",
    "sg:tags":[
        "machine"
    ],
    "wof:name":"CNC Link",
    "wof:placetype":"venue"
},
  "geometry": {"coordinates":[-82.98958500000001,42.449111],"type":"Point"}
}