{
  "type": "Feature",
  "properties": {
    "iso:country":"US",
    "sg:address":"18460 Oakfield St",
    "sg:city":"Detroit",
    "sg:classifiers":[
        {
            "category":"Social Services",
            "subcategory":"Child Care",
            "type":"Services"
        }
    ],
    "sg:phone":"+1 313 272 7670",
    "sg:postcode":"48235",
    "sg:province":"MI",
    "sg:tags":[
        "day"
    ],
    "wof:name":"Honey Bear Home Daycare",
    "wof:placetype":"venue"
},
  "geometry": {"coordinates":[-83.21479600000001,42.425949],"type":"Point"}
}