{
  "type": "Feature",
  "properties": {
    "iso:country":"US",
    "sg:address":"6591 Schmeid Rd",
    "sg:city":"Lakeview",
    "sg:classifiers":[
        {
            "category":"Professional",
            "subcategory":"Business Services",
            "type":"Services"
        }
    ],
    "sg:phone":"+1 989 352 7542",
    "sg:postcode":"48850",
    "sg:province":"MI",
    "wof:name":"Affordable Engineered Solution",
    "wof:placetype":"venue"
},
  "geometry": {"coordinates":[-85.218153,43.459063],"type":"Point"}
}