{
  "type": "Feature",
  "properties": {
    "iso:country":"US",
    "sg:address":"1087 S Patterson Rd",
    "sg:city":"Wayland",
    "sg:classifiers":[
        {
            "category":"Building & Trades",
            "subcategory":"Landscaping Services",
            "type":"Services"
        }
    ],
    "sg:phone":"+1 269 792 6820",
    "sg:postcode":"49348",
    "sg:province":"MI",
    "sg:tags":[
        "lawn",
        "maintenance",
        "grounds"
    ],
    "wof:name":"Witte Lawn Maintenance Inc",
    "wof:placetype":"venue"
},
  "geometry": {"coordinates":[-85.54416999999999,42.636134],"type":"Point"}
}