{
  "type": "Feature",
  "properties": {
    "iso:country":"US",
    "sg:address":"1495 Imlay City Rd",
    "sg:city":"Lapeer",
    "sg:classifiers":[
        {
            "category":"Banks & Credit Unions",
            "subcategory":"Bank",
            "type":"Services"
        }
    ],
    "sg:phone":"+1 810 664 1698",
    "sg:postcode":"48446",
    "sg:province":"MI",
    "sg:tags":[
        "loan"
    ],
    "wof:name":"Lapeer County Community Credit",
    "wof:placetype":"venue"
},
  "geometry": {"coordinates":[-83.28522599999999,43.046492],"type":"Point"}
}