{
  "type": "Feature",
  "properties": {
    "iso:country":"US",
    "sg:address":"635 Godfrey Ave SW",
    "sg:city":"Grand Rapids",
    "sg:classifiers":[
        {
            "category":"Professional",
            "type":"Services"
        }
    ],
    "sg:phone":"+1 616 742 5555",
    "sg:postcode":"49503",
    "sg:province":"MI",
    "sg:tags":[
        "establishment"
    ],
    "wof:name":"Rivertown Resin Repelltzng Inc",
    "wof:placetype":"venue"
},
  "geometry": {"coordinates":[-85.6823,42.952385],"type":"Point"}
}