{
  "type": "Feature",
  "properties": {
    "iso:country":"US",
    "sg:address":"512 W 3rd St",
    "sg:city":"Monroe",
    "sg:classifiers":[
        {
            "category":"Professional",
            "subcategory":"Accounting & Tax Preparation",
            "type":"Services"
        }
    ],
    "sg:phone":"+1 734 242 3784",
    "sg:postcode":"48161",
    "sg:province":"MI",
    "sg:tags":[
        "return"
    ],
    "wof:name":"Smb Income Tax",
    "wof:placetype":"venue"
},
  "geometry": {"coordinates":[-83.407414,41.917766],"type":"Point"}
}