{
  "type": "Feature",
  "properties": {
    "iso:country":"US",
    "sg:address":"13874 Medina Rd",
    "sg:city":"Hudson",
    "sg:classifiers":[
        {
            "category":"Organizations",
            "subcategory":"Religious Organization",
            "type":"Services"
        }
    ],
    "sg:phone":"+1 517 448 3036",
    "sg:postcode":"49247",
    "sg:province":"MI",
    "wof:name":"Rev Diane Morgan",
    "wof:placetype":"venue"
},
  "geometry": {"coordinates":[-84.288877,41.812667],"type":"Point"}
}