{
  "type": "Feature",
  "properties": {
    "iso:country":"US",
    "sg:address":"28735 Bradner Dr",
    "sg:city":"Warren",
    "sg:classifiers":[
        {
            "category":"Building & Trades",
            "subcategory":"Landscaping Services",
            "type":"Services"
        }
    ],
    "sg:phone":"+1 586 445 9454",
    "sg:postcode":"48088",
    "sg:province":"MI",
    "sg:tags":[
        "lawn",
        "maintenance",
        "grounds"
    ],
    "wof:name":"Three T's Lawn Care",
    "wof:placetype":"venue"
},
  "geometry": {"coordinates":[-82.984413,42.50456],"type":"Point"}
}