{
  "type": "Feature",
  "properties": {
    "iso:country":"US",
    "sg:address":"3131 Woodland Dr SE",
    "sg:city":"Kentwood",
    "sg:classifiers":[
        {
            "category":"Shopping",
            "subcategory":"Department Store",
            "type":"Retail Goods"
        }
    ],
    "sg:phone":"+1 616 957 0110",
    "sg:postcode":"49512",
    "sg:province":"MI",
    "sg:website":"www.kohls.com",
    "wof:name":"Kohl's",
    "wof:placetype":"venue"
},
  "geometry": {"coordinates":[-85.592163,42.91491],"type":"Point"}
}