{
  "type": "Feature",
  "properties": {
    "iso:country":"US",
    "sg:address":"26916 Sibley Rd",
    "sg:city":"Romulus",
    "sg:classifiers":[
        {
            "category":"Professional",
            "subcategory":"Art Services",
            "type":"Services"
        }
    ],
    "sg:phone":"+1 734 229 0861",
    "sg:postcode":"48174",
    "sg:province":"MI",
    "sg:tags":[
        "commercial",
        "design"
    ],
    "wof:name":"Broadway Type & Graphics",
    "wof:placetype":"venue"
},
  "geometry": {"coordinates":[-83.293768,42.166898],"type":"Point"}
}