{
  "type": "Feature",
  "properties": {
    "iso:country":"US",
    "sg:address":"3822 Fenton Rd",
    "sg:city":"Flint",
    "sg:classifiers":[
        {
            "category":"Fast Food",
            "type":"Food & Drink"
        },
        {
            "category":"Restaurant",
            "type":"Food & Drink"
        },
        {
            "category":"Food & Beverages",
            "subcategory":"Groceries & Convenience Stores",
            "type":"Retail Goods"
        }
    ],
    "sg:phone":"+1 810 234 3248",
    "sg:postcode":"48507",
    "sg:province":"MI",
    "sg:tags":[
        "shop",
        "american",
        "sandwich",
        "take"
    ],
    "sg:website":"http://www.subway.com",
    "wof:name":"Subway",
    "wof:placetype":"venue"
},
  "geometry": {"coordinates":[-83.693045,42.988259],"type":"Point"}
}