{
  "type": "Feature",
  "properties": {
    "iso:country":"US",
    "sg:address":"1348 Vinewood St",
    "sg:city":"Auburn Hills",
    "sg:classifiers":[
        {
            "category":"Freight",
            "type":"Transportation"
        }
    ],
    "sg:phone":"+1 248 475 0638",
    "sg:postcode":"48326",
    "sg:province":"MI",
    "sg:tags":[
        "operator",
        "local",
        "trucking"
    ],
    "wof:name":"Lafferty Trucking Inc",
    "wof:placetype":"venue"
},
  "geometry": {"coordinates":[-83.273386,42.688674],"type":"Point"}
}