{
  "type": "Feature",
  "properties": {
    "iso:country":"US",
    "sg:address":"445 Hamilton Ave",
    "sg:city":"Iron Mountain",
    "sg:classifiers":[
        {
            "category":"Education",
            "subcategory":"School",
            "type":"Public Place"
        }
    ],
    "sg:phone":"+1 906 779 2680",
    "sg:postcode":"49802",
    "sg:province":"MI",
    "wof:name":"Kingsford Junior High School",
    "wof:placetype":"venue"
},
  "geometry": {"coordinates":[-88.07203699999999,45.805892],"type":"Point"}
}