{
  "type": "Feature",
  "properties": {
    "iso:country":"US",
    "sg:address":"49362 Sandra",
    "sg:city":"Utica",
    "sg:classifiers":[
        {
            "category":"Professional",
            "subcategory":"Computer Services",
            "type":"Services"
        }
    ],
    "sg:phone":"+1 586 323 6394",
    "sg:postcode":"48315",
    "sg:province":"MI",
    "sg:tags":[
        "programing",
        "custom"
    ],
    "wof:name":"JD Systems",
    "wof:placetype":"venue"
},
  "geometry": {"coordinates":[-82.996546,42.657589],"type":"Point"}
}