{
  "type": "Feature",
  "properties": {
    "iso:country":"US",
    "sg:address":"20262 Lichfield Rd",
    "sg:city":"Detroit",
    "sg:classifiers":[
        {
            "category":"Social Services",
            "subcategory":"Child Care",
            "type":"Services"
        }
    ],
    "sg:phone":"+1 313 862 3706",
    "sg:postcode":"48221",
    "sg:province":"MI",
    "sg:tags":[
        "day"
    ],
    "wof:name":"Early Learning Center",
    "wof:placetype":"venue"
},
  "geometry": {"coordinates":[-83.133045,42.442594],"type":"Point"}
}