{
  "type": "Feature",
  "properties": {
    "iso:country":"US",
    "sg:address":"6510 W Grand River Ave",
    "sg:city":"Lansing",
    "sg:classifiers":[
        {
            "category":"Shopping",
            "subcategory":"Bicycles & Sporting Goods",
            "type":"Retail Goods"
        }
    ],
    "sg:phone":"+1 517 321 1436",
    "sg:postcode":"48906",
    "sg:province":"MI",
    "wof:name":"Genes Sporting Supply",
    "wof:placetype":"venue"
},
  "geometry": {"coordinates":[-84.65554899999999,42.782253],"type":"Point"}
}