{
  "type": "Feature",
  "properties": {
    "iso:country":"US",
    "sg:address":"560 Kinneville Rd",
    "sg:city":"Leslie",
    "sg:phone":"+1 517 589 9625",
    "sg:postcode":"49251",
    "sg:province":"MI",
    "sg:tags":[
        "farm",
        "corn",
        "wheat",
        "soybean"
    ],
    "wof:name":"Jackson Farms",
    "wof:placetype":"venue"
},
  "geometry": {"coordinates":[-84.366781,42.465717],"type":"Point"}
}