{
  "type": "Feature",
  "properties": {
    "iso:country":"US",
    "sg:address":"29212 Glenwood St",
    "sg:city":"Inkster",
    "sg:classifiers":[
        {
            "category":"Organizations",
            "subcategory":"Community Association",
            "type":"Services"
        }
    ],
    "sg:phone":"+1 734 467 1981",
    "sg:postcode":"48141",
    "sg:province":"MI",
    "wof:name":"Individuals Helping Our People",
    "wof:placetype":"venue"
},
  "geometry": {"coordinates":[-83.329341,42.302302],"type":"Point"}
}