{
  "type": "Feature",
  "properties": {
    "iso:country":"US",
    "sg:address":"425 North St",
    "sg:city":"Blissfield",
    "sg:classifiers":[
        {
            "category":"Professional",
            "type":"Services"
        }
    ],
    "sg:phone":"+1 517 486 3407",
    "sg:postcode":"49228",
    "sg:province":"MI",
    "wof:name":"Alpha Enterprises",
    "wof:placetype":"venue"
},
  "geometry": {"coordinates":[-83.869117,41.846211],"type":"Point"}
}