{
  "type": "Feature",
  "properties": {
    "iso:country":"US",
    "sg:address":"11100 Linden Rd",
    "sg:city":"Fenton",
    "sg:classifiers":[
        {
            "category":"Shopping",
            "type":"Retail Goods"
        }
    ],
    "sg:phone":"+1 810 750 2723",
    "sg:postcode":"48430",
    "sg:province":"MI",
    "sg:tags":[
        "picture",
        "frame"
    ],
    "wof:name":"Shadowood",
    "wof:placetype":"venue"
},
  "geometry": {"coordinates":[-83.78607599999999,42.77151],"type":"Point"}
}