{
  "type": "Feature",
  "properties": {
    "iso:country":"US",
    "sg:address":"851 E Knox Rd",
    "sg:city":"Beaverton",
    "sg:classifiers":[
        {
            "category":"Personal",
            "subcategory":"Beauty Salon",
            "type":"Services"
        }
    ],
    "sg:phone":"+1 989 435 3834",
    "sg:postcode":"48612",
    "sg:province":"MI",
    "wof:name":"Kathy's Hair Salon",
    "wof:placetype":"venue"
},
  "geometry": {"coordinates":[-84.337193,43.886222],"type":"Point"}
}