{
  "type": "Feature",
  "properties": {
    "iso:country":"US",
    "sg:address":"10361 W Van Buren Rd",
    "sg:city":"Riverdale",
    "sg:classifiers":[
        {
            "category":"Home & Garden",
            "subcategory":"Building Materials",
            "type":"Retail Goods"
        }
    ],
    "sg:phone":"+1 989 833 7135",
    "sg:postcode":"48877",
    "sg:province":"MI",
    "sg:tags":[
        "lumber"
    ],
    "wof:name":"Log Cabin Lumber",
    "wof:placetype":"venue"
},
  "geometry": {"coordinates":[-84.820691,43.364703],"type":"Point"}
}