{
  "type": "Feature",
  "properties": {
    "iso:country":"US",
    "sg:address":"5260 N Saginaw St",
    "sg:city":"Flint",
    "sg:classifiers":[
        {
            "category":"Shopping",
            "type":"Retail Goods"
        }
    ],
    "sg:phone":"+1 810 787 7000",
    "sg:postcode":"48505",
    "sg:province":"MI",
    "sg:tags":[
        "pet",
        "food",
        "supply"
    ],
    "wof:name":"Cobb Bait Tackle & Pet Supply",
    "wof:placetype":"venue"
},
  "geometry": {"coordinates":[-83.694051,43.082952],"type":"Point"}
}