{
  "type": "Feature",
  "properties": {
    "iso:country":"US",
    "sg:address":"22525 Woodward Ave",
    "sg:city":"Ferndale",
    "sg:classifiers":[
        {
            "category":"Restaurant",
            "type":"Food & Drink"
        }
    ],
    "sg:menulink":"http://www.allmenus.com/mi/ferndale/185862-mcdonalds/menu/",
    "sg:postcode":"48220",
    "sg:province":"MI",
    "sg:tags":[
        "burger",
        "american"
    ],
    "wof:name":"McDonald's",
    "wof:placetype":"venue"
},
  "geometry": {"coordinates":[-83.133456,42.458557],"type":"Point"}
}