{
  "type": "Feature",
  "properties": {
    "iso:country":"US",
    "sg:address":"4215 S Baldwin Rd",
    "sg:city":"Lake Orion",
    "sg:classifiers":[
        {
            "category":"Shopping",
            "subcategory":"Florist",
            "type":"Retail Goods"
        }
    ],
    "sg:phone":"+1 248 393 6307",
    "sg:postcode":"48359",
    "sg:province":"MI",
    "wof:name":"Hillside Florist & Gifts LLC",
    "wof:placetype":"venue"
},
  "geometry": {"coordinates":[-83.30736899999999,42.719539],"type":"Point"}
}