{
  "type": "Feature",
  "properties": {
    "iso:country":"US",
    "sg:address":"33020 Northwestern Hwy",
    "sg:city":"West Bloomfield",
    "sg:classifiers":[
        {
            "category":"Shopping",
            "subcategory":"Beauty & Cosmetics",
            "type":"Retail Goods"
        }
    ],
    "sg:phone":"+1 248 855 1380",
    "sg:postcode":"48322",
    "sg:province":"MI",
    "sg:tags":[
        "supply"
    ],
    "wof:name":"Cosmoprof",
    "wof:placetype":"venue"
},
  "geometry": {"coordinates":[-83.35772900000001,42.52882],"type":"Point"}
}