{
  "type": "Feature",
  "properties": {
    "iso:country":"US",
    "sg:address":"5929 Murray Rd",
    "sg:city":"Whitehall",
    "sg:classifiers":[
        {
            "category":"Professional",
            "subcategory":"Business Services",
            "type":"Services"
        }
    ],
    "sg:phone":"+1 231 893 5929",
    "sg:postcode":"49461",
    "sg:province":"MI",
    "sg:tags":[
        "organization",
        "religious"
    ],
    "wof:name":"Galactic Foundation",
    "wof:placetype":"venue"
},
  "geometry": {"coordinates":[-86.41967699999999,43.366797],"type":"Point"}
}