{
  "type": "Feature",
  "properties": {
    "iso:country":"US",
    "sg:address":"1298 Indianwood Rd",
    "sg:city":"Lake Orion",
    "sg:classifiers":[
        {
            "category":"Personal",
            "subcategory":"Beauty Salon",
            "type":"Services"
        }
    ],
    "sg:phone":"+1 248 568 3008",
    "sg:postcode":"48362",
    "sg:province":"MI",
    "sg:tags":[
        "shop"
    ],
    "wof:name":"Eugenios Hair Place LLC",
    "wof:placetype":"venue"
},
  "geometry": {"coordinates":[-83.27207799999999,42.788599],"type":"Point"}
}