{
  "type": "Feature",
  "properties": {
    "iso:country":"US",
    "sg:address":"1231 E Center St",
    "sg:city":"Ithaca",
    "sg:classifiers":[
        {
            "category":"Freight",
            "type":"Transportation"
        }
    ],
    "sg:phone":"+1 989 875 4389",
    "sg:postcode":"48847",
    "sg:province":"MI",
    "sg:tags":[
        "commercial",
        "storage"
    ],
    "wof:name":"R & B Mini-Storage",
    "wof:placetype":"venue"
},
  "geometry": {"coordinates":[-84.59056,43.291652],"type":"Point"}
}