{
  "type": "Feature",
  "properties": {
    "iso:country":"US",
    "sg:address":"8840 48th Ave",
    "sg:city":"Hudsonville",
    "sg:classifiers":[
        {
            "category":"Building & Trades",
            "subcategory":"Landscaping Services",
            "type":"Services"
        }
    ],
    "sg:phone":"+1 616 669 4981",
    "sg:postcode":"49426",
    "sg:province":"MI",
    "sg:tags":[
        "landscape",
        "contractor"
    ],
    "wof:name":"Beachtree Gardens",
    "wof:placetype":"venue"
},
  "geometry": {"coordinates":[-85.903046,42.934235],"type":"Point"}
}