{
  "type": "Feature",
  "properties": {
    "iso:country":"US",
    "sg:address":"4736 Churchill Rd",
    "sg:city":"Leslie",
    "sg:classifiers":[
        {
            "category":"Building & Trades",
            "subcategory":"Landscaping Services",
            "type":"Services"
        }
    ],
    "sg:phone":"+1 517 589 9322",
    "sg:postcode":"49251",
    "sg:province":"MI",
    "sg:tags":[
        "lawn",
        "maintenance",
        "grounds"
    ],
    "wof:name":"Cort's Lawn & Landscape",
    "wof:placetype":"venue"
},
  "geometry": {"coordinates":[-84.44407200000001,42.444558],"type":"Point"}
}