{
  "type": "Feature",
  "properties": {
    "iso:country":"US",
    "sg:address":"3031 Green Meadow Dr",
    "sg:city":"Jenison",
    "sg:classifiers":[
        {
            "category":"Professional",
            "subcategory":"Management & Consulting",
            "type":"Services"
        }
    ],
    "sg:phone":"+1 616 669 8153",
    "sg:postcode":"49428",
    "sg:province":"MI",
    "sg:tags":[
        "public",
        "relations",
        "consult"
    ],
    "wof:name":"Option One Enterprises",
    "wof:placetype":"venue"
},
  "geometry": {"coordinates":[-85.857991,42.914113],"type":"Point"}
}