{
  "type": "Feature",
  "properties": {
    "iso:country":"US",
    "sg:address":"1175 Orange Blossom Ln",
    "sg:city":"Mount Morris",
    "sg:classifiers":[
        {
            "category":"Shopping",
            "subcategory":"Clothing, Apparel, & Fashions",
            "type":"Retail Goods"
        }
    ],
    "sg:phone":"+1 810 787 3421",
    "sg:postcode":"48458",
    "sg:province":"MI",
    "wof:name":"Divine Apparel",
    "wof:placetype":"venue"
},
  "geometry": {"coordinates":[-83.69978999999999,43.093186],"type":"Point"}
}