{
  "type": "Feature",
  "properties": {
    "iso:country":"US",
    "sg:address":"4151 Seminole St",
    "sg:city":"Detroit",
    "sg:classifiers":[
        {
            "category":"Education",
            "subcategory":"School",
            "type":"Public Place"
        }
    ],
    "sg:phone":"+1 313 571 3400",
    "sg:postcode":"48214",
    "sg:province":"MI",
    "wof:name":"Communities In Schools of Detroit Inc",
    "wof:placetype":"venue"
},
  "geometry": {"coordinates":[-83.00630200000001,42.3722],"type":"Point"}
}