{
  "type": "Feature",
  "properties": {
    "iso:country":"US",
    "sg:address":"4228 Greenwood Dr",
    "sg:city":"Benton Harbor",
    "sg:classifiers":[
        {
            "category":"Professional",
            "type":"Services"
        }
    ],
    "sg:phone":"+1 269 849 1672",
    "sg:postcode":"49022",
    "sg:province":"MI",
    "sg:tags":[
        "establishment"
    ],
    "wof:name":"Greenco",
    "wof:placetype":"venue"
},
  "geometry": {"coordinates":[-86.40503200000001,42.193293],"type":"Point"}
}