{
  "type": "Feature",
  "properties": {
    "iso:country":"US",
    "sg:address":"561 E Evelyn Ave",
    "sg:city":"Hazel Park",
    "sg:classifiers":[
        {
            "category":"Building & Trades",
            "subcategory":"Construction",
            "type":"Services"
        }
    ],
    "sg:phone":"+1 248 548 1132",
    "sg:postcode":"48030",
    "sg:province":"MI",
    "sg:tags":[
        "resurfacing",
        "floor",
        "laying",
        "refinishing",
        "contractor"
    ],
    "wof:name":"Russes Quality Floors",
    "wof:placetype":"venue"
},
  "geometry": {"coordinates":[-83.09831699999999,42.453296],"type":"Point"}
}