{
  "type": "Feature",
  "properties": {
    "iso:country":"US",
    "sg:address":"48 Apollo Ave",
    "sg:city":"Flushing",
    "sg:classifiers":[
        {
            "category":"Professional",
            "type":"Services"
        }
    ],
    "sg:phone":"+1 810 659 3876",
    "sg:postcode":"48433",
    "sg:province":"MI",
    "wof:name":"Aok Services",
    "wof:placetype":"venue"
},
  "geometry": {"coordinates":[-83.86057099999999,43.114785],"type":"Point"}
}