{
  "type": "Feature",
  "properties": {
    "iso:country":"US",
    "sg:address":"4100 Commerce Dr",
    "sg:city":"Flushing",
    "sg:classifiers":[
        {
            "category":"Social Services",
            "subcategory":"Job Training",
            "type":"Services"
        }
    ],
    "sg:phone":"+1 810 659 0062",
    "sg:postcode":"48433",
    "sg:province":"MI",
    "sg:tags":[
        "rehabilitation"
    ],
    "wof:name":"Freedom Work Opportunities",
    "wof:placetype":"venue"
},
  "geometry": {"coordinates":[-83.80904200000001,43.061472],"type":"Point"}
}