{
  "type": "Feature",
  "properties": {
    "iso:country":"US",
    "sg:address":"7650 Venture Ave NW",
    "sg:city":"Sparta",
    "sg:classifiers":[
        {
            "category":"Wholesale",
            "subcategory":"Machinery & Supplies",
            "type":"Manufacturing & Wholesale Goods"
        }
    ],
    "sg:phone":"+1 616 887 7739",
    "sg:postcode":"49345",
    "sg:province":"MI",
    "sg:tags":[
        "sprinkler"
    ],
    "wof:name":"Blaze Fire Protection",
    "wof:placetype":"venue"
},
  "geometry": {"coordinates":[-85.695002,43.102538],"type":"Point"}
}