{
  "type": "Feature",
  "properties": {
    "iso:country":"US",
    "sg:address":"2226 S Airport Rd W",
    "sg:city":"Traverse City",
    "sg:classifiers":[
        {
            "category":"Wholesale",
            "subcategory":"Stationery",
            "type":"Manufacturing & Wholesale Goods"
        }
    ],
    "sg:phone":"+1 231 932 9804",
    "sg:postcode":"49684",
    "sg:province":"MI",
    "sg:tags":[
        "mapping"
    ],
    "wof:name":"Advanced Mapping Technologies",
    "wof:placetype":"venue"
},
  "geometry": {"coordinates":[-85.620333,44.733324],"type":"Point"}
}