{
  "type": "Feature",
  "properties": {
    "iso:country":"US",
    "sg:address":"2051 Meek Dr NE",
    "sg:city":"Belmont",
    "sg:classifiers":[
        {
            "category":"Building & Trades",
            "subcategory":"Landscaping Services",
            "type":"Services"
        }
    ],
    "sg:phone":"+1 616 866 2731",
    "sg:postcode":"49306",
    "sg:province":"MI",
    "sg:tags":[
        "lawn",
        "maintenance",
        "grounds"
    ],
    "wof:name":"Lawn Ranger",
    "wof:placetype":"venue"
},
  "geometry": {"coordinates":[-85.616344,43.095265],"type":"Point"}
}