{
  "type": "Feature",
  "properties": {
    "iso:country":"US",
    "sg:address":"645 Hackett St",
    "sg:city":"Ionia",
    "sg:classifiers":[
        {
            "category":"Education",
            "subcategory":"School",
            "type":"Public Place"
        }
    ],
    "sg:phone":"+1 616 527 8018",
    "sg:postcode":"48846",
    "sg:province":"MI",
    "wof:name":"Emerson Elementary School",
    "wof:placetype":"venue"
},
  "geometry": {"coordinates":[-85.07296599999999,42.984456],"type":"Point"}
}