{
  "type": "Feature",
  "properties": {
    "iso:country":"US",
    "sg:address":"3585 Laureate Dr",
    "sg:city":"Holt",
    "sg:classifiers":[
        {
            "category":"Personal",
            "subcategory":"Beauty Salon",
            "type":"Services"
        }
    ],
    "sg:phone":"+1 517 694 4247",
    "sg:postcode":"48842",
    "sg:province":"MI",
    "sg:tags":[
        "shop"
    ],
    "wof:name":"Positive Image",
    "wof:placetype":"venue"
},
  "geometry": {"coordinates":[-84.48866,42.655252],"type":"Point"}
}