{
  "type": "Feature",
  "properties": {
    "iso:country":"US",
    "sg:address":"6375 Napier Rd",
    "sg:city":"Plymouth",
    "sg:classifiers":[
        {
            "category":"Building & Trades",
            "subcategory":"Construction",
            "type":"Services"
        }
    ],
    "sg:phone":"+1 734 414 0828",
    "sg:postcode":"48170",
    "sg:province":"MI",
    "sg:tags":[
        "interior",
        "design"
    ],
    "wof:name":"Precision Installation & Services",
    "wof:placetype":"venue"
},
  "geometry": {"coordinates":[-83.55555200000001,42.376191],"type":"Point"}
}