{
  "type": "Feature",
  "properties": {
    "iso:country":"US",
    "sg:address":"471 South Blvd E",
    "sg:city":"Pontiac",
    "sg:classifiers":[
        {
            "category":"Organizations",
            "subcategory":"Religious Organization",
            "type":"Services"
        }
    ],
    "sg:phone":"+1 248 332 8917",
    "sg:postcode":"48341",
    "sg:province":"MI",
    "sg:tags":[
        "church"
    ],
    "wof:name":"United Missionary Baptist Chr",
    "wof:placetype":"venue"
},
  "geometry": {"coordinates":[-83.263914,42.619837],"type":"Point"}
}