{
  "type": "Feature",
  "properties": {
    "iso:country":"US",
    "sg:address":"4080 24th Ave",
    "sg:city":"Fort Gratiot",
    "sg:classifiers":[
        {
            "category":"Autos & Motor Vehicles",
            "subcategory":"Automobile Sales",
            "type":"Retail Goods"
        }
    ],
    "sg:phone":"+1 810 385 4481",
    "sg:postcode":"48059",
    "sg:province":"MI",
    "sg:tags":[
        "car",
        "dealer"
    ],
    "wof:name":"Blue Water Chrysler Plymouth",
    "wof:placetype":"venue"
},
  "geometry": {"coordinates":[-82.455904,43.025813],"type":"Point"}
}