{
  "type": "Feature",
  "properties": {
    "iso:country":"US",
    "sg:address":"809 Welch Blvd",
    "sg:city":"Flint",
    "sg:classifiers":[
        {
            "category":"Shopping",
            "subcategory":"Department Store",
            "type":"Retail Goods"
        }
    ],
    "sg:phone":"+1 810 424 9522",
    "sg:postcode":"48504",
    "sg:province":"MI",
    "sg:tags":[
        "shop"
    ],
    "wof:name":"Welsh Dollar",
    "wof:placetype":"venue"
},
  "geometry": {"coordinates":[-83.715394,43.030748],"type":"Point"}
}