{
  "type": "Feature",
  "properties": {
    "iso:country":"US",
    "sg:address":"624 E Colby St",
    "sg:city":"Whitehall",
    "sg:classifiers":[
        {
            "category":"Autos & Motor Vehicles",
            "subcategory":"Fuel & Gas Station",
            "type":"Retail Goods"
        }
    ],
    "sg:phone":"+1 231 894 2618",
    "sg:postcode":"49461",
    "sg:province":"MI",
    "sg:tags":[
        "oil"
    ],
    "wof:name":"Mobil 1",
    "wof:placetype":"venue"
},
  "geometry": {"coordinates":[-86.33918799999999,43.409588],"type":"Point"}
}