{
  "type": "Feature",
  "properties": {
    "iso:country":"US",
    "sg:address":"6140 Dixie Hwy",
    "sg:city":"Clarkston",
    "sg:classifiers":[
        {
            "category":"Professional",
            "subcategory":"Lawyer & Legal Services",
            "type":"Services"
        }
    ],
    "sg:phone":"+1 248 623 7477",
    "sg:postcode":"48346",
    "sg:province":"MI",
    "wof:name":"Jay F Welter",
    "wof:placetype":"venue"
},
  "geometry": {"coordinates":[-83.406066,42.708302],"type":"Point"}
}