{
  "type": "Feature",
  "properties": {
    "iso:country":"US",
    "sg:address":"136 E Walled Lake Dr",
    "sg:city":"Walled Lake",
    "sg:classifiers":[
        {
            "category":"Restaurant",
            "type":"Food & Drink"
        }
    ],
    "sg:phone":"+1 248 669 1601",
    "sg:postcode":"48390",
    "sg:province":"MI",
    "wof:name":"Lake Plaza Sub",
    "wof:placetype":"venue"
},
  "geometry": {"coordinates":[-83.48448999999999,42.531461],"type":"Point"}
}