{
  "type": "Feature",
  "properties": {
    "iso:country":"US",
    "sg:address":"126 E Columbia Ave",
    "sg:city":"Battle Creek",
    "sg:classifiers":[
        {
            "category":"Insurance",
            "subcategory":"Insurance Agent",
            "type":"Services"
        }
    ],
    "sg:phone":"+1 269 660 2100",
    "sg:postcode":"49015",
    "sg:province":"MI",
    "wof:name":"Farm Bureau Ins",
    "wof:placetype":"venue"
},
  "geometry": {"coordinates":[-85.193425,42.298492],"type":"Point"}
}