{
  "type": "Feature",
  "properties": {
    "iso:country":"US",
    "sg:address":"14057 Cottonwood Ave",
    "sg:city":"Sand Lake",
    "sg:phone":"+1 616 636 8667",
    "sg:postcode":"49343",
    "sg:province":"MI",
    "sg:tags":[
        "farm",
        "grain",
        "cash"
    ],
    "wof:name":"Fred Patten",
    "wof:placetype":"venue"
},
  "geometry": {"coordinates":[-85.60220200000001,43.300834],"type":"Point"}
}