{
  "type": "Feature",
  "properties": {
    "iso:country":"US",
    "sg:address":"35 N Hawkins Rd",
    "sg:city":"Gladwin",
    "sg:classifiers":[
        {
            "category":"Retail",
            "subcategory":"Car Wash",
            "type":"Services"
        }
    ],
    "sg:phone":"+1 989 246 2270",
    "sg:postcode":"48624",
    "sg:province":"MI",
    "sg:tags":[
        "carwash"
    ],
    "wof:name":"Supreme Auto Detailing",
    "wof:placetype":"venue"
},
  "geometry": {"coordinates":[-84.446361,43.986186],"type":"Point"}
}