{
  "type": "Feature",
  "properties": {
    "iso:country":"US",
    "sg:address":"294 Dellwood Ave",
    "sg:city":"Pontiac",
    "sg:classifiers":[
        {
            "category":"Banks & Credit Unions",
            "subcategory":"Financial Services",
            "type":"Services"
        }
    ],
    "sg:phone":"+1 248 332 3324",
    "sg:postcode":"48341",
    "sg:province":"MI",
    "sg:tags":[
        "investor"
    ],
    "wof:name":"4 Rivers Investments",
    "wof:placetype":"venue"
},
  "geometry": {"coordinates":[-83.28092100000001,42.614634],"type":"Point"}
}