{
  "type": "Feature",
  "properties": {
    "iso:country":"US",
    "sg:address":"4350 Sylvania-Petersburg Rd",
    "sg:city":"Petersburg",
    "sg:classifiers":[
        {
            "category":"Freight",
            "type":"Transportation"
        }
    ],
    "sg:phone":"+1 734 279 2756",
    "sg:postcode":"49270",
    "sg:province":"MI",
    "sg:tags":[
        "trucking"
    ],
    "wof:name":"Robert Ignatowicz Excavating",
    "wof:placetype":"venue"
},
  "geometry": {"coordinates":[-83.710077,41.887282],"type":"Point"}
}