{
  "type": "Feature",
  "properties": {
    "iso:country":"US",
    "sg:address":"4608 E 9 Mile Rd",
    "sg:city":"Warren",
    "sg:classifiers":[
        {
            "category":"Restaurant",
            "type":"Food & Drink"
        }
    ],
    "sg:phone":"+1 586 757 3510",
    "sg:postcode":"48091",
    "sg:province":"MI",
    "wof:name":"Tubby's Famous Submarine Shop",
    "wof:placetype":"venue"
},
  "geometry": {"coordinates":[-83.058601,42.462101],"type":"Point"}
}