{
  "type": "Feature",
  "properties": {
    "iso:country":"US",
    "sg:address":"221 W Michigan Ave",
    "sg:city":"Marshall",
    "sg:classifiers":[
        {
            "category":"Professional",
            "subcategory":"Lawyer & Legal Services",
            "type":"Services"
        }
    ],
    "sg:phone":"+1 269 781 1099",
    "sg:postcode":"49068",
    "sg:province":"MI",
    "sg:tags":[
        "attorney"
    ],
    "wof:name":"Mark E WEBB Law Office",
    "wof:placetype":"venue"
},
  "geometry": {"coordinates":[-84.961444,42.27196],"type":"Point"}
}