{
  "type": "Feature",
  "properties": {
    "iso:country":"US",
    "sg:address":"7376 W Stanley Rd",
    "sg:city":"Flushing",
    "sg:classifiers":[
        {
            "category":"Organizations",
            "subcategory":"Community Association",
            "type":"Services"
        }
    ],
    "sg:phone":"+1 810 659 4898",
    "sg:postcode":"48433",
    "sg:province":"MI",
    "sg:tags":[
        "fraternal"
    ],
    "wof:name":"Independent Order Foresters",
    "wof:placetype":"venue"
},
  "geometry": {"coordinates":[-83.82706,43.103443],"type":"Point"}
}