{
  "type": "Feature",
  "properties": {
    "iso:country":"US",
    "sg:address":"3685 Cloverville Rd",
    "sg:city":"Fruitport",
    "sg:classifiers":[
        {
            "category":"Banks & Credit Unions",
            "subcategory":"Bank",
            "type":"Services"
        }
    ],
    "sg:phone":"+1 231 733 2360",
    "sg:postcode":"49415",
    "sg:province":"MI",
    "sg:tags":[
        "loan",
        "real estate"
    ],
    "wof:name":"Wells Fargo Home Mortgage",
    "wof:placetype":"venue"
},
  "geometry": {"coordinates":[-86.13628,43.188564],"type":"Point"}
}