{
  "type": "Feature",
  "properties": {
    "iso:country":"US",
    "sg:address":"6063 Fenton Rd",
    "sg:city":"Flint",
    "sg:classifiers":[
        {
            "category":"Retail",
            "subcategory":"Funeral Services",
            "type":"Services"
        }
    ],
    "sg:phone":"+1 877 537 4277",
    "sg:postcode":"48439",
    "sg:province":"MI",
    "sg:tags":[
        "director",
        "home",
        "cemetery"
    ],
    "sg:website":"www.sharpfuneralhomes.com",
    "wof:name":"Sharp Funeral Homes",
    "wof:placetype":"venue"
},
  "geometry": {"coordinates":[-83.69133600000001,42.942378],"type":"Point"}
}