{
  "type": "Feature",
  "properties": {
    "iso:country":"US",
    "sg:address":"8745 E Hersey Rd",
    "sg:city":"Evart",
    "sg:classifiers":[
        {
            "category":"Farming",
            "subcategory":"Dairy Farm",
            "type":"Manufacturing & Wholesale Goods"
        }
    ],
    "sg:phone":"+1 231 734 2852",
    "sg:postcode":"49631",
    "sg:province":"MI",
    "wof:name":"Custer Acres",
    "wof:placetype":"venue"
},
  "geometry": {"coordinates":[-85.253519,43.850005],"type":"Point"}
}