{
  "type": "Feature",
  "properties": {
    "iso:country":"US",
    "sg:address":"2550 E Oakley Park Rd Ste 200",
    "sg:city":"Commerce Township",
    "sg:classifiers":[
        {
            "category":"Home & Garden",
            "subcategory":"Carpets & Floor Coverings",
            "type":"Retail Goods"
        }
    ],
    "sg:phone":"+1 248 669 3737",
    "sg:postcode":"48390",
    "sg:province":"MI",
    "sg:tags":[
        "carpeting"
    ],
    "wof:name":"Imperial Floor Covering Inc",
    "wof:placetype":"venue"
},
  "geometry": {"coordinates":[-83.45410200000001,42.570202],"type":"Point"}
}