{
  "type": "Feature",
  "properties": {
    "iso:country":"US",
    "sg:address":"1520 N Lincoln Rd",
    "sg:city":"Escanaba",
    "sg:classifiers":[
        {
            "category":"Travel",
            "subcategory":"Hotels & Motels",
            "type":"Entertainment"
        }
    ],
    "sg:phone":"+1 906 786 3405",
    "sg:postcode":"49829",
    "sg:province":"MI",
    "wof:name":"Lencor Motel",
    "wof:placetype":"venue"
},
  "geometry": {"coordinates":[-87.07813,45.765805],"type":"Point"}
}