{
  "type": "Feature",
  "properties": {
    "iso:country":"US",
    "sg:address":"1290 Canada Rd",
    "sg:city":"Grant",
    "sg:classifiers":[
        {
            "category":"Home & Garden",
            "subcategory":"Building Materials",
            "type":"Retail Goods"
        }
    ],
    "sg:phone":"+1 231 834 8342",
    "sg:postcode":"49318",
    "sg:province":"MI",
    "sg:tags":[
        "glass",
        "window",
        "plate"
    ],
    "wof:name":"Master Glass Co",
    "wof:placetype":"venue"
},
  "geometry": {"coordinates":[-85.849974,43.222792],"type":"Point"}
}