{
  "type": "Feature",
  "properties": {
    "iso:country":"US",
    "sg:address":"2181 E Apple Ave",
    "sg:city":"Muskegon",
    "sg:classifiers":[
        {
            "category":"Retail",
            "subcategory":"Laundry & Dry Cleaning",
            "type":"Services"
        }
    ],
    "sg:phone":"+1 231 773 5339",
    "sg:postcode":"49442",
    "sg:province":"MI",
    "wof:name":"Archer Family Enterprise",
    "wof:placetype":"venue"
},
  "geometry": {"coordinates":[-86.189904,43.23414],"type":"Point"}
}