{
  "type": "Feature",
  "properties": {
    "iso:country":"US",
    "sg:address":"7903 US Hwy 2",
    "sg:city":"Rapid River",
    "sg:classifiers":[
        {
            "category":"Shopping",
            "subcategory":"Gifts & Souvenirs",
            "type":"Retail Goods"
        }
    ],
    "sg:phone":"+1 906 474 0035",
    "sg:postcode":"49878",
    "sg:province":"MI",
    "sg:tags":[
        "shop"
    ],
    "wof:name":"Willowood Station",
    "wof:placetype":"venue"
},
  "geometry": {"coordinates":[-86.966945,45.926537],"type":"Point"}
}