{
  "type": "Feature",
  "properties": {
    "iso:country":"US",
    "sg:address":"11049 W Corunna Rd",
    "sg:city":"Lennon",
    "sg:classifiers":[
        {
            "category":"Manufacturing",
            "subcategory":"Printing",
            "type":"Manufacturing & Wholesale Goods"
        }
    ],
    "sg:phone":"+1 810 621 4990",
    "sg:postcode":"48449",
    "sg:province":"MI",
    "sg:tags":[
        "printer"
    ],
    "sg:website":"www.fjgrafik.com",
    "wof:name":"F J Grafik Inc",
    "wof:placetype":"venue"
},
  "geometry": {"coordinates":[-83.89117299999999,43.000647],"type":"Point"}
}