{
  "type": "Feature",
  "properties": {
    "iso:country":"US",
    "sg:address":"2152 Malvina St",
    "sg:city":"Lincoln Park",
    "sg:classifiers":[
        {
            "category":"Building & Trades",
            "subcategory":"Construction",
            "type":"Services"
        }
    ],
    "sg:phone":"+1 313 386 3707",
    "sg:postcode":"48146",
    "sg:province":"MI",
    "sg:tags":[
        "house"
    ],
    "wof:name":"Martinez Remodeling Inc",
    "wof:placetype":"venue"
},
  "geometry": {"coordinates":[-83.20109100000001,42.237436],"type":"Point"}
}