{
  "type": "Feature",
  "properties": {
    "iso:country":"US",
    "sg:address":"545 Cheshire Dr NE",
    "sg:city":"Grand Rapids",
    "sg:classifiers":[
        {
            "category":"Personal",
            "type":"Services"
        }
    ],
    "sg:phone":"+1 616 365 9355",
    "sg:postcode":"49505",
    "sg:province":"MI",
    "sg:tags":[
        "therapist",
        "massage"
    ],
    "wof:name":"Cheshire Wellness",
    "wof:placetype":"venue"
},
  "geometry": {"coordinates":[-85.655128,43.002875],"type":"Point"}
}