{
  "type": "Feature",
  "properties": {
    "iso:country":"US",
    "sg:address":"438 Elder Rd",
    "sg:city":"Mancelona",
    "sg:classifiers":[
        {
            "category":"Manufacturing",
            "subcategory":"Motor Vehicles & Parts",
            "type":"Manufacturing & Wholesale Goods"
        }
    ],
    "sg:phone":"+1 231 587 9433",
    "sg:postcode":"49659",
    "sg:province":"MI",
    "sg:tags":[
        "automobile",
        "supply"
    ],
    "wof:name":"Dura Automotive Systems",
    "wof:placetype":"venue"
},
  "geometry": {"coordinates":[-85.086033,44.887648],"type":"Point"}
}