{
  "type": "Feature",
  "properties": {
    "iso:country":"US",
    "sg:address":"3632 Auburn Ave NE",
    "sg:city":"Grand Rapids",
    "sg:classifiers":[
        {
            "category":"Professional",
            "subcategory":"Business Services",
            "type":"Services"
        }
    ],
    "sg:phone":"+1 616 364 0778",
    "sg:postcode":"49525",
    "sg:province":"MI",
    "sg:tags":[
        "equipment",
        "industrial",
        "inspection"
    ],
    "wof:name":"Independent Mch Inspections",
    "wof:placetype":"venue"
},
  "geometry": {"coordinates":[-85.63770700000001,43.0303],"type":"Point"}
}