{
  "type": "Feature",
  "properties": {
    "iso:country":"US",
    "sg:address":"5171 Martin Rd",
    "sg:city":"Mussey",
    "sg:classifiers":[
        {
            "category":"Professional",
            "type":"Services"
        }
    ],
    "sg:phone":"+1 810 395 7555",
    "sg:postcode":"48014",
    "sg:province":"MI",
    "wof:name":"Michigan Hwy Hazard Recovery",
    "wof:placetype":"venue"
},
  "geometry": {"coordinates":[-82.969317,43.044475],"type":"Point"}
}