{
  "type": "Feature",
  "properties": {
    "iso:country":"US",
    "sg:address":"2093 Orchard Lake Rd",
    "sg:city":"West Bloomfield",
    "sg:classifiers":[
        {
            "category":"Recreation",
            "subcategory":"Amusement Park",
            "type":"Entertainment"
        }
    ],
    "sg:phone":"+1 248 335 1500",
    "sg:postcode":"48323",
    "sg:province":"MI",
    "sg:website":"www.recreationinc.com",
    "wof:name":"Recreation Inc",
    "wof:placetype":"venue"
},
  "geometry": {"coordinates":[-83.367203,42.5704],"type":"Point"}
}