{
  "type": "Feature",
  "properties": {
    "iso:country":"US",
    "sg:address":"609 N Main St",
    "sg:city":"Royal Oak",
    "sg:classifiers":[
        {
            "category":"Professional",
            "subcategory":"Business Services",
            "type":"Services"
        }
    ],
    "sg:phone":"+1 248 399 9133",
    "sg:postcode":"48067",
    "sg:province":"MI",
    "wof:name":"Krystal Enterprises Inc",
    "wof:placetype":"venue"
},
  "geometry": {"coordinates":[-83.14458,42.494475],"type":"Point"}
}