{
  "type": "Feature",
  "properties": {
    "iso:country":"US",
    "sg:address":"14975 Oxford Ct",
    "sg:city":"Southgate",
    "sg:classifiers":[
        {
            "category":"Building & Trades",
            "subcategory":"Cleaning & Sanitation",
            "type":"Services"
        }
    ],
    "sg:phone":"+1 734 282 8029",
    "sg:postcode":"48195",
    "sg:province":"MI",
    "sg:tags":[
        "maintenance"
    ],
    "wof:name":"Motor City Maintenance & Svc",
    "wof:placetype":"venue"
},
  "geometry": {"coordinates":[-83.20646000000001,42.217798],"type":"Point"}
}