{
  "type": "Feature",
  "properties": {
    "iso:country":"US",
    "sg:address":"770 West St",
    "sg:city":"Lapeer",
    "sg:classifiers":[
        {
            "category":"Bars & Pubs",
            "subcategory":"Sports Bar",
            "type":"Food & Drink"
        }
    ],
    "sg:menulink":"http://www.allmenus.com/mi/lapeer/251397-teds-sports-pub--grill/menu/",
    "sg:phone":"+1 810 667 0006",
    "sg:postcode":"48446",
    "sg:province":"MI",
    "sg:tags":[
        "american"
    ],
    "wof:name":"Ted's Sports Pub & Grill",
    "wof:placetype":"venue"
},
  "geometry": {"coordinates":[-83.321342,43.042087],"type":"Point"}
}