{
  "type": "Feature",
  "properties": {
    "iso:country":"US",
    "sg:address":"1409 Allen Dr",
    "sg:city":"Troy",
    "sg:classifiers":[
        {
            "category":"Wholesale",
            "subcategory":"Hardware",
            "type":"Manufacturing & Wholesale Goods"
        }
    ],
    "sg:phone":"+1 248 616 9200",
    "sg:postcode":"48083",
    "sg:province":"MI",
    "wof:name":"Liebert Corporation",
    "wof:placetype":"venue"
},
  "geometry": {"coordinates":[-83.124979,42.547386],"type":"Point"}
}