{
  "type": "Feature",
  "properties": {
    "iso:country":"US",
    "sg:address":"16455 Carter Rd",
    "sg:city":"Trenton",
    "sg:classifiers":[
        {
            "category":"Building & Trades",
            "subcategory":"Construction",
            "type":"Services"
        }
    ],
    "sg:phone":"+1 734 692 0120",
    "sg:postcode":"48183",
    "sg:province":"MI",
    "sg:tags":[
        "painter"
    ],
    "wof:name":"Scheffler Painting",
    "wof:placetype":"venue"
},
  "geometry": {"coordinates":[-83.219398,42.1479],"type":"Point"}
}