{
  "type": "Feature",
  "properties": {
    "iso:country":"US",
    "sg:address":"322 N Main St",
    "sg:city":"Cheboygan",
    "sg:classifiers":[
        {
            "category":"Restaurant",
            "type":"Food & Drink"
        }
    ],
    "sg:phone":"+1 231 627 2459",
    "sg:postcode":"49721",
    "sg:province":"MI",
    "wof:name":"Pappas' Restaurant",
    "wof:placetype":"venue"
},
  "geometry": {"coordinates":[-84.473421,45.64831],"type":"Point"}
}