{
  "type": "Feature",
  "properties": {
    "iso:country":"US",
    "sg:address":"5959 S Oak St",
    "sg:city":"Glen Arbor",
    "sg:classifiers":[
        {
            "category":"Building & Trades",
            "subcategory":"Cleaning & Sanitation",
            "type":"Services"
        }
    ],
    "sg:phone":"+1 231 334 3304",
    "sg:postcode":"49636",
    "sg:province":"MI",
    "sg:tags":[
        "house"
    ],
    "wof:name":"American Maid",
    "wof:placetype":"venue"
},
  "geometry": {"coordinates":[-85.98547499999999,44.895928],"type":"Point"}
}