{
  "type": "Feature",
  "properties": {
    "iso:country":"US",
    "sg:address":"51705 Sass Rd",
    "sg:city":"Chesterfield",
    "sg:classifiers":[
        {
            "category":"Personal",
            "subcategory":"Adult",
            "type":"Services"
        }
    ],
    "sg:phone":"+1 586 421 2094",
    "sg:postcode":"48047",
    "sg:province":"MI",
    "sg:tags":[
        "escort"
    ],
    "wof:name":"Azzure Adult Model & Escort",
    "wof:placetype":"venue"
},
  "geometry": {"coordinates":[-82.787488,42.681445],"type":"Point"}
}