{
  "type": "Feature",
  "properties": {
    "iso:country":"US",
    "sg:address":"50620 Jefferson Ave",
    "sg:city":"New Baltimore",
    "sg:classifiers":[
        {
            "category":"Real Estate",
            "subcategory":"Real Estate Operator",
            "type":"Services"
        }
    ],
    "sg:phone":"+1 586 725 7622",
    "sg:postcode":"48047",
    "sg:province":"MI",
    "sg:tags":[
        "apartment"
    ],
    "wof:name":"Anchor Bay Apartments",
    "wof:placetype":"venue"
},
  "geometry": {"coordinates":[-82.753477,42.67162],"type":"Point"}
}