{
  "type": "Feature",
  "properties": {
    "iso:country":"US",
    "sg:address":"530 Maxwell Rd",
    "sg:city":"Cheboygan",
    "sg:classifiers":[
        {
            "category":"Personal",
            "subcategory":"Beauty Salon",
            "type":"Services"
        }
    ],
    "sg:phone":"+1 231 627 5962",
    "sg:postcode":"49721",
    "sg:province":"MI",
    "sg:tags":[
        "shop"
    ],
    "wof:name":"Lissa's Family Hair Care",
    "wof:placetype":"venue"
},
  "geometry": {"coordinates":[-84.504552,45.60568],"type":"Point"}
}