{
  "type": "Feature",
  "properties": {
    "iso:country":"US",
    "sg:address":"810 N Spring St",
    "sg:city":"Saint Johns",
    "sg:classifiers":[
        {
            "category":"Building & Trades",
            "subcategory":"Construction",
            "type":"Services"
        }
    ],
    "sg:phone":"+1 989 224 2758",
    "sg:postcode":"48879",
    "sg:province":"MI",
    "sg:tags":[
        "contractor"
    ],
    "wof:name":"Cornwell Construction",
    "wof:placetype":"venue"
},
  "geometry": {"coordinates":[-84.556827,43.010473],"type":"Point"}
}