{
  "type": "Feature",
  "properties": {
    "iso:country":"US",
    "sg:address":"112 S Main St",
    "sg:city":"Frankenmuth",
    "sg:classifiers":[
        {
            "category":"Home & Garden",
            "subcategory":"Hardware",
            "type":"Retail Goods"
        }
    ],
    "sg:phone":"+1 989 652 6131",
    "sg:postcode":"48734",
    "sg:province":"MI",
    "wof:name":"Gill-Roy's Complete Hardware",
    "wof:placetype":"venue"
},
  "geometry": {"coordinates":[-83.738221,43.335638],"type":"Point"}
}