{
  "type": "Feature",
  "properties": {
    "iso:country":"US",
    "sg:address":"55611 Pontiac Trl",
    "sg:city":"New Hudson",
    "sg:classifiers":[
        {
            "category":"Wholesale",
            "subcategory":"Durable Goods & Equipment",
            "type":"Manufacturing & Wholesale Goods"
        }
    ],
    "sg:phone":"+1 248 486 3096",
    "sg:postcode":"48165",
    "sg:province":"MI",
    "sg:tags":[
        "importer"
    ],
    "wof:name":"Barton Beers",
    "wof:placetype":"venue"
},
  "geometry": {"coordinates":[-83.601403,42.520756],"type":"Point"}
}