{
  "type": "Feature",
  "properties": {
    "iso:country":"US",
    "sg:address":"12719 S West-Bay Shore Dr",
    "sg:city":"Traverse City",
    "sg:classifiers":[
        {
            "category":"Home & Garden",
            "subcategory":"Furniture",
            "type":"Retail Goods"
        }
    ],
    "sg:phone":"+1 231 922 7202",
    "sg:postcode":"49684",
    "sg:province":"MI",
    "sg:tags":[
        "cabinet"
    ],
    "wof:name":"Curtis Cabinet Co",
    "wof:placetype":"venue"
},
  "geometry": {"coordinates":[-85.63633299999999,44.794105],"type":"Point"}
}