{
  "type": "Feature",
  "properties": {
    "iso:country":"US",
    "sg:address":"234 Nickels Arc",
    "sg:city":"Ann Arbor",
    "sg:classifiers":[
        {
            "category":"Real Estate",
            "subcategory":"Architect",
            "type":"Services"
        }
    ],
    "sg:phone":"+1 734 665 0211",
    "sg:postcode":"48104",
    "sg:province":"MI",
    "sg:tags":[
        "architectural"
    ],
    "wof:name":"Lincoln Poley Architect",
    "wof:placetype":"venue"
},
  "geometry": {"coordinates":[-83.741449,42.278475],"type":"Point"}
}