{
  "type": "Feature",
  "properties": {
    "iso:country":"US",
    "sg:address":"12963 Grayfield St",
    "sg:city":"Detroit",
    "sg:classifiers":[
        {
            "category":"Social Services",
            "subcategory":"Adult Care",
            "type":"Services"
        }
    ],
    "sg:phone":"+1 313 531 5151",
    "sg:postcode":"48223",
    "sg:province":"MI",
    "sg:tags":[
        "foster",
        "provider"
    ],
    "wof:name":"Debra Daniels",
    "wof:placetype":"venue"
},
  "geometry": {"coordinates":[-83.26866699999999,42.382616],"type":"Point"}
}