{
  "type": "Feature",
  "properties": {
    "iso:country":"US",
    "sg:address":"2301 S Industrial Hwy",
    "sg:city":"Ann Arbor",
    "sg:classifiers":[
        {
            "category":"Home & Garden",
            "subcategory":"Carpets & Floor Coverings",
            "type":"Retail Goods"
        }
    ],
    "sg:phone":"+1 734 332 8682",
    "sg:postcode":"48104",
    "sg:province":"MI",
    "wof:name":"Floor Mart Inc",
    "wof:placetype":"venue"
},
  "geometry": {"coordinates":[-83.73287999999999,42.251524],"type":"Point"}
}