{
  "type": "Feature",
  "properties": {
    "iso:country":"US",
    "sg:address":"9245 Kercheval St",
    "sg:city":"Detroit",
    "sg:classifiers":[
        {
            "category":"Organizations",
            "subcategory":"Religious Organization",
            "type":"Services"
        }
    ],
    "sg:phone":"+1 313 822 0725",
    "sg:postcode":"48214",
    "sg:province":"MI",
    "wof:name":"Allen Temple C M E Church",
    "wof:placetype":"venue"
},
  "geometry": {"coordinates":[-82.988197,42.363201],"type":"Point"}
}