{
  "type": "Feature",
  "properties": {
    "iso:country":"US",
    "sg:address":"2661 N Swede Rd",
    "sg:city":"Midland",
    "sg:classifiers":[
        {
            "category":"Professional",
            "subcategory":"Business Services",
            "type":"Services"
        }
    ],
    "sg:phone":"+1 989 835 1095",
    "sg:postcode":"48642",
    "sg:province":"MI",
    "wof:name":"Senior Financial Strategies",
    "wof:placetype":"venue"
},
  "geometry": {"coordinates":[-84.20724,43.687116],"type":"Point"}
}