{
  "type": "Feature",
  "properties": {
    "iso:country":"US",
    "sg:address":"815 Kohler Rd",
    "sg:city":"Barton City",
    "sg:classifiers":[
        {
            "category":"Sports & Exercise",
            "subcategory":"Golf",
            "type":"Entertainment"
        }
    ],
    "sg:phone":"+1 989 736 9556",
    "sg:postcode":"48705",
    "sg:province":"MI",
    "sg:tags":[
        "course"
    ],
    "wof:name":"Back Nine Of BC Inc",
    "wof:placetype":"venue"
},
  "geometry": {"coordinates":[-83.676147,44.667158],"type":"Point"}
}