{
  "type": "Feature",
  "properties": {
    "iso:country":"US",
    "sg:address":"2353 62nd St",
    "sg:city":"Fennville",
    "sg:classifiers":[
        {
            "category":"Professional",
            "subcategory":"Management & Consulting",
            "type":"Services"
        }
    ],
    "sg:phone":"+1 269 561 5097",
    "sg:postcode":"49408",
    "sg:province":"MI",
    "sg:tags":[
        "retail",
        "direct",
        "sales"
    ],
    "wof:name":"Goose Country Soap Cakes",
    "wof:placetype":"venue"
},
  "geometry": {"coordinates":[-86.15241399999999,42.593899],"type":"Point"}
}