{
  "type": "Feature",
  "properties": {
    "iso:country":"US",
    "sg:address":"8501 Capital St",
    "sg:city":"Oak Park",
    "sg:classifiers":[
        {
            "category":"Professional",
            "subcategory":"Advertising",
            "type":"Services"
        }
    ],
    "sg:phone":"+1 248 398 8777",
    "sg:postcode":"48237",
    "sg:province":"MI",
    "sg:tags":[
        "designer",
        "display",
        "producer"
    ],
    "wof:name":"SCHLUETER Design & Exhibit Inc",
    "wof:placetype":"venue"
},
  "geometry": {"coordinates":[-83.161907,42.455507],"type":"Point"}
}