{
  "type": "Feature",
  "properties": {
    "iso:country":"US",
    "sg:address":"1122 Walnut St",
    "sg:city":"Ypsilanti",
    "sg:classifiers":[
        {
            "category":"Education",
            "subcategory":"School",
            "type":"Public Place"
        }
    ],
    "sg:phone":"+1 734 482 7070",
    "sg:postcode":"48198",
    "sg:province":"MI",
    "wof:name":"Calvary Christn Lower Academy",
    "wof:placetype":"venue"
},
  "geometry": {"coordinates":[-83.588235,42.248936],"type":"Point"}
}