{
  "type": "Feature",
  "properties": {
    "iso:country":"US",
    "sg:address":"123 S Washington St",
    "sg:city":"Owosso",
    "sg:classifiers":[
        {
            "category":"Social Services",
            "type":"Services"
        }
    ],
    "sg:phone":"+1 989 723 0330",
    "sg:postcode":"48867",
    "sg:province":"MI",
    "sg:tags":[
        "counseling"
    ],
    "wof:name":"Trinity Counseling Svc",
    "wof:placetype":"venue"
},
  "geometry": {"coordinates":[-84.170571,42.997306],"type":"Point"}
}