{
  "type": "Feature",
  "properties": {
    "iso:country":"US",
    "sg:address":"1344 Nita",
    "sg:city":"Pinckney",
    "sg:classifiers":[
        {
            "category":"Health Services",
            "subcategory":"Doctor",
            "type":"Services"
        }
    ],
    "sg:phone":"+1 734 878 2519",
    "sg:postcode":"48169",
    "sg:province":"MI",
    "sg:tags":[
        "medical"
    ],
    "wof:name":"Clinical Healing Inc",
    "wof:placetype":"venue"
},
  "geometry": {"coordinates":[-83.91555200000001,42.428277],"type":"Point"}
}