{
  "type": "Feature",
  "properties": {
    "iso:country":"US",
    "sg:address":"777 Goguac St W",
    "sg:city":"Battle Creek",
    "sg:classifiers":[
        {
            "category":"Professional",
            "subcategory":"Accounting & Tax Preparation",
            "type":"Services"
        }
    ],
    "sg:phone":"+1 269 962 2524",
    "sg:postcode":"49015",
    "sg:province":"MI",
    "sg:tags":[
        "accountant"
    ],
    "wof:name":"Carol Harms Accounting & Tax",
    "wof:placetype":"venue"
},
  "geometry": {"coordinates":[-85.219196,42.312011],"type":"Point"}
}