{
  "type": "Feature",
  "properties": {
    "iso:country":"US",
    "sg:address":"11785 Sparta Ave NW",
    "sg:city":"Sparta",
    "sg:classifiers":[
        {
            "category":"Building & Trades",
            "subcategory":"Construction",
            "type":"Services"
        }
    ],
    "sg:phone":"+1 616 887 7998",
    "sg:postcode":"49345",
    "sg:province":"MI",
    "sg:tags":[
        "hanging",
        "contractor"
    ],
    "wof:name":"Wallpapering Plus",
    "wof:placetype":"venue"
},
  "geometry": {"coordinates":[-85.710572,43.176599],"type":"Point"}
}