{
  "type": "Feature",
  "properties": {
    "iso:country":"US",
    "sg:address":"2103 E Reid Rd",
    "sg:city":"Grand Blanc",
    "sg:classifiers":[
        {
            "category":"Education",
            "subcategory":"School",
            "type":"Public Place"
        }
    ],
    "sg:phone":"+1 810 591 7121",
    "sg:postcode":"48439",
    "sg:province":"MI",
    "sg:tags":[
        "high",
        "middle",
        "elementary"
    ],
    "wof:name":"Grand Blanc Community Schools",
    "wof:placetype":"venue"
},
  "geometry": {"coordinates":[-83.668025,42.929879],"type":"Point"}
}