{
  "type": "Feature",
  "properties": {
    "iso:country":"US",
    "sg:address":"2050 Camelot Rd",
    "sg:city":"Ann Arbor",
    "sg:classifiers":[
        {
            "category":"Professional",
            "subcategory":"Management & Consulting",
            "type":"Services"
        }
    ],
    "sg:phone":"+1 734 668 7842",
    "sg:postcode":"48104",
    "sg:province":"MI",
    "sg:tags":[
        "business"
    ],
    "wof:name":"J C W Consulting",
    "wof:placetype":"venue"
},
  "geometry": {"coordinates":[-83.717433,42.253788],"type":"Point"}
}