{
  "type": "Feature",
  "properties": {
    "iso:country":"US",
    "sg:address":"28726 Grand River Ave",
    "sg:city":"Farmington Hills",
    "sg:classifiers":[
        {
            "category":"Fast Food",
            "type":"Food & Drink"
        }
    ],
    "sg:phone":"+1 248 888 9077",
    "sg:postcode":"48336",
    "sg:province":"MI",
    "sg:tags":[
        "burger"
    ],
    "wof:name":"King Kong Burgers & Chicken",
    "wof:placetype":"venue"
},
  "geometry": {"coordinates":[-83.32995200000001,42.445746],"type":"Point"}
}