{
  "type": "Feature",
  "properties": {
    "iso:country":"US",
    "sg:address":"8946 Cherry Ave",
    "sg:city":"Rapid City",
    "sg:classifiers":[
        {
            "category":"Building & Trades",
            "subcategory":"Construction",
            "type":"Services"
        }
    ],
    "sg:phone":"+1 231 264 9313",
    "sg:postcode":"49676",
    "sg:province":"MI",
    "sg:tags":[
        "contractor"
    ],
    "wof:name":"Charles Coy Masonry",
    "wof:placetype":"venue"
},
  "geometry": {"coordinates":[-85.350089,44.901585],"type":"Point"}
}