{
  "type": "Feature",
  "properties": {
    "iso:country":"US",
    "sg:address":"32800 Groesbeck Hwy",
    "sg:city":"Fraser",
    "sg:classifiers":[
        {
            "category":"Home & Garden",
            "subcategory":"Building Materials",
            "type":"Retail Goods"
        }
    ],
    "sg:phone":"+1 586 296 6500",
    "sg:postcode":"48026",
    "sg:province":"MI",
    "sg:tags":[
        "roofing"
    ],
    "sg:website":"www.allied.com",
    "wof:name":"Allied Building Products Corp",
    "wof:placetype":"venue"
},
  "geometry": {"coordinates":[-82.937186,42.535328],"type":"Point"}
}