{
  "type": "Feature",
  "properties": {
    "iso:country":"US",
    "sg:address":"15212 Howard City Edmore Rd",
    "sg:city":"Howard City",
    "sg:classifiers":[
        {
            "category":"Government",
            "subcategory":"Office",
            "type":"Public Place"
        }
    ],
    "sg:phone":"+1 231 762 4555",
    "sg:postcode":"49329",
    "sg:province":"MI",
    "sg:tags":[
        "village"
    ],
    "wof:name":"Winfield Twp Office",
    "wof:placetype":"venue"
},
  "geometry": {"coordinates":[-85.38531,43.431774],"type":"Point"}
}