{
  "type": "Feature",
  "properties": {
    "iso:country":"US",
    "sg:address":"110 S Washington St",
    "sg:city":"Oxford",
    "sg:classifiers":[
        {
            "category":"Real Estate",
            "subcategory":"Real Estate Services",
            "type":"Services"
        }
    ],
    "sg:phone":"+1 248 969 1430",
    "sg:postcode":"48371",
    "sg:province":"MI",
    "sg:tags":[
        "company",
        "title"
    ],
    "wof:name":"First American Title",
    "wof:placetype":"venue"
},
  "geometry": {"coordinates":[-83.262068,42.821532],"type":"Point"}
}