{
  "type": "Feature",
  "properties": {
    "iso:country":"US",
    "sg:address":"141 E Grand River Ave",
    "sg:city":"Fowlerville",
    "sg:classifiers":[
        {
            "category":"Bars & Pubs",
            "type":"Food & Drink"
        }
    ],
    "sg:phone":"+1 517 223 8413",
    "sg:postcode":"48836",
    "sg:province":"MI",
    "wof:name":"Bloated Goat Saloon",
    "wof:placetype":"venue"
},
  "geometry": {"coordinates":[-84.07283200000001,42.660747],"type":"Point"}
}