{
  "type": "Feature",
  "properties": {
    "iso:country":"US",
    "sg:address":"17043 Kercheval St",
    "sg:city":"Grosse Pointe",
    "sg:classifiers":[
        {
            "category":"Coffee & Tea",
            "type":"Food & Drink"
        }
    ],
    "sg:phone":"+1 313 417 9247",
    "sg:postcode":"48230",
    "sg:province":"MI",
    "wof:name":"Caribou Coffee",
    "wof:placetype":"venue"
},
  "geometry": {"coordinates":[-82.9161,42.390301],"type":"Point"}
}