{
  "type": "Feature",
  "properties": {
    "iso:country":"US",
    "sg:address":"12090 Kentucky St",
    "sg:city":"Detroit",
    "sg:classifiers":[
        {
            "category":"Personal",
            "subcategory":"Beauty Salon",
            "type":"Services"
        }
    ],
    "sg:phone":"+1 313 834 1499",
    "sg:postcode":"48204",
    "sg:province":"MI",
    "sg:tags":[
        "shop"
    ],
    "wof:name":"Vees Salon & Hair Accessories",
    "wof:placetype":"venue"
},
  "geometry": {"coordinates":[-83.157659,42.37817],"type":"Point"}
}