{
  "type": "Feature",
  "properties": {
    "iso:country":"US",
    "sg:address":"202 Clinton St",
    "sg:city":"Petoskey",
    "sg:classifiers":[
        {
            "category":"Health Services",
            "subcategory":"Hospital",
            "type":"Services"
        }
    ],
    "sg:phone":"+1 231 487 0781",
    "sg:postcode":"49770",
    "sg:province":"MI",
    "sg:tags":[
        "mental"
    ],
    "wof:name":"Lisa D Irish",
    "wof:placetype":"venue"
},
  "geometry": {"coordinates":[-84.94976800000001,45.375853],"type":"Point"}
}