{
  "type": "Feature",
  "properties": {
    "iso:country":"US",
    "sg:address":"1858 7th St",
    "sg:city":"Wyandotte",
    "sg:classifiers":[
        {
            "category":"Retail",
            "subcategory":"Repair Shop",
            "type":"Services"
        }
    ],
    "sg:phone":"+1 734 284 1411",
    "sg:postcode":"48192",
    "sg:province":"MI",
    "sg:tags":[
        "refrigeration"
    ],
    "wof:name":"Johns Refrigeration",
    "wof:placetype":"venue"
},
  "geometry": {"coordinates":[-83.160455,42.214462],"type":"Point"}
}