{
  "type": "Feature",
  "properties": {
    "iso:country":"US",
    "sg:address":"35607 Churchill St",
    "sg:city":"Richmond",
    "sg:classifiers":[
        {
            "category":"Professional",
            "subcategory":"Business Services",
            "type":"Services"
        }
    ],
    "sg:phone":"+1 586 727 7819",
    "sg:postcode":"48062",
    "sg:province":"MI",
    "wof:name":"Foster Design",
    "wof:placetype":"venue"
},
  "geometry": {"coordinates":[-82.758718,42.813421],"type":"Point"}
}