{
  "type": "Feature",
  "properties": {
    "iso:country":"US",
    "sg:address":"216 S Main St",
    "sg:city":"Ishpeming",
    "sg:classifiers":[
        {
            "category":"Social Services",
            "type":"Services"
        }
    ],
    "sg:phone":"+1 906 486 8186",
    "sg:postcode":"49849",
    "sg:province":"MI",
    "sg:tags":[
        "counseling"
    ],
    "wof:name":"Harbor Counseling Svc",
    "wof:placetype":"venue"
},
  "geometry": {"coordinates":[-87.668882,46.489264],"type":"Point"}
}