{
  "type": "Feature",
  "properties": {
    "iso:country":"US",
    "sg:address":"3871 Andover Ave",
    "sg:city":"Auburn Hills",
    "sg:classifiers":[
        {
            "category":"Professional",
            "subcategory":"Management & Consulting",
            "type":"Services"
        }
    ],
    "sg:phone":"+1 248 844 9780",
    "sg:postcode":"48326",
    "sg:province":"MI",
    "sg:tags":[
        "consultant"
    ],
    "wof:name":"Sustain A Build Consulting",
    "wof:placetype":"venue"
},
  "geometry": {"coordinates":[-83.213131,42.640101],"type":"Point"}
}