{
  "type": "Feature",
  "properties": {
    "iso:country":"US",
    "sg:address":"27575 Spring Valley Dr",
    "sg:city":"Farmington",
    "sg:classifiers":[
        {
            "category":"Professional",
            "subcategory":"Business Services",
            "type":"Services"
        }
    ],
    "sg:phone":"+1 248 442 1454",
    "sg:postcode":"48336",
    "sg:province":"MI",
    "wof:name":"Gearig Enterprises Inc",
    "wof:placetype":"venue"
},
  "geometry": {"coordinates":[-83.320711,42.460794],"type":"Point"}
}