{
  "type": "Feature",
  "properties": {
    "iso:country":"US",
    "sg:address":"24550 N River Rd",
    "sg:city":"Mt Clemens",
    "sg:classifiers":[
        {
            "category":"Professional",
            "subcategory":"Business Services",
            "type":"Services"
        }
    ],
    "sg:phone":"+1 586 468 4610",
    "sg:postcode":"48043",
    "sg:province":"MI",
    "sg:website":"www.trutechsystems.com",
    "wof:name":"Tru Tech Systems",
    "wof:placetype":"venue"
},
  "geometry": {"coordinates":[-82.86008699999999,42.592638],"type":"Point"}
}