{
  "type": "Feature",
  "properties": {
    "iso:country":"US",
    "sg:address":"5535 Keyes Dr",
    "sg:city":"Kalamazoo",
    "sg:classifiers":[
        {
            "category":"Education",
            "subcategory":"School",
            "type":"Public Place"
        }
    ],
    "sg:phone":"+1 269 488 1400",
    "sg:postcode":"49004",
    "sg:province":"MI",
    "wof:name":"North Elementary School",
    "wof:placetype":"venue"
},
  "geometry": {"coordinates":[-85.560166,42.339931],"type":"Point"}
}