{
  "type": "Feature",
  "properties": {
    "iso:country":"US",
    "sg:address":"2089 Wieneke Rd",
    "sg:city":"Saginaw",
    "sg:classifiers":[
        {
            "category":"Organizations",
            "subcategory":"Professional Association",
            "type":"Services"
        }
    ],
    "sg:phone":"+1 989 799 1212",
    "sg:postcode":"48603",
    "sg:province":"MI",
    "wof:name":"Saginaw Township Business Assn",
    "wof:placetype":"venue"
},
  "geometry": {"coordinates":[-84.029678,43.440469],"type":"Point"}
}