{
  "type": "Feature",
  "properties": {
    "iso:country":"US",
    "sg:address":"469 S Haven St",
    "sg:city":"South Haven",
    "sg:classifiers":[
        {
            "category":"Autos & Motor Vehicles",
            "subcategory":"Fuel & Gas Station",
            "type":"Retail Goods"
        }
    ],
    "sg:phone":"+1 269 637 8983",
    "sg:postcode":"49090",
    "sg:province":"MI",
    "sg:tags":[
        "oil"
    ],
    "wof:name":"Tucker's Shell & Food Mart",
    "wof:placetype":"venue"
},
  "geometry": {"coordinates":[-86.27485299999999,42.396534],"type":"Point"}
}