{
  "type": "Feature",
  "properties": {
    "iso:country":"US",
    "sg:address":"13017 Buno Rd",
    "sg:city":"Milford",
    "sg:classifiers":[
        {
            "category":"Mining & Drilling",
            "type":"Manufacturing & Wholesale Goods"
        }
    ],
    "sg:phone":"+1 248 685 1853",
    "sg:postcode":"48380",
    "sg:province":"MI",
    "sg:tags":[
        "construction"
    ],
    "wof:name":"Butler Mill Service Company",
    "wof:placetype":"venue"
},
  "geometry": {"coordinates":[-83.683007,42.547463],"type":"Point"}
}