{
  "type": "Feature",
  "properties": {
    "iso:country":"US",
    "sg:address":"3244 Bridlewood Dr",
    "sg:city":"Rochester",
    "sg:classifiers":[
        {
            "category":"Real Estate",
            "subcategory":"Real Estate Operator",
            "type":"Services"
        }
    ],
    "sg:phone":"+1 248 371 0071",
    "sg:postcode":"48306",
    "sg:province":"MI",
    "sg:tags":[
        "building",
        "nonresidential"
    ],
    "wof:name":"Properous Properties",
    "wof:placetype":"venue"
},
  "geometry": {"coordinates":[-83.200988,42.727755],"type":"Point"}
}