{
  "type": "Feature",
  "properties": {
    "iso:country":"US",
    "sg:address":"32155 N River Rd",
    "sg:city":"Harrison Twp",
    "sg:classifiers":[
        {
            "category":"Recreation",
            "subcategory":"Marina",
            "type":"Entertainment"
        }
    ],
    "sg:phone":"+1 586 463 6150",
    "sg:postcode":"48045",
    "sg:province":"MI",
    "sg:tags":[
        "storage",
        "boat"
    ],
    "wof:name":"C & N Marine Boat Transport",
    "wof:placetype":"venue"
},
  "geometry": {"coordinates":[-82.778144,42.595861],"type":"Point"}
}