{
  "type": "Feature",
  "properties": {
    "iso:country":"US",
    "sg:address":"1650 S Saginaw St",
    "sg:city":"Flint",
    "sg:classifiers":[
        {
            "category":"Autos & Motor Vehicles",
            "subcategory":"Automobile Sales",
            "type":"Retail Goods"
        }
    ],
    "sg:phone":"+1 810 767 9653",
    "sg:postcode":"48503",
    "sg:province":"MI",
    "sg:tags":[
        "car"
    ],
    "wof:name":"Newman Motor Sales",
    "wof:placetype":"venue"
},
  "geometry": {"coordinates":[-83.680965,43.006088],"type":"Point"}
}