{
  "type": "Feature",
  "properties": {
    "iso:country":"US",
    "sg:address":"9479 Riley St",
    "sg:city":"Zeeland",
    "sg:classifiers":[
        {
            "category":"Personal",
            "subcategory":"Tanning Parlor",
            "type":"Services"
        }
    ],
    "sg:phone":"+1 616 931 9909",
    "sg:postcode":"49464",
    "sg:province":"MI",
    "sg:tags":[
        "salon"
    ],
    "wof:name":"Axis Tanning",
    "wof:placetype":"venue"
},
  "geometry": {"coordinates":[-86.01621400000001,42.826966],"type":"Point"}
}