{
  "type": "Feature",
  "properties": {
    "iso:country":"US",
    "sg:address":"20913 Washington St",
    "sg:city":"Roseville",
    "sg:classifiers":[
        {
            "category":"Professional",
            "type":"Services"
        }
    ],
    "sg:phone":"+1 586 775 9530",
    "sg:postcode":"48066",
    "sg:province":"MI",
    "wof:name":"Personal Expressions",
    "wof:placetype":"venue"
},
  "geometry": {"coordinates":[-82.904644,42.513997],"type":"Point"}
}