{
  "type": "Feature",
  "properties": {
    "iso:country":"US",
    "sg:address":"1900 Westwood Dr",
    "sg:city":"Angola",
    "sg:classifiers":[
        {
            "category":"Organizations",
            "subcategory":"Labor Organization",
            "type":"Services"
        }
    ],
    "sg:phone":"+1 260 665 1990",
    "sg:postcode":"46703",
    "sg:province":"MI",
    "wof:name":"International Union",
    "wof:placetype":"venue"
},
  "geometry": {"coordinates":[-85.027928,41.636151],"type":"Point"}
}