{
  "type": "Feature",
  "properties": {
    "iso:country":"US",
    "sg:address":"46 Mill St",
    "sg:city":"Ortonville",
    "sg:classifiers":[
        {
            "category":"Personal",
            "subcategory":"Beauty Salon",
            "type":"Services"
        }
    ],
    "sg:phone":"+1 248 627 2030",
    "sg:postcode":"48462",
    "sg:province":"MI",
    "sg:tags":[
        "shop"
    ],
    "wof:name":"First Impressions Hair Salon",
    "wof:placetype":"venue"
},
  "geometry": {"coordinates":[-83.452286,42.85272],"type":"Point"}
}