{
  "type": "Feature",
  "properties": {
    "iso:country":"US",
    "sg:address":"32 S Charles St",
    "sg:city":"White Cloud",
    "sg:classifiers":[
        {
            "category":"Health Services",
            "subcategory":"Chiropractor",
            "type":"Services"
        }
    ],
    "sg:phone":"+1 231 689 6277",
    "sg:postcode":"49349",
    "sg:province":"MI",
    "wof:name":"White Cloud Chiro Life Ctr",
    "wof:placetype":"venue"
},
  "geometry": {"coordinates":[-85.77175699999999,43.553521],"type":"Point"}
}