{
  "type": "Feature",
  "properties": {
    "iso:country":"US",
    "sg:address":"5502 Main St",
    "sg:city":"Lexington",
    "sg:classifiers":[
        {
            "category":"Restaurant",
            "type":"Food & Drink"
        }
    ],
    "sg:phone":"+1 810 359 7201",
    "sg:postcode":"48450",
    "sg:province":"MI",
    "wof:name":"Cadillac House",
    "wof:placetype":"venue"
},
  "geometry": {"coordinates":[-82.531082,43.268268],"type":"Point"}
}