{
  "type": "Feature",
  "properties": {
    "iso:country":"US",
    "sg:address":"13206 Fagan Rd",
    "sg:city":"Holly",
    "sg:classifiers":[
        {
            "category":"Building & Trades",
            "subcategory":"Construction",
            "type":"Services"
        }
    ],
    "sg:phone":"+1 248 634 2788",
    "sg:postcode":"48442",
    "sg:province":"MI",
    "sg:tags":[
        "contractor"
    ],
    "wof:name":"Dt Services & Aqua Blast",
    "wof:placetype":"venue"
},
  "geometry": {"coordinates":[-83.609756,42.831118],"type":"Point"}
}