{
  "type": "Feature",
  "properties": {
    "iso:country":"US",
    "sg:address":"51355 Glenwood Rd",
    "sg:city":"Dowagiac",
    "sg:classifiers":[
        {
            "category":"Education",
            "subcategory":"School",
            "type":"Public Place"
        }
    ],
    "sg:phone":"+1 269 782 2879",
    "sg:postcode":"49047",
    "sg:province":"MI",
    "wof:name":"Glenwood Union SDA School",
    "wof:placetype":"venue"
},
  "geometry": {"coordinates":[-86.030727,42.050846],"type":"Point"}
}