{
  "type": "Feature",
  "properties": {
    "iso:country":"US",
    "sg:address":"4345 Sawkaw Dr NE",
    "sg:city":"Grand Rapids",
    "sg:classifiers":[
        {
            "category":"Wholesale",
            "subcategory":"Electrical",
            "type":"Manufacturing & Wholesale Goods"
        }
    ],
    "sg:phone":"+1 616 364 8373",
    "sg:postcode":"49525",
    "sg:province":"MI",
    "sg:tags":[
        "repair",
        "communication",
        "equipment",
        "computer",
        "facsimile",
        "copying"
    ],
    "wof:name":"Classic Communications Inc",
    "wof:placetype":"venue"
},
  "geometry": {"coordinates":[-85.604542,43.041132],"type":"Point"}
}