{
  "type": "Feature",
  "properties": {
    "iso:country":"US",
    "sg:address":"1769 S Cedar St",
    "sg:city":"Imlay City",
    "sg:classifiers":[
        {
            "category":"Health Services",
            "subcategory":"Health Practitioner",
            "type":"Services"
        }
    ],
    "sg:phone":"+1 810 724 0421",
    "sg:postcode":"48444",
    "sg:province":"MI",
    "sg:tags":[
        "therapist",
        "physical"
    ],
    "wof:name":"Thibodeau Physical Therapy",
    "wof:placetype":"venue"
},
  "geometry": {"coordinates":[-83.071702,43.013677],"type":"Point"}
}