{
  "type": "Feature",
  "properties": {
    "iso:country":"US",
    "sg:address":"1301 Imlay City Rd",
    "sg:city":"Lapeer",
    "sg:classifiers":[
        {
            "category":"Autos & Motor Vehicles",
            "subcategory":"Automobile Sales",
            "type":"Retail Goods"
        }
    ],
    "sg:phone":"+1 810 667 6710",
    "sg:postcode":"48446",
    "sg:province":"MI",
    "sg:tags":[
        "car",
        "dealer"
    ],
    "wof:name":"Thompson Motors Inc",
    "wof:placetype":"venue"
},
  "geometry": {"coordinates":[-83.286975,43.047233],"type":"Point"}
}