{
  "type": "Feature",
  "properties": {
    "iso:country":"US",
    "sg:address":"9393 Elton Hwy",
    "sg:city":"Tipton",
    "sg:classifiers":[
        {
            "category":"Manufacturing",
            "subcategory":"Metals",
            "type":"Manufacturing & Wholesale Goods"
        }
    ],
    "sg:phone":"+1 517 431 2173",
    "sg:postcode":"49287",
    "sg:province":"MI",
    "sg:tags":[
        "post",
        "fitting",
        "fence"
    ],
    "wof:name":"Dawn To Dusk Cedar Products",
    "wof:placetype":"venue"
},
  "geometry": {"coordinates":[-84.10309100000001,42.016547],"type":"Point"}
}