{
  "type": "Feature",
  "properties": {
    "iso:country":"US",
    "sg:address":"3924 Pine Grove Ave",
    "sg:city":"Fort Gratiot",
    "sg:classifiers":[
        {
            "category":"Wholesale",
            "subcategory":"Motor Vehicles",
            "type":"Manufacturing & Wholesale Goods"
        }
    ],
    "sg:phone":"+1 810 966 4900",
    "sg:postcode":"48059",
    "sg:province":"MI",
    "sg:tags":[
        "repair"
    ],
    "wof:name":"Taylor Made V-Twins",
    "wof:placetype":"venue"
},
  "geometry": {"coordinates":[-82.467674,43.029969],"type":"Point"}
}