{
  "type": "Feature",
  "properties": {
    "iso:country":"US",
    "sg:address":"601 Walnut Ln",
    "sg:city":"Union City",
    "sg:classifiers":[
        {
            "category":"Education",
            "subcategory":"School",
            "type":"Public Place"
        }
    ],
    "sg:phone":"+1 517 741 9405",
    "sg:postcode":"49094",
    "sg:province":"MI",
    "wof:name":"Project First Step",
    "wof:placetype":"venue"
},
  "geometry": {"coordinates":[-85.142933,42.070481],"type":"Point"}
}