{
  "type": "Feature",
  "properties": {
    "iso:country":"US",
    "sg:address":"329 Water St",
    "sg:city":"Saugatuck",
    "sg:classifiers":[
        {
            "category":"Restaurant",
            "type":"Food & Drink"
        }
    ],
    "sg:phone":"+1 269 857 2012",
    "sg:postcode":"49453",
    "sg:province":"MI",
    "wof:name":"Comfort Cafe",
    "wof:placetype":"venue"
},
  "geometry": {"coordinates":[-86.20531699999999,42.657225],"type":"Point"}
}