{
  "type": "Feature",
  "properties": {
    "iso:country":"US",
    "sg:address":"1100 Bridge St",
    "sg:city":"Charlevoix",
    "sg:classifiers":[
        {
            "category":"Retail",
            "subcategory":"Auto Repair",
            "type":"Services"
        }
    ],
    "sg:phone":"+1 231 547 7450",
    "sg:postcode":"49720",
    "sg:province":"MI",
    "sg:tags":[
        "general"
    ],
    "wof:name":"Allstate",
    "wof:placetype":"venue"
},
  "geometry": {"coordinates":[-85.25872200000001,45.311609],"type":"Point"}
}