{
  "type": "Feature",
  "properties": {
    "iso:country":"US",
    "sg:address":"1035 Long Lake Dr",
    "sg:city":"Brighton",
    "sg:classifiers":[
        {
            "category":"Real Estate",
            "subcategory":"Real Estate Operator",
            "type":"Services"
        }
    ],
    "sg:phone":"+1 810 632 4502",
    "sg:postcode":"48114",
    "sg:province":"MI",
    "sg:tags":[
        "property",
        "lessor"
    ],
    "wof:name":"Light Associates Inc",
    "wof:placetype":"venue"
},
  "geometry": {"coordinates":[-83.74279300000001,42.618514],"type":"Point"}
}