{
  "type": "Feature",
  "properties": {
    "iso:country":"US",
    "sg:address":"1126 Pinehurst Blvd",
    "sg:city":"Mount Morris",
    "sg:classifiers":[
        {
            "category":"Social Services",
            "subcategory":"Child Care",
            "type":"Services"
        }
    ],
    "sg:phone":"+1 810 686 5739",
    "sg:postcode":"48458",
    "sg:province":"MI",
    "sg:tags":[
        "day"
    ],
    "wof:name":"Creation Crnr Christn Day Care",
    "wof:placetype":"venue"
},
  "geometry": {"coordinates":[-83.70043800000001,43.128325],"type":"Point"}
}