{
  "type": "Feature",
  "properties": {
    "iso:country":"US",
    "sg:address":"68 S 160th Ave",
    "sg:city":"Holland",
    "sg:classifiers":[
        {
            "category":"Retail",
            "subcategory":"Repair Shop",
            "type":"Services"
        }
    ],
    "sg:phone":"+1 616 399 6941",
    "sg:postcode":"49424",
    "sg:province":"MI",
    "wof:name":"Doezema Marine Inc",
    "wof:placetype":"venue"
},
  "geometry": {"coordinates":[-86.17715200000001,42.79481],"type":"Point"}
}