{
  "type": "Feature",
  "properties": {
    "iso:country":"US",
    "sg:address":"2340 Oak Forest Rd",
    "sg:city":"Buchanan",
    "sg:classifiers":[
        {
            "category":"Museum",
            "type":"Entertainment"
        }
    ],
    "sg:phone":"+1 269 695 2057",
    "sg:postcode":"49107",
    "sg:province":"MI",
    "sg:tags":[
        "gallery"
    ],
    "wof:name":"Pears Flour Mill",
    "wof:placetype":"venue"
},
  "geometry": {"coordinates":[-86.382581,41.785157],"type":"Point"}
}