{
  "type": "Feature",
  "properties": {
    "iso:country":"US",
    "sg:address":"512 N Park St",
    "sg:city":"Kalamazoo",
    "sg:classifiers":[
        {
            "category":"Food & Beverages",
            "subcategory":"Groceries & Convenience Stores",
            "type":"Retail Goods"
        }
    ],
    "sg:phone":"+1 269 226 9607",
    "sg:postcode":"49007",
    "sg:province":"MI",
    "sg:tags":[
        "grocer"
    ],
    "wof:name":"Felpausch Food Ctr",
    "wof:placetype":"venue"
},
  "geometry": {"coordinates":[-85.587345,42.295657],"type":"Point"}
}