{
  "type": "Feature",
  "properties": {
    "iso:country":"US",
    "sg:address":"5596 E Metz Hwy",
    "sg:city":"Posen",
    "sg:classifiers":[
        {
            "category":"Farming",
            "subcategory":"Dairy Farm",
            "type":"Manufacturing & Wholesale Goods"
        }
    ],
    "sg:phone":"+1 989 766 8874",
    "sg:postcode":"49776",
    "sg:province":"MI",
    "wof:name":"Mulka Julian Farm",
    "wof:placetype":"venue"
},
  "geometry": {"coordinates":[-83.740032,45.29101],"type":"Point"}
}