{
  "type": "Feature",
  "properties": {
    "iso:country":"US",
    "sg:address":"9740 Shepherd Rd",
    "sg:city":"Onsted",
    "sg:classifiers":[
        {
            "category":"Organizations",
            "subcategory":"Community Association",
            "type":"Services"
        }
    ],
    "sg:phone":"+1 517 467 6100",
    "sg:postcode":"49265",
    "sg:province":"MI",
    "wof:name":"Home Owners Repair Service",
    "wof:placetype":"venue"
},
  "geometry": {"coordinates":[-84.180494,41.97256],"type":"Point"}
}