{
  "type": "Feature",
  "properties": {
    "iso:country":"US",
    "sg:address":"5516 W River Dr NE",
    "sg:city":"Comstock Park",
    "sg:classifiers":[
        {
            "category":"Manufacturing",
            "subcategory":"Tools & Machinery",
            "type":"Manufacturing & Wholesale Goods"
        }
    ],
    "sg:phone":"+1 616 784 7171",
    "sg:postcode":"49321",
    "sg:province":"MI",
    "sg:tags":[
        "die",
        "maker"
    ],
    "wof:name":"Kentwater Tool & Mfg Co",
    "wof:placetype":"venue"
},
  "geometry": {"coordinates":[-85.648509,43.054625],"type":"Point"}
}