{
  "type": "Feature",
  "properties": {
    "iso:country":"US",
    "sg:address":"56951 New Haven Rd",
    "sg:city":"Chesterfield",
    "sg:classifiers":[
        {
            "category":"Shopping",
            "subcategory":"Clothing, Apparel, & Fashions",
            "type":"Retail Goods"
        }
    ],
    "sg:phone":"+1 586 749 9808",
    "sg:postcode":"48051",
    "sg:province":"MI",
    "sg:tags":[
        "alteration"
    ],
    "wof:name":"Creative Cleaners & Sewing Ctr",
    "wof:placetype":"venue"
},
  "geometry": {"coordinates":[-82.787981,42.719134],"type":"Point"}
}