{
  "type": "Feature",
  "properties": {
    "iso:country":"US",
    "sg:address":"30200 Telegraph Rd",
    "sg:city":"Franklin",
    "sg:classifiers":[
        {
            "category":"Real Estate",
            "subcategory":"Real Estate Agent",
            "type":"Services"
        }
    ],
    "sg:phone":"+1 248 593 8719",
    "sg:postcode":"48025",
    "sg:province":"MI",
    "wof:name":"Bingham Farms",
    "wof:placetype":"venue"
},
  "geometry": {"coordinates":[-83.28524400000001,42.510157],"type":"Point"}
}