{
  "type": "Feature",
  "properties": {
    "iso:country":"US",
    "sg:address":"20950 B Dr N",
    "sg:city":"Marshall",
    "sg:classifiers":[
        {
            "category":"Building & Trades",
            "subcategory":"Construction",
            "type":"Services"
        }
    ],
    "sg:phone":"+1 269 781 7107",
    "sg:postcode":"49068",
    "sg:province":"MI",
    "sg:tags":[
        "roofing",
        "contractor"
    ],
    "wof:name":"Kentwood Roofing",
    "wof:placetype":"venue"
},
  "geometry": {"coordinates":[-84.88174600000001,42.261253],"type":"Point"}
}