{
  "type": "Feature",
  "properties": {
    "iso:country":"US",
    "sg:address":"6539 Dale Ave",
    "sg:city":"Hudsonville",
    "sg:classifiers":[
        {
            "category":"Communications",
            "subcategory":"Film & Video Production",
            "type":"Services"
        },
        {
            "category":"Building & Trades",
            "subcategory":"Equipment Rental",
            "type":"Services"
        }
    ],
    "sg:phone":"+1 616 662 1763",
    "sg:postcode":"49426",
    "sg:province":"MI",
    "sg:tags":[
        "motion",
        "audio",
        "leasing"
    ],
    "wof:name":"Frielink Productions LLC",
    "wof:placetype":"venue"
},
  "geometry": {"coordinates":[-85.88605,42.887602],"type":"Point"}
}