{
  "type": "Feature",
  "properties": {
    "iso:country":"US",
    "sg:address":"1320 W Washington St",
    "sg:city":"Greenville",
    "sg:classifiers":[
        {
            "category":"Organizations",
            "subcategory":"Community Association",
            "type":"Services"
        }
    ],
    "sg:phone":"+1 616 754 5063",
    "sg:postcode":"48838",
    "sg:province":"MI",
    "sg:tags":[
        "legion"
    ],
    "wof:name":"American Legion Post 101",
    "wof:placetype":"venue"
},
  "geometry": {"coordinates":[-85.272514,43.177336],"type":"Point"}
}