{
  "type": "Feature",
  "properties": {
    "iso:country":"US",
    "sg:address":"22850 Michigan Ave",
    "sg:city":"Dearborn",
    "sg:classifiers":[
        {
            "category":"Health Services",
            "subcategory":"Optometrist",
            "type":"Services"
        }
    ],
    "sg:phone":"+1 313 562 8000",
    "sg:postcode":"48124",
    "sg:province":"MI",
    "wof:name":"Dr Harvey Firestone",
    "wof:placetype":"venue"
},
  "geometry": {"coordinates":[-83.256659,42.303381],"type":"Point"}
}