{
  "type": "Feature",
  "properties": {
    "iso:country":"US",
    "sg:address":"27355 Woodsfield St",
    "sg:city":"Inkster",
    "sg:classifiers":[
        {
            "category":"Education",
            "subcategory":"School",
            "type":"Public Place"
        }
    ],
    "sg:phone":"+1 313 827 0762",
    "sg:postcode":"48141",
    "sg:province":"MI",
    "sg:tags":[
        "high",
        "middle",
        "elementary"
    ],
    "wof:name":"Discover Arts & Technology Academy",
    "wof:placetype":"venue"
},
  "geometry": {"coordinates":[-83.309738,42.307345],"type":"Point"}
}