{
  "type": "Feature",
  "properties": {
    "iso:country":"US",
    "sg:address":"5157 W Carpenter Rd",
    "sg:city":"Flint",
    "sg:classifiers":[
        {
            "category":"Home & Garden",
            "subcategory":"Building Materials",
            "type":"Retail Goods"
        }
    ],
    "sg:phone":"+1 810 720 2936",
    "sg:postcode":"48504",
    "sg:province":"MI",
    "wof:name":"Thomas & Sons Glass",
    "wof:placetype":"venue"
},
  "geometry": {"coordinates":[-83.79277500000001,43.078556],"type":"Point"}
}