{
  "type": "Feature",
  "properties": {
    "iso:country":"US",
    "sg:address":"3574 W Drahner Rd",
    "sg:city":"Oxford",
    "sg:classifiers":[
        {
            "category":"Building & Trades",
            "subcategory":"Landscaping Services",
            "type":"Services"
        }
    ],
    "sg:phone":"+1 248 420 7600",
    "sg:postcode":"48371",
    "sg:province":"MI",
    "wof:name":"P C Lawn Care",
    "wof:placetype":"venue"
},
  "geometry": {"coordinates":[-83.32957399999999,42.813842],"type":"Point"}
}