{
  "type": "Feature",
  "properties": {
    "iso:country":"US",
    "sg:address":"29150 Farmington Rd",
    "sg:city":"Farmington Hills",
    "sg:classifiers":[
        {
            "category":"Recreation",
            "type":"Entertainment"
        }
    ],
    "sg:phone":"+1 248 553 9025",
    "sg:postcode":"48334",
    "sg:province":"MI",
    "sg:tags":[
        "tennis",
        "court"
    ],
    "wof:name":"Kendallwood Club",
    "wof:placetype":"venue"
},
  "geometry": {"coordinates":[-83.378722,42.510445],"type":"Point"}
}