{
  "type": "Feature",
  "properties": {
    "iso:country":"US",
    "sg:address":"245 N Fillmore Rd",
    "sg:city":"Coldwater",
    "sg:classifiers":[
        {
            "category":"Manufacturing",
            "subcategory":"Metals",
            "type":"Manufacturing & Wholesale Goods"
        }
    ],
    "sg:phone":"+1 517 279 1011",
    "sg:postcode":"49036",
    "sg:province":"MI",
    "sg:tags":[
        "primary"
    ],
    "wof:name":"Interamerican Zinc Inc",
    "wof:placetype":"venue"
},
  "geometry": {"coordinates":[-85.023341,41.917809],"type":"Point"}
}