{
  "type": "Feature",
  "properties": {
    "iso:country":"US",
    "sg:address":"2524 Harding Ave",
    "sg:city":"Muskegon",
    "sg:classifiers":[
        {
            "category":"Professional",
            "subcategory":"Accounting & Tax Preparation",
            "type":"Services"
        }
    ],
    "sg:phone":"+1 231 759 0135",
    "sg:postcode":"49441",
    "sg:province":"MI",
    "sg:tags":[
        "return",
        "filing"
    ],
    "wof:name":"Don Ferenz Accounting & Tax",
    "wof:placetype":"venue"
},
  "geometry": {"coordinates":[-86.30537099999999,43.210616],"type":"Point"}
}