{
  "type": "Feature",
  "properties": {
    "iso:country":"US",
    "sg:address":"1267 E Siena Heights Dr",
    "sg:city":"Adrian",
    "sg:classifiers":[
        {
            "category":"Education",
            "subcategory":"School",
            "type":"Public Place"
        }
    ],
    "sg:phone":"+1 517 263 4898",
    "sg:postcode":"49221",
    "sg:province":"MI",
    "wof:name":"Montessori Childerns House",
    "wof:placetype":"venue"
},
  "geometry": {"coordinates":[-84.009851,41.905232],"type":"Point"}
}