{
  "type": "Feature",
  "properties": {
    "iso:country":"US",
    "sg:address":"2425 Dexter Rd",
    "sg:city":"Auburn Hills",
    "sg:classifiers":[
        {
            "category":"Shopping",
            "subcategory":"Catalog Store",
            "type":"Retail Goods"
        }
    ],
    "sg:phone":"+1 248 373 2810",
    "sg:postcode":"48326",
    "sg:province":"MI",
    "sg:tags":[
        "mail",
        "house"
    ],
    "wof:name":"Tri-G Unlimited",
    "wof:placetype":"venue"
},
  "geometry": {"coordinates":[-83.230238,42.672033],"type":"Point"}
}