{
  "type": "Feature",
  "properties": {
    "iso:country":"US",
    "sg:address":"620 S Lafayette St",
    "sg:city":"South Lyon",
    "sg:classifiers":[
        {
            "category":"Manufacturing",
            "subcategory":"Tools & Machinery",
            "type":"Manufacturing & Wholesale Goods"
        }
    ],
    "sg:phone":"+1 248 486 7676",
    "sg:postcode":"48178",
    "sg:province":"MI",
    "sg:tags":[
        "tobacco",
        "supply"
    ],
    "wof:name":"Tobacco Road Inc",
    "wof:placetype":"venue"
},
  "geometry": {"coordinates":[-83.65110799999999,42.454526],"type":"Point"}
}