{
  "type": "Feature",
  "properties": {
    "iso:country":"US",
    "sg:address":"16710 Lakeshore Rd",
    "sg:city":"New Buffalo",
    "sg:classifiers":[
        {
            "category":"Restaurant",
            "type":"Food & Drink"
        }
    ],
    "sg:phone":"+1 269 469 3330",
    "sg:postcode":"49129",
    "sg:province":"MI",
    "sg:website":"www.skipsotherplace.com",
    "wof:name":"Skip's Other Place",
    "wof:placetype":"venue"
},
  "geometry": {"coordinates":[-86.705237,41.81803],"type":"Point"}
}