{
  "type": "Feature",
  "properties": {
    "iso:country":"US",
    "sg:address":"103 W Clinton St",
    "sg:city":"Durand",
    "sg:classifiers":[
        {
            "category":"Health Services",
            "subcategory":"Doctor",
            "type":"Services"
        }
    ],
    "sg:phone":"+1 989 288 6165",
    "sg:postcode":"48429",
    "sg:province":"MI",
    "sg:tags":[
        "dentist"
    ],
    "wof:name":"Tirtha & Lewis",
    "wof:placetype":"venue"
},
  "geometry": {"coordinates":[-83.984675,42.911906],"type":"Point"}
}