{
  "type": "Feature",
  "properties": {
    "iso:country":"US",
    "sg:address":"1000 S Getty St",
    "sg:city":"Muskegon",
    "sg:classifiers":[
        {
            "category":"Shopping",
            "subcategory":"Pharmacy",
            "type":"Retail Goods"
        }
    ],
    "sg:phone":"+1 231 767 1432",
    "sg:postcode":"49442",
    "sg:province":"MI",
    "wof:name":"Walgreens",
    "wof:placetype":"venue"
},
  "geometry": {"coordinates":[-86.22406100000001,43.234954],"type":"Point"}
}