{
  "type": "Feature",
  "properties": {
    "iso:country":"US",
    "sg:address":"41721 Onaway Dr",
    "sg:city":"Northville",
    "sg:classifiers":[
        {
            "category":"Organizations",
            "subcategory":"Professional Association",
            "type":"Services"
        }
    ],
    "sg:phone":"+1 248 344 2904",
    "sg:postcode":"48167",
    "sg:province":"MI",
    "sg:tags":[
        "business"
    ],
    "wof:name":"Cug Inc",
    "wof:placetype":"venue"
},
  "geometry": {"coordinates":[-83.45775399999999,42.442329],"type":"Point"}
}