{
  "type": "Feature",
  "properties": {
    "iso:country":"US",
    "sg:address":"805 W Giles Rd",
    "sg:city":"Muskegon",
    "sg:classifiers":[
        {
            "category":"Education",
            "subcategory":"Dance Studio",
            "type":"Public Place"
        }
    ],
    "sg:phone":"+1 231 744 1430",
    "sg:postcode":"49445",
    "sg:province":"MI",
    "wof:name":"Sika School Of Dancing",
    "wof:placetype":"venue"
},
  "geometry": {"coordinates":[-86.26163200000001,43.277806],"type":"Point"}
}