{
  "type": "Feature",
  "properties": {
    "iso:country":"US",
    "sg:address":"9721 Elm Ave",
    "sg:city":"Newaygo",
    "sg:classifiers":[
        {
            "category":"Building & Trades",
            "subcategory":"Construction",
            "type":"Services"
        }
    ],
    "sg:phone":"+1 231 937 6910",
    "sg:postcode":"49337",
    "sg:province":"MI",
    "sg:tags":[
        "hanging",
        "contractor"
    ],
    "wof:name":"Buggs Quality Painting",
    "wof:placetype":"venue"
},
  "geometry": {"coordinates":[-85.642287,43.3782],"type":"Point"}
}