{
  "type": "Feature",
  "properties": {
    "iso:country":"US",
    "sg:address":"5035 W Outer Dr",
    "sg:city":"Detroit",
    "sg:classifiers":[
        {
            "category":"Professional",
            "subcategory":"Business Services",
            "type":"Services"
        }
    ],
    "sg:phone":"+1 313 862 4052",
    "sg:postcode":"48235",
    "sg:province":"MI",
    "sg:tags":[
        "recording",
        "production",
        "music"
    ],
    "wof:name":"2 Unified Records",
    "wof:placetype":"venue"
},
  "geometry": {"coordinates":[-83.17536200000001,42.430573],"type":"Point"}
}