{
  "type": "Feature",
  "properties": {
    "iso:country":"US",
    "sg:address":"6701 Bancroft Rd",
    "sg:city":"Bancroft",
    "sg:classifiers":[
        {
            "category":"Travel",
            "subcategory":"Travel Agent",
            "type":"Entertainment"
        }
    ],
    "sg:phone":"+1 989 634 5296",
    "sg:postcode":"48414",
    "sg:province":"MI",
    "sg:tags":[
        "agency",
        "bureau"
    ],
    "wof:name":"Hometown Travel Home Office",
    "wof:placetype":"venue"
},
  "geometry": {"coordinates":[-84.069121,42.899826],"type":"Point"}
}