{
  "type": "Feature",
  "properties": {
    "iso:country":"US",
    "sg:address":"5438 Sashabaw Rd",
    "sg:city":"Clarkston",
    "sg:classifiers":[
        {
            "category":"Shopping",
            "subcategory":"Florist",
            "type":"Retail Goods"
        }
    ],
    "sg:phone":"+1 248 623 2255",
    "sg:postcode":"48346",
    "sg:province":"MI",
    "wof:name":"Carrol's Flowers & Gardens",
    "wof:placetype":"venue"
},
  "geometry": {"coordinates":[-83.37858,42.712697],"type":"Point"}
}