{
  "type": "Feature",
  "properties": {
    "iso:country":"US",
    "sg:address":"9591 Curtis Rd",
    "sg:city":"Nashville",
    "sg:classifiers":[
        {
            "category":"Farming",
            "subcategory":"Livestock Farm",
            "type":"Manufacturing & Wholesale Goods"
        }
    ],
    "sg:phone":"+1 517 852 9266",
    "sg:postcode":"49073",
    "sg:province":"MI",
    "sg:tags":[
        "beef",
        "feedlot",
        "cattle"
    ],
    "wof:name":"Thomas Burns",
    "wof:placetype":"venue"
},
  "geometry": {"coordinates":[-85.073842,42.515415],"type":"Point"}
}