{
  "type": "Feature",
  "properties": {
    "iso:country":"US",
    "sg:address":"31280 Groesbeck Hwy",
    "sg:city":"Fraser",
    "sg:classifiers":[
        {
            "category":"Shopping",
            "subcategory":"Hobbies, Toys, & Games",
            "type":"Retail Goods"
        }
    ],
    "sg:phone":"+1 586 296 6116",
    "sg:postcode":"48026",
    "sg:province":"MI",
    "sg:tags":[
        "shop",
        "hobby"
    ],
    "wof:name":"P & D Hobby Shop",
    "wof:placetype":"venue"
},
  "geometry": {"coordinates":[-82.944801,42.5261],"type":"Point"}
}