{
  "type": "Feature",
  "properties": {
    "iso:country":"US",
    "sg:address":"4080 Page Ave",
    "sg:city":"Michigan Center",
    "sg:classifiers":[
        {
            "category":"Restaurant",
            "type":"Food & Drink"
        }
    ],
    "sg:menulink":"http://www.allmenus.com/mi/leoni/196906-burger-king/menu/",
    "sg:phone":"+1 517 764 7705",
    "sg:postcode":"49254",
    "sg:province":"MI",
    "sg:tags":[
        "burger",
        "american"
    ],
    "wof:name":"Burger King",
    "wof:placetype":"venue"
},
  "geometry": {"coordinates":[-84.340166,42.236642],"type":"Point"}
}