{
  "type": "Feature",
  "properties": {
    "iso:country":"US",
    "sg:address":"8800 E 8 Mile Rd",
    "sg:city":"Detroit",
    "sg:classifiers":[
        {
            "category":"Personal",
            "subcategory":"Nail Salon",
            "type":"Services"
        }
    ],
    "sg:phone":"+1 313 366 9945",
    "sg:postcode":"48234",
    "sg:province":"MI",
    "wof:name":"Gel Nails",
    "wof:placetype":"venue"
},
  "geometry": {"coordinates":[-83.018501,42.4482],"type":"Point"}
}