{
  "type": "Feature",
  "properties": {
    "iso:country":"US",
    "sg:address":"4324 W Saginaw Hwy",
    "sg:city":"Lansing",
    "sg:classifiers":[
        {
            "category":"Shopping",
            "type":"Retail Goods"
        }
    ],
    "sg:phone":"+1 517 321 2070",
    "sg:postcode":"48917",
    "sg:province":"MI",
    "sg:tags":[
        "coin",
        "dealer",
        "merchandise",
        "supply"
    ],
    "wof:name":"Kelly's Coin & Stamp",
    "wof:placetype":"venue"
},
  "geometry": {"coordinates":[-84.610057,42.74119],"type":"Point"}
}