{
  "type": "Feature",
  "properties": {
    "iso:country":"US",
    "sg:address":"275 Clyde Rd",
    "sg:city":"Highland",
    "sg:classifiers":[
        {
            "category":"Building & Trades",
            "subcategory":"Electrical",
            "type":"Services"
        }
    ],
    "sg:phone":"+1 248 887 4384",
    "sg:postcode":"48357",
    "sg:province":"MI",
    "sg:tags":[
        "electric",
        "contractor"
    ],
    "wof:name":"Kim's Cleaning",
    "wof:placetype":"venue"
},
  "geometry": {"coordinates":[-83.625826,42.681349],"type":"Point"}
}