{
  "type": "Feature",
  "properties": {
    "iso:country":"US",
    "sg:address":"3444 S Genesee Rd",
    "sg:city":"Burton",
    "sg:classifiers":[
        {
            "category":"Education",
            "subcategory":"School",
            "type":"Public Place"
        }
    ],
    "sg:phone":"+1 810 591 0604",
    "sg:postcode":"48519",
    "sg:province":"MI",
    "sg:website":"www.athertonschools.com",
    "wof:name":"Atherton Community Middle Schl",
    "wof:placetype":"venue"
},
  "geometry": {"coordinates":[-83.61413,42.985699],"type":"Point"}
}