{
  "type": "Feature",
  "properties": {
    "iso:country":"US",
    "sg:address":"1055 Parmelee Ave NW",
    "sg:city":"Grand Rapids",
    "sg:classifiers":[
        {
            "category":"Manufacturing",
            "subcategory":"Printing",
            "type":"Manufacturing & Wholesale Goods"
        }
    ],
    "sg:phone":"+1 616 453 9240",
    "sg:postcode":"49504",
    "sg:province":"MI",
    "sg:tags":[
        "printer"
    ],
    "wof:name":"KJM Svc",
    "wof:placetype":"venue"
},
  "geometry": {"coordinates":[-85.724114,42.984573],"type":"Point"}
}