{
  "type": "Feature",
  "properties": {
    "iso:country":"US",
    "sg:address":"4899 Fashion Square Blvd",
    "sg:city":"Saginaw",
    "sg:classifiers":[
        {
            "category":"Personal",
            "subcategory":"Beauty Salon",
            "type":"Services"
        }
    ],
    "sg:phone":"+1 989 249 7579",
    "sg:postcode":"48604",
    "sg:province":"MI",
    "sg:tags":[
        "shop"
    ],
    "wof:name":"Modern Nails",
    "wof:placetype":"venue"
},
  "geometry": {"coordinates":[-83.97068299999999,43.477699],"type":"Point"}
}