{
  "type": "Feature",
  "properties": {
    "iso:country":"US",
    "sg:address":"4236 84th St SE",
    "sg:city":"Caledonia",
    "sg:classifiers":[
        {
            "category":"Building & Trades",
            "subcategory":"Landscaping Services",
            "type":"Services"
        }
    ],
    "sg:phone":"+1 616 891 3547",
    "sg:postcode":"49316",
    "sg:province":"MI",
    "sg:tags":[
        "tree"
    ],
    "wof:name":"Absolute Tree Svc Inc",
    "wof:placetype":"venue"
},
  "geometry": {"coordinates":[-85.557376,42.811802],"type":"Point"}
}