{
  "type": "Feature",
  "properties": {
    "iso:country":"US",
    "sg:address":"3101 N Saginaw St",
    "sg:city":"Flint",
    "sg:classifiers":[
        {
            "category":"Recreation",
            "type":"Entertainment"
        }
    ],
    "sg:phone":"+1 810 789 9956",
    "sg:postcode":"48505",
    "sg:province":"MI",
    "wof:name":"North End Pool Room",
    "wof:placetype":"venue"
},
  "geometry": {"coordinates":[-83.693786,43.044663],"type":"Point"}
}