{
  "type": "Feature",
  "properties": {
    "iso:country":"US",
    "sg:address":"23744 Beech Rd",
    "sg:city":"Southfield",
    "sg:classifiers":[
        {
            "category":"Building & Trades",
            "subcategory":"Construction",
            "type":"Services"
        }
    ],
    "sg:phone":"+1 248 355 9645",
    "sg:postcode":"48033",
    "sg:province":"MI",
    "sg:tags":[
        "carpentry",
        "contractor"
    ],
    "wof:name":"Contrast Building",
    "wof:placetype":"venue"
},
  "geometry": {"coordinates":[-83.298152,42.457015],"type":"Point"}
}