{
  "type": "Feature",
  "properties": {
    "iso:country":"US",
    "sg:address":"3400 Agnes St",
    "sg:city":"Jackson",
    "sg:classifiers":[
        {
            "category":"Wholesale",
            "subcategory":"Groceries",
            "type":"Manufacturing & Wholesale Goods"
        }
    ],
    "sg:phone":"+1 517 787 6682",
    "sg:postcode":"49203",
    "sg:province":"MI",
    "sg:tags":[
        "confectionery"
    ],
    "wof:name":"Frederick Distrubuting",
    "wof:placetype":"venue"
},
  "geometry": {"coordinates":[-84.448224,42.214573],"type":"Point"}
}