{
  "type": "Feature",
  "properties": {
    "iso:country":"US",
    "sg:address":"26190 Eastgate Blvd",
    "sg:city":"Roseville",
    "sg:classifiers":[
        {
            "category":"Shopping",
            "subcategory":"Discount & Variety Stores",
            "type":"Retail Goods"
        }
    ],
    "sg:phone":"+1 586 775 8110",
    "sg:postcode":"48066",
    "sg:province":"MI",
    "wof:name":"99 Cents Stores",
    "wof:placetype":"venue"
},
  "geometry": {"coordinates":[-82.939886,42.488435],"type":"Point"}
}