{
  "type": "Feature",
  "properties": {
    "iso:country":"US",
    "sg:address":"819 E Webb Dr",
    "sg:city":"Dewitt",
    "sg:classifiers":[
        {
            "category":"Banks & Credit Unions",
            "subcategory":"Investment Brokerage",
            "type":"Services"
        }
    ],
    "sg:phone":"+1 517 668 8441",
    "sg:postcode":"48820",
    "sg:province":"MI",
    "sg:tags":[
        "consultant",
        "planning",
        "financial"
    ],
    "wof:name":"Three Generations Financial",
    "wof:placetype":"venue"
},
  "geometry": {"coordinates":[-84.56023500000001,42.835947],"type":"Point"}
}