{
  "type": "Feature",
  "properties": {
    "iso:country":"US",
    "sg:address":"20853 Farmington Rd",
    "sg:city":"Farmington",
    "sg:classifiers":[
        {
            "category":"Professional",
            "subcategory":"Employment Agencies",
            "type":"Services"
        }
    ],
    "sg:phone":"+1 248 476 9091",
    "sg:postcode":"48336",
    "sg:province":"MI",
    "wof:name":"Excellacare Inc",
    "wof:placetype":"venue"
},
  "geometry": {"coordinates":[-83.37539700000001,42.443298],"type":"Point"}
}