{
  "type": "Feature",
  "properties": {
    "iso:country":"US",
    "sg:address":"1114 S 7th St",
    "sg:city":"St Clair",
    "sg:classifiers":[
        {
            "category":"Social Services",
            "type":"Services"
        }
    ],
    "sg:phone":"+1 810 326 4505",
    "sg:postcode":"48079",
    "sg:province":"MI",
    "sg:tags":[
        "organization",
        "welfare"
    ],
    "wof:name":"Kids In Distress Svc Inc",
    "wof:placetype":"venue"
},
  "geometry": {"coordinates":[-82.492604,42.818005],"type":"Point"}
}