{
  "type": "Feature",
  "properties": {
    "iso:country":"US",
    "sg:address":"4044 N M 52",
    "sg:city":"Stockbridge",
    "sg:classifiers":[
        {
            "category":"Farming",
            "subcategory":"Farm",
            "type":"Manufacturing & Wholesale Goods"
        }
    ],
    "sg:phone":"+1 517 851 8870",
    "sg:postcode":"49285",
    "sg:province":"MI",
    "wof:name":"Sommer Farms",
    "wof:placetype":"venue"
},
  "geometry": {"coordinates":[-84.190139,42.459851],"type":"Point"}
}