{
  "type": "Feature",
  "properties": {
    "iso:country":"US",
    "sg:address":"23845 Van Dyke Ave",
    "sg:city":"Center Line",
    "sg:classifiers":[
        {
            "category":"Health Services",
            "subcategory":"Doctor",
            "type":"Services"
        }
    ],
    "sg:phone":"+1 586 755 1750",
    "sg:postcode":"48015",
    "sg:province":"MI",
    "sg:tags":[
        "dentist"
    ],
    "wof:name":"Russell A Sassack DDS",
    "wof:placetype":"venue"
},
  "geometry": {"coordinates":[-83.02701999999999,42.469152],"type":"Point"}
}