{
  "type": "Feature",
  "properties": {
    "iso:country":"US",
    "sg:address":"1495 Royston Rd",
    "sg:city":"Eaton Rapids",
    "sg:phone":"+1 517 663 8425",
    "sg:postcode":"48827",
    "sg:province":"MI",
    "sg:tags":[
        "farm",
        "corn",
        "wheat",
        "soybean"
    ],
    "wof:name":"Cupp Rosamond",
    "wof:placetype":"venue"
},
  "geometry": {"coordinates":[-84.71898400000001,42.545667],"type":"Point"}
}