{
  "type": "Feature",
  "properties": {
    "iso:country":"US",
    "sg:address":"3850 Monroe St",
    "sg:city":"Dearborn",
    "sg:classifiers":[
        {
            "category":"Food & Beverages",
            "subcategory":"Groceries & Convenience Stores",
            "type":"Retail Goods"
        }
    ],
    "sg:phone":"+1 313 563 5671",
    "sg:postcode":"48124",
    "sg:province":"MI",
    "sg:website":"www.7-eleven.com",
    "wof:name":"7-Eleven Store No 32820",
    "wof:placetype":"venue"
},
  "geometry": {"coordinates":[-83.25129699999999,42.282299],"type":"Point"}
}