{
  "type": "Feature",
  "properties": {
    "iso:country":"US",
    "sg:address":"1503 E High St",
    "sg:city":"Jackson",
    "sg:classifiers":[
        {
            "category":"Retail",
            "subcategory":"Repair Shop",
            "type":"Services"
        }
    ],
    "sg:phone":"+1 517 782 8448",
    "sg:postcode":"49203",
    "sg:province":"MI",
    "sg:tags":[
        "welding"
    ],
    "wof:name":"Atlas Welding Company",
    "wof:placetype":"venue"
},
  "geometry": {"coordinates":[-84.38432400000001,42.233129],"type":"Point"}
}