{
  "type": "Feature",
  "properties": {
    "iso:country":"US",
    "sg:address":"301 Senate Ave",
    "sg:city":"Ypsilanti",
    "sg:classifiers":[
        {
            "category":"Real Estate",
            "subcategory":"Real Estate Agent",
            "type":"Services"
        }
    ],
    "sg:phone":"+1 734 663 4305",
    "sg:postcode":"48197",
    "sg:province":"MI",
    "wof:name":"Susan Fecteau",
    "wof:placetype":"venue"
},
  "geometry": {"coordinates":[-83.650544,42.241865],"type":"Point"}
}