{
  "type": "Feature",
  "properties": {
    "iso:country":"US",
    "sg:address":"20564 Hall Rd",
    "sg:city":"Clinton Twp",
    "sg:classifiers":[
        {
            "category":"Home & Garden",
            "subcategory":"Building Materials",
            "type":"Retail Goods"
        }
    ],
    "sg:phone":"+1 586 416 5000",
    "sg:postcode":"48038",
    "sg:province":"MI",
    "sg:tags":[
        "door"
    ],
    "wof:name":"Taylor Made Products",
    "wof:placetype":"venue"
},
  "geometry": {"coordinates":[-82.92272,42.628183],"type":"Point"}
}