{
  "type": "Feature",
  "properties": {
    "iso:country":"US",
    "sg:address":"2429 Spring Arbor Rd",
    "sg:city":"Jackson",
    "sg:classifiers":[
        {
            "category":"Banks & Credit Unions",
            "subcategory":"Investment Brokerage",
            "type":"Services"
        }
    ],
    "sg:phone":"+1 517 789 5577",
    "sg:postcode":"49203",
    "sg:province":"MI",
    "sg:tags":[
        "security"
    ],
    "wof:name":"Edward Jones 01654",
    "wof:placetype":"venue"
},
  "geometry": {"coordinates":[-84.443032,42.234332],"type":"Point"}
}