{
  "type": "Feature",
  "properties": {
    "iso:country":"US",
    "sg:address":"5832 Naneva Ct",
    "sg:city":"West Bloomfield",
    "sg:classifiers":[
        {
            "category":"Professional",
            "subcategory":"Management & Consulting",
            "type":"Services"
        }
    ],
    "sg:phone":"+1 248 538 0136",
    "sg:postcode":"48322",
    "sg:province":"MI",
    "sg:tags":[
        "business"
    ],
    "sg:website":"www.trizgroup.com",
    "wof:name":"Triz Group",
    "wof:placetype":"venue"
},
  "geometry": {"coordinates":[-83.33095299999999,42.552313],"type":"Point"}
}