{
  "type": "Feature",
  "properties": {
    "iso:country":"US",
    "sg:address":"30715 Halecreek St",
    "sg:city":"Romulus",
    "sg:classifiers":[
        {
            "category":"Building & Trades",
            "subcategory":"Landscaping Services",
            "type":"Services"
        }
    ],
    "sg:phone":"+1 734 229 9813",
    "sg:postcode":"48174",
    "sg:province":"MI",
    "sg:tags":[
        "landscape"
    ],
    "wof:name":"Taylor Landscaping LLC",
    "wof:placetype":"venue"
},
  "geometry": {"coordinates":[-83.338354,42.18833],"type":"Point"}
}