{
  "type": "Feature",
  "properties": {
    "iso:country":"US",
    "sg:address":"26191 Dutch Settlement St",
    "sg:city":"Dowagiac",
    "sg:classifiers":[
        {
            "category":"Building & Trades",
            "subcategory":"Construction",
            "type":"Services"
        }
    ],
    "sg:phone":"+1 269 782 6292",
    "sg:postcode":"49047",
    "sg:province":"MI",
    "sg:tags":[
        "general",
        "contractor"
    ],
    "wof:name":"J F Construction",
    "wof:placetype":"venue"
},
  "geometry": {"coordinates":[-86.07824599999999,41.983605],"type":"Point"}
}