{
  "type": "Feature",
  "properties": {
    "iso:country":"US",
    "sg:address":"4779 Snoopy Ln",
    "sg:city":"Frederic",
    "sg:classifiers":[
        {
            "category":"Building & Trades",
            "subcategory":"Cleaning & Sanitation",
            "type":"Services"
        }
    ],
    "sg:phone":"+1 989 348 2457",
    "sg:postcode":"49733",
    "sg:province":"MI",
    "sg:tags":[
        "janitor"
    ],
    "wof:name":"Sparkling Cleaning Svc",
    "wof:placetype":"venue"
},
  "geometry": {"coordinates":[-84.761027,44.754507],"type":"Point"}
}