{
  "type": "Feature",
  "properties": {
    "iso:country":"US",
    "sg:address":"2803 Arrowwood Trl",
    "sg:city":"Ann Arbor",
    "sg:classifiers":[
        {
            "category":"Organizations",
            "subcategory":"Religious Organization",
            "type":"Services"
        }
    ],
    "sg:phone":"+1 734 663 5769",
    "sg:postcode":"48105",
    "sg:province":"MI",
    "wof:name":"Born Agan Ch Jesus Christ Apst",
    "wof:placetype":"venue"
},
  "geometry": {"coordinates":[-83.73437,42.307676],"type":"Point"}
}