{
  "type": "Feature",
  "properties": {
    "iso:country":"US",
    "sg:address":"2522 Wyckham Dr",
    "sg:city":"Lansing",
    "sg:classifiers":[
        {
            "category":"Social Services",
            "subcategory":"Child Care",
            "type":"Services"
        }
    ],
    "sg:phone":"+1 517 321 6863",
    "sg:postcode":"48906",
    "sg:province":"MI",
    "sg:tags":[
        "day"
    ],
    "wof:name":"Parents of Murdered Child",
    "wof:placetype":"venue"
},
  "geometry": {"coordinates":[-84.598252,42.76121],"type":"Point"}
}