{
  "type": "Feature",
  "properties": {
    "iso:country":"US",
    "sg:address":"1310 E Wagner Rd",
    "sg:city":"Buchanan",
    "sg:classifiers":[
        {
            "category":"Retail",
            "subcategory":"Repair Shop",
            "type":"Services"
        }
    ],
    "sg:phone":"+1 269 695 4175",
    "sg:postcode":"49107",
    "sg:province":"MI",
    "wof:name":"Domestic Delite Housekeeping",
    "wof:placetype":"venue"
},
  "geometry": {"coordinates":[-86.425629,41.848852],"type":"Point"}
}