{
  "type": "Feature",
  "properties": {
    "iso:country":"US",
    "sg:address":"1456 Southbound Gratiot Ave",
    "sg:city":"Mount Clemens",
    "sg:classifiers":[
        {
            "category":"Shopping",
            "type":"Retail Goods"
        }
    ],
    "sg:phone":"+1 586 465 9237",
    "sg:postcode":"48043",
    "sg:province":"MI",
    "sg:tags":[
        "medical",
        "apparatus",
        "supply"
    ],
    "wof:name":"Home Medical Equipment Store",
    "wof:placetype":"venue"
},
  "geometry": {"coordinates":[-82.886769,42.579565],"type":"Point"}
}