{
  "type": "Feature",
  "properties": {
    "iso:country":"US",
    "sg:address":"209 US Hwy 41",
    "sg:city":"Negaunee",
    "sg:classifiers":[
        {
            "category":"Wholesale",
            "subcategory":"Auto Parts",
            "type":"Manufacturing & Wholesale Goods"
        }
    ],
    "sg:phone":"+1 906 475 9951",
    "sg:postcode":"49866",
    "sg:province":"MI",
    "sg:tags":[
        "automobile",
        "rebuilt"
    ],
    "wof:name":"Superior Auto Parts",
    "wof:placetype":"venue"
},
  "geometry": {"coordinates":[-87.606837,46.5092],"type":"Point"}
}