{
  "type": "Feature",
  "properties": {
    "iso:country":"US",
    "sg:address":"222 W Greenshield Rd",
    "sg:city":"Lake Orion",
    "sg:classifiers":[
        {
            "category":"Professional",
            "type":"Services"
        }
    ],
    "sg:phone":"+1 248 393 9100",
    "sg:postcode":"48360",
    "sg:province":"MI",
    "sg:tags":[
        "establishment"
    ],
    "wof:name":"D R Nelson & Assoc",
    "wof:placetype":"venue"
},
  "geometry": {"coordinates":[-83.254704,42.74269],"type":"Point"}
}