{
  "type": "Feature",
  "properties": {
    "iso:country":"US",
    "sg:address":"3904 Cherry Hills Pl",
    "sg:city":"Traverse City",
    "sg:classifiers":[
        {
            "category":"Professional",
            "subcategory":"Advertising",
            "type":"Services"
        }
    ],
    "sg:phone":"+1 231 947 0180",
    "sg:postcode":"49684",
    "sg:province":"MI",
    "sg:tags":[
        "agency"
    ],
    "wof:name":"Andersongordon Associates",
    "wof:placetype":"venue"
},
  "geometry": {"coordinates":[-85.65491,44.740823],"type":"Point"}
}