{
  "type": "Feature",
  "properties": {
    "iso:country":"US",
    "sg:address":"320 S Lafayette St",
    "sg:city":"South Lyon",
    "sg:classifiers":[
        {
            "category":"Manufacturing",
            "subcategory":"Textiles",
            "type":"Manufacturing & Wholesale Goods"
        }
    ],
    "sg:phone":"+1 248 446 6094",
    "sg:postcode":"48178",
    "sg:province":"MI",
    "sg:tags":[
        "knitting",
        "mills"
    ],
    "wof:name":"Knitting Bin",
    "wof:placetype":"venue"
},
  "geometry": {"coordinates":[-83.651067,42.45591],"type":"Point"}
}