{
  "type": "Feature",
  "properties": {
    "iso:country":"US",
    "sg:address":"11200 Fowler Rd",
    "sg:city":"Brant",
    "sg:classifiers":[
        {
            "category":"Insurance",
            "subcategory":"Insurance Agent",
            "type":"Services"
        }
    ],
    "sg:phone":"+1 989 585 2076",
    "sg:postcode":"48614",
    "sg:province":"MI",
    "sg:tags":[
        "consultant"
    ],
    "wof:name":"Atlas Risk Decisions Inc",
    "wof:placetype":"venue"
},
  "geometry": {"coordinates":[-84.268593,43.255835],"type":"Point"}
}