{
  "type": "Feature",
  "properties": {
    "iso:country":"US",
    "sg:address":"1190 W Front St",
    "sg:city":"Monroe",
    "sg:classifiers":[
        {
            "category":"Restaurant",
            "type":"Food & Drink"
        }
    ],
    "sg:menulink":"http://www.allmenus.com/mi/monroe/163703-skyline-chili/menu/",
    "sg:phone":"+1 734 241 5929",
    "sg:postcode":"48161",
    "sg:province":"MI",
    "sg:tags":[
        "mexican"
    ],
    "wof:name":"Skyline Chili",
    "wof:placetype":"venue"
},
  "geometry": {"coordinates":[-83.415279,41.919431],"type":"Point"}
}