{
  "type": "Feature",
  "properties": {
    "iso:country":"US",
    "sg:address":"4612 N Cochran Rd",
    "sg:city":"Charlotte",
    "sg:phone":"+1 517 543 0529",
    "sg:postcode":"48813",
    "sg:province":"MI",
    "sg:tags":[
        "farm",
        "grain",
        "cash"
    ],
    "wof:name":"Madry Farms",
    "wof:placetype":"venue"
},
  "geometry": {"coordinates":[-84.83662200000001,42.639665],"type":"Point"}
}