{
  "type": "Feature",
  "properties": {
    "iso:country":"US",
    "sg:address":"6602 Cranwood Dr",
    "sg:city":"Flint",
    "sg:classifiers":[
        {
            "category":"Communications",
            "subcategory":"Film & Video Production",
            "type":"Services"
        }
    ],
    "sg:phone":"+1 810 789 3507",
    "sg:postcode":"48505",
    "sg:province":"MI",
    "sg:tags":[
        "motion"
    ],
    "wof:name":"Grim Life Production",
    "wof:placetype":"venue"
},
  "geometry": {"coordinates":[-83.714958,43.07211],"type":"Point"}
}