{
  "type": "Feature",
  "properties": {
    "iso:country":"US",
    "sg:address":"4590 State St",
    "sg:city":"Saginaw",
    "sg:classifiers":[
        {
            "category":"Personal",
            "subcategory":"Beauty Salon",
            "type":"Services"
        }
    ],
    "sg:phone":"+1 989 797 6733",
    "sg:postcode":"48603",
    "sg:province":"MI",
    "wof:name":"Graceful Styles",
    "wof:placetype":"venue"
},
  "geometry": {"coordinates":[-84.005608,43.436822],"type":"Point"}
}