{
  "type": "Feature",
  "properties": {
    "iso:country":"US",
    "sg:address":"2577 W X Y Ave",
    "sg:city":"Schoolcraft",
    "sg:phone":"+1 269 679 5634",
    "sg:postcode":"49087",
    "sg:province":"MI",
    "sg:tags":[
        "farm",
        "corn",
        "grain",
        "cash",
        "soybean"
    ],
    "wof:name":"Chapin Firman",
    "wof:placetype":"venue"
},
  "geometry": {"coordinates":[-85.625423,42.092105],"type":"Point"}
}