{
  "type": "Feature",
  "properties": {
    "iso:country":"US",
    "sg:address":"303 S Summit St",
    "sg:city":"Morenci",
    "sg:classifiers":[
        {
            "category":"Retail",
            "subcategory":"Funeral Services",
            "type":"Services"
        }
    ],
    "sg:phone":"+1 517 458 2311",
    "sg:postcode":"49256",
    "sg:province":"MI",
    "sg:tags":[
        "director"
    ],
    "wof:name":"Eagle Funeral Home",
    "wof:placetype":"venue"
},
  "geometry": {"coordinates":[-84.21522400000001,41.717043],"type":"Point"}
}