{
  "type": "Feature",
  "properties": {
    "iso:country":"US",
    "sg:address":"1 Westside Saginaw Rd",
    "sg:city":"Bay City",
    "sg:classifiers":[
        {
            "category":"Autos & Motor Vehicles",
            "subcategory":"Automobile Sales",
            "type":"Retail Goods"
        }
    ],
    "sg:phone":"+1 989 692 7669",
    "sg:postcode":"48706",
    "sg:province":"MI",
    "sg:tags":[
        "parts",
        "snowmobile",
        "accessory"
    ],
    "wof:name":"Snowmobilers Warehouse",
    "wof:placetype":"venue"
},
  "geometry": {"coordinates":[-83.92209099999999,43.578904],"type":"Point"}
}