{
  "type": "Feature",
  "properties": {
    "iso:country":"US",
    "sg:address":"1570 Forest Ln",
    "sg:city":"Bloomfield Hills",
    "sg:classifiers":[
        {
            "category":"Professional",
            "subcategory":"Business Services",
            "type":"Services"
        }
    ],
    "sg:phone":"+1 248 644 3497",
    "sg:postcode":"48301",
    "sg:province":"MI",
    "sg:tags":[
        "promotion",
        "sales"
    ],
    "wof:name":"M B S",
    "wof:placetype":"venue"
},
  "geometry": {"coordinates":[-83.25445999999999,42.534498],"type":"Point"}
}