{
  "type": "Feature",
  "properties": {
    "iso:country":"US",
    "sg:address":"106 E State St",
    "sg:city":"Scottville",
    "sg:classifiers":[
        {
            "category":"Health Services",
            "subcategory":"Chiropractor",
            "type":"Services"
        }
    ],
    "sg:phone":"+1 231 757 3356",
    "sg:postcode":"49454",
    "sg:province":"MI",
    "wof:name":"Family Care Chiropractic",
    "wof:placetype":"venue"
},
  "geometry": {"coordinates":[-86.27938899999999,43.954764],"type":"Point"}
}