{
  "type": "Feature",
  "properties": {
    "iso:country":"US",
    "sg:address":"43340 Warren Rd",
    "sg:city":"Canton",
    "sg:classifiers":[
        {
            "category":"Building & Trades",
            "subcategory":"Locksmith",
            "type":"Services"
        }
    ],
    "sg:phone":"+1 734 259 4480",
    "sg:postcode":"48187",
    "sg:province":"MI",
    "sg:tags":[
        "key"
    ],
    "wof:name":"24 Hour Emergency Locksmith",
    "wof:placetype":"venue"
},
  "geometry": {"coordinates":[-83.468334,42.336922],"type":"Point"}
}