{
  "type": "Feature",
  "properties": {
    "iso:country":"US",
    "sg:address":"7377 Challis Rd",
    "sg:city":"Brighton",
    "sg:classifiers":[
        {
            "category":"Government",
            "subcategory":"Office",
            "type":"Public Place"
        }
    ],
    "sg:phone":"+1 810 227 2968",
    "sg:postcode":"48116",
    "sg:province":"MI",
    "sg:tags":[
        "village"
    ],
    "wof:name":"Brighton City Water Plant",
    "wof:placetype":"venue"
},
  "geometry": {"coordinates":[-83.806089,42.543468],"type":"Point"}
}