{
  "type": "Feature",
  "properties": {
    "iso:country":"US",
    "sg:address":"26581 Beamer St",
    "sg:city":"Harrison Township",
    "sg:classifiers":[
        {
            "category":"Building & Trades",
            "subcategory":"Construction",
            "type":"Services"
        }
    ],
    "sg:phone":"+1 586 463 2659",
    "sg:postcode":"48045",
    "sg:province":"MI",
    "sg:tags":[
        "house"
    ],
    "wof:name":"New Creations Construction",
    "wof:placetype":"venue"
},
  "geometry": {"coordinates":[-82.84411799999999,42.569435],"type":"Point"}
}