{
  "type": "Feature",
  "properties": {
    "iso:country":"US",
    "sg:address":"22390 W 7 Mile Rd",
    "sg:city":"Detroit",
    "sg:classifiers":[
        {
            "category":"Organizations",
            "subcategory":"Membership Organization",
            "type":"Services"
        }
    ],
    "sg:phone":"+1 313 387 1234",
    "sg:postcode":"48219",
    "sg:province":"MI",
    "sg:tags":[
        "profit",
        "rehab",
        "juvenile",
        "center"
    ],
    "wof:name":"Starrvista Inc",
    "wof:placetype":"venue"
},
  "geometry": {"coordinates":[-83.26233499999999,42.429208],"type":"Point"}
}