{
  "type": "Feature",
  "properties": {
    "iso:country":"US",
    "sg:address":"2307 Hill St",
    "sg:city":"Ann Arbor",
    "sg:classifiers":[
        {
            "category":"Banks & Credit Unions",
            "subcategory":"Investment Brokerage",
            "type":"Services"
        }
    ],
    "sg:phone":"+1 734 769 1533",
    "sg:postcode":"48104",
    "sg:province":"MI",
    "sg:tags":[
        "security"
    ],
    "wof:name":"Bacchus Global Assets LLC",
    "wof:placetype":"venue"
},
  "geometry": {"coordinates":[-83.71925400000001,42.273334],"type":"Point"}
}