{
  "type": "Feature",
  "properties": {
    "iso:country":"US",
    "sg:address":"2197 Moon St",
    "sg:city":"Muskegon",
    "sg:classifiers":[
        {
            "category":"Professional",
            "subcategory":"Art Services",
            "type":"Services"
        }
    ],
    "sg:phone":"+1 231 759 1111",
    "sg:postcode":"49441",
    "sg:province":"MI",
    "sg:tags":[
        "graphic",
        "designer"
    ],
    "wof:name":"Interactive Media Design",
    "wof:placetype":"venue"
},
  "geometry": {"coordinates":[-86.29232399999999,43.213109],"type":"Point"}
}