{
  "type": "Feature",
  "properties": {
    "iso:country":"US",
    "sg:address":"3375 Oak Hollow Dr SE",
    "sg:city":"Grand Rapids",
    "sg:classifiers":[
        {
            "category":"Professional",
            "type":"Services"
        }
    ],
    "sg:phone":"+1 616 949 8819",
    "sg:postcode":"49546",
    "sg:province":"MI",
    "sg:tags":[
        "establishment"
    ],
    "wof:name":"Spectre Trading",
    "wof:placetype":"venue"
},
  "geometry": {"coordinates":[-85.58682899999999,42.957542],"type":"Point"}
}