{
  "type": "Feature",
  "properties": {
    "iso:country":"US",
    "sg:address":"2663 44th St SW",
    "sg:city":"Wyoming",
    "sg:classifiers":[
        {
            "category":"Health Services",
            "subcategory":"Doctor",
            "type":"Services"
        }
    ],
    "sg:phone":"+1 616 538 7320",
    "sg:postcode":"49519",
    "sg:province":"MI",
    "sg:tags":[
        "dentist"
    ],
    "wof:name":"John D Bouws DDS",
    "wof:placetype":"venue"
},
  "geometry": {"coordinates":[-85.73172,42.88469],"type":"Point"}
}