{
  "type": "Feature",
  "properties": {
    "iso:country":"US",
    "sg:address":"4956 Stewart Rd",
    "sg:city":"Sterling",
    "sg:classifiers":[
        {
            "category":"Wholesale",
            "subcategory":"Farm Supplies",
            "type":"Manufacturing & Wholesale Goods"
        }
    ],
    "sg:phone":"+1 989 654 2717",
    "sg:postcode":"48659",
    "sg:province":"MI",
    "sg:tags":[
        "bean",
        "broker",
        "dealer"
    ],
    "sg:website":"www.steeleandcompany.com",
    "wof:name":"Steele & Co",
    "wof:placetype":"venue"
},
  "geometry": {"coordinates":[-84.002453,44.054856],"type":"Point"}
}