{
  "type": "Feature",
  "properties": {
    "iso:country":"US",
    "sg:address":"24518 Victory St",
    "sg:city":"Center Line",
    "sg:classifiers":[
        {
            "category":"Building & Trades",
            "subcategory":"Construction",
            "type":"Services"
        }
    ],
    "sg:phone":"+1 586 757 8524",
    "sg:postcode":"48015",
    "sg:province":"MI",
    "sg:tags":[
        "house"
    ],
    "wof:name":"Balch Construction",
    "wof:placetype":"venue"
},
  "geometry": {"coordinates":[-83.018542,42.474297],"type":"Point"}
}