{
  "type": "Feature",
  "properties": {
    "iso:country":"US",
    "sg:address":"325 Garfield St",
    "sg:city":"Iron Mountain",
    "sg:classifiers":[
        {
            "category":"Professional",
            "subcategory":"Engineering",
            "type":"Services"
        }
    ],
    "sg:phone":"+1 906 779 5903",
    "sg:postcode":"49802",
    "sg:province":"MI",
    "sg:tags":[
        "engineer"
    ],
    "wof:name":"Pantti Engineering",
    "wof:placetype":"venue"
},
  "geometry": {"coordinates":[-88.09484999999999,45.792791],"type":"Point"}
}