{
  "type": "Feature",
  "properties": {
    "iso:country":"US",
    "sg:address":"3454 Birchwood Dr",
    "sg:city":"Rogers City",
    "sg:classifiers":[
        {
            "category":"Retail",
            "subcategory":"Repair Shop",
            "type":"Services"
        }
    ],
    "sg:phone":"+1 989 734 7462",
    "sg:postcode":"49779",
    "sg:province":"MI",
    "wof:name":"Barr N Neccessities",
    "wof:placetype":"venue"
},
  "geometry": {"coordinates":[-83.854525,45.438174],"type":"Point"}
}