{
  "type": "Feature",
  "properties": {
    "iso:country":"US",
    "sg:address":"23765 Lawrence Ave",
    "sg:city":"Warren",
    "sg:classifiers":[
        {
            "category":"Real Estate",
            "subcategory":"Real Estate Operator",
            "type":"Services"
        }
    ],
    "sg:phone":"+1 586 756 8280",
    "sg:postcode":"48091",
    "sg:province":"MI",
    "sg:tags":[
        "mobile",
        "home",
        "site",
        "community"
    ],
    "wof:name":"Motor City Trailer Park Inc",
    "wof:placetype":"venue"
},
  "geometry": {"coordinates":[-83.03154499999999,42.469313],"type":"Point"}
}