{
  "type": "Feature",
  "properties": {
    "iso:country":"US",
    "sg:address":"9918 N Tudor Rd",
    "sg:city":"Berrien Springs",
    "sg:classifiers":[
        {
            "category":"Manufacturing",
            "subcategory":"Building Materials",
            "type":"Manufacturing & Wholesale Goods"
        }
    ],
    "sg:phone":"+1 269 471 2351",
    "sg:postcode":"49103",
    "sg:province":"MI",
    "sg:tags":[
        "molding"
    ],
    "sg:website":"www.tafcor.com",
    "wof:name":"Tafcor Inc",
    "wof:placetype":"venue"
},
  "geometry": {"coordinates":[-86.34464699999999,41.939448],"type":"Point"}
}