{
  "type": "Feature",
  "properties": {
    "iso:country":"US",
    "sg:address":"7415 Red Arrow Hwy",
    "sg:city":"Watervliet",
    "sg:classifiers":[
        {
            "category":"Restaurant",
            "type":"Food & Drink"
        }
    ],
    "sg:phone":"+1 269 463 6688",
    "sg:postcode":"49098",
    "sg:province":"MI",
    "wof:name":"Moo's Place",
    "wof:placetype":"venue"
},
  "geometry": {"coordinates":[-86.279848,42.186087],"type":"Point"}
}