{
  "type": "Feature",
  "properties": {
    "iso:country":"US",
    "sg:address":"4288 Dixie Hwy",
    "sg:city":"Waterford",
    "sg:classifiers":[
        {
            "category":"Shopping",
            "subcategory":"Bicycles & Sporting Goods",
            "type":"Retail Goods"
        }
    ],
    "sg:phone":"+1 248 674 8220",
    "sg:postcode":"48329",
    "sg:province":"MI",
    "wof:name":"Summit Sports",
    "wof:placetype":"venue"
},
  "geometry": {"coordinates":[-83.37292600000001,42.680802],"type":"Point"}
}