{
  "type": "Feature",
  "properties": {
    "iso:country":"US",
    "sg:address":"32255 Northwestern Hwy",
    "sg:city":"Farmington Hills",
    "sg:classifiers":[
        {
            "category":"Banks & Credit Unions",
            "subcategory":"Investment Brokerage",
            "type":"Services"
        },
        {
            "category":"Professional",
            "subcategory":"Management & Consulting",
            "type":"Services"
        }
    ],
    "sg:phone":"+1 248 208 8800",
    "sg:postcode":"48334",
    "sg:province":"MI",
    "sg:tags":[
        "advisory",
        "financial",
        "business",
        "consultant"
    ],
    "sg:website":"www.gosrr.com",
    "wof:name":"Stout Risus & Ross Inc",
    "wof:placetype":"venue"
},
  "geometry": {"coordinates":[-83.354669,42.527108],"type":"Point"}
}