{
  "type": "Feature",
  "properties": {
    "iso:country":"US",
    "sg:address":"19731 Van Dyke St",
    "sg:city":"Detroit",
    "sg:classifiers":[
        {
            "category":"Shopping",
            "subcategory":"Department Store",
            "type":"Retail Goods"
        }
    ],
    "sg:phone":"+1 313 892 2830",
    "sg:postcode":"48234",
    "sg:province":"MI",
    "wof:name":"Sounds of City",
    "wof:placetype":"venue"
},
  "geometry": {"coordinates":[-83.02441899999999,42.438854],"type":"Point"}
}