{
  "type": "Feature",
  "properties": {
    "iso:country":"US",
    "sg:address":"1937 Millbank St SE",
    "sg:city":"Grand Rapids",
    "sg:classifiers":[
        {
            "category":"Wholesale",
            "subcategory":"Durable Goods & Equipment",
            "type":"Manufacturing & Wholesale Goods"
        }
    ],
    "sg:phone":"+1 616 452 9878",
    "sg:postcode":"49508",
    "sg:province":"MI",
    "sg:tags":[
        "exporter"
    ],
    "wof:name":"Bob Carpenter & Group Inc",
    "wof:placetype":"venue"
},
  "geometry": {"coordinates":[-85.619581,42.901062],"type":"Point"}
}