{
  "type": "Feature",
  "properties": {
    "iso:country":"US",
    "sg:address":"43613 Buckthorn Ct",
    "sg:city":"Sterling Heights",
    "sg:classifiers":[
        {
            "category":"Professional",
            "subcategory":"Art Services",
            "type":"Services"
        }
    ],
    "sg:phone":"+1 586 726 1430",
    "sg:postcode":"48314",
    "sg:province":"MI",
    "sg:tags":[
        "graphic",
        "design"
    ],
    "wof:name":"Cotter Pin Studio",
    "wof:placetype":"venue"
},
  "geometry": {"coordinates":[-83.07688,42.611934],"type":"Point"}
}