{
  "type": "Feature",
  "properties": {
    "iso:country":"US",
    "sg:address":"4871 Coit Ave NE",
    "sg:city":"Grand Rapids",
    "sg:classifiers":[
        {
            "category":"Wholesale",
            "subcategory":"Toys & Hobbies",
            "type":"Manufacturing & Wholesale Goods"
        }
    ],
    "sg:phone":"+1 616 364 9367",
    "sg:postcode":"49525",
    "sg:province":"MI",
    "sg:tags":[
        "wholesaler"
    ],
    "wof:name":"Fashion Mate Accessories",
    "wof:placetype":"venue"
},
  "geometry": {"coordinates":[-85.62605499999999,43.053472],"type":"Point"}
}