{
  "type": "Feature",
  "properties": {
    "iso:country":"US",
    "sg:address":"3270 Perkins St",
    "sg:city":"Saginaw",
    "sg:classifiers":[
        {
            "category":"Education",
            "subcategory":"School",
            "type":"Public Place"
        }
    ],
    "sg:phone":"+1 989 755 5421",
    "sg:postcode":"48601",
    "sg:province":"MI",
    "wof:name":"Henry A Doerr Child Dev Ctr",
    "wof:placetype":"venue"
},
  "geometry": {"coordinates":[-83.898838,43.421807],"type":"Point"}
}