{
  "type": "Feature",
  "properties": {
    "iso:country":"US",
    "sg:address":"28145 Greenfield Rd",
    "sg:city":"Southfield",
    "sg:classifiers":[
        {
            "category":"Building & Trades",
            "subcategory":"Construction",
            "type":"Services"
        }
    ],
    "sg:phone":"+1 313 864 0008",
    "sg:postcode":"48076",
    "sg:province":"MI",
    "sg:tags":[
        "masonry",
        "contractor"
    ],
    "wof:name":"Custom Mason Contractors",
    "wof:placetype":"venue"
},
  "geometry": {"coordinates":[-83.20291400000001,42.497347],"type":"Point"}
}