{
  "type": "Feature",
  "properties": {
    "iso:country":"US",
    "sg:address":"7946 Main St",
    "sg:city":"Birch Run",
    "sg:classifiers":[
        {
            "category":"Manufacturing",
            "subcategory":"Printing",
            "type":"Manufacturing & Wholesale Goods"
        }
    ],
    "sg:phone":"+1 989 737 7304",
    "sg:postcode":"48415",
    "sg:province":"MI",
    "sg:tags":[
        "commercial"
    ],
    "wof:name":"Coupar Creations",
    "wof:placetype":"venue"
},
  "geometry": {"coordinates":[-83.79561,43.25006],"type":"Point"}
}