{
  "type": "Feature",
  "properties": {
    "iso:country":"US",
    "sg:address":"36547 Goddard Rd",
    "sg:city":"Romulus",
    "sg:classifiers":[
        {
            "category":"Home & Garden",
            "subcategory":"Household Appliances",
            "type":"Retail Goods"
        }
    ],
    "sg:phone":"+1 734 229 0702",
    "sg:postcode":"48174",
    "sg:province":"MI",
    "wof:name":"Appliance Outlet Stores Inc",
    "wof:placetype":"venue"
},
  "geometry": {"coordinates":[-83.396759,42.221823],"type":"Point"}
}