{
  "type": "Feature",
  "properties": {
    "iso:country":"US",
    "sg:address":"10229 S Graham Rd",
    "sg:city":"St Charles",
    "sg:classifiers":[
        {
            "category":"Autos & Motor Vehicles",
            "subcategory":"Automobile Sales",
            "type":"Retail Goods"
        }
    ],
    "sg:phone":"+1 989 865 6969",
    "sg:postcode":"48655",
    "sg:province":"MI",
    "sg:tags":[
        "car",
        "dealer"
    ],
    "wof:name":"Hoerner Used Cars",
    "wof:placetype":"venue"
},
  "geometry": {"coordinates":[-84.153339,43.27491],"type":"Point"}
}