{
  "type": "Feature",
  "properties": {
    "iso:country":"US",
    "sg:address":"45600 S Summit Pkwy",
    "sg:city":"Canton",
    "sg:classifiers":[
        {
            "category":"Sports & Exercise",
            "subcategory":"Golf",
            "type":"Entertainment"
        }
    ],
    "sg:phone":"+1 734 397 6460",
    "sg:postcode":"48187",
    "sg:province":"MI",
    "wof:name":"Canton Township of",
    "wof:placetype":"venue"
},
  "geometry": {"coordinates":[-83.488124,42.292888],"type":"Point"}
}