{
  "type": "Feature",
  "properties": {
    "iso:country":"US",
    "sg:address":"14500 Greenfield Rd",
    "sg:city":"Detroit",
    "sg:classifiers":[
        {
            "category":"Place Of Worship",
            "subcategory":"Church",
            "type":"Public Place"
        },
        {
            "category":"Place Of Worship",
            "type":"Public Place"
        }
    ],
    "sg:phone":"+1 313 659 1990",
    "sg:postcode":"48227",
    "sg:province":"MI",
    "sg:tags":[
        "churches-interdenominational",
        "denomination",
        "churches-various",
        "churches-non-denominational"
    ],
    "wof:name":"Faith Outreach Ministries",
    "wof:placetype":"venue"
},
  "geometry": {"coordinates":[-83.19841,42.394279],"type":"Point"}
}