{
  "type": "Feature",
  "properties": {
    "iso:country":"US",
    "sg:address":"2065 Franklin Rd",
    "sg:city":"Bloomfield Hills",
    "sg:classifiers":[
        {
            "category":"Shopping",
            "type":"Retail Goods"
        }
    ],
    "sg:phone":"+1 248 334 5800",
    "sg:postcode":"48302",
    "sg:province":"MI",
    "sg:tags":[
        "installation",
        "telecommunication"
    ],
    "wof:name":"CTS/UNITEL",
    "wof:placetype":"venue"
},
  "geometry": {"coordinates":[-83.287516,42.607047],"type":"Point"}
}