{
  "type": "Feature",
  "properties": {
    "iso:country":"US",
    "sg:address":"2991 Winesap St NE",
    "sg:city":"Grand Rapids",
    "sg:classifiers":[
        {
            "category":"Professional",
            "type":"Services"
        }
    ],
    "sg:phone":"+1 616 364 8078",
    "sg:postcode":"49525",
    "sg:province":"MI",
    "wof:name":"Outsource Solutions",
    "wof:placetype":"venue"
},
  "geometry": {"coordinates":[-85.596203,43.009189],"type":"Point"}
}