{
  "type": "Feature",
  "properties": {
    "iso:country":"US",
    "sg:address":"5503 Windmill Ct",
    "sg:city":"Lansing",
    "sg:classifiers":[
        {
            "category":"Professional",
            "subcategory":"Employment Agencies",
            "type":"Services"
        }
    ],
    "sg:phone":"+1 517 371 3023",
    "sg:postcode":"48917",
    "sg:province":"MI",
    "wof:name":"Protemps Inc",
    "wof:placetype":"venue"
},
  "geometry": {"coordinates":[-84.627985,42.732909],"type":"Point"}
}