{
  "type": "Feature",
  "properties": {
    "iso:country":"US",
    "sg:address":"104 E Wexford Ave",
    "sg:city":"Buckley",
    "sg:classifiers":[
        {
            "category":"Personal",
            "subcategory":"Beauty Salon",
            "type":"Services"
        }
    ],
    "sg:phone":"+1 231 269 4098",
    "sg:postcode":"49620",
    "sg:province":"MI",
    "wof:name":"Creative Hands Family Haircare",
    "wof:placetype":"venue"
},
  "geometry": {"coordinates":[-85.67692,44.504257],"type":"Point"}
}