{
  "type": "Feature",
  "properties": {
    "iso:country":"US",
    "sg:address":"24310 Country Squire St",
    "sg:city":"Clinton Township",
    "sg:classifiers":[
        {
            "category":"Retail",
            "subcategory":"Repair Shop",
            "type":"Services"
        }
    ],
    "sg:phone":"+1 586 792 6326",
    "sg:postcode":"48035",
    "sg:province":"MI",
    "wof:name":"Digital Imaging Doctors",
    "wof:placetype":"venue"
},
  "geometry": {"coordinates":[-82.866613,42.562109],"type":"Point"}
}