{
  "type": "Feature",
  "properties": {
    "iso:country":"US",
    "sg:address":"29606 Westbrook Pkwy",
    "sg:city":"Southfield",
    "sg:classifiers":[
        {
            "category":"Shopping",
            "subcategory":"Crafts & Fabrics",
            "type":"Retail Goods"
        }
    ],
    "sg:phone":"+1 248 395 2763",
    "sg:postcode":"48076",
    "sg:province":"MI",
    "sg:tags":[
        "sewing"
    ],
    "wof:name":"Stitches In Time",
    "wof:placetype":"venue"
},
  "geometry": {"coordinates":[-83.23662,42.508084],"type":"Point"}
}