{
  "type": "Feature",
  "properties": {
    "iso:country":"US",
    "sg:address":"34770 23 Mile Rd",
    "sg:city":"New Baltimore",
    "sg:classifiers":[
        {
            "category":"Restaurant",
            "type":"Food & Drink"
        }
    ],
    "sg:menulink":"http://www.allmenus.com/mi/chesterfield/142148-subway/menu/",
    "sg:phone":"+1 586 725 4212",
    "sg:postcode":"48047",
    "sg:province":"MI",
    "sg:tags":[
        "american",
        "sandwich"
    ],
    "wof:name":"Subway",
    "wof:placetype":"venue"
},
  "geometry": {"coordinates":[-82.759213,42.675937],"type":"Point"}
}