{
  "type": "Feature",
  "properties": {
    "iso:country":"US",
    "sg:address":"2378 Melton Dr",
    "sg:city":"Howell",
    "sg:classifiers":[
        {
            "category":"Freight",
            "type":"Transportation"
        }
    ],
    "sg:phone":"+1 517 552 0644",
    "sg:postcode":"48843",
    "sg:province":"MI",
    "wof:name":"STG Trucking",
    "wof:placetype":"venue"
},
  "geometry": {"coordinates":[-83.907005,42.612117],"type":"Point"}
}