{
  "type": "Feature",
  "properties": {
    "iso:country":"US",
    "sg:address":"210 Maple St",
    "sg:city":"Big Rapids",
    "sg:classifiers":[
        {
            "category":"Real Estate",
            "subcategory":"Real Estate Agent",
            "type":"Services"
        }
    ],
    "sg:phone":"+1 231 592 0000",
    "sg:postcode":"49307",
    "sg:province":"MI",
    "wof:name":"Circle U Realty",
    "wof:placetype":"venue"
},
  "geometry": {"coordinates":[-85.48189499999999,43.698299],"type":"Point"}
}