{
  "type": "Feature",
  "properties": {
    "iso:country":"US",
    "sg:address":"23025 Old Orchard Trl",
    "sg:city":"Birmingham",
    "sg:classifiers":[
        {
            "category":"Professional",
            "subcategory":"Management & Consulting",
            "type":"Services"
        }
    ],
    "sg:phone":"+1 248 433 1492",
    "sg:postcode":"48025",
    "sg:province":"MI",
    "sg:tags":[
        "pharmacy"
    ],
    "wof:name":"Richard Berchou",
    "wof:placetype":"venue"
},
  "geometry": {"coordinates":[-83.28106,42.523502],"type":"Point"}
}