{
  "type": "Feature",
  "properties": {
    "iso:country":"US",
    "sg:address":"9052 S 13 Rd",
    "sg:city":"Cadillac",
    "sg:classifiers":[
        {
            "category":"Real Estate",
            "subcategory":"Real Estate Agent",
            "type":"Services"
        }
    ],
    "sg:phone":"+1 231 775 2660",
    "sg:postcode":"49601",
    "sg:province":"MI",
    "wof:name":"Paul Bunyan Board Of Realtors",
    "wof:placetype":"venue"
},
  "geometry": {"coordinates":[-85.70013899999999,44.207079],"type":"Point"}
}