{
  "type": "Feature",
  "properties": {
    "iso:country":"US",
    "sg:address":"7145 Perkins 30.5 Rd",
    "sg:city":"Rapid River",
    "sg:classifiers":[
        {
            "category":"Building & Trades",
            "subcategory":"Construction",
            "type":"Services"
        }
    ],
    "sg:phone":"+1 906 474 6075",
    "sg:postcode":"49878",
    "sg:province":"MI",
    "sg:tags":[
        "excavation",
        "contractor"
    ],
    "wof:name":"Rapid Excavating Inc",
    "wof:placetype":"venue"
},
  "geometry": {"coordinates":[-87.006835,45.970878],"type":"Point"}
}