{
  "type": "Feature",
  "properties": {
    "iso:country":"US",
    "sg:address":"4785 State St",
    "sg:city":"Saginaw",
    "sg:classifiers":[
        {
            "category":"Autos & Motor Vehicles",
            "subcategory":"Auto Supplies",
            "type":"Retail Goods"
        }
    ],
    "sg:phone":"+1 989 799 5490",
    "sg:postcode":"48603",
    "sg:province":"MI",
    "sg:tags":[
        "automobile",
        "parts"
    ],
    "wof:name":"West Side Auto Parts",
    "wof:placetype":"venue"
},
  "geometry": {"coordinates":[-84.01157000000001,43.436745],"type":"Point"}
}