{
  "type": "Feature",
  "properties": {
    "iso:country":"US",
    "sg:address":"8449 Old US Hwy 23",
    "sg:city":"Fenton",
    "sg:classifiers":[
        {
            "category":"Restaurant",
            "type":"Food & Drink"
        }
    ],
    "sg:phone":"+1 810 714 4612",
    "sg:postcode":"48430",
    "sg:province":"MI",
    "sg:tags":[
        "caterer"
    ],
    "wof:name":"Sherry's Catering",
    "wof:placetype":"venue"
},
  "geometry": {"coordinates":[-83.763717,42.723084],"type":"Point"}
}