{
  "type": "Feature",
  "properties": {
    "iso:country":"US",
    "sg:address":"26440 Southfield Rd",
    "sg:city":"Lathrup Village",
    "sg:classifiers":[
        {
            "category":"Banks & Credit Unions",
            "subcategory":"Bank",
            "type":"Services"
        }
    ],
    "sg:phone":"+1 248 395 2277",
    "sg:postcode":"48076",
    "sg:province":"MI",
    "sg:tags":[
        "financing"
    ],
    "wof:name":"Victory Automotive League",
    "wof:placetype":"venue"
},
  "geometry": {"coordinates":[-83.22163,42.484501],"type":"Point"}
}