{
  "type": "Feature",
  "properties": {
    "iso:country":"US",
    "sg:address":"3430 Inverary Dr",
    "sg:city":"Lansing",
    "sg:classifiers":[
        {
            "category":"Retail",
            "subcategory":"Repair Shop",
            "type":"Services"
        }
    ],
    "sg:phone":"+1 517 882 6026",
    "sg:postcode":"48911",
    "sg:province":"MI",
    "sg:tags":[
        "medical",
        "telescope"
    ],
    "wof:name":"Clear-Vue Laboratories",
    "wof:placetype":"venue"
},
  "geometry": {"coordinates":[-84.599645,42.704974],"type":"Point"}
}