{
  "type": "Feature",
  "properties": {
    "iso:country":"US",
    "sg:address":"3183 E Bullock Creek Dr",
    "sg:city":"Midland",
    "sg:classifiers":[
        {
            "category":"Home & Garden",
            "subcategory":"Home Furnishings",
            "type":"Retail Goods"
        }
    ],
    "sg:phone":"+1 989 835 9477",
    "sg:postcode":"48640",
    "sg:province":"MI",
    "wof:name":"Daves Special Pottery",
    "wof:placetype":"venue"
},
  "geometry": {"coordinates":[-84.244347,43.579942],"type":"Point"}
}