{
  "type": "Feature",
  "properties": {
    "iso:country":"US",
    "sg:address":"6600 Bloomfield Ln",
    "sg:city":"West Bloomfield",
    "sg:classifiers":[
        {
            "category":"Professional",
            "subcategory":"Business Services",
            "type":"Services"
        }
    ],
    "sg:phone":"+1 248 661 2843",
    "sg:postcode":"48322",
    "sg:province":"MI",
    "wof:name":"Sir Earl Inc",
    "wof:placetype":"venue"
},
  "geometry": {"coordinates":[-83.33272599999999,42.541103],"type":"Point"}
}