{
  "type": "Feature",
  "properties": {
    "iso:country":"US",
    "sg:address":"1155 Jackson Xing",
    "sg:city":"Jackson",
    "sg:classifiers":[
        {
            "category":"Shopping",
            "subcategory":"Gifts & Souvenirs",
            "type":"Retail Goods"
        }
    ],
    "sg:phone":"+1 517 796 0963",
    "sg:postcode":"49202",
    "sg:province":"MI",
    "sg:tags":[
        "shop"
    ],
    "wof:name":"York Country Designs",
    "wof:placetype":"venue"
},
  "geometry": {"coordinates":[-84.433781,42.269565],"type":"Point"}
}