{
  "type": "Feature",
  "properties": {
    "iso:country":"US",
    "sg:address":"22105 Benjamin St",
    "sg:city":"St Clair Shores",
    "sg:classifiers":[
        {
            "category":"Building & Trades",
            "subcategory":"Electrical",
            "type":"Services"
        }
    ],
    "sg:phone":"+1 586 775 0007",
    "sg:postcode":"48081",
    "sg:province":"MI",
    "sg:tags":[
        "electric",
        "contractor"
    ],
    "wof:name":"Larry Hysell Electric",
    "wof:placetype":"venue"
},
  "geometry": {"coordinates":[-82.895421,42.482025],"type":"Point"}
}