{
  "type": "Feature",
  "properties": {
    "iso:country":"US",
    "sg:address":"18411 Avon Ave",
    "sg:city":"Detroit",
    "sg:classifiers":[
        {
            "category":"Banks & Credit Unions",
            "subcategory":"Financial Services",
            "type":"Services"
        }
    ],
    "sg:phone":"+1 313 532 3963",
    "sg:postcode":"48219",
    "sg:province":"MI",
    "sg:tags":[
        "investor"
    ],
    "wof:name":"D Riley Investments",
    "wof:placetype":"venue"
},
  "geometry": {"coordinates":[-83.226473,42.426618],"type":"Point"}
}