{
  "type": "Feature",
  "properties": {
    "iso:country":"US",
    "sg:address":"16 S Smith St",
    "sg:city":"New Buffalo",
    "sg:classifiers":[
        {
            "category":"Shopping",
            "subcategory":"Hobbies, Toys, & Games",
            "type":"Retail Goods"
        }
    ],
    "sg:phone":"+1 269 469 6811",
    "sg:postcode":"49117",
    "sg:province":"MI",
    "wof:name":"I Love Toy Trains",
    "wof:placetype":"venue"
},
  "geometry": {"coordinates":[-86.74682,41.792475],"type":"Point"}
}