{
  "type": "Feature",
  "properties": {
    "iso:country":"US",
    "sg:address":"19109 W Mcnichols Rd",
    "sg:city":"Detroit",
    "sg:classifiers":[
        {
            "category":"Restaurant",
            "type":"Food & Drink"
        }
    ],
    "sg:menulink":"http://www.allmenus.com/mi/detroit/248062-l-georges-coney-island/menu/",
    "sg:phone":"+1 313 533 7645",
    "sg:postcode":"48219",
    "sg:province":"MI",
    "sg:tags":[
        "american",
        "diner"
    ],
    "wof:name":"L. Georges Coney Island",
    "wof:placetype":"venue"
},
  "geometry": {"coordinates":[-83.229427,42.415339],"type":"Point"}
}