{
  "type": "Feature",
  "properties": {
    "iso:country":"US",
    "sg:address":"26523 Little Mack Ave",
    "sg:city":"Saint Clair Shores",
    "sg:classifiers":[
        {
            "category":"Cinema",
            "subcategory":"Movie Rental",
            "type":"Entertainment"
        }
    ],
    "sg:phone":"+1 586 773 0730",
    "sg:postcode":"48081",
    "sg:province":"MI",
    "sg:tags":[
        "video",
        "tape"
    ],
    "wof:name":"Video Castle",
    "wof:placetype":"venue"
},
  "geometry": {"coordinates":[-82.907501,42.488154],"type":"Point"}
}