{
  "type": "Feature",
  "properties": {
    "iso:country":"US",
    "sg:address":"11607 Telegraph Rd",
    "sg:city":"Taylor",
    "sg:classifiers":[
        {
            "category":"Shopping",
            "subcategory":"Mobile Phones",
            "type":"Retail Goods"
        }
    ],
    "sg:phone":"+1 313 357 2498",
    "sg:postcode":"48180",
    "sg:province":"MI",
    "wof:name":"New Age Communications",
    "wof:placetype":"venue"
},
  "geometry": {"coordinates":[-83.2687,42.222698],"type":"Point"}
}