{
  "type": "Feature",
  "properties": {
    "iso:country":"US",
    "sg:address":"2117 Jones Rd",
    "sg:city":"Waterford",
    "sg:classifiers":[
        {
            "category":"Retail",
            "subcategory":"Repair Shop",
            "type":"Services"
        }
    ],
    "sg:phone":"+1 248 618 9140",
    "sg:postcode":"48327",
    "sg:province":"MI",
    "wof:name":"R & B Pump Technologies",
    "wof:placetype":"venue"
},
  "geometry": {"coordinates":[-83.403274,42.668253],"type":"Point"}
}