{
  "type": "Feature",
  "properties": {
    "iso:country":"US",
    "sg:address":"455 Skeel Ave",
    "sg:city":"Harrison Township",
    "sg:classifiers":[
        {
            "category":"Professional",
            "subcategory":"Business Services",
            "type":"Services"
        }
    ],
    "sg:phone":"+1 586 469 0104",
    "sg:postcode":"48045",
    "sg:province":"MI",
    "sg:tags":[
        "department",
        "manager",
        "volunteer"
    ],
    "wof:name":"Lori Grein",
    "wof:placetype":"venue"
},
  "geometry": {"coordinates":[-82.80665,42.606132],"type":"Point"}
}