{
  "type": "Feature",
  "properties": {
    "iso:country":"US",
    "sg:address":"838 4th Ave",
    "sg:city":"Lake Odessa",
    "sg:classifiers":[
        {
            "category":"Food & Beverages",
            "subcategory":"Groceries & Convenience Stores",
            "type":"Retail Goods"
        }
    ],
    "sg:phone":"+1 616 374 8879",
    "sg:postcode":"48849",
    "sg:province":"MI",
    "sg:tags":[
        "grocer"
    ],
    "wof:name":"Carl's Super Market Inc",
    "wof:placetype":"venue"
},
  "geometry": {"coordinates":[-85.138071,42.780569],"type":"Point"}
}