{
  "type": "Feature",
  "properties": {
    "iso:country":"US",
    "sg:address":"4635 N Mission Rd",
    "sg:city":"Rosebush",
    "sg:classifiers":[
        {
            "category":"Travel",
            "subcategory":"Hotels & Motels",
            "type":"Entertainment"
        }
    ],
    "sg:phone":"+1 989 433 5341",
    "sg:postcode":"48878",
    "sg:province":"MI",
    "sg:tags":[
        "operation"
    ],
    "wof:name":"White Wagon Motel",
    "wof:placetype":"venue"
},
  "geometry": {"coordinates":[-84.767911,43.704213],"type":"Point"}
}