{
  "type": "Feature",
  "properties": {
    "iso:country":"US",
    "sg:address":"4100 Capitol City Blvd",
    "sg:city":"Lansing",
    "sg:classifiers":[
        {
            "category":"Retail",
            "subcategory":"Auto Rental",
            "type":"Services"
        }
    ],
    "sg:phone":"+1 517 321 1445",
    "sg:postcode":"48906",
    "sg:province":"MI",
    "sg:tags":[
        "passenger",
        "car"
    ],
    "wof:name":"Hertz",
    "wof:placetype":"venue"
},
  "geometry": {"coordinates":[-84.588982,42.774635],"type":"Point"}
}