{
  "type": "Feature",
  "properties": {
    "iso:country":"US",
    "sg:address":"6000 Stanford St",
    "sg:city":"Detroit",
    "sg:classifiers":[
        {
            "category":"Organizations",
            "subcategory":"Non-profit Organization",
            "type":"Services"
        }
    ],
    "sg:phone":"+1 313 894 7570",
    "sg:postcode":"48210",
    "sg:province":"MI",
    "sg:tags":[
        "social"
    ],
    "wof:name":"Spivey Community Redevelopment",
    "wof:placetype":"venue"
},
  "geometry": {"coordinates":[-83.114378,42.349903],"type":"Point"}
}