{
  "type": "Feature",
  "properties": {
    "iso:country":"US",
    "sg:address":"2442 Douglas Dr",
    "sg:city":"Prescott",
    "sg:classifiers":[
        {
            "category":"Professional",
            "subcategory":"Business Services",
            "type":"Services"
        }
    ],
    "sg:phone":"+1 989 873 8065",
    "sg:postcode":"48756",
    "sg:province":"MI",
    "wof:name":"All Around Power Washing",
    "wof:placetype":"venue"
},
  "geometry": {"coordinates":[-84.027288,44.218107],"type":"Point"}
}