{
  "type": "Feature",
  "properties": {
    "iso:country":"US",
    "sg:address":"3827 Luoma Rd",
    "sg:city":"Chatham",
    "sg:classifiers":[
        {
            "category":"Retail",
            "subcategory":"Auto Repair",
            "type":"Services"
        }
    ],
    "sg:phone":"+1 906 387 5120",
    "sg:postcode":"49816",
    "sg:province":"MI",
    "sg:tags":[
        "automotive"
    ],
    "wof:name":"Daniel Boone Performance",
    "wof:placetype":"venue"
},
  "geometry": {"coordinates":[-86.927532,46.325726],"type":"Point"}
}