{
  "type": "Feature",
  "properties": {
    "iso:country":"US",
    "sg:address":"10631 Dix",
    "sg:city":"Dearborn",
    "sg:classifiers":[
        {
            "category":"Food & Beverages",
            "subcategory":"Meat & Fish",
            "type":"Retail Goods"
        }
    ],
    "sg:phone":"+1 313 843 1225",
    "sg:postcode":"48120",
    "sg:province":"MI",
    "sg:tags":[
        "shop"
    ],
    "wof:name":"Islamic Market",
    "wof:placetype":"venue"
},
  "geometry": {"coordinates":[-83.146708,42.301379],"type":"Point"}
}