{
  "type": "Feature",
  "properties": {
    "iso:country":"US",
    "sg:address":"25200 Mound Rd",
    "sg:city":"Warren",
    "sg:classifiers":[
        {
            "category":"Wholesale",
            "subcategory":"Groceries",
            "type":"Manufacturing & Wholesale Goods"
        }
    ],
    "sg:phone":"+1 586 756 7422",
    "sg:postcode":"48091",
    "sg:province":"MI",
    "sg:tags":[
        "food",
        "broker"
    ],
    "wof:name":"ABC Food Broker",
    "wof:placetype":"venue"
},
  "geometry": {"coordinates":[-83.045198,42.477497],"type":"Point"}
}