{
  "type": "Feature",
  "properties": {
    "iso:country":"US",
    "sg:address":"115 W Shawnee St",
    "sg:city":"Tecumseh",
    "sg:classifiers":[
        {
            "category":"Professional",
            "type":"Services"
        }
    ],
    "sg:phone":"+1 517 423 7926",
    "sg:postcode":"49286",
    "sg:province":"MI",
    "wof:name":"B & B Specialist Services",
    "wof:placetype":"venue"
},
  "geometry": {"coordinates":[-83.946911,42.006888],"type":"Point"}
}