{
  "type": "Feature",
  "properties": {
    "iso:country":"US",
    "sg:address":"1700 N Drake Rd",
    "sg:city":"Kalamazoo",
    "sg:classifiers":[
        {
            "category":"Organizations",
            "subcategory":"Religious Organization",
            "type":"Services"
        }
    ],
    "sg:phone":"+1 269 381 6658",
    "sg:postcode":"49006",
    "sg:province":"MI",
    "wof:name":"Westwood Bptst Chrch Kalamazoo",
    "wof:placetype":"venue"
},
  "geometry": {"coordinates":[-85.64804100000001,42.309636],"type":"Point"}
}