{
  "type": "Feature",
  "properties": {
    "iso:country":"US",
    "sg:address":"306 S Main St",
    "sg:city":"Linden",
    "sg:classifiers":[
        {
            "category":"Social Services",
            "subcategory":"Child Care",
            "type":"Services"
        }
    ],
    "sg:phone":"+1 810 735 5080",
    "sg:postcode":"48451",
    "sg:province":"MI",
    "wof:name":"Linden Children's Ctr",
    "wof:placetype":"venue"
},
  "geometry": {"coordinates":[-83.78101599999999,42.812428],"type":"Point"}
}