{
  "type": "Feature",
  "properties": {
    "iso:country":"US",
    "sg:address":"4360 Willow Oak Ct",
    "sg:city":"Grand Blanc",
    "sg:classifiers":[
        {
            "category":"Professional",
            "subcategory":"Business Services",
            "type":"Services"
        }
    ],
    "sg:phone":"+1 810 743 0797",
    "sg:postcode":"48439",
    "sg:province":"MI",
    "wof:name":"Jrt Enterprises",
    "wof:placetype":"venue"
},
  "geometry": {"coordinates":[-83.605318,42.965748],"type":"Point"}
}