{
  "type": "Feature",
  "properties": {
    "iso:country":"US",
    "sg:address":"39526 Chantilly Dr",
    "sg:city":"Sterling Heights",
    "sg:classifiers":[
        {
            "category":"Professional",
            "subcategory":"Business Services",
            "type":"Services"
        }
    ],
    "sg:phone":"+1 586 979 6464",
    "sg:postcode":"48313",
    "sg:province":"MI",
    "wof:name":"Mr Build Home Inspections",
    "wof:placetype":"venue"
},
  "geometry": {"coordinates":[-83.002555,42.584039],"type":"Point"}
}