{
  "type": "Feature",
  "properties": {
    "iso:country":"US",
    "sg:address":"11533 E 12 Mile Rd",
    "sg:city":"Warren",
    "sg:classifiers":[
        {
            "category":"Personal",
            "subcategory":"Nail Salon",
            "type":"Services"
        }
    ],
    "sg:phone":"+1 586 576 0101",
    "sg:postcode":"48093",
    "sg:province":"MI",
    "wof:name":"Brenda's Nails",
    "wof:placetype":"venue"
},
  "geometry": {"coordinates":[-83.00788799999999,42.507208],"type":"Point"}
}