{
  "type": "Feature",
  "properties": {
    "iso:country":"US",
    "sg:address":"9486 Dow Rd",
    "sg:city":"Mulliken",
    "sg:classifiers":[
        {
            "category":"Organizations",
            "subcategory":"Religious Organization",
            "type":"Services"
        }
    ],
    "sg:phone":"+1 517 566 6505",
    "sg:postcode":"48861",
    "sg:province":"MI",
    "wof:name":"Tinsel Oil By Barbara Bosworth",
    "wof:placetype":"venue"
},
  "geometry": {"coordinates":[-84.955962,42.705101],"type":"Point"}
}