{
  "type": "Feature",
  "properties": {
    "iso:country":"US",
    "sg:address":"3922 Lake Michigan Dr NW",
    "sg:city":"Grand Rapids",
    "sg:classifiers":[
        {
            "category":"Restaurant",
            "type":"Food & Drink"
        }
    ],
    "sg:phone":"+1 616 735 0781",
    "sg:postcode":"49544",
    "sg:province":"MI",
    "wof:name":"Wendy's",
    "wof:placetype":"venue"
},
  "geometry": {"coordinates":[-85.766409,42.97219],"type":"Point"}
}