{
  "type": "Feature",
  "properties": {
    "iso:country":"US",
    "sg:address":"173 Burr Oak Dr",
    "sg:city":"Spring Arbor",
    "sg:classifiers":[
        {
            "category":"Manufacturing",
            "subcategory":"Glass & Minerals",
            "type":"Manufacturing & Wholesale Goods"
        }
    ],
    "sg:phone":"+1 517 750 1274",
    "sg:postcode":"49283",
    "sg:province":"MI",
    "sg:tags":[
        "product",
        "nonmetallic",
        "mfg"
    ],
    "wof:name":"Golden Anvil",
    "wof:placetype":"venue"
},
  "geometry": {"coordinates":[-84.55830899999999,42.200965],"type":"Point"}
}