{
  "type": "Feature",
  "properties": {
    "iso:country":"US",
    "sg:address":"3090 Shirley Dr",
    "sg:city":"Jackson",
    "sg:classifiers":[
        {
            "category":"Personal",
            "type":"Services"
        }
    ],
    "sg:phone":"+1 517 414 9962",
    "sg:postcode":"49201",
    "sg:province":"MI",
    "sg:tags":[
        "program",
        "physical",
        "exercise",
        "fitness"
    ],
    "wof:name":"Dana's Workouts",
    "wof:placetype":"venue"
},
  "geometry": {"coordinates":[-84.43117700000001,42.286629],"type":"Point"}
}