{
  "type": "Feature",
  "properties": {
    "iso:country":"US",
    "sg:address":"3232 Fashion Square Blvd",
    "sg:city":"Saginaw",
    "sg:classifiers":[
        {
            "category":"Banks & Credit Unions",
            "subcategory":"Bank",
            "type":"Services"
        }
    ],
    "sg:phone":"+1 989 792 8700",
    "sg:postcode":"48603",
    "sg:province":"MI",
    "sg:tags":[
        "mortgage"
    ],
    "wof:name":"Advanced Mortgage & Financial",
    "wof:placetype":"venue"
},
  "geometry": {"coordinates":[-83.96942199999999,43.457738],"type":"Point"}
}