{
  "type": "Feature",
  "properties": {
    "iso:country":"US",
    "sg:address":"1394 E Bristol Rd",
    "sg:city":"Burton",
    "sg:classifiers":[
        {
            "category":"Professional",
            "subcategory":"Business Services",
            "type":"Services"
        }
    ],
    "sg:phone":"+1 810 744 2266",
    "sg:postcode":"48529",
    "sg:province":"MI",
    "wof:name":"Bea Cobb's Monogram Shop",
    "wof:placetype":"venue"
},
  "geometry": {"coordinates":[-83.67706800000001,42.974261],"type":"Point"}
}