{
  "type": "Feature",
  "properties": {
    "iso:country":"US",
    "sg:address":"38555 Mound Rd",
    "sg:city":"Sterling Heights",
    "sg:classifiers":[
        {
            "category":"Insurance",
            "subcategory":"Insurance Agent",
            "type":"Services"
        }
    ],
    "sg:phone":"+1 586 276 2826",
    "sg:postcode":"48310",
    "sg:province":"MI",
    "wof:name":"Special Risk Factor",
    "wof:placetype":"venue"
},
  "geometry": {"coordinates":[-83.05006899999999,42.576215],"type":"Point"}
}