{
  "type": "Feature",
  "properties": {
    "iso:country":"US",
    "sg:address":"3058 N State Rd Ste B",
    "sg:city":"Davison",
    "sg:classifiers":[
        {
            "category":"Retail",
            "subcategory":"Veterinary Services",
            "type":"Services"
        }
    ],
    "sg:phone":"+1 810 412 4700",
    "sg:postcode":"48423",
    "sg:province":"MI",
    "sg:tags":[
        "veterinarian"
    ],
    "wof:name":"Childs Veterinary Clinic",
    "wof:placetype":"venue"
},
  "geometry": {"coordinates":[-83.51777199999999,43.050666],"type":"Point"}
}