{
  "type": "Feature",
  "properties": {
    "iso:country":"US",
    "sg:address":"200 W Ludington St",
    "sg:city":"Iron Mountain",
    "sg:classifiers":[
        {
            "category":"Organizations",
            "subcategory":"Non-profit Organization",
            "type":"Services"
        }
    ],
    "sg:phone":"+1 906 779 9435",
    "sg:postcode":"49801",
    "sg:province":"MI",
    "sg:tags":[
        "information",
        "alcoholism",
        "treatment"
    ],
    "wof:name":"Reflection",
    "wof:placetype":"venue"
},
  "geometry": {"coordinates":[-88.06975,45.820355],"type":"Point"}
}