{
  "type": "Feature",
  "properties": {
    "iso:country":"US",
    "sg:address":"15803 S Lowell Rd",
    "sg:city":"Lansing",
    "sg:classifiers":[
        {
            "category":"Personal",
            "type":"Services"
        }
    ],
    "sg:phone":"+1 517 410 6750",
    "sg:postcode":"48906",
    "sg:province":"MI",
    "wof:name":"Rental Guide Inc",
    "wof:placetype":"venue"
},
  "geometry": {"coordinates":[-84.641884,42.793238],"type":"Point"}
}