{
  "type": "Feature",
  "properties": {
    "iso:country":"US",
    "sg:address":"5121 Woodview Ct",
    "sg:city":"Dearborn",
    "sg:classifiers":[
        {
            "category":"Health Services",
            "subcategory":"Doctor",
            "type":"Services"
        }
    ],
    "sg:phone":"+1 313 441 6583",
    "sg:postcode":"48126",
    "sg:province":"MI",
    "sg:tags":[
        "medical"
    ],
    "wof:name":"Bohra Bs MD PC",
    "wof:placetype":"venue"
},
  "geometry": {"coordinates":[-83.229964,42.324269],"type":"Point"}
}