{
  "type": "Feature",
  "properties": {
    "iso:country":"US",
    "sg:address":"3608 Centennial Dr",
    "sg:city":"Midland",
    "sg:classifiers":[
        {
            "category":"Building & Trades",
            "subcategory":"Construction",
            "type":"Services"
        }
    ],
    "sg:phone":"+1 989 496 9300",
    "sg:postcode":"48642",
    "sg:province":"MI",
    "sg:tags":[
        "new",
        "residential"
    ],
    "wof:name":"DCM Construction Inc",
    "wof:placetype":"venue"
},
  "geometry": {"coordinates":[-84.185667,43.600042],"type":"Point"}
}