{
  "type": "Feature",
  "properties": {
    "iso:country":"US",
    "sg:address":"38785 Plumbrook Dr",
    "sg:city":"Farmington Hills",
    "sg:classifiers":[
        {
            "category":"Wholesale",
            "subcategory":"Machinery & Supplies",
            "type":"Manufacturing & Wholesale Goods"
        }
    ],
    "sg:phone":"+1 248 489 9553",
    "sg:postcode":"48331",
    "sg:province":"MI",
    "wof:name":"John Miller Machine Sales",
    "wof:placetype":"venue"
},
  "geometry": {"coordinates":[-83.43561099999999,42.502254],"type":"Point"}
}