{
  "type": "Feature",
  "properties": {
    "iso:country":"US",
    "sg:address":"7300 Hickory Ridge Rd",
    "sg:city":"Holly",
    "sg:classifiers":[
        {
            "category":"Organizations",
            "subcategory":"Community Association",
            "type":"Services"
        }
    ],
    "sg:phone":"+1 248 887 4533",
    "sg:postcode":"48442",
    "sg:province":"MI",
    "wof:name":"Camp Ohiyesa YMCA",
    "wof:placetype":"venue"
},
  "geometry": {"coordinates":[-83.66435199999999,42.700736],"type":"Point"}
}