{
  "type": "Feature",
  "properties": {
    "iso:country":"US",
    "sg:address":"601 S Grand Traverse St",
    "sg:city":"Flint",
    "sg:classifiers":[
        {
            "category":"Professional",
            "subcategory":"Lawyer & Legal Services",
            "type":"Services"
        }
    ],
    "sg:phone":"+1 810 767 9400",
    "sg:postcode":"48502",
    "sg:province":"MI",
    "wof:name":"Cianciosi Lawrence D Atty",
    "wof:placetype":"venue"
},
  "geometry": {"coordinates":[-83.693398,43.013],"type":"Point"}
}