{
  "type": "Feature",
  "properties": {
    "iso:country":"US",
    "sg:address":"20889 Hampton Rd",
    "sg:city":"Harper Woods",
    "sg:classifiers":[
        {
            "category":"Building & Trades",
            "subcategory":"Construction",
            "type":"Services"
        }
    ],
    "sg:phone":"+1 586 360 7564",
    "sg:postcode":"48225",
    "sg:province":"MI",
    "sg:tags":[
        "hanging",
        "contractor"
    ],
    "wof:name":"Pinnacle Painting",
    "wof:placetype":"venue"
},
  "geometry": {"coordinates":[-82.912913,42.449752],"type":"Point"}
}