{
  "type": "Feature",
  "properties": {
    "iso:country":"US",
    "sg:address":"427 N 3rd St",
    "sg:city":"Marquette",
    "sg:classifiers":[
        {
            "category":"Insurance",
            "subcategory":"Hazard Insurance",
            "type":"Services"
        }
    ],
    "sg:phone":"+1 906 226 3965",
    "sg:postcode":"49855",
    "sg:province":"MI",
    "sg:tags":[
        "carrier"
    ],
    "wof:name":"Pia Inc",
    "wof:placetype":"venue"
},
  "geometry": {"coordinates":[-87.39480500000001,46.546889],"type":"Point"}
}