{
  "type": "Feature",
  "properties": {
    "iso:country":"US",
    "sg:address":"636 Forest St",
    "sg:city":"Charlotte",
    "sg:classifiers":[
        {
            "category":"Building & Trades",
            "subcategory":"Construction",
            "type":"Services"
        }
    ],
    "sg:phone":"+1 517 543 1075",
    "sg:postcode":"48813",
    "sg:province":"MI",
    "sg:tags":[
        "residential"
    ],
    "wof:name":"Sam Loves Construction",
    "wof:placetype":"venue"
},
  "geometry": {"coordinates":[-84.840935,42.574747],"type":"Point"}
}