{
  "type": "Feature",
  "properties": {
    "iso:country":"US",
    "sg:address":"15610 Stuart Rd",
    "sg:city":"Chesaning",
    "sg:classifiers":[
        {
            "category":"Building & Trades",
            "subcategory":"Construction",
            "type":"Services"
        }
    ],
    "sg:phone":"+1 989 845 5283",
    "sg:postcode":"48616",
    "sg:province":"MI",
    "sg:tags":[
        "contractor"
    ],
    "wof:name":"Rick Moore",
    "wof:placetype":"venue"
},
  "geometry": {"coordinates":[-84.090287,43.194338],"type":"Point"}
}