{
  "type": "Feature",
  "properties": {
    "iso:country":"US",
    "sg:address":"1517 66th St",
    "sg:city":"Fennville",
    "sg:classifiers":[
        {
            "category":"Shopping",
            "type":"Retail Goods"
        }
    ],
    "sg:phone":"+1 269 227 3715",
    "sg:postcode":"49408",
    "sg:province":"MI",
    "sg:tags":[
        "awning",
        "canopy"
    ],
    "sg:website":"www.midwestgroundcovers.com",
    "wof:name":"Midwest Groundcovers",
    "wof:placetype":"venue"
},
  "geometry": {"coordinates":[-86.188659,42.533608],"type":"Point"}
}