{
  "type": "Feature",
  "properties": {
    "iso:country":"US",
    "sg:address":"22431 Gratiot Ave",
    "sg:city":"Eastpointe",
    "sg:classifiers":[
        {
            "category":"Personal",
            "subcategory":"Beauty Salon",
            "type":"Services"
        }
    ],
    "sg:phone":"+1 586 776 5270",
    "sg:postcode":"48021",
    "sg:province":"MI",
    "wof:name":"Grondin's Hair Ctr",
    "wof:placetype":"venue"
},
  "geometry": {"coordinates":[-82.959744,42.462271],"type":"Point"}
}