{
  "type": "Feature",
  "properties": {
    "iso:country":"US",
    "sg:address":"4500 Villa France Dr",
    "sg:city":"Brighton",
    "sg:classifiers":[
        {
            "category":"Utilities",
            "subcategory":"Telephone",
            "type":"Services"
        }
    ],
    "sg:phone":"+1 810 225 7627",
    "sg:postcode":"48116",
    "sg:province":"MI",
    "sg:tags":[
        "company"
    ],
    "wof:name":"A T & T",
    "wof:placetype":"venue"
},
  "geometry": {"coordinates":[-83.849942,42.530504],"type":"Point"}
}