{
  "type": "Feature",
  "properties": {
    "iso:country":"US",
    "sg:address":"700 Tower Dr",
    "sg:city":"Troy",
    "sg:classifiers":[
        {
            "category":"Professional",
            "subcategory":"Employment Agencies",
            "type":"Services"
        }
    ],
    "sg:phone":"+1 248 879 9723",
    "sg:postcode":"48098",
    "sg:province":"MI",
    "wof:name":"Defined Employee Management Inc",
    "wof:placetype":"venue"
},
  "geometry": {"coordinates":[-83.16400299999999,42.592411],"type":"Point"}
}