{
  "type": "Feature",
  "properties": {
    "iso:country":"US",
    "sg:address":"15873 Middlebelt Rd Ste 100",
    "sg:city":"Livonia",
    "sg:classifiers":[
        {
            "category":"Health Services",
            "subcategory":"Dentist",
            "type":"Services"
        }
    ],
    "sg:phone":"+1 734 425 4400",
    "sg:postcode":"48154",
    "sg:province":"MI",
    "sg:website":"www.jamesstewart.wordpress.com",
    "wof:name":"James R. Stewart Jr., DDS",
    "wof:placetype":"venue"
},
  "geometry": {"coordinates":[-83.334807,42.403877],"type":"Point"}
}