{
  "type": "Feature",
  "properties": {
    "iso:country":"US",
    "sg:address":"2380 Oak Valley Dr",
    "sg:city":"Ann Arbor",
    "sg:classifiers":[
        {
            "category":"Social Services",
            "subcategory":"Child Care",
            "type":"Services"
        }
    ],
    "sg:phone":"+1 734 996 9352",
    "sg:postcode":"48108",
    "sg:province":"MI",
    "sg:tags":[
        "day",
        "preschool"
    ],
    "wof:name":"Tutor Time International Inc",
    "wof:placetype":"venue"
},
  "geometry": {"coordinates":[-83.754729,42.235774],"type":"Point"}
}