{
  "type": "Feature",
  "properties": {
    "iso:country":"US",
    "sg:address":"109 E Upton Ave",
    "sg:city":"Reed City",
    "sg:classifiers":[
        {
            "category":"Insurance",
            "subcategory":"Insurance Agent",
            "type":"Services"
        }
    ],
    "sg:phone":"+1 231 832 3214",
    "sg:postcode":"49677",
    "sg:province":"MI",
    "wof:name":"Hinkle-Witbeck Insurance Agcy",
    "wof:placetype":"venue"
},
  "geometry": {"coordinates":[-85.509434,43.875894],"type":"Point"}
}