{
  "type": "Feature",
  "properties": {
    "iso:country":"US",
    "sg:address":"4755 Rochester Rd",
    "sg:city":"Troy",
    "sg:classifiers":[
        {
            "category":"Manufacturing",
            "subcategory":"Metals",
            "type":"Manufacturing & Wholesale Goods"
        }
    ],
    "sg:phone":"+1 248 689 7373",
    "sg:postcode":"48085",
    "sg:province":"MI",
    "sg:tags":[
        "automotive",
        "stampings"
    ],
    "sg:website":"www.versatubecorp.com",
    "wof:name":"Versatube Corp",
    "wof:placetype":"venue"
},
  "geometry": {"coordinates":[-83.128911,42.59003],"type":"Point"}
}