{
  "type": "Feature",
  "properties": {
    "iso:country":"US",
    "sg:address":"22777 Harper Ave",
    "sg:city":"St Clair Shores",
    "sg:classifiers":[
        {
            "category":"Organizations",
            "subcategory":"Labor Organization",
            "type":"Services"
        }
    ],
    "sg:phone":"+1 586 777 4787",
    "sg:postcode":"48080",
    "sg:province":"MI",
    "wof:name":"Office & Professional Employee",
    "wof:placetype":"venue"
},
  "geometry": {"coordinates":[-82.909071,42.463262],"type":"Point"}
}