{
  "type": "Feature",
  "properties": {
    "iso:country":"US",
    "sg:address":"1105 6th St",
    "sg:city":"Traverse City",
    "sg:classifiers":[
        {
            "category":"Health Services",
            "subcategory":"Clinic",
            "type":"Services"
        }
    ],
    "sg:phone":"+1 231 935 6449",
    "sg:postcode":"49684",
    "sg:province":"MI",
    "sg:tags":[
        "wellness",
        "program"
    ],
    "wof:name":"Munson Wellness Programs",
    "wof:placetype":"venue"
},
  "geometry": {"coordinates":[-85.64219900000001,44.761563],"type":"Point"}
}