{
  "type": "Feature",
  "properties": {
    "iso:country":"US",
    "sg:address":"233 Butler St",
    "sg:city":"Saugatuck",
    "sg:classifiers":[
        {
            "category":"Home & Garden",
            "subcategory":"Furniture",
            "type":"Retail Goods"
        }
    ],
    "sg:phone":"+1 269 857 3941",
    "sg:postcode":"49453",
    "sg:province":"MI",
    "wof:name":"Oosting Furniture & Appliances",
    "wof:placetype":"venue"
},
  "geometry": {"coordinates":[-86.204027,42.656298],"type":"Point"}
}