{
  "type": "Feature",
  "properties": {
    "iso:country":"US",
    "sg:address":"6952 John R Rd",
    "sg:city":"Troy",
    "sg:classifiers":[
        {
            "category":"Social Services",
            "subcategory":"Child Care",
            "type":"Services"
        }
    ],
    "sg:phone":"+1 248 879 8097",
    "sg:postcode":"48085",
    "sg:province":"MI",
    "sg:tags":[
        "elementary",
        "school",
        "day"
    ],
    "wof:name":"Troy Little Scholars",
    "wof:placetype":"venue"
},
  "geometry": {"coordinates":[-83.110603,42.622799],"type":"Point"}
}