{
  "type": "Feature",
  "properties": {
    "iso:country":"US",
    "sg:address":"24840 Cooke St",
    "sg:city":"Dearborn",
    "sg:classifiers":[
        {
            "category":"Manufacturing",
            "subcategory":"Jewelry",
            "type":"Manufacturing & Wholesale Goods"
        }
    ],
    "sg:phone":"+1 313 278 0384",
    "sg:postcode":"48124",
    "sg:province":"MI",
    "sg:tags":[
        "costume",
        "mfg"
    ],
    "wof:name":"All That Snazz",
    "wof:placetype":"venue"
},
  "geometry": {"coordinates":[-83.27923199999999,42.295135],"type":"Point"}
}