{
  "type": "Feature",
  "properties": {
    "iso:country":"US",
    "sg:address":"603 Minnesota Ave",
    "sg:city":"Gladstone",
    "sg:classifiers":[
        {
            "category":"Personal",
            "subcategory":"Barber",
            "type":"Services"
        }
    ],
    "sg:phone":"+1 906 428 9218",
    "sg:postcode":"49837",
    "sg:province":"MI",
    "sg:tags":[
        "shop"
    ],
    "wof:name":"Barber",
    "wof:placetype":"venue"
},
  "geometry": {"coordinates":[-87.015685,45.847443],"type":"Point"}
}