{
  "type": "Feature",
  "properties": {
    "iso:country":"US",
    "sg:address":"501 W Bridge St",
    "sg:city":"Big Rapids",
    "sg:classifiers":[
        {
            "category":"Education",
            "subcategory":"School",
            "type":"Public Place"
        }
    ],
    "sg:phone":"+1 231 796 6234",
    "sg:postcode":"49307",
    "sg:province":"MI",
    "sg:website":"www.brps.k12.mi.us",
    "wof:name":"Hillcrest Elementary School",
    "wof:placetype":"venue"
},
  "geometry": {"coordinates":[-85.490437,43.70594],"type":"Point"}
}