{
  "type": "Feature",
  "properties": {
    "iso:country":"US",
    "sg:address":"6103 S Westnedge Ave",
    "sg:city":"Portage",
    "sg:classifiers":[
        {
            "category":"Retail",
            "subcategory":"Auto Repair",
            "type":"Services"
        }
    ],
    "sg:phone":"+1 269 323 0034",
    "sg:postcode":"49002",
    "sg:province":"MI",
    "sg:tags":[
        "repairing",
        "automobile"
    ],
    "wof:name":"Lentz USA Svc Ctr Inc",
    "wof:placetype":"venue"
},
  "geometry": {"coordinates":[-85.58942999999999,42.226082],"type":"Point"}
}