{
  "type": "Feature",
  "properties": {
    "iso:country":"US",
    "sg:address":"2892 E Maple Rd",
    "sg:city":"Troy",
    "sg:classifiers":[
        {
            "category":"Building & Trades",
            "subcategory":"Equipment Rental",
            "type":"Services"
        }
    ],
    "sg:phone":"+1 248 588 1972",
    "sg:postcode":"48083",
    "sg:province":"MI",
    "wof:name":"U Save Rental Inc",
    "wof:placetype":"venue"
},
  "geometry": {"coordinates":[-83.09045999999999,42.549231],"type":"Point"}
}