{
  "type": "Feature",
  "properties": {
    "iso:country":"US",
    "sg:address":"1190 W Newberg Rd",
    "sg:city":"Pinconning",
    "sg:classifiers":[
        {
            "category":"Farming",
            "subcategory":"Farm",
            "type":"Manufacturing & Wholesale Goods"
        }
    ],
    "sg:phone":"+1 989 879 3490",
    "sg:postcode":"48650",
    "sg:province":"MI",
    "wof:name":"Lahar Brothers Farms",
    "wof:placetype":"venue"
},
  "geometry": {"coordinates":[-84.100967,43.811776],"type":"Point"}
}