{
  "type": "Feature",
  "properties": {
    "iso:country":"US",
    "sg:address":"1116 W 14 Mile Rd",
    "sg:city":"Clawson",
    "sg:classifiers":[
        {
            "category":"Retail",
            "subcategory":"Auto Repair",
            "type":"Services"
        }
    ],
    "sg:phone":"+1 248 288 4738",
    "sg:postcode":"48017",
    "sg:province":"MI",
    "sg:tags":[
        "automobile",
        "lubrication"
    ],
    "wof:name":"Uncle Ed's Oil Shoppe",
    "wof:placetype":"venue"
},
  "geometry": {"coordinates":[-83.163197,42.533173],"type":"Point"}
}