{
  "type": "Feature",
  "properties": {
    "iso:country":"US",
    "sg:address":"12790 Bryce Rd",
    "sg:city":"Emmett",
    "sg:classifiers":[
        {
            "category":"Retail",
            "subcategory":"Animal Services",
            "type":"Services"
        }
    ],
    "sg:phone":"+1 810 395 2873",
    "sg:postcode":"48022",
    "sg:province":"MI",
    "wof:name":"Dog Barn Training Center",
    "wof:placetype":"venue"
},
  "geometry": {"coordinates":[-82.83703300000001,43.0135],"type":"Point"}
}