{
  "type": "Feature",
  "properties": {
    "iso:country":"US",
    "sg:address":"5063 W Bloomfield Lake Rd",
    "sg:city":"West Bloomfield",
    "sg:classifiers":[
        {
            "category":"Building & Trades",
            "subcategory":"Construction",
            "type":"Services"
        }
    ],
    "sg:phone":"+1 248 681 7939",
    "sg:postcode":"48323",
    "sg:province":"MI",
    "sg:tags":[
        "residential"
    ],
    "wof:name":"Carter Property Improvement &",
    "wof:placetype":"venue"
},
  "geometry": {"coordinates":[-83.379299,42.562064],"type":"Point"}
}