{
  "type": "Feature",
  "properties": {
    "iso:country":"US",
    "sg:address":"473 Peterboro St",
    "sg:city":"Detroit",
    "sg:classifiers":[
        {
            "category":"Shopping",
            "subcategory":"Gifts & Souvenirs",
            "type":"Retail Goods"
        }
    ],
    "sg:phone":"+1 313 832 8007",
    "sg:postcode":"48201",
    "sg:province":"MI",
    "wof:name":"Wholesale Gift House",
    "wof:placetype":"venue"
},
  "geometry": {"coordinates":[-83.061511,42.343809],"type":"Point"}
}