{
  "type": "Feature",
  "properties": {
    "iso:country":"US",
    "sg:address":"2884 Birchwood Dr",
    "sg:city":"Waterford",
    "sg:classifiers":[
        {
            "category":"Education",
            "subcategory":"Dance Studio",
            "type":"Public Place"
        }
    ],
    "sg:phone":"+1 248 618 8967",
    "sg:postcode":"48329",
    "sg:province":"MI",
    "wof:name":"Marinas Academy of Dance",
    "wof:placetype":"venue"
},
  "geometry": {"coordinates":[-83.40004999999999,42.681551],"type":"Point"}
}