{
  "type": "Feature",
  "properties": {
    "iso:country":"US",
    "sg:address":"301 W Walton Blvd",
    "sg:city":"Pontiac",
    "sg:classifiers":[
        {
            "category":"Building & Trades",
            "subcategory":"Landscaping Services",
            "type":"Services"
        }
    ],
    "sg:phone":"+1 248 299 5351",
    "sg:postcode":"48340",
    "sg:province":"MI",
    "sg:tags":[
        "lawn",
        "maintenance",
        "grounds"
    ],
    "wof:name":"Atwood Lawncare Inc",
    "wof:placetype":"venue"
},
  "geometry": {"coordinates":[-83.31211399999999,42.678782],"type":"Point"}
}