{
  "type": "Feature",
  "properties": {
    "iso:country":"US",
    "sg:address":"6791 Old 28th St SE",
    "sg:city":"Grand Rapids",
    "sg:classifiers":[
        {
            "category":"Professional",
            "type":"Services"
        }
    ],
    "sg:phone":"+1 616 957 0535",
    "sg:postcode":"49546",
    "sg:province":"MI",
    "sg:tags":[
        "writer"
    ],
    "sg:website":"www.the-wordsmiths.com",
    "wof:name":"Wordsmiths",
    "wof:placetype":"venue"
},
  "geometry": {"coordinates":[-85.500642,42.913316],"type":"Point"}
}