{
  "type": "Feature",
  "properties": {
    "iso:country":"US",
    "sg:address":"400 N State St",
    "sg:city":"Big Rapids",
    "sg:classifiers":[
        {
            "category":"Professional",
            "subcategory":"Business Services",
            "type":"Services"
        }
    ],
    "sg:phone":"+1 231 796 5445",
    "sg:postcode":"49307",
    "sg:province":"MI",
    "sg:tags":[
        "water",
        "softener",
        "treatment"
    ],
    "wof:name":"Hendricksen Water Conditioning",
    "wof:placetype":"venue"
},
  "geometry": {"coordinates":[-85.48406199999999,43.703382],"type":"Point"}
}