{
  "type": "Feature",
  "properties": {
    "iso:country":"US",
    "sg:address":"3240 Plainfield Ave NE",
    "sg:city":"Grand Rapids",
    "sg:classifiers":[
        {
            "category":"Autos & Motor Vehicles",
            "subcategory":"Auto Supplies",
            "type":"Retail Goods"
        }
    ],
    "sg:phone":"+1 616 364 8113",
    "sg:postcode":"49525",
    "sg:province":"MI",
    "sg:tags":[
        "tire"
    ],
    "wof:name":"Goodyear-Gemini Auto Svc",
    "wof:placetype":"venue"
},
  "geometry": {"coordinates":[-85.63457699999999,43.020272],"type":"Point"}
}