{
  "type": "Feature",
  "properties": {
    "iso:country":"US",
    "sg:address":"2595 5th St",
    "sg:city":"Shelbyville",
    "sg:classifiers":[
        {
            "category":"Building & Trades",
            "subcategory":"Landscaping Services",
            "type":"Services"
        }
    ],
    "sg:phone":"+1 269 792 0582",
    "sg:postcode":"49344",
    "sg:province":"MI",
    "sg:tags":[
        "landscape"
    ],
    "wof:name":"Countryside Landscaping",
    "wof:placetype":"venue"
},
  "geometry": {"coordinates":[-85.597722,42.594628],"type":"Point"}
}