{
  "type": "Feature",
  "properties": {
    "iso:country":"US",
    "sg:address":"108 Brooklyn Rd",
    "sg:city":"Napoleon",
    "sg:classifiers":[
        {
            "category":"Banks & Credit Unions",
            "subcategory":"Bank",
            "type":"Services"
        }
    ],
    "sg:phone":"+1 517 536 8692",
    "sg:postcode":"49201",
    "sg:province":"MI",
    "wof:name":"Flagstar Bank",
    "wof:placetype":"venue"
},
  "geometry": {"coordinates":[-84.248391,42.161984],"type":"Point"}
}