{
  "type": "Feature",
  "properties": {
    "iso:country":"US",
    "sg:address":"21186 Hall Rd",
    "sg:city":"Clinton Township",
    "sg:classifiers":[
        {
            "category":"Sports & Exercise",
            "subcategory":"Bicycle Rental",
            "type":"Entertainment"
        }
    ],
    "sg:phone":"+1 586 493 4370",
    "sg:postcode":"48038",
    "sg:province":"MI",
    "sg:tags":[
        "wear"
    ],
    "wof:name":"Detroit Lacrosse",
    "wof:placetype":"venue"
},
  "geometry": {"coordinates":[-82.905996,42.628231],"type":"Point"}
}