{
  "type": "Feature",
  "properties": {
    "iso:country":"US",
    "sg:address":"8565 N Silvery Ln Ste 401",
    "sg:city":"Dearborn Heights",
    "sg:classifiers":[
        {
            "category":"Health Services",
            "subcategory":"Health Practitioner",
            "type":"Services"
        }
    ],
    "sg:phone":"+1 313 359 9595",
    "sg:postcode":"48127",
    "sg:province":"MI",
    "sg:tags":[
        "therapy",
        "physical"
    ],
    "sg:website":"www.performance-rehab.net",
    "wof:name":"Performance Rehab Inc",
    "wof:placetype":"venue"
},
  "geometry": {"coordinates":[-83.28416,42.354735],"type":"Point"}
}