{
  "type": "Feature",
  "properties": {
    "iso:country":"US",
    "sg:address":"2540 Rochester Rd",
    "sg:city":"Royal Oak",
    "sg:classifiers":[
        {
            "category":"Real Estate",
            "subcategory":"Real Estate Operator",
            "type":"Services"
        }
    ],
    "sg:phone":"+1 248 398 5350",
    "sg:postcode":"48073",
    "sg:province":"MI",
    "sg:tags":[
        "apartment"
    ],
    "wof:name":"Fernwood Manor",
    "wof:placetype":"venue"
},
  "geometry": {"coordinates":[-83.141018,42.511965],"type":"Point"}
}