{
  "type": "Feature",
  "properties": {
    "iso:country":"US",
    "sg:address":"581 E Jefferson Ave",
    "sg:city":"Detroit",
    "sg:classifiers":[
        {
            "category":"Deli",
            "type":"Food & Drink"
        }
    ],
    "sg:phone":"+1 313 962 3354",
    "sg:postcode":"48226",
    "sg:province":"MI",
    "wof:name":"Nathan's Deli",
    "wof:placetype":"venue"
},
  "geometry": {"coordinates":[-83.038498,42.3316],"type":"Point"}
}