{
  "type": "Feature",
  "properties": {
    "iso:country":"US",
    "sg:address":"26220 Ohio Ave",
    "sg:city":"Novi",
    "sg:classifiers":[
        {
            "category":"Organizations",
            "subcategory":"Labor Organization",
            "type":"Services"
        }
    ],
    "sg:phone":"+1 248 348 6872",
    "sg:postcode":"48374",
    "sg:province":"MI",
    "wof:name":"Flooring Intrntl",
    "wof:placetype":"venue"
},
  "geometry": {"coordinates":[-83.549115,42.481704],"type":"Point"}
}