{
  "type": "Feature",
  "properties": {
    "iso:country":"US",
    "sg:address":"12264 Riverside Dr",
    "sg:city":"White Pigeon",
    "sg:classifiers":[
        {
            "category":"Retail",
            "subcategory":"Repair Shop",
            "type":"Services"
        }
    ],
    "sg:phone":"+1 269 483 9186",
    "sg:postcode":"49099",
    "sg:province":"MI",
    "sg:tags":[
        "electrical"
    ],
    "wof:name":"White Aero",
    "wof:placetype":"venue"
},
  "geometry": {"coordinates":[-85.716441,41.809712],"type":"Point"}
}