{
  "type": "Feature",
  "properties": {
    "iso:country":"US",
    "sg:address":"2051 S Rochester Rd",
    "sg:city":"Rochester Hills",
    "sg:classifiers":[
        {
            "category":"Shopping",
            "subcategory":"Pharmacy",
            "type":"Retail Goods"
        }
    ],
    "sg:phone":"+1 248 852 0004",
    "sg:postcode":"48307",
    "sg:province":"MI",
    "wof:name":"Rite Aid Pharmacy",
    "wof:placetype":"venue"
},
  "geometry": {"coordinates":[-83.132407,42.651471],"type":"Point"}
}