{
  "type": "Feature",
  "properties": {
    "iso:country":"US",
    "sg:address":"5343 Doherty St",
    "sg:city":"West Bloomfield",
    "sg:classifiers":[
        {
            "category":"Wholesale",
            "subcategory":"Durable Goods & Equipment",
            "type":"Manufacturing & Wholesale Goods"
        }
    ],
    "sg:phone":"+1 248 737 4467",
    "sg:postcode":"48323",
    "sg:province":"MI",
    "wof:name":"C H International Business Dev",
    "wof:placetype":"venue"
},
  "geometry": {"coordinates":[-83.358149,42.564275],"type":"Point"}
}