{
  "type": "Feature",
  "properties": {
    "iso:country":"US",
    "sg:address":"1670 S Raisinville Rd",
    "sg:city":"Monroe",
    "sg:classifiers":[
        {
            "category":"Education",
            "subcategory":"School",
            "type":"Public Place"
        }
    ],
    "sg:phone":"+1 734 241 9496",
    "sg:postcode":"48161",
    "sg:province":"MI",
    "sg:website":"www.meadowmontessori.org",
    "wof:name":"Meadow Montessori School",
    "wof:placetype":"venue"
},
  "geometry": {"coordinates":[-83.47539999999999,41.910775],"type":"Point"}
}