{
  "type": "Feature",
  "properties": {
    "iso:country":"US",
    "sg:address":"8962 Sussex Dr",
    "sg:city":"White Lake",
    "sg:classifiers":[
        {
            "category":"Building & Trades",
            "subcategory":"Construction",
            "type":"Services"
        }
    ],
    "sg:phone":"+1 248 698 1014",
    "sg:postcode":"48386",
    "sg:province":"MI",
    "sg:tags":[
        "carpentry",
        "contractor"
    ],
    "wof:name":"Pride Craft Builders",
    "wof:placetype":"venue"
},
  "geometry": {"coordinates":[-83.46197600000001,42.637746],"type":"Point"}
}