{
  "type": "Feature",
  "properties": {
    "iso:country":"US",
    "sg:address":"209 Meadow Hills Ln",
    "sg:city":"Fremont",
    "sg:classifiers":[
        {
            "category":"Social Services",
            "subcategory":"Job Training",
            "type":"Services"
        }
    ],
    "sg:phone":"+1 231 924 5840",
    "sg:postcode":"49412",
    "sg:province":"MI",
    "sg:tags":[
        "retardation",
        "disabled",
        "mental",
        "dev"
    ],
    "wof:name":"Arc/Newaygo County",
    "wof:placetype":"venue"
},
  "geometry": {"coordinates":[-85.926289,43.46853],"type":"Point"}
}