{
  "type": "Feature",
  "properties": {
    "iso:country":"US",
    "sg:address":"4354 Maybee Rd",
    "sg:city":"Lake Orion",
    "sg:classifiers":[
        {
            "category":"Manufacturing",
            "subcategory":"Tools & Machinery",
            "type":"Manufacturing & Wholesale Goods"
        }
    ],
    "sg:phone":"+1 248 391 2663",
    "sg:postcode":"48359",
    "sg:province":"MI",
    "sg:tags":[
        "industry",
        "mfg"
    ],
    "wof:name":"Schram Farms",
    "wof:placetype":"venue"
},
  "geometry": {"coordinates":[-83.32941700000001,42.728501],"type":"Point"}
}