{
  "type": "Feature",
  "properties": {
    "iso:country":"US",
    "sg:address":"1101 Broad St",
    "sg:city":"St Joseph",
    "sg:classifiers":[
        {
            "category":"Professional",
            "subcategory":"Art Services",
            "type":"Services"
        }
    ],
    "sg:phone":"+1 269 982 0933",
    "sg:postcode":"49085",
    "sg:province":"MI",
    "sg:tags":[
        "photographer"
    ],
    "sg:website":"www.dkfoto.com",
    "wof:name":"David Knight Photography",
    "wof:placetype":"venue"
},
  "geometry": {"coordinates":[-86.474986,42.104192],"type":"Point"}
}