{
  "type": "Feature",
  "properties": {
    "iso:country":"US",
    "sg:address":"11533 E 12 Mile Rd",
    "sg:city":"Warren",
    "sg:classifiers":[
        {
            "category":"Personal",
            "type":"Services"
        }
    ],
    "sg:phone":"+1 586 558 3007",
    "sg:postcode":"48093",
    "sg:province":"MI",
    "sg:tags":[
        "program",
        "physical",
        "exercise",
        "fitness"
    ],
    "wof:name":"Ladys Workout Exp Of Warren",
    "wof:placetype":"venue"
},
  "geometry": {"coordinates":[-83.007879,42.507118],"type":"Point"}
}