{
  "type": "Feature",
  "properties": {
    "iso:country":"US",
    "sg:address":"8780 E 8 Mile Rd",
    "sg:city":"Detroit",
    "sg:classifiers":[
        {
            "category":"Shopping",
            "subcategory":"Clothing, Apparel, & Fashions",
            "type":"Retail Goods"
        }
    ],
    "sg:phone":"+1 313 892 1683",
    "sg:postcode":"48234",
    "sg:province":"MI",
    "sg:tags":[
        "accessory",
        "clothing",
        "women's"
    ],
    "wof:name":"Simply Fashions",
    "wof:placetype":"venue"
},
  "geometry": {"coordinates":[-83.01860000000001,42.4482],"type":"Point"}
}