{
  "type": "Feature",
  "properties": {
    "iso:country":"US",
    "sg:address":"2520 N Euclid Ave",
    "sg:city":"Bay City",
    "sg:classifiers":[
        {
            "category":"Health Services",
            "subcategory":"Doctor",
            "type":"Services"
        }
    ],
    "sg:phone":"+1 989 684 8183",
    "sg:postcode":"48706",
    "sg:province":"MI",
    "sg:tags":[
        "physician",
        "surgeon",
        "medical"
    ],
    "wof:name":"Bangor Medical Center",
    "wof:placetype":"venue"
},
  "geometry": {"coordinates":[-83.912556,43.660699],"type":"Point"}
}