{
  "type": "Feature",
  "properties": {
    "iso:country":"US",
    "sg:address":"1700 N Van Dyke Rd",
    "sg:city":"Bad Axe",
    "sg:classifiers":[
        {
            "category":"Health Services",
            "subcategory":"Hospital",
            "type":"Services"
        }
    ],
    "sg:phone":"+1 989 269 7877",
    "sg:postcode":"48413",
    "sg:province":"MI",
    "sg:tags":[
        "mental"
    ],
    "wof:name":"Assertive Community Treatment",
    "wof:placetype":"venue"
},
  "geometry": {"coordinates":[-83.00146100000001,43.839808],"type":"Point"}
}