{
  "type": "Feature",
  "properties": {
    "iso:country":"US",
    "sg:address":"43762 Utica Rd",
    "sg:city":"Sterling Heights",
    "sg:classifiers":[
        {
            "category":"Building & Trades",
            "subcategory":"Construction",
            "type":"Services"
        }
    ],
    "sg:phone":"+1 586 997 3877",
    "sg:postcode":"48314",
    "sg:province":"MI",
    "sg:tags":[
        "insulation",
        "heat",
        "contractor"
    ],
    "wof:name":"Oberson Insulation Co",
    "wof:placetype":"venue"
},
  "geometry": {"coordinates":[-83.032302,42.611575],"type":"Point"}
}