{
  "type": "Feature",
  "properties": {
    "iso:country":"US",
    "sg:address":"10523 Wedgewood Ct",
    "sg:city":"Clarkston",
    "sg:classifiers":[
        {
            "category":"Professional",
            "subcategory":"Accounting & Tax Preparation",
            "type":"Services"
        }
    ],
    "sg:phone":"+1 248 922 0336",
    "sg:postcode":"48348",
    "sg:province":"MI",
    "wof:name":"Patrick McCarty CPA",
    "wof:placetype":"venue"
},
  "geometry": {"coordinates":[-83.38390099999999,42.791901],"type":"Point"}
}