{
  "type": "Feature",
  "properties": {
    "iso:country":"US",
    "sg:address":"103 S Main St",
    "sg:city":"Olivet",
    "sg:classifiers":[
        {
            "category":"Banks & Credit Unions",
            "subcategory":"Bank",
            "type":"Services"
        }
    ],
    "sg:phone":"+1 269 749 2811",
    "sg:postcode":"49076",
    "sg:province":"MI",
    "wof:name":"Eaton Federal Savings Bank",
    "wof:placetype":"venue"
},
  "geometry": {"coordinates":[-84.924052,42.446728],"type":"Point"}
}