{
  "type": "Feature",
  "properties": {
    "iso:country":"US",
    "sg:address":"3219 Miller Rd",
    "sg:city":"Flint",
    "sg:classifiers":[
        {
            "category":"Utilities",
            "subcategory":"Cable",
            "type":"Services"
        }
    ],
    "sg:phone":"+1 810 720 0041",
    "sg:postcode":"48507",
    "sg:province":"MI",
    "sg:tags":[
        "television"
    ],
    "wof:name":"Lodge Net Entertainment",
    "wof:placetype":"venue"
},
  "geometry": {"coordinates":[-83.740911,42.988573],"type":"Point"}
}