{
  "type": "Feature",
  "properties": {
    "iso:country":"US",
    "sg:address":"10225 W 34 Rd",
    "sg:city":"Harrietta",
    "sg:classifiers":[
        {
            "category":"Building & Trades",
            "subcategory":"Construction",
            "type":"Services"
        }
    ],
    "sg:phone":"+1 231 389 0100",
    "sg:postcode":"49638",
    "sg:province":"MI",
    "sg:tags":[
        "cleaning",
        "contractor"
    ],
    "wof:name":"Steam Way Of Northern Michigan",
    "wof:placetype":"venue"
},
  "geometry": {"coordinates":[-85.78507,44.280154],"type":"Point"}
}