{
  "type": "Feature",
  "properties": {
    "iso:country":"US",
    "sg:address":"827 N Vernon St",
    "sg:city":"Dearborn",
    "sg:classifiers":[
        {
            "category":"Professional",
            "subcategory":"Engineering",
            "type":"Services"
        },
        {
            "category":"Professional",
            "subcategory":"Business Services",
            "type":"Services"
        },
        {
            "category":"Professional",
            "subcategory":"Management & Consulting",
            "type":"Services"
        }
    ],
    "sg:phone":"+1 313 562 7161",
    "sg:postcode":"48128",
    "sg:province":"MI",
    "sg:tags":[
        "consultant",
        "product",
        "engineer",
        "ecological",
        "environmental"
    ],
    "wof:name":"Cls Bioremediation",
    "wof:placetype":"venue"
},
  "geometry": {"coordinates":[-83.275621,42.317427],"type":"Point"}
}