{
  "type": "Feature",
  "properties": {
    "iso:country":"US",
    "sg:address":"4107 W 13 Mile Rd",
    "sg:city":"Royal Oak",
    "sg:classifiers":[
        {
            "category":"Food & Beverages",
            "subcategory":"Liquor & Beverages",
            "type":"Retail Goods"
        }
    ],
    "sg:phone":"+1 248 288 6670",
    "sg:postcode":"48073",
    "sg:province":"MI",
    "sg:tags":[
        "beer",
        "spirit",
        "wine"
    ],
    "wof:name":"Tip-Top Party Store",
    "wof:placetype":"venue"
},
  "geometry": {"coordinates":[-83.199699,42.517399],"type":"Point"}
}