{
  "type": "Feature",
  "properties": {
    "iso:country":"US",
    "sg:address":"8329 Herron Rd",
    "sg:city":"Herron",
    "sg:classifiers":[
        {
            "category":"Retail",
            "subcategory":"Portrait Studio",
            "type":"Services"
        }
    ],
    "sg:phone":"+1 989 727 3310",
    "sg:postcode":"49744",
    "sg:province":"MI",
    "sg:tags":[
        "photo"
    ],
    "wof:name":"Authier Photos For Folks",
    "wof:placetype":"venue"
},
  "geometry": {"coordinates":[-83.646792,44.955859],"type":"Point"}
}