{
  "type": "Feature",
  "properties": {
    "iso:country":"US",
    "sg:address":"4115 E Y Ave",
    "sg:city":"Vicksburg",
    "sg:classifiers":[
        {
            "category":"Building & Trades",
            "subcategory":"Landscaping Services",
            "type":"Services"
        }
    ],
    "sg:phone":"+1 269 649 4578",
    "sg:postcode":"49097",
    "sg:province":"MI",
    "wof:name":"Lakeside Lawn Care",
    "wof:placetype":"venue"
},
  "geometry": {"coordinates":[-85.538078,42.085238],"type":"Point"}
}