{
  "type": "Feature",
  "properties": {
    "iso:country":"US",
    "sg:address":"4684 Fraser Rd",
    "sg:city":"Bay City",
    "sg:classifiers":[
        {
            "category":"Manufacturing",
            "subcategory":"Building Materials",
            "type":"Manufacturing & Wholesale Goods"
        }
    ],
    "sg:phone":"+1 989 686 5681",
    "sg:postcode":"48706",
    "sg:province":"MI",
    "sg:tags":[
        "plywood",
        "veneer"
    ],
    "wof:name":"Ply-Forms Inc",
    "wof:placetype":"venue"
},
  "geometry": {"coordinates":[-84.011971,43.606158],"type":"Point"}
}