{
  "type": "Feature",
  "properties": {
    "iso:country":"US",
    "sg:address":"3740 John R",
    "sg:city":"Detroit",
    "sg:classifiers":[
        {
            "category":"Parking",
            "type":"Transportation"
        }
    ],
    "sg:phone":"+1 800 310 7275",
    "sg:postcode":"48201",
    "sg:province":"MI",
    "sg:website":"www.717parking.com/detroit",
    "wof:name":"717 Parking Services",
    "wof:placetype":"venue"
},
  "geometry": {"coordinates":[-83.056731,42.349575],"type":"Point"}
}