{
  "type": "Feature",
  "properties": {
    "iso:country":"US",
    "sg:address":"590 28th St SE",
    "sg:city":"Grand Rapids",
    "sg:classifiers":[
        {
            "category":"Autos & Motor Vehicles",
            "subcategory":"Automobile Sales",
            "type":"Retail Goods"
        }
    ],
    "sg:phone":"+1 616 301 2544",
    "sg:postcode":"49548",
    "sg:province":"MI",
    "sg:tags":[
        "car",
        "dealer"
    ],
    "wof:name":"Landman Auto Sales",
    "wof:placetype":"venue"
},
  "geometry": {"coordinates":[-85.652896,42.912748],"type":"Point"}
}