{
  "type": "Feature",
  "properties": {
    "iso:country":"US",
    "sg:address":"8877 River Valley Rd",
    "sg:city":"Brighton",
    "sg:classifiers":[
        {
            "category":"Wholesale",
            "subcategory":"Construction Materials",
            "type":"Manufacturing & Wholesale Goods"
        }
    ],
    "sg:phone":"+1 810 231 8118",
    "sg:postcode":"48116",
    "sg:province":"MI",
    "sg:tags":[
        "tile"
    ],
    "wof:name":"B C Tile & Marble",
    "wof:placetype":"venue"
},
  "geometry": {"coordinates":[-83.793448,42.472387],"type":"Point"}
}