{
  "type": "Feature",
  "properties": {
    "iso:country":"US",
    "sg:address":"53 W Wall St",
    "sg:city":"Benton Harbor",
    "sg:classifiers":[
        {
            "category":"Professional",
            "subcategory":"Engineering",
            "type":"Services"
        }
    ],
    "sg:phone":"+1 269 927 1880",
    "sg:postcode":"49022",
    "sg:province":"MI",
    "sg:website":"www.integritydes.com",
    "wof:name":"Integrity Design Inc",
    "wof:placetype":"venue"
},
  "geometry": {"coordinates":[-86.455714,42.115045],"type":"Point"}
}