{
  "type": "Feature",
  "properties": {
    "iso:country":"US",
    "sg:address":"200 Holton Rd",
    "sg:city":"Muskegon",
    "sg:classifiers":[
        {
            "category":"Professional",
            "subcategory":"Lawyer & Legal Services",
            "type":"Services"
        }
    ],
    "sg:phone":"+1 231 744 6991",
    "sg:postcode":"49445",
    "sg:province":"MI",
    "sg:tags":[
        "attorney"
    ],
    "wof:name":"Thomas Gruich",
    "wof:placetype":"venue"
},
  "geometry": {"coordinates":[-86.249695,43.265764],"type":"Point"}
}