{
  "type": "Feature",
  "properties": {
    "iso:country":"US",
    "sg:address":"17369 S Wilson Rd",
    "sg:city":"Kinross",
    "sg:classifiers":[
        {
            "category":"Wholesale",
            "subcategory":"Auto Parts",
            "type":"Manufacturing & Wholesale Goods"
        }
    ],
    "sg:phone":"+1 906 495 2817",
    "sg:postcode":"49752",
    "sg:province":"MI",
    "sg:tags":[
        "truck",
        "accessory"
    ],
    "wof:name":"Liquid Liners",
    "wof:placetype":"venue"
},
  "geometry": {"coordinates":[-84.425665,46.248025],"type":"Point"}
}