{
  "type": "Feature",
  "properties": {
    "iso:country":"US",
    "sg:address":"2962 E Sanilac Rd",
    "sg:city":"Carsonville",
    "sg:classifiers":[
        {
            "category":"Manufacturing",
            "subcategory":"Lumber",
            "type":"Manufacturing & Wholesale Goods"
        }
    ],
    "sg:phone":"+1 810 657 9151",
    "sg:postcode":"48419",
    "sg:province":"MI",
    "sg:tags":[
        "sawmill"
    ],
    "wof:name":"Black River Hardwoods",
    "wof:placetype":"venue"
},
  "geometry": {"coordinates":[-82.72181399999999,43.424986],"type":"Point"}
}