{
  "type": "Feature",
  "properties": {
    "iso:country":"US",
    "sg:address":"2940 W Carleton Rd",
    "sg:city":"Hillsdale",
    "sg:classifiers":[
        {
            "category":"Restaurant",
            "type":"Food & Drink"
        }
    ],
    "sg:phone":"+1 517 439 9522",
    "sg:postcode":"49242",
    "sg:province":"MI",
    "wof:name":"Hillsdale Garden Restaurant",
    "wof:placetype":"venue"
},
  "geometry": {"coordinates":[-84.652012,41.944931],"type":"Point"}
}