{
  "type": "Feature",
  "properties": {
    "iso:country":"US",
    "sg:address":"1500 Bogie Lake Rd",
    "sg:city":"White Lake",
    "sg:classifiers":[
        {
            "category":"Education",
            "subcategory":"School",
            "type":"Public Place"
        }
    ],
    "sg:phone":"+1 248 684 8030",
    "sg:postcode":"48383",
    "sg:province":"MI",
    "wof:name":"Lakewood Elementary School",
    "wof:placetype":"venue"
},
  "geometry": {"coordinates":[-83.520256,42.627277],"type":"Point"}
}