{
  "type": "Feature",
  "properties": {
    "iso:country":"US",
    "sg:address":"523 N Mc Ewan St",
    "sg:city":"Clare",
    "sg:classifiers":[
        {
            "category":"Shopping",
            "subcategory":"Gifts & Souvenirs",
            "type":"Retail Goods"
        }
    ],
    "sg:phone":"+1 989 386 2879",
    "sg:postcode":"48617",
    "sg:province":"MI",
    "wof:name":"Charming Cards & Gifts",
    "wof:placetype":"venue"
},
  "geometry": {"coordinates":[-84.768255,43.822179],"type":"Point"}
}