{
  "type": "Feature",
  "properties": {
    "iso:country":"US",
    "sg:address":"908 Adams St",
    "sg:city":"Lapeer",
    "sg:classifiers":[
        {
            "category":"Building & Trades",
            "subcategory":"Cleaning & Sanitation",
            "type":"Services"
        }
    ],
    "sg:phone":"+1 810 664 3344",
    "sg:postcode":"48446",
    "sg:province":"MI",
    "sg:tags":[
        "ventilating",
        "system"
    ],
    "wof:name":"Duct Doctors Inc",
    "wof:placetype":"venue"
},
  "geometry": {"coordinates":[-83.32093999999999,43.057897],"type":"Point"}
}