{
  "type": "Feature",
  "properties": {
    "iso:country":"US",
    "sg:address":"21894 Harper Ave",
    "sg:city":"St Clair Shores",
    "sg:classifiers":[
        {
            "category":"Personal",
            "subcategory":"Beauty Salon",
            "type":"Services"
        }
    ],
    "sg:phone":"+1 586 773 8583",
    "sg:postcode":"48080",
    "sg:province":"MI",
    "sg:tags":[
        "shop",
        "manicuring"
    ],
    "wof:name":"Notorious Nails Inc",
    "wof:placetype":"venue"
},
  "geometry": {"coordinates":[-82.91189900000001,42.456504],"type":"Point"}
}