{
  "type": "Feature",
  "properties": {
    "iso:country":"US",
    "sg:address":"702 Meadowview Dr",
    "sg:city":"Lansing",
    "sg:classifiers":[
        {
            "category":"Social Services",
            "subcategory":"Child Care",
            "type":"Services"
        }
    ],
    "sg:phone":"+1 517 886 9049",
    "sg:postcode":"48917",
    "sg:province":"MI",
    "sg:tags":[
        "day"
    ],
    "wof:name":"Adela R Ghannam",
    "wof:placetype":"venue"
},
  "geometry": {"coordinates":[-84.609495,42.725445],"type":"Point"}
}