{
  "type": "Feature",
  "properties": {
    "iso:country":"US",
    "sg:address":"45013 Catalpa Blvd",
    "sg:city":"Macomb",
    "sg:classifiers":[
        {
            "category":"Real Estate",
            "subcategory":"Real Estate Services",
            "type":"Services"
        }
    ],
    "sg:phone":"+1 586 469 8800",
    "sg:postcode":"48044",
    "sg:province":"MI",
    "sg:tags":[
        "management",
        "property"
    ],
    "wof:name":"Community Sales Inc",
    "wof:placetype":"venue"
},
  "geometry": {"coordinates":[-82.901492,42.629003],"type":"Point"}
}