{
  "type": "Feature",
  "properties": {
    "iso:country":"US",
    "sg:address":"5421 W Center Dr",
    "sg:city":"Hurley",
    "sg:classifiers":[
        {
            "category":"Building & Trades",
            "subcategory":"Construction",
            "type":"Services"
        }
    ],
    "sg:phone":"+1 715 561 4221",
    "sg:postcode":"54534",
    "sg:province":"WI",
    "sg:tags":[
        "commercial",
        "contractor"
    ],
    "wof:name":"Ero Nasi Construction Co Inc",
    "wof:placetype":"venue"
},
  "geometry": {"coordinates":[-90.204929,46.472089],"type":"Point"}
}