{
  "type": "Feature",
  "properties": {
    "iso:country":"US",
    "sg:address":"23400 Woodward Ave",
    "sg:city":"Ferndale",
    "sg:classifiers":[
        {
            "category":"Shopping",
            "subcategory":"Clothing, Apparel, & Fashions",
            "type":"Retail Goods"
        },
        {
            "category":"Cinema",
            "subcategory":"Movie Rental",
            "type":"Entertainment"
        }
    ],
    "sg:phone":"+1 248 542 8500",
    "sg:postcode":"48220",
    "sg:province":"MI",
    "sg:tags":[
        "game",
        "lingerie",
        "video"
    ],
    "wof:name":"Priscilla's",
    "wof:placetype":"venue"
},
  "geometry": {"coordinates":[-83.137901,42.466],"type":"Point"}
}