{
  "type": "Feature",
  "properties": {
    "iso:country":"US",
    "sg:address":"50630 Bellfort Ct",
    "sg:city":"Chesterfield",
    "sg:classifiers":[
        {
            "category":"Wholesale",
            "subcategory":"Plants",
            "type":"Manufacturing & Wholesale Goods"
        }
    ],
    "sg:phone":"+1 586 725 3721",
    "sg:postcode":"48047",
    "sg:province":"MI",
    "sg:tags":[
        "florist"
    ],
    "wof:name":"Larry's Orchids",
    "wof:placetype":"venue"
},
  "geometry": {"coordinates":[-82.76931,42.671406],"type":"Point"}
}