{
  "type": "Feature",
  "properties": {
    "iso:country":"US",
    "sg:address":"28630 Southfield Rd",
    "sg:city":"Southfield",
    "sg:classifiers":[
        {
            "category":"Insurance",
            "subcategory":"Insurance Agent",
            "type":"Services"
        }
    ],
    "sg:phone":"+1 248 569 7070",
    "sg:postcode":"48076",
    "sg:province":"MI",
    "wof:name":"AAA Southfield Inc",
    "wof:placetype":"venue"
},
  "geometry": {"coordinates":[-83.222398,42.500269],"type":"Point"}
}