{
  "type": "Feature",
  "properties": {
    "iso:country":"US",
    "sg:address":"32401 8 Mile Rd",
    "sg:city":"Livonia",
    "sg:classifiers":[
        {
            "category":"Professional",
            "subcategory":"Lawyer & Legal Services",
            "type":"Services"
        }
    ],
    "sg:phone":"+1 248 474 1252",
    "sg:postcode":"48152",
    "sg:province":"MI",
    "wof:name":"Trivax Harry S Atty",
    "wof:placetype":"venue"
},
  "geometry": {"coordinates":[-83.366302,42.440701],"type":"Point"}
}