{
  "type": "Feature",
  "properties": {
    "iso:country":"US",
    "sg:address":"3974 Rochester Rd",
    "sg:city":"Troy",
    "sg:classifiers":[
        {
            "category":"Personal",
            "subcategory":"Nail Salon",
            "type":"Services"
        }
    ],
    "sg:phone":"+1 248 524 2143",
    "sg:postcode":"48083",
    "sg:province":"MI",
    "wof:name":"Premiere Nail Club",
    "wof:placetype":"venue"
},
  "geometry": {"coordinates":[-83.128197,42.577499],"type":"Point"}
}