{
  "type": "Feature",
  "properties": {
    "iso:country":"US",
    "sg:address":"2976 Ivanrest Ave SW",
    "sg:city":"Grandville",
    "sg:classifiers":[
        {
            "category":"Professional",
            "type":"Services"
        }
    ],
    "sg:phone":"+1 616 530 9610",
    "sg:postcode":"49418",
    "sg:province":"MI",
    "sg:tags":[
        "establishment"
    ],
    "wof:name":"Performance Plus Quick Lube",
    "wof:placetype":"venue"
},
  "geometry": {"coordinates":[-85.743928,42.911911],"type":"Point"}
}