{
  "type": "Feature",
  "properties": {
    "iso:country":"US",
    "sg:address":"1038 129th Ave",
    "sg:city":"Wayland",
    "sg:classifiers":[
        {
            "category":"Professional",
            "type":"Services"
        }
    ],
    "sg:phone":"+1 269 792 9247",
    "sg:postcode":"49348",
    "sg:province":"MI",
    "wof:name":"Julie A Fox",
    "wof:placetype":"venue"
},
  "geometry": {"coordinates":[-85.652168,42.630421],"type":"Point"}
}