{
  "type": "Feature",
  "properties": {
    "iso:country":"US",
    "sg:address":"21411 Civic Center Dr",
    "sg:city":"Southfield",
    "sg:classifiers":[
        {
            "category":"Banks & Credit Unions",
            "subcategory":"Financial Services",
            "type":"Services"
        }
    ],
    "sg:phone":"+1 248 262 9820",
    "sg:postcode":"48076",
    "sg:province":"MI",
    "sg:tags":[
        "broker",
        "mortgage"
    ],
    "wof:name":"Metrowide Mortgage",
    "wof:placetype":"venue"
},
  "geometry": {"coordinates":[-83.254204,42.479301],"type":"Point"}
}