{
  "type": "Feature",
  "properties": {
    "iso:country":"US",
    "sg:address":"9007 Old State Rd",
    "sg:city":"Fairgrove",
    "sg:classifiers":[
        {
            "category":"Autos & Motor Vehicles",
            "subcategory":"Boat Sales",
            "type":"Retail Goods"
        }
    ],
    "sg:phone":"+1 989 893 0077",
    "sg:postcode":"48733",
    "sg:province":"MI",
    "sg:tags":[
        "top",
        "upholstery",
        "cover"
    ],
    "wof:name":"G & B Custom Boat Canvas",
    "wof:placetype":"venue"
},
  "geometry": {"coordinates":[-83.66355,43.584384],"type":"Point"}
}