{
  "type": "Feature",
  "properties": {
    "iso:country":"US",
    "sg:address":"2885 Maxwell Rd",
    "sg:city":"Petoskey",
    "sg:classifiers":[
        {
            "category":"Professional",
            "subcategory":"Research",
            "type":"Services"
        },
        {
            "category":"Professional",
            "subcategory":"Management & Consulting",
            "type":"Services"
        }
    ],
    "sg:phone":"+1 231 348 9806",
    "sg:postcode":"49770",
    "sg:province":"MI",
    "sg:tags":[
        "environmental",
        "ecological",
        "business"
    ],
    "wof:name":"Northern Environmental Svcs",
    "wof:placetype":"venue"
},
  "geometry": {"coordinates":[-84.815139,45.334091],"type":"Point"}
}