{
  "type": "Feature",
  "properties": {
    "iso:country":"US",
    "sg:address":"5275 Miller Rd",
    "sg:city":"Flint",
    "sg:classifiers":[
        {
            "category":"Restaurant",
            "type":"Food & Drink"
        }
    ],
    "sg:phone":"+1 810 732 4390",
    "sg:postcode":"48507",
    "sg:province":"MI",
    "sg:tags":[
        "caterer"
    ],
    "sg:website":"www.pestos.com",
    "wof:name":"Pesto's",
    "wof:placetype":"venue"
},
  "geometry": {"coordinates":[-83.780592,42.973833],"type":"Point"}
}