{
  "type": "Feature",
  "properties": {
    "iso:country":"US",
    "sg:address":"25264 Branchaster Rd",
    "sg:city":"Farmington Hills",
    "sg:classifiers":[
        {
            "category":"Health Services",
            "subcategory":"Health Practitioner",
            "type":"Services"
        }
    ],
    "sg:phone":"+1 248 320 7010",
    "sg:postcode":"48336",
    "sg:province":"MI",
    "sg:tags":[
        "pathologist",
        "speech"
    ],
    "wof:name":"Ruth Klueger & Assoc",
    "wof:placetype":"venue"
},
  "geometry": {"coordinates":[-83.32105900000001,42.482076],"type":"Point"}
}