{
  "type": "Feature",
  "properties": {
    "iso:country":"US",
    "sg:address":"300 Seminole Ct",
    "sg:city":"Midland",
    "sg:classifiers":[
        {
            "category":"Building & Trades",
            "subcategory":"Construction",
            "type":"Services"
        }
    ],
    "sg:phone":"+1 989 835 3679",
    "sg:postcode":"48642",
    "sg:province":"MI",
    "sg:tags":[
        "excavation",
        "excavating",
        "contractor"
    ],
    "wof:name":"D Sias Excavating",
    "wof:placetype":"venue"
},
  "geometry": {"coordinates":[-84.22369500000001,43.636678],"type":"Point"}
}