{
  "type": "Feature",
  "properties": {
    "iso:country":"US",
    "sg:address":"24436 Conifer",
    "sg:city":"Farmington Hills",
    "sg:classifiers":[
        {
            "category":"Wholesale",
            "subcategory":"Electrical",
            "type":"Manufacturing & Wholesale Goods"
        },
        {
            "category":"Professional",
            "subcategory":"Computer Services",
            "type":"Services"
        }
    ],
    "sg:phone":"+1 248 473 9912",
    "sg:postcode":"48335",
    "sg:province":"MI",
    "sg:tags":[
        "control",
        "design",
        "system",
        "contractor"
    ],
    "wof:name":"Alpha Controls Design Inc",
    "wof:placetype":"venue"
},
  "geometry": {"coordinates":[-83.40314600000001,42.471463],"type":"Point"}
}