{
  "type": "Feature",
  "properties": {
    "iso:country":"US",
    "sg:address":"307 W Cedar Ave",
    "sg:city":"Gladwin",
    "sg:classifiers":[
        {
            "category":"Wholesale",
            "subcategory":"Chemicals & Plastics",
            "type":"Manufacturing & Wholesale Goods"
        }
    ],
    "sg:phone":"+1 989 426 1551",
    "sg:postcode":"48624",
    "sg:province":"MI",
    "sg:tags":[
        "oxygen"
    ],
    "wof:name":"ABC Medical Supply-Gladwin",
    "wof:placetype":"venue"
},
  "geometry": {"coordinates":[-84.490461,43.980627],"type":"Point"}
}