{
  "type": "Feature",
  "properties": {
    "iso:country":"US",
    "sg:address":"1501 Washington Blvd",
    "sg:city":"Detroit",
    "sg:classifiers":[
        {
            "category":"Organizations",
            "subcategory":"Membership Organization",
            "type":"Services"
        }
    ],
    "sg:phone":"+1 313 237 5500",
    "sg:postcode":"48226",
    "sg:province":"MI",
    "wof:name":"Auto Club Group Insurance Co",
    "wof:placetype":"venue"
},
  "geometry": {"coordinates":[-83.05120599999999,42.335837],"type":"Point"}
}