{
  "type": "Feature",
  "properties": {
    "iso:country":"US",
    "sg:address":"578 N Cedar St",
    "sg:city":"Mason",
    "sg:classifiers":[
        {
            "category":"Professional",
            "subcategory":"Business Services",
            "type":"Services"
        }
    ],
    "sg:phone":"+1 517 676 2000",
    "sg:postcode":"48854",
    "sg:province":"MI",
    "sg:tags":[
        "water",
        "treatment"
    ],
    "wof:name":"Ecowater Systems",
    "wof:placetype":"venue"
},
  "geometry": {"coordinates":[-84.452763,42.584258],"type":"Point"}
}