{
  "type": "Feature",
  "properties": {
    "iso:country":"US",
    "sg:address":"28 S Prospect St",
    "sg:city":"Ypsilanti",
    "sg:classifiers":[
        {
            "category":"Health Services",
            "subcategory":"Nursing And Care Facility",
            "type":"Services"
        }
    ],
    "sg:phone":"+1 734 483 2220",
    "sg:postcode":"48198",
    "sg:province":"MI",
    "sg:tags":[
        "skilled"
    ],
    "wof:name":"Bortz Health Care",
    "wof:placetype":"venue"
},
  "geometry": {"coordinates":[-83.602047,42.239829],"type":"Point"}
}