{
  "type": "Feature",
  "properties": {
    "iso:country":"US",
    "sg:address":"2544 Garfield Ave NW",
    "sg:city":"Grand Rapids",
    "sg:classifiers":[
        {
            "category":"Retail",
            "subcategory":"Animal Services",
            "type":"Services"
        }
    ],
    "sg:phone":"+1 616 784 3336",
    "sg:postcode":"49544",
    "sg:province":"MI",
    "sg:tags":[
        "cat",
        "dog",
        "kennel"
    ],
    "wof:name":"Michigan Shephard Kennels Inc",
    "wof:placetype":"venue"
},
  "geometry": {"coordinates":[-85.697836,43.010627],"type":"Point"}
}