{
  "type": "Feature",
  "properties": {
    "iso:country":"US",
    "sg:address":"1224 Division St",
    "sg:city":"Marquette",
    "sg:classifiers":[
        {
            "category":"Professional",
            "subcategory":"Accounting & Tax Preparation",
            "type":"Services"
        }
    ],
    "sg:phone":"+1 906 228 3372",
    "sg:postcode":"49855",
    "sg:province":"MI",
    "sg:tags":[
        "accountant"
    ],
    "wof:name":"Doing Business Assoc",
    "wof:placetype":"venue"
},
  "geometry": {"coordinates":[-87.39838,46.533743],"type":"Point"}
}