{
  "type": "Feature",
  "properties": {
    "iso:country":"US",
    "sg:address":"600 Butternut Dr",
    "sg:city":"Holland",
    "sg:classifiers":[
        {
            "category":"Organizations",
            "subcategory":"Religious Organization",
            "type":"Services"
        }
    ],
    "sg:phone":"+1 616 399 2558",
    "sg:postcode":"49424",
    "sg:province":"MI",
    "sg:tags":[
        "church"
    ],
    "sg:website":"www.roseparkbaptist.com",
    "wof:name":"Rose Park Baptist Church Inc",
    "wof:placetype":"venue"
},
  "geometry": {"coordinates":[-86.125152,42.815982],"type":"Point"}
}