{
  "type": "Feature",
  "properties": {
    "iso:country":"US",
    "sg:address":"301 Custer Dr",
    "sg:city":"Battle Creek",
    "sg:classifiers":[
        {
            "category":"Organizations",
            "subcategory":"Religious Organization",
            "type":"Services"
        }
    ],
    "sg:phone":"+1 269 968 0233",
    "sg:postcode":"49028",
    "sg:province":"MI",
    "sg:tags":[
        "church"
    ],
    "wof:name":"Faith Assembly Of God",
    "wof:placetype":"venue"
},
  "geometry": {"coordinates":[-85.03188,41.767642],"type":"Point"}
}