{
  "type": "Feature",
  "properties": {
    "iso:country":"US",
    "sg:address":"746 Hannah Ave",
    "sg:city":"Traverse City",
    "sg:classifiers":[
        {
            "category":"Building & Trades",
            "subcategory":"Cleaning & Sanitation",
            "type":"Services"
        }
    ],
    "sg:phone":"+1 231 933 0584",
    "sg:postcode":"49686",
    "sg:province":"MI",
    "sg:tags":[
        "maintenance"
    ],
    "wof:name":"Cleaning By Nancy",
    "wof:placetype":"venue"
},
  "geometry": {"coordinates":[-85.60618100000001,44.755336],"type":"Point"}
}