{
  "type": "Feature",
  "properties": {
    "iso:country":"US",
    "sg:address":"1307 Higgins Dr",
    "sg:city":"Cheboygan",
    "sg:classifiers":[
        {
            "category":"Utilities",
            "subcategory":"Refuse",
            "type":"Services"
        }
    ],
    "sg:phone":"+1 231 627 4652",
    "sg:postcode":"49721",
    "sg:province":"MI",
    "sg:tags":[
        "waste",
        "management"
    ],
    "wof:name":"Waste Management",
    "wof:placetype":"venue"
},
  "geometry": {"coordinates":[-84.492395,45.652046],"type":"Point"}
}