{
  "type": "Feature",
  "properties": {
    "iso:country":"US",
    "sg:address":"8020 E Cloverdale Rd",
    "sg:city":"Nashville",
    "sg:classifiers":[
        {
            "category":"Real Estate",
            "subcategory":"Architect",
            "type":"Services"
        }
    ],
    "sg:phone":"+1 517 852 1579",
    "sg:postcode":"49073",
    "sg:province":"MI",
    "sg:tags":[
        "estimate",
        "construction"
    ],
    "wof:name":"M S Construction",
    "wof:placetype":"venue"
},
  "geometry": {"coordinates":[-85.11355,42.537947],"type":"Point"}
}