{
  "type": "Feature",
  "properties": {
    "iso:country":"US",
    "sg:address":"4325 Main St",
    "sg:city":"Brown City",
    "sg:classifiers":[
        {
            "category":"Personal",
            "subcategory":"Beauty Salon",
            "type":"Services"
        }
    ],
    "sg:phone":"+1 810 346 3798",
    "sg:postcode":"48416",
    "sg:province":"MI",
    "wof:name":"Styling Station",
    "wof:placetype":"venue"
},
  "geometry": {"coordinates":[-82.991733,43.212032],"type":"Point"}
}