{
  "type": "Feature",
  "properties": {
    "iso:country":"US",
    "sg:address":"1805 Canyon Trl",
    "sg:city":"Lansing",
    "sg:classifiers":[
        {
            "category":"Professional",
            "subcategory":"Engineering",
            "type":"Services"
        }
    ],
    "sg:phone":"+1 517 321 2624",
    "sg:postcode":"48917",
    "sg:province":"MI",
    "sg:tags":[
        "consultant"
    ],
    "wof:name":"Stanley & Associates Inc",
    "wof:placetype":"venue"
},
  "geometry": {"coordinates":[-84.614931,42.754283],"type":"Point"}
}