{
  "type": "Feature",
  "properties": {
    "iso:country":"US",
    "sg:address":"23300 Allen Rd",
    "sg:city":"Trenton",
    "sg:classifiers":[
        {
            "category":"Home & Garden",
            "subcategory":"Hardware",
            "type":"Retail Goods"
        }
    ],
    "sg:phone":"+1 734 671 4400",
    "sg:postcode":"48183",
    "sg:province":"MI",
    "sg:tags":[
        "store"
    ],
    "wof:name":"Home Depot Store No 2738",
    "wof:placetype":"venue"
},
  "geometry": {"coordinates":[-83.226196,42.138302],"type":"Point"}
}