{
  "type": "Feature",
  "properties": {
    "iso:country":"US",
    "sg:address":"2668 W Court St",
    "sg:city":"Flint",
    "sg:classifiers":[
        {
            "category":"Personal",
            "subcategory":"Barber",
            "type":"Services"
        }
    ],
    "sg:phone":"+1 810 235 1355",
    "sg:postcode":"48503",
    "sg:province":"MI",
    "sg:tags":[
        "shop"
    ],
    "wof:name":"Dale's Place",
    "wof:placetype":"venue"
},
  "geometry": {"coordinates":[-83.724039,43.006977],"type":"Point"}
}