{
  "type": "Feature",
  "properties": {
    "iso:country":"US",
    "sg:address":"852 Robin Wood Ct",
    "sg:city":"Traverse City",
    "sg:classifiers":[
        {
            "category":"Professional",
            "subcategory":"Research",
            "type":"Services"
        }
    ],
    "sg:phone":"+1 231 933 9846",
    "sg:postcode":"49686",
    "sg:province":"MI",
    "sg:tags":[
        "development",
        "laboratory"
    ],
    "wof:name":"North Bay Bio Science",
    "wof:placetype":"venue"
},
  "geometry": {"coordinates":[-85.602997,44.743149],"type":"Point"}
}