{
  "type": "Feature",
  "properties": {
    "iso:country":"US",
    "sg:address":"220 W Michigan Ave",
    "sg:city":"Paw Paw",
    "sg:classifiers":[
        {
            "category":"Professional",
            "subcategory":"Accounting & Tax Preparation",
            "type":"Services"
        }
    ],
    "sg:phone":"+1 269 657 4578",
    "sg:postcode":"49079",
    "sg:province":"MI",
    "sg:tags":[
        "accountant"
    ],
    "wof:name":"Cameron & Smith PC",
    "wof:placetype":"venue"
},
  "geometry": {"coordinates":[-85.89804700000001,42.217602],"type":"Point"}
}