{
  "type": "Feature",
  "properties": {
    "iso:country":"US",
    "sg:address":"13064 Wisner Ave",
    "sg:city":"Grant",
    "sg:classifiers":[
        {
            "category":"Manufacturing",
            "subcategory":"Metals",
            "type":"Manufacturing & Wholesale Goods"
        }
    ],
    "sg:phone":"+1 231 834 8791",
    "sg:postcode":"49327",
    "sg:province":"MI",
    "sg:tags":[
        "tower"
    ],
    "wof:name":"Grant Tower Inc",
    "wof:placetype":"venue"
},
  "geometry": {"coordinates":[-85.870012,43.316495],"type":"Point"}
}