{
  "type": "Feature",
  "properties": {
    "iso:country":"US",
    "sg:address":"4200 Woodward Ave # 207",
    "sg:city":"Pontiac",
    "sg:classifiers":[
        {
            "category":"Health Services",
            "subcategory":"Doctor",
            "type":"Services"
        }
    ],
    "sg:phone":"+1 248 322 6103",
    "sg:postcode":"48201",
    "sg:province":"MI",
    "sg:website":"www.michiganurology.com",
    "wof:name":"Michigan Institute of Urology",
    "wof:placetype":"venue"
},
  "geometry": {"coordinates":[-83.28873400000001,42.632778],"type":"Point"}
}