{
  "type": "Feature",
  "properties": {
    "iso:country":"US",
    "sg:address":"224 S Cedar St",
    "sg:city":"Kalkaska",
    "sg:classifiers":[
        {
            "category":"Health Services",
            "subcategory":"Clinic",
            "type":"Services"
        }
    ],
    "sg:phone":"+1 231 258 8679",
    "sg:postcode":"49646",
    "sg:province":"MI",
    "sg:tags":[
        "wellness",
        "program"
    ],
    "wof:name":"Wellness Center",
    "wof:placetype":"venue"
},
  "geometry": {"coordinates":[-85.176153,44.733471],"type":"Point"}
}