{
  "type": "Feature",
  "properties": {
    "iso:country":"US",
    "sg:address":"22155 W Village Dr",
    "sg:city":"Dearborn",
    "sg:classifiers":[
        {
            "category":"Professional",
            "subcategory":"Business Services",
            "type":"Services"
        }
    ],
    "sg:phone":"+1 313 561 5131",
    "sg:postcode":"48124",
    "sg:province":"MI",
    "sg:tags":[
        "notary",
        "republic"
    ],
    "wof:name":"Emily Joyce Olkowski",
    "wof:placetype":"venue"
},
  "geometry": {"coordinates":[-83.246616,42.304842],"type":"Point"}
}