{
  "type": "Feature",
  "properties": {
    "iso:country":"US",
    "sg:address":"969 Chicago Rd",
    "sg:city":"Troy",
    "sg:classifiers":[
        {
            "category":"Banks & Credit Unions",
            "subcategory":"Bank",
            "type":"Services"
        }
    ],
    "sg:phone":"+1 248 269 6000",
    "sg:postcode":"48083",
    "sg:province":"MI",
    "sg:tags":[
        "other",
        "plan",
        "card"
    ],
    "sg:website":"www.nabancard.com",
    "wof:name":"North American Bancard",
    "wof:placetype":"venue"
},
  "geometry": {"coordinates":[-83.11387000000001,42.548714],"type":"Point"}
}