{
  "type": "Feature",
  "properties": {
    "iso:country":"US",
    "sg:address":"924 Broken Ridge Dr",
    "sg:city":"Lansing",
    "sg:classifiers":[
        {
            "category":"Real Estate",
            "subcategory":"Surveying",
            "type":"Services"
        }
    ],
    "sg:phone":"+1 517 323 9471",
    "sg:postcode":"48917",
    "sg:province":"MI",
    "sg:tags":[
        "surveyor"
    ],
    "wof:name":"Southern Michigan Land Srvyng",
    "wof:placetype":"venue"
},
  "geometry": {"coordinates":[-84.65173299999999,42.723781],"type":"Point"}
}