{
  "type": "Feature",
  "properties": {
    "iso:country":"US",
    "sg:address":"1033 Lumina Dr",
    "sg:city":"Jenison",
    "sg:classifiers":[
        {
            "category":"Wholesale",
            "subcategory":"Machinery & Supplies",
            "type":"Manufacturing & Wholesale Goods"
        }
    ],
    "sg:phone":"+1 616 457 5003",
    "sg:postcode":"49428",
    "sg:province":"MI",
    "sg:tags":[
        "equipment",
        "sand",
        "gravel",
        "handling"
    ],
    "wof:name":"Aggtech",
    "wof:placetype":"venue"
},
  "geometry": {"coordinates":[-85.808757,42.926631],"type":"Point"}
}