{
  "type": "Feature",
  "properties": {
    "iso:country":"US",
    "sg:address":"1400 Keystone Ave",
    "sg:city":"Lansing",
    "sg:classifiers":[
        {
            "category":"Wholesale",
            "subcategory":"Office Equipment",
            "type":"Manufacturing & Wholesale Goods"
        }
    ],
    "sg:phone":"+1 517 393 3440",
    "sg:postcode":"48911",
    "sg:province":"MI",
    "sg:tags":[
        "machine",
        "duplicating",
        "copying"
    ],
    "sg:website":"www.polackcorp.com",
    "wof:name":"Polack Corp",
    "wof:placetype":"venue"
},
  "geometry": {"coordinates":[-84.529445,42.676246],"type":"Point"}
}