{
  "type": "Feature",
  "properties": {
    "iso:country":"US",
    "sg:address":"4918 Ledgerock St",
    "sg:city":"Jackson",
    "sg:classifiers":[
        {
            "category":"Building & Trades",
            "subcategory":"Construction",
            "type":"Services"
        }
    ],
    "sg:phone":"+1 517 784 7206",
    "sg:postcode":"49201",
    "sg:province":"MI",
    "sg:tags":[
        "house"
    ],
    "wof:name":"Mark Cardwell Builders",
    "wof:placetype":"venue"
},
  "geometry": {"coordinates":[-84.407347,42.307624],"type":"Point"}
}