{
  "type": "Feature",
  "properties": {
    "iso:country":"US",
    "sg:address":"410 S Linden St",
    "sg:city":"Marshall",
    "sg:classifiers":[
        {
            "category":"Professional",
            "subcategory":"Business Services",
            "type":"Services"
        }
    ],
    "sg:phone":"+1 269 781 2711",
    "sg:postcode":"49068",
    "sg:province":"MI",
    "wof:name":"Michigan Grain Inspection Svc",
    "wof:placetype":"venue"
},
  "geometry": {"coordinates":[-84.969205,42.267841],"type":"Point"}
}