{
  "type": "Feature",
  "properties": {
    "iso:country":"US",
    "sg:address":"6873 N Fairland Loop",
    "sg:city":"Menominee",
    "sg:classifiers":[
        {
            "category":"Freight",
            "type":"Transportation"
        }
    ],
    "sg:phone":"+1 906 863 5791",
    "sg:postcode":"49858",
    "sg:province":"MI",
    "sg:tags":[
        "general"
    ],
    "wof:name":"Security Storage",
    "wof:placetype":"venue"
},
  "geometry": {"coordinates":[-87.672692,45.136491],"type":"Point"}
}