{
  "type": "Feature",
  "properties": {
    "iso:country":"US",
    "sg:address":"5321 Main St",
    "sg:city":"Lexington",
    "sg:classifiers":[
        {
            "category":"Retail",
            "subcategory":"Self-service Laundry",
            "type":"Services"
        }
    ],
    "sg:phone":"+1 810 359 8092",
    "sg:postcode":"48450",
    "sg:province":"MI",
    "wof:name":"Conlee's Bright & Clean",
    "wof:placetype":"venue"
},
  "geometry": {"coordinates":[-82.53126399999999,43.272734],"type":"Point"}
}