{
  "type": "Feature",
  "properties": {
    "iso:country":"US",
    "sg:address":"14625 Doster Rd",
    "sg:city":"Plainwell",
    "sg:classifiers":[
        {
            "category":"Professional",
            "subcategory":"Management & Consulting",
            "type":"Services"
        }
    ],
    "sg:phone":"+1 269 372 2210",
    "sg:postcode":"49080",
    "sg:province":"MI",
    "sg:tags":[
        "co",
        "business",
        "trade"
    ],
    "wof:name":"Analytcal Tstg Consulting Svcs",
    "wof:placetype":"venue"
},
  "geometry": {"coordinates":[-85.543351,42.443633],"type":"Point"}
}