{
  "type": "Feature",
  "properties": {
    "iso:country":"US",
    "sg:address":"10927 W Monroe Rd",
    "sg:city":"Riverdale",
    "sg:classifiers":[
        {
            "category":"Building & Trades",
            "subcategory":"Plumbing",
            "type":"Services"
        }
    ],
    "sg:phone":"+1 989 833 7319",
    "sg:postcode":"48832",
    "sg:province":"MI",
    "sg:tags":[
        "septic"
    ],
    "wof:name":"Security Septic Tanks Inc",
    "wof:placetype":"venue"
},
  "geometry": {"coordinates":[-84.826351,43.408273],"type":"Point"}
}