{
  "type": "Feature",
  "properties": {
    "iso:country":"US",
    "sg:address":"37 Balfour Dr",
    "sg:city":"Bloomfield Hills",
    "sg:classifiers":[
        {
            "category":"Retail",
            "subcategory":"Auto Repair",
            "type":"Services"
        }
    ],
    "sg:phone":"+1 248 540 6098",
    "sg:postcode":"48304",
    "sg:province":"MI",
    "sg:tags":[
        "automotive",
        "parts",
        "painting"
    ],
    "wof:name":"Doris Richard",
    "wof:placetype":"venue"
},
  "geometry": {"coordinates":[-83.25287299999999,42.591128],"type":"Point"}
}