{
  "type": "Feature",
  "properties": {
    "iso:country":"US",
    "sg:address":"34562 Rhonswood St",
    "sg:city":"Farmington",
    "sg:classifiers":[
        {
            "category":"Professional",
            "subcategory":"Management & Consulting",
            "type":"Services"
        }
    ],
    "sg:phone":"+1 248 474 1062",
    "sg:postcode":"48335",
    "sg:province":"MI",
    "wof:name":"Top Quality Window Co",
    "wof:placetype":"venue"
},
  "geometry": {"coordinates":[-83.388605,42.445066],"type":"Point"}
}