{
  "type": "Feature",
  "properties": {
    "iso:country":"US",
    "sg:address":"10 E Center St",
    "sg:city":"Douglas",
    "sg:classifiers":[
        {
            "category":"Shopping",
            "type":"Retail Goods"
        }
    ],
    "sg:phone":"+1 269 857 3311",
    "sg:postcode":"49406",
    "sg:province":"MI",
    "sg:tags":[
        "art",
        "gallery",
        "dealer"
    ],
    "wof:name":"Cadwallader Fine Art",
    "wof:placetype":"venue"
},
  "geometry": {"coordinates":[-86.200835,42.643813],"type":"Point"}
}