{
  "type": "Feature",
  "properties": {
    "iso:country":"US",
    "sg:address":"5945 Oakman Blvd",
    "sg:city":"Dearborn",
    "sg:classifiers":[
        {
            "category":"Professional",
            "subcategory":"Accounting & Tax Preparation",
            "type":"Services"
        }
    ],
    "sg:phone":"+1 313 804 2779",
    "sg:postcode":"48126",
    "sg:province":"MI",
    "wof:name":"Tammy L Berry",
    "wof:placetype":"venue"
},
  "geometry": {"coordinates":[-83.16929,42.33194],"type":"Point"}
}