{
  "type": "Feature",
  "properties": {
    "iso:country":"US",
    "sg:address":"8319 Apple Blossom Ln",
    "sg:city":"Flushing",
    "sg:classifiers":[
        {
            "category":"Real Estate",
            "subcategory":"Real Estate Agent",
            "type":"Services"
        }
    ],
    "sg:phone":"+1 810 249 4900",
    "sg:postcode":"48433",
    "sg:province":"MI",
    "wof:name":"Remax Select Realty",
    "wof:placetype":"venue"
},
  "geometry": {"coordinates":[-83.846166,43.078878],"type":"Point"}
}