{
  "type": "Feature",
  "properties": {
    "iso:country":"US",
    "sg:address":"1357 S Main St",
    "sg:city":"Adrian",
    "sg:classifiers":[
        {
            "category":"Bars & Pubs",
            "type":"Food & Drink"
        }
    ],
    "sg:menulink":"http://www.allmenus.com/mi/madison/224316-garfields-restaurant--pub/menu/",
    "sg:phone":"+1 517 266 1512",
    "sg:postcode":"49221",
    "sg:province":"MI",
    "sg:tags":[
        "american"
    ],
    "wof:name":"Garfield's Restaurant & Pub",
    "wof:placetype":"venue"
},
  "geometry": {"coordinates":[-84.04326,41.880238],"type":"Point"}
}