{
  "type": "Feature",
  "properties": {
    "iso:country":"US",
    "sg:address":"982 Cliffdale Dr",
    "sg:city":"Haslett",
    "sg:classifiers":[
        {
            "category":"Professional",
            "subcategory":"Business Services",
            "type":"Services"
        }
    ],
    "sg:phone":"+1 517 339 6525",
    "sg:postcode":"48840",
    "sg:province":"MI",
    "wof:name":"Inside Out Home Inspections",
    "wof:placetype":"venue"
},
  "geometry": {"coordinates":[-84.38318099999999,42.745032],"type":"Point"}
}