{
  "type": "Feature",
  "properties": {
    "iso:country":"US",
    "sg:address":"2100 Brooklyn Rd",
    "sg:city":"Jackson",
    "sg:classifiers":[
        {
            "category":"Shopping",
            "type":"Retail Goods"
        }
    ],
    "sg:phone":"+1 517 787 1330",
    "sg:postcode":"49203",
    "sg:province":"MI",
    "sg:tags":[
        "awning",
        "canopy"
    ],
    "wof:name":"Jackson Canvas Co",
    "wof:placetype":"venue"
},
  "geometry": {"coordinates":[-84.378846,42.216938],"type":"Point"}
}