{
  "type": "Feature",
  "properties": {
    "iso:country":"US",
    "sg:address":"5442 Poplar Dr",
    "sg:city":"Monroe",
    "sg:classifiers":[
        {
            "category":"Professional",
            "subcategory":"Secretarial Services",
            "type":"Services"
        }
    ],
    "sg:phone":"+1 734 240 7170",
    "sg:postcode":"48161",
    "sg:province":"MI",
    "sg:tags":[
        "reporting"
    ],
    "wof:name":"Jordan Antonina",
    "wof:placetype":"venue"
},
  "geometry": {"coordinates":[-83.41656999999999,41.8838],"type":"Point"}
}