{
  "type": "Feature",
  "properties": {
    "iso:country":"US",
    "sg:address":"2321 Corunna Rd",
    "sg:city":"Flint",
    "sg:classifiers":[
        {
            "category":"Professional",
            "subcategory":"Lawyer & Legal Services",
            "type":"Services"
        }
    ],
    "sg:phone":"+1 810 235 4770",
    "sg:postcode":"48503",
    "sg:province":"MI",
    "wof:name":"Rowe James L Atty",
    "wof:placetype":"venue"
},
  "geometry": {"coordinates":[-83.71700300000001,43.004299],"type":"Point"}
}