{
  "type": "Feature",
  "properties": {
    "iso:country":"US",
    "sg:address":"2016 Carlton Ct",
    "sg:city":"White Lake",
    "sg:classifiers":[
        {
            "category":"Professional",
            "subcategory":"Engineering",
            "type":"Services"
        }
    ],
    "sg:phone":"+1 248 889 5702",
    "sg:postcode":"48383",
    "sg:province":"MI",
    "wof:name":"J V Force Inc",
    "wof:placetype":"venue"
},
  "geometry": {"coordinates":[-83.5243,42.623197],"type":"Point"}
}