{
  "type": "Feature",
  "properties": {
    "iso:country":"US",
    "sg:address":"2030 Fawn Ave",
    "sg:city":"Middleville",
    "sg:classifiers":[
        {
            "category":"Organizations",
            "subcategory":"Religious Organization",
            "type":"Services"
        }
    ],
    "sg:phone":"+1 269 795 7076",
    "sg:postcode":"49333",
    "sg:province":"MI",
    "sg:tags":[
        "church"
    ],
    "wof:name":"Cornerstone Wesleyan Church",
    "wof:placetype":"venue"
},
  "geometry": {"coordinates":[-85.461744,42.684926],"type":"Point"}
}