{
  "type": "Feature",
  "properties": {
    "iso:country":"US",
    "sg:address":"319 Bay St",
    "sg:city":"Petoskey",
    "sg:classifiers":[
        {
            "category":"Shopping",
            "subcategory":"Gifts & Souvenirs",
            "type":"Retail Goods"
        }
    ],
    "sg:phone":"+1 231 487 0759",
    "sg:postcode":"49770",
    "sg:province":"MI",
    "sg:tags":[
        "accessory"
    ],
    "wof:name":"Forte By The Bay",
    "wof:placetype":"venue"
},
  "geometry": {"coordinates":[-84.95560500000001,45.375971],"type":"Point"}
}