{
  "type": "Feature",
  "properties": {
    "iso:country":"US",
    "sg:address":"255 S Main St",
    "sg:city":"Woodland",
    "sg:classifiers":[
        {
            "category":"Wholesale",
            "subcategory":"Electrical",
            "type":"Manufacturing & Wholesale Goods"
        }
    ],
    "sg:phone":"+1 269 367 9181",
    "sg:postcode":"48897",
    "sg:province":"MI",
    "sg:tags":[
        "electric",
        "motor"
    ],
    "wof:name":"Mayhem Motor Works LLC",
    "wof:placetype":"venue"
},
  "geometry": {"coordinates":[-85.134173,42.723228],"type":"Point"}
}