{
  "type": "Feature",
  "properties": {
    "iso:country":"US",
    "sg:address":"15224 Wyoming St",
    "sg:city":"Detroit",
    "sg:classifiers":[
        {
            "category":"Restaurant",
            "type":"Food & Drink"
        }
    ],
    "sg:phone":"+1 313 934 4444",
    "sg:postcode":"48238",
    "sg:province":"MI",
    "sg:tags":[
        "pizza"
    ],
    "wof:name":"Crazy Joe's Pizza",
    "wof:placetype":"venue"
},
  "geometry": {"coordinates":[-83.15949999999999,42.402302],"type":"Point"}
}