{
  "type": "Feature",
  "properties": {
    "iso:country":"US",
    "sg:address":"30895 W Huron River Dr",
    "sg:city":"Flat Rock",
    "sg:classifiers":[
        {
            "category":"Retail",
            "subcategory":"Funeral Services",
            "type":"Services"
        },
        {
            "category":"Shopping",
            "subcategory":"Florist",
            "type":"Retail Goods"
        }
    ],
    "sg:phone":"+1 734 783 2646",
    "sg:postcode":"48134",
    "sg:province":"MI",
    "sg:tags":[
        "cemetery"
    ],
    "sg:website":"www.michmemfuneralhome.com",
    "wof:name":"Michigan Memorial Funeral Home and Floral Shop",
    "wof:placetype":"venue"
},
  "geometry": {"coordinates":[-83.337192,42.120016],"type":"Point"}
}