{
  "type": "Feature",
  "properties": {
    "iso:country":"US",
    "sg:address":"12080 S Beyer Rd",
    "sg:city":"Birch Run",
    "sg:classifiers":[
        {
            "category":"Shopping",
            "type":"Retail Goods"
        }
    ],
    "sg:phone":"+1 989 624 9831",
    "sg:postcode":"48415",
    "sg:province":"MI",
    "sg:tags":[
        "factory",
        "outlet"
    ],
    "wof:name":"Athlete's Foot",
    "wof:placetype":"venue"
},
  "geometry": {"coordinates":[-83.77472899999999,43.2477],"type":"Point"}
}