{
  "type": "Feature",
  "properties": {
    "iso:country":"US",
    "sg:address":"3060 S Channel Dr",
    "sg:city":"Harsens Island",
    "sg:classifiers":[
        {
            "category":"Food & Beverages",
            "subcategory":"Groceries & Convenience Stores",
            "type":"Retail Goods"
        }
    ],
    "sg:phone":"+1 810 748 9961",
    "sg:postcode":"48028",
    "sg:province":"MI",
    "sg:tags":[
        "grocer"
    ],
    "wof:name":"San Souci Market",
    "wof:placetype":"venue"
},
  "geometry": {"coordinates":[-82.561814,42.581413],"type":"Point"}
}