{
  "type": "Feature",
  "properties": {
    "iso:country":"US",
    "sg:address":"4098 Lake Shore Rd",
    "sg:city":"Boyne City",
    "sg:classifiers":[
        {
            "category":"Professional",
            "type":"Services"
        }
    ],
    "sg:phone":"+1 231 582 9909",
    "sg:postcode":"49712",
    "sg:province":"MI",
    "sg:tags":[
        "establishment"
    ],
    "wof:name":"Alexander Dun & Sons LTD",
    "wof:placetype":"venue"
},
  "geometry": {"coordinates":[-85.06475,45.214925],"type":"Point"}
}