{
  "type": "Feature",
  "properties": {
    "iso:country":"US",
    "sg:address":"735 Carton St",
    "sg:city":"Flint",
    "sg:classifiers":[
        {
            "category":"Professional",
            "type":"Services"
        }
    ],
    "sg:phone":"+1 810 787 8542",
    "sg:postcode":"48505",
    "sg:province":"MI",
    "sg:tags":[
        "establishment"
    ],
    "wof:name":"Bolden Average Anderson",
    "wof:placetype":"venue"
},
  "geometry": {"coordinates":[-83.691309,43.048518],"type":"Point"}
}