{
  "type": "Feature",
  "properties": {
    "iso:country":"US",
    "sg:address":"18401 Wyoming St",
    "sg:city":"Detroit",
    "sg:classifiers":[
        {
            "category":"Deli",
            "type":"Food & Drink"
        }
    ],
    "sg:phone":"+1 313 864 6145",
    "sg:postcode":"48221",
    "sg:province":"MI",
    "wof:name":"Deli Plaza Delicatessen",
    "wof:placetype":"venue"
},
  "geometry": {"coordinates":[-83.16089599999999,42.426102],"type":"Point"}
}