{
  "type": "Feature",
  "properties": {
    "iso:country":"US",
    "sg:address":"20100 Haggerty Rd",
    "sg:city":"Livonia",
    "sg:classifiers":[
        {
            "category":"Food & Beverages",
            "subcategory":"Groceries & Convenience Stores",
            "type":"Retail Goods"
        }
    ],
    "sg:phone":"+1 734 462 3683",
    "sg:postcode":"48152",
    "sg:province":"MI",
    "wof:name":"Luxottica Store # C4291",
    "wof:placetype":"venue"
},
  "geometry": {"coordinates":[-83.433277,42.433796],"type":"Point"}
}