{
  "type": "Feature",
  "properties": {
    "iso:country":"US",
    "sg:address":"700 Barry Rd",
    "sg:city":"Haslett",
    "sg:classifiers":[
        {
            "category":"Building & Trades",
            "subcategory":"Construction",
            "type":"Services"
        }
    ],
    "sg:phone":"+1 517 655 8891",
    "sg:postcode":"48840",
    "sg:province":"MI",
    "sg:tags":[
        "downspouts",
        "gutter"
    ],
    "wof:name":"Sunrise Seamless",
    "wof:placetype":"venue"
},
  "geometry": {"coordinates":[-84.347345,42.769469],"type":"Point"}
}