{
  "type": "Feature",
  "properties": {
    "iso:country":"US",
    "sg:address":"9483 Portage Trl",
    "sg:city":"White Lake",
    "sg:classifiers":[
        {
            "category":"Freight",
            "type":"Transportation"
        }
    ],
    "sg:phone":"+1 248 698 3147",
    "sg:postcode":"48386",
    "sg:province":"MI",
    "sg:tags":[
        "trucking"
    ],
    "wof:name":"Allen Transport",
    "wof:placetype":"venue"
},
  "geometry": {"coordinates":[-83.472188,42.637042],"type":"Point"}
}