{
  "type": "Feature",
  "properties": {
    "iso:country":"US",
    "sg:address":"11034 Mae Ave",
    "sg:city":"Warren",
    "sg:classifiers":[
        {
            "category":"Travel",
            "subcategory":"Hotels & Motels",
            "type":"Entertainment"
        },
        {
            "category":"Personal",
            "type":"Services"
        }
    ],
    "sg:phone":"+1 586 755 5651",
    "sg:postcode":"48089",
    "sg:province":"MI",
    "sg:tags":[
        "concierge",
        "assistant"
    ],
    "sg:website":"http://coolfamilytrees.homestead.com",
    "wof:name":"Aurora Graphics Cool Family Trees",
    "wof:placetype":"venue"
},
  "geometry": {"coordinates":[-83.015629,42.484492],"type":"Point"}
}