{
  "type": "Feature",
  "properties": {
    "iso:country":"US",
    "sg:address":"645 Menard Dr",
    "sg:city":"Lansing",
    "sg:classifiers":[
        {
            "category":"Restaurant",
            "type":"Food & Drink"
        }
    ],
    "sg:menulink":"http://www.allmenus.com/mi/delta/186068-mcdonalds/menu/",
    "sg:postcode":"48917",
    "sg:province":"MI",
    "sg:tags":[
        "burger",
        "american"
    ],
    "wof:name":"McDonald's",
    "wof:placetype":"venue"
},
  "geometry": {"coordinates":[-84.677296,42.740374],"type":"Point"}
}