{
  "type": "Feature",
  "properties": {
    "iso:country":"US",
    "sg:address":"1329 Michigan Ave",
    "sg:city":"St Louis",
    "sg:classifiers":[
        {
            "category":"Social Services",
            "subcategory":"Adult Care",
            "type":"Services"
        }
    ],
    "sg:phone":"+1 989 681 4341",
    "sg:postcode":"48880",
    "sg:province":"MI",
    "sg:tags":[
        "organization",
        "senior",
        "citizen"
    ],
    "wof:name":"Gratiot Community Senior Ctr",
    "wof:placetype":"venue"
},
  "geometry": {"coordinates":[-84.62213800000001,43.395638],"type":"Point"}
}