{
  "type": "Feature",
  "properties": {
    "iso:country":"US",
    "sg:address":"8040 Vantine Rd",
    "sg:city":"Goodrich",
    "sg:classifiers":[
        {
            "category":"Professional",
            "type":"Services"
        }
    ],
    "sg:phone":"+1 810 636 4164",
    "sg:postcode":"48438",
    "sg:province":"MI",
    "wof:name":"Jeffand Wendy Edgett",
    "wof:placetype":"venue"
},
  "geometry": {"coordinates":[-83.550686,42.877712],"type":"Point"}
}