{
  "type": "Feature",
  "properties": {
    "iso:country":"US",
    "sg:address":"521 Woodmere Ave",
    "sg:city":"Traverse City",
    "sg:classifiers":[
        {
            "category":"Retail",
            "subcategory":"Auto Repair",
            "type":"Services"
        }
    ],
    "sg:phone":"+1 231 929 1809",
    "sg:postcode":"49686",
    "sg:province":"MI",
    "sg:tags":[
        "body",
        "automobile",
        "painting"
    ],
    "wof:name":"Bay Area Collision",
    "wof:placetype":"venue"
},
  "geometry": {"coordinates":[-85.6075,44.758947],"type":"Point"}
}