{
  "type": "Feature",
  "properties": {
    "iso:country":"US",
    "sg:address":"4554 W Baker Rd",
    "sg:city":"Coleman",
    "sg:classifiers":[
        {
            "category":"Building & Trades",
            "subcategory":"Construction",
            "type":"Services"
        }
    ],
    "sg:phone":"+1 810 240 9678",
    "sg:postcode":"48618",
    "sg:province":"MI",
    "sg:tags":[
        "concrete",
        "contractor"
    ],
    "wof:name":"Willeys Concrete",
    "wof:placetype":"venue"
},
  "geometry": {"coordinates":[-84.547315,43.771261],"type":"Point"}
}