{
  "type": "Feature",
  "properties": {
    "iso:country":"US",
    "sg:address":"4560 Munger Rd",
    "sg:city":"Tipton",
    "sg:classifiers":[
        {
            "category":"Social Services",
            "subcategory":"Adult Care",
            "type":"Services"
        }
    ],
    "sg:phone":"+1 517 431 2064",
    "sg:postcode":"49287",
    "sg:province":"MI",
    "sg:tags":[
        "foster",
        "provider"
    ],
    "wof:name":"Stein Amy Joann-Tirado D",
    "wof:placetype":"venue"
},
  "geometry": {"coordinates":[-84.073778,42.02802],"type":"Point"}
}