{
  "type": "Feature",
  "properties": {
    "iso:country":"US",
    "sg:address":"36580 Farmbrook Dr",
    "sg:city":"Clinton Twp",
    "sg:classifiers":[
        {
            "category":"Shopping",
            "subcategory":"Computers & Home Electronics",
            "type":"Retail Goods"
        }
    ],
    "sg:phone":"+1 586 792 4209",
    "sg:postcode":"48035",
    "sg:province":"MI",
    "sg:tags":[
        "equipment",
        "dealer"
    ],
    "wof:name":"Devin Technology",
    "wof:placetype":"venue"
},
  "geometry": {"coordinates":[-82.919561,42.566686],"type":"Point"}
}