{
  "type": "Feature",
  "properties": {
    "iso:country":"US",
    "sg:address":"125 N Kalamazoo Mall",
    "sg:city":"Kalamazoo",
    "sg:classifiers":[
        {
            "category":"Restaurant",
            "type":"Food & Drink"
        }
    ],
    "sg:menulink":"http://www.allmenus.com/mi/kalamazoo/121149-the-union/menu/",
    "sg:phone":"+1 269 384 6756",
    "sg:postcode":"49007",
    "sg:province":"MI",
    "sg:tags":[
        "soup",
        "american",
        "sandwich",
        "salad"
    ],
    "wof:name":"The Union",
    "wof:placetype":"venue"
},
  "geometry": {"coordinates":[-85.58308,42.290491],"type":"Point"}
}