{
  "type": "Feature",
  "properties": {
    "iso:country":"US",
    "sg:address":"1000 Republic Dr",
    "sg:city":"Allen Park",
    "sg:classifiers":[
        {
            "category":"Manufacturing",
            "subcategory":"Motor Vehicles & Parts",
            "type":"Manufacturing & Wholesale Goods"
        }
    ],
    "sg:phone":"+1 313 845 3322",
    "sg:postcode":"48101",
    "sg:province":"MI",
    "sg:tags":[
        "body",
        "mfg"
    ],
    "wof:name":"Ford",
    "wof:placetype":"venue"
},
  "geometry": {"coordinates":[-83.19969399999999,42.298836],"type":"Point"}
}