{
  "type": "Feature",
  "properties": {
    "iso:country":"US",
    "sg:address":"2207 Dawson Ave NE",
    "sg:city":"Grand Rapids",
    "sg:classifiers":[
        {
            "category":"Professional",
            "subcategory":"Business Services",
            "type":"Services"
        }
    ],
    "sg:phone":"+1 616 634 0339",
    "sg:postcode":"49505",
    "sg:province":"MI",
    "wof:name":"Leslie Clausen",
    "wof:placetype":"venue"
},
  "geometry": {"coordinates":[-85.638588,43.001653],"type":"Point"}
}