{
  "type": "Feature",
  "properties": {
    "iso:country":"US",
    "sg:address":"10795 Dixie Hwy",
    "sg:city":"Springfield Twp",
    "sg:classifiers":[
        {
            "category":"Cinema",
            "subcategory":"Movie Rental",
            "type":"Entertainment"
        }
    ],
    "sg:phone":"+1 248 620 1700",
    "sg:postcode":"48350",
    "sg:province":"MI",
    "sg:tags":[
        "leasing",
        "video",
        "disc",
        "tape"
    ],
    "wof:name":"Video Palace",
    "wof:placetype":"venue"
},
  "geometry": {"coordinates":[-83.50320499999999,42.784172],"type":"Point"}
}