{
  "type": "Feature",
  "properties": {
    "iso:country":"US",
    "sg:address":"14 Market St",
    "sg:city":"Mount Clemens",
    "sg:classifiers":[
        {
            "category":"Restaurant",
            "type":"Food & Drink"
        }
    ],
    "sg:menulink":"http://www.allmenus.com/mi/mount-clemens/24209-sorrento-pizza/menu/",
    "sg:phone":"+1 586 463 8677",
    "sg:postcode":"48043",
    "sg:province":"MI",
    "sg:tags":[
        "american",
        "pizza"
    ],
    "wof:name":"Sorrento Pizza",
    "wof:placetype":"venue"
},
  "geometry": {"coordinates":[-82.87527300000001,42.598164],"type":"Point"}
}