{
  "type": "Feature",
  "properties": {
    "iso:country":"US",
    "sg:address":"1940 N Stark Rd",
    "sg:city":"Midland",
    "sg:classifiers":[
        {
            "category":"Building & Trades",
            "subcategory":"Plumbing",
            "type":"Services"
        }
    ],
    "sg:phone":"+1 989 633 3333",
    "sg:postcode":"48642",
    "sg:province":"MI",
    "sg:tags":[
        "heating",
        "contractor"
    ],
    "wof:name":"Wholesale Heating Supply",
    "wof:placetype":"venue"
},
  "geometry": {"coordinates":[-84.309845,43.666235],"type":"Point"}
}