{
  "type": "Feature",
  "properties": {
    "iso:country":"US",
    "sg:address":"7280 Riley Rd",
    "sg:city":"Corunna",
    "sg:phone":"+1 989 743 3393",
    "sg:postcode":"48817",
    "sg:province":"MI",
    "sg:tags":[
        "farm",
        "grain",
        "cash"
    ],
    "wof:name":"Richard Kalisek",
    "wof:placetype":"venue"
},
  "geometry": {"coordinates":[-84.01405099999999,43.073049],"type":"Point"}
}