{
  "type": "Feature",
  "properties": {
    "iso:country":"US",
    "sg:address":"6445 N Canton Center Rd",
    "sg:city":"Canton",
    "sg:classifiers":[
        {
            "category":"Retail",
            "subcategory":"Laundry & Dry Cleaning",
            "type":"Services"
        }
    ],
    "sg:phone":"+1 734 451 9755",
    "sg:postcode":"48187",
    "sg:province":"MI",
    "wof:name":"Kristal Cleaners",
    "wof:placetype":"venue"
},
  "geometry": {"coordinates":[-83.488542,42.330257],"type":"Point"}
}