{
  "type": "Feature",
  "properties": {
    "iso:country":"US",
    "sg:address":"25950 Five Mile Road",
    "sg:city":"Redford",
    "sg:classifiers":[
        {
            "category":"Professional",
            "subcategory":"Art Services",
            "type":"Services"
        }
    ],
    "sg:phone":"+1 313 535 0100",
    "sg:postcode":"48239",
    "sg:province":"MI",
    "sg:tags":[
        "photographer"
    ],
    "sg:website":"www.vippictures.net",
    "wof:name":"V.I.P. Pictures",
    "wof:placetype":"venue"
},
  "geometry": {"coordinates":[-83.297847,42.399698],"type":"Point"}
}