{
  "type": "Feature",
  "properties": {
    "iso:country":"US",
    "sg:address":"7980 US Hwy 12",
    "sg:city":"Onsted",
    "sg:classifiers":[
        {
            "category":"Shopping",
            "subcategory":"Gifts & Souvenirs",
            "type":"Retail Goods"
        }
    ],
    "sg:phone":"+1 517 467 9200",
    "sg:postcode":"49265",
    "sg:province":"MI",
    "sg:tags":[
        "shop"
    ],
    "wof:name":"Irish Hills Trade Ctr LTD",
    "wof:placetype":"venue"
},
  "geometry": {"coordinates":[-84.147203,42.056642],"type":"Point"}
}