{
  "type": "Feature",
  "properties": {
    "iso:country":"US",
    "sg:address":"201 E Main St",
    "sg:city":"Northville",
    "sg:classifiers":[
        {
            "category":"Banks & Credit Unions",
            "subcategory":"Bank",
            "type":"Services"
        }
    ],
    "sg:phone":"+1 248 449 3700",
    "sg:postcode":"48167",
    "sg:province":"MI",
    "sg:tags":[
        "state"
    ],
    "wof:name":"Main Street Bank Inc",
    "wof:placetype":"venue"
},
  "geometry": {"coordinates":[-83.48036500000001,42.431235],"type":"Point"}
}