{
  "type": "Feature",
  "properties": {
    "iso:country":"US",
    "sg:address":"245 Stoneville Rd",
    "sg:city":"Ishpeming",
    "sg:classifiers":[
        {
            "category":"Shopping",
            "subcategory":"Pharmacy",
            "type":"Retail Goods"
        }
    ],
    "sg:phone":"+1 906 485 5099",
    "sg:postcode":"49849",
    "sg:province":"MI",
    "wof:name":"Superior Transcription",
    "wof:placetype":"venue"
},
  "geometry": {"coordinates":[-87.718611,46.48351],"type":"Point"}
}