{
  "type": "Feature",
  "properties": {
    "iso:country":"US",
    "sg:address":"10304 Baldwin Rd",
    "sg:city":"Bridgman",
    "sg:classifiers":[
        {
            "category":"Restaurant",
            "type":"Food & Drink"
        }
    ],
    "sg:phone":"+1 269 465 6148",
    "sg:postcode":"49106",
    "sg:province":"MI",
    "sg:tags":[
        "eating"
    ],
    "wof:name":"Silver Spoon Restaurant & Lo",
    "wof:placetype":"venue"
},
  "geometry": {"coordinates":[-86.562466,41.931988],"type":"Point"}
}