{
  "type": "Feature",
  "properties": {
    "iso:country":"US",
    "sg:address":"9246 Kephart Ln",
    "sg:city":"Berrien Springs",
    "sg:classifiers":[
        {
            "category":"Freight",
            "type":"Transportation"
        }
    ],
    "sg:phone":"+1 269 471 1075",
    "sg:postcode":"49103",
    "sg:province":"MI",
    "wof:name":"Careful Transit Inc",
    "wof:placetype":"venue"
},
  "geometry": {"coordinates":[-86.342567,41.954268],"type":"Point"}
}