{
  "type": "Feature",
  "properties": {
    "iso:country":"US",
    "sg:address":"7572 Watford Dr",
    "sg:city":"West Bloomfield",
    "sg:classifiers":[
        {
            "category":"Building & Trades",
            "subcategory":"Construction",
            "type":"Services"
        }
    ],
    "sg:phone":"+1 248 661 9260",
    "sg:postcode":"48322",
    "sg:province":"MI",
    "sg:tags":[
        "windows",
        "door"
    ],
    "wof:name":"Window Source LLC",
    "wof:placetype":"venue"
},
  "geometry": {"coordinates":[-83.430937,42.533257],"type":"Point"}
}