{
  "type": "Feature",
  "properties": {
    "iso:country":"US",
    "sg:address":"5831 E 13 Mile Rd",
    "sg:city":"Warren",
    "sg:classifiers":[
        {
            "category":"Personal",
            "subcategory":"Barber",
            "type":"Services"
        }
    ],
    "sg:phone":"+1 586 979 4285",
    "sg:postcode":"48092",
    "sg:province":"MI",
    "wof:name":"Malana Barber Styling Shop",
    "wof:placetype":"venue"
},
  "geometry": {"coordinates":[-83.049301,42.520901],"type":"Point"}
}