{
  "type": "Feature",
  "properties": {
    "iso:country":"US",
    "sg:address":"45985 Hollowoode Ln",
    "sg:city":"Macomb",
    "sg:classifiers":[
        {
            "category":"Professional",
            "subcategory":"Computer Services",
            "type":"Services"
        }
    ],
    "sg:phone":"+1 586 263 3271",
    "sg:postcode":"48044",
    "sg:province":"MI",
    "sg:tags":[
        "datum"
    ],
    "wof:name":"Intertechnolgies Inc",
    "wof:placetype":"venue"
},
  "geometry": {"coordinates":[-82.944965,42.635898],"type":"Point"}
}