{
  "type": "Feature",
  "properties": {
    "iso:country":"US",
    "sg:address":"1308 Burch St",
    "sg:city":"Mt Pleasant",
    "sg:classifiers":[
        {
            "category":"Social Services",
            "type":"Services"
        }
    ],
    "sg:phone":"+1 989 773 4663",
    "sg:postcode":"48858",
    "sg:province":"MI",
    "sg:tags":[
        "organization",
        "welfare"
    ],
    "wof:name":"Salvation Army",
    "wof:placetype":"venue"
},
  "geometry": {"coordinates":[-84.79179000000001,43.598085],"type":"Point"}
}