{
  "type": "Feature",
  "properties": {
    "iso:country":"US",
    "sg:address":"39940 Co Rd 673",
    "sg:city":"Lawrence",
    "sg:classifiers":[
        {
            "category":"Farming",
            "subcategory":"Livestock Farm",
            "type":"Manufacturing & Wholesale Goods"
        }
    ],
    "sg:phone":"+1 269 674 8305",
    "sg:postcode":"49064",
    "sg:province":"MI",
    "sg:tags":[
        "specialty",
        "animal"
    ],
    "wof:name":"Lucky Dog Farm LLC",
    "wof:placetype":"venue"
},
  "geometry": {"coordinates":[-86.03268199999999,42.272813],"type":"Point"}
}