{
  "type": "Feature",
  "properties": {
    "iso:country":"US",
    "sg:address":"303 Fairway Dr",
    "sg:city":"Coldwater",
    "sg:classifiers":[
        {
            "category":"Professional",
            "subcategory":"Management & Consulting",
            "type":"Services"
        }
    ],
    "sg:phone":"+1 517 278 6873",
    "sg:postcode":"49036",
    "sg:province":"MI",
    "sg:tags":[
        "business"
    ],
    "wof:name":"Harshaw & Associates Inc",
    "wof:placetype":"venue"
},
  "geometry": {"coordinates":[-85.01853699999999,41.978761],"type":"Point"}
}