{
  "type": "Feature",
  "properties": {
    "iso:country":"US",
    "sg:address":"1601 N Stephenson Ave",
    "sg:city":"Iron Mountain",
    "sg:classifiers":[
        {
            "category":"Retail",
            "subcategory":"Car Wash",
            "type":"Services"
        }
    ],
    "sg:phone":"+1 906 774 0968",
    "sg:postcode":"49801",
    "sg:province":"MI",
    "sg:tags":[
        "automobile",
        "detail",
        "clean"
    ],
    "wof:name":"Rapid Detail",
    "wof:placetype":"venue"
},
  "geometry": {"coordinates":[-88.057216,45.834802],"type":"Point"}
}