{
  "type": "Feature",
  "properties": {
    "iso:country":"US",
    "sg:address":"513 Sturgis Ave",
    "sg:city":"Sturgis",
    "sg:classifiers":[
        {
            "category":"Professional",
            "subcategory":"Computer Services",
            "type":"Services"
        }
    ],
    "sg:phone":"+1 269 651 5775",
    "sg:postcode":"49091",
    "sg:province":"MI",
    "sg:tags":[
        "datum"
    ],
    "wof:name":"Transcription Richmond Waldron",
    "wof:placetype":"venue"
},
  "geometry": {"coordinates":[-85.41733000000001,41.808441],"type":"Point"}
}