{
  "type": "Feature",
  "properties": {
    "iso:country":"US",
    "sg:address":"26631 Southfield Rd",
    "sg:city":"Lathrup Village",
    "sg:classifiers":[
        {
            "category":"Community Center",
            "type":"Public Place"
        }
    ],
    "sg:phone":"+1 248 552 8195",
    "sg:postcode":"48076",
    "sg:province":"MI",
    "sg:tags":[
        "medical"
    ],
    "wof:name":"Beaumont Lathrup Village Primary Care",
    "wof:placetype":"venue"
},
  "geometry": {"coordinates":[-83.221906,42.485283],"type":"Point"}
}