{
  "type": "Feature",
  "properties": {
    "iso:country":"US",
    "sg:address":"117 N Kidd St",
    "sg:city":"Ionia",
    "sg:classifiers":[
        {
            "category":"Government",
            "subcategory":"Post Office",
            "type":"Public Place"
        }
    ],
    "sg:phone":"+1 616 527 3370",
    "sg:postcode":"48846",
    "sg:province":"MI",
    "wof:name":"US Post Office",
    "wof:placetype":"venue"
},
  "geometry": {"coordinates":[-85.064356,42.983401],"type":"Point"}
}