{
  "type": "Feature",
  "properties": {
    "iso:country":"US",
    "sg:address":"9828 Dixie Hwy",
    "sg:city":"Anchorville",
    "sg:classifiers":[
        {
            "category":"Government",
            "subcategory":"Post Office",
            "type":"Public Place"
        }
    ],
    "sg:phone":"+1 586 725 9332",
    "sg:postcode":"48023",
    "sg:province":"MI",
    "wof:name":"US Post Office",
    "wof:placetype":"venue"
},
  "geometry": {"coordinates":[-82.70235099999999,42.689932],"type":"Point"}
}