{
  "type": "Feature",
  "properties": {
    "iso:country":"US",
    "sg:address":"1074 Olmstead Rd",
    "sg:city":"Muir",
    "sg:classifiers":[
        {
            "category":"Organizations",
            "subcategory":"Religious Organization",
            "type":"Services"
        }
    ],
    "sg:phone":"+1 989 855 2247",
    "sg:postcode":"48860",
    "sg:province":"MI",
    "wof:name":"Lyons United Methdst Parsonage",
    "wof:placetype":"venue"
},
  "geometry": {"coordinates":[-84.956204,43.012006],"type":"Point"}
}