{
  "type": "Feature",
  "properties": {
    "iso:country":"US",
    "sg:address":"2510 N Fraser Rd",
    "sg:city":"Pinconning",
    "sg:classifiers":[
        {
            "category":"Building & Trades",
            "subcategory":"Electrical",
            "type":"Services"
        }
    ],
    "sg:phone":"+1 989 879 2730",
    "sg:postcode":"48650",
    "sg:province":"MI",
    "sg:tags":[
        "electric",
        "contractor"
    ],
    "wof:name":"Rosenbrock Electric Bill",
    "wof:placetype":"venue"
},
  "geometry": {"coordinates":[-84.006496,43.815797],"type":"Point"}
}