{
  "type": "Feature",
  "properties": {
    "iso:country":"US",
    "sg:address":"23999 W 10 Mile Rd Ste 101",
    "sg:city":"Southfield",
    "sg:classifiers":[
        {
            "category":"Professional",
            "subcategory":"Accounting & Tax Preparation",
            "type":"Services"
        }
    ],
    "sg:phone":"+1 248 827 7272",
    "sg:postcode":"48034",
    "sg:province":"MI",
    "sg:tags":[
        "accountant"
    ],
    "wof:name":"Ring Elliott H PC",
    "wof:placetype":"venue"
},
  "geometry": {"coordinates":[-83.27889999999999,42.471901],"type":"Point"}
}