{
  "type": "Feature",
  "properties": {
    "iso:country":"US",
    "sg:address":"2800 S Cedar St",
    "sg:city":"Lansing",
    "sg:classifiers":[
        {
            "category":"Autos & Motor Vehicles",
            "subcategory":"Automobile Sales",
            "type":"Retail Goods"
        }
    ],
    "sg:phone":"+1 517 882 8606",
    "sg:postcode":"48910",
    "sg:province":"MI",
    "sg:tags":[
        "car",
        "dealer"
    ],
    "wof:name":"Beal Street Auto Sales",
    "wof:placetype":"venue"
},
  "geometry": {"coordinates":[-84.548019,42.702819],"type":"Point"}
}