{
  "type": "Feature",
  "properties": {
    "iso:country":"US",
    "sg:address":"884 S State St",
    "sg:city":"Caro",
    "sg:classifiers":[
        {
            "category":"Restaurant",
            "type":"Food & Drink"
        }
    ],
    "sg:menulink":"http://www.allmenus.com/mi/indianfields/142424-subway/menu/",
    "sg:phone":"+1 989 672 4470",
    "sg:postcode":"48723",
    "sg:province":"MI",
    "sg:tags":[
        "american",
        "sandwich"
    ],
    "wof:name":"Subway",
    "wof:placetype":"venue"
},
  "geometry": {"coordinates":[-83.406356,43.481378],"type":"Point"}
}