{
  "type": "Feature",
  "properties": {
    "iso:country":"US",
    "sg:address":"500 West St",
    "sg:city":"Bloomingdale",
    "sg:classifiers":[
        {
            "category":"Professional",
            "subcategory":"Business Services",
            "type":"Services"
        }
    ],
    "sg:phone":"+1 269 521 4200",
    "sg:postcode":"49026",
    "sg:province":"MI",
    "wof:name":"Dotson Enterprises",
    "wof:placetype":"venue"
},
  "geometry": {"coordinates":[-85.959885,42.386049],"type":"Point"}
}