{
  "type": "Feature",
  "properties": {
    "iso:country":"US",
    "sg:address":"1305 Prospect Ave",
    "sg:city":"Iron Mountain",
    "sg:classifiers":[
        {
            "category":"Social Services",
            "type":"Services"
        }
    ],
    "sg:phone":"+1 906 774 1112",
    "sg:postcode":"49801",
    "sg:province":"MI",
    "sg:tags":[
        "information",
        "abuse",
        "domestic",
        "treatment"
    ],
    "wof:name":"Caring House",
    "wof:placetype":"venue"
},
  "geometry": {"coordinates":[-88.069991,45.809746],"type":"Point"}
}