{
  "type": "Feature",
  "properties": {
    "iso:country":"US",
    "sg:address":"478 N 3rd St",
    "sg:city":"Rogers City",
    "sg:classifiers":[
        {
            "category":"Banks & Credit Unions",
            "subcategory":"Bank",
            "type":"Services"
        }
    ],
    "sg:phone":"+1 989 734 4130",
    "sg:postcode":"49779",
    "sg:province":"MI",
    "sg:tags":[
        "state",
        "loan",
        "broker"
    ],
    "wof:name":"Calcite Credit Union",
    "wof:placetype":"venue"
},
  "geometry": {"coordinates":[-83.82019099999999,45.423454],"type":"Point"}
}