{
  "type": "Feature",
  "properties": {
    "iso:country":"US",
    "sg:address":"8005 McCain Rd",
    "sg:city":"Parma",
    "sg:classifiers":[
        {
            "category":"Professional",
            "subcategory":"Business Services",
            "type":"Services"
        }
    ],
    "sg:phone":"+1 517 531 8187",
    "sg:postcode":"49269",
    "sg:province":"MI",
    "wof:name":"Js Services",
    "wof:placetype":"venue"
},
  "geometry": {"coordinates":[-84.57088,42.232823],"type":"Point"}
}