{
  "type": "Feature",
  "properties": {
    "iso:country":"US",
    "sg:address":"52 Marshall St",
    "sg:city":"Coldwater",
    "sg:classifiers":[
        {
            "category":"Organizations",
            "subcategory":"Religious Organization",
            "type":"Services"
        }
    ],
    "sg:phone":"+1 517 278 7848",
    "sg:postcode":"49036",
    "sg:province":"MI",
    "sg:tags":[
        "church"
    ],
    "wof:name":"First Presbyterian Church",
    "wof:placetype":"venue"
},
  "geometry": {"coordinates":[-85.00032299999999,41.942551],"type":"Point"}
}