{
  "type": "Feature",
  "properties": {
    "iso:country":"US",
    "sg:address":"3261 Fleck Rd",
    "sg:city":"Six Lakes",
    "sg:classifiers":[
        {
            "category":"Manufacturing",
            "subcategory":"Glass & Minerals",
            "type":"Manufacturing & Wholesale Goods"
        }
    ],
    "sg:phone":"+1 989 365 3010",
    "sg:postcode":"48886",
    "sg:province":"MI",
    "sg:tags":[
        "ready"
    ],
    "wof:name":"High Grade Materials Co",
    "wof:placetype":"venue"
},
  "geometry": {"coordinates":[-85.150313,43.43008],"type":"Point"}
}