{
  "type": "Feature",
  "properties": {
    "iso:country":"US",
    "sg:address":"4083 E Shawnee Rd",
    "sg:city":"Berrien Springs",
    "sg:classifiers":[
        {
            "category":"Organizations",
            "subcategory":"Non-profit Organization",
            "type":"Services"
        }
    ],
    "sg:phone":"+1 269 471 2017",
    "sg:postcode":"49103",
    "sg:province":"MI",
    "wof:name":"Central County Ctr For Senior",
    "wof:placetype":"venue"
},
  "geometry": {"coordinates":[-86.356048,41.943362],"type":"Point"}
}