{
  "type": "Feature",
  "properties": {
    "iso:country":"US",
    "sg:address":"708 Waymarket Dr",
    "sg:city":"Ann Arbor",
    "sg:classifiers":[
        {
            "category":"Professional",
            "subcategory":"Management & Consulting",
            "type":"Services"
        }
    ],
    "sg:phone":"+1 734 327 3671",
    "sg:postcode":"48103",
    "sg:province":"MI",
    "sg:tags":[
        "consultant",
        "telecommunication"
    ],
    "wof:name":"Outtel Communication Services",
    "wof:placetype":"venue"
},
  "geometry": {"coordinates":[-83.757155,42.243337],"type":"Point"}
}