{
  "type": "Feature",
  "properties": {
    "iso:country":"US",
    "sg:address":"126 N Michigan Ave",
    "sg:city":"Hastings",
    "sg:classifiers":[
        {
            "category":"Restaurant",
            "type":"Food & Drink"
        }
    ],
    "sg:menulink":"http://www.allmenus.com/mi/hastings/55933-mikes-monster-pizza/menu/",
    "sg:phone":"+1 269 945 0003",
    "sg:postcode":"49058",
    "sg:province":"MI",
    "sg:tags":[
        "american",
        "pizza"
    ],
    "wof:name":"Mike's Monster Pizza",
    "wof:placetype":"venue"
},
  "geometry": {"coordinates":[-85.28612200000001,42.649015],"type":"Point"}
}