{
  "type": "Feature",
  "properties": {
    "iso:country":"US",
    "sg:address":"1066 US Hwy 31",
    "sg:city":"Pellston",
    "sg:classifiers":[
        {
            "category":"Building & Trades",
            "subcategory":"Construction",
            "type":"Services"
        }
    ],
    "sg:phone":"+1 231 539 8252",
    "sg:postcode":"49769",
    "sg:province":"MI",
    "sg:tags":[
        "roofing",
        "contractor"
    ],
    "wof:name":"John Lee Roofing",
    "wof:placetype":"venue"
},
  "geometry": {"coordinates":[-84.78390400000001,45.543641],"type":"Point"}
}