{
  "type": "Feature",
  "properties": {
    "iso:country":"US",
    "sg:address":"4341 N Henderson Rd",
    "sg:city":"Davison",
    "sg:classifiers":[
        {
            "category":"Farming",
            "subcategory":"Farm",
            "type":"Manufacturing & Wholesale Goods"
        }
    ],
    "sg:phone":"+1 810 653 7796",
    "sg:postcode":"48423",
    "sg:province":"MI",
    "sg:tags":[
        "crop",
        "general"
    ],
    "wof:name":"CA Johnson Stock Farm",
    "wof:placetype":"venue"
},
  "geometry": {"coordinates":[-83.47918799999999,43.07402],"type":"Point"}
}