{
  "type": "Feature",
  "properties": {
    "iso:country":"US",
    "sg:address":"1384 Rosewood St",
    "sg:city":"Ann Arbor",
    "sg:classifiers":[
        {
            "category":"Professional",
            "subcategory":"Computer Services",
            "type":"Services"
        }
    ],
    "sg:phone":"+1 313 594 0850",
    "sg:postcode":"48104",
    "sg:province":"MI",
    "sg:tags":[
        "datum"
    ],
    "wof:name":"Potsiecom",
    "wof:placetype":"venue"
},
  "geometry": {"coordinates":[-83.73040899999999,42.255115],"type":"Point"}
}