{
  "type": "Feature",
  "properties": {
    "iso:country":"US",
    "sg:address":"156 Kensington Ave",
    "sg:city":"Ferndale",
    "sg:classifiers":[
        {
            "category":"Building & Trades",
            "subcategory":"Construction",
            "type":"Services"
        }
    ],
    "sg:phone":"+1 248 541 5826",
    "sg:postcode":"48220",
    "sg:province":"MI",
    "sg:tags":[
        "roofing",
        "contractor"
    ],
    "wof:name":"Jeff Cates Contracting Co",
    "wof:placetype":"venue"
},
  "geometry": {"coordinates":[-83.144558,42.446546],"type":"Point"}
}