{
  "type": "Feature",
  "properties": {
    "iso:country":"US",
    "sg:address":"3703 County 416 20th Rd",
    "sg:city":"Gladstone",
    "sg:classifiers":[
        {
            "category":"Food & Beverages",
            "subcategory":"Groceries & Convenience Stores",
            "type":"Retail Goods"
        }
    ],
    "sg:phone":"+1 906 786 0340",
    "sg:postcode":"49829",
    "sg:province":"MI",
    "sg:tags":[
        "grocer"
    ],
    "wof:name":"Flat Rock Grocery",
    "wof:placetype":"venue"
},
  "geometry": {"coordinates":[-87.174539,45.826083],"type":"Point"}
}