{
  "type": "Feature",
  "properties": {
    "iso:country":"US",
    "sg:address":"725 S Park Rd",
    "sg:city":"Benton Harbor",
    "sg:classifiers":[
        {
            "category":"Building & Trades",
            "subcategory":"Construction",
            "type":"Services"
        }
    ],
    "sg:phone":"+1 269 944 3606",
    "sg:postcode":"49022",
    "sg:province":"MI",
    "sg:tags":[
        "insulation",
        "heat",
        "contractor"
    ],
    "wof:name":"Eagle Mechanical Insulation",
    "wof:placetype":"venue"
},
  "geometry": {"coordinates":[-86.320453,42.106595],"type":"Point"}
}