{
  "type": "Feature",
  "properties": {
    "iso:country":"US",
    "sg:address":"2266 Ellis Rd",
    "sg:city":"Frankfort",
    "sg:classifiers":[
        {
            "category":"Retail",
            "subcategory":"Animal Services",
            "type":"Services"
        }
    ],
    "sg:phone":"+1 231 352 4501",
    "sg:postcode":"49635",
    "sg:province":"MI",
    "wof:name":"Wagging Tail Kennel",
    "wof:placetype":"venue"
},
  "geometry": {"coordinates":[-86.190271,44.604546],"type":"Point"}
}