{
  "type": "Feature",
  "properties": {
    "iso:country":"US",
    "sg:address":"42130 Ford Rd",
    "sg:city":"Canton",
    "sg:classifiers":[
        {
            "category":"Recreation",
            "subcategory":"Amusement Park",
            "type":"Entertainment"
        },
        {
            "category":"Sports & Exercise",
            "subcategory":"Ice Rink",
            "type":"Entertainment"
        },
        {
            "category":"Sports & Exercise",
            "subcategory":"Sports Center",
            "type":"Entertainment"
        }
    ],
    "sg:phone":"+1 734 844 7746",
    "sg:postcode":"48187",
    "sg:province":"MI",
    "sg:tags":[
        "skating",
        "amateur",
        "team"
    ],
    "wof:name":"Zap Zone Lazer Tag B-Days & Private Parties",
    "wof:placetype":"venue"
},
  "geometry": {"coordinates":[-83.4562,42.3228],"type":"Point"}
}