{
  "type": "Feature",
  "properties": {
    "iso:country":"US",
    "sg:address":"23191 Marter Rd",
    "sg:city":"St Clair Shores",
    "sg:classifiers":[
        {
            "category":"Shopping",
            "subcategory":"Florist",
            "type":"Retail Goods"
        }
    ],
    "sg:phone":"+1 586 771 2290",
    "sg:postcode":"48080",
    "sg:province":"MI",
    "sg:tags":[
        "grocery"
    ],
    "sg:website":"www.kroger.com",
    "wof:name":"Kroger",
    "wof:placetype":"venue"
},
  "geometry": {"coordinates":[-82.88347,42.459473],"type":"Point"}
}