{
  "type": "Feature",
  "properties": {
    "iso:country":"US",
    "sg:address":"26155 Delton St",
    "sg:city":"Madison Heights",
    "sg:classifiers":[
        {
            "category":"Professional",
            "subcategory":"Management & Consulting",
            "type":"Services"
        }
    ],
    "sg:phone":"+1 248 541 1517",
    "sg:postcode":"48071",
    "sg:province":"MI",
    "wof:name":"Tavis Inc",
    "wof:placetype":"venue"
},
  "geometry": {"coordinates":[-83.101741,42.484683],"type":"Point"}
}