{
  "type": "Feature",
  "properties": {
    "iso:country":"US",
    "sg:address":"1379 Briarwood Ct",
    "sg:city":"Waterford",
    "sg:classifiers":[
        {
            "category":"Building & Trades",
            "subcategory":"Cleaning & Sanitation",
            "type":"Services"
        }
    ],
    "sg:phone":"+1 248 360 5754",
    "sg:postcode":"48327",
    "sg:province":"MI",
    "sg:tags":[
        "janitor"
    ],
    "wof:name":"Real Quality Cleaning",
    "wof:placetype":"venue"
},
  "geometry": {"coordinates":[-83.41421,42.62005],"type":"Point"}
}