{
  "type": "Feature",
  "properties": {
    "iso:country":"US",
    "sg:address":"1141 S. Rose Street",
    "sg:city":"Kalamazoo",
    "sg:classifiers":[
        {
            "category":"Personal",
            "subcategory":"Beauty Salon",
            "type":"Services"
        },
        {
            "category":"Personal",
            "subcategory":"Day Spa",
            "type":"Services"
        }
    ],
    "sg:phone":"+1 269 345 0007",
    "sg:postcode":"49007",
    "sg:province":"MI",
    "sg:tags":[
        "hair",
        "stylist"
    ],
    "sg:website":"http://www.facebook.com/avantehairanddayspa",
    "wof:name":"Avante' Hair & Day Spa",
    "wof:placetype":"venue"
},
  "geometry": {"coordinates":[-85.585238,42.279954],"type":"Point"}
}