{
  "type": "Feature",
  "properties": {
    "iso:country":"US",
    "sg:address":"612 Main St",
    "sg:city":"St Joseph",
    "sg:classifiers":[
        {
            "category":"Real Estate",
            "subcategory":"Real Estate Agent",
            "type":"Services"
        }
    ],
    "sg:phone":"+1 269 983 5555",
    "sg:postcode":"49085",
    "sg:province":"MI",
    "wof:name":"Winters-Associates Developers",
    "wof:placetype":"venue"
},
  "geometry": {"coordinates":[-86.48326,42.105971],"type":"Point"}
}