{
  "type": "Feature",
  "properties": {
    "iso:country":"US",
    "sg:address":"330 W 14 Mile Rd",
    "sg:city":"Clawson",
    "sg:classifiers":[
        {
            "category":"Health Services",
            "subcategory":"Doctor",
            "type":"Services"
        }
    ],
    "sg:phone":"+1 248 435 8880",
    "sg:postcode":"48017",
    "sg:province":"MI",
    "sg:tags":[
        "dentist"
    ],
    "wof:name":"Lawrence Strugala DDS PC",
    "wof:placetype":"venue"
},
  "geometry": {"coordinates":[-83.15212699999999,42.533406],"type":"Point"}
}