{
  "type": "Feature",
  "properties": {
    "iso:country":"US",
    "sg:address":"3457 E Grand River Ave",
    "sg:city":"Howell",
    "sg:classifiers":[
        {
            "category":"Shopping",
            "subcategory":"Bicycles & Sporting Goods",
            "type":"Retail Goods"
        }
    ],
    "sg:phone":"+1 517 545 5590",
    "sg:postcode":"48843",
    "sg:province":"MI",
    "sg:tags":[
        "saddlery",
        "harness"
    ],
    "wof:name":"Howell Tack Shack LLC",
    "wof:placetype":"venue"
},
  "geometry": {"coordinates":[-83.88468,42.590657],"type":"Point"}
}