{
  "type": "Feature",
  "properties": {
    "iso:country":"US",
    "sg:address":"5905 W US Hwy 10",
    "sg:city":"Ludington",
    "sg:classifiers":[
        {
            "category":"Shopping",
            "subcategory":"Clothing, Apparel, & Fashions",
            "type":"Retail Goods"
        }
    ],
    "sg:phone":"+1 231 843 3734",
    "sg:postcode":"49431",
    "sg:province":"MI",
    "sg:tags":[
        "infant",
        "wear"
    ],
    "wof:name":"ABC Kidz",
    "wof:placetype":"venue"
},
  "geometry": {"coordinates":[-86.426754,43.956078],"type":"Point"}
}