{
  "type": "Feature",
  "properties": {
    "iso:country":"US",
    "sg:address":"47282 Bluejay Dr",
    "sg:city":"Macomb",
    "sg:classifiers":[
        {
            "category":"Building & Trades",
            "subcategory":"Construction",
            "type":"Services"
        }
    ],
    "sg:phone":"+1 586 412 1817",
    "sg:postcode":"48044",
    "sg:province":"MI",
    "sg:tags":[
        "floor",
        "laying",
        "contractor"
    ],
    "wof:name":"Gc Sanding Inc",
    "wof:placetype":"venue"
},
  "geometry": {"coordinates":[-82.917441,42.644627],"type":"Point"}
}