{
  "type": "Feature",
  "properties": {
    "iso:country":"US",
    "sg:address":"1112 E Centre Ave",
    "sg:city":"Portage",
    "sg:classifiers":[
        {
            "category":"Personal",
            "subcategory":"Beauty Salon",
            "type":"Services"
        }
    ],
    "sg:phone":"+1 269 324 3227",
    "sg:postcode":"49002",
    "sg:province":"MI",
    "wof:name":"Vallar",
    "wof:placetype":"venue"
},
  "geometry": {"coordinates":[-85.576841,42.200995],"type":"Point"}
}