{
  "type": "Feature",
  "properties": {
    "iso:country":"US",
    "sg:address":"625 Baldwin Ave",
    "sg:city":"Royal Oak",
    "sg:classifiers":[
        {
            "category":"Travel",
            "subcategory":"Travel Agent",
            "type":"Entertainment"
        }
    ],
    "sg:phone":"+1 248 414 5234",
    "sg:postcode":"48067",
    "sg:province":"MI",
    "sg:tags":[
        "agency",
        "bureau"
    ],
    "wof:name":"Viking Travel",
    "wof:placetype":"venue"
},
  "geometry": {"coordinates":[-83.135411,42.495254],"type":"Point"}
}