{
  "type": "Feature",
  "properties": {
    "iso:country":"US",
    "sg:address":"20913 Gibraltar Rd",
    "sg:city":"Brownstown Twp",
    "sg:classifiers":[
        {
            "category":"Autos & Motor Vehicles",
            "subcategory":"Fuel & Gas Station",
            "type":"Retail Goods"
        }
    ],
    "sg:phone":"+1 734 675 9337",
    "sg:postcode":"48183",
    "sg:province":"MI",
    "wof:name":"Fast Track",
    "wof:placetype":"venue"
},
  "geometry": {"coordinates":[-83.23732200000001,42.095203],"type":"Point"}
}