{
  "type": "Feature",
  "properties": {
    "iso:country":"US",
    "sg:address":"2025 Middlebelt Rd",
    "sg:city":"Inkster",
    "sg:classifiers":[
        {
            "category":"Government",
            "subcategory":"Office",
            "type":"Public Place"
        }
    ],
    "sg:phone":"+1 734 728 7530",
    "sg:postcode":"48141",
    "sg:province":"MI",
    "sg:tags":[
        "conservation"
    ],
    "wof:name":"Inkster Park & Recreation",
    "wof:placetype":"venue"
},
  "geometry": {"coordinates":[-83.329476,42.292158],"type":"Point"}
}