{
  "type": "Feature",
  "properties": {
    "iso:country":"US",
    "sg:address":"6247 Pine St",
    "sg:city":"Cass City",
    "sg:classifiers":[
        {
            "category":"Retail",
            "subcategory":"Repair Shop",
            "type":"Services"
        }
    ],
    "sg:phone":"+1 989 872 4930",
    "sg:postcode":"48726",
    "sg:province":"MI",
    "sg:tags":[
        "bicycle",
        "accessory"
    ],
    "wof:name":"Ackermans Bike Repair",
    "wof:placetype":"venue"
},
  "geometry": {"coordinates":[-83.181236,43.599871],"type":"Point"}
}