{
  "type": "Feature",
  "properties": {
    "iso:country":"US",
    "sg:address":"7667 US Hwy 23 N",
    "sg:city":"Alpena",
    "sg:classifiers":[
        {
            "category":"Social Services",
            "subcategory":"Child Care",
            "type":"Services"
        }
    ],
    "sg:phone":"+1 989 358 5560",
    "sg:postcode":"49707",
    "sg:province":"MI",
    "sg:tags":[
        "day"
    ],
    "wof:name":"Hinks Chapter 1 Pre-School",
    "wof:placetype":"venue"
},
  "geometry": {"coordinates":[-83.425777,45.158708],"type":"Point"}
}