{
  "type": "Feature",
  "properties": {
    "iso:country":"US",
    "sg:address":"3540 US Hwy 131",
    "sg:city":"Kalkaska",
    "sg:classifiers":[
        {
            "category":"Mining & Drilling",
            "type":"Manufacturing & Wholesale Goods"
        }
    ],
    "sg:phone":"+1 231 258 4960",
    "sg:postcode":"49646",
    "sg:province":"MI",
    "sg:tags":[
        "field",
        "oil"
    ],
    "wof:name":"Target Oil Tools",
    "wof:placetype":"venue"
},
  "geometry": {"coordinates":[-85.16107599999999,44.770128],"type":"Point"}
}