{
  "type": "Feature",
  "properties": {
    "iso:country":"US",
    "sg:address":"1109 S Stephenson Ave",
    "sg:city":"Iron Mountain",
    "sg:classifiers":[
        {
            "category":"Restaurant",
            "type":"Food & Drink"
        }
    ],
    "sg:menulink":"http://www.allmenus.com/mi/iron-mountain/185725-mcdonalds/menu/",
    "sg:postcode":"49801",
    "sg:province":"MI",
    "sg:tags":[
        "burger",
        "american"
    ],
    "wof:name":"McDonald's",
    "wof:placetype":"venue"
},
  "geometry": {"coordinates":[-88.06071300000001,45.812509],"type":"Point"}
}