{
  "type": "Feature",
  "properties": {
    "iso:country":"US",
    "sg:address":"57889 Van Dyke Rd",
    "sg:city":"Washington",
    "sg:classifiers":[
        {
            "category":"Food & Beverages",
            "subcategory":"Liquor & Beverages",
            "type":"Retail Goods"
        }
    ],
    "sg:phone":"+1 586 781 5614",
    "sg:postcode":"48094",
    "sg:province":"MI",
    "wof:name":"Stoney Creek Liquor Shoppe",
    "wof:placetype":"venue"
},
  "geometry": {"coordinates":[-83.03560299999999,42.719154],"type":"Point"}
}