{
  "type": "Feature",
  "properties": {
    "iso:country":"US",
    "sg:address":"9794 Jericho Rd",
    "sg:city":"Bridgman",
    "sg:classifiers":[
        {
            "category":"Real Estate",
            "subcategory":"Real Estate Operator",
            "type":"Services"
        }
    ],
    "sg:phone":"+1 269 465 5612",
    "sg:postcode":"49106",
    "sg:province":"MI",
    "sg:tags":[
        "building",
        "nonresidential"
    ],
    "wof:name":"Stama Enterprises",
    "wof:placetype":"venue"
},
  "geometry": {"coordinates":[-86.533446,41.941319],"type":"Point"}
}