{
  "type": "Feature",
  "properties": {
    "iso:country":"US",
    "sg:address":"3301 Sutton Rd",
    "sg:city":"Adrian",
    "sg:classifiers":[
        {
            "category":"Organizations",
            "subcategory":"Labor Organization",
            "type":"Services"
        }
    ],
    "sg:phone":"+1 517 264 9534",
    "sg:postcode":"49221",
    "sg:province":"MI",
    "wof:name":"United Steelworkers Of America",
    "wof:placetype":"venue"
},
  "geometry": {"coordinates":[-83.956948,41.948808],"type":"Point"}
}