{
  "type": "Feature",
  "properties": {
    "iso:country":"US",
    "sg:address":"1260 Chicago Dr",
    "sg:city":"Jenison",
    "sg:classifiers":[
        {
            "category":"Organizations",
            "subcategory":"Religious Organization",
            "type":"Services"
        }
    ],
    "sg:phone":"+1 616 457 3610",
    "sg:postcode":"49428",
    "sg:province":"MI",
    "sg:tags":[
        "church"
    ],
    "wof:name":"Grace Bible Fellowship Church",
    "wof:placetype":"venue"
},
  "geometry": {"coordinates":[-85.814893,42.894548],"type":"Point"}
}