{
  "type": "Feature",
  "properties": {
    "iso:country":"US",
    "sg:address":"2901 N Dort Hwy",
    "sg:city":"Flint",
    "sg:classifiers":[
        {
            "category":"Food & Beverages",
            "subcategory":"Groceries & Convenience Stores",
            "type":"Retail Goods"
        }
    ],
    "sg:phone":"+1 810 233 6559",
    "sg:postcode":"48506",
    "sg:province":"MI",
    "sg:tags":[
        "alcoholic"
    ],
    "wof:name":"Payton Place",
    "wof:placetype":"venue"
},
  "geometry": {"coordinates":[-83.65557099999999,43.041422],"type":"Point"}
}