{
  "type": "Feature",
  "properties": {
    "iso:country":"US",
    "sg:address":"1001 S Bridge St",
    "sg:city":"Linden",
    "sg:classifiers":[
        {
            "category":"Real Estate",
            "subcategory":"Real Estate Operator",
            "type":"Services"
        }
    ],
    "sg:phone":"+1 810 629 4957",
    "sg:postcode":"48451",
    "sg:province":"MI",
    "sg:tags":[
        "apartment"
    ],
    "wof:name":"Parkside Place Apartments",
    "wof:placetype":"venue"
},
  "geometry": {"coordinates":[-83.78201199999999,42.808997],"type":"Point"}
}