{
  "type": "Feature",
  "properties": {
    "iso:country":"US",
    "sg:address":"14095 Farmington Rd",
    "sg:city":"Livonia",
    "sg:classifiers":[
        {
            "category":"Retail",
            "subcategory":"Repair Shop",
            "type":"Services"
        }
    ],
    "sg:phone":"+1 734 458 9556",
    "sg:postcode":"48154",
    "sg:province":"MI",
    "sg:tags":[
        "supply"
    ],
    "wof:name":"Komatsu America Industries",
    "wof:placetype":"venue"
},
  "geometry": {"coordinates":[-83.373105,42.383832],"type":"Point"}
}