{
  "type": "Feature",
  "properties": {
    "iso:country":"US",
    "sg:address":"2600 W State Hwy 21",
    "sg:city":"St Johns",
    "sg:classifiers":[
        {
            "category":"Home & Garden",
            "subcategory":"Garden Supply",
            "type":"Retail Goods"
        }
    ],
    "sg:phone":"+1 989 227 2725",
    "sg:postcode":"48879",
    "sg:province":"MI",
    "sg:tags":[
        "landscaping",
        "equipment"
    ],
    "wof:name":"Harden-Landscaping Supplies",
    "wof:placetype":"venue"
},
  "geometry": {"coordinates":[-84.57399700000001,43.001585],"type":"Point"}
}