{
  "type": "Feature",
  "properties": {
    "iso:country":"US",
    "sg:address":"2192 S Otsego Ave",
    "sg:city":"Gaylord",
    "sg:classifiers":[
        {
            "category":"Real Estate",
            "subcategory":"Real Estate Agent",
            "type":"Services"
        }
    ],
    "sg:phone":"+1 989 732 1012",
    "sg:postcode":"49735",
    "sg:province":"MI",
    "wof:name":"Koske Realty",
    "wof:placetype":"venue"
},
  "geometry": {"coordinates":[-84.67756900000001,45.002171],"type":"Point"}
}