{
  "type": "Feature",
  "properties": {
    "iso:country":"US",
    "sg:address":"4522 Elmwood Ave",
    "sg:city":"Royal Oak",
    "sg:classifiers":[
        {
            "category":"Professional",
            "subcategory":"Computer Services",
            "type":"Services"
        }
    ],
    "sg:phone":"+1 248 549 3696",
    "sg:postcode":"48073",
    "sg:province":"MI",
    "sg:tags":[
        "related"
    ],
    "wof:name":"Richard Dudchik & Associates",
    "wof:placetype":"venue"
},
  "geometry": {"coordinates":[-83.19349800000001,42.528976],"type":"Point"}
}