{
  "type": "Feature",
  "properties": {
    "iso:country":"US",
    "sg:address":"67310 Van Dyke Rd",
    "sg:city":"Washington",
    "sg:classifiers":[
        {
            "category":"Shopping",
            "subcategory":"Clothing, Apparel, & Fashions",
            "type":"Retail Goods"
        }
    ],
    "sg:phone":"+1 586 336 7340",
    "sg:postcode":"48095",
    "sg:province":"MI",
    "wof:name":"Plumm Krazy LLC",
    "wof:placetype":"venue"
},
  "geometry": {"coordinates":[-83.013198,42.789218],"type":"Point"}
}