{
  "type": "Feature",
  "properties": {
    "iso:country":"US",
    "sg:address":"31035 Beachwalk Dr",
    "sg:city":"Novi",
    "sg:classifiers":[
        {
            "category":"Professional",
            "subcategory":"Management & Consulting",
            "type":"Services"
        }
    ],
    "sg:phone":"+1 248 668 1686",
    "sg:postcode":"48377",
    "sg:province":"MI",
    "sg:tags":[
        "support",
        "facility"
    ],
    "wof:name":"Total Office Solution Inc",
    "wof:placetype":"venue"
},
  "geometry": {"coordinates":[-83.47091399999999,42.526208],"type":"Point"}
}