{
  "type": "Feature",
  "properties": {
    "iso:country":"US",
    "sg:address":"622 Page Ave",
    "sg:city":"Jackson",
    "sg:classifiers":[
        {
            "category":"Food & Beverages",
            "subcategory":"Bakery",
            "type":"Retail Goods"
        }
    ],
    "sg:phone":"+1 517 787 5726",
    "sg:postcode":"49203",
    "sg:province":"MI",
    "sg:tags":[
        "baker"
    ],
    "wof:name":"European Bakery",
    "wof:placetype":"venue"
},
  "geometry": {"coordinates":[-84.387496,42.245067],"type":"Point"}
}