{
  "type": "Feature",
  "properties": {
    "iso:country":"US",
    "sg:address":"5703 S Saginaw Rd",
    "sg:city":"Flint",
    "sg:classifiers":[
        {
            "category":"Shopping",
            "subcategory":"Pharmacy",
            "type":"Retail Goods"
        }
    ],
    "sg:phone":"+1 810 695 4643",
    "sg:postcode":"48507",
    "sg:province":"MI",
    "wof:name":"Walgreens",
    "wof:placetype":"venue"
},
  "geometry": {"coordinates":[-83.65150800000001,42.945683],"type":"Point"}
}