{
  "type": "Feature",
  "properties": {
    "iso:country":"US",
    "sg:address":"520 Samuel St",
    "sg:city":"Stephenson",
    "sg:classifiers":[
        {
            "category":"Government",
            "subcategory":"Post Office",
            "type":"Public Place"
        }
    ],
    "sg:phone":"+1 906 753 6919",
    "sg:postcode":"49887",
    "sg:province":"MI",
    "wof:name":"US Post Office",
    "wof:placetype":"venue"
},
  "geometry": {"coordinates":[-87.610984,45.415343],"type":"Point"}
}