{
  "type": "Feature",
  "properties": {
    "iso:country":"US",
    "sg:address":"3125 Bross Rd",
    "sg:city":"Hastings",
    "sg:classifiers":[
        {
            "category":"Utilities",
            "subcategory":"Telephone",
            "type":"Services"
        }
    ],
    "sg:phone":"+1 269 945 8700",
    "sg:postcode":"49058",
    "sg:province":"MI",
    "sg:tags":[
        "telecommunication"
    ],
    "sg:website":"www.telecoml.com",
    "wof:name":"Dinan Inc",
    "wof:placetype":"venue"
},
  "geometry": {"coordinates":[-85.371923,42.607899],"type":"Point"}
}