{
  "type": "Feature",
  "properties": {
    "iso:country":"US",
    "sg:address":"1890 Crooks Rd",
    "sg:city":"Troy",
    "sg:classifiers":[
        {
            "category":"Wholesale",
            "subcategory":"Durable Goods & Equipment",
            "type":"Manufacturing & Wholesale Goods"
        }
    ],
    "sg:phone":"+1 248 362 3400",
    "sg:postcode":"48084",
    "sg:province":"MI",
    "sg:tags":[
        "representative",
        "manufacturer"
    ],
    "wof:name":"Hi-Tech Environments",
    "wof:placetype":"venue"
},
  "geometry": {"coordinates":[-83.166684,42.552485],"type":"Point"}
}