{
  "type": "Feature",
  "properties": {
    "iso:country":"US",
    "sg:address":"25750 Novi Rd",
    "sg:city":"Novi",
    "sg:classifiers":[
        {
            "category":"Bars & Pubs",
            "type":"Food & Drink"
        },
        {
            "category":"Restaurant",
            "type":"Food & Drink"
        },
        {
            "category":"Arts & Performance",
            "subcategory":"Theater",
            "type":"Entertainment"
        }
    ],
    "sg:menulink":"http://www.allmenus.com/mi/novi/253305-5th-avenue-ballroom/menu/",
    "sg:phone":"+1 248 735 4011",
    "sg:postcode":"48375",
    "sg:province":"MI",
    "sg:tags":[
        "sandwich",
        "food",
        "pub",
        "burger",
        "american",
        "barbecue"
    ],
    "wof:name":"5th Avenue Ballroom",
    "wof:placetype":"venue"
},
  "geometry": {"coordinates":[-83.475312,42.477938],"type":"Point"}
}