{
  "type": "Feature",
  "properties": {
    "iso:country":"US",
    "sg:address":"1964 Valley Rd",
    "sg:city":"Alanson",
    "sg:classifiers":[
        {
            "category":"Social Services",
            "subcategory":"Child Care",
            "type":"Services"
        }
    ],
    "sg:phone":"+1 231 529 6578",
    "sg:postcode":"49706",
    "sg:province":"MI",
    "sg:tags":[
        "day",
        "provider"
    ],
    "wof:name":"Werden Margaret Day Care",
    "wof:placetype":"venue"
},
  "geometry": {"coordinates":[-84.87414800000001,45.478235],"type":"Point"}
}