{
  "type": "Feature",
  "properties": {
    "iso:country":"US",
    "sg:address":"3551 Lake Michigan Dr NW",
    "sg:city":"Grand Rapids",
    "sg:classifiers":[
        {
            "category":"Shopping",
            "type":"Retail Goods"
        }
    ],
    "sg:phone":"+1 616 453 2004",
    "sg:postcode":"49544",
    "sg:province":"MI",
    "sg:tags":[
        "equipment",
        "telephone",
        "supply"
    ],
    "wof:name":"Ask-A-Tec",
    "wof:placetype":"venue"
},
  "geometry": {"coordinates":[-85.872103,42.972334],"type":"Point"}
}