{
  "type": "Feature",
  "properties": {
    "iso:country":"US",
    "sg:address":"5120 University Ave",
    "sg:city":"Warren",
    "sg:classifiers":[
        {
            "category":"Professional",
            "subcategory":"Lawyer & Legal Services",
            "type":"Services"
        }
    ],
    "sg:phone":"+1 586 573 7988",
    "sg:postcode":"48092",
    "sg:province":"MI",
    "wof:name":"Zorza John Atty",
    "wof:placetype":"venue"
},
  "geometry": {"coordinates":[-83.05376699999999,42.492095],"type":"Point"}
}