{
  "type": "Feature",
  "properties": {
    "iso:country":"US",
    "sg:address":"715 N University Ave",
    "sg:city":"Ann Arbor",
    "sg:classifiers":[
        {
            "category":"Restaurant",
            "type":"Food & Drink"
        }
    ],
    "sg:menulink":"http://www.allmenus.com/mi/ann-arbor/17585-silvios-organic-pizza/menu/",
    "sg:phone":"+1 734 214 6666",
    "sg:postcode":"48104",
    "sg:province":"MI",
    "sg:tags":[
        "american",
        "italian",
        "pizza"
    ],
    "wof:name":"Silvio's Organic Pizza",
    "wof:placetype":"venue"
},
  "geometry": {"coordinates":[-83.740604,42.278642],"type":"Point"}
}