{
  "type": "Feature",
  "properties": {
    "iso:country":"US",
    "sg:address":"5995 Leonard St",
    "sg:city":"Coopersville",
    "sg:classifiers":[
        {
            "category":"Shopping",
            "type":"Retail Goods"
        }
    ],
    "sg:phone":"+1 616 677 1992",
    "sg:postcode":"49404",
    "sg:province":"MI",
    "sg:tags":[
        "merchandise"
    ],
    "wof:name":"Avon",
    "wof:placetype":"venue"
},
  "geometry": {"coordinates":[-85.935778,43.016211],"type":"Point"}
}