{
  "type": "Feature",
  "properties": {
    "iso:country":"US",
    "sg:address":"3797 W Howell Rd",
    "sg:city":"Mason",
    "sg:classifiers":[
        {
            "category":"Social Services",
            "subcategory":"Child Care",
            "type":"Services"
        }
    ],
    "sg:phone":"+1 517 676 2327",
    "sg:postcode":"48854",
    "sg:province":"MI",
    "sg:tags":[
        "day"
    ],
    "wof:name":"Yennior Day Care",
    "wof:placetype":"venue"
},
  "geometry": {"coordinates":[-84.49320400000001,42.596538],"type":"Point"}
}