{
  "type": "Feature",
  "properties": {
    "iso:country":"US",
    "sg:address":"1024 Minnesota Dr",
    "sg:city":"Troy",
    "sg:classifiers":[
        {
            "category":"Building & Trades",
            "subcategory":"Construction",
            "type":"Services"
        }
    ],
    "sg:phone":"+1 248 229 2315",
    "sg:postcode":"48083",
    "sg:province":"MI",
    "sg:tags":[
        "remodeling",
        "family"
    ],
    "wof:name":"Charles York Construction",
    "wof:placetype":"venue"
},
  "geometry": {"coordinates":[-83.096321,42.545486],"type":"Point"}
}