{
  "type": "Feature",
  "properties": {
    "iso:country":"US",
    "sg:address":"5152 Morrish Rd",
    "sg:city":"Swartz Creek",
    "sg:classifiers":[
        {
            "category":"Building & Trades",
            "subcategory":"Construction",
            "type":"Services"
        }
    ],
    "sg:phone":"+1 810 630 0855",
    "sg:postcode":"48473",
    "sg:province":"MI",
    "sg:tags":[
        "house"
    ],
    "wof:name":"Hildys Home Improvements",
    "wof:placetype":"venue"
},
  "geometry": {"coordinates":[-83.831743,42.94938],"type":"Point"}
}