{
  "type": "Feature",
  "properties": {
    "iso:country":"US",
    "sg:address":"1195 W Lake Dr",
    "sg:city":"Novi",
    "sg:classifiers":[
        {
            "category":"Retail",
            "subcategory":"Portrait Studio",
            "type":"Services"
        }
    ],
    "sg:phone":"+1 248 960 1971",
    "sg:postcode":"48377",
    "sg:province":"MI",
    "sg:tags":[
        "photography"
    ],
    "wof:name":"Scrimshaw Aerial Photography",
    "wof:placetype":"venue"
},
  "geometry": {"coordinates":[-83.48617900000001,42.524988],"type":"Point"}
}