{
  "type": "Feature",
  "properties": {
    "iso:country":"US",
    "sg:address":"311 E Court St",
    "sg:city":"Flint",
    "sg:classifiers":[
        {
            "category":"Social Services",
            "type":"Services"
        }
    ],
    "sg:phone":"+1 810 232 0888",
    "sg:postcode":"48502",
    "sg:province":"MI",
    "wof:name":"Wellness Services",
    "wof:placetype":"venue"
},
  "geometry": {"coordinates":[-83.684128,43.014302],"type":"Point"}
}