{
  "type": "Feature",
  "properties": {
    "iso:country":"US",
    "sg:address":"21250 Harper Ave",
    "sg:city":"St Clair Shores",
    "sg:classifiers":[
        {
            "category":"Shopping",
            "type":"Retail Goods"
        }
    ],
    "sg:phone":"+1 586 447 0010",
    "sg:postcode":"48080",
    "sg:province":"MI",
    "sg:tags":[
        "equipment",
        "supply"
    ],
    "wof:name":"Belanger Brower Group",
    "wof:placetype":"venue"
},
  "geometry": {"coordinates":[-82.913889,42.452142],"type":"Point"}
}