{
  "type": "Feature",
  "properties": {
    "iso:country":"US",
    "sg:address":"9999 Heyden St",
    "sg:city":"Detroit",
    "sg:classifiers":[
        {
            "category":"Social Services",
            "subcategory":"Adult Care",
            "type":"Services"
        }
    ],
    "sg:phone":"+1 313 835 7659",
    "sg:postcode":"48228",
    "sg:province":"MI",
    "sg:tags":[
        "foster",
        "provider"
    ],
    "wof:name":"Jacqueline Chapman",
    "wof:placetype":"venue"
},
  "geometry": {"coordinates":[-83.23859299999999,42.367076],"type":"Point"}
}