{
  "type": "Feature",
  "properties": {
    "iso:country":"US",
    "sg:address":"7219 Maple St",
    "sg:city":"Dearborn",
    "sg:classifiers":[
        {
            "category":"Shopping",
            "subcategory":"Mobile Phones",
            "type":"Retail Goods"
        },
        {
            "category":"Wholesale",
            "subcategory":"Computers",
            "type":"Manufacturing & Wholesale Goods"
        }
    ],
    "sg:phone":"+1 313 945 1000",
    "sg:postcode":"48126",
    "sg:province":"MI",
    "wof:name":"Digital Accessories",
    "wof:placetype":"venue"
},
  "geometry": {"coordinates":[-83.179497,42.3442],"type":"Point"}
}