{
  "type": "Feature",
  "properties": {
    "iso:country":"US",
    "sg:address":"18860 W 10 Mile Rd",
    "sg:city":"Southfield",
    "sg:classifiers":[
        {
            "category":"Wholesale",
            "subcategory":"Medical Equipment & Supplies",
            "type":"Manufacturing & Wholesale Goods"
        }
    ],
    "sg:phone":"+1 248 557 8700",
    "sg:postcode":"48075",
    "sg:province":"MI",
    "sg:tags":[
        "dental"
    ],
    "wof:name":"William Bonanni",
    "wof:placetype":"venue"
},
  "geometry": {"coordinates":[-83.229687,42.473274],"type":"Point"}
}