{
  "type": "Feature",
  "properties": {
    "iso:country":"US",
    "sg:address":"2392 S Stone Rd",
    "sg:city":"Fremont",
    "sg:classifiers":[
        {
            "category":"Wholesale",
            "subcategory":"Auto Parts",
            "type":"Manufacturing & Wholesale Goods"
        }
    ],
    "sg:phone":"+1 231 924 6500",
    "sg:postcode":"49412",
    "sg:province":"MI",
    "sg:tags":[
        "automobile",
        "rebuilt"
    ],
    "wof:name":"Leo's Auto Parts",
    "wof:placetype":"venue"
},
  "geometry": {"coordinates":[-85.959847,43.510759],"type":"Point"}
}