{
  "type": "Feature",
  "properties": {
    "iso:country":"US",
    "sg:address":"19644 Pinewoods Dr",
    "sg:city":"Lake Ann",
    "sg:classifiers":[
        {
            "category":"Building & Trades",
            "subcategory":"Construction",
            "type":"Services"
        }
    ],
    "sg:phone":"+1 231 929 0241",
    "sg:postcode":"49650",
    "sg:province":"MI",
    "sg:tags":[
        "general",
        "contractor"
    ],
    "wof:name":"Boquette Builders Inc",
    "wof:placetype":"venue"
},
  "geometry": {"coordinates":[-85.84454100000001,44.742908],"type":"Point"}
}