{
  "type": "Feature",
  "properties": {
    "iso:country":"US",
    "sg:address":"16600 Henry Rd",
    "sg:city":"Thompsonville",
    "sg:classifiers":[
        {
            "category":"Professional",
            "subcategory":"Accounting & Tax Preparation",
            "type":"Services"
        }
    ],
    "sg:phone":"+1 231 378 4742",
    "sg:postcode":"49683",
    "sg:province":"MI",
    "sg:tags":[
        "bookkeeping",
        "general"
    ],
    "wof:name":"D Humphrey Accounting",
    "wof:placetype":"venue"
},
  "geometry": {"coordinates":[-85.99092,44.47064],"type":"Point"}
}