{
  "type": "Feature",
  "properties": {
    "iso:country":"US",
    "sg:address":"34830 Potter St",
    "sg:city":"Memphis",
    "sg:classifiers":[
        {
            "category":"Education",
            "subcategory":"Library",
            "type":"Public Place"
        }
    ],
    "sg:phone":"+1 810 392 2980",
    "sg:postcode":"48041",
    "sg:province":"MI",
    "wof:name":"Memphis Public Library",
    "wof:placetype":"venue"
},
  "geometry": {"coordinates":[-82.77063200000001,42.895506],"type":"Point"}
}