{
  "type": "Feature",
  "properties": {
    "iso:country":"US",
    "sg:address":"2365 Joslyn Ct",
    "sg:city":"Lake Orion",
    "sg:classifiers":[
        {
            "category":"Shopping",
            "subcategory":"Jewelry",
            "type":"Retail Goods"
        }
    ],
    "sg:phone":"+1 248 391 4790",
    "sg:postcode":"48360",
    "sg:province":"MI",
    "sg:tags":[
        "clocks"
    ],
    "wof:name":"Whittington's Home Accents",
    "wof:placetype":"venue"
},
  "geometry": {"coordinates":[-83.28375699999999,42.744574],"type":"Point"}
}