{
  "type": "Feature",
  "properties": {
    "iso:country":"US",
    "sg:address":"18301 Frazho Rd",
    "sg:city":"Roseville",
    "sg:classifiers":[
        {
            "category":"Shopping",
            "subcategory":"Catalog Store",
            "type":"Retail Goods"
        }
    ],
    "sg:phone":"+1 586 776 2377",
    "sg:postcode":"48066",
    "sg:province":"MI",
    "sg:tags":[
        "house",
        "mail"
    ],
    "wof:name":"Lambs of Love",
    "wof:placetype":"venue"
},
  "geometry": {"coordinates":[-82.93238700000001,42.487569],"type":"Point"}
}