{
  "type": "Feature",
  "properties": {
    "iso:country":"US",
    "sg:address":"3471 US Hwy 31 S",
    "sg:city":"Manistee",
    "sg:classifiers":[
        {
            "category":"Autos & Motor Vehicles",
            "subcategory":"Automobile Sales",
            "type":"Retail Goods"
        }
    ],
    "sg:phone":"+1 231 723 9975",
    "sg:postcode":"49660",
    "sg:province":"MI",
    "sg:tags":[
        "car",
        "dealer"
    ],
    "sg:website":"www.manisteeford.com",
    "wof:name":"Manistee Ford-Mercury Inc",
    "wof:placetype":"venue"
},
  "geometry": {"coordinates":[-86.304963,44.198385],"type":"Point"}
}