{
  "type": "Feature",
  "properties": {
    "iso:country":"US",
    "sg:address":"30100 Telegraph Rd",
    "sg:city":"Bingham Farms",
    "sg:classifiers":[
        {
            "category":"Professional",
            "subcategory":"Lawyer & Legal Services",
            "type":"Services"
        }
    ],
    "sg:phone":"+1 248 475 0075",
    "sg:postcode":"48025",
    "sg:province":"MI",
    "sg:tags":[
        "attorney"
    ],
    "wof:name":"Kallabat & Assoc PC",
    "wof:placetype":"venue"
},
  "geometry": {"coordinates":[-83.285331,42.510593],"type":"Point"}
}