{
  "type": "Feature",
  "properties": {
    "iso:country":"US",
    "sg:address":"2770 29th St SE",
    "sg:city":"Grand Rapids",
    "sg:classifiers":[
        {
            "category":"Food & Beverages",
            "subcategory":"Specialty",
            "type":"Retail Goods"
        }
    ],
    "sg:phone":"+1 616 942 2980",
    "sg:postcode":"49512",
    "sg:province":"MI",
    "sg:tags":[
        "gourmet",
        "shop"
    ],
    "sg:website":"www.gbrusso.com",
    "wof:name":"G B Russo & Son Intl Grocery",
    "wof:placetype":"venue"
},
  "geometry": {"coordinates":[-85.60713699999999,42.910757],"type":"Point"}
}