{
  "type": "Feature",
  "properties": {
    "iso:country":"US",
    "sg:address":"9234 Plainview Ave",
    "sg:city":"Detroit",
    "sg:classifiers":[
        {
            "category":"Banks & Credit Unions",
            "subcategory":"Financial Services",
            "type":"Services"
        }
    ],
    "sg:phone":"+1 313 397 6167",
    "sg:postcode":"48228",
    "sg:province":"MI",
    "sg:tags":[
        "consultant",
        "planning"
    ],
    "wof:name":"Justus Foreclosure",
    "wof:placetype":"venue"
},
  "geometry": {"coordinates":[-83.234747,42.361758],"type":"Point"}
}