{
  "type": "Feature",
  "properties": {
    "iso:country":"US",
    "sg:address":"33834 Woodward Ave",
    "sg:city":"Birmingham",
    "sg:classifiers":[
        {
            "category":"Shopping",
            "subcategory":"Clothing, Apparel, & Fashions",
            "type":"Retail Goods"
        }
    ],
    "sg:phone":"+1 248 646 5555",
    "sg:postcode":"48009",
    "sg:province":"MI",
    "sg:tags":[
        "sewing",
        "alteration"
    ],
    "wof:name":"Class Tailor",
    "wof:placetype":"venue"
},
  "geometry": {"coordinates":[-83.204875,42.537718],"type":"Point"}
}