{
  "type": "Feature",
  "properties": {
    "iso:country":"US",
    "sg:address":"54368 Merkel Ln",
    "sg:city":"Utica",
    "sg:classifiers":[
        {
            "category":"Real Estate",
            "subcategory":"Real Estate Agent",
            "type":"Services"
        }
    ],
    "sg:phone":"+1 586 677 7494",
    "sg:postcode":"48316",
    "sg:province":"MI",
    "wof:name":"Andrew Charles McCloskey",
    "wof:placetype":"venue"
},
  "geometry": {"coordinates":[-83.057115,42.693859],"type":"Point"}
}