{
  "type": "Feature",
  "properties": {
    "iso:country":"US",
    "sg:address":"515 S Parker St",
    "sg:city":"Marine City",
    "sg:phone":"+1 810 765 7960",
    "sg:postcode":"48039",
    "sg:province":"MI",
    "sg:tags":[
        "gas"
    ],
    "wof:name":"Pegasus Propane",
    "wof:placetype":"venue"
},
  "geometry": {"coordinates":[-82.500362,42.714535],"type":"Point"}
}