{
  "type": "Feature",
  "properties": {
    "iso:country":"US",
    "sg:address":"3322 Division Ave S",
    "sg:city":"Grand Rapids",
    "sg:classifiers":[
        {
            "category":"Retail",
            "subcategory":"Auto Repair",
            "type":"Services"
        }
    ],
    "sg:phone":"+1 616 452 0715",
    "sg:postcode":"49548",
    "sg:province":"MI",
    "sg:tags":[
        "transmission",
        "general"
    ],
    "wof:name":"Discount Transmission",
    "wof:placetype":"venue"
},
  "geometry": {"coordinates":[-85.665481,42.903985],"type":"Point"}
}