{
  "type": "Feature",
  "properties": {
    "iso:country":"US",
    "sg:address":"1000 1st St",
    "sg:city":"Buckley",
    "sg:classifiers":[
        {
            "category":"Personal",
            "subcategory":"Beauty Salon",
            "type":"Services"
        }
    ],
    "sg:phone":"+1 231 269 3545",
    "sg:postcode":"49620",
    "sg:province":"MI",
    "wof:name":"Alice's Hair Styling",
    "wof:placetype":"venue"
},
  "geometry": {"coordinates":[-85.67668999999999,44.508551],"type":"Point"}
}