{
  "type": "Feature",
  "properties": {
    "iso:country":"US",
    "sg:address":"4574 Dowling St",
    "sg:city":"Montague",
    "sg:classifiers":[
        {
            "category":"Retail",
            "subcategory":"Repair Shop",
            "type":"Services"
        }
    ],
    "sg:phone":"+1 231 893 2666",
    "sg:postcode":"49437",
    "sg:province":"MI",
    "wof:name":"Arnies Upholstery",
    "wof:placetype":"venue"
},
  "geometry": {"coordinates":[-86.355236,43.416497],"type":"Point"}
}