{
  "type": "Feature",
  "properties": {
    "iso:country":"US",
    "sg:address":"8180 Broadmoor Ave SE",
    "sg:city":"Caledonia",
    "sg:classifiers":[
        {
            "category":"Professional",
            "subcategory":"Engineering",
            "type":"Services"
        }
    ],
    "sg:phone":"+1 616 891 0800",
    "sg:postcode":"49316",
    "sg:province":"MI",
    "sg:website":"www.wilcoxassociates.com",
    "wof:name":"Asphalt Pavement Testing Co",
    "wof:placetype":"venue"
},
  "geometry": {"coordinates":[-85.51318499999999,42.81732],"type":"Point"}
}