{
  "type": "Feature",
  "properties": {
    "iso:country":"US",
    "sg:address":"5553 Allen Rd",
    "sg:city":"Allen Park",
    "sg:classifiers":[
        {
            "category":"Professional",
            "subcategory":"Management & Consulting",
            "type":"Services"
        }
    ],
    "sg:phone":"+1 313 928 5200",
    "sg:postcode":"48101",
    "sg:province":"MI",
    "sg:tags":[
        "business"
    ],
    "wof:name":"Productive Solutions Intl",
    "wof:placetype":"venue"
},
  "geometry": {"coordinates":[-83.20283499999999,42.262954],"type":"Point"}
}