{
  "type": "Feature",
  "properties": {
    "iso:country":"US",
    "sg:address":"17177 N Laurel Park Dr Ste 437",
    "sg:city":"Livonia",
    "sg:classifiers":[
        {
            "category":"Health Services",
            "subcategory":"Doctor",
            "type":"Services"
        },
        {
            "category":"Health Services",
            "subcategory":"Clinic",
            "type":"Services"
        }
    ],
    "sg:phone":"+1 734 432 6066",
    "sg:postcode":"48152",
    "sg:province":"MI",
    "sg:tags":[
        "counseling",
        "mental"
    ],
    "wof:name":"Wilanowski Alexandra MD",
    "wof:placetype":"venue"
},
  "geometry": {"coordinates":[-83.41950199999999,42.413502],"type":"Point"}
}