{
  "type": "Feature",
  "properties": {
    "iso:country":"US",
    "sg:address":"36830 Harper Ave",
    "sg:city":"Clinton Township",
    "sg:classifiers":[
        {
            "category":"Restaurant",
            "type":"Food & Drink"
        }
    ],
    "sg:menulink":"http://www.allmenus.com/mi/clinton/44016-rams-horn/menu/",
    "sg:phone":"+1 586 792 9960",
    "sg:postcode":"48035",
    "sg:province":"MI",
    "sg:tags":[
        "american",
        "diner"
    ],
    "wof:name":"Ram's Horn",
    "wof:placetype":"venue"
},
  "geometry": {"coordinates":[-82.871712,42.568314],"type":"Point"}
}