{
  "type": "Feature",
  "properties": {
    "iso:country":"US",
    "sg:address":"4501 Woodward Ave",
    "sg:city":"Detroit",
    "sg:classifiers":[
        {
            "category":"Real Estate",
            "subcategory":"Real Estate Services",
            "type":"Services"
        },
        {
            "category":"Real Estate",
            "subcategory":"Real Estate Operator",
            "type":"Services"
        }
    ],
    "sg:phone":"+1 313 316 0824",
    "sg:postcode":"48201",
    "sg:province":"MI",
    "sg:tags":[
        "apartment",
        "property",
        "management"
    ],
    "sg:website":"www.studio1apartments.com",
    "wof:name":"Studio One Apartments",
    "wof:placetype":"venue"
},
  "geometry": {"coordinates":[-83.062499,42.35362],"type":"Point"}
}