{
  "type": "Feature",
  "properties": {
    "iso:country":"US",
    "sg:address":"1761 Samaria Rd",
    "sg:city":"Erie",
    "sg:classifiers":[
        {
            "category":"Real Estate",
            "subcategory":"Architect",
            "type":"Services"
        }
    ],
    "sg:phone":"+1 734 856 3000",
    "sg:postcode":"48133",
    "sg:province":"MI",
    "wof:name":"Micheal Lee Hammond Architect",
    "wof:placetype":"venue"
},
  "geometry": {"coordinates":[-83.49982799999999,41.809404],"type":"Point"}
}