{
  "type": "Feature",
  "properties": {
    "iso:country":"US",
    "sg:address":"22787 Macomb Industrial Dr",
    "sg:city":"Clinton Twp",
    "sg:classifiers":[
        {
            "category":"Wholesale",
            "subcategory":"Construction Materials",
            "type":"Manufacturing & Wholesale Goods"
        }
    ],
    "sg:phone":"+1 586 465 2680",
    "sg:postcode":"48036",
    "sg:province":"MI",
    "sg:tags":[
        "garage",
        "organizer",
        "cabinet"
    ],
    "wof:name":"Closet Connections",
    "wof:placetype":"venue"
},
  "geometry": {"coordinates":[-82.882142,42.622606],"type":"Point"}
}