{
  "type": "Feature",
  "properties": {
    "iso:country":"US",
    "sg:address":"4205 Woodcreek Dr",
    "sg:city":"Ypsilanti",
    "sg:classifiers":[
        {
            "category":"Professional",
            "subcategory":"Management & Consulting",
            "type":"Services"
        }
    ],
    "sg:phone":"+1 734 572 3632",
    "sg:postcode":"48197",
    "sg:province":"MI",
    "sg:tags":[
        "business"
    ],
    "wof:name":"Sarkar Nitis",
    "wof:placetype":"venue"
},
  "geometry": {"coordinates":[-83.672195,42.229026],"type":"Point"}
}