{
  "type": "Feature",
  "properties": {
    "iso:country":"US",
    "sg:address":"4151 S Canton Center Rd",
    "sg:city":"Canton",
    "sg:classifiers":[
        {
            "category":"Shopping",
            "subcategory":"Pharmacy",
            "type":"Retail Goods"
        }
    ],
    "sg:phone":"+1 734 394 0027",
    "sg:postcode":"48188",
    "sg:province":"MI",
    "sg:tags":[
        "drugstore"
    ],
    "sg:website":"www.riteaid.com",
    "wof:name":"Rite Aid Pharmacies",
    "wof:placetype":"venue"
},
  "geometry": {"coordinates":[-83.485677,42.2773],"type":"Point"}
}