{
  "type": "Feature",
  "properties": {
    "iso:country":"US",
    "sg:address":"2700 Boyne Rd",
    "sg:city":"Marlette",
    "sg:classifiers":[
        {
            "category":"Building & Trades",
            "subcategory":"Construction",
            "type":"Services"
        }
    ],
    "sg:phone":"+1 989 635 3339",
    "sg:postcode":"48453",
    "sg:province":"MI",
    "sg:tags":[
        "contractor"
    ],
    "wof:name":"Yourway Builders Inc",
    "wof:placetype":"venue"
},
  "geometry": {"coordinates":[-83.06435399999999,43.334937],"type":"Point"}
}