{
  "type": "Feature",
  "properties": {
    "iso:country":"US",
    "sg:address":"1456 Harpst St",
    "sg:city":"Ann Arbor",
    "sg:classifiers":[
        {
            "category":"Professional",
            "subcategory":"Computer Services",
            "type":"Services"
        }
    ],
    "sg:phone":"+1 734 662 7803",
    "sg:postcode":"48104",
    "sg:province":"MI",
    "sg:tags":[
        "related"
    ],
    "wof:name":"Computer Serv & Software",
    "wof:placetype":"venue"
},
  "geometry": {"coordinates":[-83.72816,42.256446],"type":"Point"}
}