{
  "type": "Feature",
  "properties": {
    "iso:country":"US",
    "sg:address":"1025 Kendalwood St NE",
    "sg:city":"Grand Rapids",
    "sg:classifiers":[
        {
            "category":"Organizations",
            "subcategory":"Non-profit Organization",
            "type":"Services"
        }
    ],
    "sg:phone":"+1 616 363 0700",
    "sg:postcode":"49505",
    "sg:province":"MI",
    "sg:tags":[
        "social"
    ],
    "wof:name":"Natural Fmly Plnnng-CCL W Mich",
    "wof:placetype":"venue"
},
  "geometry": {"coordinates":[-85.64308,43.018421],"type":"Point"}
}