{
  "type": "Feature",
  "properties": {
    "iso:country":"US",
    "sg:address":"303 N Broadway St",
    "sg:city":"Cassopolis",
    "sg:classifiers":[
        {
            "category":"Sports & Exercise",
            "subcategory":"Gym",
            "type":"Entertainment"
        }
    ],
    "sg:phone":"+1 269 445 6116",
    "sg:postcode":"49031",
    "sg:province":"MI",
    "sg:tags":[
        "club",
        "health",
        "studio",
        "gymnasium"
    ],
    "wof:name":"Curves For Women",
    "wof:placetype":"venue"
},
  "geometry": {"coordinates":[-86.012646,41.916794],"type":"Point"}
}