{
  "type": "Feature",
  "properties": {
    "iso:country":"US",
    "sg:address":"215 Plexus Dr",
    "sg:city":"Oxford",
    "sg:classifiers":[
        {
            "category":"Manufacturing",
            "subcategory":"Metals",
            "type":"Manufacturing & Wholesale Goods"
        }
    ],
    "sg:phone":"+1 248 628 4300",
    "sg:postcode":"48371",
    "sg:province":"MI",
    "sg:tags":[
        "casting",
        "investment"
    ],
    "sg:website":"www.barroncast.com",
    "wof:name":"Barroncast Inc",
    "wof:placetype":"venue"
},
  "geometry": {"coordinates":[-83.29409800000001,42.867651],"type":"Point"}
}