{
  "type": "Feature",
  "properties": {
    "iso:country":"US",
    "sg:address":"32000 Utica Rd",
    "sg:city":"Fraser",
    "sg:classifiers":[
        {
            "category":"Shopping",
            "subcategory":"Gifts & Souvenirs",
            "type":"Retail Goods"
        }
    ],
    "sg:phone":"+1 586 415 2665",
    "sg:postcode":"48026",
    "sg:province":"MI",
    "sg:tags":[
        "shop"
    ],
    "wof:name":"Far Out",
    "wof:placetype":"venue"
},
  "geometry": {"coordinates":[-82.949158,42.532447],"type":"Point"}
}