{
  "type": "Feature",
  "properties": {
    "iso:country":"US",
    "sg:address":"1417 N Jenison Ave",
    "sg:city":"Lansing",
    "sg:classifiers":[
        {
            "category":"Building & Trades",
            "subcategory":"Plumbing",
            "type":"Services"
        }
    ],
    "sg:phone":"+1 517 853 9625",
    "sg:postcode":"48915",
    "sg:province":"MI",
    "sg:tags":[
        "furnace",
        "cleaning"
    ],
    "wof:name":"Bill's Furnace Svc",
    "wof:placetype":"venue"
},
  "geometry": {"coordinates":[-84.572821,42.749558],"type":"Point"}
}