{
  "type": "Feature",
  "properties": {
    "iso:country":"US",
    "sg:address":"871 S State Hwy 88",
    "sg:city":"Bellaire",
    "sg:classifiers":[
        {
            "category":"Professional",
            "subcategory":"Business Services",
            "type":"Services"
        }
    ],
    "sg:phone":"+1 231 533 8893",
    "sg:postcode":"49615",
    "sg:province":"MI",
    "wof:name":"Green Door Accents",
    "wof:placetype":"venue"
},
  "geometry": {"coordinates":[-85.220122,45.019008],"type":"Point"}
}