{
  "type": "Feature",
  "properties": {
    "iso:country":"US",
    "sg:address":"7000 S Westnedge Ave",
    "sg:city":"Portage",
    "sg:classifiers":[
        {
            "category":"Autos & Motor Vehicles",
            "subcategory":"Fuel & Gas Station",
            "type":"Retail Goods"
        }
    ],
    "sg:phone":"+1 269 323 0275",
    "sg:postcode":"49002",
    "sg:province":"MI",
    "sg:tags":[
        "shop",
        "repair",
        "station"
    ],
    "wof:name":"Shell",
    "wof:placetype":"venue"
},
  "geometry": {"coordinates":[-85.589423,42.212582],"type":"Point"}
}