{
  "type": "Feature",
  "properties": {
    "iso:country":"US",
    "sg:address":"4876 Oaklane Path",
    "sg:city":"Stevensville",
    "sg:classifiers":[
        {
            "category":"Education",
            "subcategory":"Special Training",
            "type":"Public Place"
        }
    ],
    "sg:phone":"+1 269 428 9914",
    "sg:postcode":"49127",
    "sg:province":"MI",
    "wof:name":"West Coast Driving School",
    "wof:placetype":"venue"
},
  "geometry": {"coordinates":[-86.535352,42.029539],"type":"Point"}
}