{
  "type": "Feature",
  "properties": {
    "iso:country":"US",
    "sg:address":"15788 104th Ave",
    "sg:city":"Nunica",
    "sg:classifiers":[
        {
            "category":"Building & Trades",
            "subcategory":"Construction",
            "type":"Services"
        }
    ],
    "sg:phone":"+1 616 837 0077",
    "sg:postcode":"49448",
    "sg:province":"MI",
    "sg:tags":[
        "concrete",
        "contractor"
    ],
    "wof:name":"Wordstock Inc",
    "wof:placetype":"venue"
},
  "geometry": {"coordinates":[-86.04699599999999,43.057003],"type":"Point"}
}