{
  "type": "Feature",
  "properties": {
    "iso:country":"US",
    "sg:address":"954 E Grand River Ave",
    "sg:city":"Williamston",
    "sg:classifiers":[
        {
            "category":"Building & Trades",
            "subcategory":"Construction",
            "type":"Services"
        }
    ],
    "sg:phone":"+1 517 655 4223",
    "sg:postcode":"48895",
    "sg:province":"MI",
    "sg:tags":[
        "designer",
        "dealer",
        "pool",
        "swimming"
    ],
    "sg:website":"www.dietzpools.com",
    "wof:name":"Dietz & Assoc",
    "wof:placetype":"venue"
},
  "geometry": {"coordinates":[-84.27421699999999,42.687335],"type":"Point"}
}