{
  "type": "Feature",
  "properties": {
    "iso:country":"US",
    "sg:address":"7546 W McNichols Rd",
    "sg:city":"Detroit",
    "sg:classifiers":[
        {
            "category":"Retail",
            "subcategory":"Laundry & Dry Cleaning",
            "type":"Services"
        }
    ],
    "sg:phone":"+1 313 862 5999",
    "sg:postcode":"48221",
    "sg:province":"MI",
    "wof:name":"Triplett Cleaners",
    "wof:placetype":"venue"
},
  "geometry": {"coordinates":[-83.147003,42.417198],"type":"Point"}
}