{
  "type": "Feature",
  "properties": {
    "iso:country":"US",
    "sg:address":"110 E Grand River Ave",
    "sg:city":"Howell",
    "sg:classifiers":[
        {
            "category":"Real Estate",
            "subcategory":"Surveying",
            "type":"Services"
        }
    ],
    "sg:phone":"+1 517 545 4141",
    "sg:postcode":"48843",
    "sg:province":"MI",
    "sg:tags":[
        "civil",
        "engineering"
    ],
    "wof:name":"Advantage Civil Engineering",
    "wof:placetype":"venue"
},
  "geometry": {"coordinates":[-83.92954,42.607225],"type":"Point"}
}