{
  "type": "Feature",
  "properties": {
    "iso:country":"US",
    "sg:address":"502 W Flint Park Blvd",
    "sg:city":"Flint",
    "sg:classifiers":[
        {
            "category":"Organizations",
            "subcategory":"Religious Organization",
            "type":"Services"
        }
    ],
    "sg:phone":"+1 810 789 1031",
    "sg:postcode":"48505",
    "sg:province":"MI",
    "wof:name":"Rising Star Baptist Church",
    "wof:placetype":"venue"
},
  "geometry": {"coordinates":[-83.713544,43.05593],"type":"Point"}
}