{
  "type": "Feature",
  "properties": {
    "iso:country":"US",
    "sg:address":"1965 Baldwin St",
    "sg:city":"Jenison",
    "sg:classifiers":[
        {
            "category":"Food & Beverages",
            "subcategory":"Groceries & Convenience Stores",
            "type":"Retail Goods"
        }
    ],
    "sg:phone":"+1 616 457 9110",
    "sg:postcode":"49428",
    "sg:province":"MI",
    "sg:tags":[
        "grocer"
    ],
    "wof:name":"D & W Food Ctr",
    "wof:placetype":"venue"
},
  "geometry": {"coordinates":[-85.83032,42.907237],"type":"Point"}
}