{
  "type": "Feature",
  "properties": {
    "iso:country":"US",
    "sg:address":"8840 Chippewa Hwy",
    "sg:city":"Bear Lake",
    "sg:classifiers":[
        {
            "category":"Education",
            "subcategory":"College",
            "type":"Public Place"
        }
    ],
    "sg:phone":"+1 231 889 4277",
    "sg:postcode":"49614",
    "sg:province":"MI",
    "wof:name":"Manistee County Co Op EXT",
    "wof:placetype":"venue"
},
  "geometry": {"coordinates":[-86.16224699999999,44.362148],"type":"Point"}
}