{
  "type": "Feature",
  "properties": {
    "iso:country":"US",
    "sg:address":"5041 E 7 Mile Rd",
    "sg:city":"Detroit",
    "sg:classifiers":[
        {
            "category":"Food & Beverages",
            "subcategory":"Groceries & Convenience Stores",
            "type":"Retail Goods"
        }
    ],
    "sg:phone":"+1 313 368 4603",
    "sg:postcode":"48234",
    "sg:province":"MI",
    "wof:name":"Ryan's Mini Mart Inc",
    "wof:placetype":"venue"
},
  "geometry": {"coordinates":[-83.05300099999999,42.433201],"type":"Point"}
}