{
  "type": "Feature",
  "properties": {
    "iso:country":"US",
    "sg:address":"22400 Pointe Dr",
    "sg:city":"Saint Clair Shores",
    "sg:classifiers":[
        {
            "category":"Professional",
            "subcategory":"Management & Consulting",
            "type":"Services"
        }
    ],
    "sg:phone":"+1 586 779 2009",
    "sg:postcode":"48081",
    "sg:province":"MI",
    "sg:tags":[
        "business"
    ],
    "wof:name":"Ogp International Ltd",
    "wof:placetype":"venue"
},
  "geometry": {"coordinates":[-82.889055,42.484034],"type":"Point"}
}