{
  "type": "Feature",
  "properties": {
    "iso:country":"US",
    "sg:address":"2027 4th St",
    "sg:city":"Jackson",
    "sg:classifiers":[
        {
            "category":"Health Services",
            "subcategory":"Doctor",
            "type":"Services"
        }
    ],
    "sg:phone":"+1 517 787 9630",
    "sg:postcode":"49203",
    "sg:province":"MI",
    "sg:tags":[
        "dentist"
    ],
    "wof:name":"Charles J Girard DDS PC",
    "wof:placetype":"venue"
},
  "geometry": {"coordinates":[-84.41817500000001,42.223835],"type":"Point"}
}