{
  "type": "Feature",
  "properties": {
    "iso:country":"US",
    "sg:address":"2183 Pless Dr",
    "sg:city":"Brighton",
    "sg:classifiers":[
        {
            "category":"Professional",
            "subcategory":"Engineering",
            "type":"Services"
        }
    ],
    "sg:phone":"+1 810 227 9533",
    "sg:postcode":"48114",
    "sg:province":"MI",
    "sg:tags":[
        "civil",
        "surveying"
    ],
    "wof:name":"Desine Inc",
    "wof:placetype":"venue"
},
  "geometry": {"coordinates":[-83.81269500000001,42.569754],"type":"Point"}
}