{
  "type": "Feature",
  "properties": {
    "iso:country":"US",
    "sg:address":"3693 Hi Villa Dr",
    "sg:city":"Lake Orion",
    "sg:classifiers":[
        {
            "category":"Manufacturing",
            "subcategory":"Food",
            "type":"Manufacturing & Wholesale Goods"
        }
    ],
    "sg:phone":"+1 248 393 3251",
    "sg:postcode":"48360",
    "sg:province":"MI",
    "sg:tags":[
        "cake",
        "product",
        "related",
        "bread"
    ],
    "wof:name":"Lbs Muffins and Yogurt",
    "wof:placetype":"venue"
},
  "geometry": {"coordinates":[-83.23913400000001,42.729839],"type":"Point"}
}