{
  "type": "Feature",
  "properties": {
    "iso:country":"US",
    "sg:address":"12240 S Beyer Rd",
    "sg:city":"Birch Run",
    "sg:classifiers":[
        {
            "category":"Shopping",
            "subcategory":"Clothing, Apparel, & Fashions",
            "type":"Retail Goods"
        }
    ],
    "sg:phone":"+1 989 624 8888",
    "sg:postcode":"48415",
    "sg:province":"MI",
    "sg:tags":[
        "jean"
    ],
    "wof:name":"Tommy Hilfiger Retail",
    "wof:placetype":"venue"
},
  "geometry": {"coordinates":[-83.774736,43.245912],"type":"Point"}
}