{
  "type": "Feature",
  "properties": {
    "iso:country":"US",
    "sg:address":"1387 Chestnut Dr",
    "sg:city":"Ypsilanti",
    "sg:classifiers":[
        {
            "category":"Professional",
            "subcategory":"Business Services",
            "type":"Services"
        }
    ],
    "sg:phone":"+1 734 434 9638",
    "sg:postcode":"48197",
    "sg:province":"MI",
    "wof:name":"Gerri Ann Enterprises",
    "wof:placetype":"venue"
},
  "geometry": {"coordinates":[-83.652334,42.257522],"type":"Point"}
}