{
  "type": "Feature",
  "properties": {
    "iso:country":"US",
    "sg:address":"21045 Mc Clung Ave",
    "sg:city":"Southfield",
    "sg:classifiers":[
        {
            "category":"Building & Trades",
            "subcategory":"Construction",
            "type":"Services"
        }
    ],
    "sg:phone":"+1 248 352 1660",
    "sg:postcode":"48075",
    "sg:province":"MI",
    "sg:tags":[
        "house",
        "residential"
    ],
    "wof:name":"Sherman Construction",
    "wof:placetype":"venue"
},
  "geometry": {"coordinates":[-83.250446,42.462565],"type":"Point"}
}