{
  "type": "Feature",
  "properties": {
    "iso:country":"US",
    "sg:address":"19001 Telegraph Rd",
    "sg:city":"Detroit",
    "sg:classifiers":[
        {
            "category":"Restaurant",
            "type":"Food & Drink"
        }
    ],
    "sg:menulink":"http://www.allmenus.com/mi/detroit/246924-detroit-fresh-fish--seafood/menu/",
    "sg:phone":"+1 313 255 1900",
    "sg:postcode":"48219",
    "sg:province":"MI",
    "sg:tags":[
        "seafood",
        "american"
    ],
    "wof:name":"Detroit Fresh Fish & Seafood",
    "wof:placetype":"venue"
},
  "geometry": {"coordinates":[-83.27796600000001,42.427942],"type":"Point"}
}