{
  "type": "Feature",
  "properties": {
    "iso:country":"US",
    "sg:address":"4020 W Blue Rd",
    "sg:city":"Mc Bain",
    "sg:classifiers":[
        {
            "category":"Building & Trades",
            "subcategory":"Construction",
            "type":"Services"
        }
    ],
    "sg:phone":"+1 231 826 4400",
    "sg:postcode":"49657",
    "sg:province":"MI",
    "sg:tags":[
        "house"
    ],
    "wof:name":"Pierre Schierbeek Builder",
    "wof:placetype":"venue"
},
  "geometry": {"coordinates":[-85.17571599999999,44.266361],"type":"Point"}
}