{
  "type": "Feature",
  "properties": {
    "iso:country":"US",
    "sg:address":"30731 Utica Rd",
    "sg:city":"Roseville",
    "sg:classifiers":[
        {
            "category":"Shopping",
            "subcategory":"Tobacco",
            "type":"Retail Goods"
        }
    ],
    "sg:phone":"+1 586 771 8733",
    "sg:postcode":"48066",
    "sg:province":"MI",
    "sg:tags":[
        "shop"
    ],
    "wof:name":"Smokers Only",
    "wof:placetype":"venue"
},
  "geometry": {"coordinates":[-82.94326599999999,42.522249],"type":"Point"}
}