{
  "type": "Feature",
  "properties": {
    "iso:country":"US",
    "sg:address":"6472 M 66 N",
    "sg:city":"Charlevoix",
    "sg:classifiers":[
        {
            "category":"Home & Garden",
            "subcategory":"Building Materials",
            "type":"Retail Goods"
        }
    ],
    "sg:phone":"+1 231 547 4464",
    "sg:postcode":"49720",
    "sg:province":"MI",
    "sg:tags":[
        "lumber"
    ],
    "wof:name":"Wolohan Lumber",
    "wof:placetype":"venue"
},
  "geometry": {"coordinates":[-85.25507399999999,45.297529],"type":"Point"}
}