{
  "type": "Feature",
  "properties": {
    "iso:country":"US",
    "sg:address":"2501 Crest Dr",
    "sg:city":"Kalamazoo",
    "sg:classifiers":[
        {
            "category":"Retail",
            "subcategory":"Repair Shop",
            "type":"Services"
        }
    ],
    "sg:phone":"+1 269 382 2056",
    "sg:postcode":"49008",
    "sg:province":"MI",
    "sg:tags":[
        "clocks",
        "parts"
    ],
    "wof:name":"Fox Clock Repair",
    "wof:placetype":"venue"
},
  "geometry": {"coordinates":[-85.619061,42.259899],"type":"Point"}
}