{
  "type": "Feature",
  "properties": {
    "iso:country":"US",
    "sg:address":"10002 Keller Rd",
    "sg:city":"Delton",
    "sg:classifiers":[
        {
            "category":"Retail",
            "subcategory":"Auto Repair",
            "type":"Services"
        }
    ],
    "sg:phone":"+1 269 623 8814",
    "sg:postcode":"49046",
    "sg:province":"MI",
    "sg:tags":[
        "repairing",
        "automobile",
        "general"
    ],
    "wof:name":"Finch's Auto Alignment",
    "wof:placetype":"venue"
},
  "geometry": {"coordinates":[-85.488495,42.560469],"type":"Point"}
}