{
  "type": "Feature",
  "properties": {
    "iso:country":"US",
    "sg:address":"13305 Armstrong Rd",
    "sg:city":"South Rockwood",
    "sg:classifiers":[
        {
            "category":"Building & Trades",
            "subcategory":"Electrical",
            "type":"Services"
        }
    ],
    "sg:phone":"+1 734 782 4002",
    "sg:postcode":"48179",
    "sg:province":"MI",
    "sg:tags":[
        "electrician"
    ],
    "wof:name":"Dotson Electric Inc",
    "wof:placetype":"venue"
},
  "geometry": {"coordinates":[-83.28420300000001,42.071301],"type":"Point"}
}