{
  "type": "Feature",
  "properties": {
    "iso:country":"US",
    "sg:address":"2262 E Remus Rd",
    "sg:city":"Mt Pleasant",
    "sg:classifiers":[
        {
            "category":"Home & Garden",
            "subcategory":"Carpets & Floor Coverings",
            "type":"Retail Goods"
        },
        {
            "category":"Building & Trades",
            "subcategory":"Construction",
            "type":"Services"
        }
    ],
    "sg:phone":"+1 989 772 2888",
    "sg:postcode":"48858",
    "sg:province":"MI",
    "sg:tags":[
        "layer",
        "dealer",
        "rug"
    ],
    "wof:name":"Lorenz United Floor Covering",
    "wof:placetype":"venue"
},
  "geometry": {"coordinates":[-84.79772800000001,43.597035],"type":"Point"}
}