{
  "type": "Feature",
  "properties": {
    "iso:country":"US",
    "sg:address":"905 Boon St",
    "sg:city":"Traverse City",
    "sg:classifiers":[
        {
            "category":"Personal",
            "subcategory":"Beauty Salon",
            "type":"Services"
        }
    ],
    "sg:phone":"+1 231 946 9159",
    "sg:postcode":"49686",
    "sg:province":"MI",
    "wof:name":"Nine-O-Five Beauty Salon",
    "wof:placetype":"venue"
},
  "geometry": {"coordinates":[-85.60015199999999,44.744293],"type":"Point"}
}