{
  "type": "Feature",
  "properties": {
    "iso:country":"US",
    "sg:address":"45259 Thornhill Rd",
    "sg:city":"Canton",
    "sg:classifiers":[
        {
            "category":"Government",
            "subcategory":"Office",
            "type":"Public Place"
        }
    ],
    "sg:phone":"+1 734 397 8606",
    "sg:postcode":"48188",
    "sg:province":"MI",
    "sg:tags":[
        "agricultural",
        "regulation",
        "marketing"
    ],
    "wof:name":"Biolab Extension Inc",
    "wof:placetype":"venue"
},
  "geometry": {"coordinates":[-83.48311099999999,42.29857],"type":"Point"}
}