{
  "type": "Feature",
  "properties": {
    "iso:country":"US",
    "sg:address":"317 W Main St",
    "sg:city":"Ionia",
    "sg:classifiers":[
        {
            "category":"Shopping",
            "subcategory":"Stationery & Office Supplies",
            "type":"Retail Goods"
        }
    ],
    "sg:phone":"+1 616 527 6000",
    "sg:postcode":"48846",
    "sg:province":"MI",
    "wof:name":"Ionia Office Works",
    "wof:placetype":"venue"
},
  "geometry": {"coordinates":[-85.066536,42.982362],"type":"Point"}
}