{
  "type": "Feature",
  "properties": {
    "iso:country":"US",
    "sg:address":"11398 Heidi Jane Ln",
    "sg:city":"Fowlerville",
    "sg:classifiers":[
        {
            "category":"Retail",
            "subcategory":"Animal Services",
            "type":"Services"
        }
    ],
    "sg:phone":"+1 517 223 0686",
    "sg:postcode":"48836",
    "sg:province":"MI",
    "wof:name":"Southwick Training Stables",
    "wof:placetype":"venue"
},
  "geometry": {"coordinates":[-84.14363899999999,42.684121],"type":"Point"}
}