{
  "type": "Feature",
  "properties": {
    "iso:country":"US",
    "sg:address":"6963 Trowbridge Cir",
    "sg:city":"Saginaw",
    "sg:classifiers":[
        {
            "category":"Professional",
            "type":"Services"
        }
    ],
    "sg:phone":"+1 989 790 3485",
    "sg:postcode":"48603",
    "sg:province":"MI",
    "wof:name":"Woodbridge It Services",
    "wof:placetype":"venue"
},
  "geometry": {"coordinates":[-84.050916,43.464884],"type":"Point"}
}