{
  "type": "Feature",
  "properties": {
    "iso:country":"US",
    "sg:address":"27380 Novi Rd",
    "sg:city":"Novi",
    "sg:classifiers":[
        {
            "category":"Shopping",
            "subcategory":"Optical Goods",
            "type":"Retail Goods"
        }
    ],
    "sg:phone":"+1 248 344 1044",
    "sg:postcode":"48377",
    "sg:province":"MI",
    "wof:name":"Lens Crafters",
    "wof:placetype":"venue"
},
  "geometry": {"coordinates":[-83.475877,42.48906],"type":"Point"}
}