{
  "type": "Feature",
  "properties": {
    "iso:country":"US",
    "sg:address":"5960 Nightingale St",
    "sg:city":"Dearborn Heights",
    "sg:classifiers":[
        {
            "category":"Building & Trades",
            "subcategory":"Construction",
            "type":"Services"
        }
    ],
    "sg:phone":"+1 313 563 1885",
    "sg:postcode":"48127",
    "sg:province":"MI",
    "sg:tags":[
        "house"
    ],
    "wof:name":"Faith Designs",
    "wof:placetype":"venue"
},
  "geometry": {"coordinates":[-83.284806,42.330612],"type":"Point"}
}