{
  "type": "Feature",
  "properties": {
    "iso:country":"US",
    "sg:address":"19766 Gennett Rd",
    "sg:city":"Charlevoix",
    "sg:classifiers":[
        {
            "category":"Professional",
            "type":"Services"
        }
    ],
    "sg:phone":"+1 231 547 3141",
    "sg:postcode":"49720",
    "sg:province":"MI",
    "wof:name":"Bucky Beaver Businesses",
    "wof:placetype":"venue"
},
  "geometry": {"coordinates":[-85.377661,45.214781],"type":"Point"}
}