{
  "type": "Feature",
  "properties": {
    "iso:country":"US",
    "sg:address":"5250 Lovers Ln",
    "sg:city":"Portage",
    "sg:classifiers":[
        {
            "category":"Health Services",
            "subcategory":"Clinic",
            "type":"Services"
        }
    ],
    "sg:phone":"+1 269 567 7000",
    "sg:postcode":"49002",
    "sg:province":"MI",
    "wof:name":"Health Risk Management",
    "wof:placetype":"venue"
},
  "geometry": {"coordinates":[-85.575028,42.241234],"type":"Point"}
}