{
  "type": "Feature",
  "properties": {
    "iso:country":"US",
    "sg:address":"15320 Three Oaks Rd",
    "sg:city":"Three Oaks",
    "sg:classifiers":[
        {
            "category":"Building & Trades",
            "subcategory":"Construction",
            "type":"Services"
        }
    ],
    "sg:phone":"+1 269 756 9407",
    "sg:postcode":"49128",
    "sg:province":"MI",
    "sg:tags":[
        "designer",
        "dealer",
        "pool",
        "swimming"
    ],
    "wof:name":"Cesears Pools LLC",
    "wof:placetype":"venue"
},
  "geometry": {"coordinates":[-86.609966,41.841785],"type":"Point"}
}