{
  "type": "Feature",
  "properties": {
    "iso:country":"US",
    "sg:address":"17595 Asbury Park",
    "sg:city":"Detroit",
    "sg:classifiers":[
        {
            "category":"Utilities",
            "subcategory":"Water",
            "type":"Services"
        },
        {
            "category":"Building & Trades",
            "subcategory":"Cleaning & Sanitation",
            "type":"Services"
        },
        {
            "category":"Home & Garden",
            "subcategory":"Building Materials",
            "type":"Retail Goods"
        },
        {
            "category":"Building & Trades",
            "subcategory":"Construction",
            "type":"Services"
        }
    ],
    "sg:phone":"+1 313 272 6793",
    "sg:postcode":"48235",
    "sg:province":"MI",
    "sg:tags":[
        "emergency",
        "fire",
        "damage",
        "contractor",
        "planning",
        "improvement",
        "remodeling",
        "restoration",
        "kitchen"
    ],
    "sg:website":"http://n?a",
    "wof:name":"Continental Construction",
    "wof:placetype":"venue"
},
  "geometry": {"coordinates":[-83.209141,42.419785],"type":"Point"}
}