{
  "type": "Feature",
  "properties": {
    "iso:country":"US",
    "sg:address":"420 S Waverly Rd",
    "sg:city":"Lansing",
    "sg:classifiers":[
        {
            "category":"Real Estate",
            "subcategory":"Real Estate Services",
            "type":"Services"
        }
    ],
    "sg:phone":"+1 517 703 1950",
    "sg:postcode":"48917",
    "sg:province":"MI",
    "sg:tags":[
        "company",
        "title"
    ],
    "wof:name":"Devon Title Agency",
    "wof:placetype":"venue"
},
  "geometry": {"coordinates":[-84.60303500000001,42.729185],"type":"Point"}
}