{
  "type": "Feature",
  "properties": {
    "iso:country":"US",
    "sg:address":"3417 N Clare Ave",
    "sg:city":"Harrison",
    "sg:classifiers":[
        {
            "category":"Freight",
            "type":"Transportation"
        }
    ],
    "sg:phone":"+1 989 539 2243",
    "sg:postcode":"48625",
    "sg:province":"MI",
    "sg:tags":[
        "commercial",
        "storage"
    ],
    "wof:name":"Harrison Storage",
    "wof:placetype":"venue"
},
  "geometry": {"coordinates":[-84.808179,44.045707],"type":"Point"}
}