{
  "type": "Feature",
  "properties": {
    "iso:country":"US",
    "sg:address":"1071 W Larch Ave",
    "sg:city":"Muskegon",
    "sg:classifiers":[
        {
            "category":"Social Services",
            "subcategory":"Child Care",
            "type":"Services"
        }
    ],
    "sg:phone":"+1 231 759 0043",
    "sg:postcode":"49441",
    "sg:province":"MI",
    "sg:tags":[
        "day",
        "provider"
    ],
    "wof:name":"Wier Virginia Mary",
    "wof:placetype":"venue"
},
  "geometry": {"coordinates":[-86.270146,43.220789],"type":"Point"}
}