{
  "type": "Feature",
  "properties": {
    "iso:country":"US",
    "sg:address":"5912 Coit Ave NE",
    "sg:city":"Grand Rapids",
    "sg:classifiers":[
        {
            "category":"Social Services",
            "subcategory":"Child Care",
            "type":"Services"
        }
    ],
    "sg:phone":"+1 616 361 7175",
    "sg:postcode":"49525",
    "sg:province":"MI",
    "sg:tags":[
        "day"
    ],
    "wof:name":"Sally Steenland",
    "wof:placetype":"venue"
},
  "geometry": {"coordinates":[-85.600697,43.055531],"type":"Point"}
}