{
  "type": "Feature",
  "properties": {
    "iso:country":"US",
    "sg:address":"19801 Prevost St",
    "sg:city":"Detroit",
    "sg:classifiers":[
        {
            "category":"Education",
            "subcategory":"School",
            "type":"Public Place"
        }
    ],
    "sg:phone":"+1 313 852 0500",
    "sg:postcode":"48235",
    "sg:province":"MI",
    "wof:name":"Detroit Public Schools",
    "wof:placetype":"venue"
},
  "geometry": {"coordinates":[-83.20451799999999,42.436631],"type":"Point"}
}