{
  "type": "Feature",
  "properties": {
    "iso:country":"US",
    "sg:address":"17026 Dix Toledo Hwy",
    "sg:city":"Wyandotte",
    "sg:classifiers":[
        {
            "category":"Wholesale",
            "subcategory":"Auto Parts",
            "type":"Manufacturing & Wholesale Goods"
        }
    ],
    "sg:phone":"+1 734 283 1644",
    "sg:postcode":"48193",
    "sg:province":"MI",
    "sg:tags":[
        "a",
        "shop",
        "tire",
        "repair",
        "automobile",
        "truck"
    ],
    "wof:name":"Waddles Tire Service Inc",
    "wof:placetype":"venue"
},
  "geometry": {"coordinates":[-83.23021900000001,42.180923],"type":"Point"}
}