{
  "type": "Feature",
  "properties": {
    "iso:country":"US",
    "sg:address":"929 Iowa St SW",
    "sg:city":"Grand Rapids",
    "sg:classifiers":[
        {
            "category":"Building & Trades",
            "subcategory":"Construction",
            "type":"Services"
        }
    ],
    "sg:phone":"+1 616 534 2326",
    "sg:postcode":"49509",
    "sg:province":"MI",
    "sg:tags":[
        "hanging",
        "contractor"
    ],
    "wof:name":"Moonlight Painting",
    "wof:placetype":"venue"
},
  "geometry": {"coordinates":[-85.68949600000001,42.893041],"type":"Point"}
}