{
  "type": "Feature",
  "properties": {
    "iso:country":"US",
    "sg:address":"1606 Boston Blvd",
    "sg:city":"Lansing",
    "sg:classifiers":[
        {
            "category":"Retail",
            "subcategory":"Repair Shop",
            "type":"Services"
        }
    ],
    "sg:phone":"+1 517 374 9633",
    "sg:postcode":"48910",
    "sg:province":"MI",
    "sg:tags":[
        "repairing",
        "piano",
        "refinishing"
    ],
    "wof:name":"Rachel Alexander-Piano Tech",
    "wof:placetype":"venue"
},
  "geometry": {"coordinates":[-84.574879,42.715075],"type":"Point"}
}