{
  "type": "Feature",
  "properties": {
    "iso:country":"US",
    "sg:address":"11610 Inkster Rd",
    "sg:city":"Redford",
    "sg:classifiers":[
        {
            "category":"Restaurant",
            "type":"Food & Drink"
        }
    ],
    "sg:phone":"+1 313 937 1667",
    "sg:postcode":"48239",
    "sg:province":"MI",
    "sg:website":"www.rallyburger.com",
    "wof:name":"Rally's Hamburgers",
    "wof:placetype":"venue"
},
  "geometry": {"coordinates":[-83.313301,42.369999],"type":"Point"}
}