{
  "type": "Feature",
  "properties": {
    "iso:country":"US",
    "sg:address":"27600 Farmington Rd",
    "sg:city":"Farmington Hills",
    "sg:classifiers":[
        {
            "category":"Shopping",
            "subcategory":"Jewelry",
            "type":"Retail Goods"
        }
    ],
    "sg:phone":"+1 248 489 5902",
    "sg:postcode":"48334",
    "sg:province":"MI",
    "wof:name":"L Z Jewelers and Gifts",
    "wof:placetype":"venue"
},
  "geometry": {"coordinates":[-83.378005,42.498314],"type":"Point"}
}