{
  "type": "Feature",
  "properties": {
    "iso:country":"US",
    "sg:address":"7640 N Wayne Rd",
    "sg:city":"Westland",
    "sg:classifiers":[
        {
            "category":"Bars & Pubs",
            "subcategory":"Nightclub",
            "type":"Food & Drink"
        }
    ],
    "sg:phone":"+1 734 422 3737",
    "sg:postcode":"48185",
    "sg:province":"MI",
    "sg:tags":[
        "nightlife"
    ],
    "wof:name":"Chatters",
    "wof:placetype":"venue"
},
  "geometry": {"coordinates":[-83.385002,42.343201],"type":"Point"}
}