{
  "type": "Feature",
  "properties": {
    "iso:country":"US",
    "sg:address":"16521 Turner St",
    "sg:city":"Lansing",
    "sg:classifiers":[
        {
            "category":"Building & Trades",
            "subcategory":"Landscaping Services",
            "type":"Services"
        }
    ],
    "sg:phone":"+1 517 484 6620",
    "sg:postcode":"48906",
    "sg:province":"MI",
    "sg:tags":[
        "landscape",
        "contractor"
    ],
    "wof:name":"Lewis Landscape Svc",
    "wof:placetype":"venue"
},
  "geometry": {"coordinates":[-84.55445400000001,42.776159],"type":"Point"}
}