{
  "type": "Feature",
  "properties": {
    "iso:country":"US",
    "sg:address":"3062 E Walton Blvd",
    "sg:city":"Auburn Hills",
    "sg:classifiers":[
        {
            "category":"Professional",
            "subcategory":"Employment Agencies",
            "type":"Services"
        }
    ],
    "sg:phone":"+1 248 292 2200",
    "sg:postcode":"48326",
    "sg:province":"MI",
    "sg:tags":[
        "employee",
        "leasing"
    ],
    "wof:name":"Your Source",
    "wof:placetype":"venue"
},
  "geometry": {"coordinates":[-83.229198,42.678755],"type":"Point"}
}