{
  "type": "Feature",
  "properties": {
    "iso:country":"US",
    "sg:address":"5717 McMillan St",
    "sg:city":"Dearborn Heights",
    "sg:classifiers":[
        {
            "category":"Social Services",
            "type":"Services"
        }
    ],
    "sg:phone":"+1 313 274 0110",
    "sg:postcode":"48127",
    "sg:province":"MI",
    "wof:name":"AB Counseling Solutions Inc",
    "wof:placetype":"venue"
},
  "geometry": {"coordinates":[-83.257972,42.328668],"type":"Point"}
}