{
  "type": "Feature",
  "properties": {
    "iso:country":"US",
    "sg:address":"624 S Mission St",
    "sg:city":"Mount Pleasant",
    "sg:classifiers":[
        {
            "category":"Personal",
            "subcategory":"Beauty Salon",
            "type":"Services"
        }
    ],
    "sg:phone":"+1 989 773 9741",
    "sg:postcode":"48858",
    "sg:province":"MI",
    "sg:tags":[
        "shop"
    ],
    "wof:name":"Shear Magic Hairstyling",
    "wof:placetype":"venue"
},
  "geometry": {"coordinates":[-84.767667,43.599156],"type":"Point"}
}