{
  "type": "Feature",
  "properties": {
    "iso:country":"US",
    "sg:address":"385 N Barry Rd",
    "sg:city":"Wheeler",
    "sg:phone":"+1 989 875 3955",
    "sg:postcode":"48662",
    "sg:province":"MI",
    "sg:tags":[
        "wheat",
        "farm",
        "corn",
        "cash",
        "grain",
        "soybean"
    ],
    "wof:name":"Maynard Gross",
    "wof:placetype":"venue"
},
  "geometry": {"coordinates":[-84.42915600000001,43.303306],"type":"Point"}
}