{
  "type": "Feature",
  "properties": {
    "iso:country":"US",
    "sg:address":"36575 Warren Rd",
    "sg:city":"Westland",
    "sg:classifiers":[
        {
            "category":"Restaurant",
            "type":"Food & Drink"
        }
    ],
    "sg:phone":"+1 734 326 2885",
    "sg:postcode":"48185",
    "sg:province":"MI",
    "sg:tags":[
        "mexican"
    ],
    "sg:website":"www.qdoba.com",
    "wof:name":"Qdoba Mexican Grill",
    "wof:placetype":"venue"
},
  "geometry": {"coordinates":[-83.401484,42.338212],"type":"Point"}
}