{
  "type": "Feature",
  "properties": {
    "iso:country":"US",
    "sg:address":"1199 Stewart Rd",
    "sg:city":"Monroe",
    "sg:classifiers":[
        {
            "category":"Social Services",
            "subcategory":"Child Care",
            "type":"Services"
        }
    ],
    "sg:phone":"+1 734 241 1002",
    "sg:postcode":"48162",
    "sg:province":"MI",
    "wof:name":"Pathway Child Care Ctr",
    "wof:placetype":"venue"
},
  "geometry": {"coordinates":[-83.40043,41.940466],"type":"Point"}
}