{
  "type": "Feature",
  "properties": {
    "iso:country":"US",
    "sg:address":"707 N Wisner St",
    "sg:city":"Jackson",
    "sg:classifiers":[
        {
            "category":"Professional",
            "subcategory":"Employment Agencies",
            "type":"Services"
        }
    ],
    "sg:phone":"+1 517 789 9677",
    "sg:postcode":"49202",
    "sg:province":"MI",
    "sg:tags":[
        "opportunity"
    ],
    "wof:name":"Fasco Temporary Svc",
    "wof:placetype":"venue"
},
  "geometry": {"coordinates":[-84.42824,42.255616],"type":"Point"}
}