{
  "type": "Feature",
  "properties": {
    "iso:country":"US",
    "sg:address":"8842 Portage Rd",
    "sg:city":"Portage",
    "sg:classifiers":[
        {
            "category":"Personal",
            "subcategory":"Beauty Salon",
            "type":"Services"
        }
    ],
    "sg:phone":"+1 269 216 3491",
    "sg:postcode":"49002",
    "sg:province":"MI",
    "wof:name":"Abstract Salon",
    "wof:placetype":"venue"
},
  "geometry": {"coordinates":[-85.562454,42.188467],"type":"Point"}
}