{
  "type": "Feature",
  "properties": {
    "iso:country":"US",
    "sg:address":"2831 Walmsley Cir",
    "sg:city":"Lake Orion",
    "sg:classifiers":[
        {
            "category":"Professional",
            "subcategory":"Management & Consulting",
            "type":"Services"
        }
    ],
    "sg:phone":"+1 248 391 4627",
    "sg:postcode":"48360",
    "sg:province":"MI",
    "sg:tags":[
        "business"
    ],
    "wof:name":"Vickers Group The",
    "wof:placetype":"venue"
},
  "geometry": {"coordinates":[-83.306186,42.738953],"type":"Point"}
}