{
  "type": "Feature",
  "properties": {
    "iso:country":"US",
    "sg:address":"1015 W Carpenter Rd",
    "sg:city":"Flint",
    "sg:classifiers":[
        {
            "category":"Retail",
            "subcategory":"Laundry & Dry Cleaning",
            "type":"Services"
        }
    ],
    "sg:phone":"+1 810 785 3485",
    "sg:postcode":"48505",
    "sg:province":"MI",
    "sg:tags":[
        "sales"
    ],
    "wof:name":"Rehoboth",
    "wof:placetype":"venue"
},
  "geometry": {"coordinates":[-83.718266,43.075272],"type":"Point"}
}