{
  "type": "Feature",
  "properties": {
    "iso:country":"US",
    "sg:address":"6101 Eagle Ridge Ln",
    "sg:city":"Flint",
    "sg:classifiers":[
        {
            "category":"Real Estate",
            "subcategory":"Real Estate Operator",
            "type":"Services"
        }
    ],
    "sg:phone":"+1 810 787 2400",
    "sg:postcode":"48505",
    "sg:province":"MI",
    "sg:tags":[
        "apartment"
    ],
    "wof:name":"Eagle Ridge Square",
    "wof:placetype":"venue"
},
  "geometry": {"coordinates":[-83.684601,43.069199],"type":"Point"}
}