{
  "type": "Feature",
  "properties": {
    "iso:country":"US",
    "sg:address":"2876 N Orr Rd",
    "sg:city":"Hemlock",
    "sg:classifiers":[
        {
            "category":"Building & Trades",
            "subcategory":"Construction",
            "type":"Services"
        }
    ],
    "sg:phone":"+1 989 213 3944",
    "sg:postcode":"48626",
    "sg:province":"MI",
    "sg:tags":[
        "concrete",
        "contractor"
    ],
    "wof:name":"Olson Concrete",
    "wof:placetype":"venue"
},
  "geometry": {"coordinates":[-84.170553,43.442775],"type":"Point"}
}