{
  "type": "Feature",
  "properties": {
    "iso:country":"US",
    "sg:address":"528 Virginia Ave",
    "sg:city":"Ann Arbor",
    "sg:classifiers":[
        {
            "category":"Real Estate",
            "subcategory":"Real Estate Agent",
            "type":"Services"
        }
    ],
    "sg:phone":"+1 734 663 7818",
    "sg:postcode":"48103",
    "sg:province":"MI",
    "wof:name":"Roma B Siller",
    "wof:placetype":"venue"
},
  "geometry": {"coordinates":[-83.76750699999999,42.277827],"type":"Point"}
}