{
  "type": "Feature",
  "properties": {
    "iso:country":"US",
    "sg:address":"6101 E M 115",
    "sg:city":"Cadillac",
    "sg:classifiers":[
        {
            "category":"Restaurant",
            "type":"Food & Drink"
        }
    ],
    "sg:phone":"+1 231 775 8800",
    "sg:postcode":"49601",
    "sg:province":"MI",
    "wof:name":"Burger King",
    "wof:placetype":"venue"
},
  "geometry": {"coordinates":[-85.459688,44.248828],"type":"Point"}
}