{
  "type": "Feature",
  "properties": {
    "iso:country":"US",
    "sg:address":"24550 Lambrecht Ave",
    "sg:city":"Eastpointe",
    "sg:classifiers":[
        {
            "category":"Building & Trades",
            "subcategory":"Construction",
            "type":"Services"
        }
    ],
    "sg:phone":"+1 586 773 0713",
    "sg:postcode":"48021",
    "sg:province":"MI",
    "sg:tags":[
        "hanging",
        "contractor"
    ],
    "wof:name":"Rae Painting",
    "wof:placetype":"venue"
},
  "geometry": {"coordinates":[-82.94143,42.474561],"type":"Point"}
}