{
  "type": "Feature",
  "properties": {
    "iso:country":"US",
    "sg:address":"23005 Gratiot Ave",
    "sg:city":"Eastpointe",
    "sg:classifiers":[
        {
            "category":"Shopping",
            "subcategory":"Clothing, Apparel, & Fashions",
            "type":"Retail Goods"
        }
    ],
    "sg:phone":"+1 586 776 8413",
    "sg:postcode":"48021",
    "sg:province":"MI",
    "sg:tags":[
        "theatrical",
        "costume"
    ],
    "wof:name":"Screamers Costumes",
    "wof:placetype":"venue"
},
  "geometry": {"coordinates":[-82.95635799999999,42.467653],"type":"Point"}
}