{
  "type": "Feature",
  "properties": {
    "iso:country":"US",
    "sg:address":"6549 Fork Ave SW",
    "sg:city":"Grand Rapids",
    "sg:classifiers":[
        {
            "category":"Professional",
            "subcategory":"Computer Services",
            "type":"Services"
        }
    ],
    "sg:phone":"+1 616 827 8653",
    "sg:postcode":"49548",
    "sg:province":"MI",
    "sg:tags":[
        "related"
    ],
    "wof:name":"Quik Type Computer Services",
    "wof:placetype":"venue"
},
  "geometry": {"coordinates":[-85.67003800000001,42.845648],"type":"Point"}
}