{
  "type": "Feature",
  "properties": {
    "iso:country":"US",
    "sg:address":"6330 Orchard Lake Rd # 120",
    "sg:city":"West Bloomfield",
    "sg:classifiers":[
        {
            "category":"Health Services",
            "subcategory":"Doctor",
            "type":"Services"
        }
    ],
    "sg:phone":"+1 248 855 3366",
    "sg:postcode":"48322",
    "sg:province":"MI",
    "sg:tags":[
        "dermatologist"
    ],
    "wof:name":"Dorman Michael A MD Dermtlgst",
    "wof:placetype":"venue"
},
  "geometry": {"coordinates":[-83.360901,42.546398],"type":"Point"}
}