{
  "type": "Feature",
  "properties": {
    "iso:country":"US",
    "sg:address":"9000 Conifer Ridge Dr SW",
    "sg:city":"Byron Center",
    "sg:classifiers":[
        {
            "category":"Professional",
            "subcategory":"Business Services",
            "type":"Services"
        }
    ],
    "sg:phone":"+1 616 878 1958",
    "sg:postcode":"49315",
    "sg:province":"MI",
    "wof:name":"Expressive Interiors",
    "wof:placetype":"venue"
},
  "geometry": {"coordinates":[-85.725742,42.802543],"type":"Point"}
}