{
  "type": "Feature",
  "properties": {
    "iso:country":"US",
    "sg:address":"5706 Kreiner Rd",
    "sg:city":"Brown City",
    "sg:classifiers":[
        {
            "category":"Insurance",
            "subcategory":"Insurance Agent",
            "type":"Services"
        }
    ],
    "sg:phone":"+1 810 346 3564",
    "sg:postcode":"48416",
    "sg:province":"MI",
    "wof:name":"A & M Personal Computers",
    "wof:placetype":"venue"
},
  "geometry": {"coordinates":[-83.03777700000001,43.210717],"type":"Point"}
}