{
  "type": "Feature",
  "properties": {
    "iso:country":"US",
    "sg:address":"10067 N State Rd",
    "sg:city":"Otisville",
    "sg:classifiers":[
        {
            "category":"Real Estate",
            "subcategory":"Real Estate Agent",
            "type":"Services"
        }
    ],
    "sg:phone":"+1 810 631 6354",
    "sg:postcode":"48463",
    "sg:province":"MI",
    "sg:tags":[
        "inspection"
    ],
    "wof:name":"Spectrum Home Inspections",
    "wof:placetype":"venue"
},
  "geometry": {"coordinates":[-83.521908,43.153296],"type":"Point"}
}