{
  "type": "Feature",
  "properties": {
    "iso:country":"US",
    "sg:address":"4070 W Polk Rd",
    "sg:city":"Hart",
    "sg:classifiers":[
        {
            "category":"Banks & Credit Unions",
            "subcategory":"Bank",
            "type":"Services"
        }
    ],
    "sg:phone":"+1 231 873 1400",
    "sg:postcode":"49420",
    "sg:province":"MI",
    "wof:name":"West Shore Bank",
    "wof:placetype":"venue"
},
  "geometry": {"coordinates":[-86.383713,43.689084],"type":"Point"}
}