{
  "type": "Feature",
  "properties": {
    "iso:country":"US",
    "sg:address":"202 W Exchange St",
    "sg:city":"Owosso",
    "sg:classifiers":[
        {
            "category":"Personal",
            "subcategory":"Tanning Parlor",
            "type":"Services"
        }
    ],
    "sg:phone":"+1 989 723 0143",
    "sg:postcode":"48867",
    "sg:province":"MI",
    "sg:tags":[
        "salon"
    ],
    "wof:name":"Picasso's Tanning Studio",
    "wof:placetype":"venue"
},
  "geometry": {"coordinates":[-84.173149,42.998615],"type":"Point"}
}