{
  "type": "Feature",
  "properties": {
    "iso:country":"US",
    "sg:address":"6017 Lancaster Dr",
    "sg:city":"Flint",
    "sg:classifiers":[
        {
            "category":"Professional",
            "subcategory":"Management & Consulting",
            "type":"Services"
        }
    ],
    "sg:phone":"+1 810 732 1099",
    "sg:postcode":"48532",
    "sg:province":"MI",
    "sg:tags":[
        "public",
        "relations"
    ],
    "wof:name":"Sign Promotion Products Amer",
    "wof:placetype":"venue"
},
  "geometry": {"coordinates":[-83.79563,43.00677],"type":"Point"}
}