{
  "type": "Feature",
  "properties": {
    "iso:country":"US",
    "sg:address":"8880 Unionville Rd",
    "sg:city":"Sebewaing",
    "sg:classifiers":[
        {
            "category":"Banks & Credit Unions",
            "subcategory":"Bank",
            "type":"Services"
        }
    ],
    "sg:phone":"+1 989 883 3310",
    "sg:postcode":"48759",
    "sg:province":"MI",
    "sg:tags":[
        "loan"
    ],
    "wof:name":"Independent Bank",
    "wof:placetype":"venue"
},
  "geometry": {"coordinates":[-83.447824,43.718753],"type":"Point"}
}