{
  "type": "Feature",
  "properties": {
    "iso:country":"US",
    "sg:address":"185 N Division Ave",
    "sg:city":"Hesperia",
    "sg:classifiers":[
        {
            "category":"Personal",
            "subcategory":"Beauty Salon",
            "type":"Services"
        }
    ],
    "sg:phone":"+1 231 854 5415",
    "sg:postcode":"49421",
    "sg:province":"MI",
    "wof:name":"Unique Beauty Salon",
    "wof:placetype":"venue"
},
  "geometry": {"coordinates":[-86.03962199999999,43.564508],"type":"Point"}
}