{
  "type": "Feature",
  "properties": {
    "iso:country":"US",
    "sg:address":"485 N Whitehall Rd",
    "sg:city":"North Muskegon",
    "sg:classifiers":[
        {
            "category":"Banks & Credit Unions",
            "subcategory":"Bank",
            "type":"Services"
        }
    ],
    "sg:phone":"+1 231 780 1880",
    "sg:postcode":"49445",
    "sg:province":"MI",
    "wof:name":"Community Shores Bank",
    "wof:placetype":"venue"
},
  "geometry": {"coordinates":[-86.252061,43.267513],"type":"Point"}
}