{
  "type": "Feature",
  "properties": {
    "iso:country":"US",
    "sg:address":"23000 Eureka Rd",
    "sg:city":"Taylor",
    "sg:classifiers":[
        {
            "category":"Shopping",
            "subcategory":"Music",
            "type":"Retail Goods"
        }
    ],
    "sg:phone":"+1 734 407 2373",
    "sg:postcode":"48180",
    "sg:province":"MI",
    "sg:tags":[
        "dvd's"
    ],
    "wof:name":"Topshelf Entertainment",
    "wof:placetype":"venue"
},
  "geometry": {"coordinates":[-83.267601,42.227699],"type":"Point"}
}