{
  "type": "Feature",
  "properties": {
    "iso:country":"US",
    "sg:address":"633 Plymouth Ave NE",
    "sg:city":"Grand Rapids",
    "sg:classifiers":[
        {
            "category":"Building & Trades",
            "subcategory":"Electrical",
            "type":"Services"
        }
    ],
    "sg:phone":"+1 616 459 1102",
    "sg:postcode":"49505",
    "sg:province":"MI",
    "sg:tags":[
        "electric",
        "contractor"
    ],
    "wof:name":"Anchor Industrial Electric Inc",
    "wof:placetype":"venue"
},
  "geometry": {"coordinates":[-85.62523400000001,42.97536],"type":"Point"}
}