{
  "type": "Feature",
  "properties": {
    "iso:country":"US",
    "sg:address":"1244 Portage St",
    "sg:city":"Kalamazoo",
    "sg:classifiers":[
        {
            "category":"Education",
            "subcategory":"Library",
            "type":"Public Place"
        }
    ],
    "sg:phone":"+1 269 345 4279",
    "sg:postcode":"49001",
    "sg:province":"MI",
    "wof:name":"Washington Square Library",
    "wof:placetype":"venue"
},
  "geometry": {"coordinates":[-85.569914,42.278786],"type":"Point"}
}