{
  "type": "Feature",
  "properties": {
    "iso:country":"US",
    "sg:address":"231 E Main St",
    "sg:city":"Harrison",
    "sg:classifiers":[
        {
            "category":"Shopping",
            "subcategory":"Jewelry",
            "type":"Retail Goods"
        }
    ],
    "sg:phone":"+1 989 539 2239",
    "sg:postcode":"48625",
    "sg:province":"MI",
    "sg:tags":[
        "jeweler"
    ],
    "wof:name":"Willer Custom Jewelry",
    "wof:placetype":"venue"
},
  "geometry": {"coordinates":[-84.796989,44.020076],"type":"Point"}
}