{
  "type": "Feature",
  "properties": {
    "iso:country":"US",
    "sg:address":"10969 Devils Lake Hwy",
    "sg:city":"Addison",
    "sg:classifiers":[
        {
            "category":"Retail",
            "subcategory":"Repair Shop",
            "type":"Services"
        }
    ],
    "sg:phone":"+1 517 547 5580",
    "sg:postcode":"49220",
    "sg:province":"MI",
    "sg:tags":[
        "sharpening"
    ],
    "wof:name":"L & L Sharpening Svc",
    "wof:placetype":"venue"
},
  "geometry": {"coordinates":[-84.298571,42.043649],"type":"Point"}
}