{
  "type": "Feature",
  "properties": {
    "iso:country":"US",
    "sg:address":"7981 Jackson Rd",
    "sg:city":"Ann Arbor",
    "sg:classifiers":[
        {
            "category":"Real Estate",
            "subcategory":"Architect",
            "type":"Services"
        }
    ],
    "sg:phone":"+1 734 424 0742",
    "sg:postcode":"48103",
    "sg:province":"MI",
    "sg:tags":[
        "architectural"
    ],
    "wof:name":"Phillips & Assoc Architects PC",
    "wof:placetype":"venue"
},
  "geometry": {"coordinates":[-83.896463,42.291577],"type":"Point"}
}