{
  "type": "Feature",
  "properties": {
    "iso:country":"US",
    "sg:address":"27069 Pinewood Dr",
    "sg:city":"Wixom",
    "sg:classifiers":[
        {
            "category":"Building & Trades",
            "subcategory":"Construction",
            "type":"Services"
        }
    ],
    "sg:phone":"+1 248 449 3565",
    "sg:postcode":"48393",
    "sg:province":"MI",
    "sg:tags":[
        "painter"
    ],
    "wof:name":"Lap Painting Corp",
    "wof:placetype":"venue"
},
  "geometry": {"coordinates":[-83.549741,42.495238],"type":"Point"}
}