{
  "type": "Feature",
  "properties": {
    "iso:country":"US",
    "sg:address":"309 S Catherine St",
    "sg:city":"Bay City",
    "sg:classifiers":[
        {
            "category":"Social Services",
            "type":"Services"
        }
    ],
    "sg:phone":"+1 989 894 5263",
    "sg:postcode":"48706",
    "sg:province":"MI",
    "sg:tags":[
        "foster",
        "adult",
        "care"
    ],
    "wof:name":"Jules Residential Care",
    "wof:placetype":"venue"
},
  "geometry": {"coordinates":[-83.901186,43.598944],"type":"Point"}
}