{
  "type": "Feature",
  "properties": {
    "iso:country":"US",
    "sg:address":"906 N Euclid Ave",
    "sg:city":"Bay City",
    "sg:classifiers":[
        {
            "category":"Restaurant",
            "type":"Food & Drink"
        }
    ],
    "sg:phone":"+1 989 686 0640",
    "sg:postcode":"48706",
    "sg:province":"MI",
    "wof:name":"KFC",
    "wof:placetype":"venue"
},
  "geometry": {"coordinates":[-83.914558,43.614191],"type":"Point"}
}