{
  "type": "Feature",
  "properties": {
    "iso:country":"US",
    "sg:address":"30100 Telegraph Rd",
    "sg:city":"Bingham Farms",
    "sg:classifiers":[
        {
            "category":"Building & Trades",
            "subcategory":"Construction",
            "type":"Services"
        }
    ],
    "sg:phone":"+1 248 540 8600",
    "sg:postcode":"48025",
    "sg:province":"MI",
    "sg:tags":[
        "contractor"
    ],
    "wof:name":"Adams Development Corporation",
    "wof:placetype":"venue"
},
  "geometry": {"coordinates":[-83.285202,42.507801],"type":"Point"}
}