{
  "type": "Feature",
  "properties": {
    "iso:country":"US",
    "sg:address":"117 N 2nd Ave",
    "sg:city":"Alpena",
    "sg:classifiers":[
        {
            "category":"Shopping",
            "subcategory":"Jewelry",
            "type":"Retail Goods"
        }
    ],
    "sg:phone":"+1 989 354 4303",
    "sg:postcode":"49707",
    "sg:province":"MI",
    "sg:tags":[
        "repair",
        "jeweler"
    ],
    "wof:name":"Kennedy's Jewelry Store",
    "wof:placetype":"venue"
},
  "geometry": {"coordinates":[-83.432513,45.062858],"type":"Point"}
}