{
  "type": "Feature",
  "properties": {
    "iso:country":"US",
    "sg:address":"8417 Pamela Dr",
    "sg:city":"Sterling Heights",
    "sg:classifiers":[
        {
            "category":"Building & Trades",
            "subcategory":"Construction",
            "type":"Services"
        }
    ],
    "sg:phone":"+1 586 978 9134",
    "sg:postcode":"48312",
    "sg:province":"MI",
    "sg:tags":[
        "contractor"
    ],
    "wof:name":"Isaman Gary J",
    "wof:placetype":"venue"
},
  "geometry": {"coordinates":[-83.025542,42.57102],"type":"Point"}
}