{
  "type": "Feature",
  "properties": {
    "iso:country":"US",
    "sg:address":"1212 Fendt Dr",
    "sg:city":"Howell",
    "sg:classifiers":[
        {
            "category":"Freight",
            "type":"Transportation"
        }
    ],
    "sg:phone":"+1 517 545 9093",
    "sg:postcode":"48843",
    "sg:province":"MI",
    "sg:tags":[
        "hauling",
        "trucking"
    ],
    "wof:name":"A & J Cartage Co",
    "wof:placetype":"venue"
},
  "geometry": {"coordinates":[-83.881308,42.579678],"type":"Point"}
}