{
  "type": "Feature",
  "properties": {
    "iso:country":"US",
    "sg:address":"907 Industrial Dr",
    "sg:city":"Tecumseh",
    "sg:classifiers":[
        {
            "category":"Manufacturing",
            "subcategory":"Rubber & Plastics",
            "type":"Manufacturing & Wholesale Goods"
        }
    ],
    "sg:phone":"+1 517 423 6595",
    "sg:postcode":"49286",
    "sg:province":"MI",
    "sg:website":"www.tc3net.com",
    "wof:name":"S F Mfg Inc",
    "wof:placetype":"venue"
},
  "geometry": {"coordinates":[-83.942487,41.991583],"type":"Point"}
}