{
  "type": "Feature",
  "properties": {
    "iso:country":"US",
    "sg:address":"7317 Linden Rd",
    "sg:city":"Swartz Creek",
    "sg:classifiers":[
        {
            "category":"Communications",
            "subcategory":"Film & Video Production",
            "type":"Services"
        }
    ],
    "sg:phone":"+1 810 655 8740",
    "sg:postcode":"48473",
    "sg:province":"MI",
    "sg:tags":[
        "motion"
    ],
    "wof:name":"Regimbal Productions",
    "wof:placetype":"venue"
},
  "geometry": {"coordinates":[-83.770293,42.922596],"type":"Point"}
}