{
  "type": "Feature",
  "properties": {
    "iso:country":"US",
    "sg:address":"21440 Universal Ave",
    "sg:city":"Eastpointe",
    "sg:classifiers":[
        {
            "category":"Education",
            "subcategory":"Special Training",
            "type":"Public Place"
        }
    ],
    "sg:phone":"+1 586 777 5180",
    "sg:postcode":"48021",
    "sg:province":"MI",
    "sg:tags":[
        "center"
    ],
    "wof:name":"Religious Education",
    "wof:placetype":"venue"
},
  "geometry": {"coordinates":[-82.95795200000001,42.456841],"type":"Point"}
}