{
  "type": "Feature",
  "properties": {
    "iso:country":"US",
    "sg:address":"521 S Dort Hwy",
    "sg:city":"Flint",
    "sg:phone":"+1 810 767 2130",
    "sg:postcode":"48503",
    "sg:province":"MI",
    "sg:tags":[
        "equipment",
        "supply"
    ],
    "wof:name":"Franklin Restaurant Equip Co",
    "wof:placetype":"venue"
},
  "geometry": {"coordinates":[-83.654692,43.020147],"type":"Point"}
}