{
  "type": "Feature",
  "properties": {
    "iso:country":"US",
    "sg:address":"3501 Lincoln Rd",
    "sg:city":"Hamilton",
    "sg:classifiers":[
        {
            "category":"Professional",
            "type":"Services"
        }
    ],
    "sg:phone":"+1 269 751 7468",
    "sg:postcode":"49419",
    "sg:province":"MI",
    "sg:tags":[
        "establishment"
    ],
    "wof:name":"Paytel Inc",
    "wof:placetype":"venue"
},
  "geometry": {"coordinates":[-86.00332299999999,42.675135],"type":"Point"}
}