{
  "type": "Feature",
  "properties": {
    "iso:country":"US",
    "sg:address":"216 S Washington Sq",
    "sg:city":"Lansing",
    "sg:classifiers":[
        {
            "category":"Deli",
            "type":"Food & Drink"
        }
    ],
    "sg:menulink":"http://www.allmenus.com/mi/lansing/127428-blimpie-subs--sandwiches/menu/",
    "sg:phone":"+1 517 374 0230",
    "sg:postcode":"48933",
    "sg:province":"MI",
    "sg:tags":[
        "wrap",
        "american",
        "sandwich"
    ],
    "wof:name":"Blimpie Subs & Sandwiches",
    "wof:placetype":"venue"
},
  "geometry": {"coordinates":[-84.552255,42.73243],"type":"Point"}
}