{
  "type": "Feature",
  "properties": {
    "iso:country":"US",
    "sg:address":"8445 48th Ave",
    "sg:city":"Hudsonville",
    "sg:classifiers":[
        {
            "category":"Wholesale",
            "subcategory":"Auto Parts",
            "type":"Manufacturing & Wholesale Goods"
        }
    ],
    "sg:phone":"+1 616 662 0930",
    "sg:postcode":"49426",
    "sg:province":"MI",
    "sg:tags":[
        "truck",
        "accessory"
    ],
    "wof:name":"Truck & Van Specialties",
    "wof:placetype":"venue"
},
  "geometry": {"coordinates":[-85.902908,42.926903],"type":"Point"}
}