{
  "type": "Feature",
  "properties": {
    "iso:country":"US",
    "sg:address":"8729 Kephart Ln",
    "sg:city":"Berrien Springs",
    "sg:classifiers":[
        {
            "category":"Social Services",
            "subcategory":"Adult Care",
            "type":"Services"
        }
    ],
    "sg:phone":"+1 269 471 9358",
    "sg:postcode":"49103",
    "sg:province":"MI",
    "sg:tags":[
        "residential"
    ],
    "wof:name":"Shimas Afc Home",
    "wof:placetype":"venue"
},
  "geometry": {"coordinates":[-86.340605,41.960357],"type":"Point"}
}