{
  "type": "Feature",
  "properties": {
    "iso:country":"US",
    "sg:address":"20947 Mack Ave",
    "sg:city":"Grosse Pointe",
    "sg:classifiers":[
        {
            "category":"Retail",
            "subcategory":"Animal Services",
            "type":"Services"
        }
    ],
    "sg:phone":"+1 313 882 8939",
    "sg:postcode":"48236",
    "sg:province":"MI",
    "sg:tags":[
        "pet",
        "salon"
    ],
    "wof:name":"Grosse Pointe Pet Salon",
    "wof:placetype":"venue"
},
  "geometry": {"coordinates":[-82.906091,42.447782],"type":"Point"}
}