{
  "type": "Feature",
  "properties": {
    "iso:country":"US",
    "sg:address":"45702 Purcell Dr",
    "sg:city":"Plymouth",
    "sg:classifiers":[
        {
            "category":"Professional",
            "subcategory":"Management & Consulting",
            "type":"Services"
        }
    ],
    "sg:phone":"+1 734 459 8861",
    "sg:postcode":"48170",
    "sg:province":"MI",
    "sg:tags":[
        "consultant"
    ],
    "wof:name":"Pine & Co",
    "wof:placetype":"venue"
},
  "geometry": {"coordinates":[-83.49121,42.36304],"type":"Point"}
}