{
  "type": "Feature",
  "properties": {
    "iso:country":"US",
    "sg:address":"4661 Korthase Rd",
    "sg:city":"Boyne City",
    "sg:classifiers":[
        {
            "category":"Building & Trades",
            "subcategory":"Construction",
            "type":"Services"
        }
    ],
    "sg:phone":"+1 231 582 7430",
    "sg:postcode":"49712",
    "sg:province":"MI",
    "sg:tags":[
        "painter"
    ],
    "wof:name":"Bricker Painting & Decorating",
    "wof:placetype":"venue"
},
  "geometry": {"coordinates":[-84.979038,45.102262],"type":"Point"}
}