{
  "type": "Feature",
  "properties": {
    "iso:country":"US",
    "sg:address":"2822 W Shore Dr",
    "sg:city":"Holland",
    "sg:classifiers":[
        {
            "category":"Insurance",
            "subcategory":"Insurance Agent",
            "type":"Services"
        }
    ],
    "sg:phone":"+1 616 396 2000",
    "sg:postcode":"49424",
    "sg:province":"MI",
    "wof:name":"Berends Hendricks Stuit Ins",
    "wof:placetype":"venue"
},
  "geometry": {"coordinates":[-86.09094899999999,42.825681],"type":"Point"}
}