{
  "type": "Feature",
  "properties": {
    "iso:country":"US",
    "sg:address":"10761 N 43rd St",
    "sg:city":"Augusta",
    "sg:classifiers":[
        {
            "category":"Professional",
            "type":"Services"
        }
    ],
    "sg:phone":"+1 269 731 2812",
    "sg:postcode":"49012",
    "sg:province":"MI",
    "wof:name":"Moon Harvest",
    "wof:placetype":"venue"
},
  "geometry": {"coordinates":[-85.351945,42.41404],"type":"Point"}
}