{
  "type": "Feature",
  "properties": {
    "iso:country":"US",
    "sg:address":"1464 Hawthorne Dr",
    "sg:city":"Saginaw",
    "sg:classifiers":[
        {
            "category":"Building & Trades",
            "subcategory":"Landscaping Services",
            "type":"Services"
        }
    ],
    "sg:phone":"+1 989 799 1004",
    "sg:postcode":"48638",
    "sg:province":"MI",
    "sg:tags":[
        "landscape",
        "contractor"
    ],
    "wof:name":"Tri-City Tree Svc & Landscpg",
    "wof:placetype":"venue"
},
  "geometry": {"coordinates":[-84.010875,43.429204],"type":"Point"}
}