{
  "type": "Feature",
  "properties": {
    "iso:country":"US",
    "sg:address":"26000 W 12 Mile Rd",
    "sg:city":"Southfield",
    "sg:classifiers":[
        {
            "category":"Professional",
            "subcategory":"Lawyer & Legal Services",
            "type":"Services"
        }
    ],
    "sg:phone":"+1 248 357 2222",
    "sg:postcode":"48034",
    "sg:province":"MI",
    "wof:name":"Bruetsch & Associates",
    "wof:placetype":"venue"
},
  "geometry": {"coordinates":[-83.30232100000001,42.500829],"type":"Point"}
}