{
  "type": "Feature",
  "properties": {
    "iso:country":"US",
    "sg:address":"57065 Gratiot Ave",
    "sg:city":"New Haven",
    "sg:classifiers":[
        {
            "category":"Food & Beverages",
            "subcategory":"Groceries & Convenience Stores",
            "type":"Retail Goods"
        }
    ],
    "sg:phone":"+1 586 749 0188",
    "sg:postcode":"48048",
    "sg:province":"MI",
    "wof:name":"Blue Water Oil",
    "wof:placetype":"venue"
},
  "geometry": {"coordinates":[-82.797105,42.719879],"type":"Point"}
}