{
  "type": "Feature",
  "properties": {
    "iso:country":"US",
    "sg:address":"3475 Plymouth Rd",
    "sg:city":"Ann Arbor",
    "sg:classifiers":[
        {
            "category":"Education",
            "subcategory":"College",
            "type":"Public Place"
        }
    ],
    "sg:phone":"+1 734 827 8040",
    "sg:postcode":"48105",
    "sg:province":"MI",
    "sg:tags":[
        "school",
        "law"
    ],
    "wof:name":"Ave Maria School of Law",
    "wof:placetype":"venue"
},
  "geometry": {"coordinates":[-83.69382400000001,42.304803],"type":"Point"}
}