{
  "type": "Feature",
  "properties": {
    "iso:country":"US",
    "sg:address":"2094 Sand Beach Rd",
    "sg:city":"Bad Axe",
    "sg:classifiers":[
        {
            "category":"Autos & Motor Vehicles",
            "subcategory":"Motorcycle Sales",
            "type":"Retail Goods"
        }
    ],
    "sg:phone":"+1 989 269 8450",
    "sg:postcode":"48413",
    "sg:province":"MI",
    "sg:tags":[
        "all",
        "terrain"
    ],
    "wof:name":"Albert's Land & Marine",
    "wof:placetype":"venue"
},
  "geometry": {"coordinates":[-82.937888,43.803848],"type":"Point"}
}