{
  "type": "Feature",
  "properties": {
    "iso:country":"US",
    "sg:address":"2030 Wickham St",
    "sg:city":"Royal Oak",
    "sg:classifiers":[
        {
            "category":"Shopping",
            "subcategory":"Computers & Home Electronics",
            "type":"Retail Goods"
        }
    ],
    "sg:phone":"+1 248 280 9430",
    "sg:postcode":"48073",
    "sg:province":"MI",
    "sg:tags":[
        "software"
    ],
    "wof:name":"Darwin Industries",
    "wof:placetype":"venue"
},
  "geometry": {"coordinates":[-83.167151,42.53945],"type":"Point"}
}