{
  "type": "Feature",
  "properties": {
    "iso:country":"US",
    "sg:address":"1550 Kingsway Ct",
    "sg:city":"Trenton",
    "sg:classifiers":[
        {
            "category":"Health Services",
            "subcategory":"Dentist",
            "type":"Services"
        }
    ],
    "sg:phone":"+1 734 671 8414",
    "sg:postcode":"48183",
    "sg:province":"MI",
    "sg:tags":[
        "cosmetic"
    ],
    "sg:website":"www.sonneandshapirodental.com",
    "wof:name":"Sonne & Shapiro Dental PC",
    "wof:placetype":"venue"
},
  "geometry": {"coordinates":[-83.191879,42.154933],"type":"Point"}
}