{
  "type": "Feature",
  "properties": {
    "iso:country":"US",
    "sg:address":"1381 Cleaver Rd",
    "sg:city":"Caro",
    "sg:classifiers":[
        {
            "category":"Social Services",
            "subcategory":"Child Care",
            "type":"Services"
        }
    ],
    "sg:phone":"+1 989 672 5437",
    "sg:postcode":"48723",
    "sg:province":"MI",
    "sg:tags":[
        "center"
    ],
    "wof:name":"Small Wonders",
    "wof:placetype":"venue"
},
  "geometry": {"coordinates":[-83.388122,43.509385],"type":"Point"}
}