{
  "type": "Feature",
  "properties": {
    "iso:country":"US",
    "sg:address":"5039 Huron Breeze Dr",
    "sg:city":"Au Gres",
    "sg:classifiers":[
        {
            "category":"Professional",
            "subcategory":"Business Services",
            "type":"Services"
        }
    ],
    "sg:phone":"+1 734 367 7250",
    "sg:postcode":"48703",
    "sg:province":"MI",
    "wof:name":"Rocky Mountain Mineral Svcs",
    "wof:placetype":"venue"
},
  "geometry": {"coordinates":[-83.600869,44.073191],"type":"Point"}
}