{
  "type": "Feature",
  "properties": {
    "iso:country":"US",
    "sg:address":"121 I and K St",
    "sg:city":"St Louis",
    "sg:classifiers":[
        {
            "category":"Education",
            "subcategory":"School",
            "type":"Public Place"
        }
    ],
    "sg:phone":"+1 989 681 3535",
    "sg:postcode":"48880",
    "sg:province":"MI",
    "wof:name":"Carrie Knause Elementary Schl",
    "wof:placetype":"venue"
},
  "geometry": {"coordinates":[-84.605468,43.41644],"type":"Point"}
}