{
  "type": "Feature",
  "properties": {
    "iso:country":"US",
    "sg:address":"2504 Monterey St",
    "sg:city":"Detroit",
    "sg:classifiers":[
        {
            "category":"Organizations",
            "subcategory":"Religious Organization",
            "type":"Services"
        }
    ],
    "sg:phone":"+1 313 868 0278",
    "sg:postcode":"48206",
    "sg:province":"MI",
    "sg:tags":[
        "churches-apostolic"
    ],
    "wof:name":"St Peters Holiness Church Of Jesus Chrirst",
    "wof:placetype":"venue"
},
  "geometry": {"coordinates":[-83.115095,42.385789],"type":"Point"}
}