{
  "type": "Feature",
  "properties": {
    "iso:country":"US",
    "sg:address":"27508 W 8 Mile Rd",
    "sg:city":"Farmington",
    "sg:classifiers":[
        {
            "category":"Professional",
            "subcategory":"Management & Consulting",
            "type":"Services"
        }
    ],
    "sg:phone":"+1 248 473 4480",
    "sg:postcode":"48336",
    "sg:province":"MI",
    "sg:tags":[
        "retail",
        "direct",
        "sales"
    ],
    "wof:name":"Peters & Oldham Co",
    "wof:placetype":"venue"
},
  "geometry": {"coordinates":[-83.318123,42.442247],"type":"Point"}
}