{
  "type": "Feature",
  "properties": {
    "iso:country":"US",
    "sg:address":"6140 N Bray Rd",
    "sg:city":"Flint",
    "sg:classifiers":[
        {
            "category":"Social Services",
            "subcategory":"Child Care",
            "type":"Services"
        }
    ],
    "sg:phone":"+1 810 760 1795",
    "sg:postcode":"48505",
    "sg:province":"MI",
    "sg:tags":[
        "start",
        "head"
    ],
    "wof:name":"Mott Hashbarger Head Start",
    "wof:placetype":"venue"
},
  "geometry": {"coordinates":[-83.656595,43.09906],"type":"Point"}
}