{
  "type": "Feature",
  "properties": {
    "iso:country":"US",
    "sg:address":"9976 US Hwy 12",
    "sg:city":"New Buffalo",
    "sg:classifiers":[
        {
            "category":"Building & Trades",
            "subcategory":"Construction",
            "type":"Services"
        }
    ],
    "sg:phone":"+1 269 469 0270",
    "sg:postcode":"49117",
    "sg:province":"MI",
    "sg:tags":[
        "maker",
        "cabinet"
    ],
    "wof:name":"Brychta's Wood Shed",
    "wof:placetype":"venue"
},
  "geometry": {"coordinates":[-86.69380200000001,41.799001],"type":"Point"}
}