{
  "type": "Feature",
  "properties": {
    "iso:country":"US",
    "sg:address":"7741 W Shippy Rd SW",
    "sg:city":"Fife Lake",
    "sg:classifiers":[
        {
            "category":"Education",
            "subcategory":"School",
            "type":"Public Place"
        }
    ],
    "sg:phone":"+1 231 369 4191",
    "sg:postcode":"49633",
    "sg:province":"MI",
    "wof:name":"Forest Area Community Supt Ofc",
    "wof:placetype":"venue"
},
  "geometry": {"coordinates":[-85.327411,44.5124],"type":"Point"}
}