{
  "type": "Feature",
  "properties": {
    "iso:country":"US",
    "sg:address":"113 N Mill St",
    "sg:city":"St Louis",
    "sg:classifiers":[
        {
            "category":"Personal",
            "subcategory":"Beauty Salon",
            "type":"Services"
        }
    ],
    "sg:phone":"+1 989 681 3573",
    "sg:postcode":"48880",
    "sg:province":"MI",
    "sg:tags":[
        "shop"
    ],
    "wof:name":"Diane's Hair Stylists",
    "wof:placetype":"venue"
},
  "geometry": {"coordinates":[-84.608817,43.409048],"type":"Point"}
}