{
  "type": "Feature",
  "properties": {
    "iso:country":"US",
    "sg:address":"1115 Washington Ave",
    "sg:city":"Grand Haven",
    "sg:classifiers":[
        {
            "category":"Food & Beverages",
            "subcategory":"Bakery",
            "type":"Retail Goods"
        }
    ],
    "sg:phone":"+1 616 842 4940",
    "sg:postcode":"49417",
    "sg:province":"MI",
    "sg:tags":[
        "baker"
    ],
    "wof:name":"Camburn's Home Bakery",
    "wof:placetype":"venue"
},
  "geometry": {"coordinates":[-86.215479,43.061037],"type":"Point"}
}