{
  "type": "Feature",
  "properties": {
    "iso:country":"US",
    "sg:address":"4360 Scott Carpenter Dr",
    "sg:city":"Jackson",
    "sg:classifiers":[
        {
            "category":"Building & Trades",
            "subcategory":"Construction",
            "type":"Services"
        }
    ],
    "sg:phone":"+1 517 788 9209",
    "sg:postcode":"49201",
    "sg:province":"MI",
    "sg:tags":[
        "general",
        "contractor"
    ],
    "wof:name":"Joy Construction",
    "wof:placetype":"venue"
},
  "geometry": {"coordinates":[-84.451286,42.302456],"type":"Point"}
}