{
  "type": "Feature",
  "properties": {
    "iso:country":"US",
    "sg:address":"77 Monroe Center St NW",
    "sg:city":"Grand Rapids",
    "sg:classifiers":[
        {
            "category":"Professional",
            "type":"Services"
        }
    ],
    "sg:phone":"+1 616 776 1234",
    "sg:postcode":"49503",
    "sg:province":"MI",
    "sg:tags":[
        "weather",
        "forecast"
    ],
    "wof:name":"Weather Forecast-Grand Rapids",
    "wof:placetype":"venue"
},
  "geometry": {"coordinates":[-85.670171,42.96486],"type":"Point"}
}