{
  "type": "Feature",
  "properties": {
    "iso:country":"US",
    "sg:address":"135 W Longwood Pl",
    "sg:city":"Detroit",
    "sg:classifiers":[
        {
            "category":"Professional",
            "subcategory":"Management & Consulting",
            "type":"Services"
        }
    ],
    "sg:phone":"+1 313 377 8070",
    "sg:postcode":"48203",
    "sg:province":"MI",
    "sg:tags":[
        "consultant",
        "education",
        "special"
    ],
    "wof:name":"My Mirror Myself",
    "wof:placetype":"venue"
},
  "geometry": {"coordinates":[-83.106436,42.421476],"type":"Point"}
}