{
  "type": "Feature",
  "properties": {
    "iso:country":"US",
    "sg:address":"1500 E Saginaw St",
    "sg:city":"Lansing",
    "sg:classifiers":[
        {
            "category":"Professional",
            "subcategory":"Research",
            "type":"Services"
        }
    ],
    "sg:phone":"+1 517 485 8333",
    "sg:postcode":"48906",
    "sg:province":"MI",
    "sg:tags":[
        "foundation",
        "philanthropic"
    ],
    "wof:name":"Greater Lansing Catholic Found",
    "wof:placetype":"venue"
},
  "geometry": {"coordinates":[-84.52764999999999,42.740902],"type":"Point"}
}