{
  "type": "Feature",
  "properties": {
    "iso:country":"US",
    "sg:address":"2745 W White Lake Dr",
    "sg:city":"Whitehall",
    "sg:classifiers":[
        {
            "category":"Social Services",
            "subcategory":"Adult Care",
            "type":"Services"
        }
    ],
    "sg:phone":"+1 231 893 5709",
    "sg:postcode":"49461",
    "sg:province":"MI",
    "sg:tags":[
        "residential"
    ],
    "wof:name":"Terra Nova",
    "wof:placetype":"venue"
},
  "geometry": {"coordinates":[-86.30871399999999,43.384495],"type":"Point"}
}