{
  "type": "Feature",
  "properties": {
    "iso:country":"US",
    "sg:address":"912 Military St",
    "sg:city":"Port Huron",
    "sg:classifiers":[
        {
            "category":"Manufacturing",
            "subcategory":"Printing",
            "type":"Manufacturing & Wholesale Goods"
        }
    ],
    "sg:phone":"+1 810 987 3160",
    "sg:postcode":"48060",
    "sg:province":"MI",
    "sg:tags":[
        "screen"
    ],
    "wof:name":"Cedar Hill Graphics",
    "wof:placetype":"venue"
},
  "geometry": {"coordinates":[-82.424458,42.974884],"type":"Point"}
}