{
  "type": "Feature",
  "properties": {
    "iso:country":"US",
    "sg:address":"1123 Lavender Ave",
    "sg:city":"Flint",
    "sg:classifiers":[
        {
            "category":"Banks & Credit Unions",
            "subcategory":"Bank",
            "type":"Services"
        }
    ],
    "sg:phone":"+1 810 252 6045",
    "sg:postcode":"48504",
    "sg:province":"MI",
    "sg:tags":[
        "loan",
        "real estate"
    ],
    "wof:name":"Marilyn Pitts",
    "wof:placetype":"venue"
},
  "geometry": {"coordinates":[-83.72956000000001,43.024509],"type":"Point"}
}