{
  "type": "Feature",
  "properties": {
    "iso:country":"US",
    "sg:address":"2900 Kellems Dr",
    "sg:city":"Hastings",
    "sg:classifiers":[
        {
            "category":"Social Services",
            "type":"Services"
        }
    ],
    "sg:phone":"+1 269 945 2801",
    "sg:postcode":"49058",
    "sg:province":"MI",
    "sg:tags":[
        "care",
        "center",
        "day"
    ],
    "wof:name":"Corner Stone Living Ctr",
    "wof:placetype":"venue"
},
  "geometry": {"coordinates":[-85.23365,42.61296],"type":"Point"}
}