{
  "type": "Feature",
  "properties": {
    "iso:country":"US",
    "sg:address":"77 W Sanilac Rd",
    "sg:city":"Sandusky",
    "sg:classifiers":[
        {
            "category":"Professional",
            "subcategory":"Accounting & Tax Preparation",
            "type":"Services"
        }
    ],
    "sg:phone":"+1 810 648 5083",
    "sg:postcode":"48471",
    "sg:province":"MI",
    "wof:name":"McGuire Bus Frm Accnting Servi",
    "wof:placetype":"venue"
},
  "geometry": {"coordinates":[-82.83141500000001,43.421191],"type":"Point"}
}