{
  "type": "Feature",
  "properties": {
    "iso:country":"US",
    "sg:address":"1017 Kensington Ave",
    "sg:city":"Grosse Pointe",
    "sg:classifiers":[
        {
            "category":"Building & Trades",
            "subcategory":"Construction",
            "type":"Services"
        }
    ],
    "sg:phone":"+1 313 417 8963",
    "sg:postcode":"48230",
    "sg:province":"MI",
    "sg:tags":[
        "residential",
        "nonresidential"
    ],
    "wof:name":"Boley Engineering and Cnstr",
    "wof:placetype":"venue"
},
  "geometry": {"coordinates":[-82.920929,42.381828],"type":"Point"}
}