{
  "type": "Feature",
  "properties": {
    "iso:country":"US",
    "sg:address":"30100 Ford Rd",
    "sg:city":"Garden City",
    "sg:classifiers":[
        {
            "category":"Manufacturing",
            "subcategory":"Signs",
            "type":"Manufacturing & Wholesale Goods"
        }
    ],
    "sg:phone":"+1 734 522 5382",
    "sg:postcode":"48135",
    "sg:province":"MI",
    "sg:tags":[
        "specialty",
        "mfg"
    ],
    "wof:name":"Vinyl Graphics Too",
    "wof:placetype":"venue"
},
  "geometry": {"coordinates":[-83.33928299999999,42.325482],"type":"Point"}
}