{
  "type": "Feature",
  "properties": {
    "iso:country":"US",
    "sg:address":"28801 66th St",
    "sg:city":"Bangor",
    "sg:classifiers":[
        {
            "category":"Building & Trades",
            "subcategory":"Landscaping Services",
            "type":"Services"
        }
    ],
    "sg:phone":"+1 269 427 1013",
    "sg:postcode":"49013",
    "sg:province":"MI",
    "sg:tags":[
        "tree"
    ],
    "wof:name":"Borden's Tree Svc",
    "wof:placetype":"venue"
},
  "geometry": {"coordinates":[-86.186756,42.314153],"type":"Point"}
}