{
  "type": "Feature",
  "properties": {
    "iso:country":"US",
    "sg:address":"651 Hoover Rd",
    "sg:city":"Barryton",
    "sg:classifiers":[
        {
            "category":"Retail",
            "subcategory":"Repair Shop",
            "type":"Services"
        }
    ],
    "sg:phone":"+1 989 382 7980",
    "sg:postcode":"49305",
    "sg:province":"MI",
    "wof:name":"R&R Horseshoeing & Trimming",
    "wof:placetype":"venue"
},
  "geometry": {"coordinates":[-85.098727,43.777198],"type":"Point"}
}