{
  "type": "Feature",
  "properties": {
    "iso:country":"US",
    "sg:address":"29069 Calahan Rd",
    "sg:city":"Roseville",
    "sg:classifiers":[
        {
            "category":"Retail",
            "subcategory":"Auto Repair",
            "type":"Services"
        }
    ],
    "sg:phone":"+1 586 772 8811",
    "sg:postcode":"48066",
    "sg:province":"MI",
    "wof:name":"Corvette Parts & Service Center",
    "wof:placetype":"venue"
},
  "geometry": {"coordinates":[-82.96350099999999,42.509499],"type":"Point"}
}