{
  "type": "Feature",
  "properties": {
    "iso:country":"US",
    "sg:address":"127 E Scott St",
    "sg:city":"Grand Ledge",
    "sg:classifiers":[
        {
            "category":"Professional",
            "subcategory":"Business Services",
            "type":"Services"
        }
    ],
    "sg:phone":"+1 517 622 8842",
    "sg:postcode":"48837",
    "sg:province":"MI",
    "sg:tags":[
        "appraiser"
    ],
    "wof:name":"Appraisal One Of Michigan",
    "wof:placetype":"venue"
},
  "geometry": {"coordinates":[-84.746566,42.751982],"type":"Point"}
}