{
  "type": "Feature",
  "properties": {
    "iso:country":"US",
    "sg:address":"1800 Crooks Rd",
    "sg:city":"Troy",
    "sg:classifiers":[
        {
            "category":"Organizations",
            "subcategory":"Professional Association",
            "type":"Services"
        }
    ],
    "sg:phone":"+1 248 244 8920",
    "sg:postcode":"48084",
    "sg:province":"MI",
    "sg:tags":[
        "business",
        "trade"
    ],
    "wof:name":"American Plastics Council",
    "wof:placetype":"venue"
},
  "geometry": {"coordinates":[-83.166781,42.553067],"type":"Point"}
}