{
  "type": "Feature",
  "properties": {
    "iso:country":"US",
    "sg:address":"1133 S Airport Rd W",
    "sg:city":"Traverse City",
    "sg:classifiers":[
        {
            "category":"Food & Beverages",
            "subcategory":"Bakery",
            "type":"Retail Goods"
        }
    ],
    "sg:phone":"+1 231 929 9866",
    "sg:postcode":"49686",
    "sg:province":"MI",
    "sg:tags":[
        "bagel"
    ],
    "wof:name":"Big Apple Bagels",
    "wof:placetype":"venue"
},
  "geometry": {"coordinates":[-85.59945399999999,44.73341],"type":"Point"}
}