{
  "type": "Feature",
  "properties": {
    "iso:country":"US",
    "sg:address":"24101 Wahl St",
    "sg:city":"Warren",
    "sg:classifiers":[
        {
            "category":"Manufacturing",
            "subcategory":"Metals",
            "type":"Manufacturing & Wholesale Goods"
        }
    ],
    "sg:phone":"+1 586 757 1800",
    "sg:postcode":"48089",
    "sg:province":"MI",
    "sg:tags":[
        "honing",
        "lapping"
    ],
    "wof:name":"Production Honing Co",
    "wof:placetype":"venue"
},
  "geometry": {"coordinates":[-82.992389,42.472729],"type":"Point"}
}