{
  "type": "Feature",
  "properties": {
    "iso:country":"US",
    "sg:address":"8417 N Blair Rd",
    "sg:city":"Breckenridge",
    "sg:classifiers":[
        {
            "category":"Home & Garden",
            "subcategory":"Furniture",
            "type":"Retail Goods"
        }
    ],
    "sg:phone":"+1 989 842 3450",
    "sg:postcode":"48615",
    "sg:province":"MI",
    "sg:tags":[
        "equipment",
        "kitchen",
        "cabinet"
    ],
    "wof:name":"Cabinet Shop",
    "wof:placetype":"venue"
},
  "geometry": {"coordinates":[-84.508432,43.412707],"type":"Point"}
}