{
  "type": "Feature",
  "properties": {
    "iso:country":"US",
    "sg:address":"3954 12 Mile Rd",
    "sg:city":"Berkley",
    "sg:classifiers":[
        {
            "category":"Shopping",
            "subcategory":"Crafts & Fabrics",
            "type":"Retail Goods"
        }
    ],
    "sg:phone":"+1 248 544 1590",
    "sg:postcode":"48072",
    "sg:province":"MI",
    "sg:tags":[
        "art",
        "supply"
    ],
    "sg:website":"munrocrafts.com/",
    "wof:name":"Munro Crafts",
    "wof:placetype":"venue"
},
  "geometry": {"coordinates":[-83.200067,42.502945],"type":"Point"}
}