{
  "type": "Feature",
  "properties": {
    "iso:country":"US",
    "sg:address":"46901 Grand River Ave",
    "sg:city":"Novi",
    "sg:classifiers":[
        {
            "category":"Wholesale",
            "subcategory":"Durable Goods & Equipment",
            "type":"Manufacturing & Wholesale Goods"
        }
    ],
    "sg:phone":"+1 248 348 0300",
    "sg:postcode":"48374",
    "sg:province":"MI",
    "sg:tags":[
        "representative",
        "manufacturer"
    ],
    "wof:name":"Garrett Burgess Inc",
    "wof:placetype":"venue"
},
  "geometry": {"coordinates":[-83.50593000000001,42.487473],"type":"Point"}
}