{
  "type": "Feature",
  "properties": {
    "iso:country":"US",
    "sg:address":"3585 N Lapeer Rd",
    "sg:city":"Lapeer",
    "sg:classifiers":[
        {
            "category":"Professional",
            "subcategory":"Business Services",
            "type":"Services"
        }
    ],
    "sg:phone":"+1 810 664 0498",
    "sg:postcode":"48446",
    "sg:province":"MI",
    "wof:name":"Running Randell D",
    "wof:placetype":"venue"
},
  "geometry": {"coordinates":[-83.310546,43.131998],"type":"Point"}
}