{
  "type": "Feature",
  "properties": {
    "iso:country":"US",
    "sg:address":"10460 N Holly Rd",
    "sg:city":"Holly",
    "sg:classifiers":[
        {
            "category":"Building & Trades",
            "subcategory":"Construction",
            "type":"Services"
        }
    ],
    "sg:phone":"+1 810 603 0723",
    "sg:postcode":"48442",
    "sg:province":"MI",
    "sg:tags":[
        "tile",
        "dealer"
    ],
    "wof:name":"Samassa Tile & Marble Inc",
    "wof:placetype":"venue"
},
  "geometry": {"coordinates":[-83.630503,42.872838],"type":"Point"}
}