{
  "type": "Feature",
  "properties": {
    "iso:country":"US",
    "sg:address":"6450 Air Cargo Dr SE",
    "sg:city":"Grand Rapids",
    "sg:classifiers":[
        {
            "category":"Professional",
            "subcategory":"Business Services",
            "type":"Services"
        }
    ],
    "sg:phone":"+1 616 575 4750",
    "sg:postcode":"49512",
    "sg:province":"MI",
    "wof:name":"Federal Express Vehicle M",
    "wof:placetype":"venue"
},
  "geometry": {"coordinates":[-85.501946,42.880327],"type":"Point"}
}