{
  "type": "Feature",
  "properties": {
    "iso:country":"US",
    "sg:address":"409 S Mitchell St",
    "sg:city":"Cadillac",
    "sg:classifiers":[
        {
            "category":"Autos & Motor Vehicles",
            "subcategory":"Fuel & Gas Station",
            "type":"Retail Goods"
        }
    ],
    "sg:phone":"+1 231 775 4051",
    "sg:postcode":"49601",
    "sg:province":"MI",
    "sg:tags":[
        "oil"
    ],
    "wof:name":"Cadillac Shell Mini Mart",
    "wof:placetype":"venue"
},
  "geometry": {"coordinates":[-85.397026,44.247521],"type":"Point"}
}