{
  "type": "Feature",
  "properties": {
    "iso:country":"US",
    "sg:address":"17184 Redford St",
    "sg:city":"Detroit",
    "sg:classifiers":[
        {
            "category":"Professional",
            "subcategory":"Management & Consulting",
            "type":"Services"
        }
    ],
    "sg:phone":"+1 313 543 2986",
    "sg:postcode":"48219",
    "sg:province":"MI",
    "sg:tags":[
        "college",
        "university",
        "co"
    ],
    "wof:name":"Innovative Teaching Solutions",
    "wof:placetype":"venue"
},
  "geometry": {"coordinates":[-83.261002,42.4151],"type":"Point"}
}