{
  "type": "Feature",
  "properties": {
    "iso:country":"US",
    "sg:address":"2540 12 Mile Rd",
    "sg:city":"Berkley",
    "sg:classifiers":[
        {
            "category":"Personal",
            "subcategory":"Beauty Salon",
            "type":"Services"
        }
    ],
    "sg:phone":"+1 248 398 4317",
    "sg:postcode":"48072",
    "sg:province":"MI",
    "sg:tags":[
        "shop"
    ],
    "wof:name":"Nail Salon",
    "wof:placetype":"venue"
},
  "geometry": {"coordinates":[-82.526597,42.621977],"type":"Point"}
}