{
  "type": "Feature",
  "properties": {
    "iso:country":"US",
    "sg:address":"2930 N Grand River Ave",
    "sg:city":"Lansing",
    "sg:classifiers":[
        {
            "category":"Banks & Credit Unions",
            "subcategory":"Bank",
            "type":"Services"
        }
    ],
    "sg:phone":"+1 517 321 1300",
    "sg:postcode":"48906",
    "sg:province":"MI",
    "wof:name":"Federal Employees Credit Union",
    "wof:placetype":"venue"
},
  "geometry": {"coordinates":[-84.572547,42.761694],"type":"Point"}
}