{
  "type": "Feature",
  "properties": {
    "iso:country":"US",
    "sg:address":"6505 Vaughan St",
    "sg:city":"Detroit",
    "sg:classifiers":[
        {
            "category":"Insurance",
            "subcategory":"Insurance Agent",
            "type":"Services"
        }
    ],
    "sg:phone":"+1 313 240 8932",
    "sg:postcode":"48228",
    "sg:province":"MI",
    "wof:name":"Dukes Investigation & SEC Inc",
    "wof:placetype":"venue"
},
  "geometry": {"coordinates":[-83.236501,42.337579],"type":"Point"}
}