{
  "type": "Feature",
  "properties": {
    "iso:country":"US",
    "sg:address":"555 Gidley Ave",
    "sg:city":"Grand Haven",
    "sg:classifiers":[
        {
            "category":"Manufacturing",
            "subcategory":"Printing",
            "type":"Manufacturing & Wholesale Goods"
        }
    ],
    "sg:phone":"+1 616 846 8550",
    "sg:postcode":"49417",
    "sg:province":"MI",
    "sg:tags":[
        "publisher"
    ],
    "wof:name":"Baker Trittin Concepts",
    "wof:placetype":"venue"
},
  "geometry": {"coordinates":[-86.19683999999999,43.055834],"type":"Point"}
}