{
  "type": "Feature",
  "properties": {
    "iso:country":"US",
    "sg:address":"121 E Montcalm St",
    "sg:city":"Pontiac",
    "sg:classifiers":[
        {
            "category":"Retail",
            "subcategory":"Auto Repair",
            "type":"Services"
        }
    ],
    "sg:phone":"+1 248 333 7845",
    "sg:postcode":"48342",
    "sg:province":"MI",
    "sg:tags":[
        "parts"
    ],
    "wof:name":"Motor Mart Service Center Inc",
    "wof:placetype":"venue"
},
  "geometry": {"coordinates":[-83.295281,42.656272],"type":"Point"}
}