{
  "type": "Feature",
  "properties": {
    "iso:country":"US",
    "sg:address":"1095 88th Ave",
    "sg:city":"Zeeland",
    "sg:classifiers":[
        {
            "category":"Farming",
            "subcategory":"Farm",
            "type":"Manufacturing & Wholesale Goods"
        }
    ],
    "sg:phone":"+1 616 772 2267",
    "sg:postcode":"49464",
    "sg:province":"MI",
    "sg:tags":[
        "crop",
        "general"
    ],
    "wof:name":"Duane Brink",
    "wof:placetype":"venue"
},
  "geometry": {"coordinates":[-86.00013,42.786494],"type":"Point"}
}