{
  "type": "Feature",
  "properties": {
    "iso:country":"US",
    "sg:address":"1296 Litchfield Rd",
    "sg:city":"Litchfield",
    "sg:phone":"+1 517 542 3547",
    "sg:postcode":"49252",
    "sg:province":"MI",
    "sg:tags":[
        "farm",
        "corn"
    ],
    "wof:name":"Albert Rossman",
    "wof:placetype":"venue"
},
  "geometry": {"coordinates":[-84.768412,42.043824],"type":"Point"}
}