{
  "type": "Feature",
  "properties": {
    "iso:country":"US",
    "sg:address":"2417 Avon St",
    "sg:city":"Saginaw",
    "sg:classifiers":[
        {
            "category":"Building & Trades",
            "subcategory":"Plumbing",
            "type":"Services"
        }
    ],
    "sg:phone":"+1 989 249 6489",
    "sg:postcode":"48602",
    "sg:province":"MI",
    "sg:tags":[
        "contractor"
    ],
    "wof:name":"Armstrong Inc",
    "wof:placetype":"venue"
},
  "geometry": {"coordinates":[-83.973023,43.441993],"type":"Point"}
}