{
  "type": "Feature",
  "properties": {
    "iso:country":"US",
    "sg:address":"2549 County Farm Rd",
    "sg:city":"Howell",
    "sg:classifiers":[
        {
            "category":"Manufacturing",
            "subcategory":"Signs",
            "type":"Manufacturing & Wholesale Goods"
        }
    ],
    "sg:phone":"+1 517 546 6958",
    "sg:postcode":"48843",
    "sg:province":"MI",
    "sg:tags":[
        "specialty",
        "mfg"
    ],
    "wof:name":"Gehringer Sign Company",
    "wof:placetype":"venue"
},
  "geometry": {"coordinates":[-83.970099,42.557406],"type":"Point"}
}