{
  "type": "Feature",
  "properties": {
    "iso:country":"US",
    "sg:address":"400 McCormick Dr",
    "sg:city":"Lapeer",
    "sg:classifiers":[
        {
            "category":"Manufacturing",
            "subcategory":"Metals",
            "type":"Manufacturing & Wholesale Goods"
        }
    ],
    "sg:phone":"+1 810 664 1816",
    "sg:postcode":"48446",
    "sg:province":"MI",
    "sg:tags":[
        "fabricated",
        "structural"
    ],
    "sg:website":"www.lapeerind.com",
    "wof:name":"Lapeer Industries Inc",
    "wof:placetype":"venue"
},
  "geometry": {"coordinates":[-83.311857,43.043653],"type":"Point"}
}