{
  "type": "Feature",
  "properties": {
    "iso:country":"US",
    "sg:address":"434 100th St SE",
    "sg:city":"Byron Center",
    "sg:classifiers":[
        {
            "category":"Social Services",
            "subcategory":"Child Care",
            "type":"Services"
        }
    ],
    "sg:phone":"+1 616 698 0365",
    "sg:postcode":"49315",
    "sg:province":"MI",
    "sg:tags":[
        "day",
        "provider"
    ],
    "wof:name":"Lynnette Bottenfield",
    "wof:placetype":"venue"
},
  "geometry": {"coordinates":[-85.64949799999999,42.78262],"type":"Point"}
}