{
  "type": "Feature",
  "properties": {
    "iso:country":"US",
    "sg:address":"15565 Northland Dr",
    "sg:city":"Southfield",
    "sg:classifiers":[
        {
            "category":"Sports & Exercise",
            "subcategory":"Gym",
            "type":"Entertainment"
        }
    ],
    "sg:phone":"+1 248 557 3870",
    "sg:postcode":"48075",
    "sg:province":"MI",
    "sg:tags":[
        "personal",
        "trainer"
    ],
    "wof:name":"Physique Spa",
    "wof:placetype":"venue"
},
  "geometry": {"coordinates":[-83.200982,42.447817],"type":"Point"}
}