{
  "type": "Feature",
  "properties": {
    "iso:country":"US",
    "sg:address":"601 Beech St",
    "sg:city":"Clare",
    "sg:classifiers":[
        {
            "category":"Professional",
            "subcategory":"Accounting & Tax Preparation",
            "type":"Services"
        }
    ],
    "sg:phone":"+1 989 386 3481",
    "sg:postcode":"48617",
    "sg:province":"MI",
    "sg:tags":[
        "accountant"
    ],
    "wof:name":"Weinlander Fitzhugh",
    "wof:placetype":"venue"
},
  "geometry": {"coordinates":[-84.77042,43.820564],"type":"Point"}
}