{
  "type": "Feature",
  "properties": {
    "iso:country":"US",
    "sg:address":"301 Maplewood St",
    "sg:city":"Greenville",
    "sg:classifiers":[
        {
            "category":"Personal",
            "subcategory":"Beauty Salon",
            "type":"Services"
        }
    ],
    "sg:phone":"+1 616 754 3617",
    "sg:postcode":"48838",
    "sg:province":"MI",
    "sg:tags":[
        "shop"
    ],
    "wof:name":"Hair",
    "wof:placetype":"venue"
},
  "geometry": {"coordinates":[-85.275729,43.179804],"type":"Point"}
}