{
  "type": "Feature",
  "properties": {
    "iso:country":"US",
    "sg:address":"17524 Sewel St",
    "sg:city":"Fraser",
    "sg:classifiers":[
        {
            "category":"Freight",
            "type":"Transportation"
        }
    ],
    "sg:phone":"+1 586 294 6774",
    "sg:postcode":"48026",
    "sg:province":"MI",
    "sg:tags":[
        "operator",
        "local",
        "trucking"
    ],
    "wof:name":"Advanced Trucking",
    "wof:placetype":"venue"
},
  "geometry": {"coordinates":[-82.94268099999999,42.540717],"type":"Point"}
}