{
  "type": "Feature",
  "properties": {
    "iso:country":"US",
    "sg:address":"4188 Old Forge Dr",
    "sg:city":"Fort Gratiot",
    "sg:classifiers":[
        {
            "category":"Retail",
            "subcategory":"Portrait Studio",
            "type":"Services"
        }
    ],
    "sg:phone":"+1 810 989 9801",
    "sg:postcode":"48059",
    "sg:province":"MI",
    "sg:tags":[
        "photographer"
    ],
    "wof:name":"Portrait Time",
    "wof:placetype":"venue"
},
  "geometry": {"coordinates":[-82.50175900000001,43.019806],"type":"Point"}
}