{
  "type": "Feature",
  "properties": {
    "iso:country":"US",
    "sg:address":"3 2 Mile Rd",
    "sg:city":"Athens",
    "sg:classifiers":[
        {
            "category":"Professional",
            "subcategory":"Business Services",
            "type":"Services"
        }
    ],
    "sg:phone":"+1 269 729 9295",
    "sg:postcode":"49011",
    "sg:province":"MI",
    "wof:name":"Village Satallite & Business",
    "wof:placetype":"venue"
},
  "geometry": {"coordinates":[-85.23560000000001,42.089937],"type":"Point"}
}