{
  "type": "Feature",
  "properties": {
    "iso:country":"US",
    "sg:address":"503 N 2nd Ave",
    "sg:city":"Alpena",
    "sg:classifiers":[
        {
            "category":"Restaurant",
            "type":"Food & Drink"
        }
    ],
    "sg:phone":"+1 989 354 8720",
    "sg:postcode":"49707",
    "sg:province":"MI",
    "wof:name":"Old Town Family Restaurant",
    "wof:placetype":"venue"
},
  "geometry": {"coordinates":[-83.42746099999999,45.065846],"type":"Point"}
}