{
  "type": "Feature",
  "properties": {
    "iso:country":"US",
    "sg:address":"5994 Saddlebag Lake Rd",
    "sg:city":"Lake Odessa",
    "sg:classifiers":[
        {
            "category":"Building & Trades",
            "subcategory":"Construction",
            "type":"Services"
        }
    ],
    "sg:phone":"+1 269 367 4955",
    "sg:postcode":"48849",
    "sg:province":"MI",
    "sg:tags":[
        "project"
    ],
    "wof:name":"Bam Bam Construction",
    "wof:placetype":"venue"
},
  "geometry": {"coordinates":[-85.074527,42.740793],"type":"Point"}
}