{
  "type": "Feature",
  "properties": {
    "iso:country":"US",
    "sg:address":"2185 E Wells Rd",
    "sg:city":"Caro",
    "sg:classifiers":[
        {
            "category":"Manufacturing",
            "subcategory":"Glass & Minerals",
            "type":"Manufacturing & Wholesale Goods"
        }
    ],
    "sg:phone":"+1 989 673 7338",
    "sg:postcode":"48723",
    "sg:province":"MI",
    "sg:tags":[
        "product",
        "ceramic"
    ],
    "sg:website":"www.ceramicsystems.com",
    "wof:name":"Ceramic Systems Inc",
    "wof:placetype":"venue"
},
  "geometry": {"coordinates":[-83.339153,43.424549],"type":"Point"}
}