{
  "type": "Feature",
  "properties": {
    "iso:country":"US",
    "sg:address":"912 W Front St",
    "sg:city":"Traverse City",
    "sg:classifiers":[
        {
            "category":"Food & Beverages",
            "subcategory":"Liquor & Beverages",
            "type":"Retail Goods"
        }
    ],
    "sg:phone":"+1 231 947 9312",
    "sg:postcode":"49684",
    "sg:province":"MI",
    "sg:tags":[
        "beer",
        "ale"
    ],
    "wof:name":"West Side Beverage",
    "wof:placetype":"venue"
},
  "geometry": {"coordinates":[-85.63941800000001,44.764096],"type":"Point"}
}