{
  "type": "Feature",
  "properties": {
    "iso:country":"US",
    "sg:address":"9343 Cherry Valley Ave SE",
    "sg:city":"Caledonia",
    "sg:classifiers":[
        {
            "category":"Personal",
            "subcategory":"Tanning Parlor",
            "type":"Services"
        }
    ],
    "sg:phone":"+1 616 536 2444",
    "sg:postcode":"49316",
    "sg:province":"MI",
    "wof:name":"Jamaican Sun",
    "wof:placetype":"venue"
},
  "geometry": {"coordinates":[-85.507127,42.794942],"type":"Point"}
}