{
  "type": "Feature",
  "properties": {
    "iso:country":"US",
    "sg:address":"3403 Sheringer Rd",
    "sg:city":"Muskegon",
    "sg:classifiers":[
        {
            "category":"Building & Trades",
            "subcategory":"Landscaping Services",
            "type":"Services"
        }
    ],
    "sg:phone":"+1 231 773 8122",
    "sg:postcode":"49444",
    "sg:province":"MI",
    "sg:tags":[
        "landscape",
        "contractor"
    ],
    "wof:name":"Ground Control Lawn & Landscp",
    "wof:placetype":"venue"
},
  "geometry": {"coordinates":[-86.163419,43.182988],"type":"Point"}
}