{
  "type": "Feature",
  "properties": {
    "iso:country":"US",
    "sg:address":"7011 W Vienna Rd",
    "sg:city":"Clio",
    "sg:classifiers":[
        {
            "category":"Restaurant",
            "type":"Food & Drink"
        }
    ],
    "sg:phone":"+1 810 639 2014",
    "sg:postcode":"48420",
    "sg:province":"MI",
    "wof:name":"Spirit Restaurant & Coney Isl",
    "wof:placetype":"venue"
},
  "geometry": {"coordinates":[-83.8164,43.177021],"type":"Point"}
}