{
  "type": "Feature",
  "properties": {
    "iso:country":"US",
    "sg:address":"605 S Parker St",
    "sg:city":"Marine City",
    "sg:classifiers":[
        {
            "category":"Real Estate",
            "subcategory":"Real Estate Agent",
            "type":"Services"
        }
    ],
    "sg:phone":"+1 810 765 4005",
    "sg:postcode":"48039",
    "sg:province":"MI",
    "sg:website":"www.frankrealestate.com",
    "wof:name":"Frank Real Estate",
    "wof:placetype":"venue"
},
  "geometry": {"coordinates":[-82.500332,42.71379],"type":"Point"}
}