{
  "type": "Feature",
  "properties": {
    "iso:country":"US",
    "sg:address":"21420 Greater Mack Ave",
    "sg:city":"Saint Clair Shores",
    "sg:classifiers":[
        {
            "category":"Professional",
            "subcategory":"Accounting & Tax Preparation",
            "type":"Services"
        }
    ],
    "sg:phone":"+1 586 772 8100",
    "sg:postcode":"48080",
    "sg:province":"MI",
    "sg:tags":[
        "accountant"
    ],
    "sg:website":"www.ghdcpa.com",
    "wof:name":"Godfrey Hammel Danneels & Co PC CPA",
    "wof:placetype":"venue"
},
  "geometry": {"coordinates":[-82.90450300000001,42.451],"type":"Point"}
}