{
  "type": "Feature",
  "properties": {
    "iso:country":"US",
    "sg:address":"14700 Brant Rd",
    "sg:city":"Saint Charles",
    "sg:classifiers":[
        {
            "category":"Professional",
            "subcategory":"Business Services",
            "type":"Services"
        }
    ],
    "sg:phone":"+1 989 585 3632",
    "sg:postcode":"48655",
    "sg:province":"MI",
    "wof:name":"Beckys Blankets",
    "wof:placetype":"venue"
},
  "geometry": {"coordinates":[-84.204838,43.259193],"type":"Point"}
}