{
  "type": "Feature",
  "properties": {
    "iso:country":"US",
    "sg:address":"6387 Pinebrook Ln",
    "sg:city":"Burton",
    "sg:classifiers":[
        {
            "category":"Building & Trades",
            "subcategory":"Construction",
            "type":"Services"
        }
    ],
    "sg:phone":"+1 810 743 1235",
    "sg:postcode":"48509",
    "sg:province":"MI",
    "sg:tags":[
        "house"
    ],
    "wof:name":"Dream House Custom Homes",
    "wof:placetype":"venue"
},
  "geometry": {"coordinates":[-83.579843,43.040394],"type":"Point"}
}