{
  "type": "Feature",
  "properties": {
    "iso:country":"US",
    "sg:address":"1249 Jolly Rd",
    "sg:city":"Okemos",
    "sg:classifiers":[
        {
            "category":"Professional",
            "subcategory":"Business Services",
            "type":"Services"
        }
    ],
    "sg:phone":"+1 517 349 5177",
    "sg:postcode":"48864",
    "sg:province":"MI",
    "wof:name":"Premiere Message-On-Hold Svc",
    "wof:placetype":"venue"
},
  "geometry": {"coordinates":[-84.393407,42.682907],"type":"Point"}
}