{
  "type": "Feature",
  "properties": {
    "iso:country":"US",
    "sg:address":"2900 Connon St",
    "sg:city":"Alpena",
    "sg:classifiers":[
        {
            "category":"Organizations",
            "subcategory":"Community Association",
            "type":"Services"
        }
    ],
    "sg:phone":"+1 989 356 9918",
    "sg:postcode":"49707",
    "sg:province":"MI",
    "sg:tags":[
        "club"
    ],
    "wof:name":"Veterans Of Foreign Wars",
    "wof:placetype":"venue"
},
  "geometry": {"coordinates":[-83.462091,45.042145],"type":"Point"}
}