{
  "type": "Feature",
  "properties": {
    "iso:country":"US",
    "sg:address":"23411 John R Rd",
    "sg:city":"Hazel Park",
    "sg:classifiers":[
        {
            "category":"Health Services",
            "subcategory":"Doctor",
            "type":"Services"
        }
    ],
    "sg:phone":"+1 248 399 8331",
    "sg:postcode":"48030",
    "sg:province":"MI",
    "sg:tags":[
        "specializing",
        "physician",
        "clinic",
        "internal",
        "medicine"
    ],
    "wof:name":"Hazel Park Medical Center",
    "wof:placetype":"venue"
},
  "geometry": {"coordinates":[-83.104192,42.465],"type":"Point"}
}