{
  "type": "Feature",
  "properties": {
    "iso:country":"US",
    "sg:address":"722 Joseph Kies St",
    "sg:city":"Clinton",
    "sg:classifiers":[
        {
            "category":"Building & Trades",
            "subcategory":"Construction",
            "type":"Services"
        }
    ],
    "sg:phone":"+1 517 456 6203",
    "sg:postcode":"49236",
    "sg:province":"MI",
    "sg:tags":[
        "handyman"
    ],
    "wof:name":"Dorr's Handyman",
    "wof:placetype":"venue"
},
  "geometry": {"coordinates":[-83.970265,42.065341],"type":"Point"}
}