{
  "type": "Feature",
  "properties": {
    "iso:country":"US",
    "sg:address":"23077 Greenfield Rd Ste 337",
    "sg:city":"Southfield",
    "sg:classifiers":[
        {
            "category":"Shopping",
            "subcategory":"Jewelry",
            "type":"Retail Goods"
        }
    ],
    "sg:phone":"+1 248 559 5192",
    "sg:postcode":"48075",
    "sg:province":"MI",
    "wof:name":"Paris Jewelry Design",
    "wof:placetype":"venue"
},
  "geometry": {"coordinates":[-83.20208100000001,42.460209],"type":"Point"}
}