{
  "type": "Feature",
  "properties": {
    "iso:country":"US",
    "sg:address":"3308 W Grand River Rd",
    "sg:city":"Owosso",
    "sg:classifiers":[
        {
            "category":"Professional",
            "subcategory":"Business Services",
            "type":"Services"
        }
    ],
    "sg:phone":"+1 989 725 6068",
    "sg:postcode":"48867",
    "sg:province":"MI",
    "sg:tags":[
        "interior",
        "consultant",
        "design",
        "decorator"
    ],
    "wof:name":"Thyme In The Country",
    "wof:placetype":"venue"
},
  "geometry": {"coordinates":[-84.227734,42.892318],"type":"Point"}
}