{
  "type": "Feature",
  "properties": {
    "iso:country":"US",
    "sg:address":"8626 Michigan Ave",
    "sg:city":"Detroit",
    "sg:classifiers":[
        {
            "category":"Restaurant",
            "type":"Food & Drink"
        }
    ],
    "sg:phone":"+1 313 581 1999",
    "sg:postcode":"48210",
    "sg:province":"MI",
    "sg:tags":[
        "pizza"
    ],
    "wof:name":"Fat Tony's Pizza",
    "wof:placetype":"venue"
},
  "geometry": {"coordinates":[-83.14819900000001,42.330037],"type":"Point"}
}