{
  "type": "Feature",
  "properties": {
    "iso:country":"US",
    "sg:address":"1715 Co Rd 492",
    "sg:city":"Marquette",
    "sg:classifiers":[
        {
            "category":"Building & Trades",
            "subcategory":"Landscaping Services",
            "type":"Services"
        }
    ],
    "sg:phone":"+1 906 225 0997",
    "sg:postcode":"49855",
    "sg:province":"MI",
    "sg:tags":[
        "landscape",
        "contractor"
    ],
    "wof:name":"Maki Dirt Works",
    "wof:placetype":"venue"
},
  "geometry": {"coordinates":[-87.425254,46.564047],"type":"Point"}
}