{
  "type": "Feature",
  "properties": {
    "iso:country":"US",
    "sg:address":"5460 Orleans Rd",
    "sg:city":"Orleans",
    "sg:classifiers":[
        {
            "category":"Shopping",
            "subcategory":"Gifts & Souvenirs",
            "type":"Retail Goods"
        }
    ],
    "sg:phone":"+1 616 761 3976",
    "sg:postcode":"48865",
    "sg:province":"MI",
    "sg:tags":[
        "party",
        "supply"
    ],
    "wof:name":"Pop Shop",
    "wof:placetype":"venue"
},
  "geometry": {"coordinates":[-85.135076,43.068258],"type":"Point"}
}