{
  "type": "Feature",
  "properties": {
    "iso:country":"US",
    "sg:address":"13900 Michigan Ave",
    "sg:city":"Dearborn",
    "sg:classifiers":[
        {
            "category":"Restaurant",
            "type":"Food & Drink"
        }
    ],
    "sg:phone":"+1 313 357 2630",
    "sg:postcode":"48126",
    "sg:province":"MI",
    "wof:name":"Ali Rayes",
    "wof:placetype":"venue"
},
  "geometry": {"coordinates":[-83.179604,42.321201],"type":"Point"}
}