{
  "type": "Feature",
  "properties": {
    "iso:country":"US",
    "sg:address":"2700 Cox Rd",
    "sg:city":"Saint Clair",
    "sg:classifiers":[
        {
            "category":"Real Estate",
            "subcategory":"Real Estate Operator",
            "type":"Services"
        }
    ],
    "sg:phone":"+1 810 329 9691",
    "sg:postcode":"48079",
    "sg:province":"MI",
    "sg:tags":[
        "mobile",
        "home",
        "site"
    ],
    "wof:name":"Saint Claire Place",
    "wof:placetype":"venue"
},
  "geometry": {"coordinates":[-82.50927900000001,42.827794],"type":"Point"}
}