{
  "type": "Feature",
  "properties": {
    "iso:country":"US",
    "sg:address":"1833 Gilbert St",
    "sg:city":"Saginaw",
    "sg:classifiers":[
        {
            "category":"Shopping",
            "type":"Retail Goods"
        }
    ],
    "sg:phone":"+1 989 793 2826",
    "sg:postcode":"48602",
    "sg:province":"MI",
    "sg:tags":[
        "merchandise"
    ],
    "wof:name":"Bob A Lou Rock",
    "wof:placetype":"venue"
},
  "geometry": {"coordinates":[-83.990824,43.398871],"type":"Point"}
}