{
  "type": "Feature",
  "properties": {
    "iso:country":"US",
    "sg:address":"27525 Michigan Ave",
    "sg:city":"Inkster",
    "sg:classifiers":[
        {
            "category":"Shopping",
            "subcategory":"Shoes",
            "type":"Retail Goods"
        }
    ],
    "sg:phone":"+1 313 563 0077",
    "sg:postcode":"48141",
    "sg:province":"MI",
    "sg:tags":[
        "store"
    ],
    "sg:website":"cherninshoeoutlet.com",
    "wof:name":"Chernin's Shoe Outlet",
    "wof:placetype":"venue"
},
  "geometry": {"coordinates":[-83.312161,42.293563],"type":"Point"}
}