{
  "type": "Feature",
  "properties": {
    "iso:country":"US",
    "sg:address":"22113 W Warren St",
    "sg:city":"Dearborn Heights",
    "sg:classifiers":[
        {
            "category":"Food & Beverages",
            "subcategory":"Groceries & Convenience Stores",
            "type":"Retail Goods"
        }
    ],
    "sg:phone":"+1 313 561 4280",
    "sg:postcode":"48127",
    "sg:province":"MI",
    "wof:name":"Lucky Star Party Shop",
    "wof:placetype":"venue"
},
  "geometry": {"coordinates":[-83.2556,42.341702],"type":"Point"}
}