{
  "type": "Feature",
  "properties": {
    "iso:country":"US",
    "sg:address":"466 E Remus Rd",
    "sg:city":"Mount Pleasant",
    "sg:classifiers":[
        {
            "category":"Arts & Performance",
            "subcategory":"Theater",
            "type":"Entertainment"
        }
    ],
    "sg:phone":"+1 989 560 5648",
    "sg:postcode":"48858",
    "sg:province":"MI",
    "sg:tags":[
        "group"
    ],
    "wof:name":"Interfayce",
    "wof:placetype":"venue"
},
  "geometry": {"coordinates":[-84.843165,43.596604],"type":"Point"}
}