{
  "type": "Feature",
  "properties": {
    "iso:country":"US",
    "sg:address":"1229 N Creyts Rd",
    "sg:city":"Lansing",
    "sg:classifiers":[
        {
            "category":"Shopping",
            "subcategory":"Clothing, Apparel, & Fashions",
            "type":"Retail Goods"
        }
    ],
    "sg:phone":"+1 517 323 7556",
    "sg:postcode":"48917",
    "sg:province":"MI",
    "wof:name":"Alterations Unlimited",
    "wof:placetype":"venue"
},
  "geometry": {"coordinates":[-84.64222599999999,42.747723],"type":"Point"}
}