{
  "type": "Feature",
  "properties": {
    "iso:country":"US",
    "sg:address":"6535 Carter Rd",
    "sg:city":"Spring Arbor",
    "sg:classifiers":[
        {
            "category":"Retail",
            "subcategory":"Animal Services",
            "type":"Services"
        }
    ],
    "sg:phone":"+1 517 750 3175",
    "sg:postcode":"49283",
    "sg:province":"MI",
    "wof:name":"Debbies Dog Grooming",
    "wof:placetype":"venue"
},
  "geometry": {"coordinates":[-84.53541,42.19913],"type":"Point"}
}