{
  "type": "Feature",
  "properties": {
    "iso:country":"US",
    "sg:address":"5009 Birkdale Dr",
    "sg:city":"Ann Arbor",
    "sg:classifiers":[
        {
            "category":"Professional",
            "subcategory":"Management & Consulting",
            "type":"Services"
        }
    ],
    "sg:phone":"+1 734 769 7536",
    "sg:postcode":"48103",
    "sg:province":"MI",
    "sg:tags":[
        "business"
    ],
    "wof:name":"Criscenti",
    "wof:placetype":"venue"
},
  "geometry": {"coordinates":[-83.82803800000001,42.279987],"type":"Point"}
}