{
  "type": "Feature",
  "properties": {
    "iso:country":"US",
    "sg:address":"23200 Hall Rd",
    "sg:city":"Trenton",
    "sg:classifiers":[
        {
            "category":"Professional",
            "subcategory":"Business Services",
            "type":"Services"
        }
    ],
    "sg:phone":"+1 734 675 1946",
    "sg:postcode":"48183",
    "sg:province":"MI",
    "wof:name":"Yankee Technologies Inc",
    "wof:placetype":"venue"
},
  "geometry": {"coordinates":[-83.246364,42.132876],"type":"Point"}
}