{
  "type": "Feature",
  "properties": {
    "iso:country":"US",
    "sg:address":"1290 Roslyn Rd",
    "sg:city":"Grosse Pointe",
    "sg:classifiers":[
        {
            "category":"Insurance",
            "subcategory":"Insurance Agent",
            "type":"Services"
        }
    ],
    "sg:phone":"+1 313 886 2922",
    "sg:postcode":"48236",
    "sg:province":"MI",
    "wof:name":"Donald J Parsons CLU Ic",
    "wof:placetype":"venue"
},
  "geometry": {"coordinates":[-82.89802299999999,42.446766],"type":"Point"}
}