{
  "type": "Feature",
  "properties": {
    "iso:country":"US",
    "sg:address":"6051 Sashabaw Rd",
    "sg:city":"Clarkston",
    "sg:classifiers":[
        {
            "category":"Organizations",
            "subcategory":"Religious Organization",
            "type":"Services"
        }
    ],
    "sg:phone":"+1 248 625 1344",
    "sg:postcode":"48346",
    "sg:province":"MI",
    "wof:name":"Bridgewood Church Assembly God",
    "wof:placetype":"venue"
},
  "geometry": {"coordinates":[-83.37893099999999,42.719104],"type":"Point"}
}