{
  "type": "Feature",
  "properties": {
    "iso:country":"US",
    "sg:address":"3275 Richfield Ct",
    "sg:city":"Flint",
    "sg:classifiers":[
        {
            "category":"Retail",
            "subcategory":"Car Wash",
            "type":"Services"
        }
    ],
    "sg:phone":"+1 810 736 5630",
    "sg:postcode":"48506",
    "sg:province":"MI",
    "wof:name":"Scrub-A-Dub Car Wash",
    "wof:placetype":"venue"
},
  "geometry": {"coordinates":[-83.612099,43.051998],"type":"Point"}
}