{
  "type": "Feature",
  "properties": {
    "iso:country":"US",
    "sg:address":"5169 Coldwater Rd",
    "sg:city":"Flint",
    "sg:classifiers":[
        {
            "category":"Building & Trades",
            "subcategory":"Plumbing",
            "type":"Services"
        }
    ],
    "sg:phone":"+1 810 720 5707",
    "sg:postcode":"48504",
    "sg:province":"MI",
    "sg:tags":[
        "conditioning",
        "air",
        "system",
        "contractor"
    ],
    "wof:name":"Parkes Heating & Cooling",
    "wof:placetype":"venue"
},
  "geometry": {"coordinates":[-83.779128,43.089617],"type":"Point"}
}