{
  "type": "Feature",
  "properties": {
    "iso:country":"US",
    "sg:address":"5832 Grand Haven Rd",
    "sg:city":"Muskegon",
    "sg:classifiers":[
        {
            "category":"Professional",
            "subcategory":"Business Services",
            "type":"Services"
        },
        {
            "category":"Professional",
            "subcategory":"Printing & Photocopies",
            "type":"Services"
        }
    ],
    "sg:phone":"+1 800 463 3339",
    "sg:postcode":"49441",
    "sg:province":"MI",
    "sg:tags":[
        "duplicating",
        "shipping",
        "copying"
    ],
    "sg:website":"http://www.fedex.com",
    "wof:name":"FedEx Express Ship Center",
    "wof:placetype":"venue"
},
  "geometry": {"coordinates":[-86.220617,43.146487],"type":"Point"}
}