{
  "type": "Feature",
  "properties": {
    "iso:country":"US",
    "sg:address":"2468 S Airport Rd W",
    "sg:city":"Traverse City",
    "sg:classifiers":[
        {
            "category":"Restaurant",
            "type":"Food & Drink"
        }
    ],
    "sg:menulink":"http://www.allmenus.com/mi/garfield/185874-mcdonalds/menu/",
    "sg:postcode":"49684",
    "sg:province":"MI",
    "sg:tags":[
        "burger",
        "american"
    ],
    "wof:name":"McDonald's",
    "wof:placetype":"venue"
},
  "geometry": {"coordinates":[-85.62477699999999,44.733567],"type":"Point"}
}