{
  "type": "Feature",
  "properties": {
    "iso:country":"US",
    "sg:address":"14236 Taft St",
    "sg:city":"Spring Lake",
    "sg:classifiers":[
        {
            "category":"Food & Beverages",
            "subcategory":"Groceries & Convenience Stores",
            "type":"Retail Goods"
        }
    ],
    "sg:phone":"+1 616 844 4465",
    "sg:postcode":"49456",
    "sg:province":"MI",
    "wof:name":"Classic Entrees Inc",
    "wof:placetype":"venue"
},
  "geometry": {"coordinates":[-86.14448899999999,43.102858],"type":"Point"}
}