{
  "type": "Feature",
  "properties": {
    "iso:country":"US",
    "sg:address":"4572 W US Hwy 10",
    "sg:city":"Ludington",
    "sg:classifiers":[
        {
            "category":"Wholesale",
            "subcategory":"Farm Supplies",
            "type":"Manufacturing & Wholesale Goods"
        }
    ],
    "sg:phone":"+1 231 843 1932",
    "sg:postcode":"49431",
    "sg:province":"MI",
    "wof:name":"Tractor Supply Co",
    "wof:placetype":"venue"
},
  "geometry": {"coordinates":[-86.39442200000001,43.955595],"type":"Point"}
}