{
  "type": "Feature",
  "properties": {
    "iso:country":"US",
    "sg:address":"9768 Deer Trl",
    "sg:city":"Haslett",
    "sg:classifiers":[
        {
            "category":"Building & Trades",
            "subcategory":"Construction",
            "type":"Services"
        }
    ],
    "sg:phone":"+1 517 655 2103",
    "sg:postcode":"48840",
    "sg:province":"MI",
    "sg:tags":[
        "house"
    ],
    "wof:name":"Tim Lawrence Construction",
    "wof:placetype":"venue"
},
  "geometry": {"coordinates":[-84.34175,42.774885],"type":"Point"}
}