{
  "type": "Feature",
  "properties": {
    "iso:country":"US",
    "sg:address":"7180 E Emery Rd",
    "sg:city":"Portland",
    "sg:classifiers":[
        {
            "category":"Retail",
            "subcategory":"Portrait Studio",
            "type":"Services"
        }
    ],
    "sg:phone":"+1 517 647 1817",
    "sg:postcode":"48875",
    "sg:province":"MI",
    "sg:tags":[
        "photo"
    ],
    "wof:name":"Lufkin Photography",
    "wof:placetype":"venue"
},
  "geometry": {"coordinates":[-84.934731,42.829577],"type":"Point"}
}