{
  "type": "Feature",
  "properties": {
    "iso:country":"US",
    "sg:address":"52 E Burdick St",
    "sg:city":"Oxford",
    "sg:classifiers":[
        {
            "category":"Government",
            "subcategory":"Post Office",
            "type":"Public Place"
        }
    ],
    "sg:phone":"+1 248 000 1111",
    "sg:postcode":"48371",
    "sg:province":"MI",
    "wof:name":"US Post Office",
    "wof:placetype":"venue"
},
  "geometry": {"coordinates":[-83.26288700000001,42.82481],"type":"Point"}
}