{
  "type": "Feature",
  "properties": {
    "iso:country":"US",
    "sg:address":"1789 S Garfield Ave",
    "sg:city":"Traverse City",
    "sg:classifiers":[
        {
            "category":"Retail",
            "subcategory":"Auto Rental",
            "type":"Services"
        }
    ],
    "sg:phone":"+1 231 933 7000",
    "sg:postcode":"49686",
    "sg:province":"MI",
    "sg:tags":[
        "renting",
        "automobile"
    ],
    "sg:website":"www.enterprise.com",
    "wof:name":"Enterprise Rent-A-Car",
    "wof:placetype":"venue"
},
  "geometry": {"coordinates":[-85.59527799999999,44.743288],"type":"Point"}
}