{
  "type": "Feature",
  "properties": {
    "iso:country":"US",
    "sg:address":"29160 Middle Crossing Rd",
    "sg:city":"Dowagiac",
    "sg:classifiers":[
        {
            "category":"Manufacturing",
            "subcategory":"Tools & Machinery",
            "type":"Manufacturing & Wholesale Goods"
        }
    ],
    "sg:phone":"+1 269 782 9154",
    "sg:postcode":"49047",
    "sg:province":"MI",
    "sg:tags":[
        "machine",
        "shop"
    ],
    "wof:name":"Innovative Fab",
    "wof:placetype":"venue"
},
  "geometry": {"coordinates":[-86.130324,42.009598],"type":"Point"}
}