{
  "type": "Feature",
  "properties": {
    "iso:country":"US",
    "sg:address":"2216 Medford Rd",
    "sg:city":"Ann Arbor",
    "sg:classifiers":[
        {
            "category":"Health Services",
            "subcategory":"Doctor",
            "type":"Services"
        }
    ],
    "sg:phone":"+1 734 971 7950",
    "sg:postcode":"48104",
    "sg:province":"MI",
    "sg:tags":[
        "urologist"
    ],
    "wof:name":"L H Wolin MD",
    "wof:placetype":"venue"
},
  "geometry": {"coordinates":[-83.71086200000001,42.255596],"type":"Point"}
}