{
  "type": "Feature",
  "properties": {
    "iso:country":"US",
    "sg:address":"283 Main St",
    "sg:city":"East Leroy",
    "sg:classifiers":[
        {
            "category":"Professional",
            "type":"Services"
        }
    ],
    "sg:phone":"+1 269 729 9114",
    "sg:postcode":"49051",
    "sg:province":"MI",
    "wof:name":"Dave Falnders Buldrs",
    "wof:placetype":"venue"
},
  "geometry": {"coordinates":[-85.221099,42.16618],"type":"Point"}
}