{
  "type": "Feature",
  "properties": {
    "iso:country":"US",
    "sg:address":"15 Washington St",
    "sg:city":"Monroe",
    "sg:classifiers":[
        {
            "category":"Restaurant",
            "type":"Food & Drink"
        }
    ],
    "sg:phone":"+1 734 384 1112",
    "sg:postcode":"48161",
    "sg:province":"MI",
    "wof:name":"Village Bistro",
    "wof:placetype":"venue"
},
  "geometry": {"coordinates":[-83.395967,41.916021],"type":"Point"}
}