{
  "type": "Feature",
  "properties": {
    "iso:country":"US",
    "sg:address":"18660 15 Mile Rd",
    "sg:city":"Fraser",
    "sg:classifiers":[
        {
            "category":"Home & Garden",
            "subcategory":"Hardware",
            "type":"Retail Goods"
        }
    ],
    "sg:phone":"+1 586 294 6812",
    "sg:postcode":"48026",
    "sg:province":"MI",
    "sg:tags":[
        "store"
    ],
    "wof:name":"Warren Pipe Supply Ace Hardware",
    "wof:placetype":"venue"
},
  "geometry": {"coordinates":[-82.930603,42.553902],"type":"Point"}
}