{
  "type": "Feature",
  "properties": {
    "iso:country":"US",
    "sg:address":"1031 N Edgeworth Ave",
    "sg:city":"Royal Oak",
    "sg:classifiers":[
        {
            "category":"Social Services",
            "subcategory":"Adult Care",
            "type":"Services"
        }
    ],
    "sg:phone":"+1 248 541 9006",
    "sg:postcode":"48067",
    "sg:province":"MI",
    "sg:tags":[
        "foster"
    ],
    "wof:name":"Pypkowski Adult Foster Care Hm",
    "wof:placetype":"venue"
},
  "geometry": {"coordinates":[-83.120197,42.499634],"type":"Point"}
}