{
  "type": "Feature",
  "properties": {
    "iso:country":"US",
    "sg:address":"783 Piper Blvd",
    "sg:city":"Detroit",
    "sg:classifiers":[
        {
            "category":"Professional",
            "type":"Services"
        }
    ],
    "sg:phone":"+1 313 870 7777",
    "sg:postcode":"48215",
    "sg:province":"MI",
    "wof:name":"Nu-Nique Corporation",
    "wof:placetype":"venue"
},
  "geometry": {"coordinates":[-82.948077,42.370362],"type":"Point"}
}