{
  "type": "Feature",
  "properties": {
    "iso:country":"US",
    "sg:address":"1824 Broadway St",
    "sg:city":"Bay City",
    "sg:classifiers":[
        {
            "category":"Recreation",
            "subcategory":"Arcade",
            "type":"Entertainment"
        }
    ],
    "sg:phone":"+1 989 892 8113",
    "sg:postcode":"48708",
    "sg:province":"MI",
    "sg:tags":[
        "operated",
        "photography",
        "coin",
        "amusement",
        "devices"
    ],
    "wof:name":"Harry's Amusement & Records",
    "wof:placetype":"venue"
},
  "geometry": {"coordinates":[-83.893822,43.570085],"type":"Point"}
}