{
  "type": "Feature",
  "properties": {
    "iso:country":"US",
    "sg:address":"4936 Lordon Ln",
    "sg:city":"Fremont",
    "sg:classifiers":[
        {
            "category":"Building & Trades",
            "subcategory":"Construction",
            "type":"Services"
        }
    ],
    "sg:phone":"+1 231 924 9147",
    "sg:postcode":"49412",
    "sg:province":"MI",
    "sg:tags":[
        "restoration",
        "cleaning",
        "patio",
        "deck"
    ],
    "wof:name":"National Power Washing Svc",
    "wof:placetype":"venue"
},
  "geometry": {"coordinates":[-85.981286,43.464482],"type":"Point"}
}