{
  "type": "Feature",
  "properties": {
    "iso:country":"US",
    "sg:address":"5332 W River Rd",
    "sg:city":"Muskegon",
    "sg:classifiers":[
        {
            "category":"Social Services",
            "subcategory":"Child Care",
            "type":"Services"
        }
    ],
    "sg:phone":"+1 231 719 2200",
    "sg:postcode":"49445",
    "sg:province":"MI",
    "sg:tags":[
        "day"
    ],
    "wof:name":"Four Sons Child Care",
    "wof:placetype":"venue"
},
  "geometry": {"coordinates":[-86.371331,43.298392],"type":"Point"}
}