{
  "type": "Feature",
  "properties": {
    "iso:country":"US",
    "sg:address":"1263 Leonard St NE",
    "sg:city":"Grand Rapids",
    "sg:classifiers":[
        {
            "category":"Restaurant",
            "type":"Food & Drink"
        }
    ],
    "sg:menulink":"http://www.allmenus.com/mi/grand-rapids/59192-hunan-chinese-restaurant/menu/",
    "sg:phone":"+1 616 458 0977",
    "sg:postcode":"49505",
    "sg:province":"MI",
    "sg:tags":[
        "asian",
        "chinese"
    ],
    "wof:name":"Hunan Chinese Restaurant",
    "wof:placetype":"venue"
},
  "geometry": {"coordinates":[-85.638419,42.984424],"type":"Point"}
}