{
  "type": "Feature",
  "properties": {
    "iso:country":"US",
    "sg:address":"83 Hillsdale St",
    "sg:city":"Hillsdale",
    "sg:classifiers":[
        {
            "category":"Personal",
            "subcategory":"Beauty Salon",
            "type":"Services"
        }
    ],
    "sg:phone":"+1 517 437 2164",
    "sg:postcode":"49242",
    "sg:province":"MI",
    "wof:name":"Attitudes",
    "wof:placetype":"venue"
},
  "geometry": {"coordinates":[-84.63157699999999,41.925521],"type":"Point"}
}