{
  "type": "Feature",
  "properties": {
    "iso:country":"US",
    "sg:address":"330 W 8 Mile Rd",
    "sg:city":"Ferndale",
    "sg:classifiers":[
        {
            "category":"Travel",
            "subcategory":"Hotels & Motels",
            "type":"Entertainment"
        }
    ],
    "sg:phone":"+1 248 548 6767",
    "sg:postcode":"48220",
    "sg:province":"MI",
    "sg:tags":[
        "operation"
    ],
    "wof:name":"Eight Wood Motel Inc",
    "wof:placetype":"venue"
},
  "geometry": {"coordinates":[-83.12800300000001,42.446634],"type":"Point"}
}