{
  "type": "Feature",
  "properties": {
    "iso:country":"US",
    "sg:address":"30695 Little Mack Ave",
    "sg:city":"Roseville",
    "sg:classifiers":[
        {
            "category":"Health Services",
            "subcategory":"Health Practitioner",
            "type":"Services"
        }
    ],
    "sg:phone":"+1 586 294 9030",
    "sg:postcode":"48066",
    "sg:province":"MI",
    "sg:tags":[
        "therapist",
        "physical"
    ],
    "wof:name":"Ortho Care Physical Therapy",
    "wof:placetype":"venue"
},
  "geometry": {"coordinates":[-82.909015,42.5235],"type":"Point"}
}