{
  "type": "Feature",
  "properties": {
    "iso:country":"US",
    "sg:address":"4600 W Kl Ave",
    "sg:city":"Kalamazoo",
    "sg:classifiers":[
        {
            "category":"Building & Trades",
            "subcategory":"Equipment Rental",
            "type":"Services"
        }
    ],
    "sg:phone":"+1 269 372 2020",
    "sg:postcode":"49006",
    "sg:province":"MI",
    "sg:tags":[
        "leasing"
    ],
    "sg:website":"www.oasishottubs.com",
    "wof:name":"Oasis Hot Tubs",
    "wof:placetype":"venue"
},
  "geometry": {"coordinates":[-85.64784400000001,42.278157],"type":"Point"}
}