{
  "type": "Feature",
  "properties": {
    "iso:country":"US",
    "sg:address":"11284 Grand Oak Dr",
    "sg:city":"Grand Blanc",
    "sg:classifiers":[
        {
            "category":"Real Estate",
            "subcategory":"Real Estate Operator",
            "type":"Services"
        }
    ],
    "sg:phone":"+1 810 694 7521",
    "sg:postcode":"48439",
    "sg:province":"MI",
    "sg:tags":[
        "apartment"
    ],
    "wof:name":"Country House Apartments",
    "wof:placetype":"venue"
},
  "geometry": {"coordinates":[-83.639,42.926701],"type":"Point"}
}