{
  "type": "Feature",
  "properties": {
    "iso:country":"US",
    "sg:address":"211 E Cedar Ave",
    "sg:city":"Gladwin",
    "sg:classifiers":[
        {
            "category":"Organizations",
            "subcategory":"Religious Organization",
            "type":"Services"
        }
    ],
    "sg:phone":"+1 989 426 9943",
    "sg:postcode":"48624",
    "sg:province":"MI",
    "sg:tags":[
        "church"
    ],
    "wof:name":"Saint Pauls Episcopal Church",
    "wof:placetype":"venue"
},
  "geometry": {"coordinates":[-84.484268,43.980557],"type":"Point"}
}