{
  "type": "Feature",
  "properties": {
    "iso:country":"US",
    "sg:address":"27461 Selkirk St",
    "sg:city":"Southfield",
    "sg:classifiers":[
        {
            "category":"Professional",
            "subcategory":"Business Services",
            "type":"Services"
        }
    ],
    "sg:phone":"+1 248 569 7911",
    "sg:postcode":"48076",
    "sg:province":"MI",
    "wof:name":"Karls Home Inspection",
    "wof:placetype":"venue"
},
  "geometry": {"coordinates":[-83.20809300000001,42.491906],"type":"Point"}
}