{
  "type": "Feature",
  "properties": {
    "iso:country":"US",
    "sg:address":"8801 Macomb St",
    "sg:city":"Grosse Ile",
    "sg:classifiers":[
        {
            "category":"Shopping",
            "subcategory":"Crafts & Fabrics",
            "type":"Retail Goods"
        }
    ],
    "sg:phone":"+1 734 675 8708",
    "sg:postcode":"48138",
    "sg:province":"MI",
    "sg:tags":[
        "sewing"
    ],
    "wof:name":"Island Needlework Studio",
    "wof:placetype":"venue"
},
  "geometry": {"coordinates":[-83.158148,42.130618],"type":"Point"}
}