{
  "type": "Feature",
  "properties": {
    "iso:country":"US",
    "sg:address":"572 Smith Ave",
    "sg:city":"Birmingham",
    "sg:classifiers":[
        {
            "category":"Building & Trades",
            "subcategory":"Construction",
            "type":"Services"
        }
    ],
    "sg:phone":"+1 248 646 9109",
    "sg:postcode":"48009",
    "sg:province":"MI",
    "sg:tags":[
        "house"
    ],
    "wof:name":"Phillip J Bartosik Builder",
    "wof:placetype":"venue"
},
  "geometry": {"coordinates":[-83.210748,42.533258],"type":"Point"}
}