{
  "type": "Feature",
  "properties": {
    "iso:country":"US",
    "sg:address":"67361 Co Rd 378",
    "sg:city":"Bangor",
    "sg:classifiers":[
        {
            "category":"Wholesale",
            "subcategory":"Machinery & Supplies",
            "type":"Manufacturing & Wholesale Goods"
        }
    ],
    "sg:phone":"+1 269 427 8086",
    "sg:postcode":"49013",
    "sg:province":"MI",
    "sg:tags":[
        "farm",
        "equipment"
    ],
    "wof:name":"Alfred Wood Agricultural Equip",
    "wof:placetype":"venue"
},
  "geometry": {"coordinates":[-86.195076,42.308229],"type":"Point"}
}