{
  "type": "Feature",
  "properties": {
    "iso:country":"US",
    "sg:address":"3068 W Klees Rd",
    "sg:city":"Stanton",
    "sg:classifiers":[
        {
            "category":"Retail",
            "subcategory":"Repair Shop",
            "type":"Services"
        }
    ],
    "sg:phone":"+1 989 831 4464",
    "sg:postcode":"48888",
    "sg:province":"MI",
    "wof:name":"T & D Power Washing",
    "wof:placetype":"venue"
},
  "geometry": {"coordinates":[-85.14447199999999,43.307294],"type":"Point"}
}