{
  "type": "Feature",
  "properties": {
    "iso:country":"US",
    "sg:address":"2749 Steamboat Springs Dr",
    "sg:city":"Rochester",
    "sg:classifiers":[
        {
            "category":"Professional",
            "subcategory":"Management & Consulting",
            "type":"Services"
        }
    ],
    "sg:phone":"+1 248 375 9507",
    "sg:postcode":"48309",
    "sg:province":"MI",
    "wof:name":"Multipass Intl Co",
    "wof:placetype":"venue"
},
  "geometry": {"coordinates":[-83.187144,42.683687],"type":"Point"}
}