{
  "type": "Feature",
  "properties": {
    "iso:country":"US",
    "sg:address":"1938 S Dort Hwy",
    "sg:city":"Flint",
    "sg:classifiers":[
        {
            "category":"Home & Garden",
            "subcategory":"Furniture",
            "type":"Retail Goods"
        }
    ],
    "sg:phone":"+1 810 239 1487",
    "sg:postcode":"48503",
    "sg:province":"MI",
    "sg:tags":[
        "mattress"
    ],
    "wof:name":"Mattress Warehouse Plus",
    "wof:placetype":"venue"
},
  "geometry": {"coordinates":[-83.654111,43.004458],"type":"Point"}
}