{
  "type": "Feature",
  "properties": {
    "iso:country":"US",
    "sg:address":"731 Griswold St",
    "sg:city":"Port Huron",
    "sg:classifiers":[
        {
            "category":"Health Services",
            "subcategory":"Clinic",
            "type":"Services"
        }
    ],
    "sg:phone":"+1 810 982 3560",
    "sg:postcode":"48060",
    "sg:province":"MI",
    "sg:tags":[
        "mental",
        "center"
    ],
    "wof:name":"Port Of Hopes Inc",
    "wof:placetype":"venue"
},
  "geometry": {"coordinates":[-82.42760199999999,42.967465],"type":"Point"}
}