{
  "type": "Feature",
  "properties": {
    "iso:country":"US",
    "sg:address":"515 Eden St",
    "sg:city":"Saint Louis",
    "sg:classifiers":[
        {
            "category":"Building & Trades",
            "subcategory":"Cleaning & Sanitation",
            "type":"Services"
        }
    ],
    "sg:phone":"+1 989 681 0596",
    "sg:postcode":"48880",
    "sg:province":"MI",
    "sg:tags":[
        "maintenance"
    ],
    "wof:name":"Pattons Commercial Cleaning",
    "wof:placetype":"venue"
},
  "geometry": {"coordinates":[-84.611019,43.416642],"type":"Point"}
}