{
  "type": "Feature",
  "properties": {
    "iso:country":"US",
    "sg:address":"8781 Monroe Rd",
    "sg:city":"Durand",
    "sg:classifiers":[
        {
            "category":"Real Estate",
            "subcategory":"Real Estate Operator",
            "type":"Services"
        }
    ],
    "sg:phone":"+1 989 288 2965",
    "sg:postcode":"48429",
    "sg:province":"MI",
    "sg:tags":[
        "building",
        "commercial"
    ],
    "wof:name":"Monroe Plaza Shopping Center",
    "wof:placetype":"venue"
},
  "geometry": {"coordinates":[-83.990717,42.921679],"type":"Point"}
}