{
  "type": "Feature",
  "properties": {
    "iso:country":"US",
    "sg:address":"17418 W 10 Mile Rd",
    "sg:city":"Southfield",
    "sg:classifiers":[
        {
            "category":"Professional",
            "subcategory":"Lawyer & Legal Services",
            "type":"Services"
        }
    ],
    "sg:phone":"+1 248 552 0757",
    "sg:postcode":"48075",
    "sg:province":"MI",
    "wof:name":"Avant Orlando Atty",
    "wof:placetype":"venue"
},
  "geometry": {"coordinates":[-83.21700300000001,42.473598],"type":"Point"}
}