{
  "type": "Feature",
  "properties": {
    "iso:country":"US",
    "sg:address":"22237 Greater Mack Ave",
    "sg:city":"St Clair Shores",
    "sg:classifiers":[
        {
            "category":"Health Services",
            "subcategory":"Health Practitioner",
            "type":"Services"
        }
    ],
    "sg:phone":"+1 586 447 6121",
    "sg:postcode":"48080",
    "sg:province":"MI",
    "sg:tags":[
        "therapist",
        "physical"
    ],
    "wof:name":"Complete Fitness Rehab",
    "wof:placetype":"venue"
},
  "geometry": {"coordinates":[-82.901495,42.45821],"type":"Point"}
}