{
  "type": "Feature",
  "properties": {
    "iso:country":"US",
    "sg:address":"5248 W Gannon Rd",
    "sg:city":"Fowlerville",
    "sg:classifiers":[
        {
            "category":"Personal",
            "subcategory":"Beauty Salon",
            "type":"Services"
        }
    ],
    "sg:phone":"+1 517 223 9873",
    "sg:postcode":"48836",
    "sg:province":"MI",
    "sg:tags":[
        "manicurist"
    ],
    "wof:name":"Custom Nails",
    "wof:placetype":"venue"
},
  "geometry": {"coordinates":[-84.021998,42.743826],"type":"Point"}
}