{
  "type": "Feature",
  "properties": {
    "iso:country":"US",
    "sg:address":"1513 Quarry Ave NW",
    "sg:city":"Grand Rapids",
    "sg:classifiers":[
        {
            "category":"Recreation",
            "type":"Entertainment"
        }
    ],
    "sg:phone":"+1 616 458 1109",
    "sg:postcode":"49504",
    "sg:province":"MI",
    "sg:tags":[
        "club",
        "private"
    ],
    "wof:name":"Saint Grg-Pter Puls Aid Societ",
    "wof:placetype":"venue"
},
  "geometry": {"coordinates":[-85.68140200000001,42.99195],"type":"Point"}
}