{
  "type": "Feature",
  "properties": {
    "iso:country":"US",
    "sg:address":"120 E Mason St",
    "sg:city":"Owosso",
    "sg:classifiers":[
        {
            "category":"Retail",
            "subcategory":"Funeral Services",
            "type":"Services"
        }
    ],
    "sg:phone":"+1 989 723 5234",
    "sg:postcode":"48867",
    "sg:province":"MI",
    "sg:website":"www.nelson-house.com",
    "wof:name":"Nelson-House Funeral Homes",
    "wof:placetype":"venue"
},
  "geometry": {"coordinates":[-84.170423,42.999398],"type":"Point"}
}