{
  "type": "Feature",
  "properties": {
    "iso:country":"US",
    "sg:address":"7950 Ashbrook Dr",
    "sg:city":"Haslett",
    "sg:classifiers":[
        {
            "category":"Building & Trades",
            "subcategory":"Landscaping Services",
            "type":"Services"
        }
    ],
    "sg:phone":"+1 517 339 2573",
    "sg:postcode":"48840",
    "sg:province":"MI",
    "wof:name":"Four Seasons Lawn Snow Removal",
    "wof:placetype":"venue"
},
  "geometry": {"coordinates":[-84.404752,42.771847],"type":"Point"}
}