{
  "type": "Feature",
  "properties": {
    "iso:country":"US",
    "sg:address":"1329 S Division St",
    "sg:city":"Traverse City",
    "sg:classifiers":[
        {
            "category":"Building & Trades",
            "subcategory":"Construction",
            "type":"Services"
        }
    ],
    "sg:phone":"+1 231 922 4890",
    "sg:postcode":"49684",
    "sg:province":"MI",
    "sg:tags":[
        "shelter"
    ],
    "wof:name":"Goodwill Inn Emergency Shelter",
    "wof:placetype":"venue"
},
  "geometry": {"coordinates":[-85.63498,44.750957],"type":"Point"}
}