{
  "type": "Feature",
  "properties": {
    "iso:country":"US",
    "sg:address":"44272 N Groesbeck Hwy",
    "sg:city":"Clinton Twp",
    "sg:classifiers":[
        {
            "category":"Manufacturing",
            "subcategory":"Printing",
            "type":"Manufacturing & Wholesale Goods"
        }
    ],
    "sg:phone":"+1 586 463 2301",
    "sg:postcode":"48036",
    "sg:province":"MI",
    "sg:tags":[
        "catalog",
        "compiler"
    ],
    "sg:website":"www.macombprinting.com",
    "wof:name":"Macomb Printing Inc",
    "wof:placetype":"venue"
},
  "geometry": {"coordinates":[-82.87877400000001,42.623377],"type":"Point"}
}