{
  "type": "Feature",
  "properties": {
    "iso:country":"US",
    "sg:address":"43678 N Gratiot Ave",
    "sg:city":"Clinton Twp",
    "sg:classifiers":[
        {
            "category":"Home & Garden",
            "subcategory":"Building Materials",
            "type":"Retail Goods"
        }
    ],
    "sg:phone":"+1 586 468 9787",
    "sg:postcode":"48036",
    "sg:province":"MI",
    "sg:tags":[
        "door"
    ],
    "sg:website":"www.fjfdoor.com",
    "wof:name":"FJF Door Sales Co",
    "wof:placetype":"venue"
},
  "geometry": {"coordinates":[-82.86796699999999,42.615566],"type":"Point"}
}