{
  "type": "Feature",
  "properties": {
    "iso:country":"US",
    "sg:address":"7070 Bowerman Rd",
    "sg:city":"Horton",
    "sg:classifiers":[
        {
            "category":"Real Estate",
            "subcategory":"Real Estate Operator",
            "type":"Services"
        }
    ],
    "sg:phone":"+1 517 563 8962",
    "sg:postcode":"49246",
    "sg:province":"MI",
    "sg:tags":[
        "dwelling"
    ],
    "wof:name":"Michigan Framers Inc",
    "wof:placetype":"venue"
},
  "geometry": {"coordinates":[-84.543852,42.160007],"type":"Point"}
}