{
  "type": "Feature",
  "properties": {
    "iso:country":"US",
    "sg:address":"3340 E Lake Lansing Rd",
    "sg:city":"East Lansing",
    "sg:classifiers":[
        {
            "category":"Restaurant",
            "type":"Food & Drink"
        }
    ],
    "sg:menulink":"http://www.allmenus.com/mi/meridian/86773-little-caesars-pizza/menu/",
    "sg:phone":"+1 517 351 0505",
    "sg:postcode":"48823",
    "sg:province":"MI",
    "sg:tags":[
        "american",
        "pizza"
    ],
    "wof:name":"Little Caesar's Pizza",
    "wof:placetype":"venue"
},
  "geometry": {"coordinates":[-84.475773,42.758349],"type":"Point"}
}