{
  "type": "Feature",
  "properties": {
    "iso:country":"US",
    "sg:address":"150 Plymouth Rd",
    "sg:city":"Plymouth",
    "sg:classifiers":[
        {
            "category":"Professional",
            "subcategory":"Computer Services",
            "type":"Services"
        }
    ],
    "sg:phone":"+1 734 451 1229",
    "sg:postcode":"48170",
    "sg:province":"MI",
    "sg:tags":[
        "consultant",
        "internet"
    ],
    "wof:name":"Radiant Communications",
    "wof:placetype":"venue"
},
  "geometry": {"coordinates":[-83.460183,42.376618],"type":"Point"}
}