{
  "type": "Feature",
  "properties": {
    "iso:country":"US",
    "sg:address":"741 E 9 Mile Rd",
    "sg:city":"Ferndale",
    "sg:classifiers":[
        {
            "category":"Food & Beverages",
            "subcategory":"Bakery",
            "type":"Retail Goods"
        }
    ],
    "sg:phone":"+1 248 545 7295",
    "sg:postcode":"48220",
    "sg:province":"MI",
    "sg:tags":[
        "donut",
        "doughnut"
    ],
    "wof:name":"Apple Fritter",
    "wof:placetype":"venue"
},
  "geometry": {"coordinates":[-83.12359600000001,42.460999],"type":"Point"}
}