{
  "type": "Feature",
  "properties": {
    "iso:country":"US",
    "sg:address":"3180 Racquet Club Dr",
    "sg:city":"Traverse City",
    "sg:classifiers":[
        {
            "category":"Banks & Credit Unions",
            "subcategory":"Bank",
            "type":"Services"
        }
    ],
    "sg:phone":"+1 231 941 5896",
    "sg:postcode":"49684",
    "sg:province":"MI",
    "sg:tags":[
        "loan"
    ],
    "wof:name":"Premier Mortgage Funding Inc",
    "wof:placetype":"venue"
},
  "geometry": {"coordinates":[-85.61739900000001,44.732341],"type":"Point"}
}