{
  "type": "Feature",
  "properties": {
    "iso:country":"US",
    "sg:address":"7105 Crosswinds Dr",
    "sg:city":"Swartz Creek",
    "sg:classifiers":[
        {
            "category":"Professional",
            "subcategory":"Business Services",
            "type":"Services"
        }
    ],
    "sg:phone":"+1 810 630 2259",
    "sg:postcode":"48473",
    "sg:province":"MI",
    "wof:name":"1st Class Home Inspections",
    "wof:placetype":"venue"
},
  "geometry": {"coordinates":[-83.815377,42.988566],"type":"Point"}
}