{
  "type": "Feature",
  "properties": {
    "iso:country":"US",
    "sg:address":"401 W Flint St",
    "sg:city":"Davison",
    "sg:classifiers":[
        {
            "category":"Personal",
            "subcategory":"Massage",
            "type":"Services"
        }
    ],
    "sg:phone":"+1 810 658 3648",
    "sg:postcode":"48423",
    "sg:province":"MI",
    "wof:name":"Massage Therapy Clinic",
    "wof:placetype":"venue"
},
  "geometry": {"coordinates":[-83.523201,43.034401],"type":"Point"}
}