{
  "type": "Feature",
  "properties": {
    "iso:country":"US",
    "sg:address":"63 Touraine Rd",
    "sg:city":"Grosse Pointe",
    "sg:classifiers":[
        {
            "category":"Professional",
            "subcategory":"Business Services",
            "type":"Services"
        }
    ],
    "sg:phone":"+1 313 882 3759",
    "sg:postcode":"48236",
    "sg:province":"MI",
    "wof:name":"Molloy & Co Inc",
    "wof:placetype":"venue"
},
  "geometry": {"coordinates":[-82.894007,42.403966],"type":"Point"}
}