{
  "type": "Feature",
  "properties": {
    "iso:country":"US",
    "sg:address":"21005 Farmington Rd",
    "sg:city":"Farmington Hills",
    "sg:classifiers":[
        {
            "category":"Insurance",
            "subcategory":"Insurance Agent",
            "type":"Services"
        }
    ],
    "sg:phone":"+1 248 477 1680",
    "sg:postcode":"48336",
    "sg:province":"MI",
    "wof:name":"Galvin Planning Svc",
    "wof:placetype":"venue"
},
  "geometry": {"coordinates":[-83.375536,42.444047],"type":"Point"}
}