{
  "type": "Feature",
  "properties": {
    "iso:country":"US",
    "sg:address":"515 S Garfield Ave",
    "sg:city":"Traverse City",
    "sg:classifiers":[
        {
            "category":"Professional",
            "subcategory":"Printing & Photocopies",
            "type":"Services"
        }
    ],
    "sg:phone":"+1 231 946 3260",
    "sg:postcode":"49686",
    "sg:province":"MI",
    "sg:tags":[
        "duplicating",
        "copying"
    ],
    "wof:name":"Copy Center KWIK Print",
    "wof:placetype":"venue"
},
  "geometry": {"coordinates":[-85.595204,44.758052],"type":"Point"}
}