{
  "type": "Feature",
  "properties": {
    "iso:country":"US",
    "sg:address":"1705 Oak St",
    "sg:city":"Niles",
    "sg:classifiers":[
        {
            "category":"Personal",
            "subcategory":"Beauty Salon",
            "type":"Services"
        }
    ],
    "sg:phone":"+1 269 684 6848",
    "sg:postcode":"49120",
    "sg:province":"MI",
    "wof:name":"Bryann's Hair Design",
    "wof:placetype":"venue"
},
  "geometry": {"coordinates":[-86.234303,41.826797],"type":"Point"}
}