{
  "type": "Feature",
  "properties": {
    "iso:country":"US",
    "sg:address":"1420 N Clare Ave",
    "sg:city":"Harrison",
    "sg:classifiers":[
        {
            "category":"Real Estate",
            "subcategory":"Developer",
            "type":"Services"
        }
    ],
    "sg:phone":"+1 989 539 2646",
    "sg:postcode":"48625",
    "sg:province":"MI",
    "wof:name":"Red Oak Development",
    "wof:placetype":"venue"
},
  "geometry": {"coordinates":[-84.78783300000001,44.00547],"type":"Point"}
}