{
  "type": "Feature",
  "properties": {
    "iso:country":"US",
    "sg:address":"41550 Grand River Ave",
    "sg:city":"Novi",
    "sg:classifiers":[
        {
            "category":"Recreation",
            "subcategory":"Amusement Park",
            "type":"Entertainment"
        },
        {
            "category":"Personal",
            "type":"Services"
        }
    ],
    "sg:phone":"248788890",
    "sg:postcode":"48375",
    "sg:province":"MI",
    "sg:tags":[
        "party",
        "planning",
        "event"
    ],
    "sg:website":"www.whirlyballwest.com",
    "wof:name":"Whirlyball Novi",
    "wof:placetype":"venue"
},
  "geometry": {"coordinates":[-83.45693,42.47667],"type":"Point"}
}