{
  "type": "Feature",
  "properties": {
    "iso:country":"US",
    "sg:address":"35705 Warren Rd",
    "sg:city":"Westland",
    "sg:classifiers":[
        {
            "category":"Shopping",
            "subcategory":"Clothing, Apparel, & Fashions",
            "type":"Retail Goods"
        }
    ],
    "sg:phone":"+1 734 728 5333",
    "sg:postcode":"48185",
    "sg:province":"MI",
    "sg:tags":[
        "accessory",
        "clothing",
        "women's"
    ],
    "sg:website":"www.dots.com",
    "wof:name":"Dots Inc",
    "wof:placetype":"venue"
},
  "geometry": {"coordinates":[-83.395203,42.3386],"type":"Point"}
}