{
  "type": "Feature",
  "properties": {
    "iso:country":"US",
    "sg:address":"10816 Fullerton St",
    "sg:city":"Detroit",
    "sg:classifiers":[
        {
            "category":"Retail",
            "subcategory":"Laundry & Dry Cleaning",
            "type":"Services"
        }
    ],
    "sg:phone":"+1 313 834 2800",
    "sg:postcode":"48238",
    "sg:province":"MI",
    "sg:tags":[
        "drycleaning",
        "plant"
    ],
    "wof:name":"Pastor Cleaners",
    "wof:placetype":"venue"
},
  "geometry": {"coordinates":[-83.168098,42.380575],"type":"Point"}
}