{
  "type": "Feature",
  "properties": {
    "iso:country":"US",
    "sg:address":"3740 Patterson Rd",
    "sg:city":"Bay City",
    "sg:classifiers":[
        {
            "category":"Wholesale",
            "subcategory":"Construction Materials",
            "type":"Manufacturing & Wholesale Goods"
        }
    ],
    "sg:phone":"+1 989 684 0900",
    "sg:postcode":"48706",
    "sg:province":"MI",
    "sg:tags":[
        "sand",
        "gravel"
    ],
    "wof:name":"Bond Crushed Concrete",
    "wof:placetype":"venue"
},
  "geometry": {"coordinates":[-83.873918,43.629298],"type":"Point"}
}