{
  "type": "Feature",
  "properties": {
    "iso:country":"US",
    "sg:address":"13 Washington St",
    "sg:city":"Monroe",
    "sg:classifiers":[
        {
            "category":"Professional",
            "subcategory":"Lawyer & Legal Services",
            "type":"Services"
        }
    ],
    "sg:phone":"+1 734 242 1001",
    "sg:postcode":"48161",
    "sg:province":"MI",
    "wof:name":"Coogan Lawrence J",
    "wof:placetype":"venue"
},
  "geometry": {"coordinates":[-83.39595199999999,41.916042],"type":"Point"}
}