{
  "type": "Feature",
  "properties": {
    "iso:country":"US",
    "sg:address":"115 E Ayer St",
    "sg:city":"Ironwood",
    "sg:classifiers":[
        {
            "category":"Professional",
            "subcategory":"Business Services",
            "type":"Services"
        }
    ],
    "sg:phone":"+1 906 932 0010",
    "sg:postcode":"49938",
    "sg:province":"MI",
    "sg:tags":[
        "investment",
        "closed"
    ],
    "wof:name":"Mediation & Training Centers",
    "wof:placetype":"venue"
},
  "geometry": {"coordinates":[-90.169431,46.455141],"type":"Point"}
}