{
  "type": "Feature",
  "properties": {
    "iso:country":"US",
    "sg:address":"102 E Michigan Ave",
    "sg:city":"Clinton",
    "sg:classifiers":[
        {
            "category":"Home & Garden",
            "subcategory":"Furniture",
            "type":"Retail Goods"
        }
    ],
    "sg:phone":"+1 517 423 1428",
    "sg:postcode":"49236",
    "sg:province":"MI",
    "sg:tags":[
        "cabinet"
    ],
    "wof:name":"M & S Kitchen & Bath",
    "wof:placetype":"venue"
},
  "geometry": {"coordinates":[-83.969337,42.073158],"type":"Point"}
}