{
  "type": "Feature",
  "properties": {
    "iso:country":"US",
    "sg:address":"30201 Dequindre Rd",
    "sg:city":"Madison Heights",
    "sg:classifiers":[
        {
            "category":"Health Services",
            "subcategory":"Chiropractor",
            "type":"Services"
        }
    ],
    "sg:phone":"+1 248 585 0399",
    "sg:postcode":"48071",
    "sg:province":"MI",
    "wof:name":"Fordiani",
    "wof:placetype":"venue"
},
  "geometry": {"coordinates":[-83.086189,42.51475],"type":"Point"}
}