{
  "type": "Feature",
  "properties": {
    "iso:country":"US",
    "sg:address":"536 Ashwood Dr",
    "sg:city":"Flushing",
    "sg:classifiers":[
        {
            "category":"Manufacturing",
            "subcategory":"Printing",
            "type":"Manufacturing & Wholesale Goods"
        }
    ],
    "sg:phone":"+1 810 659 7214",
    "sg:postcode":"48433",
    "sg:province":"MI",
    "sg:tags":[
        "book"
    ],
    "wof:name":"Kabeka Inc",
    "wof:placetype":"venue"
},
  "geometry": {"coordinates":[-83.84097,43.070426],"type":"Point"}
}