{
  "type": "Feature",
  "properties": {
    "iso:country":"US",
    "sg:address":"4924 S Wayne Rd",
    "sg:city":"Wayne",
    "sg:classifiers":[
        {
            "category":"Organizations",
            "subcategory":"Community Association",
            "type":"Services"
        }
    ],
    "sg:phone":"+1 734 728 0527",
    "sg:postcode":"48184",
    "sg:province":"MI",
    "wof:name":"Veterans Haven Inc",
    "wof:placetype":"venue"
},
  "geometry": {"coordinates":[-83.38851200000001,42.272293],"type":"Point"}
}