{
  "type": "Feature",
  "properties": {
    "iso:country":"US",
    "sg:address":"1514 Wealthy St SE",
    "sg:city":"Grand Rapids",
    "sg:classifiers":[
        {
            "category":"Real Estate",
            "subcategory":"Real Estate Agent",
            "type":"Services"
        }
    ],
    "sg:phone":"+1 616 451 8700",
    "sg:postcode":"49506",
    "sg:province":"MI",
    "sg:tags":[
        "development",
        "management",
        "commercial"
    ],
    "wof:name":"City Realty and Dev Corp",
    "wof:placetype":"venue"
},
  "geometry": {"coordinates":[-85.632088,42.955435],"type":"Point"}
}