{
  "type": "Feature",
  "properties": {
    "iso:country":"US",
    "sg:address":"4153 Jimbo Dr",
    "sg:city":"Burton",
    "sg:classifiers":[
        {
            "category":"Building & Trades",
            "subcategory":"Construction",
            "type":"Services"
        }
    ],
    "sg:phone":"+1 810 744 2560",
    "sg:postcode":"48529",
    "sg:province":"MI",
    "sg:tags":[
        "contractor"
    ],
    "wof:name":"Black & White Asphalt Inc",
    "wof:placetype":"venue"
},
  "geometry": {"coordinates":[-83.644581,42.970711],"type":"Point"}
}