{
  "type": "Feature",
  "properties": {
    "iso:country":"US",
    "sg:address":"32210 Garfield Rd",
    "sg:city":"Fraser",
    "sg:classifiers":[
        {
            "category":"Retail",
            "subcategory":"Auto Repair",
            "type":"Services"
        }
    ],
    "sg:phone":"+1 586 294 2930",
    "sg:postcode":"48026",
    "sg:province":"MI",
    "sg:tags":[
        "body",
        "automobile",
        "painting"
    ],
    "wof:name":"Garfield Collision",
    "wof:placetype":"venue"
},
  "geometry": {"coordinates":[-82.949471,42.53423],"type":"Point"}
}