{
  "type": "Feature",
  "properties": {
    "iso:country":"US",
    "sg:address":"247 Lafayette Ave NE",
    "sg:city":"Grand Rapids",
    "sg:classifiers":[
        {
            "category":"Professional",
            "subcategory":"Detective & Security Services",
            "type":"Services"
        }
    ],
    "sg:phone":"+1 616 774 7191",
    "sg:postcode":"49503",
    "sg:province":"MI",
    "wof:name":"Cole & Co",
    "wof:placetype":"venue"
},
  "geometry": {"coordinates":[-85.661946,42.96819],"type":"Point"}
}