{
  "type": "Feature",
  "properties": {
    "iso:country":"US",
    "sg:address":"255 S Old Woodward Ave",
    "sg:city":"Birmingham",
    "sg:classifiers":[
        {
            "category":"Shopping",
            "subcategory":"Jewelry",
            "type":"Retail Goods"
        }
    ],
    "sg:phone":"+1 248 594 8300",
    "sg:postcode":"48009",
    "sg:province":"MI",
    "sg:tags":[
        "jeweler"
    ],
    "wof:name":"Blue Heron Designs",
    "wof:placetype":"venue"
},
  "geometry": {"coordinates":[-83.21385100000001,42.546519],"type":"Point"}
}