{
  "type": "Feature",
  "properties": {
    "iso:country":"US",
    "sg:address":"21093 North Ave",
    "sg:city":"Battle Creek",
    "sg:classifiers":[
        {
            "category":"Manufacturing",
            "subcategory":"Tools & Machinery",
            "type":"Manufacturing & Wholesale Goods"
        }
    ],
    "sg:phone":"+1 269 968 3800",
    "sg:postcode":"49017",
    "sg:province":"MI",
    "sg:tags":[
        "excavating",
        "hauling",
        "dirt"
    ],
    "wof:name":"O K Wrecking",
    "wof:placetype":"venue"
},
  "geometry": {"coordinates":[-85.173524,42.381598],"type":"Point"}
}