{
  "type": "Feature",
  "properties": {
    "iso:country":"US",
    "sg:address":"740 Rivard St",
    "sg:city":"Detroit",
    "sg:classifiers":[
        {
            "category":"Building & Trades",
            "subcategory":"Locksmith",
            "type":"Services"
        }
    ],
    "sg:phone":"+1 313 279 6280",
    "sg:postcode":"48207",
    "sg:province":"MI",
    "sg:tags":[
        "key"
    ],
    "wof:name":"01 Detroit Locksmith",
    "wof:placetype":"venue"
},
  "geometry": {"coordinates":[-83.035251,42.33495],"type":"Point"}
}