{
  "type": "Feature",
  "properties": {
    "iso:country":"US",
    "sg:address":"3360 Aurora Dr",
    "sg:city":"Petoskey",
    "sg:classifiers":[
        {
            "category":"Travel",
            "subcategory":"Hotels & Motels",
            "type":"Entertainment"
        }
    ],
    "sg:phone":"+1 906 847 3384",
    "sg:postcode":"49770",
    "sg:province":"MI",
    "wof:name":"Lakeview Management Group Inc",
    "wof:placetype":"venue"
},
  "geometry": {"coordinates":[-84.90149,45.385681],"type":"Point"}
}