{
  "type": "Feature",
  "properties": {
    "iso:country":"US",
    "sg:address":"105 N Sophia St",
    "sg:city":"Homer",
    "sg:classifiers":[
        {
            "category":"Recreation",
            "type":"Entertainment"
        }
    ],
    "sg:phone":"+1 517 568 4971",
    "sg:postcode":"49245",
    "sg:province":"MI",
    "sg:tags":[
        "guide"
    ],
    "wof:name":"Lucky Duck Sport Fishing Chart",
    "wof:placetype":"venue"
},
  "geometry": {"coordinates":[-84.80705399999999,42.146653],"type":"Point"}
}