{
  "type": "Feature",
  "properties": {
    "iso:country":"US",
    "sg:address":"222 S Main St",
    "sg:city":"Rochester",
    "sg:classifiers":[
        {
            "category":"Professional",
            "subcategory":"Management & Consulting",
            "type":"Services"
        }
    ],
    "sg:phone":"+1 248 601 5215",
    "sg:postcode":"48307",
    "sg:province":"MI",
    "sg:tags":[
        "public",
        "relations"
    ],
    "wof:name":"SBH Communications",
    "wof:placetype":"venue"
},
  "geometry": {"coordinates":[-83.133645,42.679132],"type":"Point"}
}