{
  "type": "Feature",
  "properties": {
    "iso:country":"US",
    "sg:address":"6730 Oak Grove Rd",
    "sg:city":"Howell",
    "sg:classifiers":[
        {
            "category":"Building & Trades",
            "subcategory":"Construction",
            "type":"Services"
        }
    ],
    "sg:phone":"+1 517 548 0023",
    "sg:postcode":"48855",
    "sg:province":"MI",
    "sg:tags":[
        "contractor"
    ],
    "wof:name":"Gothic Drywall",
    "wof:placetype":"venue"
},
  "geometry": {"coordinates":[-83.945768,42.698177],"type":"Point"}
}