{
  "type": "Feature",
  "properties": {
    "iso:country":"US",
    "sg:address":"16164 US Hwy 41",
    "sg:city":"Rapid River",
    "sg:classifiers":[
        {
            "category":"Insurance",
            "subcategory":"Insurance Agent",
            "type":"Services"
        }
    ],
    "sg:phone":"+1 906 428 3518",
    "sg:postcode":"49878",
    "sg:province":"MI",
    "wof:name":"Farmers Insurance Group",
    "wof:placetype":"venue"
},
  "geometry": {"coordinates":[-86.98018999999999,46.120124],"type":"Point"}
}