{
  "type": "Feature",
  "properties": {
    "iso:country":"US",
    "sg:address":"5708 W Wackerly St",
    "sg:city":"Midland",
    "sg:classifiers":[
        {
            "category":"Retail",
            "subcategory":"Auto Repair",
            "type":"Services"
        }
    ],
    "sg:phone":"+1 989 636 7734",
    "sg:postcode":"48642",
    "sg:province":"MI",
    "sg:tags":[
        "body",
        "automotive"
    ],
    "wof:name":"Body Shop By Daniel",
    "wof:placetype":"venue"
},
  "geometry": {"coordinates":[-84.292502,43.655189],"type":"Point"}
}