{
  "type": "Feature",
  "properties": {
    "iso:country":"US",
    "sg:address":"4160 E Grand River Ave",
    "sg:city":"Howell",
    "sg:classifiers":[
        {
            "category":"Sports & Exercise",
            "subcategory":"Gym",
            "type":"Entertainment"
        }
    ],
    "sg:phone":"+1 517 552 4983",
    "sg:postcode":"48843",
    "sg:province":"MI",
    "sg:tags":[
        "club",
        "health",
        "studio",
        "gymnasium"
    ],
    "wof:name":"Howell Fitness Ctr",
    "wof:placetype":"venue"
},
  "geometry": {"coordinates":[-83.871228,42.585594],"type":"Point"}
}