{
  "type": "Feature",
  "properties": {
    "iso:country":"US",
    "sg:address":"6857 Bridgemont Dr",
    "sg:city":"Canton",
    "sg:classifiers":[
        {
            "category":"Professional",
            "subcategory":"Computer Services",
            "type":"Services"
        }
    ],
    "sg:phone":"+1 734 354 6520",
    "sg:postcode":"48187",
    "sg:province":"MI",
    "sg:tags":[
        "programing",
        "custom"
    ],
    "wof:name":"Intellikats Inc",
    "wof:placetype":"venue"
},
  "geometry": {"coordinates":[-83.489278,42.334464],"type":"Point"}
}