{
  "type": "Feature",
  "properties": {
    "iso:country":"US",
    "sg:address":"14377 E O N Ave",
    "sg:city":"Climax",
    "sg:classifiers":[
        {
            "category":"Food & Beverages",
            "subcategory":"Groceries & Convenience Stores",
            "type":"Retail Goods"
        }
    ],
    "sg:phone":"+1 269 746 4242",
    "sg:postcode":"49034",
    "sg:province":"MI",
    "sg:tags":[
        "grocer"
    ],
    "wof:name":"Sinclair's Spartan Store",
    "wof:placetype":"venue"
},
  "geometry": {"coordinates":[-85.348347,42.23808],"type":"Point"}
}