{
  "type": "Feature",
  "properties": {
    "iso:country":"US",
    "sg:address":"25315 Culver St",
    "sg:city":"Saint Clair Shores",
    "sg:classifiers":[
        {
            "category":"Social Services",
            "subcategory":"Child Care",
            "type":"Services"
        }
    ],
    "sg:phone":"+1 586 779 4459",
    "sg:postcode":"48081",
    "sg:province":"MI",
    "sg:tags":[
        "day"
    ],
    "wof:name":"Katherine Morney",
    "wof:placetype":"venue"
},
  "geometry": {"coordinates":[-82.914861,42.483146],"type":"Point"}
}