{
  "type": "Feature",
  "properties": {
    "iso:country":"US",
    "sg:address":"31730 Hoover Rd Ste A",
    "sg:city":"Warren",
    "sg:classifiers":[
        {
            "category":"Health Services",
            "subcategory":"Doctor",
            "type":"Services"
        }
    ],
    "sg:phone":"+1 586 268 9222",
    "sg:postcode":"48093",
    "sg:province":"MI",
    "sg:website":"www.warrenallergyandasthmacare.com",
    "wof:name":"Warren Allergy & Asthma Care",
    "wof:placetype":"venue"
},
  "geometry": {"coordinates":[-83.007609,42.52698],"type":"Point"}
}