{
  "type": "Feature",
  "properties": {
    "iso:country":"US",
    "sg:address":"430 Genesee St",
    "sg:city":"Owosso",
    "sg:classifiers":[
        {
            "category":"Shopping",
            "subcategory":"Catalog Store",
            "type":"Retail Goods"
        }
    ],
    "sg:phone":"+1 989 729 0390",
    "sg:postcode":"48867",
    "sg:province":"MI",
    "sg:tags":[
        "house",
        "mail"
    ],
    "wof:name":"Westmans General Merchandise",
    "wof:placetype":"venue"
},
  "geometry": {"coordinates":[-84.176399,42.995779],"type":"Point"}
}