{
  "type": "Feature",
  "properties": {
    "iso:country":"US",
    "sg:address":"1592 Wiltshire Rd",
    "sg:city":"Berkley",
    "sg:classifiers":[
        {
            "category":"Building & Trades",
            "subcategory":"Construction",
            "type":"Services"
        }
    ],
    "sg:phone":"+1 248 547 0013",
    "sg:postcode":"48072",
    "sg:province":"MI",
    "sg:tags":[
        "house"
    ],
    "wof:name":"Rogers Rl Home Improvement",
    "wof:placetype":"venue"
},
  "geometry": {"coordinates":[-83.172567,42.499016],"type":"Point"}
}