{
  "type": "Feature",
  "properties": {
    "iso:country":"US",
    "sg:address":"2831 Hayes St",
    "sg:city":"Marne",
    "sg:classifiers":[
        {
            "category":"Farming",
            "subcategory":"Farm",
            "type":"Manufacturing & Wholesale Goods"
        }
    ],
    "sg:phone":"+1 616 677 3680",
    "sg:postcode":"49435",
    "sg:province":"MI",
    "sg:tags":[
        "crop",
        "general"
    ],
    "wof:name":"Voogt Farms",
    "wof:placetype":"venue"
},
  "geometry": {"coordinates":[-85.857201,43.030949],"type":"Point"}
}