{
  "type": "Feature",
  "properties": {
    "iso:country":"US",
    "sg:address":"25333 W 12 Mile Rd",
    "sg:city":"Southfield",
    "sg:classifiers":[
        {
            "category":"Communications",
            "subcategory":"Radio Station",
            "type":"Services"
        }
    ],
    "sg:phone":"+1 248 208 0396",
    "sg:postcode":"48034",
    "sg:province":"MI",
    "wof:name":"Broadcast W Jlb",
    "wof:placetype":"venue"
},
  "geometry": {"coordinates":[-83.29510000000001,42.500725],"type":"Point"}
}