{
  "type": "Feature",
  "properties": {
    "iso:country":"US",
    "sg:address":"2757 University Dr",
    "sg:city":"Auburn Hills",
    "sg:classifiers":[
        {
            "category":"Banks & Credit Unions",
            "subcategory":"Bank",
            "type":"Services"
        }
    ],
    "sg:phone":"+1 248 340 6022",
    "sg:postcode":"48326",
    "sg:province":"MI",
    "sg:tags":[
        "loan",
        "real estate"
    ],
    "wof:name":"Countrywide Home Loans",
    "wof:placetype":"venue"
},
  "geometry": {"coordinates":[-83.235557,42.66898],"type":"Point"}
}