{
  "type": "Feature",
  "properties": {
    "iso:country":"US",
    "sg:address":"1718 Holland St",
    "sg:city":"Birmingham",
    "sg:classifiers":[
        {
            "category":"Professional",
            "subcategory":"Computer Services",
            "type":"Services"
        }
    ],
    "sg:phone":"+1 248 650 0514",
    "sg:postcode":"48009",
    "sg:province":"MI",
    "sg:tags":[
        "development",
        "system",
        "software"
    ],
    "wof:name":"Cresma Corporation",
    "wof:placetype":"venue"
},
  "geometry": {"coordinates":[-83.196777,42.541595],"type":"Point"}
}