{
  "type": "Feature",
  "properties": {
    "iso:country":"US",
    "sg:address":"1890 Deer Lake Rd",
    "sg:city":"Ishpeming",
    "sg:classifiers":[
        {
            "category":"Manufacturing",
            "subcategory":"Lumber",
            "type":"Manufacturing & Wholesale Goods"
        }
    ],
    "sg:phone":"+1 906 360 6673",
    "sg:postcode":"49849",
    "sg:province":"MI",
    "sg:tags":[
        "consultant",
        "forest"
    ],
    "wof:name":"Moosewood Forestry",
    "wof:placetype":"venue"
},
  "geometry": {"coordinates":[-87.695441,46.558779],"type":"Point"}
}