{
  "type": "Feature",
  "properties": {
    "iso:country":"US",
    "sg:address":"107 3rd St",
    "sg:city":"Kalkaska",
    "sg:classifiers":[
        {
            "category":"Restaurant",
            "type":"Food & Drink"
        }
    ],
    "sg:phone":"+1 231 258 4636",
    "sg:postcode":"49646",
    "sg:province":"MI",
    "wof:name":"Third Street Cafe",
    "wof:placetype":"venue"
},
  "geometry": {"coordinates":[-85.180199,44.730862],"type":"Point"}
}