{
  "type": "Feature",
  "properties": {
    "iso:country":"US",
    "sg:address":"11395 E Lakewood Blvd",
    "sg:city":"Holland",
    "sg:classifiers":[
        {
            "category":"Autos & Motor Vehicles",
            "subcategory":"Auto Supplies",
            "type":"Retail Goods"
        }
    ],
    "sg:phone":"+1 616 393 6500",
    "sg:postcode":"49424",
    "sg:province":"MI",
    "wof:name":"Speedwise Motorsports",
    "wof:placetype":"venue"
},
  "geometry": {"coordinates":[-86.062963,42.805047],"type":"Point"}
}