{
  "type": "Feature",
  "properties": {
    "iso:country":"US",
    "sg:address":"4965 Edgewood St",
    "sg:city":"Dearborn Heights",
    "sg:classifiers":[
        {
            "category":"Building & Trades",
            "subcategory":"Cleaning & Sanitation",
            "type":"Services"
        }
    ],
    "sg:phone":"+1 313 274 0587",
    "sg:postcode":"48125",
    "sg:province":"MI",
    "sg:tags":[
        "maintenance"
    ],
    "wof:name":"Moonlite Janitorial Services",
    "wof:placetype":"venue"
},
  "geometry": {"coordinates":[-83.22749899999999,42.273981],"type":"Point"}
}