{
  "type": "Feature",
  "properties": {
    "iso:country":"US",
    "sg:address":"4130 E 9 Mile Rd",
    "sg:city":"Warren",
    "sg:classifiers":[
        {
            "category":"Shopping",
            "subcategory":"Department Store",
            "type":"Retail Goods"
        },
        {
            "category":"Shopping",
            "subcategory":"Discount & Variety Stores",
            "type":"Retail Goods"
        }
    ],
    "sg:phone":"+1 586 755 1460",
    "sg:postcode":"48091",
    "sg:province":"MI",
    "wof:name":"Bur-Lers Variety Store",
    "wof:placetype":"venue"
},
  "geometry": {"coordinates":[-83.064138,42.462249],"type":"Point"}
}