{
  "type": "Feature",
  "properties": {
    "iso:country":"US",
    "sg:address":"6310 Central St",
    "sg:city":"Romulus",
    "sg:classifiers":[
        {
            "category":"Real Estate",
            "subcategory":"Real Estate Operator",
            "type":"Services"
        }
    ],
    "sg:phone":"+1 734 729 5060",
    "sg:postcode":"48174",
    "sg:province":"MI",
    "sg:tags":[
        "property",
        "lessor"
    ],
    "wof:name":"Ksk Properties",
    "wof:placetype":"venue"
},
  "geometry": {"coordinates":[-83.326314,42.261821],"type":"Point"}
}