{
  "type": "Feature",
  "properties": {
    "iso:country":"US",
    "sg:address":"47622 Brittany Ct",
    "sg:city":"Novi",
    "sg:classifiers":[
        {
            "category":"Professional",
            "subcategory":"Management & Consulting",
            "type":"Services"
        }
    ],
    "sg:phone":"+1 248 349 6045",
    "sg:postcode":"48374",
    "sg:province":"MI",
    "sg:tags":[
        "business"
    ],
    "wof:name":"Alampi & Assoc",
    "wof:placetype":"venue"
},
  "geometry": {"coordinates":[-83.516066,42.451657],"type":"Point"}
}