{
  "type": "Feature",
  "properties": {
    "iso:country":"US",
    "sg:address":"14156 Eureka Rd",
    "sg:city":"Southgate",
    "sg:classifiers":[
        {
            "category":"Shopping",
            "subcategory":"Florist",
            "type":"Retail Goods"
        }
    ],
    "sg:phone":"+1 734 928 4797",
    "sg:postcode":"48195",
    "sg:province":"MI",
    "wof:name":"Wally's Flower Shop",
    "wof:placetype":"venue"
},
  "geometry": {"coordinates":[-83.196242,42.199476],"type":"Point"}
}