{
  "type": "Feature",
  "properties": {
    "iso:country":"US",
    "sg:address":"12056 Austin Rd",
    "sg:city":"Brooklyn",
    "sg:classifiers":[
        {
            "category":"Retail",
            "subcategory":"Repair Shop",
            "type":"Services"
        }
    ],
    "sg:phone":"+1 517 536 7016",
    "sg:postcode":"49230",
    "sg:province":"MI",
    "wof:name":"Powersports Engine Repair",
    "wof:placetype":"venue"
},
  "geometry": {"coordinates":[-84.18329900000001,42.146156],"type":"Point"}
}