{
  "type": "Feature",
  "properties": {
    "iso:country":"US",
    "sg:address":"6075 Baywood Dr",
    "sg:city":"Portage",
    "sg:classifiers":[
        {
            "category":"Social Services",
            "subcategory":"Child Care",
            "type":"Services"
        }
    ],
    "sg:phone":"+1 269 329 1114",
    "sg:postcode":"49024",
    "sg:province":"MI",
    "sg:tags":[
        "day"
    ],
    "wof:name":"Kaliedescope",
    "wof:placetype":"venue"
},
  "geometry": {"coordinates":[-85.63023099999999,42.229097],"type":"Point"}
}