{
  "type": "Feature",
  "properties": {
    "iso:country":"US",
    "sg:address":"541 N Spencer Rd",
    "sg:city":"Mears",
    "sg:classifiers":[
        {
            "category":"Health Services",
            "subcategory":"Doctor",
            "type":"Services"
        }
    ],
    "sg:phone":"+1 231 873 7478",
    "sg:postcode":"49436",
    "sg:province":"MI",
    "sg:tags":[
        "physician",
        "surgeon"
    ],
    "wof:name":"D R Communications LLC",
    "wof:placetype":"venue"
},
  "geometry": {"coordinates":[-86.51739600000001,43.655527],"type":"Point"}
}