{
  "type": "Feature",
  "properties": {
    "iso:country":"US",
    "sg:address":"31157 Woodward Ave",
    "sg:city":"Royal Oak",
    "sg:classifiers":[
        {
            "category":"Health Services",
            "subcategory":"Doctor",
            "type":"Services"
        }
    ],
    "sg:phone":"+1 248 288 1176",
    "sg:postcode":"48073",
    "sg:province":"MI",
    "wof:name":"Goldman Kenneth A MD",
    "wof:placetype":"venue"
},
  "geometry": {"coordinates":[-83.188142,42.519419],"type":"Point"}
}