{
  "type": "Feature",
  "properties": {
    "iso:country":"US",
    "sg:address":"14571 Judson Ave",
    "sg:city":"Thompsonville",
    "sg:classifiers":[
        {
            "category":"Ferry",
            "type":"Transportation"
        }
    ],
    "sg:phone":"+1 231 378 2680",
    "sg:postcode":"49683",
    "sg:province":"MI",
    "sg:tags":[
        "boat"
    ],
    "wof:name":"Tangle Five Charter Svc",
    "wof:placetype":"venue"
},
  "geometry": {"coordinates":[-85.947284,44.522439],"type":"Point"}
}