{
  "type": "Feature",
  "properties": {
    "iso:country":"US",
    "sg:address":"128 N Main St",
    "sg:city":"Evart",
    "sg:classifiers":[
        {
            "category":"Shopping",
            "subcategory":"Gifts & Souvenirs",
            "type":"Retail Goods"
        }
    ],
    "sg:phone":"+1 231 734 2551",
    "sg:postcode":"49631",
    "sg:province":"MI",
    "sg:tags":[
        "shop"
    ],
    "wof:name":"Holihan's Drug Store",
    "wof:placetype":"venue"
},
  "geometry": {"coordinates":[-85.259399,43.901526],"type":"Point"}
}