{
  "type": "Feature",
  "properties": {
    "iso:country":"US",
    "sg:address":"324 W Lake St",
    "sg:city":"Tawas City",
    "sg:classifiers":[
        {
            "category":"Banks & Credit Unions",
            "subcategory":"Bank",
            "type":"Services"
        }
    ],
    "sg:phone":"+1 989 362 7980",
    "sg:postcode":"48763",
    "sg:province":"MI",
    "wof:name":"Iosco Community Credit Union",
    "wof:placetype":"venue"
},
  "geometry": {"coordinates":[-83.515765,44.268775],"type":"Point"}
}