{
  "type": "Feature",
  "properties": {
    "iso:country":"US",
    "sg:address":"1125 W Civic Center Dr",
    "sg:city":"Traverse City",
    "sg:classifiers":[
        {
            "category":"Government",
            "subcategory":"Office",
            "type":"Public Place"
        }
    ],
    "sg:phone":"+1 231 922 4895",
    "sg:postcode":"49686",
    "sg:province":"MI",
    "wof:name":"Grand Traverse Multi-Purpose",
    "wof:placetype":"venue"
},
  "geometry": {"coordinates":[-85.59495699999999,44.762622],"type":"Point"}
}