{
  "type": "Feature",
  "properties": {
    "iso:country":"US",
    "sg:address":"18148 Dorset St",
    "sg:city":"Southfield",
    "sg:classifiers":[
        {
            "category":"Social Services",
            "subcategory":"Adult Care",
            "type":"Services"
        }
    ],
    "sg:phone":"+1 248 552 0246",
    "sg:postcode":"48075",
    "sg:province":"MI",
    "sg:tags":[
        "home"
    ],
    "wof:name":"Josephine Uwazurike",
    "wof:placetype":"venue"
},
  "geometry": {"coordinates":[-83.222922,42.450898],"type":"Point"}
}