{
  "type": "Feature",
  "properties": {
    "iso:country":"US",
    "sg:address":"15353 Hall Rd",
    "sg:city":"Macomb",
    "sg:classifiers":[
        {
            "category":"Home & Garden",
            "subcategory":"Carpets & Floor Coverings",
            "type":"Retail Goods"
        }
    ],
    "sg:phone":"+1 586 532 7900",
    "sg:postcode":"48044",
    "sg:province":"MI",
    "sg:tags":[
        "rug",
        "flooring"
    ],
    "sg:website":"www.proqualityflooring.com",
    "wof:name":"Pro Quality Flooring",
    "wof:placetype":"venue"
},
  "geometry": {"coordinates":[-82.97148900000001,42.627972],"type":"Point"}
}