{
  "type": "Feature",
  "properties": {
    "iso:country":"US",
    "sg:address":"2151 E Jefferson Ave",
    "sg:city":"Detroit",
    "sg:classifiers":[
        {
            "category":"Health Services",
            "subcategory":"Doctor",
            "type":"Services"
        }
    ],
    "sg:phone":"+1 313 259 7990",
    "sg:postcode":"48207",
    "sg:province":"MI",
    "sg:tags":[
        "medical",
        "center"
    ],
    "wof:name":"Concentra Medical Centers",
    "wof:placetype":"venue"
},
  "geometry": {"coordinates":[-83.02510100000001,42.3372],"type":"Point"}
}