{
  "type": "Feature",
  "properties": {
    "iso:country":"US",
    "sg:address":"301 E McClellan St",
    "sg:city":"Flint",
    "sg:classifiers":[
        {
            "category":"Education",
            "subcategory":"School",
            "type":"Public Place"
        }
    ],
    "sg:phone":"+1 810 785 8588",
    "sg:postcode":"48505",
    "sg:province":"MI",
    "sg:tags":[
        "high",
        "middle",
        "elementary"
    ],
    "wof:name":"Garfield Edison Partnership School",
    "wof:placetype":"venue"
},
  "geometry": {"coordinates":[-83.70120199999999,43.0438],"type":"Point"}
}