{
  "type": "Feature",
  "properties": {
    "iso:country":"US",
    "sg:address":"1202 2nd St",
    "sg:city":"Marquette",
    "sg:classifiers":[
        {
            "category":"Building & Trades",
            "subcategory":"Construction",
            "type":"Services"
        }
    ],
    "sg:phone":"+1 906 226 8868",
    "sg:postcode":"49855",
    "sg:province":"MI",
    "sg:tags":[
        "contractor"
    ],
    "wof:name":"Kelly Pavers & Construction",
    "wof:placetype":"venue"
},
  "geometry": {"coordinates":[-87.393474,46.555545],"type":"Point"}
}