{
  "type": "Feature",
  "properties": {
    "iso:country":"US",
    "sg:address":"37501 Cherry Hill Rd",
    "sg:city":"Westland",
    "sg:classifiers":[
        {
            "category":"Retail",
            "subcategory":"Auto Repair",
            "type":"Services"
        }
    ],
    "sg:phone":"+1 734 261 9066",
    "sg:postcode":"48186",
    "sg:province":"MI",
    "sg:tags":[
        "automotive"
    ],
    "wof:name":"Wirts Towing Inc",
    "wof:placetype":"venue"
},
  "geometry": {"coordinates":[-83.412228,42.309386],"type":"Point"}
}