{
  "type": "Feature",
  "properties": {
    "iso:country":"US",
    "sg:address":"338 State St",
    "sg:city":"Harbor Springs",
    "sg:classifiers":[
        {
            "category":"Real Estate",
            "subcategory":"Real Estate Agent",
            "type":"Services"
        }
    ],
    "sg:phone":"+1 231 526 1181",
    "sg:postcode":"49740",
    "sg:province":"MI",
    "wof:name":"John C Carr",
    "wof:placetype":"venue"
},
  "geometry": {"coordinates":[-84.991867,45.431498],"type":"Point"}
}