{
  "type": "Feature",
  "properties": {
    "iso:country":"US",
    "sg:address":"9695 Forest Ridge Dr",
    "sg:city":"Clarkston",
    "sg:classifiers":[
        {
            "category":"Professional",
            "subcategory":"Computer Services",
            "type":"Services"
        }
    ],
    "sg:phone":"+1 248 620 2318",
    "sg:postcode":"48348",
    "sg:province":"MI",
    "wof:name":"C Y Worldwide Inc",
    "wof:placetype":"venue"
},
  "geometry": {"coordinates":[-83.47906,42.747292],"type":"Point"}
}