{
  "type": "Feature",
  "properties": {
    "iso:country":"US",
    "sg:address":"209 E State St",
    "sg:city":"Clare",
    "sg:classifiers":[
        {
            "category":"Social Services",
            "type":"Services"
        }
    ],
    "sg:phone":"+1 989 386 4289",
    "sg:postcode":"48617",
    "sg:province":"MI",
    "sg:tags":[
        "youth",
        "organization",
        "center"
    ],
    "wof:name":"Mid Michigan Community Action",
    "wof:placetype":"venue"
},
  "geometry": {"coordinates":[-84.76612799999999,43.822491],"type":"Point"}
}