{
  "type": "Feature",
  "properties": {
    "iso:country":"US",
    "sg:address":"45264 Seabrook Dr",
    "sg:city":"Canton",
    "sg:classifiers":[
        {
            "category":"Professional",
            "subcategory":"Business Services",
            "type":"Services"
        }
    ],
    "sg:phone":"+1 734 397 3272",
    "sg:postcode":"48188",
    "sg:province":"MI",
    "wof:name":"Ajn Computing Solutions",
    "wof:placetype":"venue"
},
  "geometry": {"coordinates":[-83.48559,42.297636],"type":"Point"}
}