{
  "type": "Feature",
  "properties": {
    "iso:country":"US",
    "sg:address":"445 E Mitchell St",
    "sg:city":"Petoskey",
    "sg:classifiers":[
        {
            "category":"Professional",
            "subcategory":"Art Services",
            "type":"Services"
        }
    ],
    "sg:phone":"+1 231 537 4707",
    "sg:postcode":"49770",
    "sg:province":"MI",
    "sg:tags":[
        "photographer"
    ],
    "wof:name":"Nancy Payne Photography",
    "wof:placetype":"venue"
},
  "geometry": {"coordinates":[-84.952975,45.373948],"type":"Point"}
}