{
  "type": "Feature",
  "properties": {
    "iso:country":"US",
    "sg:address":"12065 Woodview Ln",
    "sg:city":"Holland",
    "sg:classifiers":[
        {
            "category":"Freight",
            "type":"Transportation"
        }
    ],
    "sg:phone":"+1 616 786 3871",
    "sg:postcode":"49424",
    "sg:province":"MI",
    "sg:tags":[
        "delivery"
    ],
    "wof:name":"Knight Enterprise",
    "wof:placetype":"venue"
},
  "geometry": {"coordinates":[-86.079534,42.822615],"type":"Point"}
}