{
  "type": "Feature",
  "properties": {
    "iso:country":"US",
    "sg:address":"1234 N Main St",
    "sg:city":"Rochester",
    "sg:classifiers":[
        {
            "category":"Real Estate",
            "subcategory":"Real Estate Agent",
            "type":"Services"
        }
    ],
    "sg:phone":"+1 248 656 3311",
    "sg:postcode":"48307",
    "sg:province":"MI",
    "wof:name":"North Star Realty",
    "wof:placetype":"venue"
},
  "geometry": {"coordinates":[-83.134124,42.691002],"type":"Point"}
}