{
  "type": "Feature",
  "properties": {
    "iso:country":"US",
    "sg:address":"3080 Van Horn Rd",
    "sg:city":"Trenton",
    "sg:classifiers":[
        {
            "category":"Home & Garden",
            "subcategory":"Hardware",
            "type":"Retail Goods"
        }
    ],
    "sg:phone":"+1 734 671 0260",
    "sg:postcode":"48183",
    "sg:province":"MI",
    "sg:tags":[
        "store"
    ],
    "wof:name":"A C O Hardware",
    "wof:placetype":"venue"
},
  "geometry": {"coordinates":[-83.20349899999999,42.126801],"type":"Point"}
}