{
  "type": "Feature",
  "properties": {
    "iso:country":"US",
    "sg:address":"21520 Mullin Ave",
    "sg:city":"Warren",
    "sg:classifiers":[
        {
            "category":"Professional",
            "type":"Services"
        },
        {
            "category":"Retail",
            "subcategory":"Repair Shop",
            "type":"Services"
        }
    ],
    "sg:phone":"+1 586 754 4345",
    "sg:postcode":"48089",
    "sg:province":"MI",
    "sg:tags":[
        "spindle"
    ],
    "wof:name":"Quality Spindle Services Inc",
    "wof:placetype":"venue"
},
  "geometry": {"coordinates":[-83.011189,42.453936],"type":"Point"}
}