{
  "type": "Feature",
  "properties": {
    "iso:country":"US",
    "sg:address":"8033 E 10 Mile Rd",
    "sg:city":"Center Line",
    "sg:classifiers":[
        {
            "category":"Wholesale",
            "subcategory":"Machinery & Supplies",
            "type":"Manufacturing & Wholesale Goods"
        },
        {
            "category":"Manufacturing",
            "subcategory":"Tools & Machinery",
            "type":"Manufacturing & Wholesale Goods"
        }
    ],
    "sg:phone":"+1 586 754 3877",
    "sg:postcode":"48015",
    "sg:province":"MI",
    "sg:tags":[
        "equipment",
        "industry",
        "mfg",
        "plastic"
    ],
    "wof:name":"Metal Forming Machinery Of Mi",
    "wof:placetype":"venue"
},
  "geometry": {"coordinates":[-83.02454,42.477566],"type":"Point"}
}