{
  "type": "Feature",
  "properties": {
    "iso:country":"US",
    "sg:address":"30100 Telegraph Rd",
    "sg:city":"Bingham Farms",
    "sg:classifiers":[
        {
            "category":"Professional",
            "subcategory":"Lawyer & Legal Services",
            "type":"Services"
        }
    ],
    "sg:phone":"+1 248 646 0325",
    "sg:postcode":"48025",
    "sg:province":"MI",
    "wof:name":"Pernick Nat",
    "wof:placetype":"venue"
},
  "geometry": {"coordinates":[-83.285217,42.508485],"type":"Point"}
}