{
  "type": "Feature",
  "properties": {
    "iso:country":"US",
    "sg:address":"3997 N 28th St",
    "sg:city":"Kalamazoo",
    "sg:classifiers":[
        {
            "category":"Freight",
            "type":"Transportation"
        }
    ],
    "sg:phone":"+1 269 343 5194",
    "sg:postcode":"49048",
    "sg:province":"MI",
    "sg:tags":[
        "delivery"
    ],
    "wof:name":"Vander Meer Louis Moving Co",
    "wof:placetype":"venue"
},
  "geometry": {"coordinates":[-85.49287,42.327232],"type":"Point"}
}