{
  "type": "Feature",
  "properties": {
    "iso:country":"US",
    "sg:address":"109 S Warren Ave",
    "sg:city":"Big Rapids",
    "sg:classifiers":[
        {
            "category":"Health Services",
            "subcategory":"Health Practitioner",
            "type":"Services"
        }
    ],
    "sg:phone":"+1 231 796 1197",
    "sg:postcode":"49307",
    "sg:province":"MI",
    "wof:name":"Joyces Manual Medicine",
    "wof:placetype":"venue"
},
  "geometry": {"coordinates":[-85.48038099999999,43.698256],"type":"Point"}
}