{
  "type": "Feature",
  "properties": {
    "iso:country":"US",
    "sg:address":"20853 Farmington Rd",
    "sg:city":"Farmington",
    "sg:classifiers":[
        {
            "category":"Building & Trades",
            "subcategory":"Construction",
            "type":"Services"
        }
    ],
    "sg:phone":"+1 248 474 9310",
    "sg:postcode":"48336",
    "sg:province":"MI",
    "sg:tags":[
        "general",
        "contractor"
    ],
    "wof:name":"Blue Dot Construction",
    "wof:placetype":"venue"
},
  "geometry": {"coordinates":[-83.375524,42.443768],"type":"Point"}
}