{
  "type": "Feature",
  "properties": {
    "iso:country":"US",
    "sg:address":"3932 N Greenbrooke Dr SE",
    "sg:city":"Kentwood",
    "sg:classifiers":[
        {
            "category":"Wholesale",
            "subcategory":"Electrical",
            "type":"Manufacturing & Wholesale Goods"
        }
    ],
    "sg:phone":"+1 616 454 5594",
    "sg:postcode":"49512",
    "sg:province":"MI",
    "sg:tags":[
        "battery"
    ],
    "wof:name":"Ideal Battery Co",
    "wof:placetype":"venue"
},
  "geometry": {"coordinates":[-85.568141,42.875016],"type":"Point"}
}