{
  "type": "Feature",
  "properties": {
    "iso:country":"US",
    "sg:address":"6482 Perry Rd",
    "sg:city":"Grand Blanc",
    "sg:classifiers":[
        {
            "category":"Farming",
            "subcategory":"Nursery",
            "type":"Manufacturing & Wholesale Goods"
        }
    ],
    "sg:phone":"+1 810 694 9462",
    "sg:postcode":"48439",
    "sg:province":"MI",
    "sg:tags":[
        "greenhouse"
    ],
    "wof:name":"Miller Greenhouse",
    "wof:placetype":"venue"
},
  "geometry": {"coordinates":[-83.573784,42.932648],"type":"Point"}
}