{
  "type": "Feature",
  "properties": {
    "iso:country":"US",
    "sg:address":"32857 Peavine St",
    "sg:city":"Dowagiac",
    "sg:classifiers":[
        {
            "category":"Real Estate",
            "subcategory":"Real Estate Operator",
            "type":"Services"
        }
    ],
    "sg:phone":"+1 269 782 5023",
    "sg:postcode":"49047",
    "sg:province":"MI",
    "sg:tags":[
        "property",
        "lessor"
    ],
    "wof:name":"Joseph Schrader",
    "wof:placetype":"venue"
},
  "geometry": {"coordinates":[-86.198661,41.956356],"type":"Point"}
}