{
  "type": "Feature",
  "properties": {
    "iso:country":"US",
    "sg:address":"6560 Mack Ave",
    "sg:city":"Detroit",
    "sg:classifiers":[
        {
            "category":"Manufacturing",
            "subcategory":"Retail Goods",
            "type":"Manufacturing & Wholesale Goods"
        }
    ],
    "sg:phone":"+1 313 579 9224",
    "sg:postcode":"48207",
    "sg:province":"MI",
    "sg:tags":[
        "product",
        "mfg"
    ],
    "wof:name":"Mack Bell Manufacturing Co",
    "wof:placetype":"venue"
},
  "geometry": {"coordinates":[-83.017777,42.362594],"type":"Point"}
}