{
  "type": "Feature",
  "properties": {
    "iso:country":"US",
    "sg:address":"29222 Orchard Lake Rd",
    "sg:city":"Farmington",
    "sg:classifiers":[
        {
            "category":"Restaurant",
            "type":"Food & Drink"
        }
    ],
    "sg:phone":"+1 248 851 1122",
    "sg:postcode":"48334",
    "sg:province":"MI",
    "sg:tags":[
        "middle",
        "eastern"
    ],
    "sg:website":"www.newsahara.com/homev3.html",
    "wof:name":"New Sahara Restaurant",
    "wof:placetype":"venue"
},
  "geometry": {"coordinates":[-83.359264,42.512018],"type":"Point"}
}