{
  "type": "Feature",
  "properties": {
    "iso:country":"US",
    "sg:address":"516 10th St",
    "sg:city":"Three Rivers",
    "sg:classifiers":[
        {
            "category":"Freight",
            "type":"Transportation"
        }
    ],
    "sg:phone":"+1 269 273 2872",
    "sg:postcode":"49093",
    "sg:province":"MI",
    "sg:tags":[
        "operator",
        "local",
        "trucking"
    ],
    "wof:name":"Jims General Service",
    "wof:placetype":"venue"
},
  "geometry": {"coordinates":[-85.62224500000001,41.938029],"type":"Point"}
}