{
  "type": "Feature",
  "properties": {
    "iso:country":"US",
    "sg:address":"2805 Granger Dr",
    "sg:city":"Lansing",
    "sg:classifiers":[
        {
            "category":"Recreation",
            "type":"Entertainment"
        }
    ],
    "sg:phone":"+1 517 322 9442",
    "sg:postcode":"48917",
    "sg:province":"MI",
    "wof:name":"Pamplona Ltd",
    "wof:placetype":"venue"
},
  "geometry": {"coordinates":[-84.615889,42.70122],"type":"Point"}
}