{
  "type": "Feature",
  "properties": {
    "iso:country":"US",
    "sg:address":"5287 Mill Wheel Dr",
    "sg:city":"Grand Blanc",
    "sg:classifiers":[
        {
            "category":"Professional",
            "subcategory":"Business Services",
            "type":"Services"
        }
    ],
    "sg:phone":"+1 810 694 8082",
    "sg:postcode":"48439",
    "sg:province":"MI",
    "wof:name":"Mace Design",
    "wof:placetype":"venue"
},
  "geometry": {"coordinates":[-83.668688,42.95265],"type":"Point"}
}