{
  "type": "Feature",
  "properties": {
    "iso:country":"US",
    "sg:address":"3266 Aspenview Trl",
    "sg:city":"Walloon Lake",
    "sg:classifiers":[
        {
            "category":"Building & Trades",
            "subcategory":"Cleaning & Sanitation",
            "type":"Services"
        }
    ],
    "sg:phone":"+1 231 535 2030",
    "sg:postcode":"49713",
    "sg:province":"MI",
    "sg:tags":[
        "janitor"
    ],
    "wof:name":"Premium Cleaning",
    "wof:placetype":"venue"
},
  "geometry": {"coordinates":[-84.85767,45.247469],"type":"Point"}
}