{
  "type": "Feature",
  "properties": {
    "iso:country":"US",
    "sg:address":"1550 N Milford Rd",
    "sg:city":"Milford",
    "sg:classifiers":[
        {
            "category":"Organizations",
            "subcategory":"Membership Organization",
            "type":"Services"
        }
    ],
    "sg:phone":"+1 248 684 3408",
    "sg:postcode":"48381",
    "sg:province":"MI",
    "wof:name":"Hilda E Bretzlaff Foundation",
    "wof:placetype":"venue"
},
  "geometry": {"coordinates":[-83.61215300000001,42.607149],"type":"Point"}
}