{
  "type": "Feature",
  "properties": {
    "iso:country":"US",
    "sg:address":"4758 Territorial Rd",
    "sg:city":"Benton Harbor",
    "sg:classifiers":[
        {
            "category":"Building & Trades",
            "subcategory":"Construction",
            "type":"Services"
        }
    ],
    "sg:phone":"+1 269 876 7230",
    "sg:postcode":"49022",
    "sg:province":"MI",
    "sg:tags":[
        "resurfacing",
        "laying",
        "refinishing",
        "floor"
    ],
    "wof:name":"Berry's Hardwood Flooring",
    "wof:placetype":"venue"
},
  "geometry": {"coordinates":[-86.343166,42.122624],"type":"Point"}
}