{
  "type": "Feature",
  "properties": {
    "iso:country":"US",
    "sg:address":"2460 Midland Rd",
    "sg:city":"Bay City",
    "sg:classifiers":[
        {
            "category":"Manufacturing",
            "subcategory":"Retail Goods",
            "type":"Manufacturing & Wholesale Goods"
        }
    ],
    "sg:phone":"+1 989 686 6302",
    "sg:postcode":"48706",
    "sg:province":"MI",
    "sg:tags":[
        "manufacturer"
    ],
    "sg:website":"www.american-power.com",
    "wof:name":"American Power Connect Systems",
    "wof:placetype":"venue"
},
  "geometry": {"coordinates":[-83.956481,43.602409],"type":"Point"}
}