{
  "type": "Feature",
  "properties": {
    "iso:country":"US",
    "sg:address":"709 N US Hwy 131",
    "sg:city":"Manton",
    "sg:classifiers":[
        {
            "category":"Travel",
            "subcategory":"Hotels & Motels",
            "type":"Entertainment"
        }
    ],
    "sg:phone":"+1 231 824 3504",
    "sg:postcode":"49663",
    "sg:province":"MI",
    "wof:name":"Green Mill Motel LLC",
    "wof:placetype":"venue"
},
  "geometry": {"coordinates":[-85.398538,44.419571],"type":"Point"}
}