{
  "type": "Feature",
  "properties": {
    "iso:country":"US",
    "sg:address":"9081 Cutler Rd",
    "sg:city":"Lakeview",
    "sg:classifiers":[
        {
            "category":"Farming",
            "subcategory":"Farm & Veterinary Services",
            "type":"Manufacturing & Wholesale Goods"
        }
    ],
    "sg:phone":"+1 989 352 6731",
    "sg:postcode":"48850",
    "sg:province":"MI",
    "sg:tags":[
        "aerial",
        "applicator"
    ],
    "wof:name":"Maurice's Flying Svc",
    "wof:placetype":"venue"
},
  "geometry": {"coordinates":[-85.26307799999999,43.453672],"type":"Point"}
}