{
  "type": "Feature",
  "properties": {
    "iso:country":"US",
    "sg:address":"28 Mariva St",
    "sg:city":"Pontiac",
    "sg:classifiers":[
        {
            "category":"Building & Trades",
            "subcategory":"Electrical",
            "type":"Services"
        }
    ],
    "sg:phone":"+1 248 332 5533",
    "sg:postcode":"48342",
    "sg:province":"MI",
    "sg:tags":[
        "electric",
        "contractor"
    ],
    "wof:name":"Engineered Maintenance Corp",
    "wof:placetype":"venue"
},
  "geometry": {"coordinates":[-83.280885,42.637147],"type":"Point"}
}