{
  "type": "Feature",
  "properties": {
    "iso:country":"US",
    "sg:address":"1017 W Main St",
    "sg:city":"Fremont",
    "sg:classifiers":[
        {
            "category":"Social Services",
            "subcategory":"Job Training",
            "type":"Services"
        }
    ],
    "sg:phone":"+1 231 924 2240",
    "sg:postcode":"49412",
    "sg:province":"MI",
    "sg:tags":[
        "rehab",
        "government"
    ],
    "wof:name":"Employment Security Commission",
    "wof:placetype":"venue"
},
  "geometry": {"coordinates":[-85.96254399999999,43.467263],"type":"Point"}
}