{
  "type": "Feature",
  "properties": {
    "iso:country":"US",
    "sg:address":"16252 Marsha",
    "sg:city":"Livonia",
    "sg:classifiers":[
        {
            "category":"Building & Trades",
            "subcategory":"Cleaning & Sanitation",
            "type":"Services"
        }
    ],
    "sg:phone":"+1 248 642 2282",
    "sg:postcode":"48154",
    "sg:province":"MI",
    "sg:tags":[
        "residential",
        "maintenance"
    ],
    "wof:name":"Mr Handyman of Naples Inc",
    "wof:placetype":"venue"
},
  "geometry": {"coordinates":[-83.42228799999999,42.404657],"type":"Point"}
}