{
  "type": "Feature",
  "properties": {
    "iso:country":"US",
    "sg:address":"5 Preston St",
    "sg:city":"Coldwater",
    "sg:classifiers":[
        {
            "category":"Professional",
            "type":"Services"
        }
    ],
    "sg:phone":"+1 517 279 7581",
    "sg:postcode":"49036",
    "sg:province":"MI",
    "sg:tags":[
        "establishment"
    ],
    "wof:name":"Counter Tops & Custom Casework",
    "wof:placetype":"venue"
},
  "geometry": {"coordinates":[-85.000321,41.934091],"type":"Point"}
}