{
  "type": "Feature",
  "properties": {
    "iso:country":"US",
    "sg:address":"12500 Jones St",
    "sg:city":"Carleton",
    "sg:classifiers":[
        {
            "category":"Real Estate",
            "subcategory":"Real Estate Operator",
            "type":"Services"
        }
    ],
    "sg:phone":"+1 734 654 6203",
    "sg:postcode":"48117",
    "sg:province":"MI",
    "sg:tags":[
        "mobile",
        "home",
        "community"
    ],
    "wof:name":"Carleton Mobile Home Park",
    "wof:placetype":"venue"
},
  "geometry": {"coordinates":[-83.389222,42.05723],"type":"Point"}
}