{
  "type": "Feature",
  "properties": {
    "iso:country":"US",
    "sg:address":"143 W 2nd St",
    "sg:city":"Perry",
    "sg:classifiers":[
        {
            "category":"Building & Trades",
            "subcategory":"Construction",
            "type":"Services"
        }
    ],
    "sg:phone":"+1 517 625 4048",
    "sg:postcode":"48872",
    "sg:province":"MI",
    "sg:tags":[
        "house"
    ],
    "wof:name":"A&D Home Improvements",
    "wof:placetype":"venue"
},
  "geometry": {"coordinates":[-84.22069999999999,42.825027],"type":"Point"}
}