{
  "type": "Feature",
  "properties": {
    "iso:country":"US",
    "sg:address":"10561 Grandview Ln",
    "sg:city":"Ironwood",
    "sg:classifiers":[
        {
            "category":"Health Services",
            "subcategory":"Doctor",
            "type":"Services"
        }
    ],
    "sg:phone":"+1 906 932 2557",
    "sg:postcode":"49938",
    "sg:province":"MI",
    "sg:tags":[
        "physician",
        "surgeon"
    ],
    "wof:name":"South Shore Orthopedics",
    "wof:placetype":"venue"
},
  "geometry": {"coordinates":[-90.10472,46.478018],"type":"Point"}
}