{
  "type": "Feature",
  "properties": {
    "iso:country":"US",
    "sg:address":"6581 28th Ave",
    "sg:city":"Hudsonville",
    "sg:classifiers":[
        {
            "category":"Banks & Credit Unions",
            "subcategory":"Investment Brokerage",
            "type":"Services"
        }
    ],
    "sg:phone":"+1 616 662 8986",
    "sg:postcode":"49426",
    "sg:province":"MI",
    "sg:tags":[
        "security"
    ],
    "wof:name":"Edward Jones Co",
    "wof:placetype":"venue"
},
  "geometry": {"coordinates":[-85.851956,42.889187],"type":"Point"}
}