{
  "type": "Feature",
  "properties": {
    "iso:country":"US",
    "sg:address":"100 Frosh Dr",
    "sg:city":"West Branch",
    "sg:classifiers":[
        {
            "category":"Building & Trades",
            "subcategory":"Construction",
            "type":"Services"
        }
    ],
    "sg:phone":"+1 989 345 3516",
    "sg:postcode":"48661",
    "sg:province":"MI",
    "sg:tags":[
        "house"
    ],
    "wof:name":"Pauley Builders Inc",
    "wof:placetype":"venue"
},
  "geometry": {"coordinates":[-84.130264,44.213721],"type":"Point"}
}