{
  "type": "Feature",
  "properties": {
    "iso:country":"US",
    "sg:address":"751 Bristol Ln",
    "sg:city":"Clarkston",
    "sg:classifiers":[
        {
            "category":"Retail",
            "subcategory":"Repair Shop",
            "type":"Services"
        }
    ],
    "sg:phone":"+1 248 393 9894",
    "sg:postcode":"48348",
    "sg:province":"MI",
    "sg:tags":[
        "machine",
        "industrial"
    ],
    "wof:name":"Rapid Machine Services Inc",
    "wof:placetype":"venue"
},
  "geometry": {"coordinates":[-83.320798,42.772048],"type":"Point"}
}