{
  "type": "Feature",
  "properties": {
    "iso:country":"US",
    "sg:address":"3107 Rochester Rd",
    "sg:city":"Royal Oak",
    "sg:classifiers":[
        {
            "category":"Health Services",
            "subcategory":"Doctor",
            "type":"Services"
        }
    ],
    "sg:phone":"+1 248 583 0505",
    "sg:postcode":"48073",
    "sg:province":"MI",
    "sg:tags":[
        "dentist"
    ],
    "wof:name":"A A Dent",
    "wof:placetype":"venue"
},
  "geometry": {"coordinates":[-83.139999,42.517799],"type":"Point"}
}