{
  "type": "Feature",
  "properties": {
    "iso:country":"US",
    "sg:address":"6041 N Reek Rd",
    "sg:city":"Fountain",
    "sg:classifiers":[
        {
            "category":"Building & Trades",
            "subcategory":"Equipment Rental",
            "type":"Services"
        }
    ],
    "sg:phone":"+1 231 464 5246",
    "sg:postcode":"49410",
    "sg:province":"MI",
    "wof:name":"Ogies Partys Store",
    "wof:placetype":"venue"
},
  "geometry": {"coordinates":[-86.1806,44.069965],"type":"Point"}
}