{
  "type": "Feature",
  "properties": {
    "iso:country":"US",
    "sg:address":"5934 Ogden St",
    "sg:city":"Detroit",
    "sg:classifiers":[
        {
            "category":"Food & Beverages",
            "subcategory":"Groceries & Convenience Stores",
            "type":"Retail Goods"
        }
    ],
    "sg:phone":"+1 313 841 4196",
    "sg:postcode":"48210",
    "sg:province":"MI",
    "wof:name":"Ogden Market",
    "wof:placetype":"venue"
},
  "geometry": {"coordinates":[-83.150497,42.335701],"type":"Point"}
}