{
  "type": "Feature",
  "properties": {
    "iso:country":"US",
    "sg:address":"2407 Riley St",
    "sg:city":"Hudsonville",
    "sg:classifiers":[
        {
            "category":"Manufacturing",
            "subcategory":"Printing",
            "type":"Manufacturing & Wholesale Goods"
        }
    ],
    "sg:phone":"+1 616 662 9966",
    "sg:postcode":"49426",
    "sg:province":"MI",
    "sg:tags":[
        "screen"
    ],
    "wof:name":"Eagles Eye Graphics",
    "wof:placetype":"venue"
},
  "geometry": {"coordinates":[-85.84231200000001,42.825734],"type":"Point"}
}