{
  "type": "Feature",
  "properties": {
    "iso:country":"US",
    "sg:address":"3707 W Maple Rd",
    "sg:city":"Bloomfield Hills",
    "sg:classifiers":[
        {
            "category":"Professional",
            "subcategory":"Management & Consulting",
            "type":"Services"
        }
    ],
    "sg:phone":"+1 248 644 2872",
    "sg:postcode":"48301",
    "sg:province":"MI",
    "sg:tags":[
        "investing"
    ],
    "wof:name":"Newman Timothy A Cfp",
    "wof:placetype":"venue"
},
  "geometry": {"coordinates":[-83.264297,42.5453],"type":"Point"}
}