{
  "type": "Feature",
  "properties": {
    "iso:country":"US",
    "sg:address":"6 Fairway Dr",
    "sg:city":"Champion",
    "sg:classifiers":[
        {
            "category":"Real Estate",
            "subcategory":"Real Estate Operator",
            "type":"Services"
        }
    ],
    "sg:phone":"+1 906 485 2043",
    "sg:postcode":"49855",
    "sg:province":"MI",
    "sg:tags":[
        "apartment"
    ],
    "wof:name":"Valley View Apartments",
    "wof:placetype":"venue"
},
  "geometry": {"coordinates":[-87.421997,46.538347],"type":"Point"}
}