{
  "type": "Feature",
  "properties": {
    "iso:country":"US",
    "sg:address":"11223 E Lakewood Blvd",
    "sg:city":"Holland",
    "sg:classifiers":[
        {
            "category":"Professional",
            "subcategory":"Business Services",
            "type":"Services"
        }
    ],
    "sg:phone":"+1 616 396 0009",
    "sg:postcode":"49424",
    "sg:province":"MI",
    "sg:tags":[
        "embroidery"
    ],
    "wof:name":"Graphix Signs & Embroidery",
    "wof:placetype":"venue"
},
  "geometry": {"coordinates":[-86.059916,42.805085],"type":"Point"}
}