{
  "type": "Feature",
  "properties": {
    "iso:country":"US",
    "sg:address":"4821 Trumbull St",
    "sg:city":"Detroit",
    "sg:classifiers":[
        {
            "category":"Professional",
            "subcategory":"Business Services",
            "type":"Services"
        }
    ],
    "sg:phone":"+1 313 832 2772",
    "sg:postcode":"48208",
    "sg:province":"MI",
    "wof:name":"Video Clinic",
    "wof:placetype":"venue"
},
  "geometry": {"coordinates":[-83.07875,42.351955],"type":"Point"}
}