{
  "type": "Feature",
  "properties": {
    "iso:country":"US",
    "sg:address":"336 Co Rd 480",
    "sg:city":"Marquette",
    "sg:classifiers":[
        {
            "category":"Food & Beverages",
            "subcategory":"Meat & Fish",
            "type":"Retail Goods"
        }
    ],
    "sg:phone":"+1 906 249 1126",
    "sg:postcode":"49855",
    "sg:province":"MI",
    "wof:name":"Beaver Grove Bison",
    "wof:placetype":"venue"
},
  "geometry": {"coordinates":[-87.346797,46.463091],"type":"Point"}
}