{
  "type": "Feature",
  "properties": {
    "iso:country":"US",
    "sg:address":"5838 S Eden Lake Rd",
    "sg:city":"Custer",
    "sg:phone":"+1 231 757 3156",
    "sg:postcode":"49405",
    "sg:province":"MI",
    "sg:tags":[
        "farm",
        "grain",
        "cash"
    ],
    "wof:name":"Tiles John",
    "wof:placetype":"venue"
},
  "geometry": {"coordinates":[-86.238846,43.848484],"type":"Point"}
}