{
  "type": "Feature",
  "properties": {
    "iso:country":"US",
    "sg:address":"12935 S West-Bay Shore Dr",
    "sg:city":"Traverse City",
    "sg:classifiers":[
        {
            "category":"Professional",
            "subcategory":"Accounting & Tax Preparation",
            "type":"Services"
        }
    ],
    "sg:phone":"+1 231 922 7777",
    "sg:postcode":"49684",
    "sg:province":"MI",
    "sg:tags":[
        "accountant"
    ],
    "wof:name":"Gregory D Seman & Co",
    "wof:placetype":"venue"
},
  "geometry": {"coordinates":[-85.637558,44.790783],"type":"Point"}
}