{
  "type": "Feature",
  "properties": {
    "iso:country":"US",
    "sg:address":"6860 S Beech Daly Rd",
    "sg:city":"Taylor",
    "sg:classifiers":[
        {
            "category":"Shopping",
            "subcategory":"Clothing, Apparel, & Fashions",
            "type":"Retail Goods"
        }
    ],
    "sg:phone":"+1 313 295 3484",
    "sg:postcode":"48180",
    "sg:province":"MI",
    "wof:name":"Popular Demand",
    "wof:placetype":"venue"
},
  "geometry": {"coordinates":[-83.289382,42.255344],"type":"Point"}
}