{
  "type": "Feature",
  "properties": {
    "iso:country":"US",
    "sg:address":"24415 W Warren St",
    "sg:city":"Dearborn Heights",
    "sg:classifiers":[
        {
            "category":"Health Services",
            "subcategory":"Doctor",
            "type":"Services"
        }
    ],
    "sg:phone":"+1 313 278 4470",
    "sg:postcode":"48127",
    "sg:province":"MI",
    "wof:name":"Irving M Blau DDS PC Inc",
    "wof:placetype":"venue"
},
  "geometry": {"coordinates":[-83.27790299999999,42.341251],"type":"Point"}
}