{
  "type": "Feature",
  "properties": {
    "iso:country":"US",
    "sg:address":"10530 S Fordney Rd",
    "sg:city":"Saint Charles",
    "sg:classifiers":[
        {
            "category":"Manufacturing",
            "subcategory":"Signs",
            "type":"Manufacturing & Wholesale Goods"
        }
    ],
    "sg:phone":"+1 989 865 6516",
    "sg:postcode":"48655",
    "sg:province":"MI",
    "sg:tags":[
        "mfg"
    ],
    "wof:name":"Hauman Signs",
    "wof:placetype":"venue"
},
  "geometry": {"coordinates":[-84.189564,43.265566],"type":"Point"}
}