{
  "type": "Feature",
  "properties": {
    "iso:country":"US",
    "sg:address":"6080 Grand River Rd",
    "sg:city":"Brighton",
    "sg:classifiers":[
        {
            "category":"Shopping",
            "subcategory":"Used Merchandise",
            "type":"Retail Goods"
        }
    ],
    "sg:phone":"+1 810 225 1886",
    "sg:postcode":"48114",
    "sg:province":"MI",
    "sg:tags":[
        "repair"
    ],
    "wof:name":"Big Cheese Productions",
    "wof:placetype":"venue"
},
  "geometry": {"coordinates":[-83.833033,42.573884],"type":"Point"}
}