{
  "type": "Feature",
  "properties": {
    "iso:country":"US",
    "sg:address":"11318 Woodward Ave",
    "sg:city":"Detroit",
    "sg:classifiers":[
        {
            "category":"Food & Beverages",
            "subcategory":"Groceries & Convenience Stores",
            "type":"Retail Goods"
        }
    ],
    "sg:phone":"+1 313 867 0891",
    "sg:postcode":"48202",
    "sg:province":"MI",
    "wof:name":"A B A Market",
    "wof:placetype":"venue"
},
  "geometry": {"coordinates":[-83.086491,42.390644],"type":"Point"}
}