{
  "type": "Feature",
  "properties": {
    "iso:country":"US",
    "sg:address":"1016 W Chisholm St",
    "sg:city":"Alpena",
    "sg:classifiers":[
        {
            "category":"Retail",
            "subcategory":"Self-service Laundry",
            "type":"Services"
        }
    ],
    "sg:phone":"+1 989 595 3428",
    "sg:postcode":"49707",
    "sg:province":"MI",
    "sg:tags":[
        "coin"
    ],
    "wof:name":"West End Laundromat",
    "wof:placetype":"venue"
},
  "geometry": {"coordinates":[-83.44486499999999,45.071753],"type":"Point"}
}