{
  "type": "Feature",
  "properties": {
    "iso:country":"US",
    "sg:address":"2690 Crooks Rd Ste 316",
    "sg:city":"Troy",
    "sg:classifiers":[
        {
            "category":"Professional",
            "subcategory":"Lawyer & Legal Services",
            "type":"Services"
        }
    ],
    "sg:phone":"+1 248 362 4343",
    "sg:postcode":"48084",
    "sg:province":"MI",
    "wof:name":"Cook Michael J PC",
    "wof:placetype":"venue"
},
  "geometry": {"coordinates":[-83.167,42.558201],"type":"Point"}
}