{
  "type": "Feature",
  "properties": {
    "iso:country":"US",
    "sg:address":"222 E Maple Rd",
    "sg:city":"Birmingham",
    "sg:classifiers":[
        {
            "category":"Shopping",
            "subcategory":"Jewelry",
            "type":"Retail Goods"
        }
    ],
    "sg:phone":"+1 248 540 4500",
    "sg:postcode":"48009",
    "sg:province":"MI",
    "wof:name":"Fuchs Halina",
    "wof:placetype":"venue"
},
  "geometry": {"coordinates":[-83.213898,42.5466],"type":"Point"}
}