{
  "type": "Feature",
  "properties": {
    "iso:country":"US",
    "sg:address":"302 W Lovett St",
    "sg:city":"Charlotte",
    "sg:classifiers":[
        {
            "category":"Organizations",
            "subcategory":"Religious Organization",
            "type":"Services"
        }
    ],
    "sg:phone":"+1 517 543 1683",
    "sg:postcode":"48813",
    "sg:province":"MI",
    "sg:tags":[
        "church"
    ],
    "wof:name":"Church Of The Nazarene",
    "wof:placetype":"venue"
},
  "geometry": {"coordinates":[-84.83154999999999,42.562316],"type":"Point"}
}