{
  "type": "Feature",
  "properties": {
    "iso:country":"US",
    "sg:address":"2930 Corporate Grove Dr",
    "sg:city":"Hudsonville",
    "sg:classifiers":[
        {
            "category":"Wholesale",
            "subcategory":"Auto Parts",
            "type":"Manufacturing & Wholesale Goods"
        }
    ],
    "sg:phone":"+1 616 896 9574",
    "sg:postcode":"49426",
    "sg:province":"MI",
    "sg:tags":[
        "truck",
        "refrigeration",
        "equipment"
    ],
    "wof:name":"Carrier Transicold",
    "wof:placetype":"venue"
},
  "geometry": {"coordinates":[-85.855064,42.848056],"type":"Point"}
}