{
  "type": "Feature",
  "properties": {
    "iso:country":"US",
    "sg:address":"4626 S Center Hwy",
    "sg:city":"Suttons Bay",
    "sg:classifiers":[
        {
            "category":"Wholesale",
            "subcategory":"Construction Materials",
            "type":"Manufacturing & Wholesale Goods"
        }
    ],
    "sg:phone":"+1 231 271 6481",
    "sg:postcode":"49682",
    "sg:province":"MI",
    "sg:tags":[
        "fence"
    ],
    "wof:name":"Compass Fencing Co",
    "wof:placetype":"venue"
},
  "geometry": {"coordinates":[-85.657055,44.914171],"type":"Point"}
}