{
  "type": "Feature",
  "properties": {
    "iso:country":"US",
    "sg:address":"1000 N Washington Ave",
    "sg:city":"Lansing",
    "sg:classifiers":[
        {
            "category":"Shopping",
            "type":"Retail Goods"
        }
    ],
    "sg:phone":"+1 517 482 1283",
    "sg:postcode":"48906",
    "sg:province":"MI",
    "sg:tags":[
        "hearing",
        "aids",
        "testing",
        "offer"
    ],
    "wof:name":"Beltone Hearing Systems",
    "wof:placetype":"venue"
},
  "geometry": {"coordinates":[-84.55211799999999,42.746108],"type":"Point"}
}