{
  "type": "Feature",
  "properties": {
    "iso:country":"US",
    "sg:address":"3318 Pine Meadow Dr SE",
    "sg:city":"Grand Rapids",
    "sg:classifiers":[
        {
            "category":"Building & Trades",
            "subcategory":"Construction",
            "type":"Services"
        }
    ],
    "sg:phone":"+1 616 940 1182",
    "sg:postcode":"49512",
    "sg:province":"MI",
    "sg:tags":[
        "house"
    ],
    "wof:name":"Iwema Construction",
    "wof:placetype":"venue"
},
  "geometry": {"coordinates":[-85.56408399999999,42.904394],"type":"Point"}
}