{
  "type": "Feature",
  "properties": {
    "iso:country":"US",
    "sg:address":"325 W Hudson Ave",
    "sg:city":"Royal Oak",
    "sg:classifiers":[
        {
            "category":"Professional",
            "subcategory":"Research",
            "type":"Services"
        }
    ],
    "sg:phone":"+1 248 582 9560",
    "sg:postcode":"48067",
    "sg:province":"MI",
    "wof:name":"CCH Inc",
    "wof:placetype":"venue"
},
  "geometry": {"coordinates":[-83.147773,42.481504],"type":"Point"}
}