{
  "type": "Feature",
  "properties": {
    "iso:country":"US",
    "sg:address":"29700 Harper Ave Ste 4",
    "sg:city":"Saint Clair Shores",
    "sg:classifiers":[
        {
            "category":"Community Center",
            "type":"Public Place"
        }
    ],
    "sg:phone":"+1 586 293 8700",
    "sg:postcode":"48082",
    "sg:province":"MI",
    "sg:tags":[
        "medical"
    ],
    "wof:name":"Lakeview Diagnostics",
    "wof:placetype":"venue"
},
  "geometry": {"coordinates":[-82.898173,42.511584],"type":"Point"}
}