{
  "type": "Feature",
  "properties": {
    "iso:country":"US",
    "sg:address":"6545 Bloomfield Ln",
    "sg:city":"West Bloomfield",
    "sg:classifiers":[
        {
            "category":"Restaurant",
            "type":"Food & Drink"
        }
    ],
    "sg:phone":"+1 248 538 7870",
    "sg:postcode":"48322",
    "sg:province":"MI",
    "wof:name":"Bob's Big Boy",
    "wof:placetype":"venue"
},
  "geometry": {"coordinates":[-83.332255,42.540465],"type":"Point"}
}