{
  "type": "Feature",
  "properties": {
    "iso:country":"US",
    "sg:address":"809 Carpenter Ave",
    "sg:city":"Iron Mountain",
    "sg:classifiers":[
        {
            "category":"Personal",
            "subcategory":"Beauty Salon",
            "type":"Services"
        }
    ],
    "sg:phone":"+1 906 774 6167",
    "sg:postcode":"49801",
    "sg:province":"MI",
    "sg:tags":[
        "shop"
    ],
    "wof:name":"Hoskings Hair Lines",
    "wof:placetype":"venue"
},
  "geometry": {"coordinates":[-88.06837299999999,45.815587],"type":"Point"}
}