{
  "type": "Feature",
  "properties": {
    "iso:country":"US",
    "sg:address":"355 Town Line Rd",
    "sg:city":"Skandia",
    "sg:classifiers":[
        {
            "category":"Building & Trades",
            "subcategory":"Construction",
            "type":"Services"
        }
    ],
    "sg:phone":"+1 906 942 7254",
    "sg:postcode":"49885",
    "sg:province":"MI",
    "sg:tags":[
        "home",
        "builder"
    ],
    "wof:name":"Bell Superior Builders",
    "wof:placetype":"venue"
},
  "geometry": {"coordinates":[-87.24133399999999,46.346073],"type":"Point"}
}