{
  "type": "Feature",
  "properties": {
    "iso:country":"US",
    "sg:address":"619 Leonard St NW",
    "sg:city":"Grand Rapids",
    "sg:classifiers":[
        {
            "category":"Autos & Motor Vehicles",
            "subcategory":"Auto Supplies",
            "type":"Retail Goods"
        }
    ],
    "sg:phone":"+1 616 742 1100",
    "sg:postcode":"49504",
    "sg:province":"MI",
    "sg:tags":[
        "automobile",
        "parts"
    ],
    "wof:name":"Autozone",
    "wof:placetype":"venue"
},
  "geometry": {"coordinates":[-85.68317399999999,42.985074],"type":"Point"}
}