{
  "type": "Feature",
  "properties": {
    "iso:country":"US",
    "sg:address":"6430 E Cowan Ln",
    "sg:city":"Sault Sainte Marie",
    "sg:classifiers":[
        {
            "category":"Personal",
            "type":"Services"
        }
    ],
    "sg:phone":"+1 906 635 9646",
    "sg:postcode":"49783",
    "sg:province":"MI",
    "sg:tags":[
        "residential",
        "electrical",
        "contractor"
    ],
    "wof:name":"Matrix",
    "wof:placetype":"venue"
},
  "geometry": {"coordinates":[-84.227907,46.521215],"type":"Point"}
}