{
  "type": "Feature",
  "properties": {
    "iso:country":"US",
    "sg:address":"31050 Seneca Ln",
    "sg:city":"Novi",
    "sg:classifiers":[
        {
            "category":"Education",
            "subcategory":"Special Training",
            "type":"Public Place"
        }
    ],
    "sg:phone":"+1 248 552 7209",
    "sg:postcode":"48377",
    "sg:province":"MI",
    "wof:name":"Test Preparation Center",
    "wof:placetype":"venue"
},
  "geometry": {"coordinates":[-83.459513,42.523723],"type":"Point"}
}