{
  "type": "Feature",
  "properties": {
    "iso:country":"US",
    "sg:address":"2425 Ritchie Rd",
    "sg:city":"Gladwin",
    "sg:classifiers":[
        {
            "category":"Building & Trades",
            "subcategory":"Construction",
            "type":"Services"
        }
    ],
    "sg:phone":"+1 989 426 7002",
    "sg:postcode":"48624",
    "sg:province":"MI",
    "sg:tags":[
        "builder",
        "gazebo"
    ],
    "wof:name":"Old Time Gazebos & Decks",
    "wof:placetype":"venue"
},
  "geometry": {"coordinates":[-84.455451,44.087754],"type":"Point"}
}