{
  "type": "Feature",
  "properties": {
    "iso:country":"US",
    "sg:address":"13365 Commerce Rd",
    "sg:city":"Milford",
    "sg:classifiers":[
        {
            "category":"Building & Trades",
            "subcategory":"Plumbing",
            "type":"Services"
        }
    ],
    "sg:phone":"+1 248 685 1652",
    "sg:postcode":"48380",
    "sg:province":"MI",
    "sg:tags":[
        "contractor",
        "mechanical"
    ],
    "wof:name":"Keith Dantes Mechanical I",
    "wof:placetype":"venue"
},
  "geometry": {"coordinates":[-83.694245,42.605588],"type":"Point"}
}