{
  "type": "Feature",
  "properties": {
    "iso:country":"US",
    "sg:address":"100 W Main St",
    "sg:city":"Addison",
    "sg:classifiers":[
        {
            "category":"Personal",
            "subcategory":"Tanning Parlor",
            "type":"Services"
        }
    ],
    "sg:phone":"+1 517 547 7835",
    "sg:postcode":"49220",
    "sg:province":"MI",
    "sg:tags":[
        "salon"
    ],
    "wof:name":"Village Coin Tanning",
    "wof:placetype":"venue"
},
  "geometry": {"coordinates":[-84.348337,41.986613],"type":"Point"}
}