{
  "type": "Feature",
  "properties": {
    "iso:country":"US",
    "sg:address":"800 S Carpenter Ave",
    "sg:city":"Iron Mountain",
    "sg:classifiers":[
        {
            "category":"Retail",
            "subcategory":"Auto Repair",
            "type":"Services"
        }
    ],
    "sg:phone":"+1 906 774 0800",
    "sg:postcode":"49802",
    "sg:province":"MI",
    "sg:tags":[
        "automotive"
    ],
    "wof:name":"Protech Lube & Wash",
    "wof:placetype":"venue"
},
  "geometry": {"coordinates":[-88.07110900000001,45.799425],"type":"Point"}
}