{
  "type": "Feature",
  "properties": {
    "iso:country":"US",
    "sg:address":"3927 28th St SE",
    "sg:city":"Grand Rapids",
    "sg:classifiers":[
        {
            "category":"Shopping",
            "subcategory":"Tobacco",
            "type":"Retail Goods"
        }
    ],
    "sg:phone":"+1 616 977 0199",
    "sg:postcode":"49512",
    "sg:province":"MI",
    "sg:tags":[
        "cigarette",
        "cigar",
        "dealer"
    ],
    "wof:name":"Admiral Discount Tobacco",
    "wof:placetype":"venue"
},
  "geometry": {"coordinates":[-85.573415,42.912604],"type":"Point"}
}