{
  "type": "Feature",
  "properties": {
    "iso:country":"US",
    "sg:address":"958 Oaklawn St NE",
    "sg:city":"Grand Rapids",
    "sg:classifiers":[
        {
            "category":"Professional",
            "subcategory":"Business Services",
            "type":"Services"
        }
    ],
    "sg:phone":"+1 616 364 1004",
    "sg:postcode":"49505",
    "sg:province":"MI",
    "wof:name":"Agape Coffee Systems",
    "wof:placetype":"venue"
},
  "geometry": {"coordinates":[-85.647218,43.008999],"type":"Point"}
}