{
  "type": "Feature",
  "properties": {
    "iso:country":"US",
    "sg:address":"7091 Conservation St NE",
    "sg:city":"Ada",
    "sg:classifiers":[
        {
            "category":"Professional",
            "subcategory":"Business Services",
            "type":"Services"
        }
    ],
    "sg:phone":"+1 616 676 9273",
    "sg:postcode":"49301",
    "sg:province":"MI",
    "wof:name":"Keynote Interiors",
    "wof:placetype":"venue"
},
  "geometry": {"coordinates":[-85.496759,42.979047],"type":"Point"}
}