{
  "type": "Feature",
  "properties": {
    "iso:country":"US",
    "sg:address":"1020 S Creyts Rd",
    "sg:city":"Lansing",
    "sg:classifiers":[
        {
            "category":"Real Estate",
            "subcategory":"Real Estate Services",
            "type":"Services"
        },
        {
            "category":"Real Estate",
            "subcategory":"Real Estate Agent",
            "type":"Services"
        }
    ],
    "sg:phone":"+1 517 321 1000",
    "sg:postcode":"48917",
    "sg:province":"MI",
    "sg:tags":[
        "consultant"
    ],
    "sg:website":"http://www.cb-hb.com",
    "wof:name":"Coldwell Banker Hubbell Briarwood",
    "wof:placetype":"venue"
},
  "geometry": {"coordinates":[-84.64235499999999,42.723737],"type":"Point"}
}