{
  "type": "Feature",
  "properties": {
    "iso:country":"US",
    "sg:address":"29820 Joy Rd",
    "sg:city":"Livonia",
    "sg:classifiers":[
        {
            "category":"Education",
            "subcategory":"Dance Studio",
            "type":"Public Place"
        }
    ],
    "sg:phone":"+1 734 513 2004",
    "sg:postcode":"48150",
    "sg:province":"MI",
    "sg:tags":[
        "art",
        "performing",
        "instruction",
        "dancing"
    ],
    "wof:name":"Deborah Chase School of Dance",
    "wof:placetype":"venue"
},
  "geometry": {"coordinates":[-83.33669999999999,42.354698],"type":"Point"}
}