{
  "type": "Feature",
  "properties": {
    "iso:country":"US",
    "sg:address":"3820 W Saginaw St",
    "sg:city":"Lansing",
    "sg:classifiers":[
        {
            "category":"Banks & Credit Unions",
            "subcategory":"Bank",
            "type":"Services"
        }
    ],
    "sg:phone":"+1 517 334 1685",
    "sg:postcode":"48917",
    "sg:province":"MI",
    "wof:name":"National City Bank",
    "wof:placetype":"venue"
},
  "geometry": {"coordinates":[-84.601812,42.741169],"type":"Point"}
}