{
  "type": "Feature",
  "properties": {
    "iso:country":"US",
    "sg:address":"22048 Hampton Ct",
    "sg:city":"Trenton",
    "sg:classifiers":[
        {
            "category":"Social Services",
            "subcategory":"Adult Care",
            "type":"Services"
        }
    ],
    "sg:phone":"+1 734 676 0142",
    "sg:postcode":"48183",
    "sg:province":"MI",
    "sg:tags":[
        "foster"
    ],
    "wof:name":"West Jefferson",
    "wof:placetype":"venue"
},
  "geometry": {"coordinates":[-83.247404,42.127492],"type":"Point"}
}