{
  "type": "Feature",
  "properties": {
    "iso:country":"US",
    "sg:address":"5825 Three Ponds Ct",
    "sg:city":"West Bloomfield",
    "sg:classifiers":[
        {
            "category":"Professional",
            "subcategory":"Management & Consulting",
            "type":"Services"
        }
    ],
    "sg:phone":"+1 248 363 0684",
    "sg:postcode":"48324",
    "sg:province":"MI",
    "sg:tags":[
        "asset"
    ],
    "wof:name":"Tcr Consulting LLP",
    "wof:placetype":"venue"
},
  "geometry": {"coordinates":[-83.400363,42.611962],"type":"Point"}
}