{
  "type": "Feature",
  "properties": {
    "iso:country":"US",
    "sg:address":"205 E Watson St",
    "sg:city":"Albion",
    "sg:classifiers":[
        {
            "category":"Real Estate",
            "subcategory":"Real Estate Operator",
            "type":"Services"
        }
    ],
    "sg:phone":"+1 517 629 8170",
    "sg:postcode":"49224",
    "sg:province":"MI",
    "sg:tags":[
        "building",
        "apartment",
        "apt"
    ],
    "wof:name":"Carriage House Apartments",
    "wof:placetype":"venue"
},
  "geometry": {"coordinates":[-84.74755999999999,42.258891],"type":"Point"}
}