{
  "type": "Feature",
  "properties": {
    "iso:country":"US",
    "sg:address":"5756 Lillian Ln",
    "sg:city":"Traverse City",
    "sg:classifiers":[
        {
            "category":"Building & Trades",
            "subcategory":"Construction",
            "type":"Services"
        }
    ],
    "sg:phone":"+1 231 943 9110",
    "sg:postcode":"49684",
    "sg:province":"MI",
    "sg:tags":[
        "painter"
    ],
    "wof:name":"Preferred Painting Etc",
    "wof:placetype":"venue"
},
  "geometry": {"coordinates":[-85.691025,44.687027],"type":"Point"}
}