{
  "type": "Feature",
  "properties": {
    "iso:country":"US",
    "sg:address":"7471 Hudson Rd",
    "sg:city":"Osseo",
    "sg:classifiers":[
        {
            "category":"Building & Trades",
            "subcategory":"Construction",
            "type":"Services"
        }
    ],
    "sg:phone":"+1 517 523 2528",
    "sg:postcode":"49266",
    "sg:province":"MI",
    "sg:tags":[
        "contractor"
    ],
    "wof:name":"P & M Roofing & Siding",
    "wof:placetype":"venue"
},
  "geometry": {"coordinates":[-84.50602000000001,41.869666],"type":"Point"}
}