{
  "type": "Feature",
  "properties": {
    "iso:country":"US",
    "sg:address":"4895 Leland Rd",
    "sg:city":"Laingsburg",
    "sg:classifiers":[
        {
            "category":"Building & Trades",
            "subcategory":"Electrical",
            "type":"Services"
        }
    ],
    "sg:phone":"+1 517 651 2100",
    "sg:postcode":"48848",
    "sg:province":"MI",
    "sg:tags":[
        "electric",
        "contractor"
    ],
    "wof:name":"Lainghollow Electric",
    "wof:placetype":"venue"
},
  "geometry": {"coordinates":[-84.332606,42.924318],"type":"Point"}
}