{
  "type": "Feature",
  "properties": {
    "iso:country":"US",
    "sg:address":"5813 Schade Dr",
    "sg:city":"Midland",
    "sg:classifiers":[
        {
            "category":"Professional",
            "subcategory":"Business Services",
            "type":"Services"
        }
    ],
    "sg:phone":"+1 989 631 7426",
    "sg:postcode":"48640",
    "sg:province":"MI",
    "wof:name":"Mvmca Limited Partnership",
    "wof:placetype":"venue"
},
  "geometry": {"coordinates":[-84.25708299999999,43.652418],"type":"Point"}
}