{
  "type": "Feature",
  "properties": {
    "iso:country":"US",
    "sg:address":"17677 Mack Ave",
    "sg:city":"Detroit",
    "sg:classifiers":[
        {
            "category":"Autos & Motor Vehicles",
            "subcategory":"Automobile Sales",
            "type":"Retail Goods"
        }
    ],
    "sg:phone":"+1 313 886 1700",
    "sg:postcode":"48224",
    "sg:province":"MI",
    "sg:tags":[
        "car"
    ],
    "wof:name":"Laethem Pontiac",
    "wof:placetype":"venue"
},
  "geometry": {"coordinates":[-82.918098,42.401299],"type":"Point"}
}