{
  "type": "Feature",
  "properties": {
    "iso:country":"US",
    "sg:address":"5275 Beckley Rd",
    "sg:city":"Battle Creek",
    "sg:classifiers":[
        {
            "category":"Personal",
            "subcategory":"Beauty Salon",
            "type":"Services"
        }
    ],
    "sg:phone":"+1 269 788 6700",
    "sg:postcode":"49015",
    "sg:province":"MI",
    "sg:tags":[
        "manicuring"
    ],
    "wof:name":"Prestige Nail Spa",
    "wof:placetype":"venue"
},
  "geometry": {"coordinates":[-85.195626,42.261113],"type":"Point"}
}