{
  "type": "Feature",
  "properties": {
    "iso:country":"US",
    "sg:address":"527 E Morley Dr",
    "sg:city":"Saginaw",
    "sg:classifiers":[
        {
            "category":"Freight",
            "type":"Transportation"
        }
    ],
    "sg:phone":"+1 989 755 3000",
    "sg:postcode":"48601",
    "sg:province":"MI",
    "sg:tags":[
        "mover"
    ],
    "sg:website":"www.stevensworldwide.com",
    "wof:name":"Stevens Worldwide Van Lines",
    "wof:placetype":"venue"
},
  "geometry": {"coordinates":[-83.867968,43.419156],"type":"Point"}
}