{
  "type": "Feature",
  "properties": {
    "iso:country":"US",
    "sg:address":"745 Hillcrest Cir",
    "sg:city":"Auburn Hills",
    "sg:classifiers":[
        {
            "category":"Banks & Credit Unions",
            "subcategory":"Financial Services",
            "type":"Services"
        }
    ],
    "sg:phone":"+1 248 451 9365",
    "sg:postcode":"48326",
    "sg:province":"MI",
    "sg:tags":[
        "company",
        "holding"
    ],
    "wof:name":"T K Holding",
    "wof:placetype":"venue"
},
  "geometry": {"coordinates":[-83.320956,42.703939],"type":"Point"}
}