{
  "type": "Feature",
  "properties": {
    "iso:country":"US",
    "sg:address":"756 N Nolet Rd",
    "sg:city":"Essexville",
    "sg:phone":"+1 989 892 2938",
    "sg:postcode":"48732",
    "sg:province":"MI",
    "sg:tags":[
        "farm",
        "beet",
        "soybean"
    ],
    "wof:name":"Gary Beslaer",
    "wof:placetype":"venue"
},
  "geometry": {"coordinates":[-83.73942099999999,43.583668],"type":"Point"}
}