{
  "type": "Feature",
  "properties": {
    "iso:country":"US",
    "sg:address":"30780 Southfield Rd",
    "sg:city":"Southfield",
    "sg:classifiers":[
        {
            "category":"Restaurant",
            "type":"Food & Drink"
        }
    ],
    "sg:phone":"+1 248 594 8888",
    "sg:postcode":"48076",
    "sg:province":"MI",
    "sg:tags":[
        "seafood"
    ],
    "wof:name":"Detroit Shrimp & Fish",
    "wof:placetype":"venue"
},
  "geometry": {"coordinates":[-83.223099,42.515598],"type":"Point"}
}