{
  "type": "Feature",
  "properties": {
    "iso:country":"US",
    "sg:address":"35335 Spring Hill Rd",
    "sg:city":"Farmington Hills",
    "sg:classifiers":[
        {
            "category":"Insurance",
            "subcategory":"Insurance Agent",
            "type":"Services"
        }
    ],
    "sg:phone":"+1 248 661 8605",
    "sg:postcode":"48331",
    "sg:province":"MI",
    "wof:name":"Midwest Insurance Agency",
    "wof:placetype":"venue"
},
  "geometry": {"coordinates":[-83.397538,42.52128],"type":"Point"}
}