{
  "type": "Feature",
  "properties": {
    "iso:country":"US",
    "sg:address":"5390 Highland Rd",
    "sg:city":"Waterford",
    "sg:classifiers":[
        {
            "category":"Manufacturing",
            "subcategory":"Printing",
            "type":"Manufacturing & Wholesale Goods"
        }
    ],
    "sg:phone":"+1 248 673 1251",
    "sg:postcode":"48327",
    "sg:province":"MI",
    "sg:tags":[
        "printer"
    ],
    "wof:name":"Arrow Printing & Office Supply",
    "wof:placetype":"venue"
},
  "geometry": {"coordinates":[-83.39537,42.660256],"type":"Point"}
}