{
  "type": "Feature",
  "properties": {
    "iso:country":"US",
    "sg:address":"1940 N Branch Rd",
    "sg:city":"North Branch",
    "sg:phone":"+1 810 688 2795",
    "sg:postcode":"48461",
    "sg:province":"MI",
    "sg:tags":[
        "farm",
        "corn",
        "soybean"
    ],
    "wof:name":"Sutter Farms",
    "wof:placetype":"venue"
},
  "geometry": {"coordinates":[-83.27647,43.227508],"type":"Point"}
}