{
  "type": "Feature",
  "properties": {
    "iso:country":"US",
    "sg:address":"9081 Anchor Bay Dr",
    "sg:city":"Clay",
    "sg:classifiers":[
        {
            "category":"Recreation",
            "subcategory":"Marina",
            "type":"Entertainment"
        }
    ],
    "sg:phone":"+1 810 794 4641",
    "sg:postcode":"48001",
    "sg:province":"MI",
    "sg:tags":[
        "storage",
        "boat"
    ],
    "wof:name":"Deckers Landing Marina",
    "wof:placetype":"venue"
},
  "geometry": {"coordinates":[-82.624257,42.650843],"type":"Point"}
}