{
  "type": "Feature",
  "properties": {
    "iso:country":"US",
    "sg:address":"305 E Grand River Ave",
    "sg:city":"Lansing",
    "sg:classifiers":[
        {
            "category":"Professional",
            "subcategory":"Business Services",
            "type":"Services"
        }
    ],
    "sg:phone":"+1 517 487 1188",
    "sg:postcode":"48906",
    "sg:province":"MI",
    "sg:tags":[
        "consultant",
        "commercial",
        "design",
        "residential",
        "interior",
        "decorator"
    ],
    "wof:name":"Pleats Interior Design Inc",
    "wof:placetype":"venue"
},
  "geometry": {"coordinates":[-84.548019,42.747399],"type":"Point"}
}