{
  "type": "Feature",
  "properties": {
    "iso:country":"US",
    "sg:address":"32231 Schoolcraft Rd",
    "sg:city":"Livonia",
    "sg:classifiers":[
        {
            "category":"Social Services",
            "subcategory":"Adult Care",
            "type":"Services"
        }
    ],
    "sg:phone":"+1 734 458 8140",
    "sg:postcode":"48150",
    "sg:province":"MI",
    "sg:tags":[
        "personal",
        "residential",
        "vocational",
        "for",
        "mental"
    ],
    "wof:name":"Quest Inc",
    "wof:placetype":"venue"
},
  "geometry": {"coordinates":[-83.362297,42.382325],"type":"Point"}
}