{
  "type": "Feature",
  "properties": {
    "iso:country":"US",
    "sg:address":"2411 14th St",
    "sg:city":"Detroit",
    "sg:classifiers":[
        {
            "category":"Government",
            "subcategory":"Office",
            "type":"Public Place"
        }
    ],
    "sg:phone":"+1 313 965 5853",
    "sg:postcode":"48216",
    "sg:province":"MI",
    "sg:tags":[
        "development"
    ],
    "wof:name":"Greater Corktown Development",
    "wof:placetype":"venue"
},
  "geometry": {"coordinates":[-83.076795,42.3317],"type":"Point"}
}