{
  "type": "Feature",
  "properties": {
    "iso:country":"US",
    "sg:address":"890 North Ave",
    "sg:city":"Battle Creek",
    "sg:classifiers":[
        {
            "category":"Food & Beverages",
            "subcategory":"Specialty",
            "type":"Retail Goods"
        }
    ],
    "sg:phone":"+1 269 968 8808",
    "sg:postcode":"49017",
    "sg:province":"MI",
    "wof:name":"Natures Blessing",
    "wof:placetype":"venue"
},
  "geometry": {"coordinates":[-85.180623,42.348607],"type":"Point"}
}