{
  "type": "Feature",
  "properties": {
    "iso:country":"US",
    "sg:address":"1860 Yosemite Blvd",
    "sg:city":"Birmingham",
    "sg:classifiers":[
        {
            "category":"Professional",
            "subcategory":"Management & Consulting",
            "type":"Services"
        }
    ],
    "sg:phone":"+1 248 320 1100",
    "sg:postcode":"48009",
    "sg:province":"MI",
    "wof:name":"Hipersol",
    "wof:placetype":"venue"
},
  "geometry": {"coordinates":[-83.196445,42.546143],"type":"Point"}
}