{
  "type": "Feature",
  "properties": {
    "iso:country":"US",
    "sg:address":"26049 Helen Rd",
    "sg:city":"Sturgis",
    "sg:classifiers":[
        {
            "category":"Shopping",
            "subcategory":"Discount & Variety Stores",
            "type":"Retail Goods"
        }
    ],
    "sg:phone":"+1 269 659 4185",
    "sg:postcode":"49091",
    "sg:province":"MI",
    "sg:tags":[
        "merchandise",
        "general"
    ],
    "wof:name":"Edwards Fe Co",
    "wof:placetype":"venue"
},
  "geometry": {"coordinates":[-85.446844,41.785686],"type":"Point"}
}