{
  "type": "Feature",
  "properties": {
    "iso:country":"US",
    "sg:address":"35277 Dunston Dr",
    "sg:city":"Sterling Heights",
    "sg:classifiers":[
        {
            "category":"Building & Trades",
            "subcategory":"Construction",
            "type":"Services"
        }
    ],
    "sg:phone":"+1 586 979 2997",
    "sg:postcode":"48310",
    "sg:province":"MI",
    "sg:tags":[
        "painter"
    ],
    "wof:name":"Spring Painting Inc",
    "wof:placetype":"venue"
},
  "geometry": {"coordinates":[-83.074709,42.552422],"type":"Point"}
}