{
  "type": "Feature",
  "properties": {
    "iso:country":"US",
    "sg:address":"14474 Ellen Dr",
    "sg:city":"Livonia",
    "sg:classifiers":[
        {
            "category":"Building & Trades",
            "subcategory":"Plumbing",
            "type":"Services"
        }
    ],
    "sg:phone":"+1 734 464 6100",
    "sg:postcode":"48154",
    "sg:province":"MI",
    "sg:tags":[
        "contractor"
    ],
    "wof:name":"Acme Heating & Cooling Co",
    "wof:placetype":"venue"
},
  "geometry": {"coordinates":[-83.38972800000001,42.389292],"type":"Point"}
}