{
  "type": "Feature",
  "properties": {
    "iso:country":"US",
    "sg:address":"4721 Zemmer Rd",
    "sg:city":"Columbiaville",
    "sg:classifiers":[
        {
            "category":"Personal",
            "subcategory":"Beauty Salon",
            "type":"Services"
        }
    ],
    "sg:phone":"+1 810 793 4848",
    "sg:postcode":"48421",
    "sg:province":"MI",
    "sg:tags":[
        "shop"
    ],
    "wof:name":"A Head Above LLC",
    "wof:placetype":"venue"
},
  "geometry": {"coordinates":[-83.413797,43.134987],"type":"Point"}
}