{
  "type": "Feature",
  "properties": {
    "iso:country":"US",
    "sg:address":"3148 Plainfield Ave NE",
    "sg:city":"Grand Rapids",
    "sg:classifiers":[
        {
            "category":"Building & Trades",
            "subcategory":"Construction",
            "type":"Services"
        }
    ],
    "sg:phone":"+1 616 235 2432",
    "sg:postcode":"49525",
    "sg:province":"MI",
    "sg:tags":[
        "general",
        "caulking",
        "contractor"
    ],
    "wof:name":"Associated Construction Svc",
    "wof:placetype":"venue"
},
  "geometry": {"coordinates":[-85.634833,43.020043],"type":"Point"}
}