{
  "type": "Feature",
  "properties": {
    "iso:country":"US",
    "sg:address":"67873 Lake Angela Dr",
    "sg:city":"Richmond",
    "sg:classifiers":[
        {
            "category":"Organizations",
            "subcategory":"Non-profit Organization",
            "type":"Services"
        }
    ],
    "sg:phone":"+1 586 727 4246",
    "sg:postcode":"48062",
    "sg:province":"MI",
    "sg:tags":[
        "social"
    ],
    "wof:name":"Just 4 Kids",
    "wof:placetype":"venue"
},
  "geometry": {"coordinates":[-82.739137,42.801687],"type":"Point"}
}