{
  "type": "Feature",
  "properties": {
    "iso:country":"US",
    "sg:address":"336 S Main St",
    "sg:city":"Rochester",
    "sg:classifiers":[
        {
            "category":"Retail",
            "subcategory":"Auto Repair",
            "type":"Services"
        }
    ],
    "sg:phone":"+1 248 650 3365",
    "sg:postcode":"48307",
    "sg:province":"MI",
    "sg:tags":[
        "automotive",
        "consultant"
    ],
    "wof:name":"Leoni Cable Inc",
    "wof:placetype":"venue"
},
  "geometry": {"coordinates":[-83.133684,42.680227],"type":"Point"}
}