{
  "type": "Feature",
  "properties": {
    "iso:country":"US",
    "sg:address":"117 N 1st St",
    "sg:city":"Ann Arbor",
    "sg:classifiers":[
        {
            "category":"Professional",
            "subcategory":"Business Services",
            "type":"Services"
        }
    ],
    "sg:phone":"+1 734 930 0011",
    "sg:postcode":"48104",
    "sg:province":"MI",
    "wof:name":"Business Realastate Netwrk LLC",
    "wof:placetype":"venue"
},
  "geometry": {"coordinates":[-83.750973,42.282288],"type":"Point"}
}