{
  "type": "Feature",
  "properties": {
    "iso:country":"US",
    "sg:address":"2171 Bankers Rd",
    "sg:city":"Hillsdale",
    "sg:classifiers":[
        {
            "category":"Sports & Exercise",
            "subcategory":"Golf",
            "type":"Entertainment"
        }
    ],
    "sg:phone":"+1 517 437 3434",
    "sg:postcode":"49242",
    "sg:province":"MI",
    "sg:tags":[
        "course"
    ],
    "wof:name":"White Oaks Golf Course",
    "wof:placetype":"venue"
},
  "geometry": {"coordinates":[-84.66915899999999,41.897999],"type":"Point"}
}