{
  "type": "Feature",
  "properties": {
    "iso:country":"US",
    "sg:address":"18518 Bishop Rd",
    "sg:city":"Chesaning",
    "sg:classifiers":[
        {
            "category":"Building & Trades",
            "subcategory":"Construction",
            "type":"Services"
        }
    ],
    "sg:phone":"+1 989 845 3368",
    "sg:postcode":"48616",
    "sg:province":"MI",
    "sg:tags":[
        "resurfacing",
        "laying",
        "refinishing",
        "floor"
    ],
    "wof:name":"C & C Harris Wood Floors",
    "wof:placetype":"venue"
},
  "geometry": {"coordinates":[-84.02831,43.153362],"type":"Point"}
}