{
  "type": "Feature",
  "properties": {
    "iso:country":"US",
    "sg:address":"30861 John R Rd",
    "sg:city":"Madison Heights",
    "sg:classifiers":[
        {
            "category":"Autos & Motor Vehicles",
            "subcategory":"Fuel & Gas Station",
            "type":"Retail Goods"
        }
    ],
    "sg:phone":"+1 248 589 9676",
    "sg:postcode":"48071",
    "sg:province":"MI",
    "sg:tags":[
        "oil"
    ],
    "wof:name":"Crescent Petroleum Inc",
    "wof:placetype":"venue"
},
  "geometry": {"coordinates":[-83.106499,42.519199],"type":"Point"}
}