{
  "type": "Feature",
  "properties": {
    "iso:country":"US",
    "sg:address":"810 Harrison St",
    "sg:city":"Belding",
    "sg:classifiers":[
        {
            "category":"Retail",
            "subcategory":"Repair Shop",
            "type":"Services"
        }
    ],
    "sg:phone":"+1 616 794 3270",
    "sg:postcode":"48809",
    "sg:province":"MI",
    "sg:tags":[
        "upholsterer"
    ],
    "wof:name":"Rackham's Custom Upholstery",
    "wof:placetype":"venue"
},
  "geometry": {"coordinates":[-85.213342,43.098292],"type":"Point"}
}