{
  "type": "Feature",
  "properties": {
    "iso:country":"US",
    "sg:address":"234 W Michigan Ave",
    "sg:city":"Jackson",
    "sg:classifiers":[
        {
            "category":"Organizations",
            "subcategory":"Religious Organization",
            "type":"Services"
        }
    ],
    "sg:phone":"+1 517 782 4128",
    "sg:postcode":"49201",
    "sg:province":"MI",
    "sg:tags":[
        "church"
    ],
    "wof:name":"Christian Science Reading Room",
    "wof:placetype":"venue"
},
  "geometry": {"coordinates":[-84.41162199999999,42.247528],"type":"Point"}
}