{
  "type": "Feature",
  "properties": {
    "iso:country":"US",
    "sg:address":"2509 56th St",
    "sg:city":"Fennville",
    "sg:classifiers":[
        {
            "category":"Building & Trades",
            "subcategory":"Cleaning & Sanitation",
            "type":"Services"
        }
    ],
    "sg:phone":"+1 616 394 9975",
    "sg:postcode":"49408",
    "sg:province":"MI",
    "sg:tags":[
        "janitor"
    ],
    "wof:name":"Extreme Clean Building Svc",
    "wof:placetype":"venue"
},
  "geometry": {"coordinates":[-86.094629,42.608417],"type":"Point"}
}