{
  "type": "Feature",
  "properties": {
    "iso:country":"US",
    "sg:address":"1196 Glen Ct",
    "sg:city":"Ann Arbor",
    "sg:classifiers":[
        {
            "category":"Professional",
            "subcategory":"Art Services",
            "type":"Services"
        }
    ],
    "sg:phone":"+1 734 668 8510",
    "sg:postcode":"48103",
    "sg:province":"MI",
    "sg:tags":[
        "commercial",
        "design"
    ],
    "wof:name":"Ruby Ruby Productions",
    "wof:placetype":"venue"
},
  "geometry": {"coordinates":[-83.868621,42.267694],"type":"Point"}
}