{
  "type": "Feature",
  "properties": {
    "iso:country":"US",
    "sg:address":"934 Industrial Pkwy",
    "sg:city":"Plainwell",
    "sg:classifiers":[
        {
            "category":"Wholesale",
            "subcategory":"Machinery & Supplies",
            "type":"Manufacturing & Wholesale Goods"
        }
    ],
    "sg:phone":"+1 269 685 9583",
    "sg:postcode":"49080",
    "sg:province":"MI",
    "sg:tags":[
        "pump"
    ],
    "wof:name":"N R Mitchell Co",
    "wof:placetype":"venue"
},
  "geometry": {"coordinates":[-85.628378,42.447954],"type":"Point"}
}