{
  "type": "Feature",
  "properties": {
    "iso:country":"US",
    "sg:address":"7096 Alden Hwy",
    "sg:city":"Bellaire",
    "sg:classifiers":[
        {
            "category":"Building & Trades",
            "subcategory":"Construction",
            "type":"Services"
        }
    ],
    "sg:phone":"+1 231 331 6531",
    "sg:postcode":"49615",
    "sg:province":"MI",
    "sg:tags":[
        "water",
        "well",
        "drilling"
    ],
    "wof:name":"Orin's Well Drilling",
    "wof:placetype":"venue"
},
  "geometry": {"coordinates":[-85.24018599999999,44.903094],"type":"Point"}
}