{
  "type": "Feature",
  "properties": {
    "iso:country":"US",
    "sg:address":"605 E Carpenter St",
    "sg:city":"Midland",
    "sg:classifiers":[
        {
            "category":"Social Services",
            "type":"Services"
        }
    ],
    "sg:phone":"+1 989 832 5184",
    "sg:postcode":"48640",
    "sg:province":"MI",
    "wof:name":"Formery Kidtricity",
    "wof:placetype":"venue"
},
  "geometry": {"coordinates":[-84.233909,43.615557],"type":"Point"}
}