{
  "type": "Feature",
  "properties": {
    "iso:country":"US",
    "sg:address":"1021 Wild Ginger Trl",
    "sg:city":"Haslett",
    "sg:classifiers":[
        {
            "category":"Professional",
            "subcategory":"Business Services",
            "type":"Services"
        }
    ],
    "sg:phone":"+1 517 256 1939",
    "sg:postcode":"48840",
    "sg:province":"MI",
    "wof:name":"Convertitcom Inc",
    "wof:placetype":"venue"
},
  "geometry": {"coordinates":[-84.38417800000001,42.760323],"type":"Point"}
}