{
  "type": "Feature",
  "properties": {
    "iso:country":"US",
    "sg:address":"3174 E V Ave",
    "sg:city":"Vicksburg",
    "sg:classifiers":[
        {
            "category":"Social Services",
            "subcategory":"Child Care",
            "type":"Services"
        }
    ],
    "sg:phone":"+1 269 649 1893",
    "sg:postcode":"49097",
    "sg:province":"MI",
    "sg:tags":[
        "day"
    ],
    "wof:name":"Adkins Daycare",
    "wof:placetype":"venue"
},
  "geometry": {"coordinates":[-85.550454,42.128658],"type":"Point"}
}