{
  "type": "Feature",
  "properties": {
    "iso:country":"US",
    "sg:address":"21700 Greenfield Rd",
    "sg:city":"Oak Park",
    "sg:classifiers":[
        {
            "category":"Banks & Credit Unions",
            "subcategory":"Bank",
            "type":"Services"
        }
    ],
    "sg:phone":"+1 248 967 2274",
    "sg:postcode":"48237",
    "sg:province":"MI",
    "sg:tags":[
        "loan",
        "broker",
        "mortgage"
    ],
    "wof:name":"Allied Home Mrtg Capitl Corp",
    "wof:placetype":"venue"
},
  "geometry": {"coordinates":[-83.20080799999999,42.452886],"type":"Point"}
}