{
  "type": "Feature",
  "properties": {
    "iso:country":"US",
    "sg:address":"177 S Main St",
    "sg:city":"Vermontville",
    "sg:classifiers":[
        {
            "category":"Bars & Pubs",
            "type":"Food & Drink"
        }
    ],
    "sg:phone":"+1 517 726 1043",
    "sg:postcode":"49096",
    "sg:province":"MI",
    "wof:name":"Roadrunners",
    "wof:placetype":"venue"
},
  "geometry": {"coordinates":[-85.024719,42.627792],"type":"Point"}
}