{
  "type": "Feature",
  "properties": {
    "iso:country":"US",
    "sg:address":"8300 Thornapple River Dr SE",
    "sg:city":"Caledonia",
    "sg:classifiers":[
        {
            "category":"Professional",
            "subcategory":"Employment Agencies",
            "type":"Services"
        }
    ],
    "sg:phone":"+1 616 891 2160",
    "sg:postcode":"49316",
    "sg:province":"MI",
    "wof:name":"Iba of Grand Rapids",
    "wof:placetype":"venue"
},
  "geometry": {"coordinates":[-85.48755,42.813823],"type":"Point"}
}