{
  "type": "Feature",
  "properties": {
    "iso:country":"US",
    "sg:address":"111 S Michigan Ave",
    "sg:city":"Saginaw",
    "sg:classifiers":[
        {
            "category":"Government",
            "subcategory":"Office",
            "type":"Public Place"
        }
    ],
    "sg:phone":"+1 989 790 5225",
    "sg:postcode":"48602",
    "sg:province":"MI",
    "sg:tags":[
        "county",
        "taxation"
    ],
    "sg:website":"www.saginawcounty.com",
    "wof:name":"County Treasurer",
    "wof:placetype":"venue"
},
  "geometry": {"coordinates":[-83.965294,43.416969],"type":"Point"}
}