{
  "type": "Feature",
  "properties": {
    "iso:country":"US",
    "sg:address":"106 Meath Rd",
    "sg:city":"Eaton Rapids",
    "sg:classifiers":[
        {
            "category":"Building & Trades",
            "subcategory":"Construction",
            "type":"Services"
        }
    ],
    "sg:phone":"+1 517 663 8540",
    "sg:postcode":"48827",
    "sg:province":"MI",
    "sg:tags":[
        "hanging",
        "contractor"
    ],
    "wof:name":"Honsowitz Painters Inc",
    "wof:placetype":"venue"
},
  "geometry": {"coordinates":[-84.64626800000001,42.511801],"type":"Point"}
}