{
  "type": "Feature",
  "properties": {
    "iso:country":"US",
    "sg:address":"51751 County Line Rd",
    "sg:city":"New Baltimore",
    "sg:classifiers":[
        {
            "category":"Manufacturing",
            "subcategory":"Metals",
            "type":"Manufacturing & Wholesale Goods"
        }
    ],
    "sg:phone":"+1 586 725 1235",
    "sg:postcode":"48047",
    "sg:province":"MI",
    "sg:tags":[
        "fabricated",
        "mfg"
    ],
    "wof:name":"Guardian Division of Elson",
    "wof:placetype":"venue"
},
  "geometry": {"coordinates":[-82.72865299999999,42.689645],"type":"Point"}
}