{
  "type": "Feature",
  "properties": {
    "iso:country":"US",
    "sg:address":"25900 W 11 Mile Rd",
    "sg:city":"Southfield",
    "sg:classifiers":[
        {
            "category":"Professional",
            "subcategory":"Accounting & Tax Preparation",
            "type":"Services"
        }
    ],
    "sg:phone":"+1 248 304 1700",
    "sg:postcode":"48034",
    "sg:province":"MI",
    "sg:tags":[
        "accountant"
    ],
    "wof:name":"Gerald Neff CPA",
    "wof:placetype":"venue"
},
  "geometry": {"coordinates":[-83.312236,42.485806],"type":"Point"}
}