{
  "type": "Feature",
  "properties": {
    "iso:country":"US",
    "sg:address":"50 I- 75 Bus",
    "sg:city":"Grayling",
    "sg:classifiers":[
        {
            "category":"Retail",
            "subcategory":"Auto Repair",
            "type":"Services"
        }
    ],
    "sg:phone":"+1 989 348 8123",
    "sg:postcode":"49738",
    "sg:province":"MI",
    "wof:name":"Grayling Auto Repair",
    "wof:placetype":"venue"
},
  "geometry": {"coordinates":[-84.71767,44.684059],"type":"Point"}
}