{
  "type": "Feature",
  "properties": {
    "iso:country":"US",
    "sg:address":"1300 W State St",
    "sg:city":"Belding",
    "sg:classifiers":[
        {
            "category":"Banks & Credit Unions",
            "subcategory":"Bank",
            "type":"Services"
        }
    ],
    "sg:phone":"+1 616 794 2161",
    "sg:postcode":"48809",
    "sg:province":"MI",
    "sg:tags":[
        "loan",
        "real estate"
    ],
    "wof:name":"Easttown Mortgage",
    "wof:placetype":"venue"
},
  "geometry": {"coordinates":[-85.245627,43.088904],"type":"Point"}
}