{
  "type": "Feature",
  "properties": {
    "iso:country":"US",
    "sg:address":"6464 Crest Dr",
    "sg:city":"Waterford",
    "sg:classifiers":[
        {
            "category":"Wholesale",
            "subcategory":"Auto Parts",
            "type":"Manufacturing & Wholesale Goods"
        }
    ],
    "sg:phone":"+1 248 666 5363",
    "sg:postcode":"48329",
    "sg:province":"MI",
    "sg:tags":[
        "automotive"
    ],
    "wof:name":"Percision Starter",
    "wof:placetype":"venue"
},
  "geometry": {"coordinates":[-83.417422,42.679239],"type":"Point"}
}