{
  "type": "Feature",
  "properties": {
    "iso:country":"US",
    "sg:address":"1901 Saint Antoine St Fl 6",
    "sg:city":"Detroit",
    "sg:classifiers":[
        {
            "category":"Professional",
            "subcategory":"Lawyer & Legal Services",
            "type":"Services"
        }
    ],
    "sg:phone":"+1 313 259 7777",
    "sg:postcode":"48226",
    "sg:province":"MI",
    "wof:name":"Bodman Llp",
    "wof:placetype":"venue"
},
  "geometry": {"coordinates":[-83.043492,42.339003],"type":"Point"}
}