{
  "type": "Feature",
  "properties": {
    "iso:country":"US",
    "sg:address":"4977 Crabapple Ct",
    "sg:city":"West Bloomfield",
    "sg:classifiers":[
        {
            "category":"Shopping",
            "subcategory":"Discount & Variety Stores",
            "type":"Retail Goods"
        }
    ],
    "sg:phone":"+1 248 682 3166",
    "sg:postcode":"48324",
    "sg:province":"MI",
    "sg:tags":[
        "merchandise",
        "general"
    ],
    "wof:name":"GLC Sales",
    "wof:placetype":"venue"
},
  "geometry": {"coordinates":[-83.383285,42.609063],"type":"Point"}
}