{
  "type": "Feature",
  "properties": {
    "iso:country":"US",
    "sg:address":"66 Main St",
    "sg:city":"Battle Creek",
    "sg:classifiers":[
        {
            "category":"Retail",
            "subcategory":"Car Wash",
            "type":"Services"
        }
    ],
    "sg:phone":"+1 269 968 2588",
    "sg:postcode":"49014",
    "sg:province":"MI",
    "sg:tags":[
        "carwash",
        "automotive"
    ],
    "wof:name":"American Towing",
    "wof:placetype":"venue"
},
  "geometry": {"coordinates":[-85.177914,42.314237],"type":"Point"}
}