{
  "type": "Feature",
  "properties": {
    "iso:country":"US",
    "sg:address":"14300 Sibley Rd",
    "sg:city":"Wyandotte",
    "sg:classifiers":[
        {
            "category":"Education",
            "subcategory":"Library",
            "type":"Public Place"
        }
    ],
    "sg:phone":"+1 734 283 1250",
    "sg:postcode":"48193",
    "sg:province":"MI",
    "wof:name":"Riverview Public Library",
    "wof:placetype":"venue"
},
  "geometry": {"coordinates":[-83.19633,42.170281],"type":"Point"}
}