{
  "type": "Feature",
  "properties": {
    "iso:country":"US",
    "sg:address":"6031 Oak Creek Dr",
    "sg:city":"Swartz Creek",
    "sg:classifiers":[
        {
            "category":"Professional",
            "type":"Services"
        }
    ],
    "sg:phone":"+1 810 655 8885",
    "sg:postcode":"48473",
    "sg:province":"MI",
    "wof:name":"Probate Services",
    "wof:placetype":"venue"
},
  "geometry": {"coordinates":[-83.779167,42.941235],"type":"Point"}
}