{
  "type": "Feature",
  "properties": {
    "iso:country":"US",
    "sg:address":"19199 15 Mile Rd",
    "sg:city":"Clinton Township",
    "sg:classifiers":[
        {
            "category":"Health Services",
            "subcategory":"Chiropractor",
            "type":"Services"
        }
    ],
    "sg:phone":"+1 586 791 5555",
    "sg:postcode":"48035",
    "sg:province":"MI",
    "wof:name":"Duchene Chiropractic PC",
    "wof:placetype":"venue"
},
  "geometry": {"coordinates":[-82.925797,42.554199],"type":"Point"}
}