{
  "type": "Feature",
  "properties": {
    "iso:country":"US",
    "sg:address":"2015 Lake Michigan Dr NW",
    "sg:city":"Grand Rapids",
    "sg:classifiers":[
        {
            "category":"Real Estate",
            "subcategory":"Real Estate Agent",
            "type":"Services"
        }
    ],
    "sg:phone":"+1 616 453 6301",
    "sg:postcode":"49504",
    "sg:province":"MI",
    "wof:name":"Westdale Better Homes & Grdns",
    "wof:placetype":"venue"
},
  "geometry": {"coordinates":[-85.717707,42.971504],"type":"Point"}
}