{
  "type": "Feature",
  "properties": {
    "iso:country":"US",
    "sg:address":"1270 S Main St",
    "sg:city":"Plymouth",
    "sg:classifiers":[
        {
            "category":"Building & Trades",
            "subcategory":"Locksmith",
            "type":"Services"
        }
    ],
    "sg:phone":"+1 248 349 0830",
    "sg:postcode":"48170",
    "sg:province":"MI",
    "sg:tags":[
        "key"
    ],
    "wof:name":"Town Locksmith Inc the",
    "wof:placetype":"venue"
},
  "geometry": {"coordinates":[-83.469803,42.361099],"type":"Point"}
}