{
  "type": "Feature",
  "properties": {
    "iso:country":"US",
    "sg:address":"5774 S Merriman Rd",
    "sg:city":"Wayne",
    "sg:classifiers":[
        {
            "category":"Food & Beverages",
            "subcategory":"Groceries & Convenience Stores",
            "type":"Retail Goods"
        }
    ],
    "sg:phone":"+1 734 721 7850",
    "sg:postcode":"48184",
    "sg:province":"MI",
    "wof:name":"Merriman's Food Market",
    "wof:placetype":"venue"
},
  "geometry": {"coordinates":[-83.348198,42.267601],"type":"Point"}
}