{
  "type": "Feature",
  "properties": {
    "iso:country":"US",
    "sg:address":"314 W Ann St",
    "sg:city":"Ann Arbor",
    "sg:classifiers":[
        {
            "category":"Retail",
            "subcategory":"Auto Repair",
            "type":"Services"
        }
    ],
    "sg:phone":"+1 734 662 4141",
    "sg:postcode":"48104",
    "sg:province":"MI",
    "sg:tags":[
        "body"
    ],
    "wof:name":"Ross-Beakes Collision Services",
    "wof:placetype":"venue"
},
  "geometry": {"coordinates":[-83.751868,42.282547],"type":"Point"}
}