{
  "type": "Feature",
  "properties": {
    "iso:country":"US",
    "sg:address":"3060 Madison Ave SE",
    "sg:city":"Wyoming",
    "sg:classifiers":[
        {
            "category":"Banks & Credit Unions",
            "subcategory":"Investment Brokerage",
            "type":"Services"
        }
    ],
    "sg:phone":"+1 616 241 4160",
    "sg:postcode":"49548",
    "sg:province":"MI",
    "sg:tags":[
        "advisory",
        "financial"
    ],
    "wof:name":"Mc Queen Financial",
    "wof:placetype":"venue"
},
  "geometry": {"coordinates":[-85.656558,42.90712],"type":"Point"}
}