{
  "type": "Feature",
  "properties": {
    "iso:country":"US",
    "sg:address":"4831 Mac Arthur Rd",
    "sg:city":"Muskegon",
    "sg:classifiers":[
        {
            "category":"Building & Trades",
            "subcategory":"Construction",
            "type":"Services"
        }
    ],
    "sg:phone":"+1 231 767 2430",
    "sg:postcode":"49442",
    "sg:province":"MI",
    "sg:tags":[
        "floor",
        "laying",
        "contractor"
    ],
    "wof:name":"B & B Installers",
    "wof:placetype":"venue"
},
  "geometry": {"coordinates":[-86.12376999999999,43.256671],"type":"Point"}
}