{
  "type": "Feature",
  "properties": {
    "iso:country":"US",
    "sg:address":"74 Market Ave SW",
    "sg:city":"Grand Rapids",
    "sg:classifiers":[
        {
            "category":"Professional",
            "subcategory":"Business Services",
            "type":"Services"
        }
    ],
    "sg:phone":"+1 616 459 4300",
    "sg:postcode":"49503",
    "sg:province":"MI",
    "sg:tags":[
        "paging",
        "answering"
    ],
    "wof:name":"Telephone Message Ctr",
    "wof:placetype":"venue"
},
  "geometry": {"coordinates":[-85.67442,42.961697],"type":"Point"}
}