{
  "type": "Feature",
  "properties": {
    "iso:country":"US",
    "sg:address":"43 S Morse St",
    "sg:city":"Sandusky",
    "sg:classifiers":[
        {
            "category":"Professional",
            "type":"Services"
        }
    ],
    "sg:phone":"+1 810 648 9042",
    "sg:postcode":"48471",
    "sg:province":"MI",
    "sg:tags":[
        "establishment"
    ],
    "wof:name":"Prestige Marketing & Conslntg",
    "wof:placetype":"venue"
},
  "geometry": {"coordinates":[-82.828345,43.420368],"type":"Point"}
}