{
  "type": "Feature",
  "properties": {
    "iso:country":"US",
    "sg:address":"1410 Lake Grove Ave SE",
    "sg:city":"Grand Rapids",
    "sg:classifiers":[
        {
            "category":"Wholesale",
            "subcategory":"Durable Goods & Equipment",
            "type":"Manufacturing & Wholesale Goods"
        }
    ],
    "sg:phone":"+1 616 942 5451",
    "sg:postcode":"49506",
    "sg:province":"MI",
    "wof:name":"Idema Sales Inc",
    "wof:placetype":"venue"
},
  "geometry": {"coordinates":[-85.60636700000001,42.936849],"type":"Point"}
}