{
  "type": "Feature",
  "properties": {
    "iso:country":"US",
    "sg:address":"15575 15 Mile Rd",
    "sg:city":"Clinton Township",
    "sg:classifiers":[
        {
            "category":"Cinema",
            "subcategory":"Movie Rental",
            "type":"Entertainment"
        }
    ],
    "sg:phone":"+1 586 285 1271",
    "sg:postcode":"48035",
    "sg:province":"MI",
    "sg:tags":[
        "game",
        "video"
    ],
    "sg:website":"www.gamecrazy.com",
    "wof:name":"Game Crazy",
    "wof:placetype":"venue"
},
  "geometry": {"coordinates":[-82.966499,42.553299],"type":"Point"}
}