{
  "type": "Feature",
  "properties": {
    "iso:country":"US",
    "sg:address":"6028 Mulberry Dr",
    "sg:city":"Sterling Heights",
    "sg:classifiers":[
        {
            "category":"Building & Trades",
            "subcategory":"Construction",
            "type":"Services"
        }
    ],
    "sg:phone":"+1 586 726 6684",
    "sg:postcode":"48314",
    "sg:province":"MI",
    "sg:tags":[
        "hanging",
        "painter",
        "contractor"
    ],
    "wof:name":"A & P Painting Co",
    "wof:placetype":"venue"
},
  "geometry": {"coordinates":[-83.048693,42.615591],"type":"Point"}
}