{
  "type": "Feature",
  "properties": {
    "iso:country":"US",
    "sg:address":"1820 N Lapeer Rd",
    "sg:city":"Lapeer",
    "sg:classifiers":[
        {
            "category":"Professional",
            "subcategory":"Accounting & Tax Preparation",
            "type":"Services"
        }
    ],
    "sg:phone":"+1 810 667 3261",
    "sg:postcode":"48446",
    "sg:province":"MI",
    "sg:tags":[
        "payroll",
        "business"
    ],
    "wof:name":"Abj & Assoc Inc",
    "wof:placetype":"venue"
},
  "geometry": {"coordinates":[-83.308503,43.082946],"type":"Point"}
}