{
  "type": "Feature",
  "properties": {
    "iso:country":"US",
    "sg:address":"4204 Lakeview Trl",
    "sg:city":"Traverse City",
    "sg:classifiers":[
        {
            "category":"Building & Trades",
            "subcategory":"Construction",
            "type":"Services"
        }
    ],
    "sg:phone":"+1 231 946 2399",
    "sg:postcode":"49686",
    "sg:province":"MI",
    "sg:tags":[
        "residential"
    ],
    "wof:name":"Roche Construction",
    "wof:placetype":"venue"
},
  "geometry": {"coordinates":[-85.490047,44.678612],"type":"Point"}
}