{
  "type": "Feature",
  "properties": {
    "iso:country":"US",
    "sg:address":"4585 Bay Rd",
    "sg:city":"Saginaw",
    "sg:classifiers":[
        {
            "category":"Restaurant",
            "type":"Food & Drink"
        }
    ],
    "sg:menulink":"http://www.allmenus.com/mi/saginaw/176376-kfc---kentucky-fried-chicken/menu/",
    "sg:phone":"+1 989 799 5796",
    "sg:postcode":"48604",
    "sg:province":"MI",
    "sg:tags":[
        "american",
        "chicken"
    ],
    "wof:name":"KFC - Kentucky Fried Chicken",
    "wof:placetype":"venue"
},
  "geometry": {"coordinates":[-83.975494,43.473749],"type":"Point"}
}