{
  "type": "Feature",
  "properties": {
    "iso:country":"US",
    "sg:address":"239 S State St",
    "sg:city":"Hesperia",
    "sg:classifiers":[
        {
            "category":"Professional",
            "subcategory":"Business Services",
            "type":"Services"
        }
    ],
    "sg:phone":"+1 231 854 6865",
    "sg:postcode":"49421",
    "sg:province":"MI",
    "sg:tags":[
        "auctioneer"
    ],
    "wof:name":"Chase Auction Svc",
    "wof:placetype":"venue"
},
  "geometry": {"coordinates":[-86.04293199999999,43.564144],"type":"Point"}
}