{
  "type": "Feature",
  "properties": {
    "iso:country":"US",
    "sg:address":"2630 S Sandusky Rd",
    "sg:city":"Sandusky",
    "sg:classifiers":[
        {
            "category":"Government",
            "subcategory":"Office",
            "type":"Public Place"
        }
    ],
    "sg:phone":"+1 810 648 3544",
    "sg:postcode":"48471",
    "sg:province":"MI",
    "sg:tags":[
        "village"
    ],
    "wof:name":"Watertown Twp Offices",
    "wof:placetype":"venue"
},
  "geometry": {"coordinates":[-82.825845,43.344399],"type":"Point"}
}