{
  "type": "Feature",
  "properties": {
    "iso:country":"US",
    "sg:address":"1790 Oak Ave",
    "sg:city":"Muskegon",
    "sg:classifiers":[
        {
            "category":"Health Services",
            "subcategory":"Doctor",
            "type":"Services"
        }
    ],
    "sg:phone":"+1 231 773 8853",
    "sg:postcode":"49442",
    "sg:province":"MI",
    "sg:tags":[
        "osteopathic"
    ],
    "wof:name":"Rollinss Fred R I Do",
    "wof:placetype":"venue"
},
  "geometry": {"coordinates":[-86.198505,43.237931],"type":"Point"}
}