{
  "type": "Feature",
  "properties": {
    "iso:country":"US",
    "sg:address":"18000 Vernier Rd",
    "sg:city":"Harper Woods",
    "sg:classifiers":[
        {
            "category":"Shopping",
            "subcategory":"Department Store",
            "type":"Retail Goods"
        },
        {
            "category":"Personal",
            "subcategory":"Beauty Salon",
            "type":"Services"
        }
    ],
    "sg:phone":"+1 248 245 2477",
    "sg:postcode":"48225",
    "sg:province":"MI",
    "sg:tags":[
        "hair"
    ],
    "wof:name":"Marshall Field's",
    "wof:placetype":"venue"
},
  "geometry": {"coordinates":[-82.93409699999999,42.449902],"type":"Point"}
}