{
  "type": "Feature",
  "properties": {
    "iso:country":"US",
    "sg:address":"27897 Orchard Lake Rd",
    "sg:city":"Farmington Hills",
    "sg:classifiers":[
        {
            "category":"Personal",
            "subcategory":"Massage",
            "type":"Services"
        }
    ],
    "sg:phone":"+1 248 324 0701",
    "sg:postcode":"48334",
    "sg:province":"MI",
    "wof:name":"Ceragem",
    "wof:placetype":"venue"
},
  "geometry": {"coordinates":[-83.35888,42.499969],"type":"Point"}
}