{
  "type": "Feature",
  "properties": {
    "iso:country":"US",
    "sg:address":"20290 Westphalia St",
    "sg:city":"Detroit",
    "sg:classifiers":[
        {
            "category":"Social Services",
            "type":"Services"
        }
    ],
    "sg:phone":"+1 313 372 3642",
    "sg:postcode":"48205",
    "sg:province":"MI",
    "wof:name":"Women In Crisis Resource Ctr",
    "wof:placetype":"venue"
},
  "geometry": {"coordinates":[-82.992811,42.446902],"type":"Point"}
}