{
  "type": "Feature",
  "properties": {
    "iso:country":"US",
    "sg:address":"300 36th St SW",
    "sg:city":"Grand Rapids",
    "sg:classifiers":[
        {
            "category":"Professional",
            "subcategory":"Management & Consulting",
            "type":"Services"
        }
    ],
    "sg:phone":"+1 616 246 3370",
    "sg:postcode":"49548",
    "sg:province":"MI",
    "sg:tags":[
        "personnel",
        "consultant"
    ],
    "wof:name":"Regional Personnel Workers Com",
    "wof:placetype":"venue"
},
  "geometry": {"coordinates":[-85.672725,42.898603],"type":"Point"}
}