{
  "type": "Feature",
  "properties": {
    "iso:country":"US",
    "sg:address":"27900 Harper Ave",
    "sg:city":"Saint Clair Shores",
    "sg:classifiers":[
        {
            "category":"Restaurant",
            "type":"Food & Drink"
        }
    ],
    "sg:menulink":"http://www.allmenus.com/mi/st-clair-shores/43430-nino-salvaggio/menu/",
    "sg:phone":"+1 586 778 3650",
    "sg:postcode":"48081",
    "sg:province":"MI",
    "sg:tags":[
        "wrap",
        "american",
        "sandwich"
    ],
    "wof:name":"Nino Salvaggio",
    "wof:placetype":"venue"
},
  "geometry": {"coordinates":[-82.897706,42.497995],"type":"Point"}
}