{
  "type": "Feature",
  "properties": {
    "iso:country":"US",
    "sg:address":"109 N Evans St",
    "sg:city":"Tecumseh",
    "sg:classifiers":[
        {
            "category":"Recreation",
            "type":"Entertainment"
        }
    ],
    "sg:phone":"+1 517 423 7697",
    "sg:postcode":"49286",
    "sg:province":"MI",
    "sg:tags":[
        "martial",
        "arts",
        "instruction"
    ],
    "wof:name":"ATA Blackbelt Academy",
    "wof:placetype":"venue"
},
  "geometry": {"coordinates":[-83.94526399999999,42.004318],"type":"Point"}
}