{
  "type": "Feature",
  "properties": {
    "iso:country":"US",
    "sg:address":"15235 Troy St",
    "sg:city":"Taylor",
    "sg:classifiers":[
        {
            "category":"Organizations",
            "subcategory":"Religious Organization",
            "type":"Services"
        }
    ],
    "sg:phone":"+1 734 946 7360",
    "sg:postcode":"48180",
    "sg:province":"MI",
    "wof:name":"Ktalior Church of Nazarene",
    "wof:placetype":"venue"
},
  "geometry": {"coordinates":[-83.274901,42.19604],"type":"Point"}
}