{
  "type": "Feature",
  "properties": {
    "iso:country":"US",
    "sg:address":"3550 N State Rd",
    "sg:city":"Ionia",
    "sg:classifiers":[
        {
            "category":"Education",
            "subcategory":"School",
            "type":"Public Place"
        }
    ],
    "sg:phone":"+1 616 527 0571",
    "sg:postcode":"48846",
    "sg:province":"MI",
    "wof:name":"R B Boyce Elementary School",
    "wof:placetype":"venue"
},
  "geometry": {"coordinates":[-85.07508799999999,43.040322],"type":"Point"}
}