{
  "type": "Feature",
  "properties": {
    "iso:country":"US",
    "sg:address":"750 Pleasant Ave",
    "sg:city":"Kalamazoo",
    "sg:classifiers":[
        {
            "category":"Professional",
            "type":"Services"
        }
    ],
    "sg:phone":"+1 269 226 9255",
    "sg:postcode":"49008",
    "sg:province":"MI",
    "sg:tags":[
        "establishment"
    ],
    "wof:name":"Snapp's Spot",
    "wof:placetype":"venue"
},
  "geometry": {"coordinates":[-85.59423700000001,42.249771],"type":"Point"}
}