{
  "type": "Feature",
  "properties": {
    "iso:country":"US",
    "sg:address":"1101 8th St",
    "sg:city":"Mio",
    "sg:classifiers":[
        {
            "category":"Organizations",
            "subcategory":"Religious Organization",
            "type":"Services"
        }
    ],
    "sg:phone":"+1 989 826 5598",
    "sg:postcode":"48647",
    "sg:province":"MI",
    "sg:tags":[
        "church"
    ],
    "wof:name":"Mio United Methodist Church",
    "wof:placetype":"venue"
},
  "geometry": {"coordinates":[-84.144308,44.652181],"type":"Point"}
}