{
  "type": "Feature",
  "properties": {
    "iso:country":"US",
    "sg:address":"13818 Hubbard Lake Rd",
    "sg:city":"Hubbard Lake",
    "sg:classifiers":[
        {
            "category":"Government",
            "subcategory":"Post Office",
            "type":"Public Place"
        }
    ],
    "sg:phone":"+1 989 727 2220",
    "sg:postcode":"49747",
    "sg:province":"MI",
    "wof:name":"US Post Office",
    "wof:placetype":"venue"
},
  "geometry": {"coordinates":[-83.58735799999999,44.875429],"type":"Point"}
}