{
  "type": "Feature",
  "properties": {
    "iso:country":"US",
    "sg:address":"2450 Hawks Ave",
    "sg:city":"Ann Arbor",
    "sg:classifiers":[
        {
            "category":"Health Services",
            "subcategory":"Clinic",
            "type":"Services"
        }
    ],
    "sg:phone":"+1 734 971 8032",
    "sg:postcode":"48108",
    "sg:province":"MI",
    "wof:name":"General Health Needs Inc",
    "wof:placetype":"venue"
},
  "geometry": {"coordinates":[-83.670303,42.250114],"type":"Point"}
}