{
  "type": "Feature",
  "properties": {
    "iso:country":"US",
    "sg:address":"3126 Babylon Rd",
    "sg:city":"Allegan",
    "sg:classifiers":[
        {
            "category":"Health Services",
            "subcategory":"Nursing And Care Facility",
            "type":"Services"
        }
    ],
    "sg:phone":"+1 269 673 2014",
    "sg:postcode":"49010",
    "sg:province":"MI",
    "sg:tags":[
        "foster",
        "adult"
    ],
    "wof:name":"Sunset House Inc",
    "wof:placetype":"venue"
},
  "geometry": {"coordinates":[-85.85150299999999,42.544882],"type":"Point"}
}