{
  "type": "Feature",
  "properties": {
    "iso:country":"US",
    "sg:address":"8200 N Wayne Rd",
    "sg:city":"Westland",
    "sg:classifiers":[
        {
            "category":"Organizations",
            "subcategory":"Religious Organization",
            "type":"Services"
        }
    ],
    "sg:phone":"+1 734 425 4421",
    "sg:postcode":"48185",
    "sg:province":"MI",
    "wof:name":"Archdioces of Detroit The",
    "wof:placetype":"venue"
},
  "geometry": {"coordinates":[-83.385671,42.349539],"type":"Point"}
}