{
  "type": "Feature",
  "properties": {
    "iso:country":"US",
    "sg:address":"5200 Gotfredson Rd",
    "sg:city":"Plymouth",
    "sg:classifiers":[
        {
            "category":"Organizations",
            "subcategory":"Community Association",
            "type":"Services"
        }
    ],
    "sg:phone":"+1 734 453 5163",
    "sg:postcode":"48170",
    "sg:province":"MI",
    "wof:name":"Villa Nova Homeowners Assoc",
    "wof:placetype":"venue"
},
  "geometry": {"coordinates":[-83.56731600000001,42.355271],"type":"Point"}
}