{
  "type": "Feature",
  "properties": {
    "iso:country":"US",
    "sg:address":"2 Pennsylvania Plz",
    "sg:city":"Petoskey",
    "sg:classifiers":[
        {
            "category":"Professional",
            "subcategory":"Management & Consulting",
            "type":"Services"
        }
    ],
    "sg:phone":"+1 231 348 9300",
    "sg:postcode":"49770",
    "sg:province":"MI",
    "sg:tags":[
        "industrial"
    ],
    "wof:name":"Clark Construction Company",
    "wof:placetype":"venue"
},
  "geometry": {"coordinates":[-84.95357,45.376275],"type":"Point"}
}