{
  "type": "Feature",
  "properties": {
    "iso:country":"US",
    "sg:address":"3449 Hadley Rd",
    "sg:city":"Metamora",
    "sg:classifiers":[
        {
            "category":"Retail",
            "subcategory":"Auto Repair",
            "type":"Services"
        }
    ],
    "sg:phone":"+1 810 797 4531",
    "sg:postcode":"48455",
    "sg:province":"MI",
    "sg:tags":[
        "repairing",
        "automobile"
    ],
    "wof:name":"Lou's Automotive Svc",
    "wof:placetype":"venue"
},
  "geometry": {"coordinates":[-83.403656,42.954206],"type":"Point"}
}