{
  "type": "Feature",
  "properties": {
    "iso:country":"US",
    "sg:address":"4070 E Chandler St",
    "sg:city":"Carsonville",
    "sg:classifiers":[
        {
            "category":"Building & Trades",
            "subcategory":"Construction",
            "type":"Services"
        }
    ],
    "sg:phone":"+1 810 657 9042",
    "sg:postcode":"48419",
    "sg:province":"MI",
    "sg:tags":[
        "painter"
    ],
    "wof:name":"Dan's Custom Paint & Power Shp",
    "wof:placetype":"venue"
},
  "geometry": {"coordinates":[-82.669738,43.426865],"type":"Point"}
}