{
  "type": "Feature",
  "properties": {
    "iso:country":"US",
    "sg:address":"5372 W Bloomfield Lake Rd",
    "sg:city":"West Bloomfield",
    "sg:classifiers":[
        {
            "category":"Home & Garden",
            "subcategory":"Furniture",
            "type":"Retail Goods"
        }
    ],
    "sg:phone":"+1 248 738 8988",
    "sg:postcode":"48323",
    "sg:province":"MI",
    "sg:tags":[
        "store"
    ],
    "wof:name":"Durable Chair Company",
    "wof:placetype":"venue"
},
  "geometry": {"coordinates":[-83.379402,42.559601],"type":"Point"}
}