{
  "type": "Feature",
  "properties": {
    "iso:country":"US",
    "sg:address":"44100 N Groesbeck Hwy",
    "sg:city":"Clinton Township",
    "sg:classifiers":[
        {
            "category":"Building & Trades",
            "subcategory":"Construction",
            "type":"Services"
        }
    ],
    "sg:phone":"+1 586 954 1338",
    "sg:postcode":"48036",
    "sg:province":"MI",
    "sg:tags":[
        "painter"
    ],
    "wof:name":"Finishing Specialties",
    "wof:placetype":"venue"
},
  "geometry": {"coordinates":[-82.879997,42.621201],"type":"Point"}
}