{
  "type": "Feature",
  "properties": {
    "iso:country":"US",
    "sg:address":"847 Michigan Ave",
    "sg:city":"Baldwin",
    "sg:classifiers":[
        {
            "category":"Retail",
            "subcategory":"Repair Shop",
            "type":"Services"
        }
    ],
    "sg:phone":"+1 231 745 3943",
    "sg:postcode":"49304",
    "sg:province":"MI",
    "sg:tags":[
        "cleaners",
        "parts",
        "vacuum"
    ],
    "wof:name":"Vac & Sew Express Inc",
    "wof:placetype":"venue"
},
  "geometry": {"coordinates":[-85.851679,43.895989],"type":"Point"}
}