{
  "type": "Feature",
  "properties": {
    "iso:country":"US",
    "sg:address":"16241 US Hwy 27",
    "sg:city":"Lansing",
    "sg:classifiers":[
        {
            "category":"Autos & Motor Vehicles",
            "subcategory":"Auto Supplies",
            "type":"Retail Goods"
        }
    ],
    "sg:phone":"+1 517 487 0740",
    "sg:postcode":"48906",
    "sg:province":"MI",
    "sg:tags":[
        "automobile",
        "parts"
    ],
    "wof:name":"Michigan Off Road Ctr",
    "wof:placetype":"venue"
},
  "geometry": {"coordinates":[-84.66871,42.781375],"type":"Point"}
}