{
  "type": "Feature",
  "properties": {
    "iso:country":"US",
    "sg:address":"1541 Dennis Rd",
    "sg:city":"Williamston",
    "sg:classifiers":[
        {
            "category":"Professional",
            "type":"Services"
        }
    ],
    "sg:phone":"+1 517 655 2573",
    "sg:postcode":"48895",
    "sg:province":"MI",
    "wof:name":"Safari Arms Services",
    "wof:placetype":"venue"
},
  "geometry": {"coordinates":[-84.294591,42.615502],"type":"Point"}
}