{
  "type": "Feature",
  "properties": {
    "iso:country":"US",
    "sg:address":"22913 Bluejay Ave",
    "sg:city":"Mattawan",
    "sg:classifiers":[
        {
            "category":"Professional",
            "type":"Services"
        }
    ],
    "sg:phone":"+1 269 375 6440",
    "sg:postcode":"49071",
    "sg:province":"MI",
    "sg:tags":[
        "establishment"
    ],
    "wof:name":"Garrison & Garrison",
    "wof:placetype":"venue"
},
  "geometry": {"coordinates":[-85.77554000000001,42.266973],"type":"Point"}
}