{
  "type": "Feature",
  "properties": {
    "iso:country":"US",
    "sg:address":"316 E Shaw St",
    "sg:city":"Howard City",
    "sg:classifiers":[
        {
            "category":"Retail",
            "subcategory":"Car Wash",
            "type":"Services"
        }
    ],
    "sg:phone":"+1 231 937 6513",
    "sg:postcode":"49329",
    "sg:province":"MI",
    "sg:tags":[
        "polishing",
        "washing"
    ],
    "wof:name":"All In A Weeks Wash",
    "wof:placetype":"venue"
},
  "geometry": {"coordinates":[-85.46808799999999,43.395756],"type":"Point"}
}