{
  "type": "Feature",
  "properties": {
    "iso:country":"US",
    "sg:address":"11980 Beaver Rd",
    "sg:city":"St Charles",
    "sg:classifiers":[
        {
            "category":"Manufacturing",
            "subcategory":"Tools & Machinery",
            "type":"Manufacturing & Wholesale Goods"
        }
    ],
    "sg:phone":"+1 989 865 9880",
    "sg:postcode":"48655",
    "sg:province":"MI",
    "sg:tags":[
        "die",
        "maker"
    ],
    "wof:name":"Method Tool",
    "wof:placetype":"venue"
},
  "geometry": {"coordinates":[-84.16195,43.3153],"type":"Point"}
}