{
  "type": "Feature",
  "properties": {
    "iso:country":"US",
    "sg:address":"21002 Mack Ave",
    "sg:city":"Grosse Pointe",
    "sg:classifiers":[
        {
            "category":"Professional",
            "subcategory":"Business Services",
            "type":"Services"
        }
    ],
    "sg:phone":"+1 313 886 7100",
    "sg:postcode":"48236",
    "sg:province":"MI",
    "sg:tags":[
        "financial"
    ],
    "wof:name":"Essex Financial Group",
    "wof:placetype":"venue"
},
  "geometry": {"coordinates":[-82.905691,42.447612],"type":"Point"}
}