{
  "type": "Feature",
  "properties": {
    "iso:country":"US",
    "sg:address":"2333 S Center Rd",
    "sg:city":"Burton",
    "sg:classifiers":[
        {
            "category":"Banks & Credit Unions",
            "subcategory":"Bank",
            "type":"Services"
        }
    ],
    "sg:phone":"+1 810 600 1300",
    "sg:postcode":"48519",
    "sg:province":"MI",
    "sg:tags":[
        "loan",
        "real estate"
    ],
    "wof:name":"Enterprise Mortgage",
    "wof:placetype":"venue"
},
  "geometry": {"coordinates":[-83.63397500000001,42.995993],"type":"Point"}
}