{
  "type": "Feature",
  "properties": {
    "iso:country":"US",
    "sg:address":"1571 Rotsel Rd",
    "sg:city":"Bloomfield Hills",
    "sg:classifiers":[
        {
            "category":"Personal",
            "type":"Services"
        }
    ],
    "sg:phone":"+1 248 745 9223",
    "sg:postcode":"48302",
    "sg:province":"MI",
    "sg:tags":[
        "mover"
    ],
    "wof:name":"J C Moving Co",
    "wof:placetype":"venue"
},
  "geometry": {"coordinates":[-83.303752,42.61218],"type":"Point"}
}