{
  "type": "Feature",
  "properties": {
    "iso:country":"US",
    "sg:address":"2241 Weber Rd",
    "sg:city":"Gladwin",
    "sg:classifiers":[
        {
            "category":"Government",
            "subcategory":"Office",
            "type":"Public Place"
        }
    ],
    "sg:phone":"+1 989 246 1153",
    "sg:postcode":"48624",
    "sg:province":"MI",
    "sg:tags":[
        "village"
    ],
    "wof:name":"Buckeye Twp Office",
    "wof:placetype":"venue"
},
  "geometry": {"coordinates":[-84.460132,43.987216],"type":"Point"}
}