{
  "type": "Feature",
  "properties": {
    "iso:country":"US",
    "sg:address":"543 N Main St",
    "sg:city":"Rochester",
    "sg:classifiers":[
        {
            "category":"Professional",
            "type":"Services"
        }
    ],
    "sg:phone":"+1 248 652 3700",
    "sg:postcode":"48307",
    "sg:province":"MI",
    "sg:tags":[
        "establishment"
    ],
    "wof:name":"Abbey Holiday LTD",
    "wof:placetype":"venue"
},
  "geometry": {"coordinates":[-83.133915,42.682683],"type":"Point"}
}