{
  "type": "Feature",
  "properties": {
    "iso:country":"US",
    "sg:address":"28660 Ryan Rd",
    "sg:city":"Warren",
    "sg:classifiers":[
        {
            "category":"Autos & Motor Vehicles",
            "subcategory":"Automobile Sales",
            "type":"Retail Goods"
        }
    ],
    "sg:phone":"+1 586 558 8839",
    "sg:postcode":"48092",
    "sg:province":"MI",
    "sg:tags":[
        "limo"
    ],
    "wof:name":"Limousine Express Inc",
    "wof:placetype":"venue"
},
  "geometry": {"coordinates":[-83.06729900000001,42.5033],"type":"Point"}
}