{
  "type": "Feature",
  "properties": {
    "iso:country":"US",
    "sg:address":"105 S Meridian St",
    "sg:city":"Cedarville",
    "sg:classifiers":[
        {
            "category":"Museum",
            "type":"Entertainment"
        }
    ],
    "sg:phone":"+1 906 484 3354",
    "sg:postcode":"49719",
    "sg:province":"MI",
    "wof:name":"Les Cheneaux Hstrcl Maritime",
    "wof:placetype":"venue"
},
  "geometry": {"coordinates":[-84.362815,45.997687],"type":"Point"}
}