{
  "type": "Feature",
  "properties": {
    "iso:country":"US",
    "sg:address":"13430 Harvard Ave NE",
    "sg:city":"Cedar Springs",
    "sg:classifiers":[
        {
            "category":"Real Estate",
            "subcategory":"Real Estate Operator",
            "type":"Services"
        }
    ],
    "sg:phone":"+1 616 754 8501",
    "sg:postcode":"49319",
    "sg:province":"MI",
    "sg:tags":[
        "building",
        "apartment"
    ],
    "wof:name":"Roscommon Aprtments Ltd Partnr",
    "wof:placetype":"venue"
},
  "geometry": {"coordinates":[-85.411389,43.209851],"type":"Point"}
}