{
  "type": "Feature",
  "properties": {
    "iso:country":"US",
    "sg:address":"33800 Hathaway St",
    "sg:city":"Livonia",
    "sg:classifiers":[
        {
            "category":"Social Services",
            "subcategory":"Adult Care",
            "type":"Services"
        }
    ],
    "sg:phone":"+1 734 261 6305",
    "sg:postcode":"48150",
    "sg:province":"MI",
    "sg:tags":[
        "residential"
    ],
    "wof:name":"Ellen Home",
    "wof:placetype":"venue"
},
  "geometry": {"coordinates":[-83.37806,42.360279],"type":"Point"}
}