{
  "type": "Feature",
  "properties": {
    "iso:country":"US",
    "sg:address":"1600 E McTaggart Rd",
    "sg:city":"Ubly",
    "sg:classifiers":[
        {
            "category":"Farming",
            "subcategory":"Farm",
            "type":"Manufacturing & Wholesale Goods"
        }
    ],
    "sg:phone":"+1 989 658 8870",
    "sg:postcode":"48475",
    "sg:province":"MI",
    "sg:tags":[
        "crop",
        "general"
    ],
    "wof:name":"Jerry Grifka",
    "wof:placetype":"venue"
},
  "geometry": {"coordinates":[-82.943825,43.724208],"type":"Point"}
}