{
  "type": "Feature",
  "properties": {
    "iso:country":"US",
    "sg:address":"228 Mussey St",
    "sg:city":"Romeo",
    "sg:classifiers":[
        {
            "category":"Organizations",
            "subcategory":"Religious Organization",
            "type":"Services"
        }
    ],
    "sg:phone":"+1 586 752 5080",
    "sg:postcode":"48065",
    "sg:province":"MI",
    "sg:tags":[
        "church"
    ],
    "wof:name":"Romeo First Church Of God",
    "wof:placetype":"venue"
},
  "geometry": {"coordinates":[-83.008763,42.804066],"type":"Point"}
}