{
  "type": "Feature",
  "properties": {
    "iso:country":"US",
    "sg:address":"21304 Mack Ave",
    "sg:city":"Grosse Pointe",
    "sg:classifiers":[
        {
            "category":"Professional",
            "subcategory":"Lawyer & Legal Services",
            "type":"Services"
        }
    ],
    "sg:phone":"+1 313 343 8860",
    "sg:postcode":"48236",
    "sg:province":"MI",
    "wof:name":"Kilber Ralph J Law Offices",
    "wof:placetype":"venue"
},
  "geometry": {"coordinates":[-82.90473900000001,42.450559],"type":"Point"}
}