{
  "type": "Feature",
  "properties": {
    "iso:country":"US",
    "sg:address":"450 Allston Dr",
    "sg:city":"Rochester Hills",
    "sg:classifiers":[
        {
            "category":"Education",
            "subcategory":"School",
            "type":"Public Place"
        }
    ],
    "sg:phone":"+1 248 651 4301",
    "sg:postcode":"48309",
    "sg:province":"MI",
    "wof:name":"Long Meadow Elementary School",
    "wof:placetype":"venue"
},
  "geometry": {"coordinates":[-83.161846,42.689994],"type":"Point"}
}