{
  "type": "Feature",
  "properties": {
    "iso:country":"US",
    "sg:address":"3085 Exeter Dr",
    "sg:city":"Milford",
    "sg:classifiers":[
        {
            "category":"Banks & Credit Unions",
            "subcategory":"Financial Services",
            "type":"Services"
        }
    ],
    "sg:phone":"+1 248 685 1906",
    "sg:postcode":"48380",
    "sg:province":"MI",
    "sg:tags":[
        "investor"
    ],
    "wof:name":"A & Z Con Sulantant Investment",
    "wof:placetype":"venue"
},
  "geometry": {"coordinates":[-83.650503,42.601735],"type":"Point"}
}