{
  "type": "Feature",
  "properties": {
    "iso:country":"US",
    "sg:address":"1431 Shannon Ln",
    "sg:city":"Lansing",
    "sg:classifiers":[
        {
            "category":"Building & Trades",
            "subcategory":"Construction",
            "type":"Services"
        }
    ],
    "sg:phone":"+1 517 323 6841",
    "sg:postcode":"48917",
    "sg:province":"MI",
    "sg:tags":[
        "contractor"
    ],
    "wof:name":"J & T Builders",
    "wof:placetype":"venue"
},
  "geometry": {"coordinates":[-84.616024,42.750834],"type":"Point"}
}