{
  "type": "Feature",
  "properties": {
    "iso:country":"US",
    "sg:address":"1841 Carter Rd",
    "sg:city":"Rochester",
    "sg:classifiers":[
        {
            "category":"Building & Trades",
            "subcategory":"Construction",
            "type":"Services"
        }
    ],
    "sg:phone":"+1 734 320 2614",
    "sg:postcode":"48306",
    "sg:province":"MI",
    "sg:tags":[
        "house"
    ],
    "wof:name":"Alexander Homes",
    "wof:placetype":"venue"
},
  "geometry": {"coordinates":[-83.096216,42.706748],"type":"Point"}
}