{
  "type": "Feature",
  "properties": {
    "iso:country":"US",
    "sg:address":"39500 High Pointe Blvd",
    "sg:city":"Novi",
    "sg:classifiers":[
        {
            "category":"Utilities",
            "subcategory":"Mobile Phone",
            "type":"Services"
        }
    ],
    "sg:phone":"+1 248 348 8163",
    "sg:postcode":"48375",
    "sg:province":"MI",
    "sg:tags":[
        "telephone",
        "cellular"
    ],
    "wof:name":"T-Mobile",
    "wof:placetype":"venue"
},
  "geometry": {"coordinates":[-83.438046,42.447733],"type":"Point"}
}