{
  "type": "Feature",
  "properties": {
    "iso:country":"US",
    "sg:address":"3094 Nina Ln",
    "sg:city":"Grawn",
    "sg:classifiers":[
        {
            "category":"Building & Trades",
            "subcategory":"Cleaning & Sanitation",
            "type":"Services"
        }
    ],
    "sg:phone":"+1 231 943 8925",
    "sg:postcode":"49637",
    "sg:province":"MI",
    "sg:tags":[
        "maintenance"
    ],
    "wof:name":"Sunrise Construcion & Maint",
    "wof:placetype":"venue"
},
  "geometry": {"coordinates":[-85.69353,44.642109],"type":"Point"}
}