{
  "type": "Feature",
  "properties": {
    "iso:country":"US",
    "sg:address":"5150 W Pierson Rd",
    "sg:city":"Flint",
    "sg:classifiers":[
        {
            "category":"Building & Trades",
            "subcategory":"Construction",
            "type":"Services"
        }
    ],
    "sg:phone":"+1 810 659 5400",
    "sg:postcode":"48504",
    "sg:province":"MI",
    "sg:tags":[
        "marking",
        "maintenance",
        "parking"
    ],
    "wof:name":"Master Seal Parking Lot",
    "wof:placetype":"venue"
},
  "geometry": {"coordinates":[-83.78003699999999,43.060544],"type":"Point"}
}