{
  "type": "Feature",
  "properties": {
    "iso:country":"US",
    "sg:address":"2155 112th Ave",
    "sg:city":"Otsego",
    "sg:phone":"+1 269 673 5884",
    "sg:postcode":"49078",
    "sg:province":"MI",
    "sg:tags":[
        "farm",
        "field",
        "crop"
    ],
    "wof:name":"Germain Farms",
    "wof:placetype":"venue"
},
  "geometry": {"coordinates":[-85.759317,42.508032],"type":"Point"}
}