{
  "type": "Feature",
  "properties": {
    "iso:country":"US",
    "sg:address":"3600 Kalamazoo Ave SE",
    "sg:city":"Grand Rapids",
    "sg:classifiers":[
        {
            "category":"Organizations",
            "subcategory":"Religious Organization",
            "type":"Services"
        }
    ],
    "sg:phone":"+1 616 452 3191",
    "sg:postcode":"49508",
    "sg:province":"MI",
    "wof:name":"Brookside Chrstn Rfrmed Church",
    "wof:placetype":"venue"
},
  "geometry": {"coordinates":[-85.626752,42.899755],"type":"Point"}
}