{
  "type": "Feature",
  "properties": {
    "iso:country":"US",
    "sg:address":"4100 Lake Dr SE",
    "sg:city":"Grand Rapids",
    "sg:classifiers":[
        {
            "category":"Health Services",
            "subcategory":"Doctor",
            "type":"Services"
        }
    ],
    "sg:phone":"+1 616 391 3759",
    "sg:postcode":"49546",
    "sg:province":"MI",
    "sg:tags":[
        "medical"
    ],
    "wof:name":"David A Quimby MD",
    "wof:placetype":"venue"
},
  "geometry": {"coordinates":[-85.568752,42.93788],"type":"Point"}
}