{
  "type": "Feature",
  "properties": {
    "iso:country":"US",
    "sg:address":"10321 42nd Ave",
    "sg:city":"Allendale",
    "sg:classifiers":[
        {
            "category":"Travel",
            "subcategory":"Hotels & Motels",
            "type":"Entertainment"
        }
    ],
    "sg:phone":"+1 616 895 9525",
    "sg:postcode":"49401",
    "sg:province":"MI",
    "sg:tags":[
        "membership",
        "lodging"
    ],
    "wof:name":"Delta Zeta Sorority",
    "wof:placetype":"venue"
},
  "geometry": {"coordinates":[-85.889056,42.957404],"type":"Point"}
}