{
  "type": "Feature",
  "properties": {
    "iso:country":"US",
    "sg:address":"3700 Lincoln Rd",
    "sg:city":"Bloomfield Hills",
    "sg:classifiers":[
        {
            "category":"Professional",
            "subcategory":"Computer Services",
            "type":"Services"
        }
    ],
    "sg:phone":"+1 248 642 8477",
    "sg:postcode":"48301",
    "sg:province":"MI",
    "sg:tags":[
        "related"
    ],
    "wof:name":"Iseffcom",
    "wof:placetype":"venue"
},
  "geometry": {"coordinates":[-83.26649999999999,42.537061],"type":"Point"}
}