{
  "type": "Feature",
  "properties": {
    "iso:country":"US",
    "sg:address":"4680 US Hwy 31",
    "sg:city":"Traverse City",
    "sg:classifiers":[
        {
            "category":"Professional",
            "subcategory":"Accounting & Tax Preparation",
            "type":"Services"
        }
    ],
    "sg:phone":"+1 231 938 7960",
    "sg:postcode":"49686",
    "sg:province":"MI",
    "wof:name":"Financial & Management Service",
    "wof:placetype":"venue"
},
  "geometry": {"coordinates":[-85.519569,44.755606],"type":"Point"}
}