{
  "type": "Feature",
  "properties": {
    "iso:country":"US",
    "sg:address":"2863 W Shore Dr",
    "sg:city":"Holland",
    "sg:classifiers":[
        {
            "category":"Professional",
            "subcategory":"Employment Agencies",
            "type":"Services"
        }
    ],
    "sg:phone":"+1 616 399 0500",
    "sg:postcode":"49424",
    "sg:province":"MI",
    "sg:tags":[
        "opportunity"
    ],
    "wof:name":"Adecco",
    "wof:placetype":"venue"
},
  "geometry": {"coordinates":[-86.091675,42.824215],"type":"Point"}
}