{
  "type": "Feature",
  "properties": {
    "iso:country":"US",
    "sg:address":"13461 S Huron River Dr",
    "sg:city":"Romulus",
    "sg:classifiers":[
        {
            "category":"Building & Trades",
            "subcategory":"Equipment Rental",
            "type":"Services"
        }
    ],
    "sg:phone":"+1 734 955 9291",
    "sg:postcode":"48174",
    "sg:province":"MI",
    "wof:name":"United Rentals",
    "wof:placetype":"venue"
},
  "geometry": {"coordinates":[-83.40442,42.206566],"type":"Point"}
}