{
  "type": "Feature",
  "properties": {
    "iso:country":"US",
    "sg:address":"1927 W Auburn Rd",
    "sg:city":"Rochester Hills",
    "sg:classifiers":[
        {
            "category":"Home & Garden",
            "subcategory":"Hardware",
            "type":"Retail Goods"
        }
    ],
    "sg:phone":"+1 248 852 5330",
    "sg:postcode":"48309",
    "sg:province":"MI",
    "sg:tags":[
        "store"
    ],
    "wof:name":"A & G Hardware",
    "wof:placetype":"venue"
},
  "geometry": {"coordinates":[-83.170197,42.634899],"type":"Point"}
}