{
  "type": "Feature",
  "properties": {
    "iso:country":"US",
    "sg:address":"707 W Michigan Ave",
    "sg:city":"Ypsilanti",
    "sg:classifiers":[
        {
            "category":"Building & Trades",
            "subcategory":"Plumbing",
            "type":"Services"
        }
    ],
    "sg:phone":"+1 734 482 4485",
    "sg:postcode":"48197",
    "sg:province":"MI",
    "sg:tags":[
        "air",
        "heating",
        "conditioning",
        "contractor"
    ],
    "wof:name":"Climate-Tech Inc",
    "wof:placetype":"venue"
},
  "geometry": {"coordinates":[-83.618651,42.241029],"type":"Point"}
}