{
  "type": "Feature",
  "properties": {
    "iso:country":"US",
    "sg:address":"2101 S Telegraph Rd",
    "sg:city":"Dearborn",
    "sg:classifiers":[
        {
            "category":"Travel",
            "subcategory":"Hotels & Motels",
            "type":"Entertainment"
        }
    ],
    "sg:phone":"+1 313 274 0001",
    "sg:postcode":"48124",
    "sg:province":"MI",
    "sg:website":"www.super8.com",
    "wof:name":"Super 8 of Dearborn",
    "wof:placetype":"venue"
},
  "geometry": {"coordinates":[-83.271004,42.296299],"type":"Point"}
}