{
  "type": "Feature",
  "properties": {
    "iso:country":"US",
    "sg:address":"4428 Linden Rd",
    "sg:city":"Flint",
    "sg:classifiers":[
        {
            "category":"Organizations",
            "subcategory":"Community Association",
            "type":"Services"
        }
    ],
    "sg:phone":"+1 810 732 3764",
    "sg:postcode":"48507",
    "sg:province":"MI",
    "wof:name":"Order of White Shrine Jrusalem",
    "wof:placetype":"venue"
},
  "geometry": {"coordinates":[-83.771674,42.958224],"type":"Point"}
}