{
  "type": "Feature",
  "properties": {
    "iso:country":"US",
    "sg:address":"1400 Rochester Rd",
    "sg:city":"Leonard",
    "sg:classifiers":[
        {
            "category":"Shopping",
            "subcategory":"Gifts & Souvenirs",
            "type":"Retail Goods"
        }
    ],
    "sg:phone":"+1 248 969 9300",
    "sg:postcode":"48367",
    "sg:province":"MI",
    "sg:tags":[
        "party",
        "supply"
    ],
    "wof:name":"C B's Superior Party Store LLC",
    "wof:placetype":"venue"
},
  "geometry": {"coordinates":[-83.147668,42.82134],"type":"Point"}
}