{
  "type": "Feature",
  "properties": {
    "iso:country":"US",
    "sg:address":"5210 Barbara Ave",
    "sg:city":"Trenton",
    "sg:classifiers":[
        {
            "category":"Real Estate",
            "subcategory":"Real Estate Services",
            "type":"Services"
        }
    ],
    "sg:phone":"+1 734 692 1400",
    "sg:postcode":"48183",
    "sg:province":"MI",
    "sg:tags":[
        "management",
        "property"
    ],
    "wof:name":"Hagen Management Services",
    "wof:placetype":"venue"
},
  "geometry": {"coordinates":[-83.19846,42.119063],"type":"Point"}
}