{
  "type": "Feature",
  "properties": {
    "iso:country":"US",
    "sg:address":"35965 S Gratiot Ave",
    "sg:city":"Clinton Township",
    "sg:classifiers":[
        {
            "category":"Home & Garden",
            "subcategory":"Carpets & Floor Coverings",
            "type":"Retail Goods"
        }
    ],
    "sg:phone":"+1 586 791 8796",
    "sg:postcode":"48035",
    "sg:province":"MI",
    "sg:tags":[
        "rug",
        "carpeting"
    ],
    "sg:website":"www.carpetcenterfloors.com",
    "wof:name":"Carpet Center & Floors",
    "wof:placetype":"venue"
},
  "geometry": {"coordinates":[-82.895798,42.5625],"type":"Point"}
}