{
  "type": "Feature",
  "properties": {
    "iso:country":"US",
    "sg:address":"7090 Wilcox Rd",
    "sg:city":"Eaton Rapids",
    "sg:phone":"+1 517 663 4257",
    "sg:postcode":"48827",
    "sg:province":"MI",
    "sg:tags":[
        "farm",
        "soybean"
    ],
    "wof:name":"Rodney Hector",
    "wof:placetype":"venue"
},
  "geometry": {"coordinates":[-84.74797,42.464393],"type":"Point"}
}