{
  "type": "Feature",
  "properties": {
    "iso:country":"US",
    "sg:address":"2682 US Hwy 23 N",
    "sg:city":"Alpena",
    "sg:classifiers":[
        {
            "category":"Shopping",
            "subcategory":"Department Store",
            "type":"Retail Goods"
        }
    ],
    "sg:phone":"+1 989 356 3868",
    "sg:postcode":"49707",
    "sg:province":"MI",
    "sg:tags":[
        "shop"
    ],
    "wof:name":"Family Dollar Store",
    "wof:placetype":"venue"
},
  "geometry": {"coordinates":[-83.45717399999999,45.093932],"type":"Point"}
}