{
  "type": "Feature",
  "properties": {
    "iso:country":"US",
    "sg:address":"3756 S Dort Hwy",
    "sg:city":"Flint",
    "sg:classifiers":[
        {
            "category":"Restaurant",
            "type":"Food & Drink"
        }
    ],
    "sg:phone":"+1 810 744 4899",
    "sg:postcode":"48507",
    "sg:province":"MI",
    "wof:name":"El Potrero Mexican Restaurant",
    "wof:placetype":"venue"
},
  "geometry": {"coordinates":[-83.653578,42.992882],"type":"Point"}
}