{
  "type": "Feature",
  "properties": {
    "iso:country":"US",
    "sg:address":"17360 W 12 Mile Rd",
    "sg:city":"Southfield",
    "sg:classifiers":[
        {
            "category":"Organizations",
            "subcategory":"Non-profit Organization",
            "type":"Services"
        }
    ],
    "sg:phone":"+1 248 443 7427",
    "sg:postcode":"48076",
    "sg:province":"MI",
    "sg:tags":[
        "service/non-profit",
        "community"
    ],
    "wof:name":"Jack's Place For Autism",
    "wof:placetype":"venue"
},
  "geometry": {"coordinates":[-83.21825200000001,42.502748],"type":"Point"}
}