{
  "type": "Feature",
  "properties": {
    "iso:country":"US",
    "sg:address":"15335 W 7 Mile Rd",
    "sg:city":"Detroit",
    "sg:classifiers":[
        {
            "category":"Organizations",
            "subcategory":"Religious Organization",
            "type":"Services"
        }
    ],
    "sg:phone":"+1 313 861 0605",
    "sg:postcode":"48235",
    "sg:province":"MI",
    "wof:name":"Saving Grace Ministries",
    "wof:placetype":"venue"
},
  "geometry": {"coordinates":[-83.198358,42.430384],"type":"Point"}
}