{
  "type": "Feature",
  "properties": {
    "iso:country":"US",
    "sg:address":"205 2nd Ave",
    "sg:city":"Bessemer",
    "sg:classifiers":[
        {
            "category":"Shopping",
            "subcategory":"Books",
            "type":"Retail Goods"
        }
    ],
    "sg:phone":"+1 906 663 0316",
    "sg:postcode":"49911",
    "sg:province":"MI",
    "sg:tags":[
        "dealer"
    ],
    "wof:name":"Connection Point",
    "wof:placetype":"venue"
},
  "geometry": {"coordinates":[-90.056118,46.475723],"type":"Point"}
}