{
  "type": "Feature",
  "properties": {
    "iso:country":"US",
    "sg:address":"5061 Galaxy Dr",
    "sg:city":"Utica",
    "sg:classifiers":[
        {
            "category":"Professional",
            "subcategory":"Business Services",
            "type":"Services"
        }
    ],
    "sg:phone":"+1 586 781 3443",
    "sg:postcode":"48316",
    "sg:province":"MI",
    "wof:name":"Alimar Funding",
    "wof:placetype":"venue"
},
  "geometry": {"coordinates":[-83.061966,42.688039],"type":"Point"}
}