{
  "type": "Feature",
  "properties": {
    "iso:country":"US",
    "sg:address":"1767 E Townline 16 Rd",
    "sg:city":"Pinconning",
    "sg:classifiers":[
        {
            "category":"Utilities",
            "type":"Services"
        }
    ],
    "sg:phone":"+1 989 879 2450",
    "sg:postcode":"48650",
    "sg:province":"MI",
    "sg:tags":[
        "sanitary"
    ],
    "wof:name":"Three P Plowing",
    "wof:placetype":"venue"
},
  "geometry": {"coordinates":[-83.975914,43.825126],"type":"Point"}
}