{
  "type": "Feature",
  "properties": {
    "iso:country":"US",
    "sg:address":"6533 E Jefferson Ave",
    "sg:city":"Detroit",
    "sg:classifiers":[
        {
            "category":"Retail",
            "subcategory":"Photofinishing",
            "type":"Services"
        }
    ],
    "sg:phone":"+1 313 396 0046",
    "sg:postcode":"48207",
    "sg:province":"MI",
    "sg:tags":[
        "laboratory"
    ],
    "wof:name":"Photo Fresh",
    "wof:placetype":"venue"
},
  "geometry": {"coordinates":[-83.007194,42.34492],"type":"Point"}
}