{
  "type": "Feature",
  "properties": {
    "iso:country":"US",
    "sg:address":"9301 Massey Dr",
    "sg:city":"Plymouth",
    "sg:classifiers":[
        {
            "category":"Retail",
            "subcategory":"Auto Repair",
            "type":"Services"
        }
    ],
    "sg:phone":"+1 734 459 3268",
    "sg:postcode":"48170",
    "sg:province":"MI",
    "wof:name":"Michigan Automotive",
    "wof:placetype":"venue"
},
  "geometry": {"coordinates":[-83.440099,42.358213],"type":"Point"}
}