{
  "type": "Feature",
  "properties": {
    "iso:country":"US",
    "sg:address":"2708 N Telegraph Rd",
    "sg:city":"Monroe",
    "sg:classifiers":[
        {
            "category":"Shopping",
            "subcategory":"Computers & Home Electronics",
            "type":"Retail Goods"
        }
    ],
    "sg:phone":"+1 734 242 0806",
    "sg:postcode":"48162",
    "sg:province":"MI",
    "sg:tags":[
        "repair",
        "radio"
    ],
    "wof:name":"Herkimer Radio Service",
    "wof:placetype":"venue"
},
  "geometry": {"coordinates":[-83.38894999999999,41.963842],"type":"Point"}
}