{
  "type": "Feature",
  "properties": {
    "iso:country":"US",
    "sg:address":"5640 Dixie Hwy",
    "sg:city":"Waterford",
    "sg:classifiers":[
        {
            "category":"Shopping",
            "subcategory":"Department Store",
            "type":"Retail Goods"
        }
    ],
    "sg:phone":"+1 248 623 2880",
    "sg:postcode":"48329",
    "sg:province":"MI",
    "sg:tags":[
        "shop"
    ],
    "sg:website":"www.biglots.com",
    "wof:name":"Big Lots",
    "wof:placetype":"venue"
},
  "geometry": {"coordinates":[-83.40029199999999,42.70029],"type":"Point"}
}