{
  "type": "Feature",
  "properties": {
    "iso:country":"US",
    "sg:address":"446 Driftwood Ave",
    "sg:city":"Rochester",
    "sg:classifiers":[
        {
            "category":"Building & Trades",
            "subcategory":"Plumbing",
            "type":"Services"
        }
    ],
    "sg:phone":"+1 248 656 9824",
    "sg:postcode":"48307",
    "sg:province":"MI",
    "sg:tags":[
        "contractor"
    ],
    "wof:name":"R&B Heating",
    "wof:placetype":"venue"
},
  "geometry": {"coordinates":[-83.115371,42.671694],"type":"Point"}
}