{
  "type": "Feature",
  "properties": {
    "iso:country":"US",
    "sg:address":"1099 Fairways Blvd",
    "sg:city":"Troy",
    "sg:classifiers":[
        {
            "category":"Arts & Performance",
            "subcategory":"Theater",
            "type":"Entertainment"
        }
    ],
    "sg:phone":"+1 248 879 2373",
    "sg:postcode":"48085",
    "sg:province":"MI",
    "sg:tags":[
        "band",
        "orchestra"
    ],
    "wof:name":"Intrigue & Stella Actis Aldo",
    "wof:placetype":"venue"
},
  "geometry": {"coordinates":[-83.126051,42.605358],"type":"Point"}
}