{
  "type": "Feature",
  "properties": {
    "iso:country":"US",
    "sg:address":"77 S Main",
    "sg:city":"Cedar Springs",
    "sg:classifiers":[
        {
            "category":"Restaurant",
            "type":"Food & Drink"
        }
    ],
    "sg:phone":"+1 616 696 1455",
    "sg:postcode":"49319",
    "sg:province":"MI",
    "wof:name":"Stein Brothers Pizza Co",
    "wof:placetype":"venue"
},
  "geometry": {"coordinates":[-85.551253,43.222209],"type":"Point"}
}