{
  "type": "Feature",
  "properties": {
    "iso:country":"US",
    "sg:address":"415 State St",
    "sg:city":"St Joseph",
    "sg:classifiers":[
        {
            "category":"Shopping",
            "subcategory":"Crafts & Fabrics",
            "type":"Retail Goods"
        }
    ],
    "sg:phone":"+1 269 982 8521",
    "sg:postcode":"49085",
    "sg:province":"MI",
    "sg:tags":[
        "material",
        "quilting",
        "supply"
    ],
    "wof:name":"Silver Needle",
    "wof:placetype":"venue"
},
  "geometry": {"coordinates":[-86.482967,42.107961],"type":"Point"}
}