{
  "type": "Feature",
  "properties": {
    "iso:country":"US",
    "sg:address":"14601 Eureka Rd",
    "sg:city":"Southgate",
    "sg:classifiers":[
        {
            "category":"Food & Beverages",
            "subcategory":"Farmers Market",
            "type":"Retail Goods"
        },
        {
            "category":"Farming",
            "subcategory":"Farm",
            "type":"Manufacturing & Wholesale Goods"
        },
        {
            "category":"Wholesale",
            "subcategory":"Fruits & Vegetables",
            "type":"Manufacturing & Wholesale Goods"
        }
    ],
    "sg:phone":"+1 734 246 4941",
    "sg:postcode":"48195",
    "sg:province":"MI",
    "sg:tags":[
        "veggie"
    ],
    "wof:name":"Eureka Farm Market",
    "wof:placetype":"venue"
},
  "geometry": {"coordinates":[-83.201905,42.198975],"type":"Point"}
}