{
  "type": "Feature",
  "properties": {
    "iso:country":"US",
    "sg:address":"18003 Ferguson St",
    "sg:city":"Detroit",
    "sg:classifiers":[
        {
            "category":"Professional",
            "subcategory":"Advertising",
            "type":"Services"
        }
    ],
    "sg:phone":"+1 313 835 5166",
    "sg:postcode":"48235",
    "sg:province":"MI",
    "sg:tags":[
        "marketing",
        "program"
    ],
    "wof:name":"Elite Marketing",
    "wof:placetype":"venue"
},
  "geometry": {"coordinates":[-83.210183,42.421187],"type":"Point"}
}