{
  "type": "Feature",
  "properties": {
    "iso:country":"US",
    "sg:address":"1154 W 1st St",
    "sg:city":"Gladwin",
    "sg:classifiers":[
        {
            "category":"Wholesale",
            "subcategory":"Machinery & Supplies",
            "type":"Manufacturing & Wholesale Goods"
        }
    ],
    "sg:phone":"+1 989 426 2870",
    "sg:postcode":"48624",
    "sg:province":"MI",
    "sg:tags":[
        "equipment",
        "log",
        "splitting"
    ],
    "wof:name":"Timber Equipment",
    "wof:placetype":"venue"
},
  "geometry": {"coordinates":[-84.502286,43.987882],"type":"Point"}
}