{
  "type": "Feature",
  "properties": {
    "iso:country":"US",
    "sg:address":"8481 Johnson Rd",
    "sg:city":"Belding",
    "sg:classifiers":[
        {
            "category":"Manufacturing",
            "subcategory":"Jewelry",
            "type":"Manufacturing & Wholesale Goods"
        }
    ],
    "sg:phone":"+1 616 794 2694",
    "sg:postcode":"48809",
    "sg:province":"MI",
    "sg:tags":[
        "precious",
        "metal",
        "mfg"
    ],
    "wof:name":"Bracelets By Barb",
    "wof:placetype":"venue"
},
  "geometry": {"coordinates":[-85.174623,43.1151],"type":"Point"}
}