{
  "type": "Feature",
  "properties": {
    "iso:country":"US",
    "sg:address":"6257 Lanman Dr",
    "sg:city":"Waterford",
    "sg:classifiers":[
        {
            "category":"Building & Trades",
            "subcategory":"Construction",
            "type":"Services"
        }
    ],
    "sg:phone":"+1 248 623 4681",
    "sg:postcode":"48329",
    "sg:province":"MI",
    "sg:tags":[
        "general",
        "contractor"
    ],
    "wof:name":"C & A Construction",
    "wof:placetype":"venue"
},
  "geometry": {"coordinates":[-83.409887,42.68502],"type":"Point"}
}