{
  "type": "Feature",
  "properties": {
    "iso:country":"US",
    "sg:address":"11 Gladys Ct",
    "sg:city":"Battle Creek",
    "sg:classifiers":[
        {
            "category":"Social Services",
            "subcategory":"Child Care",
            "type":"Services"
        }
    ],
    "sg:phone":"+1 269 964 7369",
    "sg:postcode":"49037",
    "sg:province":"MI",
    "sg:tags":[
        "day"
    ],
    "wof:name":"Jaynes Fun Time Day Care",
    "wof:placetype":"venue"
},
  "geometry": {"coordinates":[-85.783608,43.407207],"type":"Point"}
}