{
  "type": "Feature",
  "properties": {
    "iso:country":"US",
    "sg:address":"17450 Mack Ave",
    "sg:city":"Grosse Pointe",
    "sg:classifiers":[
        {
            "category":"Retail",
            "subcategory":"Laundry & Dry Cleaning",
            "type":"Services"
        }
    ],
    "sg:phone":"+1 313 884 6890",
    "sg:postcode":"48230",
    "sg:province":"MI",
    "wof:name":"One Hour Martinizing",
    "wof:placetype":"venue"
},
  "geometry": {"coordinates":[-82.919197,42.398399],"type":"Point"}
}