{
  "type": "Feature",
  "properties": {
    "iso:country":"US",
    "sg:address":"3656 Woodcliff Dr",
    "sg:city":"Kalamazoo",
    "sg:classifiers":[
        {
            "category":"Shopping",
            "type":"Retail Goods"
        }
    ],
    "sg:phone":"+1 269 544 7244",
    "sg:postcode":"49008",
    "sg:province":"MI",
    "sg:tags":[
        "cosmetic",
        "perfume"
    ],
    "wof:name":"Mary Kay Cosmetics",
    "wof:placetype":"venue"
},
  "geometry": {"coordinates":[-85.63266900000001,42.256195],"type":"Point"}
}