{
  "type": "Feature",
  "properties": {
    "iso:country":"US",
    "sg:address":"388 Bondie St",
    "sg:city":"Wyandotte",
    "sg:classifiers":[
        {
            "category":"Building & Trades",
            "subcategory":"Construction",
            "type":"Services"
        }
    ],
    "sg:phone":"+1 734 284 5255",
    "sg:postcode":"48192",
    "sg:province":"MI",
    "sg:tags":[
        "house"
    ],
    "wof:name":"Ecd Home Repairs",
    "wof:placetype":"venue"
},
  "geometry": {"coordinates":[-83.155198,42.228298],"type":"Point"}
}