{
  "type": "Feature",
  "properties": {
    "iso:country":"US",
    "sg:address":"25330 Send St",
    "sg:city":"Southfield",
    "sg:classifiers":[
        {
            "category":"Health Services",
            "subcategory":"Doctor",
            "type":"Services"
        }
    ],
    "sg:phone":"+1 248 355 1300",
    "sg:postcode":"48066",
    "sg:province":"MI",
    "sg:tags":[
        "medical"
    ],
    "wof:name":"Leonard Sahn MD PC",
    "wof:placetype":"venue"
},
  "geometry": {"coordinates":[-82.965214,42.481684],"type":"Point"}
}