{
  "type": "Feature",
  "properties": {
    "iso:country":"US",
    "sg:address":"3666 10th St",
    "sg:city":"Wayland",
    "sg:classifiers":[
        {
            "category":"Manufacturing",
            "subcategory":"Printing",
            "type":"Manufacturing & Wholesale Goods"
        }
    ],
    "sg:phone":"+1 269 792 0007",
    "sg:postcode":"49348",
    "sg:province":"MI",
    "sg:tags":[
        "bookbinding"
    ],
    "wof:name":"West Michigan Bookbindery",
    "wof:placetype":"venue"
},
  "geometry": {"coordinates":[-85.64369499999999,42.687899],"type":"Point"}
}