{
  "type": "Feature",
  "properties": {
    "iso:country":"US",
    "sg:address":"225 E Lyons St",
    "sg:city":"Schoolcraft",
    "sg:classifiers":[
        {
            "category":"Banks & Credit Unions",
            "subcategory":"Bank",
            "type":"Services"
        }
    ],
    "sg:phone":"+1 269 679 5296",
    "sg:postcode":"49087",
    "sg:province":"MI",
    "sg:tags":[
        "loan",
        "real estate"
    ],
    "sg:website":"www.greenstonefcs.com",
    "wof:name":"Greenstone Farm Credit Svc",
    "wof:placetype":"venue"
},
  "geometry": {"coordinates":[-85.636154,42.121588],"type":"Point"}
}