{
  "type": "Feature",
  "properties": {
    "iso:country":"US",
    "sg:address":"220 N Main St",
    "sg:city":"Adrian",
    "sg:classifiers":[
        {
            "category":"Government",
            "subcategory":"Office",
            "type":"Public Place"
        }
    ],
    "sg:phone":"+1 517 263 3696",
    "sg:postcode":"49221",
    "sg:province":"MI",
    "sg:tags":[
        "armed",
        "force",
        "recruiting"
    ],
    "wof:name":"US Naval Recruiting",
    "wof:placetype":"venue"
},
  "geometry": {"coordinates":[-84.034901,41.901278],"type":"Point"}
}