{
  "type": "Feature",
  "properties": {
    "iso:country":"US",
    "sg:address":"1201 Stone St",
    "sg:city":"Port Huron",
    "sg:classifiers":[
        {
            "category":"Health Services",
            "subcategory":"Doctor",
            "type":"Services"
        }
    ],
    "sg:phone":"+1 810 982 8742",
    "sg:postcode":"48060",
    "sg:province":"MI",
    "sg:tags":[
        "physician",
        "surgeon"
    ],
    "wof:name":"Physician Healthcare Network",
    "wof:placetype":"venue"
},
  "geometry": {"coordinates":[-82.43083799999999,42.987521],"type":"Point"}
}