{
  "type": "Feature",
  "properties": {
    "iso:country":"US",
    "sg:address":"7665 Merriman Rd",
    "sg:city":"Romulus",
    "sg:classifiers":[
        {
            "category":"Banks & Credit Unions",
            "subcategory":"Bank",
            "type":"Services"
        }
    ],
    "sg:phone":"+1 734 641 8400",
    "sg:postcode":"48174",
    "sg:province":"MI",
    "sg:website":"www.pscunow.com",
    "wof:name":"Public Service Credit Union",
    "wof:placetype":"venue"
},
  "geometry": {"coordinates":[-83.34687700000001,42.248248],"type":"Point"}
}