{
  "type": "Feature",
  "properties": {
    "iso:country":"US",
    "sg:address":"702 N Front St",
    "sg:city":"Dowagiac",
    "sg:classifiers":[
        {
            "category":"Real Estate",
            "subcategory":"Real Estate Agent",
            "type":"Services"
        }
    ],
    "sg:phone":"+1 269 782 5777",
    "sg:postcode":"49047",
    "sg:province":"MI",
    "sg:website":"www.springsteenrealty.com",
    "wof:name":"Springsteen Realty",
    "wof:placetype":"venue"
},
  "geometry": {"coordinates":[-86.107286,41.992521],"type":"Point"}
}