{
  "type": "Feature",
  "properties": {
    "iso:country":"US",
    "sg:address":"436 Hawkins St",
    "sg:city":"Ypsilanti",
    "sg:classifiers":[
        {
            "category":"Organizations",
            "subcategory":"Religious Organization",
            "type":"Services"
        }
    ],
    "sg:phone":"+1 734 483 6339",
    "sg:postcode":"48197",
    "sg:province":"MI",
    "wof:name":"Mt Olive Church God In Christ",
    "wof:placetype":"venue"
},
  "geometry": {"coordinates":[-83.622254,42.235682],"type":"Point"}
}