{
  "type": "Feature",
  "properties": {
    "iso:country":"US",
    "sg:address":"3255 Trowbridge St",
    "sg:city":"Detroit",
    "sg:classifiers":[
        {
            "category":"Building & Trades",
            "subcategory":"Construction",
            "type":"Services"
        }
    ],
    "sg:phone":"+1 313 874 1238",
    "sg:postcode":"48212",
    "sg:province":"MI",
    "sg:tags":[
        "house"
    ],
    "wof:name":"EPM Home Improvement",
    "wof:placetype":"venue"
},
  "geometry": {"coordinates":[-83.05934999999999,42.399121],"type":"Point"}
}