{
  "type": "Feature",
  "properties": {
    "iso:country":"US",
    "sg:address":"20771 Randall St",
    "sg:city":"Farmington Hills",
    "sg:classifiers":[
        {
            "category":"Building & Trades",
            "subcategory":"Construction",
            "type":"Services"
        }
    ],
    "sg:phone":"+1 248 474 0707",
    "sg:postcode":"48336",
    "sg:province":"MI",
    "sg:tags":[
        "contractor"
    ],
    "wof:name":"Rotondo Construction Inc",
    "wof:placetype":"venue"
},
  "geometry": {"coordinates":[-83.3526,42.4412],"type":"Point"}
}