{
  "type": "Feature",
  "properties": {
    "iso:country":"US",
    "sg:address":"5121 Broadmoor Ave SE",
    "sg:city":"Grand Rapids",
    "sg:classifiers":[
        {
            "category":"Retail",
            "subcategory":"Auto Repair",
            "type":"Services"
        }
    ],
    "sg:phone":"+1 616 656 5959",
    "sg:postcode":"49512",
    "sg:province":"MI",
    "sg:tags":[
        "automobile",
        "lubrication"
    ],
    "wof:name":"Express Care Quick Lube",
    "wof:placetype":"venue"
},
  "geometry": {"coordinates":[-85.555277,42.87119],"type":"Point"}
}