{
  "type": "Feature",
  "properties": {
    "iso:country":"US",
    "sg:address":"8033 Brookfield Rd",
    "sg:city":"Charlotte",
    "sg:classifiers":[
        {
            "category":"Government",
            "subcategory":"Office",
            "type":"Public Place"
        }
    ],
    "sg:phone":"+1 517 543 3060",
    "sg:postcode":"48813",
    "sg:province":"MI",
    "sg:tags":[
        "village"
    ],
    "wof:name":"Brookfield Township Hall",
    "wof:placetype":"venue"
},
  "geometry": {"coordinates":[-84.796823,42.450234],"type":"Point"}
}