{
  "type": "Feature",
  "properties": {
    "iso:country":"US",
    "sg:address":"19500 Ford Rd",
    "sg:city":"Dearborn",
    "sg:classifiers":[
        {
            "category":"Sports & Exercise",
            "subcategory":"Sports Center",
            "type":"Entertainment"
        },
        {
            "category":"Organizations",
            "subcategory":"Religious Organization",
            "type":"Services"
        }
    ],
    "sg:phone":"+1 313 271 1835",
    "sg:postcode":"48128",
    "sg:province":"MI",
    "sg:tags":[
        "amateur",
        "team"
    ],
    "wof:name":"Islamic Center of America",
    "wof:placetype":"venue"
},
  "geometry": {"coordinates":[-83.24074400000001,42.328626],"type":"Point"}
}