{
  "type": "Feature",
  "properties": {
    "iso:country":"US",
    "sg:address":"5675 Forcier Ct",
    "sg:city":"Shelby Twp",
    "sg:classifiers":[
        {
            "category":"Wholesale",
            "subcategory":"Machinery & Supplies",
            "type":"Manufacturing & Wholesale Goods"
        },
        {
            "category":"Building & Trades",
            "subcategory":"Plumbing",
            "type":"Services"
        }
    ],
    "sg:phone":"+1 586 254 2222",
    "sg:postcode":"48317",
    "sg:province":"MI",
    "sg:tags":[
        "plumbing",
        "equipment",
        "sewer",
        "cleaning",
        "repair"
    ],
    "wof:name":"Royal Sewer & Plumbing Service",
    "wof:placetype":"venue"
},
  "geometry": {"coordinates":[-83.054025,42.658473],"type":"Point"}
}