{
  "type": "Feature",
  "properties": {
    "iso:country":"US",
    "sg:address":"2303 Gratiot Blvd",
    "sg:city":"Marysville",
    "sg:classifiers":[
        {
            "category":"Real Estate",
            "subcategory":"Real Estate Agent",
            "type":"Services"
        }
    ],
    "sg:phone":"+1 810 364 7484",
    "sg:postcode":"48040",
    "sg:province":"MI",
    "wof:name":"Scott R Worden Mortgage",
    "wof:placetype":"venue"
},
  "geometry": {"coordinates":[-82.48627999999999,42.915485],"type":"Point"}
}