{
  "type": "Feature",
  "properties": {
    "iso:country":"US",
    "sg:address":"114 N Main St",
    "sg:city":"Ithaca",
    "sg:classifiers":[
        {
            "category":"Health Services",
            "subcategory":"Doctor",
            "type":"Services"
        }
    ],
    "sg:phone":"+1 989 875 4800",
    "sg:postcode":"48847",
    "sg:province":"MI",
    "sg:tags":[
        "osteopathic"
    ],
    "wof:name":"Center For Womens Health Care",
    "wof:placetype":"venue"
},
  "geometry": {"coordinates":[-84.605571,43.292814],"type":"Point"}
}