{
  "type": "Feature",
  "properties": {
    "iso:country":"US",
    "sg:address":"8579 River Oaks Cir",
    "sg:city":"Greenville",
    "sg:classifiers":[
        {
            "category":"Professional",
            "subcategory":"Management & Consulting",
            "type":"Services"
        }
    ],
    "sg:phone":"+1 616 225 2170",
    "sg:postcode":"48838",
    "sg:province":"MI",
    "sg:tags":[
        "consultant",
        "training"
    ],
    "sg:website":"www.dieology.com",
    "wof:name":"Dieology",
    "wof:placetype":"venue"
},
  "geometry": {"coordinates":[-85.24676700000001,43.153209],"type":"Point"}
}