{
  "type": "Feature",
  "properties": {
    "iso:country":"US",
    "sg:address":"23200 W 13 Mile Rd",
    "sg:city":"Bingham Farms",
    "sg:classifiers":[
        {
            "category":"Manufacturing",
            "subcategory":"Textiles",
            "type":"Manufacturing & Wholesale Goods"
        }
    ],
    "sg:phone":"+1 248 647 2912",
    "sg:postcode":"48025",
    "sg:province":"MI",
    "wof:name":"Justin M Anderson Designs",
    "wof:placetype":"venue"
},
  "geometry": {"coordinates":[-83.27591099999999,42.51585],"type":"Point"}
}