{
  "type": "Feature",
  "properties": {
    "iso:country":"US",
    "sg:address":"840 Davis Rd",
    "sg:city":"Sandusky",
    "sg:classifiers":[
        {
            "category":"Farming",
            "subcategory":"Livestock Farm",
            "type":"Manufacturing & Wholesale Goods"
        }
    ],
    "sg:phone":"+1 810 648 9105",
    "sg:postcode":"48471",
    "sg:province":"MI",
    "sg:tags":[
        "beef",
        "feedlot",
        "cattle"
    ],
    "wof:name":"Larry Miller",
    "wof:placetype":"venue"
},
  "geometry": {"coordinates":[-82.802364,43.450621],"type":"Point"}
}