{
  "type": "Feature",
  "properties": {
    "iso:country":"US",
    "sg:address":"22030 Kenosha St",
    "sg:city":"Oak Park",
    "sg:classifiers":[
        {
            "category":"Social Services",
            "subcategory":"Child Care",
            "type":"Services"
        }
    ],
    "sg:phone":"+1 248 336 8476",
    "sg:postcode":"48237",
    "sg:province":"MI",
    "sg:tags":[
        "day"
    ],
    "wof:name":"Candyland",
    "wof:placetype":"venue"
},
  "geometry": {"coordinates":[-83.190175,42.457545],"type":"Point"}
}