{
  "type": "Feature",
  "properties": {
    "iso:country":"US",
    "sg:address":"845 E Napier Ave",
    "sg:city":"Benton Harbor",
    "sg:classifiers":[
        {
            "category":"Retail",
            "subcategory":"Auto Repair",
            "type":"Services"
        }
    ],
    "sg:phone":"+1 269 927 1919",
    "sg:postcode":"49022",
    "sg:province":"MI",
    "sg:tags":[
        "muffler",
        "shop",
        "brake"
    ],
    "wof:name":"Muffler Man",
    "wof:placetype":"venue"
},
  "geometry": {"coordinates":[-86.43859999999999,42.087158],"type":"Point"}
}