{
  "type": "Feature",
  "properties": {
    "iso:country":"US",
    "sg:address":"6046 Piers Gorge Rd",
    "sg:city":"Norway",
    "sg:classifiers":[
        {
            "category":"Professional",
            "type":"Services"
        }
    ],
    "sg:phone":"+1 906 563 8351",
    "sg:postcode":"49870",
    "sg:province":"MI",
    "sg:tags":[
        "establishment"
    ],
    "wof:name":"Alwine Hilarie",
    "wof:placetype":"venue"
},
  "geometry": {"coordinates":[-87.938794,45.759825],"type":"Point"}
}