{
  "type": "Feature",
  "properties": {
    "iso:country":"US",
    "sg:address":"2213 W Main St",
    "sg:city":"Kalamazoo",
    "sg:classifiers":[
        {
            "category":"Professional",
            "subcategory":"Management & Consulting",
            "type":"Services"
        }
    ],
    "sg:phone":"+1 269 226 9327",
    "sg:postcode":"49006",
    "sg:province":"MI",
    "sg:tags":[
        "personnel",
        "consultant"
    ],
    "wof:name":"Health Care Professional",
    "wof:placetype":"venue"
},
  "geometry": {"coordinates":[-85.616778,42.294751],"type":"Point"}
}