{
  "type": "Feature",
  "properties": {
    "iso:country":"US",
    "sg:address":"77 State Hwy 77",
    "sg:city":"Hurley",
    "sg:classifiers":[
        {
            "category":"Professional",
            "type":"Services"
        }
    ],
    "sg:phone":"+1 715 561 5085",
    "sg:postcode":"54534",
    "sg:province":"WI",
    "sg:tags":[
        "establishment"
    ],
    "wof:name":"Hide-A-Way",
    "wof:placetype":"venue"
},
  "geometry": {"coordinates":[-90.179724,46.449817],"type":"Point"}
}