{
  "type": "Feature",
  "properties": {
    "iso:country":"US",
    "sg:address":"1383 E Pinconning Rd",
    "sg:city":"Pinconning",
    "sg:classifiers":[
        {
            "category":"Government",
            "subcategory":"Office",
            "type":"Public Place"
        }
    ],
    "sg:phone":"+1 989 879 3761",
    "sg:postcode":"48650",
    "sg:province":"MI",
    "wof:name":"Bay County Road Commission",
    "wof:placetype":"venue"
},
  "geometry": {"coordinates":[-83.99256699999999,43.853794],"type":"Point"}
}