{
  "type": "Feature",
  "properties": {
    "iso:country":"US",
    "sg:address":"7071 Orchard Lake Rd Ste 225",
    "sg:city":"West Bloomfield",
    "sg:classifiers":[
        {
            "category":"Health Services",
            "subcategory":"Doctor",
            "type":"Services"
        }
    ],
    "sg:phone":"+1 248 851 8281",
    "sg:postcode":"48322",
    "sg:province":"MI",
    "wof:name":"Fiksman Irina Psychtrst",
    "wof:placetype":"venue"
},
  "geometry": {"coordinates":[-83.360298,42.534302],"type":"Point"}
}