{
  "type": "Feature",
  "properties": {
    "iso:country":"US",
    "sg:address":"138 W Upton Ave",
    "sg:city":"Reed City",
    "sg:classifiers":[
        {
            "category":"Manufacturing",
            "subcategory":"Lumber",
            "type":"Manufacturing & Wholesale Goods"
        }
    ],
    "sg:phone":"+1 231 832 5341",
    "sg:postcode":"49677",
    "sg:province":"MI",
    "sg:tags":[
        "government"
    ],
    "wof:name":"US Forestry Dept",
    "wof:placetype":"venue"
},
  "geometry": {"coordinates":[-85.511171,43.876032],"type":"Point"}
}