{
  "type": "Feature",
  "properties": {
    "iso:country":"US",
    "sg:address":"3145 Copper Ave",
    "sg:city":"Fenton",
    "sg:classifiers":[
        {
            "category":"Manufacturing",
            "subcategory":"Tools & Machinery",
            "type":"Manufacturing & Wholesale Goods"
        }
    ],
    "sg:phone":"+1 810 714 4775",
    "sg:postcode":"48430",
    "sg:province":"MI",
    "sg:tags":[
        "physician",
        "surgeon"
    ],
    "wof:name":"Excel Medical Products L L C",
    "wof:placetype":"venue"
},
  "geometry": {"coordinates":[-83.73105099999999,42.792865],"type":"Point"}
}