{
  "type": "Feature",
  "properties": {
    "iso:country":"US",
    "sg:address":"29101 Northwestern Hwy",
    "sg:city":"Southfield",
    "sg:classifiers":[
        {
            "category":"Restaurant",
            "type":"Food & Drink"
        }
    ],
    "sg:phone":"+1 248 358 1600",
    "sg:postcode":"48034",
    "sg:province":"MI",
    "sg:tags":[
        "pizza"
    ],
    "wof:name":"Bellacino's Pizza & Grinders",
    "wof:placetype":"venue"
},
  "geometry": {"coordinates":[-83.309898,42.501202],"type":"Point"}
}