{
  "type": "Feature",
  "properties": {
    "iso:country":"US",
    "sg:address":"2629 Kingstowne Dr",
    "sg:city":"Commerce Township",
    "sg:classifiers":[
        {
            "category":"Communications",
            "type":"Services"
        }
    ],
    "sg:phone":"+1 248 960 0166",
    "sg:postcode":"48390",
    "sg:province":"MI",
    "sg:tags":[
        "web",
        "design"
    ],
    "wof:name":"Pro Link Inc",
    "wof:placetype":"venue"
},
  "geometry": {"coordinates":[-83.451773,42.554309],"type":"Point"}
}