{
  "type": "Feature",
  "properties": {
    "iso:country":"US",
    "sg:address":"15406 Gary Ln",
    "sg:city":"Bath",
    "sg:classifiers":[
        {
            "category":"Organizations",
            "subcategory":"Religious Organization",
            "type":"Services"
        }
    ],
    "sg:phone":"+1 517 214 2349",
    "sg:postcode":"48808",
    "sg:province":"MI",
    "wof:name":"Universal Life Church",
    "wof:placetype":"venue"
},
  "geometry": {"coordinates":[-84.453913,42.792811],"type":"Point"}
}