{
  "type": "Feature",
  "properties": {
    "iso:country":"US",
    "sg:address":"805 S State Rd",
    "sg:city":"Davison",
    "sg:classifiers":[
        {
            "category":"Shopping",
            "subcategory":"Mobile Phones",
            "type":"Retail Goods"
        }
    ],
    "sg:phone":"+1 810 658 8487",
    "sg:postcode":"48423",
    "sg:province":"MI",
    "sg:website":"www.radioshack.com",
    "wof:name":"Radioshack",
    "wof:placetype":"venue"
},
  "geometry": {"coordinates":[-83.517747,43.021581],"type":"Point"}
}