{
  "type": "Feature",
  "properties": {
    "iso:country":"US",
    "sg:address":"113 Mc Pherson Ave",
    "sg:city":"Lansing",
    "sg:classifiers":[
        {
            "category":"Recreation",
            "type":"Entertainment"
        }
    ],
    "sg:phone":"+1 517 371 2399",
    "sg:postcode":"48915",
    "sg:province":"MI",
    "wof:name":"Lansing Warriors Basketball",
    "wof:placetype":"venue"
},
  "geometry": {"coordinates":[-84.57487500000001,42.733023],"type":"Point"}
}