{
  "type": "Feature",
  "properties": {
    "iso:country":"US",
    "sg:address":"2335 S Center Rd",
    "sg:city":"Burton",
    "sg:classifiers":[
        {
            "category":"Building & Trades",
            "subcategory":"Construction",
            "type":"Services"
        }
    ],
    "sg:phone":"+1 810 743 4355",
    "sg:postcode":"48519",
    "sg:province":"MI",
    "sg:tags":[
        "contractor"
    ],
    "wof:name":"P C Watters",
    "wof:placetype":"venue"
},
  "geometry": {"coordinates":[-83.63387299999999,42.992968],"type":"Point"}
}