{
  "type": "Feature",
  "properties": {
    "iso:country":"US",
    "sg:address":"8397 Senator St",
    "sg:city":"Detroit",
    "sg:classifiers":[
        {
            "category":"Professional",
            "subcategory":"Business Services",
            "type":"Services"
        }
    ],
    "sg:phone":"+1 313 842 1909",
    "sg:postcode":"48209",
    "sg:province":"MI",
    "wof:name":"Montemayor Express",
    "wof:placetype":"venue"
},
  "geometry": {"coordinates":[-83.130368,42.308566],"type":"Point"}
}