{
  "type": "Feature",
  "properties": {
    "iso:country":"US",
    "sg:address":"4147 Orchard Lake Rd",
    "sg:city":"Orchard Lake",
    "sg:classifiers":[
        {
            "category":"Personal",
            "subcategory":"Beauty Salon",
            "type":"Services"
        }
    ],
    "sg:phone":"+1 248 626 2211",
    "sg:postcode":"48323",
    "sg:province":"MI",
    "wof:name":"Cut-N-More",
    "wof:placetype":"venue"
},
  "geometry": {"coordinates":[-83.36223699999999,42.577661],"type":"Point"}
}