{
  "type": "Feature",
  "properties": {
    "iso:country":"US",
    "sg:address":"800 E Steel St",
    "sg:city":"St Johns",
    "sg:classifiers":[
        {
            "category":"Shopping",
            "type":"Retail Goods"
        }
    ],
    "sg:phone":"+1 989 227 9207",
    "sg:postcode":"48879",
    "sg:province":"MI",
    "sg:tags":[
        "monument"
    ],
    "wof:name":"Brewer Bouchey Monument",
    "wof:placetype":"venue"
},
  "geometry": {"coordinates":[-84.547952,43.006094],"type":"Point"}
}