{
  "type": "Feature",
  "properties": {
    "iso:country":"US",
    "sg:address":"10 White Hills Ave NE",
    "sg:city":"Grand Rapids",
    "sg:classifiers":[
        {
            "category":"Professional",
            "subcategory":"Business Services",
            "type":"Services"
        }
    ],
    "sg:phone":"+1 616 957 2309",
    "sg:postcode":"49546",
    "sg:province":"MI",
    "sg:tags":[
        "appraiser"
    ],
    "wof:name":"Kent County Appraisals",
    "wof:placetype":"venue"
},
  "geometry": {"coordinates":[-85.56972,42.964545],"type":"Point"}
}