{
  "type": "Feature",
  "properties": {
    "iso:country":"US",
    "sg:address":"763 S Michigan Ave",
    "sg:city":"Howell",
    "sg:classifiers":[
        {
            "category":"Food & Beverages",
            "subcategory":"Groceries & Convenience Stores",
            "type":"Retail Goods"
        }
    ],
    "sg:phone":"+1 517 546 4764",
    "sg:postcode":"48843",
    "sg:province":"MI",
    "wof:name":"Convenience Depot",
    "wof:placetype":"venue"
},
  "geometry": {"coordinates":[-83.933567,42.60076],"type":"Point"}
}