{
  "type": "Feature",
  "properties": {
    "iso:country":"US",
    "sg:address":"7800 W Grand River Hwy",
    "sg:city":"Grand Ledge",
    "sg:classifiers":[
        {
            "category":"Restaurant",
            "type":"Food & Drink"
        }
    ],
    "sg:phone":"+1 517 622 4564",
    "sg:postcode":"48837",
    "sg:province":"MI",
    "wof:name":"Country Market Restaurant",
    "wof:placetype":"venue"
},
  "geometry": {"coordinates":[-84.67573,42.785999],"type":"Point"}
}