{
  "type": "Feature",
  "properties": {
    "iso:country":"US",
    "sg:address":"38196 Villa Mar St",
    "sg:city":"Harrison Township",
    "sg:classifiers":[
        {
            "category":"Organizations",
            "subcategory":"Community Association",
            "type":"Services"
        }
    ],
    "sg:phone":"+1 586 463 7246",
    "sg:postcode":"48045",
    "sg:province":"MI",
    "wof:name":"Pointe Rosa Home Owners A",
    "wof:placetype":"venue"
},
  "geometry": {"coordinates":[-82.815427,42.576646],"type":"Point"}
}