{
  "type": "Feature",
  "properties": {
    "iso:country":"US",
    "sg:address":"1934 N Lakeshore Dr",
    "sg:city":"Ludington",
    "sg:classifiers":[
        {
            "category":"Travel",
            "subcategory":"Hotels & Motels",
            "type":"Entertainment"
        }
    ],
    "sg:phone":"+1 231 843 3884",
    "sg:postcode":"49431",
    "sg:province":"MI",
    "sg:tags":[
        "operation"
    ],
    "wof:name":"Motel Lakewood",
    "wof:placetype":"venue"
},
  "geometry": {"coordinates":[-86.459839,43.990522],"type":"Point"}
}