{
  "type": "Feature",
  "properties": {
    "iso:country":"US",
    "sg:address":"15999 W 12 Mile Rd",
    "sg:city":"Southfield",
    "sg:classifiers":[
        {
            "category":"Social Services",
            "type":"Services"
        }
    ],
    "sg:phone":"+1 248 483 5484",
    "sg:postcode":"48076",
    "sg:province":"MI",
    "wof:name":"Morning Star Adoption Resource",
    "wof:placetype":"venue"
},
  "geometry": {"coordinates":[-83.206323,42.502839],"type":"Point"}
}