{
  "type": "Feature",
  "properties": {
    "iso:country":"US",
    "sg:address":"22400 Hillview Ln",
    "sg:city":"Birmingham",
    "sg:classifiers":[
        {
            "category":"Education",
            "subcategory":"School",
            "type":"Public Place"
        }
    ],
    "sg:phone":"+1 248 646 7717",
    "sg:postcode":"48025",
    "sg:province":"MI",
    "wof:name":"Hillview Campus",
    "wof:placetype":"venue"
},
  "geometry": {"coordinates":[-83.262833,42.511639],"type":"Point"}
}