{
  "type": "Feature",
  "properties": {
    "iso:country":"US",
    "sg:address":"6706 Picketts Way",
    "sg:city":"Lansing",
    "sg:classifiers":[
        {
            "category":"Building & Trades",
            "subcategory":"Construction",
            "type":"Services"
        }
    ],
    "sg:phone":"+1 517 886 5195",
    "sg:postcode":"48917",
    "sg:province":"MI",
    "sg:tags":[
        "hanging",
        "contractor"
    ],
    "wof:name":"Dp Painters LLC",
    "wof:placetype":"venue"
},
  "geometry": {"coordinates":[-84.649384,42.727802],"type":"Point"}
}