{
  "type": "Feature",
  "properties": {
    "iso:country":"US",
    "sg:address":"42275 Sable Blvd",
    "sg:city":"Sterling Heights",
    "sg:classifiers":[
        {
            "category":"Organizations",
            "subcategory":"Religious Organization",
            "type":"Services"
        }
    ],
    "sg:phone":"+1 586 726 7440",
    "sg:postcode":"48314",
    "sg:province":"MI",
    "wof:name":"Raptoplous Christ",
    "wof:placetype":"venue"
},
  "geometry": {"coordinates":[-83.07273000000001,42.602637],"type":"Point"}
}