{
  "type": "Feature",
  "properties": {
    "iso:country":"US",
    "sg:address":"3607 W 14 Mile Rd",
    "sg:city":"Royal Oak",
    "sg:classifiers":[
        {
            "category":"Real Estate",
            "subcategory":"Developer",
            "type":"Services"
        }
    ],
    "sg:phone":"+1 248 549 3489",
    "sg:postcode":"48073",
    "sg:province":"MI",
    "sg:tags":[
        "cemetery"
    ],
    "wof:name":"Andrew Phythian",
    "wof:placetype":"venue"
},
  "geometry": {"coordinates":[-83.189471,42.532342],"type":"Point"}
}