{
  "type": "Feature",
  "properties": {
    "iso:country":"US",
    "sg:address":"23625 Northwestern Hwy",
    "sg:city":"Southfield",
    "sg:classifiers":[
        {
            "category":"Professional",
            "subcategory":"Lawyer & Legal Services",
            "type":"Services"
        }
    ],
    "sg:phone":"+1 248 355 5020",
    "sg:postcode":"48075",
    "sg:province":"MI",
    "wof:name":"Tochman Peter R",
    "wof:placetype":"venue"
},
  "geometry": {"coordinates":[-83.22869900000001,42.4631],"type":"Point"}
}