{
  "type": "Feature",
  "properties": {
    "iso:country":"US",
    "sg:address":"506 W Carleton Rd",
    "sg:city":"Hillsdale",
    "sg:classifiers":[
        {
            "category":"Health Services",
            "subcategory":"Doctor",
            "type":"Services"
        }
    ],
    "sg:phone":"+1 517 437 4414",
    "sg:postcode":"49242",
    "sg:province":"MI",
    "sg:tags":[
        "physician",
        "surgeon"
    ],
    "wof:name":"Hillsdale Laser Clinic",
    "wof:placetype":"venue"
},
  "geometry": {"coordinates":[-84.646546,41.939451],"type":"Point"}
}