{
  "type": "Feature",
  "properties": {
    "iso:country":"US",
    "sg:address":"41826 Ramsgate Ct",
    "sg:city":"Sterling Heights",
    "sg:classifiers":[
        {
            "category":"Education",
            "subcategory":"Special Training",
            "type":"Public Place"
        }
    ],
    "sg:phone":"+1 586 726 2587",
    "sg:postcode":"48314",
    "sg:province":"MI",
    "sg:tags":[
        "aid",
        "instruction",
        "first"
    ],
    "wof:name":"A One Health & Safety",
    "wof:placetype":"venue"
},
  "geometry": {"coordinates":[-83.082351,42.599553],"type":"Point"}
}