{
  "type": "Feature",
  "properties": {
    "iso:country":"US",
    "sg:address":"9000 Haggerty Rd",
    "sg:city":"Belleville",
    "sg:classifiers":[
        {
            "category":"Banks & Credit Unions",
            "subcategory":"Bank",
            "type":"Services"
        }
    ],
    "sg:phone":"+1 734 957 5082",
    "sg:postcode":"48111",
    "sg:province":"MI",
    "sg:tags":[
        "national",
        "commercial"
    ],
    "wof:name":"Bank One",
    "wof:placetype":"venue"
},
  "geometry": {"coordinates":[-83.44541700000001,42.238155],"type":"Point"}
}