{
  "type": "Feature",
  "properties": {
    "iso:country":"US",
    "sg:address":"319 Tittabawassee Rd",
    "sg:city":"Saginaw",
    "sg:classifiers":[
        {
            "category":"Organizations",
            "subcategory":"Professional Association",
            "type":"Services"
        }
    ],
    "sg:phone":"+1 989 755 0931",
    "sg:postcode":"48604",
    "sg:province":"MI",
    "sg:tags":[
        "business"
    ],
    "wof:name":"City of Zilwaukee",
    "wof:placetype":"venue"
},
  "geometry": {"coordinates":[-83.92067400000001,43.479325],"type":"Point"}
}