{
  "type": "Feature",
  "properties": {
    "iso:country":"US",
    "sg:address":"4800 Broadmoor Ave SE",
    "sg:city":"Kentwood",
    "sg:classifiers":[
        {
            "category":"Shopping",
            "type":"Retail Goods"
        }
    ],
    "sg:phone":"+1 616 698 8054",
    "sg:postcode":"49512",
    "sg:province":"MI",
    "sg:tags":[
        "cosmetic",
        "perfume"
    ],
    "wof:name":"Mary Kay Cosmetics",
    "wof:placetype":"venue"
},
  "geometry": {"coordinates":[-85.56411300000001,42.882673],"type":"Point"}
}