{
  "type": "Feature",
  "properties": {
    "iso:country":"US",
    "sg:address":"61381 Miriam Dr",
    "sg:city":"Washington",
    "sg:classifiers":[
        {
            "category":"Retail",
            "subcategory":"Repair Shop",
            "type":"Services"
        }
    ],
    "sg:phone":"+1 586 677 3203",
    "sg:postcode":"48094",
    "sg:province":"MI",
    "sg:tags":[
        "cleaning"
    ],
    "wof:name":"R & R Cleaning Services",
    "wof:placetype":"venue"
},
  "geometry": {"coordinates":[-83.043982,42.745393],"type":"Point"}
}