{
  "type": "Feature",
  "properties": {
    "iso:country":"US",
    "sg:address":"33739 King Richard Dr",
    "sg:city":"Sterling Heights",
    "sg:classifiers":[
        {
            "category":"Professional",
            "subcategory":"Detective & Security Services",
            "type":"Services"
        }
    ],
    "sg:phone":"+1 586 264 3880",
    "sg:postcode":"48310",
    "sg:province":"MI",
    "sg:tags":[
        "guard",
        "patrol"
    ],
    "wof:name":"Security Devices",
    "wof:placetype":"venue"
},
  "geometry": {"coordinates":[-83.06375800000001,42.540179],"type":"Point"}
}