{
  "type": "Feature",
  "properties": {
    "iso:country":"US",
    "sg:address":"16300 W 9 Mile Rd",
    "sg:city":"Southfield",
    "sg:classifiers":[
        {
            "category":"Professional",
            "subcategory":"Management & Consulting",
            "type":"Services"
        }
    ],
    "sg:phone":"+1 248 569 0834",
    "sg:postcode":"48075",
    "sg:province":"MI",
    "sg:tags":[
        "consultant"
    ],
    "wof:name":"K R Consultants",
    "wof:placetype":"venue"
},
  "geometry": {"coordinates":[-83.210297,42.459157],"type":"Point"}
}