{
  "type": "Feature",
  "properties": {
    "iso:country":"US",
    "sg:address":"48714 Sturgis Ct",
    "sg:city":"Shelby Twp",
    "sg:classifiers":[
        {
            "category":"Manufacturing",
            "subcategory":"Tools & Machinery",
            "type":"Manufacturing & Wholesale Goods"
        }
    ],
    "sg:phone":"+1 586 566 3895",
    "sg:postcode":"48315",
    "sg:province":"MI",
    "sg:tags":[
        "broaching"
    ],
    "wof:name":"Broaching Service Inc",
    "wof:placetype":"venue"
},
  "geometry": {"coordinates":[-82.991696,42.653638],"type":"Point"}
}