{
  "type": "Feature",
  "properties": {
    "iso:country":"US",
    "sg:address":"939 E Portage Ave",
    "sg:city":"Sault Ste Marie",
    "sg:classifiers":[
        {
            "category":"Banks & Credit Unions",
            "subcategory":"Investment Brokerage",
            "type":"Services"
        }
    ],
    "sg:phone":"+1 906 632 4985",
    "sg:postcode":"49783",
    "sg:province":"MI",
    "sg:tags":[
        "retirement",
        "planning"
    ],
    "wof:name":"Edward Jones Co",
    "wof:placetype":"venue"
},
  "geometry": {"coordinates":[-84.326177,46.49361],"type":"Point"}
}