{
  "type": "Feature",
  "properties": {
    "iso:country":"US",
    "sg:address":"2197 E Mount Morris Rd",
    "sg:city":"Mt Morris",
    "sg:classifiers":[
        {
            "category":"Health Services",
            "subcategory":"Clinic",
            "type":"Services"
        }
    ],
    "sg:phone":"+1 810 564 0100",
    "sg:postcode":"48458",
    "sg:province":"MI",
    "sg:tags":[
        "home"
    ],
    "wof:name":"Evergreen Personal Svc",
    "wof:placetype":"venue"
},
  "geometry": {"coordinates":[-83.67401599999999,43.119853],"type":"Point"}
}