{
  "type": "Feature",
  "properties": {
    "iso:country":"US",
    "sg:address":"2896 Dormax St SW",
    "sg:city":"Grandville",
    "sg:classifiers":[
        {
            "category":"Wholesale",
            "subcategory":"Meat",
            "type":"Manufacturing & Wholesale Goods"
        }
    ],
    "sg:phone":"+1 616 538 3333",
    "sg:postcode":"49418",
    "sg:province":"MI",
    "wof:name":"T & C Foods Inc",
    "wof:placetype":"venue"
},
  "geometry": {"coordinates":[-85.735956,42.911318],"type":"Point"}
}