{
  "type": "Feature",
  "properties": {
    "iso:country":"US",
    "sg:address":"210 Wilcox Pkwy",
    "sg:city":"Clare",
    "sg:classifiers":[
        {
            "category":"Personal",
            "subcategory":"Beauty Salon",
            "type":"Services"
        }
    ],
    "sg:phone":"+1 989 386 6151",
    "sg:postcode":"48617",
    "sg:province":"MI",
    "wof:name":"Mj Murphy's Of Clare",
    "wof:placetype":"venue"
},
  "geometry": {"coordinates":[-84.765265,43.829209],"type":"Point"}
}