{
  "type": "Feature",
  "properties": {
    "iso:country":"US",
    "sg:address":"2920 Ashmun St",
    "sg:city":"Sault Ste Marie",
    "sg:classifiers":[
        {
            "category":"Organizations",
            "subcategory":"Religious Organization",
            "type":"Services"
        }
    ],
    "sg:phone":"+1 906 632 6941",
    "sg:postcode":"49783",
    "sg:province":"MI",
    "sg:tags":[
        "church"
    ],
    "wof:name":"Living Word Church-Sault Ste",
    "wof:placetype":"venue"
},
  "geometry": {"coordinates":[-84.354032,46.467239],"type":"Point"}
}