{
  "type": "Feature",
  "properties": {
    "iso:country":"US",
    "sg:address":"208 S Main St",
    "sg:city":"Almont",
    "sg:classifiers":[
        {
            "category":"Food & Beverages",
            "subcategory":"Groceries & Convenience Stores",
            "type":"Retail Goods"
        }
    ],
    "sg:phone":"+1 810 798 8369",
    "sg:postcode":"48003",
    "sg:province":"MI",
    "wof:name":"Speedy Q Market",
    "wof:placetype":"venue"
},
  "geometry": {"coordinates":[-83.045124,42.919577],"type":"Point"}
}