{
  "type": "Feature",
  "properties": {
    "iso:country":"US",
    "sg:address":"590 Pinehurst Dr",
    "sg:city":"Canton",
    "sg:classifiers":[
        {
            "category":"Professional",
            "subcategory":"Computer Services",
            "type":"Services"
        }
    ],
    "sg:phone":"+1 734 981 9394",
    "sg:postcode":"48188",
    "sg:province":"MI",
    "sg:tags":[
        "related"
    ],
    "wof:name":"Intellisoft",
    "wof:placetype":"venue"
},
  "geometry": {"coordinates":[-83.489206,42.305012],"type":"Point"}
}