{
  "type": "Feature",
  "properties": {
    "iso:country":"US",
    "sg:address":"8464 W Stanley Rd",
    "sg:city":"Flushing",
    "sg:classifiers":[
        {
            "category":"Building & Trades",
            "subcategory":"Landscaping Services",
            "type":"Services"
        }
    ],
    "sg:phone":"+1 810 487 0514",
    "sg:postcode":"48433",
    "sg:province":"MI",
    "wof:name":"Gardner Lawn Care",
    "wof:placetype":"venue"
},
  "geometry": {"coordinates":[-83.84991599999999,43.103335],"type":"Point"}
}