{
  "type": "Feature",
  "properties": {
    "iso:country":"US",
    "sg:address":"812 Cypress St",
    "sg:city":"Manistee",
    "sg:classifiers":[
        {
            "category":"Health Services",
            "subcategory":"Doctor",
            "type":"Services"
        }
    ],
    "sg:phone":"+1 231 723 6512",
    "sg:postcode":"49660",
    "sg:province":"MI",
    "sg:tags":[
        "dentist"
    ],
    "wof:name":"High-Tech Dental",
    "wof:placetype":"venue"
},
  "geometry": {"coordinates":[-86.319208,44.238251],"type":"Point"}
}