{
  "type": "Feature",
  "properties": {
    "iso:country":"US",
    "sg:address":"43646 Normandy Ave",
    "sg:city":"Sterling Heights",
    "sg:classifiers":[
        {
            "category":"Building & Trades",
            "subcategory":"Plumbing",
            "type":"Services"
        }
    ],
    "sg:phone":"+1 586 709 8832",
    "sg:postcode":"48314",
    "sg:province":"MI",
    "sg:tags":[
        "plumbing",
        "contractor"
    ],
    "wof:name":"Bob's Excavating",
    "wof:placetype":"venue"
},
  "geometry": {"coordinates":[-83.040325,42.614091],"type":"Point"}
}