{
  "type": "Feature",
  "properties": {
    "iso:country":"US",
    "sg:address":"58533 Territorial Rd",
    "sg:city":"Lawrence",
    "sg:classifiers":[
        {
            "category":"Retail",
            "subcategory":"Portrait Studio",
            "type":"Services"
        }
    ],
    "sg:phone":"+1 269 674 8333",
    "sg:postcode":"49064",
    "sg:province":"MI",
    "sg:tags":[
        "photo"
    ],
    "wof:name":"Saule Uldis Photography",
    "wof:placetype":"venue"
},
  "geometry": {"coordinates":[-86.000426,42.206231],"type":"Point"}
}