{
  "type": "Feature",
  "properties": {
    "iso:country":"US",
    "sg:address":"1095 S Raucholz Rd",
    "sg:city":"Hemlock",
    "sg:classifiers":[
        {
            "category":"Building & Trades",
            "subcategory":"Landscaping Services",
            "type":"Services"
        }
    ],
    "sg:phone":"+1 989 642 2200",
    "sg:postcode":"48626",
    "sg:province":"MI",
    "sg:tags":[
        "landscape",
        "contractor"
    ],
    "wof:name":"Knoll Landscaping",
    "wof:placetype":"venue"
},
  "geometry": {"coordinates":[-84.209808,43.406912],"type":"Point"}
}