{
  "type": "Feature",
  "properties": {
    "iso:country":"US",
    "sg:address":"3160 Jaquay Rd",
    "sg:city":"Boyne City",
    "sg:classifiers":[
        {
            "category":"Shopping",
            "subcategory":"Hobbies, Toys, & Games",
            "type":"Retail Goods"
        }
    ],
    "sg:phone":"+1 231 536 9000",
    "sg:postcode":"49712",
    "sg:province":"MI",
    "sg:tags":[
        "craft",
        "supply"
    ],
    "wof:name":"Eternity Arts",
    "wof:placetype":"venue"
},
  "geometry": {"coordinates":[-85.03928399999999,45.160052],"type":"Point"}
}