{
  "type": "Feature",
  "properties": {
    "iso:country":"US",
    "sg:address":"14326 Edgewater Dr",
    "sg:city":"Gregory",
    "sg:classifiers":[
        {
            "category":"Farming",
            "subcategory":"Farm",
            "type":"Manufacturing & Wholesale Goods"
        }
    ],
    "sg:phone":"+1 734 475 7926",
    "sg:postcode":"48137",
    "sg:province":"MI",
    "wof:name":"Hi Me Farms",
    "wof:placetype":"venue"
},
  "geometry": {"coordinates":[-84.01387099999999,42.416479],"type":"Point"}
}