{
  "type": "Feature",
  "properties": {
    "iso:country":"US",
    "sg:address":"8294 Orchard Ave",
    "sg:city":"Warren",
    "sg:classifiers":[
        {
            "category":"Building & Trades",
            "subcategory":"Landscaping Services",
            "type":"Services"
        }
    ],
    "sg:phone":"+1 586 759 5246",
    "sg:postcode":"48089",
    "sg:province":"MI",
    "wof:name":"Thumpers Lawn Care",
    "wof:placetype":"venue"
},
  "geometry": {"coordinates":[-83.02140199999999,42.454934],"type":"Point"}
}