{
  "type": "Feature",
  "properties": {
    "iso:country":"US",
    "sg:address":"351 Gloria Ln",
    "sg:city":"Manistee",
    "sg:classifiers":[
        {
            "category":"Social Services",
            "type":"Services"
        }
    ],
    "sg:phone":"+1 231 723 4035",
    "sg:postcode":"49660",
    "sg:province":"MI",
    "sg:tags":[
        "youth",
        "organization",
        "center"
    ],
    "wof:name":"Crooked Tree Girl Scout C",
    "wof:placetype":"venue"
},
  "geometry": {"coordinates":[-86.309782,44.28582],"type":"Point"}
}