{
  "type": "Feature",
  "properties": {
    "iso:country":"US",
    "sg:address":"20556 Chapel St",
    "sg:city":"Detroit",
    "sg:classifiers":[
        {
            "category":"Retail",
            "subcategory":"Auto Repair",
            "type":"Services"
        }
    ],
    "sg:phone":"+1 313 538 2008",
    "sg:postcode":"48219",
    "sg:province":"MI",
    "sg:tags":[
        "automotive"
    ],
    "wof:name":"Hughes Towing",
    "wof:placetype":"venue"
},
  "geometry": {"coordinates":[-83.255065,42.441886],"type":"Point"}
}