{
  "type": "Feature",
  "properties": {
    "iso:country":"US",
    "sg:address":"8336 Mason Dr",
    "sg:city":"Newaygo",
    "sg:classifiers":[
        {
            "category":"Autos & Motor Vehicles",
            "subcategory":"Boat Sales",
            "type":"Retail Goods"
        }
    ],
    "sg:phone":"+1 231 652 6207",
    "sg:postcode":"49337",
    "sg:province":"MI",
    "sg:tags":[
        "dealer",
        "sales"
    ],
    "wof:name":"Newaygo Marine Inc",
    "wof:placetype":"venue"
},
  "geometry": {"coordinates":[-85.800805,43.402701],"type":"Point"}
}