{
  "type": "Feature",
  "properties": {
    "iso:country":"US",
    "sg:address":"3834 N Mill Rd",
    "sg:city":"Dryden",
    "sg:classifiers":[
        {
            "category":"Organizations",
            "subcategory":"Religious Organization",
            "type":"Services"
        }
    ],
    "sg:phone":"+1 810 796 4701",
    "sg:postcode":"48428",
    "sg:province":"MI",
    "sg:tags":[
        "church"
    ],
    "wof:name":"St Cornelius Religious Edu",
    "wof:placetype":"venue"
},
  "geometry": {"coordinates":[-83.125445,42.948711],"type":"Point"}
}