{
  "type": "Feature",
  "properties": {
    "iso:country":"US",
    "sg:address":"7315 Schaefer Rd",
    "sg:city":"Dearborn",
    "sg:classifiers":[
        {
            "category":"Restaurant",
            "type":"Food & Drink"
        }
    ],
    "sg:menulink":"http://www.allmenus.com/mi/dearborn/86741-little-caesars-pizza/menu/",
    "sg:phone":"+1 313 943 3380",
    "sg:postcode":"48126",
    "sg:province":"MI",
    "sg:tags":[
        "american",
        "pizza"
    ],
    "wof:name":"Little Caesars Pizza",
    "wof:placetype":"venue"
},
  "geometry": {"coordinates":[-83.177091,42.345081],"type":"Point"}
}