{
  "type": "Feature",
  "properties": {
    "iso:country":"US",
    "sg:address":"11715 Boyne City Rd",
    "sg:city":"Charlevoix",
    "sg:classifiers":[
        {
            "category":"Social Services",
            "subcategory":"Child Care",
            "type":"Services"
        }
    ],
    "sg:phone":"+1 231 547 4250",
    "sg:postcode":"49720",
    "sg:province":"MI",
    "sg:tags":[
        "day"
    ],
    "wof:name":"Sues T L C Child Care",
    "wof:placetype":"venue"
},
  "geometry": {"coordinates":[-85.212558,45.32931],"type":"Point"}
}