{
  "type": "Feature",
  "properties": {
    "iso:country":"US",
    "sg:address":"5944 Par View Dr",
    "sg:city":"Ypsilanti",
    "sg:classifiers":[
        {
            "category":"Organizations",
            "subcategory":"Labor Organization",
            "type":"Services"
        }
    ],
    "sg:phone":"+1 734 483 6575",
    "sg:postcode":"48197",
    "sg:province":"MI",
    "wof:name":"Melvindale Federation Teachers",
    "wof:placetype":"venue"
},
  "geometry": {"coordinates":[-83.631226,42.202314],"type":"Point"}
}