{
  "type": "Feature",
  "properties": {
    "iso:country":"US",
    "sg:address":"321 Straight Ave SW",
    "sg:city":"Grand Rapids",
    "sg:classifiers":[
        {
            "category":"Manufacturing",
            "subcategory":"Tools & Machinery",
            "type":"Manufacturing & Wholesale Goods"
        }
    ],
    "sg:phone":"+1 616 459 3205",
    "sg:postcode":"49504",
    "sg:province":"MI",
    "sg:tags":[
        "cutting"
    ],
    "sg:website":"www.stalteredge.com",
    "wof:name":"Stalter Edge Tool Inc",
    "wof:placetype":"venue"
},
  "geometry": {"coordinates":[-85.687422,42.95874],"type":"Point"}
}