{
  "type": "Feature",
  "properties": {
    "iso:country":"US",
    "sg:address":"4326 Lake Forest Dr W",
    "sg:city":"Ann Arbor",
    "sg:classifiers":[
        {
            "category":"Manufacturing",
            "subcategory":"Printing",
            "type":"Manufacturing & Wholesale Goods"
        }
    ],
    "sg:phone":"+1 734 327 9923",
    "sg:postcode":"48108",
    "sg:province":"MI",
    "sg:tags":[
        "publishing"
    ],
    "wof:name":"Kinch Publishing",
    "wof:placetype":"venue"
},
  "geometry": {"coordinates":[-83.77116100000001,42.222465],"type":"Point"}
}