{
  "type": "Feature",
  "properties": {
    "iso:country":"US",
    "sg:address":"21133 Bridge St",
    "sg:city":"Southfield",
    "sg:classifiers":[
        {
            "category":"Shopping",
            "subcategory":"Computers & Home Electronics",
            "type":"Retail Goods"
        }
    ],
    "sg:phone":"+1 248 356 4399",
    "sg:postcode":"48034",
    "sg:province":"MI",
    "sg:website":"www.bluewatertech.com",
    "wof:name":"Blue Water Technologies",
    "wof:placetype":"venue"
},
  "geometry": {"coordinates":[-83.284599,42.446201],"type":"Point"}
}