{
  "type": "Feature",
  "properties": {
    "iso:country":"US",
    "sg:address":"6225 Brackett Rd",
    "sg:city":"Williamsburg",
    "sg:classifiers":[
        {
            "category":"Building & Trades",
            "subcategory":"Cleaning & Sanitation",
            "type":"Services"
        }
    ],
    "sg:phone":"+1 231 267 9262",
    "sg:postcode":"49690",
    "sg:province":"MI",
    "sg:tags":[
        "maintenance"
    ],
    "wof:name":"K and K Maintenance and Cnstr",
    "wof:placetype":"venue"
},
  "geometry": {"coordinates":[-85.450869,44.78731],"type":"Point"}
}