{
  "type": "Feature",
  "properties": {
    "iso:country":"US",
    "sg:address":"2504 Lakeshore Rd",
    "sg:city":"Applegate",
    "sg:classifiers":[
        {
            "category":"Bars & Pubs",
            "type":"Food & Drink"
        }
    ],
    "sg:phone":"+1 810 622 8172",
    "sg:postcode":"48401",
    "sg:province":"MI",
    "wof:name":"Shady Shores Inn Inc",
    "wof:placetype":"venue"
},
  "geometry": {"coordinates":[-82.540306,43.357965],"type":"Point"}
}