{
  "type": "Feature",
  "properties": {
    "iso:country":"US",
    "sg:address":"3960 Elk Dr",
    "sg:city":"Rochester",
    "sg:classifiers":[
        {
            "category":"Building & Trades",
            "subcategory":"Construction",
            "type":"Services"
        }
    ],
    "sg:phone":"+1 248 652 2843",
    "sg:postcode":"48306",
    "sg:province":"MI",
    "sg:tags":[
        "hanging",
        "contractor"
    ],
    "wof:name":"Macolm Painting Inc",
    "wof:placetype":"venue"
},
  "geometry": {"coordinates":[-83.139652,42.741815],"type":"Point"}
}