{
  "type": "Feature",
  "properties": {
    "iso:country":"US",
    "sg:address":"4633 Patterson Ave SE",
    "sg:city":"Grand Rapids",
    "sg:classifiers":[
        {
            "category":"Professional",
            "subcategory":"Business Services",
            "type":"Services"
        },
        {
            "category":"Professional",
            "subcategory":"Advertising",
            "type":"Services"
        }
    ],
    "sg:phone":"+1 616 940 9955",
    "sg:postcode":"49512",
    "sg:province":"MI",
    "sg:tags":[
        "exhibit",
        "designer",
        "design",
        "display",
        "producer"
    ],
    "wof:name":"Exhibit Design Consultants",
    "wof:placetype":"venue"
},
  "geometry": {"coordinates":[-85.54689,42.877324],"type":"Point"}
}