{
  "type": "Feature",
  "properties": {
    "iso:country":"US",
    "sg:address":"2910 Eastern Ave SE",
    "sg:city":"Grand Rapids",
    "sg:classifiers":[
        {
            "category":"Restaurant",
            "type":"Food & Drink"
        }
    ],
    "sg:phone":"+1 616 245 4650",
    "sg:postcode":"49508",
    "sg:province":"MI",
    "sg:website":"www.hotnnow.com",
    "wof:name":"Hot 'n Now Hamburgers",
    "wof:placetype":"venue"
},
  "geometry": {"coordinates":[-85.646824,42.90931],"type":"Point"}
}