{
  "type": "Feature",
  "properties": {
    "iso:country":"US",
    "sg:address":"2076 Champaign Rd",
    "sg:city":"Lincoln Park",
    "sg:classifiers":[
        {
            "category":"Freight",
            "type":"Transportation"
        }
    ],
    "sg:phone":"+1 313 381 1152",
    "sg:postcode":"48146",
    "sg:province":"MI",
    "sg:tags":[
        "operator",
        "local",
        "trucking"
    ],
    "wof:name":"Dalton Delivery",
    "wof:placetype":"venue"
},
  "geometry": {"coordinates":[-83.200222,42.246435],"type":"Point"}
}