{
  "type": "Feature",
  "properties": {
    "iso:country":"US",
    "sg:address":"16630 Wyoming St",
    "sg:city":"Detroit",
    "sg:classifiers":[
        {
            "category":"Social Services",
            "type":"Services"
        }
    ],
    "sg:phone":"+1 313 862 3234",
    "sg:postcode":"48221",
    "sg:province":"MI",
    "wof:name":"Coalition On Tmpry Shelters",
    "wof:placetype":"venue"
},
  "geometry": {"coordinates":[-83.16007500000001,42.412716],"type":"Point"}
}