{
  "type": "Feature",
  "properties": {
    "iso:country":"US",
    "sg:address":"2735 Waldheim Dr",
    "sg:city":"Port Huron",
    "sg:classifiers":[
        {
            "category":"Professional",
            "subcategory":"Business Services",
            "type":"Services"
        }
    ],
    "sg:phone":"+1 810 987 8378",
    "sg:postcode":"48060",
    "sg:province":"MI",
    "wof:name":"1st Priority Home Inspections",
    "wof:placetype":"venue"
},
  "geometry": {"coordinates":[-82.460661,43.012173],"type":"Point"}
}