{
  "type": "Feature",
  "properties": {
    "iso:country":"US",
    "sg:address":"4016 W Main St",
    "sg:city":"Kalamazoo",
    "sg:classifiers":[
        {
            "category":"Health Services",
            "subcategory":"Doctor",
            "type":"Services"
        }
    ],
    "sg:phone":"+1 269 344 3366",
    "sg:postcode":"49006",
    "sg:province":"MI",
    "sg:tags":[
        "medical"
    ],
    "wof:name":"I Care Physicans and Surgeons",
    "wof:placetype":"venue"
},
  "geometry": {"coordinates":[-85.640192,42.296325],"type":"Point"}
}