{
  "type": "Feature",
  "properties": {
    "iso:country":"US",
    "sg:address":"456 E 16th St",
    "sg:city":"Holland",
    "sg:classifiers":[
        {
            "category":"Health Services",
            "subcategory":"Optometrist",
            "type":"Services"
        }
    ],
    "sg:phone":"+1 616 395 2020",
    "sg:postcode":"49423",
    "sg:province":"MI",
    "wof:name":"Family Eye Care of Holland",
    "wof:placetype":"venue"
},
  "geometry": {"coordinates":[-86.08855,42.783101],"type":"Point"}
}