{
  "type": "Feature",
  "properties": {
    "iso:country":"US",
    "sg:address":"11463 Bryce Rd",
    "sg:city":"Emmett",
    "sg:phone":"+1 586 779 1509",
    "sg:postcode":"48022",
    "sg:province":"MI",
    "sg:tags":[
        "farm",
        "soybean"
    ],
    "wof:name":"Jerome Schramm",
    "wof:placetype":"venue"
},
  "geometry": {"coordinates":[-82.78574999999999,43.014389],"type":"Point"}
}