{
  "type": "Feature",
  "properties": {
    "iso:country":"US",
    "sg:address":"429 13th St",
    "sg:city":"Port Huron",
    "sg:classifiers":[
        {
            "category":"Building & Trades",
            "subcategory":"Landscaping Services",
            "type":"Services"
        }
    ],
    "sg:phone":"+1 810 966 3850",
    "sg:postcode":"48060",
    "sg:province":"MI",
    "sg:tags":[
        "lawn",
        "maintenance",
        "grounds"
    ],
    "wof:name":"M & L Lawncare",
    "wof:placetype":"venue"
},
  "geometry": {"coordinates":[-82.43848,42.979313],"type":"Point"}
}