{
  "type": "Feature",
  "properties": {
    "iso:country":"US",
    "sg:address":"49357 Pontiac Trl",
    "sg:city":"Wixom",
    "sg:classifiers":[
        {
            "category":"Professional",
            "subcategory":"Engineering",
            "type":"Services"
        }
    ],
    "sg:phone":"+1 248 926 2000",
    "sg:postcode":"48393",
    "sg:province":"MI",
    "sg:tags":[
        "engineer"
    ],
    "sg:website":"www.sectorengineering.com",
    "wof:name":"Sector Engineering",
    "wof:placetype":"venue"
},
  "geometry": {"coordinates":[-83.53716900000001,42.524226],"type":"Point"}
}