{
  "type": "Feature",
  "properties": {
    "iso:country":"US",
    "sg:address":"1226 Main St",
    "sg:city":"Melvin",
    "sg:classifiers":[
        {
            "category":"Building & Trades",
            "subcategory":"Construction",
            "type":"Services"
        }
    ],
    "sg:phone":"+1 810 378 5970",
    "sg:postcode":"48454",
    "sg:province":"MI",
    "sg:tags":[
        "downspouts",
        "gutter"
    ],
    "wof:name":"Eastern Michigan Seamless Eave",
    "wof:placetype":"venue"
},
  "geometry": {"coordinates":[-82.862228,43.186574],"type":"Point"}
}