{
  "type": "Feature",
  "properties": {
    "iso:country":"US",
    "sg:address":"115 Albert Ave",
    "sg:city":"East Lansing",
    "sg:classifiers":[
        {
            "category":"Restaurant",
            "type":"Food & Drink"
        }
    ],
    "sg:menulink":"http://www.allmenus.com/mi/east-lansing/248907-mennas-joint/menu/",
    "sg:phone":"+1 517 351 3827",
    "sg:postcode":"48823",
    "sg:province":"MI",
    "sg:tags":[
        "wrap",
        "american"
    ],
    "wof:name":"Menna's Joint",
    "wof:placetype":"venue"
},
  "geometry": {"coordinates":[-84.48370799999999,42.736027],"type":"Point"}
}