{
  "type": "Feature",
  "properties": {
    "iso:country":"US",
    "sg:address":"4651 Platt Rd",
    "sg:city":"Ann Arbor",
    "sg:classifiers":[
        {
            "category":"Professional",
            "subcategory":"Research",
            "type":"Services"
        }
    ],
    "sg:phone":"+1 734 477 9344",
    "sg:postcode":"48108",
    "sg:province":"MI",
    "sg:tags":[
        "develop",
        "plastic"
    ],
    "wof:name":"Mgv Enterprises",
    "wof:placetype":"venue"
},
  "geometry": {"coordinates":[-83.699569,42.22232],"type":"Point"}
}