{
  "type": "Feature",
  "properties": {
    "iso:country":"US",
    "sg:address":"29758 Southfield Rd",
    "sg:city":"Southfield",
    "sg:classifiers":[
        {
            "category":"Food & Beverages",
            "subcategory":"Groceries & Convenience Stores",
            "type":"Retail Goods"
        }
    ],
    "sg:phone":"+1 248 424 9838",
    "sg:postcode":"48076",
    "sg:province":"MI",
    "wof:name":"Oriental Imports Ls",
    "wof:placetype":"venue"
},
  "geometry": {"coordinates":[-83.22267600000001,42.508341],"type":"Point"}
}