{
  "type": "Feature",
  "properties": {
    "iso:country":"US",
    "sg:address":"18073 Mendota St",
    "sg:city":"Detroit",
    "sg:classifiers":[
        {
            "category":"Social Services",
            "subcategory":"Adult Care",
            "type":"Services"
        }
    ],
    "sg:phone":"+1 313 864 6913",
    "sg:postcode":"48221",
    "sg:province":"MI",
    "sg:tags":[
        "foster",
        "provider"
    ],
    "wof:name":"Irene Middlebrooks",
    "wof:placetype":"venue"
},
  "geometry": {"coordinates":[-83.166197,42.423411],"type":"Point"}
}