{
  "type": "Feature",
  "properties": {
    "iso:country":"US",
    "sg:address":"2712 N Saginaw St",
    "sg:city":"Flint",
    "sg:classifiers":[
        {
            "category":"Manufacturing",
            "subcategory":"Apparel",
            "type":"Manufacturing & Wholesale Goods"
        }
    ],
    "sg:phone":"+1 810 767 9113",
    "sg:postcode":"48505",
    "sg:province":"MI",
    "sg:tags":[
        "sewing",
        "contractor"
    ],
    "wof:name":"Jermerson Sewing Co",
    "wof:placetype":"venue"
},
  "geometry": {"coordinates":[-83.69386,43.041584],"type":"Point"}
}