{
  "type": "Feature",
  "properties": {
    "iso:country":"US",
    "sg:address":"2890 S Rochester Rd",
    "sg:city":"Rochester Hills",
    "sg:classifiers":[
        {
            "category":"Autos & Motor Vehicles",
            "subcategory":"Automobile Sales",
            "type":"Retail Goods"
        }
    ],
    "sg:phone":"+1 248 852 0400",
    "sg:postcode":"48307",
    "sg:province":"MI",
    "sg:tags":[
        "car",
        "dealer"
    ],
    "sg:website":"www.huntingtonford.com",
    "wof:name":"Huntington Ford Inc",
    "wof:placetype":"venue"
},
  "geometry": {"coordinates":[-83.13200999999999,42.640153],"type":"Point"}
}