{
  "type": "Feature",
  "properties": {
    "iso:country":"US",
    "sg:address":"118 W Ottawa St",
    "sg:city":"Lansing",
    "sg:classifiers":[
        {
            "category":"Professional",
            "subcategory":"Management & Consulting",
            "type":"Services"
        }
    ],
    "sg:phone":"+1 517 485 8301",
    "sg:postcode":"48933",
    "sg:province":"MI",
    "sg:tags":[
        "consultant",
        "government"
    ],
    "wof:name":"Pfizer",
    "wof:placetype":"venue"
},
  "geometry": {"coordinates":[-84.553656,42.734751],"type":"Point"}
}