{
  "type": "Feature",
  "properties": {
    "iso:country":"US",
    "sg:address":"17655 Ryan Rd",
    "sg:city":"Detroit",
    "sg:classifiers":[
        {
            "category":"Freight",
            "type":"Transportation"
        }
    ],
    "sg:phone":"+1 313 892 9040",
    "sg:postcode":"48212",
    "sg:province":"MI",
    "sg:tags":[
        "warehouse"
    ],
    "wof:name":"Winston Bros Iron & Metal Co",
    "wof:placetype":"venue"
},
  "geometry": {"coordinates":[-83.062702,42.422739],"type":"Point"}
}