{
  "type": "Feature",
  "properties": {
    "iso:country":"US",
    "sg:address":"2271 Star Ct",
    "sg:city":"Rochester Hills",
    "sg:classifiers":[
        {
            "category":"Shopping",
            "subcategory":"Bicycles & Sporting Goods",
            "type":"Retail Goods"
        }
    ],
    "sg:phone":"+1 248 852 6490",
    "sg:postcode":"48309",
    "sg:province":"MI",
    "sg:tags":[
        "gun",
        "gunsmith"
    ],
    "wof:name":"Acc-U-Rail",
    "wof:placetype":"venue"
},
  "geometry": {"coordinates":[-83.176216,42.646018],"type":"Point"}
}