{
  "type": "Feature",
  "properties": {
    "iso:country":"US",
    "sg:address":"605 S Paw Paw St",
    "sg:city":"Lawrence",
    "sg:classifiers":[
        {
            "category":"Real Estate",
            "subcategory":"Real Estate Operator",
            "type":"Services"
        }
    ],
    "sg:phone":"+1 269 674 4157",
    "sg:postcode":"49064",
    "sg:province":"MI",
    "sg:tags":[
        "apartment"
    ],
    "wof:name":"Lawerance Down Apartments",
    "wof:placetype":"venue"
},
  "geometry": {"coordinates":[-86.051151,42.214501],"type":"Point"}
}