{
  "type": "Feature",
  "properties": {
    "iso:country":"US",
    "sg:address":"2032 Lagoon Dr",
    "sg:city":"Okemos",
    "sg:classifiers":[
        {
            "category":"Wholesale",
            "subcategory":"Medical Equipment & Supplies",
            "type":"Manufacturing & Wholesale Goods"
        }
    ],
    "sg:phone":"+1 517 349 9131",
    "sg:postcode":"48864",
    "sg:province":"MI",
    "wof:name":"Garrette & Assocs Ltd",
    "wof:placetype":"venue"
},
  "geometry": {"coordinates":[-84.42144,42.713191],"type":"Point"}
}