{
  "type": "Feature",
  "properties": {
    "iso:country":"US",
    "sg:address":"44852 Heydenreich Rd",
    "sg:city":"Clinton Township",
    "sg:classifiers":[
        {
            "category":"Building & Trades",
            "subcategory":"Plumbing",
            "type":"Services"
        }
    ],
    "sg:phone":"+1 248 642 1662",
    "sg:postcode":"48038",
    "sg:province":"MI",
    "wof:name":"Mr Rooter",
    "wof:placetype":"venue"
},
  "geometry": {"coordinates":[-82.916702,42.6273],"type":"Point"}
}