{
  "type": "Feature",
  "properties": {
    "iso:country":"US",
    "sg:address":"6154 Westview Dr",
    "sg:city":"Grand Blanc",
    "sg:classifiers":[
        {
            "category":"Professional",
            "subcategory":"Business Services",
            "type":"Services"
        }
    ],
    "sg:phone":"+1 810 694 1748",
    "sg:postcode":"48439",
    "sg:province":"MI",
    "wof:name":"Monogram Associates Inc",
    "wof:placetype":"venue"
},
  "geometry": {"coordinates":[-83.57931499999999,42.934683],"type":"Point"}
}