{
  "type": "Feature",
  "properties": {
    "iso:country":"US",
    "sg:address":"30168 Puritan St",
    "sg:city":"Livonia",
    "sg:classifiers":[
        {
            "category":"Building & Trades",
            "subcategory":"Plumbing",
            "type":"Services"
        }
    ],
    "sg:phone":"+1 734 762 3262",
    "sg:postcode":"48154",
    "sg:province":"MI",
    "wof:name":"A N J Plumbing Services",
    "wof:placetype":"venue"
},
  "geometry": {"coordinates":[-83.34293099999999,42.405317],"type":"Point"}
}