{
  "type": "Feature",
  "properties": {
    "iso:country":"US",
    "sg:address":"424 W Wackerly St",
    "sg:city":"Midland",
    "sg:classifiers":[
        {
            "category":"Health Services",
            "subcategory":"Health Practitioner",
            "type":"Services"
        }
    ],
    "sg:phone":"+1 989 631 4100",
    "sg:postcode":"48640",
    "sg:province":"MI",
    "sg:tags":[
        "therapy",
        "physical"
    ],
    "wof:name":"Midland Sport & Spine",
    "wof:placetype":"venue"
},
  "geometry": {"coordinates":[-84.226911,43.654786],"type":"Point"}
}