{
  "type": "Feature",
  "properties": {
    "iso:country":"US",
    "sg:address":"6975 N Waverly St",
    "sg:city":"Dearborn Heights",
    "sg:classifiers":[
        {
            "category":"Retail",
            "subcategory":"Auto Repair",
            "type":"Services"
        }
    ],
    "sg:phone":"+1 313 565 8816",
    "sg:postcode":"48127",
    "sg:province":"MI",
    "sg:tags":[
        "general"
    ],
    "wof:name":"Antonios R V Repairs",
    "wof:placetype":"venue"
},
  "geometry": {"coordinates":[-83.271862,42.339043],"type":"Point"}
}