{
  "type": "Feature",
  "properties": {
    "iso:country":"US",
    "sg:address":"437 Jeffrey Ave",
    "sg:city":"Royal Oak",
    "sg:classifiers":[
        {
            "category":"Health Services",
            "subcategory":"Doctor",
            "type":"Services"
        }
    ],
    "sg:phone":"+1 248 435 5326",
    "sg:postcode":"48073",
    "sg:province":"MI",
    "sg:tags":[
        "surgeon",
        "oral"
    ],
    "wof:name":"Smith Matthew J DDS",
    "wof:placetype":"venue"
},
  "geometry": {"coordinates":[-83.15070299999999,42.5252],"type":"Point"}
}