{
  "type": "Feature",
  "properties": {
    "iso:country":"US",
    "sg:address":"214 Spencer St NE",
    "sg:city":"Grand Rapids",
    "sg:classifiers":[
        {
            "category":"Organizations",
            "subcategory":"Religious Organization",
            "type":"Services"
        }
    ],
    "sg:phone":"+1 616 454 7625",
    "sg:postcode":"49505",
    "sg:province":"MI",
    "wof:name":"Plainfield United Methodist",
    "wof:placetype":"venue"
},
  "geometry": {"coordinates":[-85.66499399999999,42.988216],"type":"Point"}
}