{
  "type": "Feature",
  "properties": {
    "iso:country":"US",
    "sg:address":"1915 Pauline Blvd",
    "sg:city":"Ann Arbor",
    "sg:classifiers":[
        {
            "category":"Professional",
            "subcategory":"Business Services",
            "type":"Services"
        }
    ],
    "sg:phone":"+1 734 995 2259",
    "sg:postcode":"48103",
    "sg:province":"MI",
    "wof:name":"Spa Limited Partnership I",
    "wof:placetype":"venue"
},
  "geometry": {"coordinates":[-83.77129499999999,42.267931],"type":"Point"}
}