{
  "type": "Feature",
  "properties": {
    "iso:country":"US",
    "sg:address":"650 E 24th St",
    "sg:city":"Holland",
    "sg:classifiers":[
        {
            "category":"Retail",
            "subcategory":"Auto Rental",
            "type":"Services"
        }
    ],
    "sg:phone":"+1 616 395 0503",
    "sg:postcode":"49423",
    "sg:province":"MI",
    "sg:tags":[
        "passenger",
        "car"
    ],
    "wof:name":"Avis Rent A Car Systems Inc",
    "wof:placetype":"venue"
},
  "geometry": {"coordinates":[-86.07865,42.775859],"type":"Point"}
}