{
  "type": "Feature",
  "properties": {
    "iso:country":"US",
    "sg:address":"39500 Orchard Hill Pl",
    "sg:city":"Novi",
    "sg:classifiers":[
        {
            "category":"Building & Trades",
            "subcategory":"Construction",
            "type":"Services"
        }
    ],
    "sg:phone":"+1 248 348 2510",
    "sg:postcode":"48375",
    "sg:province":"MI",
    "sg:tags":[
        "management"
    ],
    "wof:name":"OBrien & Gere Technical Svcs",
    "wof:placetype":"venue"
},
  "geometry": {"coordinates":[-83.438835,42.438765],"type":"Point"}
}