{
  "type": "Feature",
  "properties": {
    "iso:country":"US",
    "sg:address":"321 E Lake St",
    "sg:city":"Petoskey",
    "sg:classifiers":[
        {
            "category":"Professional",
            "subcategory":"Lawyer & Legal Services",
            "type":"Services"
        }
    ],
    "sg:phone":"+1 231 348 4500",
    "sg:postcode":"49770",
    "sg:province":"MI",
    "sg:tags":[
        "attorney"
    ],
    "wof:name":"John Turner",
    "wof:placetype":"venue"
},
  "geometry": {"coordinates":[-84.95698899999999,45.375029],"type":"Point"}
}