{
  "type": "Feature",
  "properties": {
    "iso:country":"US",
    "sg:address":"3380 Jefferson Ave SE",
    "sg:city":"Grand Rapids",
    "sg:classifiers":[
        {
            "category":"Professional",
            "subcategory":"Management & Consulting",
            "type":"Services"
        }
    ],
    "sg:phone":"+1 616 241 3122",
    "sg:postcode":"49548",
    "sg:province":"MI",
    "sg:tags":[
        "training",
        "resource",
        "human"
    ],
    "sg:website":"www.qsiteam.com",
    "wof:name":"Quantum Services Inc",
    "wof:placetype":"venue"
},
  "geometry": {"coordinates":[-85.661288,42.902731],"type":"Point"}
}