{
  "type": "Feature",
  "properties": {
    "iso:country":"US",
    "sg:address":"36345 Groesbeck Hwy",
    "sg:city":"Clinton Twp",
    "sg:classifiers":[
        {
            "category":"Wholesale",
            "subcategory":"Hardware",
            "type":"Manufacturing & Wholesale Goods"
        }
    ],
    "sg:phone":"+1 586 791 2930",
    "sg:postcode":"48035",
    "sg:province":"MI",
    "sg:tags":[
        "furnace"
    ],
    "wof:name":"Air Solutions",
    "wof:placetype":"venue"
},
  "geometry": {"coordinates":[-82.914877,42.565733],"type":"Point"}
}