{
  "type": "Feature",
  "properties": {
    "iso:country":"US",
    "sg:address":"20225 E 9 Mile Rd",
    "sg:city":"St Clair Shores",
    "sg:classifiers":[
        {
            "category":"Professional",
            "subcategory":"Management & Consulting",
            "type":"Services"
        },
        {
            "category":"Health Services",
            "subcategory":"Clinic",
            "type":"Services"
        }
    ],
    "sg:phone":"+1 586 772 1090",
    "sg:postcode":"48080",
    "sg:province":"MI",
    "sg:tags":[
        "consultant",
        "business"
    ],
    "wof:name":"Cornerstone Health Service",
    "wof:placetype":"venue"
},
  "geometry": {"coordinates":[-82.913822,42.465948],"type":"Point"}
}