{
  "type": "Feature",
  "properties": {
    "iso:country":"US",
    "sg:address":"7471 Woodcliff Dr",
    "sg:city":"Hudsonville",
    "sg:classifiers":[
        {
            "category":"Organizations",
            "subcategory":"Religious Organization",
            "type":"Services"
        }
    ],
    "sg:phone":"+1 616 669 9151",
    "sg:postcode":"49426",
    "sg:province":"MI",
    "wof:name":"Cedar Presbyterian Church",
    "wof:placetype":"venue"
},
  "geometry": {"coordinates":[-85.89348099999999,42.906276],"type":"Point"}
}