{
  "type": "Feature",
  "properties": {
    "iso:country":"US",
    "sg:address":"233 Lothrop Rd",
    "sg:city":"Grosse Pointe",
    "sg:classifiers":[
        {
            "category":"Professional",
            "subcategory":"Lawyer & Legal Services",
            "type":"Services"
        }
    ],
    "sg:phone":"+1 313 882 3965",
    "sg:postcode":"48236",
    "sg:province":"MI",
    "wof:name":"Elizabeth Deluca",
    "wof:placetype":"venue"
},
  "geometry": {"coordinates":[-82.900853,42.402706],"type":"Point"}
}