{
  "type": "Feature",
  "properties": {
    "iso:country":"US",
    "sg:address":"14804 Beech Daly Rd",
    "sg:city":"Redford",
    "sg:classifiers":[
        {
            "category":"Professional",
            "subcategory":"Business Services",
            "type":"Services"
        }
    ],
    "sg:phone":"+1 313 534 2412",
    "sg:postcode":"48239",
    "sg:province":"MI",
    "wof:name":"Martha Bauer Interiors",
    "wof:placetype":"venue"
},
  "geometry": {"coordinates":[-83.29565700000001,42.395954],"type":"Point"}
}