{
  "type": "Feature",
  "properties": {
    "iso:country":"US",
    "sg:address":"616 Call St",
    "sg:city":"Boyne City",
    "sg:classifiers":[
        {
            "category":"Building & Trades",
            "subcategory":"Construction",
            "type":"Services"
        }
    ],
    "sg:phone":"+1 231 582 6916",
    "sg:postcode":"49712",
    "sg:province":"MI",
    "sg:tags":[
        "house",
        "contractor"
    ],
    "wof:name":"Welch Construction",
    "wof:placetype":"venue"
},
  "geometry": {"coordinates":[-84.998205,45.220173],"type":"Point"}
}