{
  "type": "Feature",
  "properties": {
    "iso:country":"US",
    "sg:address":"30911 Woodward Ave",
    "sg:city":"Royal Oak",
    "sg:classifiers":[
        {
            "category":"Government",
            "subcategory":"City Hall",
            "type":"Public Place"
        }
    ],
    "sg:phone":"+1 888 767 6424",
    "sg:postcode":"48073",
    "sg:province":"MI",
    "sg:website":"www.michigan.gov/sos/",
    "wof:name":"Secretary of State - Royal Oak Branch Office",
    "wof:placetype":"venue"
},
  "geometry": {"coordinates":[-83.185586,42.516997],"type":"Point"}
}