{
  "type": "Feature",
  "properties": {
    "iso:country":"US",
    "sg:address":"5481 W Main St",
    "sg:city":"Kalamazoo",
    "sg:classifiers":[
        {
            "category":"Fast Food",
            "type":"Food & Drink"
        },
        {
            "category":"Restaurant",
            "type":"Food & Drink"
        }
    ],
    "sg:phone":"+1 269 345 2550",
    "sg:postcode":"49009",
    "sg:province":"MI",
    "sg:tags":[
        "seafood"
    ],
    "sg:website":"http://www.ljsilvers.com",
    "wof:name":"Long John Silver's",
    "wof:placetype":"venue"
},
  "geometry": {"coordinates":[-85.657516,42.296107],"type":"Point"}
}