{
  "type": "Feature",
  "properties": {
    "iso:country":"US",
    "sg:address":"620 Beck St",
    "sg:city":"Jonesville",
    "sg:classifiers":[
        {
            "category":"Restaurant",
            "type":"Food & Drink"
        }
    ],
    "sg:phone":"+1 517 849 2890",
    "sg:postcode":"49250",
    "sg:province":"MI",
    "sg:tags":[
        "pizza"
    ],
    "wof:name":"Johnson's Pizza & Subs",
    "wof:placetype":"venue"
},
  "geometry": {"coordinates":[-84.665502,41.967903],"type":"Point"}
}