{
  "type": "Feature",
  "properties": {
    "iso:country":"US",
    "sg:address":"812 Ship St",
    "sg:city":"St Joseph",
    "sg:classifiers":[
        {
            "category":"Health Services",
            "subcategory":"Chiropractor",
            "type":"Services"
        }
    ],
    "sg:phone":"+1 269 983 1160",
    "sg:postcode":"49085",
    "sg:province":"MI",
    "wof:name":"Paula M Pfahler DC",
    "wof:placetype":"venue"
},
  "geometry": {"coordinates":[-86.47787700000001,42.10874],"type":"Point"}
}