{
  "type": "Feature",
  "properties": {
    "iso:country":"US",
    "sg:address":"2800 W Big Beaver",
    "sg:city":"Troy",
    "sg:classifiers":[
        {
            "category":"Shopping",
            "subcategory":"Hobbies, Toys, & Games",
            "type":"Retail Goods"
        }
    ],
    "sg:phone":"+1 248 816 3350",
    "sg:postcode":"48084",
    "sg:province":"MI",
    "sg:tags":[
        "toy",
        "store"
    ],
    "sg:website":"www.lego.com",
    "wof:name":"Lego Store",
    "wof:placetype":"venue"
},
  "geometry": {"coordinates":[-83.184039,42.562721],"type":"Point"}
}