{
  "type": "Feature",
  "properties": {
    "iso:country":"US",
    "sg:address":"111 W Kingsley",
    "sg:city":"Ann Arbor",
    "sg:classifiers":[
        {
            "category":"Professional",
            "subcategory":"Advertising",
            "type":"Services"
        }
    ],
    "sg:phone":"+1 646 467 8200",
    "sg:postcode":"48103",
    "sg:province":"MI",
    "sg:tags":[
        "ecommerce-advertising",
        "ecommerce-media",
        "incentives",
        "promotions",
        "media",
        "advertising"
    ],
    "sg:website":"http://www.hooklogic.com",
    "wof:name":"HookLogic",
    "wof:placetype":"venue"
},
  "geometry": {"coordinates":[-83.74952999999999,42.284953],"type":"Point"}
}