{
  "type": "Feature",
  "properties": {
    "iso:country":"US",
    "sg:address":"354 N Lapeer Rd",
    "sg:city":"Oxford",
    "sg:classifiers":[
        {
            "category":"Professional",
            "type":"Services"
        }
    ],
    "sg:phone":"+1 248 969 1143",
    "sg:postcode":"48371",
    "sg:province":"MI",
    "wof:name":"Trejo Communications",
    "wof:placetype":"venue"
},
  "geometry": {"coordinates":[-83.269215,42.830581],"type":"Point"}
}