{
  "type": "Feature",
  "properties": {
    "iso:country":"US",
    "sg:address":"30852 W 10 Mile Rd",
    "sg:city":"Farmington Hills",
    "sg:classifiers":[
        {
            "category":"Health Services",
            "subcategory":"Doctor",
            "type":"Services"
        }
    ],
    "sg:phone":"+1 248 426 9291",
    "sg:postcode":"48336",
    "sg:province":"MI",
    "sg:tags":[
        "physician",
        "surgeon"
    ],
    "wof:name":"SDI Future Health",
    "wof:placetype":"venue"
},
  "geometry": {"coordinates":[-83.350775,42.470413],"type":"Point"}
}