{
  "type": "Feature",
  "properties": {
    "iso:country":"US",
    "sg:address":"792 Harcourt Rd",
    "sg:city":"Grosse Pointe",
    "sg:classifiers":[
        {
            "category":"Building & Trades",
            "subcategory":"Construction",
            "type":"Services"
        }
    ],
    "sg:phone":"+1 313 824 6300",
    "sg:postcode":"48230",
    "sg:province":"MI",
    "sg:tags":[
        "interior",
        "design"
    ],
    "wof:name":"Urso Designs Inc",
    "wof:placetype":"venue"
},
  "geometry": {"coordinates":[-82.92440000000001,42.374802],"type":"Point"}
}