{
  "type": "Feature",
  "properties": {
    "iso:country":"US",
    "sg:address":"40760 Garfield Rd",
    "sg:city":"Clinton Twp",
    "sg:classifiers":[
        {
            "category":"Professional",
            "subcategory":"Business Services",
            "type":"Services"
        }
    ],
    "sg:phone":"+1 586 412 1333",
    "sg:postcode":"48038",
    "sg:province":"MI",
    "sg:tags":[
        "box",
        "mail"
    ],
    "wof:name":"Packaging Store",
    "wof:placetype":"venue"
},
  "geometry": {"coordinates":[-82.95234499999999,42.597917],"type":"Point"}
}