{
  "type": "Feature",
  "properties": {
    "iso:country":"US",
    "sg:address":"2477 US Hwy 23 N",
    "sg:city":"Alpena",
    "sg:classifiers":[
        {
            "category":"Retail",
            "subcategory":"Auto Repair",
            "type":"Services"
        }
    ],
    "sg:phone":"+1 989 356 9302",
    "sg:postcode":"49707",
    "sg:province":"MI",
    "wof:name":"Huron Diesel Service",
    "wof:placetype":"venue"
},
  "geometry": {"coordinates":[-83.456525,45.094812],"type":"Point"}
}