{
  "type": "Feature",
  "properties": {
    "iso:country":"US",
    "sg:address":"5315 Isabella St",
    "sg:city":"Midland",
    "sg:classifiers":[
        {
            "category":"Organizations",
            "subcategory":"Religious Organization",
            "type":"Services"
        }
    ],
    "sg:phone":"+1 989 631 0820",
    "sg:postcode":"48640",
    "sg:province":"MI",
    "sg:tags":[
        "church"
    ],
    "wof:name":"Nease Memorial Church-Nazarene",
    "wof:placetype":"venue"
},
  "geometry": {"coordinates":[-84.313294,43.612143],"type":"Point"}
}