{
  "type": "Feature",
  "properties": {
    "iso:country":"US",
    "sg:address":"468 Cadieux Rd",
    "sg:city":"Grosse Pointe",
    "sg:classifiers":[
        {
            "category":"Health Services",
            "subcategory":"Doctor",
            "type":"Services"
        }
    ],
    "sg:phone":"+1 313 343 1630",
    "sg:postcode":"48230",
    "sg:province":"MI",
    "sg:tags":[
        "medical"
    ],
    "wof:name":"Bryer David MD",
    "wof:placetype":"venue"
},
  "geometry": {"coordinates":[-82.915389,42.384167],"type":"Point"}
}