{
  "type": "Feature",
  "properties": {
    "iso:country":"US",
    "sg:address":"8951 Park St",
    "sg:city":"Richland",
    "sg:classifiers":[
        {
            "category":"Education",
            "subcategory":"Library",
            "type":"Public Place"
        }
    ],
    "sg:phone":"+1 269 629 9085",
    "sg:postcode":"49083",
    "sg:province":"MI",
    "sg:website":"www.richlandlibrary.org",
    "wof:name":"Richland Community Library",
    "wof:placetype":"venue"
},
  "geometry": {"coordinates":[-85.455544,42.376983],"type":"Point"}
}