{
  "type": "Feature",
  "properties": {
    "iso:country":"US",
    "sg:address":"46090 Michigan Ave",
    "sg:city":"Canton",
    "sg:classifiers":[
        {
            "category":"Shopping",
            "subcategory":"Party Supplies",
            "type":"Retail Goods"
        }
    ],
    "sg:phone":"+1 734 495 1222",
    "sg:postcode":"48188",
    "sg:province":"MI",
    "wof:name":"Pump It Up",
    "wof:placetype":"venue"
},
  "geometry": {"coordinates":[-83.49157099999999,42.270991],"type":"Point"}
}