{
  "type": "Feature",
  "properties": {
    "iso:country":"US",
    "sg:address":"15705 Parkside St",
    "sg:city":"Detroit",
    "sg:classifiers":[
        {
            "category":"Organizations",
            "subcategory":"Religious Organization",
            "type":"Services"
        }
    ],
    "sg:phone":"+1 313 861 2070",
    "sg:postcode":"48238",
    "sg:province":"MI",
    "wof:name":"North W Chrch of God of Dtroit",
    "wof:placetype":"venue"
},
  "geometry": {"coordinates":[-83.131743,42.409764],"type":"Point"}
}