{
  "type": "Feature",
  "properties": {
    "iso:country":"US",
    "sg:address":"333 E 5th St",
    "sg:city":"Mio",
    "sg:classifiers":[
        {
            "category":"Professional",
            "subcategory":"Research",
            "type":"Services"
        }
    ],
    "sg:phone":"+1 989 826 3887",
    "sg:postcode":"48647",
    "sg:province":"MI",
    "sg:tags":[
        "environmental",
        "ecological"
    ],
    "wof:name":"Earth Tech Inc",
    "wof:placetype":"venue"
},
  "geometry": {"coordinates":[-84.125759,44.655127],"type":"Point"}
}