{
  "type": "Feature",
  "properties": {
    "iso:country":"US",
    "sg:address":"527 N Grand Traverse St",
    "sg:city":"Flint",
    "sg:classifiers":[
        {
            "category":"Food & Beverages",
            "subcategory":"Groceries & Convenience Stores",
            "type":"Retail Goods"
        }
    ],
    "sg:phone":"+1 810 239 4092",
    "sg:postcode":"48503",
    "sg:province":"MI",
    "sg:website":"www.sunocoinc.com",
    "wof:name":"Sunoco Gas & Go",
    "wof:placetype":"venue"
},
  "geometry": {"coordinates":[-83.69928299999999,43.018281],"type":"Point"}
}