{
  "type": "Feature",
  "properties": {
    "iso:country":"US",
    "sg:address":"5224 Howe St",
    "sg:city":"Utica",
    "sg:classifiers":[
        {
            "category":"Building & Trades",
            "subcategory":"Construction",
            "type":"Services"
        }
    ],
    "sg:phone":"+1 586 739 2192",
    "sg:postcode":"48317",
    "sg:province":"MI",
    "sg:tags":[
        "house"
    ],
    "wof:name":"D Carlson Builder",
    "wof:placetype":"venue"
},
  "geometry": {"coordinates":[-83.057008,42.642059],"type":"Point"}
}