{
  "type": "Feature",
  "properties": {
    "iso:country":"US",
    "sg:address":"4151 Okemos Rd",
    "sg:city":"Okemos",
    "sg:classifiers":[
        {
            "category":"Insurance",
            "subcategory":"Insurance Agent",
            "type":"Services"
        }
    ],
    "sg:phone":"+1 517 349 4230",
    "sg:postcode":"48864",
    "sg:province":"MI",
    "wof:name":"Hrh Insurance",
    "wof:placetype":"venue"
},
  "geometry": {"coordinates":[-84.43245400000001,42.697904],"type":"Point"}
}