{
  "type": "Feature",
  "properties": {
    "iso:country":"US",
    "sg:address":"17816 Woodward Ave",
    "sg:city":"Highland Park",
    "sg:classifiers":[
        {
            "category":"Organizations",
            "subcategory":"Religious Organization",
            "type":"Services"
        }
    ],
    "sg:phone":"+1 313 869 5150",
    "sg:postcode":"48203",
    "sg:province":"MI",
    "wof:name":"Metropolitan A M E Zion Church",
    "wof:placetype":"venue"
},
  "geometry": {"coordinates":[-83.1082,42.422401],"type":"Point"}
}