{
  "type": "Feature",
  "properties": {
    "iso:country":"US",
    "sg:address":"31555 W 14 Mile Rd Ste 300",
    "sg:city":"Farmington Hills",
    "sg:classifiers":[
        {
            "category":"Banks & Credit Unions",
            "subcategory":"Investment Brokerage",
            "type":"Services"
        },
        {
            "category":"Banks & Credit Unions",
            "subcategory":"Financial Services",
            "type":"Services"
        }
    ],
    "sg:phone":"+1 248 626 1600",
    "sg:postcode":"48334",
    "sg:province":"MI",
    "sg:tags":[
        "investing",
        "advising"
    ],
    "sg:website":"www.ameripriseadvisors.com",
    "wof:name":"Eric Furlotte - Ameriprise Financial Advisor",
    "wof:placetype":"venue"
},
  "geometry": {"coordinates":[-83.361909,42.528349],"type":"Point"}
}