{
  "type": "Feature",
  "properties": {
    "iso:country":"US",
    "sg:address":"2950 Edgestone Dr",
    "sg:city":"Hudsonville",
    "sg:classifiers":[
        {
            "category":"Professional",
            "subcategory":"Employment Agencies",
            "type":"Services"
        }
    ],
    "sg:phone":"+1 231 357 0629",
    "sg:postcode":"49426",
    "sg:province":"MI",
    "wof:name":"Linchpin Quality Solutions",
    "wof:placetype":"venue"
},
  "geometry": {"coordinates":[-85.855785,42.886509],"type":"Point"}
}