{
  "type": "Feature",
  "properties": {
    "iso:country":"US",
    "sg:address":"9398 Stony Creek Rd",
    "sg:city":"Ypsilanti",
    "sg:classifiers":[
        {
            "category":"Social Services",
            "subcategory":"Child Care",
            "type":"Services"
        }
    ],
    "sg:phone":"+1 734 481 8089",
    "sg:postcode":"48197",
    "sg:province":"MI",
    "sg:tags":[
        "day"
    ],
    "wof:name":"Betty Short",
    "wof:placetype":"venue"
},
  "geometry": {"coordinates":[-83.653187,42.153394],"type":"Point"}
}