{
  "type": "Feature",
  "properties": {
    "iso:country":"US",
    "sg:address":"12250 Delta St",
    "sg:city":"Taylor",
    "sg:classifiers":[
        {
            "category":"Food & Beverages",
            "subcategory":"Cheese",
            "type":"Retail Goods"
        }
    ],
    "sg:phone":"+1 734 946 4500",
    "sg:postcode":"48180",
    "sg:province":"MI",
    "sg:tags":[
        "shop"
    ],
    "wof:name":"Miceli and Oldfield",
    "wof:placetype":"venue"
},
  "geometry": {"coordinates":[-83.276703,42.2169],"type":"Point"}
}