{
  "type": "Feature",
  "properties": {
    "iso:country":"US",
    "sg:address":"4733 W Wickford",
    "sg:city":"Bloomfield Hills",
    "sg:classifiers":[
        {
            "category":"Health Services",
            "subcategory":"Doctor",
            "type":"Services"
        }
    ],
    "sg:phone":"+1 248 258 3468",
    "sg:postcode":"48302",
    "sg:province":"MI",
    "sg:tags":[
        "physician",
        "surgeon"
    ],
    "wof:name":"Gerald C Timmis MD",
    "wof:placetype":"venue"
},
  "geometry": {"coordinates":[-83.288178,42.571708],"type":"Point"}
}