{
  "type": "Feature",
  "properties": {
    "iso:country":"US",
    "sg:address":"14455 Ford Rd",
    "sg:city":"Dearborn",
    "sg:classifiers":[
        {
            "category":"Farming",
            "subcategory":"Nursery",
            "type":"Manufacturing & Wholesale Goods"
        },
        {
            "category":"Home & Garden",
            "subcategory":"Garden Supply",
            "type":"Retail Goods"
        }
    ],
    "sg:phone":"+1 313 216 8888",
    "sg:postcode":"48126",
    "sg:province":"MI",
    "sg:tags":[
        "equipment",
        "growers'",
        "hydroponics"
    ],
    "sg:website":"http://www.hydrogiant.com",
    "wof:name":"Hydro Giant",
    "wof:placetype":"venue"
},
  "geometry": {"coordinates":[-83.184241,42.329323],"type":"Point"}
}