{
  "type": "Feature",
  "properties": {
    "iso:country":"US",
    "sg:address":"515 W Ionia St",
    "sg:city":"Lansing",
    "sg:classifiers":[
        {
            "category":"Shopping",
            "subcategory":"Florist",
            "type":"Retail Goods"
        }
    ],
    "sg:phone":"+1 517 372 5610",
    "sg:postcode":"48933",
    "sg:province":"MI",
    "wof:name":"Belen's Flowers",
    "wof:placetype":"venue"
},
  "geometry": {"coordinates":[-84.558742,42.735957],"type":"Point"}
}