{
  "type": "Feature",
  "properties": {
    "iso:country":"US",
    "sg:address":"5121 Division Ave S",
    "sg:city":"Grand Rapids",
    "sg:classifiers":[
        {
            "category":"Recreation",
            "type":"Entertainment"
        }
    ],
    "sg:phone":"+1 616 249 1911",
    "sg:postcode":"49548",
    "sg:province":"MI",
    "sg:tags":[
        "safety",
        "instruction",
        "marksmanship",
        "gun"
    ],
    "sg:website":"www.silverbulletfirearms.com",
    "wof:name":"Silver Bullet Firearms Indoor",
    "wof:placetype":"venue"
},
  "geometry": {"coordinates":[-85.66431,42.869858],"type":"Point"}
}