{
  "type": "Feature",
  "properties": {
    "iso:country":"US",
    "sg:address":"2068 N Norma St",
    "sg:city":"Westland",
    "sg:classifiers":[
        {
            "category":"Professional",
            "subcategory":"Advertising",
            "type":"Services"
        }
    ],
    "sg:phone":"+1 734 729 9429",
    "sg:postcode":"48185",
    "sg:province":"MI",
    "sg:tags":[
        "mail",
        "direct"
    ],
    "wof:name":"H E Walker",
    "wof:placetype":"venue"
},
  "geometry": {"coordinates":[-83.419376,42.323039],"type":"Point"}
}