{
  "type": "Feature",
  "properties": {
    "iso:country":"US",
    "sg:address":"2654 S Getty St",
    "sg:city":"Muskegon",
    "sg:classifiers":[
        {
            "category":"Restaurant",
            "type":"Food & Drink"
        }
    ],
    "sg:phone":"+1 231 739 1201",
    "sg:postcode":"49444",
    "sg:province":"MI",
    "wof:name":"Nino's Inn",
    "wof:placetype":"venue"
},
  "geometry": {"coordinates":[-86.22465200000001,43.20396],"type":"Point"}
}