{
  "type": "Feature",
  "properties": {
    "iso:country":"US",
    "sg:address":"20440 Bedford Rd N",
    "sg:city":"Battle Creek",
    "sg:classifiers":[
        {
            "category":"Organizations",
            "subcategory":"Religious Organization",
            "type":"Services"
        }
    ],
    "sg:phone":"+1 269 964 1960",
    "sg:postcode":"49017",
    "sg:province":"MI",
    "wof:name":"Urbandale 7th Day Advnt Church",
    "wof:placetype":"venue"
},
  "geometry": {"coordinates":[-85.234925,42.372562],"type":"Point"}
}