{
  "type": "Feature",
  "properties": {
    "iso:country":"US",
    "sg:address":"13219 W McNichols Rd",
    "sg:city":"Detroit",
    "sg:classifiers":[
        {
            "category":"Retail",
            "subcategory":"Repair Shop",
            "type":"Services"
        }
    ],
    "sg:phone":"+1 313 864 2560",
    "sg:postcode":"48235",
    "sg:province":"MI",
    "sg:tags":[
        "upholstery",
        "work"
    ],
    "wof:name":"Rosedale Upholstering",
    "wof:placetype":"venue"
},
  "geometry": {"coordinates":[-83.176174,42.416534],"type":"Point"}
}