{
  "type": "Feature",
  "properties": {
    "iso:country":"US",
    "sg:address":"2747 Somerset Blvd",
    "sg:city":"Troy",
    "sg:classifiers":[
        {
            "category":"Building & Trades",
            "subcategory":"Cleaning & Sanitation",
            "type":"Services"
        }
    ],
    "sg:phone":"+1 586 566 0033",
    "sg:postcode":"48084",
    "sg:province":"MI",
    "sg:tags":[
        "maintenance"
    ],
    "wof:name":"Homemaid Housekeeping Inc",
    "wof:placetype":"venue"
},
  "geometry": {"coordinates":[-83.18227899999999,42.554354],"type":"Point"}
}