{
  "type": "Feature",
  "properties": {
    "iso:country":"US",
    "sg:address":"5105 W Bristol Rd",
    "sg:city":"Flint",
    "sg:classifiers":[
        {
            "category":"Health Services",
            "subcategory":"Doctor",
            "type":"Services"
        }
    ],
    "sg:phone":"+1 810 733 0822",
    "sg:postcode":"48507",
    "sg:province":"MI",
    "sg:tags":[
        "medical"
    ],
    "wof:name":"Marta Bonkowski MD",
    "wof:placetype":"venue"
},
  "geometry": {"coordinates":[-83.774838,42.973287],"type":"Point"}
}