{
  "type": "Feature",
  "properties": {
    "iso:country":"US",
    "sg:address":"2460 Market St",
    "sg:city":"Detroit",
    "sg:classifiers":[
        {
            "category":"Restaurant",
            "type":"Food & Drink"
        }
    ],
    "sg:phone":"+1 313 393 1711",
    "sg:postcode":"48207",
    "sg:province":"MI",
    "sg:tags":[
        "traditional",
        "american"
    ],
    "sg:website":"www.viviosbloodymary.com/",
    "wof:name":"Vivio's Food & Spirits",
    "wof:placetype":"venue"
},
  "geometry": {"coordinates":[-83.038803,42.345901],"type":"Point"}
}