{
  "type": "Feature",
  "properties": {
    "iso:country":"US",
    "sg:address":"12211 Rosemary Ave",
    "sg:city":"Detroit",
    "sg:classifiers":[
        {
            "category":"Social Services",
            "subcategory":"Adult Care",
            "type":"Services"
        }
    ],
    "sg:phone":"+1 313 526 4515",
    "sg:postcode":"48213",
    "sg:province":"MI",
    "sg:tags":[
        "foster",
        "provider"
    ],
    "wof:name":"Earnest Foster",
    "wof:placetype":"venue"
},
  "geometry": {"coordinates":[-82.98535200000001,42.411109],"type":"Point"}
}