{
  "type": "Feature",
  "properties": {
    "iso:country":"US",
    "sg:address":"29200 Southfield Rd",
    "sg:city":"Southfield",
    "sg:classifiers":[
        {
            "category":"Insurance",
            "subcategory":"Insurance Agent",
            "type":"Services"
        }
    ],
    "sg:phone":"+1 248 552 9400",
    "sg:postcode":"48076",
    "sg:province":"MI",
    "wof:name":"Poole & Jackson Insurance Agcy",
    "wof:placetype":"venue"
},
  "geometry": {"coordinates":[-83.22255,42.503329],"type":"Point"}
}