{
  "type": "Feature",
  "properties": {
    "iso:country":"US",
    "sg:address":"2311 Monroe St",
    "sg:city":"Dearborn",
    "sg:classifiers":[
        {
            "category":"Restaurant",
            "type":"Food & Drink"
        }
    ],
    "sg:phone":"+1 313 274 9810",
    "sg:postcode":"48124",
    "sg:province":"MI",
    "sg:tags":[
        "pizza"
    ],
    "wof:name":"Joe Reno's Pizzeria",
    "wof:placetype":"venue"
},
  "geometry": {"coordinates":[-83.247101,42.295799],"type":"Point"}
}