{
  "type": "Feature",
  "properties": {
    "iso:country":"US",
    "sg:address":"19435 Mendota St",
    "sg:city":"Detroit",
    "sg:classifiers":[
        {
            "category":"Personal",
            "subcategory":"Barber",
            "type":"Services"
        }
    ],
    "sg:phone":"+1 313 819 2251",
    "sg:postcode":"48221",
    "sg:province":"MI",
    "sg:tags":[
        "shop"
    ],
    "wof:name":"Jeanette E Richmond",
    "wof:placetype":"venue"
},
  "geometry": {"coordinates":[-83.166684,42.436495],"type":"Point"}
}