{
  "type": "Feature",
  "properties": {
    "iso:country":"US",
    "sg:address":"4074 Gratiot Ave",
    "sg:city":"Port Huron",
    "sg:classifiers":[
        {
            "category":"Professional",
            "type":"Services"
        }
    ],
    "sg:phone":"+1 810 385 3085",
    "sg:postcode":"48060",
    "sg:province":"MI",
    "wof:name":"Fernandez Enterprises",
    "wof:placetype":"venue"
},
  "geometry": {"coordinates":[-82.436412,43.026366],"type":"Point"}
}