{
  "type": "Feature",
  "properties": {
    "iso:country":"US",
    "sg:address":"43500 W Oaks Dr",
    "sg:city":"Novi",
    "sg:classifiers":[
        {
            "category":"Shopping",
            "subcategory":"Department Store",
            "type":"Retail Goods"
        }
    ],
    "sg:phone":"+1 248 348 3355",
    "sg:postcode":"48377",
    "sg:province":"MI",
    "sg:website":"www.marshalls.com",
    "wof:name":"Marshalls",
    "wof:placetype":"venue"
},
  "geometry": {"coordinates":[-83.47642500000001,42.491189],"type":"Point"}
}