{
  "type": "Feature",
  "properties": {
    "iso:country":"US",
    "sg:address":"4181 Schaefer Rd",
    "sg:city":"Dearborn",
    "sg:classifiers":[
        {
            "category":"Retail",
            "subcategory":"Auto Repair",
            "type":"Services"
        }
    ],
    "sg:phone":"+1 313 581 5833",
    "sg:postcode":"48126",
    "sg:province":"MI",
    "sg:tags":[
        "shop"
    ],
    "wof:name":"Jim's Dearborn Auto Repair",
    "wof:placetype":"venue"
},
  "geometry": {"coordinates":[-83.17590300000001,42.316799],"type":"Point"}
}