{
  "type": "Feature",
  "properties": {
    "iso:country":"US",
    "sg:address":"7869 US Hwy 41",
    "sg:city":"Stephenson",
    "sg:classifiers":[
        {
            "category":"Manufacturing",
            "subcategory":"Lumber",
            "type":"Manufacturing & Wholesale Goods"
        }
    ],
    "sg:phone":"+1 906 753 4046",
    "sg:postcode":"49887",
    "sg:province":"MI",
    "sg:tags":[
        "forester"
    ],
    "wof:name":"Schrot Forestry Consulting",
    "wof:placetype":"venue"
},
  "geometry": {"coordinates":[-87.610072,45.402986],"type":"Point"}
}