{
  "type": "Feature",
  "properties": {
    "iso:country":"US",
    "sg:address":"938 Amber View Dr SW",
    "sg:city":"Byron Center",
    "sg:classifiers":[
        {
            "category":"Wholesale",
            "subcategory":"Durable Goods & Equipment",
            "type":"Manufacturing & Wholesale Goods"
        }
    ],
    "sg:phone":"+1 616 878 4022",
    "sg:postcode":"49315",
    "sg:province":"MI",
    "sg:tags":[
        "representative",
        "manufacturer"
    ],
    "wof:name":"H C & Assoc",
    "wof:placetype":"venue"
},
  "geometry": {"coordinates":[-85.68727699999999,42.838758],"type":"Point"}
}