{
  "type": "Feature",
  "properties": {
    "iso:country":"US",
    "sg:address":"1367 Lakeview Dr",
    "sg:city":"Rochester",
    "sg:classifiers":[
        {
            "category":"Professional",
            "subcategory":"Business Services",
            "type":"Services"
        }
    ],
    "sg:phone":"+1 248 608 8488",
    "sg:postcode":"48306",
    "sg:province":"MI",
    "wof:name":"Nsd Enterprises Inc",
    "wof:placetype":"venue"
},
  "geometry": {"coordinates":[-83.128421,42.701834],"type":"Point"}
}