{
  "type": "Feature",
  "properties": {
    "iso:country":"US",
    "sg:address":"592 Seabrook Dr",
    "sg:city":"Rochester Hills",
    "sg:classifiers":[
        {
            "category":"Shopping",
            "subcategory":"Catalog Store",
            "type":"Retail Goods"
        }
    ],
    "sg:phone":"+1 248 608 1641",
    "sg:postcode":"48307",
    "sg:province":"MI",
    "sg:tags":[
        "mail",
        "order"
    ],
    "wof:name":"B J Specials",
    "wof:placetype":"venue"
},
  "geometry": {"coordinates":[-83.119829,42.667261],"type":"Point"}
}