{
  "type": "Feature",
  "properties": {
    "iso:country":"US",
    "sg:address":"6062 Pinecroft Dr",
    "sg:city":"West Bloomfield",
    "sg:classifiers":[
        {
            "category":"Professional",
            "subcategory":"Management & Consulting",
            "type":"Services"
        }
    ],
    "sg:phone":"+1 248 865 9882",
    "sg:postcode":"48322",
    "sg:province":"MI",
    "wof:name":"Core Products Group",
    "wof:placetype":"venue"
},
  "geometry": {"coordinates":[-83.36767999999999,42.548957],"type":"Point"}
}