{
  "type": "Feature",
  "properties": {
    "iso:country":"US",
    "sg:address":"324 Main St",
    "sg:city":"Blanchard",
    "sg:classifiers":[
        {
            "category":"Government",
            "subcategory":"Office",
            "type":"Public Place"
        }
    ],
    "sg:phone":"+1 989 561 2642",
    "sg:postcode":"49310",
    "sg:province":"MI",
    "sg:tags":[
        "village"
    ],
    "wof:name":"Rolland Twp Hall",
    "wof:placetype":"venue"
},
  "geometry": {"coordinates":[-85.08132500000001,43.519905],"type":"Point"}
}