{
  "type": "Feature",
  "properties": {
    "iso:country":"US",
    "sg:address":"550 S Loomis Rd",
    "sg:city":"Mount Pleasant",
    "sg:classifiers":[
        {
            "category":"Social Services",
            "subcategory":"Child Care",
            "type":"Services"
        }
    ],
    "sg:phone":"+1 989 773 0670",
    "sg:postcode":"48858",
    "sg:province":"MI",
    "sg:tags":[
        "day"
    ],
    "wof:name":"Heartland Daycare",
    "wof:placetype":"venue"
},
  "geometry": {"coordinates":[-84.66828099999999,43.632767],"type":"Point"}
}