{
  "type": "Feature",
  "properties": {
    "iso:country":"US",
    "sg:address":"8575 Kier Rd",
    "sg:city":"Clarkston",
    "sg:classifiers":[
        {
            "category":"Building & Trades",
            "subcategory":"Construction",
            "type":"Services"
        }
    ],
    "sg:phone":"+1 248 625 6761",
    "sg:postcode":"48348",
    "sg:province":"MI",
    "sg:tags":[
        "general",
        "contractor"
    ],
    "wof:name":"B & D Contractors Inc",
    "wof:placetype":"venue"
},
  "geometry": {"coordinates":[-83.453788,42.789216],"type":"Point"}
}