{
  "type": "Feature",
  "properties": {
    "iso:country":"US",
    "sg:address":"1037 Wilkie St",
    "sg:city":"Alpena",
    "sg:classifiers":[
        {
            "category":"Building & Trades",
            "subcategory":"Construction",
            "type":"Services"
        }
    ],
    "sg:phone":"+1 989 354 3904",
    "sg:postcode":"49707",
    "sg:province":"MI",
    "sg:tags":[
        "contractor"
    ],
    "wof:name":"Mytko Masonry",
    "wof:placetype":"venue"
},
  "geometry": {"coordinates":[-83.472066,45.036178],"type":"Point"}
}