{
  "type": "Feature",
  "properties": {
    "iso:country":"US",
    "sg:address":"810 Terrace St",
    "sg:city":"Muskegon",
    "sg:classifiers":[
        {
            "category":"Health Services",
            "subcategory":"Optometrist",
            "type":"Services"
        }
    ],
    "sg:phone":"+1 231 726 4234",
    "sg:postcode":"49440",
    "sg:province":"MI",
    "wof:name":"Dennis D Cobler OD",
    "wof:placetype":"venue"
},
  "geometry": {"coordinates":[-86.24717,43.237638],"type":"Point"}
}