{
  "type": "Feature",
  "properties": {
    "iso:country":"US",
    "sg:address":"628 60th St",
    "sg:city":"Pullman",
    "sg:classifiers":[
        {
            "category":"Professional",
            "subcategory":"Business Services",
            "type":"Services"
        }
    ],
    "sg:phone":"+1 269 236 5880",
    "sg:postcode":"49450",
    "sg:province":"MI",
    "sg:tags":[
        "translator",
        "interpreter"
    ],
    "wof:name":"Russian Language Specialties",
    "wof:placetype":"venue"
},
  "geometry": {"coordinates":[-86.129232,42.465518],"type":"Point"}
}