{
  "type": "Feature",
  "properties": {
    "iso:country":"US",
    "sg:address":"14211 Myers Rd",
    "sg:city":"Dewitt",
    "sg:classifiers":[
        {
            "category":"Real Estate",
            "subcategory":"Real Estate Operator",
            "type":"Services"
        }
    ],
    "sg:phone":"+1 517 485 4228",
    "sg:postcode":"48820",
    "sg:province":"MI",
    "sg:tags":[
        "property",
        "lessor"
    ],
    "wof:name":"Dorothy Thomas",
    "wof:placetype":"venue"
},
  "geometry": {"coordinates":[-84.55263600000001,42.807477],"type":"Point"}
}