{
  "type": "Feature",
  "properties": {
    "iso:country":"US",
    "sg:address":"263 Glazier Rd",
    "sg:city":"Chelsea",
    "sg:classifiers":[
        {
            "category":"Building & Trades",
            "subcategory":"Construction",
            "type":"Services"
        }
    ],
    "sg:phone":"+1 734 475 1886",
    "sg:postcode":"48118",
    "sg:province":"MI",
    "sg:tags":[
        "hanging",
        "contractor"
    ],
    "wof:name":"Maler Der",
    "wof:placetype":"venue"
},
  "geometry": {"coordinates":[-84.09521100000001,42.311856],"type":"Point"}
}