{
  "type": "Feature",
  "properties": {
    "iso:country":"US",
    "sg:address":"333 12th St",
    "sg:city":"Plainwell",
    "sg:classifiers":[
        {
            "category":"Real Estate",
            "subcategory":"Real Estate Operator",
            "type":"Services"
        }
    ],
    "sg:phone":"+1 269 685 6772",
    "sg:postcode":"49080",
    "sg:province":"MI",
    "sg:tags":[
        "building",
        "apartment"
    ],
    "wof:name":"Country Knoll Apartments",
    "wof:placetype":"venue"
},
  "geometry": {"coordinates":[-85.661271,42.446959],"type":"Point"}
}