{
  "type": "Feature",
  "properties": {
    "iso:country":"US",
    "sg:address":"1000 S Main St",
    "sg:city":"Adrian",
    "sg:classifiers":[
        {
            "category":"Autos & Motor Vehicles",
            "subcategory":"Auto Supplies",
            "type":"Retail Goods"
        }
    ],
    "sg:phone":"+1 517 263 5383",
    "sg:postcode":"49221",
    "sg:province":"MI",
    "sg:tags":[
        "automobile",
        "parts"
    ],
    "sg:website":"www.autozone.com",
    "wof:name":"Autozone",
    "wof:placetype":"venue"
},
  "geometry": {"coordinates":[-84.04336499999999,41.884252],"type":"Point"}
}