{
  "type": "Feature",
  "properties": {
    "iso:country":"US",
    "sg:address":"15198 E 13 Mile Rd",
    "sg:city":"Warren",
    "sg:classifiers":[
        {
            "category":"Restaurant",
            "type":"Food & Drink"
        }
    ],
    "sg:phone":"+1 586 779 7930",
    "sg:postcode":"48088",
    "sg:province":"MI",
    "wof:name":"Big Boy Restaurants",
    "wof:placetype":"venue"
},
  "geometry": {"coordinates":[-82.96910099999999,42.523499],"type":"Point"}
}