{
  "type": "Feature",
  "properties": {
    "iso:country":"US",
    "sg:address":"1103 Washington Ave",
    "sg:city":"Holland",
    "sg:classifiers":[
        {
            "category":"Health Services",
            "subcategory":"Medical Lab",
            "type":"Services"
        }
    ],
    "sg:phone":"+1 616 396 2266",
    "sg:postcode":"49423",
    "sg:province":"MI",
    "sg:tags":[
        "laboratory",
        "dental"
    ],
    "wof:name":"Lakeshore Ceramic Dental Lab",
    "wof:placetype":"venue"
},
  "geometry": {"coordinates":[-86.116371,42.758029],"type":"Point"}
}