{
  "type": "Feature",
  "properties": {
    "iso:country":"US",
    "sg:address":"3011 W Grand Blvd",
    "sg:city":"Detroit",
    "sg:classifiers":[
        {
            "category":"Professional",
            "subcategory":"Management & Consulting",
            "type":"Services"
        }
    ],
    "sg:phone":"+1 313 872 2401",
    "sg:postcode":"48202",
    "sg:province":"MI",
    "wof:name":"Consumer Cr Counseling Svcs MI",
    "wof:placetype":"venue"
},
  "geometry": {"coordinates":[-83.076533,42.369237],"type":"Point"}
}