{
  "type": "Feature",
  "properties": {
    "iso:country":"US",
    "sg:address":"910 Jenks Blvd",
    "sg:city":"Kalamazoo",
    "sg:classifiers":[
        {
            "category":"Organizations",
            "subcategory":"Religious Organization",
            "type":"Services"
        }
    ],
    "sg:phone":"+1 269 349 9788",
    "sg:postcode":"49006",
    "sg:province":"MI",
    "sg:tags":[
        "church"
    ],
    "wof:name":"Hope Reformed Church",
    "wof:placetype":"venue"
},
  "geometry": {"coordinates":[-85.62153000000001,42.301531],"type":"Point"}
}