{
  "type": "Feature",
  "properties": {
    "iso:country":"US",
    "sg:address":"468 E Big Beaver Rd",
    "sg:city":"Troy",
    "sg:classifiers":[
        {
            "category":"Professional",
            "subcategory":"Computer Services",
            "type":"Services"
        }
    ],
    "sg:phone":"+1 248 740 2356",
    "sg:postcode":"48083",
    "sg:province":"MI",
    "sg:tags":[
        "programing",
        "custom"
    ],
    "wof:name":"Browser Soft",
    "wof:placetype":"venue"
},
  "geometry": {"coordinates":[-83.137873,42.56265],"type":"Point"}
}