{
  "type": "Feature",
  "properties": {
    "iso:country":"US",
    "sg:address":"2554 W North Union Rd",
    "sg:city":"Midland",
    "sg:classifiers":[
        {
            "category":"Home & Garden",
            "subcategory":"Carpets & Floor Coverings",
            "type":"Retail Goods"
        }
    ],
    "sg:phone":"+1 989 923 1701",
    "sg:postcode":"48642",
    "sg:province":"MI",
    "sg:tags":[
        "material",
        "flooring"
    ],
    "wof:name":"Kens Custom Floors",
    "wof:placetype":"venue"
},
  "geometry": {"coordinates":[-84.152111,43.611978],"type":"Point"}
}