{
  "type": "Feature",
  "properties": {
    "iso:country":"US",
    "sg:address":"212 Bellevue St SW",
    "sg:city":"Grand Rapids",
    "sg:classifiers":[
        {
            "category":"Organizations",
            "subcategory":"Religious Organization",
            "type":"Services"
        }
    ],
    "sg:phone":"+1 616 534 4948",
    "sg:postcode":"49548",
    "sg:province":"MI",
    "sg:tags":[
        "church"
    ],
    "wof:name":"Vietnamese United Methodist",
    "wof:placetype":"venue"
},
  "geometry": {"coordinates":[-85.673556,42.888599],"type":"Point"}
}