{
  "type": "Feature",
  "properties": {
    "iso:country":"US",
    "sg:address":"2400 28th St SW",
    "sg:city":"Wyoming",
    "sg:classifiers":[
        {
            "category":"Autos & Motor Vehicles",
            "subcategory":"Fuel & Gas Station",
            "type":"Retail Goods"
        }
    ],
    "sg:phone":"+1 616 534 5789",
    "sg:postcode":"49519",
    "sg:province":"MI",
    "sg:tags":[
        "oil"
    ],
    "wof:name":"Don's BP Svc",
    "wof:placetype":"venue"
},
  "geometry": {"coordinates":[-85.72599599999999,42.91393],"type":"Point"}
}