{
  "type": "Feature",
  "properties": {
    "iso:country":"US",
    "sg:address":"1990 Sherwood Glen",
    "sg:city":"Bloomfield Hills",
    "sg:classifiers":[
        {
            "category":"Building & Trades",
            "subcategory":"Cleaning & Sanitation",
            "type":"Services"
        }
    ],
    "sg:phone":"+1 248 539 7792",
    "sg:postcode":"48302",
    "sg:province":"MI",
    "sg:tags":[
        "maintenance"
    ],
    "wof:name":"All Purpose Cleaning Inc",
    "wof:placetype":"venue"
},
  "geometry": {"coordinates":[-83.322644,42.572842],"type":"Point"}
}