{
  "type": "Feature",
  "properties": {
    "iso:country":"US",
    "sg:address":"16420 Schoolcraft St",
    "sg:city":"Detroit",
    "sg:classifiers":[
        {
            "category":"Retail",
            "subcategory":"Laundry & Dry Cleaning",
            "type":"Services"
        }
    ],
    "sg:phone":"+1 313 838 2323",
    "sg:postcode":"48227",
    "sg:province":"MI",
    "sg:tags":[
        "fragrance"
    ],
    "wof:name":"Immaculate Carpet & Uphl Clg",
    "wof:placetype":"venue"
},
  "geometry": {"coordinates":[-83.20927500000001,42.386913],"type":"Point"}
}