{
  "type": "Feature",
  "properties": {
    "iso:country":"US",
    "sg:address":"4343 Highland Rd",
    "sg:city":"Waterford",
    "sg:classifiers":[
        {
            "category":"Retail",
            "subcategory":"Auto Repair",
            "type":"Services"
        }
    ],
    "sg:phone":"+1 248 683 1361",
    "sg:postcode":"48328",
    "sg:province":"MI",
    "sg:tags":[
        "transmission",
        "clutches"
    ],
    "wof:name":"Beatty Transmission Service",
    "wof:placetype":"venue"
},
  "geometry": {"coordinates":[-83.373287,42.654168],"type":"Point"}
}