{
  "type": "Feature",
  "properties": {
    "iso:country":"US",
    "sg:address":"1894 Emily Ct",
    "sg:city":"Auburn Hills",
    "sg:classifiers":[
        {
            "category":"Building & Trades",
            "subcategory":"Cleaning & Sanitation",
            "type":"Services"
        }
    ],
    "sg:phone":"+1 248 377 1828",
    "sg:postcode":"48326",
    "sg:province":"MI",
    "sg:tags":[
        "floor",
        "laying",
        "maintenance",
        "contractor"
    ],
    "wof:name":"Authentic Hardwood Flooring",
    "wof:placetype":"venue"
},
  "geometry": {"coordinates":[-83.24903999999999,42.670345],"type":"Point"}
}