{
  "type": "Feature",
  "properties": {
    "iso:country":"US",
    "sg:address":"55826 60th Ave",
    "sg:city":"Lawrence",
    "sg:classifiers":[
        {
            "category":"Professional",
            "subcategory":"Management & Consulting",
            "type":"Services"
        }
    ],
    "sg:phone":"+1 269 674 8866",
    "sg:postcode":"49064",
    "sg:province":"MI",
    "sg:tags":[
        "fuel"
    ],
    "wof:name":"International Plant Management",
    "wof:placetype":"venue"
},
  "geometry": {"coordinates":[-86.08671699999999,42.200464],"type":"Point"}
}