{
  "type": "Feature",
  "properties": {
    "iso:country":"US",
    "sg:address":"5571 Crippen Ave SW",
    "sg:city":"Grand Rapids",
    "sg:classifiers":[
        {
            "category":"Real Estate",
            "subcategory":"Real Estate Agent",
            "type":"Services"
        }
    ],
    "sg:phone":"+1 616 493 4900",
    "sg:postcode":"49548",
    "sg:province":"MI",
    "wof:name":"Castle Creek Realty",
    "wof:placetype":"venue"
},
  "geometry": {"coordinates":[-85.672579,42.862851],"type":"Point"}
}