{
  "type": "Feature",
  "properties": {
    "iso:country":"US",
    "sg:address":"4473 Remembrance Rd NW",
    "sg:city":"Grand Rapids",
    "sg:classifiers":[
        {
            "category":"Education",
            "subcategory":"School",
            "type":"Public Place"
        }
    ],
    "sg:phone":"+1 616 453 4757",
    "sg:postcode":"49534",
    "sg:province":"MI",
    "sg:website":"www.khps.org",
    "wof:name":"Kenowa Hills Tranportation",
    "wof:placetype":"venue"
},
  "geometry": {"coordinates":[-85.78160699999999,43.011684],"type":"Point"}
}