{
  "type": "Feature",
  "properties": {
    "iso:country":"US",
    "sg:address":"503 W Park Dr",
    "sg:city":"Rogers City",
    "sg:classifiers":[
        {
            "category":"Utilities",
            "subcategory":"Refuse",
            "type":"Services"
        }
    ],
    "sg:phone":"+1 989 734 2199",
    "sg:postcode":"49779",
    "sg:province":"MI",
    "sg:tags":[
        "system"
    ],
    "wof:name":"Waste Management",
    "wof:placetype":"venue"
},
  "geometry": {"coordinates":[-83.814877,45.409611],"type":"Point"}
}