{
  "type": "Feature",
  "properties": {
    "iso:country":"US",
    "sg:address":"47904 Anna Ct",
    "sg:city":"Wixom",
    "sg:classifiers":[
        {
            "category":"Home & Garden",
            "subcategory":"Carpets & Floor Coverings",
            "type":"Retail Goods"
        }
    ],
    "sg:phone":"+1 248 668 0265",
    "sg:postcode":"48393",
    "sg:province":"MI",
    "sg:tags":[
        "material"
    ],
    "wof:name":"Professional Flooring Supply",
    "wof:placetype":"venue"
},
  "geometry": {"coordinates":[-83.518919,42.506092],"type":"Point"}
}