{
  "type": "Feature",
  "properties": {
    "iso:country":"US",
    "sg:address":"525 S Center St",
    "sg:city":"Hartford",
    "sg:classifiers":[
        {
            "category":"Health Services",
            "subcategory":"Doctor",
            "type":"Services"
        }
    ],
    "sg:phone":"+1 269 621 4063",
    "sg:postcode":"49057",
    "sg:province":"MI",
    "sg:tags":[
        "medical"
    ],
    "wof:name":"Rhodes Charles MD",
    "wof:placetype":"venue"
},
  "geometry": {"coordinates":[-86.16666499999999,42.200587],"type":"Point"}
}