{
  "type": "Feature",
  "properties": {
    "iso:country":"US",
    "sg:address":"1330 Ranier St",
    "sg:city":"Canton",
    "sg:classifiers":[
        {
            "category":"Social Services",
            "subcategory":"Child Care",
            "type":"Services"
        }
    ],
    "sg:phone":"+1 734 981 7438",
    "sg:postcode":"48187",
    "sg:province":"MI",
    "sg:tags":[
        "home",
        "day"
    ],
    "wof:name":"Donna McClellan",
    "wof:placetype":"venue"
},
  "geometry": {"coordinates":[-83.465564,42.317315],"type":"Point"}
}