{
  "type": "Feature",
  "properties": {
    "iso:country":"US",
    "sg:address":"20624 W 8 Mile Rd",
    "sg:city":"Southfield",
    "sg:classifiers":[
        {
            "category":"Home & Garden",
            "subcategory":"Carpets & Floor Coverings",
            "type":"Retail Goods"
        }
    ],
    "sg:phone":"+1 248 356 1243",
    "sg:postcode":"48075",
    "sg:province":"MI",
    "sg:tags":[
        "carpeting"
    ],
    "sg:website":"www.flooringexpresswholesale.com",
    "wof:name":"Flooring Express Wholesale",
    "wof:placetype":"venue"
},
  "geometry": {"coordinates":[-83.245102,42.444],"type":"Point"}
}