{
  "type": "Feature",
  "properties": {
    "iso:country":"US",
    "sg:address":"8265 Lake Pine Dr",
    "sg:city":"Commerce Twp",
    "sg:classifiers":[
        {
            "category":"Wholesale",
            "subcategory":"Durable Goods & Equipment",
            "type":"Manufacturing & Wholesale Goods"
        }
    ],
    "sg:phone":"+1 248 366 0060",
    "sg:postcode":"48382",
    "sg:province":"MI",
    "sg:tags":[
        "representative",
        "manufacturer"
    ],
    "wof:name":"Conlon Fries Co",
    "wof:placetype":"venue"
},
  "geometry": {"coordinates":[-83.448176,42.583152],"type":"Point"}
}