{
  "type": "Feature",
  "properties": {
    "iso:country":"US",
    "sg:address":"2323 Oak St",
    "sg:city":"Port Huron",
    "sg:classifiers":[
        {
            "category":"Restaurant",
            "type":"Food & Drink"
        }
    ],
    "sg:menulink":"http://www.allmenus.com/mi/port-huron/182292-wendys/menu/",
    "sg:phone":"+1 810 985 5255",
    "sg:postcode":"48060",
    "sg:province":"MI",
    "sg:tags":[
        "burger",
        "american",
        "soup"
    ],
    "wof:name":"Wendy's",
    "wof:placetype":"venue"
},
  "geometry": {"coordinates":[-82.451418,42.965793],"type":"Point"}
}