{
  "type": "Feature",
  "properties": {
    "iso:country":"US",
    "sg:address":"3989 Sun Rapids Dr",
    "sg:city":"Okemos",
    "sg:classifiers":[
        {
            "category":"Professional",
            "subcategory":"Computer Services",
            "type":"Services"
        }
    ],
    "sg:phone":"+1 517 381 2302",
    "sg:postcode":"48864",
    "sg:province":"MI",
    "sg:tags":[
        "consulting",
        "related",
        "business"
    ],
    "wof:name":"Innovative & Quality Solutions",
    "wof:placetype":"venue"
},
  "geometry": {"coordinates":[-84.440388,42.696986],"type":"Point"}
}