{
  "type": "Feature",
  "properties": {
    "iso:country":"US",
    "sg:address":"5287 Maitland Rd",
    "sg:city":"North Street",
    "sg:classifiers":[
        {
            "category":"Building & Trades",
            "subcategory":"Construction",
            "type":"Services"
        }
    ],
    "sg:phone":"+1 810 984 3578",
    "sg:postcode":"48049",
    "sg:province":"MI",
    "sg:tags":[
        "floor",
        "laying",
        "contractor"
    ],
    "wof:name":"Glombowski Flooring",
    "wof:placetype":"venue"
},
  "geometry": {"coordinates":[-82.543194,43.029579],"type":"Point"}
}