{
  "type": "Feature",
  "properties": {
    "iso:country":"US",
    "sg:address":"22731 Newman St Ste 235",
    "sg:city":"Dearborn",
    "sg:classifiers":[
        {
            "category":"Health Services",
            "subcategory":"Doctor",
            "type":"Services"
        },
        {
            "category":"Health Services",
            "subcategory":"Clinic",
            "type":"Services"
        }
    ],
    "sg:phone":"+1 313 274 5490",
    "sg:postcode":"48124",
    "sg:province":"MI",
    "sg:tags":[
        "counseling",
        "mental"
    ],
    "wof:name":"Gibbs Patricia L PHD",
    "wof:placetype":"venue"
},
  "geometry": {"coordinates":[-83.25536099999999,42.302686],"type":"Point"}
}