{
  "type": "Feature",
  "properties": {
    "iso:country":"US",
    "sg:address":"11405 Vienna Rd",
    "sg:city":"Montrose",
    "sg:classifiers":[
        {
            "category":"Professional",
            "subcategory":"Employment Agencies",
            "type":"Services"
        }
    ],
    "sg:phone":"+1 248 706 1830",
    "sg:postcode":"48457",
    "sg:province":"MI",
    "sg:tags":[
        "help",
        "supply",
        "scene",
        "crime",
        "trauma",
        "clean"
    ],
    "sg:website":"http://www.aftermathprofessionals.com",
    "wof:name":"Aftermath Professionals Inc",
    "wof:placetype":"venue"
},
  "geometry": {"coordinates":[-83.90776700000001,43.176137],"type":"Point"}
}