{
  "type": "Feature",
  "properties": {
    "iso:country":"US",
    "sg:address":"12288 Felch St",
    "sg:city":"Holland",
    "sg:classifiers":[
        {
            "category":"Shopping",
            "subcategory":"Department Store",
            "type":"Retail Goods"
        }
    ],
    "sg:phone":"+1 616 393 7777",
    "sg:postcode":"49424",
    "sg:province":"MI",
    "sg:website":"http://www.kohls.com",
    "wof:name":"Kohl's",
    "wof:placetype":"venue"
},
  "geometry": {"coordinates":[-86.087515,42.819301],"type":"Point"}
}