{
  "type": "Feature",
  "properties": {
    "iso:country":"US",
    "sg:address":"101 N Albion St",
    "sg:city":"Albion",
    "sg:classifiers":[
        {
            "category":"Government",
            "subcategory":"Office",
            "type":"Public Place"
        }
    ],
    "sg:phone":"+1 517 629 5522",
    "sg:postcode":"49224",
    "sg:province":"MI",
    "wof:name":"Family Independence Agency",
    "wof:placetype":"venue"
},
  "geometry": {"coordinates":[-84.762191,42.246832],"type":"Point"}
}