{
  "type": "Feature",
  "properties": {
    "iso:country":"US",
    "sg:address":"8120 Pickerel Lake Rd",
    "sg:city":"Petoskey",
    "sg:classifiers":[
        {
            "category":"Restaurant",
            "type":"Food & Drink"
        }
    ],
    "sg:phone":"+1 231 347 7147",
    "sg:postcode":"49770",
    "sg:province":"MI",
    "sg:tags":[
        "eating"
    ],
    "wof:name":"Lauralex Inc",
    "wof:placetype":"venue"
},
  "geometry": {"coordinates":[-84.801992,45.377061],"type":"Point"}
}