{
  "type": "Feature",
  "properties": {
    "iso:country":"US",
    "sg:address":"1288 9th St",
    "sg:city":"Muskegon",
    "sg:classifiers":[
        {
            "category":"Retail",
            "subcategory":"Auto Repair",
            "type":"Services"
        }
    ],
    "sg:phone":"+1 231 722 1309",
    "sg:postcode":"49441",
    "sg:province":"MI",
    "sg:tags":[
        "towing",
        "wrecker"
    ],
    "wof:name":"Robinson's Towing",
    "wof:placetype":"venue"
},
  "geometry": {"coordinates":[-86.260007,43.229563],"type":"Point"}
}