{
  "type": "Feature",
  "properties": {
    "iso:country":"US",
    "sg:address":"8763 Hall Rd",
    "sg:city":"Utica",
    "sg:classifiers":[
        {
            "category":"Professional",
            "subcategory":"Detective & Security Services",
            "type":"Services"
        }
    ],
    "sg:phone":"+1 586 803 0003",
    "sg:postcode":"48317",
    "sg:province":"MI",
    "wof:name":"Ricco Investigations Inc",
    "wof:placetype":"venue"
},
  "geometry": {"coordinates":[-83.026899,42.625964],"type":"Point"}
}