{
  "type": "Feature",
  "properties": {
    "iso:country":"US",
    "sg:address":"315 Whiting St",
    "sg:city":"St Clair",
    "sg:classifiers":[
        {
            "category":"Manufacturing",
            "subcategory":"Rubber & Plastics",
            "type":"Manufacturing & Wholesale Goods"
        }
    ],
    "sg:phone":"+1 810 329 2271",
    "sg:postcode":"48079",
    "sg:province":"MI",
    "sg:website":"www.bwpi.com",
    "wof:name":"Blue Water Plastics Co",
    "wof:placetype":"venue"
},
  "geometry": {"coordinates":[-82.498829,42.820997],"type":"Point"}
}