{
  "type": "Feature",
  "properties": {
    "iso:country":"US",
    "sg:address":"5535 Wesch Rd",
    "sg:city":"Brooklyn",
    "sg:classifiers":[
        {
            "category":"Sports & Exercise",
            "subcategory":"Golf",
            "type":"Entertainment"
        }
    ],
    "sg:phone":"+1 517 592 6259",
    "sg:postcode":"49230",
    "sg:province":"MI",
    "sg:tags":[
        "course",
        "bar"
    ],
    "wof:name":"Clark Lk Golf Crse Drving Rnge",
    "wof:placetype":"venue"
},
  "geometry": {"coordinates":[-84.31569500000001,42.102457],"type":"Point"}
}