{
  "type": "Feature",
  "properties": {
    "iso:country":"US",
    "sg:address":"12741 W Warren Ave",
    "sg:city":"Dearborn",
    "sg:classifiers":[
        {
            "category":"Bakery",
            "type":"Food & Drink"
        }
    ],
    "sg:phone":"+1 313 582 7878",
    "sg:postcode":"48126",
    "sg:province":"MI",
    "wof:name":"New Afrah Bakery and Pastries",
    "wof:placetype":"venue"
},
  "geometry": {"coordinates":[-83.167801,42.344101],"type":"Point"}
}