{
  "type": "Feature",
  "properties": {
    "iso:country":"US",
    "sg:address":"1795 W Main St",
    "sg:city":"Owosso",
    "sg:classifiers":[
        {
            "category":"Organizations",
            "subcategory":"Non-profit Organization",
            "type":"Services"
        }
    ],
    "sg:phone":"+1 989 723 2556",
    "sg:postcode":"48867",
    "sg:province":"MI",
    "sg:tags":[
        "disability"
    ],
    "wof:name":"Capital Area Ctr-Ind Living",
    "wof:placetype":"venue"
},
  "geometry": {"coordinates":[-84.19837699999999,42.997552],"type":"Point"}
}