{
  "type": "Feature",
  "properties": {
    "iso:country":"US",
    "sg:address":"2565 E Highland Rd",
    "sg:city":"Highland",
    "sg:classifiers":[
        {
            "category":"Autos & Motor Vehicles",
            "subcategory":"Automobile Sales",
            "type":"Retail Goods"
        }
    ],
    "sg:phone":"+1 248 887 3222",
    "sg:postcode":"48356",
    "sg:province":"MI",
    "sg:tags":[
        "car",
        "dealer"
    ],
    "sg:website":"www.m59dodge.com",
    "wof:name":"M59 Dodge",
    "wof:placetype":"venue"
},
  "geometry": {"coordinates":[-83.578525,42.653842],"type":"Point"}
}