{
  "type": "Feature",
  "properties": {
    "iso:country":"US",
    "sg:address":"5701 136th Ave",
    "sg:city":"Holland",
    "sg:classifiers":[
        {
            "category":"Real Estate",
            "subcategory":"Real Estate Agent",
            "type":"Services"
        }
    ],
    "sg:phone":"+1 616 399 1651",
    "sg:postcode":"49424",
    "sg:province":"MI",
    "sg:tags":[
        "cooperative"
    ],
    "wof:name":"Mich Blueberry Growers Assn",
    "wof:placetype":"venue"
},
  "geometry": {"coordinates":[-86.1193,42.876069],"type":"Point"}
}