{
  "type": "Feature",
  "properties": {
    "iso:country":"US",
    "sg:address":"1677 Bradford St NE",
    "sg:city":"Grand Rapids",
    "sg:classifiers":[
        {
            "category":"Professional",
            "subcategory":"Management & Consulting",
            "type":"Services"
        }
    ],
    "sg:phone":"+1 616 454 8033",
    "sg:postcode":"49503",
    "sg:province":"MI",
    "wof:name":"Kelly Consultants",
    "wof:placetype":"venue"
},
  "geometry": {"coordinates":[-85.62685999999999,42.97735],"type":"Point"}
}