{
  "type": "Feature",
  "properties": {
    "iso:country":"US",
    "sg:address":"835 E Hoague Rd",
    "sg:city":"Free Soil",
    "sg:classifiers":[
        {
            "category":"Recreation",
            "type":"Entertainment"
        }
    ],
    "sg:phone":"+1 231 464 5156",
    "sg:postcode":"49411",
    "sg:province":"MI",
    "sg:tags":[
        "hall",
        "auditorium"
    ],
    "wof:name":"Grant Township Community Ctr",
    "wof:placetype":"venue"
},
  "geometry": {"coordinates":[-86.261095,44.151546],"type":"Point"}
}