{
  "type": "Feature",
  "properties": {
    "iso:country":"US",
    "sg:address":"2137 Darwin Ave SW",
    "sg:city":"Grand Rapids",
    "sg:classifiers":[
        {
            "category":"Social Services",
            "subcategory":"Child Care",
            "type":"Services"
        }
    ],
    "sg:phone":"+1 616 246 6989",
    "sg:postcode":"49507",
    "sg:province":"MI",
    "sg:tags":[
        "day"
    ],
    "wof:name":"Judith Kalee",
    "wof:placetype":"venue"
},
  "geometry": {"coordinates":[-85.673356,42.925112],"type":"Point"}
}