{
  "type": "Feature",
  "properties": {
    "iso:country":"US",
    "sg:address":"23629 Liberty St",
    "sg:city":"Farmington",
    "sg:classifiers":[
        {
            "category":"Professional",
            "subcategory":"Computer Services",
            "type":"Services"
        }
    ],
    "sg:phone":"+1 586 870 1646",
    "sg:postcode":"48335",
    "sg:province":"MI",
    "sg:tags":[
        "consultant",
        "software"
    ],
    "wof:name":"Professional Access Ltd",
    "wof:placetype":"venue"
},
  "geometry": {"coordinates":[-83.378394,42.46524],"type":"Point"}
}