{
  "type": "Feature",
  "properties": {
    "iso:country":"US",
    "sg:address":"4045 Cranbrook Ct",
    "sg:city":"Bloomfield Hills",
    "sg:classifiers":[
        {
            "category":"Banks & Credit Unions",
            "subcategory":"Financial Services",
            "type":"Services"
        }
    ],
    "sg:phone":"+1 248 647 5350",
    "sg:postcode":"48301",
    "sg:province":"MI",
    "sg:tags":[
        "investment"
    ],
    "wof:name":"Katko Family Ltd Partnership",
    "wof:placetype":"venue"
},
  "geometry": {"coordinates":[-83.284695,42.548895],"type":"Point"}
}