{
  "type": "Feature",
  "properties": {
    "iso:country":"US",
    "sg:address":"12988 S Cedar Rd",
    "sg:city":"Cedar",
    "sg:classifiers":[
        {
            "category":"Building & Trades",
            "subcategory":"Plumbing",
            "type":"Services"
        }
    ],
    "sg:phone":"+1 231 228 6664",
    "sg:postcode":"49621",
    "sg:province":"MI",
    "sg:tags":[
        "contractor"
    ],
    "wof:name":"DMS Plumbing & Heating",
    "wof:placetype":"venue"
},
  "geometry": {"coordinates":[-85.778503,44.789162],"type":"Point"}
}