{
  "type": "Feature",
  "properties": {
    "iso:country":"US",
    "sg:address":"5975 Diamond Dr",
    "sg:city":"Troy",
    "sg:classifiers":[
        {
            "category":"Professional",
            "subcategory":"Engineering",
            "type":"Services"
        }
    ],
    "sg:phone":"+1 248 828 1190",
    "sg:postcode":"48085",
    "sg:province":"MI",
    "sg:tags":[
        "consul",
        "eng"
    ],
    "wof:name":"Virtual Solutions Inc",
    "wof:placetype":"venue"
},
  "geometry": {"coordinates":[-83.099873,42.606559],"type":"Point"}
}