{
  "type": "Feature",
  "properties": {
    "iso:country":"US",
    "sg:address":"6920 Red Arrow Hwy",
    "sg:city":"Coloma",
    "sg:classifiers":[
        {
            "category":"Retail",
            "subcategory":"Veterinary Services",
            "type":"Services"
        }
    ],
    "sg:phone":"+1 269 468 6017",
    "sg:postcode":"49038",
    "sg:province":"MI",
    "sg:tags":[
        "clinic",
        "hospital",
        "veterinarian",
        "specialty"
    ],
    "wof:name":"Arrow Pet Clinic",
    "wof:placetype":"venue"
},
  "geometry": {"coordinates":[-86.29052,42.186093],"type":"Point"}
}