{
  "type": "Feature",
  "properties": {
    "iso:country":"US",
    "sg:address":"4078 17 Mile Rd",
    "sg:city":"Sterling Heights",
    "sg:classifiers":[
        {
            "category":"Restaurant",
            "type":"Food & Drink"
        }
    ],
    "sg:menulink":"http://www.allmenus.com/mi/sterling-heights/26982-hungry-howies-pizza/menu/",
    "sg:phone":"+1 586 268 8800",
    "sg:postcode":"48310",
    "sg:province":"MI",
    "sg:tags":[
        "wrap",
        "american",
        "sandwich",
        "pizza"
    ],
    "wof:name":"Hungry Howie's Pizza",
    "wof:placetype":"venue"
},
  "geometry": {"coordinates":[-83.069338,42.57921],"type":"Point"}
}