{
  "type": "Feature",
  "properties": {
    "iso:country":"US",
    "sg:address":"14204 Glenwood St",
    "sg:city":"Detroit",
    "sg:classifiers":[
        {
            "category":"Arts & Performance",
            "subcategory":"Theater",
            "type":"Entertainment"
        }
    ],
    "sg:phone":"+1 313 521 0302",
    "sg:postcode":"48205",
    "sg:province":"MI",
    "sg:tags":[
        "group"
    ],
    "wof:name":"Armed & Dangerous",
    "wof:placetype":"venue"
},
  "geometry": {"coordinates":[-82.975201,42.43047],"type":"Point"}
}