{
  "type": "Feature",
  "properties": {
    "iso:country":"US",
    "sg:address":"20257 Hall Rd",
    "sg:city":"Macomb Township",
    "sg:classifiers":[
        {
            "category":"Restaurant",
            "type":"Food & Drink"
        }
    ],
    "sg:phone":"+1 586 286 2300",
    "sg:postcode":"48044",
    "sg:province":"MI",
    "sg:tags":[
        "new",
        "american"
    ],
    "sg:website":"www.leosconeyisland.com/default....",
    "wof:name":"Leo's Coney Island",
    "wof:placetype":"venue"
},
  "geometry": {"coordinates":[-82.921201,42.628946],"type":"Point"}
}