{
  "type": "Feature",
  "properties": {
    "iso:country":"US",
    "sg:address":"6960 Orchard Lake Rd Ste 306",
    "sg:city":"West Bloomfield",
    "sg:classifiers":[
        {
            "category":"Banks & Credit Unions",
            "subcategory":"Bank",
            "type":"Services"
        }
    ],
    "sg:phone":"+1 248 855 8660",
    "sg:postcode":"48322",
    "sg:province":"MI",
    "wof:name":"Minority Alliance Capital",
    "wof:placetype":"venue"
},
  "geometry": {"coordinates":[-83.360497,42.5364],"type":"Point"}
}