{
  "type": "Feature",
  "properties": {
    "iso:country":"US",
    "sg:address":"3379 Orchard Dr",
    "sg:city":"Pinckney",
    "sg:classifiers":[
        {
            "category":"Home & Garden",
            "subcategory":"Building Materials",
            "type":"Retail Goods"
        }
    ],
    "sg:phone":"+1 734 878 1671",
    "sg:postcode":"48169",
    "sg:province":"MI",
    "wof:name":"Brians Brick & Block",
    "wof:placetype":"venue"
},
  "geometry": {"coordinates":[-83.88236499999999,42.470235],"type":"Point"}
}