{
  "type": "Feature",
  "properties": {
    "iso:country":"US",
    "sg:address":"101 N Main St",
    "sg:city":"Capac",
    "sg:classifiers":[
        {
            "category":"Personal",
            "subcategory":"Beauty Salon",
            "type":"Services"
        }
    ],
    "sg:phone":"+1 810 395 7951",
    "sg:postcode":"48014",
    "sg:province":"MI",
    "wof:name":"Perfection Hair Salon & Sure",
    "wof:placetype":"venue"
},
  "geometry": {"coordinates":[-82.92848600000001,43.014078],"type":"Point"}
}