{
  "type": "Feature",
  "properties": {
    "iso:country":"US",
    "sg:address":"5229 US Hwy 31",
    "sg:city":"Williamsburg",
    "sg:classifiers":[
        {
            "category":"Travel",
            "subcategory":"Hotels & Motels",
            "type":"Entertainment"
        }
    ],
    "sg:phone":"+1 231 938 2410",
    "sg:postcode":"49690",
    "sg:province":"MI",
    "wof:name":"Surfside Resort",
    "wof:placetype":"venue"
},
  "geometry": {"coordinates":[-85.510936,44.762202],"type":"Point"}
}