{
  "type": "Feature",
  "properties": {
    "iso:country":"US",
    "sg:address":"959 Lake Dr SE",
    "sg:city":"Grand Rapids",
    "sg:classifiers":[
        {
            "category":"Building & Trades",
            "subcategory":"Construction",
            "type":"Services"
        }
    ],
    "sg:phone":"+1 616 363 2122",
    "sg:postcode":"49506",
    "sg:province":"MI",
    "sg:tags":[
        "carpentry",
        "contractor"
    ],
    "wof:name":"Unique Reflections Cstm Frmng",
    "wof:placetype":"venue"
},
  "geometry": {"coordinates":[-85.64730299999999,42.960463],"type":"Point"}
}