{
  "type": "Feature",
  "properties": {
    "iso:country":"US",
    "sg:address":"33841 Lyndon St",
    "sg:city":"Livonia",
    "sg:classifiers":[
        {
            "category":"Arena",
            "subcategory":"Sports Club",
            "type":"Entertainment"
        }
    ],
    "sg:phone":"+1 734 427 1280",
    "sg:postcode":"48154",
    "sg:province":"MI",
    "wof:name":"Eddie Edgar Sports Arena",
    "wof:placetype":"venue"
},
  "geometry": {"coordinates":[-83.37667500000001,42.389964],"type":"Point"}
}