{
  "type": "Feature",
  "properties": {
    "iso:country":"US",
    "sg:address":"2615 Aero-Park Dr",
    "sg:city":"Traverse City",
    "sg:classifiers":[
        {
            "category":"Manufacturing",
            "subcategory":"Glass & Minerals",
            "type":"Manufacturing & Wholesale Goods"
        }
    ],
    "sg:phone":"+1 231 929 2121",
    "sg:postcode":"49686",
    "sg:province":"MI",
    "sg:tags":[
        "abrasive",
        "product"
    ],
    "sg:website":"www.boride-eng-abr.com",
    "wof:name":"Boride Engineered Abrasives",
    "wof:placetype":"venue"
},
  "geometry": {"coordinates":[-85.56824899999999,44.74313],"type":"Point"}
}