{
  "type": "Feature",
  "properties": {
    "iso:country":"US",
    "sg:address":"7504 Hart Dr",
    "sg:city":"Kalamazoo",
    "sg:classifiers":[
        {
            "category":"Freight",
            "type":"Transportation"
        }
    ],
    "sg:phone":"+1 269 344 5624",
    "sg:postcode":"49009",
    "sg:province":"MI",
    "sg:tags":[
        "trucking"
    ],
    "wof:name":"Stoneburner Transport",
    "wof:placetype":"venue"
},
  "geometry": {"coordinates":[-85.703704,42.368644],"type":"Point"}
}