{
  "type": "Feature",
  "properties": {
    "iso:country":"US",
    "sg:address":"3351 Linden Rd",
    "sg:city":"Flint",
    "sg:classifiers":[
        {
            "category":"Shopping",
            "subcategory":"Clothing, Apparel, & Fashions",
            "type":"Retail Goods"
        }
    ],
    "sg:phone":"+1 810 230 8369",
    "sg:postcode":"48507",
    "sg:province":"MI",
    "sg:website":"www.hottopic.com",
    "wof:name":"Hot Topic",
    "wof:placetype":"venue"
},
  "geometry": {"coordinates":[-83.771897,42.976604],"type":"Point"}
}