{
  "type": "Feature",
  "properties": {
    "iso:country":"US",
    "sg:address":"240 N Adams Rd",
    "sg:city":"Rochester Hills",
    "sg:classifiers":[
        {
            "category":"Shopping",
            "subcategory":"Clothing, Apparel, & Fashions",
            "type":"Retail Goods"
        }
    ],
    "sg:phone":"+1 248 375 9626",
    "sg:postcode":"48309",
    "sg:province":"MI",
    "wof:name":"Abercrombie & Fitch",
    "wof:placetype":"venue"
},
  "geometry": {"coordinates":[-83.194035,42.680523],"type":"Point"}
}