{
  "type": "Feature",
  "properties": {
    "iso:country":"US",
    "sg:address":"887 Co Rd 480",
    "sg:city":"Marquette",
    "sg:classifiers":[
        {
            "category":"Retail",
            "subcategory":"Auto Repair",
            "type":"Services"
        }
    ],
    "sg:phone":"+1 906 249 9075",
    "sg:postcode":"49855",
    "sg:province":"MI",
    "sg:tags":[
        "parts",
        "truck"
    ],
    "wof:name":"Crossroads Truck Repair Inc",
    "wof:placetype":"venue"
},
  "geometry": {"coordinates":[-87.392189,46.461029],"type":"Point"}
}