{
  "type": "Feature",
  "properties": {
    "iso:country":"US",
    "sg:address":"2150 E 10 Mile Rd",
    "sg:city":"Warren",
    "sg:classifiers":[
        {
            "category":"Wholesale",
            "subcategory":"Groceries",
            "type":"Manufacturing & Wholesale Goods"
        }
    ],
    "sg:phone":"+1 586 756 6100",
    "sg:postcode":"48091",
    "sg:province":"MI",
    "sg:tags":[
        "equipment",
        "pizza",
        "supply"
    ],
    "wof:name":"Dough & Spice Inc",
    "wof:placetype":"venue"
},
  "geometry": {"coordinates":[-83.08055899999999,42.476335],"type":"Point"}
}