{
  "type": "Feature",
  "properties": {
    "iso:country":"US",
    "sg:address":"901 S Brown St",
    "sg:city":"Jackson",
    "sg:classifiers":[
        {
            "category":"Personal",
            "subcategory":"Tattoo Parlor",
            "type":"Services"
        }
    ],
    "sg:phone":"+1 517 768 8388",
    "sg:postcode":"49203",
    "sg:province":"MI",
    "sg:tags":[
        "tattooing"
    ],
    "wof:name":"Ye Olde Skull Tattoo",
    "wof:placetype":"venue"
},
  "geometry": {"coordinates":[-84.43311,42.238254],"type":"Point"}
}