{
  "type": "Feature",
  "properties": {
    "iso:country":"US",
    "sg:address":"109 W Clinton St",
    "sg:city":"Howell",
    "sg:classifiers":[
        {
            "category":"Professional",
            "subcategory":"Accounting & Tax Preparation",
            "type":"Services"
        }
    ],
    "sg:phone":"+1 517 546 2130",
    "sg:postcode":"48843",
    "sg:province":"MI",
    "sg:tags":[
        "accountant",
        "public"
    ],
    "wof:name":"Bredernitz & Wagner & Co PC",
    "wof:placetype":"venue"
},
  "geometry": {"coordinates":[-83.930103,42.608316],"type":"Point"}
}