{
  "type": "Feature",
  "properties": {
    "iso:country":"US",
    "sg:address":"3208 Arbor Dr",
    "sg:city":"Fenton",
    "sg:classifiers":[
        {
            "category":"Building & Trades",
            "subcategory":"Construction",
            "type":"Services"
        }
    ],
    "sg:phone":"+1 810 714 2378",
    "sg:postcode":"48430",
    "sg:province":"MI",
    "sg:tags":[
        "house"
    ],
    "wof:name":"Watson Construction",
    "wof:placetype":"venue"
},
  "geometry": {"coordinates":[-83.73798600000001,42.802751],"type":"Point"}
}