{
  "type": "Feature",
  "properties": {
    "iso:country":"US",
    "sg:address":"12682 Cleveland Ave",
    "sg:city":"Buchanan",
    "sg:classifiers":[
        {
            "category":"Farming",
            "subcategory":"Farm",
            "type":"Manufacturing & Wholesale Goods"
        }
    ],
    "sg:phone":"+1 269 422 2374",
    "sg:postcode":"49107",
    "sg:province":"MI",
    "sg:tags":[
        "crop",
        "general"
    ],
    "wof:name":"Dennis Strauss",
    "wof:placetype":"venue"
},
  "geometry": {"coordinates":[-86.49426200000001,41.889134],"type":"Point"}
}