{
  "type": "Feature",
  "properties": {
    "iso:country":"US",
    "sg:address":"6488 Hollowtree Ct",
    "sg:city":"Saline",
    "sg:classifiers":[
        {
            "category":"Organizations",
            "subcategory":"Membership Organization",
            "type":"Services"
        }
    ],
    "sg:phone":"+1 313 532 7336",
    "sg:postcode":"48176",
    "sg:province":"MI",
    "wof:name":"Michigan Wood Carvers Assn",
    "wof:placetype":"venue"
},
  "geometry": {"coordinates":[-83.808065,42.191206],"type":"Point"}
}