{
  "type": "Feature",
  "properties": {
    "iso:country":"US",
    "sg:address":"11690 Hoskins Ave",
    "sg:city":"Cedar Springs",
    "sg:classifiers":[
        {
            "category":"Professional",
            "subcategory":"Engineering",
            "type":"Services"
        }
    ],
    "sg:phone":"+1 616 866 4122",
    "sg:postcode":"49319",
    "sg:province":"MI",
    "wof:name":"Millenium Machine Control",
    "wof:placetype":"venue"
},
  "geometry": {"coordinates":[-85.591285,43.18275],"type":"Point"}
}