{
  "type": "Feature",
  "properties": {
    "iso:country":"US",
    "sg:address":"909 S Stewart Ave",
    "sg:city":"Fremont",
    "sg:classifiers":[
        {
            "category":"Professional",
            "subcategory":"Research",
            "type":"Services"
        }
    ],
    "sg:phone":"+1 231 924 8026",
    "sg:postcode":"49412",
    "sg:province":"MI",
    "sg:tags":[
        "foundation",
        "philanthropic"
    ],
    "wof:name":"Foster Grandparents Program",
    "wof:placetype":"venue"
},
  "geometry": {"coordinates":[-85.940072,43.458876],"type":"Point"}
}