{
  "type": "Feature",
  "properties": {
    "iso:country":"US",
    "sg:address":"5991 Victoria St",
    "sg:city":"Belleville",
    "sg:classifiers":[
        {
            "category":"Shopping",
            "subcategory":"Clothing, Apparel, & Fashions",
            "type":"Retail Goods"
        }
    ],
    "sg:phone":"+1 734 564 4649",
    "sg:postcode":"48111",
    "sg:province":"MI",
    "wof:name":"Natural Adult Desire",
    "wof:placetype":"venue"
},
  "geometry": {"coordinates":[-83.54073,42.257679],"type":"Point"}
}