{
  "type": "Feature",
  "properties": {
    "iso:country":"US",
    "sg:address":"427 Dennis St",
    "sg:city":"Adrian",
    "sg:classifiers":[
        {
            "category":"Real Estate",
            "subcategory":"Real Estate Agent",
            "type":"Services"
        }
    ],
    "sg:phone":"+1 517 265 5807",
    "sg:postcode":"49221",
    "sg:province":"MI",
    "sg:tags":[
        "management"
    ],
    "wof:name":"J & R Property Management",
    "wof:placetype":"venue"
},
  "geometry": {"coordinates":[-84.03716900000001,41.89506],"type":"Point"}
}