{
  "type": "Feature",
  "properties": {
    "iso:country":"US",
    "sg:address":"2479 Warwick Dr",
    "sg:city":"Troy",
    "sg:classifiers":[
        {
            "category":"Professional",
            "subcategory":"Lawyer & Legal Services",
            "type":"Services"
        }
    ],
    "sg:phone":"+1 248 643 8130",
    "sg:postcode":"48084",
    "sg:province":"MI",
    "sg:tags":[
        "attorney"
    ],
    "wof:name":"Stephen J Dunn",
    "wof:placetype":"venue"
},
  "geometry": {"coordinates":[-83.191801,42.556329],"type":"Point"}
}