{
  "type": "Feature",
  "properties": {
    "iso:country":"US",
    "sg:address":"300 W 14 Mile Rd",
    "sg:city":"Troy",
    "sg:classifiers":[
        {
            "category":"Health Services",
            "subcategory":"Dentist",
            "type":"Services"
        }
    ],
    "sg:phone":"+1 248 585 5227",
    "sg:postcode":"48083",
    "sg:province":"MI",
    "sg:tags":[
        "orthodontist"
    ],
    "wof:name":"Sears Dental",
    "wof:placetype":"venue"
},
  "geometry": {"coordinates":[-83.10929899999999,42.534401],"type":"Point"}
}