{
  "type": "Feature",
  "properties": {
    "iso:country":"US",
    "sg:address":"145 Brady St",
    "sg:city":"Allegan",
    "sg:classifiers":[
        {
            "category":"Insurance",
            "subcategory":"Title Insurance",
            "type":"Services"
        }
    ],
    "sg:phone":"+1 269 673 2071",
    "sg:postcode":"49010",
    "sg:province":"MI",
    "sg:tags":[
        "company"
    ],
    "wof:name":"Metropolitan Title Company",
    "wof:placetype":"venue"
},
  "geometry": {"coordinates":[-85.848354,42.526569],"type":"Point"}
}