{
  "type": "Feature",
  "properties": {
    "iso:country":"US",
    "sg:address":"101 River St",
    "sg:city":"Boyne City",
    "sg:classifiers":[
        {
            "category":"Banks & Credit Unions",
            "subcategory":"Bank",
            "type":"Services"
        }
    ],
    "sg:phone":"+1 231 582 6731",
    "sg:postcode":"49712",
    "sg:province":"MI",
    "sg:tags":[
        "national"
    ],
    "wof:name":"Huntington National Bank",
    "wof:placetype":"venue"
},
  "geometry": {"coordinates":[-85.014144,45.21502],"type":"Point"}
}