{
  "type": "Feature",
  "properties": {
    "iso:country":"US",
    "sg:address":"1014 S Beacon Blvd",
    "sg:city":"Grand Haven",
    "sg:classifiers":[
        {
            "category":"Professional",
            "subcategory":"Employment Agencies",
            "type":"Services"
        }
    ],
    "sg:phone":"+1 616 844 6666",
    "sg:postcode":"49417",
    "sg:province":"MI",
    "sg:tags":[
        "opportunity"
    ],
    "wof:name":"Employment Solutions",
    "wof:placetype":"venue"
},
  "geometry": {"coordinates":[-86.220073,43.051692],"type":"Point"}
}