{
  "type": "Feature",
  "properties": {
    "iso:country":"US",
    "sg:address":"2725 Fort St",
    "sg:city":"Wyandotte",
    "sg:classifiers":[
        {
            "category":"Retail",
            "subcategory":"Repair Shop",
            "type":"Services"
        }
    ],
    "sg:phone":"+1 734 282 4488",
    "sg:postcode":"48192",
    "sg:province":"MI",
    "sg:tags":[
        "reupholstery",
        "furniture"
    ],
    "wof:name":"Young's Upholstery",
    "wof:placetype":"venue"
},
  "geometry": {"coordinates":[-83.180199,42.206699],"type":"Point"}
}