{
  "type": "Feature",
  "properties": {
    "iso:country":"US",
    "sg:address":"7180 N Dort Hwy",
    "sg:city":"Mt Morris",
    "sg:classifiers":[
        {
            "category":"Wholesale",
            "subcategory":"Motor Vehicles",
            "type":"Manufacturing & Wholesale Goods"
        }
    ],
    "sg:phone":"+1 810 564 2825",
    "sg:postcode":"48458",
    "sg:province":"MI",
    "sg:tags":[
        "auction",
        "automobile"
    ],
    "wof:name":"Manheim's",
    "wof:placetype":"venue"
},
  "geometry": {"coordinates":[-83.676001,43.117742],"type":"Point"}
}