{
  "type": "Feature",
  "properties": {
    "iso:country":"US",
    "sg:address":"116 Tecumseh St",
    "sg:city":"Dundee",
    "sg:classifiers":[
        {
            "category":"Professional",
            "subcategory":"Accounting & Tax Preparation",
            "type":"Services"
        }
    ],
    "sg:phone":"+1 734 529 2497",
    "sg:postcode":"48131",
    "sg:province":"MI",
    "sg:tags":[
        "return"
    ],
    "wof:name":"H & R Block",
    "wof:placetype":"venue"
},
  "geometry": {"coordinates":[-83.660573,41.957452],"type":"Point"}
}