{
  "type": "Feature",
  "properties": {
    "iso:country":"US",
    "sg:address":"21532 Schoenherr Rd",
    "sg:city":"Warren",
    "sg:classifiers":[
        {
            "category":"Professional",
            "subcategory":"Lawyer & Legal Services",
            "type":"Services"
        }
    ],
    "sg:phone":"+1 586 778 9124",
    "sg:postcode":"48089",
    "sg:province":"MI",
    "wof:name":"Awada Mark N Law Office of",
    "wof:placetype":"venue"
},
  "geometry": {"coordinates":[-82.985707,42.455194],"type":"Point"}
}