{
  "type": "Feature",
  "properties": {
    "iso:country":"US",
    "sg:address":"21659 Sheffield Dr",
    "sg:city":"Farmington Hills",
    "sg:classifiers":[
        {
            "category":"Freight",
            "type":"Transportation"
        }
    ],
    "sg:phone":"+1 248 442 2323",
    "sg:postcode":"48335",
    "sg:province":"MI",
    "sg:tags":[
        "cartage",
        "trucking"
    ],
    "wof:name":"Transtec Corp",
    "wof:placetype":"venue"
},
  "geometry": {"coordinates":[-83.409612,42.448666],"type":"Point"}
}