{
  "type": "Feature",
  "properties": {
    "iso:country":"US",
    "sg:address":"1591 E Hastings Lake Rd",
    "sg:city":"Jonesville",
    "sg:classifiers":[
        {
            "category":"Organizations",
            "subcategory":"Community Association",
            "type":"Services"
        }
    ],
    "sg:phone":"+1 517 849 2225",
    "sg:postcode":"49250",
    "sg:province":"MI",
    "wof:name":"Jonesville Riverfest Committee",
    "wof:placetype":"venue"
},
  "geometry": {"coordinates":[-84.625615,42.029131],"type":"Point"}
}