{
  "type": "Feature",
  "properties": {
    "iso:country":"US",
    "sg:address":"31300 Northwestern Hwy",
    "sg:city":"Farmington Hills",
    "sg:classifiers":[
        {
            "category":"Professional",
            "subcategory":"Lawyer & Legal Services",
            "type":"Services"
        }
    ],
    "sg:phone":"+1 248 865 8810",
    "sg:postcode":"48334",
    "sg:province":"MI",
    "wof:name":"Imami Shaheen I",
    "wof:placetype":"venue"
},
  "geometry": {"coordinates":[-83.336197,42.516998],"type":"Point"}
}