{
  "type": "Feature",
  "properties": {
    "iso:country":"US",
    "sg:address":"1481 S Burdick St",
    "sg:city":"Kalamazoo",
    "sg:classifiers":[
        {
            "category":"Building & Trades",
            "subcategory":"Construction",
            "type":"Services"
        }
    ],
    "sg:phone":"+1 269 385 4348",
    "sg:postcode":"49001",
    "sg:province":"MI",
    "sg:tags":[
        "general",
        "contractor"
    ],
    "wof:name":"Homeperfect",
    "wof:placetype":"venue"
},
  "geometry": {"coordinates":[-85.582893,42.277379],"type":"Point"}
}