{
  "type": "Feature",
  "properties": {
    "iso:country":"US",
    "sg:address":"4141 Laurence Ave",
    "sg:city":"Allen Park",
    "sg:classifiers":[
        {
            "category":"Social Services",
            "subcategory":"Child Care",
            "type":"Services"
        },
        {
            "category":"Education",
            "subcategory":"Preschool",
            "type":"Public Place"
        },
        {
            "category":"Education",
            "subcategory":"School",
            "type":"Public Place"
        }
    ],
    "sg:phone":"+1 313 382 2777",
    "sg:postcode":"48101",
    "sg:province":"MI",
    "sg:tags":[
        "elementary",
        "day"
    ],
    "sg:website":"www.montessorichildcenter.com",
    "wof:name":"Montessori Children's Center of Allen Pk",
    "wof:placetype":"venue"
},
  "geometry": {"coordinates":[-83.19259599999999,42.269901],"type":"Point"}
}