{
  "type": "Feature",
  "properties": {
    "iso:country":"US",
    "sg:address":"12130 Hogan Rd",
    "sg:city":"Gaines",
    "sg:classifiers":[
        {
            "category":"Building & Trades",
            "subcategory":"Construction",
            "type":"Services"
        }
    ],
    "sg:phone":"+1 810 735 1225",
    "sg:postcode":"48436",
    "sg:province":"MI",
    "sg:tags":[
        "residential",
        "property",
        "ownership"
    ],
    "wof:name":"Miller Homes Inc",
    "wof:placetype":"venue"
},
  "geometry": {"coordinates":[-83.80346400000001,42.851712],"type":"Point"}
}