{
  "type": "Feature",
  "properties": {
    "iso:country":"US",
    "sg:address":"2859 Industrial Row Dr",
    "sg:city":"Troy",
    "sg:classifiers":[
        {
            "category":"Autos & Motor Vehicles",
            "subcategory":"Auto Supplies",
            "type":"Retail Goods"
        }
    ],
    "sg:phone":"+1 248 435 0269",
    "sg:postcode":"48084",
    "sg:province":"MI",
    "sg:tags":[
        "equipment",
        "racing",
        "car",
        "automobile"
    ],
    "wof:name":"Ram Power",
    "wof:placetype":"venue"
},
  "geometry": {"coordinates":[-83.18365300000001,42.540707],"type":"Point"}
}