{
  "type": "Feature",
  "properties": {
    "iso:country":"US",
    "sg:address":"2175 Howard Rd",
    "sg:city":"Petoskey",
    "sg:classifiers":[
        {
            "category":"Retail",
            "subcategory":"Auto Repair",
            "type":"Services"
        }
    ],
    "sg:phone":"+1 231 347 8545",
    "sg:postcode":"49770",
    "sg:province":"MI",
    "sg:tags":[
        "repairing",
        "automobile",
        "general"
    ],
    "wof:name":"Bill's Auto Clinic",
    "wof:placetype":"venue"
},
  "geometry": {"coordinates":[-84.955585,45.347097],"type":"Point"}
}