{
  "type": "Feature",
  "properties": {
    "iso:country":"US",
    "sg:address":"1702 Barlow St",
    "sg:city":"Traverse City",
    "sg:classifiers":[
        {
            "category":"Building & Trades",
            "subcategory":"Construction",
            "type":"Services"
        }
    ],
    "sg:phone":"+1 231 947 0085",
    "sg:postcode":"49686",
    "sg:province":"MI",
    "sg:tags":[
        "house"
    ],
    "wof:name":"Fields Construction",
    "wof:placetype":"venue"
},
  "geometry": {"coordinates":[-85.605639,44.736938],"type":"Point"}
}