{
  "type": "Feature",
  "properties": {
    "iso:country":"US",
    "sg:address":"15378 Middlebelt Rd",
    "sg:city":"Livonia",
    "sg:classifiers":[
        {
            "category":"Fast Food",
            "type":"Food & Drink"
        }
    ],
    "sg:phone":"+1 734 427 9740",
    "sg:postcode":"48154",
    "sg:province":"MI",
    "sg:tags":[
        "burger"
    ],
    "sg:website":"www.burgerking.com",
    "wof:name":"Burger King",
    "wof:placetype":"venue"
},
  "geometry": {"coordinates":[-83.334396,42.3997],"type":"Point"}
}