{
  "type": "Feature",
  "properties": {
    "iso:country":"US",
    "sg:address":"1111 W Michigan Ave",
    "sg:city":"Clinton",
    "sg:classifiers":[
        {
            "category":"Retail",
            "subcategory":"Auto Rental",
            "type":"Services"
        }
    ],
    "sg:phone":"+1 517 456 7888",
    "sg:postcode":"49236",
    "sg:province":"MI",
    "sg:tags":[
        "renting",
        "automobile"
    ],
    "wof:name":"Enterprise Rent-A-Car",
    "wof:placetype":"venue"
},
  "geometry": {"coordinates":[-83.980153,42.071612],"type":"Point"}
}