{
  "type": "Feature",
  "properties": {
    "iso:country":"US",
    "sg:address":"44287 Merrill Rd",
    "sg:city":"Sterling Heights",
    "sg:classifiers":[
        {
            "category":"Professional",
            "subcategory":"Computer Services",
            "type":"Services"
        }
    ],
    "sg:phone":"+1 586 323 2004",
    "sg:postcode":"48314",
    "sg:province":"MI",
    "sg:tags":[
        "related"
    ],
    "wof:name":"Wisdom Computer Services",
    "wof:placetype":"venue"
},
  "geometry": {"coordinates":[-83.046921,42.619524],"type":"Point"}
}