{
  "type": "Feature",
  "properties": {
    "iso:country":"US",
    "sg:address":"37039 Ladywood",
    "sg:city":"Livonia",
    "sg:classifiers":[
        {
            "category":"Building & Trades",
            "subcategory":"Landscaping Services",
            "type":"Services"
        }
    ],
    "sg:phone":"+1 248 736 2019",
    "sg:postcode":"48154",
    "sg:province":"MI",
    "wof:name":"BPI Lawn Care",
    "wof:placetype":"venue"
},
  "geometry": {"coordinates":[-83.40943,42.401468],"type":"Point"}
}