{
  "type": "Feature",
  "properties": {
    "iso:country":"US",
    "sg:address":"5312 Grand River Dr NE",
    "sg:city":"Grand Rapids",
    "sg:classifiers":[
        {
            "category":"Retail",
            "subcategory":"Animal Services",
            "type":"Services"
        }
    ],
    "sg:phone":"+1 616 361 6303",
    "sg:postcode":"49525",
    "sg:province":"MI",
    "wof:name":"Carols Critters Lots of Love",
    "wof:placetype":"venue"
},
  "geometry": {"coordinates":[-85.58420599999999,43.05351],"type":"Point"}
}