{
  "type": "Feature",
  "properties": {
    "iso:country":"US",
    "sg:address":"1006 W Huron Ave",
    "sg:city":"Vassar",
    "sg:classifiers":[
        {
            "category":"Personal",
            "subcategory":"Tanning Parlor",
            "type":"Services"
        }
    ],
    "sg:phone":"+1 989 823 7662",
    "sg:postcode":"48768",
    "sg:province":"MI",
    "sg:tags":[
        "salon"
    ],
    "wof:name":"Golden Image",
    "wof:placetype":"venue"
},
  "geometry": {"coordinates":[-83.593065,43.373687],"type":"Point"}
}