{
  "type": "Feature",
  "properties": {
    "iso:country":"US",
    "sg:address":"24462 Sorrentino Ct",
    "sg:city":"Clinton Twp",
    "sg:classifiers":[
        {
            "category":"Manufacturing",
            "subcategory":"Metals",
            "type":"Manufacturing & Wholesale Goods"
        }
    ],
    "sg:phone":"+1 586 790 4060",
    "sg:postcode":"48035",
    "sg:province":"MI",
    "sg:tags":[
        "fabricator",
        "sheet"
    ],
    "wof:name":"Beck Industries Inc",
    "wof:placetype":"venue"
},
  "geometry": {"coordinates":[-82.865095,42.554513],"type":"Point"}
}