{
  "type": "Feature",
  "properties": {
    "iso:country":"US",
    "sg:address":"148 Maple Cir",
    "sg:city":"Climax",
    "sg:classifiers":[
        {
            "category":"Wholesale",
            "subcategory":"Machinery & Supplies",
            "type":"Manufacturing & Wholesale Goods"
        }
    ],
    "sg:phone":"+1 269 746 4699",
    "sg:postcode":"49034",
    "sg:province":"MI",
    "sg:tags":[
        "equipment",
        "hydraulic"
    ],
    "wof:name":"Cuyler Gerald-Energy",
    "wof:placetype":"venue"
},
  "geometry": {"coordinates":[-85.326937,42.2405],"type":"Point"}
}