{
  "type": "Feature",
  "properties": {
    "iso:country":"US",
    "sg:address":"6706 W Dewey Rd",
    "sg:city":"Ludington",
    "sg:classifiers":[
        {
            "category":"Building & Trades",
            "subcategory":"Construction",
            "type":"Services"
        }
    ],
    "sg:phone":"+1 231 845 5092",
    "sg:postcode":"49431",
    "sg:province":"MI",
    "sg:tags":[
        "house"
    ],
    "wof:name":"Engel Construction",
    "wof:placetype":"venue"
},
  "geometry": {"coordinates":[-86.447891,44.02164],"type":"Point"}
}