{
  "type": "Feature",
  "properties": {
    "iso:country":"US",
    "sg:address":"1914 Cobb Ave",
    "sg:city":"Kalamazoo",
    "sg:classifiers":[
        {
            "category":"Organizations",
            "subcategory":"Non-profit Organization",
            "type":"Services"
        }
    ],
    "sg:phone":"+1 269 978 1188",
    "sg:postcode":"49007",
    "sg:province":"MI",
    "sg:tags":[
        "human"
    ],
    "wof:name":"Kalamazoo County Human Svc",
    "wof:placetype":"venue"
},
  "geometry": {"coordinates":[-85.594804,42.307929],"type":"Point"}
}