{
  "type": "Feature",
  "properties": {
    "iso:country":"US",
    "sg:address":"20021 Kelly Rd",
    "sg:city":"Harper Woods",
    "sg:classifiers":[
        {
            "category":"Professional",
            "subcategory":"Accounting & Tax Preparation",
            "type":"Services"
        }
    ],
    "sg:phone":"+1 313 371 1210",
    "sg:postcode":"48225",
    "sg:province":"MI",
    "sg:tags":[
        "return"
    ],
    "wof:name":"K & S Tax Service",
    "wof:placetype":"venue"
},
  "geometry": {"coordinates":[-82.945798,42.444617],"type":"Point"}
}