{
  "type": "Feature",
  "properties": {
    "iso:country":"US",
    "sg:address":"1012 Elmsford Dr",
    "sg:city":"Troy",
    "sg:classifiers":[
        {
            "category":"Building & Trades",
            "subcategory":"Pest Control",
            "type":"Services"
        }
    ],
    "sg:phone":"+1 248 583 0548",
    "sg:postcode":"48083",
    "sg:province":"MI",
    "sg:website":"www.organicpestcontrolmichigan.com",
    "wof:name":"American Pest Control",
    "wof:placetype":"venue"
},
  "geometry": {"coordinates":[-83.13069900000001,42.541901],"type":"Point"}
}