{
  "type": "Feature",
  "properties": {
    "iso:country":"US",
    "sg:address":"424 Cottage Grove St SE",
    "sg:city":"Grand Rapids",
    "sg:classifiers":[
        {
            "category":"Professional",
            "type":"Services"
        }
    ],
    "sg:phone":"+1 616 243 4507",
    "sg:postcode":"49507",
    "sg:province":"MI",
    "sg:tags":[
        "establishment"
    ],
    "wof:name":"Multi-Tech Precision",
    "wof:placetype":"venue"
},
  "geometry": {"coordinates":[-85.65792999999999,42.935479],"type":"Point"}
}