{
  "type": "Feature",
  "properties": {
    "iso:country":"US",
    "sg:address":"1177 Tihart Rd",
    "sg:city":"Okemos",
    "sg:classifiers":[
        {
            "category":"Shopping",
            "subcategory":"Bicycles & Sporting Goods",
            "type":"Retail Goods"
        }
    ],
    "sg:phone":"+1 517 339 2700",
    "sg:postcode":"48864",
    "sg:province":"MI",
    "sg:tags":[
        "saddlery",
        "harness"
    ],
    "wof:name":"Stable-Mate",
    "wof:placetype":"venue"
},
  "geometry": {"coordinates":[-84.386494,42.733671],"type":"Point"}
}