{
  "type": "Feature",
  "properties": {
    "iso:country":"US",
    "sg:address":"3234 Lake Dr",
    "sg:city":"Highland",
    "sg:classifiers":[
        {
            "category":"Manufacturing",
            "subcategory":"Textiles",
            "type":"Manufacturing & Wholesale Goods"
        }
    ],
    "sg:phone":"+1 248 887 8779",
    "sg:postcode":"48356",
    "sg:province":"MI",
    "sg:tags":[
        "mill",
        "fabric"
    ],
    "wof:name":"Flannelrama",
    "wof:placetype":"venue"
},
  "geometry": {"coordinates":[-83.570536,42.658568],"type":"Point"}
}