{
  "type": "Feature",
  "properties": {
    "iso:country":"US",
    "sg:address":"24505 Meadowbrook Rd",
    "sg:city":"Novi",
    "sg:classifiers":[
        {
            "category":"Organizations",
            "subcategory":"Religious Organization",
            "type":"Services"
        }
    ],
    "sg:phone":"+1 248 349 8847",
    "sg:postcode":"48375",
    "sg:province":"MI",
    "wof:name":"Church of Holy Family",
    "wof:placetype":"venue"
},
  "geometry": {"coordinates":[-83.455367,42.47002],"type":"Point"}
}