{
  "type": "Feature",
  "properties": {
    "iso:country":"US",
    "sg:address":"19427 Birchridge St",
    "sg:city":"Southfield",
    "sg:classifiers":[
        {
            "category":"Wholesale",
            "subcategory":"Computers",
            "type":"Manufacturing & Wholesale Goods"
        }
    ],
    "sg:phone":"+1 248 356 2629",
    "sg:postcode":"48075",
    "sg:province":"MI",
    "sg:tags":[
        "consulting",
        "business"
    ],
    "wof:name":"U S Graphic Arts Inc",
    "wof:placetype":"venue"
},
  "geometry": {"coordinates":[-83.23123200000001,42.455602],"type":"Point"}
}