{
  "type": "Feature",
  "properties": {
    "iso:country":"US",
    "sg:address":"5002 S Clinton St",
    "sg:city":"Stockbridge",
    "sg:classifiers":[
        {
            "category":"Shopping",
            "type":"Retail Goods"
        }
    ],
    "sg:phone":"+1 517 851 7355",
    "sg:postcode":"49285",
    "sg:province":"MI",
    "sg:tags":[
        "wedding",
        "supply"
    ],
    "wof:name":"Stockbridge Floral",
    "wof:placetype":"venue"
},
  "geometry": {"coordinates":[-84.180053,42.435763],"type":"Point"}
}