{
  "type": "Feature",
  "properties": {
    "iso:country":"US",
    "sg:address":"3890 Charlevoix Ave",
    "sg:city":"Petoskey",
    "sg:classifiers":[
        {
            "category":"Building & Trades",
            "subcategory":"Construction",
            "type":"Services"
        }
    ],
    "sg:phone":"+1 231 347 7594",
    "sg:postcode":"49770",
    "sg:province":"MI",
    "sg:tags":[
        "roofing",
        "contractor"
    ],
    "wof:name":"Bayside Roofing Inc",
    "wof:placetype":"venue"
},
  "geometry": {"coordinates":[-85.022425,45.360942],"type":"Point"}
}