{
  "type": "Feature",
  "properties": {
    "iso:country":"US",
    "sg:address":"1601 E Michigan Ave",
    "sg:city":"Jackson",
    "sg:classifiers":[
        {
            "category":"Food & Beverages",
            "subcategory":"Groceries & Convenience Stores",
            "type":"Retail Goods"
        }
    ],
    "sg:phone":"+1 517 768 9006",
    "sg:postcode":"49202",
    "sg:province":"MI",
    "wof:name":"Buddy's Mini Mart Inc",
    "wof:placetype":"venue"
},
  "geometry": {"coordinates":[-84.38314699999999,42.251633],"type":"Point"}
}