{
  "type": "Feature",
  "properties": {
    "iso:country":"US",
    "sg:address":"5649 S Greenville Rd",
    "sg:city":"Greenville",
    "sg:classifiers":[
        {
            "category":"Organizations",
            "subcategory":"Community Association",
            "type":"Services"
        }
    ],
    "sg:phone":"+1 616 754 8115",
    "sg:postcode":"48838",
    "sg:province":"MI",
    "sg:tags":[
        "fraternal"
    ],
    "wof:name":"Loyal Order Of Moose",
    "wof:placetype":"venue"
},
  "geometry": {"coordinates":[-85.25262499999999,43.211473],"type":"Point"}
}