{
  "type": "Feature",
  "properties": {
    "iso:country":"US",
    "sg:address":"1926 Virginia Park St",
    "sg:city":"Detroit",
    "sg:classifiers":[
        {
            "category":"Organizations",
            "subcategory":"Religious Organization",
            "type":"Services"
        }
    ],
    "sg:phone":"+1 313 895 6442",
    "sg:postcode":"48206",
    "sg:province":"MI",
    "wof:name":"Grace Episcopal Church",
    "wof:placetype":"venue"
},
  "geometry": {"coordinates":[-83.09840199999999,42.368727],"type":"Point"}
}