{
  "type": "Feature",
  "properties": {
    "iso:country":"US",
    "sg:address":"5029 Esta Dr",
    "sg:city":"Flint",
    "sg:classifiers":[
        {
            "category":"Freight",
            "type":"Transportation"
        }
    ],
    "sg:phone":"+1 810 736 5163",
    "sg:postcode":"48506",
    "sg:province":"MI",
    "sg:tags":[
        "operator",
        "local",
        "trucking"
    ],
    "wof:name":"Fhs Trucking",
    "wof:placetype":"venue"
},
  "geometry": {"coordinates":[-83.615061,43.062667],"type":"Point"}
}