{
  "type": "Feature",
  "properties": {
    "iso:country":"US",
    "sg:address":"45114 Ford Rd",
    "sg:city":"Canton",
    "sg:classifiers":[
        {
            "category":"Restaurant",
            "type":"Food & Drink"
        }
    ],
    "sg:phone":"+1 734 459 9740",
    "sg:postcode":"48187",
    "sg:province":"MI",
    "wof:name":"Burger King Restaurants",
    "wof:placetype":"venue"
},
  "geometry": {"coordinates":[-83.485703,42.322102],"type":"Point"}
}