{
  "type": "Feature",
  "properties": {
    "iso:country":"US",
    "sg:address":"25860 Yale St",
    "sg:city":"Inkster",
    "sg:classifiers":[
        {
            "category":"Social Services",
            "subcategory":"Child Care",
            "type":"Services"
        }
    ],
    "sg:phone":"+1 313 274 0323",
    "sg:postcode":"48141",
    "sg:province":"MI",
    "sg:tags":[
        "home",
        "day"
    ],
    "wof:name":"Linda Lee Jones",
    "wof:placetype":"venue"
},
  "geometry": {"coordinates":[-83.29328099999999,42.28855],"type":"Point"}
}