{
  "type": "Feature",
  "properties": {
    "iso:country":"US",
    "sg:address":"37000 Grand River Ave",
    "sg:city":"Farmington",
    "sg:classifiers":[
        {
            "category":"Real Estate",
            "subcategory":"Real Estate Services",
            "type":"Services"
        }
    ],
    "sg:phone":"+1 248 427 9055",
    "sg:postcode":"48335",
    "sg:province":"MI",
    "sg:tags":[
        "abstract",
        "title"
    ],
    "wof:name":"Chicago Title",
    "wof:placetype":"venue"
},
  "geometry": {"coordinates":[-83.411655,42.468786],"type":"Point"}
}