{
  "type": "Feature",
  "properties": {
    "iso:country":"US",
    "sg:address":"4163 24th Ave",
    "sg:city":"Fort Gratiot",
    "sg:classifiers":[
        {
            "category":"Home & Garden",
            "subcategory":"Carpets & Floor Coverings",
            "type":"Retail Goods"
        }
    ],
    "sg:phone":"+1 810 385 3800",
    "sg:postcode":"48059",
    "sg:province":"MI",
    "wof:name":"World Of Floors",
    "wof:placetype":"venue"
},
  "geometry": {"coordinates":[-82.45650500000001,43.033901],"type":"Point"}
}