{
  "type": "Feature",
  "properties": {
    "iso:country":"US",
    "sg:address":"718 Grace Ave",
    "sg:city":"Alma",
    "sg:classifiers":[
        {
            "category":"Government",
            "subcategory":"Office",
            "type":"Public Place"
        }
    ],
    "sg:phone":"+1 989 463 1201",
    "sg:postcode":"48801",
    "sg:province":"MI",
    "sg:tags":[
        "county"
    ],
    "wof:name":"Gratiot County Cmh",
    "wof:placetype":"venue"
},
  "geometry": {"coordinates":[-84.64409499999999,43.38415],"type":"Point"}
}