{
  "type": "Feature",
  "properties": {
    "iso:country":"US",
    "sg:address":"12889 N Basell Dr",
    "sg:city":"Hemlock",
    "sg:classifiers":[
        {
            "category":"Professional",
            "subcategory":"Business Services",
            "type":"Services"
        }
    ],
    "sg:phone":"+1 989 642 8555",
    "sg:postcode":"48626",
    "sg:province":"MI",
    "wof:name":"Sounding Board Recording",
    "wof:placetype":"venue"
},
  "geometry": {"coordinates":[-84.16652499999999,43.414634],"type":"Point"}
}