{
  "type": "Feature",
  "properties": {
    "iso:country":"US",
    "sg:address":"812 26th St",
    "sg:city":"Bay City",
    "sg:classifiers":[
        {
            "category":"Manufacturing",
            "subcategory":"Electronics",
            "type":"Manufacturing & Wholesale Goods"
        },
        {
            "category":"Shopping",
            "subcategory":"Computers & Home Electronics",
            "type":"Retail Goods"
        }
    ],
    "sg:phone":"+1 989 892 5856",
    "sg:postcode":"48708",
    "sg:province":"MI",
    "sg:tags":[
        "sound",
        "equipment",
        "system",
        "repair"
    ],
    "wof:name":"Sound State",
    "wof:placetype":"venue"
},
  "geometry": {"coordinates":[-83.889841,43.576569],"type":"Point"}
}