{
  "type": "Feature",
  "properties": {
    "iso:country":"US",
    "sg:address":"26129 W 6 Mile Rd",
    "sg:city":"Redford",
    "sg:classifiers":[
        {
            "category":"Health Services",
            "subcategory":"Doctor",
            "type":"Services"
        }
    ],
    "sg:phone":"+1 313 532 5156",
    "sg:postcode":"48240",
    "sg:province":"MI",
    "sg:tags":[
        "surgeon",
        "oral"
    ],
    "wof:name":"Decapite James W DDS",
    "wof:placetype":"venue"
},
  "geometry": {"coordinates":[-83.300301,42.4137],"type":"Point"}
}