{
  "type": "Feature",
  "properties": {
    "iso:country":"US",
    "sg:address":"1450 Greenbrier Dr",
    "sg:city":"Traverse City",
    "sg:classifiers":[
        {
            "category":"Professional",
            "type":"Services"
        }
    ],
    "sg:phone":"+1 231 941 7265",
    "sg:postcode":"49684",
    "sg:province":"MI",
    "wof:name":"MSP Services",
    "wof:placetype":"venue"
},
  "geometry": {"coordinates":[-85.675462,44.708257],"type":"Point"}
}