{
  "type": "Feature",
  "properties": {
    "iso:country":"US",
    "sg:address":"5291 Mary Ct",
    "sg:city":"Saginaw",
    "sg:classifiers":[
        {
            "category":"Organizations",
            "subcategory":"Religious Organization",
            "type":"Services"
        }
    ],
    "sg:phone":"+1 989 792 9422",
    "sg:postcode":"48603",
    "sg:province":"MI",
    "wof:name":"Saint Thomas Aquinas School",
    "wof:placetype":"venue"
},
  "geometry": {"coordinates":[-84.020884,43.439949],"type":"Point"}
}