{
  "type": "Feature",
  "properties": {
    "iso:country":"US",
    "sg:address":"41808 Ford Rd",
    "sg:city":"Canton",
    "sg:classifiers":[
        {
            "category":"Restaurant",
            "type":"Food & Drink"
        }
    ],
    "sg:phone":"+1 734 844 8000",
    "sg:postcode":"48187",
    "sg:province":"MI",
    "sg:tags":[
        "mexican"
    ],
    "sg:website":"www.tacotime.com/",
    "wof:name":"Taco Time",
    "wof:placetype":"venue"
},
  "geometry": {"coordinates":[-83.453003,42.323002],"type":"Point"}
}