{
  "type": "Feature",
  "properties": {
    "iso:country":"US",
    "sg:address":"109 S Main St",
    "sg:city":"Capac",
    "sg:classifiers":[
        {
            "category":"Professional",
            "subcategory":"Accounting & Tax Preparation",
            "type":"Services"
        }
    ],
    "sg:phone":"+1 810 395 4359",
    "sg:postcode":"48014",
    "sg:province":"MI",
    "sg:tags":[
        "return",
        "filing"
    ],
    "wof:name":"Barb's Bookkeeping & Tax Svc",
    "wof:placetype":"venue"
},
  "geometry": {"coordinates":[-82.92850199999999,43.012496],"type":"Point"}
}