{
  "type": "Feature",
  "properties": {
    "iso:country":"US",
    "sg:address":"8436 Cascade St",
    "sg:city":"Commerce Township",
    "sg:classifiers":[
        {
            "category":"Professional",
            "subcategory":"Management & Consulting",
            "type":"Services"
        }
    ],
    "sg:phone":"+1 248 756 4510",
    "sg:postcode":"48382",
    "sg:province":"MI",
    "sg:tags":[
        "construction"
    ],
    "wof:name":"Demuyt Kelley Cstm Renovations",
    "wof:placetype":"venue"
},
  "geometry": {"coordinates":[-83.449828,42.614401],"type":"Point"}
}