{
  "type": "Feature",
  "properties": {
    "iso:country":"US",
    "sg:address":"1317 Poplar Ave",
    "sg:city":"Royal Oak",
    "sg:classifiers":[
        {
            "category":"Building & Trades",
            "subcategory":"Cleaning & Sanitation",
            "type":"Services"
        }
    ],
    "sg:phone":"+1 248 280 2026",
    "sg:postcode":"48073",
    "sg:province":"MI",
    "sg:tags":[
        "carpet"
    ],
    "wof:name":"Mr Sweeps Cleaning Services",
    "wof:placetype":"venue"
},
  "geometry": {"coordinates":[-83.160025,42.516426],"type":"Point"}
}