{
  "type": "Feature",
  "properties": {
    "iso:country":"US",
    "sg:address":"228 Abbott Rd",
    "sg:city":"East Lansing",
    "sg:classifiers":[
        {
            "category":"Shopping",
            "subcategory":"Music",
            "type":"Retail Goods"
        }
    ],
    "sg:phone":"+1 517 351 2636",
    "sg:postcode":"48823",
    "sg:province":"MI",
    "sg:tags":[
        "compact",
        "record",
        "disc",
        "tape"
    ],
    "wof:name":"CD Warehouse",
    "wof:placetype":"venue"
},
  "geometry": {"coordinates":[-84.483693,42.73553],"type":"Point"}
}