{
  "type": "Feature",
  "properties": {
    "iso:country":"US",
    "sg:address":"166 Welcome Rd",
    "sg:city":"Hastings",
    "sg:classifiers":[
        {
            "category":"Utilities",
            "subcategory":"Refuse",
            "type":"Services"
        }
    ],
    "sg:phone":"+1 269 948 9206",
    "sg:postcode":"49058",
    "sg:province":"MI",
    "sg:tags":[
        "garbage",
        "collection"
    ],
    "wof:name":"Jim's Pickup Svc",
    "wof:placetype":"venue"
},
  "geometry": {"coordinates":[-85.283745,42.697882],"type":"Point"}
}