{
  "type": "Feature",
  "properties": {
    "iso:country":"US",
    "sg:address":"138 S Front St",
    "sg:city":"Dowagiac",
    "sg:classifiers":[
        {
            "category":"Shopping",
            "subcategory":"Clothing, Apparel, & Fashions",
            "type":"Retail Goods"
        }
    ],
    "sg:phone":"+1 269 782 7445",
    "sg:postcode":"49047",
    "sg:province":"MI",
    "wof:name":"Marshall Shoppe",
    "wof:placetype":"venue"
},
  "geometry": {"coordinates":[-86.108108,41.983262],"type":"Point"}
}