{
  "type": "Feature",
  "properties": {
    "iso:country":"US",
    "sg:address":"4649 Elm Dr",
    "sg:city":"Bay City",
    "sg:classifiers":[
        {
            "category":"Professional",
            "subcategory":"Accounting & Tax Preparation",
            "type":"Services"
        }
    ],
    "sg:phone":"+1 989 684 3045",
    "sg:postcode":"48706",
    "sg:province":"MI",
    "sg:tags":[
        "accountant",
        "return"
    ],
    "wof:name":"Oliver Associates 1040",
    "wof:placetype":"venue"
},
  "geometry": {"coordinates":[-83.97064899999999,43.603852],"type":"Point"}
}