{
  "type": "Feature",
  "properties": {
    "iso:country":"US",
    "sg:address":"42446 Ehrke Dr",
    "sg:city":"Clinton Twp",
    "sg:classifiers":[
        {
            "category":"Organizations",
            "subcategory":"Community Association",
            "type":"Services"
        }
    ],
    "sg:phone":"+1 586 286 1814",
    "sg:postcode":"48038",
    "sg:province":"MI",
    "wof:name":"Clinton Valley Little League",
    "wof:placetype":"venue"
},
  "geometry": {"coordinates":[-82.965735,42.605993],"type":"Point"}
}