{
  "type": "Feature",
  "properties": {
    "iso:country":"US",
    "sg:address":"348 S Waverly Rd",
    "sg:city":"Holland",
    "sg:classifiers":[
        {
            "category":"Personal",
            "subcategory":"Hair Removal",
            "type":"Services"
        }
    ],
    "sg:phone":"+1 616 392 2805",
    "sg:postcode":"49423",
    "sg:province":"MI",
    "sg:tags":[
        "consulting",
        "management"
    ],
    "wof:name":"Schreur & Associates Inc",
    "wof:placetype":"venue"
},
  "geometry": {"coordinates":[-86.077656,42.784682],"type":"Point"}
}