{
  "type": "Feature",
  "properties": {
    "iso:country":"US",
    "sg:address":"33310 W 12 Mile Rd",
    "sg:city":"Farmington Hills",
    "sg:classifiers":[
        {
            "category":"Shopping",
            "subcategory":"Gifts & Souvenirs",
            "type":"Retail Goods"
        }
    ],
    "sg:phone":"+1 248 553 7070",
    "sg:postcode":"48334",
    "sg:province":"MI",
    "sg:tags":[
        "stationery",
        "shop",
        "card"
    ],
    "wof:name":"Jeanne's Hallmark Shop",
    "wof:placetype":"venue"
},
  "geometry": {"coordinates":[-83.37690000000001,42.498798],"type":"Point"}
}