{
  "type": "Feature",
  "properties": {
    "iso:country":"US",
    "sg:address":"728 E 8th St",
    "sg:city":"Holland",
    "sg:classifiers":[
        {
            "category":"Insurance",
            "subcategory":"Insurance Agent",
            "type":"Services"
        }
    ],
    "sg:phone":"+1 616 392 2105",
    "sg:postcode":"49423",
    "sg:province":"MI",
    "wof:name":"Buursma Agency",
    "wof:placetype":"venue"
},
  "geometry": {"coordinates":[-86.075225,42.79038],"type":"Point"}
}