{
  "type": "Feature",
  "properties": {
    "iso:country":"US",
    "sg:address":"6784 S 6th St",
    "sg:city":"Kalamazoo",
    "sg:classifiers":[
        {
            "category":"Real Estate",
            "subcategory":"Real Estate Agent",
            "type":"Services"
        }
    ],
    "sg:phone":"+1 269 207 4496",
    "sg:postcode":"49009",
    "sg:province":"MI",
    "sg:tags":[
        "inspection"
    ],
    "sg:website":"www.homeanalysts.com",
    "wof:name":"Home Analysts Inc",
    "wof:placetype":"venue"
},
  "geometry": {"coordinates":[-85.70622400000001,42.219838],"type":"Point"}
}