{
  "type": "Feature",
  "properties": {
    "iso:country":"US",
    "sg:address":"5204 Foxcroft Dr",
    "sg:city":"Kalamazoo",
    "sg:classifiers":[
        {
            "category":"Travel",
            "subcategory":"Travel Agent",
            "type":"Entertainment"
        }
    ],
    "sg:phone":"+1 269 375 9229",
    "sg:postcode":"49009",
    "sg:province":"MI",
    "sg:tags":[
        "agency",
        "bureau"
    ],
    "wof:name":"Mark Of Travel",
    "wof:placetype":"venue"
},
  "geometry": {"coordinates":[-85.653378,42.206195],"type":"Point"}
}