{
  "type": "Feature",
  "properties": {
    "iso:country":"US",
    "sg:address":"35235 Automation Dr",
    "sg:city":"Clinton Twp",
    "sg:classifiers":[
        {
            "category":"Manufacturing",
            "subcategory":"Tools & Machinery",
            "type":"Manufacturing & Wholesale Goods"
        }
    ],
    "sg:phone":"+1 586 790 1430",
    "sg:postcode":"48035",
    "sg:province":"MI",
    "sg:tags":[
        "machine",
        "shop"
    ],
    "wof:name":"Beacon Manufacturing Inc",
    "wof:placetype":"venue"
},
  "geometry": {"coordinates":[-82.883978,42.557367],"type":"Point"}
}