{
  "type": "Feature",
  "properties": {
    "iso:country":"US",
    "sg:address":"3800 S Baldwin Rd",
    "sg:city":"Lake Orion",
    "sg:classifiers":[
        {
            "category":"Food & Beverages",
            "subcategory":"Bakery",
            "type":"Retail Goods"
        }
    ],
    "sg:phone":"+1 248 393 6048",
    "sg:postcode":"48359",
    "sg:province":"MI",
    "sg:tags":[
        "baker"
    ],
    "wof:name":"Great Lakes Bread Co",
    "wof:placetype":"venue"
},
  "geometry": {"coordinates":[-83.307541,42.723855],"type":"Point"}
}