{
  "type": "Feature",
  "properties": {
    "iso:country":"US",
    "sg:address":"4355 Wimbledon Dr",
    "sg:city":"Grandville",
    "sg:classifiers":[
        {
            "category":"Building & Trades",
            "subcategory":"Construction",
            "type":"Services"
        }
    ],
    "sg:phone":"+1 616 532 4247",
    "sg:postcode":"49418",
    "sg:province":"MI",
    "sg:tags":[
        "hanging",
        "contractor"
    ],
    "wof:name":"Walt Henry Painting",
    "wof:placetype":"venue"
},
  "geometry": {"coordinates":[-85.769435,42.881972],"type":"Point"}
}