{
  "type": "Feature",
  "properties": {
    "iso:country":"US",
    "sg:address":"735 Lake St",
    "sg:city":"Saugatuck",
    "sg:classifiers":[
        {
            "category":"Real Estate",
            "subcategory":"Real Estate Agent",
            "type":"Services"
        }
    ],
    "sg:phone":"+1 269 857 7829",
    "sg:postcode":"49453",
    "sg:province":"MI",
    "sg:tags":[
        "management"
    ],
    "wof:name":"Lakeshore Lodging Inc",
    "wof:placetype":"venue"
},
  "geometry": {"coordinates":[-86.196625,42.652237],"type":"Point"}
}