{
  "type": "Feature",
  "properties": {
    "iso:country":"US",
    "sg:address":"4420 E Davison St",
    "sg:city":"Hamtramck",
    "sg:classifiers":[
        {
            "category":"Health Services",
            "subcategory":"Doctor",
            "type":"Services"
        }
    ],
    "sg:phone":"+1 313 369 1500",
    "sg:postcode":"48212",
    "sg:province":"MI",
    "wof:name":"Shrivastava Arunima MD",
    "wof:placetype":"venue"
},
  "geometry": {"coordinates":[-83.05729700000001,42.417],"type":"Point"}
}