{
  "type": "Feature",
  "properties": {
    "iso:country":"US",
    "sg:address":"37050 Emery St",
    "sg:city":"Clinton Twp",
    "sg:classifiers":[
        {
            "category":"Building & Trades",
            "subcategory":"Construction",
            "type":"Services"
        }
    ],
    "sg:phone":"+1 586 783 7500",
    "sg:postcode":"48036",
    "sg:province":"MI",
    "sg:tags":[
        "restoration",
        "cleaning",
        "patio",
        "deck"
    ],
    "wof:name":"Supreme Power Cleaning Inc",
    "wof:placetype":"venue"
},
  "geometry": {"coordinates":[-82.909235,42.570168],"type":"Point"}
}