{
  "type": "Feature",
  "properties": {
    "iso:country":"US",
    "sg:address":"5963 E 14 Mile Rd",
    "sg:city":"Sterling Heights",
    "sg:classifiers":[
        {
            "category":"Professional",
            "subcategory":"Computer Services",
            "type":"Services"
        }
    ],
    "sg:phone":"+1 586 939 4660",
    "sg:postcode":"48312",
    "sg:province":"MI",
    "sg:website":"www.cellularadvantageinc.com",
    "wof:name":"Cellular Advantage",
    "wof:placetype":"venue"
},
  "geometry": {"coordinates":[-83.043558,42.536337],"type":"Point"}
}