{
  "type": "Feature",
  "properties": {
    "iso:country":"US",
    "sg:address":"22178 W 9 Mile Rd",
    "sg:city":"Southfield",
    "sg:classifiers":[
        {
            "category":"Professional",
            "subcategory":"Management & Consulting",
            "type":"Services"
        }
    ],
    "sg:phone":"+1 248 352 4830",
    "sg:postcode":"48033",
    "sg:province":"MI",
    "sg:tags":[
        "consultant",
        "business"
    ],
    "wof:name":"Su-Pra Enterprises Inc",
    "wof:placetype":"venue"
},
  "geometry": {"coordinates":[-83.26008299999999,42.457857],"type":"Point"}
}