{
  "type": "Feature",
  "properties": {
    "iso:country":"US",
    "sg:address":"22506 Lawrence Ave",
    "sg:city":"Dearborn",
    "sg:classifiers":[
        {
            "category":"Professional",
            "subcategory":"Lawyer & Legal Services",
            "type":"Services"
        }
    ],
    "sg:phone":"+1 313 963 8524",
    "sg:postcode":"48128",
    "sg:province":"MI",
    "wof:name":"Law Office of Scott-Meisel Pllc",
    "wof:placetype":"venue"
},
  "geometry": {"coordinates":[-83.258821,42.323667],"type":"Point"}
}