{
  "type": "Feature",
  "properties": {
    "iso:country":"US",
    "sg:address":"100 Renaissance Center Level A, SteA106",
    "sg:city":"Detroit",
    "sg:classifiers":[
        {
            "category":"Restaurant",
            "type":"Food & Drink"
        }
    ],
    "sg:phone":"+1 313 567 3701",
    "sg:postcode":"48243",
    "sg:province":"MI",
    "sg:tags":[
        "mexican"
    ],
    "sg:website":"www.salsaritas.com",
    "wof:name":"Salsarita's Fresh Cantina",
    "wof:placetype":"venue"
},
  "geometry": {"coordinates":[-83.039232,42.330369],"type":"Point"}
}