{
  "type": "Feature",
  "properties": {
    "iso:country":"US",
    "sg:address":"27934 Glenwood St",
    "sg:city":"St Clair Shores",
    "sg:classifiers":[
        {
            "category":"Professional",
            "subcategory":"Accounting & Tax Preparation",
            "type":"Services"
        }
    ],
    "sg:phone":"+1 586 771 3561",
    "sg:postcode":"48081",
    "sg:province":"MI",
    "sg:tags":[
        "bookkeeping",
        "general"
    ],
    "wof:name":"Gogolin Bookkeeping",
    "wof:placetype":"venue"
},
  "geometry": {"coordinates":[-82.898971,42.497564],"type":"Point"}
}