{
  "type": "Feature",
  "properties": {
    "iso:country":"US",
    "sg:address":"10001 Burgess Ct",
    "sg:city":"White Lake",
    "sg:classifiers":[
        {
            "category":"Building & Trades",
            "subcategory":"Landscaping Services",
            "type":"Services"
        }
    ],
    "sg:phone":"+1 248 698 4232",
    "sg:postcode":"48386",
    "sg:province":"MI",
    "wof:name":"Joes Lawn Serv & Property",
    "wof:placetype":"venue"
},
  "geometry": {"coordinates":[-83.484577,42.634169],"type":"Point"}
}