{
  "type": "Feature",
  "properties": {
    "iso:country":"US",
    "sg:address":"11731 Marion",
    "sg:city":"Redford",
    "sg:classifiers":[
        {
            "category":"Professional",
            "type":"Services"
        }
    ],
    "sg:phone":"+1 313 937 3599",
    "sg:postcode":"48239",
    "sg:province":"MI",
    "wof:name":"Lynch Machine LLC",
    "wof:placetype":"venue"
},
  "geometry": {"coordinates":[-83.292642,42.372938],"type":"Point"}
}