{
  "type": "Feature",
  "properties": {
    "iso:country":"US",
    "sg:address":"3715 Gardner Ave",
    "sg:city":"Berkley",
    "sg:classifiers":[
        {
            "category":"Shopping",
            "type":"Retail Goods"
        }
    ],
    "sg:phone":"+1 248 398 2907",
    "sg:postcode":"48072",
    "sg:province":"MI",
    "sg:tags":[
        "fund",
        "games",
        "merchandise",
        "raising",
        "supply"
    ],
    "wof:name":"Jimmy Dykes Scholarship Fund Inc",
    "wof:placetype":"venue"
},
  "geometry": {"coordinates":[-83.19184300000001,42.505748],"type":"Point"}
}