{
  "type": "Feature",
  "properties": {
    "iso:country":"US",
    "sg:address":"8188 Jordan Rd",
    "sg:city":"Melvin",
    "sg:classifiers":[
        {
            "category":"Social Services",
            "subcategory":"Child Care",
            "type":"Services"
        }
    ],
    "sg:phone":"+1 810 387 3782",
    "sg:postcode":"48454",
    "sg:province":"MI",
    "sg:tags":[
        "day"
    ],
    "wof:name":"Little Sprouts Day Care",
    "wof:placetype":"venue"
},
  "geometry": {"coordinates":[-82.821569,43.179575],"type":"Point"}
}