{
  "type": "Feature",
  "properties": {
    "iso:country":"US",
    "sg:address":"6519 Center St",
    "sg:city":"Ellsworth",
    "sg:classifiers":[
        {
            "category":"Retail",
            "subcategory":"Portrait Studio",
            "type":"Services"
        }
    ],
    "sg:phone":"+1 231 588 2204",
    "sg:postcode":"49729",
    "sg:province":"MI",
    "sg:tags":[
        "photographer"
    ],
    "wof:name":"Imagemakers",
    "wof:placetype":"venue"
},
  "geometry": {"coordinates":[-85.247434,45.165329],"type":"Point"}
}