{
  "type": "Feature",
  "properties": {
    "iso:country":"US",
    "sg:address":"3110 Schuette Rd",
    "sg:city":"Midland",
    "sg:classifiers":[
        {
            "category":"Manufacturing",
            "subcategory":"Chemicals & Compounds",
            "type":"Manufacturing & Wholesale Goods"
        }
    ],
    "sg:phone":"+1 989 496 2016",
    "sg:postcode":"48642",
    "sg:province":"MI",
    "wof:name":"Dendritech Inc",
    "wof:placetype":"venue"
},
  "geometry": {"coordinates":[-84.192183,43.599225],"type":"Point"}
}