{
  "type": "Feature",
  "properties": {
    "iso:country":"US",
    "sg:address":"39319 Plymouth Rd",
    "sg:city":"Livonia",
    "sg:classifiers":[
        {
            "category":"Professional",
            "subcategory":"Lawyer & Legal Services",
            "type":"Services"
        }
    ],
    "sg:phone":"+1 734 591 4890",
    "sg:postcode":"48150",
    "sg:province":"MI",
    "wof:name":"Schneider Charles Law Offices",
    "wof:placetype":"venue"
},
  "geometry": {"coordinates":[-83.42455200000001,42.370572],"type":"Point"}
}