{
  "type": "Feature",
  "properties": {
    "iso:country":"US",
    "sg:address":"1100 Owendale Dr",
    "sg:city":"Troy",
    "sg:classifiers":[
        {
            "category":"Shopping",
            "type":"Retail Goods"
        }
    ],
    "sg:phone":"+1 248 244 9000",
    "sg:postcode":"48083",
    "sg:province":"MI",
    "sg:tags":[
        "foot",
        "appliance"
    ],
    "wof:name":"Fastech Labs",
    "wof:placetype":"venue"
},
  "geometry": {"coordinates":[-83.127551,42.561025],"type":"Point"}
}