{
  "type": "Feature",
  "properties": {
    "iso:country":"US",
    "sg:address":"7050 Eveline",
    "sg:city":"Holly",
    "sg:classifiers":[
        {
            "category":"Food & Beverages",
            "subcategory":"Specialty",
            "type":"Retail Goods"
        }
    ],
    "sg:phone":"+1 248 625 4061",
    "sg:postcode":"48442",
    "sg:province":"MI",
    "sg:tags":[
        "gourmet",
        "shop"
    ],
    "wof:name":"Gourmet Chuckwagon",
    "wof:placetype":"venue"
},
  "geometry": {"coordinates":[-83.59755699999999,42.702075],"type":"Point"}
}