{
  "type": "Feature",
  "properties": {
    "iso:country":"US",
    "sg:address":"1420 Iroquois Pl",
    "sg:city":"Ann Arbor",
    "sg:classifiers":[
        {
            "category":"Professional",
            "subcategory":"Management & Consulting",
            "type":"Services"
        }
    ],
    "sg:phone":"+1 734 662 6272",
    "sg:postcode":"48104",
    "sg:province":"MI",
    "wof:name":"Arbor Training Associates",
    "wof:placetype":"venue"
},
  "geometry": {"coordinates":[-83.73081999999999,42.259696],"type":"Point"}
}