{
  "type": "Feature",
  "properties": {
    "iso:country":"US",
    "sg:address":"401 John St",
    "sg:city":"Kalamazoo",
    "sg:classifiers":[
        {
            "category":"Health Services",
            "subcategory":"Health Practitioner",
            "type":"Services"
        }
    ],
    "sg:phone":"+1 269 341 6400",
    "sg:postcode":"49007",
    "sg:province":"MI",
    "wof:name":"MSU/Kcms Infectious Disease",
    "wof:placetype":"venue"
},
  "geometry": {"coordinates":[-85.58164600000001,42.287667],"type":"Point"}
}