{
  "type": "Feature",
  "properties": {
    "iso:country":"US",
    "sg:address":"2914 Vogue Blvd",
    "sg:city":"Saginaw",
    "sg:classifiers":[
        {
            "category":"Retail",
            "subcategory":"Auto Repair",
            "type":"Services"
        }
    ],
    "sg:phone":"+1 989 790 0855",
    "sg:postcode":"48603",
    "sg:province":"MI",
    "sg:tags":[
        "automotive",
        "exhaust"
    ],
    "wof:name":"Muffler Man",
    "wof:placetype":"venue"
},
  "geometry": {"coordinates":[-83.973257,43.452695],"type":"Point"}
}