{
  "type": "Feature",
  "properties": {
    "iso:country":"US",
    "sg:address":"1500 Avalon St",
    "sg:city":"Midland",
    "sg:classifiers":[
        {
            "category":"Professional",
            "subcategory":"Art Services",
            "type":"Services"
        }
    ],
    "sg:phone":"+1 989 631 8075",
    "sg:postcode":"48642",
    "sg:province":"MI",
    "sg:tags":[
        "photographer"
    ],
    "wof:name":"Photography By David",
    "wof:placetype":"venue"
},
  "geometry": {"coordinates":[-84.209727,43.646569],"type":"Point"}
}