{
  "type": "Feature",
  "properties": {
    "iso:country":"US",
    "sg:address":"288 S Main St",
    "sg:city":"Romeo",
    "sg:classifiers":[
        {
            "category":"Health Services",
            "subcategory":"Health Practitioner",
            "type":"Services"
        }
    ],
    "sg:phone":"+1 586 752 0091",
    "sg:postcode":"48065",
    "sg:province":"MI",
    "sg:tags":[
        "psychologist"
    ],
    "wof:name":"Claude Eggertsen",
    "wof:placetype":"venue"
},
  "geometry": {"coordinates":[-83.013504,42.797994],"type":"Point"}
}