{
  "type": "Feature",
  "properties": {
    "iso:country":"US",
    "sg:address":"1535 Monroe Ave NW",
    "sg:city":"Grand Rapids",
    "sg:classifiers":[
        {
            "category":"Organizations",
            "subcategory":"Community Association",
            "type":"Services"
        }
    ],
    "sg:phone":"+1 616 361 1245",
    "sg:postcode":"49505",
    "sg:province":"MI",
    "sg:tags":[
        "military"
    ],
    "wof:name":"Veterans Of Foreign Wars",
    "wof:placetype":"venue"
},
  "geometry": {"coordinates":[-85.67064999999999,42.99119],"type":"Point"}
}