{
  "type": "Feature",
  "properties": {
    "iso:country":"US",
    "sg:address":"929 E Chicago Rd",
    "sg:city":"Quincy",
    "sg:classifiers":[
        {
            "category":"Autos & Motor Vehicles",
            "subcategory":"Automobile Sales",
            "type":"Retail Goods"
        }
    ],
    "sg:phone":"+1 517 639 4951",
    "sg:postcode":"49082",
    "sg:province":"MI",
    "sg:tags":[
        "car",
        "dealer"
    ],
    "wof:name":"Jack's Direct Market Auto",
    "wof:placetype":"venue"
},
  "geometry": {"coordinates":[-84.90338199999999,41.940942],"type":"Point"}
}