{
  "type": "Feature",
  "properties": {
    "iso:country":"US",
    "sg:address":"29145 Northwestern Hwy",
    "sg:city":"Southfield",
    "sg:classifiers":[
        {
            "category":"Bakery",
            "type":"Food & Drink"
        }
    ],
    "sg:phone":"+1 248 352 8548",
    "sg:postcode":"48034",
    "sg:province":"MI",
    "wof:name":"Star Bakery",
    "wof:placetype":"venue"
},
  "geometry": {"coordinates":[-83.30999799999999,42.501301],"type":"Point"}
}