{
  "type": "Feature",
  "properties": {
    "iso:country":"US",
    "sg:address":"1166 McKinley St",
    "sg:city":"Wyandotte",
    "sg:classifiers":[
        {
            "category":"Real Estate",
            "subcategory":"Real Estate Services",
            "type":"Services"
        }
    ],
    "sg:phone":"+1 734 285 4442",
    "sg:postcode":"48192",
    "sg:province":"MI",
    "sg:tags":[
        "management",
        "property"
    ],
    "wof:name":"K S & Associates Inc",
    "wof:placetype":"venue"
},
  "geometry": {"coordinates":[-83.1546,42.221611],"type":"Point"}
}