{
  "type": "Feature",
  "properties": {
    "iso:country":"US",
    "sg:address":"4230 N Grant Ave",
    "sg:city":"Harrison",
    "sg:classifiers":[
        {
            "category":"Social Services",
            "subcategory":"Child Care",
            "type":"Services"
        }
    ],
    "sg:phone":"+1 989 539 9976",
    "sg:postcode":"48625",
    "sg:province":"MI",
    "sg:tags":[
        "day"
    ],
    "wof:name":"Maria Meranda",
    "wof:placetype":"venue"
},
  "geometry": {"coordinates":[-84.78818800000001,44.048963],"type":"Point"}
}