{
  "type": "Feature",
  "properties": {
    "iso:country":"US",
    "sg:address":"28800 Ryan Rd",
    "sg:city":"Warren",
    "sg:classifiers":[
        {
            "category":"Health Services",
            "subcategory":"Doctor",
            "type":"Services"
        }
    ],
    "sg:phone":"+1 586 558 1100",
    "sg:postcode":"48092",
    "sg:province":"MI",
    "sg:tags":[
        "medical"
    ],
    "wof:name":"University Ctr For Wns Mdicine",
    "wof:placetype":"venue"
},
  "geometry": {"coordinates":[-83.06743,42.505075],"type":"Point"}
}