{
  "type": "Feature",
  "properties": {
    "iso:country":"US",
    "sg:address":"19210 Gloria Dr",
    "sg:city":"Macomb",
    "sg:classifiers":[
        {
            "category":"Manufacturing",
            "subcategory":"Tools & Machinery",
            "type":"Manufacturing & Wholesale Goods"
        }
    ],
    "sg:phone":"+1 586 263 5090",
    "sg:postcode":"48044",
    "sg:province":"MI",
    "sg:tags":[
        "equipment",
        "electric"
    ],
    "wof:name":"American Midwest Power",
    "wof:placetype":"venue"
},
  "geometry": {"coordinates":[-82.929434,42.665275],"type":"Point"}
}