{
  "type": "Feature",
  "properties": {
    "iso:country":"US",
    "sg:address":"8470 State Hwy 119",
    "sg:city":"Harbor Springs",
    "sg:classifiers":[
        {
            "category":"Professional",
            "subcategory":"Business Services",
            "type":"Services"
        }
    ],
    "sg:phone":"+1 231 348 1010",
    "sg:postcode":"49740",
    "sg:province":"MI",
    "wof:name":"Postal Connection",
    "wof:placetype":"venue"
},
  "geometry": {"coordinates":[-85.00693099999999,45.431501],"type":"Point"}
}