{
  "type": "Feature",
  "properties": {
    "iso:country":"US",
    "sg:address":"9028 N Irish Rd",
    "sg:city":"Mount Morris",
    "sg:classifiers":[
        {
            "category":"Retail",
            "subcategory":"Auto Repair",
            "type":"Services"
        }
    ],
    "sg:phone":"+1 810 631 4265",
    "sg:postcode":"48463",
    "sg:province":"MI",
    "sg:tags":[
        "body"
    ],
    "wof:name":"Premium Auto Painters",
    "wof:placetype":"venue"
},
  "geometry": {"coordinates":[-83.55854600000001,43.15086],"type":"Point"}
}