{
  "type": "Feature",
  "properties": {
    "iso:country":"US",
    "sg:address":"930 S University Ave",
    "sg:city":"Ann Arbor",
    "sg:classifiers":[
        {
            "category":"Education",
            "subcategory":"Special Training",
            "type":"Public Place"
        }
    ],
    "sg:phone":"+1 734 763 6148",
    "sg:postcode":"48104",
    "sg:province":"MI",
    "sg:tags":[
        "dept",
        "chemistry"
    ],
    "wof:name":"Chemistry Department",
    "wof:placetype":"venue"
},
  "geometry": {"coordinates":[-83.74068699999999,42.274947],"type":"Point"}
}