{
  "type": "Feature",
  "properties": {
    "iso:country":"US",
    "sg:address":"1981 S Cochran Ave",
    "sg:city":"Charlotte",
    "sg:classifiers":[
        {
            "category":"Manufacturing",
            "subcategory":"Paper Products",
            "type":"Manufacturing & Wholesale Goods"
        }
    ],
    "sg:phone":"+1 517 543 7566",
    "sg:postcode":"48813",
    "sg:province":"MI",
    "sg:tags":[
        "bag"
    ],
    "wof:name":"Bags Paper & More",
    "wof:placetype":"venue"
},
  "geometry": {"coordinates":[-84.83577099999999,42.538949],"type":"Point"}
}