{
  "type": "Feature",
  "properties": {
    "iso:country":"US",
    "sg:address":"126 32nd St SW",
    "sg:city":"Grand Rapids",
    "sg:classifiers":[
        {
            "category":"Wholesale",
            "subcategory":"Groceries",
            "type":"Manufacturing & Wholesale Goods"
        }
    ],
    "sg:phone":"+1 616 452 7979",
    "sg:postcode":"49548",
    "sg:province":"MI",
    "sg:tags":[
        "honey"
    ],
    "wof:name":"Al Haarsma Honey Products",
    "wof:placetype":"venue"
},
  "geometry": {"coordinates":[-85.66947500000001,42.905816],"type":"Point"}
}