{
  "type": "Feature",
  "properties": {
    "iso:country":"US",
    "sg:address":"4433 W Saginaw Hwy",
    "sg:city":"Lansing",
    "sg:classifiers":[
        {
            "category":"Building & Trades",
            "subcategory":"Construction",
            "type":"Services"
        }
    ],
    "sg:phone":"+1 517 321 7196",
    "sg:postcode":"48917",
    "sg:province":"MI",
    "sg:tags":[
        "house",
        "builder",
        "operative",
        "res"
    ],
    "wof:name":"Mulder Company",
    "wof:placetype":"venue"
},
  "geometry": {"coordinates":[-84.611375,42.741034],"type":"Point"}
}