{
  "type": "Feature",
  "properties": {
    "iso:country":"US",
    "sg:address":"421 W Front St",
    "sg:city":"Traverse City",
    "sg:classifiers":[
        {
            "category":"Building & Trades",
            "subcategory":"Plumbing",
            "type":"Services"
        }
    ],
    "sg:phone":"+1 231 946 5212",
    "sg:postcode":"49684",
    "sg:province":"MI",
    "sg:tags":[
        "plumbing",
        "contractor"
    ],
    "wof:name":"Walters & Hemming Inc",
    "wof:placetype":"venue"
},
  "geometry": {"coordinates":[-85.62892100000001,44.763962],"type":"Point"}
}