{
  "type": "Feature",
  "properties": {
    "iso:country":"US",
    "sg:address":"26261 Evergreen Rd Ste 110",
    "sg:city":"Southfield",
    "sg:classifiers":[
        {
            "category":"Professional",
            "subcategory":"Lawyer & Legal Services",
            "type":"Services"
        }
    ],
    "sg:phone":"+1 248 355 2150",
    "sg:postcode":"48076",
    "sg:province":"MI",
    "wof:name":"Cousens Mark H Atty",
    "wof:placetype":"venue"
},
  "geometry": {"coordinates":[-83.24099699999999,42.483002],"type":"Point"}
}