{
  "type": "Feature",
  "properties": {
    "iso:country":"US",
    "sg:address":"420 W Magnetic St",
    "sg:city":"Marquette",
    "sg:classifiers":[
        {
            "category":"Education",
            "subcategory":"Library",
            "type":"Public Place"
        }
    ],
    "sg:phone":"+1 906 225 3429",
    "sg:postcode":"49855",
    "sg:province":"MI",
    "sg:tags":[
        "special",
        "interest"
    ],
    "wof:name":"Kevin F O'Brien Hlth Sci Libr",
    "wof:placetype":"venue"
},
  "geometry": {"coordinates":[-87.400513,46.553668],"type":"Point"}
}