{
  "type": "Feature",
  "properties": {
    "iso:country":"US",
    "sg:address":"2664 Crossing Cir",
    "sg:city":"Traverse City",
    "sg:classifiers":[
        {
            "category":"Autos & Motor Vehicles",
            "subcategory":"Boat Sales",
            "type":"Retail Goods"
        }
    ],
    "sg:phone":"+1 231 932 1851",
    "sg:postcode":"49684",
    "sg:province":"MI",
    "sg:tags":[
        "equipment",
        "supply"
    ],
    "sg:website":"www.boatersworld.com",
    "wof:name":"Boater's World Marine Ctr",
    "wof:placetype":"venue"
},
  "geometry": {"coordinates":[-85.63435200000001,44.727266],"type":"Point"}
}