{
  "type": "Feature",
  "properties": {
    "iso:country":"US",
    "sg:address":"215 W Lake St",
    "sg:city":"Tawas City",
    "sg:classifiers":[
        {
            "category":"Shopping",
            "subcategory":"Department Store",
            "type":"Retail Goods"
        }
    ],
    "sg:phone":"+1 989 362 8833",
    "sg:postcode":"48763",
    "sg:province":"MI",
    "wof:name":"Sears Roebuck & Co",
    "wof:placetype":"venue"
},
  "geometry": {"coordinates":[-83.51313,44.270719],"type":"Point"}
}