{
  "type": "Feature",
  "properties": {
    "iso:country":"US",
    "sg:address":"4806 N Mission Rd",
    "sg:city":"Rosebush",
    "sg:classifiers":[
        {
            "category":"Building & Trades",
            "subcategory":"Equipment Rental",
            "type":"Services"
        }
    ],
    "sg:phone":"+1 989 433 2970",
    "sg:postcode":"48878",
    "sg:province":"MI",
    "sg:tags":[
        "crane"
    ],
    "wof:name":"Glenn Higgins Crane Svc",
    "wof:placetype":"venue"
},
  "geometry": {"coordinates":[-84.767816,43.709329],"type":"Point"}
}