{
  "type": "Feature",
  "properties": {
    "iso:country":"US",
    "sg:address":"22705 Hoover Rd",
    "sg:city":"Warren",
    "sg:classifiers":[
        {
            "category":"Building & Trades",
            "subcategory":"Plumbing",
            "type":"Services"
        }
    ],
    "sg:phone":"+1 586 754 9906",
    "sg:postcode":"48089",
    "sg:province":"MI",
    "sg:tags":[
        "conditioning",
        "air",
        "system",
        "contractor"
    ],
    "wof:name":"Tech Borne",
    "wof:placetype":"venue"
},
  "geometry": {"coordinates":[-83.005697,42.461569],"type":"Point"}
}