{
  "type": "Feature",
  "properties": {
    "iso:country":"US",
    "sg:address":"312 Clinton Ave",
    "sg:city":"St Clair",
    "sg:classifiers":[
        {
            "category":"Home & Garden",
            "subcategory":"Hardware",
            "type":"Retail Goods"
        }
    ],
    "sg:phone":"+1 810 329 3421",
    "sg:postcode":"48079",
    "sg:province":"MI",
    "wof:name":"Blake Hardware",
    "wof:placetype":"venue"
},
  "geometry": {"coordinates":[-82.489062,42.821329],"type":"Point"}
}