{
  "type": "Feature",
  "properties": {
    "iso:country":"US",
    "sg:address":"3080 Grange Hall Rd",
    "sg:city":"Holly",
    "sg:classifiers":[
        {
            "category":"Building & Trades",
            "subcategory":"Construction",
            "type":"Services"
        }
    ],
    "sg:phone":"+1 248 634 5611",
    "sg:postcode":"48442",
    "sg:province":"MI",
    "sg:tags":[
        "excavating",
        "contractor"
    ],
    "wof:name":"Ron Dennis Supply",
    "wof:placetype":"venue"
},
  "geometry": {"coordinates":[-83.642554,42.805262],"type":"Point"}
}