{
  "type": "Feature",
  "properties": {
    "iso:country":"US",
    "sg:address":"4138 Lady Slipper Dr",
    "sg:city":"Traverse City",
    "sg:classifiers":[
        {
            "category":"Retail",
            "subcategory":"Portrait Studio",
            "type":"Services"
        }
    ],
    "sg:phone":"+1 231 929 2477",
    "sg:postcode":"49684",
    "sg:province":"MI",
    "sg:tags":[
        "photo"
    ],
    "wof:name":"Algomah Signs",
    "wof:placetype":"venue"
},
  "geometry": {"coordinates":[-85.65989399999999,44.700825],"type":"Point"}
}