{
  "type": "Feature",
  "properties": {
    "iso:country":"US",
    "sg:address":"380 W Borden Rd",
    "sg:city":"Rose City",
    "sg:classifiers":[
        {
            "category":"Shopping",
            "subcategory":"Computers & Home Electronics",
            "type":"Retail Goods"
        }
    ],
    "sg:phone":"+1 989 343 1213",
    "sg:postcode":"48654",
    "sg:province":"MI",
    "sg:tags":[
        "software"
    ],
    "wof:name":"Custom Software Inc",
    "wof:placetype":"venue"
},
  "geometry": {"coordinates":[-84.142802,44.464505],"type":"Point"}
}