{
  "type": "Feature",
  "properties": {
    "iso:country":"US",
    "sg:address":"7669 Highland Rd",
    "sg:city":"Waterford",
    "sg:classifiers":[
        {
            "category":"Personal",
            "subcategory":"Barber",
            "type":"Services"
        }
    ],
    "sg:phone":"+1 248 886 8603",
    "sg:postcode":"48327",
    "sg:province":"MI",
    "wof:name":"Vintage Barber Shoppe",
    "wof:placetype":"venue"
},
  "geometry": {"coordinates":[-83.44158400000001,42.660274],"type":"Point"}
}