{
  "type": "Feature",
  "properties": {
    "iso:country":"US",
    "sg:address":"154 West St",
    "sg:city":"Battle Creek",
    "sg:classifiers":[
        {
            "category":"Health Services",
            "subcategory":"Doctor",
            "type":"Services"
        }
    ],
    "sg:phone":"+1 269 969 6150",
    "sg:postcode":"49037",
    "sg:province":"MI",
    "sg:tags":[
        "physician",
        "surgeon"
    ],
    "wof:name":"Neuro-Surgical Svc",
    "wof:placetype":"venue"
},
  "geometry": {"coordinates":[-85.561086,43.219961],"type":"Point"}
}