{
  "type": "Feature",
  "properties": {
    "iso:country":"US",
    "sg:address":"111 W Genesee St",
    "sg:city":"Lapeer",
    "sg:classifiers":[
        {
            "category":"Professional",
            "subcategory":"Accounting & Tax Preparation",
            "type":"Services"
        }
    ],
    "sg:phone":"+1 810 664 6533",
    "sg:postcode":"48446",
    "sg:province":"MI",
    "sg:tags":[
        "return"
    ],
    "wof:name":"Michaud Bookkeeping & Tax Svc",
    "wof:placetype":"venue"
},
  "geometry": {"coordinates":[-83.302134,43.050871],"type":"Point"}
}