{
  "type": "Feature",
  "properties": {
    "iso:country":"US",
    "sg:address":"175 E Main St",
    "sg:city":"Harbor Springs",
    "sg:classifiers":[
        {
            "category":"Shopping",
            "type":"Retail Goods"
        }
    ],
    "sg:phone":"+1 231 526 5377",
    "sg:postcode":"49740",
    "sg:province":"MI",
    "sg:tags":[
        "art",
        "gallery",
        "dealer"
    ],
    "wof:name":"KNOX Galleries",
    "wof:placetype":"venue"
},
  "geometry": {"coordinates":[-84.988417,45.429809],"type":"Point"}
}