{
  "type": "Feature",
  "properties": {
    "iso:country":"US",
    "sg:address":"6797 Sadie Ln",
    "sg:city":"Belleville",
    "sg:classifiers":[
        {
            "category":"Professional",
            "subcategory":"Employment Agencies",
            "type":"Services"
        }
    ],
    "sg:phone":"+1 734 397 3178",
    "sg:postcode":"48111",
    "sg:province":"MI",
    "wof:name":"Divine Mercy Nurse Recruiting",
    "wof:placetype":"venue"
},
  "geometry": {"coordinates":[-83.46336100000001,42.255925],"type":"Point"}
}