{
  "type": "Feature",
  "properties": {
    "iso:country":"US",
    "sg:address":"13464 Atwell Rd",
    "sg:city":"Emmett",
    "sg:classifiers":[
        {
            "category":"Building & Trades",
            "subcategory":"Electrical",
            "type":"Services"
        }
    ],
    "sg:phone":"+1 810 395 2463",
    "sg:postcode":"48022",
    "sg:province":"MI",
    "sg:tags":[
        "electrical",
        "contractor"
    ],
    "wof:name":"Dewitte Electric Company",
    "wof:placetype":"venue"
},
  "geometry": {"coordinates":[-82.868222,42.994957],"type":"Point"}
}