{
  "type": "Feature",
  "properties": {
    "iso:country":"US",
    "sg:address":"584 44th St SE",
    "sg:city":"Grand Rapids",
    "sg:classifiers":[
        {
            "category":"Building & Trades",
            "subcategory":"Plumbing",
            "type":"Services"
        }
    ],
    "sg:phone":"+1 616 538 0220",
    "sg:postcode":"49548",
    "sg:province":"MI",
    "sg:tags":[
        "conditioning",
        "air",
        "system",
        "contractor"
    ],
    "sg:website":"www.penningplumbing.com",
    "wof:name":"Penning Plumbing Heating & AC",
    "wof:placetype":"venue"
},
  "geometry": {"coordinates":[-85.65074300000001,42.883784],"type":"Point"}
}