{
  "type": "Feature",
  "properties": {
    "iso:country":"US",
    "sg:address":"444 Frandor Ave",
    "sg:city":"Lansing",
    "sg:classifiers":[
        {
            "category":"Shopping",
            "subcategory":"Clothing, Apparel, & Fashions",
            "type":"Retail Goods"
        }
    ],
    "sg:phone":"+1 517 351 6969",
    "sg:postcode":"48912",
    "sg:province":"MI",
    "sg:tags":[
        "furnishing"
    ],
    "wof:name":"Holden-Reid Clothiers",
    "wof:placetype":"venue"
},
  "geometry": {"coordinates":[-84.506564,42.738306],"type":"Point"}
}