{
  "type": "Feature",
  "properties": {
    "iso:country":"US",
    "sg:address":"754 Franklin St SE",
    "sg:city":"Grand Rapids",
    "sg:classifiers":[
        {
            "category":"Banks & Credit Unions",
            "subcategory":"Bank",
            "type":"Services"
        }
    ],
    "sg:phone":"+1 616 771 5000",
    "sg:postcode":"49507",
    "sg:province":"MI",
    "sg:tags":[
        "state"
    ],
    "wof:name":"Fifth Third Bank",
    "wof:placetype":"venue"
},
  "geometry": {"coordinates":[-85.650248,42.948315],"type":"Point"}
}