{
  "type": "Feature",
  "properties": {
    "iso:country":"US",
    "sg:address":"230 N Rochester Rd",
    "sg:city":"Clawson",
    "sg:classifiers":[
        {
            "category":"Communications",
            "subcategory":"Film & Video Production",
            "type":"Services"
        }
    ],
    "sg:phone":"+1 248 588 1660",
    "sg:postcode":"48017",
    "sg:province":"MI",
    "sg:tags":[
        "taping"
    ],
    "wof:name":"Bombay Video Production",
    "wof:placetype":"venue"
},
  "geometry": {"coordinates":[-83.13543900000001,42.53518],"type":"Point"}
}