{
  "type": "Feature",
  "properties": {
    "iso:country":"US",
    "sg:address":"4730 Lovett St",
    "sg:city":"Detroit",
    "sg:classifiers":[
        {
            "category":"School Buses",
            "type":"Transportation"
        }
    ],
    "sg:phone":"+1 313 897 7660",
    "sg:postcode":"48210",
    "sg:province":"MI",
    "sg:tags":[
        "acting",
        "workshop"
    ],
    "wof:name":"E Entertainment",
    "wof:placetype":"venue"
},
  "geometry": {"coordinates":[-83.10914099999999,42.339955],"type":"Point"}
}