{
  "type": "Feature",
  "properties": {
    "iso:country":"US",
    "sg:address":"1505 E Auburn Rd",
    "sg:city":"Rochester Hills",
    "sg:classifiers":[
        {
            "category":"Retail",
            "subcategory":"Animal Services",
            "type":"Services"
        }
    ],
    "sg:phone":"+1 248 853 0970",
    "sg:postcode":"48307",
    "sg:province":"MI",
    "sg:tags":[
        "pet",
        "grooming",
        "washing"
    ],
    "wof:name":"Grooming By Peggy",
    "wof:placetype":"venue"
},
  "geometry": {"coordinates":[-83.100701,42.637281],"type":"Point"}
}