{
  "type": "Feature",
  "properties": {
    "iso:country":"US",
    "sg:address":"2135 W Popple Rd",
    "sg:city":"Bad Axe",
    "sg:classifiers":[
        {
            "category":"Retail",
            "subcategory":"Repair Shop",
            "type":"Services"
        }
    ],
    "sg:phone":"+1 989 269 3272",
    "sg:postcode":"48413",
    "sg:province":"MI",
    "wof:name":"Pampered Upholstery",
    "wof:placetype":"venue"
},
  "geometry": {"coordinates":[-83.063548,43.764005],"type":"Point"}
}