{
  "type": "Feature",
  "properties": {
    "iso:country":"US",
    "sg:address":"2310 Cooper Ave",
    "sg:city":"Saginaw",
    "sg:classifiers":[
        {
            "category":"Building & Trades",
            "subcategory":"Landscaping Services",
            "type":"Services"
        }
    ],
    "sg:phone":"+1 989 249 5223",
    "sg:postcode":"48602",
    "sg:province":"MI",
    "wof:name":"Woodnicks Tree & Lawncare",
    "wof:placetype":"venue"
},
  "geometry": {"coordinates":[-83.972756,43.430545],"type":"Point"}
}