{
  "type": "Feature",
  "properties": {
    "iso:country":"US",
    "sg:address":"44744 Helm St",
    "sg:city":"Plymouth",
    "sg:classifiers":[
        {
            "category":"Professional",
            "subcategory":"Management & Consulting",
            "type":"Services"
        }
    ],
    "sg:phone":"+1 734 453 8804",
    "sg:postcode":"48170",
    "sg:province":"MI",
    "wof:name":"Financial One Inc",
    "wof:placetype":"venue"
},
  "geometry": {"coordinates":[-83.488328,42.391715],"type":"Point"}
}