{
  "type": "Feature",
  "properties": {
    "iso:country":"US",
    "sg:address":"1209 S Alstott Dr",
    "sg:city":"Howell",
    "sg:classifiers":[
        {
            "category":"Retail",
            "subcategory":"Portrait Studio",
            "type":"Services"
        }
    ],
    "sg:phone":"+1 517 546 1923",
    "sg:postcode":"48843",
    "sg:province":"MI",
    "sg:tags":[
        "photo"
    ],
    "wof:name":"Robert Vanmarter Photography",
    "wof:placetype":"venue"
},
  "geometry": {"coordinates":[-83.949746,42.587543],"type":"Point"}
}