{
  "type": "Feature",
  "properties": {
    "iso:country":"US",
    "sg:address":"1432 Maynard Rd",
    "sg:city":"Cheboygan",
    "sg:classifiers":[
        {
            "category":"Professional",
            "subcategory":"Business Services",
            "type":"Services"
        }
    ],
    "sg:phone":"+1 231 627 2665",
    "sg:postcode":"49721",
    "sg:province":"MI",
    "wof:name":"Northern MI Marine Apprsl Loc",
    "wof:placetype":"venue"
},
  "geometry": {"coordinates":[-84.516868,45.620312],"type":"Point"}
}