{
  "type": "Feature",
  "properties": {
    "iso:country":"US",
    "sg:address":"43900 Grand River Ave",
    "sg:city":"Novi",
    "sg:classifiers":[
        {
            "category":"Professional",
            "type":"Services"
        }
    ],
    "sg:phone":"+1 248 348 7263",
    "sg:postcode":"48375",
    "sg:province":"MI",
    "sg:tags":[
        "establishment"
    ],
    "wof:name":"Autotech",
    "wof:placetype":"venue"
},
  "geometry": {"coordinates":[-83.48448399999999,42.482797],"type":"Point"}
}