{
  "type": "Feature",
  "properties": {
    "iso:country":"US",
    "sg:address":"3754 Naomi Rd",
    "sg:city":"Sodus",
    "sg:classifiers":[
        {
            "category":"Manufacturing",
            "subcategory":"Glass & Minerals",
            "type":"Manufacturing & Wholesale Goods"
        }
    ],
    "sg:phone":"+1 269 927 4888",
    "sg:postcode":"49126",
    "sg:province":"MI",
    "sg:tags":[
        "product",
        "mfg"
    ],
    "wof:name":"Discount Glass",
    "wof:placetype":"venue"
},
  "geometry": {"coordinates":[-86.363878,42.043389],"type":"Point"}
}