{
  "type": "Feature",
  "properties": {
    "iso:country":"US",
    "sg:address":"1428 44th St SW",
    "sg:city":"Wyoming",
    "sg:classifiers":[
        {
            "category":"Manufacturing",
            "subcategory":"Furniture",
            "type":"Manufacturing & Wholesale Goods"
        }
    ],
    "sg:phone":"+1 616 531 2844",
    "sg:postcode":"49509",
    "sg:province":"MI",
    "sg:tags":[
        "equipment",
        "supply"
    ],
    "sg:website":"www.hri-inc.com",
    "wof:name":"Hri",
    "wof:placetype":"venue"
},
  "geometry": {"coordinates":[-85.701809,42.884284],"type":"Point"}
}