{
  "type": "Feature",
  "properties": {
    "iso:country":"US",
    "sg:address":"4414 136th Ave",
    "sg:city":"Holland",
    "sg:classifiers":[
        {
            "category":"Manufacturing",
            "subcategory":"Metals",
            "type":"Manufacturing & Wholesale Goods"
        },
        {
            "category":"Manufacturing",
            "subcategory":"Tools & Machinery",
            "type":"Manufacturing & Wholesale Goods"
        }
    ],
    "sg:phone":"+1 616 392 8188",
    "sg:postcode":"49424",
    "sg:province":"MI",
    "sg:tags":[
        "machine",
        "shop",
        "guard",
        "mfg"
    ],
    "wof:name":"Machine Guard & Cover Co",
    "wof:placetype":"venue"
},
  "geometry": {"coordinates":[-86.11825,42.849278],"type":"Point"}
}