{
  "type": "Feature",
  "properties": {
    "iso:country":"US",
    "sg:address":"476 Bear Lake Rd",
    "sg:city":"Muskegon",
    "sg:classifiers":[
        {
            "category":"Building & Trades",
            "subcategory":"Construction",
            "type":"Services"
        }
    ],
    "sg:phone":"+1 231 744 8134",
    "sg:postcode":"49445",
    "sg:province":"MI",
    "sg:tags":[
        "home",
        "builder"
    ],
    "wof:name":"Life Style Homes",
    "wof:placetype":"venue"
},
  "geometry": {"coordinates":[-86.298072,43.245686],"type":"Point"}
}