{
  "type": "Feature",
  "properties": {
    "iso:country":"US",
    "sg:address":"8761 N 120th Ave",
    "sg:city":"Hart",
    "sg:classifiers":[
        {
            "category":"Building & Trades",
            "subcategory":"Construction",
            "type":"Services"
        }
    ],
    "sg:phone":"+1 231 873 5261",
    "sg:postcode":"49420",
    "sg:province":"MI",
    "sg:tags":[
        "masonry",
        "contractor"
    ],
    "wof:name":"Ruggles & Son Masonry",
    "wof:placetype":"venue"
},
  "geometry": {"coordinates":[-86.25840599999999,43.800641],"type":"Point"}
}