{
  "type": "Feature",
  "properties": {
    "iso:country":"US",
    "sg:address":"3760 Pollina Ave",
    "sg:city":"Fort Gratiot",
    "sg:classifiers":[
        {
            "category":"Social Services",
            "subcategory":"Child Care",
            "type":"Services"
        }
    ],
    "sg:phone":"+1 810 982 3423",
    "sg:postcode":"48059",
    "sg:province":"MI",
    "sg:tags":[
        "day"
    ],
    "wof:name":"Sherry Jean Bartley",
    "wof:placetype":"venue"
},
  "geometry": {"coordinates":[-82.484694,43.014159],"type":"Point"}
}