{
  "type": "Feature",
  "properties": {
    "iso:country":"US",
    "sg:address":"700 W Prairie Ronde St",
    "sg:city":"Dowagiac",
    "sg:classifiers":[
        {
            "category":"Government",
            "subcategory":"Office",
            "type":"Public Place"
        }
    ],
    "sg:phone":"+1 269 782 3334",
    "sg:postcode":"49047",
    "sg:province":"MI",
    "sg:tags":[
        "state",
        "security"
    ],
    "wof:name":"National Guard Recruiting",
    "wof:placetype":"venue"
},
  "geometry": {"coordinates":[-86.119416,41.991094],"type":"Point"}
}