{
  "type": "Feature",
  "properties": {
    "iso:country":"US",
    "sg:address":"14443 Rosemont Ave",
    "sg:city":"Detroit",
    "sg:classifiers":[
        {
            "category":"Professional",
            "subcategory":"Engineering",
            "type":"Services"
        }
    ],
    "sg:phone":"+1 313 273 2229",
    "sg:postcode":"48223",
    "sg:province":"MI",
    "sg:tags":[
        "consulting",
        "engineer"
    ],
    "wof:name":"Thomas Linda & Associates LLC",
    "wof:placetype":"venue"
},
  "geometry": {"coordinates":[-83.220207,42.392119],"type":"Point"}
}