{
  "type": "Feature",
  "properties": {
    "iso:country":"US",
    "sg:address":"2409 Tarry Dr",
    "sg:city":"Sterling Heights",
    "sg:classifiers":[
        {
            "category":"Manufacturing",
            "subcategory":"Printing",
            "type":"Manufacturing & Wholesale Goods"
        }
    ],
    "sg:phone":"+1 586 264 5495",
    "sg:postcode":"48310",
    "sg:province":"MI",
    "sg:tags":[
        "commercial"
    ],
    "wof:name":"Urban Textiles",
    "wof:placetype":"venue"
},
  "geometry": {"coordinates":[-83.08444299999999,42.540832],"type":"Point"}
}