{
  "type": "Feature",
  "properties": {
    "iso:country":"US",
    "sg:address":"23933 Allen Rd",
    "sg:city":"Trenton",
    "sg:classifiers":[
        {
            "category":"Manufacturing",
            "subcategory":"Metals",
            "type":"Manufacturing & Wholesale Goods"
        }
    ],
    "sg:phone":"+1 734 692 1926",
    "sg:postcode":"48183",
    "sg:province":"MI",
    "sg:tags":[
        "blast",
        "furnace",
        "works"
    ],
    "wof:name":"KG Specialty Metal LLC",
    "wof:placetype":"venue"
},
  "geometry": {"coordinates":[-83.22578900000001,42.134497],"type":"Point"}
}