{
  "type": "Feature",
  "properties": {
    "iso:country":"US",
    "sg:address":"336 Parkdale Ave",
    "sg:city":"Royal Oak",
    "sg:classifiers":[
        {
            "category":"Banks & Credit Unions",
            "subcategory":"Bank",
            "type":"Services"
        }
    ],
    "sg:phone":"+1 248 545 4428",
    "sg:postcode":"48073",
    "sg:province":"MI",
    "sg:tags":[
        "loan",
        "real estate"
    ],
    "wof:name":"North American Mortgage Co",
    "wof:placetype":"venue"
},
  "geometry": {"coordinates":[-83.14037999999999,42.509903],"type":"Point"}
}