{
  "type": "Feature",
  "properties": {
    "iso:country":"US",
    "sg:address":"2125 N Ely Hwy",
    "sg:city":"Alma",
    "sg:classifiers":[
        {
            "category":"Building & Trades",
            "subcategory":"Construction",
            "type":"Services"
        }
    ],
    "sg:phone":"+1 989 463 2730",
    "sg:postcode":"48801",
    "sg:province":"MI",
    "sg:tags":[
        "house"
    ],
    "wof:name":"Cotter Construction",
    "wof:placetype":"venue"
},
  "geometry": {"coordinates":[-84.706395,43.321069],"type":"Point"}
}