{
  "type": "Feature",
  "properties": {
    "iso:country":"US",
    "sg:address":"12350 E Outer Dr",
    "sg:city":"Detroit",
    "sg:classifiers":[
        {
            "category":"Education",
            "subcategory":"Library",
            "type":"Public Place"
        }
    ],
    "sg:phone":"+1 313 267 6562",
    "sg:postcode":"48224",
    "sg:province":"MI",
    "wof:name":"Public Library",
    "wof:placetype":"venue"
},
  "geometry": {"coordinates":[-82.936842,42.403812],"type":"Point"}
}