{
  "type": "Feature",
  "properties": {
    "iso:country":"US",
    "sg:address":"220 W Pike St",
    "sg:city":"Pontiac",
    "sg:classifiers":[
        {
            "category":"Communications",
            "subcategory":"Film & Video Production",
            "type":"Services"
        }
    ],
    "sg:phone":"+1 248 335 4045",
    "sg:postcode":"48341",
    "sg:province":"MI",
    "sg:tags":[
        "motion"
    ],
    "wof:name":"First Hand Productions",
    "wof:placetype":"venue"
},
  "geometry": {"coordinates":[-83.30214700000001,42.635227],"type":"Point"}
}