{
  "type": "Feature",
  "properties": {
    "iso:country":"US",
    "sg:address":"1935 Smith St",
    "sg:city":"Ypsilanti",
    "sg:classifiers":[
        {
            "category":"Wholesale",
            "subcategory":"Hardware",
            "type":"Manufacturing & Wholesale Goods"
        }
    ],
    "sg:phone":"+1 734 483 9118",
    "sg:postcode":"48198",
    "sg:province":"MI",
    "wof:name":"Locks of Braids",
    "wof:placetype":"venue"
},
  "geometry": {"coordinates":[-83.567527,42.218832],"type":"Point"}
}