{
  "type": "Feature",
  "properties": {
    "iso:country":"US",
    "sg:address":"407 W Webster Ave",
    "sg:city":"Muskegon",
    "sg:classifiers":[
        {
            "category":"Building & Trades",
            "subcategory":"Construction",
            "type":"Services"
        }
    ],
    "sg:phone":"+1 231 722 0542",
    "sg:postcode":"49440",
    "sg:province":"MI",
    "sg:tags":[
        "house"
    ],
    "wof:name":"Tom Russo Builder",
    "wof:placetype":"venue"
},
  "geometry": {"coordinates":[-86.253445,43.232606],"type":"Point"}
}