{
  "type": "Feature",
  "properties": {
    "iso:country":"US",
    "sg:address":"610 W 14 Mile Rd",
    "sg:city":"Clawson",
    "sg:classifiers":[
        {
            "category":"Retail",
            "subcategory":"Animal Services",
            "type":"Services"
        }
    ],
    "sg:phone":"+1 248 280 6900",
    "sg:postcode":"48017",
    "sg:province":"MI",
    "sg:tags":[
        "pet",
        "aquarium",
        "store",
        "supply"
    ],
    "sg:website":"www.atlantisfish.net",
    "wof:name":"Atlantis Fish Shoppe",
    "wof:placetype":"venue"
},
  "geometry": {"coordinates":[-83.155321,42.533384],"type":"Point"}
}