{
  "type": "Feature",
  "properties": {
    "iso:country":"US",
    "sg:address":"101 Alfred Wright Blvd",
    "sg:city":"Ironwood",
    "sg:classifiers":[
        {
            "category":"Organizations",
            "subcategory":"Professional Association",
            "type":"Services"
        }
    ],
    "sg:phone":"+1 906 932 2840",
    "sg:postcode":"49938",
    "sg:province":"MI",
    "sg:tags":[
        "business"
    ],
    "wof:name":"XCEL Energy Inc",
    "wof:placetype":"venue"
},
  "geometry": {"coordinates":[-90.167424,46.447967],"type":"Point"}
}