{
  "type": "Feature",
  "properties": {
    "iso:country":"US",
    "sg:address":"15115 E Jefferson Ave",
    "sg:city":"Grosse Pointe",
    "sg:classifiers":[
        {
            "category":"Government",
            "subcategory":"Office",
            "type":"Public Place"
        }
    ],
    "sg:phone":"+1 313 822 6200",
    "sg:postcode":"48230",
    "sg:province":"MI",
    "sg:tags":[
        "municipality"
    ],
    "wof:name":"Grosse Pointe Park City of",
    "wof:placetype":"venue"
},
  "geometry": {"coordinates":[-82.937523,42.375862],"type":"Point"}
}