{
  "type": "Feature",
  "properties": {
    "iso:country":"US",
    "sg:address":"32758 Birchwood St",
    "sg:city":"Westland",
    "sg:classifiers":[
        {
            "category":"Professional",
            "subcategory":"Art Services",
            "type":"Services"
        }
    ],
    "sg:phone":"+1 734 722 8941",
    "sg:postcode":"48186",
    "sg:province":"MI",
    "sg:tags":[
        "photography",
        "commercial"
    ],
    "wof:name":"Monroes Studio",
    "wof:placetype":"venue"
},
  "geometry": {"coordinates":[-83.36167,42.305143],"type":"Point"}
}