{
  "type": "Feature",
  "properties": {
    "iso:country":"US",
    "sg:address":"3721 Hagen Dr SE",
    "sg:city":"Grand Rapids",
    "sg:classifiers":[
        {
            "category":"Manufacturing",
            "subcategory":"Metals",
            "type":"Manufacturing & Wholesale Goods"
        }
    ],
    "sg:phone":"+1 616 245 4607",
    "sg:postcode":"49548",
    "sg:province":"MI",
    "wof:name":"Benteler Automotive Corp",
    "wof:placetype":"venue"
},
  "geometry": {"coordinates":[-85.657453,42.897412],"type":"Point"}
}