{
  "type": "Feature",
  "properties": {
    "iso:country":"US",
    "sg:address":"6499 W Grand Blanc Rd",
    "sg:city":"Swartz Creek",
    "sg:classifiers":[
        {
            "category":"Personal",
            "type":"Services"
        }
    ],
    "sg:phone":"+1 810 655 2222",
    "sg:postcode":"48473",
    "sg:province":"MI",
    "wof:name":"Why Weight Inc",
    "wof:placetype":"venue"
},
  "geometry": {"coordinates":[-83.804631,42.91326],"type":"Point"}
}