{
  "type": "Feature",
  "properties": {
    "iso:country":"US",
    "sg:address":"1400 Carpenter Ave",
    "sg:city":"Iron Mountain",
    "sg:classifiers":[
        {
            "category":"Shopping",
            "subcategory":"Pharmacy",
            "type":"Retail Goods"
        }
    ],
    "sg:phone":"+1 906 779 1842",
    "sg:postcode":"49801",
    "sg:province":"MI",
    "wof:name":"Iron Mountain Pharmacy",
    "wof:placetype":"venue"
},
  "geometry": {"coordinates":[-88.06867699999999,45.808721],"type":"Point"}
}