{
  "type": "Feature",
  "properties": {
    "iso:country":"US",
    "sg:address":"27041 Southfield Rd",
    "sg:city":"Lathrup Village",
    "sg:classifiers":[
        {
            "category":"Health Services",
            "subcategory":"Clinic",
            "type":"Services"
        }
    ],
    "sg:phone":"+1 248 443 2175",
    "sg:postcode":"48076",
    "sg:province":"MI",
    "sg:tags":[
        "home"
    ],
    "wof:name":"Advanced Home Care Of Michigan",
    "wof:placetype":"venue"
},
  "geometry": {"coordinates":[-83.221988,42.488545],"type":"Point"}
}