{
  "type": "Feature",
  "properties": {
    "iso:country":"US",
    "sg:address":"1881 Chilson Rd",
    "sg:city":"Howell",
    "sg:classifiers":[
        {
            "category":"Retail",
            "subcategory":"Auto Repair",
            "type":"Services"
        }
    ],
    "sg:phone":"+1 517 540 9618",
    "sg:postcode":"48843",
    "sg:province":"MI",
    "sg:tags":[
        "automobile",
        "customizing"
    ],
    "wof:name":"Todd's Customs & Rods Inc",
    "wof:placetype":"venue"
},
  "geometry": {"coordinates":[-83.892965,42.57199],"type":"Point"}
}