{
  "type": "Feature",
  "properties": {
    "iso:country":"US",
    "sg:address":"52 E Bacon St",
    "sg:city":"Hillsdale",
    "sg:classifiers":[
        {
            "category":"Professional",
            "subcategory":"Research",
            "type":"Services"
        }
    ],
    "sg:phone":"+1 517 439 5101",
    "sg:postcode":"49242",
    "sg:province":"MI",
    "sg:tags":[
        "foundation",
        "philanthropic"
    ],
    "wof:name":"Hillsdale County Community",
    "wof:placetype":"venue"
},
  "geometry": {"coordinates":[-84.631997,41.919989],"type":"Point"}
}