{
  "type": "Feature",
  "properties": {
    "iso:country":"US",
    "sg:address":"660 Woodward Ave Ste 1010",
    "sg:city":"Detroit",
    "sg:classifiers":[
        {
            "category":"Professional",
            "subcategory":"Lawyer & Legal Services",
            "type":"Services"
        }
    ],
    "sg:phone":"+1 313 465 7582",
    "sg:postcode":"48226",
    "sg:province":"MI",
    "wof:name":"Cameron Carolee K",
    "wof:placetype":"venue"
},
  "geometry": {"coordinates":[-83.045968,42.330879],"type":"Point"}
}