{
  "type": "Feature",
  "properties": {
    "iso:country":"US",
    "sg:address":"20092 Livernois Ave",
    "sg:city":"Detroit",
    "sg:classifiers":[
        {
            "category":"Personal",
            "subcategory":"Beauty Salon",
            "type":"Services"
        }
    ],
    "sg:phone":"+1 313 863 2600",
    "sg:postcode":"48221",
    "sg:province":"MI",
    "sg:tags":[
        "shop"
    ],
    "wof:name":"Joyce James Sunset Room Inc",
    "wof:placetype":"venue"
},
  "geometry": {"coordinates":[-83.141702,42.438913],"type":"Point"}
}