{
  "type": "Feature",
  "properties": {
    "iso:country":"US",
    "sg:address":"3095 W Thompson Rd",
    "sg:city":"Fenton",
    "sg:classifiers":[
        {
            "category":"Retail",
            "subcategory":"Auto Repair",
            "type":"Services"
        }
    ],
    "sg:phone":"+1 810 714 4440",
    "sg:postcode":"48430",
    "sg:province":"MI",
    "sg:tags":[
        "automotive"
    ],
    "wof:name":"KS Enterprises LLC",
    "wof:placetype":"venue"
},
  "geometry": {"coordinates":[-83.732551,42.862883],"type":"Point"}
}