{
  "type": "Feature",
  "properties": {
    "iso:country":"US",
    "sg:address":"15853 Trumbull Dr",
    "sg:city":"Macomb",
    "sg:classifiers":[
        {
            "category":"Home & Garden",
            "subcategory":"Furniture",
            "type":"Retail Goods"
        }
    ],
    "sg:phone":"+1 586 566 6036",
    "sg:postcode":"48044",
    "sg:province":"MI",
    "sg:tags":[
        "top",
        "counter"
    ],
    "wof:name":"Solid Surface Refinishers",
    "wof:placetype":"venue"
},
  "geometry": {"coordinates":[-82.96594899999999,42.652261],"type":"Point"}
}