{
  "type": "Feature",
  "properties": {
    "iso:country":"US",
    "sg:address":"18590 Mack Ave",
    "sg:city":"Grosse Pointe",
    "sg:classifiers":[
        {
            "category":"Shopping",
            "subcategory":"Florist",
            "type":"Retail Goods"
        }
    ],
    "sg:phone":"+1 313 881 7800",
    "sg:postcode":"48236",
    "sg:province":"MI",
    "sg:website":"www.charvattheflorist.com",
    "wof:name":"Charvat the Florist",
    "wof:placetype":"venue"
},
  "geometry": {"coordinates":[-82.912201,42.412601],"type":"Point"}
}