{
  "type": "Feature",
  "properties": {
    "iso:country":"US",
    "sg:address":"6070 Fenton Rd",
    "sg:city":"Flint",
    "sg:classifiers":[
        {
            "category":"Personal",
            "subcategory":"Beauty Salon",
            "type":"Services"
        }
    ],
    "sg:phone":"+1 810 232 8840",
    "sg:postcode":"48507",
    "sg:province":"MI",
    "sg:tags":[
        "body",
        "wrap"
    ],
    "wof:name":"Form-You-3 Weight Loss Ctr",
    "wof:placetype":"venue"
},
  "geometry": {"coordinates":[-83.692088,42.942619],"type":"Point"}
}