{
  "type": "Feature",
  "properties": {
    "iso:country":"US",
    "sg:address":"21439 Kelly Rd",
    "sg:city":"Eastpointe",
    "sg:classifiers":[
        {
            "category":"Organizations",
            "subcategory":"Religious Organization",
            "type":"Services"
        }
    ],
    "sg:phone":"+1 586 777 7723",
    "sg:postcode":"48021",
    "sg:province":"MI",
    "sg:tags":[
        "baptist",
        "church"
    ],
    "wof:name":"Christ Mssionary Baptst Church",
    "wof:placetype":"venue"
},
  "geometry": {"coordinates":[-82.93592200000001,42.455751],"type":"Point"}
}