{
  "type": "Feature",
  "properties": {
    "iso:country":"US",
    "sg:address":"22301 Allen Rd",
    "sg:city":"Woodhaven",
    "sg:classifiers":[
        {
            "category":"Restaurant",
            "type":"Food & Drink"
        }
    ],
    "sg:phone":"+1 734 362 8730",
    "sg:postcode":"48183",
    "sg:province":"MI",
    "wof:name":"Woodhaven Ground Round",
    "wof:placetype":"venue"
},
  "geometry": {"coordinates":[-83.225345,42.145728],"type":"Point"}
}