{
  "type": "Feature",
  "properties": {
    "iso:country":"US",
    "sg:address":"108 E 3rd St",
    "sg:city":"Harbor Springs",
    "sg:classifiers":[
        {
            "category":"Shopping",
            "subcategory":"Bicycles & Sporting Goods",
            "type":"Retail Goods"
        }
    ],
    "sg:phone":"+1 231 526 7152",
    "sg:postcode":"49740",
    "sg:province":"MI",
    "wof:name":"Touring Gear",
    "wof:placetype":"venue"
},
  "geometry": {"coordinates":[-84.988041,45.43047],"type":"Point"}
}