{
  "type": "Feature",
  "properties": {
    "iso:country":"US",
    "sg:address":"8194 Shields Dr",
    "sg:city":"Saginaw",
    "sg:classifiers":[
        {
            "category":"Restaurant",
            "type":"Food & Drink"
        }
    ],
    "sg:phone":"+1 989 781 5565",
    "sg:postcode":"48609",
    "sg:province":"MI",
    "sg:tags":[
        "caterer"
    ],
    "wof:name":"Schaefer Catering",
    "wof:placetype":"venue"
},
  "geometry": {"coordinates":[-84.07587599999999,43.419001],"type":"Point"}
}