{
  "type": "Feature",
  "properties": {
    "iso:country":"US",
    "sg:address":"2130 Brookhaven Dr SE",
    "sg:city":"Ada",
    "sg:classifiers":[
        {
            "category":"Wholesale",
            "subcategory":"Construction Materials",
            "type":"Manufacturing & Wholesale Goods"
        }
    ],
    "sg:phone":"+1 616 682 0029",
    "sg:postcode":"49301",
    "sg:province":"MI",
    "sg:tags":[
        "lumber"
    ],
    "sg:website":"www.workbench.com",
    "wof:name":"L L Johnson Lumber Mfg Co",
    "wof:placetype":"venue"
},
  "geometry": {"coordinates":[-85.466711,42.927232],"type":"Point"}
}