{
  "type": "Feature",
  "properties": {
    "iso:country":"US",
    "sg:address":"114 Prmrose Trl",
    "sg:city":"Battle Creek",
    "sg:classifiers":[
        {
            "category":"Personal",
            "subcategory":"Beauty Salon",
            "type":"Services"
        }
    ],
    "sg:phone":"+1 269 964 2554",
    "sg:postcode":"49017",
    "sg:province":"MI",
    "wof:name":"Penny's Hair & Body Shop",
    "wof:placetype":"venue"
},
  "geometry": {"coordinates":[-85.144391,42.367581],"type":"Point"}
}