{
  "type": "Feature",
  "properties": {
    "iso:country":"US",
    "sg:address":"3606 Powell Hwy",
    "sg:city":"Ionia",
    "sg:classifiers":[
        {
            "category":"Building & Trades",
            "subcategory":"Construction",
            "type":"Services"
        }
    ],
    "sg:phone":"+1 616 527 8850",
    "sg:postcode":"48846",
    "sg:province":"MI",
    "sg:tags":[
        "hanging"
    ],
    "wof:name":"Baker Richard Painter & Dctr",
    "wof:placetype":"venue"
},
  "geometry": {"coordinates":[-85.01544699999999,43.04],"type":"Point"}
}