{
  "type": "Feature",
  "properties": {
    "iso:country":"US",
    "sg:address":"401 Shady Oaks St",
    "sg:city":"Lake Orion",
    "sg:classifiers":[
        {
            "category":"Shopping",
            "subcategory":"Hobbies, Toys, & Games",
            "type":"Retail Goods"
        }
    ],
    "sg:phone":"+1 248 693 4473",
    "sg:postcode":"48362",
    "sg:province":"MI",
    "sg:tags":[
        "craft"
    ],
    "wof:name":"Ricky's Craftworks Inc",
    "wof:placetype":"venue"
},
  "geometry": {"coordinates":[-83.26237399999999,42.77512],"type":"Point"}
}