{
  "type": "Feature",
  "properties": {
    "iso:country":"US",
    "sg:address":"10177 108th St SE",
    "sg:city":"Middleville",
    "sg:classifiers":[
        {
            "category":"Health Services",
            "subcategory":"Medical Lab",
            "type":"Services"
        }
    ],
    "sg:phone":"+1 616 891 8531",
    "sg:postcode":"49333",
    "sg:province":"MI",
    "sg:tags":[
        "laboratory",
        "dental"
    ],
    "wof:name":"Caledonia Oral Arts",
    "wof:placetype":"venue"
},
  "geometry": {"coordinates":[-85.41235500000001,42.769209],"type":"Point"}
}