{
  "type": "Feature",
  "properties": {
    "iso:country":"US",
    "sg:address":"5743 E 13 Mile Rd",
    "sg:city":"Warren",
    "sg:classifiers":[
        {
            "category":"Shopping",
            "subcategory":"Bicycles & Sporting Goods",
            "type":"Retail Goods"
        }
    ],
    "sg:phone":"+1 586 264 1150",
    "sg:postcode":"48092",
    "sg:province":"MI",
    "sg:tags":[
        "bike"
    ],
    "wof:name":"Albe's Cycle Center Inc",
    "wof:placetype":"venue"
},
  "geometry": {"coordinates":[-83.049896,42.520901],"type":"Point"}
}