{
  "type": "Feature",
  "properties": {
    "iso:country":"US",
    "sg:address":"17301 W 7 Mile Rd",
    "sg:city":"Detroit",
    "sg:classifiers":[
        {
            "category":"Home & Garden",
            "subcategory":"Furniture",
            "type":"Retail Goods"
        }
    ],
    "sg:phone":"+1 313 279 2613",
    "sg:postcode":"48235",
    "sg:province":"MI",
    "sg:tags":[
        "store"
    ],
    "wof:name":"Capital Furniture",
    "wof:placetype":"venue"
},
  "geometry": {"coordinates":[-83.21393500000001,42.430023],"type":"Point"}
}