{
  "type": "Feature",
  "properties": {
    "iso:country":"US",
    "sg:address":"1311 Porters Ln",
    "sg:city":"Bloomfield Hills",
    "sg:classifiers":[
        {
            "category":"Health Services",
            "subcategory":"Doctor",
            "type":"Services"
        }
    ],
    "sg:phone":"+1 248 332 1341",
    "sg:postcode":"48302",
    "sg:province":"MI",
    "sg:tags":[
        "medical"
    ],
    "wof:name":"Dariouche Mohammadi Dr",
    "wof:placetype":"venue"
},
  "geometry": {"coordinates":[-83.294124,42.592199],"type":"Point"}
}