{
  "type": "Feature",
  "properties": {
    "iso:country":"US",
    "sg:address":"257 Industrial Park Rd",
    "sg:city":"Crystal Falls",
    "sg:classifiers":[
        {
            "category":"Manufacturing",
            "subcategory":"Building Materials",
            "type":"Manufacturing & Wholesale Goods"
        }
    ],
    "sg:phone":"+1 906 822 7321",
    "sg:postcode":"49920",
    "sg:province":"MI",
    "sg:tags":[
        "mfg"
    ],
    "wof:name":"Magiglide Inc",
    "wof:placetype":"venue"
},
  "geometry": {"coordinates":[-88.411157,46.203155],"type":"Point"}
}