{
  "type": "Feature",
  "properties": {
    "iso:country":"US",
    "sg:address":"5050 Gull Rd",
    "sg:city":"Kalamazoo",
    "sg:classifiers":[
        {
            "category":"Insurance",
            "subcategory":"Insurance Agent",
            "type":"Services"
        }
    ],
    "sg:phone":"+1 269 373 1010",
    "sg:postcode":"49048",
    "sg:province":"MI",
    "wof:name":"Allstate",
    "wof:placetype":"venue"
},
  "geometry": {"coordinates":[-85.530739,42.319058],"type":"Point"}
}