{
  "type": "Feature",
  "properties": {
    "iso:country":"US",
    "sg:address":"5105 French Line Rd",
    "sg:city":"Applegate",
    "sg:classifiers":[
        {
            "category":"Farming",
            "subcategory":"Farm",
            "type":"Manufacturing & Wholesale Goods"
        }
    ],
    "sg:phone":"+1 810 633 9901",
    "sg:postcode":"48401",
    "sg:province":"MI",
    "sg:tags":[
        "crop",
        "general"
    ],
    "wof:name":"Henry Buiting",
    "wof:placetype":"venue"
},
  "geometry": {"coordinates":[-82.62202499999999,43.370415],"type":"Point"}
}