{
  "type": "Feature",
  "properties": {
    "iso:country":"US",
    "sg:address":"26699 W 12 Mile Rd",
    "sg:city":"Southfield",
    "sg:classifiers":[
        {
            "category":"Health Services",
            "subcategory":"Health Practitioner",
            "type":"Services"
        }
    ],
    "sg:phone":"+1 248 353 3260",
    "sg:postcode":"48034",
    "sg:province":"MI",
    "sg:tags":[
        "therapist",
        "physical"
    ],
    "wof:name":"Wayne Center For Physical",
    "wof:placetype":"venue"
},
  "geometry": {"coordinates":[-83.311294,42.500395],"type":"Point"}
}