{
  "type": "Feature",
  "properties": {
    "iso:country":"US",
    "sg:address":"36539 Gratiot Ave",
    "sg:city":"Clinton Township",
    "sg:classifiers":[
        {
            "category":"Restaurant",
            "type":"Food & Drink"
        }
    ],
    "sg:phone":"+1 586 790 4448",
    "sg:postcode":"48035",
    "sg:province":"MI",
    "sg:tags":[
        "thai"
    ],
    "wof:name":"Little Thai Express",
    "wof:placetype":"venue"
},
  "geometry": {"coordinates":[-82.894097,42.565504],"type":"Point"}
}