{
  "type": "Feature",
  "properties": {
    "iso:country":"US",
    "sg:address":"188 Main St",
    "sg:city":"East Leroy",
    "sg:classifiers":[
        {
            "category":"Government",
            "subcategory":"Post Office",
            "type":"Public Place"
        }
    ],
    "sg:phone":"+1 269 729 4221",
    "sg:postcode":"49051",
    "sg:province":"MI",
    "wof:name":"US Post Office",
    "wof:placetype":"venue"
},
  "geometry": {"coordinates":[-85.21977800000001,42.166346],"type":"Point"}
}