{
  "type": "Feature",
  "properties": {
    "iso:country":"US",
    "sg:address":"2580 Lake Ave",
    "sg:city":"Muskegon",
    "sg:classifiers":[
        {
            "category":"Shopping",
            "subcategory":"Pharmacy",
            "type":"Retail Goods"
        }
    ],
    "sg:phone":"+1 231 744 8393",
    "sg:postcode":"49445",
    "sg:province":"MI",
    "wof:name":"Rite Aid Pharmacy",
    "wof:placetype":"venue"
},
  "geometry": {"coordinates":[-86.250063,43.265582],"type":"Point"}
}