{
  "type": "Feature",
  "properties": {
    "iso:country":"US",
    "sg:address":"3642 Bluebush Rd",
    "sg:city":"Monroe",
    "sg:classifiers":[
        {
            "category":"Building & Trades",
            "subcategory":"Construction",
            "type":"Services"
        }
    ],
    "sg:phone":"+1 734 457 4527",
    "sg:postcode":"48162",
    "sg:province":"MI",
    "sg:tags":[
        "maintenance",
        "contractor"
    ],
    "wof:name":"Dettloff Powerwash",
    "wof:placetype":"venue"
},
  "geometry": {"coordinates":[-83.429913,41.968208],"type":"Point"}
}