{
  "type": "Feature",
  "properties": {
    "iso:country":"US",
    "sg:address":"66901 95th Ave",
    "sg:city":"Dowagiac",
    "sg:classifiers":[
        {
            "category":"Retail",
            "subcategory":"Self-service Laundry",
            "type":"Services"
        }
    ],
    "sg:phone":"+1 269 424 5075",
    "sg:postcode":"49047",
    "sg:province":"MI",
    "wof:name":"Lucy & Ethel's Laundromat",
    "wof:placetype":"venue"
},
  "geometry": {"coordinates":[-86.190848,42.074829],"type":"Point"}
}