{
  "type": "Feature",
  "properties": {
    "iso:country":"US",
    "sg:address":"10821 Pierce St",
    "sg:city":"Zeeland",
    "sg:classifiers":[
        {
            "category":"Food & Beverages",
            "subcategory":"Fruits & Vegetables",
            "type":"Retail Goods"
        }
    ],
    "sg:phone":"+1 616 875 8853",
    "sg:postcode":"49464",
    "sg:province":"MI",
    "sg:tags":[
        "produce"
    ],
    "wof:name":"Woodland Acres Blueberry Farm",
    "wof:placetype":"venue"
},
  "geometry": {"coordinates":[-86.053211,42.957367],"type":"Point"}
}