{
  "type": "Feature",
  "properties": {
    "iso:country":"US",
    "sg:address":"14555 Champaign Rd Ofc",
    "sg:city":"Allen Park",
    "sg:classifiers":[
        {
            "category":"Real Estate",
            "subcategory":"Real Estate Operator",
            "type":"Services"
        }
    ],
    "sg:phone":"+1 313 382 6650",
    "sg:postcode":"48101",
    "sg:province":"MI",
    "sg:tags":[
        "apartment"
    ],
    "wof:name":"Champaign Garden Apts",
    "wof:placetype":"venue"
},
  "geometry": {"coordinates":[-83.202698,42.245701],"type":"Point"}
}