{
  "type": "Feature",
  "properties": {
    "iso:country":"US",
    "sg:address":"2070 S Almont Ave",
    "sg:city":"Imlay City",
    "sg:classifiers":[
        {
            "category":"Real Estate",
            "subcategory":"Real Estate Operator",
            "type":"Services"
        }
    ],
    "sg:phone":"+1 810 724 2900",
    "sg:postcode":"48444",
    "sg:province":"MI",
    "sg:tags":[
        "mobile",
        "home",
        "community"
    ],
    "wof:name":"Maple Grove Communities",
    "wof:placetype":"venue"
},
  "geometry": {"coordinates":[-83.076429,43.004791],"type":"Point"}
}