{
  "type": "Feature",
  "properties": {
    "iso:country":"US",
    "sg:address":"31 E Main St",
    "sg:city":"Sebewaing",
    "sg:classifiers":[
        {
            "category":"Building & Trades",
            "subcategory":"Plumbing",
            "type":"Services"
        }
    ],
    "sg:phone":"+1 989 883 2770",
    "sg:postcode":"48759",
    "sg:province":"MI",
    "sg:tags":[
        "plumbing",
        "contractor"
    ],
    "wof:name":"Kundinger & Kroll Inc",
    "wof:placetype":"venue"
},
  "geometry": {"coordinates":[-83.450867,43.73223],"type":"Point"}
}