{
  "type": "Feature",
  "properties": {
    "iso:country":"US",
    "sg:address":"600 W 6th Ave",
    "sg:city":"Flint",
    "sg:classifiers":[
        {
            "category":"Health Services",
            "subcategory":"Hospital",
            "type":"Services"
        }
    ],
    "sg:phone":"+1 810 424 0204",
    "sg:postcode":"48503",
    "sg:province":"MI",
    "wof:name":"Obstetrics & Gynecological Associates",
    "wof:placetype":"venue"
},
  "geometry": {"coordinates":[-83.703496,43.021277],"type":"Point"}
}