{
  "type": "Feature",
  "properties": {
    "iso:country":"US",
    "sg:address":"3318 M L King Ave",
    "sg:city":"Flint",
    "sg:classifiers":[
        {
            "category":"Restaurant",
            "type":"Food & Drink"
        }
    ],
    "sg:phone":"+1 810 785 8620",
    "sg:postcode":"48505",
    "sg:province":"MI",
    "sg:tags":[
        "barbeque"
    ],
    "wof:name":"Max Beef-Pro Bar-B-Q",
    "wof:placetype":"venue"
},
  "geometry": {"coordinates":[-83.704498,43.045799],"type":"Point"}
}