{
  "type": "Feature",
  "properties": {
    "iso:country":"US",
    "sg:address":"129 N Rochester Rd",
    "sg:city":"Clawson",
    "sg:classifiers":[
        {
            "category":"Retail",
            "subcategory":"Repair Shop",
            "type":"Services"
        },
        {
            "category":"Building & Trades",
            "subcategory":"Construction",
            "type":"Services"
        }
    ],
    "sg:phone":"+1 248 588 7822",
    "sg:postcode":"48017",
    "sg:province":"MI",
    "sg:tags":[
        "mobile",
        "home"
    ],
    "wof:name":"Mr Journeyman Inc",
    "wof:placetype":"venue"
},
  "geometry": {"coordinates":[-83.13552,42.535548],"type":"Point"}
}