{
  "type": "Feature",
  "properties": {
    "iso:country":"US",
    "sg:address":"444 Church St Ste 301",
    "sg:city":"Flint",
    "sg:classifiers":[
        {
            "category":"Banks & Credit Unions",
            "subcategory":"Atm",
            "type":"Services"
        }
    ],
    "sg:phone":"+1 810 235 1299",
    "sg:postcode":"48502",
    "sg:province":"MI",
    "sg:tags":[
        "bankruptcy"
    ],
    "sg:website":"www.cuzydlolaw.com",
    "wof:name":"Cuzydlo Law Group Pllc",
    "wof:placetype":"venue"
},
  "geometry": {"coordinates":[-83.693848,43.015174],"type":"Point"}
}