{
  "type": "Feature",
  "properties": {
    "iso:country":"US",
    "sg:address":"1125 US Hwy 31",
    "sg:city":"Petoskey",
    "sg:classifiers":[
        {
            "category":"Banks & Credit Unions",
            "subcategory":"Financial Services",
            "type":"Services"
        }
    ],
    "sg:phone":"+1 231 348 1110",
    "sg:postcode":"49770",
    "sg:province":"MI",
    "sg:tags":[
        "patent"
    ],
    "wof:name":"Big Apple Bagels",
    "wof:placetype":"venue"
},
  "geometry": {"coordinates":[-84.917779,45.389627],"type":"Point"}
}