{
  "type": "Feature",
  "properties": {
    "iso:country":"US",
    "sg:address":"110 Cardinal Crest St",
    "sg:city":"Jackson",
    "sg:classifiers":[
        {
            "category":"Social Services",
            "subcategory":"Child Care",
            "type":"Services"
        }
    ],
    "sg:phone":"+1 517 783 4686",
    "sg:postcode":"49202",
    "sg:province":"MI",
    "sg:tags":[
        "day"
    ],
    "wof:name":"Joannas Day Care",
    "wof:placetype":"venue"
},
  "geometry": {"coordinates":[-84.406389,42.30058],"type":"Point"}
}