{
  "type": "Feature",
  "properties": {
    "iso:country":"US",
    "sg:address":"20700 Ecorse Rd",
    "sg:city":"Taylor",
    "sg:classifiers":[
        {
            "category":"Banks & Credit Unions",
            "subcategory":"Atm",
            "type":"Services"
        }
    ],
    "sg:phone":"+1 313 388 5720",
    "sg:postcode":"48180",
    "sg:province":"MI",
    "sg:tags":[
        "bankruptcy"
    ],
    "wof:name":"Bankruptcy Centers",
    "wof:placetype":"venue"
},
  "geometry": {"coordinates":[-83.2397,42.256401],"type":"Point"}
}