{
  "type": "Feature",
  "properties": {
    "iso:country":"US",
    "sg:address":"2700 Robert T Longway Blvd",
    "sg:city":"Flint",
    "sg:classifiers":[
        {
            "category":"Health Services",
            "subcategory":"Hospital",
            "type":"Services"
        }
    ],
    "sg:phone":"+1 810 235 2344",
    "sg:postcode":"48503",
    "sg:province":"MI",
    "sg:tags":[
        "general"
    ],
    "wof:name":"Hurley Medical Center Inc",
    "wof:placetype":"venue"
},
  "geometry": {"coordinates":[-83.655052,43.02501],"type":"Point"}
}