{
  "type": "Feature",
  "properties": {
    "iso:country":"US",
    "sg:address":"2986 Walbridge Dr",
    "sg:city":"Rochester",
    "sg:classifiers":[
        {
            "category":"Retail",
            "subcategory":"Portrait Studio",
            "type":"Services"
        }
    ],
    "sg:phone":"+1 248 299 8726",
    "sg:postcode":"48307",
    "sg:province":"MI",
    "sg:tags":[
        "photo"
    ],
    "wof:name":"Bhandari Photography",
    "wof:placetype":"venue"
},
  "geometry": {"coordinates":[-83.140905,42.641744],"type":"Point"}
}