{
  "type": "Feature",
  "properties": {
    "iso:country":"US",
    "sg:address":"26851 Schoenherr Rd",
    "sg:city":"Warren",
    "sg:classifiers":[
        {
            "category":"Fast Food",
            "type":"Food & Drink"
        },
        {
            "category":"Restaurant",
            "type":"Food & Drink"
        }
    ],
    "sg:phone":"+1 586 755 0180",
    "sg:postcode":"48089",
    "sg:province":"MI",
    "sg:tags":[
        "traditional",
        "american",
        "chicken",
        "wing"
    ],
    "sg:website":"chickenshack.com/",
    "wof:name":"Chicken Shack",
    "wof:placetype":"venue"
},
  "geometry": {"coordinates":[-82.987099,42.4911],"type":"Point"}
}