{
  "type": "Feature",
  "properties": {
    "iso:country":"US",
    "sg:address":"36950 Ryan Rd",
    "sg:city":"Sterling Heights",
    "sg:classifiers":[
        {
            "category":"Building & Trades",
            "subcategory":"Construction",
            "type":"Services"
        }
    ],
    "sg:phone":"+1 586 258 3737",
    "sg:postcode":"48310",
    "sg:province":"MI",
    "sg:tags":[
        "contractor"
    ],
    "wof:name":"Hawc Inc",
    "wof:placetype":"venue"
},
  "geometry": {"coordinates":[-83.06969599999999,42.564037],"type":"Point"}
}