{
  "type": "Feature",
  "properties": {
    "iso:country":"US",
    "sg:address":"3308 W Monroe Rd",
    "sg:city":"Hart",
    "sg:classifiers":[
        {
            "category":"Professional",
            "subcategory":"Business Services",
            "type":"Services"
        }
    ],
    "sg:phone":"+1 231 873 0215",
    "sg:postcode":"49420",
    "sg:province":"MI",
    "wof:name":"Green Ventures",
    "wof:placetype":"venue"
},
  "geometry": {"coordinates":[-86.362409,43.761312],"type":"Point"}
}