{
  "type": "Feature",
  "properties": {
    "iso:country":"US",
    "sg:address":"22606 Corteville St",
    "sg:city":"St Clair Shores",
    "sg:classifiers":[
        {
            "category":"Shopping",
            "subcategory":"Hobbies, Toys, & Games",
            "type":"Retail Goods"
        }
    ],
    "sg:phone":"+1 248 589 0462",
    "sg:postcode":"48081",
    "sg:province":"MI",
    "sg:tags":[
        "magician",
        "supply"
    ],
    "wof:name":"Wunderground",
    "wof:placetype":"venue"
},
  "geometry": {"coordinates":[-82.88462,42.50721],"type":"Point"}
}