{
  "type": "Feature",
  "properties": {
    "iso:country":"US",
    "sg:address":"1499 Wealthy St SE",
    "sg:city":"Grand Rapids",
    "sg:classifiers":[
        {
            "category":"Food & Beverages",
            "subcategory":"Groceries & Convenience Stores",
            "type":"Retail Goods"
        }
    ],
    "sg:phone":"+1 616 451 2711",
    "sg:postcode":"49506",
    "sg:province":"MI",
    "sg:tags":[
        "grocer"
    ],
    "wof:name":"Sami's Party Store",
    "wof:placetype":"venue"
},
  "geometry": {"coordinates":[-85.63400300000001,42.955504],"type":"Point"}
}