{
  "type": "Feature",
  "properties": {
    "iso:country":"US",
    "sg:address":"1172 Amos St",
    "sg:city":"Pontiac",
    "sg:classifiers":[
        {
            "category":"Shopping",
            "subcategory":"Gifts & Souvenirs",
            "type":"Retail Goods"
        }
    ],
    "sg:phone":"+1 248 390 1219",
    "sg:postcode":"48342",
    "sg:province":"MI",
    "wof:name":"Gifts DElegance",
    "wof:placetype":"venue"
},
  "geometry": {"coordinates":[-83.258002,42.654927],"type":"Point"}
}