{
  "type": "Feature",
  "properties": {
    "iso:country":"US",
    "sg:address":"29100 Northwestern Hwy",
    "sg:city":"Southfield",
    "sg:classifiers":[
        {
            "category":"Building & Trades",
            "subcategory":"Construction",
            "type":"Services"
        }
    ],
    "sg:phone":"+1 248 350 3322",
    "sg:postcode":"48034",
    "sg:province":"MI",
    "sg:tags":[
        "contractor"
    ],
    "wof:name":"Singer Building Company",
    "wof:placetype":"venue"
},
  "geometry": {"coordinates":[-83.310303,42.501999],"type":"Point"}
}