{
  "type": "Feature",
  "properties": {
    "iso:country":"US",
    "sg:address":"512 Williamsport Ct",
    "sg:city":"White Lake",
    "sg:classifiers":[
        {
            "category":"Professional",
            "subcategory":"Management & Consulting",
            "type":"Services"
        }
    ],
    "sg:phone":"+1 248 698 4568",
    "sg:postcode":"48386",
    "sg:province":"MI",
    "sg:tags":[
        "marketing"
    ],
    "wof:name":"M & M Marketing",
    "wof:placetype":"venue"
},
  "geometry": {"coordinates":[-83.454989,42.627649],"type":"Point"}
}