{
  "type": "Feature",
  "properties": {
    "iso:country":"US",
    "sg:address":"73 Mirabeau Ct",
    "sg:city":"Rochester Hills",
    "sg:classifiers":[
        {
            "category":"Real Estate",
            "subcategory":"Real Estate Agent",
            "type":"Services"
        }
    ],
    "sg:phone":"+1 248 246 1658",
    "sg:postcode":"48307",
    "sg:province":"MI",
    "sg:tags":[
        "appraiser"
    ],
    "wof:name":"Gott Appraisal Inc",
    "wof:placetype":"venue"
},
  "geometry": {"coordinates":[-83.104812,42.668327],"type":"Point"}
}