{
  "type": "Feature",
  "properties": {
    "iso:country":"US",
    "sg:address":"31636 Schoolcraft Rd",
    "sg:city":"Livonia",
    "sg:classifiers":[
        {
            "category":"Health Services",
            "subcategory":"Dentist",
            "type":"Services"
        }
    ],
    "sg:phone":"+1 734 522 7313",
    "sg:postcode":"48150",
    "sg:province":"MI",
    "wof:name":"Sivertson John DDS Ms",
    "wof:placetype":"venue"
},
  "geometry": {"coordinates":[-83.356056,42.383478],"type":"Point"}
}