{
  "type": "Feature",
  "properties": {
    "iso:country":"US",
    "sg:address":"6767 Main St",
    "sg:city":"Caseville",
    "sg:classifiers":[
        {
            "category":"Government",
            "subcategory":"Office",
            "type":"Public Place"
        }
    ],
    "sg:phone":"+1 989 856 2102",
    "sg:postcode":"48725",
    "sg:province":"MI",
    "sg:tags":[
        "village"
    ],
    "wof:name":"Caseville Village Hall",
    "wof:placetype":"venue"
},
  "geometry": {"coordinates":[-83.27227000000001,43.939027],"type":"Point"}
}