{
  "type": "Feature",
  "properties": {
    "iso:country":"US",
    "sg:address":"15111 Northville Rd",
    "sg:city":"Plymouth",
    "sg:classifiers":[
        {
            "category":"Professional",
            "subcategory":"Accounting & Tax Preparation",
            "type":"Services"
        }
    ],
    "sg:phone":"+1 734 420 0294",
    "sg:postcode":"48170",
    "sg:province":"MI",
    "sg:tags":[
        "bookkeeping"
    ],
    "wof:name":"Polmar Inc",
    "wof:placetype":"venue"
},
  "geometry": {"coordinates":[-83.46874,42.395363],"type":"Point"}
}