{
  "type": "Feature",
  "properties": {
    "iso:country":"US",
    "sg:address":"970 W Long Lake Rd",
    "sg:city":"Bloomfield Hills",
    "sg:classifiers":[
        {
            "category":"Building & Trades",
            "subcategory":"Equipment Rental",
            "type":"Services"
        }
    ],
    "sg:phone":"+1 248 646 8476",
    "sg:postcode":"48302",
    "sg:province":"MI",
    "wof:name":"B & L Leasing Inc",
    "wof:placetype":"venue"
},
  "geometry": {"coordinates":[-83.27866400000001,42.581468],"type":"Point"}
}