{
  "type": "Feature",
  "properties": {
    "iso:country":"US",
    "sg:address":"4353 US Hwy 10",
    "sg:city":"Sears",
    "sg:classifiers":[
        {
            "category":"Building & Trades",
            "subcategory":"Landscaping Services",
            "type":"Services"
        }
    ],
    "sg:phone":"+1 231 734 2451",
    "sg:postcode":"49679",
    "sg:province":"MI",
    "sg:tags":[
        "topsoil"
    ],
    "wof:name":"Morgan Farm & Gardens",
    "wof:placetype":"venue"
},
  "geometry": {"coordinates":[-85.16861400000001,43.90064],"type":"Point"}
}