{
  "type": "Feature",
  "properties": {
    "iso:country":"US",
    "sg:address":"6385 N Monroe St",
    "sg:city":"Monroe",
    "sg:classifiers":[
        {
            "category":"Building & Trades",
            "subcategory":"Landscaping Services",
            "type":"Services"
        }
    ],
    "sg:phone":"+1 734 379 9522",
    "sg:postcode":"48162",
    "sg:province":"MI",
    "sg:tags":[
        "lawn",
        "maintenance",
        "grounds"
    ],
    "wof:name":"Daleo Lawn Svc",
    "wof:placetype":"venue"
},
  "geometry": {"coordinates":[-83.37349,41.969639],"type":"Point"}
}