{
  "type": "Feature",
  "properties": {
    "iso:country":"US",
    "sg:address":"1049 Olivia Ave",
    "sg:city":"Ann Arbor",
    "sg:classifiers":[
        {
            "category":"Real Estate",
            "subcategory":"Developer",
            "type":"Services"
        }
    ],
    "sg:phone":"+1 734 995 9651",
    "sg:postcode":"48104",
    "sg:province":"MI",
    "wof:name":"Jones Properties",
    "wof:placetype":"venue"
},
  "geometry": {"coordinates":[-83.731359,42.269063],"type":"Point"}
}