{
  "type": "Feature",
  "properties": {
    "iso:country":"US",
    "sg:address":"641 S Crystal Ave",
    "sg:city":"Benton Harbor",
    "sg:classifiers":[
        {
            "category":"Retail",
            "subcategory":"Animal Services",
            "type":"Services"
        }
    ],
    "sg:phone":"+1 269 927 3303",
    "sg:postcode":"49022",
    "sg:province":"MI",
    "sg:tags":[
        "shelter"
    ],
    "wof:name":"Humane Society-Southwestern",
    "wof:placetype":"venue"
},
  "geometry": {"coordinates":[-86.417315,42.106085],"type":"Point"}
}