{
  "type": "Feature",
  "properties": {
    "iso:country":"US",
    "sg:address":"1111 S Commerce Rd",
    "sg:city":"Walled Lake",
    "sg:classifiers":[
        {
            "category":"Retail",
            "subcategory":"Auto Rental",
            "type":"Services"
        }
    ],
    "sg:phone":"+1 248 960 3773",
    "sg:postcode":"48390",
    "sg:province":"MI",
    "sg:tags":[
        "renting",
        "automobile"
    ],
    "wof:name":"Enterprise Rent-A-Car",
    "wof:placetype":"venue"
},
  "geometry": {"coordinates":[-83.478104,42.544805],"type":"Point"}
}