{
  "type": "Feature",
  "properties": {
    "iso:country":"US",
    "sg:address":"15 E Washington St",
    "sg:city":"Coldwater",
    "sg:classifiers":[
        {
            "category":"Health Services",
            "subcategory":"Doctor",
            "type":"Services"
        }
    ],
    "sg:phone":"+1 517 279 1730",
    "sg:postcode":"49036",
    "sg:province":"MI",
    "wof:name":"Midwest Oral Mxllfcial Surgery",
    "wof:placetype":"venue"
},
  "geometry": {"coordinates":[-85.001074,41.93805],"type":"Point"}
}