{
  "type": "Feature",
  "properties": {
    "iso:country":"US",
    "sg:address":"3596 Barberry Cir",
    "sg:city":"Wixom",
    "sg:classifiers":[
        {
            "category":"Building & Trades",
            "subcategory":"Construction",
            "type":"Services"
        }
    ],
    "sg:phone":"+1 248 669 1034",
    "sg:postcode":"48393",
    "sg:province":"MI",
    "sg:tags":[
        "house"
    ],
    "wof:name":"Factor Home Improvements",
    "wof:placetype":"venue"
},
  "geometry": {"coordinates":[-83.54231900000001,42.550948],"type":"Point"}
}