{
  "type": "Feature",
  "properties": {
    "iso:country":"US",
    "sg:address":"7901 Squires Ct NE",
    "sg:city":"Rockford",
    "sg:classifiers":[
        {
            "category":"Banks & Credit Unions",
            "subcategory":"Financial Services",
            "type":"Services"
        }
    ],
    "sg:phone":"+1 616 874 8029",
    "sg:postcode":"49341",
    "sg:province":"MI",
    "sg:tags":[
        "investor"
    ],
    "wof:name":"Common Cash Club",
    "wof:placetype":"venue"
},
  "geometry": {"coordinates":[-85.473032,43.125526],"type":"Point"}
}