{
  "type": "Feature",
  "properties": {
    "iso:country":"US",
    "sg:address":"2069 W Wattles Rd",
    "sg:city":"Troy",
    "sg:classifiers":[
        {
            "category":"Professional",
            "subcategory":"Computer Services",
            "type":"Services"
        }
    ],
    "sg:phone":"+1 248 643 7393",
    "sg:postcode":"48098",
    "sg:province":"MI",
    "sg:tags":[
        "consultant",
        "designer"
    ],
    "wof:name":"Nexor Technologies Inc",
    "wof:placetype":"venue"
},
  "geometry": {"coordinates":[-83.188433,42.576145],"type":"Point"}
}