{
  "type": "Feature",
  "properties": {
    "iso:country":"US",
    "sg:address":"18354 Fenkell St",
    "sg:city":"Detroit",
    "sg:classifiers":[
        {
            "category":"Restaurant",
            "type":"Food & Drink"
        }
    ],
    "sg:menulink":"http://www.allmenus.com/mi/detroit/247107-the-house-soul-food/menu/",
    "sg:phone":"+1 313 273 6643",
    "sg:postcode":"48223",
    "sg:province":"MI",
    "sg:tags":[
        "american",
        "soul"
    ],
    "wof:name":"The House Soul Food",
    "wof:placetype":"venue"
},
  "geometry": {"coordinates":[-83.221532,42.401031],"type":"Point"}
}