{
  "type": "Feature",
  "properties": {
    "iso:country":"US",
    "sg:address":"555 S Old Woodward Ave Ste 12L",
    "sg:city":"Birmingham",
    "sg:classifiers":[
        {
            "category":"Sports & Exercise",
            "subcategory":"Gym",
            "type":"Entertainment"
        }
    ],
    "sg:phone":"+1 248 644 5700",
    "sg:postcode":"48009",
    "sg:province":"MI",
    "sg:tags":[
        "trainer"
    ],
    "sg:website":"www.petesbodyshop.net/",
    "wof:name":"Pete's Body Shop Personal Fitness Training",
    "wof:placetype":"venue"
},
  "geometry": {"coordinates":[-83.21004000000001,42.543086],"type":"Point"}
}