{
  "type": "Feature",
  "properties": {
    "iso:country":"US",
    "sg:address":"301 S Main St",
    "sg:city":"Ann Arbor",
    "sg:classifiers":[
        {
            "category":"Museum",
            "type":"Entertainment"
        }
    ],
    "sg:phone":"+1 734 761 4620",
    "sg:postcode":"48104",
    "sg:province":"MI",
    "sg:tags":[
        "gallery",
        "jewelry"
    ],
    "wof:name":"Selo Shevel Gallery",
    "wof:placetype":"venue"
},
  "geometry": {"coordinates":[-83.748651,42.277954],"type":"Point"}
}