{
  "type": "Feature",
  "properties": {
    "iso:country":"US",
    "sg:address":"11779 E 8 Mile Rd",
    "sg:city":"Warren",
    "sg:classifiers":[
        {
            "category":"Fast Food",
            "type":"Food & Drink"
        },
        {
            "category":"Food & Beverages",
            "subcategory":"Meat & Fish",
            "type":"Retail Goods"
        }
    ],
    "sg:phone":"+1 586 773 1243",
    "sg:postcode":"48089",
    "sg:province":"MI",
    "sg:tags":[
        "burger",
        "hot",
        "dog"
    ],
    "sg:website":"www.wendys.com",
    "wof:name":"Wendy's Old Fashioned Hamburgers",
    "wof:placetype":"venue"
},
  "geometry": {"coordinates":[-83.002796,42.449275],"type":"Point"}
}