{
  "type": "Feature",
  "properties": {
    "iso:country":"US",
    "sg:address":"7345 E Washington Rd",
    "sg:city":"Ithaca",
    "sg:phone":"+1 989 875 2373",
    "sg:postcode":"48847",
    "sg:province":"MI",
    "sg:tags":[
        "farm",
        "corn",
        "grain",
        "cash"
    ],
    "wof:name":"Scott Mc Crory",
    "wof:placetype":"venue"
},
  "geometry": {"coordinates":[-84.453973,43.291877],"type":"Point"}
}