{
  "type": "Feature",
  "properties": {
    "iso:country":"US",
    "sg:address":"17132 Hall Rd",
    "sg:city":"Clinton Twp",
    "sg:classifiers":[
        {
            "category":"Building & Trades",
            "subcategory":"Construction",
            "type":"Services"
        }
    ],
    "sg:phone":"+1 586 226 3661",
    "sg:postcode":"48038",
    "sg:province":"MI",
    "sg:tags":[
        "home",
        "builder"
    ],
    "wof:name":"Lexor Group Marquis Homes",
    "wof:placetype":"venue"
},
  "geometry": {"coordinates":[-82.95078100000001,42.627542],"type":"Point"}
}