{
  "type": "Feature",
  "properties": {
    "iso:country":"US",
    "sg:address":"1485 Division Dr",
    "sg:city":"Hartland",
    "sg:classifiers":[
        {
            "category":"Building & Trades",
            "subcategory":"Construction",
            "type":"Services"
        }
    ],
    "sg:phone":"+1 810 632 7066",
    "sg:postcode":"48353",
    "sg:province":"MI",
    "sg:tags":[
        "contractor"
    ],
    "wof:name":"Tile Tom",
    "wof:placetype":"venue"
},
  "geometry": {"coordinates":[-83.736165,42.626533],"type":"Point"}
}