{
  "type": "Feature",
  "properties": {
    "iso:country":"US",
    "sg:address":"7256 Bowers Rd",
    "sg:city":"Imlay City",
    "sg:classifiers":[
        {
            "category":"Manufacturing",
            "subcategory":"Metals",
            "type":"Manufacturing & Wholesale Goods"
        },
        {
            "category":"Manufacturing",
            "subcategory":"Motor Vehicles & Parts",
            "type":"Manufacturing & Wholesale Goods"
        }
    ],
    "sg:phone":"+1 810 724 2000",
    "sg:postcode":"48444",
    "sg:province":"MI",
    "sg:tags":[
        "body",
        "repair",
        "mfg",
        "auto",
        "tr",
        "general",
        "truck",
        "bus",
        "fabrication",
        "structural"
    ],
    "wof:name":"Mark Body Truck & Equipment Co",
    "wof:placetype":"venue"
},
  "geometry": {"coordinates":[-83.059764,43.06602],"type":"Point"}
}