{
  "type": "Feature",
  "properties": {
    "iso:country":"US",
    "sg:address":"1341 S Center Rd",
    "sg:city":"Burton",
    "sg:classifiers":[
        {
            "category":"Restaurant",
            "type":"Food & Drink"
        }
    ],
    "sg:phone":"+1 810 743 9600",
    "sg:postcode":"48509",
    "sg:province":"MI",
    "wof:name":"Walli's Restaurant",
    "wof:placetype":"venue"
},
  "geometry": {"coordinates":[-83.634697,43.0168],"type":"Point"}
}