{
  "type": "Feature",
  "properties": {
    "iso:country":"US",
    "sg:address":"113 E Baraga Ave",
    "sg:city":"Marquette",
    "sg:classifiers":[
        {
            "category":"Wholesale",
            "subcategory":"Machinery & Supplies",
            "type":"Manufacturing & Wholesale Goods"
        }
    ],
    "sg:phone":"+1 906 228 9083",
    "sg:postcode":"49855",
    "sg:province":"MI",
    "sg:tags":[
        "asbestos",
        "abatement"
    ],
    "wof:name":"Debco Equipment and Supply Co",
    "wof:placetype":"venue"
},
  "geometry": {"coordinates":[-87.39288999999999,46.540619],"type":"Point"}
}