{
  "type": "Feature",
  "properties": {
    "iso:country":"US",
    "sg:address":"46499 Oak Manor Ct E",
    "sg:city":"Canton",
    "sg:classifiers":[
        {
            "category":"Professional",
            "subcategory":"Business Services",
            "type":"Services"
        }
    ],
    "sg:phone":"+1 734 673 2810",
    "sg:postcode":"48187",
    "sg:province":"MI",
    "sg:tags":[
        "financial"
    ],
    "wof:name":"Amdg Bus Advissory Svcs PLC",
    "wof:placetype":"venue"
},
  "geometry": {"coordinates":[-83.50514800000001,42.333312],"type":"Point"}
}