{
  "type": "Feature",
  "properties": {
    "iso:country":"US",
    "sg:address":"1000 W University Dr",
    "sg:city":"Rochester Hills",
    "sg:classifiers":[
        {
            "category":"Professional",
            "subcategory":"Accounting & Tax Preparation",
            "type":"Services"
        }
    ],
    "sg:phone":"+1 248 656 2200",
    "sg:postcode":"48307",
    "sg:province":"MI",
    "sg:tags":[
        "auditing",
        "return",
        "filing"
    ],
    "wof:name":"Craun Freeman & Associates PC",
    "wof:placetype":"venue"
},
  "geometry": {"coordinates":[-83.14848000000001,42.681774],"type":"Point"}
}