{
  "type": "Feature",
  "properties": {
    "iso:country":"US",
    "sg:address":"400 Renaissance Center",
    "sg:city":"Detroit",
    "sg:classifiers":[
        {
            "category":"Professional",
            "subcategory":"Management & Consulting",
            "type":"Services"
        }
    ],
    "sg:phone":"+1 313 259 5060",
    "sg:postcode":"48243",
    "sg:province":"MI",
    "sg:tags":[
        "public",
        "relations"
    ],
    "wof:name":"Midwest Public Relations Off",
    "wof:placetype":"venue"
},
  "geometry": {"coordinates":[-83.039343,42.33032],"type":"Point"}
}