{
  "type": "Feature",
  "properties": {
    "iso:country":"US",
    "sg:address":"6925 Junction Rd",
    "sg:city":"Bridgeport",
    "sg:classifiers":[
        {
            "category":"Organizations",
            "subcategory":"Religious Organization",
            "type":"Services"
        }
    ],
    "sg:phone":"+1 517 652 7304",
    "sg:postcode":"48722",
    "sg:province":"MI",
    "wof:name":"Episcopal Group Home Inc",
    "wof:placetype":"venue"
},
  "geometry": {"coordinates":[-83.82511100000001,43.335862],"type":"Point"}
}