{
  "type": "Feature",
  "properties": {
    "iso:country":"US",
    "sg:address":"23400 Michigan Ave Ste P27",
    "sg:city":"Dearborn",
    "sg:classifiers":[
        {
            "category":"Professional",
            "subcategory":"Lawyer & Legal Services",
            "type":"Services"
        }
    ],
    "sg:phone":"+1 313 216 8157",
    "sg:postcode":"48124",
    "sg:province":"MI",
    "sg:tags":[
        "divorce",
        "law",
        "family"
    ],
    "wof:name":"Popescu - Seeley Valentina Pllc",
    "wof:placetype":"venue"
},
  "geometry": {"coordinates":[-83.263436,42.302091],"type":"Point"}
}