{
  "type": "Feature",
  "properties": {
    "iso:country":"US",
    "sg:address":"1234 E Broomfield St",
    "sg:city":"Mount Pleasant",
    "sg:classifiers":[
        {
            "category":"Professional",
            "subcategory":"Accounting & Tax Preparation",
            "type":"Services"
        }
    ],
    "sg:phone":"+1 989 779 1188",
    "sg:postcode":"48858",
    "sg:province":"MI",
    "sg:tags":[
        "auditing",
        "bookkeeping"
    ],
    "wof:name":"Gartner & Howard Cpas PC",
    "wof:placetype":"venue"
},
  "geometry": {"coordinates":[-84.75508600000001,43.582636],"type":"Point"}
}