{
  "type": "Feature",
  "properties": {
    "iso:country":"US",
    "sg:address":"18184 Mack Ave",
    "sg:city":"Grosse Pointe",
    "sg:classifiers":[
        {
            "category":"Autos & Motor Vehicles",
            "subcategory":"Fuel & Gas Station",
            "type":"Retail Goods"
        }
    ],
    "sg:phone":"+1 313 884 5599",
    "sg:postcode":"48230",
    "sg:province":"MI",
    "wof:name":"Beaupre Service Inc",
    "wof:placetype":"venue"
},
  "geometry": {"coordinates":[-82.91480300000001,42.407001],"type":"Point"}
}