{
  "type": "Feature",
  "properties": {
    "iso:country":"US",
    "sg:address":"201 E Main St",
    "sg:city":"Harbor Springs",
    "sg:classifiers":[
        {
            "category":"Food & Beverages",
            "subcategory":"Candy",
            "type":"Retail Goods"
        },
        {
            "category":"Manufacturing",
            "subcategory":"Food",
            "type":"Manufacturing & Wholesale Goods"
        }
    ],
    "sg:phone":"+1 231 526 6121",
    "sg:postcode":"49740",
    "sg:province":"MI",
    "sg:tags":[
        "confectionery",
        "mfg"
    ],
    "wof:name":"Howse's Candy Haus",
    "wof:placetype":"venue"
},
  "geometry": {"coordinates":[-84.986075,45.430301],"type":"Point"}
}