{
  "type": "Feature",
  "properties": {
    "iso:country":"US",
    "sg:address":"36 Ridge Rd",
    "sg:city":"Pleasant Rdg",
    "sg:classifiers":[
        {
            "category":"Building & Trades",
            "subcategory":"Construction",
            "type":"Services"
        }
    ],
    "sg:phone":"+1 248 548 4300",
    "sg:postcode":"48069",
    "sg:province":"MI",
    "sg:tags":[
        "contractor"
    ],
    "wof:name":"Rose Collection the",
    "wof:placetype":"venue"
},
  "geometry": {"coordinates":[-83.14830000000001,42.4706],"type":"Point"}
}