{
  "type": "Feature",
  "properties": {
    "iso:country":"US",
    "sg:address":"720 Huron Ave",
    "sg:city":"Port Huron",
    "sg:classifiers":[
        {
            "category":"Retail",
            "subcategory":"Repair Shop",
            "type":"Services"
        }
    ],
    "sg:phone":"+1 810 985 5976",
    "sg:postcode":"48060",
    "sg:province":"MI",
    "sg:tags":[
        "lock",
        "locksmith"
    ],
    "wof:name":"Acme Locksmiths",
    "wof:placetype":"venue"
},
  "geometry": {"coordinates":[-82.42442200000001,42.982072],"type":"Point"}
}