{
  "type": "Feature",
  "properties": {
    "iso:country":"US",
    "sg:address":"1203 Gratiot Ave",
    "sg:city":"Saginaw",
    "sg:classifiers":[
        {
            "category":"Personal",
            "subcategory":"Beauty Salon",
            "type":"Services"
        }
    ],
    "sg:phone":"+1 989 791 1235",
    "sg:postcode":"48602",
    "sg:province":"MI",
    "sg:tags":[
        "shop"
    ],
    "wof:name":"Salon Renaissance Inc",
    "wof:placetype":"venue"
},
  "geometry": {"coordinates":[-83.97838299999999,43.41491],"type":"Point"}
}