{
  "type": "Feature",
  "properties": {
    "iso:country":"US",
    "sg:address":"1677 Range Rd",
    "sg:city":"Kimball",
    "sg:classifiers":[
        {
            "category":"Autos & Motor Vehicles",
            "subcategory":"Fuel & Gas Station",
            "type":"Retail Goods"
        }
    ],
    "sg:phone":"+1 810 364 7802",
    "sg:postcode":"48074",
    "sg:province":"MI",
    "sg:tags":[
        "oil"
    ],
    "wof:name":"Speedway",
    "wof:placetype":"venue"
},
  "geometry": {"coordinates":[-82.502191,42.956086],"type":"Point"}
}