{
  "type": "Feature",
  "properties": {
    "iso:country":"US",
    "sg:address":"14041 Helmer Rd S",
    "sg:city":"Battle Creek",
    "sg:classifiers":[
        {
            "category":"Organizations",
            "subcategory":"Religious Organization",
            "type":"Services"
        }
    ],
    "sg:phone":"+1 269 962 5771",
    "sg:postcode":"49015",
    "sg:province":"MI",
    "sg:tags":[
        "church"
    ],
    "wof:name":"Battle Creek Hanmee Church",
    "wof:placetype":"venue"
},
  "geometry": {"coordinates":[-85.23811499999999,42.275224],"type":"Point"}
}