{
  "type": "Feature",
  "properties": {
    "iso:country":"US",
    "sg:address":"8027 M 37",
    "sg:city":"Wellston",
    "sg:classifiers":[
        {
            "category":"Recreation",
            "type":"Entertainment"
        }
    ],
    "sg:phone":"+1 231 862 3661",
    "sg:postcode":"49689",
    "sg:province":"MI",
    "sg:tags":[
        "charter",
        "canoe"
    ],
    "wof:name":"Bosman's Canoe Rental",
    "wof:placetype":"venue"
},
  "geometry": {"coordinates":[-85.806212,44.222133],"type":"Point"}
}