{
  "type": "Feature",
  "properties": {
    "iso:country":"US",
    "sg:address":"5685 Highland Rd",
    "sg:city":"Waterford",
    "sg:classifiers":[
        {
            "category":"Organizations",
            "subcategory":"Labor Organization",
            "type":"Services"
        }
    ],
    "sg:phone":"+1 248 673 4589",
    "sg:postcode":"48327",
    "sg:province":"MI",
    "wof:name":"Waterford Association",
    "wof:placetype":"venue"
},
  "geometry": {"coordinates":[-83.405945,42.659943],"type":"Point"}
}