{
  "type": "Feature",
  "properties": {
    "iso:country":"US",
    "sg:address":"14637 US Hwy 131",
    "sg:city":"Schoolcraft",
    "sg:classifiers":[
        {
            "category":"Home & Garden",
            "subcategory":"Garden Supply",
            "type":"Retail Goods"
        }
    ],
    "sg:phone":"+1 269 679 4526",
    "sg:postcode":"49087",
    "sg:province":"MI",
    "sg:tags":[
        "landscaping",
        "equipment"
    ],
    "wof:name":"C J's Statuary",
    "wof:placetype":"venue"
},
  "geometry": {"coordinates":[-85.636821,42.103682],"type":"Point"}
}