{
  "type": "Feature",
  "properties": {
    "iso:country":"US",
    "sg:address":"302 S State St",
    "sg:city":"Caro",
    "sg:classifiers":[
        {
            "category":"Retail",
            "subcategory":"Funeral Services",
            "type":"Services"
        }
    ],
    "sg:phone":"+1 989 673 3433",
    "sg:postcode":"48723",
    "sg:province":"MI",
    "sg:tags":[
        "plan"
    ],
    "wof:name":"Collon Funeral Home",
    "wof:placetype":"venue"
},
  "geometry": {"coordinates":[-83.39810199999999,43.487762],"type":"Point"}
}