{
  "type": "Feature",
  "properties": {
    "iso:country":"US",
    "sg:address":"6572 Lincoln St",
    "sg:city":"Gagetown",
    "sg:classifiers":[
        {
            "category":"Personal",
            "subcategory":"Beauty Salon",
            "type":"Services"
        }
    ],
    "sg:phone":"+1 989 665 2512",
    "sg:postcode":"48735",
    "sg:province":"MI",
    "wof:name":"Hairs-To-U",
    "wof:placetype":"venue"
},
  "geometry": {"coordinates":[-83.24401899999999,43.658247],"type":"Point"}
}