{
  "type": "Feature",
  "properties": {
    "iso:country":"US",
    "sg:address":"18105 N Wind Dr",
    "sg:city":"Fraser",
    "sg:classifiers":[
        {
            "category":"Banks & Credit Unions",
            "subcategory":"Investment Brokerage",
            "type":"Services"
        }
    ],
    "sg:phone":"+1 586 293 6816",
    "sg:postcode":"48026",
    "sg:province":"MI",
    "sg:tags":[
        "advisory"
    ],
    "wof:name":"Simple Life Investment Grp",
    "wof:placetype":"venue"
},
  "geometry": {"coordinates":[-82.933849,42.528624],"type":"Point"}
}