{
  "type": "Feature",
  "properties": {
    "iso:country":"US",
    "sg:address":"44388 Thunder Bay Dr",
    "sg:city":"Clinton Township",
    "sg:classifiers":[
        {
            "category":"Professional",
            "subcategory":"Accounting & Tax Preparation",
            "type":"Services"
        }
    ],
    "sg:phone":"+1 586 286 5366",
    "sg:postcode":"48038",
    "sg:province":"MI",
    "sg:tags":[
        "return"
    ],
    "wof:name":"Bobs Account & Tax Services",
    "wof:placetype":"venue"
},
  "geometry": {"coordinates":[-82.930398,42.622955],"type":"Point"}
}