{
  "type": "Feature",
  "properties": {
    "iso:country":"US",
    "sg:address":"41225 Irwin Dr",
    "sg:city":"Harrison Twp",
    "sg:classifiers":[
        {
            "category":"Wholesale",
            "subcategory":"Electrical",
            "type":"Manufacturing & Wholesale Goods"
        }
    ],
    "sg:phone":"+1 586 469 0710",
    "sg:postcode":"48045",
    "sg:province":"MI",
    "sg:tags":[
        "electric",
        "motor"
    ],
    "wof:name":"A & C Electric Motor Sales",
    "wof:placetype":"venue"
},
  "geometry": {"coordinates":[-82.851817,42.603273],"type":"Point"}
}