{
  "type": "Feature",
  "properties": {
    "iso:country":"US",
    "sg:address":"10505 Co Rd 601",
    "sg:city":"Champion",
    "sg:classifiers":[
        {
            "category":"Organizations",
            "subcategory":"Religious Organization",
            "type":"Services"
        }
    ],
    "sg:phone":"+1 906 339 2129",
    "sg:postcode":"49814",
    "sg:province":"MI",
    "sg:tags":[
        "church"
    ],
    "wof:name":"Apostolic Lutheran Church",
    "wof:placetype":"venue"
},
  "geometry": {"coordinates":[-87.907786,46.485743],"type":"Point"}
}