{
  "type": "Feature",
  "properties": {
    "iso:country":"US",
    "sg:address":"2593 Abbe Rd",
    "sg:city":"Comins",
    "sg:phone":"+1 989 848 2289",
    "sg:postcode":"48619",
    "sg:province":"MI",
    "sg:tags":[
        "farm",
        "grain",
        "cash"
    ],
    "wof:name":"Truman Ross",
    "wof:placetype":"venue"
},
  "geometry": {"coordinates":[-84.05085699999999,44.768678],"type":"Point"}
}