{
  "type": "Feature",
  "properties": {
    "iso:country":"US",
    "sg:address":"1301 McPherson Park Dr",
    "sg:city":"Howell",
    "sg:classifiers":[
        {
            "category":"Building & Trades",
            "subcategory":"Cleaning & Sanitation",
            "type":"Services"
        }
    ],
    "sg:phone":"+1 517 545 1237",
    "sg:postcode":"48843",
    "sg:province":"MI",
    "sg:tags":[
        "maintenance"
    ],
    "wof:name":"Ellidle",
    "wof:placetype":"venue"
},
  "geometry": {"coordinates":[-83.950945,42.607334],"type":"Point"}
}