{
  "type": "Feature",
  "properties": {
    "iso:country":"US",
    "sg:address":"195 S Main St",
    "sg:city":"Northville",
    "sg:classifiers":[
        {
            "category":"Organizations",
            "subcategory":"Professional Association",
            "type":"Services"
        }
    ],
    "sg:phone":"+1 248 349 7640",
    "sg:postcode":"48167",
    "sg:province":"MI",
    "sg:tags":[
        "chamber",
        "commerce"
    ],
    "wof:name":"Northville Chamber of Commerce",
    "wof:placetype":"venue"
},
  "geometry": {"coordinates":[-83.475801,42.430502],"type":"Point"}
}