{
  "type": "Feature",
  "properties": {
    "iso:country":"US",
    "sg:address":"5125 W Dunbar Rd",
    "sg:city":"Monroe",
    "sg:classifiers":[
        {
            "category":"Recreation",
            "type":"Entertainment"
        }
    ],
    "sg:phone":"+1 734 269 6158",
    "sg:postcode":"48161",
    "sg:province":"MI",
    "wof:name":"Asian Martial Arts Academy",
    "wof:placetype":"venue"
},
  "geometry": {"coordinates":[-83.51987200000001,41.916865],"type":"Point"}
}