{
  "type": "Feature",
  "properties": {
    "iso:country":"US",
    "sg:address":"1509 E Dayton Rd",
    "sg:city":"Caro",
    "sg:classifiers":[
        {
            "category":"Building & Trades",
            "subcategory":"Construction",
            "type":"Services"
        }
    ],
    "sg:phone":"+1 989 673 7663",
    "sg:postcode":"48723",
    "sg:province":"MI",
    "sg:tags":[
        "bulldozing"
    ],
    "wof:name":"Kappen Excavating LLC",
    "wof:placetype":"venue"
},
  "geometry": {"coordinates":[-83.36663299999999,43.48734],"type":"Point"}
}