{
  "type": "Feature",
  "properties": {
    "iso:country":"US",
    "sg:address":"625 E Big Beaver Rd",
    "sg:city":"Troy",
    "sg:classifiers":[
        {
            "category":"Banks & Credit Unions",
            "subcategory":"Investment Brokerage",
            "type":"Services"
        }
    ],
    "sg:phone":"+1 248 740 0293",
    "sg:postcode":"48083",
    "sg:province":"MI",
    "sg:tags":[
        "consultant",
        "planning",
        "financial"
    ],
    "wof:name":"Stragetic Money Management Svc",
    "wof:placetype":"venue"
},
  "geometry": {"coordinates":[-83.128975,42.563092],"type":"Point"}
}