{
  "type": "Feature",
  "properties": {
    "iso:country":"US",
    "sg:address":"1100 E Ganson St",
    "sg:city":"Jackson",
    "sg:classifiers":[
        {
            "category":"Retail",
            "subcategory":"Auto Repair",
            "type":"Services"
        }
    ],
    "sg:phone":"+1 517 783 2364",
    "sg:postcode":"49201",
    "sg:province":"MI",
    "sg:tags":[
        "repairing",
        "automobile"
    ],
    "wof:name":"Crank & Go Auto Svc",
    "wof:placetype":"venue"
},
  "geometry": {"coordinates":[-84.39278,42.254756],"type":"Point"}
}