{
  "type": "Feature",
  "properties": {
    "iso:country":"US",
    "sg:address":"6555 Sashabaw Rd",
    "sg:city":"Clarkston",
    "sg:classifiers":[
        {
            "category":"Food & Beverages",
            "subcategory":"Groceries & Convenience Stores",
            "type":"Retail Goods"
        }
    ],
    "sg:phone":"+1 248 625 9289",
    "sg:postcode":"48346",
    "sg:province":"MI",
    "sg:tags":[
        "grocer"
    ],
    "wof:name":"Farmer Jack Market",
    "wof:placetype":"venue"
},
  "geometry": {"coordinates":[-83.379735,42.735662],"type":"Point"}
}