{
  "type": "Feature",
  "properties": {
    "iso:country":"US",
    "sg:address":"23851 Ford Rd",
    "sg:city":"Dearborn",
    "sg:classifiers":[
        {
            "category":"Health Services",
            "subcategory":"Dentist",
            "type":"Services"
        }
    ],
    "sg:phone":"+1 313 278 1400",
    "sg:postcode":"48128",
    "sg:province":"MI",
    "wof:name":"Nielson Gregory",
    "wof:placetype":"venue"
},
  "geometry": {"coordinates":[-83.270302,42.3269],"type":"Point"}
}