{
  "type": "Feature",
  "properties": {
    "iso:country":"US",
    "sg:address":"364 N Main St",
    "sg:city":"Watervliet",
    "sg:classifiers":[
        {
            "category":"Professional",
            "subcategory":"Accounting & Tax Preparation",
            "type":"Services"
        }
    ],
    "sg:phone":"+1 269 463 6971",
    "sg:postcode":"49098",
    "sg:province":"MI",
    "sg:tags":[
        "return",
        "filing"
    ],
    "wof:name":"Paw Paw Lake Accounting",
    "wof:placetype":"venue"
},
  "geometry": {"coordinates":[-86.260189,42.188433],"type":"Point"}
}