{
  "type": "Feature",
  "properties": {
    "iso:country":"US",
    "sg:address":"3412 Beck Rd",
    "sg:city":"Howell",
    "sg:classifiers":[
        {
            "category":"Building & Trades",
            "subcategory":"Construction",
            "type":"Services"
        }
    ],
    "sg:phone":"+1 517 548 2299",
    "sg:postcode":"48843",
    "sg:province":"MI",
    "sg:tags":[
        "home",
        "builder"
    ],
    "wof:name":"Unified Building Co",
    "wof:placetype":"venue"
},
  "geometry": {"coordinates":[-83.884156,42.577583],"type":"Point"}
}