{
  "type": "Feature",
  "properties": {
    "iso:country":"US",
    "sg:address":"18849 Floral St",
    "sg:city":"Livonia",
    "sg:classifiers":[
        {
            "category":"Retail",
            "subcategory":"Repair Shop",
            "type":"Services"
        }
    ],
    "sg:phone":"+1 248 777 3716",
    "sg:postcode":"48152",
    "sg:province":"MI",
    "wof:name":"American Priority One Services",
    "wof:placetype":"venue"
},
  "geometry": {"coordinates":[-83.32249,42.42657],"type":"Point"}
}