{
  "type": "Feature",
  "properties": {
    "iso:country":"US",
    "sg:address":"8177 Racine St",
    "sg:city":"Birch Run",
    "sg:classifiers":[
        {
            "category":"Education",
            "subcategory":"School",
            "type":"Public Place"
        }
    ],
    "sg:phone":"+1 989 624 0273",
    "sg:postcode":"48415",
    "sg:province":"MI",
    "sg:tags":[
        "alternative"
    ],
    "wof:name":"Birch Run Pre School",
    "wof:placetype":"venue"
},
  "geometry": {"coordinates":[-83.792053,43.251535],"type":"Point"}
}