{
  "type": "Feature",
  "properties": {
    "iso:country":"US",
    "sg:address":"10 E Auburn Rd",
    "sg:city":"Rochester Hills",
    "sg:classifiers":[
        {
            "category":"Manufacturing",
            "subcategory":"Glass & Minerals",
            "type":"Manufacturing & Wholesale Goods"
        }
    ],
    "sg:phone":"+1 248 852 4700",
    "sg:postcode":"48307",
    "sg:province":"MI",
    "sg:tags":[
        "stone",
        "cut",
        "product"
    ],
    "wof:name":"Stone Shop",
    "wof:placetype":"venue"
},
  "geometry": {"coordinates":[-83.125371,42.636259],"type":"Point"}
}