{
  "type": "Feature",
  "properties": {
    "iso:country":"US",
    "sg:address":"420 E Howard St",
    "sg:city":"Owosso",
    "sg:classifiers":[
        {
            "category":"Wholesale",
            "subcategory":"Seafood",
            "type":"Manufacturing & Wholesale Goods"
        }
    ],
    "sg:phone":"+1 989 725 1315",
    "sg:postcode":"48867",
    "sg:province":"MI",
    "wof:name":"Donlan's Fish & Seafoods Inc",
    "wof:placetype":"venue"
},
  "geometry": {"coordinates":[-84.166493,42.992783],"type":"Point"}
}