{
  "type": "Feature",
  "properties": {
    "iso:country":"US",
    "sg:address":"3431 N 5th St",
    "sg:city":"Niles",
    "sg:classifiers":[
        {
            "category":"Retail",
            "subcategory":"Repair Shop",
            "type":"Services"
        }
    ],
    "sg:phone":"+1 269 684 1105",
    "sg:postcode":"49120",
    "sg:province":"MI",
    "sg:tags":[
        "taxidermist"
    ],
    "wof:name":"Michael E Baker Taxidermist",
    "wof:placetype":"venue"
},
  "geometry": {"coordinates":[-86.233799,41.872527],"type":"Point"}
}