{
  "type": "Feature",
  "properties": {
    "iso:country":"US",
    "sg:address":"830 Carp River Dr",
    "sg:city":"Ishpeming",
    "sg:classifiers":[
        {
            "category":"Shopping",
            "subcategory":"Computers & Home Electronics",
            "type":"Retail Goods"
        }
    ],
    "sg:phone":"+1 906 486 9997",
    "sg:postcode":"49849",
    "sg:province":"MI",
    "sg:tags":[
        "software"
    ],
    "wof:name":"Radio Shack",
    "wof:placetype":"venue"
},
  "geometry": {"coordinates":[-87.680328,46.500648],"type":"Point"}
}