{
  "type": "Feature",
  "properties": {
    "iso:country":"US",
    "sg:address":"20723 Van Dyke Ave",
    "sg:city":"Warren",
    "sg:classifiers":[
        {
            "category":"Professional",
            "type":"Services"
        }
    ],
    "sg:phone":"+1 586 552 8000",
    "sg:postcode":"48089",
    "sg:province":"MI",
    "sg:tags":[
        "establishment"
    ],
    "wof:name":"Waff Group East Inc",
    "wof:placetype":"venue"
},
  "geometry": {"coordinates":[-83.024974,42.449022],"type":"Point"}
}