{
  "type": "Feature",
  "properties": {
    "iso:country":"US",
    "sg:address":"600 S 5th St",
    "sg:city":"Crystal Falls",
    "sg:classifiers":[
        {
            "category":"Travel",
            "subcategory":"Hotels & Motels",
            "type":"Entertainment"
        }
    ],
    "sg:phone":"+1 906 875 6655",
    "sg:postcode":"49920",
    "sg:province":"MI",
    "wof:name":"Cedar-Inn Motel",
    "wof:placetype":"venue"
},
  "geometry": {"coordinates":[-88.334008,46.089217],"type":"Point"}
}