{
  "type": "Feature",
  "properties": {
    "iso:country":"US",
    "sg:address":"1551 Vermont Ave",
    "sg:city":"Marysville",
    "sg:classifiers":[
        {
            "category":"Insurance",
            "subcategory":"Insurance Agent",
            "type":"Services"
        }
    ],
    "sg:phone":"+1 810 982 3662",
    "sg:postcode":"48040",
    "sg:province":"MI",
    "wof:name":"Dandron & Assoc Insurance",
    "wof:placetype":"venue"
},
  "geometry": {"coordinates":[-82.483161,42.906312],"type":"Point"}
}