{
  "type": "Feature",
  "properties": {
    "iso:country":"US",
    "sg:address":"7400 Dixie Hwy",
    "sg:city":"Clarkston",
    "sg:classifiers":[
        {
            "category":"Retail",
            "subcategory":"Auto Repair",
            "type":"Services"
        }
    ],
    "sg:phone":"+1 248 620 9220",
    "sg:postcode":"48346",
    "sg:province":"MI",
    "sg:tags":[
        "van",
        "conversion",
        "truck",
        "accessory"
    ],
    "wof:name":"Truck King USA",
    "wof:placetype":"venue"
},
  "geometry": {"coordinates":[-83.435265,42.727625],"type":"Point"}
}