{
  "type": "Feature",
  "properties": {
    "iso:country":"US",
    "sg:address":"1281 Winding Way",
    "sg:city":"Temperance",
    "sg:classifiers":[
        {
            "category":"Retail",
            "subcategory":"Auto Repair",
            "type":"Services"
        }
    ],
    "sg:phone":"+1 734 847 2529",
    "sg:postcode":"48182",
    "sg:province":"MI",
    "sg:tags":[
        "carwash",
        "general"
    ],
    "wof:name":"Secor Detailing and R V Servic",
    "wof:placetype":"venue"
},
  "geometry": {"coordinates":[-83.57442,41.740771],"type":"Point"}
}