{
  "type": "Feature",
  "properties": {
    "iso:country":"US",
    "sg:address":"60 Brady Ln",
    "sg:city":"Bloomfield Hills",
    "sg:classifiers":[
        {
            "category":"Professional",
            "subcategory":"Business Services",
            "type":"Services"
        }
    ],
    "sg:phone":"+1 248 647 3219",
    "sg:postcode":"48304",
    "sg:province":"MI",
    "wof:name":"Pine Tree Interiors",
    "wof:placetype":"venue"
},
  "geometry": {"coordinates":[-83.236794,42.573198],"type":"Point"}
}