{
  "type": "Feature",
  "properties": {
    "iso:country":"US",
    "sg:address":"319 Bay St",
    "sg:city":"Petoskey",
    "sg:classifiers":[
        {
            "category":"Home & Garden",
            "subcategory":"Furniture",
            "type":"Retail Goods"
        }
    ],
    "sg:phone":"+1 231 348 6906",
    "sg:postcode":"49770",
    "sg:province":"MI",
    "sg:tags":[
        "equipment",
        "kitchen",
        "cabinet"
    ],
    "sg:website":"www.kitandco.com",
    "wof:name":"Kitchen & Co",
    "wof:placetype":"venue"
},
  "geometry": {"coordinates":[-84.95560500000001,45.375971],"type":"Point"}
}