{
  "type": "Feature",
  "properties": {
    "iso:country":"US",
    "sg:address":"14350 Rutland St",
    "sg:city":"Detroit",
    "sg:classifiers":[
        {
            "category":"Arts & Performance",
            "subcategory":"Theater",
            "type":"Entertainment"
        }
    ],
    "sg:phone":"+1 313 273 4398",
    "sg:postcode":"48227",
    "sg:province":"MI",
    "sg:tags":[
        "theatrical"
    ],
    "wof:name":"Reality Records",
    "wof:placetype":"venue"
},
  "geometry": {"coordinates":[-83.213492,42.393377],"type":"Point"}
}