{
  "type": "Feature",
  "properties": {
    "iso:country":"US",
    "sg:address":"3774 Joy Rd",
    "sg:city":"Detroit",
    "sg:classifiers":[
        {
            "category":"Home & Garden",
            "subcategory":"Building Materials",
            "type":"Retail Goods"
        }
    ],
    "sg:phone":"+1 313 896 3700",
    "sg:postcode":"48206",
    "sg:province":"MI",
    "sg:tags":[
        "equipment",
        "fixture",
        "lighting"
    ],
    "wof:name":"Annex Electric Supply Co",
    "wof:placetype":"venue"
},
  "geometry": {"coordinates":[-83.119698,42.369499],"type":"Point"}
}