{
  "type": "Feature",
  "properties": {
    "iso:country":"US",
    "sg:address":"3354 State Hwy 18",
    "sg:city":"Beaverton",
    "sg:classifiers":[
        {
            "category":"Shopping",
            "subcategory":"Computers & Home Electronics",
            "type":"Retail Goods"
        }
    ],
    "sg:phone":"+1 989 435 3762",
    "sg:postcode":"48612",
    "sg:province":"MI",
    "sg:tags":[
        "equipment",
        "dealer"
    ],
    "wof:name":"Genesis Computer Systems",
    "wof:placetype":"venue"
},
  "geometry": {"coordinates":[-84.495082,43.888611],"type":"Point"}
}