{
  "type": "Feature",
  "properties": {
    "iso:country":"US",
    "sg:address":"3850 28th St SE",
    "sg:city":"Grand Rapids",
    "sg:classifiers":[
        {
            "category":"Home & Garden",
            "subcategory":"Furniture",
            "type":"Retail Goods"
        }
    ],
    "sg:phone":"+1 616 942 1040",
    "sg:postcode":"49512",
    "sg:province":"MI",
    "sg:tags":[
        "mattress"
    ],
    "wof:name":"Jonathan Stevens Mattress Co",
    "wof:placetype":"venue"
},
  "geometry": {"coordinates":[-85.570153,42.912461],"type":"Point"}
}