{
  "type": "Feature",
  "properties": {
    "iso:country":"US",
    "sg:address":"1305 Ford Rd",
    "sg:city":"White Lake",
    "sg:classifiers":[
        {
            "category":"Social Services",
            "subcategory":"Adult Care",
            "type":"Services"
        }
    ],
    "sg:phone":"+1 248 887 0616",
    "sg:postcode":"48383",
    "sg:province":"MI",
    "sg:tags":[
        "foster"
    ],
    "wof:name":"Penny Lane Adult Foster Care",
    "wof:placetype":"venue"
},
  "geometry": {"coordinates":[-83.54193600000001,42.642891],"type":"Point"}
}