{
  "type": "Feature",
  "properties": {
    "iso:country":"US",
    "sg:address":"6767 Miller Rd",
    "sg:city":"Buckley",
    "sg:classifiers":[
        {
            "category":"Manufacturing",
            "subcategory":"Printing",
            "type":"Manufacturing & Wholesale Goods"
        }
    ],
    "sg:phone":"+1 231 263 7381",
    "sg:postcode":"49620",
    "sg:province":"MI",
    "sg:tags":[
        "publishing"
    ],
    "wof:name":"Klr Comminications Inc",
    "wof:placetype":"venue"
},
  "geometry": {"coordinates":[-85.708359,44.584781],"type":"Point"}
}