{
  "type": "Feature",
  "properties": {
    "iso:country":"US",
    "sg:address":"1640 E Paris Ave SE",
    "sg:city":"Grand Rapids",
    "sg:classifiers":[
        {
            "category":"Health Services",
            "subcategory":"Health Practitioner",
            "type":"Services"
        }
    ],
    "sg:phone":"+1 616 233 3599",
    "sg:postcode":"49546",
    "sg:province":"MI",
    "sg:tags":[
        "therapist",
        "physical"
    ],
    "wof:name":"Rehabpros",
    "wof:placetype":"venue"
},
  "geometry": {"coordinates":[-85.56992,42.933429],"type":"Point"}
}