{
  "type": "Feature",
  "properties": {
    "iso:country":"US",
    "sg:address":"2950 W Square Lake Rd Ste 212",
    "sg:city":"Troy",
    "sg:classifiers":[
        {
            "category":"Banks & Credit Unions",
            "subcategory":"Bank",
            "type":"Services"
        }
    ],
    "sg:phone":"+1 248 641 7300",
    "sg:postcode":"48098",
    "sg:province":"MI",
    "wof:name":"State Farm Insurance-Laine Reynolds",
    "wof:placetype":"venue"
},
  "geometry": {"coordinates":[-83.207397,42.605],"type":"Point"}
}