{
  "type": "Feature",
  "properties": {
    "iso:country":"US",
    "sg:address":"1036 Robb St",
    "sg:city":"East Lansing",
    "sg:classifiers":[
        {
            "category":"Recreation",
            "type":"Entertainment"
        }
    ],
    "sg:phone":"+1 517 351 1992",
    "sg:postcode":"48823",
    "sg:province":"MI",
    "wof:name":"Ticketman Tickets",
    "wof:placetype":"venue"
},
  "geometry": {"coordinates":[-84.460087,42.745669],"type":"Point"}
}