{
  "type": "Feature",
  "properties": {
    "iso:country":"US",
    "sg:address":"9950 Pebble Creek Ct",
    "sg:city":"Davisburg",
    "sg:classifiers":[
        {
            "category":"Professional",
            "subcategory":"Management & Consulting",
            "type":"Services"
        }
    ],
    "sg:phone":"+1 248 620 6280",
    "sg:postcode":"48350",
    "sg:province":"MI",
    "sg:tags":[
        "marketing",
        "consultant"
    ],
    "wof:name":"Trajectory Limited",
    "wof:placetype":"venue"
},
  "geometry": {"coordinates":[-83.486552,42.754809],"type":"Point"}
}