{
  "type": "Feature",
  "properties": {
    "iso:country":"US",
    "sg:address":"17901 Huron River Dr Ste 103",
    "sg:city":"New Boston",
    "sg:classifiers":[
        {
            "category":"Sports & Exercise",
            "subcategory":"Gym",
            "type":"Entertainment"
        }
    ],
    "sg:phone":"+1 734 753 9918",
    "sg:postcode":"48164",
    "sg:province":"MI",
    "sg:tags":[
        "trainer"
    ],
    "sg:website":"www.curves.com",
    "wof:name":"Curves For Women",
    "wof:placetype":"venue"
},
  "geometry": {"coordinates":[-83.403046,42.173349],"type":"Point"}
}