{
  "type": "Feature",
  "properties": {
    "iso:country":"US",
    "sg:address":"5907 Logan St S",
    "sg:city":"Lansing",
    "sg:classifiers":[
        {
            "category":"Organizations",
            "subcategory":"Religious Organization",
            "type":"Services"
        }
    ],
    "sg:phone":"+1 517 882 8918",
    "sg:postcode":"48911",
    "sg:province":"MI",
    "sg:tags":[
        "baptist",
        "church"
    ],
    "wof:name":"Grove Maple Baptist Church",
    "wof:placetype":"venue"
},
  "geometry": {"coordinates":[-84.579412,42.672423],"type":"Point"}
}