{
  "type": "Feature",
  "properties": {
    "iso:country":"US",
    "sg:address":"130 N 1st St",
    "sg:city":"Ann Arbor",
    "sg:classifiers":[
        {
            "category":"Professional",
            "subcategory":"Business Services",
            "type":"Services"
        }
    ],
    "sg:phone":"+1 734 665 5007",
    "sg:postcode":"48104",
    "sg:province":"MI",
    "wof:name":"Deardorff Design Resource",
    "wof:placetype":"venue"
},
  "geometry": {"coordinates":[-83.750828,42.282149],"type":"Point"}
}