{
  "type": "Feature",
  "properties": {
    "iso:country":"US",
    "sg:address":"3000 Auburn Rd",
    "sg:city":"Auburn Hills",
    "sg:classifiers":[
        {
            "category":"Professional",
            "type":"Services"
        }
    ],
    "sg:phone":"+1 248 852 5800",
    "sg:postcode":"48326",
    "sg:province":"MI",
    "sg:tags":[
        "establishment"
    ],
    "wof:name":"Auburn Utilities Inc",
    "wof:placetype":"venue"
},
  "geometry": {"coordinates":[-83.232069,42.6334],"type":"Point"}
}