{
  "type": "Feature",
  "properties": {
    "iso:country":"US",
    "sg:address":"10720 Wilson Rd",
    "sg:city":"New Buffalo",
    "sg:classifiers":[
        {
            "category":"Professional",
            "subcategory":"Computer Services",
            "type":"Services"
        }
    ],
    "sg:phone":"+1 269 469 5944",
    "sg:postcode":"49117",
    "sg:province":"MI",
    "sg:tags":[
        "consultant",
        "designer"
    ],
    "wof:name":"Action PCA",
    "wof:placetype":"venue"
},
  "geometry": {"coordinates":[-86.71221799999999,41.769981],"type":"Point"}
}