{
  "type": "Feature",
  "properties": {
    "iso:country":"US",
    "sg:address":"4310 Belvidere St",
    "sg:city":"Detroit",
    "sg:classifiers":[
        {
            "category":"Food & Beverages",
            "subcategory":"Liquor & Beverages",
            "type":"Retail Goods"
        }
    ],
    "sg:phone":"+1 313 922 0541",
    "sg:postcode":"48214",
    "sg:province":"MI",
    "sg:tags":[
        "beer",
        "spirit",
        "wine"
    ],
    "wof:name":"Thomas & Thomas Party Store",
    "wof:placetype":"venue"
},
  "geometry": {"coordinates":[-82.998802,42.376999],"type":"Point"}
}