{
  "type": "Feature",
  "properties": {
    "iso:country":"US",
    "sg:address":"19189 W 10 Mile Rd",
    "sg:city":"Southfield",
    "sg:classifiers":[
        {
            "category":"Professional",
            "subcategory":"Lawyer & Legal Services",
            "type":"Services"
        }
    ],
    "sg:phone":"+1 248 948 1022",
    "sg:postcode":"48075",
    "sg:province":"MI",
    "wof:name":"Muawad & Muawad PC",
    "wof:placetype":"venue"
},
  "geometry": {"coordinates":[-83.23291500000001,42.473094],"type":"Point"}
}