{
  "type": "Feature",
  "properties": {
    "iso:country":"US",
    "sg:address":"17570 W 12 Mile Rd",
    "sg:city":"Southfield",
    "sg:classifiers":[
        {
            "category":"Professional",
            "type":"Services"
        }
    ],
    "sg:phone":"+1 248 226 4005",
    "sg:postcode":"48076",
    "sg:province":"MI",
    "sg:tags":[
        "establishment"
    ],
    "wof:name":"Comtrust",
    "wof:placetype":"venue"
},
  "geometry": {"coordinates":[-83.222295,42.502536],"type":"Point"}
}