{
  "type": "Feature",
  "properties": {
    "iso:country":"US",
    "sg:address":"2155 Glen Echo Dr SE",
    "sg:city":"Grand Rapids",
    "sg:classifiers":[
        {
            "category":"Shopping",
            "type":"Retail Goods"
        }
    ],
    "sg:phone":"+1 800 870 7684",
    "sg:postcode":"49546",
    "sg:province":"MI",
    "sg:tags":[
        "gallery",
        "merchandise"
    ],
    "wof:name":"Art Douma Supplies Inc",
    "wof:placetype":"venue"
},
  "geometry": {"coordinates":[-85.602253,42.924141],"type":"Point"}
}