{
  "type": "Feature",
  "properties": {
    "iso:country":"US",
    "sg:address":"95 Studer Dr",
    "sg:city":"Grass Lake",
    "sg:classifiers":[
        {
            "category":"Retail",
            "subcategory":"Repair Shop",
            "type":"Services"
        }
    ],
    "sg:phone":"+1 517 783 2255",
    "sg:postcode":"49240",
    "sg:province":"MI",
    "sg:tags":[
        "electrical"
    ],
    "wof:name":"Gase Appliance Service",
    "wof:placetype":"venue"
},
  "geometry": {"coordinates":[-84.257406,42.285921],"type":"Point"}
}