{
  "type": "Feature",
  "properties": {
    "iso:country":"US",
    "sg:address":"6225 Cleveland Ave",
    "sg:city":"Stevensville",
    "sg:classifiers":[
        {
            "category":"Recreation",
            "type":"Entertainment"
        }
    ],
    "sg:phone":"+1 269 556 0251",
    "sg:postcode":"49127",
    "sg:province":"MI",
    "sg:tags":[
        "parks"
    ],
    "wof:name":"Lincoln Township Parks",
    "wof:placetype":"venue"
},
  "geometry": {"coordinates":[-86.49476199999999,42.002672],"type":"Point"}
}