{
  "type": "Feature",
  "properties": {
    "iso:country":"US",
    "sg:address":"5646 Klam Rd",
    "sg:city":"Columbiaville",
    "sg:classifiers":[
        {
            "category":"Farming",
            "subcategory":"Farm",
            "type":"Manufacturing & Wholesale Goods"
        }
    ],
    "sg:phone":"+1 810 793 7336",
    "sg:postcode":"48421",
    "sg:province":"MI",
    "sg:tags":[
        "crop",
        "general"
    ],
    "wof:name":"Christopher Muto",
    "wof:placetype":"venue"
},
  "geometry": {"coordinates":[-83.389971,43.194773],"type":"Point"}
}