{
  "type": "Feature",
  "properties": {
    "iso:country":"US",
    "sg:address":"341 Washington St",
    "sg:city":"Traverse City",
    "sg:classifiers":[
        {
            "category":"Organizations",
            "subcategory":"Religious Organization",
            "type":"Services"
        }
    ],
    "sg:phone":"+1 231 947 2330",
    "sg:postcode":"49684",
    "sg:province":"MI",
    "wof:name":"Grace Episcopal Church",
    "wof:placetype":"venue"
},
  "geometry": {"coordinates":[-85.616938,44.761822],"type":"Point"}
}