{
  "type": "Feature",
  "properties": {
    "iso:country":"US",
    "sg:address":"23347 Meadlawn Dr",
    "sg:city":"Dearborn Heights",
    "sg:classifiers":[
        {
            "category":"Professional",
            "subcategory":"Lawyer & Legal Services",
            "type":"Services"
        }
    ],
    "sg:phone":"+1 313 561 1174",
    "sg:postcode":"48127",
    "sg:province":"MI",
    "wof:name":"Monolidis Theodore Atty",
    "wof:placetype":"venue"
},
  "geometry": {"coordinates":[-83.263496,42.328899],"type":"Point"}
}