{
  "type": "Feature",
  "properties": {
    "iso:country":"US",
    "sg:address":"3951 E 10 Mile Rd",
    "sg:city":"Warren",
    "sg:classifiers":[
        {
            "category":"Autos & Motor Vehicles",
            "subcategory":"Fuel & Gas Station",
            "type":"Retail Goods"
        }
    ],
    "sg:phone":"+1 586 757 1280",
    "sg:postcode":"48091",
    "sg:province":"MI",
    "sg:tags":[
        "oil"
    ],
    "wof:name":"10 Mile & Ryan Citgo Auto Svc",
    "wof:placetype":"venue"
},
  "geometry": {"coordinates":[-83.06621800000001,42.476772],"type":"Point"}
}