{
  "type": "Feature",
  "properties": {
    "iso:country":"US",
    "sg:address":"36 N Center St",
    "sg:city":"Sebewaing",
    "sg:classifiers":[
        {
            "category":"Shopping",
            "type":"Retail Goods"
        }
    ],
    "sg:phone":"+1 989 883 3401",
    "sg:postcode":"48759",
    "sg:province":"MI",
    "sg:tags":[
        "craft",
        "gallery",
        "dealer"
    ],
    "wof:name":"K & B Country Creations",
    "wof:placetype":"venue"
},
  "geometry": {"coordinates":[-83.45124300000001,43.732809],"type":"Point"}
}