{
  "type": "Feature",
  "properties": {
    "iso:country":"US",
    "sg:address":"2677 Nodular Dr",
    "sg:city":"Saginaw",
    "sg:classifiers":[
        {
            "category":"Freight",
            "type":"Transportation"
        }
    ],
    "sg:phone":"+1 989 752 6805",
    "sg:postcode":"48601",
    "sg:province":"MI",
    "sg:tags":[
        "trucking"
    ],
    "wof:name":"Bay Shippers LLC",
    "wof:placetype":"venue"
},
  "geometry": {"coordinates":[-83.883781,43.448074],"type":"Point"}
}