{
  "type": "Feature",
  "properties": {
    "iso:country":"US",
    "sg:address":"653 Marston St",
    "sg:city":"Detroit",
    "sg:classifiers":[
        {
            "category":"Professional",
            "type":"Services"
        }
    ],
    "sg:phone":"+1 313 875 6561",
    "sg:postcode":"48202",
    "sg:province":"MI",
    "wof:name":"Kens Hospitality Service",
    "wof:placetype":"venue"
},
  "geometry": {"coordinates":[-83.070582,42.377058],"type":"Point"}
}