{
  "type": "Feature",
  "properties": {
    "iso:country":"US",
    "sg:address":"600 Randolph St",
    "sg:city":"Detroit",
    "sg:classifiers":[
        {
            "category":"Government",
            "subcategory":"Court House",
            "type":"Public Place"
        }
    ],
    "sg:phone":"+1 313 224 5030",
    "sg:postcode":"48226",
    "sg:province":"MI",
    "sg:tags":[
        "legal"
    ],
    "wof:name":"Corporation Counsel",
    "wof:placetype":"venue"
},
  "geometry": {"coordinates":[-83.043577,42.33228],"type":"Point"}
}