{
  "type": "Feature",
  "properties": {
    "iso:country":"US",
    "sg:address":"77 W Center St",
    "sg:city":"Saginaw",
    "sg:classifiers":[
        {
            "category":"Professional",
            "subcategory":"Computer Services",
            "type":"Services"
        }
    ],
    "sg:phone":"+1 989 757 0122",
    "sg:postcode":"48602",
    "sg:province":"MI",
    "sg:tags":[
        "datum",
        "programing",
        "custom"
    ],
    "wof:name":"EDS",
    "wof:placetype":"venue"
},
  "geometry": {"coordinates":[-83.971155,43.40466],"type":"Point"}
}