{
  "type": "Feature",
  "properties": {
    "iso:country":"US",
    "sg:address":"310 E Lansing Rd",
    "sg:city":"East Lansing",
    "sg:classifiers":[
        {
            "category":"Education",
            "subcategory":"Special Training",
            "type":"Public Place"
        }
    ],
    "sg:phone":"+1 517 355 9300",
    "sg:postcode":"48857",
    "sg:province":"MI",
    "wof:name":"Matrix",
    "wof:placetype":"venue"
},
  "geometry": {"coordinates":[-84.157932,42.85185],"type":"Point"}
}