{
  "type": "Feature",
  "properties": {
    "iso:country":"US",
    "sg:address":"122 N Oak St",
    "sg:city":"Buchanan",
    "sg:classifiers":[
        {
            "category":"Organizations",
            "subcategory":"Community Association",
            "type":"Services"
        }
    ],
    "sg:phone":"+1 269 695 7144",
    "sg:postcode":"49107",
    "sg:province":"MI",
    "sg:tags":[
        "fraternal"
    ],
    "wof:name":"Masonic Lodge",
    "wof:placetype":"venue"
},
  "geometry": {"coordinates":[-86.36100500000001,41.827974],"type":"Point"}
}