{
  "type": "Feature",
  "properties": {
    "iso:country":"US",
    "sg:address":"200 Arthur St",
    "sg:city":"Manistee",
    "sg:classifiers":[
        {
            "category":"Travel",
            "subcategory":"Hotels & Motels",
            "type":"Entertainment"
        }
    ],
    "sg:phone":"+1 231 723 9949",
    "sg:postcode":"49660",
    "sg:province":"MI",
    "wof:name":"Carriage Inn",
    "wof:placetype":"venue"
},
  "geometry": {"coordinates":[-86.316374,44.259851],"type":"Point"}
}