{
  "type": "Feature",
  "properties": {
    "iso:country":"US",
    "sg:address":"1377 Perry Lake Rd",
    "sg:city":"Ortonville",
    "sg:classifiers":[
        {
            "category":"Building & Trades",
            "subcategory":"Construction",
            "type":"Services"
        }
    ],
    "sg:phone":"+1 248 627 1011",
    "sg:postcode":"48462",
    "sg:province":"MI",
    "sg:tags":[
        "hanging",
        "contractor"
    ],
    "wof:name":"Special Touch Painting",
    "wof:placetype":"venue"
},
  "geometry": {"coordinates":[-83.394068,42.835377],"type":"Point"}
}