{
  "type": "Feature",
  "properties": {
    "iso:country":"US",
    "sg:address":"8870 Florence St",
    "sg:city":"Lake",
    "sg:classifiers":[
        {
            "category":"Organizations",
            "subcategory":"Religious Organization",
            "type":"Services"
        }
    ],
    "sg:phone":"+1 989 544 3391",
    "sg:postcode":"48632",
    "sg:province":"MI",
    "wof:name":"Liberty Bible Baptist Church",
    "wof:placetype":"venue"
},
  "geometry": {"coordinates":[-85.02597400000001,43.863163],"type":"Point"}
}