{
  "type": "Feature",
  "properties": {
    "iso:country":"US",
    "sg:address":"6930 Guinea Rd",
    "sg:city":"Charlotte",
    "sg:classifiers":[
        {
            "category":"Retail",
            "subcategory":"Auto Repair",
            "type":"Services"
        }
    ],
    "sg:phone":"+1 517 322 9374",
    "sg:postcode":"48813",
    "sg:province":"MI",
    "sg:tags":[
        "automotive"
    ],
    "wof:name":"American Dream Diversified",
    "wof:placetype":"venue"
},
  "geometry": {"coordinates":[-84.683179,42.670834],"type":"Point"}
}