{
  "type": "Feature",
  "properties": {
    "iso:country":"US",
    "sg:address":"1845 Thunderbird Dr",
    "sg:city":"Troy",
    "sg:classifiers":[
        {
            "category":"Manufacturing",
            "subcategory":"Rubber & Plastics",
            "type":"Manufacturing & Wholesale Goods"
        }
    ],
    "sg:phone":"+1 248 269 7696",
    "sg:postcode":"48084",
    "sg:province":"MI",
    "sg:tags":[
        "automotive",
        "engineering",
        "provides",
        "for",
        "mfg"
    ],
    "sg:website":"www.mathson.com",
    "wof:name":"Mathson Industries Inc",
    "wof:placetype":"venue"
},
  "geometry": {"coordinates":[-83.154129,42.550457],"type":"Point"}
}