{
  "type": "Feature",
  "properties": {
    "iso:country":"US",
    "sg:address":"734 Brady St",
    "sg:city":"Chesaning",
    "sg:classifiers":[
        {
            "category":"Organizations",
            "subcategory":"Religious Organization",
            "type":"Services"
        }
    ],
    "sg:phone":"+1 989 845 7878",
    "sg:postcode":"48616",
    "sg:province":"MI",
    "sg:tags":[
        "church"
    ],
    "wof:name":"New Wine Full Gospel Church",
    "wof:placetype":"venue"
},
  "geometry": {"coordinates":[-84.122044,43.187959],"type":"Point"}
}