{
  "type": "Feature",
  "properties": {
    "iso:country":"US",
    "sg:address":"26622 Woodward Ave",
    "sg:city":"Royal Oak",
    "sg:classifiers":[
        {
            "category":"Professional",
            "subcategory":"Lawyer & Legal Services",
            "type":"Services"
        }
    ],
    "sg:phone":"+1 248 546 7200",
    "sg:postcode":"48067",
    "sg:province":"MI",
    "wof:name":"David I Kaufman PC",
    "wof:placetype":"venue"
},
  "geometry": {"coordinates":[-83.157433,42.488256],"type":"Point"}
}