{
  "type": "Feature",
  "properties": {
    "iso:country":"US",
    "sg:address":"37623 W 12 Mile Rd",
    "sg:city":"Farmington Hills",
    "sg:classifiers":[
        {
            "category":"Wholesale",
            "subcategory":"Stationery",
            "type":"Manufacturing & Wholesale Goods"
        },
        {
            "category":"Manufacturing",
            "subcategory":"Printing",
            "type":"Manufacturing & Wholesale Goods"
        }
    ],
    "sg:phone":"+1 248 553 5833",
    "sg:postcode":"48331",
    "sg:province":"MI",
    "sg:tags":[
        "printer",
        "supply"
    ],
    "wof:name":"Galaxy Enterprises",
    "wof:placetype":"venue"
},
  "geometry": {"coordinates":[-83.42125299999999,42.497511],"type":"Point"}
}