{
  "type": "Feature",
  "properties": {
    "iso:country":"US",
    "sg:address":"7116 Tireman St",
    "sg:city":"Detroit",
    "sg:classifiers":[
        {
            "category":"Building & Trades",
            "subcategory":"Plumbing",
            "type":"Services"
        }
    ],
    "sg:phone":"+1 313 834 4400",
    "sg:postcode":"48204",
    "sg:province":"MI",
    "wof:name":"Washington Ben & Sons Plumbing & Heating",
    "wof:placetype":"venue"
},
  "geometry": {"coordinates":[-83.141296,42.3522],"type":"Point"}
}