{
  "type": "Feature",
  "properties": {
    "iso:country":"US",
    "sg:address":"23423 Coventry Woods Ln",
    "sg:city":"Southfield",
    "sg:classifiers":[
        {
            "category":"Professional",
            "subcategory":"Business Services",
            "type":"Services"
        }
    ],
    "sg:phone":"+1 248 809 2171",
    "sg:postcode":"48034",
    "sg:province":"MI",
    "sg:tags":[
        "holding"
    ],
    "wof:name":"Whr Holdings",
    "wof:placetype":"venue"
},
  "geometry": {"coordinates":[-83.27529699999999,42.492913],"type":"Point"}
}