{
  "type": "Feature",
  "properties": {
    "iso:country":"US",
    "sg:address":"2928 Cady Dr",
    "sg:city":"Brighton",
    "sg:classifiers":[
        {
            "category":"Professional",
            "subcategory":"Management & Consulting",
            "type":"Services"
        }
    ],
    "sg:phone":"+1 810 227 3470",
    "sg:postcode":"48114",
    "sg:province":"MI",
    "wof:name":"Aqem",
    "wof:placetype":"venue"
},
  "geometry": {"coordinates":[-83.74326600000001,42.561021],"type":"Point"}
}