{
  "type": "Feature",
  "properties": {
    "iso:country":"US",
    "sg:address":"8730 George F Bunker Blvd",
    "sg:city":"Sterling Heights",
    "sg:classifiers":[
        {
            "category":"Real Estate",
            "subcategory":"Real Estate Operator",
            "type":"Services"
        }
    ],
    "sg:phone":"+1 586 731 7182",
    "sg:postcode":"48313",
    "sg:province":"MI",
    "sg:tags":[
        "apartment"
    ],
    "wof:name":"Sterling Commons 1 Garage",
    "wof:placetype":"venue"
},
  "geometry": {"coordinates":[-83.022598,42.601101],"type":"Point"}
}