{
  "type": "Feature",
  "properties": {
    "iso:country":"US",
    "sg:address":"375 River St",
    "sg:city":"Manistee",
    "sg:classifiers":[
        {
            "category":"Organizations",
            "subcategory":"Non-profit Organization",
            "type":"Services"
        }
    ],
    "sg:phone":"+1 231 723 2331",
    "sg:postcode":"49660",
    "sg:province":"MI",
    "sg:tags":[
        "social"
    ],
    "wof:name":"United Way of Manistee County",
    "wof:placetype":"venue"
},
  "geometry": {"coordinates":[-86.322211,44.247796],"type":"Point"}
}