{
  "type": "Feature",
  "properties": {
    "iso:country":"US",
    "sg:address":"6353 N Elms Rd",
    "sg:city":"Flushing",
    "sg:classifiers":[
        {
            "category":"Building & Trades",
            "subcategory":"Construction",
            "type":"Services"
        }
    ],
    "sg:phone":"+1 810 659 7098",
    "sg:postcode":"48433",
    "sg:province":"MI",
    "sg:tags":[
        "house"
    ],
    "wof:name":"Pierson Gibbs Custom Home",
    "wof:placetype":"venue"
},
  "geometry": {"coordinates":[-83.81364499999999,43.098887],"type":"Point"}
}