{
  "type": "Feature",
  "properties": {
    "iso:country":"US",
    "sg:address":"2784 Edgar Rd",
    "sg:city":"Edmore",
    "sg:classifiers":[
        {
            "category":"Wholesale",
            "subcategory":"Machinery & Supplies",
            "type":"Manufacturing & Wholesale Goods"
        }
    ],
    "sg:phone":"+1 989 427 5678",
    "sg:postcode":"48829",
    "sg:province":"MI",
    "sg:tags":[
        "crane",
        "derrick"
    ],
    "wof:name":"Simon Crane Svc",
    "wof:placetype":"venue"
},
  "geometry": {"coordinates":[-85.025567,43.422436],"type":"Point"}
}