{
  "type": "Feature",
  "properties": {
    "iso:country":"US",
    "sg:address":"13193 Wayne Rd",
    "sg:city":"Livonia",
    "sg:classifiers":[
        {
            "category":"Communications",
            "subcategory":"Newspaper",
            "type":"Services"
        }
    ],
    "sg:phone":"+1 734 513 2212",
    "sg:postcode":"48150",
    "sg:province":"MI",
    "sg:tags":[
        "print",
        "medium"
    ],
    "sg:website":"www.phimcobindery.com",
    "wof:name":"Phimco Bindery",
    "wof:placetype":"venue"
},
  "geometry": {"coordinates":[-83.38870199999999,42.378601],"type":"Point"}
}