{
  "type": "Feature",
  "properties": {
    "iso:country":"US",
    "sg:address":"8826 E Huron Line Rd",
    "sg:city":"Ruth",
    "sg:classifiers":[
        {
            "category":"Building & Trades",
            "subcategory":"Construction",
            "type":"Services"
        }
    ],
    "sg:phone":"+1 989 864 3751",
    "sg:postcode":"48470",
    "sg:province":"MI",
    "sg:tags":[
        "excavating",
        "contractor"
    ],
    "wof:name":"Cliff A Messing Excavating",
    "wof:placetype":"venue"
},
  "geometry": {"coordinates":[-82.676852,43.688269],"type":"Point"}
}