{
  "type": "Feature",
  "properties": {
    "iso:country":"US",
    "sg:address":"4052 Bay Rd",
    "sg:city":"Saginaw",
    "sg:classifiers":[
        {
            "category":"Food & Beverages",
            "subcategory":"Specialty",
            "type":"Retail Goods"
        }
    ],
    "sg:phone":"+1 989 799 5998",
    "sg:postcode":"48603",
    "sg:province":"MI",
    "wof:name":"International Foods & Spices",
    "wof:placetype":"venue"
},
  "geometry": {"coordinates":[-83.97543400000001,43.468683],"type":"Point"}
}