{
  "type": "Feature",
  "properties": {
    "iso:country":"US",
    "sg:address":"725 S Adams Rd",
    "sg:city":"Birmingham",
    "sg:classifiers":[
        {
            "category":"Shopping",
            "subcategory":"Clothing, Apparel, & Fashions",
            "type":"Retail Goods"
        }
    ],
    "sg:phone":"+1 248 645 2702",
    "sg:postcode":"48009",
    "sg:province":"MI",
    "sg:tags":[
        "furnishing"
    ],
    "wof:name":"Grant Clothiers",
    "wof:placetype":"venue"
},
  "geometry": {"coordinates":[-83.205423,42.541771],"type":"Point"}
}