{
  "type": "Feature",
  "properties": {
    "iso:country":"US",
    "sg:address":"75 W Carleton Rd",
    "sg:city":"Hillsdale",
    "sg:classifiers":[
        {
            "category":"Restaurant",
            "type":"Food & Drink"
        }
    ],
    "sg:phone":"+1 517 437 3470",
    "sg:postcode":"49242",
    "sg:province":"MI",
    "wof:name":"Finish Lines",
    "wof:placetype":"venue"
},
  "geometry": {"coordinates":[-84.63888300000001,41.926494],"type":"Point"}
}