{
  "type": "Feature",
  "properties": {
    "iso:country":"US",
    "sg:address":"14488 Hanna Rd",
    "sg:city":"Spruce",
    "sg:classifiers":[
        {
            "category":"Building & Trades",
            "subcategory":"Construction",
            "type":"Services"
        }
    ],
    "sg:phone":"+1 989 471 2619",
    "sg:postcode":"48762",
    "sg:province":"MI",
    "sg:tags":[
        "tile",
        "dealer"
    ],
    "wof:name":"Di Marzo Ceramic Tile Co",
    "wof:placetype":"venue"
},
  "geometry": {"coordinates":[-83.42997200000001,44.865069],"type":"Point"}
}