{
  "type": "Feature",
  "properties": {
    "iso:country":"US",
    "sg:address":"1267 Elliott Ave",
    "sg:city":"Madison Heights",
    "sg:classifiers":[
        {
            "category":"Local Transit",
            "type":"Transportation"
        }
    ],
    "sg:phone":"+1 248 398 6474",
    "sg:postcode":"48071",
    "sg:province":"MI",
    "sg:tags":[
        "limousine"
    ],
    "wof:name":"A N Nightmoves Limo Inc",
    "wof:placetype":"venue"
},
  "geometry": {"coordinates":[-83.091568,42.508971],"type":"Point"}
}