{
  "type": "Feature",
  "properties": {
    "iso:country":"US",
    "sg:address":"500 Fern Pl",
    "sg:city":"Marquette",
    "sg:classifiers":[
        {
            "category":"Personal",
            "type":"Services"
        }
    ],
    "sg:phone":"+1 906 228 8248",
    "sg:postcode":"49855",
    "sg:province":"MI",
    "sg:tags":[
        "therapist",
        "massage"
    ],
    "wof:name":"Intentional Healing Massage",
    "wof:placetype":"venue"
},
  "geometry": {"coordinates":[-87.381051,46.548241],"type":"Point"}
}