{
  "type": "Feature",
  "properties": {
    "iso:country":"US",
    "sg:address":"26078 W Chicago Rd",
    "sg:city":"Sturgis",
    "sg:classifiers":[
        {
            "category":"Real Estate",
            "subcategory":"Real Estate Agent",
            "type":"Services"
        }
    ],
    "sg:phone":"+1 269 651 2776",
    "sg:postcode":"49091",
    "sg:province":"MI",
    "wof:name":"Remax Elite Group Real Estate",
    "wof:placetype":"venue"
},
  "geometry": {"coordinates":[-85.444046,41.796327],"type":"Point"}
}