{
  "type": "Feature",
  "properties": {
    "iso:country":"US",
    "sg:address":"30161 Southfield Rd Ste 202",
    "sg:city":"Southfield",
    "sg:classifiers":[
        {
            "category":"Professional",
            "subcategory":"Accounting & Tax Preparation",
            "type":"Services"
        }
    ],
    "sg:phone":"+1 248 594 7273",
    "sg:postcode":"48076",
    "sg:province":"MI",
    "sg:tags":[
        "accountant"
    ],
    "wof:name":"Zorski & Associates PC",
    "wof:placetype":"venue"
},
  "geometry": {"coordinates":[-83.223099,42.5116],"type":"Point"}
}