{
  "type": "Feature",
  "properties": {
    "iso:country":"US",
    "sg:address":"106 Rose St",
    "sg:city":"Traverse City",
    "sg:classifiers":[
        {
            "category":"Professional",
            "subcategory":"Lawyer & Legal Services",
            "type":"Services"
        }
    ],
    "sg:phone":"+1 231 946 1282",
    "sg:postcode":"49686",
    "sg:province":"MI",
    "sg:tags":[
        "attorney"
    ],
    "wof:name":"David J Clark Law Office",
    "wof:placetype":"venue"
},
  "geometry": {"coordinates":[-85.60037699999999,44.763773],"type":"Point"}
}