{
  "type": "Feature",
  "properties": {
    "iso:country":"US",
    "sg:address":"1919 Fred W Moore Hwy",
    "sg:city":"St Clair",
    "sg:classifiers":[
        {
            "category":"Professional",
            "subcategory":"Business Services",
            "type":"Services"
        }
    ],
    "sg:phone":"+1 810 329 5166",
    "sg:postcode":"48079",
    "sg:province":"MI",
    "sg:tags":[
        "embroidery"
    ],
    "wof:name":"Pine River Embroidery",
    "wof:placetype":"venue"
},
  "geometry": {"coordinates":[-82.506461,42.817048],"type":"Point"}
}