{
  "type": "Feature",
  "properties": {
    "iso:country":"US",
    "sg:address":"6484 W Marlette Rd",
    "sg:city":"Marlette",
    "sg:classifiers":[
        {
            "category":"Restaurant",
            "type":"Food & Drink"
        }
    ],
    "sg:phone":"+1 989 635 5170",
    "sg:postcode":"48453",
    "sg:province":"MI",
    "sg:tags":[
        "eating"
    ],
    "wof:name":"Westside Grill & Lounge",
    "wof:placetype":"venue"
},
  "geometry": {"coordinates":[-83.078497,43.327843],"type":"Point"}
}