{
  "type": "Feature",
  "properties": {
    "iso:country":"US",
    "sg:address":"810 Michigan St",
    "sg:city":"Port Huron",
    "sg:classifiers":[
        {
            "category":"Banks & Credit Unions",
            "subcategory":"Investment Brokerage",
            "type":"Services"
        }
    ],
    "sg:phone":"+1 810 987 1500",
    "sg:postcode":"48060",
    "sg:province":"MI",
    "sg:tags":[
        "security",
        "dealer"
    ],
    "wof:name":"Oppenheimer & Co Inc",
    "wof:placetype":"venue"
},
  "geometry": {"coordinates":[-82.423401,42.983206],"type":"Point"}
}