{
  "type": "Feature",
  "properties": {
    "iso:country":"US",
    "sg:address":"1148 S Airport Rd W",
    "sg:city":"Traverse City",
    "sg:classifiers":[
        {
            "category":"Shopping",
            "subcategory":"Clothing, Apparel, & Fashions",
            "type":"Retail Goods"
        }
    ],
    "sg:phone":"+1 231 946 3430",
    "sg:postcode":"49686",
    "sg:province":"MI",
    "wof:name":"Fashion Bug",
    "wof:placetype":"venue"
},
  "geometry": {"coordinates":[-85.59922400000001,44.733258],"type":"Point"}
}