{
  "type": "Feature",
  "properties": {
    "iso:country":"US",
    "sg:address":"7951 Elm Ave",
    "sg:city":"Newaygo",
    "sg:classifiers":[
        {
            "category":"Recreation",
            "type":"Entertainment"
        }
    ],
    "sg:phone":"+1 231 652 1720",
    "sg:postcode":"49337",
    "sg:province":"MI",
    "sg:tags":[
        "club",
        "membership"
    ],
    "wof:name":"Newaygo County Sportsmans Club",
    "wof:placetype":"venue"
},
  "geometry": {"coordinates":[-85.64237300000001,43.411242],"type":"Point"}
}