{
  "type": "Feature",
  "properties": {
    "iso:country":"US",
    "sg:address":"4237 Hillsdale Ave NE",
    "sg:city":"Grand Rapids",
    "sg:classifiers":[
        {
            "category":"Building & Trades",
            "subcategory":"Landscaping Services",
            "type":"Services"
        }
    ],
    "sg:phone":"+1 616 364 5854",
    "sg:postcode":"49525",
    "sg:province":"MI",
    "sg:tags":[
        "lawn",
        "maintenance",
        "grounds"
    ],
    "wof:name":"Donald Harkes Lawn Care",
    "wof:placetype":"venue"
},
  "geometry": {"coordinates":[-85.62392199999999,43.040993],"type":"Point"}
}