{
  "type": "Feature",
  "properties": {
    "iso:country":"US",
    "sg:address":"18628 Lindsay St",
    "sg:city":"Detroit",
    "sg:classifiers":[
        {
            "category":"Professional",
            "type":"Services"
        }
    ],
    "sg:phone":"+1 313 270 5326",
    "sg:postcode":"48235",
    "sg:province":"MI",
    "wof:name":"Paragon Collective",
    "wof:placetype":"venue"
},
  "geometry": {"coordinates":[-83.213691,42.428172],"type":"Point"}
}