{
  "type": "Feature",
  "properties": {
    "iso:country":"US",
    "sg:address":"3079 Hasler Lake Rd",
    "sg:city":"Lapeer",
    "sg:classifiers":[
        {
            "category":"Farming",
            "subcategory":"Farm",
            "type":"Manufacturing & Wholesale Goods"
        }
    ],
    "sg:phone":"+1 810 797 4402",
    "sg:postcode":"48446",
    "sg:province":"MI",
    "sg:tags":[
        "crop",
        "general"
    ],
    "wof:name":"Dale Gleason",
    "wof:placetype":"venue"
},
  "geometry": {"coordinates":[-83.44835399999999,42.965747],"type":"Point"}
}