{
  "type": "Feature",
  "properties": {
    "iso:country":"US",
    "sg:address":"2081 Teaneck Cir",
    "sg:city":"Wixom",
    "sg:classifiers":[
        {
            "category":"Professional",
            "subcategory":"Management & Consulting",
            "type":"Services"
        }
    ],
    "sg:phone":"+1 313 506 8084",
    "sg:postcode":"48393",
    "sg:province":"MI",
    "wof:name":"Jagwire Management LLC",
    "wof:placetype":"venue"
},
  "geometry": {"coordinates":[-83.511985,42.541842],"type":"Point"}
}