{
  "type": "Feature",
  "properties": {
    "iso:country":"US",
    "sg:address":"63364 Co Rd 376",
    "sg:city":"Bangor",
    "sg:classifiers":[
        {
            "category":"Building & Trades",
            "subcategory":"Construction",
            "type":"Services"
        }
    ],
    "sg:phone":"+1 269 621 3476",
    "sg:postcode":"49013",
    "sg:province":"MI",
    "sg:tags":[
        "fence",
        "contractor"
    ],
    "wof:name":"Gregory's Plastic Fence",
    "wof:placetype":"venue"
},
  "geometry": {"coordinates":[-86.159808,42.265603],"type":"Point"}
}