{
  "type": "Feature",
  "properties": {
    "iso:country":"US",
    "sg:address":"7223 Buckthorn Dr",
    "sg:city":"West Bloomfield",
    "sg:classifiers":[
        {
            "category":"Travel",
            "subcategory":"Travel Agent",
            "type":"Entertainment"
        }
    ],
    "sg:phone":"+1 248 363 1407",
    "sg:postcode":"48324",
    "sg:province":"MI",
    "sg:tags":[
        "agency",
        "bureau"
    ],
    "wof:name":"Merlo Travel Svc",
    "wof:placetype":"venue"
},
  "geometry": {"coordinates":[-83.42527,42.587906],"type":"Point"}
}