{
  "type": "Feature",
  "properties": {
    "iso:country":"US",
    "sg:address":"4592 Mauck Rd",
    "sg:city":"Hillsdale",
    "sg:classifiers":[
        {
            "category":"Organizations",
            "subcategory":"Non-profit Organization",
            "type":"Services"
        }
    ],
    "sg:phone":"+1 517 287 5011",
    "sg:postcode":"49242",
    "sg:province":"MI",
    "sg:tags":[
        "social"
    ],
    "wof:name":"Thrivent",
    "wof:placetype":"venue"
},
  "geometry": {"coordinates":[-84.56326199999999,41.941926],"type":"Point"}
}