{
  "type": "Feature",
  "properties": {
    "iso:country":"US",
    "sg:address":"23021 Webster St",
    "sg:city":"Oak Park",
    "sg:classifiers":[
        {
            "category":"Wholesale",
            "subcategory":"Jewelry",
            "type":"Manufacturing & Wholesale Goods"
        }
    ],
    "sg:phone":"+1 248 582 9352",
    "sg:postcode":"48237",
    "sg:province":"MI",
    "sg:tags":[
        "item",
        "novelty"
    ],
    "wof:name":"Pe Specialty Gifts",
    "wof:placetype":"venue"
},
  "geometry": {"coordinates":[-83.17726999999999,42.461879],"type":"Point"}
}