{
  "type": "Feature",
  "properties": {
    "iso:country":"US",
    "sg:address":"4172 W Pierson Rd",
    "sg:city":"Flint",
    "sg:classifiers":[
        {
            "category":"Autos & Motor Vehicles",
            "subcategory":"Fuel & Gas Station",
            "type":"Retail Goods"
        }
    ],
    "sg:phone":"+1 810 789 3780",
    "sg:postcode":"48504",
    "sg:province":"MI",
    "sg:tags":[
        "oil"
    ],
    "wof:name":"RPF Oil Co",
    "wof:placetype":"venue"
},
  "geometry": {"coordinates":[-83.760345,43.06074],"type":"Point"}
}