{
  "type": "Feature",
  "properties": {
    "iso:country":"US",
    "sg:address":"102 E Upton Ave",
    "sg:city":"Reed City",
    "sg:classifiers":[
        {
            "category":"Restaurant",
            "type":"Food & Drink"
        }
    ],
    "sg:phone":"+1 231 832 9833",
    "sg:postcode":"49677",
    "sg:province":"MI",
    "sg:tags":[
        "caterer"
    ],
    "wof:name":"Pere Marquette Catering LLC",
    "wof:placetype":"venue"
},
  "geometry": {"coordinates":[-85.509004,43.876071],"type":"Point"}
}