{
  "type": "Feature",
  "properties": {
    "iso:country":"US",
    "sg:address":"39400 Woodward Ave",
    "sg:city":"Bloomfield Hills",
    "sg:classifiers":[
        {
            "category":"Professional",
            "subcategory":"Lawyer & Legal Services",
            "type":"Services"
        }
    ],
    "sg:phone":"+1 248 646 9090",
    "sg:postcode":"48304",
    "sg:province":"MI",
    "wof:name":"Law Office of David B Gunsberg",
    "wof:placetype":"venue"
},
  "geometry": {"coordinates":[-83.242599,42.5811],"type":"Point"}
}