{
  "type": "Feature",
  "properties": {
    "iso:country":"US",
    "sg:address":"41805 Merrimac Cir",
    "sg:city":"Clinton Township",
    "sg:classifiers":[
        {
            "category":"Recreation",
            "type":"Entertainment"
        }
    ],
    "sg:phone":"+1 586 286 7240",
    "sg:postcode":"48038",
    "sg:province":"MI",
    "wof:name":"Healing Ways",
    "wof:placetype":"venue"
},
  "geometry": {"coordinates":[-82.92531099999999,42.604572],"type":"Point"}
}