{
  "type": "Feature",
  "properties": {
    "iso:country":"US",
    "sg:address":"137 E Main Ave",
    "sg:city":"Zeeland",
    "sg:classifiers":[
        {
            "category":"Shopping",
            "subcategory":"Florist",
            "type":"Retail Goods"
        }
    ],
    "sg:phone":"+1 616 772 6015",
    "sg:postcode":"49464",
    "sg:province":"MI",
    "wof:name":"Zeeland Floral & Gift",
    "wof:placetype":"venue"
},
  "geometry": {"coordinates":[-86.015845,42.812394],"type":"Point"}
}