{
  "type": "Feature",
  "properties": {
    "iso:country":"US",
    "sg:address":"11104 Watertower Ct",
    "sg:city":"Holland",
    "sg:classifiers":[
        {
            "category":"Autos & Motor Vehicles",
            "subcategory":"Automobile Sales",
            "type":"Retail Goods"
        }
    ],
    "sg:phone":"+1 616 393 8760",
    "sg:postcode":"49424",
    "sg:province":"MI",
    "sg:tags":[
        "car",
        "dealer"
    ],
    "wof:name":"Kay & Bee Auto Sales & Leasing",
    "wof:placetype":"venue"
},
  "geometry": {"coordinates":[-86.057671,42.802718],"type":"Point"}
}