{
  "type": "Feature",
  "properties": {
    "iso:country":"US",
    "sg:address":"1972 N Green Meadow St",
    "sg:city":"Sanford",
    "sg:classifiers":[
        {
            "category":"Freight",
            "type":"Transportation"
        }
    ],
    "sg:phone":"+1 989 687 9377",
    "sg:postcode":"48657",
    "sg:province":"MI",
    "sg:tags":[
        "general"
    ],
    "wof:name":"Sanford Storage",
    "wof:placetype":"venue"
},
  "geometry": {"coordinates":[-84.346705,43.666742],"type":"Point"}
}