{
  "type": "Feature",
  "properties": {
    "iso:country":"US",
    "sg:address":"380 Scheuner Dr",
    "sg:city":"Alpena",
    "sg:classifiers":[
        {
            "category":"Health Services",
            "subcategory":"Nursing And Care Facility",
            "type":"Services"
        },
        {
            "category":"Social Services",
            "subcategory":"Adult Care",
            "type":"Services"
        }
    ],
    "sg:phone":"+1 989 356 2896",
    "sg:postcode":"49707",
    "sg:province":"MI",
    "sg:tags":[
        "residential"
    ],
    "wof:name":"Sonrise Adult Foster Care Inc",
    "wof:placetype":"venue"
},
  "geometry": {"coordinates":[-83.46796999999999,45.074472],"type":"Point"}
}