{
  "type": "Feature",
  "properties": {
    "iso:country":"US",
    "sg:address":"487 Francis St",
    "sg:city":"East China",
    "sg:classifiers":[
        {
            "category":"Insurance",
            "subcategory":"Insurance Agent",
            "type":"Services"
        }
    ],
    "sg:phone":"+1 810 765 9345",
    "sg:postcode":"48054",
    "sg:province":"MI",
    "wof:name":"Kelb Agency LTD",
    "wof:placetype":"venue"
},
  "geometry": {"coordinates":[-82.490951,42.743964],"type":"Point"}
}