{
  "type": "Feature",
  "properties": {
    "iso:country":"US",
    "sg:address":"14715 Klenk St",
    "sg:city":"Detroit",
    "sg:classifiers":[
        {
            "category":"Recreation",
            "subcategory":"Boat Charter",
            "type":"Entertainment"
        }
    ],
    "sg:phone":"+1 313 331 9820",
    "sg:postcode":"48215",
    "sg:province":"MI",
    "sg:tags":[
        "boating"
    ],
    "wof:name":"D J Kuhn",
    "wof:placetype":"venue"
},
  "geometry": {"coordinates":[-82.931,42.360802],"type":"Point"}
}