{
  "type": "Feature",
  "properties": {
    "iso:country":"US",
    "sg:address":"6030 S Martin Luther King Jr Blvd",
    "sg:city":"Lansing",
    "sg:classifiers":[
        {
            "category":"Restaurant",
            "type":"Food & Drink"
        }
    ],
    "sg:phone":"+1 517 882 9636",
    "sg:postcode":"48911",
    "sg:province":"MI",
    "wof:name":"Los Gringos Restaurant",
    "wof:placetype":"venue"
},
  "geometry": {"coordinates":[-84.58076,42.671746],"type":"Point"}
}