{
  "type": "Feature",
  "properties": {
    "iso:country":"US",
    "sg:address":"326 E Leroy St",
    "sg:city":"Burlington",
    "sg:classifiers":[
        {
            "category":"Organizations",
            "subcategory":"Religious Organization",
            "type":"Services"
        }
    ],
    "sg:phone":"+1 517 765 2417",
    "sg:postcode":"49029",
    "sg:province":"MI",
    "wof:name":"Parsonage",
    "wof:placetype":"venue"
},
  "geometry": {"coordinates":[-85.071388,42.106459],"type":"Point"}
}