{
  "type": "Feature",
  "properties": {
    "iso:country":"US",
    "sg:address":"21520 Harper Ave",
    "sg:city":"Saint Clair Shores",
    "sg:classifiers":[
        {
            "category":"Personal",
            "subcategory":"Tanning Parlor",
            "type":"Services"
        },
        {
            "category":"Personal",
            "subcategory":"Day Spa",
            "type":"Services"
        }
    ],
    "sg:phone":"+1 586 773 1450",
    "sg:postcode":"48080",
    "sg:province":"MI",
    "wof:name":"North Beach Sun Spa",
    "wof:placetype":"venue"
},
  "geometry": {"coordinates":[-82.912903,42.4543],"type":"Point"}
}