{
  "type": "Feature",
  "properties": {
    "iso:country":"US",
    "sg:address":"958 Mona Brook Rd",
    "sg:city":"Muskegon",
    "sg:classifiers":[
        {
            "category":"Professional",
            "subcategory":"Research",
            "type":"Services"
        }
    ],
    "sg:phone":"+1 231 798 7619",
    "sg:postcode":"49441",
    "sg:province":"MI",
    "sg:tags":[
        "nonphysical",
        "commercial"
    ],
    "wof:name":"Sytsema Acquisition Company",
    "wof:placetype":"venue"
},
  "geometry": {"coordinates":[-86.26777800000001,43.174328],"type":"Point"}
}