{
  "type": "Feature",
  "properties": {
    "iso:country":"US",
    "sg:address":"510 Savage Rd",
    "sg:city":"Belleville",
    "sg:classifiers":[
        {
            "category":"Professional",
            "subcategory":"Engineering",
            "type":"Services"
        }
    ],
    "sg:phone":"+1 734 946 7265",
    "sg:postcode":"48111",
    "sg:province":"MI",
    "sg:tags":[
        "consultant"
    ],
    "wof:name":"Servotech Engineering",
    "wof:placetype":"venue"
},
  "geometry": {"coordinates":[-83.475191,42.202911],"type":"Point"}
}