{
  "type": "Feature",
  "properties": {
    "iso:country":"US",
    "sg:address":"610 N Baldwin Rd",
    "sg:city":"Oxford",
    "sg:classifiers":[
        {
            "category":"Professional",
            "subcategory":"Business Services",
            "type":"Services"
        }
    ],
    "sg:phone":"+1 248 628 0199",
    "sg:postcode":"48371",
    "sg:province":"MI",
    "wof:name":"McKinnon Designs",
    "wof:placetype":"venue"
},
  "geometry": {"coordinates":[-83.33448,42.831983],"type":"Point"}
}