{
  "type": "Feature",
  "properties": {
    "iso:country":"US",
    "sg:address":"17101 Kercheval St",
    "sg:city":"Grosse Pointe",
    "sg:classifiers":[
        {
            "category":"Home & Garden",
            "subcategory":"Hardware",
            "type":"Retail Goods"
        }
    ],
    "sg:phone":"+1 313 882 9230",
    "sg:postcode":"48230",
    "sg:province":"MI",
    "sg:tags":[
        "store"
    ],
    "wof:name":"Damman Hardware",
    "wof:placetype":"venue"
},
  "geometry": {"coordinates":[-82.9151,42.390598],"type":"Point"}
}