{
  "type": "Feature",
  "properties": {
    "iso:country":"US",
    "sg:address":"128 S Main St",
    "sg:city":"Mt Pleasant",
    "sg:classifiers":[
        {
            "category":"Restaurant",
            "type":"Food & Drink"
        }
    ],
    "sg:phone":"+1 989 772 0864",
    "sg:postcode":"48858",
    "sg:province":"MI",
    "sg:website":"www.thebrass.com",
    "wof:name":"Brass Saloon",
    "wof:placetype":"venue"
},
  "geometry": {"coordinates":[-84.776735,43.604197],"type":"Point"}
}