{
  "type": "Feature",
  "properties": {
    "iso:country":"US",
    "sg:address":"4234 Main St",
    "sg:city":"Petoskey",
    "sg:classifiers":[
        {
            "category":"Shopping",
            "subcategory":"Clothing, Apparel, & Fashions",
            "type":"Retail Goods"
        }
    ],
    "sg:phone":"+1 231 439 2626",
    "sg:postcode":"49770",
    "sg:province":"MI",
    "wof:name":"Threads",
    "wof:placetype":"venue"
},
  "geometry": {"coordinates":[-85.02002299999999,45.367049],"type":"Point"}
}