{
  "type": "Feature",
  "properties": {
    "iso:country":"US",
    "sg:address":"9241 S Mackinac Trl",
    "sg:city":"Sault Ste Marie",
    "sg:classifiers":[
        {
            "category":"Wholesale",
            "subcategory":"Machinery & Supplies",
            "type":"Manufacturing & Wholesale Goods"
        }
    ],
    "sg:phone":"+1 906 632 6095",
    "sg:postcode":"49783",
    "sg:province":"MI",
    "sg:tags":[
        "contractor"
    ],
    "wof:name":"AIS Construction Equip Corp",
    "wof:placetype":"venue"
},
  "geometry": {"coordinates":[-84.407078,46.371703],"type":"Point"}
}