{
  "type": "Feature",
  "properties": {
    "iso:country":"US",
    "sg:address":"6820 W Main St",
    "sg:city":"Kalamazoo",
    "sg:classifiers":[
        {
            "category":"Restaurant",
            "type":"Food & Drink"
        }
    ],
    "sg:phone":"+1 269 353 8599",
    "sg:postcode":"49009",
    "sg:province":"MI",
    "wof:name":"Mc Donald's",
    "wof:placetype":"venue"
},
  "geometry": {"coordinates":[-85.686156,42.295822],"type":"Point"}
}