{
  "type": "Feature",
  "properties": {
    "iso:country":"US",
    "sg:address":"4223 131st Ave",
    "sg:city":"Hamilton",
    "sg:classifiers":[
        {
            "category":"Communications",
            "subcategory":"Film & Video Production",
            "type":"Services"
        }
    ],
    "sg:phone":"+1 269 751 7501",
    "sg:postcode":"49419",
    "sg:province":"MI",
    "sg:tags":[
        "motion"
    ],
    "wof:name":"Jazzbud Productions",
    "wof:placetype":"venue"
},
  "geometry": {"coordinates":[-85.95842500000001,42.642735],"type":"Point"}
}