{
  "type": "Feature",
  "properties": {
    "iso:country":"US",
    "sg:address":"2657 Cullen Rd",
    "sg:city":"Howell",
    "sg:classifiers":[
        {
            "category":"Communications",
            "type":"Services"
        }
    ],
    "sg:phone":"+1 517 545 0055",
    "sg:postcode":"48855",
    "sg:province":"MI",
    "wof:name":"Rickhoff Communications",
    "wof:placetype":"venue"
},
  "geometry": {"coordinates":[-83.778058,42.644187],"type":"Point"}
}