{
  "type": "Feature",
  "properties": {
    "iso:country":"US",
    "sg:address":"30919 Orchard Lake Rd",
    "sg:city":"Farmington Hills",
    "sg:classifiers":[
        {
            "category":"Shopping",
            "subcategory":"Beauty & Cosmetics",
            "type":"Retail Goods"
        }
    ],
    "sg:phone":"+1 248 626 0282",
    "sg:postcode":"48334",
    "sg:province":"MI",
    "sg:tags":[
        "supply"
    ],
    "wof:name":"Sally's Beauty Supply",
    "wof:placetype":"venue"
},
  "geometry": {"coordinates":[-83.360096,42.524452],"type":"Point"}
}