{
  "type": "Feature",
  "properties": {
    "iso:country":"US",
    "sg:address":"411 Mill St",
    "sg:city":"Ortonville",
    "sg:classifiers":[
        {
            "category":"Bars & Pubs",
            "type":"Food & Drink"
        }
    ],
    "sg:phone":"+1 248 627 2333",
    "sg:postcode":"48462",
    "sg:province":"MI",
    "wof:name":"Village Pub",
    "wof:placetype":"venue"
},
  "geometry": {"coordinates":[-83.44302,42.85226],"type":"Point"}
}