{
  "type": "Feature",
  "properties": {
    "iso:country":"US",
    "sg:address":"21607 Fenkell St",
    "sg:city":"Detroit",
    "sg:classifiers":[
        {
            "category":"Personal",
            "type":"Services"
        }
    ],
    "sg:phone":"+1 313 592 8968",
    "sg:postcode":"48223",
    "sg:province":"MI",
    "sg:tags":[
        "association"
    ],
    "wof:name":"Forbidden Wheels Inc",
    "wof:placetype":"venue"
},
  "geometry": {"coordinates":[-83.255543,42.400241],"type":"Point"}
}