{
  "type": "Feature",
  "properties": {
    "iso:country":"US",
    "sg:address":"30201 Orchard Lake Rd",
    "sg:city":"Farmington",
    "sg:classifiers":[
        {
            "category":"Insurance",
            "subcategory":"Insurance Agent",
            "type":"Services"
        }
    ],
    "sg:phone":"+1 248 851 5050",
    "sg:postcode":"48334",
    "sg:province":"MI",
    "wof:name":"State Farm Insurance",
    "wof:placetype":"venue"
},
  "geometry": {"coordinates":[-83.359792,42.520165],"type":"Point"}
}