{
  "type": "Feature",
  "properties": {
    "iso:country":"US",
    "sg:address":"980 Rusch Rd S",
    "sg:city":"Traverse City",
    "sg:classifiers":[
        {
            "category":"Wholesale",
            "subcategory":"Non-durable Goods",
            "type":"Manufacturing & Wholesale Goods"
        }
    ],
    "sg:phone":"+1 231 946 7825",
    "sg:postcode":"49686",
    "sg:province":"MI",
    "wof:name":"Maison Distributing",
    "wof:placetype":"venue"
},
  "geometry": {"coordinates":[-85.57503800000001,44.678695],"type":"Point"}
}