{
  "type": "Feature",
  "properties": {
    "iso:country":"US",
    "sg:address":"3119 N Campbell Rd",
    "sg:city":"Royal Oak",
    "sg:classifiers":[
        {
            "category":"Organizations",
            "subcategory":"Religious Organization",
            "type":"Services"
        }
    ],
    "sg:phone":"+1 248 588 5488",
    "sg:postcode":"48073",
    "sg:province":"MI",
    "wof:name":"Church of Redeemer",
    "wof:placetype":"venue"
},
  "geometry": {"coordinates":[-83.125804,42.519349],"type":"Point"}
}