{
  "type": "Feature",
  "properties": {
    "iso:country":"US",
    "sg:address":"22364 Goddard Rd",
    "sg:city":"Taylor",
    "sg:classifiers":[
        {
            "category":"Food & Beverages",
            "subcategory":"Liquor & Beverages",
            "type":"Retail Goods"
        }
    ],
    "sg:phone":"+1 313 291 2670",
    "sg:postcode":"48180",
    "sg:province":"MI",
    "sg:tags":[
        "eating",
        "alcoholic"
    ],
    "wof:name":"Wing Ding Licorice Shop",
    "wof:placetype":"venue"
},
  "geometry": {"coordinates":[-83.254096,42.226988],"type":"Point"}
}