{
  "type": "Feature",
  "properties": {
    "iso:country":"US",
    "sg:address":"737 E Roberts Ave",
    "sg:city":"Hazel Park",
    "sg:classifiers":[
        {
            "category":"Building & Trades",
            "subcategory":"Landscaping Services",
            "type":"Services"
        }
    ],
    "sg:phone":"+1 248 548 4941",
    "sg:postcode":"48030",
    "sg:province":"MI",
    "sg:tags":[
        "landscape"
    ],
    "wof:name":"Harts Outdoor Services Inc",
    "wof:placetype":"venue"
},
  "geometry": {"coordinates":[-83.09650999999999,42.458527],"type":"Point"}
}