{
  "type": "Feature",
  "properties": {
    "iso:country":"US",
    "sg:address":"554 Churchgrove Rd",
    "sg:city":"Frankenmuth",
    "sg:classifiers":[
        {
            "category":"Wholesale",
            "subcategory":"Machinery & Supplies",
            "type":"Manufacturing & Wholesale Goods"
        }
    ],
    "sg:phone":"+1 989 652 8775",
    "sg:postcode":"48734",
    "sg:province":"MI",
    "sg:tags":[
        "equipment",
        "material",
        "handling"
    ],
    "wof:name":"Northland Equipment Inc",
    "wof:placetype":"venue"
},
  "geometry": {"coordinates":[-83.74844899999999,43.34699],"type":"Point"}
}