{
  "type": "Feature",
  "properties": {
    "iso:country":"US",
    "sg:address":"48237 Chesterfield Dr S",
    "sg:city":"Canton",
    "sg:classifiers":[
        {
            "category":"Retail",
            "subcategory":"Laundry & Dry Cleaning",
            "type":"Services"
        }
    ],
    "sg:phone":"+1 734 454 7179",
    "sg:postcode":"48187",
    "sg:province":"MI",
    "sg:tags":[
        "drycleaning",
        "plant"
    ],
    "wof:name":"Ozzie M Amberg",
    "wof:placetype":"venue"
},
  "geometry": {"coordinates":[-83.51809799999999,42.338012],"type":"Point"}
}