{
  "type": "Feature",
  "properties": {
    "iso:country":"US",
    "sg:address":"49689 51st Ave",
    "sg:city":"Lawrence",
    "sg:classifiers":[
        {
            "category":"Retail",
            "subcategory":"Animal Services",
            "type":"Services"
        }
    ],
    "sg:phone":"+1 269 674 3383",
    "sg:postcode":"49064",
    "sg:province":"MI",
    "wof:name":"Firefly Farm",
    "wof:placetype":"venue"
},
  "geometry": {"coordinates":[-86.02857400000001,42.233552],"type":"Point"}
}