{
  "type": "Feature",
  "properties": {
    "iso:country":"US",
    "sg:address":"610 N State St",
    "sg:city":"Big Rapids",
    "sg:classifiers":[
        {
            "category":"Professional",
            "subcategory":"Accounting & Tax Preparation",
            "type":"Services"
        }
    ],
    "sg:phone":"+1 231 796 4411",
    "sg:postcode":"49307",
    "sg:province":"MI",
    "sg:tags":[
        "return",
        "filing"
    ],
    "wof:name":"Big Rapids Tax Svc",
    "wof:placetype":"venue"
},
  "geometry": {"coordinates":[-85.484026,43.705912],"type":"Point"}
}