{
  "type": "Feature",
  "properties": {
    "iso:country":"US",
    "sg:address":"136 N Densmore St",
    "sg:city":"Muskegon",
    "sg:classifiers":[
        {
            "category":"Real Estate",
            "subcategory":"Real Estate Agent",
            "type":"Services"
        }
    ],
    "sg:phone":"+1 231 777 3742",
    "sg:postcode":"49442",
    "sg:province":"MI",
    "wof:name":"Home Concepts West Michigan",
    "wof:placetype":"venue"
},
  "geometry": {"coordinates":[-86.178674,43.254336],"type":"Point"}
}