{
  "type": "Feature",
  "properties": {
    "iso:country":"US",
    "sg:address":"4871 Folks Rd",
    "sg:city":"Horton",
    "sg:classifiers":[
        {
            "category":"Organizations",
            "subcategory":"Community Association",
            "type":"Services"
        }
    ],
    "sg:phone":"+1 517 563 8801",
    "sg:postcode":"49246",
    "sg:province":"MI",
    "wof:name":"Hanover Horton Area Lions",
    "wof:placetype":"venue"
},
  "geometry": {"coordinates":[-84.49549500000001,42.116095],"type":"Point"}
}