{
  "type": "Feature",
  "properties": {
    "iso:country":"US",
    "sg:address":"4700 Wildflower Ct",
    "sg:city":"Ann Arbor",
    "sg:classifiers":[
        {
            "category":"Professional",
            "subcategory":"Computer Services",
            "type":"Services"
        }
    ],
    "sg:phone":"+1 734 996 0771",
    "sg:postcode":"48108",
    "sg:province":"MI",
    "sg:tags":[
        "prepackaged",
        "software"
    ],
    "wof:name":"Arbor Moon Software Inc",
    "wof:placetype":"venue"
},
  "geometry": {"coordinates":[-83.74820699999999,42.211268],"type":"Point"}
}