{
  "type": "Feature",
  "properties": {
    "iso:country":"US",
    "sg:address":"8533 E US Hwy 10",
    "sg:city":"Chase",
    "sg:classifiers":[
        {
            "category":"Building & Trades",
            "subcategory":"Construction",
            "type":"Services"
        }
    ],
    "sg:phone":"+1 231 832 3672",
    "sg:postcode":"49623",
    "sg:province":"MI",
    "sg:tags":[
        "mobile",
        "home"
    ],
    "wof:name":"Dave's Mobile & Modular",
    "wof:placetype":"venue"
},
  "geometry": {"coordinates":[-85.631629,43.887734],"type":"Point"}
}