{
  "type": "Feature",
  "properties": {
    "iso:country":"US",
    "sg:address":"19814 Louise St",
    "sg:city":"Livonia",
    "sg:classifiers":[
        {
            "category":"Education",
            "subcategory":"School",
            "type":"Public Place"
        }
    ],
    "sg:phone":"+1 248 919 0404",
    "sg:postcode":"48152",
    "sg:province":"MI",
    "sg:tags":[
        "high",
        "middle",
        "elementary"
    ],
    "wof:name":"Grandview Elementary School",
    "wof:placetype":"venue"
},
  "geometry": {"coordinates":[-83.34089,42.433432],"type":"Point"}
}