{
  "type": "Feature",
  "properties": {
    "iso:country":"US",
    "sg:address":"28 Elder Dr",
    "sg:city":"Nunica",
    "sg:classifiers":[
        {
            "category":"Social Services",
            "subcategory":"Child Care",
            "type":"Services"
        }
    ],
    "sg:phone":"+1 616 846 6784",
    "sg:postcode":"49448",
    "sg:province":"MI",
    "sg:tags":[
        "day"
    ],
    "wof:name":"Precious Memory Daycare",
    "wof:placetype":"venue"
},
  "geometry": {"coordinates":[-86.117283,43.091443],"type":"Point"}
}