{
  "type": "Feature",
  "properties": {
    "iso:country":"US",
    "sg:address":"28212 Shock St",
    "sg:city":"Saint Clair Shores",
    "sg:classifiers":[
        {
            "category":"Wholesale",
            "subcategory":"Auto Parts",
            "type":"Manufacturing & Wholesale Goods"
        }
    ],
    "sg:phone":"+1 586 773 4699",
    "sg:postcode":"48081",
    "sg:province":"MI",
    "sg:tags":[
        "training",
        "installation"
    ],
    "wof:name":"Quality Equipment Services LLC",
    "wof:placetype":"venue"
},
  "geometry": {"coordinates":[-82.906522,42.502298],"type":"Point"}
}