{
  "type": "Feature",
  "properties": {
    "iso:country":"US",
    "sg:address":"3795 Davison Rd",
    "sg:city":"Lapeer",
    "sg:classifiers":[
        {
            "category":"Building & Trades",
            "subcategory":"Construction",
            "type":"Services"
        }
    ],
    "sg:phone":"+1 810 338 1308",
    "sg:postcode":"48446",
    "sg:province":"MI",
    "sg:tags":[
        "house"
    ],
    "wof:name":"D & T Construction",
    "wof:placetype":"venue"
},
  "geometry": {"coordinates":[-83.37289800000001,43.042548],"type":"Point"}
}