{
  "type": "Feature",
  "properties": {
    "iso:country":"US",
    "sg:address":"2321 Pine Grove Ave",
    "sg:city":"Port Huron",
    "sg:classifiers":[
        {
            "category":"Freight",
            "type":"Transportation"
        }
    ],
    "sg:phone":"+1 810 984 4114",
    "sg:postcode":"48060",
    "sg:province":"MI",
    "sg:tags":[
        "broker",
        "customs"
    ],
    "sg:website":"www.livingstonintl.com",
    "wof:name":"Livingston International Inc",
    "wof:placetype":"venue"
},
  "geometry": {"coordinates":[-82.436533,42.99805],"type":"Point"}
}