{
  "type": "Feature",
  "properties": {
    "iso:country":"US",
    "sg:address":"3500 Dove Rd",
    "sg:city":"Port Huron",
    "sg:classifiers":[
        {
            "category":"Freight",
            "type":"Transportation"
        }
    ],
    "sg:phone":"+1 810 364 5700",
    "sg:postcode":"48060",
    "sg:province":"MI",
    "sg:tags":[
        "trucking"
    ],
    "wof:name":"S A Torello Inc",
    "wof:placetype":"venue"
},
  "geometry": {"coordinates":[-82.468906,42.951683],"type":"Point"}
}