{
  "type": "Feature",
  "properties": {
    "iso:country":"US",
    "sg:address":"9929 S M 43 Hwy",
    "sg:city":"Delton",
    "sg:classifiers":[
        {
            "category":"Retail",
            "subcategory":"Auto Repair",
            "type":"Services"
        }
    ],
    "sg:phone":"+1 269 623 5261",
    "sg:postcode":"49046",
    "sg:province":"MI",
    "sg:tags":[
        "body",
        "automobile",
        "painting"
    ],
    "wof:name":"Delton Body Shop",
    "wof:placetype":"venue"
},
  "geometry": {"coordinates":[-85.408967,42.509895],"type":"Point"}
}