{
  "type": "Feature",
  "properties": {
    "iso:country":"US",
    "sg:address":"216 S Bridge St",
    "sg:city":"Grand Ledge",
    "sg:classifiers":[
        {
            "category":"Home & Garden",
            "subcategory":"Furniture",
            "type":"Retail Goods"
        }
    ],
    "sg:phone":"+1 517 622 8288",
    "sg:postcode":"48837",
    "sg:province":"MI",
    "wof:name":"About The Home",
    "wof:placetype":"venue"
},
  "geometry": {"coordinates":[-84.746247,42.753443],"type":"Point"}
}