{
  "type": "Feature",
  "properties": {
    "iso:country":"US",
    "sg:address":"3556 Wakefield Rd",
    "sg:city":"Berkley",
    "sg:classifiers":[
        {
            "category":"Building & Trades",
            "subcategory":"Landscaping Services",
            "type":"Services"
        }
    ],
    "sg:phone":"+1 248 542 1404",
    "sg:postcode":"48072",
    "sg:province":"MI",
    "wof:name":"Container Scapes",
    "wof:placetype":"venue"
},
  "geometry": {"coordinates":[-83.188215,42.504355],"type":"Point"}
}