{
  "type": "Feature",
  "properties": {
    "iso:country":"US",
    "sg:address":"1651 E M 21",
    "sg:city":"Owosso",
    "sg:classifiers":[
        {
            "category":"Shopping",
            "subcategory":"Music",
            "type":"Retail Goods"
        }
    ],
    "sg:phone":"+1 989 723 5892",
    "sg:postcode":"48867",
    "sg:province":"MI",
    "sg:tags":[
        "compact",
        "record",
        "disc",
        "tape"
    ],
    "wof:name":"Sam Goody",
    "wof:placetype":"venue"
},
  "geometry": {"coordinates":[-84.132746,42.998114],"type":"Point"}
}