{
  "type": "Feature",
  "properties": {
    "iso:country":"US",
    "sg:address":"1685 County Farm Rd",
    "sg:city":"Howell",
    "sg:classifiers":[
        {
            "category":"Building & Trades",
            "subcategory":"Construction",
            "type":"Services"
        }
    ],
    "sg:phone":"+1 517 545 8928",
    "sg:postcode":"48843",
    "sg:province":"MI",
    "sg:tags":[
        "home",
        "improvement"
    ],
    "wof:name":"Karon Construction",
    "wof:placetype":"venue"
},
  "geometry": {"coordinates":[-83.965689,42.5696],"type":"Point"}
}