{
  "type": "Feature",
  "properties": {
    "iso:country":"US",
    "sg:address":"5965 Wall St",
    "sg:city":"Sterling Heights",
    "sg:classifiers":[
        {
            "category":"Wholesale",
            "subcategory":"Machinery & Supplies",
            "type":"Manufacturing & Wholesale Goods"
        },
        {
            "category":"Professional",
            "type":"Services"
        }
    ],
    "sg:phone":"+1 586 978 9610",
    "sg:postcode":"48312",
    "sg:province":"MI",
    "sg:tags":[
        "repairing"
    ],
    "wof:name":"International Machine Services",
    "wof:placetype":"venue"
},
  "geometry": {"coordinates":[-83.046515,42.570616],"type":"Point"}
}