{
  "type": "Feature",
  "properties": {
    "iso:country":"US",
    "sg:address":"43 N Union St",
    "sg:city":"Battle Creek",
    "sg:classifiers":[
        {
            "category":"Social Services",
            "subcategory":"Child Care",
            "type":"Services"
        }
    ],
    "sg:phone":"+1 269 962 1552",
    "sg:postcode":"49017",
    "sg:province":"MI",
    "sg:tags":[
        "day"
    ],
    "wof:name":"Hills Daycare",
    "wof:placetype":"venue"
},
  "geometry": {"coordinates":[-85.167568,42.323536],"type":"Point"}
}