{
  "type": "Feature",
  "properties": {
    "iso:country":"US",
    "sg:address":"7467 E Houghton Lake Rd",
    "sg:city":"Merritt",
    "sg:classifiers":[
        {
            "category":"Restaurant",
            "type":"Food & Drink"
        }
    ],
    "sg:phone":"+1 231 328 3333",
    "sg:postcode":"49667",
    "sg:province":"MI",
    "wof:name":"B K D's Northern Cafe",
    "wof:placetype":"venue"
},
  "geometry": {"coordinates":[-84.947974,44.336105],"type":"Point"}
}