{
  "type": "Feature",
  "properties": {
    "iso:country":"US",
    "sg:address":"677 E Main St",
    "sg:city":"Centreville",
    "sg:classifiers":[
        {
            "category":"Insurance",
            "subcategory":"Insurance Agent",
            "type":"Services"
        }
    ],
    "sg:phone":"+1 269 467 8974",
    "sg:postcode":"49032",
    "sg:province":"MI",
    "wof:name":"Sprowl & Swartz",
    "wof:placetype":"venue"
},
  "geometry": {"coordinates":[-85.511404,41.921912],"type":"Point"}
}