{
  "type": "Feature",
  "properties": {
    "iso:country":"US",
    "sg:address":"12160 W Herbison Rd",
    "sg:city":"Eagle",
    "sg:classifiers":[
        {
            "category":"Professional",
            "subcategory":"Management & Consulting",
            "type":"Services"
        }
    ],
    "sg:phone":"+1 517 626 2200",
    "sg:postcode":"48822",
    "sg:province":"MI",
    "sg:tags":[
        "consultant",
        "safety"
    ],
    "wof:name":"Specialized Safety Svc",
    "wof:placetype":"venue"
},
  "geometry": {"coordinates":[-84.76476700000001,42.82993],"type":"Point"}
}