{
  "type": "Feature",
  "properties": {
    "iso:country":"US",
    "sg:address":"4248 Trinity Ln",
    "sg:city":"Pinckney",
    "sg:classifiers":[
        {
            "category":"Building & Trades",
            "subcategory":"Landscaping Services",
            "type":"Services"
        }
    ],
    "sg:phone":"+1 734 954 0082",
    "sg:postcode":"48169",
    "sg:province":"MI",
    "sg:tags":[
        "landscape",
        "contractor"
    ],
    "wof:name":"Green Valley Landscaping",
    "wof:placetype":"venue"
},
  "geometry": {"coordinates":[-83.86418999999999,42.486069],"type":"Point"}
}