{
  "type": "Feature",
  "properties": {
    "iso:country":"US",
    "sg:address":"32605 W 12 Mile Rd",
    "sg:city":"Farmington Hills",
    "sg:classifiers":[
        {
            "category":"Professional",
            "type":"Services"
        }
    ],
    "sg:phone":"+1 248 489 3111",
    "sg:postcode":"48334",
    "sg:province":"MI",
    "sg:tags":[
        "establishment"
    ],
    "wof:name":"Poirier & Assoc",
    "wof:placetype":"venue"
},
  "geometry": {"coordinates":[-83.372118,42.498777],"type":"Point"}
}