{
  "type": "Feature",
  "properties": {
    "iso:country":"US",
    "sg:address":"545 Ada Dr SE",
    "sg:city":"Ada",
    "sg:classifiers":[
        {
            "category":"Health Services",
            "subcategory":"Chiropractor",
            "type":"Services"
        }
    ],
    "sg:phone":"+1 616 676 2888",
    "sg:postcode":"49301",
    "sg:province":"MI",
    "wof:name":"Ada Chiropractic",
    "wof:placetype":"venue"
},
  "geometry": {"coordinates":[-85.48673599999999,42.954994],"type":"Point"}
}