{
  "type": "Feature",
  "properties": {
    "iso:country":"US",
    "sg:address":"8364 E French Rd",
    "sg:city":"Elsie",
    "sg:classifiers":[
        {
            "category":"Farming",
            "subcategory":"Dairy Farm",
            "type":"Manufacturing & Wholesale Goods"
        }
    ],
    "sg:phone":"+1 989 862 5014",
    "sg:postcode":"48831",
    "sg:province":"MI",
    "wof:name":"Dan Acre",
    "wof:placetype":"venue"
},
  "geometry": {"coordinates":[-84.39236200000001,43.059596],"type":"Point"}
}