{
  "type": "Feature",
  "properties": {
    "iso:country":"US",
    "sg:address":"174 E M-134",
    "sg:city":"Cedarville",
    "sg:classifiers":[
        {
            "category":"Autos & Motor Vehicles",
            "subcategory":"Automobile Sales",
            "type":"Retail Goods"
        }
    ],
    "sg:phone":"+1 906 484 3749",
    "sg:postcode":"49719",
    "sg:province":"MI",
    "sg:tags":[
        "car",
        "dealer"
    ],
    "wof:name":"Hill's Used Cars",
    "wof:placetype":"venue"
},
  "geometry": {"coordinates":[-84.35965,45.999331],"type":"Point"}
}