{
  "type": "Feature",
  "properties": {
    "iso:country":"US",
    "sg:address":"1005 Riverbank St",
    "sg:city":"Lincoln Park",
    "sg:classifiers":[
        {
            "category":"Education",
            "subcategory":"School",
            "type":"Public Place"
        }
    ],
    "sg:phone":"+1 313 928 8821",
    "sg:postcode":"48146",
    "sg:province":"MI",
    "wof:name":"John Hs Davenport",
    "wof:placetype":"venue"
},
  "geometry": {"coordinates":[-83.180543,42.229679],"type":"Point"}
}