{
  "type": "Feature",
  "properties": {
    "iso:country":"US",
    "sg:address":"412 S Washington Ave",
    "sg:city":"Royal Oak",
    "sg:classifiers":[
        {
            "category":"Shopping",
            "subcategory":"Clothing, Apparel, & Fashions",
            "type":"Retail Goods"
        }
    ],
    "sg:phone":"+1 248 543 8078",
    "sg:postcode":"48067",
    "sg:province":"MI",
    "sg:tags":[
        "men's",
        "clothing",
        "accessory",
        "women's"
    ],
    "wof:name":"Project 3",
    "wof:placetype":"venue"
},
  "geometry": {"coordinates":[-83.14658900000001,42.48712],"type":"Point"}
}