{
  "type": "Feature",
  "properties": {
    "iso:country":"US",
    "sg:address":"1713 N Washington Ave",
    "sg:city":"Royal Oak",
    "sg:classifiers":[
        {
            "category":"Social Services",
            "subcategory":"Child Care",
            "type":"Services"
        }
    ],
    "sg:phone":"+1 248 398 0968",
    "sg:postcode":"48067",
    "sg:province":"MI",
    "sg:tags":[
        "day"
    ],
    "wof:name":"Unger Ethlyn",
    "wof:placetype":"venue"
},
  "geometry": {"coordinates":[-83.147328,42.50415],"type":"Point"}
}