{
  "type": "Feature",
  "properties": {
    "iso:country":"US",
    "sg:address":"8240 Brookwood Dr",
    "sg:city":"Portage",
    "sg:classifiers":[
        {
            "category":"Building & Trades",
            "subcategory":"Landscaping Services",
            "type":"Services"
        }
    ],
    "sg:phone":"+1 269 324 5538",
    "sg:postcode":"49024",
    "sg:province":"MI",
    "sg:tags":[
        "landscape"
    ],
    "wof:name":"Extensive Landscape Services",
    "wof:placetype":"venue"
},
  "geometry": {"coordinates":[-85.606593,42.199893],"type":"Point"}
}