{
  "type": "Feature",
  "properties": {
    "iso:country":"US",
    "sg:address":"17558 Bailey Rd",
    "sg:city":"Bailey",
    "sg:classifiers":[
        {
            "category":"Wholesale",
            "subcategory":"Construction Materials",
            "type":"Manufacturing & Wholesale Goods"
        }
    ],
    "sg:phone":"+1 231 834 5854",
    "sg:postcode":"49303",
    "sg:province":"MI",
    "sg:tags":[
        "brick",
        "common",
        "face"
    ],
    "wof:name":"Universal Systems",
    "wof:placetype":"venue"
},
  "geometry": {"coordinates":[-85.816198,43.278314],"type":"Point"}
}