{
  "type": "Feature",
  "properties": {
    "iso:country":"US",
    "sg:address":"202 N Old Woodward Ave",
    "sg:city":"Birmingham",
    "sg:classifiers":[
        {
            "category":"Home & Garden",
            "subcategory":"Furniture",
            "type":"Retail Goods"
        }
    ],
    "sg:phone":"+1 248 258 8813",
    "sg:postcode":"48009",
    "sg:province":"MI",
    "sg:tags":[
        "store"
    ],
    "wof:name":"Arhaus Furniture",
    "wof:placetype":"venue"
},
  "geometry": {"coordinates":[-83.214597,42.547288],"type":"Point"}
}