{
  "type": "Feature",
  "properties": {
    "iso:country":"US",
    "sg:address":"324 W Erie Rd",
    "sg:city":"Temperance",
    "sg:classifiers":[
        {
            "category":"Professional",
            "subcategory":"Engineering",
            "type":"Services"
        }
    ],
    "sg:phone":"+1 734 856 1266",
    "sg:postcode":"48182",
    "sg:province":"MI",
    "sg:tags":[
        "general",
        "contractor"
    ],
    "wof:name":"George Kreft",
    "wof:placetype":"venue"
},
  "geometry": {"coordinates":[-83.55615899999999,41.794185],"type":"Point"}
}