{
  "type": "Feature",
  "properties": {
    "iso:country":"US",
    "sg:address":"108 1st St",
    "sg:city":"Battle Creek",
    "sg:classifiers":[
        {
            "category":"Professional",
            "subcategory":"Art Services",
            "type":"Services"
        }
    ],
    "sg:phone":"+1 231 264 0505",
    "sg:postcode":"49014",
    "sg:province":"MI",
    "sg:tags":[
        "photographer"
    ],
    "wof:name":"Kym's Photo Kopies & More",
    "wof:placetype":"venue"
},
  "geometry": {"coordinates":[-85.162294,42.312707],"type":"Point"}
}