{
  "type": "Feature",
  "properties": {
    "iso:country":"US",
    "sg:address":"20175 40th Ave",
    "sg:city":"Marion",
    "sg:classifiers":[
        {
            "category":"Freight",
            "type":"Transportation"
        }
    ],
    "sg:phone":"+1 231 743 6452",
    "sg:postcode":"49665",
    "sg:province":"MI",
    "sg:tags":[
        "operator",
        "local",
        "trucking"
    ],
    "wof:name":"Terry Wagner Trucking",
    "wof:placetype":"venue"
},
  "geometry": {"coordinates":[-85.167603,44.104899],"type":"Point"}
}