{
  "type": "Feature",
  "properties": {
    "iso:country":"US",
    "sg:address":"53300 Van Dyke Ave",
    "sg:city":"Shelby Twp",
    "sg:classifiers":[
        {
            "category":"Education",
            "subcategory":"School",
            "type":"Public Place"
        }
    ],
    "sg:phone":"+1 586 677 8133",
    "sg:postcode":"48316",
    "sg:province":"MI",
    "wof:name":"Petite School Of Knowledge",
    "wof:placetype":"venue"
},
  "geometry": {"coordinates":[-83.03442699999999,42.687056],"type":"Point"}
}