{
  "type": "Feature",
  "properties": {
    "iso:country":"US",
    "sg:address":"7210 N Merriman Rd",
    "sg:city":"Westland",
    "sg:classifiers":[
        {
            "category":"Retail",
            "subcategory":"Auto Repair",
            "type":"Services"
        }
    ],
    "sg:phone":"+1 734 421 6446",
    "sg:postcode":"48185",
    "sg:province":"MI",
    "wof:name":"Muffler Man",
    "wof:placetype":"venue"
},
  "geometry": {"coordinates":[-83.34989899999999,42.340199],"type":"Point"}
}