{
  "type": "Feature",
  "properties": {
    "iso:country":"US",
    "sg:address":"444 W Lincoln St",
    "sg:city":"Birmingham",
    "sg:classifiers":[
        {
            "category":"Professional",
            "subcategory":"Management & Consulting",
            "type":"Services"
        }
    ],
    "sg:phone":"+1 248 647 5822",
    "sg:postcode":"48009",
    "sg:province":"MI",
    "sg:tags":[
        "party",
        "planning"
    ],
    "wof:name":"Occasions",
    "wof:placetype":"venue"
},
  "geometry": {"coordinates":[-83.218828,42.538854],"type":"Point"}
}