{
  "type": "Feature",
  "properties": {
    "iso:country":"US",
    "sg:address":"608 24th St",
    "sg:city":"Port Huron",
    "sg:classifiers":[
        {
            "category":"Restaurant",
            "type":"Food & Drink"
        }
    ],
    "sg:menulink":"http://www.allmenus.com/mi/port-huron/176469-kfc---kentucky-fried-chicken/menu/",
    "sg:phone":"+1 810 984 5083",
    "sg:postcode":"48060",
    "sg:province":"MI",
    "sg:tags":[
        "american",
        "chicken"
    ],
    "wof:name":"KFC - Kentucky Fried Chicken",
    "wof:placetype":"venue"
},
  "geometry": {"coordinates":[-82.45291,42.976914],"type":"Point"}
}