{
  "type": "Feature",
  "properties": {
    "iso:country":"US",
    "sg:address":"12048 S Straits Hwy",
    "sg:city":"Wolverine",
    "sg:classifiers":[
        {
            "category":"Recreation",
            "type":"Entertainment"
        }
    ],
    "sg:phone":"+1 231 525 8414",
    "sg:postcode":"49799",
    "sg:province":"MI",
    "wof:name":"Grandia Inc",
    "wof:placetype":"venue"
},
  "geometry": {"coordinates":[-84.60762699999999,45.287142],"type":"Point"}
}