{
  "type": "Feature",
  "properties": {
    "iso:country":"US",
    "sg:address":"14031 Fenton",
    "sg:city":"Redford",
    "sg:classifiers":[
        {
            "category":"Real Estate",
            "subcategory":"Developer",
            "type":"Services"
        }
    ],
    "sg:phone":"+1 313 531 8736",
    "sg:postcode":"48239",
    "sg:province":"MI",
    "wof:name":"Atinez Development",
    "wof:placetype":"venue"
},
  "geometry": {"coordinates":[-83.28133200000001,42.390017],"type":"Point"}
}