{
  "type": "Feature",
  "properties": {
    "iso:country":"US",
    "sg:address":"3655 28th St SE",
    "sg:city":"Grand Rapids",
    "sg:classifiers":[
        {
            "category":"Shopping",
            "type":"Retail Goods"
        }
    ],
    "sg:phone":"+1 616 942 5600",
    "sg:postcode":"49512",
    "sg:province":"MI",
    "sg:tags":[
        "art",
        "gallery",
        "dealer"
    ],
    "wof:name":"Gallery",
    "wof:placetype":"venue"
},
  "geometry": {"coordinates":[-85.57726099999999,42.912596],"type":"Point"}
}