{
  "type": "Feature",
  "properties": {
    "iso:country":"US",
    "sg:address":"24660 Beierman Ave",
    "sg:city":"Warren",
    "sg:classifiers":[
        {
            "category":"Professional",
            "subcategory":"Engineering",
            "type":"Services"
        }
    ],
    "sg:phone":"+1 586 754 2835",
    "sg:postcode":"48091",
    "sg:province":"MI",
    "wof:name":"Bn Engineering Associate",
    "wof:placetype":"venue"
},
  "geometry": {"coordinates":[-83.05575,42.475306],"type":"Point"}
}