{
  "type": "Feature",
  "properties": {
    "iso:country":"US",
    "sg:address":"911 Crescent St NE",
    "sg:city":"Grand Rapids",
    "sg:classifiers":[
        {
            "category":"Building & Trades",
            "subcategory":"Construction",
            "type":"Services"
        }
    ],
    "sg:phone":"+1 616 454 8834",
    "sg:postcode":"49503",
    "sg:province":"MI",
    "sg:tags":[
        "hanging",
        "contractor"
    ],
    "wof:name":"Colonial Decorators",
    "wof:placetype":"venue"
},
  "geometry": {"coordinates":[-85.64484400000001,42.969162],"type":"Point"}
}