{
  "type": "Feature",
  "properties": {
    "iso:country":"US",
    "sg:address":"5042 Clydesdale Ln",
    "sg:city":"Saginaw",
    "sg:classifiers":[
        {
            "category":"Professional",
            "type":"Services"
        }
    ],
    "sg:phone":"+1 989 792 0208",
    "sg:postcode":"48603",
    "sg:province":"MI",
    "wof:name":"Reginald Bixler",
    "wof:placetype":"venue"
},
  "geometry": {"coordinates":[-84.01564500000001,43.44871],"type":"Point"}
}