{
  "type": "Feature",
  "properties": {
    "iso:country":"US",
    "sg:address":"4917 Schaefer Rd",
    "sg:city":"Dearborn",
    "sg:classifiers":[
        {
            "category":"Banks & Credit Unions",
            "subcategory":"Bank",
            "type":"Services"
        }
    ],
    "sg:phone":"+1 313 582 1158",
    "sg:postcode":"48126",
    "sg:province":"MI",
    "sg:tags":[
        "banker",
        "mortgage"
    ],
    "wof:name":"Colony Mortgage Corporation",
    "wof:placetype":"venue"
},
  "geometry": {"coordinates":[-83.176098,42.323745],"type":"Point"}
}