{
  "type": "Feature",
  "properties": {
    "iso:country":"US",
    "sg:address":"507 Water St",
    "sg:city":"East Jordan",
    "sg:classifiers":[
        {
            "category":"Organizations",
            "subcategory":"Non-profit Organization",
            "type":"Services"
        }
    ],
    "sg:phone":"+1 231 536 2440",
    "sg:postcode":"49727",
    "sg:province":"MI",
    "wof:name":"Charlevoix County Comm Fndtn",
    "wof:placetype":"venue"
},
  "geometry": {"coordinates":[-85.13888799999999,45.154034],"type":"Point"}
}