{
  "type": "Feature",
  "properties": {
    "iso:country":"US",
    "sg:address":"6133 Keller Rd",
    "sg:city":"Delton",
    "sg:classifiers":[
        {
            "category":"Building & Trades",
            "subcategory":"Construction",
            "type":"Services"
        }
    ],
    "sg:phone":"+1 269 623 3912",
    "sg:postcode":"49046",
    "sg:province":"MI",
    "sg:tags":[
        "designer",
        "dealer",
        "pool",
        "swimming"
    ],
    "sg:website":"www.swimsmith.com",
    "wof:name":"Swimsmith Co",
    "wof:placetype":"venue"
},
  "geometry": {"coordinates":[-85.407105,42.558388],"type":"Point"}
}