{
  "type": "Feature",
  "properties": {
    "iso:country":"US",
    "sg:address":"2801 W Delhi Rd",
    "sg:city":"Ann Arbor",
    "sg:classifiers":[
        {
            "category":"Recreation",
            "type":"Entertainment"
        }
    ],
    "sg:phone":"+1 734 668 7090",
    "sg:postcode":"48103",
    "sg:province":"MI",
    "wof:name":"Hawthorn Hill Farm Inc",
    "wof:placetype":"venue"
},
  "geometry": {"coordinates":[-83.820391,42.319977],"type":"Point"}
}