{
  "type": "Feature",
  "properties": {
    "iso:country":"US",
    "sg:address":"244 N Rose St",
    "sg:city":"Kalamazoo",
    "sg:classifiers":[
        {
            "category":"Banks & Credit Unions",
            "subcategory":"Financial Services",
            "type":"Services"
        }
    ],
    "sg:phone":"+1 269 552 9233",
    "sg:postcode":"49007",
    "sg:province":"MI",
    "sg:tags":[
        "management",
        "open",
        "investment"
    ],
    "wof:name":"Sled Runner Investments Inc",
    "wof:placetype":"venue"
},
  "geometry": {"coordinates":[-85.58474,42.293112],"type":"Point"}
}