{
  "type": "Feature",
  "properties": {
    "iso:country":"US",
    "sg:address":"28983 Little Mack Ave",
    "sg:city":"Saint Clair Shores",
    "sg:classifiers":[
        {
            "category":"Manufacturing",
            "subcategory":"Textiles",
            "type":"Manufacturing & Wholesale Goods"
        }
    ],
    "sg:phone":"+1 586 772 1196",
    "sg:postcode":"48081",
    "sg:province":"MI",
    "sg:tags":[
        "interior",
        "curtain",
        "design"
    ],
    "wof:name":"Nitsa's Interiors",
    "wof:placetype":"venue"
},
  "geometry": {"coordinates":[-82.908401,42.509499],"type":"Point"}
}