{
  "type": "Feature",
  "properties": {
    "iso:country":"US",
    "sg:address":"35 W Chicago St",
    "sg:city":"Coldwater",
    "sg:classifiers":[
        {
            "category":"Shopping",
            "subcategory":"Clothing, Apparel, & Fashions",
            "type":"Retail Goods"
        }
    ],
    "sg:phone":"+1 517 279 7249",
    "sg:postcode":"49036",
    "sg:province":"MI",
    "sg:tags":[
        "wear"
    ],
    "wof:name":"Mulberry Bush",
    "wof:placetype":"venue"
},
  "geometry": {"coordinates":[-85.001634,41.940657],"type":"Point"}
}