{
  "type": "Feature",
  "properties": {
    "iso:country":"US",
    "sg:address":"138 W Slosson Ave",
    "sg:city":"Reed City",
    "sg:classifiers":[
        {
            "category":"Retail",
            "subcategory":"Funeral Services",
            "type":"Services"
        }
    ],
    "sg:phone":"+1 231 832 2251",
    "sg:postcode":"49677",
    "sg:province":"MI",
    "sg:tags":[
        "director"
    ],
    "wof:name":"Mc Dowell Funeral Home",
    "wof:placetype":"venue"
},
  "geometry": {"coordinates":[-85.511162,43.874918],"type":"Point"}
}