{
  "type": "Feature",
  "properties": {
    "iso:country":"US",
    "sg:address":"9297 SW Greenville Rd",
    "sg:city":"Greenville",
    "sg:classifiers":[
        {
            "category":"Wholesale",
            "subcategory":"Machinery & Supplies",
            "type":"Manufacturing & Wholesale Goods"
        }
    ],
    "sg:phone":"+1 616 754 1339",
    "sg:postcode":"48838",
    "sg:province":"MI",
    "sg:tags":[
        "valve"
    ],
    "wof:name":"ABS Ind Supply",
    "wof:placetype":"venue"
},
  "geometry": {"coordinates":[-85.25694,43.158862],"type":"Point"}
}