{
  "type": "Feature",
  "properties": {
    "iso:country":"US",
    "sg:address":"401 S Old Woodward Ave",
    "sg:city":"Birmingham",
    "sg:classifiers":[
        {
            "category":"Banks & Credit Unions",
            "subcategory":"Financial Services",
            "type":"Services"
        }
    ],
    "sg:phone":"+1 248 723 1300",
    "sg:postcode":"48009",
    "sg:province":"MI",
    "sg:tags":[
        "broker",
        "mortgage"
    ],
    "wof:name":"Hamlin Mortgage Company",
    "wof:placetype":"venue"
},
  "geometry": {"coordinates":[-83.212097,42.544399],"type":"Point"}
}