{
  "type": "Feature",
  "properties": {
    "iso:country":"US",
    "sg:address":"104 W Scott St",
    "sg:city":"Grand Ledge",
    "sg:classifiers":[
        {
            "category":"Health Services",
            "subcategory":"Chiropractor",
            "type":"Services"
        }
    ],
    "sg:phone":"+1 517 627 3525",
    "sg:postcode":"48837",
    "sg:province":"MI",
    "wof:name":"Koroniotis Chiropractic Clinic",
    "wof:placetype":"venue"
},
  "geometry": {"coordinates":[-84.747381,42.752638],"type":"Point"}
}