{
  "type": "Feature",
  "properties": {
    "iso:country":"US",
    "sg:address":"27942 Harper Ave",
    "sg:city":"St Clair Shores",
    "sg:classifiers":[
        {
            "category":"Shopping",
            "subcategory":"Florist",
            "type":"Retail Goods"
        }
    ],
    "sg:phone":"+1 586 445 2010",
    "sg:postcode":"48081",
    "sg:province":"MI",
    "wof:name":"Salvaggio Floral",
    "wof:placetype":"venue"
},
  "geometry": {"coordinates":[-82.897671,42.497529],"type":"Point"}
}