{
  "type": "Feature",
  "properties": {
    "iso:country":"US",
    "sg:address":"1128 Seville Rd",
    "sg:city":"Rochester",
    "sg:classifiers":[
        {
            "category":"Building & Trades",
            "subcategory":"Construction",
            "type":"Services"
        }
    ],
    "sg:phone":"+1 248 651 1735",
    "sg:postcode":"48309",
    "sg:province":"MI",
    "sg:tags":[
        "house",
        "nonresidential"
    ],
    "wof:name":"Building Unlimited Inc",
    "wof:placetype":"venue"
},
  "geometry": {"coordinates":[-83.166057,42.661674],"type":"Point"}
}