{
  "type": "Feature",
  "properties": {
    "iso:country":"US",
    "sg:address":"30834 Schoenherr Rd",
    "sg:city":"Warren",
    "sg:classifiers":[
        {
            "category":"Shopping",
            "subcategory":"Pharmacy",
            "type":"Retail Goods"
        }
    ],
    "sg:phone":"+1 586 775 1221",
    "sg:postcode":"48088",
    "sg:province":"MI",
    "sg:tags":[
        "drugstore"
    ],
    "wof:name":"Sterling-Warren Pharmacy",
    "wof:placetype":"venue"
},
  "geometry": {"coordinates":[-82.988035,42.520665],"type":"Point"}
}