{
  "type": "Feature",
  "properties": {
    "iso:country":"US",
    "sg:address":"47054 Auburn Ct",
    "sg:city":"Utica",
    "sg:classifiers":[
        {
            "category":"Professional",
            "subcategory":"Business Services",
            "type":"Services"
        }
    ],
    "sg:phone":"+1 586 246 5881",
    "sg:postcode":"48317",
    "sg:province":"MI",
    "wof:name":"Jt Enterprises",
    "wof:placetype":"venue"
},
  "geometry": {"coordinates":[-83.065629,42.639652],"type":"Point"}
}