{
  "type": "Feature",
  "properties": {
    "iso:country":"US",
    "sg:address":"9284 W 8th St",
    "sg:city":"Hesperia",
    "sg:classifiers":[
        {
            "category":"Farming",
            "subcategory":"Farm",
            "type":"Manufacturing & Wholesale Goods"
        }
    ],
    "sg:phone":"+1 231 854 1667",
    "sg:postcode":"49421",
    "sg:province":"MI",
    "sg:tags":[
        "crop",
        "general"
    ],
    "wof:name":"Isabel Prentiss",
    "wof:placetype":"venue"
},
  "geometry": {"coordinates":[-86.031741,43.539537],"type":"Point"}
}