{
  "type": "Feature",
  "properties": {
    "iso:country":"US",
    "sg:address":"207 E Columbia Ave",
    "sg:city":"Battle Creek",
    "sg:classifiers":[
        {
            "category":"Real Estate",
            "subcategory":"Real Estate Agent",
            "type":"Services"
        },
        {
            "category":"Professional",
            "subcategory":"Business Services",
            "type":"Services"
        }
    ],
    "sg:phone":"+1 269 965 1444",
    "sg:postcode":"49015",
    "sg:province":"MI",
    "sg:tags":[
        "appraiser"
    ],
    "sg:website":"www.bratcherandassociates.com",
    "wof:name":"Bratcher & Associates",
    "wof:placetype":"venue"
},
  "geometry": {"coordinates":[-85.191204,42.298652],"type":"Point"}
}