{
  "type": "Feature",
  "properties": {
    "iso:country":"US",
    "sg:address":"211 E Saint Clair St",
    "sg:city":"Romeo",
    "sg:classifiers":[
        {
            "category":"Food & Beverages",
            "subcategory":"Liquor & Beverages",
            "type":"Retail Goods"
        }
    ],
    "sg:phone":"+1 586 752 4000",
    "sg:postcode":"48065",
    "sg:province":"MI",
    "wof:name":"Uptown Liquor Stores",
    "wof:placetype":"venue"
},
  "geometry": {"coordinates":[-83.013041,42.802675],"type":"Point"}
}