{
  "type": "Feature",
  "properties": {
    "iso:country":"US",
    "sg:address":"2516 State Hwy 55",
    "sg:city":"Tawas City",
    "sg:classifiers":[
        {
            "category":"Home & Garden",
            "subcategory":"Garden Supply",
            "type":"Retail Goods"
        }
    ],
    "sg:phone":"+1 989 362 4143",
    "sg:postcode":"48763",
    "sg:province":"MI",
    "sg:tags":[
        "engine"
    ],
    "wof:name":"Now Small Engine Repair",
    "wof:placetype":"venue"
},
  "geometry": {"coordinates":[-83.62753600000001,44.278879],"type":"Point"}
}