{
  "type": "Feature",
  "properties": {
    "iso:country":"US",
    "sg:address":"14220 Michigan Ave",
    "sg:city":"Dearborn",
    "sg:classifiers":[
        {
            "category":"Retail",
            "subcategory":"Self-service Laundry",
            "type":"Services"
        }
    ],
    "sg:phone":"+1 313 584 8290",
    "sg:postcode":"48126",
    "sg:province":"MI",
    "sg:tags":[
        "operated",
        "dry",
        "coin",
        "cleaning"
    ],
    "wof:name":"Air Fresh Laundry & Cleaners",
    "wof:placetype":"venue"
},
  "geometry": {"coordinates":[-83.181332,42.320701],"type":"Point"}
}