{
  "type": "Feature",
  "properties": {
    "iso:country":"US",
    "sg:address":"14444 W McNichols Rd",
    "sg:city":"Detroit",
    "sg:classifiers":[
        {
            "category":"Personal",
            "subcategory":"Beauty Salon",
            "type":"Services"
        }
    ],
    "sg:phone":"+1 313 863 9757",
    "sg:postcode":"48235",
    "sg:province":"MI",
    "sg:tags":[
        "shop"
    ],
    "wof:name":"Xavier Hair & Nails",
    "wof:placetype":"venue"
},
  "geometry": {"coordinates":[-83.188039,42.416563],"type":"Point"}
}