{
  "type": "Feature",
  "properties": {
    "iso:country":"US",
    "sg:address":"2494 Deckerville Rd",
    "sg:city":"Snover",
    "sg:classifiers":[
        {
            "category":"Shopping",
            "subcategory":"Gifts & Souvenirs",
            "type":"Retail Goods"
        }
    ],
    "sg:phone":"+1 810 672 9344",
    "sg:postcode":"48472",
    "sg:province":"MI",
    "sg:tags":[
        "party",
        "supply"
    ],
    "wof:name":"Best Place Inc",
    "wof:placetype":"venue"
},
  "geometry": {"coordinates":[-82.91528599999999,43.521611],"type":"Point"}
}