{
  "type": "Feature",
  "properties": {
    "iso:country":"US",
    "sg:address":"8080 N 32nd St",
    "sg:city":"Richland",
    "sg:classifiers":[
        {
            "category":"Personal",
            "subcategory":"Beauty Salon",
            "type":"Services"
        }
    ],
    "sg:phone":"+1 269 629 4237",
    "sg:postcode":"49083",
    "sg:province":"MI",
    "wof:name":"Hair Den",
    "wof:placetype":"venue"
},
  "geometry": {"coordinates":[-85.455196,42.37774],"type":"Point"}
}