{
  "type": "Feature",
  "properties": {
    "iso:country":"US",
    "sg:address":"3244 Johnson Rd",
    "sg:city":"Stevensville",
    "sg:classifiers":[
        {
            "category":"Professional",
            "subcategory":"Computer Services",
            "type":"Services"
        }
    ],
    "sg:phone":"+1 269 466 2082",
    "sg:postcode":"49127",
    "sg:province":"MI",
    "sg:tags":[
        "related"
    ],
    "wof:name":"Straight Gate",
    "wof:placetype":"venue"
},
  "geometry": {"coordinates":[-86.52974399999999,42.00713],"type":"Point"}
}