{
  "type": "Feature",
  "properties": {
    "iso:country":"US",
    "sg:address":"1113 Washington Ave",
    "sg:city":"Grand Haven",
    "sg:classifiers":[
        {
            "category":"Personal",
            "subcategory":"Beauty Salon",
            "type":"Services"
        }
    ],
    "sg:phone":"+1 616 842 1590",
    "sg:postcode":"49417",
    "sg:province":"MI",
    "wof:name":"Envogue Hair & Tanning Salon",
    "wof:placetype":"venue"
},
  "geometry": {"coordinates":[-86.21551599999999,43.061035],"type":"Point"}
}