{
  "type": "Feature",
  "properties": {
    "iso:country":"US",
    "sg:address":"3404 Pine Grove Dr",
    "sg:city":"Midland",
    "sg:classifiers":[
        {
            "category":"Professional",
            "subcategory":"Research",
            "type":"Services"
        }
    ],
    "sg:phone":"+1 989 631 8824",
    "sg:postcode":"48640",
    "sg:province":"MI",
    "sg:tags":[
        "organization",
        "noncommercial"
    ],
    "wof:name":"Rrc Consulting LLC",
    "wof:placetype":"venue"
},
  "geometry": {"coordinates":[-84.26886399999999,43.630237],"type":"Point"}
}