{
  "type": "Feature",
  "properties": {
    "iso:country":"US",
    "sg:address":"215 S Greendale Rd",
    "sg:city":"Shepherd",
    "sg:classifiers":[
        {
            "category":"Retail",
            "subcategory":"Auto Repair",
            "type":"Services"
        }
    ],
    "sg:phone":"+1 989 772 3198",
    "sg:postcode":"48883",
    "sg:province":"MI",
    "sg:tags":[
        "body",
        "supply"
    ],
    "wof:name":"Dave Starks Vets",
    "wof:placetype":"venue"
},
  "geometry": {"coordinates":[-84.578221,43.604539],"type":"Point"}
}