{
  "type": "Feature",
  "properties": {
    "iso:country":"US",
    "sg:address":"1361 S Crawford Rd",
    "sg:city":"Mount Pleasant",
    "sg:classifiers":[
        {
            "category":"Professional",
            "subcategory":"Management & Consulting",
            "type":"Services"
        }
    ],
    "sg:phone":"+1 989 289 8393",
    "sg:postcode":"48858",
    "sg:province":"MI",
    "sg:tags":[
        "business"
    ],
    "wof:name":"Kurt Nothstine Consulting",
    "wof:placetype":"venue"
},
  "geometry": {"coordinates":[-84.787457,43.588411],"type":"Point"}
}