{
  "type": "Feature",
  "properties": {
    "iso:country":"US",
    "sg:address":"141 W Upton Ave",
    "sg:city":"Reed City",
    "sg:classifiers":[
        {
            "category":"Personal",
            "subcategory":"Beauty Salon",
            "type":"Services"
        }
    ],
    "sg:phone":"+1 231 832 2228",
    "sg:postcode":"49677",
    "sg:province":"MI",
    "sg:tags":[
        "shop"
    ],
    "wof:name":"Prime Design Hair Salon",
    "wof:placetype":"venue"
},
  "geometry": {"coordinates":[-85.51114200000001,43.875883],"type":"Point"}
}