{
  "type": "Feature",
  "properties": {
    "iso:country":"US",
    "sg:address":"565 W Hathaway Rd",
    "sg:city":"Harbor Springs",
    "sg:classifiers":[
        {
            "category":"Travel",
            "subcategory":"Campground",
            "type":"Entertainment"
        }
    ],
    "sg:phone":"+1 231 436 5643",
    "sg:postcode":"49740",
    "sg:province":"MI",
    "sg:tags":[
        "trailer"
    ],
    "wof:name":"Mackinaw City KOA",
    "wof:placetype":"venue"
},
  "geometry": {"coordinates":[-84.92801,45.435074],"type":"Point"}
}