{
  "type": "Feature",
  "properties": {
    "iso:country":"US",
    "sg:address":"31435 Madison Ave",
    "sg:city":"Madison Heights",
    "sg:classifiers":[
        {
            "category":"Wholesale",
            "subcategory":"Chemicals & Plastics",
            "type":"Manufacturing & Wholesale Goods"
        }
    ],
    "sg:phone":"+1 248 588 8833",
    "sg:postcode":"48071",
    "sg:province":"MI",
    "sg:tags":[
        "dyestuff",
        "dye"
    ],
    "sg:website":"www.midlanddesignservice.com",
    "wof:name":"Midland Design Svc",
    "wof:placetype":"venue"
},
  "geometry": {"coordinates":[-83.124816,42.523107],"type":"Point"}
}