{
  "type": "Feature",
  "properties": {
    "iso:country":"US",
    "sg:address":"57 Division St",
    "sg:city":"Coldwater",
    "sg:classifiers":[
        {
            "category":"Government",
            "subcategory":"Fire Station",
            "type":"Public Place"
        },
        {
            "category":"Government",
            "subcategory":"Police Station",
            "type":"Public Place"
        }
    ],
    "sg:phone":"+1 517 278 4177",
    "sg:postcode":"49036",
    "sg:province":"MI",
    "sg:tags":[
        "department",
        "protection"
    ],
    "wof:name":"Coldwater Police Department",
    "wof:placetype":"venue"
},
  "geometry": {"coordinates":[-85.00115599999999,41.938795],"type":"Point"}
}