{
  "type": "Feature",
  "properties": {
    "iso:country":"US",
    "sg:address":"4150 Pontiac Lake Rd",
    "sg:city":"Waterford",
    "sg:classifiers":[
        {
            "category":"Organizations",
            "subcategory":"Religious Organization",
            "type":"Services"
        }
    ],
    "sg:phone":"+1 248 674 1212",
    "sg:postcode":"48328",
    "sg:province":"MI",
    "sg:tags":[
        "church"
    ],
    "sg:website":"www.ascensionlutheran.us",
    "wof:name":"Ascension Lutheran Church",
    "wof:placetype":"venue"
},
  "geometry": {"coordinates":[-83.368692,42.654969],"type":"Point"}
}