{
  "type": "Feature",
  "properties": {
    "iso:country":"US",
    "sg:address":"4024 Eagle Lake Rd",
    "sg:city":"Bloomingdale",
    "sg:classifiers":[
        {
            "category":"Autos & Motor Vehicles",
            "subcategory":"Automobile Sales",
            "type":"Retail Goods"
        }
    ],
    "sg:phone":"+1 269 521 3859",
    "sg:postcode":"49026",
    "sg:province":"MI",
    "sg:tags":[
        "used"
    ],
    "wof:name":"Youngbloods Auto Sales",
    "wof:placetype":"venue"
},
  "geometry": {"coordinates":[-85.931236,42.432971],"type":"Point"}
}