{
  "type": "Feature",
  "properties": {
    "iso:country":"US",
    "sg:address":"20932 Harper Ave",
    "sg:city":"Harper Woods",
    "sg:classifiers":[
        {
            "category":"Retail",
            "subcategory":"Auto Repair",
            "type":"Services"
        }
    ],
    "sg:phone":"+1 313 886 8755",
    "sg:postcode":"48225",
    "sg:province":"MI",
    "sg:tags":[
        "conversion",
        "van",
        "custom"
    ],
    "wof:name":"Custom Van LLC",
    "wof:placetype":"venue"
},
  "geometry": {"coordinates":[-82.914993,42.449576],"type":"Point"}
}