{
  "type": "Feature",
  "properties": {
    "iso:country":"US",
    "sg:address":"4952 Rauch Rd",
    "sg:city":"Petersburg",
    "sg:classifiers":[
        {
            "category":"Building & Trades",
            "subcategory":"Construction",
            "type":"Services"
        }
    ],
    "sg:phone":"+1 734 856 1057",
    "sg:postcode":"49270",
    "sg:province":"MI",
    "sg:tags":[
        "excavating",
        "contractor"
    ],
    "wof:name":"Link Brothers Trucking",
    "wof:placetype":"venue"
},
  "geometry": {"coordinates":[-83.664862,41.822136],"type":"Point"}
}