{
  "type": "Feature",
  "properties": {
    "iso:country":"US",
    "sg:address":"1241 E Beltline Ave NE",
    "sg:city":"Grand Rapids",
    "sg:classifiers":[
        {
            "category":"Professional",
            "subcategory":"Management & Consulting",
            "type":"Services"
        },
        {
            "category":"Professional",
            "subcategory":"Accounting & Tax Preparation",
            "type":"Services"
        }
    ],
    "sg:phone":"+1 616 942 6440",
    "sg:postcode":"49525",
    "sg:province":"MI",
    "sg:tags":[
        "accountant"
    ],
    "sg:website":"www.ahpplc.com",
    "wof:name":"Andrews Hooper & Pavlik P L C",
    "wof:placetype":"venue"
},
  "geometry": {"coordinates":[-85.59081399999999,42.985171],"type":"Point"}
}