{
  "type": "Feature",
  "properties": {
    "iso:country":"US",
    "sg:address":"2850 E Beltline Ave NE",
    "sg:city":"Grand Rapids",
    "sg:classifiers":[
        {
            "category":"Professional",
            "subcategory":"Accounting & Tax Preparation",
            "type":"Services"
        }
    ],
    "sg:phone":"+1 616 361 1559",
    "sg:postcode":"49525",
    "sg:province":"MI",
    "sg:tags":[
        "accountant"
    ],
    "wof:name":"Stephan P De WITT & Co",
    "wof:placetype":"venue"
},
  "geometry": {"coordinates":[-85.589995,43.014387],"type":"Point"}
}