{
  "type": "Feature",
  "properties": {
    "iso:country":"US",
    "sg:address":"2505 S Waverly Rd",
    "sg:city":"Lansing",
    "sg:classifiers":[
        {
            "category":"Building & Trades",
            "subcategory":"Construction",
            "type":"Services"
        }
    ],
    "sg:phone":"+1 517 646 9166",
    "sg:postcode":"48911",
    "sg:province":"MI",
    "sg:tags":[
        "concrete",
        "contractor"
    ],
    "wof:name":"Lansing Poured Wall Co",
    "wof:placetype":"venue"
},
  "geometry": {"coordinates":[-84.603005,42.706711],"type":"Point"}
}