{
  "type": "Feature",
  "properties": {
    "iso:country":"US",
    "sg:address":"3924 Pine Grove Ave",
    "sg:city":"Fort Gratiot",
    "sg:classifiers":[
        {
            "category":"Building & Trades",
            "subcategory":"Electrical",
            "type":"Services"
        }
    ],
    "sg:phone":"+1 810 984 2503",
    "sg:postcode":"48059",
    "sg:province":"MI",
    "sg:tags":[
        "electric",
        "contractor"
    ],
    "wof:name":"Northern Electric & Lighting",
    "wof:placetype":"venue"
},
  "geometry": {"coordinates":[-82.467674,43.029969],"type":"Point"}
}