{
  "type": "Feature",
  "properties": {
    "iso:country":"US",
    "sg:address":"45810 Edgewater St",
    "sg:city":"New Baltimore",
    "sg:classifiers":[
        {
            "category":"Building & Trades",
            "subcategory":"Construction",
            "type":"Services"
        }
    ],
    "sg:phone":"+1 586 949 5918",
    "sg:postcode":"48047",
    "sg:province":"MI",
    "sg:tags":[
        "house"
    ],
    "wof:name":"Dalessandr Construction C",
    "wof:placetype":"venue"
},
  "geometry": {"coordinates":[-82.81532300000001,42.640116],"type":"Point"}
}