{
  "type": "Feature",
  "properties": {
    "iso:country":"US",
    "sg:address":"439 Toll St",
    "sg:city":"Monroe",
    "sg:classifiers":[
        {
            "category":"Building & Trades",
            "subcategory":"Construction",
            "type":"Services"
        }
    ],
    "sg:phone":"+1 734 384 8482",
    "sg:postcode":"48162",
    "sg:province":"MI",
    "sg:tags":[
        "house"
    ],
    "wof:name":"Amato Construction",
    "wof:placetype":"venue"
},
  "geometry": {"coordinates":[-83.40684899999999,41.926843],"type":"Point"}
}