{
  "type": "Feature",
  "properties": {
    "iso:country":"US",
    "sg:address":"27081 Co Rd 354",
    "sg:city":"Lawton",
    "sg:classifiers":[
        {
            "category":"Professional",
            "subcategory":"Computer Services",
            "type":"Services"
        }
    ],
    "sg:phone":"+1 269 624 9926",
    "sg:postcode":"49065",
    "sg:province":"MI",
    "sg:tags":[
        "design",
        "system"
    ],
    "wof:name":"Technical Computer Support",
    "wof:placetype":"venue"
},
  "geometry": {"coordinates":[-85.81377000000001,42.142005],"type":"Point"}
}