{
  "type": "Feature",
  "properties": {
    "iso:country":"US",
    "sg:address":"1410 Phelon St",
    "sg:city":"Saginaw",
    "sg:classifiers":[
        {
            "category":"Real Estate",
            "subcategory":"Real Estate Agent",
            "type":"Services"
        }
    ],
    "sg:phone":"+1 989 754 4421",
    "sg:postcode":"48601",
    "sg:province":"MI",
    "wof:name":"Beets Bob & Assoc Real Estate",
    "wof:placetype":"venue"
},
  "geometry": {"coordinates":[-83.931178,43.417295],"type":"Point"}
}