{
  "type": "Feature",
  "properties": {
    "iso:country":"US",
    "sg:address":"707 S Van Dyke Rd",
    "sg:city":"Bad Axe",
    "sg:classifiers":[
        {
            "category":"Food & Beverages",
            "subcategory":"Groceries & Convenience Stores",
            "type":"Retail Goods"
        }
    ],
    "sg:phone":"+1 989 269 6711",
    "sg:postcode":"48413",
    "sg:province":"MI",
    "wof:name":"People's Choice Market",
    "wof:placetype":"venue"
},
  "geometry": {"coordinates":[-83.013794,43.801713],"type":"Point"}
}