{
  "type": "Feature",
  "properties": {
    "iso:country":"US",
    "sg:address":"49949 Downing Ct",
    "sg:city":"Shelby Twp",
    "sg:classifiers":[
        {
            "category":"Professional",
            "type":"Services"
        }
    ],
    "sg:phone":"+1 586 566 1722",
    "sg:postcode":"48315",
    "sg:province":"MI",
    "sg:tags":[
        "establishment"
    ],
    "wof:name":"K F Wilde",
    "wof:placetype":"venue"
},
  "geometry": {"coordinates":[-82.991446,42.66278],"type":"Point"}
}