{
  "type": "Feature",
  "properties": {
    "iso:country":"US",
    "sg:address":"119 S State St",
    "sg:city":"Shelby",
    "sg:classifiers":[
        {
            "category":"Professional",
            "type":"Services"
        }
    ],
    "sg:phone":"+1 231 861 6349",
    "sg:postcode":"49455",
    "sg:province":"MI",
    "sg:tags":[
        "establishment"
    ],
    "wof:name":"Migrant Wic Program",
    "wof:placetype":"venue"
},
  "geometry": {"coordinates":[-86.36593999999999,43.606334],"type":"Point"}
}