{
  "type": "Feature",
  "properties": {
    "iso:country":"US",
    "sg:address":"15701 E 9 Mile Rd",
    "sg:city":"Eastpointe",
    "sg:classifiers":[
        {
            "category":"Government",
            "subcategory":"Office",
            "type":"Public Place"
        }
    ],
    "sg:phone":"+1 586 445 5099",
    "sg:postcode":"48021",
    "sg:province":"MI",
    "sg:tags":[
        "village"
    ],
    "wof:name":"Eastpointe Housing Commission",
    "wof:placetype":"venue"
},
  "geometry": {"coordinates":[-82.960188,42.464714],"type":"Point"}
}