{
  "type": "Feature",
  "properties": {
    "iso:country":"US",
    "sg:address":"28011 Schoenherr Rd",
    "sg:city":"Warren",
    "sg:classifiers":[
        {
            "category":"Shopping",
            "subcategory":"Pharmacy",
            "type":"Retail Goods"
        }
    ],
    "sg:phone":"+1 586 582 0700",
    "sg:postcode":"48088",
    "sg:province":"MI",
    "sg:tags":[
        "drugstore"
    ],
    "wof:name":"Highland Park Pharmacy",
    "wof:placetype":"venue"
},
  "geometry": {"coordinates":[-82.987426,42.500326],"type":"Point"}
}