{
  "type": "Feature",
  "properties": {
    "iso:country":"US",
    "sg:address":"5748 Royalwood Dr",
    "sg:city":"West Bloomfield",
    "sg:classifiers":[
        {
            "category":"Professional",
            "subcategory":"Management & Consulting",
            "type":"Services"
        }
    ],
    "sg:phone":"+1 248 661 0733",
    "sg:postcode":"48322",
    "sg:province":"MI",
    "sg:tags":[
        "technical"
    ],
    "wof:name":"JG Business Group",
    "wof:placetype":"venue"
},
  "geometry": {"coordinates":[-83.394961,42.546283],"type":"Point"}
}