{
  "type": "Feature",
  "properties": {
    "iso:country":"US",
    "sg:address":"3872 Rivard St",
    "sg:city":"Detroit",
    "sg:classifiers":[
        {
            "category":"Social Services",
            "subcategory":"Child Care",
            "type":"Services"
        }
    ],
    "sg:phone":"+1 313 832 2425",
    "sg:postcode":"48207",
    "sg:province":"MI",
    "sg:tags":[
        "day"
    ],
    "wof:name":"Nourishing Nest",
    "wof:placetype":"venue"
},
  "geometry": {"coordinates":[-83.04700099999999,42.353855],"type":"Point"}
}