{
  "type": "Feature",
  "properties": {
    "iso:country":"US",
    "sg:address":"4384 Arden Pl",
    "sg:city":"Royal Oak",
    "sg:classifiers":[
        {
            "category":"Building & Trades",
            "subcategory":"Construction",
            "type":"Services"
        }
    ],
    "sg:phone":"+1 248 644 5553",
    "sg:postcode":"48073",
    "sg:province":"MI",
    "sg:tags":[
        "house"
    ],
    "wof:name":"Neighborhood Construction",
    "wof:placetype":"venue"
},
  "geometry": {"coordinates":[-83.197716,42.528105],"type":"Point"}
}