{
  "type": "Feature",
  "properties": {
    "iso:country":"US",
    "sg:address":"115 S 5th St",
    "sg:city":"West Branch",
    "sg:classifiers":[
        {
            "category":"Banks & Credit Unions",
            "subcategory":"Bank",
            "type":"Services"
        }
    ],
    "sg:phone":"+1 989 345 1854",
    "sg:postcode":"48661",
    "sg:province":"MI",
    "wof:name":"First Collections",
    "wof:placetype":"venue"
},
  "geometry": {"coordinates":[-84.241338,44.27608],"type":"Point"}
}