{
  "type": "Feature",
  "properties": {
    "iso:country":"US",
    "sg:address":"1150 E 9 Mile Rd",
    "sg:city":"Ferndale",
    "sg:classifiers":[
        {
            "category":"Retail",
            "subcategory":"Veterinary Services",
            "type":"Services"
        }
    ],
    "sg:phone":"+1 248 414 5363",
    "sg:postcode":"48220",
    "sg:province":"MI",
    "sg:tags":[
        "veterinarian"
    ],
    "wof:name":"Little Friends of Ferndale",
    "wof:placetype":"venue"
},
  "geometry": {"coordinates":[-83.11914400000001,42.460961],"type":"Point"}
}