{
  "type": "Feature",
  "properties": {
    "iso:country":"US",
    "sg:address":"24709 Ross St",
    "sg:city":"Dearborn",
    "sg:classifiers":[
        {
            "category":"Retail",
            "subcategory":"Repair Shop",
            "type":"Services"
        }
    ],
    "sg:phone":"+1 313 274 1623",
    "sg:postcode":"48124",
    "sg:province":"MI",
    "wof:name":"T J H Inc",
    "wof:placetype":"venue"
},
  "geometry": {"coordinates":[-83.27965399999999,42.282354],"type":"Point"}
}