{
  "type": "Feature",
  "properties": {
    "iso:country":"US",
    "sg:address":"3965 Maple Dr",
    "sg:city":"Ypsilanti",
    "sg:classifiers":[
        {
            "category":"Professional",
            "subcategory":"Management & Consulting",
            "type":"Services"
        }
    ],
    "sg:phone":"+1 734 528 0859",
    "sg:postcode":"48197",
    "sg:province":"MI",
    "sg:tags":[
        "food"
    ],
    "wof:name":"Litening Quick Svc",
    "wof:placetype":"venue"
},
  "geometry": {"coordinates":[-83.66303600000001,42.233195],"type":"Point"}
}