{
  "type": "Feature",
  "properties": {
    "iso:country":"US",
    "sg:address":"7814 Galbraith Rd",
    "sg:city":"Cheboygan",
    "sg:classifiers":[
        {
            "category":"Freight",
            "type":"Transportation"
        }
    ],
    "sg:phone":"+1 231 625 9725",
    "sg:postcode":"49721",
    "sg:province":"MI",
    "sg:tags":[
        "special"
    ],
    "wof:name":"Norsmen Storage",
    "wof:placetype":"venue"
},
  "geometry": {"coordinates":[-84.454368,45.572208],"type":"Point"}
}