{
  "type": "Feature",
  "properties": {
    "iso:country":"US",
    "sg:address":"45621 Hayes Rd",
    "sg:city":"Shelby Township",
    "sg:classifiers":[
        {
            "category":"Personal",
            "subcategory":"Nail Salon",
            "type":"Services"
        }
    ],
    "sg:phone":"+1 586 532 8876",
    "sg:postcode":"48315",
    "sg:province":"MI",
    "wof:name":"Elegant Nail Spa",
    "wof:placetype":"venue"
},
  "geometry": {"coordinates":[-82.97363799999999,42.631306],"type":"Point"}
}