{
  "type": "Feature",
  "properties": {
    "iso:country":"US",
    "sg:address":"16316 S Main St",
    "sg:city":"Hermansville",
    "sg:classifiers":[
        {
            "category":"Professional",
            "type":"Services"
        }
    ],
    "sg:phone":"+1 906 498 2331",
    "sg:postcode":"49847",
    "sg:province":"MI",
    "sg:tags":[
        "establishment"
    ],
    "wof:name":"Wisconsin Lift Truck",
    "wof:placetype":"venue"
},
  "geometry": {"coordinates":[-87.602138,45.704898],"type":"Point"}
}