{
  "type": "Feature",
  "properties": {
    "iso:country":"US",
    "sg:address":"828 Westchester Rd",
    "sg:city":"Grosse Pointe",
    "sg:classifiers":[
        {
            "category":"Building & Trades",
            "subcategory":"Construction",
            "type":"Services"
        }
    ],
    "sg:phone":"+1 313 331 1250",
    "sg:postcode":"48230",
    "sg:province":"MI",
    "sg:tags":[
        "hanging",
        "contractor"
    ],
    "wof:name":"Desantis J A Painting LLC",
    "wof:placetype":"venue"
},
  "geometry": {"coordinates":[-82.931009,42.374083],"type":"Point"}
}