{
  "type": "Feature",
  "properties": {
    "iso:country":"US",
    "sg:address":"1506 Laughlin Dr NW",
    "sg:city":"Grand Rapids",
    "sg:classifiers":[
        {
            "category":"Professional",
            "subcategory":"Management & Consulting",
            "type":"Services"
        }
    ],
    "sg:phone":"+1 616 453 6738",
    "sg:postcode":"49504",
    "sg:province":"MI",
    "wof:name":"Samsoterra Marketing",
    "wof:placetype":"venue"
},
  "geometry": {"coordinates":[-85.74344000000001,42.99334],"type":"Point"}
}