{
  "type": "Feature",
  "properties": {
    "iso:country":"US",
    "sg:address":"14154 Farmington Rd",
    "sg:city":"Livonia",
    "sg:classifiers":[
        {
            "category":"Ice Cream",
            "type":"Food & Drink"
        }
    ],
    "sg:phone":"+1 734 421 3523",
    "sg:postcode":"48154",
    "sg:province":"MI",
    "sg:tags":[
        "frozen",
        "yogurt"
    ],
    "wof:name":"Hard Ice Cream Cafe",
    "wof:placetype":"venue"
},
  "geometry": {"coordinates":[-83.373001,42.386101],"type":"Point"}
}