{
  "type": "Feature",
  "properties": {
    "iso:country":"US",
    "sg:address":"544 Wa Wee Nork Dr",
    "sg:city":"Battle Creek",
    "sg:classifiers":[
        {
            "category":"Professional",
            "subcategory":"Management & Consulting",
            "type":"Services"
        }
    ],
    "sg:phone":"+1 269 966 6751",
    "sg:postcode":"49015",
    "sg:province":"MI",
    "sg:tags":[
        "repair",
        "monitoring"
    ],
    "wof:name":"Ram Industrial LLC",
    "wof:placetype":"venue"
},
  "geometry": {"coordinates":[-85.214915,42.296578],"type":"Point"}
}