{
  "type": "Feature",
  "properties": {
    "iso:country":"US",
    "sg:address":"1487 Cauchy Rd",
    "sg:city":"Mio",
    "sg:classifiers":[
        {
            "category":"Autos & Motor Vehicles",
            "subcategory":"Motorcycle Sales",
            "type":"Retail Goods"
        }
    ],
    "sg:phone":"+1 989 826 6035",
    "sg:postcode":"48647",
    "sg:province":"MI",
    "wof:name":"Toms Motor Shop & Racing Eqp",
    "wof:placetype":"venue"
},
  "geometry": {"coordinates":[-84.119426,44.637027],"type":"Point"}
}