{
  "type": "Feature",
  "properties": {
    "iso:country":"US",
    "sg:address":"7402 Shaw Rd",
    "sg:city":"Imlay City",
    "sg:classifiers":[
        {
            "category":"Wholesale",
            "subcategory":"Scrap",
            "type":"Manufacturing & Wholesale Goods"
        }
    ],
    "sg:phone":"+1 810 724 7700",
    "sg:postcode":"48444",
    "sg:province":"MI",
    "sg:tags":[
        "metal",
        "iron"
    ],
    "wof:name":"Jo Cor Investments",
    "wof:placetype":"venue"
},
  "geometry": {"coordinates":[-83.054704,43.102542],"type":"Point"}
}