{
  "type": "Feature",
  "properties": {
    "iso:country":"US",
    "sg:address":"105 Hall St",
    "sg:city":"Traverse City",
    "sg:classifiers":[
        {
            "category":"Health Services",
            "subcategory":"Hospital",
            "type":"Services"
        }
    ],
    "sg:phone":"+1 231 922 2060",
    "sg:postcode":"49684",
    "sg:province":"MI",
    "sg:tags":[
        "mental"
    ],
    "wof:name":"Traverse House",
    "wof:placetype":"venue"
},
  "geometry": {"coordinates":[-85.62703500000001,44.766174],"type":"Point"}
}