{
  "type": "Feature",
  "properties": {
    "iso:country":"US",
    "sg:address":"3951 Brubaker Rd",
    "sg:city":"Petoskey",
    "sg:classifiers":[
        {
            "category":"Education",
            "subcategory":"Vocational School",
            "type":"Public Place"
        }
    ],
    "sg:phone":"+1 231 439 9720",
    "sg:postcode":"49770",
    "sg:province":"MI",
    "sg:tags":[
        "instruction",
        "taxidermy"
    ],
    "wof:name":"Stick & String Taxidermy",
    "wof:placetype":"venue"
},
  "geometry": {"coordinates":[-84.892826,45.342044],"type":"Point"}
}