{
  "type": "Feature",
  "properties": {
    "iso:country":"US",
    "sg:address":"2900 E 8 Mile Rd",
    "sg:city":"Detroit",
    "sg:classifiers":[
        {
            "category":"Restaurant",
            "type":"Food & Drink"
        }
    ],
    "sg:phone":"+1 313 366 4300",
    "sg:postcode":"48234",
    "sg:province":"MI",
    "sg:tags":[
        "chinese",
        "buffet"
    ],
    "wof:name":"China Gourmet Buffet Express",
    "wof:placetype":"venue"
},
  "geometry": {"coordinates":[-83.074181,42.446993],"type":"Point"}
}