{
  "type": "Feature",
  "properties": {
    "iso:country":"US",
    "sg:address":"747 S Monroe St",
    "sg:city":"Monroe",
    "sg:classifiers":[
        {
            "category":"Shopping",
            "subcategory":"Florist",
            "type":"Retail Goods"
        }
    ],
    "sg:phone":"+1 734 242 6565",
    "sg:postcode":"48161",
    "sg:province":"MI",
    "sg:website":"www.monroeflorist.biz",
    "wof:name":"Monroe Florist",
    "wof:placetype":"venue"
},
  "geometry": {"coordinates":[-83.40376000000001,41.908978],"type":"Point"}
}