{
  "type": "Feature",
  "properties": {
    "iso:country":"US",
    "sg:address":"11400 W Herbison Rd",
    "sg:city":"Eagle",
    "sg:classifiers":[
        {
            "category":"Building & Trades",
            "subcategory":"Construction",
            "type":"Services"
        }
    ],
    "sg:phone":"+1 517 626 7018",
    "sg:postcode":"48822",
    "sg:province":"MI",
    "sg:tags":[
        "concrete",
        "contractor"
    ],
    "wof:name":"Kessler Concrete Construction",
    "wof:placetype":"venue"
},
  "geometry": {"coordinates":[-84.753719,42.828526],"type":"Point"}
}