{
  "type": "Feature",
  "properties": {
    "iso:country":"US",
    "sg:address":"631 W Adrian St",
    "sg:city":"Blissfield",
    "sg:phone":"+1 517 486 6020",
    "sg:postcode":"49228",
    "sg:province":"MI",
    "sg:website":"http://www.beckeyskountrykitchen.homestead.com",
    "wof:name":"Beckey's Kountry Kitchen",
    "wof:placetype":"venue"
},
  "geometry": {"coordinates":[-83.876375,41.836232],"type":"Point"}
}