{
  "type": "Feature",
  "properties": {
    "iso:country":"US",
    "sg:address":"9901 Chalmers St",
    "sg:city":"Detroit",
    "sg:classifiers":[
        {
            "category":"Personal",
            "subcategory":"Beauty Salon",
            "type":"Services"
        }
    ],
    "sg:phone":"+1 313 527 3880",
    "sg:postcode":"48213",
    "sg:province":"MI",
    "sg:tags":[
        "shop"
    ],
    "wof:name":"Just For You Unisex Buty Salon",
    "wof:placetype":"venue"
},
  "geometry": {"coordinates":[-82.969886,42.413112],"type":"Point"}
}