{
  "type": "Feature",
  "properties": {
    "iso:country":"US",
    "sg:address":"4375 Seymour Lake Rd",
    "sg:city":"Oxford",
    "sg:classifiers":[
        {
            "category":"Home & Garden",
            "subcategory":"Garden Supply",
            "type":"Retail Goods"
        }
    ],
    "sg:phone":"+1 248 628 2118",
    "sg:postcode":"48371",
    "sg:province":"MI",
    "sg:tags":[
        "sprinkler"
    ],
    "wof:name":"Falcon Lawn Sprinklers",
    "wof:placetype":"venue"
},
  "geometry": {"coordinates":[-83.36694799999999,42.808938],"type":"Point"}
}