{
  "type": "Feature",
  "properties": {
    "iso:country":"US",
    "sg:address":"977 W Houghton Lake Dr",
    "sg:city":"Prudenville",
    "sg:classifiers":[
        {
            "category":"Restaurant",
            "type":"Food & Drink"
        }
    ],
    "sg:phone":"+1 989 366 4882",
    "sg:postcode":"48651",
    "sg:province":"MI",
    "sg:tags":[
        "eating"
    ],
    "wof:name":"Lees Kitchen",
    "wof:placetype":"venue"
},
  "geometry": {"coordinates":[-84.655281,44.298523],"type":"Point"}
}