{
  "type": "Feature",
  "properties": {
    "iso:country":"US",
    "sg:address":"1841 Gover Pkwy",
    "sg:city":"Mt Pleasant",
    "sg:classifiers":[
        {
            "category":"Freight",
            "type":"Transportation"
        }
    ],
    "sg:phone":"+1 989 772 8879",
    "sg:postcode":"48858",
    "sg:province":"MI",
    "sg:tags":[
        "dry",
        "bulk",
        "trucking"
    ],
    "sg:website":"www.mlttruckinginc.com",
    "wof:name":"MLT Inc",
    "wof:placetype":"venue"
},
  "geometry": {"coordinates":[-84.74288300000001,43.584707],"type":"Point"}
}