{
  "type": "Feature",
  "properties": {
    "iso:country":"US",
    "sg:address":"8542 N Canton Center Rd",
    "sg:city":"Canton",
    "sg:classifiers":[
        {
            "category":"Health Services",
            "subcategory":"Doctor",
            "type":"Services"
        }
    ],
    "sg:phone":"+1 734 455 8310",
    "sg:postcode":"48187",
    "sg:province":"MI",
    "sg:tags":[
        "practice",
        "family"
    ],
    "wof:name":"Dua Prem P MD PC",
    "wof:placetype":"venue"
},
  "geometry": {"coordinates":[-83.488899,42.349201],"type":"Point"}
}