{
  "type": "Feature",
  "properties": {
    "iso:country":"US",
    "sg:address":"2101 E 12 Mile Rd",
    "sg:city":"Warren",
    "sg:classifiers":[
        {
            "category":"Building & Trades",
            "subcategory":"Plumbing",
            "type":"Services"
        }
    ],
    "sg:phone":"+1 586 755 7490",
    "sg:postcode":"48092",
    "sg:province":"MI",
    "wof:name":"Christion Brothers Plumbing & Service Cleaning",
    "wof:placetype":"venue"
},
  "geometry": {"coordinates":[-83.083603,42.505299],"type":"Point"}
}