{
  "type": "Feature",
  "properties": {
    "iso:country":"US",
    "sg:address":"3071 Grange Hall Rd",
    "sg:city":"Ortonville",
    "sg:classifiers":[
        {
            "category":"Real Estate",
            "subcategory":"Developer",
            "type":"Services"
        }
    ],
    "sg:phone":"+1 248 627 2955",
    "sg:postcode":"48462",
    "sg:province":"MI",
    "wof:name":"St Dennis Development Inc",
    "wof:placetype":"venue"
},
  "geometry": {"coordinates":[-83.479637,42.831959],"type":"Point"}
}