{
  "type": "Feature",
  "properties": {
    "iso:country":"US",
    "sg:address":"3343 E Clarkston Rd",
    "sg:city":"Oakland",
    "sg:classifiers":[
        {
            "category":"Retail",
            "subcategory":"Animal Services",
            "type":"Services"
        }
    ],
    "sg:phone":"+1 248 693 8544",
    "sg:postcode":"48363",
    "sg:province":"MI",
    "sg:tags":[
        "pet",
        "boarding",
        "sitting"
    ],
    "wof:name":"English Pet Sitters",
    "wof:placetype":"venue"
},
  "geometry": {"coordinates":[-83.205286,42.768308],"type":"Point"}
}