{
  "type": "Feature",
  "properties": {
    "iso:country":"US",
    "sg:address":"1300 E Beltline Ave SE",
    "sg:city":"Grand Rapids",
    "sg:classifiers":[
        {
            "category":"Organizations",
            "subcategory":"Religious Organization",
            "type":"Services"
        }
    ],
    "sg:phone":"+1 616 957 9117",
    "sg:postcode":"49506",
    "sg:province":"MI",
    "sg:website":"www.home.earthlink.net/~goinup",
    "wof:name":"Immanuel Reformed Church",
    "wof:placetype":"venue"
},
  "geometry": {"coordinates":[-85.585082,42.938289],"type":"Point"}
}