{
  "type": "Feature",
  "properties": {
    "iso:country":"US",
    "sg:address":"375 N Mc Clellan Ave",
    "sg:city":"Marquette",
    "sg:classifiers":[
        {
            "category":"Professional",
            "subcategory":"Lawyer & Legal Services",
            "type":"Services"
        }
    ],
    "sg:phone":"+1 906 228 9001",
    "sg:postcode":"49855",
    "sg:province":"MI",
    "sg:tags":[
        "attorney"
    ],
    "wof:name":"Finkbeiner & Burnham",
    "wof:placetype":"venue"
},
  "geometry": {"coordinates":[-87.419876,46.548676],"type":"Point"}
}