{
  "type": "Feature",
  "properties": {
    "iso:country":"US",
    "sg:address":"949 Enders Ave",
    "sg:city":"Benton Harbor",
    "sg:classifiers":[
        {
            "category":"Building & Trades",
            "subcategory":"Landscaping Services",
            "type":"Services"
        }
    ],
    "sg:phone":"+1 269 926 1723",
    "sg:postcode":"49022",
    "sg:province":"MI",
    "sg:tags":[
        "tree"
    ],
    "wof:name":"Clemons Tree Svc",
    "wof:placetype":"venue"
},
  "geometry": {"coordinates":[-86.448052,42.131649],"type":"Point"}
}