{
  "type": "Feature",
  "properties": {
    "iso:country":"US",
    "sg:address":"111 W 6th St",
    "sg:city":"Clare",
    "sg:classifiers":[
        {
            "category":"Health Services",
            "subcategory":"Doctor",
            "type":"Services"
        }
    ],
    "sg:phone":"+1 989 802 5020",
    "sg:postcode":"48617",
    "sg:province":"MI",
    "sg:tags":[
        "medical"
    ],
    "wof:name":"Ali Joseph MD Ob-Gyn",
    "wof:placetype":"venue"
},
  "geometry": {"coordinates":[-84.77027,43.820489],"type":"Point"}
}