{
  "type": "Feature",
  "properties": {
    "iso:country":"US",
    "sg:address":"45100 Sterritt St",
    "sg:city":"Utica",
    "sg:classifiers":[
        {
            "category":"Insurance",
            "subcategory":"Insurance Agent",
            "type":"Services"
        }
    ],
    "sg:phone":"+1 586 731 5556",
    "sg:postcode":"48317",
    "sg:province":"MI",
    "wof:name":"State Farm Insurance",
    "wof:placetype":"venue"
},
  "geometry": {"coordinates":[-83.017599,42.626922],"type":"Point"}
}