{
  "type": "Feature",
  "properties": {
    "iso:country":"US",
    "sg:address":"6740 Meadow Ave",
    "sg:city":"Warren",
    "sg:classifiers":[
        {
            "category":"Building & Trades",
            "subcategory":"Locksmith",
            "type":"Services"
        }
    ],
    "sg:phone":"+1 586 759 0358",
    "sg:postcode":"48091",
    "sg:province":"MI",
    "sg:tags":[
        "key"
    ],
    "wof:name":"All Around Towing",
    "wof:placetype":"venue"
},
  "geometry": {"coordinates":[-83.033964,42.453835],"type":"Point"}
}