{
  "type": "Feature",
  "properties": {
    "iso:country":"US",
    "sg:address":"6081 Lanake Ln",
    "sg:city":"Imlay City",
    "sg:classifiers":[
        {
            "category":"Health Services",
            "subcategory":"Clinic",
            "type":"Services"
        }
    ],
    "sg:phone":"+1 810 724 3708",
    "sg:postcode":"48444",
    "sg:province":"MI",
    "wof:name":"Ebert Medical P C",
    "wof:placetype":"venue"
},
  "geometry": {"coordinates":[-83.104163,43.035826],"type":"Point"}
}