{
  "type": "Feature",
  "properties": {
    "iso:country":"US",
    "sg:address":"15206 Hawley Rd",
    "sg:city":"Holly",
    "sg:classifiers":[
        {
            "category":"Professional",
            "subcategory":"Management & Consulting",
            "type":"Services"
        }
    ],
    "sg:phone":"+1 248 634 9555",
    "sg:postcode":"48442",
    "sg:province":"MI",
    "sg:tags":[
        "consultant",
        "business"
    ],
    "wof:name":"Trombley Roofing Consultants",
    "wof:placetype":"venue"
},
  "geometry": {"coordinates":[-83.549612,42.810057],"type":"Point"}
}