{
  "type": "Feature",
  "properties": {
    "iso:country":"US",
    "sg:address":"2348 Pajot Rd",
    "sg:city":"Kawkawlin",
    "sg:classifiers":[
        {
            "category":"Building & Trades",
            "subcategory":"Construction",
            "type":"Services"
        }
    ],
    "sg:phone":"+1 989 791 4344",
    "sg:postcode":"48631",
    "sg:province":"MI",
    "sg:tags":[
        "downspouts",
        "gutter"
    ],
    "wof:name":"M & M Seamless Gutters",
    "wof:placetype":"venue"
},
  "geometry": {"coordinates":[-84.04734000000001,43.670403],"type":"Point"}
}