{
  "type": "Feature",
  "properties": {
    "iso:country":"US",
    "sg:address":"1874 S Stine Rd",
    "sg:city":"Charlotte",
    "sg:classifiers":[
        {
            "category":"Retail",
            "subcategory":"Animal Services",
            "type":"Services"
        }
    ],
    "sg:phone":"+1 517 541 8039",
    "sg:postcode":"48813",
    "sg:province":"MI",
    "sg:tags":[
        "pet",
        "grooming",
        "washing"
    ],
    "wof:name":"Cassidy Country Pet Grooming",
    "wof:placetype":"venue"
},
  "geometry": {"coordinates":[-84.895099,42.542499],"type":"Point"}
}