{
  "type": "Feature",
  "properties": {
    "iso:country":"US",
    "sg:address":"1790 State Hwy 50",
    "sg:city":"Tecumseh",
    "sg:classifiers":[
        {
            "category":"Autos & Motor Vehicles",
            "subcategory":"Recreational Vehicle Sales",
            "type":"Retail Goods"
        }
    ],
    "sg:phone":"+1 517 423 1783",
    "sg:postcode":"49286",
    "sg:province":"MI",
    "wof:name":"Tecumseh Rv & Trailer Sales",
    "wof:placetype":"venue"
},
  "geometry": {"coordinates":[-84.003854,42.009507],"type":"Point"}
}