{
  "type": "Feature",
  "properties": {
    "iso:country":"US",
    "sg:address":"20723 Wyoming St Ste B",
    "sg:city":"Ferndale",
    "sg:classifiers":[
        {
            "category":"Personal",
            "subcategory":"Nail Salon",
            "type":"Services"
        }
    ],
    "sg:phone":"+1 248 399 5711",
    "sg:postcode":"48220",
    "sg:province":"MI",
    "wof:name":"90's Nails",
    "wof:placetype":"venue"
},
  "geometry": {"coordinates":[-83.16155000000001,42.446135],"type":"Point"}
}