{
  "type": "Feature",
  "properties": {
    "iso:country":"US",
    "sg:address":"2140 Lincoln Rd",
    "sg:city":"Allegan",
    "sg:classifiers":[
        {
            "category":"Farming",
            "subcategory":"Orchard",
            "type":"Manufacturing & Wholesale Goods"
        }
    ],
    "sg:phone":"+1 269 673 5964",
    "sg:postcode":"49010",
    "sg:province":"MI",
    "sg:tags":[
        "grove",
        "management"
    ],
    "wof:name":"Hillcrest Orchards",
    "wof:placetype":"venue"
},
  "geometry": {"coordinates":[-85.913887,42.572836],"type":"Point"}
}