{
  "type": "Feature",
  "properties": {
    "iso:country":"US",
    "sg:address":"1356 Electric Ave",
    "sg:city":"Lincoln Park",
    "sg:classifiers":[
        {
            "category":"Real Estate",
            "subcategory":"Real Estate Operator",
            "type":"Services"
        }
    ],
    "sg:phone":"+1 313 388 4660",
    "sg:postcode":"48146",
    "sg:province":"MI",
    "sg:tags":[
        "apartment"
    ],
    "wof:name":"Lincoln Park Housing Comm",
    "wof:placetype":"venue"
},
  "geometry": {"coordinates":[-83.170828,42.254941],"type":"Point"}
}