{
  "type": "Feature",
  "properties": {
    "iso:country":"US",
    "sg:address":"1910 N Villa Ct",
    "sg:city":"Essexville",
    "sg:classifiers":[
        {
            "category":"Real Estate",
            "subcategory":"Real Estate Operator",
            "type":"Services"
        }
    ],
    "sg:phone":"+1 989 892 9491",
    "sg:postcode":"48732",
    "sg:province":"MI",
    "sg:tags":[
        "building",
        "apartment",
        "manage"
    ],
    "wof:name":"Hampton House Villas",
    "wof:placetype":"venue"
},
  "geometry": {"coordinates":[-83.84692699999999,43.592295],"type":"Point"}
}