{
  "type": "Feature",
  "properties": {
    "iso:country":"US",
    "sg:address":"6882 Wintergreen Dr",
    "sg:city":"Fruitport",
    "sg:classifiers":[
        {
            "category":"Banks & Credit Unions",
            "subcategory":"Investment Brokerage",
            "type":"Services"
        }
    ],
    "sg:phone":"+1 231 865 1502",
    "sg:postcode":"49415",
    "sg:province":"MI",
    "sg:tags":[
        "advisory"
    ],
    "wof:name":"Bailey & Bailey Capital Brks",
    "wof:placetype":"venue"
},
  "geometry": {"coordinates":[-86.16994099999999,43.124935],"type":"Point"}
}