{
  "type": "Feature",
  "properties": {
    "iso:country":"US",
    "sg:address":"3055 E West Maple Rd",
    "sg:city":"Commerce Township",
    "sg:classifiers":[
        {
            "category":"Autos & Motor Vehicles",
            "subcategory":"Automobile Sales",
            "type":"Retail Goods"
        },
        {
            "category":"Retail",
            "subcategory":"Auto Rental",
            "type":"Services"
        },
        {
            "category":"Retail",
            "subcategory":"Auto Repair",
            "type":"Services"
        }
    ],
    "sg:phone":"+1 810 227 4429",
    "sg:postcode":"48390",
    "sg:province":"MI",
    "sg:tags":[
        "body",
        "shop",
        "car"
    ],
    "sg:website":"www.dwyerandsons.com",
    "wof:name":"Dwyer & Sons Volvo Subaru Inc",
    "wof:placetype":"venue"
},
  "geometry": {"coordinates":[-83.445297,42.542999],"type":"Point"}
}