{
  "type": "Feature",
  "properties": {
    "iso:country":"US",
    "sg:address":"6295 Martin Rd",
    "sg:city":"Muskegon",
    "sg:classifiers":[
        {
            "category":"Building & Trades",
            "subcategory":"Construction",
            "type":"Services"
        }
    ],
    "sg:phone":"+1 231 798 4154",
    "sg:postcode":"49444",
    "sg:province":"MI",
    "sg:tags":[
        "contractor"
    ],
    "wof:name":"J & J Concrete",
    "wof:placetype":"venue"
},
  "geometry": {"coordinates":[-86.24572000000001,43.132833],"type":"Point"}
}