{
  "type": "Feature",
  "properties": {
    "iso:country":"US",
    "sg:address":"22605 Heslip Dr",
    "sg:city":"Novi",
    "sg:classifiers":[
        {
            "category":"Manufacturing",
            "subcategory":"Tools & Machinery",
            "type":"Manufacturing & Wholesale Goods"
        }
    ],
    "sg:phone":"+1 248 349 7860",
    "sg:postcode":"48375",
    "sg:province":"MI",
    "sg:tags":[
        "building",
        "die",
        "construction",
        "maker",
        "equipment"
    ],
    "sg:website":"http://www.cavtool.com",
    "wof:name":"Cav Tool Company",
    "wof:placetype":"venue"
},
  "geometry": {"coordinates":[-83.46781,42.454754],"type":"Point"}
}