{
  "type": "Feature",
  "properties": {
    "iso:country":"US",
    "sg:address":"300 Michigan Ave",
    "sg:city":"Grayling",
    "sg:classifiers":[
        {
            "category":"Government",
            "subcategory":"Post Office",
            "type":"Public Place"
        }
    ],
    "sg:phone":"+1 989 000 1111",
    "sg:postcode":"49738",
    "sg:province":"MI",
    "wof:name":"US Post Office",
    "wof:placetype":"venue"
},
  "geometry": {"coordinates":[-84.71287599999999,44.662803],"type":"Point"}
}