{
  "type": "Feature",
  "properties": {
    "iso:country":"US",
    "sg:address":"15744 W Warren Ave",
    "sg:city":"Detroit",
    "sg:classifiers":[
        {
            "category":"Restaurant",
            "type":"Food & Drink"
        }
    ],
    "sg:phone":"+1 313 581 8605",
    "sg:postcode":"48228",
    "sg:province":"MI",
    "sg:tags":[
        "deli",
        "cafe"
    ],
    "wof:name":"Hawaiian Cafe",
    "wof:placetype":"venue"
},
  "geometry": {"coordinates":[-83.199519,42.3437],"type":"Point"}
}