{
  "type": "Feature",
  "properties": {
    "iso:country":"US",
    "sg:address":"1691 Columbia Rd",
    "sg:city":"Berkley",
    "sg:classifiers":[
        {
            "category":"Professional",
            "subcategory":"Management & Consulting",
            "type":"Services"
        }
    ],
    "sg:phone":"+1 248 586 1092",
    "sg:postcode":"48072",
    "sg:province":"MI",
    "sg:tags":[
        "business"
    ],
    "wof:name":"Lifestyles International",
    "wof:placetype":"venue"
},
  "geometry": {"coordinates":[-83.172995,42.490574],"type":"Point"}
}