{
  "type": "Feature",
  "properties": {
    "iso:country":"US",
    "sg:address":"14500 Laplaisance Rd",
    "sg:city":"Monroe",
    "sg:classifiers":[
        {
            "category":"Shopping",
            "subcategory":"Gifts & Souvenirs",
            "type":"Retail Goods"
        }
    ],
    "sg:phone":"+1 734 242 1993",
    "sg:postcode":"48161",
    "sg:province":"MI",
    "sg:tags":[
        "party",
        "supply"
    ],
    "sg:website":"www.partyamerica.com",
    "wof:name":"Paper Factory Outlet",
    "wof:placetype":"venue"
},
  "geometry": {"coordinates":[-83.394616,41.87885],"type":"Point"}
}