{
  "type": "Feature",
  "properties": {
    "iso:country":"US",
    "sg:address":"31045 Orchard Lake Rd",
    "sg:city":"Farmington Hills",
    "sg:classifiers":[
        {
            "category":"Shopping",
            "subcategory":"Clothing, Apparel, & Fashions",
            "type":"Retail Goods"
        }
    ],
    "sg:phone":"+1 248 626 9858",
    "sg:postcode":"48334",
    "sg:province":"MI",
    "sg:tags":[
        "men's",
        "clothing",
        "furnishing"
    ],
    "sg:website":"www.menswearhouse.com",
    "wof:name":"Men's Wearhouse",
    "wof:placetype":"venue"
},
  "geometry": {"coordinates":[-83.3601,42.5257],"type":"Point"}
}