{
  "type": "Feature",
  "properties": {
    "iso:country":"US",
    "sg:address":"10625 Belleville Rd",
    "sg:city":"Belleville",
    "sg:classifiers":[
        {
            "category":"Autos & Motor Vehicles",
            "subcategory":"Auto Supplies",
            "type":"Retail Goods"
        }
    ],
    "sg:phone":"+1 734 697 2424",
    "sg:postcode":"48111",
    "sg:province":"MI",
    "sg:tags":[
        "tire"
    ],
    "wof:name":"Advanced Auto Care & Tire Inc",
    "wof:placetype":"venue"
},
  "geometry": {"coordinates":[-83.48512100000001,42.21912],"type":"Point"}
}