{
  "type": "Feature",
  "properties": {
    "iso:country":"US",
    "sg:address":"34790 Ford Rd",
    "sg:city":"Westland",
    "sg:classifiers":[
        {
            "category":"Cinema",
            "subcategory":"Movie Rental",
            "type":"Entertainment"
        }
    ],
    "sg:phone":"+1 734 326 3415",
    "sg:postcode":"48185",
    "sg:province":"MI",
    "sg:tags":[
        "game",
        "video"
    ],
    "sg:website":"www.gamestop.com",
    "wof:name":"Gamestop Store 2250",
    "wof:placetype":"venue"
},
  "geometry": {"coordinates":[-83.38280899999999,42.32469],"type":"Point"}
}