{
  "type": "Feature",
  "properties": {
    "iso:country":"US",
    "sg:address":"7575 Jericho Ave NE",
    "sg:city":"Rockford",
    "sg:classifiers":[
        {
            "category":"Parking",
            "type":"Transportation"
        },
        {
            "category":"Wholesale",
            "subcategory":"Construction Materials",
            "type":"Manufacturing & Wholesale Goods"
        }
    ],
    "sg:phone":"+1 616 866 2165",
    "sg:postcode":"49341",
    "sg:province":"MI",
    "sg:tags":[
        "pet",
        "automobile",
        "fence"
    ],
    "wof:name":"Pet Alert Hidden Dog Fence",
    "wof:placetype":"venue"
},
  "geometry": {"coordinates":[-85.56571599999999,43.100153],"type":"Point"}
}