{
  "type": "Feature",
  "properties": {
    "iso:country":"US",
    "sg:address":"22300 W McNichols Rd",
    "sg:city":"Detroit",
    "sg:classifiers":[
        {
            "category":"Autos & Motor Vehicles",
            "subcategory":"Auto Supplies",
            "type":"Retail Goods"
        },
        {
            "category":"Retail",
            "subcategory":"Auto Repair",
            "type":"Services"
        }
    ],
    "sg:phone":"+1 313 531 7670",
    "sg:postcode":"48219",
    "sg:province":"MI",
    "sg:tags":[
        "tire"
    ],
    "wof:name":"Center Tire Inc",
    "wof:placetype":"venue"
},
  "geometry": {"coordinates":[-83.260696,42.414799],"type":"Point"}
}