{
  "type": "Feature",
  "properties": {
    "iso:country":"US",
    "sg:address":"810 E Huron River Dr",
    "sg:city":"Belleville",
    "sg:classifiers":[
        {
            "category":"Education",
            "subcategory":"School",
            "type":"Public Place"
        }
    ],
    "sg:phone":"+1 734 697 7455",
    "sg:postcode":"48111",
    "sg:province":"MI",
    "sg:tags":[
        "child",
        "day",
        "care"
    ],
    "wof:name":"Bethany Day Care Center",
    "wof:placetype":"venue"
},
  "geometry": {"coordinates":[-83.47293500000001,42.209916],"type":"Point"}
}