{
  "type": "Feature",
  "properties": {
    "iso:country":"US",
    "sg:address":"2207 Traversefield Dr",
    "sg:city":"Traverse City",
    "sg:classifiers":[
        {
            "category":"Utilities",
            "subcategory":"Natural Gas",
            "type":"Services"
        }
    ],
    "sg:phone":"+1 231 922 8554",
    "sg:postcode":"49686",
    "sg:province":"MI",
    "sg:tags":[
        "heat",
        "company",
        "supplying"
    ],
    "wof:name":"Tommark Inc",
    "wof:placetype":"venue"
},
  "geometry": {"coordinates":[-85.58736,44.717129],"type":"Point"}
}