{
  "type": "Feature",
  "properties": {
    "iso:country":"US",
    "sg:address":"10750 Royston Rd",
    "sg:city":"Grand Ledge",
    "sg:classifiers":[
        {
            "category":"Professional",
            "subcategory":"Business Services",
            "type":"Services"
        }
    ],
    "sg:phone":"+1 517 627 8827",
    "sg:postcode":"48837",
    "sg:province":"MI",
    "wof:name":"Dewey Devern Charter",
    "wof:placetype":"venue"
},
  "geometry": {"coordinates":[-84.719876,42.71547],"type":"Point"}
}