{
  "type": "Feature",
  "properties": {
    "iso:country":"US",
    "sg:address":"2107 Charlton Ave",
    "sg:city":"Ann Arbor",
    "sg:classifiers":[
        {
            "category":"Personal",
            "subcategory":"Beauty Salon",
            "type":"Services"
        }
    ],
    "sg:phone":"+1 734 995 5268",
    "sg:postcode":"48103",
    "sg:province":"MI",
    "sg:tags":[
        "shop",
        "landscape"
    ],
    "wof:name":"Clean Cut Lawnservices",
    "wof:placetype":"venue"
},
  "geometry": {"coordinates":[-83.776858,42.278939],"type":"Point"}
}