{
  "type": "Feature",
  "properties": {
    "iso:country":"US",
    "sg:address":"3210 Jewell Rd",
    "sg:city":"Howell",
    "sg:classifiers":[
        {
            "category":"Organizations",
            "subcategory":"Community Association",
            "type":"Services"
        }
    ],
    "sg:phone":"+1 517 546 4556",
    "sg:postcode":"48843",
    "sg:province":"MI",
    "sg:tags":[
        "club"
    ],
    "wof:name":"Howell Gun Club",
    "wof:placetype":"venue"
},
  "geometry": {"coordinates":[-83.96951,42.57493],"type":"Point"}
}