{
  "type": "Feature",
  "properties": {
    "iso:country":"US",
    "sg:address":"15 Forest Pl",
    "sg:city":"Plymouth",
    "sg:classifiers":[
        {
            "category":"Restaurant",
            "type":"Food & Drink"
        }
    ],
    "sg:phone":"+1 734 455 3310",
    "sg:postcode":"48170",
    "sg:province":"MI",
    "sg:tags":[
        "traditional",
        "american"
    ],
    "wof:name":"Cozy Cafe",
    "wof:placetype":"venue"
},
  "geometry": {"coordinates":[-83.488899,42.3675],"type":"Point"}
}