{
  "type": "Feature",
  "properties": {
    "iso:country":"US",
    "sg:address":"328 E Lansing Rd",
    "sg:city":"East Lansing",
    "sg:classifiers":[
        {
            "category":"Health Services",
            "subcategory":"Doctor",
            "type":"Services"
        }
    ],
    "sg:phone":"+1 517 432 2280",
    "sg:postcode":"48857",
    "sg:province":"MI",
    "sg:tags":[
        "physician",
        "surgeon"
    ],
    "wof:name":"Richard Griffin MD",
    "wof:placetype":"venue"
},
  "geometry": {"coordinates":[-84.15770000000001,42.851987],"type":"Point"}
}