{
  "type": "Feature",
  "properties": {
    "iso:country":"US",
    "sg:address":"4665 Dobie Rd",
    "sg:city":"Okemos",
    "sg:classifiers":[
        {
            "category":"Real Estate",
            "subcategory":"Real Estate Operator",
            "type":"Services"
        }
    ],
    "sg:phone":"+1 517 349 0560",
    "sg:postcode":"48864",
    "sg:province":"MI",
    "sg:tags":[
        "building",
        "apartment"
    ],
    "wof:name":"Scottsdale Investment Co",
    "wof:placetype":"venue"
},
  "geometry": {"coordinates":[-84.41041,42.715972],"type":"Point"}
}