{
  "type": "Feature",
  "properties": {
    "iso:country":"US",
    "sg:address":"2442 Orchard Lake Rd",
    "sg:city":"Sylvan Lake",
    "sg:classifiers":[
        {
            "category":"Restaurant",
            "type":"Food & Drink"
        }
    ],
    "sg:phone":"+1 248 683 5458",
    "sg:postcode":"48320",
    "sg:province":"MI",
    "wof:name":"The Lodge At Orchard Lake",
    "wof:placetype":"venue"
},
  "geometry": {"coordinates":[-83.33289600000001,42.609864],"type":"Point"}
}