{
  "type": "Feature",
  "properties": {
    "iso:country":"US",
    "sg:address":"1724 Maiden Ln",
    "sg:city":"St Joseph",
    "sg:classifiers":[
        {
            "category":"Real Estate",
            "subcategory":"Real Estate Agent",
            "type":"Services"
        }
    ],
    "sg:phone":"+1 269 429 6323",
    "sg:postcode":"49085",
    "sg:province":"MI",
    "sg:tags":[
        "cooperative"
    ],
    "wof:name":"H A Food Co Op",
    "wof:placetype":"venue"
},
  "geometry": {"coordinates":[-86.495667,42.050563],"type":"Point"}
}