{
  "type": "Feature",
  "properties": {
    "iso:country":"US",
    "sg:address":"36843 S Gratiot Ave",
    "sg:city":"Clinton Twp",
    "sg:classifiers":[
        {
            "category":"Autos & Motor Vehicles",
            "subcategory":"Fuel & Gas Station",
            "type":"Retail Goods"
        }
    ],
    "sg:phone":"+1 586 792 2343",
    "sg:postcode":"48035",
    "sg:province":"MI",
    "sg:tags":[
        "oil"
    ],
    "wof:name":"BP",
    "wof:placetype":"venue"
},
  "geometry": {"coordinates":[-82.892368,42.568694],"type":"Point"}
}