{
  "type": "Feature",
  "properties": {
    "iso:country":"US",
    "sg:address":"2041 W Grand River Ave",
    "sg:city":"Okemos",
    "sg:classifiers":[
        {
            "category":"Home & Garden",
            "subcategory":"Home Furnishings",
            "type":"Retail Goods"
        },
        {
            "category":"Home & Garden",
            "subcategory":"Furniture",
            "type":"Retail Goods"
        }
    ],
    "sg:phone":"+1 517 349 2555",
    "sg:postcode":"48864",
    "sg:province":"MI",
    "sg:tags":[
        "burning",
        "stove",
        "equipment",
        "wood",
        "fireplace",
        "patio"
    ],
    "wof:name":"Heat n Sweep Inc",
    "wof:placetype":"venue"
},
  "geometry": {"coordinates":[-84.424103,42.721405],"type":"Point"}
}