{
  "type": "Feature",
  "properties": {
    "iso:country":"US",
    "sg:address":"14326 Woburn Dr",
    "sg:city":"Traverse City",
    "sg:classifiers":[
        {
            "category":"Professional",
            "subcategory":"Business Services",
            "type":"Services"
        }
    ],
    "sg:phone":"+1 231 223 4207",
    "sg:postcode":"49686",
    "sg:province":"MI",
    "wof:name":"Jireh Enterprises",
    "wof:placetype":"venue"
},
  "geometry": {"coordinates":[-85.518433,44.895758],"type":"Point"}
}