{
  "type": "Feature",
  "properties": {
    "iso:country":"US",
    "sg:address":"7930 Meisner Rd",
    "sg:city":"Casco",
    "sg:classifiers":[
        {
            "category":"Recreation",
            "type":"Entertainment"
        }
    ],
    "sg:phone":"+1 810 765 4966",
    "sg:postcode":"48064",
    "sg:province":"MI",
    "sg:tags":[
        "club",
        "membership",
        "halls",
        "ballroom",
        "auditorium"
    ],
    "wof:name":"Perch Point Conservation Club",
    "wof:placetype":"venue"
},
  "geometry": {"coordinates":[-82.631297,42.753838],"type":"Point"}
}