{
  "type": "Feature",
  "properties": {
    "iso:country":"US",
    "sg:address":"27727 Michigan Ave",
    "sg:city":"Inkster",
    "sg:classifiers":[
        {
            "category":"Real Estate",
            "subcategory":"Real Estate Agent",
            "type":"Services"
        }
    ],
    "sg:phone":"+1 313 565 2554",
    "sg:postcode":"48141",
    "sg:province":"MI",
    "wof:name":"Home Buyers & Sellers Network",
    "wof:placetype":"venue"
},
  "geometry": {"coordinates":[-83.31361,42.293125],"type":"Point"}
}