{
  "type": "Feature",
  "properties": {
    "iso:country":"US",
    "sg:address":"39327 Garfield Rd",
    "sg:city":"Clinton Township",
    "sg:classifiers":[
        {
            "category":"Arena",
            "subcategory":"Sports Club",
            "type":"Entertainment"
        }
    ],
    "sg:phone":"+1 586 263 9449",
    "sg:postcode":"48038",
    "sg:province":"MI",
    "sg:tags":[
        "martial art"
    ],
    "wof:name":"Naama Karate Schools",
    "wof:placetype":"venue"
},
  "geometry": {"coordinates":[-82.95210299999999,42.587299],"type":"Point"}
}