{
  "type": "Feature",
  "properties": {
    "iso:country":"US",
    "sg:address":"800 Soule Blvd",
    "sg:city":"Ann Arbor",
    "sg:classifiers":[
        {
            "category":"Education",
            "subcategory":"School",
            "type":"Public Place"
        }
    ],
    "sg:phone":"+1 734 994 1934",
    "sg:postcode":"48103",
    "sg:province":"MI",
    "wof:name":"Eberwhite Elementary School",
    "wof:placetype":"venue"
},
  "geometry": {"coordinates":[-83.764431,42.273446],"type":"Point"}
}