{
  "type": "Feature",
  "properties": {
    "iso:country":"US",
    "sg:address":"5728 N Telegraph Rd",
    "sg:city":"Dearborn Heights",
    "sg:classifiers":[
        {
            "category":"Personal",
            "subcategory":"Nail Salon",
            "type":"Services"
        }
    ],
    "sg:phone":"+1 313 565 6183",
    "sg:postcode":"48127",
    "sg:province":"MI",
    "sg:website":"www.hollywoodnailsalon.com",
    "wof:name":"Hollywood Nails",
    "wof:placetype":"venue"
},
  "geometry": {"coordinates":[-83.2724,42.329899],"type":"Point"}
}