{
  "type": "Feature",
  "properties": {
    "iso:country":"US",
    "sg:address":"2801 Timberwyck Trail Dr",
    "sg:city":"Troy",
    "sg:classifiers":[
        {
            "category":"Arts & Performance",
            "subcategory":"Theater",
            "type":"Entertainment"
        }
    ],
    "sg:phone":"+1 248 647 1306",
    "sg:postcode":"48098",
    "sg:province":"MI",
    "sg:tags":[
        "group"
    ],
    "wof:name":"Mb2",
    "wof:placetype":"venue"
},
  "geometry": {"coordinates":[-83.202209,42.583747],"type":"Point"}
}