{
  "type": "Feature",
  "properties": {
    "iso:country":"US",
    "sg:address":"1953 Union St",
    "sg:city":"Benton Harbor",
    "sg:classifiers":[
        {
            "category":"Social Services",
            "type":"Services"
        }
    ],
    "sg:phone":"+1 269 925 0177",
    "sg:postcode":"49022",
    "sg:province":"MI",
    "sg:tags":[
        "organization",
        "welfare"
    ],
    "wof:name":"Dimes Entertainment",
    "wof:placetype":"venue"
},
  "geometry": {"coordinates":[-86.44135799999999,42.083034],"type":"Point"}
}