{
  "type": "Feature",
  "properties": {
    "iso:country":"US",
    "sg:address":"4245 Norton Rd",
    "sg:city":"Howell",
    "sg:classifiers":[
        {
            "category":"Building & Trades",
            "subcategory":"Cleaning & Sanitation",
            "type":"Services"
        }
    ],
    "sg:phone":"+1 517 546 6510",
    "sg:postcode":"48843",
    "sg:province":"MI",
    "sg:tags":[
        "butler",
        "maid"
    ],
    "wof:name":"Jiffy Maids",
    "wof:placetype":"venue"
},
  "geometry": {"coordinates":[-83.998704,42.592473],"type":"Point"}
}