{
  "type": "Feature",
  "properties": {
    "iso:country":"US",
    "sg:address":"2319 Gratiot Blvd",
    "sg:city":"Marysville",
    "sg:classifiers":[
        {
            "category":"Restaurant",
            "type":"Food & Drink"
        }
    ],
    "sg:phone":"+1 810 364 3663",
    "sg:postcode":"48040",
    "sg:province":"MI",
    "wof:name":"Poncho's Mexican American",
    "wof:placetype":"venue"
},
  "geometry": {"coordinates":[-82.486377,42.915425],"type":"Point"}
}