{
  "type": "Feature",
  "properties": {
    "iso:country":"US",
    "sg:address":"18 1st St",
    "sg:city":"Mount Clemens",
    "sg:classifiers":[
        {
            "category":"Professional",
            "subcategory":"Lawyer & Legal Services",
            "type":"Services"
        }
    ],
    "sg:phone":"+1 586 463 7060",
    "sg:postcode":"48043",
    "sg:province":"MI",
    "wof:name":"Ronald J Gricius P C",
    "wof:placetype":"venue"
},
  "geometry": {"coordinates":[-82.875298,42.595798],"type":"Point"}
}