{
  "type": "Feature",
  "properties": {
    "iso:country":"US",
    "sg:address":"2676 Lakeshore Dr",
    "sg:city":"Niles",
    "sg:classifiers":[
        {
            "category":"Autos & Motor Vehicles",
            "subcategory":"Boat Sales",
            "type":"Retail Goods"
        }
    ],
    "sg:phone":"+1 269 684 0712",
    "sg:postcode":"49120",
    "sg:province":"MI",
    "sg:tags":[
        "engine",
        "repair",
        "marine"
    ],
    "wof:name":"K & G Marine Inc",
    "wof:placetype":"venue"
},
  "geometry": {"coordinates":[-86.180173,41.840064],"type":"Point"}
}