{
  "type": "Feature",
  "properties": {
    "iso:country":"US",
    "sg:address":"6051 Constitution Blvd",
    "sg:city":"Portage",
    "sg:classifiers":[
        {
            "category":"Sports & Exercise",
            "subcategory":"Gym",
            "type":"Entertainment"
        }
    ],
    "sg:phone":"+1 269 329 9000",
    "sg:postcode":"49024",
    "sg:province":"MI",
    "sg:tags":[
        "fitness",
        "physical",
        "facility"
    ],
    "wof:name":"Powerhouse Gym of Kalamazoo",
    "wof:placetype":"venue"
},
  "geometry": {"coordinates":[-85.601348,42.227645],"type":"Point"}
}