{
  "type": "Feature",
  "properties": {
    "iso:country":"US",
    "sg:address":"911 Michigan Ave",
    "sg:city":"Baldwin",
    "sg:classifiers":[
        {
            "category":"Government",
            "subcategory":"Office",
            "type":"Public Place"
        }
    ],
    "sg:phone":"+1 231 745 2722",
    "sg:postcode":"49304",
    "sg:province":"MI",
    "wof:name":"Building Dept",
    "wof:placetype":"venue"
},
  "geometry": {"coordinates":[-85.851651,43.897307],"type":"Point"}
}