{
  "type": "Feature",
  "properties": {
    "iso:country":"US",
    "sg:address":"17356 W 12 Mile Rd Ste 202",
    "sg:city":"Southfield",
    "sg:classifiers":[
        {
            "category":"Professional",
            "subcategory":"Lawyer & Legal Services",
            "type":"Services"
        }
    ],
    "sg:phone":"+1 248 569 5467",
    "sg:postcode":"48076",
    "sg:province":"MI",
    "wof:name":"Law Offices of Folake Akande",
    "wof:placetype":"venue"
},
  "geometry": {"coordinates":[-83.218225,42.50275],"type":"Point"}
}