{
  "type": "Feature",
  "properties": {
    "iso:country":"US",
    "sg:address":"1107 W Cedar Ave",
    "sg:city":"Gladwin",
    "sg:classifiers":[
        {
            "category":"Restaurant",
            "type":"Food & Drink"
        }
    ],
    "sg:phone":"+1 989 426 6662",
    "sg:postcode":"48624",
    "sg:province":"MI",
    "wof:name":"Mc Donald's",
    "wof:placetype":"venue"
},
  "geometry": {"coordinates":[-84.500293,43.980768],"type":"Point"}
}