{
  "type": "Feature",
  "properties": {
    "iso:country":"US",
    "sg:address":"3699 S Airport Rd W",
    "sg:city":"Traverse City",
    "sg:classifiers":[
        {
            "category":"Health Services",
            "subcategory":"Doctor",
            "type":"Services"
        }
    ],
    "sg:phone":"+1 231 941 2201",
    "sg:postcode":"49686",
    "sg:province":"MI",
    "wof:name":"Phillip Carl Yancho DDS",
    "wof:placetype":"venue"
},
  "geometry": {"coordinates":[-85.652963,44.722857],"type":"Point"}
}