{
  "type": "Feature",
  "properties": {
    "iso:country":"US",
    "sg:address":"5421 Beckley Rd",
    "sg:city":"Battle Creek",
    "sg:classifiers":[
        {
            "category":"Restaurant",
            "type":"Food & Drink"
        }
    ],
    "sg:menulink":"http://www.allmenus.com/mi/battle-creek/42710-bob-evans/menu/",
    "sg:phone":"+1 269 979 4144",
    "sg:postcode":"49015",
    "sg:province":"MI",
    "sg:tags":[
        "american"
    ],
    "wof:name":"Bob Evans",
    "wof:placetype":"venue"
},
  "geometry": {"coordinates":[-85.18974900000001,42.261066],"type":"Point"}
}