{
  "type": "Feature",
  "properties": {
    "iso:country":"US",
    "sg:address":"155 E Commerce St",
    "sg:city":"Milford",
    "sg:classifiers":[
        {
            "category":"Personal",
            "subcategory":"Beauty Salon",
            "type":"Services"
        }
    ],
    "sg:phone":"+1 248 684 5680",
    "sg:postcode":"48381",
    "sg:province":"MI",
    "wof:name":"Celebrity Styles",
    "wof:placetype":"venue"
},
  "geometry": {"coordinates":[-83.599659,42.591752],"type":"Point"}
}