{
  "type": "Feature",
  "properties": {
    "iso:country":"US",
    "sg:address":"28730 Harper Ave",
    "sg:city":"Saint Clair Shores",
    "sg:classifiers":[
        {
            "category":"Health Services",
            "subcategory":"Doctor",
            "type":"Services"
        }
    ],
    "sg:phone":"+1 586 279 0033",
    "sg:postcode":"48081",
    "sg:province":"MI",
    "sg:tags":[
        "practice",
        "family"
    ],
    "wof:name":"Shores Primary Care",
    "wof:placetype":"venue"
},
  "geometry": {"coordinates":[-82.897903,42.504799],"type":"Point"}
}