{
  "type": "Feature",
  "properties": {
    "iso:country":"US",
    "sg:address":"14020 Telegraph Rd",
    "sg:city":"Flat Rock",
    "sg:classifiers":[
        {
            "category":"Retail",
            "subcategory":"Auto Repair",
            "type":"Services"
        }
    ],
    "sg:phone":"+1 734 782 0575",
    "sg:postcode":"48134",
    "sg:province":"MI",
    "wof:name":"A and M Transmissions Inc",
    "wof:placetype":"venue"
},
  "geometry": {"coordinates":[-83.307602,42.075802],"type":"Point"}
}