{
  "type": "Feature",
  "properties": {
    "iso:country":"US",
    "sg:address":"920 Water St",
    "sg:city":"Hancock",
    "sg:classifiers":[
        {
            "category":"Organizations",
            "subcategory":"Non-profit Organization",
            "type":"Services"
        }
    ],
    "sg:phone":"+1 906 482 4438",
    "sg:postcode":"49930",
    "sg:province":"MI",
    "sg:tags":[
        "social"
    ],
    "wof:name":"Omega House",
    "wof:placetype":"venue"
},
  "geometry": {"coordinates":[-88.595178,47.124886],"type":"Point"}
}