{
  "type": "Feature",
  "properties": {
    "iso:country":"US",
    "sg:address":"2700 E Lansing Dr",
    "sg:city":"East Lansing",
    "sg:classifiers":[
        {
            "category":"Retail",
            "subcategory":"Auto Repair",
            "type":"Services"
        }
    ],
    "sg:phone":"+1 517 337 3100",
    "sg:postcode":"48823",
    "sg:province":"MI",
    "sg:tags":[
        "automotive",
        "center",
        "lubrication"
    ],
    "wof:name":"Jiffy Lube",
    "wof:placetype":"venue"
},
  "geometry": {"coordinates":[-84.45058299999999,42.749595],"type":"Point"}
}