{
  "type": "Feature",
  "properties": {
    "iso:country":"US",
    "sg:address":"507 E Shiawassee St",
    "sg:city":"Lansing",
    "sg:classifiers":[
        {
            "category":"Shopping",
            "subcategory":"Bicycles & Sporting Goods",
            "type":"Retail Goods"
        }
    ],
    "sg:phone":"+1 517 482 8585",
    "sg:postcode":"48912",
    "sg:province":"MI",
    "sg:tags":[
        "repair",
        "sport",
        "mfg"
    ],
    "wof:name":"Riverfront Cycle Inc",
    "wof:placetype":"venue"
},
  "geometry": {"coordinates":[-84.543618,42.737299],"type":"Point"}
}