{
  "type": "Feature",
  "properties": {
    "iso:country":"US",
    "sg:address":"3401 Pine Mountain Rd",
    "sg:city":"Iron Mountain",
    "sg:classifiers":[
        {
            "category":"Sports & Exercise",
            "subcategory":"Golf",
            "type":"Entertainment"
        }
    ],
    "sg:phone":"+1 906 774 0003",
    "sg:postcode":"49801",
    "sg:province":"MI",
    "sg:tags":[
        "course"
    ],
    "wof:name":"Eagle Mountain Golf Course",
    "wof:placetype":"venue"
},
  "geometry": {"coordinates":[-88.09273,45.843018],"type":"Point"}
}