{
  "type": "Feature",
  "properties": {
    "iso:country":"US",
    "sg:address":"1241 Water Cliff Dr",
    "sg:city":"Bloomfield Hills",
    "sg:classifiers":[
        {
            "category":"Professional",
            "subcategory":"Business Services",
            "type":"Services"
        }
    ],
    "sg:phone":"+1 248 258 5853",
    "sg:postcode":"48302",
    "sg:province":"MI",
    "sg:tags":[
        "notary",
        "public"
    ],
    "wof:name":"Becker Frederique",
    "wof:placetype":"venue"
},
  "geometry": {"coordinates":[-83.288408,42.5763],"type":"Point"}
}