{
  "type": "Feature",
  "properties": {
    "iso:country":"US",
    "sg:address":"120 W 11 Mile Rd",
    "sg:city":"Royal Oak",
    "sg:classifiers":[
        {
            "category":"Shopping",
            "subcategory":"Musical Instruments",
            "type":"Retail Goods"
        }
    ],
    "sg:phone":"+1 248 548 9393",
    "sg:postcode":"48067",
    "sg:province":"MI",
    "sg:tags":[
        "repair"
    ],
    "wof:name":"Flute Specialists Inc",
    "wof:placetype":"venue"
},
  "geometry": {"coordinates":[-83.14530499999999,42.489873],"type":"Point"}
}