{
  "type": "Feature",
  "properties": {
    "iso:country":"US",
    "sg:address":"612 S Park St",
    "sg:city":"Kalamazoo",
    "sg:classifiers":[
        {
            "category":"Professional",
            "subcategory":"Management & Consulting",
            "type":"Services"
        }
    ],
    "sg:phone":"+1 269 345 9433",
    "sg:postcode":"49007",
    "sg:province":"MI",
    "sg:tags":[
        "construction"
    ],
    "wof:name":"Hamann Diekema Construction",
    "wof:placetype":"venue"
},
  "geometry": {"coordinates":[-85.587294,42.28524],"type":"Point"}
}