{
  "type": "Feature",
  "properties": {
    "iso:country":"US",
    "sg:address":"338 W Allegan St",
    "sg:city":"Otsego",
    "sg:classifiers":[
        {
            "category":"Health Services",
            "subcategory":"Dentist",
            "type":"Services"
        }
    ],
    "sg:phone":"+1 269 694 2074",
    "sg:postcode":"49078",
    "sg:province":"MI",
    "wof:name":"Merda, Michael Dds",
    "wof:placetype":"venue"
},
  "geometry": {"coordinates":[-85.691429,42.459462],"type":"Point"}
}