{
  "type": "Feature",
  "properties": {
    "iso:country":"US",
    "sg:address":"66421 Sherman Mill Rd",
    "sg:city":"Sturgis",
    "sg:classifiers":[
        {
            "category":"Farming",
            "subcategory":"Farm",
            "type":"Manufacturing & Wholesale Goods"
        }
    ],
    "sg:phone":"+1 269 651 3044",
    "sg:postcode":"49091",
    "sg:province":"MI",
    "sg:tags":[
        "crop",
        "general"
    ],
    "wof:name":"Deer Creek Farms Inc",
    "wof:placetype":"venue"
},
  "geometry": {"coordinates":[-85.477086,41.833486],"type":"Point"}
}