{
  "type": "Feature",
  "properties": {
    "iso:country":"US",
    "sg:address":"6663 Bloomfield Ln",
    "sg:city":"West Bloomfield",
    "sg:classifiers":[
        {
            "category":"Utilities",
            "subcategory":"Mobile Phone",
            "type":"Services"
        }
    ],
    "sg:phone":"+1 248 855 3800",
    "sg:postcode":"48322",
    "sg:province":"MI",
    "sg:tags":[
        "telephone",
        "cellular"
    ],
    "wof:name":"Nextel World Cellular",
    "wof:placetype":"venue"
},
  "geometry": {"coordinates":[-83.33263599999999,42.541904],"type":"Point"}
}