{
  "type": "Feature",
  "properties": {
    "iso:country":"US",
    "sg:address":"110 Park St",
    "sg:city":"Albion",
    "sg:classifiers":[
        {
            "category":"Insurance",
            "subcategory":"Insurance Agent",
            "type":"Services"
        }
    ],
    "sg:phone":"+1 517 629 2976",
    "sg:postcode":"49224",
    "sg:province":"MI",
    "sg:tags":[
        "life",
        "carrier"
    ],
    "wof:name":"Dan M Siler Agency",
    "wof:placetype":"venue"
},
  "geometry": {"coordinates":[-84.741005,42.24537],"type":"Point"}
}