{
  "type": "Feature",
  "properties": {
    "iso:country":"US",
    "sg:address":"8058 Flintlock Rd",
    "sg:city":"Mount Morris",
    "sg:classifiers":[
        {
            "category":"Building & Trades",
            "subcategory":"Construction",
            "type":"Services"
        }
    ],
    "sg:phone":"+1 810 686 5982",
    "sg:postcode":"48458",
    "sg:province":"MI",
    "sg:tags":[
        "carpentry",
        "contractor"
    ],
    "wof:name":"R & L Carpenter Contractors",
    "wof:placetype":"venue"
},
  "geometry": {"coordinates":[-83.784583,43.123057],"type":"Point"}
}