{
  "type": "Feature",
  "properties": {
    "iso:country":"US",
    "sg:address":"115 5th St",
    "sg:city":"Jackson",
    "sg:classifiers":[
        {
            "category":"Restaurant",
            "type":"Food & Drink"
        }
    ],
    "sg:phone":"+1 517 764 1512",
    "sg:postcode":"49203",
    "sg:province":"MI",
    "wof:name":"Spanglers Center Diner-Fax",
    "wof:placetype":"venue"
},
  "geometry": {"coordinates":[-84.394561,42.193249],"type":"Point"}
}