{
  "type": "Feature",
  "properties": {
    "iso:country":"US",
    "sg:address":"2144 S State St",
    "sg:city":"Ann Arbor",
    "sg:classifiers":[
        {
            "category":"Real Estate",
            "subcategory":"Real Estate Agent",
            "type":"Services"
        }
    ],
    "sg:phone":"+1 734 995 9400",
    "sg:postcode":"48104",
    "sg:province":"MI",
    "wof:name":"Keller Williams Realtors",
    "wof:placetype":"venue"
},
  "geometry": {"coordinates":[-83.73977600000001,42.255595],"type":"Point"}
}