{
  "type": "Feature",
  "properties": {
    "iso:country":"US",
    "sg:address":"1970 Pipestone Rd",
    "sg:city":"Benton Harbor",
    "sg:classifiers":[
        {
            "category":"Home & Garden",
            "subcategory":"Household Appliances",
            "type":"Retail Goods"
        }
    ],
    "sg:phone":"+1 269 934 3112",
    "sg:postcode":"49022",
    "sg:province":"MI",
    "sg:tags":[
        "machine",
        "sewing"
    ],
    "wof:name":"Erica's Viking White Sewing",
    "wof:placetype":"venue"
},
  "geometry": {"coordinates":[-86.4196,42.085341],"type":"Point"}
}