{
  "type": "Feature",
  "properties": {
    "iso:country":"US",
    "sg:address":"817 W Montcalm St",
    "sg:city":"Greenville",
    "sg:classifiers":[
        {
            "category":"Building & Trades",
            "subcategory":"Construction",
            "type":"Services"
        }
    ],
    "sg:phone":"+1 616 225 8629",
    "sg:postcode":"48838",
    "sg:province":"MI",
    "sg:tags":[
        "contractor"
    ],
    "wof:name":"Rogers Masonry",
    "wof:placetype":"venue"
},
  "geometry": {"coordinates":[-85.26602099999999,43.183171],"type":"Point"}
}