{
  "type": "Feature",
  "properties": {
    "iso:country":"US",
    "sg:address":"10 N 3rd St",
    "sg:city":"Niles",
    "sg:classifiers":[
        {
            "category":"Banks & Credit Unions",
            "subcategory":"Investment Brokerage",
            "type":"Services"
        }
    ],
    "sg:phone":"+1 269 684 7605",
    "sg:postcode":"49120",
    "sg:province":"MI",
    "sg:tags":[
        "consultant",
        "planning",
        "financial"
    ],
    "wof:name":"Mutual Service Corp",
    "wof:placetype":"venue"
},
  "geometry": {"coordinates":[-86.256215,41.828862],"type":"Point"}
}