{
  "type": "Feature",
  "properties": {
    "iso:country":"US",
    "sg:address":"150 Burniah Ln",
    "sg:city":"Lake Orion",
    "sg:classifiers":[
        {
            "category":"Real Estate",
            "subcategory":"Real Estate Agent",
            "type":"Services"
        }
    ],
    "sg:phone":"+1 248 693 5668",
    "sg:postcode":"48362",
    "sg:province":"MI",
    "sg:tags":[
        "appraiser"
    ],
    "wof:name":"Appraise This",
    "wof:placetype":"venue"
},
  "geometry": {"coordinates":[-83.28398900000001,42.785451],"type":"Point"}
}