{
  "type": "Feature",
  "properties": {
    "iso:country":"US",
    "sg:address":"13685 S West-Bay Shore Dr",
    "sg:city":"Traverse City",
    "sg:classifiers":[
        {
            "category":"Social Services",
            "type":"Services"
        }
    ],
    "sg:phone":"+1 231 933 4661",
    "sg:postcode":"49684",
    "sg:province":"MI",
    "sg:tags":[
        "counselor",
        "marriage",
        "family"
    ],
    "wof:name":"Heeren Family Therapy",
    "wof:placetype":"venue"
},
  "geometry": {"coordinates":[-85.640139,44.778839],"type":"Point"}
}