{
  "type": "Feature",
  "properties": {
    "iso:country":"US",
    "sg:address":"25 Dickinson St",
    "sg:city":"Mount Clemens",
    "sg:classifiers":[
        {
            "category":"Shopping",
            "subcategory":"Used Merchandise",
            "type":"Retail Goods"
        }
    ],
    "sg:phone":"+1 586 469 7879",
    "sg:postcode":"48043",
    "sg:province":"MI",
    "wof:name":"Kimmel Antiques",
    "wof:placetype":"venue"
},
  "geometry": {"coordinates":[-82.874109,42.597226],"type":"Point"}
}