{
  "type": "Feature",
  "properties": {
    "iso:country":"US",
    "sg:address":"4094 Norman Rd",
    "sg:city":"Arcadia",
    "sg:classifiers":[
        {
            "category":"Building & Trades",
            "subcategory":"Construction",
            "type":"Services"
        }
    ],
    "sg:phone":"+1 231 889 3570",
    "sg:postcode":"49613",
    "sg:province":"MI",
    "sg:tags":[
        "concrete",
        "contractor"
    ],
    "wof:name":"Shoreline Erosion Control",
    "wof:placetype":"venue"
},
  "geometry": {"coordinates":[-86.225318,44.50955],"type":"Point"}
}