{
  "type": "Feature",
  "properties": {
    "iso:country":"US",
    "sg:address":"594 Arrowhead Ave SE",
    "sg:city":"Grand Rapids",
    "sg:classifiers":[
        {
            "category":"Professional",
            "type":"Services"
        }
    ],
    "sg:phone":"+1 616 956 5089",
    "sg:postcode":"49546",
    "sg:province":"MI",
    "sg:tags":[
        "establishment"
    ],
    "wof:name":"Spnp AAA",
    "wof:placetype":"venue"
},
  "geometry": {"coordinates":[-85.558549,42.954672],"type":"Point"}
}