{
  "type": "Feature",
  "properties": {
    "iso:country":"US",
    "sg:address":"2312 Greenfield Rd",
    "sg:city":"Berkley",
    "sg:classifiers":[
        {
            "category":"Place Of Worship",
            "subcategory":"Church",
            "type":"Public Place"
        }
    ],
    "sg:phone":"+1 248 544 1800",
    "sg:postcode":"48072",
    "sg:province":"MI",
    "sg:tags":[
        "churches-presbyterian"
    ],
    "wof:name":"Greenfield Presbyterian Church",
    "wof:placetype":"venue"
},
  "geometry": {"coordinates":[-83.202634,42.493321],"type":"Point"}
}