{
  "type": "Feature",
  "properties": {
    "iso:country":"US",
    "sg:address":"2100 S Saginaw Rd",
    "sg:city":"Midland",
    "sg:classifiers":[
        {
            "category":"Retail",
            "subcategory":"Auto Repair",
            "type":"Services"
        }
    ],
    "sg:phone":"+1 989 835 5030",
    "sg:postcode":"48640",
    "sg:province":"MI",
    "sg:tags":[
        "brake"
    ],
    "sg:website":"http://www.tuffy.com",
    "wof:name":"Tuffy Auto Service Centers",
    "wof:placetype":"venue"
},
  "geometry": {"coordinates":[-84.21154799999999,43.612251],"type":"Point"}
}