{
  "type": "Feature",
  "properties": {
    "iso:country":"US",
    "sg:address":"4055 17 Mile Rd",
    "sg:city":"Sterling Heights",
    "sg:classifiers":[
        {
            "category":"Restaurant",
            "type":"Food & Drink"
        }
    ],
    "sg:menulink":"http://www.allmenus.com/mi/sterling-heights/131091-kabob-arbeel/menu/",
    "sg:phone":"+1 586 979 8500",
    "sg:postcode":"48310",
    "sg:province":"MI",
    "sg:tags":[
        "middle",
        "eastern"
    ],
    "wof:name":"Kabob Arbeel",
    "wof:placetype":"venue"
},
  "geometry": {"coordinates":[-83.069603,42.579202],"type":"Point"}
}