{
  "type": "Feature",
  "properties": {
    "iso:country":"US",
    "sg:address":"2075 E Gorman Rd",
    "sg:city":"Adrian",
    "sg:classifiers":[
        {
            "category":"Building & Trades",
            "subcategory":"Landscaping Services",
            "type":"Services"
        }
    ],
    "sg:phone":"+1 517 436 3042",
    "sg:postcode":"49221",
    "sg:province":"MI",
    "sg:tags":[
        "landscape"
    ],
    "wof:name":"Rods Landscaping Service",
    "wof:placetype":"venue"
},
  "geometry": {"coordinates":[-84.004164,41.82449],"type":"Point"}
}