{
  "type": "Feature",
  "properties": {
    "iso:country":"US",
    "sg:address":"5633 Lamone Dr",
    "sg:city":"Lansing",
    "sg:classifiers":[
        {
            "category":"Wholesale",
            "subcategory":"Hardware",
            "type":"Manufacturing & Wholesale Goods"
        }
    ],
    "sg:phone":"+1 517 882 2427",
    "sg:postcode":"48911",
    "sg:province":"MI",
    "sg:tags":[
        "parts",
        "refrigerating"
    ],
    "wof:name":"Carrier Great Lakes",
    "wof:placetype":"venue"
},
  "geometry": {"coordinates":[-84.53497299999999,42.675554],"type":"Point"}
}