{
  "type": "Feature",
  "properties": {
    "iso:country":"US",
    "sg:address":"13444 15 Mile Rd",
    "sg:city":"Sterling Heights",
    "sg:classifiers":[
        {
            "category":"Shopping",
            "subcategory":"Bridal",
            "type":"Retail Goods"
        }
    ],
    "sg:phone":"+1 586 795 8505",
    "sg:postcode":"48312",
    "sg:province":"MI",
    "wof:name":"Blaga's Bridal",
    "wof:placetype":"venue"
},
  "geometry": {"coordinates":[-82.990303,42.552101],"type":"Point"}
}