{
  "type": "Feature",
  "properties": {
    "iso:country":"US",
    "sg:address":"272 E Main St",
    "sg:city":"Ionia",
    "sg:classifiers":[
        {
            "category":"Insurance",
            "subcategory":"Insurance Agent",
            "type":"Services"
        }
    ],
    "sg:phone":"+1 616 527 1777",
    "sg:postcode":"48846",
    "sg:province":"MI",
    "wof:name":"Farm Bureau Insurance",
    "wof:placetype":"venue"
},
  "geometry": {"coordinates":[-85.05717300000001,42.983325],"type":"Point"}
}