{
  "type": "Feature",
  "properties": {
    "iso:country":"US",
    "sg:address":"14289 E Lime Island Rd",
    "sg:city":"Goetzville",
    "sg:classifiers":[
        {
            "category":"Travel",
            "subcategory":"Hotels & Motels",
            "type":"Entertainment"
        }
    ],
    "sg:phone":"+1 906 297 6355",
    "sg:postcode":"49736",
    "sg:province":"MI",
    "sg:tags":[
        "resort",
        "operation"
    ],
    "wof:name":"Jack's Landing",
    "wof:placetype":"venue"
},
  "geometry": {"coordinates":[-84.06720199999999,46.086321],"type":"Point"}
}