{
  "type": "Feature",
  "properties": {
    "iso:country":"US",
    "sg:address":"3110 S Martin Luther King Jr Blvd",
    "sg:city":"Lansing",
    "sg:classifiers":[
        {
            "category":"Restaurant",
            "type":"Food & Drink"
        }
    ],
    "sg:menulink":"http://www.allmenus.com/mi/lansing/163053-rallys/menu/",
    "sg:phone":"+1 517 887 9380",
    "sg:postcode":"48910",
    "sg:province":"MI",
    "sg:tags":[
        "sandwich",
        "dog",
        "burger",
        "hot",
        "wrap",
        "american"
    ],
    "wof:name":"Rally's",
    "wof:placetype":"venue"
},
  "geometry": {"coordinates":[-84.56738199999999,42.70139],"type":"Point"}
}