{
  "type": "Feature",
  "properties": {
    "iso:country":"US",
    "sg:address":"1705 Hill St",
    "sg:city":"Ann Arbor",
    "sg:classifiers":[
        {
            "category":"Organizations",
            "subcategory":"Community Association",
            "type":"Services"
        }
    ],
    "sg:phone":"+1 734 761 6442",
    "sg:postcode":"48104",
    "sg:province":"MI",
    "wof:name":"Delta CHI",
    "wof:placetype":"venue"
},
  "geometry": {"coordinates":[-83.726992,42.272827],"type":"Point"}
}