{
  "type": "Feature",
  "properties": {
    "iso:country":"US",
    "sg:address":"835 Bogie Lake Rd",
    "sg:city":"White Lake",
    "sg:classifiers":[
        {
            "category":"Building & Trades",
            "subcategory":"Construction",
            "type":"Services"
        }
    ],
    "sg:phone":"+1 248 887 5762",
    "sg:postcode":"48383",
    "sg:province":"MI",
    "sg:tags":[
        "floor",
        "laying",
        "contractor"
    ],
    "wof:name":"Image & Design Hardwood Floors",
    "wof:placetype":"venue"
},
  "geometry": {"coordinates":[-83.523871,42.634801],"type":"Point"}
}