{
  "type": "Feature",
  "properties": {
    "iso:country":"US",
    "sg:address":"330 W Main St",
    "sg:city":"Benton Harbor",
    "sg:classifiers":[
        {
            "category":"Shopping",
            "subcategory":"Clothing, Apparel, & Fashions",
            "type":"Retail Goods"
        }
    ],
    "sg:phone":"+1 269 927 3139",
    "sg:postcode":"49022",
    "sg:province":"MI",
    "sg:tags":[
        "uniform",
        "supply"
    ],
    "sg:website":"www.actiongarmentrental.com",
    "wof:name":"ACTION Garment Rental Inc",
    "wof:placetype":"venue"
},
  "geometry": {"coordinates":[-86.463559,42.114036],"type":"Point"}
}