{
  "type": "Feature",
  "properties": {
    "iso:country":"US",
    "sg:address":"9389 N Haggerty Rd",
    "sg:city":"Plymouth",
    "sg:classifiers":[
        {
            "category":"Health Services",
            "subcategory":"Doctor",
            "type":"Services"
        }
    ],
    "sg:phone":"+1 734 459 0326",
    "sg:postcode":"48170",
    "sg:province":"MI",
    "sg:tags":[
        "surgeon",
        "oral"
    ],
    "wof:name":"Baxter William W Ms Jr DDS",
    "wof:placetype":"venue"
},
  "geometry": {"coordinates":[-83.44499999999999,42.3577],"type":"Point"}
}