{
  "type": "Feature",
  "properties": {
    "iso:country":"US",
    "sg:address":"3251 Henry St",
    "sg:city":"Muskegon",
    "sg:classifiers":[
        {
            "category":"Banks & Credit Unions",
            "subcategory":"Investment Brokerage",
            "type":"Services"
        }
    ],
    "sg:phone":"+1 231 739 7127",
    "sg:postcode":"49441",
    "sg:province":"MI",
    "sg:tags":[
        "consultant",
        "planning",
        "financial"
    ],
    "wof:name":"Waddell & Reed Inc",
    "wof:placetype":"venue"
},
  "geometry": {"coordinates":[-86.263459,43.19302],"type":"Point"}
}