{
  "type": "Feature",
  "properties": {
    "iso:country":"US",
    "sg:address":"15212 Edmore Dr",
    "sg:city":"Detroit",
    "sg:classifiers":[
        {
            "category":"Banks & Credit Unions",
            "subcategory":"Financial Services",
            "type":"Services"
        }
    ],
    "sg:phone":"+1 313 839 4864",
    "sg:postcode":"48205",
    "sg:province":"MI",
    "sg:tags":[
        "investor"
    ],
    "wof:name":"1st Star Investments LLC",
    "wof:placetype":"venue"
},
  "geometry": {"coordinates":[-82.963655,42.447165],"type":"Point"}
}