{
  "type": "Feature",
  "properties": {
    "iso:country":"US",
    "sg:address":"413 E Saint Clair St",
    "sg:city":"Romeo",
    "sg:classifiers":[
        {
            "category":"Manufacturing",
            "subcategory":"Rubber & Plastics",
            "type":"Manufacturing & Wholesale Goods"
        }
    ],
    "sg:phone":"+1 586 336 9933",
    "sg:postcode":"48065",
    "sg:province":"MI",
    "wof:name":"Exceptional Mold & Engineering",
    "wof:placetype":"venue"
},
  "geometry": {"coordinates":[-83.00460099999999,42.80287],"type":"Point"}
}