{
  "type": "Feature",
  "properties": {
    "iso:country":"US",
    "sg:address":"4807 E M-55",
    "sg:city":"Prescott",
    "sg:classifiers":[
        {
            "category":"Retail",
            "subcategory":"Auto Repair",
            "type":"Services"
        }
    ],
    "sg:phone":"+1 989 873 3542",
    "sg:postcode":"48756",
    "sg:province":"MI",
    "sg:tags":[
        "body",
        "automobile",
        "painting"
    ],
    "wof:name":"Brown's Collision",
    "wof:placetype":"venue"
},
  "geometry": {"coordinates":[-83.933772,44.277166],"type":"Point"}
}