{
  "type": "Feature",
  "properties": {
    "iso:country":"US",
    "sg:address":"1961 Pine Ridge Dr",
    "sg:city":"Jenison",
    "sg:classifiers":[
        {
            "category":"Building & Trades",
            "subcategory":"Construction",
            "type":"Services"
        }
    ],
    "sg:phone":"+1 616 662 3821",
    "sg:postcode":"49428",
    "sg:province":"MI",
    "sg:tags":[
        "general",
        "contractor"
    ],
    "wof:name":"Superior Curb Cutting Equip",
    "wof:placetype":"venue"
},
  "geometry": {"coordinates":[-85.83086299999999,42.891779],"type":"Point"}
}