{
  "type": "Feature",
  "properties": {
    "iso:country":"US",
    "sg:address":"3381 Lyle Rd",
    "sg:city":"Beaverton",
    "sg:classifiers":[
        {
            "category":"Wholesale",
            "subcategory":"Construction Materials",
            "type":"Manufacturing & Wholesale Goods"
        }
    ],
    "sg:phone":"+1 989 435 9927",
    "sg:postcode":"48612",
    "sg:province":"MI",
    "sg:tags":[
        "pallet",
        "skid"
    ],
    "wof:name":"D & M Pallet",
    "wof:placetype":"venue"
},
  "geometry": {"coordinates":[-84.49847800000001,43.829013],"type":"Point"}
}