{
  "type": "Feature",
  "properties": {
    "iso:country":"US",
    "sg:address":"27925 Golf Pointe Blvd",
    "sg:city":"Farmington Hills",
    "sg:classifiers":[
        {
            "category":"Restaurant",
            "type":"Food & Drink"
        }
    ],
    "sg:phone":"+1 248 489 9400",
    "sg:postcode":"48331",
    "sg:province":"MI",
    "sg:website":"www. lovingspoonful.com",
    "wof:name":"Loving Spoonful",
    "wof:placetype":"venue"
},
  "geometry": {"coordinates":[-83.423698,42.498299],"type":"Point"}
}