{
  "type": "Feature",
  "properties": {
    "iso:country":"US",
    "sg:address":"42211 Garfield Rd Ste 311",
    "sg:city":"Clinton Township",
    "sg:classifiers":[
        {
            "category":"Building & Trades",
            "subcategory":"Landscaping Services",
            "type":"Services"
        },
        {
            "category":"Wholesale",
            "subcategory":"Scrap",
            "type":"Manufacturing & Wholesale Goods"
        }
    ],
    "sg:phone":"+1 586 630 0665",
    "sg:postcode":"48038",
    "sg:province":"MI",
    "sg:tags":[
        "junk",
        "hauling",
        "gardener",
        "removal"
    ],
    "sg:website":"www.jbrdisposal.com",
    "wof:name":"JBR Disposal",
    "wof:placetype":"venue"
},
  "geometry": {"coordinates":[-82.95273299999999,42.60693],"type":"Point"}
}