{
  "type": "Feature",
  "properties": {
    "iso:country":"US",
    "sg:address":"8214 Crestview Dr",
    "sg:city":"Cadillac",
    "sg:classifiers":[
        {
            "category":"Building & Trades",
            "subcategory":"Construction",
            "type":"Services"
        }
    ],
    "sg:phone":"+1 231 775 0618",
    "sg:postcode":"49601",
    "sg:province":"MI",
    "sg:tags":[
        "contractor"
    ],
    "wof:name":"Al Thomsen Builder",
    "wof:placetype":"venue"
},
  "geometry": {"coordinates":[-85.41303600000001,44.212852],"type":"Point"}
}