{
  "type": "Feature",
  "properties": {
    "iso:country":"US",
    "sg:address":"32215 Michigan Ave",
    "sg:city":"Wayne",
    "sg:classifiers":[
        {
            "category":"Autos & Motor Vehicles",
            "subcategory":"Fuel & Gas Station",
            "type":"Retail Goods"
        }
    ],
    "sg:phone":"+1 734 721 5920",
    "sg:postcode":"48184",
    "sg:province":"MI",
    "sg:tags":[
        "station"
    ],
    "wof:name":"Hillyards Mobile Service",
    "wof:placetype":"venue"
},
  "geometry": {"coordinates":[-83.35614,42.284112],"type":"Point"}
}