{
  "type": "Feature",
  "properties": {
    "iso:country":"US",
    "sg:address":"45527 Heatherwoode Dr",
    "sg:city":"Macomb",
    "sg:classifiers":[
        {
            "category":"Building & Trades",
            "subcategory":"Construction",
            "type":"Services"
        }
    ],
    "sg:phone":"+1 586 263 1644",
    "sg:postcode":"48044",
    "sg:province":"MI",
    "sg:tags":[
        "hanging",
        "contractor"
    ],
    "wof:name":"K&K Painting",
    "wof:placetype":"venue"
},
  "geometry": {"coordinates":[-82.94485899999999,42.631853],"type":"Point"}
}