{
  "type": "Feature",
  "properties": {
    "iso:country":"US",
    "sg:address":"8460 S State Rd",
    "sg:city":"Portland",
    "sg:classifiers":[
        {
            "category":"Professional",
            "subcategory":"Business Services",
            "type":"Services"
        }
    ],
    "sg:phone":"+1 616 374 8818",
    "sg:postcode":"48875",
    "sg:province":"MI",
    "wof:name":"Auto Salvage Auction Inc",
    "wof:placetype":"venue"
},
  "geometry": {"coordinates":[-85.075045,42.863556],"type":"Point"}
}