{
  "type": "Feature",
  "properties": {
    "iso:country":"US",
    "sg:address":"45284 Engel Dr",
    "sg:city":"Utica",
    "sg:classifiers":[
        {
            "category":"Personal",
            "subcategory":"Beauty Salon",
            "type":"Services"
        }
    ],
    "sg:phone":"+1 586 997 4068",
    "sg:postcode":"48317",
    "sg:province":"MI",
    "sg:tags":[
        "treatment",
        "skin"
    ],
    "wof:name":"Sharon Turner",
    "wof:placetype":"venue"
},
  "geometry": {"coordinates":[-83.026742,42.628472],"type":"Point"}
}