{
  "type": "Feature",
  "properties": {
    "iso:country":"US",
    "sg:address":"100 Outer Dr Clear Lake",
    "sg:city":"Fremont",
    "sg:classifiers":[
        {
            "category":"Food & Beverages",
            "subcategory":"Groceries & Convenience Stores",
            "type":"Retail Goods"
        }
    ],
    "sg:phone":"+1 260 495 9765",
    "sg:postcode":"46737",
    "sg:province":"MI",
    "sg:tags":[
        "grocer"
    ],
    "wof:name":"Clear Lake General Store",
    "wof:placetype":"venue"
},
  "geometry": {"coordinates":[-84.82306,41.730137],"type":"Point"}
}