{
  "type": "Feature",
  "properties": {
    "iso:country":"US",
    "sg:address":"7100 Stadium Dr",
    "sg:city":"Kalamazoo",
    "sg:classifiers":[
        {
            "category":"Home & Garden",
            "subcategory":"Furniture",
            "type":"Retail Goods"
        }
    ],
    "sg:phone":"+1 269 375 5900",
    "sg:postcode":"49009",
    "sg:province":"MI",
    "sg:website":"www.wellingripleyandlabs.com",
    "wof:name":"Welling Ripley & Labs",
    "wof:placetype":"venue"
},
  "geometry": {"coordinates":[-85.688845,42.256889],"type":"Point"}
}