{
  "type": "Feature",
  "properties": {
    "iso:country":"US",
    "sg:address":"400 N Main St",
    "sg:city":"Onsted",
    "sg:classifiers":[
        {
            "category":"Shopping",
            "subcategory":"Pharmacy",
            "type":"Retail Goods"
        }
    ],
    "sg:phone":"+1 517 467 7225",
    "sg:postcode":"49265",
    "sg:province":"MI",
    "wof:name":"Freedom Apothecary Too",
    "wof:placetype":"venue"
},
  "geometry": {"coordinates":[-84.189727,42.011718],"type":"Point"}
}