{
  "type": "Feature",
  "properties": {
    "iso:country":"US",
    "sg:address":"366 E Lansing Rd",
    "sg:city":"East Lansing",
    "sg:classifiers":[
        {
            "category":"Education",
            "subcategory":"Special Training",
            "type":"Public Place"
        }
    ],
    "sg:phone":"+1 517 353 1288",
    "sg:postcode":"48857",
    "sg:province":"MI",
    "wof:name":"Nsu Community Music School",
    "wof:placetype":"venue"
},
  "geometry": {"coordinates":[-84.15721000000001,42.852275],"type":"Point"}
}