{
  "type": "Feature",
  "properties": {
    "iso:country":"US",
    "sg:address":"201 S Bennett St",
    "sg:city":"Rose City",
    "sg:classifiers":[
        {
            "category":"Personal",
            "subcategory":"Beauty Salon",
            "type":"Services"
        }
    ],
    "sg:phone":"+1 989 685 3636",
    "sg:postcode":"48654",
    "sg:province":"MI",
    "wof:name":"Shear Perfection",
    "wof:placetype":"venue"
},
  "geometry": {"coordinates":[-84.11622199999999,44.420586],"type":"Point"}
}