{
  "type": "Feature",
  "properties": {
    "iso:country":"US",
    "sg:address":"1608 S Gray Rd",
    "sg:city":"West Branch",
    "sg:classifiers":[
        {
            "category":"Insurance",
            "subcategory":"Insurance Agent",
            "type":"Services"
        }
    ],
    "sg:phone":"+1 989 345 0424",
    "sg:postcode":"48661",
    "sg:province":"MI",
    "wof:name":"Crecine Agency Inc",
    "wof:placetype":"venue"
},
  "geometry": {"coordinates":[-84.266937,44.291225],"type":"Point"}
}