{
  "type": "Feature",
  "properties": {
    "iso:country":"US",
    "sg:address":"1661 Haynor Rd",
    "sg:city":"Ionia",
    "sg:classifiers":[
        {
            "category":"Home & Garden",
            "subcategory":"Building Materials",
            "type":"Retail Goods"
        }
    ],
    "sg:phone":"+1 616 527 8759",
    "sg:postcode":"48846",
    "sg:province":"MI",
    "sg:tags":[
        "door"
    ],
    "wof:name":"Door Systems",
    "wof:placetype":"venue"
},
  "geometry": {"coordinates":[-85.092837,43.010735],"type":"Point"}
}