{
  "type": "Feature",
  "properties": {
    "iso:country":"US",
    "sg:address":"2367 Acorn Ct",
    "sg:city":"West Bloomfield",
    "sg:classifiers":[
        {
            "category":"Professional",
            "subcategory":"Lawyer & Legal Services",
            "type":"Services"
        }
    ],
    "sg:phone":"+1 248 972 0997",
    "sg:postcode":"48324",
    "sg:province":"MI",
    "sg:tags":[
        "attorney"
    ],
    "wof:name":"Crane Law Group",
    "wof:placetype":"venue"
},
  "geometry": {"coordinates":[-83.32555499999999,42.600002],"type":"Point"}
}