{
  "type": "Feature",
  "properties": {
    "iso:country":"US",
    "sg:address":"534 Constitution St",
    "sg:city":"Canton",
    "sg:classifiers":[
        {
            "category":"Building & Trades",
            "subcategory":"Construction",
            "type":"Services"
        }
    ],
    "sg:phone":"+1 248 388 8472",
    "sg:postcode":"48188",
    "sg:province":"MI",
    "sg:tags":[
        "altering",
        "remodeling",
        "contractor"
    ],
    "sg:website":"www.relevantyellow.com/Construct...",
    "wof:name":"Mozart Renovations",
    "wof:placetype":"venue"
},
  "geometry": {"coordinates":[-83.53609899999999,42.301967],"type":"Point"}
}