{
  "type": "Feature",
  "properties": {
    "iso:country":"US",
    "sg:address":"978 Jackson St",
    "sg:city":"Kalamazoo",
    "sg:classifiers":[
        {
            "category":"Autos & Motor Vehicles",
            "subcategory":"Fuel & Gas Station",
            "type":"Retail Goods"
        }
    ],
    "sg:phone":"+1 517 623 6651",
    "sg:postcode":"49001",
    "sg:province":"MI",
    "sg:tags":[
        "oil"
    ],
    "wof:name":"Dansville Gas & More",
    "wof:placetype":"venue"
},
  "geometry": {"coordinates":[-85.568887,42.282902],"type":"Point"}
}