{
  "type": "Feature",
  "properties": {
    "iso:country":"US",
    "sg:address":"639 Puritan Ave",
    "sg:city":"Birmingham",
    "sg:classifiers":[
        {
            "category":"Real Estate",
            "subcategory":"Developer",
            "type":"Services"
        }
    ],
    "sg:phone":"+1 248 357 1000",
    "sg:postcode":"48009",
    "sg:province":"MI",
    "sg:tags":[
        "land"
    ],
    "wof:name":"Brown Street Associates",
    "wof:placetype":"venue"
},
  "geometry": {"coordinates":[-83.2298,42.551707],"type":"Point"}
}