{
  "type": "Feature",
  "properties": {
    "iso:country":"US",
    "sg:address":"360 Maple St",
    "sg:city":"Sault Ste Marie",
    "sg:classifiers":[
        {
            "category":"Education",
            "subcategory":"School",
            "type":"Public Place"
        }
    ],
    "sg:phone":"+1 906 635 6141",
    "sg:postcode":"49783",
    "sg:province":"MI",
    "wof:name":"St Mary's Elementary School",
    "wof:placetype":"venue"
},
  "geometry": {"coordinates":[-84.342124,46.497741],"type":"Point"}
}