{
  "type": "Feature",
  "properties": {
    "iso:country":"US",
    "sg:address":"1254 52nd St SE",
    "sg:city":"Grand Rapids",
    "sg:classifiers":[
        {
            "category":"Social Services",
            "subcategory":"Adult Care",
            "type":"Services"
        }
    ],
    "sg:phone":"+1 616 455 0779",
    "sg:postcode":"49508",
    "sg:province":"MI",
    "sg:tags":[
        "foster"
    ],
    "wof:name":"Sunstream Afc",
    "wof:placetype":"venue"
},
  "geometry": {"coordinates":[-85.634404,42.869173],"type":"Point"}
}