{
  "type": "Feature",
  "properties": {
    "iso:country":"US",
    "sg:address":"8140 Konczal St",
    "sg:city":"Center Line",
    "sg:classifiers":[
        {
            "category":"Organizations",
            "subcategory":"Religious Organization",
            "type":"Services"
        }
    ],
    "sg:phone":"+1 586 757 7471",
    "sg:postcode":"48015",
    "sg:province":"MI",
    "wof:name":"First Smong Baptist Church",
    "wof:placetype":"venue"
},
  "geometry": {"coordinates":[-83.025751,42.476656],"type":"Point"}
}