{
  "type": "Feature",
  "properties": {
    "iso:country":"US",
    "sg:address":"6701 US Hwy 23",
    "sg:city":"Spruce",
    "sg:classifiers":[
        {
            "category":"Wholesale",
            "subcategory":"Farm Supplies",
            "type":"Manufacturing & Wholesale Goods"
        }
    ],
    "sg:phone":"+1 989 471 5523",
    "sg:postcode":"48762",
    "sg:province":"MI",
    "sg:tags":[
        "feed"
    ],
    "wof:name":"Miller Feeds LLC",
    "wof:placetype":"venue"
},
  "geometry": {"coordinates":[-83.41169499999999,44.848533],"type":"Point"}
}