{
  "type": "Feature",
  "properties": {
    "iso:country":"US",
    "sg:address":"2145 Crooks Rd Ste 90",
    "sg:city":"Troy",
    "sg:classifiers":[
        {
            "category":"Professional",
            "subcategory":"Computer Services",
            "type":"Services"
        }
    ],
    "sg:phone":"+1 248 649 3830",
    "sg:postcode":"48084",
    "sg:province":"MI",
    "sg:tags":[
        "repair"
    ],
    "wof:name":"Computer Technologies Inc",
    "wof:placetype":"venue"
},
  "geometry": {"coordinates":[-83.166798,42.552768],"type":"Point"}
}