{
  "type": "Feature",
  "properties": {
    "iso:country":"US",
    "sg:address":"6320 Lewis Ave",
    "sg:city":"Temperance",
    "sg:classifiers":[
        {
            "category":"Education",
            "subcategory":"School",
            "type":"Public Place"
        }
    ],
    "sg:phone":"+1 734 847 6771",
    "sg:postcode":"48182",
    "sg:province":"MI",
    "sg:tags":[
        "church"
    ],
    "sg:website":"www.la-bc.org",
    "wof:name":"Lewis Avenue Baptist Church",
    "wof:placetype":"venue"
},
  "geometry": {"coordinates":[-83.566885,41.731699],"type":"Point"}
}