{
  "type": "Feature",
  "properties": {
    "iso:country":"US",
    "sg:address":"1051 N. Canton Center Road",
    "sg:city":"Canton",
    "sg:classifiers":[
        {
            "category":"Community Center",
            "type":"Public Place"
        }
    ],
    "sg:phone":"+1 734 844 5400",
    "sg:postcode":"48187",
    "sg:province":"MI",
    "sg:tags":[
        "medical"
    ],
    "sg:website":"www2.med.umich.edu/healthcenters...",
    "wof:name":"University Of Michigan- Canton Health Center",
    "wof:placetype":"venue"
},
  "geometry": {"coordinates":[-83.488739,42.31321],"type":"Point"}
}