{
  "type": "Feature",
  "properties": {
    "iso:country":"US",
    "sg:address":"1265 Fletcher St",
    "sg:city":"National City",
    "sg:classifiers":[
        {
            "category":"Building & Trades",
            "subcategory":"Construction",
            "type":"Services"
        }
    ],
    "sg:phone":"+1 989 469 3619",
    "sg:postcode":"48748",
    "sg:province":"MI",
    "sg:tags":[
        "house"
    ],
    "wof:name":"Kindell Eugene Builders",
    "wof:placetype":"venue"
},
  "geometry": {"coordinates":[-83.681242,44.315381],"type":"Point"}
}