{
  "type": "Feature",
  "properties": {
    "iso:country":"US",
    "sg:address":"2409 Valleyview Dr",
    "sg:city":"Troy",
    "sg:classifiers":[
        {
            "category":"Professional",
            "subcategory":"Business Services",
            "type":"Services"
        }
    ],
    "sg:phone":"+1 248 641 7081",
    "sg:postcode":"48098",
    "sg:province":"MI",
    "wof:name":"Rafco Business Link",
    "wof:placetype":"venue"
},
  "geometry": {"coordinates":[-83.19593,42.594395],"type":"Point"}
}