{
  "type": "Feature",
  "properties": {
    "iso:country":"US",
    "sg:address":"9924 Whittier St",
    "sg:city":"Detroit",
    "sg:classifiers":[
        {
            "category":"Real Estate",
            "subcategory":"Real Estate Agent",
            "type":"Services"
        }
    ],
    "sg:phone":"+1 313 881 5080",
    "sg:postcode":"48224",
    "sg:province":"MI",
    "sg:tags":[
        "consulting",
        "management"
    ],
    "wof:name":"Exsell Realtors Inc",
    "wof:placetype":"venue"
},
  "geometry": {"coordinates":[-82.94834899999999,42.415056],"type":"Point"}
}