{
  "type": "Feature",
  "properties": {
    "iso:country":"US",
    "sg:address":"100 Mellville St",
    "sg:city":"Engadine",
    "sg:classifiers":[
        {
            "category":"Autos & Motor Vehicles",
            "subcategory":"Fuel & Gas Station",
            "type":"Retail Goods"
        }
    ],
    "sg:phone":"+1 906 477 6222",
    "sg:postcode":"49827",
    "sg:province":"MI",
    "sg:tags":[
        "oil"
    ],
    "wof:name":"D & D Mobil Mart Engadine",
    "wof:placetype":"venue"
},
  "geometry": {"coordinates":[-85.571434,46.116654],"type":"Point"}
}