{
  "type": "Feature",
  "properties": {
    "iso:country":"US",
    "sg:address":"9253 Tonneberger Dr",
    "sg:city":"Tecumseh",
    "sg:classifiers":[
        {
            "category":"Building & Trades",
            "subcategory":"Construction",
            "type":"Services"
        }
    ],
    "sg:phone":"+1 517 423 5078",
    "sg:postcode":"49286",
    "sg:province":"MI",
    "sg:tags":[
        "contractor"
    ],
    "wof:name":"Custom Construction",
    "wof:placetype":"venue"
},
  "geometry": {"coordinates":[-83.95948199999999,42.028119],"type":"Point"}
}