{
  "type": "Feature",
  "properties": {
    "iso:country":"US",
    "sg:address":"1102 S Main St",
    "sg:city":"Cheboygan",
    "sg:classifiers":[
        {
            "category":"Restaurant",
            "type":"Food & Drink"
        }
    ],
    "sg:menulink":"http://www.allmenus.com/mi/cheboygan/79550-pizza-hut/menu/",
    "sg:phone":"+1 231 627 6641",
    "sg:postcode":"49721",
    "sg:province":"MI",
    "sg:tags":[
        "american",
        "pizza"
    ],
    "wof:name":"Pizza Hut",
    "wof:placetype":"venue"
},
  "geometry": {"coordinates":[-84.478247,45.627769],"type":"Point"}
}