{
  "type": "Feature",
  "properties": {
    "iso:country":"US",
    "sg:address":"1674 Waterbury Dr SE",
    "sg:city":"Grand Rapids",
    "sg:classifiers":[
        {
            "category":"Professional",
            "type":"Services"
        }
    ],
    "sg:phone":"+1 616 827 8936",
    "sg:postcode":"49508",
    "sg:province":"MI",
    "wof:name":"Irvine Assoc",
    "wof:placetype":"venue"
},
  "geometry": {"coordinates":[-85.623881,42.863981],"type":"Point"}
}