{
  "type": "Feature",
  "properties": {
    "iso:country":"US",
    "sg:address":"24445 Hass St",
    "sg:city":"Dearborn Heights",
    "sg:classifiers":[
        {
            "category":"Social Services",
            "subcategory":"Child Care",
            "type":"Services"
        }
    ],
    "sg:phone":"+1 313 565 9800",
    "sg:postcode":"48127",
    "sg:province":"MI",
    "sg:tags":[
        "day"
    ],
    "wof:name":"D W O Christian Academy",
    "wof:placetype":"venue"
},
  "geometry": {"coordinates":[-83.276991,42.334104],"type":"Point"}
}