{
  "type": "Feature",
  "properties": {
    "iso:country":"US",
    "sg:address":"35300 E Michigan Ave",
    "sg:city":"Wayne",
    "sg:classifiers":[
        {
            "category":"Cinema",
            "subcategory":"Movie Rental",
            "type":"Entertainment"
        }
    ],
    "sg:phone":"+1 734 729 1003",
    "sg:postcode":"48184",
    "sg:province":"MI",
    "sg:tags":[
        "game",
        "video"
    ],
    "sg:website":"www.blockbuster.com",
    "wof:name":"Blockbuster Video",
    "wof:placetype":"venue"
},
  "geometry": {"coordinates":[-83.38629899999999,42.279999],"type":"Point"}
}