{
  "type": "Feature",
  "properties": {
    "iso:country":"US",
    "sg:address":"5775 Beckley Rd",
    "sg:city":"Battle Creek",
    "sg:classifiers":[
        {
            "category":"Shopping",
            "subcategory":"Jewelry",
            "type":"Retail Goods"
        }
    ],
    "sg:phone":"+1 269 979 2488",
    "sg:postcode":"49015",
    "sg:province":"MI",
    "sg:tags":[
        "jeweler"
    ],
    "wof:name":"Jewlery Palace",
    "wof:placetype":"venue"
},
  "geometry": {"coordinates":[-85.181121,42.261122],"type":"Point"}
}