{
  "type": "Feature",
  "properties": {
    "iso:country":"US",
    "sg:address":"6570 M 66 N",
    "sg:city":"Charlevoix",
    "sg:classifiers":[
        {
            "category":"Shopping",
            "subcategory":"Department Store",
            "type":"Retail Goods"
        }
    ],
    "sg:phone":"+1 231 547 1459",
    "sg:postcode":"49720",
    "sg:province":"MI",
    "sg:tags":[
        "shop"
    ],
    "wof:name":"Dollar Tree",
    "wof:placetype":"venue"
},
  "geometry": {"coordinates":[-85.25454000000001,45.296711],"type":"Point"}
}