{
  "type": "Feature",
  "properties": {
    "iso:country":"US",
    "sg:address":"4786 E Lansing Rd",
    "sg:city":"Bancroft",
    "sg:phone":"+1 989 743 3249",
    "sg:postcode":"48414",
    "sg:province":"MI",
    "sg:tags":[
        "oil"
    ],
    "wof:name":"Blight Oil & Propane Inc",
    "wof:placetype":"venue"
},
  "geometry": {"coordinates":[-84.066425,42.884674],"type":"Point"}
}