{
  "type": "Feature",
  "properties": {
    "iso:country":"US",
    "sg:address":"4600 US Hwy 223",
    "sg:city":"Adrian",
    "sg:classifiers":[
        {
            "category":"Professional",
            "subcategory":"Business Services",
            "type":"Services"
        }
    ],
    "sg:phone":"+1 517 265 8000",
    "sg:postcode":"49221",
    "sg:province":"MI",
    "sg:tags":[
        "water",
        "treatment"
    ],
    "wof:name":"American Aqua Inc",
    "wof:placetype":"venue"
},
  "geometry": {"coordinates":[-84.078925,41.905602],"type":"Point"}
}