{
  "type": "Feature",
  "properties": {
    "iso:country":"US",
    "sg:address":"722 State Hwy 139",
    "sg:city":"Benton Harbor",
    "sg:classifiers":[
        {
            "category":"Autos & Motor Vehicles",
            "subcategory":"Automobile Sales",
            "type":"Retail Goods"
        }
    ],
    "sg:phone":"+1 269 926 7265",
    "sg:postcode":"49022",
    "sg:province":"MI",
    "sg:tags":[
        "car",
        "dealer"
    ],
    "wof:name":"Image Motors",
    "wof:placetype":"venue"
},
  "geometry": {"coordinates":[-86.4346,42.101763],"type":"Point"}
}