{
  "type": "Feature",
  "properties": {
    "iso:country":"US",
    "sg:address":"64692 Balk Rd",
    "sg:city":"Sturgis",
    "sg:classifiers":[
        {
            "category":"Building & Trades",
            "subcategory":"Construction",
            "type":"Services"
        }
    ],
    "sg:phone":"+1 269 651 5915",
    "sg:postcode":"49091",
    "sg:province":"MI",
    "sg:tags":[
        "hanging",
        "contractor"
    ],
    "wof:name":"Mike S Painting",
    "wof:placetype":"venue"
},
  "geometry": {"coordinates":[-85.467843,41.857584],"type":"Point"}
}