{
  "type": "Feature",
  "properties": {
    "iso:country":"US",
    "sg:address":"1440 28th St SW",
    "sg:city":"Wyoming",
    "sg:classifiers":[
        {
            "category":"Retail",
            "subcategory":"Car Wash",
            "type":"Services"
        }
    ],
    "sg:phone":"+1 616 538 4186",
    "sg:postcode":"49509",
    "sg:province":"MI",
    "sg:tags":[
        "polishing",
        "washing"
    ],
    "wof:name":"Prime Auto Wash",
    "wof:placetype":"venue"
},
  "geometry": {"coordinates":[-85.70272900000001,42.913391],"type":"Point"}
}