{
  "type": "Feature",
  "properties": {
    "iso:country":"US",
    "sg:address":"6272 Elwyn Ct",
    "sg:city":"Clarklake",
    "sg:classifiers":[
        {
            "category":"Professional",
            "subcategory":"Business Services",
            "type":"Services"
        }
    ],
    "sg:phone":"+1 517 592 2931",
    "sg:postcode":"49234",
    "sg:province":"MI",
    "sg:tags":[
        "inspection"
    ],
    "wof:name":"MDF Inspections",
    "wof:placetype":"venue"
},
  "geometry": {"coordinates":[-84.30143,42.118604],"type":"Point"}
}