{
  "type": "Feature",
  "properties": {
    "iso:country":"US",
    "sg:address":"8290 N Glass Rd",
    "sg:city":"Farwell",
    "sg:phone":"+1 989 588 2568",
    "sg:postcode":"48622",
    "sg:province":"MI",
    "sg:tags":[
        "farm",
        "field",
        "crop"
    ],
    "wof:name":"Ray Westphal",
    "wof:placetype":"venue"
},
  "geometry": {"coordinates":[-84.863513,43.770243],"type":"Point"}
}