{
  "type": "Feature",
  "properties": {
    "iso:country":"US",
    "sg:address":"222 S Lafayette St",
    "sg:city":"Greenville",
    "sg:classifiers":[
        {
            "category":"Personal",
            "subcategory":"Beauty Salon",
            "type":"Services"
        }
    ],
    "sg:phone":"+1 616 225 1887",
    "sg:postcode":"48838",
    "sg:province":"MI",
    "wof:name":"Creative Design",
    "wof:placetype":"venue"
},
  "geometry": {"coordinates":[-85.253061,43.179398],"type":"Point"}
}