{
  "type": "Feature",
  "properties": {
    "iso:country":"US",
    "sg:address":"9522 American St",
    "sg:city":"Detroit",
    "sg:classifiers":[
        {
            "category":"Real Estate",
            "subcategory":"Real Estate Agent",
            "type":"Services"
        }
    ],
    "sg:phone":"+1 313 850 6474",
    "sg:postcode":"48204",
    "sg:province":"MI",
    "sg:tags":[
        "property",
        "management",
        "rental"
    ],
    "wof:name":"Register26 Limited Lblty Corp",
    "wof:placetype":"venue"
},
  "geometry": {"coordinates":[-83.144564,42.369537],"type":"Point"}
}