{
  "type": "Feature",
  "properties": {
    "iso:country":"US",
    "sg:address":"4343 Brandywyne Dr",
    "sg:city":"Troy",
    "sg:classifiers":[
        {
            "category":"Health Services",
            "subcategory":"Clinic",
            "type":"Services"
        }
    ],
    "sg:phone":"+1 248 649 0399",
    "sg:postcode":"48098",
    "sg:province":"MI",
    "sg:tags":[
        "specialty",
        "outpatient"
    ],
    "wof:name":"John J Messana",
    "wof:placetype":"venue"
},
  "geometry": {"coordinates":[-83.19231499999999,42.580393],"type":"Point"}
}