{
  "type": "Feature",
  "properties": {
    "iso:country":"US",
    "sg:address":"330 Honeysuckle Ln",
    "sg:city":"Lansing",
    "sg:classifiers":[
        {
            "category":"Wholesale",
            "subcategory":"Non-durable Goods",
            "type":"Manufacturing & Wholesale Goods"
        }
    ],
    "sg:phone":"+1 517 323 7320",
    "sg:postcode":"48917",
    "sg:province":"MI",
    "sg:tags":[
        "advertising"
    ],
    "wof:name":"Photo Sharp Inc",
    "wof:placetype":"venue"
},
  "geometry": {"coordinates":[-84.613552,42.730517],"type":"Point"}
}