{
  "type": "Feature",
  "properties": {
    "iso:country":"US",
    "sg:address":"25642 Firwood Ave",
    "sg:city":"Warren",
    "sg:classifiers":[
        {
            "category":"Shopping",
            "subcategory":"Hobbies, Toys, & Games",
            "type":"Retail Goods"
        }
    ],
    "sg:phone":"+1 586 552 8011",
    "sg:postcode":"48089",
    "sg:province":"MI",
    "sg:tags":[
        "supply"
    ],
    "wof:name":"Aces Full Poker",
    "wof:placetype":"venue"
},
  "geometry": {"coordinates":[-82.970997,42.485616],"type":"Point"}
}