{
  "type": "Feature",
  "properties": {
    "iso:country":"US",
    "sg:address":"510 W 17th St",
    "sg:city":"Holland",
    "sg:classifiers":[
        {
            "category":"Wholesale",
            "subcategory":"Meat",
            "type":"Manufacturing & Wholesale Goods"
        }
    ],
    "sg:phone":"+1 616 394 5102",
    "sg:postcode":"49423",
    "sg:province":"MI",
    "sg:tags":[
        "food",
        "distributor"
    ],
    "wof:name":"The Ero Group",
    "wof:placetype":"venue"
},
  "geometry": {"coordinates":[-86.130183,42.781914],"type":"Point"}
}