{
  "type": "Feature",
  "properties": {
    "iso:country":"US",
    "sg:address":"9081 1st St",
    "sg:city":"Baroda",
    "sg:classifiers":[
        {
            "category":"Government",
            "subcategory":"Fire Station",
            "type":"Public Place"
        }
    ],
    "sg:phone":"+1 269 422 6900",
    "sg:postcode":"49101",
    "sg:province":"MI",
    "sg:tags":[
        "department",
        "protection"
    ],
    "wof:name":"Baroda Fire Department",
    "wof:placetype":"venue"
},
  "geometry": {"coordinates":[-86.48557700000001,41.952321],"type":"Point"}
}