{
  "type": "Feature",
  "properties": {
    "iso:country":"US",
    "sg:address":"2535 Airport Rd",
    "sg:city":"Adrian",
    "sg:classifiers":[
        {
            "category":"Retail",
            "subcategory":"Laundry & Dry Cleaning",
            "type":"Services"
        }
    ],
    "sg:phone":"+1 517 263 7146",
    "sg:postcode":"49221",
    "sg:province":"MI",
    "wof:name":"Chem Dry of Lenawee",
    "wof:placetype":"venue"
},
  "geometry": {"coordinates":[-84.06567200000001,41.881628],"type":"Point"}
}