{
  "type": "Feature",
  "properties": {
    "iso:country":"US",
    "sg:address":"3600 Bradway Blvd",
    "sg:city":"Bloomfield Hills",
    "sg:classifiers":[
        {
            "category":"Education",
            "subcategory":"School",
            "type":"Public Place"
        }
    ],
    "sg:phone":"+1 248 647 2522",
    "sg:postcode":"48301",
    "sg:province":"MI",
    "sg:tags":[
        "high",
        "middle",
        "elementary"
    ],
    "wof:name":"Detroit Country Day School",
    "wof:placetype":"venue"
},
  "geometry": {"coordinates":[-83.262109,42.547932],"type":"Point"}
}