{
  "type": "Feature",
  "properties": {
    "iso:country":"US",
    "sg:address":"9220 Faussett Rd",
    "sg:city":"Fenton",
    "sg:classifiers":[
        {
            "category":"Building & Trades",
            "subcategory":"Landscaping Services",
            "type":"Services"
        }
    ],
    "sg:phone":"+1 810 714 9321",
    "sg:postcode":"48430",
    "sg:province":"MI",
    "sg:tags":[
        "landscape",
        "contractor"
    ],
    "wof:name":"Twin Towers Landscaping",
    "wof:placetype":"venue"
},
  "geometry": {"coordinates":[-83.77909699999999,42.707279],"type":"Point"}
}