{
  "type": "Feature",
  "properties": {
    "iso:country":"US",
    "sg:address":"728 Gratiot Ave",
    "sg:city":"Alma",
    "sg:classifiers":[
        {
            "category":"Wholesale",
            "subcategory":"Photographic Equipment",
            "type":"Manufacturing & Wholesale Goods"
        }
    ],
    "sg:phone":"+1 989 463 5334",
    "sg:postcode":"48801",
    "sg:province":"MI",
    "sg:tags":[
        "photo"
    ],
    "wof:name":"Lovin Country Too Inc",
    "wof:placetype":"venue"
},
  "geometry": {"coordinates":[-84.658513,43.384873],"type":"Point"}
}