{
  "type": "Feature",
  "properties": {
    "iso:country":"US",
    "sg:address":"7228 Johnson Rd",
    "sg:city":"Flushing",
    "sg:classifiers":[
        {
            "category":"Building & Trades",
            "subcategory":"Construction",
            "type":"Services"
        }
    ],
    "sg:phone":"+1 810 659 3572",
    "sg:postcode":"48433",
    "sg:province":"MI",
    "sg:tags":[
        "house"
    ],
    "wof:name":"Design Master Builders Inc",
    "wof:placetype":"venue"
},
  "geometry": {"coordinates":[-83.82852699999999,43.10995],"type":"Point"}
}