{
  "type": "Feature",
  "properties": {
    "iso:country":"US",
    "sg:address":"4626 Old Plank Rd",
    "sg:city":"Milford",
    "sg:classifiers":[
        {
            "category":"Building & Trades",
            "subcategory":"Construction",
            "type":"Services"
        }
    ],
    "sg:phone":"+1 248 685 2678",
    "sg:postcode":"48381",
    "sg:province":"MI",
    "sg:tags":[
        "excavation",
        "contractor"
    ],
    "wof:name":"Diamond Contracting",
    "wof:placetype":"venue"
},
  "geometry": {"coordinates":[-83.57690599999999,42.527182],"type":"Point"}
}