{
  "type": "Feature",
  "properties": {
    "iso:country":"US",
    "sg:address":"5870 Safety Dr NE",
    "sg:city":"Belmont",
    "sg:classifiers":[
        {
            "category":"Recreation",
            "subcategory":"Amusement Park",
            "type":"Entertainment"
        },
        {
            "category":"Recreation",
            "subcategory":"Picnic Area",
            "type":"Entertainment"
        }
    ],
    "sg:phone":"+1 616 785 5215",
    "sg:postcode":"49306",
    "sg:province":"MI",
    "sg:tags":[
        "device",
        "place",
        "arcade"
    ],
    "sg:website":"http://theblastfactory.com",
    "wof:name":"Blast Factory",
    "wof:placetype":"venue"
},
  "geometry": {"coordinates":[-85.63269200000001,43.069483],"type":"Point"}
}