{
  "type": "Feature",
  "properties": {
    "iso:country":"US",
    "sg:address":"23001 Sagebrush",
    "sg:city":"Novi",
    "sg:classifiers":[
        {
            "category":"Insurance",
            "subcategory":"Life Insurance",
            "type":"Services"
        }
    ],
    "sg:phone":"+1 248 348 0915",
    "sg:postcode":"48375",
    "sg:province":"MI",
    "sg:tags":[
        "carrier"
    ],
    "wof:name":"Roger Spagnuolo",
    "wof:placetype":"venue"
},
  "geometry": {"coordinates":[-83.470564,42.455594],"type":"Point"}
}