{
  "type": "Feature",
  "properties": {
    "iso:country":"US",
    "sg:address":"923 10th St",
    "sg:city":"Plainwell",
    "sg:classifiers":[
        {
            "category":"Organizations",
            "subcategory":"Professional Association",
            "type":"Services"
        }
    ],
    "sg:phone":"+1 269 685 5907",
    "sg:postcode":"49080",
    "sg:province":"MI",
    "wof:name":"Alpha Delta Kappa Sororit",
    "wof:placetype":"venue"
},
  "geometry": {"coordinates":[-85.641766,42.48777],"type":"Point"}
}