{
  "type": "Feature",
  "properties": {
    "iso:country":"US",
    "sg:address":"550 N Old Woodward Ave",
    "sg:city":"Birmingham",
    "sg:classifiers":[
        {
            "category":"Shopping",
            "type":"Retail Goods"
        }
    ],
    "sg:phone":"+1 248 647 5470",
    "sg:postcode":"48009",
    "sg:province":"MI",
    "sg:tags":[
        "art",
        "gallery",
        "dealer"
    ],
    "wof:name":"Yaw Gallery",
    "wof:placetype":"venue"
},
  "geometry": {"coordinates":[-83.21804400000001,42.551521],"type":"Point"}
}