{
  "type": "Feature",
  "properties": {
    "iso:country":"US",
    "sg:address":"7661 Bitterbush",
    "sg:city":"Clarkston",
    "sg:classifiers":[
        {
            "category":"Building & Trades",
            "subcategory":"Construction",
            "type":"Services"
        }
    ],
    "sg:phone":"+1 248 620 3979",
    "sg:postcode":"48348",
    "sg:province":"MI",
    "sg:tags":[
        "contractor"
    ],
    "wof:name":"Castlewood Custom Homes Inc",
    "wof:placetype":"venue"
},
  "geometry": {"coordinates":[-83.442887,42.763427],"type":"Point"}
}