{
  "type": "Feature",
  "properties": {
    "iso:country":"US",
    "sg:address":"718 Kuhl Rd",
    "sg:city":"Bay Port",
    "sg:classifiers":[
        {
            "category":"Insurance",
            "subcategory":"Insurance Agent",
            "type":"Services"
        }
    ],
    "sg:phone":"+1 989 656 2461",
    "sg:postcode":"48720",
    "sg:province":"MI",
    "wof:name":"Thumb Insurance",
    "wof:placetype":"venue"
},
  "geometry": {"coordinates":[-83.39772000000001,43.807604],"type":"Point"}
}