{
  "type": "Feature",
  "properties": {
    "iso:country":"US",
    "sg:address":"24241 Susan Dr",
    "sg:city":"Farmington",
    "sg:classifiers":[
        {
            "category":"Real Estate",
            "subcategory":"Real Estate Operator",
            "type":"Services"
        }
    ],
    "sg:phone":"+1 248 442 1314",
    "sg:postcode":"48336",
    "sg:province":"MI",
    "sg:tags":[
        "building",
        "nonresidential"
    ],
    "wof:name":"Vinraw Properties",
    "wof:placetype":"venue"
},
  "geometry": {"coordinates":[-83.329398,42.467791],"type":"Point"}
}