{
  "type": "Feature",
  "properties": {
    "iso:country":"US",
    "sg:address":"205 Washington Sq S",
    "sg:city":"Lansing",
    "sg:classifiers":[
        {
            "category":"Restaurant",
            "type":"Food & Drink"
        }
    ],
    "sg:phone":"+1 517 487 3333",
    "sg:postcode":"48933",
    "sg:province":"MI",
    "sg:tags":[
        "delicatessen"
    ],
    "wof:name":"Byblos",
    "wof:placetype":"venue"
},
  "geometry": {"coordinates":[-84.552181,42.731381],"type":"Point"}
}