{
  "type": "Feature",
  "properties": {
    "iso:country":"US",
    "sg:address":"6415 W M-72",
    "sg:city":"Grayling",
    "sg:classifiers":[
        {
            "category":"Restaurant",
            "type":"Food & Drink"
        }
    ],
    "sg:phone":"+1 989 344 1918",
    "sg:postcode":"49738",
    "sg:province":"MI",
    "sg:tags":[
        "parlor",
        "ice",
        "cream"
    ],
    "wof:name":"Wimpy's",
    "wof:placetype":"venue"
},
  "geometry": {"coordinates":[-84.765472,44.661619],"type":"Point"}
}