{
  "type": "Feature",
  "properties": {
    "iso:country":"US",
    "sg:address":"412 N Superior St",
    "sg:city":"Albion",
    "sg:classifiers":[
        {
            "category":"Personal",
            "subcategory":"Barber",
            "type":"Services"
        }
    ],
    "sg:phone":"+1 517 629 7370",
    "sg:postcode":"49224",
    "sg:province":"MI",
    "wof:name":"Irene's Superior Unisex Salon",
    "wof:placetype":"venue"
},
  "geometry": {"coordinates":[-84.75296,42.248317],"type":"Point"}
}