{
  "type": "Feature",
  "properties": {
    "iso:country":"US",
    "sg:address":"5098 N Wacousta Rd",
    "sg:city":"Fowler",
    "sg:classifiers":[
        {
            "category":"Manufacturing",
            "subcategory":"Tools & Machinery",
            "type":"Manufacturing & Wholesale Goods"
        }
    ],
    "sg:phone":"+1 989 682 4828",
    "sg:postcode":"48835",
    "sg:province":"MI",
    "sg:tags":[
        "industrial",
        "mfg"
    ],
    "wof:name":"Judd Enterprise",
    "wof:placetype":"venue"
},
  "geometry": {"coordinates":[-84.700249,43.065262],"type":"Point"}
}