{
  "type": "Feature",
  "properties": {
    "iso:country":"US",
    "sg:address":"7804 Allen Rd",
    "sg:city":"Allen Park",
    "sg:classifiers":[
        {
            "category":"Health Services",
            "subcategory":"Doctor",
            "type":"Services"
        }
    ],
    "sg:phone":"+1 313 388 0033",
    "sg:postcode":"48101",
    "sg:province":"MI",
    "sg:tags":[
        "medical"
    ],
    "wof:name":"Raper Ralph W MD",
    "wof:placetype":"venue"
},
  "geometry": {"coordinates":[-83.216904,42.251801],"type":"Point"}
}