{
  "type": "Feature",
  "properties": {
    "iso:country":"US",
    "sg:address":"1254 Heatherwoode Rd",
    "sg:city":"Flint",
    "sg:classifiers":[
        {
            "category":"Health Services",
            "subcategory":"Doctor",
            "type":"Services"
        }
    ],
    "sg:phone":"+1 810 733 6943",
    "sg:postcode":"48532",
    "sg:province":"MI",
    "sg:tags":[
        "medical"
    ],
    "wof:name":"Epifania Aranas MD",
    "wof:placetype":"venue"
},
  "geometry": {"coordinates":[-83.776968,43.02396],"type":"Point"}
}