{
  "type": "Feature",
  "properties": {
    "iso:country":"US",
    "sg:address":"6270 Waldon Rd",
    "sg:city":"Clarkston",
    "sg:classifiers":[
        {
            "category":"Professional",
            "subcategory":"Computer Services",
            "type":"Services"
        }
    ],
    "sg:phone":"+1 248 625 1152",
    "sg:postcode":"48346",
    "sg:province":"MI",
    "sg:tags":[
        "datum"
    ],
    "wof:name":"Likuid Creations",
    "wof:placetype":"venue"
},
  "geometry": {"coordinates":[-83.39819900000001,42.733235],"type":"Point"}
}