{
  "type": "Feature",
  "properties": {
    "iso:country":"US",
    "sg:address":"51512 Industrial Dr",
    "sg:city":"New Baltimore",
    "sg:classifiers":[
        {
            "category":"Professional",
            "subcategory":"Management & Consulting",
            "type":"Services"
        }
    ],
    "sg:phone":"+1 586 716 2300",
    "sg:postcode":"48047",
    "sg:province":"MI",
    "sg:tags":[
        "development",
        "industrial"
    ],
    "sg:website":"www.whittlesey.com",
    "wof:name":"Whittlesey Development",
    "wof:placetype":"venue"
},
  "geometry": {"coordinates":[-82.754932,42.683522],"type":"Point"}
}