{
  "type": "Feature",
  "properties": {
    "iso:country":"US",
    "sg:address":"355 Marauder St",
    "sg:city":"Gwinn",
    "sg:classifiers":[
        {
            "category":"Professional",
            "subcategory":"Computer Services",
            "type":"Services"
        }
    ],
    "sg:phone":"+1 906 346 9327",
    "sg:postcode":"49841",
    "sg:province":"MI",
    "sg:tags":[
        "repair"
    ],
    "wof:name":"C & D Computech",
    "wof:placetype":"venue"
},
  "geometry": {"coordinates":[-87.357674,46.332902],"type":"Point"}
}