{
  "type": "Feature",
  "properties": {
    "iso:country":"US",
    "sg:address":"47230 Hayes Rd",
    "sg:city":"Macomb",
    "sg:classifiers":[
        {
            "category":"Building & Trades",
            "subcategory":"Construction",
            "type":"Services"
        }
    ],
    "sg:phone":"+1 586 532 2070",
    "sg:postcode":"48044",
    "sg:province":"MI",
    "sg:tags":[
        "general",
        "contractor"
    ],
    "wof:name":"F H Martin Constructors",
    "wof:placetype":"venue"
},
  "geometry": {"coordinates":[-82.973827,42.642491],"type":"Point"}
}