{
  "type": "Feature",
  "properties": {
    "iso:country":"US",
    "sg:address":"2691 Carpenter Rd",
    "sg:city":"Lapeer",
    "sg:classifiers":[
        {
            "category":"Professional",
            "subcategory":"Business Services",
            "type":"Services"
        }
    ],
    "sg:phone":"+1 810 793 6650",
    "sg:postcode":"48446",
    "sg:province":"MI",
    "sg:tags":[
        "honing",
        "lapping",
        "grinding"
    ],
    "wof:name":"Lapeer Precision Specialties",
    "wof:placetype":"venue"
},
  "geometry": {"coordinates":[-83.37082599999999,43.106286],"type":"Point"}
}