{
  "type": "Feature",
  "properties": {
    "iso:country":"US",
    "sg:address":"24833 Ryan Rd",
    "sg:city":"Warren",
    "sg:classifiers":[
        {
            "category":"Personal",
            "subcategory":"Beauty Salon",
            "type":"Services"
        }
    ],
    "sg:phone":"+1 586 427 1588",
    "sg:postcode":"48091",
    "sg:province":"MI",
    "wof:name":"Beauty Secrets By Candy",
    "wof:placetype":"venue"
},
  "geometry": {"coordinates":[-83.065186,42.474826],"type":"Point"}
}