{
  "type": "Feature",
  "properties": {
    "iso:country":"US",
    "sg:address":"22141 Coolidge Hwy",
    "sg:city":"Oak Park",
    "sg:classifiers":[
        {
            "category":"Shopping",
            "subcategory":"Gifts & Souvenirs",
            "type":"Retail Goods"
        }
    ],
    "sg:phone":"+1 248 542 6777",
    "sg:postcode":"48237",
    "sg:province":"MI",
    "sg:tags":[
        "shop"
    ],
    "wof:name":"Tihal Custom Design",
    "wof:placetype":"venue"
},
  "geometry": {"coordinates":[-83.181956,42.457652],"type":"Point"}
}