{
  "type": "Feature",
  "properties": {
    "iso:country":"US",
    "sg:address":"6250 S Cedar St",
    "sg:city":"Lansing",
    "sg:classifiers":[
        {
            "category":"Shopping",
            "type":"Retail Goods"
        }
    ],
    "sg:phone":"+1 517 393 7780",
    "sg:postcode":"48911",
    "sg:province":"MI",
    "sg:tags":[
        "telephone",
        "cellular"
    ],
    "wof:name":"Radio Shack",
    "wof:placetype":"venue"
},
  "geometry": {"coordinates":[-84.542976,42.667479],"type":"Point"}
}