{
  "type": "Feature",
  "properties": {
    "iso:country":"US",
    "sg:address":"855 W Sanilac Rd",
    "sg:city":"Sandusky",
    "sg:classifiers":[
        {
            "category":"Building & Trades",
            "subcategory":"Construction",
            "type":"Services"
        }
    ],
    "sg:phone":"+1 810 648 3299",
    "sg:postcode":"48471",
    "sg:province":"MI",
    "sg:website":"www.united-const.com",
    "wof:name":"United Construction",
    "wof:placetype":"venue"
},
  "geometry": {"coordinates":[-82.85945100000001,43.420612],"type":"Point"}
}