{
  "type": "Feature",
  "properties": {
    "iso:country":"US",
    "sg:address":"6401 N Elms Rd",
    "sg:city":"Flushing",
    "sg:classifiers":[
        {
            "category":"Professional",
            "subcategory":"Computer Services",
            "type":"Services"
        }
    ],
    "sg:phone":"+1 810 659 2497",
    "sg:postcode":"48433",
    "sg:province":"MI",
    "sg:tags":[
        "software"
    ],
    "wof:name":"Ogden Software",
    "wof:placetype":"venue"
},
  "geometry": {"coordinates":[-83.813655,43.099828],"type":"Point"}
}