{
  "type": "Feature",
  "properties": {
    "iso:country":"US",
    "sg:address":"4718 Parkridge Dr",
    "sg:city":"Waterford",
    "sg:classifiers":[
        {
            "category":"Professional",
            "type":"Services"
        }
    ],
    "sg:phone":"+1 248 623 6352",
    "sg:postcode":"48329",
    "sg:province":"MI",
    "wof:name":"Carr Rayne",
    "wof:placetype":"venue"
},
  "geometry": {"coordinates":[-83.38352399999999,42.700226],"type":"Point"}
}