{
  "type": "Feature",
  "properties": {
    "iso:country":"US",
    "sg:address":"14100 Lakeside Cir",
    "sg:city":"Sterling Heights",
    "sg:classifiers":[
        {
            "category":"Health Services",
            "subcategory":"Dentist",
            "type":"Services"
        }
    ],
    "sg:phone":"+1 586 566 9916",
    "sg:postcode":"48313",
    "sg:province":"MI",
    "sg:website":"www.dentalworks.com",
    "wof:name":"DentalWorks",
    "wof:placetype":"venue"
},
  "geometry": {"coordinates":[-82.985989,42.622344],"type":"Point"}
}