{
  "type": "Feature",
  "properties": {
    "iso:country":"US",
    "sg:address":"1826 Rowland Ave SE",
    "sg:city":"Grand Rapids",
    "sg:classifiers":[
        {
            "category":"Communications",
            "subcategory":"Film & Video Production",
            "type":"Services"
        }
    ],
    "sg:phone":"+1 616 957 4082",
    "sg:postcode":"49546",
    "sg:province":"MI",
    "sg:tags":[
        "audio"
    ],
    "wof:name":"Talking Donkey Productions",
    "wof:placetype":"venue"
},
  "geometry": {"coordinates":[-85.57512,42.927444],"type":"Point"}
}