{
  "type": "Feature",
  "properties": {
    "iso:country":"US",
    "sg:address":"4510 W Main St",
    "sg:city":"Kalamazoo",
    "sg:classifiers":[
        {
            "category":"Personal",
            "subcategory":"Tanning Parlor",
            "type":"Services"
        }
    ],
    "sg:phone":"+1 269 382 5100",
    "sg:postcode":"49006",
    "sg:province":"MI",
    "sg:tags":[
        "salon"
    ],
    "wof:name":"Mirage Tanning Ctr",
    "wof:placetype":"venue"
},
  "geometry": {"coordinates":[-85.645652,42.296349],"type":"Point"}
}