{
  "type": "Feature",
  "properties": {
    "iso:country":"US",
    "sg:address":"21320 Kipling St",
    "sg:city":"Oak Park",
    "sg:classifiers":[
        {
            "category":"Manufacturing",
            "subcategory":"Printing",
            "type":"Manufacturing & Wholesale Goods"
        }
    ],
    "sg:phone":"+1 248 541 4608",
    "sg:postcode":"48237",
    "sg:province":"MI",
    "sg:tags":[
        "printer"
    ],
    "wof:name":"Functional Arts",
    "wof:placetype":"venue"
},
  "geometry": {"coordinates":[-83.185294,42.452288],"type":"Point"}
}