{
  "type": "Feature",
  "properties": {
    "iso:country":"US",
    "sg:address":"3626 S Lakeshore Dr",
    "sg:city":"St Joseph",
    "sg:classifiers":[
        {
            "category":"Real Estate",
            "subcategory":"Real Estate Operator",
            "type":"Services"
        }
    ],
    "sg:phone":"+1 269 429 4481",
    "sg:postcode":"49085",
    "sg:province":"MI",
    "sg:tags":[
        "apartment"
    ],
    "wof:name":"Lakeshore Condos",
    "wof:placetype":"venue"
},
  "geometry": {"coordinates":[-86.514287,42.051641],"type":"Point"}
}