{
  "type": "Feature",
  "properties": {
    "iso:country":"US",
    "sg:address":"1000 Muskegon Ave NW",
    "sg:city":"Grand Rapids",
    "sg:classifiers":[
        {
            "category":"Wholesale",
            "subcategory":"Electrical",
            "type":"Manufacturing & Wholesale Goods"
        }
    ],
    "sg:phone":"+1 616 454 9800",
    "sg:postcode":"49504",
    "sg:province":"MI",
    "sg:tags":[
        "fire",
        "equipment",
        "protection"
    ],
    "sg:website":"www.rapidfireprotection.com",
    "wof:name":"Rapid Fire Protection",
    "wof:placetype":"venue"
},
  "geometry": {"coordinates":[-85.68433899999999,42.983256],"type":"Point"}
}