{
  "type": "Feature",
  "properties": {
    "iso:country":"US",
    "sg:address":"12175 Goudy Lk Rd",
    "sg:city":"Otisville",
    "sg:classifiers":[
        {
            "category":"Retail",
            "subcategory":"Auto Repair",
            "type":"Services"
        }
    ],
    "sg:phone":"+1 810 793 6137",
    "sg:postcode":"48463",
    "sg:province":"MI",
    "sg:tags":[
        "glass",
        "replacement"
    ],
    "wof:name":"Falcons Auto Glass",
    "wof:placetype":"venue"
},
  "geometry": {"coordinates":[-83.471681,43.168247],"type":"Point"}
}