{
  "type": "Feature",
  "properties": {
    "iso:country":"US",
    "sg:address":"430 Leonard St NW",
    "sg:city":"Grand Rapids",
    "sg:classifiers":[
        {
            "category":"Organizations",
            "subcategory":"Religious Organization",
            "type":"Services"
        }
    ],
    "sg:phone":"+1 616 451 4976",
    "sg:postcode":"49504",
    "sg:province":"MI",
    "sg:tags":[
        "church"
    ],
    "wof:name":"Alpha & Omega Worship Ctr",
    "wof:placetype":"venue"
},
  "geometry": {"coordinates":[-85.678769,42.984919],"type":"Point"}
}