{
  "type": "Feature",
  "properties": {
    "iso:country":"US",
    "sg:address":"3000 N Stephens Rd",
    "sg:city":"Fountain",
    "sg:classifiers":[
        {
            "category":"Farming",
            "subcategory":"Aquatic Farm",
            "type":"Manufacturing & Wholesale Goods"
        }
    ],
    "sg:phone":"+1 231 357 6076",
    "sg:postcode":"49405",
    "sg:province":"MI",
    "sg:tags":[
        "aquaculture"
    ],
    "wof:name":"West Michigan Aquaculture",
    "wof:placetype":"venue"
},
  "geometry": {"coordinates":[-86.200726,44.018302],"type":"Point"}
}