{
  "type": "Feature",
  "properties": {
    "iso:country":"US",
    "sg:address":"312 Ellsworth Ave SW",
    "sg:city":"Grand Rapids",
    "sg:classifiers":[
        {
            "category":"Professional",
            "subcategory":"Art Services",
            "type":"Services"
        }
    ],
    "sg:phone":"+1 616 454 1001",
    "sg:postcode":"49503",
    "sg:province":"MI",
    "sg:tags":[
        "photographer"
    ],
    "wof:name":"Big Event",
    "wof:placetype":"venue"
},
  "geometry": {"coordinates":[-85.673417,42.957259],"type":"Point"}
}