{
  "type": "Feature",
  "properties": {
    "iso:country":"US",
    "sg:address":"2525 Telegraph Rd Ste 201",
    "sg:city":"Bloomfield Hills",
    "sg:classifiers":[
        {
            "category":"Health Services",
            "subcategory":"Doctor",
            "type":"Services"
        }
    ],
    "sg:phone":"+1 248 338 0100",
    "sg:postcode":"48302",
    "sg:province":"MI",
    "sg:website":"www.associatedobgyn.net",
    "wof:name":"Robert M Robins, MD",
    "wof:placetype":"venue"
},
  "geometry": {"coordinates":[-83.289928,42.603762],"type":"Point"}
}