{
  "type": "Feature",
  "properties": {
    "iso:country":"US",
    "sg:address":"1190 E Milham Ave",
    "sg:city":"Portage",
    "sg:classifiers":[
        {
            "category":"Health Services",
            "subcategory":"Doctor",
            "type":"Services"
        }
    ],
    "sg:phone":"+1 269 323 1554",
    "sg:postcode":"49002",
    "sg:province":"MI",
    "sg:tags":[
        "dentist"
    ],
    "wof:name":"Timothy D Walbridge D S",
    "wof:placetype":"venue"
},
  "geometry": {"coordinates":[-85.575293,42.230063],"type":"Point"}
}