{
  "type": "Feature",
  "properties": {
    "iso:country":"US",
    "sg:address":"39023 Harper Ave",
    "sg:city":"Clinton Township",
    "sg:classifiers":[
        {
            "category":"Retail",
            "subcategory":"Portrait Studio",
            "type":"Services"
        },
        {
            "category":"Shopping",
            "subcategory":"Pharmacy",
            "type":"Retail Goods"
        }
    ],
    "sg:phone":"+1 586 463 4565",
    "sg:postcode":"48036",
    "sg:province":"MI",
    "sg:tags":[
        "photography",
        "drugstore",
        "store"
    ],
    "wof:name":"Familymeds Pharmacy",
    "wof:placetype":"venue"
},
  "geometry": {"coordinates":[-82.865196,42.585899],"type":"Point"}
}