{
  "type": "Feature",
  "properties": {
    "iso:country":"US",
    "sg:address":"26521 Joe Dr",
    "sg:city":"Warren",
    "sg:classifiers":[
        {
            "category":"Real Estate",
            "subcategory":"Real Estate Agent",
            "type":"Services"
        }
    ],
    "sg:phone":"+1 586 751 1650",
    "sg:postcode":"48091",
    "sg:province":"MI",
    "wof:name":"Klos Real Estate Dev",
    "wof:placetype":"venue"
},
  "geometry": {"coordinates":[-83.078369,42.486582],"type":"Point"}
}