{
  "type": "Feature",
  "properties": {
    "iso:country":"US",
    "sg:address":"17026 Clinton River Rd",
    "sg:city":"Clinton Twp",
    "sg:classifiers":[
        {
            "category":"Professional",
            "type":"Services"
        }
    ],
    "sg:phone":"+1 586 412 0786",
    "sg:postcode":"48038",
    "sg:province":"MI",
    "sg:tags":[
        "establishment"
    ],
    "wof:name":"Fernhill Village",
    "wof:placetype":"venue"
},
  "geometry": {"coordinates":[-82.94921100000001,42.579031],"type":"Point"}
}