{
  "type": "Feature",
  "properties": {
    "iso:country":"US",
    "sg:address":"1768 Hampton Rd",
    "sg:city":"Grosse Pointe",
    "sg:classifiers":[
        {
            "category":"Professional",
            "subcategory":"Employment Agencies",
            "type":"Services"
        }
    ],
    "sg:phone":"+1 313 886 2131",
    "sg:postcode":"48236",
    "sg:province":"MI",
    "sg:tags":[
        "help",
        "supply"
    ],
    "wof:name":"Workenders",
    "wof:placetype":"venue"
},
  "geometry": {"coordinates":[-82.90580799999999,42.447568],"type":"Point"}
}