{
  "type": "Feature",
  "properties": {
    "iso:country":"US",
    "sg:address":"14495 Boom Rd",
    "sg:city":"Spring Lake",
    "sg:classifiers":[
        {
            "category":"Retail",
            "subcategory":"Portrait Studio",
            "type":"Services"
        }
    ],
    "sg:phone":"+1 616 846 3029",
    "sg:postcode":"49456",
    "sg:province":"MI",
    "sg:tags":[
        "photo"
    ],
    "wof:name":"Adams Photo Studio",
    "wof:placetype":"venue"
},
  "geometry": {"coordinates":[-86.147621,43.044861],"type":"Point"}
}