{
  "type": "Feature",
  "properties": {
    "iso:country":"US",
    "sg:address":"32497 Schoolcraft Rd",
    "sg:city":"Livonia",
    "sg:classifiers":[
        {
            "category":"Wholesale",
            "subcategory":"Office Equipment",
            "type":"Manufacturing & Wholesale Goods"
        }
    ],
    "sg:phone":"+1 248 471 5337",
    "sg:postcode":"48150",
    "sg:province":"MI",
    "sg:tags":[
        "business"
    ],
    "wof:name":"Essential Business Supplies",
    "wof:placetype":"venue"
},
  "geometry": {"coordinates":[-83.36535000000001,42.382249],"type":"Point"}
}