{
  "type": "Feature",
  "properties": {
    "iso:country":"US",
    "sg:address":"3810 Mystic Valley Dr",
    "sg:city":"Bloomfield Hills",
    "sg:classifiers":[
        {
            "category":"Building & Trades",
            "subcategory":"Construction",
            "type":"Services"
        }
    ],
    "sg:phone":"+1 248 723 9770",
    "sg:postcode":"48302",
    "sg:province":"MI",
    "sg:tags":[
        "interior",
        "design"
    ],
    "wof:name":"Presence II Inc",
    "wof:placetype":"venue"
},
  "geometry": {"coordinates":[-83.281767,42.584671],"type":"Point"}
}