{
  "type": "Feature",
  "properties": {
    "iso:country":"US",
    "sg:address":"33000 Civic Center Dr",
    "sg:city":"Livonia",
    "sg:classifiers":[
        {
            "category":"Government",
            "subcategory":"Office",
            "type":"Public Place"
        }
    ],
    "sg:phone":"+1 734 466 2200",
    "sg:postcode":"48154",
    "sg:province":"MI",
    "sg:tags":[
        "city"
    ],
    "wof:name":"City of Livonia",
    "wof:placetype":"venue"
},
  "geometry": {"coordinates":[-83.37099499999999,42.395081],"type":"Point"}
}