{
  "type": "Feature",
  "properties": {
    "iso:country":"US",
    "sg:address":"4585 Lake Shore Dr",
    "sg:city":"Charlevoix",
    "sg:classifiers":[
        {
            "category":"Real Estate",
            "subcategory":"Architect",
            "type":"Services"
        }
    ],
    "sg:phone":"+1 231 547 9160",
    "sg:postcode":"49720",
    "sg:province":"MI",
    "wof:name":"John Dziurman Architects LTD",
    "wof:placetype":"venue"
},
  "geometry": {"coordinates":[-85.364983,45.274902],"type":"Point"}
}