{
  "type": "Feature",
  "properties": {
    "iso:country":"US",
    "sg:address":"2200 Hilton Rd",
    "sg:city":"Ferndale",
    "sg:classifiers":[
        {
            "category":"Building & Trades",
            "subcategory":"Construction",
            "type":"Services"
        }
    ],
    "sg:phone":"+1 248 543 8453",
    "sg:postcode":"48220",
    "sg:province":"MI",
    "sg:tags":[
        "tile",
        "dealer"
    ],
    "wof:name":"Quality Tile Inc",
    "wof:placetype":"venue"
},
  "geometry": {"coordinates":[-83.12319599999999,42.46564],"type":"Point"}
}