{
  "type": "Feature",
  "properties": {
    "iso:country":"US",
    "sg:address":"9554 Pickwick Cir E",
    "sg:city":"Taylor",
    "sg:classifiers":[
        {
            "category":"Food & Beverages",
            "subcategory":"Specialty",
            "type":"Retail Goods"
        }
    ],
    "sg:phone":"+1 313 291 2465",
    "sg:postcode":"48180",
    "sg:province":"MI",
    "sg:tags":[
        "water",
        "bottled"
    ],
    "wof:name":"Living Water Inc",
    "wof:placetype":"venue"
},
  "geometry": {"coordinates":[-83.234154,42.241089],"type":"Point"}
}