{
  "type": "Feature",
  "properties": {
    "iso:country":"US",
    "sg:address":"9691 Secor Rd",
    "sg:city":"Temperance",
    "sg:classifiers":[
        {
            "category":"Building & Trades",
            "subcategory":"Construction",
            "type":"Services"
        }
    ],
    "sg:phone":"+1 734 854 3683",
    "sg:postcode":"48182",
    "sg:province":"MI",
    "sg:tags":[
        "home",
        "improvement"
    ],
    "wof:name":"Kevin Fraley Builder/Rmdlng",
    "wof:placetype":"venue"
},
  "geometry": {"coordinates":[-83.627488,41.790451],"type":"Point"}
}