{
  "type": "Feature",
  "properties": {
    "iso:country":"US",
    "sg:address":"3597 W Beard Rd",
    "sg:city":"Perry",
    "sg:classifiers":[
        {
            "category":"Freight",
            "type":"Transportation"
        }
    ],
    "sg:phone":"+1 517 625 1864",
    "sg:postcode":"48872",
    "sg:province":"MI",
    "sg:tags":[
        "operator",
        "local",
        "trucking"
    ],
    "wof:name":"Bradley L Vogel Trucking",
    "wof:placetype":"venue"
},
  "geometry": {"coordinates":[-84.247062,42.805044],"type":"Point"}
}