{
  "type": "Feature",
  "properties": {
    "iso:country":"US",
    "sg:address":"25010 Ford Rd",
    "sg:city":"Dearborn Heights",
    "sg:classifiers":[
        {
            "category":"Banks & Credit Unions",
            "subcategory":"Bank",
            "type":"Services"
        }
    ],
    "sg:phone":"+1 313 359 3199",
    "sg:postcode":"48127",
    "sg:province":"MI",
    "sg:tags":[
        "broker",
        "mortgage"
    ],
    "wof:name":"Regional Financial Group Inc",
    "wof:placetype":"venue"
},
  "geometry": {"coordinates":[-83.28334099999999,42.326842],"type":"Point"}
}