{
  "type": "Feature",
  "properties": {
    "iso:country":"US",
    "sg:address":"5963 Bunker Hill Rd",
    "sg:city":"Williamsburg",
    "sg:classifiers":[
        {
            "category":"Building & Trades",
            "subcategory":"Construction",
            "type":"Services"
        }
    ],
    "sg:phone":"+1 231 938 7011",
    "sg:postcode":"49690",
    "sg:province":"MI",
    "sg:tags":[
        "home",
        "builder"
    ],
    "wof:name":"Plamondon & Plamondon",
    "wof:placetype":"venue"
},
  "geometry": {"coordinates":[-85.45638099999999,44.756195],"type":"Point"}
}