{
  "type": "Feature",
  "properties": {
    "iso:country":"US",
    "sg:address":"25700 W 7 Mile Rd",
    "sg:city":"Redford",
    "sg:classifiers":[
        {
            "category":"Shopping",
            "subcategory":"Pharmacy",
            "type":"Retail Goods"
        }
    ],
    "sg:phone":"+1 313 592 1202",
    "sg:postcode":"48240",
    "sg:province":"MI",
    "sg:tags":[
        "drugstore"
    ],
    "sg:website":"www.cvs.com",
    "wof:name":"Cvs Pharmacy",
    "wof:placetype":"venue"
},
  "geometry": {"coordinates":[-83.295799,42.428398],"type":"Point"}
}