{
  "type": "Feature",
  "properties": {
    "iso:country":"US",
    "sg:address":"1180 W Columbia Ave",
    "sg:city":"Battle Creek",
    "sg:classifiers":[
        {
            "category":"Retail",
            "subcategory":"Auto Repair",
            "type":"Services"
        }
    ],
    "sg:phone":"+1 269 969 3082",
    "sg:postcode":"49015",
    "sg:province":"MI",
    "sg:tags":[
        "body",
        "automobile",
        "painting"
    ],
    "wof:name":"Painters Equipment & Supply Co",
    "wof:placetype":"venue"
},
  "geometry": {"coordinates":[-85.22045799999999,42.297587],"type":"Point"}
}