{
  "type": "Feature",
  "properties": {
    "iso:country":"US",
    "sg:address":"790 Hoague Rd",
    "sg:city":"Manistee",
    "sg:classifiers":[
        {
            "category":"Professional",
            "subcategory":"Business Services",
            "type":"Services"
        }
    ],
    "sg:phone":"+1 231 723 3237",
    "sg:postcode":"49660",
    "sg:province":"MI",
    "wof:name":"Rvm Solutions Inc",
    "wof:placetype":"venue"
},
  "geometry": {"coordinates":[-86.30910900000001,44.152654],"type":"Point"}
}