{
  "type": "Feature",
  "properties": {
    "iso:country":"US",
    "sg:address":"207 S Main St",
    "sg:city":"Ann Arbor",
    "sg:classifiers":[
        {
            "category":"Recreation",
            "type":"Entertainment"
        }
    ],
    "sg:phone":"+1 734 741 7219",
    "sg:postcode":"48104",
    "sg:province":"MI",
    "wof:name":"Andrie C Gulvezan",
    "wof:placetype":"venue"
},
  "geometry": {"coordinates":[-83.748487,42.27964],"type":"Point"}
}