{
  "type": "Feature",
  "properties": {
    "iso:country":"US",
    "sg:address":"1441 W Chicago Blvd",
    "sg:city":"Tecumseh",
    "sg:classifiers":[
        {
            "category":"Restaurant",
            "type":"Food & Drink"
        }
    ],
    "sg:menulink":"http://www.allmenus.com/mi/tecumseh/67822-foxs-pizza-den/menu/",
    "sg:phone":"+1 517 423 7000",
    "sg:postcode":"49286",
    "sg:province":"MI",
    "sg:tags":[
        "american",
        "pizza"
    ],
    "wof:name":"Fox's Pizza Den",
    "wof:placetype":"venue"
},
  "geometry": {"coordinates":[-83.96646200000001,42.006499],"type":"Point"}
}