{
  "type": "Feature",
  "properties": {
    "iso:country":"US",
    "sg:address":"6709 Chicago Rd",
    "sg:city":"Warren",
    "sg:classifiers":[
        {
            "category":"Wholesale",
            "subcategory":"Hardware",
            "type":"Manufacturing & Wholesale Goods"
        }
    ],
    "sg:phone":"+1 586 264 0410",
    "sg:postcode":"48092",
    "sg:province":"MI",
    "sg:tags":[
        "nut",
        "bolt"
    ],
    "sg:website":"www.metricsunlimited.com",
    "wof:name":"Metrics Unlimited Inc",
    "wof:placetype":"venue"
},
  "geometry": {"coordinates":[-83.037567,42.524505],"type":"Point"}
}