{
  "type": "Feature",
  "properties": {
    "iso:country":"US",
    "sg:address":"2181 Sharon Hollow Rd",
    "sg:city":"Grass Lake",
    "sg:classifiers":[
        {
            "category":"Home & Garden",
            "subcategory":"Garden Supply",
            "type":"Retail Goods"
        }
    ],
    "sg:phone":"+1 517 522 5898",
    "sg:postcode":"49240",
    "sg:province":"MI",
    "sg:tags":[
        "nurseryman"
    ],
    "wof:name":"Taylor & Sons Nursery",
    "wof:placetype":"venue"
},
  "geometry": {"coordinates":[-84.093526,42.231667],"type":"Point"}
}