{
  "type": "Feature",
  "properties": {
    "iso:country":"US",
    "sg:address":"224 McCormick St",
    "sg:city":"Williamston",
    "sg:classifiers":[
        {
            "category":"Building & Trades",
            "subcategory":"Construction",
            "type":"Services"
        }
    ],
    "sg:phone":"+1 517 655 6039",
    "sg:postcode":"48895",
    "sg:province":"MI",
    "sg:tags":[
        "contractor"
    ],
    "wof:name":"Story Roofing & Construction",
    "wof:placetype":"venue"
},
  "geometry": {"coordinates":[-84.29237999999999,42.690064],"type":"Point"}
}