{
  "type": "Feature",
  "properties": {
    "iso:country":"US",
    "sg:address":"69170 State Hwy 62",
    "sg:city":"Edwardsburg",
    "sg:classifiers":[
        {
            "category":"Insurance",
            "subcategory":"Insurance Agent",
            "type":"Services"
        }
    ],
    "sg:phone":"+1 269 663 7015",
    "sg:postcode":"49112",
    "sg:province":"MI",
    "wof:name":"State Farm Insurance",
    "wof:placetype":"venue"
},
  "geometry": {"coordinates":[-86.081267,41.79533],"type":"Point"}
}