{
  "type": "Feature",
  "properties": {
    "iso:country":"US",
    "sg:address":"2121 City Natl Bk Bg",
    "sg:city":"Detroit",
    "sg:classifiers":[
        {
            "category":"Professional",
            "subcategory":"Lawyer & Legal Services",
            "type":"Services"
        }
    ],
    "sg:phone":"+1 313 964 5010",
    "sg:postcode":"48201",
    "sg:province":"MI",
    "sg:tags":[
        "personal",
        "injury"
    ],
    "wof:name":"Rader Ronald Atty",
    "wof:placetype":"venue"
},
  "geometry": {"coordinates":[-83.058899,42.3489],"type":"Point"}
}