{
  "type": "Feature",
  "properties": {
    "iso:country":"US",
    "sg:address":"645 E Big Beaver Rd",
    "sg:city":"Troy",
    "sg:classifiers":[
        {
            "category":"Restaurant",
            "type":"Food & Drink"
        }
    ],
    "sg:phone":"+1 248 680 0066",
    "sg:postcode":"48083",
    "sg:province":"MI",
    "sg:tags":[
        "traditional",
        "american"
    ],
    "sg:website":"www.bigbeavertavern.com",
    "wof:name":"Big Beaver Tavern",
    "wof:placetype":"venue"
},
  "geometry": {"coordinates":[-83.135256,42.562953],"type":"Point"}
}