{
  "type": "Feature",
  "properties": {
    "iso:country":"US",
    "sg:address":"2042 S 40th St",
    "sg:city":"Climax",
    "sg:classifiers":[
        {
            "category":"Professional",
            "type":"Services"
        }
    ],
    "sg:phone":"+1 269 746 5323",
    "sg:postcode":"49034",
    "sg:province":"MI",
    "sg:tags":[
        "establishment"
    ],
    "wof:name":"Kalamazoo Valley Group",
    "wof:placetype":"venue"
},
  "geometry": {"coordinates":[-85.375951,42.2702],"type":"Point"}
}