{
  "type": "Feature",
  "properties": {
    "iso:country":"US",
    "sg:address":"1522 Hudson Rd",
    "sg:city":"Hillsdale",
    "sg:classifiers":[
        {
            "category":"Professional",
            "subcategory":"Accounting & Tax Preparation",
            "type":"Services"
        }
    ],
    "sg:phone":"+1 517 439 1585",
    "sg:postcode":"49242",
    "sg:province":"MI",
    "sg:tags":[
        "accountant"
    ],
    "wof:name":"Lambert & Bildner",
    "wof:placetype":"venue"
},
  "geometry": {"coordinates":[-84.62154,41.900882],"type":"Point"}
}