{
  "type": "Feature",
  "properties": {
    "iso:country":"US",
    "sg:address":"23801 Gratiot Ave",
    "sg:city":"Eastpointe",
    "sg:classifiers":[
        {
            "category":"Wholesale",
            "subcategory":"Machinery & Supplies",
            "type":"Manufacturing & Wholesale Goods"
        }
    ],
    "sg:phone":"+1 586 447 9902",
    "sg:postcode":"48021",
    "sg:province":"MI",
    "wof:name":"Multi-Tech Equipment",
    "wof:placetype":"venue"
},
  "geometry": {"coordinates":[-82.95446,42.470535],"type":"Point"}
}