{
  "type": "Feature",
  "properties": {
    "iso:country":"US",
    "sg:address":"17601 W Warren Ave",
    "sg:city":"Detroit",
    "sg:classifiers":[
        {
            "category":"Shopping",
            "subcategory":"Mobile Phones",
            "type":"Retail Goods"
        }
    ],
    "sg:phone":"+1 313 584 3000",
    "sg:postcode":"48228",
    "sg:province":"MI",
    "wof:name":"Zarcom Communications",
    "wof:placetype":"venue"
},
  "geometry": {"coordinates":[-83.213504,42.343132],"type":"Point"}
}