{
  "type": "Feature",
  "properties": {
    "iso:country":"US",
    "sg:address":"2116 Deer Lake Ave",
    "sg:city":"Ishpeming",
    "sg:classifiers":[
        {
            "category":"Building & Trades",
            "subcategory":"Construction",
            "type":"Services"
        }
    ],
    "sg:phone":"+1 906 486 9959",
    "sg:postcode":"49849",
    "sg:province":"MI",
    "sg:tags":[
        "general",
        "contractor"
    ],
    "wof:name":"Pajula & Maki General Contrs",
    "wof:placetype":"venue"
},
  "geometry": {"coordinates":[-87.669166,46.512684],"type":"Point"}
}