{
  "type": "Feature",
  "properties": {
    "iso:country":"US",
    "sg:address":"438 7th St",
    "sg:city":"Traverse City",
    "sg:classifiers":[
        {
            "category":"Professional",
            "type":"Services"
        }
    ],
    "sg:phone":"+1 231 929 4528",
    "sg:postcode":"49684",
    "sg:province":"MI",
    "wof:name":"Absolute Home Service",
    "wof:placetype":"venue"
},
  "geometry": {"coordinates":[-85.629009,44.76056],"type":"Point"}
}