{
  "type": "Feature",
  "properties": {
    "iso:country":"US",
    "sg:address":"1500 W Washington St",
    "sg:city":"Marquette",
    "sg:classifiers":[
        {
            "category":"Professional",
            "subcategory":"Accounting & Tax Preparation",
            "type":"Services"
        }
    ],
    "sg:phone":"+1 906 226 7771",
    "sg:postcode":"49855",
    "sg:province":"MI",
    "sg:tags":[
        "accountant"
    ],
    "wof:name":"Northern Tax & Accounting",
    "wof:placetype":"venue"
},
  "geometry": {"coordinates":[-87.425966,46.546187],"type":"Point"}
}