{
  "type": "Feature",
  "properties": {
    "iso:country":"US",
    "sg:address":"1113 W Warren Ave",
    "sg:city":"Detroit",
    "sg:classifiers":[
        {
            "category":"Restaurant",
            "type":"Food & Drink"
        }
    ],
    "sg:menulink":"http://www.allmenus.com/mi/detroit/56867-subway/menu/",
    "sg:phone":"+1 313 832 3812",
    "sg:postcode":"48201",
    "sg:province":"MI",
    "sg:tags":[
        "american",
        "sandwich"
    ],
    "wof:name":"Subway",
    "wof:placetype":"venue"
},
  "geometry": {"coordinates":[-83.074005,42.35356],"type":"Point"}
}