{
  "type": "Feature",
  "properties": {
    "iso:country":"US",
    "sg:address":"110 E Main St",
    "sg:city":"Stockbridge",
    "sg:classifiers":[
        {
            "category":"Restaurant",
            "type":"Food & Drink"
        }
    ],
    "sg:phone":"+1 517 851 8479",
    "sg:postcode":"49285",
    "sg:province":"MI",
    "wof:name":"Barbie's Country Restaurant",
    "wof:placetype":"venue"
},
  "geometry": {"coordinates":[-84.17903099999999,42.451316],"type":"Point"}
}