{
  "type": "Feature",
  "properties": {
    "iso:country":"US",
    "sg:address":"10000 Wayne Rd",
    "sg:city":"Romulus",
    "sg:classifiers":[
        {
            "category":"Building & Trades",
            "subcategory":"Construction",
            "type":"Services"
        }
    ],
    "sg:phone":"+1 734 955 9225",
    "sg:postcode":"48174",
    "sg:province":"MI",
    "sg:tags":[
        "contractor"
    ],
    "wof:name":"Royale Group LLC",
    "wof:placetype":"venue"
},
  "geometry": {"coordinates":[-83.385812,42.231395],"type":"Point"}
}