{
  "type": "Feature",
  "properties": {
    "iso:country":"US",
    "sg:address":"640 Michigan Ave",
    "sg:city":"Holland",
    "sg:classifiers":[
        {
            "category":"Health Services",
            "subcategory":"Doctor",
            "type":"Services"
        }
    ],
    "sg:phone":"+1 616 394 3748",
    "sg:postcode":"49423",
    "sg:province":"MI",
    "sg:tags":[
        "medical"
    ],
    "wof:name":"Kraker Steven K MD",
    "wof:placetype":"venue"
},
  "geometry": {"coordinates":[-86.113587,42.773421],"type":"Point"}
}