{
  "type": "Feature",
  "properties": {
    "iso:country":"US",
    "sg:address":"1225 Jewett Ave",
    "sg:city":"Ann Arbor",
    "sg:classifiers":[
        {
            "category":"Retail",
            "subcategory":"Auto Repair",
            "type":"Services"
        }
    ],
    "sg:phone":"+1 734 665 9707",
    "sg:postcode":"48104",
    "sg:province":"MI",
    "sg:tags":[
        "automotive",
        "general"
    ],
    "wof:name":"Professional Auto Technicians",
    "wof:placetype":"venue"
},
  "geometry": {"coordinates":[-83.72918799999999,42.254197],"type":"Point"}
}