{
  "type": "Feature",
  "properties": {
    "iso:country":"US",
    "sg:address":"6485 Lakeshore St",
    "sg:city":"West Bloomfield",
    "sg:classifiers":[
        {
            "category":"Professional",
            "subcategory":"Business Services",
            "type":"Services"
        }
    ],
    "sg:phone":"+1 248 706 3554",
    "sg:postcode":"48323",
    "sg:province":"MI",
    "wof:name":"A Precise Home Inspection Inc",
    "wof:placetype":"venue"
},
  "geometry": {"coordinates":[-83.41099699999999,42.570451],"type":"Point"}
}