{
  "type": "Feature",
  "properties": {
    "iso:country":"US",
    "sg:address":"306 W Flint St",
    "sg:city":"Davison",
    "sg:classifiers":[
        {
            "category":"Health Services",
            "subcategory":"Hospital",
            "type":"Services"
        },
        {
            "category":"Banks & Credit Unions",
            "subcategory":"Investment Brokerage",
            "type":"Services"
        },
        {
            "category":"Insurance",
            "subcategory":"Hazard Insurance",
            "type":"Services"
        }
    ],
    "sg:phone":"+1 810 653 4844",
    "sg:postcode":"48423",
    "sg:province":"MI",
    "sg:tags":[
        "hospitalization",
        "business",
        "resume",
        "medical",
        "commercial",
        "agent",
        "surgical",
        "plan"
    ],
    "wof:name":"Stewart & Associates/Valley Insurance Agency",
    "wof:placetype":"venue"
},
  "geometry": {"coordinates":[-83.521551,43.034625],"type":"Point"}
}