{
  "type": "Feature",
  "properties": {
    "iso:country":"US",
    "sg:address":"89 Bridge St",
    "sg:city":"Saranac",
    "sg:classifiers":[
        {
            "category":"Social Services",
            "type":"Services"
        }
    ],
    "sg:phone":"+1 616 642 0992",
    "sg:postcode":"48881",
    "sg:province":"MI",
    "sg:tags":[
        "youth",
        "organization",
        "center"
    ],
    "wof:name":"Saranac Youth Ctr",
    "wof:placetype":"venue"
},
  "geometry": {"coordinates":[-85.213302,42.929335],"type":"Point"}
}