{
  "type": "Feature",
  "properties": {
    "iso:country":"US",
    "sg:address":"414 E Hudson Ave",
    "sg:city":"Royal Oak",
    "sg:classifiers":[
        {
            "category":"Freight",
            "type":"Transportation"
        },
        {
            "category":"Retail",
            "subcategory":"Auto Rental",
            "type":"Services"
        }
    ],
    "sg:phone":"+1 248 541 4020",
    "sg:postcode":"48067",
    "sg:province":"MI",
    "sg:tags":[
        "truck",
        "up",
        "recyclables"
    ],
    "sg:website":"www.royaloakrecycling.com",
    "wof:name":"Royal Oak Waste Paper & Met Co",
    "wof:placetype":"venue"
},
  "geometry": {"coordinates":[-83.140027,42.481594],"type":"Point"}
}