{
  "type": "Feature",
  "properties": {
    "iso:country":"US",
    "sg:address":"21100 Penn St Ste 2709",
    "sg:city":"Taylor",
    "sg:classifiers":[
        {
            "category":"Home & Garden",
            "subcategory":"Hardware",
            "type":"Retail Goods"
        },
        {
            "category":"Home & Garden",
            "subcategory":"Building Materials",
            "type":"Retail Goods"
        }
    ],
    "sg:phone":"+1 734 374 1901",
    "sg:postcode":"48180",
    "sg:province":"MI",
    "sg:tags":[
        "store",
        "supply"
    ],
    "sg:website":"www.homedepot.com",
    "wof:name":"The Home Depot",
    "wof:placetype":"venue"
},
  "geometry": {"coordinates":[-83.241033,42.20026],"type":"Point"}
}