{
  "type": "Feature",
  "properties": {
    "iso:country":"US",
    "sg:address":"5285 Summit St",
    "sg:city":"Flint",
    "sg:classifiers":[
        {
            "category":"Professional",
            "type":"Services"
        }
    ],
    "sg:phone":"+1 810 591 4731",
    "sg:postcode":"48505",
    "sg:province":"MI",
    "wof:name":"Northgate Support Svc",
    "wof:placetype":"venue"
},
  "geometry": {"coordinates":[-83.69913,43.083669],"type":"Point"}
}