{
  "type": "Feature",
  "properties": {
    "iso:country":"US",
    "sg:address":"26740 Lathrup Blvd",
    "sg:city":"Lathrup Village",
    "sg:classifiers":[
        {
            "category":"Insurance",
            "subcategory":"Insurance Agent",
            "type":"Services"
        },
        {
            "category":"Professional",
            "subcategory":"Credit Reporting & Collection",
            "type":"Services"
        }
    ],
    "sg:phone":"+1 248 557 8398",
    "sg:postcode":"48076",
    "sg:province":"MI",
    "sg:tags":[
        "adjuster"
    ],
    "wof:name":"Continental Adjusting Service",
    "wof:placetype":"venue"
},
  "geometry": {"coordinates":[-83.218166,42.486145],"type":"Point"}
}