{
  "type": "Feature",
  "properties": {
    "iso:country":"US",
    "sg:address":"9840 Bellevue Rd",
    "sg:city":"Battle Creek",
    "sg:classifiers":[
        {
            "category":"Wholesale",
            "subcategory":"Vending Machines",
            "type":"Manufacturing & Wholesale Goods"
        }
    ],
    "sg:phone":"+1 269 965 7887",
    "sg:postcode":"49014",
    "sg:province":"MI",
    "wof:name":"Cereal City Snacks Inc",
    "wof:placetype":"venue"
},
  "geometry": {"coordinates":[-85.106132,42.363112],"type":"Point"}
}