{
  "type": "Feature",
  "properties": {
    "iso:country":"US",
    "sg:address":"883 Sumpter Rd",
    "sg:city":"Belleville",
    "sg:classifiers":[
        {
            "category":"Restaurant",
            "type":"Food & Drink"
        }
    ],
    "sg:menulink":"http://www.allmenus.com/mi/belleville/26341-cottage-inn-pizza/menu/",
    "sg:phone":"+1 734 699 1200",
    "sg:postcode":"48111",
    "sg:province":"MI",
    "sg:tags":[
        "wrap",
        "american",
        "sandwich",
        "pizza"
    ],
    "wof:name":"Cottage Inn Pizza",
    "wof:placetype":"venue"
},
  "geometry": {"coordinates":[-83.484354,42.194486],"type":"Point"}
}