{
  "type": "Feature",
  "properties": {
    "iso:country":"US",
    "sg:address":"1077 US Hwy 27 Bus",
    "sg:city":"St Johns",
    "sg:classifiers":[
        {
            "category":"Shopping",
            "subcategory":"Gifts & Souvenirs",
            "type":"Retail Goods"
        }
    ],
    "sg:phone":"+1 989 224 9396",
    "sg:postcode":"48879",
    "sg:province":"MI",
    "sg:tags":[
        "shop"
    ],
    "wof:name":"Haddad's Gifts-Southpoint",
    "wof:placetype":"venue"
},
  "geometry": {"coordinates":[-84.551924,43.009027],"type":"Point"}
}