{
  "type": "Feature",
  "properties": {
    "iso:country":"US",
    "sg:address":"50290 Gratiot Ave",
    "sg:city":"Chesterfield",
    "sg:classifiers":[
        {
            "category":"Shopping",
            "subcategory":"Pharmacy",
            "type":"Retail Goods"
        }
    ],
    "sg:phone":"+1 586 949 6110",
    "sg:postcode":"48051",
    "sg:province":"MI",
    "wof:name":"Rite Aid Pharmacy",
    "wof:placetype":"venue"
},
  "geometry": {"coordinates":[-82.838157,42.668171],"type":"Point"}
}