{
  "type": "Feature",
  "properties": {
    "iso:country":"US",
    "sg:address":"4664 Havana Ave SW",
    "sg:city":"Grand Rapids",
    "sg:classifiers":[
        {
            "category":"Shopping",
            "subcategory":"Stationery & Office Supplies",
            "type":"Retail Goods"
        }
    ],
    "sg:phone":"+1 616 538 3416",
    "sg:postcode":"49509",
    "sg:province":"MI",
    "sg:tags":[
        "stationer"
    ],
    "wof:name":"Luanne's Creations",
    "wof:placetype":"venue"
},
  "geometry": {"coordinates":[-85.69991400000001,42.878516],"type":"Point"}
}