{
  "type": "Feature",
  "properties": {
    "iso:country":"US",
    "sg:address":"2555 Benzie Hwy",
    "sg:city":"Benzonia",
    "sg:classifiers":[
        {
            "category":"Freight",
            "type":"Transportation"
        }
    ],
    "sg:phone":"+1 231 882 0077",
    "sg:postcode":"49616",
    "sg:province":"MI",
    "sg:tags":[
        "commercial",
        "storage"
    ],
    "wof:name":"R Storage",
    "wof:placetype":"venue"
},
  "geometry": {"coordinates":[-86.09922299999999,44.591478],"type":"Point"}
}