{
  "type": "Feature",
  "properties": {
    "iso:country":"US",
    "sg:address":"2225 Pine Ridge Dr",
    "sg:city":"Jenison",
    "sg:classifiers":[
        {
            "category":"Manufacturing",
            "subcategory":"Tools & Machinery",
            "type":"Manufacturing & Wholesale Goods"
        }
    ],
    "sg:phone":"+1 616 662 5471",
    "sg:postcode":"49428",
    "sg:province":"MI",
    "sg:tags":[
        "equipment",
        "system",
        "automation"
    ],
    "wof:name":"Fabrication Technologies",
    "wof:placetype":"venue"
},
  "geometry": {"coordinates":[-85.836461,42.891781],"type":"Point"}
}