{
  "type": "Feature",
  "properties": {
    "iso:country":"US",
    "sg:address":"10195 Dymond Rd",
    "sg:city":"Honor",
    "sg:classifiers":[
        {
            "category":"Professional",
            "type":"Services"
        }
    ],
    "sg:phone":"+1 231 325 5923",
    "sg:postcode":"49640",
    "sg:province":"MI",
    "sg:tags":[
        "establishment"
    ],
    "wof:name":"Hortsystems Inc",
    "wof:placetype":"venue"
},
  "geometry": {"coordinates":[-86.03304799999999,44.725744],"type":"Point"}
}