{
  "type": "Feature",
  "properties": {
    "iso:country":"US",
    "sg:address":"4265 E 10 Mile Rd",
    "sg:city":"Warren",
    "sg:classifiers":[
        {
            "category":"Health Services",
            "subcategory":"Doctor",
            "type":"Services"
        }
    ],
    "sg:phone":"+1 586 757 2221",
    "sg:postcode":"48091",
    "sg:province":"MI",
    "sg:tags":[
        "dentist"
    ],
    "wof:name":"Baltarowich Maria DDS PC",
    "wof:placetype":"venue"
},
  "geometry": {"coordinates":[-83.063103,42.476898],"type":"Point"}
}