{
  "type": "Feature",
  "properties": {
    "iso:country":"US",
    "sg:address":"25740 Arden Park Dr",
    "sg:city":"Farmington Hills",
    "sg:classifiers":[
        {
            "category":"Personal",
            "type":"Services"
        }
    ],
    "sg:phone":"+1 248 615 9778",
    "sg:postcode":"48336",
    "sg:province":"MI",
    "sg:tags":[
        "doctor"
    ],
    "wof:name":"Image Therapeutic Care Llc",
    "wof:placetype":"venue"
},
  "geometry": {"coordinates":[-83.322197,42.483601],"type":"Point"}
}