{
  "type": "Feature",
  "properties": {
    "iso:country":"US",
    "sg:address":"3140 N Monroe St",
    "sg:city":"Monroe",
    "sg:classifiers":[
        {
            "category":"Freight",
            "type":"Transportation"
        }
    ],
    "sg:phone":"+1 734 240 0672",
    "sg:postcode":"48162",
    "sg:province":"MI",
    "sg:tags":[
        "broker",
        "trucking"
    ],
    "wof:name":"Motor City Transport Inc",
    "wof:placetype":"venue"
},
  "geometry": {"coordinates":[-83.378345,41.956517],"type":"Point"}
}