{
  "type": "Feature",
  "properties": {
    "iso:country":"US",
    "sg:address":"217 S Main St",
    "sg:city":"Perry",
    "sg:classifiers":[
        {
            "category":"Organizations",
            "subcategory":"Religious Organization",
            "type":"Services"
        }
    ],
    "sg:phone":"+1 517 625 3123",
    "sg:postcode":"48872",
    "sg:province":"MI",
    "sg:tags":[
        "church"
    ],
    "wof:name":"Perry Baptist Church",
    "wof:placetype":"venue"
},
  "geometry": {"coordinates":[-84.218895,42.822999],"type":"Point"}
}