{
  "type": "Feature",
  "properties": {
    "iso:country":"US",
    "sg:address":"2222 Pine Grove Ct",
    "sg:city":"Ann Arbor",
    "sg:classifiers":[
        {
            "category":"Professional",
            "subcategory":"Management & Consulting",
            "type":"Services"
        }
    ],
    "sg:phone":"+1 734 662 3846",
    "sg:postcode":"48103",
    "sg:province":"MI",
    "wof:name":"Jls Associates",
    "wof:placetype":"venue"
},
  "geometry": {"coordinates":[-83.76391,42.301879],"type":"Point"}
}