{
  "type": "Feature",
  "properties": {
    "iso:country":"US",
    "sg:address":"19310 Conant St",
    "sg:city":"Detroit",
    "sg:classifiers":[
        {
            "category":"Food & Beverages",
            "subcategory":"Groceries & Convenience Stores",
            "type":"Retail Goods"
        }
    ],
    "sg:phone":"+1 313 368 1631",
    "sg:postcode":"48234",
    "sg:province":"MI",
    "wof:name":"Dairy Mart",
    "wof:placetype":"venue"
},
  "geometry": {"coordinates":[-83.07544,42.435684],"type":"Point"}
}