{
  "type": "Feature",
  "properties": {
    "iso:country":"US",
    "sg:address":"7204 Dur Moll Ave",
    "sg:city":"Shelby Twp",
    "sg:classifiers":[
        {
            "category":"Building & Trades",
            "subcategory":"Construction",
            "type":"Services"
        }
    ],
    "sg:phone":"+1 586 997 0867",
    "sg:postcode":"48317",
    "sg:province":"MI",
    "sg:tags":[
        "sewer",
        "contractor"
    ],
    "wof:name":"Dylans Sewer & Drain",
    "wof:placetype":"venue"
},
  "geometry": {"coordinates":[-83.038055,42.644658],"type":"Point"}
}