{
  "type": "Feature",
  "properties": {
    "iso:country":"US",
    "sg:address":"28 Tracie Ln",
    "sg:city":"Marquette",
    "sg:classifiers":[
        {
            "category":"Building & Trades",
            "subcategory":"Electrical",
            "type":"Services"
        }
    ],
    "sg:phone":"+1 906 249 5106",
    "sg:postcode":"49855",
    "sg:province":"MI",
    "sg:tags":[
        "electric",
        "contractor"
    ],
    "wof:name":"Rozek Electric",
    "wof:placetype":"venue"
},
  "geometry": {"coordinates":[-87.36973399999999,46.481477],"type":"Point"}
}