{
  "type": "Feature",
  "properties": {
    "iso:country":"US",
    "sg:address":"14001 Fenkell St",
    "sg:city":"Detroit",
    "sg:classifiers":[
        {
            "category":"Restaurant",
            "type":"Food & Drink"
        }
    ],
    "sg:phone":"+1 313 836 0001",
    "sg:postcode":"48227",
    "sg:province":"MI",
    "sg:tags":[
        "barbeque"
    ],
    "wof:name":"Lee's Texas Style Bar-B-Q",
    "wof:placetype":"venue"
},
  "geometry": {"coordinates":[-83.182602,42.401901],"type":"Point"}
}