{
  "type": "Feature",
  "properties": {
    "iso:country":"US",
    "sg:address":"4511 Broadmoor Ave SE",
    "sg:city":"Grand Rapids",
    "sg:classifiers":[
        {
            "category":"Freight",
            "type":"Transportation"
        }
    ],
    "sg:phone":"+1 616 554 1813",
    "sg:postcode":"49512",
    "sg:province":"MI",
    "wof:name":"Expeditors Of Washington",
    "wof:placetype":"venue"
},
  "geometry": {"coordinates":[-85.564913,42.882358],"type":"Point"}
}