{
  "type": "Feature",
  "properties": {
    "iso:country":"US",
    "sg:address":"15075 US Hwy 131",
    "sg:city":"Schoolcraft",
    "sg:classifiers":[
        {
            "category":"Wholesale",
            "subcategory":"Machinery & Supplies",
            "type":"Manufacturing & Wholesale Goods"
        }
    ],
    "sg:phone":"+1 269 679 3110",
    "sg:postcode":"49087",
    "sg:province":"MI",
    "sg:tags":[
        "equipment",
        "welding"
    ],
    "wof:name":"Miller Welding Supply South",
    "wof:placetype":"venue"
},
  "geometry": {"coordinates":[-85.63665,42.097853],"type":"Point"}
}