{
  "type": "Feature",
  "properties": {
    "iso:country":"US",
    "sg:address":"6315 Sashabaw Rd",
    "sg:city":"Clarkston",
    "sg:classifiers":[
        {
            "category":"Utilities",
            "subcategory":"Mobile Phone",
            "type":"Services"
        },
        {
            "category":"Coffee & Tea",
            "type":"Food & Drink"
        }
    ],
    "sg:phone":"+1 248 625 5066",
    "sg:postcode":"48346",
    "sg:province":"MI",
    "sg:tags":[
        "restaurant",
        "brewing",
        "espresso",
        "hotspot",
        "device",
        "wi-fi"
    ],
    "sg:website":"http://www.cariboucoffee.com",
    "wof:name":"Caribou Coffee Company",
    "wof:placetype":"venue"
},
  "geometry": {"coordinates":[-83.379481,42.730094],"type":"Point"}
}