{
  "type": "Feature",
  "properties": {
    "iso:country":"US",
    "sg:address":"909 S Franklin Ave",
    "sg:city":"Flint",
    "sg:classifiers":[
        {
            "category":"Banks & Credit Unions",
            "subcategory":"Financial Services",
            "type":"Services"
        }
    ],
    "sg:phone":"+1 810 239 7010",
    "sg:postcode":"48503",
    "sg:province":"MI",
    "sg:tags":[
        "trust",
        "management"
    ],
    "wof:name":"S J Moss Trust",
    "wof:placetype":"venue"
},
  "geometry": {"coordinates":[-83.66486,43.016271],"type":"Point"}
}