{
  "type": "Feature",
  "properties": {
    "iso:country":"US",
    "sg:address":"811 Adams St",
    "sg:city":"Bay City",
    "sg:classifiers":[
        {
            "category":"Shopping",
            "subcategory":"Clothing, Apparel, & Fashions",
            "type":"Retail Goods"
        }
    ],
    "sg:phone":"+1 989 893 6071",
    "sg:postcode":"48708",
    "sg:province":"MI",
    "sg:tags":[
        "dancing",
        "supply"
    ],
    "wof:name":"Dancer's Shoppe",
    "wof:placetype":"venue"
},
  "geometry": {"coordinates":[-83.886594,43.598907],"type":"Point"}
}