{
  "type": "Feature",
  "properties": {
    "iso:country":"US",
    "sg:address":"36636 Lansbury Ln",
    "sg:city":"Farmington",
    "sg:classifiers":[
        {
            "category":"Shopping",
            "subcategory":"Gifts & Souvenirs",
            "type":"Retail Goods"
        }
    ],
    "sg:phone":"+1 248 477 2358",
    "sg:postcode":"48335",
    "sg:province":"MI",
    "wof:name":"Wild Card Enterprises",
    "wof:placetype":"venue"
},
  "geometry": {"coordinates":[-83.40817,42.4633],"type":"Point"}
}