{
  "type": "Feature",
  "properties": {
    "iso:country":"US",
    "sg:address":"20732 Negaunee St",
    "sg:city":"Southfield",
    "sg:classifiers":[
        {
            "category":"Manufacturing",
            "subcategory":"Printing",
            "type":"Manufacturing & Wholesale Goods"
        }
    ],
    "sg:phone":"+1 248 350 8230",
    "sg:postcode":"48033",
    "sg:province":"MI",
    "sg:tags":[
        "printer"
    ],
    "sg:website":"www.mwprinting.com",
    "wof:name":"Michigan Wholesale Printing",
    "wof:placetype":"venue"
},
  "geometry": {"coordinates":[-83.31317,42.443906],"type":"Point"}
}