{
  "type": "Feature",
  "properties": {
    "iso:country":"US",
    "sg:address":"114 S Main St",
    "sg:city":"Mount Pleasant",
    "sg:classifiers":[
        {
            "category":"Shopping",
            "subcategory":"Used Merchandise",
            "type":"Retail Goods"
        }
    ],
    "sg:phone":"+1 989 773 4579",
    "sg:postcode":"48858",
    "sg:province":"MI",
    "wof:name":"Bibliophilia",
    "wof:placetype":"venue"
},
  "geometry": {"coordinates":[-84.776736,43.604327],"type":"Point"}
}