{
  "type": "Feature",
  "properties": {
    "iso:country":"US",
    "sg:address":"325 Erickson Ave",
    "sg:city":"Marquette",
    "sg:classifiers":[
        {
            "category":"Shopping",
            "subcategory":"Gifts & Souvenirs",
            "type":"Retail Goods"
        }
    ],
    "sg:phone":"+1 906 226 2023",
    "sg:postcode":"49855",
    "sg:province":"MI",
    "sg:tags":[
        "shop"
    ],
    "wof:name":"Rings & Things",
    "wof:placetype":"venue"
},
  "geometry": {"coordinates":[-87.440096,46.551333],"type":"Point"}
}