{
  "type": "Feature",
  "properties": {
    "iso:country":"US",
    "sg:address":"33700 Hooker Rd",
    "sg:city":"Chesterfield",
    "sg:classifiers":[
        {
            "category":"Education",
            "subcategory":"School",
            "type":"Public Place"
        }
    ],
    "sg:phone":"+1 586 725 7541",
    "sg:postcode":"48047",
    "sg:province":"MI",
    "wof:name":"Lottie M Schmidt Elementary",
    "wof:placetype":"venue"
},
  "geometry": {"coordinates":[-82.769807,42.6631],"type":"Point"}
}