{
  "type": "Feature",
  "properties": {
    "iso:country":"US",
    "sg:address":"25401 Harper Ave",
    "sg:city":"Saint Clair Shores",
    "sg:classifiers":[
        {
            "category":"Health Services",
            "subcategory":"Doctor",
            "type":"Services"
        }
    ],
    "sg:phone":"+1 586 466 6800",
    "sg:postcode":"48081",
    "sg:province":"MI",
    "sg:tags":[
        "medical"
    ],
    "wof:name":"South East Health Dept",
    "wof:placetype":"venue"
},
  "geometry": {"coordinates":[-82.900953,42.481836],"type":"Point"}
}