{
  "type": "Feature",
  "properties": {
    "iso:country":"US",
    "sg:address":"1631 Highwood W",
    "sg:city":"Pontiac",
    "sg:classifiers":[
        {
            "category":"Manufacturing",
            "subcategory":"Metals",
            "type":"Manufacturing & Wholesale Goods"
        }
    ],
    "sg:phone":"+1 248 334 7436",
    "sg:postcode":"48340",
    "sg:province":"MI",
    "sg:tags":[
        "treating",
        "heat"
    ],
    "wof:name":"Detroit Steel Treating Co",
    "wof:placetype":"venue"
},
  "geometry": {"coordinates":[-83.290245,42.681483],"type":"Point"}
}