{
  "type": "Feature",
  "properties": {
    "iso:country":"US",
    "sg:address":"228 W Washington St",
    "sg:city":"Marquette",
    "sg:classifiers":[
        {
            "category":"Banks & Credit Unions",
            "subcategory":"Bank",
            "type":"Services"
        }
    ],
    "sg:phone":"+1 906 228 6080",
    "sg:postcode":"49855",
    "sg:province":"MI",
    "sg:tags":[
        "financing"
    ],
    "wof:name":"Shorebank Capital Inc",
    "wof:placetype":"venue"
},
  "geometry": {"coordinates":[-87.397114,46.5439],"type":"Point"}
}