{
  "type": "Feature",
  "properties": {
    "iso:country":"US",
    "sg:address":"2950 Matthew Rd",
    "sg:city":"Niles",
    "sg:classifiers":[
        {
            "category":"Real Estate",
            "subcategory":"Real Estate Operator",
            "type":"Services"
        }
    ],
    "sg:phone":"+1 269 683 6364",
    "sg:postcode":"49120",
    "sg:province":"MI",
    "sg:tags":[
        "property",
        "lessor"
    ],
    "wof:name":"Donald L Camp",
    "wof:placetype":"venue"
},
  "geometry": {"coordinates":[-86.330581,41.885885],"type":"Point"}
}