{
  "type": "Feature",
  "properties": {
    "iso:country":"US",
    "sg:address":"104 S Michigan Ave",
    "sg:city":"Coldwater",
    "sg:classifiers":[
        {
            "category":"Retail",
            "subcategory":"Auto Repair",
            "type":"Services"
        }
    ],
    "sg:phone":"+1 517 278 7453",
    "sg:postcode":"49036",
    "sg:province":"MI",
    "sg:tags":[
        "automotive"
    ],
    "wof:name":"4x4 Posi Lok",
    "wof:placetype":"venue"
},
  "geometry": {"coordinates":[-84.98097300000001,41.934478],"type":"Point"}
}