{
  "type": "Feature",
  "properties": {
    "iso:country":"US",
    "sg:address":"3030 Abbottsford Rd",
    "sg:city":"North Street",
    "sg:classifiers":[
        {
            "category":"Professional",
            "subcategory":"Business Services",
            "type":"Services"
        }
    ],
    "sg:phone":"+1 810 987 6803",
    "sg:postcode":"48049",
    "sg:province":"MI",
    "wof:name":"Huron Design",
    "wof:placetype":"venue"
},
  "geometry": {"coordinates":[-82.560773,42.996084],"type":"Point"}
}