{
  "type": "Feature",
  "properties": {
    "iso:country":"US",
    "sg:address":"4318 Plainfield Ave NE",
    "sg:city":"Grand Rapids",
    "sg:classifiers":[
        {
            "category":"Professional",
            "subcategory":"Accounting & Tax Preparation",
            "type":"Services"
        }
    ],
    "sg:phone":"+1 616 364 4117",
    "sg:postcode":"49525",
    "sg:province":"MI",
    "sg:tags":[
        "return",
        "filing"
    ],
    "sg:website":"www.hrblock.com",
    "wof:name":"H & R Block Tax Svc",
    "wof:placetype":"venue"
},
  "geometry": {"coordinates":[-85.608343,43.040533],"type":"Point"}
}