{
  "type": "Feature",
  "properties": {
    "iso:country":"US",
    "sg:address":"14579 Kerner Dr",
    "sg:city":"Sterling Heights",
    "sg:classifiers":[
        {
            "category":"Manufacturing",
            "subcategory":"Retail Goods",
            "type":"Manufacturing & Wholesale Goods"
        }
    ],
    "sg:phone":"+1 586 247 1853",
    "sg:postcode":"48313",
    "sg:province":"MI",
    "sg:tags":[
        "product",
        "mfg"
    ],
    "wof:name":"JMB Industries",
    "wof:placetype":"venue"
},
  "geometry": {"coordinates":[-82.97844499999999,42.615123],"type":"Point"}
}