{
  "type": "Feature",
  "properties": {
    "iso:country":"US",
    "sg:address":"2380 Science Pkwy",
    "sg:city":"Okemos",
    "sg:classifiers":[
        {
            "category":"Manufacturing",
            "subcategory":"Tools & Machinery",
            "type":"Manufacturing & Wholesale Goods"
        }
    ],
    "sg:phone":"+1 517 706 0060",
    "sg:postcode":"48864",
    "sg:province":"MI",
    "sg:tags":[
        "physician",
        "surgeon"
    ],
    "wof:name":"Information Health Network",
    "wof:placetype":"venue"
},
  "geometry": {"coordinates":[-84.436545,42.706834],"type":"Point"}
}