{
  "type": "Feature",
  "properties": {
    "iso:country":"US",
    "sg:address":"4924 Karen Ave SW",
    "sg:city":"Wyoming",
    "sg:classifiers":[
        {
            "category":"Building & Trades",
            "subcategory":"Construction",
            "type":"Services"
        }
    ],
    "sg:phone":"+1 616 534 6130",
    "sg:postcode":"49548",
    "sg:province":"MI",
    "sg:tags":[
        "painter"
    ],
    "wof:name":"Anderson Painting & Powerwash",
    "wof:placetype":"venue"
},
  "geometry": {"coordinates":[-85.671363,42.873599],"type":"Point"}
}