{
  "type": "Feature",
  "properties": {
    "iso:country":"US",
    "sg:address":"349 W Saginaw St",
    "sg:city":"Hemlock",
    "sg:classifiers":[
        {
            "category":"Banks & Credit Unions",
            "subcategory":"Bank",
            "type":"Services"
        }
    ],
    "sg:phone":"+1 989 642 5244",
    "sg:postcode":"48626",
    "sg:province":"MI",
    "wof:name":"NBD Saginaw-Hemlock Branch",
    "wof:placetype":"venue"
},
  "geometry": {"coordinates":[-84.232904,43.414352],"type":"Point"}
}