{
  "type": "Feature",
  "properties": {
    "iso:country":"US",
    "sg:address":"66811 Gratiot Ave",
    "sg:city":"Richmond",
    "sg:classifiers":[
        {
            "category":"Professional",
            "subcategory":"Accounting & Tax Preparation",
            "type":"Services"
        }
    ],
    "sg:phone":"+1 586 727 2533",
    "sg:postcode":"48062",
    "sg:province":"MI",
    "sg:tags":[
        "return"
    ],
    "wof:name":"H & R Block",
    "wof:placetype":"venue"
},
  "geometry": {"coordinates":[-82.738147,42.792728],"type":"Point"}
}