{
  "type": "Feature",
  "properties": {
    "iso:country":"US",
    "sg:address":"1125 W Territorial Rd",
    "sg:city":"Battle Creek",
    "sg:classifiers":[
        {
            "category":"Organizations",
            "subcategory":"Non-profit Organization",
            "type":"Services"
        }
    ],
    "sg:phone":"+1 269 964 7577",
    "sg:postcode":"49015",
    "sg:province":"MI",
    "sg:tags":[
        "information",
        "alcoholism",
        "treatment"
    ],
    "wof:name":"A A",
    "wof:placetype":"venue"
},
  "geometry": {"coordinates":[-85.215425,42.304656],"type":"Point"}
}