{
  "type": "Feature",
  "properties": {
    "iso:country":"US",
    "sg:address":"4215 N Center Rd",
    "sg:city":"Saginaw",
    "sg:classifiers":[
        {
            "category":"Communications",
            "subcategory":"Film & Video Production",
            "type":"Services"
        }
    ],
    "sg:phone":"+1 989 799 1529",
    "sg:postcode":"48604",
    "sg:province":"MI",
    "sg:tags":[
        "duplication",
        "tape"
    ],
    "wof:name":"Contract Sales",
    "wof:placetype":"venue"
},
  "geometry": {"coordinates":[-84.015125,43.469387],"type":"Point"}
}