{
  "type": "Feature",
  "properties": {
    "iso:country":"US",
    "sg:address":"4300 W Pierson Rd",
    "sg:city":"Flint",
    "sg:classifiers":[
        {
            "category":"Restaurant",
            "type":"Food & Drink"
        }
    ],
    "sg:phone":"+1 810 720 9230",
    "sg:postcode":"48504",
    "sg:province":"MI",
    "wof:name":"Junkano Restaurant",
    "wof:placetype":"venue"
},
  "geometry": {"coordinates":[-83.762912,43.060722],"type":"Point"}
}