{
  "type": "Feature",
  "properties": {
    "iso:country":"US",
    "sg:address":"4222 Huron St",
    "sg:city":"Dearborn Heights",
    "sg:classifiers":[
        {
            "category":"Organizations",
            "subcategory":"Community Association",
            "type":"Services"
        }
    ],
    "sg:phone":"+1 313 562 2907",
    "sg:postcode":"48125",
    "sg:province":"MI",
    "wof:name":"Kiwanis International",
    "wof:placetype":"venue"
},
  "geometry": {"coordinates":[-83.237628,42.278987],"type":"Point"}
}