{
  "type": "Feature",
  "properties": {
    "iso:country":"US",
    "sg:address":"17475 Judy Ct",
    "sg:city":"Macomb",
    "sg:classifiers":[
        {
            "category":"Professional",
            "subcategory":"Business Services",
            "type":"Services"
        }
    ],
    "sg:phone":"+1 586 286 9121",
    "sg:postcode":"48044",
    "sg:province":"MI",
    "wof:name":"A Beautiful Design",
    "wof:placetype":"venue"
},
  "geometry": {"coordinates":[-82.948013,42.647455],"type":"Point"}
}