{
  "type": "Feature",
  "properties": {
    "iso:country":"US",
    "sg:address":"27600 Farmington Rd",
    "sg:city":"Farmington Hills",
    "sg:classifiers":[
        {
            "category":"Manufacturing",
            "subcategory":"Tools & Machinery",
            "type":"Manufacturing & Wholesale Goods"
        },
        {
            "category":"Shopping",
            "subcategory":"Computers & Home Electronics",
            "type":"Retail Goods"
        }
    ],
    "sg:phone":"+1 248 488 0155",
    "sg:postcode":"48334",
    "sg:province":"MI",
    "sg:tags":[
        "repair",
        "printer",
        "laser",
        "cartridge",
        "rebuild",
        "equipment",
        "toner",
        "dealer"
    ],
    "wof:name":"Nationwide Toner Cartridge",
    "wof:placetype":"venue"
},
  "geometry": {"coordinates":[-83.37804800000001,42.495239],"type":"Point"}
}