{
  "type": "Feature",
  "properties": {
    "iso:country":"US",
    "sg:address":"26323 Hendrie Blvd",
    "sg:city":"Huntington Woods",
    "sg:classifiers":[
        {
            "category":"Professional",
            "subcategory":"Business Services",
            "type":"Services"
        }
    ],
    "sg:phone":"+1 248 398 8415",
    "sg:postcode":"48070",
    "sg:province":"MI",
    "wof:name":"Allen Hope Limited Partnership",
    "wof:placetype":"venue"
},
  "geometry": {"coordinates":[-83.159611,42.485304],"type":"Point"}
}