{
  "type": "Feature",
  "properties": {
    "iso:country":"US",
    "sg:address":"4429 Traders Mine Rd",
    "sg:city":"Iron Mountain",
    "sg:classifiers":[
        {
            "category":"Building & Trades",
            "subcategory":"Construction",
            "type":"Services"
        }
    ],
    "sg:phone":"+1 906 779 2086",
    "sg:postcode":"49801",
    "sg:province":"MI",
    "sg:tags":[
        "general",
        "contractor"
    ],
    "wof:name":"Northern Restoration Constr",
    "wof:placetype":"venue"
},
  "geometry": {"coordinates":[-88.04196899999999,45.880076],"type":"Point"}
}