{
  "type": "Feature",
  "properties": {
    "iso:country":"US",
    "sg:address":"38933 Harper Ave",
    "sg:city":"Clinton Township",
    "sg:classifiers":[
        {
            "category":"Health Services",
            "subcategory":"Chiropractor",
            "type":"Services"
        }
    ],
    "sg:phone":"+1 586 468 5500",
    "sg:postcode":"48036",
    "sg:province":"MI",
    "sg:website":"www.chiropracticfc.com",
    "wof:name":"Gramzow Amy D DC",
    "wof:placetype":"venue"
},
  "geometry": {"coordinates":[-82.867401,42.584499],"type":"Point"}
}