{
  "type": "Feature",
  "properties": {
    "iso:country":"US",
    "sg:address":"567 Kentucky Dr",
    "sg:city":"Rochester",
    "sg:classifiers":[
        {
            "category":"Professional",
            "type":"Services"
        }
    ],
    "sg:phone":"+1 248 650 9618",
    "sg:postcode":"48307",
    "sg:province":"MI",
    "wof:name":"Administrative Advisors Inc",
    "wof:placetype":"venue"
},
  "geometry": {"coordinates":[-83.142304,42.645063],"type":"Point"}
}