{
  "type": "Feature",
  "properties": {
    "iso:country":"US",
    "sg:address":"38895 Lakeshore Dr",
    "sg:city":"Harrison Twp",
    "sg:classifiers":[
        {
            "category":"Freight",
            "type":"Transportation"
        },
        {
            "category":"Local Transit",
            "type":"Transportation"
        }
    ],
    "sg:phone":"+1 586 783 0433",
    "sg:postcode":"48045",
    "sg:province":"MI",
    "sg:tags":[
        "operator",
        "airport",
        "trucking"
    ],
    "wof:name":"Blazer Delivery & Shuttle Svc",
    "wof:placetype":"venue"
},
  "geometry": {"coordinates":[-82.78864900000001,42.587994],"type":"Point"}
}