{
  "type": "Feature",
  "properties": {
    "iso:country":"US",
    "sg:address":"5720 E Napier Ave",
    "sg:city":"Benton Harbor",
    "sg:classifiers":[
        {
            "category":"Food & Beverages",
            "subcategory":"Groceries & Convenience Stores",
            "type":"Retail Goods"
        }
    ],
    "sg:phone":"+1 269 944 3324",
    "sg:postcode":"49022",
    "sg:province":"MI",
    "wof:name":"Schilkes Farms",
    "wof:placetype":"venue"
},
  "geometry": {"coordinates":[-86.319874,42.093964],"type":"Point"}
}