{
  "type": "Feature",
  "properties": {
    "iso:country":"US",
    "sg:address":"200 7th St",
    "sg:city":"Calumet",
    "sg:classifiers":[
        {
            "category":"Retail",
            "subcategory":"Auto Repair",
            "type":"Services"
        }
    ],
    "sg:phone":"+1 906 337 2277",
    "sg:postcode":"49913",
    "sg:province":"MI",
    "sg:tags":[
        "repairing",
        "automobile"
    ],
    "wof:name":"Seventh Street Garage",
    "wof:placetype":"venue"
},
  "geometry": {"coordinates":[-88.455083,47.24628],"type":"Point"}
}