{
  "type": "Feature",
  "properties": {
    "iso:country":"US",
    "sg:address":"9345 Buckingham St",
    "sg:city":"White Lake",
    "sg:classifiers":[
        {
            "category":"Professional",
            "subcategory":"Business Services",
            "type":"Services"
        }
    ],
    "sg:phone":"+1 248 241 5997",
    "sg:postcode":"48386",
    "sg:province":"MI",
    "wof:name":"Sev Design",
    "wof:placetype":"venue"
},
  "geometry": {"coordinates":[-83.469272,42.669084],"type":"Point"}
}