{
  "type": "Feature",
  "properties": {
    "iso:country":"US",
    "sg:address":"140 Hartsough St",
    "sg:city":"Plymouth",
    "sg:classifiers":[
        {
            "category":"Manufacturing",
            "subcategory":"Chemicals & Compounds",
            "type":"Manufacturing & Wholesale Goods"
        }
    ],
    "sg:phone":"+1 734 455 4775",
    "sg:postcode":"48170",
    "sg:province":"MI",
    "sg:tags":[
        "glass",
        "mfg",
        "enamel",
        "pigment"
    ],
    "wof:name":"Glass and Ceramic",
    "wof:placetype":"venue"
},
  "geometry": {"coordinates":[-83.461032,42.363743],"type":"Point"}
}