{
  "type": "Feature",
  "properties": {
    "iso:country":"US",
    "sg:address":"13654 Irene Ct",
    "sg:city":"Warren",
    "sg:classifiers":[
        {
            "category":"Building & Trades",
            "subcategory":"Cleaning & Sanitation",
            "type":"Services"
        }
    ],
    "sg:phone":"+1 586 771 7303",
    "sg:postcode":"48088",
    "sg:province":"MI",
    "sg:website":"www.tandrjanitorial.com/",
    "wof:name":"T & R Janitorial",
    "wof:placetype":"venue"
},
  "geometry": {"coordinates":[-82.98649399999999,42.511805],"type":"Point"}
}