{
  "type": "Feature",
  "properties": {
    "iso:country":"US",
    "sg:address":"7296 Skeels Rd",
    "sg:city":"Holton",
    "sg:classifiers":[
        {
            "category":"Retail",
            "subcategory":"Auto Repair",
            "type":"Services"
        }
    ],
    "sg:phone":"+1 231 821 2630",
    "sg:postcode":"49425",
    "sg:province":"MI",
    "sg:tags":[
        "body"
    ],
    "wof:name":"Proctors Auto Upholstery",
    "wof:placetype":"venue"
},
  "geometry": {"coordinates":[-86.06111900000001,43.467047],"type":"Point"}
}