{
  "type": "Feature",
  "properties": {
    "iso:country":"US",
    "sg:address":"514 Poplar Ave",
    "sg:city":"Royal Oak",
    "sg:classifiers":[
        {
            "category":"Social Services",
            "subcategory":"Child Care",
            "type":"Services"
        }
    ],
    "sg:phone":"+1 248 585 0897",
    "sg:postcode":"48073",
    "sg:province":"MI",
    "sg:tags":[
        "day"
    ],
    "wof:name":"Patricia Kerr",
    "wof:placetype":"venue"
},
  "geometry": {"coordinates":[-83.150593,42.517583],"type":"Point"}
}