{
  "type": "Feature",
  "properties": {
    "iso:country":"US",
    "sg:address":"424 Fairlane Dr",
    "sg:city":"Alma",
    "sg:classifiers":[
        {
            "category":"Professional",
            "subcategory":"Management & Consulting",
            "type":"Services"
        }
    ],
    "sg:phone":"+1 989 466 2851",
    "sg:postcode":"48801",
    "sg:province":"MI",
    "wof:name":"Life Enhancing Programs",
    "wof:placetype":"venue"
},
  "geometry": {"coordinates":[-84.68235300000001,43.380362],"type":"Point"}
}