{
  "type": "Feature",
  "properties": {
    "iso:country":"US",
    "sg:address":"6052 Linfield Ave SE",
    "sg:city":"Alto",
    "sg:classifiers":[
        {
            "category":"Organizations",
            "subcategory":"Community Association",
            "type":"Services"
        }
    ],
    "sg:phone":"+1 616 868 6490",
    "sg:postcode":"49302",
    "sg:province":"MI",
    "sg:tags":[
        "military"
    ],
    "wof:name":"American Legion",
    "wof:placetype":"venue"
},
  "geometry": {"coordinates":[-85.382885,42.855662],"type":"Point"}
}