{
  "type": "Feature",
  "properties": {
    "iso:country":"US",
    "sg:address":"3779 Whispering Woods Dr",
    "sg:city":"Muskegon",
    "sg:classifiers":[
        {
            "category":"Building & Trades",
            "subcategory":"Construction",
            "type":"Services"
        }
    ],
    "sg:phone":"+1 231 767 0251",
    "sg:postcode":"49444",
    "sg:province":"MI",
    "sg:tags":[
        "house"
    ],
    "wof:name":"Brad Couch Builders",
    "wof:placetype":"venue"
},
  "geometry": {"coordinates":[-86.17859300000001,43.190035],"type":"Point"}
}