{
  "type": "Feature",
  "properties": {
    "iso:country":"US",
    "sg:address":"45978 Dunkirk Ct",
    "sg:city":"Macomb",
    "sg:classifiers":[
        {
            "category":"Freight",
            "type":"Transportation"
        }
    ],
    "sg:phone":"+1 586 463 6846",
    "sg:postcode":"48044",
    "sg:province":"MI",
    "sg:tags":[
        "trucking"
    ],
    "wof:name":"On Time Transportation Xpress",
    "wof:placetype":"venue"
},
  "geometry": {"coordinates":[-82.899089,42.636826],"type":"Point"}
}