{
  "type": "Feature",
  "properties": {
    "iso:country":"US",
    "sg:address":"193 Mill St",
    "sg:city":"Ortonville",
    "sg:classifiers":[
        {
            "category":"Home & Garden",
            "subcategory":"Home Furnishings",
            "type":"Retail Goods"
        }
    ],
    "sg:phone":"+1 248 627 3020",
    "sg:postcode":"48462",
    "sg:province":"MI",
    "wof:name":"Darcels Drape Room",
    "wof:placetype":"venue"
},
  "geometry": {"coordinates":[-83.45112899999999,42.852664],"type":"Point"}
}