{
  "type": "Feature",
  "properties": {
    "iso:country":"US",
    "sg:address":"1810 Ottawa Beach Rd",
    "sg:city":"Holland",
    "sg:classifiers":[
        {
            "category":"Recreation",
            "type":"Entertainment"
        }
    ],
    "sg:phone":"+1 616 786 2628",
    "sg:postcode":"49424",
    "sg:province":"MI",
    "sg:tags":[
        "charter",
        "boat"
    ],
    "wof:name":"Boat & Seadoo Rentals-Holland",
    "wof:placetype":"venue"
},
  "geometry": {"coordinates":[-86.18644,42.792059],"type":"Point"}
}