{
  "type": "Feature",
  "properties": {
    "iso:country":"US",
    "sg:address":"1191 Miners Run",
    "sg:city":"Rochester",
    "sg:classifiers":[
        {
            "category":"Shopping",
            "subcategory":"Music",
            "type":"Retail Goods"
        }
    ],
    "sg:phone":"+1 248 659 8203",
    "sg:postcode":"48306",
    "sg:province":"MI",
    "sg:tags":[
        "store"
    ],
    "wof:name":"Enforcemant Records",
    "wof:placetype":"venue"
},
  "geometry": {"coordinates":[-83.095978,42.702381],"type":"Point"}
}