{
  "type": "Feature",
  "properties": {
    "iso:country":"US",
    "sg:address":"7320 Wilkinson Dr NE",
    "sg:city":"Rockford",
    "sg:classifiers":[
        {
            "category":"Real Estate",
            "subcategory":"Real Estate Operator",
            "type":"Services"
        }
    ],
    "sg:phone":"+1 616 874 6375",
    "sg:postcode":"49341",
    "sg:province":"MI",
    "sg:tags":[
        "building",
        "nonresidential"
    ],
    "wof:name":"Normandie Building Partnership",
    "wof:placetype":"venue"
},
  "geometry": {"coordinates":[-85.486777,43.096166],"type":"Point"}
}