{
  "type": "Feature",
  "properties": {
    "iso:country":"US",
    "sg:address":"2415 Diamond Dr",
    "sg:city":"Traverse City",
    "sg:classifiers":[
        {
            "category":"Freight",
            "type":"Transportation"
        }
    ],
    "sg:phone":"+1 231 932 7620",
    "sg:postcode":"49684",
    "sg:province":"MI",
    "sg:tags":[
        "consultant"
    ],
    "wof:name":"Old Dominion Freight",
    "wof:placetype":"venue"
},
  "geometry": {"coordinates":[-85.62355700000001,44.729479],"type":"Point"}
}