{
  "type": "Feature",
  "properties": {
    "iso:country":"US",
    "sg:address":"4685 Webber Ave NE",
    "sg:city":"Grand Rapids",
    "sg:classifiers":[
        {
            "category":"Retail",
            "subcategory":"Repair Shop",
            "type":"Services"
        },
        {
            "category":"Retail",
            "subcategory":"Auto Repair",
            "type":"Services"
        }
    ],
    "sg:phone":"+1 616 363 2335",
    "sg:postcode":"49525",
    "sg:province":"MI",
    "sg:tags":[
        "automotive",
        "consultant"
    ],
    "wof:name":"Automotive Refinish Marketers",
    "wof:placetype":"venue"
},
  "geometry": {"coordinates":[-85.58002999999999,43.050264],"type":"Point"}
}