{
  "type": "Feature",
  "properties": {
    "iso:country":"US",
    "sg:address":"37713 Maplehill St",
    "sg:city":"Harrison Township",
    "sg:classifiers":[
        {
            "category":"Professional",
            "subcategory":"Research",
            "type":"Services"
        }
    ],
    "sg:phone":"+1 586 465 3778",
    "sg:postcode":"48045",
    "sg:province":"MI",
    "sg:tags":[
        "commercial",
        "physical"
    ],
    "wof:name":"R Lg Technologies",
    "wof:placetype":"venue"
},
  "geometry": {"coordinates":[-82.81914500000001,42.572025],"type":"Point"}
}