{
  "type": "Feature",
  "properties": {
    "iso:country":"US",
    "sg:address":"1161 W Woodside Dr",
    "sg:city":"Haslett",
    "sg:classifiers":[
        {
            "category":"Wholesale",
            "subcategory":"Non-durable Goods",
            "type":"Manufacturing & Wholesale Goods"
        }
    ],
    "sg:phone":"+1 517 339 0084",
    "sg:postcode":"48840",
    "sg:province":"MI",
    "wof:name":"Deneen Marketing Group",
    "wof:placetype":"venue"
},
  "geometry": {"coordinates":[-84.390463,42.744936],"type":"Point"}
}