{
  "type": "Feature",
  "properties": {
    "iso:country":"US",
    "sg:address":"20 W 8th St",
    "sg:city":"Holland",
    "sg:classifiers":[
        {
            "category":"Banks & Credit Unions",
            "subcategory":"Financial Services",
            "type":"Services"
        }
    ],
    "sg:phone":"+1 616 392 6254",
    "sg:postcode":"49423",
    "sg:province":"MI",
    "sg:tags":[
        "company",
        "bank",
        "holding"
    ],
    "wof:name":"D&D Restaurant Group",
    "wof:placetype":"venue"
},
  "geometry": {"coordinates":[-86.108294,42.790235],"type":"Point"}
}