{
  "type": "Feature",
  "properties": {
    "iso:country":"US",
    "sg:address":"2678 Ore Valley Dr",
    "sg:city":"Hartland",
    "sg:classifiers":[
        {
            "category":"Building & Trades",
            "subcategory":"Construction",
            "type":"Services"
        }
    ],
    "sg:phone":"+1 810 632 7909",
    "sg:postcode":"48353",
    "sg:province":"MI",
    "sg:tags":[
        "foundation"
    ],
    "wof:name":"E Young Construction Co",
    "wof:placetype":"venue"
},
  "geometry": {"coordinates":[-83.726449,42.643911],"type":"Point"}
}