{
  "type": "Feature",
  "properties": {
    "iso:country":"US",
    "sg:address":"3058 1st St",
    "sg:city":"Wyandotte",
    "sg:classifiers":[
        {
            "category":"Banks & Credit Unions",
            "subcategory":"Bank",
            "type":"Services"
        }
    ],
    "sg:phone":"+1 734 285 1889",
    "sg:postcode":"48192",
    "sg:province":"MI",
    "wof:name":"Charter One Bank",
    "wof:placetype":"venue"
},
  "geometry": {"coordinates":[-83.1502,42.202301],"type":"Point"}
}