{
  "type": "Feature",
  "properties": {
    "iso:country":"US",
    "sg:address":"5349 Lucerne Ave",
    "sg:city":"Kalamazoo",
    "sg:classifiers":[
        {
            "category":"Professional",
            "subcategory":"Accounting & Tax Preparation",
            "type":"Services"
        }
    ],
    "sg:phone":"+1 269 382 4826",
    "sg:postcode":"49048",
    "sg:province":"MI",
    "sg:tags":[
        "return",
        "filing"
    ],
    "wof:name":"Next Day Tax Cash",
    "wof:placetype":"venue"
},
  "geometry": {"coordinates":[-85.524879,42.30165],"type":"Point"}
}