{
  "type": "Feature",
  "properties": {
    "iso:country":"US",
    "sg:address":"760 N Van Dyke Rd",
    "sg:city":"Bad Axe",
    "sg:classifiers":[
        {
            "category":"Shopping",
            "subcategory":"Department Store",
            "type":"Retail Goods"
        }
    ],
    "sg:phone":"+1 989 269 9945",
    "sg:postcode":"48413",
    "sg:province":"MI",
    "wof:name":"Kmart",
    "wof:placetype":"venue"
},
  "geometry": {"coordinates":[-83.00098,43.819187],"type":"Point"}
}