{
  "type": "Feature",
  "properties": {
    "iso:country":"US",
    "sg:address":"2427 W Centre Ave",
    "sg:city":"Portage",
    "sg:classifiers":[
        {
            "category":"Professional",
            "subcategory":"Lawyer & Legal Services",
            "type":"Services"
        }
    ],
    "sg:phone":"+1 269 488 6330",
    "sg:postcode":"49024",
    "sg:province":"MI",
    "sg:tags":[
        "attorney"
    ],
    "wof:name":"Mc Carthy Law Group",
    "wof:placetype":"venue"
},
  "geometry": {"coordinates":[-85.617789,42.20101],"type":"Point"}
}