{
  "type": "Feature",
  "properties": {
    "iso:country":"US",
    "sg:address":"31 Vine St",
    "sg:city":"Hillsdale",
    "sg:classifiers":[
        {
            "category":"Organizations",
            "subcategory":"Religious Organization",
            "type":"Services"
        }
    ],
    "sg:phone":"+1 517 439 2694",
    "sg:postcode":"49242",
    "sg:province":"MI",
    "sg:tags":[
        "church"
    ],
    "wof:name":"Seventh Day Adventist Church",
    "wof:placetype":"venue"
},
  "geometry": {"coordinates":[-84.628224,41.924616],"type":"Point"}
}