{
  "type": "Feature",
  "properties": {
    "iso:country":"US",
    "sg:address":"22230 Woodward Ave",
    "sg:city":"Ferndale",
    "sg:classifiers":[
        {
            "category":"Donuts",
            "subcategory":"None",
            "type":"Food & Drink"
        }
    ],
    "sg:phone":"+1 248 546 2573",
    "sg:postcode":"48220",
    "sg:province":"MI",
    "sg:website":"http://www.timhortons.com/",
    "wof:name":"Tim Horton's",
    "wof:placetype":"venue"
},
  "geometry": {"coordinates":[-83.13130200000001,42.455799],"type":"Point"}
}