{
  "type": "Feature",
  "properties": {
    "iso:country":"US",
    "sg:address":"812 Berkshire Rd",
    "sg:city":"Ann Arbor",
    "sg:classifiers":[
        {
            "category":"Health Services",
            "subcategory":"Doctor",
            "type":"Services"
        }
    ],
    "sg:phone":"+1 734 747 9965",
    "sg:postcode":"48104",
    "sg:province":"MI",
    "sg:tags":[
        "medical"
    ],
    "wof:name":"Francis Robert Fekety Jr",
    "wof:placetype":"venue"
},
  "geometry": {"coordinates":[-83.720282,42.271327],"type":"Point"}
}