{
  "type": "Feature",
  "properties": {
    "iso:country":"US",
    "sg:address":"17271 E 9 Mile Rd",
    "sg:city":"Eastpointe",
    "sg:classifiers":[
        {
            "category":"Restaurant",
            "type":"Food & Drink"
        }
    ],
    "sg:phone":"+1 586 445 6100",
    "sg:postcode":"48021",
    "sg:province":"MI",
    "sg:tags":[
        "breakfast",
        "brunch"
    ],
    "sg:website":"www.granmashouseofpancakes.com",
    "wof:name":"Granma's House of Pancakes",
    "wof:placetype":"venue"
},
  "geometry": {"coordinates":[-82.943614,42.464969],"type":"Point"}
}