{
  "type": "Feature",
  "properties": {
    "iso:country":"US",
    "sg:address":"2955 Packard Rd",
    "sg:city":"Ypsilanti",
    "sg:classifiers":[
        {
            "category":"Recreation",
            "type":"Entertainment"
        }
    ],
    "sg:phone":"+1 734 434 2150",
    "sg:postcode":"48197",
    "sg:province":"MI",
    "sg:tags":[
        "club",
        "country",
        "private"
    ],
    "wof:name":"Washtenaw Country Club Inc",
    "wof:placetype":"venue"
},
  "geometry": {"coordinates":[-83.657843,42.244914],"type":"Point"}
}