{
  "type": "Feature",
  "properties": {
    "iso:country":"US",
    "sg:address":"2208 Normandy Dr",
    "sg:city":"Troy",
    "sg:classifiers":[
        {
            "category":"Professional",
            "subcategory":"Computer Services",
            "type":"Services"
        }
    ],
    "sg:phone":"+1 248 879 0472",
    "sg:postcode":"48085",
    "sg:province":"MI",
    "sg:tags":[
        "datum"
    ],
    "wof:name":"Surmount Sites",
    "wof:placetype":"venue"
},
  "geometry": {"coordinates":[-83.105772,42.611154],"type":"Point"}
}