{
  "type": "Feature",
  "properties": {
    "iso:country":"US",
    "sg:address":"2629 Prairie St SW",
    "sg:city":"Wyoming",
    "sg:classifiers":[
        {
            "category":"Retail",
            "subcategory":"Auto Repair",
            "type":"Services"
        }
    ],
    "sg:phone":"+1 616 531 7760",
    "sg:postcode":"49519",
    "sg:province":"MI",
    "sg:tags":[
        "transmission"
    ],
    "wof:name":"Quality Transmission Parts",
    "wof:placetype":"venue"
},
  "geometry": {"coordinates":[-85.73070199999999,42.906627],"type":"Point"}
}