{
  "type": "Feature",
  "properties": {
    "iso:country":"US",
    "sg:address":"4773 W Grand River Ave",
    "sg:city":"Lansing",
    "sg:phone":"+1 517 321 0172",
    "sg:postcode":"48906",
    "sg:province":"MI",
    "sg:tags":[
        "oil"
    ],
    "wof:name":"Mooney Oil Co",
    "wof:placetype":"venue"
},
  "geometry": {"coordinates":[-84.619625,42.775066],"type":"Point"}
}