{
  "type": "Feature",
  "properties": {
    "iso:country":"US",
    "sg:address":"16148 Larkspur St",
    "sg:city":"Roseville",
    "sg:classifiers":[
        {
            "category":"Personal",
            "type":"Services"
        }
    ],
    "sg:phone":"+1 586 774 0624",
    "sg:postcode":"48066",
    "sg:province":"MI",
    "wof:name":"Customer Connections",
    "wof:placetype":"venue"
},
  "geometry": {"coordinates":[-82.95650000000001,42.521483],"type":"Point"}
}