{
  "type": "Feature",
  "properties": {
    "iso:country":"US",
    "sg:address":"5004 Lannoo St",
    "sg:city":"Grosse Pointe",
    "sg:classifiers":[
        {
            "category":"Retail",
            "subcategory":"Auto Rental",
            "type":"Services"
        }
    ],
    "sg:phone":"+1 313 884 5069",
    "sg:postcode":"48236",
    "sg:province":"MI",
    "sg:tags":[
        "passenger",
        "car"
    ],
    "wof:name":"Kei Tan Enterprises LLC",
    "wof:placetype":"venue"
},
  "geometry": {"coordinates":[-82.91330499999999,42.415912],"type":"Point"}
}