{
  "type": "Feature",
  "properties": {
    "iso:country":"US",
    "sg:address":"19732 Hubbell St",
    "sg:city":"Detroit",
    "sg:classifiers":[
        {
            "category":"Professional",
            "subcategory":"Management & Consulting",
            "type":"Services"
        }
    ],
    "sg:phone":"+1 313 974 2552",
    "sg:postcode":"48235",
    "sg:province":"MI",
    "sg:tags":[
        "benefit",
        "planning",
        "resource",
        "human"
    ],
    "wof:name":"Lindsey JD Inc",
    "wof:placetype":"venue"
},
  "geometry": {"coordinates":[-83.190271,42.437657],"type":"Point"}
}