{
  "type": "Feature",
  "properties": {
    "iso:country":"US",
    "sg:address":"3229 S Saginaw Rd",
    "sg:city":"Midland",
    "sg:classifiers":[
        {
            "category":"Wholesale",
            "subcategory":"Metals & Minerals",
            "type":"Manufacturing & Wholesale Goods"
        }
    ],
    "sg:phone":"+1 989 496 2720",
    "sg:postcode":"48640",
    "sg:province":"MI",
    "sg:tags":[
        "steel",
        "warehouse"
    ],
    "wof:name":"Apex Steel Co",
    "wof:placetype":"venue"
},
  "geometry": {"coordinates":[-84.20751199999999,43.602967],"type":"Point"}
}