{
  "type": "Feature",
  "properties": {
    "iso:country":"US",
    "sg:address":"531 E Kittle Rd",
    "sg:city":"Mio",
    "sg:classifiers":[
        {
            "category":"Home & Garden",
            "subcategory":"Garden Supply",
            "type":"Retail Goods"
        }
    ],
    "sg:phone":"+1 989 848 8346",
    "sg:postcode":"48647",
    "sg:province":"MI",
    "sg:tags":[
        "lawn",
        "mower"
    ],
    "wof:name":"Sensenig's Repair",
    "wof:placetype":"venue"
},
  "geometry": {"coordinates":[-84.111423,44.695963],"type":"Point"}
}