{
  "type": "Feature",
  "properties": {
    "iso:country":"US",
    "sg:address":"1029 S Germania Rd",
    "sg:city":"Marlette",
    "sg:classifiers":[
        {
            "category":"Professional",
            "type":"Services"
        }
    ],
    "sg:phone":"+1 989 635 7880",
    "sg:postcode":"48453",
    "sg:province":"MI",
    "wof:name":"Puckett Poultry",
    "wof:placetype":"venue"
},
  "geometry": {"coordinates":[-83.006758,43.386826],"type":"Point"}
}