{
  "type": "Feature",
  "properties": {
    "iso:country":"US",
    "sg:address":"40704 Hayes Rd",
    "sg:city":"Clinton Twp",
    "sg:classifiers":[
        {
            "category":"Shopping",
            "subcategory":"Florist",
            "type":"Retail Goods"
        }
    ],
    "sg:phone":"+1 586 286 1270",
    "sg:postcode":"48038",
    "sg:province":"MI",
    "wof:name":"Candy Bouquet",
    "wof:placetype":"venue"
},
  "geometry": {"coordinates":[-82.971903,42.595317],"type":"Point"}
}