{
  "type": "Feature",
  "properties": {
    "iso:country":"US",
    "sg:address":"207 N Cedar St",
    "sg:city":"Traverse City",
    "sg:classifiers":[
        {
            "category":"Government",
            "subcategory":"Office",
            "type":"Public Place"
        }
    ],
    "sg:phone":"+1 231 264 8174",
    "sg:postcode":"49684",
    "sg:province":"MI",
    "sg:tags":[
        "village"
    ],
    "wof:name":"Edward C Grace Mem Harbor",
    "wof:placetype":"venue"
},
  "geometry": {"coordinates":[-85.636489,44.765888],"type":"Point"}
}