{
  "type": "Feature",
  "properties": {
    "iso:country":"US",
    "sg:address":"14015 Tall Oaks Dr",
    "sg:city":"Wyandotte",
    "sg:classifiers":[
        {
            "category":"Professional",
            "subcategory":"Management & Consulting",
            "type":"Services"
        }
    ],
    "sg:phone":"+1 734 479 1563",
    "sg:postcode":"48193",
    "sg:province":"MI",
    "wof:name":"N S Marketing Inc",
    "wof:placetype":"venue"
},
  "geometry": {"coordinates":[-83.19295,42.165667],"type":"Point"}
}