{
  "type": "Feature",
  "properties": {
    "iso:country":"US",
    "sg:address":"7750 Culbert Rd",
    "sg:city":"Osseo",
    "sg:classifiers":[
        {
            "category":"Shopping",
            "subcategory":"Gifts & Souvenirs",
            "type":"Retail Goods"
        }
    ],
    "sg:phone":"+1 517 523 3364",
    "sg:postcode":"49266",
    "sg:province":"MI",
    "wof:name":"My Favorite Things",
    "wof:placetype":"venue"
},
  "geometry": {"coordinates":[-84.500501,41.898362],"type":"Point"}
}