{
  "type": "Feature",
  "properties": {
    "iso:country":"US",
    "sg:address":"6600 W Maple Rd",
    "sg:city":"West Bloomfield",
    "sg:classifiers":[
        {
            "category":"Personal",
            "type":"Services"
        }
    ],
    "sg:phone":"+1 248 661 1000",
    "sg:postcode":"48322",
    "sg:province":"MI",
    "sg:tags":[
        "local"
    ],
    "sg:website":"www.jccdet.org",
    "wof:name":"Jewish Community Center of Metropolitan Detroit",
    "wof:placetype":"venue"
},
  "geometry": {"coordinates":[-83.402152,42.543437],"type":"Point"}
}