{
  "type": "Feature",
  "properties": {
    "iso:country":"US",
    "sg:address":"8291 N Byron Rd",
    "sg:city":"New Lothrop",
    "sg:phone":"+1 810 638 5748",
    "sg:postcode":"48460",
    "sg:province":"MI",
    "sg:tags":[
        "farm",
        "cash",
        "crop"
    ],
    "wof:name":"Schnell Dairy Farm",
    "wof:placetype":"venue"
},
  "geometry": {"coordinates":[-83.948753,43.127635],"type":"Point"}
}