{
  "type": "Feature",
  "properties": {
    "iso:country":"US",
    "sg:address":"14895 Swan Creek Rd",
    "sg:city":"Hemlock",
    "sg:phone":"+1 989 642 8477",
    "sg:postcode":"48626",
    "sg:province":"MI",
    "sg:tags":[
        "farm",
        "corn",
        "soybean"
    ],
    "wof:name":"Jack Walker",
    "wof:placetype":"venue"
},
  "geometry": {"coordinates":[-84.206582,43.377501],"type":"Point"}
}