{
  "type": "Feature",
  "properties": {
    "iso:country":"US",
    "sg:address":"4759 Eastern Ave SE",
    "sg:city":"Kentwood",
    "sg:classifiers":[
        {
            "category":"Retail",
            "subcategory":"Veterinary Services",
            "type":"Services"
        }
    ],
    "sg:phone":"+1 616 531 5530",
    "sg:postcode":"49508",
    "sg:province":"MI",
    "sg:tags":[
        "veterinarian"
    ],
    "wof:name":"Kentwood Veterinary Clinic",
    "wof:placetype":"venue"
},
  "geometry": {"coordinates":[-85.645447,42.877458],"type":"Point"}
}