{
  "type": "Feature",
  "properties": {
    "iso:country":"US",
    "sg:address":"3032 130th Ave",
    "sg:city":"Hopkins",
    "sg:classifiers":[
        {
            "category":"Banks & Credit Unions",
            "subcategory":"Investment Brokerage",
            "type":"Services"
        }
    ],
    "sg:phone":"+1 269 793 7099",
    "sg:postcode":"49328",
    "sg:province":"MI",
    "sg:tags":[
        "security"
    ],
    "wof:name":"R L Notes",
    "wof:placetype":"venue"
},
  "geometry": {"coordinates":[-85.840975,42.638219],"type":"Point"}
}