{
  "type": "Feature",
  "properties": {
    "iso:country":"US",
    "sg:address":"100 W Cloverland Dr",
    "sg:city":"Ironwood",
    "sg:classifiers":[
        {
            "category":"Shopping",
            "subcategory":"Bicycles & Sporting Goods",
            "type":"Retail Goods"
        }
    ],
    "sg:phone":"+1 906 932 5253",
    "sg:postcode":"49938",
    "sg:province":"MI",
    "wof:name":"Black Bear Sporting Goods",
    "wof:placetype":"venue"
},
  "geometry": {"coordinates":[-90.174701,46.463329],"type":"Point"}
}