{
  "type": "Feature",
  "properties": {
    "iso:country":"US",
    "sg:address":"54380 Pontiac Trl",
    "sg:city":"Milford",
    "sg:classifiers":[
        {
            "category":"Real Estate",
            "subcategory":"Real Estate Agent",
            "type":"Services"
        }
    ],
    "sg:phone":"+1 248 676 2120",
    "sg:postcode":"48381",
    "sg:province":"MI",
    "wof:name":"Home Properties",
    "wof:placetype":"venue"
},
  "geometry": {"coordinates":[-83.588292,42.522846],"type":"Point"}
}