{
  "type": "Feature",
  "properties": {
    "iso:country":"US",
    "sg:address":"1930 Petersburg Rd",
    "sg:city":"Dundee",
    "sg:classifiers":[
        {
            "category":"Farming",
            "subcategory":"Farm",
            "type":"Manufacturing & Wholesale Goods"
        }
    ],
    "sg:phone":"+1 734 279 2622",
    "sg:postcode":"48131",
    "sg:province":"MI",
    "sg:tags":[
        "produce",
        "farmer"
    ],
    "wof:name":"Beland Farms",
    "wof:placetype":"venue"
},
  "geometry": {"coordinates":[-83.710179,41.917454],"type":"Point"}
}