{
  "type": "Feature",
  "properties": {
    "iso:country":"US",
    "sg:address":"250 Kleiner St",
    "sg:city":"Frankenmuth",
    "sg:classifiers":[
        {
            "category":"Retail",
            "subcategory":"Car Wash",
            "type":"Services"
        }
    ],
    "sg:phone":"+1 989 652 3502",
    "sg:postcode":"48734",
    "sg:province":"MI",
    "sg:tags":[
        "automobile",
        "detail",
        "clean"
    ],
    "wof:name":"Covenient Auto Cleaning",
    "wof:placetype":"venue"
},
  "geometry": {"coordinates":[-83.742192,43.341737],"type":"Point"}
}