{
  "type": "Feature",
  "properties": {
    "iso:country":"US",
    "sg:address":"7202 Rockford St",
    "sg:city":"Portage",
    "sg:classifiers":[
        {
            "category":"Building & Trades",
            "subcategory":"Construction",
            "type":"Services"
        }
    ],
    "sg:phone":"+1 269 323 2379",
    "sg:postcode":"49024",
    "sg:province":"MI",
    "sg:tags":[
        "house"
    ],
    "wof:name":"Oak Shore Builders",
    "wof:placetype":"venue"
},
  "geometry": {"coordinates":[-85.60849899999999,42.211147],"type":"Point"}
}