{
  "type": "Feature",
  "properties": {
    "iso:country":"US",
    "sg:address":"4759 E Houghton Lake Dr",
    "sg:city":"Houghton Lake",
    "sg:classifiers":[
        {
            "category":"Cinema",
            "subcategory":"Movie Rental",
            "type":"Entertainment"
        }
    ],
    "sg:phone":"+1 989 366 6579",
    "sg:postcode":"48629",
    "sg:province":"MI",
    "sg:tags":[
        "eating",
        "video",
        "tape"
    ],
    "wof:name":"Timbers Pizza & Videos",
    "wof:placetype":"venue"
},
  "geometry": {"coordinates":[-84.677925,44.352793],"type":"Point"}
}