{
  "type": "Feature",
  "properties": {
    "iso:country":"US",
    "sg:address":"39635 Clearview St",
    "sg:city":"Harrison Township",
    "sg:classifiers":[
        {
            "category":"Retail",
            "subcategory":"Funeral Services",
            "type":"Services"
        }
    ],
    "sg:phone":"+1 586 468 6935",
    "sg:postcode":"48045",
    "sg:province":"MI",
    "wof:name":"Great Lakes Mortuary",
    "wof:placetype":"venue"
},
  "geometry": {"coordinates":[-82.81079200000001,42.595791],"type":"Point"}
}