{
  "type": "Feature",
  "properties": {
    "iso:country":"US",
    "sg:address":"1203 Brooklyn Ave",
    "sg:city":"Ann Arbor",
    "sg:classifiers":[
        {
            "category":"Professional",
            "subcategory":"Business Services",
            "type":"Services"
        }
    ],
    "sg:phone":"+1 734 662 5198",
    "sg:postcode":"48104",
    "sg:province":"MI",
    "wof:name":"Impro Assoc",
    "wof:placetype":"venue"
},
  "geometry": {"coordinates":[-83.732805,42.263716],"type":"Point"}
}