{
  "type": "Feature",
  "properties": {
    "iso:country":"US",
    "sg:address":"2722 Foster Ave NE",
    "sg:city":"Grand Rapids",
    "sg:classifiers":[
        {
            "category":"Professional",
            "subcategory":"Computer Services",
            "type":"Services"
        }
    ],
    "sg:phone":"+1 616 868 6480",
    "sg:postcode":"49505",
    "sg:province":"MI",
    "sg:tags":[
        "programing",
        "custom"
    ],
    "wof:name":"Scot Harig Inc",
    "wof:placetype":"venue"
},
  "geometry": {"coordinates":[-85.648098,43.012665],"type":"Point"}
}