{
  "type": "Feature",
  "properties": {
    "iso:country":"US",
    "sg:address":"297 E Maple Rd",
    "sg:city":"Birmingham",
    "sg:classifiers":[
        {
            "category":"Cafe",
            "type":"Food & Drink"
        }
    ],
    "sg:menulink":"http://www.allmenus.com/mi/birmingham/283559-maple-leaf-cafe/menu/",
    "sg:phone":"+1 248 723 1222",
    "sg:postcode":"48009",
    "sg:province":"MI",
    "sg:tags":[
        "american"
    ],
    "wof:name":"Maple Leaf Cafe",
    "wof:placetype":"venue"
},
  "geometry": {"coordinates":[-83.21321500000001,42.54672],"type":"Point"}
}