{
  "type": "Feature",
  "properties": {
    "iso:country":"US",
    "sg:address":"3175 M Dr S",
    "sg:city":"Athens",
    "sg:classifiers":[
        {
            "category":"Building & Trades",
            "subcategory":"Plumbing",
            "type":"Services"
        }
    ],
    "sg:phone":"+1 269 729 4009",
    "sg:postcode":"49011",
    "sg:province":"MI",
    "sg:tags":[
        "contractor"
    ],
    "wof:name":"AAA Sanitation",
    "wof:placetype":"venue"
},
  "geometry": {"coordinates":[-85.222785,42.152059],"type":"Point"}
}