{
  "type": "Feature",
  "properties": {
    "iso:country":"US",
    "sg:address":"2926 US Hwy 27 Bus",
    "sg:city":"St Johns",
    "sg:classifiers":[
        {
            "category":"Personal",
            "type":"Services"
        },
        {
            "category":"Building & Trades",
            "subcategory":"Construction",
            "type":"Services"
        }
    ],
    "sg:phone":"+1 989 224 0834",
    "sg:postcode":"48879",
    "sg:province":"MI",
    "sg:tags":[
        "handyman"
    ],
    "wof:name":"G's Maintenance Home & Repair",
    "wof:placetype":"venue"
},
  "geometry": {"coordinates":[-84.542897,42.973262],"type":"Point"}
}