{
  "type": "Feature",
  "properties": {
    "iso:country":"US",
    "sg:address":"339 Fisher Rd",
    "sg:city":"Grosse Pointe",
    "sg:classifiers":[
        {
            "category":"Retail",
            "subcategory":"Self-service Laundry",
            "type":"Services"
        }
    ],
    "sg:phone":"+1 313 882 8260",
    "sg:postcode":"48230",
    "sg:province":"MI",
    "sg:tags":[
        "dry",
        "cleaners"
    ],
    "wof:name":"American Dry Cleaning Stores",
    "wof:placetype":"venue"
},
  "geometry": {"coordinates":[-82.904504,42.391308],"type":"Point"}
}