{
  "type": "Feature",
  "properties": {
    "iso:country":"US",
    "sg:address":"50439 McClish Rd",
    "sg:city":"Mendon",
    "sg:classifiers":[
        {
            "category":"Farming",
            "subcategory":"Poultry Farm",
            "type":"Manufacturing & Wholesale Goods"
        }
    ],
    "sg:phone":"+1 269 496 7808",
    "sg:postcode":"49072",
    "sg:province":"MI",
    "sg:tags":[
        "chicken",
        "egg"
    ],
    "wof:name":"Gary Klein Farms",
    "wof:placetype":"venue"
},
  "geometry": {"coordinates":[-85.410994,42.065547],"type":"Point"}
}