{
  "type": "Feature",
  "properties": {
    "iso:country":"US",
    "sg:address":"28519 Ford Rd",
    "sg:city":"Garden City",
    "sg:classifiers":[
        {
            "category":"Personal",
            "subcategory":"Nail Salon",
            "type":"Services"
        }
    ],
    "sg:phone":"+1 734 422 9359",
    "sg:postcode":"48135",
    "sg:province":"MI",
    "wof:name":"Family Nail",
    "wof:placetype":"venue"
},
  "geometry": {"coordinates":[-83.317802,42.325901],"type":"Point"}
}