{
  "type": "Feature",
  "properties": {
    "iso:country":"US",
    "sg:address":"3565 Fairlane Dr",
    "sg:city":"Allen Park",
    "sg:classifiers":[
        {
            "category":"Personal",
            "subcategory":"Nail Salon",
            "type":"Services"
        }
    ],
    "sg:phone":"+1 313 271 8804",
    "sg:postcode":"48101",
    "sg:province":"MI",
    "wof:name":"Rose Nail",
    "wof:placetype":"venue"
},
  "geometry": {"coordinates":[-83.207459,42.278258],"type":"Point"}
}