{
  "type": "Feature",
  "properties": {
    "iso:country":"US",
    "sg:address":"4578 Scenic Dr",
    "sg:city":"Hamilton",
    "sg:classifiers":[
        {
            "category":"Building & Trades",
            "subcategory":"Construction",
            "type":"Services"
        }
    ],
    "sg:phone":"+1 269 751 6271",
    "sg:postcode":"49419",
    "sg:province":"MI",
    "sg:tags":[
        "house"
    ],
    "wof:name":"Robert Pott Builder",
    "wof:placetype":"venue"
},
  "geometry": {"coordinates":[-85.989307,42.674961],"type":"Point"}
}