{
  "type": "Feature",
  "properties": {
    "iso:country":"US",
    "sg:address":"3349 Newgate Dr",
    "sg:city":"Troy",
    "sg:classifiers":[
        {
            "category":"Professional",
            "subcategory":"Management & Consulting",
            "type":"Services"
        }
    ],
    "sg:phone":"+1 248 258 5268",
    "sg:postcode":"48084",
    "sg:province":"MI",
    "wof:name":"FB Management",
    "wof:placetype":"venue"
},
  "geometry": {"coordinates":[-83.202381,42.56536],"type":"Point"}
}