{
  "type": "Feature",
  "properties": {
    "iso:country":"US",
    "sg:address":"28852 Steele Dr",
    "sg:city":"Warren",
    "sg:classifiers":[
        {
            "category":"Retail",
            "subcategory":"Auto Repair",
            "type":"Services"
        }
    ],
    "sg:phone":"+1 586 777 9992",
    "sg:postcode":"48088",
    "sg:province":"MI",
    "sg:tags":[
        "general"
    ],
    "wof:name":"Frank S Garage",
    "wof:placetype":"venue"
},
  "geometry": {"coordinates":[-82.980468,42.504703],"type":"Point"}
}