{
  "type": "Feature",
  "properties": {
    "iso:country":"US",
    "sg:address":"600 N Old Woodward Ave Ste 101",
    "sg:city":"Birmingham",
    "sg:classifiers":[
        {
            "category":"Personal",
            "subcategory":"Hair Removal",
            "type":"Services"
        }
    ],
    "sg:phone":"+1 248 594 1544",
    "sg:postcode":"48009",
    "sg:province":"MI",
    "sg:website":"www.georgiswaxingstudio.com",
    "wof:name":"Georgi's Waxing Studio",
    "wof:placetype":"venue"
},
  "geometry": {"coordinates":[-83.217825,42.551711],"type":"Point"}
}