{
  "type": "Feature",
  "properties": {
    "iso:country":"US",
    "sg:address":"6485 Deland Rd",
    "sg:city":"Flushing",
    "sg:classifiers":[
        {
            "category":"Professional",
            "subcategory":"Business Services",
            "type":"Services"
        }
    ],
    "sg:phone":"+1 810 487 0620",
    "sg:postcode":"48433",
    "sg:province":"MI",
    "wof:name":"Medical Transcribers",
    "wof:placetype":"venue"
},
  "geometry": {"coordinates":[-83.843383,43.101529],"type":"Point"}
}