{
  "type": "Feature",
  "properties": {
    "iso:country":"US",
    "sg:address":"4511 Van Dyke Rd",
    "sg:city":"Almont",
    "sg:classifiers":[
        {
            "category":"Banks & Credit Unions",
            "subcategory":"Bank",
            "type":"Services"
        }
    ],
    "sg:phone":"+1 810 798 3907",
    "sg:postcode":"48003",
    "sg:province":"MI",
    "sg:tags":[
        "commercial"
    ],
    "wof:name":"Tri County Bank",
    "wof:placetype":"venue"
},
  "geometry": {"coordinates":[-83.055425,42.93436],"type":"Point"}
}