{
  "type": "Feature",
  "properties": {
    "iso:country":"US",
    "sg:address":"5551 S Martindale St",
    "sg:city":"Detroit",
    "sg:classifiers":[
        {
            "category":"Retail",
            "subcategory":"Repair Shop",
            "type":"Services"
        }
    ],
    "sg:phone":"+1 313 894 2561",
    "sg:postcode":"48204",
    "sg:province":"MI",
    "wof:name":"Obb Cleaning",
    "wof:placetype":"venue"
},
  "geometry": {"coordinates":[-83.132926,42.359889],"type":"Point"}
}