{
  "type": "Feature",
  "properties": {
    "iso:country":"US",
    "sg:address":"262 74th St",
    "sg:city":"South Haven",
    "sg:classifiers":[
        {
            "category":"Social Services",
            "type":"Services"
        }
    ],
    "sg:phone":"+1 269 637 4662",
    "sg:postcode":"49090",
    "sg:province":"MI",
    "wof:name":"Family Learning Center",
    "wof:placetype":"venue"
},
  "geometry": {"coordinates":[-86.261848,42.437531],"type":"Point"}
}