{
  "type": "Feature",
  "properties": {
    "iso:country":"US",
    "sg:address":"3143 Detroit St",
    "sg:city":"Dearborn",
    "sg:classifiers":[
        {
            "category":"Building & Trades",
            "subcategory":"Construction",
            "type":"Services"
        }
    ],
    "sg:phone":"+1 313 278 8453",
    "sg:postcode":"48124",
    "sg:province":"MI",
    "sg:tags":[
        "contractor"
    ],
    "wof:name":"Chandler Tile & Style",
    "wof:placetype":"venue"
},
  "geometry": {"coordinates":[-83.22964,42.288032],"type":"Point"}
}