{
  "type": "Feature",
  "properties": {
    "iso:country":"US",
    "sg:address":"1215 W Parnall Rd",
    "sg:city":"Jackson",
    "sg:classifiers":[
        {
            "category":"Building & Trades",
            "subcategory":"Cleaning & Sanitation",
            "type":"Services"
        }
    ],
    "sg:phone":"+1 517 780 7866",
    "sg:postcode":"49201",
    "sg:province":"MI",
    "sg:tags":[
        "maintenance",
        "con"
    ],
    "wof:name":"Coldwater Lake State Park",
    "wof:placetype":"venue"
},
  "geometry": {"coordinates":[-84.42194499999999,42.291033],"type":"Point"}
}