{
  "type": "Feature",
  "properties": {
    "iso:country":"US",
    "sg:address":"1500 Birney St",
    "sg:city":"Saginaw",
    "sg:classifiers":[
        {
            "category":"Shopping",
            "subcategory":"Used Merchandise",
            "type":"Retail Goods"
        }
    ],
    "sg:phone":"+1 989 497 9634",
    "sg:postcode":"48602",
    "sg:province":"MI",
    "sg:tags":[
        "shop",
        "consignment"
    ],
    "wof:name":"Michael J's Menswear",
    "wof:placetype":"venue"
},
  "geometry": {"coordinates":[-83.982626,43.420993],"type":"Point"}
}