{
  "type": "Feature",
  "properties": {
    "iso:country":"US",
    "sg:address":"533 3rd St",
    "sg:city":"Manistee",
    "sg:classifiers":[
        {
            "category":"Wholesale",
            "subcategory":"Stationery",
            "type":"Manufacturing & Wholesale Goods"
        }
    ],
    "sg:phone":"+1 231 398 2040",
    "sg:postcode":"49660",
    "sg:province":"MI",
    "sg:tags":[
        "packaging",
        "material"
    ],
    "wof:name":"Accord Paper",
    "wof:placetype":"venue"
},
  "geometry": {"coordinates":[-86.333117,44.244379],"type":"Point"}
}