{
  "type": "Feature",
  "properties": {
    "iso:country":"US",
    "sg:address":"3415 Ray Rd",
    "sg:city":"Grand Blanc",
    "sg:classifiers":[
        {
            "category":"Building & Trades",
            "subcategory":"Construction",
            "type":"Services"
        }
    ],
    "sg:phone":"+1 810 750 0818",
    "sg:postcode":"48439",
    "sg:province":"MI",
    "sg:tags":[
        "carpentry",
        "contractor"
    ],
    "wof:name":"Countertops R US",
    "wof:placetype":"venue"
},
  "geometry": {"coordinates":[-83.64993800000001,42.871964],"type":"Point"}
}