{
  "type": "Feature",
  "properties": {
    "iso:country":"US",
    "sg:address":"5445 Dutch Rd",
    "sg:city":"Leslie",
    "sg:classifiers":[
        {
            "category":"Personal",
            "type":"Services"
        }
    ],
    "sg:phone":"+1 517 589 5118",
    "sg:postcode":"49251",
    "sg:province":"MI",
    "wof:name":"Top To Bottom",
    "wof:placetype":"venue"
},
  "geometry": {"coordinates":[-84.398876,42.43502],"type":"Point"}
}