{
  "type": "Feature",
  "properties": {
    "iso:country":"US",
    "sg:address":"112 N Almer St",
    "sg:city":"Caro",
    "sg:classifiers":[
        {
            "category":"Organizations",
            "subcategory":"Religious Organization",
            "type":"Services"
        }
    ],
    "sg:phone":"+1 989 673 7283",
    "sg:postcode":"48723",
    "sg:province":"MI",
    "sg:tags":[
        "clergy"
    ],
    "wof:name":"Ronald C Wigand Rev",
    "wof:placetype":"venue"
},
  "geometry": {"coordinates":[-83.39704999999999,43.490877],"type":"Point"}
}