{
  "type": "Feature",
  "properties": {
    "iso:country":"US",
    "sg:address":"901 W Milham Rd",
    "sg:city":"Portage",
    "sg:classifiers":[
        {
            "category":"Banks & Credit Unions",
            "subcategory":"Bank",
            "type":"Services"
        }
    ],
    "sg:phone":"+1 269 492 0630",
    "sg:postcode":"49024",
    "sg:province":"MI",
    "wof:name":"First Community Credit Union",
    "wof:placetype":"venue"
},
  "geometry": {"coordinates":[-85.601528,42.23005],"type":"Point"}
}