{
  "type": "Feature",
  "properties": {
    "iso:country":"US",
    "sg:address":"3731 W A B Ave",
    "sg:city":"Plainwell",
    "sg:classifiers":[
        {
            "category":"Home & Garden",
            "subcategory":"Carpets & Floor Coverings",
            "type":"Retail Goods"
        }
    ],
    "sg:phone":"+1 269 685 5309",
    "sg:postcode":"49080",
    "sg:province":"MI",
    "wof:name":"Sunrise Floor & Trim",
    "wof:placetype":"venue"
},
  "geometry": {"coordinates":[-85.62981000000001,42.41285],"type":"Point"}
}