{
  "type": "Feature",
  "properties": {
    "iso:country":"US",
    "sg:address":"1427 Harwood Dr",
    "sg:city":"Oxford",
    "sg:classifiers":[
        {
            "category":"Building & Trades",
            "subcategory":"Construction",
            "type":"Services"
        }
    ],
    "sg:phone":"+1 248 628 1448",
    "sg:postcode":"48371",
    "sg:province":"MI",
    "sg:tags":[
        "house"
    ],
    "wof:name":"Austin Const Co",
    "wof:placetype":"venue"
},
  "geometry": {"coordinates":[-83.295433,42.819865],"type":"Point"}
}