{
  "type": "Feature",
  "properties": {
    "iso:country":"US",
    "sg:address":"5344 E Apple Ave",
    "sg:city":"Muskegon",
    "sg:classifiers":[
        {
            "category":"Restaurant",
            "type":"Food & Drink"
        }
    ],
    "sg:phone":"+1 231 788 3593",
    "sg:postcode":"49442",
    "sg:province":"MI",
    "sg:tags":[
        "pizza"
    ],
    "wof:name":"Arturo's Discount Pizza",
    "wof:placetype":"venue"
},
  "geometry": {"coordinates":[-86.11385,43.234899],"type":"Point"}
}