{
  "type": "Feature",
  "properties": {
    "iso:country":"US",
    "sg:address":"4864 Cornell Rd",
    "sg:city":"Okemos",
    "sg:classifiers":[
        {
            "category":"Professional",
            "subcategory":"Business Services",
            "type":"Services"
        }
    ],
    "sg:phone":"+1 517 333 9595",
    "sg:postcode":"48864",
    "sg:province":"MI",
    "wof:name":"Premier Companies",
    "wof:placetype":"venue"
},
  "geometry": {"coordinates":[-84.39293499999999,42.71667],"type":"Point"}
}