{
  "type": "Feature",
  "properties": {
    "iso:country":"US",
    "sg:address":"9065 S Mundy Ave",
    "sg:city":"Newaygo",
    "sg:classifiers":[
        {
            "category":"Building & Trades",
            "subcategory":"Construction",
            "type":"Services"
        }
    ],
    "sg:phone":"+1 231 652 6670",
    "sg:postcode":"49337",
    "sg:province":"MI",
    "sg:tags":[
        "garage",
        "builder"
    ],
    "wof:name":"North Country Construction",
    "wof:placetype":"venue"
},
  "geometry": {"coordinates":[-85.81087100000001,43.39033],"type":"Point"}
}