{
  "type": "Feature",
  "properties": {
    "iso:country":"US",
    "sg:address":"1088 Cloverlawn Blvd",
    "sg:city":"Lincoln Park",
    "sg:classifiers":[
        {
            "category":"Professional",
            "type":"Services"
        },
        {
            "category":"Retail",
            "subcategory":"Event Space",
            "type":"Services"
        }
    ],
    "sg:phone":"+1 313 389 5591",
    "sg:postcode":"48146",
    "sg:province":"MI",
    "sg:tags":[
        "venue",
        "caterer"
    ],
    "wof:name":"Catering by Kellie",
    "wof:placetype":"venue"
},
  "geometry": {"coordinates":[-83.178101,42.2244],"type":"Point"}
}