{
  "type": "Feature",
  "properties": {
    "iso:country":"US",
    "sg:address":"925 W Washington St",
    "sg:city":"Marquette",
    "sg:classifiers":[
        {
            "category":"Personal",
            "type":"Services"
        }
    ],
    "sg:phone":"+1 906 228 6123",
    "sg:postcode":"49855",
    "sg:province":"MI",
    "wof:name":"Weight Watchers",
    "wof:placetype":"venue"
},
  "geometry": {"coordinates":[-87.412767,46.545775],"type":"Point"}
}