{
  "type": "Feature",
  "properties": {
    "iso:country":"US",
    "sg:address":"3043 M 189",
    "sg:city":"Stambaugh",
    "sg:classifiers":[
        {
            "category":"Building & Trades",
            "subcategory":"Construction",
            "type":"Services"
        }
    ],
    "sg:phone":"+1 906 265 9918",
    "sg:postcode":"49935",
    "sg:province":"WI",
    "sg:tags":[
        "general",
        "contractor"
    ],
    "wof:name":"Manitta LA Construction",
    "wof:placetype":"venue"
},
  "geometry": {"coordinates":[-88.637114,46.014723],"type":"Point"}
}