{
  "type": "Feature",
  "properties": {
    "iso:country":"US",
    "sg:address":"45489 Galway Dr",
    "sg:city":"Novi",
    "sg:classifiers":[
        {
            "category":"Real Estate",
            "subcategory":"Real Estate Agent",
            "type":"Services"
        }
    ],
    "sg:phone":"+1 248 348 3429",
    "sg:postcode":"48374",
    "sg:province":"MI",
    "sg:tags":[
        "manager"
    ],
    "wof:name":"Lexington Green Hmeowners Assn",
    "wof:placetype":"venue"
},
  "geometry": {"coordinates":[-83.494558,42.44502],"type":"Point"}
}