{
  "type": "Feature",
  "properties": {
    "iso:country":"US",
    "sg:address":"2800 W Territorial Rd",
    "sg:city":"Battle Creek",
    "sg:classifiers":[
        {
            "category":"Government",
            "subcategory":"Office",
            "type":"Public Place"
        }
    ],
    "sg:phone":"+1 269 962 2103",
    "sg:postcode":"49015",
    "sg:province":"MI",
    "sg:tags":[
        "transportation"
    ],
    "wof:name":"Line Station Maint Section",
    "wof:placetype":"venue"
},
  "geometry": {"coordinates":[-85.25318300000001,42.304486],"type":"Point"}
}