{
  "type": "Feature",
  "properties": {
    "iso:country":"US",
    "sg:address":"257 Old State Rd",
    "sg:city":"Gaylord",
    "sg:classifiers":[
        {
            "category":"Shopping",
            "subcategory":"Gifts & Souvenirs",
            "type":"Retail Goods"
        }
    ],
    "sg:phone":"+1 989 732 9227",
    "sg:postcode":"49735",
    "sg:province":"MI",
    "wof:name":"Nature House",
    "wof:placetype":"venue"
},
  "geometry": {"coordinates":[-84.664862,44.915338],"type":"Point"}
}