{
  "type": "Feature",
  "properties": {
    "iso:country":"US",
    "sg:address":"15416 New Holland St",
    "sg:city":"Holland",
    "sg:classifiers":[
        {
            "category":"Retail",
            "subcategory":"Repair Shop",
            "type":"Services"
        }
    ],
    "sg:phone":"+1 616 399 2103",
    "sg:postcode":"49424",
    "sg:province":"MI",
    "wof:name":"Touch of Nature",
    "wof:placetype":"venue"
},
  "geometry": {"coordinates":[-86.164694,42.855741],"type":"Point"}
}