{
  "type": "Feature",
  "properties": {
    "iso:country":"US",
    "sg:address":"4255 Hart Dr",
    "sg:city":"Saint Joseph",
    "sg:classifiers":[
        {
            "category":"Professional",
            "subcategory":"Business Services",
            "type":"Services"
        }
    ],
    "sg:phone":"+1 269 428 5056",
    "sg:postcode":"49085",
    "sg:province":"MI",
    "wof:name":"Winfield Technology Inc",
    "wof:placetype":"venue"
},
  "geometry": {"coordinates":[-86.44463399999999,42.042787],"type":"Point"}
}