{
  "type": "Feature",
  "properties": {
    "iso:country":"US",
    "sg:address":"827 Michigan St",
    "sg:city":"Port Huron",
    "sg:classifiers":[
        {
            "category":"Insurance",
            "subcategory":"Insurance Agent",
            "type":"Services"
        }
    ],
    "sg:phone":"+1 810 982 8221",
    "sg:postcode":"48060",
    "sg:province":"MI",
    "sg:website":"www.maplethorpeins.com",
    "wof:name":"Maplethorpe Insurance",
    "wof:placetype":"venue"
},
  "geometry": {"coordinates":[-82.423545,42.983035],"type":"Point"}
}