{
  "type": "Feature",
  "properties": {
    "iso:country":"US",
    "sg:address":"28043 Hoover Rd",
    "sg:city":"Warren",
    "sg:classifiers":[
        {
            "category":"Health Services",
            "subcategory":"Doctor",
            "type":"Services"
        }
    ],
    "sg:phone":"+1 586 751 5588",
    "sg:postcode":"48093",
    "sg:province":"MI",
    "sg:tags":[
        "dentist"
    ],
    "wof:name":"J Girardi DDS",
    "wof:placetype":"venue"
},
  "geometry": {"coordinates":[-83.00669000000001,42.501918],"type":"Point"}
}