{
  "type": "Feature",
  "properties": {
    "iso:country":"US",
    "sg:address":"3126 Hixon Rd",
    "sg:city":"Rochester",
    "sg:classifiers":[
        {
            "category":"Building & Trades",
            "subcategory":"Landscaping Services",
            "type":"Services"
        }
    ],
    "sg:phone":"+1 586 336 9659",
    "sg:postcode":"48306",
    "sg:province":"MI",
    "sg:tags":[
        "landscape"
    ],
    "wof:name":"New Plant",
    "wof:placetype":"venue"
},
  "geometry": {"coordinates":[-83.10718300000001,42.753138],"type":"Point"}
}