{
  "type": "Feature",
  "properties": {
    "iso:country":"US",
    "sg:address":"6821 Sadie Ln",
    "sg:city":"Belleville",
    "sg:classifiers":[
        {
            "category":"Restaurant",
            "type":"Food & Drink"
        }
    ],
    "sg:phone":"+1 734 398 6969",
    "sg:postcode":"48111",
    "sg:province":"MI",
    "sg:tags":[
        "eating"
    ],
    "wof:name":"Shivam of Howell Inc",
    "wof:placetype":"venue"
},
  "geometry": {"coordinates":[-83.46335999999999,42.255898],"type":"Point"}
}