{
  "type": "Feature",
  "properties": {
    "iso:country":"US",
    "sg:address":"3259 24th Ave SW",
    "sg:city":"Hudsonville",
    "sg:classifiers":[
        {
            "category":"Retail",
            "subcategory":"Repair Shop",
            "type":"Services"
        }
    ],
    "sg:phone":"+1 616 896 8005",
    "sg:postcode":"49426",
    "sg:province":"MI",
    "sg:tags":[
        "welding"
    ],
    "wof:name":"ADT Welding",
    "wof:placetype":"venue"
},
  "geometry": {"coordinates":[-85.842279,42.825457],"type":"Point"}
}