{
  "type": "Feature",
  "properties": {
    "iso:country":"US",
    "sg:address":"2800 Indianwood Rd",
    "sg:city":"Lake Orion",
    "sg:classifiers":[
        {
            "category":"Education",
            "subcategory":"School",
            "type":"Public Place"
        }
    ],
    "sg:phone":"+1 248 814 1724",
    "sg:postcode":"48362",
    "sg:province":"MI",
    "wof:name":"Paint Creek Elementary School",
    "wof:placetype":"venue"
},
  "geometry": {"coordinates":[-83.302784,42.785082],"type":"Point"}
}