{
  "type": "Feature",
  "properties": {
    "iso:country":"US",
    "sg:address":"16423 Jennings Rd",
    "sg:city":"Fenton",
    "sg:classifiers":[
        {
            "category":"Real Estate",
            "subcategory":"Real Estate Operator",
            "type":"Services"
        }
    ],
    "sg:phone":"+1 810 629 5898",
    "sg:postcode":"48430",
    "sg:province":"MI",
    "sg:tags":[
        "mobile",
        "home",
        "community"
    ],
    "wof:name":"Fenton Oaks MHC",
    "wof:placetype":"venue"
},
  "geometry": {"coordinates":[-83.741422,42.793626],"type":"Point"}
}