{
  "type": "Feature",
  "properties": {
    "iso:country":"US",
    "sg:address":"2355 Pheasant Ct SE",
    "sg:city":"Grand Rapids",
    "sg:classifiers":[
        {
            "category":"Professional",
            "subcategory":"Advertising",
            "type":"Services"
        }
    ],
    "sg:phone":"+1 616 942 9375",
    "sg:postcode":"49546",
    "sg:province":"MI",
    "wof:name":"City Tour Magazi8ne",
    "wof:placetype":"venue"
},
  "geometry": {"coordinates":[-85.540887,42.921247],"type":"Point"}
}