{
  "type": "Feature",
  "properties": {
    "iso:country":"US",
    "sg:address":"808 Carpenter Ave NW",
    "sg:city":"Grand Rapids",
    "sg:classifiers":[
        {
            "category":"Manufacturing",
            "subcategory":"Printing",
            "type":"Manufacturing & Wholesale Goods"
        }
    ],
    "sg:phone":"+1 616 453 3543",
    "sg:postcode":"49504",
    "sg:province":"MI",
    "sg:tags":[
        "screen"
    ],
    "wof:name":"Bivins Graphics",
    "wof:placetype":"venue"
},
  "geometry": {"coordinates":[-85.734499,42.986126],"type":"Point"}
}