{
  "type": "Feature",
  "properties": {
    "iso:country":"US",
    "sg:address":"11880 Oak Ridge Ct",
    "sg:city":"Pinckney",
    "sg:classifiers":[
        {
            "category":"Building & Trades",
            "subcategory":"Construction",
            "type":"Services"
        }
    ],
    "sg:phone":"+1 734 878 9973",
    "sg:postcode":"48169",
    "sg:province":"MI",
    "wof:name":"Carl Kleinsteuber",
    "wof:placetype":"venue"
},
  "geometry": {"coordinates":[-83.98808699999999,42.425624],"type":"Point"}
}