{
  "type": "Feature",
  "properties": {
    "iso:country":"US",
    "sg:address":"4190 Telegraph Rd",
    "sg:city":"Bloomfield Hills",
    "sg:classifiers":[
        {
            "category":"Real Estate",
            "subcategory":"Architect",
            "type":"Services"
        }
    ],
    "sg:phone":"+1 248 646 8877",
    "sg:postcode":"48302",
    "sg:province":"MI",
    "sg:website":"www.btaa.net",
    "wof:name":"Brown Teefey & Assoc Archtcts",
    "wof:placetype":"venue"
},
  "geometry": {"coordinates":[-83.28122,42.581197],"type":"Point"}
}