{
  "type": "Feature",
  "properties": {
    "iso:country":"US",
    "sg:address":"4552 Billmar St SW",
    "sg:city":"Grandville",
    "sg:classifiers":[
        {
            "category":"Social Services",
            "subcategory":"Child Care",
            "type":"Services"
        }
    ],
    "sg:phone":"+1 616 532 6139",
    "sg:postcode":"49418",
    "sg:province":"MI",
    "sg:tags":[
        "day"
    ],
    "wof:name":"Gail Mejeur",
    "wof:placetype":"venue"
},
  "geometry": {"coordinates":[-85.77550100000001,42.894479],"type":"Point"}
}