{
  "type": "Feature",
  "properties": {
    "iso:country":"US",
    "sg:address":"210 S Hancock St",
    "sg:city":"Pentwater",
    "sg:classifiers":[
        {
            "category":"Restaurant",
            "type":"Food & Drink"
        }
    ],
    "sg:phone":"+1 231 869 4009",
    "sg:postcode":"49449",
    "sg:province":"MI",
    "wof:name":"House Of Flavors Ice Cream",
    "wof:placetype":"venue"
},
  "geometry": {"coordinates":[-86.432986,43.779862],"type":"Point"}
}