{
  "type": "Feature",
  "properties": {
    "iso:country":"US",
    "sg:address":"580 Burton St SW",
    "sg:city":"Grand Rapids",
    "sg:classifiers":[
        {
            "category":"Wholesale",
            "subcategory":"Scrap",
            "type":"Manufacturing & Wholesale Goods"
        }
    ],
    "sg:phone":"+1 616 245 9168",
    "sg:postcode":"49507",
    "sg:province":"MI",
    "sg:tags":[
        "waste"
    ],
    "wof:name":"Krell Paper Stock Co",
    "wof:placetype":"venue"
},
  "geometry": {"coordinates":[-85.681319,42.927803],"type":"Point"}
}