{
  "type": "Feature",
  "properties": {
    "iso:country":"US",
    "sg:address":"115 N Michigan Ave",
    "sg:city":"Howell",
    "sg:classifiers":[
        {
            "category":"Shopping",
            "subcategory":"Used Merchandise",
            "type":"Retail Goods"
        }
    ],
    "sg:phone":"+1 517 552 1080",
    "sg:postcode":"48843",
    "sg:province":"MI",
    "wof:name":"Antiques On Ave",
    "wof:placetype":"venue"
},
  "geometry": {"coordinates":[-83.929045,42.607866],"type":"Point"}
}