{
  "type": "Feature",
  "properties": {
    "iso:country":"US",
    "sg:address":"1435 W Center Rd",
    "sg:city":"Essexville",
    "sg:classifiers":[
        {
            "category":"Education",
            "subcategory":"School",
            "type":"Public Place"
        }
    ],
    "sg:phone":"+1 989 686 4771",
    "sg:postcode":"48732",
    "sg:province":"MI",
    "wof:name":"Living & Learning Center",
    "wof:placetype":"venue"
},
  "geometry": {"coordinates":[-83.8365,43.594163],"type":"Point"}
}