{
  "type": "Feature",
  "properties": {
    "iso:country":"US",
    "sg:address":"7170 Cooley Lake Rd",
    "sg:city":"Waterford",
    "sg:classifiers":[
        {
            "category":"Shopping",
            "subcategory":"Used Merchandise",
            "type":"Retail Goods"
        }
    ],
    "sg:phone":"+1 248 360 4977",
    "sg:postcode":"48327",
    "sg:province":"MI",
    "sg:tags":[
        "shop",
        "consignment"
    ],
    "wof:name":"Open Door Resale Store",
    "wof:placetype":"venue"
},
  "geometry": {"coordinates":[-83.424353,42.6156],"type":"Point"}
}