{
  "type": "Feature",
  "properties": {
    "iso:country":"US",
    "sg:address":"2759 Wisner Hwy",
    "sg:city":"Adrian",
    "sg:classifiers":[
        {
            "category":"Building & Trades",
            "subcategory":"Construction",
            "type":"Services"
        }
    ],
    "sg:phone":"+1 517 263 6561",
    "sg:postcode":"49221",
    "sg:province":"MI",
    "sg:tags":[
        "contractor"
    ],
    "wof:name":"Foor Custom Building",
    "wof:placetype":"venue"
},
  "geometry": {"coordinates":[-84.04507,41.925194],"type":"Point"}
}