{
  "type": "Feature",
  "properties": {
    "iso:country":"US",
    "sg:address":"8789 Harding Rd",
    "sg:city":"Farwell",
    "sg:classifiers":[
        {
            "category":"Social Services",
            "subcategory":"Adult Care",
            "type":"Services"
        }
    ],
    "sg:phone":"+1 989 588 9662",
    "sg:postcode":"48622",
    "sg:province":"MI",
    "sg:tags":[
        "foster"
    ],
    "wof:name":"Halstead Adult Foster Care",
    "wof:placetype":"venue"
},
  "geometry": {"coordinates":[-84.909639,43.860881],"type":"Point"}
}