{
  "type": "Feature",
  "properties": {
    "iso:country":"US",
    "sg:address":"2027 Haaland Rd",
    "sg:city":"Traverse City",
    "sg:classifiers":[
        {
            "category":"Real Estate",
            "subcategory":"Real Estate Agent",
            "type":"Services"
        }
    ],
    "sg:phone":"+1 231 929 0110",
    "sg:postcode":"49686",
    "sg:province":"MI",
    "wof:name":"Larry Derda & Co Realtors",
    "wof:placetype":"venue"
},
  "geometry": {"coordinates":[-85.496083,44.718085],"type":"Point"}
}