{
  "type": "Feature",
  "properties": {
    "iso:country":"US",
    "sg:address":"29990 John R Rd",
    "sg:city":"Madison Heights",
    "sg:classifiers":[
        {
            "category":"Retail",
            "subcategory":"Car Wash",
            "type":"Services"
        }
    ],
    "sg:phone":"+1 248 545 3136",
    "sg:postcode":"48071",
    "sg:province":"MI",
    "sg:tags":[
        "polishing",
        "washing"
    ],
    "wof:name":"Doc's Auto Wash",
    "wof:placetype":"venue"
},
  "geometry": {"coordinates":[-83.10597300000001,42.511451],"type":"Point"}
}