{
  "type": "Feature",
  "properties": {
    "iso:country":"US",
    "sg:address":"3790 Rochester Rd",
    "sg:city":"Troy",
    "sg:classifiers":[
        {
            "category":"Education",
            "subcategory":"Music School",
            "type":"Public Place"
        }
    ],
    "sg:phone":"+1 248 680 0010",
    "sg:postcode":"48083",
    "sg:province":"MI",
    "sg:tags":[
        "instrument",
        "teacher",
        "musical"
    ],
    "sg:website":"www.anderson-music.com",
    "wof:name":"Anderson Music Co",
    "wof:placetype":"venue"
},
  "geometry": {"coordinates":[-83.12809799999999,42.573799],"type":"Point"}
}