{
  "type": "Feature",
  "properties": {
    "iso:country":"US",
    "sg:address":"211 N Telegraph Rd",
    "sg:city":"Monroe",
    "sg:classifiers":[
        {
            "category":"Food & Beverages",
            "subcategory":"Groceries & Convenience Stores",
            "type":"Retail Goods"
        }
    ],
    "sg:phone":"+1 734 241 7667",
    "sg:postcode":"48162",
    "sg:province":"MI",
    "sg:tags":[
        "grocer"
    ],
    "wof:name":"Food Town Store",
    "wof:placetype":"venue"
},
  "geometry": {"coordinates":[-83.41342,41.925977],"type":"Point"}
}