{
  "type": "Feature",
  "properties": {
    "iso:country":"US",
    "sg:address":"60401 Mount Vernon Rd",
    "sg:city":"Rochester",
    "sg:classifiers":[
        {
            "category":"Personal",
            "type":"Services"
        }
    ],
    "sg:phone":"+1 248 652 8579",
    "sg:postcode":"48306",
    "sg:province":"MI",
    "sg:tags":[
        "therapist",
        "massage"
    ],
    "wof:name":"Hand In Hand Healing Body Work",
    "wof:placetype":"venue"
},
  "geometry": {"coordinates":[-83.08723000000001,42.738616],"type":"Point"}
}