{
  "type": "Feature",
  "properties": {
    "iso:country":"US",
    "sg:address":"329 Wesley St",
    "sg:city":"Rochester",
    "sg:classifiers":[
        {
            "category":"Home & Garden",
            "subcategory":"Furniture",
            "type":"Retail Goods"
        }
    ],
    "sg:phone":"+1 248 656 8280",
    "sg:postcode":"48307",
    "sg:province":"MI",
    "wof:name":"Michigan Furniture Associates",
    "wof:placetype":"venue"
},
  "geometry": {"coordinates":[-83.141913,42.680139],"type":"Point"}
}