{
  "type": "Feature",
  "properties": {
    "iso:country":"US",
    "sg:address":"1110 South Dr",
    "sg:city":"Flint",
    "sg:classifiers":[
        {
            "category":"Professional",
            "subcategory":"Management & Consulting",
            "type":"Services"
        }
    ],
    "sg:phone":"+1 810 237 8893",
    "sg:postcode":"48503",
    "sg:province":"MI",
    "sg:tags":[
        "environmental",
        "consultant"
    ],
    "wof:name":"Aquest Corp",
    "wof:placetype":"venue"
},
  "geometry": {"coordinates":[-83.707425,43.004899],"type":"Point"}
}