{
  "type": "Feature",
  "properties": {
    "iso:country":"US",
    "sg:address":"10995 W Carleton Rd",
    "sg:city":"Clayton",
    "sg:classifiers":[
        {
            "category":"Food & Beverages",
            "subcategory":"Groceries & Convenience Stores",
            "type":"Retail Goods"
        }
    ],
    "sg:phone":"+1 517 445 2719",
    "sg:postcode":"49235",
    "sg:province":"MI",
    "wof:name":"Clayton PS Mart",
    "wof:placetype":"venue"
},
  "geometry": {"coordinates":[-84.23527199999999,41.856988],"type":"Point"}
}