{
  "type": "Feature",
  "properties": {
    "iso:country":"US",
    "sg:address":"24254 80th Ave",
    "sg:city":"Lawton",
    "sg:classifiers":[
        {
            "category":"Social Services",
            "type":"Services"
        }
    ],
    "sg:phone":"+1 269 624 1410",
    "sg:postcode":"49065",
    "sg:province":"MI",
    "wof:name":"The Compassionate Friends",
    "wof:placetype":"venue"
},
  "geometry": {"coordinates":[-85.77929399999999,42.127434],"type":"Point"}
}