{
  "type": "Feature",
  "properties": {
    "iso:country":"US",
    "sg:address":"14613 Lyons St",
    "sg:city":"Livonia",
    "sg:classifiers":[
        {
            "category":"Professional",
            "subcategory":"Management & Consulting",
            "type":"Services"
        }
    ],
    "sg:phone":"+1 734 513 8457",
    "sg:postcode":"48154",
    "sg:province":"MI",
    "wof:name":"Westbrook Enterprise",
    "wof:placetype":"venue"
},
  "geometry": {"coordinates":[-83.32215600000001,42.394162],"type":"Point"}
}