{
  "type": "Feature",
  "properties": {
    "iso:country":"US",
    "sg:address":"1725 Aitken Rd",
    "sg:city":"Croswell",
    "sg:phone":"+1 810 679 4888",
    "sg:postcode":"48422",
    "sg:province":"MI",
    "sg:tags":[
        "farm",
        "grain",
        "cash"
    ],
    "wof:name":"Durand Farms Inc",
    "wof:placetype":"venue"
},
  "geometry": {"coordinates":[-82.74431300000001,43.318449],"type":"Point"}
}