{
  "type": "Feature",
  "properties": {
    "iso:country":"US",
    "sg:address":"3395 Notre Dame Path",
    "sg:city":"Stevensville",
    "sg:classifiers":[
        {
            "category":"Professional",
            "subcategory":"Management & Consulting",
            "type":"Services"
        }
    ],
    "sg:phone":"+1 269 428 2787",
    "sg:postcode":"49127",
    "sg:province":"MI",
    "sg:tags":[
        "business"
    ],
    "wof:name":"Grand Mere Consulting",
    "wof:placetype":"venue"
},
  "geometry": {"coordinates":[-86.53634599999999,42.025801],"type":"Point"}
}