{
  "type": "Feature",
  "properties": {
    "iso:country":"US",
    "sg:address":"124 N Main St",
    "sg:city":"Onsted",
    "sg:classifiers":[
        {
            "category":"Shopping",
            "subcategory":"Discount & Variety Stores",
            "type":"Retail Goods"
        }
    ],
    "sg:phone":"+1 517 467 4792",
    "sg:postcode":"49265",
    "sg:province":"MI",
    "wof:name":"Onsted Variety",
    "wof:placetype":"venue"
},
  "geometry": {"coordinates":[-84.18964800000001,42.006536],"type":"Point"}
}