{
  "type": "Feature",
  "properties": {
    "iso:country":"US",
    "sg:address":"316 Van Buren St W",
    "sg:city":"Battle Creek",
    "sg:classifiers":[
        {
            "category":"Retail",
            "subcategory":"Auto Repair",
            "type":"Services"
        }
    ],
    "sg:phone":"+1 269 968 7188",
    "sg:postcode":"49037",
    "sg:province":"MI",
    "sg:tags":[
        "repairing",
        "automobile"
    ],
    "wof:name":"D & H Automotive",
    "wof:placetype":"venue"
},
  "geometry": {"coordinates":[-85.849689,43.710223],"type":"Point"}
}