{
  "type": "Feature",
  "properties": {
    "iso:country":"US",
    "sg:address":"15921 Vinecrest St",
    "sg:city":"Spring Lake",
    "sg:classifiers":[
        {
            "category":"Building & Trades",
            "subcategory":"Construction",
            "type":"Services"
        }
    ],
    "sg:phone":"+1 616 847 5029",
    "sg:postcode":"49456",
    "sg:province":"MI",
    "sg:tags":[
        "house"
    ],
    "wof:name":"Kossuth Const LLC",
    "wof:placetype":"venue"
},
  "geometry": {"coordinates":[-86.181786,43.067683],"type":"Point"}
}