{
  "type": "Feature",
  "properties": {
    "iso:country":"US",
    "sg:address":"50 Turk St",
    "sg:city":"Pontiac",
    "sg:classifiers":[
        {
            "category":"Wholesale",
            "subcategory":"Scrap",
            "type":"Manufacturing & Wholesale Goods"
        }
    ],
    "sg:phone":"+1 248 338 6320",
    "sg:postcode":"48341",
    "sg:province":"MI",
    "sg:tags":[
        "metal",
        "iron"
    ],
    "wof:name":"Oakland Salvage Inc",
    "wof:placetype":"venue"
},
  "geometry": {"coordinates":[-83.284488,42.627529],"type":"Point"}
}