{
  "type": "Feature",
  "properties": {
    "iso:country":"US",
    "sg:address":"1040 Franklin St SE",
    "sg:city":"Grand Rapids",
    "sg:classifiers":[
        {
            "category":"Real Estate",
            "subcategory":"Architect",
            "type":"Services"
        }
    ],
    "sg:phone":"+1 616 452 1246",
    "sg:postcode":"49507",
    "sg:province":"MI",
    "wof:name":"Judson Jones & Assoc Inc",
    "wof:placetype":"venue"
},
  "geometry": {"coordinates":[-85.642072,42.948235],"type":"Point"}
}