{
  "type": "Feature",
  "properties": {
    "iso:country":"US",
    "sg:address":"29638 Oakwood St",
    "sg:city":"Inkster",
    "sg:classifiers":[
        {
            "category":"Personal",
            "type":"Services"
        }
    ],
    "sg:phone":"+1 734 641 0685",
    "sg:postcode":"48141",
    "sg:province":"MI",
    "wof:name":"Sunugal Braids",
    "wof:placetype":"venue"
},
  "geometry": {"coordinates":[-83.33462400000001,42.303084],"type":"Point"}
}