{
  "type": "Feature",
  "properties": {
    "iso:country":"US",
    "sg:address":"1606 N Westnedge Ave",
    "sg:city":"Kalamazoo",
    "sg:classifiers":[
        {
            "category":"Food & Beverages",
            "subcategory":"Groceries & Convenience Stores",
            "type":"Retail Goods"
        }
    ],
    "sg:phone":"+1 269 341 9221",
    "sg:postcode":"49007",
    "sg:province":"MI",
    "wof:name":"J & A Convenience Store",
    "wof:placetype":"venue"
},
  "geometry": {"coordinates":[-85.589934,42.308738],"type":"Point"}
}