{
  "type": "Feature",
  "properties": {
    "iso:country":"US",
    "sg:address":"1001 Marshall Rd",
    "sg:city":"Coldwater",
    "sg:classifiers":[
        {
            "category":"Autos & Motor Vehicles",
            "subcategory":"Automobile Sales",
            "type":"Retail Goods"
        }
    ],
    "sg:phone":"+1 517 278 6372",
    "sg:postcode":"49036",
    "sg:province":"MI",
    "sg:tags":[
        "car",
        "dealer"
    ],
    "wof:name":"Jim's Motor Sales",
    "wof:placetype":"venue"
},
  "geometry": {"coordinates":[-85.00096499999999,42.029298],"type":"Point"}
}