{
  "type": "Feature",
  "properties": {
    "iso:country":"US",
    "sg:address":"15409 Hall Rd",
    "sg:city":"Macomb",
    "sg:classifiers":[
        {
            "category":"Shopping",
            "subcategory":"Musical Instruments",
            "type":"Retail Goods"
        }
    ],
    "sg:phone":"+1 586 566 8981",
    "sg:postcode":"48044",
    "sg:province":"MI",
    "sg:tags":[
        "repair"
    ],
    "wof:name":"Guitars and Company Inc",
    "wof:placetype":"venue"
},
  "geometry": {"coordinates":[-82.971521,42.627907],"type":"Point"}
}