{
  "type": "Feature",
  "properties": {
    "iso:country":"US",
    "sg:address":"3325 Leith St",
    "sg:city":"Flint",
    "sg:classifiers":[
        {
            "category":"Building & Trades",
            "subcategory":"Landscaping Services",
            "type":"Services"
        }
    ],
    "sg:phone":"+1 810 618 0269",
    "sg:postcode":"48506",
    "sg:province":"MI",
    "sg:tags":[
        "tree"
    ],
    "wof:name":"E & S Tree Svc",
    "wof:placetype":"venue"
},
  "geometry": {"coordinates":[-83.643277,43.042916],"type":"Point"}
}