{
  "type": "Feature",
  "properties": {
    "iso:country":"US",
    "sg:address":"5645 S M 52",
    "sg:city":"Perry",
    "sg:classifiers":[
        {
            "category":"Building & Trades",
            "subcategory":"Construction",
            "type":"Services"
        }
    ],
    "sg:phone":"+1 517 468 3232",
    "sg:postcode":"48872",
    "sg:province":"MI",
    "sg:tags":[
        "course",
        "golf"
    ],
    "wof:name":"Mtm Golf Services Inc",
    "wof:placetype":"venue"
},
  "geometry": {"coordinates":[-84.223992,42.743697],"type":"Point"}
}