{
  "type": "Feature",
  "properties": {
    "iso:country":"US",
    "sg:address":"3777 Timberwolf Dr",
    "sg:city":"Traverse City",
    "sg:classifiers":[
        {
            "category":"Personal",
            "subcategory":"Beauty Salon",
            "type":"Services"
        }
    ],
    "sg:phone":"+1 231 946 0049",
    "sg:postcode":"49684",
    "sg:province":"MI",
    "wof:name":"Judy's Golden Shear",
    "wof:placetype":"venue"
},
  "geometry": {"coordinates":[-85.673765,44.742807],"type":"Point"}
}