{
  "type": "Feature",
  "properties": {
    "iso:country":"US",
    "sg:address":"58 Sagamore Trl SE",
    "sg:city":"Lowell",
    "sg:classifiers":[
        {
            "category":"Professional",
            "subcategory":"Art Services",
            "type":"Services"
        }
    ],
    "sg:phone":"+1 616 897 1746",
    "sg:postcode":"49331",
    "sg:province":"MI",
    "sg:tags":[
        "commercial",
        "design"
    ],
    "wof:name":"JP Designs",
    "wof:placetype":"venue"
},
  "geometry": {"coordinates":[-85.31818699999999,42.960097],"type":"Point"}
}