{
  "type": "Feature",
  "properties": {
    "iso:country":"US",
    "sg:address":"5750 Clay Ave SW",
    "sg:city":"Wyoming",
    "sg:classifiers":[
        {
            "category":"Autos & Motor Vehicles",
            "subcategory":"Auto Supplies",
            "type":"Retail Goods"
        }
    ],
    "sg:phone":"+1 616 257 8850",
    "sg:postcode":"49548",
    "sg:province":"MI",
    "sg:tags":[
        "tire"
    ],
    "wof:name":"Lake Tire Svc",
    "wof:placetype":"venue"
},
  "geometry": {"coordinates":[-85.67617300000001,42.858044],"type":"Point"}
}