{
  "type": "Feature",
  "properties": {
    "iso:country":"US",
    "sg:address":"945 N Van Dyke Rd",
    "sg:city":"Marlette",
    "sg:classifiers":[
        {
            "category":"Professional",
            "subcategory":"Business Services",
            "type":"Services"
        }
    ],
    "sg:phone":"+1 989 635 1510",
    "sg:postcode":"48453",
    "sg:province":"MI",
    "wof:name":"Burpee Enterprize",
    "wof:placetype":"venue"
},
  "geometry": {"coordinates":[-83.088498,43.438738],"type":"Point"}
}