{
  "type": "Feature",
  "properties": {
    "iso:country":"US",
    "sg:address":"14550 30th Ave",
    "sg:city":"Remus",
    "sg:classifiers":[
        {
            "category":"Organizations",
            "subcategory":"Religious Organization",
            "type":"Services"
        }
    ],
    "sg:phone":"+1 989 967 8476",
    "sg:postcode":"49340",
    "sg:province":"MI",
    "sg:tags":[
        "church"
    ],
    "sg:website":"www.watchtower.org",
    "wof:name":"Jehovah's Witnesses Church",
    "wof:placetype":"venue"
},
  "geometry": {"coordinates":[-85.146376,43.681618],"type":"Point"}
}