{
  "type": "Feature",
  "properties": {
    "iso:country":"US",
    "sg:address":"9706 Andersonville Rd",
    "sg:city":"Clarkston",
    "sg:classifiers":[
        {
            "category":"Building & Trades",
            "subcategory":"Construction",
            "type":"Services"
        }
    ],
    "sg:phone":"+1 248 625 0009",
    "sg:postcode":"48346",
    "sg:province":"MI",
    "sg:tags":[
        "pumping",
        "contractor"
    ],
    "wof:name":"Thompson Pump Midwest",
    "wof:placetype":"venue"
},
  "geometry": {"coordinates":[-83.47976199999999,42.721322],"type":"Point"}
}