{
  "type": "Feature",
  "properties": {
    "iso:country":"US",
    "sg:address":"1132 US Hwy 23",
    "sg:city":"Tawas City",
    "sg:classifiers":[
        {
            "category":"Retail",
            "subcategory":"Auto Repair",
            "type":"Services"
        }
    ],
    "sg:phone":"+1 989 362 2882",
    "sg:postcode":"48763",
    "sg:province":"MI",
    "sg:tags":[
        "body",
        "go"
    ],
    "wof:name":"Tawas Auto & Boat Upholstery",
    "wof:placetype":"venue"
},
  "geometry": {"coordinates":[-83.569013,44.117635],"type":"Point"}
}