{
  "type": "Feature",
  "properties": {
    "iso:country":"US",
    "sg:address":"811 S Westnedge Ave",
    "sg:city":"Kalamazoo",
    "sg:classifiers":[
        {
            "category":"Social Services",
            "type":"Services"
        }
    ],
    "sg:phone":"+1 269 349 2388",
    "sg:postcode":"49008",
    "sg:province":"MI",
    "sg:tags":[
        "youth",
        "organization",
        "center"
    ],
    "wof:name":"Vineyard Outreach",
    "wof:placetype":"venue"
},
  "geometry": {"coordinates":[-85.589495,42.283747],"type":"Point"}
}