{
  "type": "Feature",
  "properties": {
    "iso:country":"US",
    "sg:address":"4188 Terpening Rd",
    "sg:city":"Harbor Springs",
    "sg:classifiers":[
        {
            "category":"Wholesale",
            "subcategory":"Construction Materials",
            "type":"Manufacturing & Wholesale Goods"
        }
    ],
    "sg:phone":"+1 231 526 5909",
    "sg:postcode":"49740",
    "sg:province":"MI",
    "sg:tags":[
        "lumber"
    ],
    "sg:website":"www.cedarlumber.com",
    "wof:name":"Northern Forest Products",
    "wof:placetype":"venue"
},
  "geometry": {"coordinates":[-85.077988,45.490611],"type":"Point"}
}