{
  "type": "Feature",
  "properties": {
    "iso:country":"US",
    "sg:address":"30012 W 12 Mile Rd",
    "sg:city":"Farmington Hills",
    "sg:classifiers":[
        {
            "category":"Restaurant",
            "type":"Food & Drink"
        }
    ],
    "sg:phone":"+1 248 855 2230",
    "sg:postcode":"48334",
    "sg:province":"MI",
    "sg:tags":[
        "out"
    ],
    "wof:name":"Mitzi's Carry Out",
    "wof:placetype":"venue"
},
  "geometry": {"coordinates":[-83.34762600000001,42.499587],"type":"Point"}
}