{
  "type": "Feature",
  "properties": {
    "iso:country":"US",
    "sg:address":"4140 Rumsey Rd",
    "sg:city":"Pittsford",
    "sg:classifiers":[
        {
            "category":"Building & Trades",
            "subcategory":"Construction",
            "type":"Services"
        }
    ],
    "sg:phone":"+1 517 523 2315",
    "sg:postcode":"49271",
    "sg:province":"MI",
    "sg:tags":[
        "excavating",
        "contractor"
    ],
    "wof:name":"Shannon Excavating",
    "wof:placetype":"venue"
},
  "geometry": {"coordinates":[-84.49571299999999,41.866952],"type":"Point"}
}