{
  "type": "Feature",
  "properties": {
    "iso:country":"US",
    "sg:address":"7735 Lane St",
    "sg:city":"Detroit",
    "sg:classifiers":[
        {
            "category":"Education",
            "subcategory":"School",
            "type":"Public Place"
        }
    ],
    "sg:phone":"+1 313 849 2419",
    "sg:postcode":"48209",
    "sg:province":"MI",
    "wof:name":"Detroit Public Schools",
    "wof:placetype":"venue"
},
  "geometry": {"coordinates":[-83.121883,42.308285],"type":"Point"}
}