{
  "type": "Feature",
  "properties": {
    "iso:country":"US",
    "sg:address":"6245 Timberland Dr",
    "sg:city":"Dimondale",
    "sg:classifiers":[
        {
            "category":"Professional",
            "subcategory":"Business Services",
            "type":"Services"
        }
    ],
    "sg:phone":"+1 517 646 0233",
    "sg:postcode":"48821",
    "sg:province":"MI",
    "sg:tags":[
        "notary",
        "public"
    ],
    "wof:name":"Gary Brydges",
    "wof:placetype":"venue"
},
  "geometry": {"coordinates":[-84.593087,42.621724],"type":"Point"}
}