{
  "type": "Feature",
  "properties": {
    "iso:country":"US",
    "sg:address":"13899 Stephens Rd",
    "sg:city":"Warren",
    "sg:classifiers":[
        {
            "category":"Organizations",
            "subcategory":"Religious Organization",
            "type":"Services"
        }
    ],
    "sg:phone":"+1 586 772 3230",
    "sg:postcode":"48089",
    "sg:province":"MI",
    "sg:tags":[
        "church"
    ],
    "wof:name":"Gideon Baptist Church Warren",
    "wof:placetype":"venue"
},
  "geometry": {"coordinates":[-82.983301,42.471272],"type":"Point"}
}