{
  "type": "Feature",
  "properties": {
    "iso:country":"US",
    "sg:address":"125 E Columbia Ave",
    "sg:city":"Pontiac",
    "sg:classifiers":[
        {
            "category":"Home & Garden",
            "subcategory":"Building Materials",
            "type":"Retail Goods"
        }
    ],
    "sg:phone":"+1 248 334 3072",
    "sg:postcode":"48340",
    "sg:province":"MI",
    "sg:tags":[
        "roofing"
    ],
    "wof:name":"ABC Supply Co",
    "wof:placetype":"venue"
},
  "geometry": {"coordinates":[-83.29627499999999,42.670151],"type":"Point"}
}