{
  "type": "Feature",
  "properties": {
    "iso:country":"US",
    "sg:address":"7807 Kenrob Dr SE",
    "sg:city":"Grand Rapids",
    "sg:classifiers":[
        {
            "category":"Organizations",
            "subcategory":"Membership Organization",
            "type":"Services"
        }
    ],
    "sg:phone":"+1 616 940 9067",
    "sg:postcode":"49546",
    "sg:province":"MI",
    "wof:name":"Hug A Bears of Kent Count",
    "wof:placetype":"venue"
},
  "geometry": {"coordinates":[-85.474705,42.894785],"type":"Point"}
}