{
  "type": "Feature",
  "properties": {
    "iso:country":"US",
    "sg:address":"846 S Squirrel Rd",
    "sg:city":"Auburn Hills",
    "sg:classifiers":[
        {
            "category":"Building & Trades",
            "subcategory":"Landscaping Services",
            "type":"Services"
        }
    ],
    "sg:phone":"+1 248 844 0950",
    "sg:postcode":"48326",
    "sg:province":"MI",
    "sg:tags":[
        "lawn",
        "maintenance",
        "grounds"
    ],
    "wof:name":"A Cut Above Lawn Maintenance",
    "wof:placetype":"venue"
},
  "geometry": {"coordinates":[-83.223727,42.62319],"type":"Point"}
}