{
  "type": "Feature",
  "properties": {
    "iso:country":"US",
    "sg:address":"720 Lincoln Rd",
    "sg:city":"Otsego",
    "sg:classifiers":[
        {
            "category":"Autos & Motor Vehicles",
            "subcategory":"Automobile Sales",
            "type":"Retail Goods"
        }
    ],
    "sg:phone":"+1 269 692 6019",
    "sg:postcode":"49078",
    "sg:province":"MI",
    "sg:tags":[
        "car",
        "used",
        "dealer"
    ],
    "wof:name":"C & S Auto Sales",
    "wof:placetype":"venue"
},
  "geometry": {"coordinates":[-85.73862699999999,42.464667],"type":"Point"}
}