{
  "type": "Feature",
  "properties": {
    "iso:country":"US",
    "sg:address":"4113 Yankee Rd",
    "sg:city":"St Clair",
    "sg:classifiers":[
        {
            "category":"Building & Trades",
            "subcategory":"Construction",
            "type":"Services"
        }
    ],
    "sg:phone":"+1 810 300 3905",
    "sg:postcode":"48079",
    "sg:province":"MI",
    "sg:tags":[
        "general",
        "contractor"
    ],
    "wof:name":"Pro Services Unlimited Inc",
    "wof:placetype":"venue"
},
  "geometry": {"coordinates":[-82.47972300000001,42.847631],"type":"Point"}
}