{
  "type": "Feature",
  "properties": {
    "iso:country":"US",
    "sg:address":"37017 Green St",
    "sg:city":"New Baltimore",
    "sg:classifiers":[
        {
            "category":"Home & Garden",
            "subcategory":"Carpets & Floor Coverings",
            "type":"Retail Goods"
        }
    ],
    "sg:phone":"+1 586 725 2320",
    "sg:postcode":"48047",
    "sg:province":"MI",
    "sg:tags":[
        "dealer",
        "rug"
    ],
    "wof:name":"Carpet Masters",
    "wof:placetype":"venue"
},
  "geometry": {"coordinates":[-82.728549,42.68686],"type":"Point"}
}