{
  "type": "Feature",
  "properties": {
    "iso:country":"US",
    "sg:address":"115 E 14th St",
    "sg:city":"Flint",
    "sg:classifiers":[
        {
            "category":"Freight",
            "type":"Transportation"
        }
    ],
    "sg:phone":"+1 810 239 5040",
    "sg:postcode":"48503",
    "sg:province":"MI",
    "sg:tags":[
        "up",
        "recyclables"
    ],
    "wof:name":"CBC Recycling Inc",
    "wof:placetype":"venue"
},
  "geometry": {"coordinates":[-83.67811500000001,43.004819],"type":"Point"}
}