{
  "type": "Feature",
  "properties": {
    "iso:country":"US",
    "sg:address":"390 N Crooks Rd Apt 98",
    "sg:city":"Clawson",
    "sg:classifiers":[
        {
            "category":"Arts & Performance",
            "subcategory":"Music",
            "type":"Entertainment"
        }
    ],
    "sg:phone":"+1 248 298 2112",
    "sg:postcode":"48017",
    "sg:province":"MI",
    "sg:tags":[
        "band",
        "orchestra"
    ],
    "wof:name":"Christy Howard Music",
    "wof:placetype":"venue"
},
  "geometry": {"coordinates":[-83.16603000000001,42.535387],"type":"Point"}
}