{
  "type": "Feature",
  "properties": {
    "iso:country":"US",
    "sg:address":"1150 Midland Rd",
    "sg:city":"Saginaw",
    "sg:classifiers":[
        {
            "category":"Farming",
            "subcategory":"Farm",
            "type":"Manufacturing & Wholesale Goods"
        }
    ],
    "sg:phone":"+1 989 793 9839",
    "sg:postcode":"48638",
    "sg:province":"MI",
    "sg:tags":[
        "crop",
        "general"
    ],
    "wof:name":"Kim Hauman Farm",
    "wof:placetype":"venue"
},
  "geometry": {"coordinates":[-84.038517,43.415478],"type":"Point"}
}