{
  "type": "Feature",
  "properties": {
    "iso:country":"US",
    "sg:address":"8375 36th St SE",
    "sg:city":"Ada",
    "sg:classifiers":[
        {
            "category":"Sports & Exercise",
            "subcategory":"Golf",
            "type":"Entertainment"
        }
    ],
    "sg:phone":"+1 616 676 2000",
    "sg:postcode":"49301",
    "sg:province":"MI",
    "sg:tags":[
        "course",
        "public"
    ],
    "sg:website":"www.quailridgegc.com",
    "wof:name":"Quail Ridge Golf Shop",
    "wof:placetype":"venue"
},
  "geometry": {"coordinates":[-85.465807,42.899546],"type":"Point"}
}