{
  "type": "Feature",
  "properties": {
    "iso:country":"US",
    "sg:address":"1301 Woodlake Ln",
    "sg:city":"Pontiac",
    "sg:classifiers":[
        {
            "category":"Real Estate",
            "subcategory":"Real Estate Operator",
            "type":"Services"
        }
    ],
    "sg:phone":"+1 248 253 1777",
    "sg:postcode":"48340",
    "sg:province":"MI",
    "sg:tags":[
        "building",
        "apartment"
    ],
    "wof:name":"Woodlake Hills Apartments",
    "wof:placetype":"venue"
},
  "geometry": {"coordinates":[-83.30422799999999,42.683488],"type":"Point"}
}