{
  "type": "Feature",
  "properties": {
    "iso:country":"US",
    "sg:address":"707 W Lead St",
    "sg:city":"Bessemer",
    "sg:classifiers":[
        {
            "category":"Travel",
            "subcategory":"Hotels & Motels",
            "type":"Entertainment"
        }
    ],
    "sg:phone":"+1 906 667 0311",
    "sg:postcode":"49911",
    "sg:province":"MI",
    "wof:name":"Bluffs View Motel",
    "wof:placetype":"venue"
},
  "geometry": {"coordinates":[-90.062218,46.481113],"type":"Point"}
}