{
  "type": "Feature",
  "properties": {
    "iso:country":"US",
    "sg:address":"25990 Crocker Blvd",
    "sg:city":"Harrison Twp",
    "sg:classifiers":[
        {
            "category":"Home & Garden",
            "subcategory":"Hardware",
            "type":"Retail Goods"
        }
    ],
    "sg:phone":"+1 586 783 6793",
    "sg:postcode":"48045",
    "sg:province":"MI",
    "wof:name":"Sears Hardware Store",
    "wof:placetype":"venue"
},
  "geometry": {"coordinates":[-82.85216,42.572368],"type":"Point"}
}