{
  "type": "Feature",
  "properties": {
    "iso:country":"US",
    "sg:address":"1022 W Silver Lake Rd",
    "sg:city":"Fenton",
    "sg:classifiers":[
        {
            "category":"Shopping",
            "subcategory":"Clothing, Apparel, & Fashions",
            "type":"Retail Goods"
        }
    ],
    "sg:phone":"+1 810 750 3512",
    "sg:postcode":"48430",
    "sg:province":"MI",
    "wof:name":"Schenk's Apparel",
    "wof:placetype":"venue"
},
  "geometry": {"coordinates":[-83.721,42.800736],"type":"Point"}
}