{
  "type": "Feature",
  "properties": {
    "iso:country":"US",
    "sg:address":"1281 Wood Haven St",
    "sg:city":"Muskegon",
    "sg:classifiers":[
        {
            "category":"Social Services",
            "subcategory":"Child Care",
            "type":"Services"
        }
    ],
    "sg:phone":"+1 231 744 5367",
    "sg:postcode":"49445",
    "sg:province":"MI",
    "sg:tags":[
        "day",
        "provider"
    ],
    "wof:name":"Donna Jean Rillema",
    "wof:placetype":"venue"
},
  "geometry": {"coordinates":[-86.23179399999999,43.277985],"type":"Point"}
}