{
  "type": "Feature",
  "properties": {
    "iso:country":"US",
    "sg:address":"106 Locust St",
    "sg:city":"Big Rapids",
    "sg:classifiers":[
        {
            "category":"Health Services",
            "subcategory":"Doctor",
            "type":"Services"
        }
    ],
    "sg:phone":"+1 231 796 8770",
    "sg:postcode":"49307",
    "sg:province":"MI",
    "sg:tags":[
        "dentist"
    ],
    "wof:name":"Caring Family Dentistry",
    "wof:placetype":"venue"
},
  "geometry": {"coordinates":[-85.48379,43.694311],"type":"Point"}
}