{
  "type": "Feature",
  "properties": {
    "iso:country":"US",
    "sg:address":"1345 Monroe Ave NW",
    "sg:city":"Grand Rapids",
    "sg:classifiers":[
        {
            "category":"Professional",
            "subcategory":"Business Services",
            "type":"Services"
        },
        {
            "category":"Banks & Credit Unions",
            "subcategory":"Financial Services",
            "type":"Services"
        }
    ],
    "sg:phone":"+1 616 459 9417",
    "sg:postcode":"49505",
    "sg:province":"MI",
    "sg:tags":[
        "franchising"
    ],
    "wof:name":"Entrepreneur's Source",
    "wof:placetype":"venue"
},
  "geometry": {"coordinates":[-85.670714,42.987475],"type":"Point"}
}