{
  "type": "Feature",
  "properties": {
    "iso:country":"US",
    "sg:address":"857 Keystone Rd N",
    "sg:city":"Traverse City",
    "sg:classifiers":[
        {
            "category":"Building & Trades",
            "subcategory":"Plumbing",
            "type":"Services"
        }
    ],
    "sg:phone":"+1 231 947 3114",
    "sg:postcode":"49686",
    "sg:province":"MI",
    "sg:tags":[
        "heating",
        "contractor"
    ],
    "wof:name":"Comfort Heating",
    "wof:placetype":"venue"
},
  "geometry": {"coordinates":[-85.615965,44.707266],"type":"Point"}
}