{
  "type": "Feature",
  "properties": {
    "iso:country":"US",
    "sg:address":"333 W Ridge St",
    "sg:city":"Marquette",
    "sg:classifiers":[
        {
            "category":"Professional",
            "subcategory":"Accounting & Tax Preparation",
            "type":"Services"
        }
    ],
    "sg:phone":"+1 906 228 9611",
    "sg:postcode":"49855",
    "sg:province":"MI",
    "sg:tags":[
        "accountant"
    ],
    "wof:name":"Marlowe Accounting & Tax Svc",
    "wof:placetype":"venue"
},
  "geometry": {"coordinates":[-87.39926800000001,46.546175],"type":"Point"}
}