{
  "type": "Feature",
  "properties": {
    "iso:country":"US",
    "sg:address":"8964 Inkster Rd",
    "sg:city":"Romulus",
    "sg:classifiers":[
        {
            "category":"Personal",
            "type":"Services"
        }
    ],
    "sg:phone":"+1 734 946 4101",
    "sg:postcode":"48174",
    "sg:province":"MI",
    "sg:tags":[
        "towing"
    ],
    "wof:name":"J & M Towing Service",
    "wof:placetype":"venue"
},
  "geometry": {"coordinates":[-83.30819700000001,42.238998],"type":"Point"}
}