{
  "type": "Feature",
  "properties": {
    "iso:country":"US",
    "sg:address":"5005 Fulton St E",
    "sg:city":"Ada",
    "sg:classifiers":[
        {
            "category":"Shopping",
            "subcategory":"Jewelry",
            "type":"Retail Goods"
        }
    ],
    "sg:phone":"+1 616 949 2633",
    "sg:postcode":"49301",
    "sg:province":"MI",
    "wof:name":"Jonathon Jewelers Thornapple",
    "wof:placetype":"venue"
},
  "geometry": {"coordinates":[-85.545168,42.962898],"type":"Point"}
}