{
  "type": "Feature",
  "properties": {
    "iso:country":"US",
    "sg:address":"1110 E Gunn Rd",
    "sg:city":"Rochester",
    "sg:classifiers":[
        {
            "category":"Building & Trades",
            "subcategory":"Construction",
            "type":"Services"
        }
    ],
    "sg:phone":"+1 248 656 4443",
    "sg:postcode":"48306",
    "sg:province":"MI",
    "sg:tags":[
        "handyman"
    ],
    "wof:name":"Estes Park",
    "wof:placetype":"venue"
},
  "geometry": {"coordinates":[-83.111251,42.748147],"type":"Point"}
}