{
  "type": "Feature",
  "properties": {
    "iso:country":"US",
    "sg:address":"1813 Haggerty Rd",
    "sg:city":"Commerce Twp",
    "sg:classifiers":[
        {
            "category":"Wholesale",
            "subcategory":"Painting Supplies",
            "type":"Manufacturing & Wholesale Goods"
        }
    ],
    "sg:phone":"+1 248 960 9993",
    "sg:postcode":"48390",
    "sg:province":"MI",
    "sg:tags":[
        "paint"
    ],
    "wof:name":"Sherwin-Williams Paints",
    "wof:placetype":"venue"
},
  "geometry": {"coordinates":[-83.438997,42.552552],"type":"Point"}
}