{
  "type": "Feature",
  "properties": {
    "iso:country":"US",
    "sg:address":"548 Budlong St",
    "sg:city":"Adrian",
    "sg:classifiers":[
        {
            "category":"Personal",
            "subcategory":"Beauty Salon",
            "type":"Services"
        }
    ],
    "sg:phone":"+1 517 265 6140",
    "sg:postcode":"49221",
    "sg:province":"MI",
    "sg:tags":[
        "shop"
    ],
    "wof:name":"Elite Design Graphix",
    "wof:placetype":"venue"
},
  "geometry": {"coordinates":[-84.050217,41.908257],"type":"Point"}
}