{
  "type": "Feature",
  "properties": {
    "iso:country":"US",
    "sg:address":"70335 Beach Dr",
    "sg:city":"Edwardsburg",
    "sg:classifiers":[
        {
            "category":"Social Services",
            "subcategory":"Child Care",
            "type":"Services"
        }
    ],
    "sg:phone":"+1 269 663 2860",
    "sg:postcode":"49112",
    "sg:province":"MI",
    "sg:tags":[
        "day"
    ],
    "wof:name":"Garver Lake Pre-School",
    "wof:placetype":"venue"
},
  "geometry": {"coordinates":[-86.05265799999999,41.778377],"type":"Point"}
}