{
  "type": "Feature",
  "properties": {
    "iso:country":"US",
    "sg:address":"9060 Raisin St",
    "sg:city":"Maybee",
    "sg:classifiers":[
        {
            "category":"Education",
            "subcategory":"Library",
            "type":"Public Place"
        }
    ],
    "sg:phone":"+1 734 587 3680",
    "sg:postcode":"48159",
    "sg:province":"MI",
    "wof:name":"Maybee Public Library",
    "wof:placetype":"venue"
},
  "geometry": {"coordinates":[-83.515514,42.004632],"type":"Point"}
}