{
  "type": "Feature",
  "properties": {
    "iso:country":"US",
    "sg:address":"375 Watts Rd",
    "sg:city":"Jackson",
    "sg:classifiers":[
        {
            "category":"Manufacturing",
            "subcategory":"Tools & Machinery",
            "type":"Manufacturing & Wholesale Goods"
        }
    ],
    "sg:phone":"+1 517 748 9169",
    "sg:postcode":"49203",
    "sg:province":"MI",
    "sg:tags":[
        "machine",
        "shop"
    ],
    "wof:name":"Custom Machining Svc",
    "wof:placetype":"venue"
},
  "geometry": {"coordinates":[-84.355535,42.251275],"type":"Point"}
}