{
  "type": "Feature",
  "properties": {
    "iso:country":"US",
    "sg:address":"7547 Hunters Ridge Dr",
    "sg:city":"Kalamazoo",
    "sg:classifiers":[
        {
            "category":"Organizations",
            "subcategory":"Professional Association",
            "type":"Services"
        }
    ],
    "sg:phone":"+1 269 372 3144",
    "sg:postcode":"49009",
    "sg:province":"MI",
    "wof:name":"Kalamazoo Area Women's Bowling",
    "wof:placetype":"venue"
},
  "geometry": {"coordinates":[-85.653738,42.207946],"type":"Point"}
}