{
  "type": "Feature",
  "properties": {
    "iso:country":"US",
    "sg:address":"137 E Laketon Ave",
    "sg:city":"Muskegon",
    "sg:classifiers":[
        {
            "category":"Social Services",
            "type":"Services"
        }
    ],
    "sg:phone":"+1 231 726 2355",
    "sg:postcode":"49442",
    "sg:province":"MI",
    "sg:tags":[
        "information",
        "center",
        "diabetes"
    ],
    "wof:name":"Diabetic Supplies Of America",
    "wof:placetype":"venue"
},
  "geometry": {"coordinates":[-86.241463,43.219625],"type":"Point"}
}