{
  "type": "Feature",
  "properties": {
    "iso:country":"US",
    "sg:address":"26441 Ford Rd",
    "sg:city":"Dearborn Heights",
    "sg:classifiers":[
        {
            "category":"Restaurant",
            "type":"Food & Drink"
        }
    ],
    "sg:phone":"+1 313 730 0222",
    "sg:postcode":"48127",
    "sg:province":"MI",
    "sg:tags":[
        "chinese"
    ],
    "wof:name":"Dynasty Chinese Food",
    "wof:placetype":"venue"
},
  "geometry": {"coordinates":[-83.302002,42.326302],"type":"Point"}
}