{
  "type": "Feature",
  "properties": {
    "iso:country":"US",
    "sg:address":"9048 E Atherton Rd",
    "sg:city":"Davison",
    "sg:classifiers":[
        {
            "category":"Farming",
            "subcategory":"Farm",
            "type":"Manufacturing & Wholesale Goods"
        }
    ],
    "sg:phone":"+1 810 653 4916",
    "sg:postcode":"48423",
    "sg:province":"MI",
    "sg:tags":[
        "crop",
        "general"
    ],
    "wof:name":"Terry Spezia",
    "wof:placetype":"venue"
},
  "geometry": {"coordinates":[-83.539548,42.990734],"type":"Point"}
}