{
  "type": "Feature",
  "properties": {
    "iso:country":"US",
    "sg:address":"46733 Hayes Rd",
    "sg:city":"Shelby Twp",
    "sg:classifiers":[
        {
            "category":"Restaurant",
            "type":"Food & Drink"
        }
    ],
    "sg:phone":"+1 586 566 6288",
    "sg:postcode":"48315",
    "sg:province":"MI",
    "wof:name":"China Gourmet",
    "wof:placetype":"venue"
},
  "geometry": {"coordinates":[-82.973816,42.638111],"type":"Point"}
}