{
  "type": "Feature",
  "properties": {
    "iso:country":"US",
    "sg:address":"317 S Mason St",
    "sg:city":"Saginaw",
    "sg:classifiers":[
        {
            "category":"Social Services",
            "subcategory":"Child Care",
            "type":"Services"
        }
    ],
    "sg:phone":"+1 989 797 4190",
    "sg:postcode":"48602",
    "sg:province":"MI",
    "wof:name":"Armishia's Playland",
    "wof:placetype":"venue"
},
  "geometry": {"coordinates":[-83.973614,43.420209],"type":"Point"}
}