{
  "type": "Feature",
  "properties": {
    "iso:country":"US",
    "sg:address":"10058 Wiggins Rd",
    "sg:city":"Howell",
    "sg:classifiers":[
        {
            "category":"Building & Trades",
            "subcategory":"Construction",
            "type":"Services"
        }
    ],
    "sg:phone":"+1 517 546 0995",
    "sg:postcode":"48855",
    "sg:province":"MI",
    "sg:tags":[
        "excavating",
        "contractor"
    ],
    "wof:name":"Simcheck Inc",
    "wof:placetype":"venue"
},
  "geometry": {"coordinates":[-83.90649500000001,42.753596],"type":"Point"}
}