{
  "type": "Feature",
  "properties": {
    "iso:country":"US",
    "sg:address":"3338 Coolidge Hwy",
    "sg:city":"Berkley",
    "sg:classifiers":[
        {
            "category":"Government",
            "subcategory":"Court House",
            "type":"Public Place"
        }
    ],
    "sg:phone":"+1 248 544 3300",
    "sg:postcode":"48072",
    "sg:province":"MI",
    "sg:tags":[
        "city"
    ],
    "wof:name":"Berkley City District Court",
    "wof:placetype":"venue"
},
  "geometry": {"coordinates":[-83.183832,42.502886],"type":"Point"}
}