{
  "type": "Feature",
  "properties": {
    "iso:country":"US",
    "sg:address":"2879 Wisconsin Rd",
    "sg:city":"Troy",
    "sg:classifiers":[
        {
            "category":"Wholesale",
            "subcategory":"Machinery & Supplies",
            "type":"Manufacturing & Wholesale Goods"
        }
    ],
    "sg:phone":"+1 248 545 5478",
    "sg:postcode":"48083",
    "sg:province":"MI",
    "sg:tags":[
        "machine",
        "floor"
    ],
    "wof:name":"Robert Hurt",
    "wof:placetype":"venue"
},
  "geometry": {"coordinates":[-83.093886,42.545715],"type":"Point"}
}