{
  "type": "Feature",
  "properties": {
    "iso:country":"US",
    "sg:address":"518 E Shaw St",
    "sg:city":"Howard City",
    "sg:classifiers":[
        {
            "category":"Insurance",
            "subcategory":"Insurance Agent",
            "type":"Services"
        }
    ],
    "sg:phone":"+1 231 937 4141",
    "sg:postcode":"49329",
    "sg:province":"MI",
    "sg:website":"www.peaseinsurance.com",
    "wof:name":"Pease Insurance",
    "wof:placetype":"venue"
},
  "geometry": {"coordinates":[-85.463803,43.39578],"type":"Point"}
}