{
  "type": "Feature",
  "properties": {
    "iso:country":"US",
    "sg:address":"4100 Mount Hope Rd",
    "sg:city":"Grass Lake",
    "sg:classifiers":[
        {
            "category":"Manufacturing",
            "subcategory":"Rubber & Plastics",
            "type":"Manufacturing & Wholesale Goods"
        }
    ],
    "sg:phone":"+1 517 522 6734",
    "sg:postcode":"49240",
    "sg:province":"MI",
    "sg:tags":[
        "molding"
    ],
    "wof:name":"J & J Plastics",
    "wof:placetype":"venue"
},
  "geometry": {"coordinates":[-84.20452899999999,42.29448],"type":"Point"}
}