{
  "type": "Feature",
  "properties": {
    "iso:country":"US",
    "sg:address":"28531 Harper Ave",
    "sg:city":"Saint Clair Shores",
    "sg:classifiers":[
        {
            "category":"Personal",
            "subcategory":"Barber",
            "type":"Services"
        }
    ],
    "sg:phone":"+1 586 771 4395",
    "sg:postcode":"48081",
    "sg:province":"MI",
    "sg:tags":[
        "shop"
    ],
    "wof:name":"Bo Rics",
    "wof:placetype":"venue"
},
  "geometry": {"coordinates":[-82.898088,42.503725],"type":"Point"}
}