{
  "type": "Feature",
  "properties": {
    "iso:country":"US",
    "sg:address":"133 E Main St",
    "sg:city":"Flushing",
    "sg:classifiers":[
        {
            "category":"Organizations",
            "subcategory":"Professional Association",
            "type":"Services"
        }
    ],
    "sg:phone":"+1 810 659 4141",
    "sg:postcode":"48433",
    "sg:province":"MI",
    "sg:tags":[
        "chambers",
        "commerce"
    ],
    "wof:name":"Flushing Chamber Of Commerce",
    "wof:placetype":"venue"
},
  "geometry": {"coordinates":[-83.854731,43.063063],"type":"Point"}
}