{
  "type": "Feature",
  "properties": {
    "iso:country":"US",
    "sg:address":"26611 W 7 Mile Rd",
    "sg:city":"Redford",
    "sg:classifiers":[
        {
            "category":"Health Services",
            "subcategory":"Health Practitioner",
            "type":"Services"
        }
    ],
    "sg:phone":"+1 313 592 4595",
    "sg:postcode":"48240",
    "sg:province":"MI",
    "sg:tags":[
        "therapy",
        "physical"
    ],
    "wof:name":"Rehab One",
    "wof:placetype":"venue"
},
  "geometry": {"coordinates":[-83.30439800000001,42.424301],"type":"Point"}
}