{
  "type": "Feature",
  "properties": {
    "iso:country":"US",
    "sg:address":"5410 Allen Rd",
    "sg:city":"Allen Park",
    "sg:classifiers":[
        {
            "category":"Retail",
            "subcategory":"Veterinary Services",
            "type":"Services"
        }
    ],
    "sg:phone":"+1 313 254 4087",
    "sg:postcode":"48101",
    "sg:province":"MI",
    "sg:tags":[
        "pet",
        "clinic",
        "boarding/pet",
        "sitting"
    ],
    "sg:website":"www.vcaallenpark.com",
    "wof:name":"VCA Allen Park Animal Hospital",
    "wof:placetype":"venue"
},
  "geometry": {"coordinates":[-83.202369,42.263551],"type":"Point"}
}