{
  "type": "Feature",
  "properties": {
    "iso:country":"US",
    "sg:address":"140 W Jefferson St",
    "sg:city":"Dimondale",
    "sg:classifiers":[
        {
            "category":"Health Services",
            "subcategory":"Doctor",
            "type":"Services"
        }
    ],
    "sg:phone":"+1 517 646 7604",
    "sg:postcode":"48821",
    "sg:province":"MI",
    "sg:tags":[
        "osteopathic"
    ],
    "wof:name":"Joe A Westwood Do",
    "wof:placetype":"venue"
},
  "geometry": {"coordinates":[-84.65210500000001,42.644424],"type":"Point"}
}