{
  "type": "Feature",
  "properties": {
    "iso:country":"US",
    "sg:address":"37473 S Groesbeck Hwy",
    "sg:city":"Clinton Twp",
    "sg:classifiers":[
        {
            "category":"Retail",
            "subcategory":"Auto Rental",
            "type":"Services"
        }
    ],
    "sg:phone":"+1 586 463 7727",
    "sg:postcode":"48036",
    "sg:province":"MI",
    "sg:tags":[
        "renting",
        "truck",
        "leasing"
    ],
    "wof:name":"U-Haul Co",
    "wof:placetype":"venue"
},
  "geometry": {"coordinates":[-82.908631,42.573731],"type":"Point"}
}