{
  "type": "Feature",
  "properties": {
    "iso:country":"US",
    "sg:address":"1256 S Poseyville Rd",
    "sg:city":"Midland",
    "sg:classifiers":[
        {
            "category":"Food & Beverages",
            "subcategory":"Groceries & Convenience Stores",
            "type":"Retail Goods"
        }
    ],
    "sg:phone":"+1 989 631 1330",
    "sg:postcode":"48640",
    "sg:province":"MI",
    "sg:tags":[
        "grocer"
    ],
    "wof:name":"Owens Party Store",
    "wof:placetype":"venue"
},
  "geometry": {"coordinates":[-84.247753,43.576028],"type":"Point"}
}