{
  "type": "Feature",
  "properties": {
    "iso:country":"US",
    "sg:address":"6455 W Bath Rd",
    "sg:city":"Perry",
    "sg:classifiers":[
        {
            "category":"Wholesale",
            "subcategory":"Construction Materials",
            "type":"Manufacturing & Wholesale Goods"
        }
    ],
    "sg:phone":"+1 517 675 5502",
    "sg:postcode":"48872",
    "sg:province":"MI",
    "sg:tags":[
        "sand",
        "gravel"
    ],
    "wof:name":"Woodhull Construction",
    "wof:placetype":"venue"
},
  "geometry": {"coordinates":[-84.279534,42.819458],"type":"Point"}
}