{
  "type": "Feature",
  "properties": {
    "iso:country":"US",
    "sg:address":"6359 W Wilson Rd",
    "sg:city":"Clio",
    "sg:classifiers":[
        {
            "category":"Social Services",
            "subcategory":"Adult Care",
            "type":"Services"
        }
    ],
    "sg:phone":"+1 810 687 0202",
    "sg:postcode":"48420",
    "sg:province":"MI",
    "sg:tags":[
        "residential"
    ],
    "wof:name":"Kruse Kare Homes Inc",
    "wof:placetype":"venue"
},
  "geometry": {"coordinates":[-83.81118600000001,43.162609],"type":"Point"}
}