{
  "type": "Feature",
  "properties": {
    "iso:country":"US",
    "sg:address":"15479 Rockdale St",
    "sg:city":"Detroit",
    "sg:classifiers":[
        {
            "category":"Social Services",
            "subcategory":"Child Care",
            "type":"Services"
        }
    ],
    "sg:phone":"+1 313 537 9535",
    "sg:postcode":"48223",
    "sg:province":"MI",
    "sg:tags":[
        "day"
    ],
    "wof:name":"Ju's Place",
    "wof:placetype":"venue"
},
  "geometry": {"coordinates":[-83.25837300000001,42.402792],"type":"Point"}
}