{
  "type": "Feature",
  "properties": {
    "iso:country":"US",
    "sg:address":"15300 Stanley Rd",
    "sg:city":"Beulah",
    "sg:classifiers":[
        {
            "category":"Farming",
            "subcategory":"Farm & Veterinary Services",
            "type":"Manufacturing & Wholesale Goods"
        }
    ],
    "sg:phone":"+1 231 325 4410",
    "sg:postcode":"49617",
    "sg:province":"MI",
    "sg:tags":[
        "livestock"
    ],
    "wof:name":"Circle V Feeds",
    "wof:placetype":"venue"
},
  "geometry": {"coordinates":[-85.921127,44.652108],"type":"Point"}
}