{
  "type": "Feature",
  "properties": {
    "iso:country":"US",
    "sg:address":"29 Superior St",
    "sg:city":"Hillsdale",
    "sg:classifiers":[
        {
            "category":"Wholesale",
            "subcategory":"Machinery & Supplies",
            "type":"Manufacturing & Wholesale Goods"
        }
    ],
    "sg:phone":"+1 517 439 1571",
    "sg:postcode":"49242",
    "sg:province":"MI",
    "sg:tags":[
        "equipment",
        "plastic"
    ],
    "wof:name":"Bailey Manufacturing Corp",
    "wof:placetype":"venue"
},
  "geometry": {"coordinates":[-84.62096,41.920872],"type":"Point"}
}