{
  "type": "Feature",
  "properties": {
    "iso:country":"US",
    "sg:address":"18580 Dequindre St",
    "sg:city":"Detroit",
    "sg:classifiers":[
        {
            "category":"Professional",
            "subcategory":"Accounting & Tax Preparation",
            "type":"Services"
        }
    ],
    "sg:phone":"+1 313 366 0847",
    "sg:postcode":"48234",
    "sg:province":"MI",
    "sg:tags":[
        "return"
    ],
    "wof:name":"Benjamin Ozell",
    "wof:placetype":"venue"
},
  "geometry": {"coordinates":[-83.082689,42.429891],"type":"Point"}
}