{
  "type": "Feature",
  "properties": {
    "iso:country":"US",
    "sg:address":"14498 Greenfield Rd",
    "sg:city":"Detroit",
    "sg:classifiers":[
        {
            "category":"Shopping",
            "subcategory":"Clothing, Apparel, & Fashions",
            "type":"Retail Goods"
        }
    ],
    "sg:phone":"+1 313 835 1029",
    "sg:postcode":"48227",
    "sg:province":"MI",
    "sg:tags":[
        "accessory"
    ],
    "sg:website":"www.rainbowshops.com",
    "wof:name":"Rainbow Apparel",
    "wof:placetype":"venue"
},
  "geometry": {"coordinates":[-83.198224,42.394272],"type":"Point"}
}