{
  "type": "Feature",
  "properties": {
    "iso:country":"US",
    "sg:address":"4534 Homestead Ln",
    "sg:city":"Portage",
    "sg:classifiers":[
        {
            "category":"Autos & Motor Vehicles",
            "subcategory":"Auto Supplies",
            "type":"Retail Goods"
        }
    ],
    "sg:phone":"+1 269 327 0345",
    "sg:postcode":"49024",
    "sg:province":"MI",
    "sg:tags":[
        "filter",
        "gas"
    ],
    "wof:name":"Steinfeld Manufacturing",
    "wof:placetype":"venue"
},
  "geometry": {"coordinates":[-85.64397700000001,42.19088],"type":"Point"}
}