{
  "type": "Feature",
  "properties": {
    "iso:country":"US",
    "sg:address":"1481 Baldwin St",
    "sg:city":"Jenison",
    "sg:classifiers":[
        {
            "category":"Organizations",
            "subcategory":"Religious Organization",
            "type":"Services"
        }
    ],
    "sg:phone":"+1 616 457 2420",
    "sg:postcode":"49428",
    "sg:province":"MI",
    "sg:tags":[
        "church"
    ],
    "sg:website":"www.holycrossjenison.org",
    "wof:name":"Holy Cross Lutheran Church",
    "wof:placetype":"venue"
},
  "geometry": {"coordinates":[-85.819937,42.907156],"type":"Point"}
}