{
  "type": "Feature",
  "properties": {
    "iso:country":"US",
    "sg:address":"11055 W Pierce Rd",
    "sg:city":"Sumner",
    "sg:classifiers":[
        {
            "category":"Insurance",
            "subcategory":"Insurance Agent",
            "type":"Services"
        }
    ],
    "sg:phone":"+1 989 584 3120",
    "sg:postcode":"48889",
    "sg:province":"MI",
    "wof:name":"ABE Construction",
    "wof:placetype":"venue"
},
  "geometry": {"coordinates":[-84.820751,43.263428],"type":"Point"}
}