{
  "type": "Feature",
  "properties": {
    "iso:country":"US",
    "sg:address":"1510 N Elms Rd",
    "sg:city":"Flint",
    "sg:classifiers":[
        {
            "category":"Insurance",
            "subcategory":"Hazard Insurance",
            "type":"Services"
        },
        {
            "category":"Insurance",
            "subcategory":"Insurance Agent",
            "type":"Services"
        }
    ],
    "sg:phone":"+1 810 733 2300",
    "sg:postcode":"48532",
    "sg:province":"MI",
    "sg:tags":[
        "adjuster",
        "property",
        "co",
        "casualty"
    ],
    "wof:name":"Pioneer State Mutual Insurance",
    "wof:placetype":"venue"
},
  "geometry": {"coordinates":[-83.81264899999999,43.030601],"type":"Point"}
}