{
  "type": "Feature",
  "properties": {
    "iso:country":"US",
    "sg:address":"5100 Inkster Rd",
    "sg:city":"Bloomfield Hills",
    "sg:classifiers":[
        {
            "category":"Organizations",
            "subcategory":"Professional Association",
            "type":"Services"
        }
    ],
    "sg:phone":"+1 248 626 9310",
    "sg:postcode":"48302",
    "sg:province":"MI",
    "wof:name":"Lone Pine Assn",
    "wof:placetype":"venue"
},
  "geometry": {"coordinates":[-83.322743,42.567231],"type":"Point"}
}