{
  "type": "Feature",
  "properties": {
    "iso:country":"US",
    "sg:address":"62 S Monroe St NE",
    "sg:city":"Rockford",
    "sg:classifiers":[
        {
            "category":"Building & Trades",
            "subcategory":"Construction",
            "type":"Services"
        }
    ],
    "sg:phone":"+1 616 866 4041",
    "sg:postcode":"49341",
    "sg:province":"MI",
    "sg:tags":[
        "contractor"
    ],
    "wof:name":"Mark Belcher Drywall",
    "wof:placetype":"venue"
},
  "geometry": {"coordinates":[-85.558092,43.118253],"type":"Point"}
}