{
  "type": "Feature",
  "properties": {
    "iso:country":"US",
    "sg:address":"1262 N Macomb St",
    "sg:city":"Monroe",
    "sg:classifiers":[
        {
            "category":"Health Services",
            "subcategory":"Doctor",
            "type":"Services"
        }
    ],
    "sg:phone":"+1 734 242 3055",
    "sg:postcode":"48162",
    "sg:province":"MI",
    "sg:tags":[
        "medical"
    ],
    "wof:name":"John W Freud MD",
    "wof:placetype":"venue"
},
  "geometry": {"coordinates":[-83.38619,41.930186],"type":"Point"}
}