{
  "type": "Feature",
  "properties": {
    "iso:country":"US",
    "sg:address":"151 Wayne St",
    "sg:city":"Bronson",
    "sg:classifiers":[
        {
            "category":"Real Estate",
            "subcategory":"Real Estate Operator",
            "type":"Services"
        }
    ],
    "sg:phone":"+1 517 369 7184",
    "sg:postcode":"49028",
    "sg:province":"MI",
    "sg:tags":[
        "apartment"
    ],
    "wof:name":"Fieldcrest Apartments",
    "wof:placetype":"venue"
},
  "geometry": {"coordinates":[-85.184994,41.872721],"type":"Point"}
}