{
  "type": "Feature",
  "properties": {
    "iso:country":"US",
    "sg:address":"318 W Wright Ave",
    "sg:city":"Shepherd",
    "sg:classifiers":[
        {
            "category":"Health Services",
            "subcategory":"Doctor",
            "type":"Services"
        }
    ],
    "sg:phone":"+1 989 828 4700",
    "sg:postcode":"48883",
    "sg:province":"MI",
    "sg:tags":[
        "physician",
        "surgeon"
    ],
    "wof:name":"Charles G Artinian MD",
    "wof:placetype":"venue"
},
  "geometry": {"coordinates":[-84.69664299999999,43.524396],"type":"Point"}
}