{
  "type": "Feature",
  "properties": {
    "iso:country":"US",
    "sg:address":"605 5th Ave",
    "sg:city":"Menominee",
    "sg:classifiers":[
        {
            "category":"Social Services",
            "subcategory":"Adult Care",
            "type":"Services"
        }
    ],
    "sg:phone":"+1 906 863 8265",
    "sg:postcode":"49858",
    "sg:province":"MI",
    "sg:tags":[
        "foster"
    ],
    "wof:name":"Kutha South",
    "wof:placetype":"venue"
},
  "geometry": {"coordinates":[-87.60923200000001,45.102831],"type":"Point"}
}