{
  "type": "Feature",
  "properties": {
    "iso:country":"US",
    "sg:address":"323 S Stephenson Ave",
    "sg:city":"Iron Mountain",
    "sg:classifiers":[
        {
            "category":"Personal",
            "subcategory":"Beauty Salon",
            "type":"Services"
        }
    ],
    "sg:phone":"+1 906 779 1495",
    "sg:postcode":"49801",
    "sg:province":"MI",
    "sg:tags":[
        "shop"
    ],
    "wof:name":"Salon 323",
    "wof:placetype":"venue"
},
  "geometry": {"coordinates":[-88.06551,45.820071],"type":"Point"}
}