{
  "type": "Feature",
  "properties": {
    "iso:country":"US",
    "sg:address":"1847 N Main St",
    "sg:city":"Royal Oak",
    "sg:classifiers":[
        {
            "category":"Professional",
            "subcategory":"Art Services",
            "type":"Services"
        },
        {
            "category":"Manufacturing",
            "subcategory":"Printing",
            "type":"Manufacturing & Wholesale Goods"
        }
    ],
    "sg:phone":"+1 248 585 1584",
    "sg:postcode":"48073",
    "sg:province":"MI",
    "sg:tags":[
        "graphic",
        "design",
        "designer",
        "typesetting"
    ],
    "sg:website":"www.firsteditiongraphics.com",
    "wof:name":"First Edition Graphics Inc",
    "wof:placetype":"venue"
},
  "geometry": {"coordinates":[-83.145043,42.505097],"type":"Point"}
}