{
  "type": "Feature",
  "properties": {
    "iso:country":"US",
    "sg:address":"7024 State Rd",
    "sg:city":"East Lansing",
    "sg:classifiers":[
        {
            "category":"Autos & Motor Vehicles",
            "subcategory":"Boat Sales",
            "type":"Retail Goods"
        }
    ],
    "sg:phone":"+1 517 339 1760",
    "sg:postcode":"48823",
    "sg:province":"MI",
    "wof:name":"Great Lakes Potter Sailboats",
    "wof:placetype":"venue"
},
  "geometry": {"coordinates":[-84.425465,42.784155],"type":"Point"}
}