{
  "type": "Feature",
  "properties": {
    "iso:country":"US",
    "sg:address":"2806 W Carleton Rd",
    "sg:city":"Hillsdale",
    "sg:classifiers":[
        {
            "category":"Health Services",
            "subcategory":"Chiropractor",
            "type":"Services"
        }
    ],
    "sg:phone":"+1 517 437 4785",
    "sg:postcode":"49242",
    "sg:province":"MI",
    "wof:name":"Family Chiropractic Life Ctr",
    "wof:placetype":"venue"
},
  "geometry": {"coordinates":[-84.646733,41.939489],"type":"Point"}
}