{
  "type": "Feature",
  "properties": {
    "iso:country":"US",
    "sg:address":"2420 Walce Dr",
    "sg:city":"West Bloomfield",
    "sg:classifiers":[
        {
            "category":"Personal",
            "subcategory":"Beauty Salon",
            "type":"Services"
        }
    ],
    "sg:phone":"+1 248 681 0520",
    "sg:postcode":"48324",
    "sg:province":"MI",
    "sg:tags":[
        "shop"
    ],
    "wof:name":"Hair Consulting",
    "wof:placetype":"venue"
},
  "geometry": {"coordinates":[-83.33255800000001,42.607423],"type":"Point"}
}