{
  "type": "Feature",
  "properties": {
    "iso:country":"US",
    "sg:address":"7338 S Lincoln Rd",
    "sg:city":"Shepherd",
    "sg:classifiers":[
        {
            "category":"Professional",
            "subcategory":"Business Services",
            "type":"Services"
        }
    ],
    "sg:phone":"+1 989 828 7338",
    "sg:postcode":"48883",
    "sg:province":"MI",
    "wof:name":"Miracle Water Treatment",
    "wof:placetype":"venue"
},
  "geometry": {"coordinates":[-84.80737499999999,43.537008],"type":"Point"}
}