{
  "type": "Feature",
  "properties": {
    "iso:country":"US",
    "sg:address":"114 Division Ave N",
    "sg:city":"Grand Rapids",
    "sg:classifiers":[
        {
            "category":"Building & Trades",
            "subcategory":"Landscaping Services",
            "type":"Services"
        }
    ],
    "sg:phone":"+1 616 459 4148",
    "sg:postcode":"49503",
    "sg:province":"MI",
    "sg:tags":[
        "lawn",
        "maintenance",
        "grounds"
    ],
    "wof:name":"K L Lawn Sprinkling",
    "wof:placetype":"venue"
},
  "geometry": {"coordinates":[-85.667922,42.966081],"type":"Point"}
}