{
  "type": "Feature",
  "properties": {
    "iso:country":"US",
    "sg:address":"5180 Glenwood Creek",
    "sg:city":"Clarkston",
    "sg:classifiers":[
        {
            "category":"Banks & Credit Unions",
            "subcategory":"Investment Brokerage",
            "type":"Services"
        }
    ],
    "sg:phone":"+1 248 391 0151",
    "sg:postcode":"48348",
    "sg:province":"MI",
    "wof:name":"Jireh Investment Corp",
    "wof:placetype":"venue"
},
  "geometry": {"coordinates":[-83.363812,42.732074],"type":"Point"}
}