{
  "type": "Feature",
  "properties": {
    "iso:country":"US",
    "sg:address":"511 W Park Dr",
    "sg:city":"Rogers City",
    "sg:classifiers":[
        {
            "category":"Home & Garden",
            "subcategory":"Building Materials",
            "type":"Retail Goods"
        }
    ],
    "sg:phone":"+1 989 734 7666",
    "sg:postcode":"49779",
    "sg:province":"MI",
    "sg:tags":[
        "mixed",
        "concrete"
    ],
    "wof:name":"Lee's Ready Mix",
    "wof:placetype":"venue"
},
  "geometry": {"coordinates":[-83.81528400000001,45.409516],"type":"Point"}
}