{
  "type": "Feature",
  "properties": {
    "iso:country":"US",
    "sg:address":"23100 Providence Dr",
    "sg:city":"Southfield",
    "sg:classifiers":[
        {
            "category":"Health Services",
            "subcategory":"Hospital",
            "type":"Services"
        }
    ],
    "sg:phone":"+1 248 424 8900",
    "sg:postcode":"48075",
    "sg:province":"MI",
    "sg:tags":[
        "mental"
    ],
    "wof:name":"Behavioral Compliance Svc",
    "wof:placetype":"venue"
},
  "geometry": {"coordinates":[-83.20684300000001,42.459994],"type":"Point"}
}