{
  "type": "Feature",
  "properties": {
    "iso:country":"US",
    "sg:address":"115 Haggerty Rd",
    "sg:city":"Canton",
    "sg:classifiers":[
        {
            "category":"Banks & Credit Unions",
            "subcategory":"Financial Services",
            "type":"Services"
        }
    ],
    "sg:phone":"+1 734 453 7749",
    "sg:postcode":"48187",
    "sg:province":"MI",
    "sg:tags":[
        "investor"
    ],
    "wof:name":"Cervi Investments Inc",
    "wof:placetype":"venue"
},
  "geometry": {"coordinates":[-83.44843299999999,42.30945],"type":"Point"}
}