{
  "type": "Feature",
  "properties": {
    "iso:country":"US",
    "sg:address":"51667 Oro",
    "sg:city":"Shelby Twp",
    "sg:classifiers":[
        {
            "category":"Autos & Motor Vehicles",
            "subcategory":"Recreational Vehicle Sales",
            "type":"Retail Goods"
        }
    ],
    "sg:phone":"+1 586 247 6480",
    "sg:postcode":"48315",
    "sg:province":"MI",
    "wof:name":"D Rv Joint Sealant Contractors",
    "wof:placetype":"venue"
},
  "geometry": {"coordinates":[-82.986248,42.671751],"type":"Point"}
}