{
  "type": "Feature",
  "properties": {
    "iso:country":"US",
    "sg:address":"5750 James Dr",
    "sg:city":"Stevensville",
    "sg:classifiers":[
        {
            "category":"Real Estate",
            "subcategory":"Real Estate Agent",
            "type":"Services"
        }
    ],
    "sg:phone":"+1 269 429 8001",
    "sg:postcode":"49127",
    "sg:province":"MI",
    "wof:name":"Core Real Estate Inc",
    "wof:placetype":"venue"
},
  "geometry": {"coordinates":[-86.49679500000001,42.013086],"type":"Point"}
}