{
  "type": "Feature",
  "properties": {
    "iso:country":"US",
    "sg:address":"581 Kimole Ln",
    "sg:city":"Adrian",
    "sg:classifiers":[
        {
            "category":"Health Services",
            "subcategory":"Nursing And Care Facility",
            "type":"Services"
        }
    ],
    "sg:phone":"+1 517 266 0943",
    "sg:postcode":"49221",
    "sg:province":"MI",
    "sg:tags":[
        "intermediate",
        "convalescent",
        "home"
    ],
    "wof:name":"Charlotte Stephenson Manor",
    "wof:placetype":"venue"
},
  "geometry": {"coordinates":[-84.048329,41.91461],"type":"Point"}
}