{
  "type": "Feature",
  "properties": {
    "iso:country":"US",
    "sg:address":"209 S Franklin St",
    "sg:city":"Saint Louis",
    "sg:classifiers":[
        {
            "category":"Social Services",
            "subcategory":"Adult Care",
            "type":"Services"
        }
    ],
    "sg:phone":"+1 989 681 2279",
    "sg:postcode":"48880",
    "sg:province":"MI",
    "sg:tags":[
        "foster",
        "provider"
    ],
    "wof:name":"Alspaugh Wesley & Sharla",
    "wof:placetype":"venue"
},
  "geometry": {"coordinates":[-84.60549399999999,43.406101],"type":"Point"}
}