{
  "type": "Feature",
  "properties": {
    "iso:country":"US",
    "sg:address":"4100 Greenway Ave",
    "sg:city":"Royal Oak",
    "sg:classifiers":[
        {
            "category":"Building & Trades",
            "subcategory":"Construction",
            "type":"Services"
        }
    ],
    "sg:phone":"+1 248 554 9740",
    "sg:postcode":"48073",
    "sg:province":"MI",
    "sg:tags":[
        "house"
    ],
    "wof:name":"Digital Construction Inc",
    "wof:placetype":"venue"
},
  "geometry": {"coordinates":[-83.180274,42.522568],"type":"Point"}
}