{
  "type": "Feature",
  "properties": {
    "iso:country":"US",
    "sg:address":"301 N Bailey St",
    "sg:city":"Romeo",
    "sg:classifiers":[
        {
            "category":"Retail",
            "subcategory":"Repair Shop",
            "type":"Services"
        }
    ],
    "sg:phone":"+1 586 752 9526",
    "sg:postcode":"48065",
    "sg:province":"MI",
    "sg:tags":[
        "blacksmith"
    ],
    "wof:name":"Blacksmith Shop Clyde Craig",
    "wof:placetype":"venue"
},
  "geometry": {"coordinates":[-83.01195800000001,42.808057],"type":"Point"}
}