{
  "type": "Feature",
  "properties": {
    "iso:country":"US",
    "sg:address":"3415 Alexander St",
    "sg:city":"Lewiston",
    "sg:classifiers":[
        {
            "category":"Wholesale",
            "subcategory":"Vending Machines",
            "type":"Manufacturing & Wholesale Goods"
        }
    ],
    "sg:phone":"+1 989 786 4288",
    "sg:postcode":"49756",
    "sg:province":"MI",
    "sg:tags":[
        "operator"
    ],
    "wof:name":"J C Vending",
    "wof:placetype":"venue"
},
  "geometry": {"coordinates":[-84.308222,44.887555],"type":"Point"}
}