{
  "type": "Feature",
  "properties": {
    "iso:country":"US",
    "sg:address":"36745 Groesbeck Hwy",
    "sg:city":"Clinton Twp",
    "sg:classifiers":[
        {
            "category":"Retail",
            "subcategory":"Portrait Studio",
            "type":"Services"
        }
    ],
    "sg:phone":"+1 586 790 3686",
    "sg:postcode":"48035",
    "sg:province":"MI",
    "sg:tags":[
        "photographer"
    ],
    "wof:name":"Elite Photographic",
    "wof:placetype":"venue"
},
  "geometry": {"coordinates":[-82.912342,42.569137],"type":"Point"}
}