{
  "type": "Feature",
  "properties": {
    "iso:country":"US",
    "sg:address":"5231 W Brookshire St",
    "sg:city":"Monroe",
    "sg:classifiers":[
        {
            "category":"Building & Trades",
            "subcategory":"Construction",
            "type":"Services"
        }
    ],
    "sg:phone":"+1 734 384 2954",
    "sg:postcode":"48161",
    "sg:province":"MI",
    "sg:tags":[
        "concrete",
        "contractor"
    ],
    "wof:name":"JMJ Concrete",
    "wof:placetype":"venue"
},
  "geometry": {"coordinates":[-83.424655,41.886593],"type":"Point"}
}