{
  "type": "Feature",
  "properties": {
    "iso:country":"US",
    "sg:address":"116 E Adrian St",
    "sg:city":"Blissfield",
    "sg:classifiers":[
        {
            "category":"Home & Garden",
            "subcategory":"Garden Supply",
            "type":"Retail Goods"
        }
    ],
    "sg:phone":"+1 517 486 3104",
    "sg:postcode":"49228",
    "sg:province":"MI",
    "sg:tags":[
        "lawn",
        "mower"
    ],
    "wof:name":"Bill's Service",
    "wof:placetype":"venue"
},
  "geometry": {"coordinates":[-83.86219,41.832235],"type":"Point"}
}