{
  "type": "Feature",
  "properties": {
    "iso:country":"US",
    "sg:address":"107 5th St",
    "sg:city":"Calumet",
    "sg:classifiers":[
        {
            "category":"Insurance",
            "subcategory":"Insurance Agent",
            "type":"Services"
        }
    ],
    "sg:phone":"+1 906 337 0491",
    "sg:postcode":"49913",
    "sg:province":"MI",
    "wof:name":"Acordia",
    "wof:placetype":"venue"
},
  "geometry": {"coordinates":[-88.452696,47.245244],"type":"Point"}
}