{
  "type": "Feature",
  "properties": {
    "iso:country":"US",
    "sg:address":"18309 Johnson Rd",
    "sg:city":"Stanwood",
    "sg:classifiers":[
        {
            "category":"Social Services",
            "subcategory":"Adult Care",
            "type":"Services"
        }
    ],
    "sg:phone":"+1 231 823 2486",
    "sg:postcode":"49346",
    "sg:province":"MI",
    "sg:tags":[
        "residential",
        "repair"
    ],
    "wof:name":"Diane Ryder",
    "wof:placetype":"venue"
},
  "geometry": {"coordinates":[-85.445375,43.602246],"type":"Point"}
}