{
  "type": "Feature",
  "properties": {
    "iso:country":"US",
    "sg:address":"16440 Northview St",
    "sg:city":"Roseville",
    "sg:classifiers":[
        {
            "category":"Organizations",
            "subcategory":"Professional Association",
            "type":"Services"
        }
    ],
    "sg:phone":"+1 586 776 2309",
    "sg:postcode":"48066",
    "sg:province":"MI",
    "wof:name":"Ubc Retiree Club No 14",
    "wof:placetype":"venue"
},
  "geometry": {"coordinates":[-82.953164,42.503967],"type":"Point"}
}