{
  "type": "Feature",
  "properties": {
    "iso:country":"US",
    "sg:address":"1505 Sheridan Rd",
    "sg:city":"Escanaba",
    "sg:classifiers":[
        {
            "category":"Building & Trades",
            "subcategory":"Construction",
            "type":"Services"
        }
    ],
    "sg:phone":"+1 906 786 4595",
    "sg:postcode":"49829",
    "sg:province":"MI",
    "sg:tags":[
        "excavating",
        "contractor"
    ],
    "wof:name":"Marvic Construction Inc",
    "wof:placetype":"venue"
},
  "geometry": {"coordinates":[-87.06922299999999,45.765971],"type":"Point"}
}