{
  "type": "Feature",
  "properties": {
    "iso:country":"US",
    "sg:address":"39763 Jefferson Ave",
    "sg:city":"Harrison Twp",
    "sg:classifiers":[
        {
            "category":"Professional",
            "subcategory":"Business Services",
            "type":"Services"
        }
    ],
    "sg:phone":"+1 586 954 0255",
    "sg:postcode":"48045",
    "sg:province":"MI",
    "sg:tags":[
        "embroidery"
    ],
    "wof:name":"Holly Jene Designs",
    "wof:placetype":"venue"
},
  "geometry": {"coordinates":[-82.80946299999999,42.594117],"type":"Point"}
}