{
  "type": "Feature",
  "properties": {
    "iso:country":"US",
    "sg:address":"1640 Charleston Ave",
    "sg:city":"Pontiac",
    "sg:classifiers":[
        {
            "category":"Retail",
            "subcategory":"Auto Repair",
            "type":"Services"
        }
    ],
    "sg:phone":"+1 248 758 0064",
    "sg:postcode":"48340",
    "sg:province":"MI",
    "sg:tags":[
        "body"
    ],
    "wof:name":"Vasquezs Bodyshop",
    "wof:placetype":"venue"
},
  "geometry": {"coordinates":[-83.313219,42.682054],"type":"Point"}
}