{
  "type": "Feature",
  "properties": {
    "iso:country":"US",
    "sg:address":"400 N Rose St",
    "sg:city":"Mount Clemens",
    "sg:classifiers":[
        {
            "category":"Education",
            "subcategory":"School",
            "type":"Public Place"
        }
    ],
    "sg:phone":"+1 586 469 6552",
    "sg:postcode":"48043",
    "sg:province":"MI",
    "wof:name":"L'anse Creuse Public Schools",
    "wof:placetype":"venue"
},
  "geometry": {"coordinates":[-82.894774,42.61357],"type":"Point"}
}