{
  "type": "Feature",
  "properties": {
    "iso:country":"US",
    "sg:address":"3710 Davison Rd",
    "sg:city":"Flint",
    "sg:classifiers":[
        {
            "category":"Health Services",
            "subcategory":"Doctor",
            "type":"Services"
        }
    ],
    "sg:phone":"+1 810 742 6600",
    "sg:postcode":"48506",
    "sg:province":"MI",
    "sg:tags":[
        "dentist"
    ],
    "wof:name":"Advanced Dental Care",
    "wof:placetype":"venue"
},
  "geometry": {"coordinates":[-83.638046,43.033102],"type":"Point"}
}