{
  "type": "Feature",
  "properties": {
    "iso:country":"US",
    "sg:address":"5366 Hunters Creek Rd",
    "sg:city":"Imlay City",
    "sg:classifiers":[
        {
            "category":"Manufacturing",
            "subcategory":"Tools & Machinery",
            "type":"Manufacturing & Wholesale Goods"
        }
    ],
    "sg:phone":"+1 810 724 3808",
    "sg:postcode":"48444",
    "sg:province":"MI",
    "sg:tags":[
        "machine",
        "shop"
    ],
    "wof:name":"Wilhelm Tool",
    "wof:placetype":"venue"
},
  "geometry": {"coordinates":[-83.126856,42.989866],"type":"Point"}
}