{
  "type": "Feature",
  "properties": {
    "iso:country":"US",
    "sg:address":"210 N Public Sq",
    "sg:city":"Angola",
    "sg:classifiers":[
        {
            "category":"Government",
            "subcategory":"Office",
            "type":"Public Place"
        }
    ],
    "sg:phone":"+1 260 665 3422",
    "sg:postcode":"46703",
    "sg:province":"MI",
    "sg:tags":[
        "village"
    ],
    "wof:name":"Angola City Water Sewage Svc",
    "wof:placetype":"venue"
},
  "geometry": {"coordinates":[-84.999391,41.634909],"type":"Point"}
}