{
  "type": "Feature",
  "properties": {
    "iso:country":"US",
    "sg:address":"1230 Cleaver Rd",
    "sg:city":"Caro",
    "sg:classifiers":[
        {
            "category":"Banks & Credit Unions",
            "subcategory":"Bank",
            "type":"Services"
        }
    ],
    "sg:phone":"+1 989 673 2042",
    "sg:postcode":"48723",
    "sg:province":"MI",
    "wof:name":"Team One Credit Union",
    "wof:placetype":"venue"
},
  "geometry": {"coordinates":[-83.387578,43.500637],"type":"Point"}
}