{
  "type": "Feature",
  "properties": {
    "iso:country":"US",
    "sg:address":"373 Minnesota Dr",
    "sg:city":"Troy",
    "sg:classifiers":[
        {
            "category":"Manufacturing",
            "subcategory":"Printing",
            "type":"Manufacturing & Wholesale Goods"
        }
    ],
    "sg:phone":"+1 248 307 9070",
    "sg:postcode":"48083",
    "sg:province":"MI",
    "sg:tags":[
        "printer"
    ],
    "wof:name":"Print Parameters",
    "wof:placetype":"venue"
},
  "geometry": {"coordinates":[-83.096053,42.535801],"type":"Point"}
}