{
  "type": "Feature",
  "properties": {
    "iso:country":"US",
    "sg:address":"5709 Hessen Rd",
    "sg:city":"Casco",
    "sg:classifiers":[
        {
            "category":"Building & Trades",
            "subcategory":"Construction",
            "type":"Services"
        }
    ],
    "sg:phone":"+1 586 727 4443",
    "sg:postcode":"48064",
    "sg:province":"MI",
    "sg:tags":[
        "contractor"
    ],
    "wof:name":"Ferqueron Builders Inc",
    "wof:placetype":"venue"
},
  "geometry": {"coordinates":[-82.650946,42.735315],"type":"Point"}
}