{
  "type": "Feature",
  "properties": {
    "iso:country":"US",
    "sg:address":"4147 Stoneleigh Rd",
    "sg:city":"Bloomfield Hills",
    "sg:classifiers":[
        {
            "category":"Banks & Credit Unions",
            "subcategory":"Investment Brokerage",
            "type":"Services"
        }
    ],
    "sg:phone":"+1 248 594 6472",
    "sg:postcode":"48302",
    "sg:province":"MI",
    "wof:name":"Crescent Financial Services",
    "wof:placetype":"venue"
},
  "geometry": {"coordinates":[-83.272974,42.580296],"type":"Point"}
}