{
  "type": "Feature",
  "properties": {
    "iso:country":"US",
    "sg:address":"908 Emerson Dr",
    "sg:city":"Troy",
    "sg:classifiers":[
        {
            "category":"Professional",
            "type":"Services"
        }
    ],
    "sg:phone":"+1 248 273 1388",
    "sg:postcode":"48084",
    "sg:province":"MI",
    "sg:tags":[
        "establishment"
    ],
    "wof:name":"Skr Technologies",
    "wof:placetype":"venue"
},
  "geometry": {"coordinates":[-83.166369,42.566505],"type":"Point"}
}