{
  "type": "Feature",
  "properties": {
    "iso:country":"US",
    "sg:address":"2529 Highview Dr",
    "sg:city":"Lapeer",
    "sg:classifiers":[
        {
            "category":"Freight",
            "type":"Transportation"
        }
    ],
    "sg:phone":"+1 810 667 7222",
    "sg:postcode":"48446",
    "sg:province":"MI",
    "sg:tags":[
        "operator",
        "local",
        "trucking"
    ],
    "wof:name":"Harris Trucking",
    "wof:placetype":"venue"
},
  "geometry": {"coordinates":[-83.244219,43.062646],"type":"Point"}
}