{
  "type": "Feature",
  "properties": {
    "iso:country":"US",
    "sg:address":"64 Michigan Ave E",
    "sg:city":"Battle Creek",
    "sg:classifiers":[
        {
            "category":"Professional",
            "subcategory":"Management & Consulting",
            "type":"Services"
        }
    ],
    "sg:phone":"+1 269 288 4300",
    "sg:postcode":"49017",
    "sg:province":"MI",
    "sg:tags":[
        "engineering",
        "telecommunication"
    ],
    "wof:name":"Bcr Network Services Inc",
    "wof:placetype":"venue"
},
  "geometry": {"coordinates":[-85.179947,42.316603],"type":"Point"}
}