{
  "type": "Feature",
  "properties": {
    "iso:country":"US",
    "sg:address":"23536 Recreation St",
    "sg:city":"St Clair Shores",
    "sg:classifiers":[
        {
            "category":"Building & Trades",
            "subcategory":"Plumbing",
            "type":"Services"
        }
    ],
    "sg:phone":"+1 586 294 4848",
    "sg:postcode":"48082",
    "sg:province":"MI",
    "sg:tags":[
        "heating",
        "contractor"
    ],
    "wof:name":"RJL Heating & Cooling",
    "wof:placetype":"venue"
},
  "geometry": {"coordinates":[-82.873755,42.530791],"type":"Point"}
}