{
  "type": "Feature",
  "properties": {
    "iso:country":"US",
    "sg:address":"212 Abbott St",
    "sg:city":"Cheboygan",
    "sg:classifiers":[
        {
            "category":"Food & Beverages",
            "subcategory":"Meat & Fish",
            "type":"Retail Goods"
        }
    ],
    "sg:phone":"+1 231 627 7125",
    "sg:postcode":"49721",
    "sg:province":"MI",
    "wof:name":"Midwest Buffalo",
    "wof:placetype":"venue"
},
  "geometry": {"coordinates":[-84.467304,45.639985],"type":"Point"}
}