{
  "type": "Feature",
  "properties": {
    "iso:country":"US",
    "sg:address":"8111 Old US Hwy 23",
    "sg:city":"Fenton",
    "sg:classifiers":[
        {
            "category":"Real Estate",
            "subcategory":"Real Estate Agent",
            "type":"Services"
        }
    ],
    "sg:phone":"+1 810 750 1370",
    "sg:postcode":"48430",
    "sg:province":"MI",
    "wof:name":"Sell Fast Realty",
    "wof:placetype":"venue"
},
  "geometry": {"coordinates":[-83.763918,42.727605],"type":"Point"}
}