{
  "type": "Feature",
  "properties": {
    "iso:country":"US",
    "sg:address":"3900 W US Hwy 10",
    "sg:city":"Ludington",
    "sg:classifiers":[
        {
            "category":"Utilities",
            "subcategory":"Mobile Phone",
            "type":"Services"
        }
    ],
    "sg:phone":"+1 231 845 7876",
    "sg:postcode":"49431",
    "sg:province":"MI",
    "sg:tags":[
        "telephone",
        "cellular"
    ],
    "wof:name":"NPI Wireless",
    "wof:placetype":"venue"
},
  "geometry": {"coordinates":[-86.37258,43.956179],"type":"Point"}
}