{
  "type": "Feature",
  "properties": {
    "iso:country":"US",
    "sg:address":"14468 Wuoksi Ave",
    "sg:city":"Kaleva",
    "sg:classifiers":[
        {
            "category":"Food & Beverages",
            "subcategory":"Groceries & Convenience Stores",
            "type":"Retail Goods"
        }
    ],
    "sg:phone":"+1 231 362 3213",
    "sg:postcode":"49645",
    "sg:province":"MI",
    "sg:tags":[
        "grocer"
    ],
    "wof:name":"Kaleva's Country Mart",
    "wof:placetype":"venue"
},
  "geometry": {"coordinates":[-86.009362,44.373499],"type":"Point"}
}