{
  "type": "Feature",
  "properties": {
    "iso:country":"US",
    "sg:address":"27000 Sheraton Dr",
    "sg:city":"Novi",
    "sg:classifiers":[
        {
            "category":"Travel",
            "subcategory":"Hotels & Motels",
            "type":"Entertainment"
        },
        {
            "category":"Retail",
            "subcategory":"Event Space",
            "type":"Services"
        },
        {
            "category":"Travel",
            "subcategory":"Resort",
            "type":"Entertainment"
        }
    ],
    "sg:phone":"+1 877 270 1412",
    "sg:postcode":"48377",
    "sg:province":"MI",
    "sg:tags":[
        "hall",
        "lodging",
        "banquet",
        "reception",
        "facility"
    ],
    "sg:website":"http://ad.doubleclick.net/clk;222817048;46581824;l?http://www.crowneplaza.com/redirect?path=hd&brandCode=cp&hotelCode=novmi&_PMID=99601036&cm_mmc=mdpr-_-yellowpages-_-cp-_-novmi",
    "wof:name":"Crowne Plaza Hotel Detroit- Novi",
    "wof:placetype":"venue"
},
  "geometry": {"coordinates":[-83.47657599999999,42.489361],"type":"Point"}
}