{
  "type": "Feature",
  "properties": {
    "iso:country":"US",
    "sg:address":"10808 Bennett Rd",
    "sg:city":"Morrice",
    "sg:classifiers":[
        {
            "category":"Building & Trades",
            "subcategory":"Construction",
            "type":"Services"
        }
    ],
    "sg:phone":"+1 517 625 1611",
    "sg:postcode":"48889",
    "sg:province":"MI",
    "sg:tags":[
        "fence",
        "contractor"
    ],
    "wof:name":"Spartan Fence Inc",
    "wof:placetype":"venue"
},
  "geometry": {"coordinates":[-84.802706,43.241761],"type":"Point"}
}