{
  "type": "Feature",
  "properties": {
    "iso:country":"US",
    "sg:address":"39520 Woodward Ave",
    "sg:city":"Bloomfield Hills",
    "sg:classifiers":[
        {
            "category":"Health Services",
            "subcategory":"Dentist",
            "type":"Services"
        }
    ],
    "sg:phone":"+1 248 645 9797",
    "sg:postcode":"48304",
    "sg:province":"MI",
    "wof:name":"Hanson Craig M PC",
    "wof:placetype":"venue"
},
  "geometry": {"coordinates":[-83.24369799999999,42.582298],"type":"Point"}
}