{
  "type": "Feature",
  "properties": {
    "iso:country":"US",
    "sg:address":"300 S State St",
    "sg:city":"Zeeland",
    "sg:classifiers":[
        {
            "category":"Organizations",
            "subcategory":"Religious Organization",
            "type":"Services"
        }
    ],
    "sg:phone":"+1 616 772 1733",
    "sg:postcode":"49464",
    "sg:province":"MI",
    "sg:tags":[
        "church"
    ],
    "sg:website":"www.winningathome.com",
    "wof:name":"Winning At Home",
    "wof:placetype":"venue"
},
  "geometry": {"coordinates":[-86.018922,42.80644],"type":"Point"}
}