{
  "type": "Feature",
  "properties": {
    "iso:country":"US",
    "sg:address":"2750 Cook Rd",
    "sg:city":"West Branch",
    "sg:classifiers":[
        {
            "category":"Restaurant",
            "type":"Food & Drink"
        }
    ],
    "sg:menulink":"http://www.allmenus.com/mi/west-branch/146299-subway/menu/",
    "sg:phone":"+1 989 345 7234",
    "sg:postcode":"48661",
    "sg:province":"MI",
    "sg:tags":[
        "american",
        "sandwich"
    ],
    "wof:name":"Subway",
    "wof:placetype":"venue"
},
  "geometry": {"coordinates":[-84.223473,44.256095],"type":"Point"}
}