{
  "type": "Feature",
  "properties": {
    "iso:country":"US",
    "sg:address":"5317 Okemos Rd",
    "sg:city":"East Lansing",
    "sg:classifiers":[
        {
            "category":"Building & Trades",
            "subcategory":"Construction",
            "type":"Services"
        }
    ],
    "sg:phone":"+1 517 347 3073",
    "sg:postcode":"48823",
    "sg:province":"MI",
    "sg:tags":[
        "residential"
    ],
    "wof:name":"Reconstruction",
    "wof:placetype":"venue"
},
  "geometry": {"coordinates":[-84.42756300000001,42.73464],"type":"Point"}
}