{
  "type": "Feature",
  "properties": {
    "iso:country":"US",
    "sg:address":"12640 Dunham Rd",
    "sg:city":"Hartland",
    "sg:classifiers":[
        {
            "category":"Professional",
            "subcategory":"Business Services",
            "type":"Services"
        }
    ],
    "sg:phone":"+1 248 889 4503",
    "sg:postcode":"48353",
    "sg:province":"MI",
    "wof:name":"Team Creative",
    "wof:placetype":"venue"
},
  "geometry": {"coordinates":[-83.706926,42.648997],"type":"Point"}
}