{
  "type": "Feature",
  "properties": {
    "iso:country":"US",
    "sg:address":"87 N Saginaw St",
    "sg:city":"Pontiac",
    "sg:classifiers":[
        {
            "category":"Shopping",
            "type":"Retail Goods"
        }
    ],
    "sg:phone":"+1 248 745 0525",
    "sg:postcode":"48342",
    "sg:province":"MI",
    "sg:tags":[
        "art",
        "gallery",
        "dealer"
    ],
    "wof:name":"Miller Studios",
    "wof:placetype":"venue"
},
  "geometry": {"coordinates":[-83.29311199999999,42.639771],"type":"Point"}
}