{
  "type": "Feature",
  "properties": {
    "iso:country":"US",
    "sg:address":"309 Inkster Rd",
    "sg:city":"Inkster",
    "sg:classifiers":[
        {
            "category":"Personal",
            "subcategory":"Nail Salon",
            "type":"Services"
        }
    ],
    "sg:phone":"+1 313 359 4688",
    "sg:postcode":"48141",
    "sg:province":"MI",
    "wof:name":"Crystal Nail",
    "wof:placetype":"venue"
},
  "geometry": {"coordinates":[-83.31075300000001,42.309913],"type":"Point"}
}