{
  "type": "Feature",
  "properties": {
    "iso:country":"US",
    "sg:address":"1402 E Parkwood Ave",
    "sg:city":"Burton",
    "sg:classifiers":[
        {
            "category":"Manufacturing",
            "subcategory":"Furniture",
            "type":"Manufacturing & Wholesale Goods"
        }
    ],
    "sg:phone":"+1 810 577 1445",
    "sg:postcode":"48529",
    "sg:province":"MI",
    "sg:tags":[
        "retail",
        "cabinet"
    ],
    "wof:name":"DK Cabinets",
    "wof:placetype":"venue"
},
  "geometry": {"coordinates":[-83.676236,42.971389],"type":"Point"}
}