{
  "type": "Feature",
  "properties": {
    "iso:country":"US",
    "sg:address":"53526 Hunters Crossing Dr",
    "sg:city":"Shelby Twp",
    "sg:classifiers":[
        {
            "category":"Personal",
            "type":"Services"
        },
        {
            "category":"Health Services",
            "subcategory":"Clinic",
            "type":"Services"
        }
    ],
    "sg:phone":"+1 586 677 1450",
    "sg:postcode":"48315",
    "sg:province":"MI",
    "sg:tags":[
        "consultant",
        "program",
        "fitness"
    ],
    "wof:name":"Health Awareness Inc",
    "wof:placetype":"venue"
},
  "geometry": {"coordinates":[-82.98603,42.687718],"type":"Point"}
}