{
  "type": "Feature",
  "properties": {
    "iso:country":"US",
    "sg:address":"3030 Overridge Dr",
    "sg:city":"Ann Arbor",
    "sg:classifiers":[
        {
            "category":"Shopping",
            "subcategory":"Jewelry",
            "type":"Retail Goods"
        }
    ],
    "sg:phone":"+1 734 677 4443",
    "sg:postcode":"48104",
    "sg:province":"MI",
    "wof:name":"Debroah Flanagan Jewelry & Met",
    "wof:placetype":"venue"
},
  "geometry": {"coordinates":[-83.698437,42.263185],"type":"Point"}
}