{
  "type": "Feature",
  "properties": {
    "iso:country":"US",
    "sg:address":"92 Bellview Dr",
    "sg:city":"Ionia",
    "sg:classifiers":[
        {
            "category":"Building & Trades",
            "subcategory":"Plumbing",
            "type":"Services"
        }
    ],
    "sg:phone":"+1 616 527 8592",
    "sg:postcode":"48846",
    "sg:province":"MI",
    "sg:tags":[
        "heating",
        "contractor"
    ],
    "sg:website":"www.homexperts.us",
    "wof:name":"Home Experts",
    "wof:placetype":"venue"
},
  "geometry": {"coordinates":[-85.069464,42.967764],"type":"Point"}
}