{
  "type": "Feature",
  "properties": {
    "iso:country":"US",
    "sg:address":"7691 N Lapeer Rd",
    "sg:city":"Fostoria",
    "sg:classifiers":[
        {
            "category":"Personal",
            "type":"Services"
        }
    ],
    "sg:phone":"+1 989 795 2258",
    "sg:postcode":"48435",
    "sg:province":"MI",
    "wof:name":"Golden Rotissery",
    "wof:placetype":"venue"
},
  "geometry": {"coordinates":[-83.31570600000001,43.260474],"type":"Point"}
}