{
  "type": "Feature",
  "properties": {
    "iso:country":"US",
    "sg:address":"2351 Holton Rd",
    "sg:city":"Muskegon",
    "sg:classifiers":[
        {
            "category":"Banks & Credit Unions",
            "subcategory":"Bank",
            "type":"Services"
        }
    ],
    "sg:phone":"+1 231 727 9116",
    "sg:postcode":"49445",
    "sg:province":"MI",
    "sg:tags":[
        "national",
        "commercial"
    ],
    "wof:name":"National City Bank",
    "wof:placetype":"venue"
},
  "geometry": {"coordinates":[-86.19940800000001,43.297049],"type":"Point"}
}