{
  "type": "Feature",
  "properties": {
    "iso:country":"US",
    "sg:address":"28505 Northwestern Hwy",
    "sg:city":"Southfield",
    "sg:classifiers":[
        {
            "category":"Restaurant",
            "type":"Food & Drink"
        }
    ],
    "sg:phone":"+1 248 796 7234",
    "sg:postcode":"48034",
    "sg:province":"MI",
    "sg:tags":[
        "middle",
        "indian",
        "eastern"
    ],
    "wof:name":"Zyggyz Grill & Chill",
    "wof:placetype":"venue"
},
  "geometry": {"coordinates":[-83.287085,42.493803],"type":"Point"}
}