{
  "type": "Feature",
  "properties": {
    "iso:country":"US",
    "sg:address":"251 S State St",
    "sg:city":"Mackinac Island",
    "sg:classifiers":[
        {
            "category":"Restaurant",
            "type":"Food & Drink"
        }
    ],
    "sg:phone":"+1 906 847 0270",
    "sg:postcode":"49740",
    "sg:province":"MI",
    "sg:tags":[
        "eating"
    ],
    "wof:name":"Pilot House Restaurant",
    "wof:placetype":"venue"
},
  "geometry": {"coordinates":[-85.013318,45.546091],"type":"Point"}
}