{
  "type": "Feature",
  "properties": {
    "iso:country":"US",
    "sg:address":"2980 Interstate Pkwy",
    "sg:city":"Kalamazoo",
    "sg:classifiers":[
        {
            "category":"Wholesale",
            "subcategory":"Sporting Goods",
            "type":"Manufacturing & Wholesale Goods"
        }
    ],
    "sg:phone":"+1 269 383 1111",
    "sg:postcode":"49048",
    "sg:province":"MI",
    "sg:tags":[
        "paint",
        "game",
        "ball"
    ],
    "sg:website":"www.crossfireinc.com",
    "wof:name":"Crossfire",
    "wof:placetype":"venue"
},
  "geometry": {"coordinates":[-85.52168,42.26094],"type":"Point"}
}