{
  "type": "Feature",
  "properties": {
    "iso:country":"US",
    "sg:address":"2 W 19th St",
    "sg:city":"Holland",
    "sg:classifiers":[
        {
            "category":"Organizations",
            "subcategory":"Religious Organization",
            "type":"Services"
        }
    ],
    "sg:phone":"+1 616 395 9697",
    "sg:postcode":"49423",
    "sg:province":"MI",
    "wof:name":"Grace Embassy Intl Church",
    "wof:placetype":"venue"
},
  "geometry": {"coordinates":[-86.107124,42.780322],"type":"Point"}
}