{
  "type": "Feature",
  "properties": {
    "iso:country":"US",
    "sg:address":"1976 Star-Batt Dr",
    "sg:city":"Rochester Hills",
    "sg:classifiers":[
        {
            "category":"Professional",
            "subcategory":"Management & Consulting",
            "type":"Services"
        },
        {
            "category":"Manufacturing",
            "subcategory":"Tools & Machinery",
            "type":"Manufacturing & Wholesale Goods"
        }
    ],
    "sg:phone":"+1 248 852 2700",
    "sg:postcode":"48309",
    "sg:province":"MI",
    "sg:tags":[
        "equipment",
        "system",
        "business",
        "automation"
    ],
    "wof:name":"Prodomax US Inc",
    "wof:placetype":"venue"
},
  "geometry": {"coordinates":[-83.170492,42.648392],"type":"Point"}
}