{
  "type": "Feature",
  "properties": {
    "iso:country":"US",
    "sg:address":"13016 E 7 Mile Rd",
    "sg:city":"Detroit",
    "sg:classifiers":[
        {
            "category":"Bars & Pubs",
            "type":"Food & Drink"
        }
    ],
    "sg:phone":"+1 313 527 6102",
    "sg:postcode":"48205",
    "sg:province":"MI",
    "sg:tags":[
        "drinking"
    ],
    "wof:name":"Mississippi Connection",
    "wof:placetype":"venue"
},
  "geometry": {"coordinates":[-82.990081,42.43473],"type":"Point"}
}