{
  "type": "Feature",
  "properties": {
    "iso:country":"US",
    "sg:address":"1700 Clear Lake Dr",
    "sg:city":"Dowling",
    "sg:classifiers":[
        {
            "category":"Travel",
            "subcategory":"Campground",
            "type":"Entertainment"
        }
    ],
    "sg:phone":"+1 269 721 8291",
    "sg:postcode":"49050",
    "sg:province":"MI",
    "sg:tags":[
        "camp"
    ],
    "sg:website":"www.wesleywoodscamp.com",
    "wof:name":"Wesley Woods United Meth Camp",
    "wof:placetype":"venue"
},
  "geometry": {"coordinates":[-85.258122,42.513415],"type":"Point"}
}