{
  "type": "Feature",
  "properties": {
    "iso:country":"US",
    "sg:address":"610 N Main St",
    "sg:city":"Lapeer",
    "sg:classifiers":[
        {
            "category":"Health Services",
            "subcategory":"Doctor",
            "type":"Services"
        }
    ],
    "sg:phone":"+1 810 667 9000",
    "sg:postcode":"48446",
    "sg:province":"MI",
    "sg:tags":[
        "medical",
        "osteopathic"
    ],
    "wof:name":"Dermatology & Cosmtc Care Ctr",
    "wof:placetype":"venue"
},
  "geometry": {"coordinates":[-83.318806,43.055524],"type":"Point"}
}