{
  "type": "Feature",
  "properties": {
    "iso:country":"US",
    "sg:address":"135 Carr St",
    "sg:city":"Fowlerville",
    "sg:classifiers":[
        {
            "category":"Building & Trades",
            "subcategory":"Construction",
            "type":"Services"
        }
    ],
    "sg:phone":"+1 517 223 0333",
    "sg:postcode":"48836",
    "sg:province":"MI",
    "sg:tags":[
        "concrete",
        "contractor"
    ],
    "wof:name":"Ames Brothers Cement",
    "wof:placetype":"venue"
},
  "geometry": {"coordinates":[-84.07388,42.65711],"type":"Point"}
}