{
  "type": "Feature",
  "properties": {
    "iso:country":"US",
    "sg:address":"2561 US Hwy 12",
    "sg:city":"Niles",
    "sg:classifiers":[
        {
            "category":"Manufacturing",
            "subcategory":"Tools & Machinery",
            "type":"Manufacturing & Wholesale Goods"
        }
    ],
    "sg:phone":"+1 269 684 4702",
    "sg:postcode":"49120",
    "sg:province":"MI",
    "sg:tags":[
        "machine",
        "shop"
    ],
    "wof:name":"Weber Machine Co",
    "wof:placetype":"venue"
},
  "geometry": {"coordinates":[-86.193298,41.782703],"type":"Point"}
}