{
  "type": "Feature",
  "properties": {
    "iso:country":"US",
    "sg:address":"29089 E River Rd",
    "sg:city":"Grosse Ile",
    "sg:classifiers":[
        {
            "category":"Building & Trades",
            "subcategory":"Construction",
            "type":"Services"
        }
    ],
    "sg:phone":"+1 734 676 8072",
    "sg:postcode":"48138",
    "sg:province":"MI",
    "sg:tags":[
        "contractor"
    ],
    "wof:name":"Cancilliari Building Company Inc",
    "wof:placetype":"venue"
},
  "geometry": {"coordinates":[-83.150398,42.093399],"type":"Point"}
}