{
  "type": "Feature",
  "properties": {
    "iso:country":"US",
    "sg:address":"121 Grand Ave",
    "sg:city":"Mt Clemens",
    "sg:classifiers":[
        {
            "category":"Building & Trades",
            "subcategory":"Construction",
            "type":"Services"
        }
    ],
    "sg:phone":"+1 586 415 8611",
    "sg:postcode":"48043",
    "sg:province":"MI",
    "sg:tags":[
        "layer",
        "carpet"
    ],
    "wof:name":"Carpet Baggers",
    "wof:placetype":"venue"
},
  "geometry": {"coordinates":[-82.88698599999999,42.600144],"type":"Point"}
}