{
  "type": "Feature",
  "properties": {
    "iso:country":"US",
    "sg:address":"1412 E 11 Mile Rd",
    "sg:city":"Royal Oak",
    "sg:classifiers":[
        {
            "category":"Real Estate",
            "subcategory":"Architect",
            "type":"Services"
        }
    ],
    "sg:phone":"+1 248 414 9270",
    "sg:postcode":"48067",
    "sg:province":"MI",
    "wof:name":"Krieger Associates",
    "wof:placetype":"venue"
},
  "geometry": {"coordinates":[-83.128066,42.490127],"type":"Point"}
}