{
  "type": "Feature",
  "properties": {
    "iso:country":"US",
    "sg:address":"2304 Tomahawk Dr",
    "sg:city":"Lapeer",
    "sg:classifiers":[
        {
            "category":"Professional",
            "subcategory":"Management & Consulting",
            "type":"Services"
        }
    ],
    "sg:phone":"+1 810 667 1704",
    "sg:postcode":"48446",
    "sg:province":"MI",
    "sg:tags":[
        "business"
    ],
    "wof:name":"Jbj Floorcovering",
    "wof:placetype":"venue"
},
  "geometry": {"coordinates":[-83.43753,43.096739],"type":"Point"}
}