{
  "type": "Feature",
  "properties": {
    "iso:country":"US",
    "sg:address":"1494 N Graham Rd",
    "sg:city":"Freeland",
    "sg:classifiers":[
        {
            "category":"Building & Trades",
            "subcategory":"Construction",
            "type":"Services"
        }
    ],
    "sg:phone":"+1 989 781 0640",
    "sg:postcode":"48623",
    "sg:province":"MI",
    "sg:tags":[
        "general",
        "contractor"
    ],
    "sg:website":"www.wolgastcorporation.com",
    "wof:name":"Wolgast Corp",
    "wof:placetype":"venue"
},
  "geometry": {"coordinates":[-84.130854,43.42547],"type":"Point"}
}