{
  "type": "Feature",
  "properties": {
    "iso:country":"US",
    "sg:address":"4825 Snyder Ave",
    "sg:city":"Fremont",
    "sg:classifiers":[
        {
            "category":"Retail",
            "subcategory":"Veterinary Services",
            "type":"Services"
        }
    ],
    "sg:phone":"+1 231 924 4940",
    "sg:postcode":"49412",
    "sg:province":"MI",
    "sg:tags":[
        "veterinarian"
    ],
    "wof:name":"Fremont Animal Hospital",
    "wof:placetype":"venue"
},
  "geometry": {"coordinates":[-85.971052,43.466965],"type":"Point"}
}