{
  "type": "Feature",
  "properties": {
    "iso:country":"US",
    "sg:address":"1136 Wealthy St SE",
    "sg:city":"Grand Rapids",
    "sg:classifiers":[
        {
            "category":"Organizations",
            "subcategory":"Religious Organization",
            "type":"Services"
        }
    ],
    "sg:phone":"+1 616 304 9292",
    "sg:postcode":"49506",
    "sg:province":"MI",
    "sg:tags":[
        "clergy"
    ],
    "wof:name":"Steve Bohlert",
    "wof:placetype":"venue"
},
  "geometry": {"coordinates":[-85.63960899999999,42.955447],"type":"Point"}
}