{
  "type": "Feature",
  "properties": {
    "iso:country":"US",
    "sg:address":"8 Peterboro St",
    "sg:city":"Detroit",
    "sg:classifiers":[
        {
            "category":"Communications",
            "subcategory":"Film & Video Production",
            "type":"Services"
        }
    ],
    "sg:phone":"+1 313 833 6350",
    "sg:postcode":"48201",
    "sg:province":"MI",
    "sg:tags":[
        "motion"
    ],
    "wof:name":"Dona Tatum",
    "wof:placetype":"venue"
},
  "geometry": {"coordinates":[-83.058717,42.344572],"type":"Point"}
}