{
  "type": "Feature",
  "properties": {
    "iso:country":"US",
    "sg:address":"5636 Oakland Dr",
    "sg:city":"Portage",
    "sg:classifiers":[
        {
            "category":"Real Estate",
            "subcategory":"Real Estate Operator",
            "type":"Services"
        }
    ],
    "sg:phone":"+1 269 323 3379",
    "sg:postcode":"49024",
    "sg:province":"MI",
    "sg:tags":[
        "building",
        "nonresidential"
    ],
    "wof:name":"Bogard Properties LLC",
    "wof:placetype":"venue"
},
  "geometry": {"coordinates":[-85.614093,42.235655],"type":"Point"}
}