{
  "type": "Feature",
  "properties": {
    "iso:country":"US",
    "sg:address":"14271 Gratiot Ave",
    "sg:city":"Detroit",
    "sg:classifiers":[
        {
            "category":"Restaurant",
            "type":"Food & Drink"
        }
    ],
    "sg:phone":"+1 313 521 4212",
    "sg:postcode":"48205",
    "sg:province":"MI",
    "wof:name":"McDonald's Hamburgers",
    "wof:placetype":"venue"
},
  "geometry": {"coordinates":[-82.977997,42.434799],"type":"Point"}
}