{
  "type": "Feature",
  "properties": {
    "iso:country":"US",
    "sg:address":"310 S Rose St",
    "sg:city":"Ishpeming",
    "sg:classifiers":[
        {
            "category":"Banks & Credit Unions",
            "subcategory":"Investment Brokerage",
            "type":"Services"
        }
    ],
    "sg:phone":"+1 906 486 7438",
    "sg:postcode":"49849",
    "sg:province":"MI",
    "sg:tags":[
        "consultant",
        "planning",
        "financial"
    ],
    "wof:name":"Barry N Dale Cft",
    "wof:placetype":"venue"
},
  "geometry": {"coordinates":[-87.717834,46.482458],"type":"Point"}
}