{
  "type": "Feature",
  "properties": {
    "iso:country":"US",
    "sg:address":"200 E Empire Ave",
    "sg:city":"Benton Harbor",
    "sg:classifiers":[
        {
            "category":"Social Services",
            "type":"Services"
        }
    ],
    "sg:phone":"+1 269 925 4333",
    "sg:postcode":"49022",
    "sg:province":"MI",
    "sg:tags":[
        "organization",
        "welfare"
    ],
    "wof:name":"Benton Harbor Street Mnstrs",
    "wof:placetype":"venue"
},
  "geometry": {"coordinates":[-86.452501,42.101648],"type":"Point"}
}