{
  "type": "Feature",
  "properties": {
    "iso:country":"US",
    "sg:address":"5011 W Bloomfield Lake Rd",
    "sg:city":"West Bloomfield",
    "sg:classifiers":[
        {
            "category":"Professional",
            "subcategory":"Engineering",
            "type":"Services"
        }
    ],
    "sg:phone":"+1 313 394 6505",
    "sg:postcode":"48323",
    "sg:province":"MI",
    "wof:name":"Jerome Wolfe",
    "wof:placetype":"venue"
},
  "geometry": {"coordinates":[-83.379384,42.564211],"type":"Point"}
}