{
  "type": "Feature",
  "properties": {
    "iso:country":"US",
    "sg:address":"2325 10th St",
    "sg:city":"Port Huron",
    "sg:classifiers":[
        {
            "category":"Autos & Motor Vehicles",
            "subcategory":"Automobile Sales",
            "type":"Retail Goods"
        }
    ],
    "sg:phone":"+1 810 984 4500",
    "sg:postcode":"48060",
    "sg:province":"MI",
    "sg:tags":[
        "used"
    ],
    "wof:name":"Tunnel Self Storage",
    "wof:placetype":"venue"
},
  "geometry": {"coordinates":[-82.43220700000001,42.959613],"type":"Point"}
}