{
  "type": "Feature",
  "properties": {
    "iso:country":"US",
    "sg:address":"119 E Columbia Ave",
    "sg:city":"Battle Creek",
    "sg:classifiers":[
        {
            "category":"Health Services",
            "subcategory":"Doctor",
            "type":"Services"
        }
    ],
    "sg:phone":"+1 269 963 4811",
    "sg:postcode":"49015",
    "sg:province":"MI",
    "wof:name":"American Dental Health Service",
    "wof:placetype":"venue"
},
  "geometry": {"coordinates":[-85.19660500000001,42.298634],"type":"Point"}
}