{
  "type": "Feature",
  "properties": {
    "iso:country":"US",
    "sg:address":"3275 Martin Rd",
    "sg:city":"Commerce Twp",
    "sg:classifiers":[
        {
            "category":"Health Services",
            "subcategory":"Nursing And Care Facility",
            "type":"Services"
        }
    ],
    "sg:phone":"+1 248 926 2920",
    "sg:postcode":"48390",
    "sg:province":"MI",
    "sg:tags":[
        "home",
        "retirement",
        "community"
    ],
    "sg:website":"www.courtyardmanor.com",
    "wof:name":"Courtyard Manor",
    "wof:placetype":"venue"
},
  "geometry": {"coordinates":[-83.449729,42.567185],"type":"Point"}
}