{
  "type": "Feature",
  "properties": {
    "iso:country":"US",
    "sg:address":"53435 Grand River Ave",
    "sg:city":"New Hudson",
    "sg:classifiers":[
        {
            "category":"Professional",
            "subcategory":"Lawyer & Legal Services",
            "type":"Services"
        }
    ],
    "sg:phone":"+1 248 486 5115",
    "sg:postcode":"48165",
    "sg:province":"MI",
    "wof:name":"Foren & Glaser",
    "wof:placetype":"venue"
},
  "geometry": {"coordinates":[-83.576814,42.503014],"type":"Point"}
}