{
  "type": "Feature",
  "properties": {
    "iso:country":"US",
    "sg:address":"801 S Adams Rd",
    "sg:city":"Birmingham",
    "sg:classifiers":[
        {
            "category":"Community Center",
            "type":"Public Place"
        }
    ],
    "sg:phone":"+1 248 646 3661",
    "sg:postcode":"48009",
    "sg:province":"MI",
    "sg:tags":[
        "medical"
    ],
    "sg:website":"http://www.naama.com",
    "wof:name":"National Arab American Medical Association",
    "wof:placetype":"venue"
},
  "geometry": {"coordinates":[-83.20549,42.541489],"type":"Point"}
}