{
  "type": "Feature",
  "properties": {
    "iso:country":"US",
    "sg:address":"24895 Mound Rd",
    "sg:city":"Warren",
    "sg:classifiers":[
        {
            "category":"Real Estate",
            "subcategory":"Real Estate Agent",
            "type":"Services"
        }
    ],
    "sg:phone":"+1 586 757 7300",
    "sg:postcode":"48091",
    "sg:province":"MI",
    "wof:name":"Red Carpet Keim Assoc",
    "wof:placetype":"venue"
},
  "geometry": {"coordinates":[-83.04572,42.476209],"type":"Point"}
}