{
  "type": "Feature",
  "properties": {
    "iso:country":"US",
    "sg:address":"15064 Houston Whittier St",
    "sg:city":"Detroit",
    "sg:classifiers":[
        {
            "category":"Health Services",
            "subcategory":"Dentist",
            "type":"Services"
        }
    ],
    "sg:phone":"+1 313 371 5500",
    "sg:postcode":"48205",
    "sg:province":"MI",
    "wof:name":"District Dental Center",
    "wof:placetype":"venue"
},
  "geometry": {"coordinates":[-82.965897,42.4207],"type":"Point"}
}