{
  "type": "Feature",
  "properties": {
    "iso:country":"US",
    "sg:address":"932 Boswell Ln",
    "sg:city":"Kalamazoo",
    "sg:classifiers":[
        {
            "category":"Education",
            "subcategory":"School",
            "type":"Public Place"
        }
    ],
    "sg:phone":"+1 269 337 0530",
    "sg:postcode":"49006",
    "sg:province":"MI",
    "wof:name":"Arcadia Elementary School",
    "wof:placetype":"venue"
},
  "geometry": {"coordinates":[-85.63436299999999,42.281782],"type":"Point"}
}