{
  "type": "Feature",
  "properties": {
    "iso:country":"US",
    "sg:address":"15416 Park Ln",
    "sg:city":"Plymouth",
    "sg:classifiers":[
        {
            "category":"Building & Trades",
            "subcategory":"Landscaping Services",
            "type":"Services"
        }
    ],
    "sg:phone":"+1 734 420 5155",
    "sg:postcode":"48170",
    "sg:province":"MI",
    "sg:tags":[
        "snow",
        "plowing"
    ],
    "wof:name":"Highland Ldscp & Snow Plowing",
    "wof:placetype":"venue"
},
  "geometry": {"coordinates":[-83.44399900000001,42.400973],"type":"Point"}
}