{
  "type": "Feature",
  "properties": {
    "iso:country":"US",
    "sg:address":"32270 Telegraph Rd",
    "sg:city":"Bingham Farms",
    "sg:classifiers":[
        {
            "category":"Health Services",
            "subcategory":"Doctor",
            "type":"Services"
        }
    ],
    "sg:phone":"+1 248 723 0817",
    "sg:postcode":"48025",
    "sg:province":"MI",
    "wof:name":"Vinuya Ricardo Z MD",
    "wof:placetype":"venue"
},
  "geometry": {"coordinates":[-83.285203,42.524633],"type":"Point"}
}