{
  "type": "Feature",
  "properties": {
    "iso:country":"US",
    "sg:address":"3035 Ponemah Dr",
    "sg:city":"Fenton",
    "sg:classifiers":[
        {
            "category":"Professional",
            "subcategory":"Research",
            "type":"Services"
        }
    ],
    "sg:phone":"+1 810 629 0857",
    "sg:postcode":"48430",
    "sg:province":"MI",
    "sg:tags":[
        "environmental",
        "ecological"
    ],
    "wof:name":"Douglas Environmental Svc Inc",
    "wof:placetype":"venue"
},
  "geometry": {"coordinates":[-83.72776399999999,42.814486],"type":"Point"}
}