{
  "type": "Feature",
  "properties": {
    "iso:country":"US",
    "sg:address":"42711 Ford Rd",
    "sg:city":"Canton",
    "sg:classifiers":[
        {
            "category":"Real Estate",
            "subcategory":"Real Estate Operator",
            "type":"Services"
        }
    ],
    "sg:phone":"+1 734 981 7200",
    "sg:postcode":"48187",
    "sg:province":"MI",
    "sg:tags":[
        "apartment"
    ],
    "wof:name":"Relocation Center Apartment Search",
    "wof:placetype":"venue"
},
  "geometry": {"coordinates":[-83.465698,42.3223],"type":"Point"}
}