{
  "type": "Feature",
  "properties": {
    "iso:country":"US",
    "sg:address":"915 S Zeeb Rd",
    "sg:city":"Ann Arbor",
    "sg:classifiers":[
        {
            "category":"Retail",
            "subcategory":"Laundry & Dry Cleaning",
            "type":"Services"
        }
    ],
    "sg:phone":"+1 734 996 9193",
    "sg:postcode":"48103",
    "sg:province":"MI",
    "sg:tags":[
        "carpet",
        "furniture"
    ],
    "wof:name":"R E Moon Specialty Services",
    "wof:placetype":"venue"
},
  "geometry": {"coordinates":[-83.83815,42.273401],"type":"Point"}
}