{
  "type": "Feature",
  "properties": {
    "iso:country":"US",
    "sg:address":"45050 Quaker Hill Dr",
    "sg:city":"Canton",
    "sg:classifiers":[
        {
            "category":"Building & Trades",
            "subcategory":"Electrical",
            "type":"Services"
        }
    ],
    "sg:phone":"+1 734 453 1954",
    "sg:postcode":"48187",
    "sg:province":"MI",
    "sg:tags":[
        "electrical",
        "contractor"
    ],
    "wof:name":"Gil Electric",
    "wof:placetype":"venue"
},
  "geometry": {"coordinates":[-83.483947,42.335316],"type":"Point"}
}