{
  "type": "Feature",
  "properties": {
    "iso:country":"US",
    "sg:address":"6440 Livernois Rd",
    "sg:city":"Troy",
    "sg:classifiers":[
        {
            "category":"Social Services",
            "subcategory":"Adult Care",
            "type":"Services"
        }
    ],
    "sg:phone":"+1 248 813 0109",
    "sg:postcode":"48098",
    "sg:province":"MI",
    "sg:tags":[
        "foster"
    ],
    "wof:name":"Assisted Living Svc",
    "wof:placetype":"venue"
},
  "geometry": {"coordinates":[-83.15005499999999,42.614263],"type":"Point"}
}