{
  "type": "Feature",
  "properties": {
    "iso:country":"US",
    "sg:address":"13996 8th Ave",
    "sg:city":"Marne",
    "sg:classifiers":[
        {
            "category":"Social Services",
            "subcategory":"Child Care",
            "type":"Services"
        }
    ],
    "sg:phone":"+1 616 677 2383",
    "sg:postcode":"49435",
    "sg:province":"MI",
    "sg:tags":[
        "home",
        "day"
    ],
    "wof:name":"Lori K Almy",
    "wof:placetype":"venue"
},
  "geometry": {"coordinates":[-85.80712,43.022271],"type":"Point"}
}