{
  "type": "Feature",
  "properties": {
    "iso:country":"US",
    "sg:address":"1161 W Lemon Creek Rd",
    "sg:city":"Baroda",
    "sg:classifiers":[
        {
            "category":"Professional",
            "subcategory":"Management & Consulting",
            "type":"Services"
        }
    ],
    "sg:phone":"+1 269 422 2894",
    "sg:postcode":"49101",
    "sg:province":"MI",
    "sg:tags":[
        "business"
    ],
    "wof:name":"Applied Environmental Tech",
    "wof:placetype":"venue"
},
  "geometry": {"coordinates":[-86.48271800000001,41.957421],"type":"Point"}
}