{
  "type": "Feature",
  "properties": {
    "iso:country":"US",
    "sg:address":"203 S Gould St",
    "sg:city":"Owosso",
    "sg:classifiers":[
        {
            "category":"Freight",
            "type":"Transportation"
        }
    ],
    "sg:phone":"+1 989 729 7867",
    "sg:postcode":"48867",
    "sg:province":"MI",
    "sg:tags":[
        "special"
    ],
    "wof:name":"A Plus Mini Storage",
    "wof:placetype":"venue"
},
  "geometry": {"coordinates":[-84.157735,42.997608],"type":"Point"}
}