{
  "type": "Feature",
  "properties": {
    "iso:country":"US",
    "sg:address":"283 Howard Ave",
    "sg:city":"Holland",
    "sg:classifiers":[
        {
            "category":"Professional",
            "subcategory":"Lawyer & Legal Services",
            "type":"Services"
        }
    ],
    "sg:phone":"+1 616 396 7423",
    "sg:postcode":"49424",
    "sg:province":"MI",
    "wof:name":"Kenneth J Uildriks",
    "wof:placetype":"venue"
},
  "geometry": {"coordinates":[-86.11929499999999,42.798508],"type":"Point"}
}