{
  "type": "Feature",
  "properties": {
    "iso:country":"US",
    "sg:address":"9390 Genesee St",
    "sg:city":"New Lothrop",
    "sg:classifiers":[
        {
            "category":"Food & Beverages",
            "subcategory":"Groceries & Convenience Stores",
            "type":"Retail Goods"
        }
    ],
    "sg:phone":"+1 810 638 5095",
    "sg:postcode":"48460",
    "sg:province":"MI",
    "sg:tags":[
        "grocer"
    ],
    "wof:name":"Confer's Grocery",
    "wof:placetype":"venue"
},
  "geometry": {"coordinates":[-83.973811,43.116666],"type":"Point"}
}