{
  "type": "Feature",
  "properties": {
    "iso:country":"US",
    "sg:address":"3305 Moraine Dr",
    "sg:city":"Brighton",
    "sg:classifiers":[
        {
            "category":"Building & Trades",
            "subcategory":"Construction",
            "type":"Services"
        }
    ],
    "sg:phone":"+1 810 333 5511",
    "sg:postcode":"48114",
    "sg:province":"MI",
    "sg:tags":[
        "house"
    ],
    "wof:name":"Honey Do This LLC",
    "wof:placetype":"venue"
},
  "geometry": {"coordinates":[-83.71725000000001,42.560418],"type":"Point"}
}