{
  "type": "Feature",
  "properties": {
    "iso:country":"US",
    "sg:address":"1422 W Court St",
    "sg:city":"Flint",
    "sg:classifiers":[
        {
            "category":"Social Services",
            "type":"Services"
        }
    ],
    "sg:phone":"+1 810 235 2544",
    "sg:postcode":"48503",
    "sg:province":"MI",
    "wof:name":"Visually Impaired Center Inc",
    "wof:placetype":"venue"
},
  "geometry": {"coordinates":[-83.703542,43.006887],"type":"Point"}
}