{
  "type": "Feature",
  "properties": {
    "iso:country":"US",
    "sg:address":"100 S Jefferson St",
    "sg:city":"Saginaw",
    "sg:classifiers":[
        {
            "category":"Utilities",
            "subcategory":"Mobile Phone",
            "type":"Services"
        }
    ],
    "sg:phone":"+1 989 752 3221",
    "sg:postcode":"48604",
    "sg:province":"MI",
    "sg:tags":[
        "telephone",
        "cellular"
    ],
    "wof:name":"Cingular Wireless",
    "wof:placetype":"venue"
},
  "geometry": {"coordinates":[-83.917968,43.478319],"type":"Point"}
}