{
  "type": "Feature",
  "properties": {
    "iso:country":"US",
    "sg:address":"31815 Southfield Rd",
    "sg:city":"Beverly Hills",
    "sg:classifiers":[
        {
            "category":"Health Services",
            "subcategory":"Doctor",
            "type":"Services"
        }
    ],
    "sg:phone":"+1 248 646 8166",
    "sg:postcode":"48025",
    "sg:province":"MI",
    "sg:tags":[
        "medicine",
        "internal"
    ],
    "wof:name":"Beverly Hills Internal Medicine",
    "wof:placetype":"venue"
},
  "geometry": {"coordinates":[-83.223761,42.523339],"type":"Point"}
}