{
  "type": "Feature",
  "properties": {
    "iso:country":"US",
    "sg:address":"9197 Brooks Rd",
    "sg:city":"Lennon",
    "sg:classifiers":[
        {
            "category":"Retail",
            "subcategory":"Repair Shop",
            "type":"Services"
        }
    ],
    "sg:phone":"+1 989 288 6068",
    "sg:postcode":"48449",
    "sg:province":"MI",
    "sg:tags":[
        "scooter",
        "motorcycle",
        "motor"
    ],
    "wof:name":"Brad Lowe Racing",
    "wof:placetype":"venue"
},
  "geometry": {"coordinates":[-83.98411299999999,42.963405],"type":"Point"}
}