{
  "type": "Feature",
  "properties": {
    "iso:country":"US",
    "sg:address":"437 N Monroe St",
    "sg:city":"Traverse City",
    "sg:classifiers":[
        {
            "category":"Retail",
            "subcategory":"Photofinishing",
            "type":"Services"
        }
    ],
    "sg:phone":"+1 231 883 5121",
    "sg:postcode":"49684",
    "sg:province":"MI",
    "sg:tags":[
        "laboratory"
    ],
    "wof:name":"Light Monkey Photo",
    "wof:placetype":"venue"
},
  "geometry": {"coordinates":[-85.641227,44.768302],"type":"Point"}
}