{
  "type": "Feature",
  "properties": {
    "iso:country":"US",
    "sg:address":"365 State Hwy 65",
    "sg:city":"Whittemore",
    "sg:classifiers":[
        {
            "category":"Building & Trades",
            "subcategory":"Plumbing",
            "type":"Services"
        }
    ],
    "sg:phone":"+1 989 756 4960",
    "sg:postcode":"48770",
    "sg:province":"MI",
    "sg:tags":[
        "product",
        "management",
        "energy",
        "system"
    ],
    "wof:name":"H & H Star Energy",
    "wof:placetype":"venue"
},
  "geometry": {"coordinates":[-83.803055,44.265741],"type":"Point"}
}