{
  "type": "Feature",
  "properties": {
    "iso:country":"US",
    "sg:address":"145 S Main St",
    "sg:city":"Eaton Rapids",
    "sg:classifiers":[
        {
            "category":"Shopping",
            "subcategory":"Gifts & Souvenirs",
            "type":"Retail Goods"
        }
    ],
    "sg:phone":"+1 517 663 4772",
    "sg:postcode":"48827",
    "sg:province":"MI",
    "wof:name":"Flutterby Creations",
    "wof:placetype":"venue"
},
  "geometry": {"coordinates":[-84.655642,42.51226],"type":"Point"}
}