{
  "type": "Feature",
  "properties": {
    "iso:country":"US",
    "sg:address":"554 Tisdale Ave",
    "sg:city":"Lansing",
    "sg:classifiers":[
        {
            "category":"Shopping",
            "subcategory":"Hobbies, Toys, & Games",
            "type":"Retail Goods"
        },
        {
            "category":"Shopping",
            "subcategory":"Crafts & Fabrics",
            "type":"Retail Goods"
        }
    ],
    "sg:phone":"+1 517 487 9284",
    "sg:postcode":"48910",
    "sg:province":"MI",
    "sg:tags":[
        "shop",
        "hobby",
        "model",
        "supplies-wholesale",
        "manufacturer"
    ],
    "wof:name":"Guiding Lights",
    "wof:placetype":"venue"
},
  "geometry": {"coordinates":[-84.545846,42.706814],"type":"Point"}
}