{
  "type": "Feature",
  "properties": {
    "iso:country":"US",
    "sg:address":"2130 N Meridian Rd",
    "sg:city":"Sanford",
    "sg:classifiers":[
        {
            "category":"Organizations",
            "subcategory":"Religious Organization",
            "type":"Services"
        }
    ],
    "sg:phone":"+1 989 687 6749",
    "sg:postcode":"48657",
    "sg:province":"MI",
    "wof:name":"Meridian Church Of God",
    "wof:placetype":"venue"
},
  "geometry": {"coordinates":[-84.368386,43.675389],"type":"Point"}
}