{
  "type": "Feature",
  "properties": {
    "iso:country":"US",
    "sg:address":"3026 Carrollton Rd",
    "sg:city":"Saginaw",
    "sg:classifiers":[
        {
            "category":"Manufacturing",
            "subcategory":"Glass & Minerals",
            "type":"Manufacturing & Wholesale Goods"
        }
    ],
    "sg:phone":"+1 989 754 8833",
    "sg:postcode":"48724",
    "sg:province":"MI",
    "sg:tags":[
        "novelty"
    ],
    "wof:name":"Cramton Gift Mfg",
    "wof:placetype":"venue"
},
  "geometry": {"coordinates":[-83.937449,43.450489],"type":"Point"}
}