{
  "type": "Feature",
  "properties": {
    "iso:country":"US",
    "sg:address":"8290 Winter Forest Dr NE",
    "sg:city":"Rockford",
    "sg:classifiers":[
        {
            "category":"Shopping",
            "subcategory":"Computers & Home Electronics",
            "type":"Retail Goods"
        }
    ],
    "sg:phone":"+1 616 874 2573",
    "sg:postcode":"49341",
    "sg:province":"MI",
    "sg:tags":[
        "audio"
    ],
    "wof:name":"Northwoods Audio & Video",
    "wof:placetype":"venue"
},
  "geometry": {"coordinates":[-85.459369,43.110841],"type":"Point"}
}