{
  "type": "Feature",
  "properties": {
    "iso:country":"US",
    "sg:address":"13501 Van Dyke St",
    "sg:city":"Detroit",
    "sg:classifiers":[
        {
            "category":"Shopping",
            "subcategory":"Clothing, Apparel, & Fashions",
            "type":"Retail Goods"
        }
    ],
    "sg:phone":"+1 313 826 6687",
    "sg:postcode":"48234",
    "sg:province":"MI",
    "sg:tags":[
        "accessory",
        "clothing",
        "women's"
    ],
    "wof:name":"Big Girls DO",
    "wof:placetype":"venue"
},
  "geometry": {"coordinates":[-83.02375499999999,42.416332],"type":"Point"}
}