{
  "type": "Feature",
  "properties": {
    "iso:country":"US",
    "sg:address":"1405 E Houghton Ave",
    "sg:city":"Houghton",
    "sg:classifiers":[
        {
            "category":"Organizations",
            "subcategory":"Professional Association",
            "type":"Services"
        }
    ],
    "sg:phone":"+1 906 482 6039",
    "sg:postcode":"49931",
    "sg:province":"MI",
    "wof:name":"Espiscopal Association For",
    "wof:placetype":"venue"
},
  "geometry": {"coordinates":[-88.551705,47.119012],"type":"Point"}
}