{
  "type": "Feature",
  "properties": {
    "iso:country":"US",
    "sg:address":"107 Monroe St",
    "sg:city":"Mancelona",
    "sg:classifiers":[
        {
            "category":"Personal",
            "subcategory":"Beauty Salon",
            "type":"Services"
        }
    ],
    "sg:phone":"+1 231 587 9581",
    "sg:postcode":"49659",
    "sg:province":"MI",
    "wof:name":"Hair Studio",
    "wof:placetype":"venue"
},
  "geometry": {"coordinates":[-85.063052,44.903449],"type":"Point"}
}