{
  "type": "Feature",
  "properties": {
    "iso:country":"US",
    "sg:address":"5015 Castle Rd",
    "sg:city":"Otter Lake",
    "sg:classifiers":[
        {
            "category":"Professional",
            "subcategory":"Accounting & Tax Preparation",
            "type":"Services"
        }
    ],
    "sg:phone":"+1 810 793 1313",
    "sg:postcode":"48464",
    "sg:province":"MI",
    "wof:name":"The Taxman Inc",
    "wof:placetype":"venue"
},
  "geometry": {"coordinates":[-83.43145699999999,43.230713],"type":"Point"}
}