{
  "type": "Feature",
  "properties": {
    "iso:country":"US",
    "sg:address":"26051 Dequindre Rd",
    "sg:city":"Madison Heights",
    "sg:classifiers":[
        {
            "category":"Building & Trades",
            "subcategory":"Cleaning & Sanitation",
            "type":"Services"
        }
    ],
    "sg:phone":"+1 248 584 1819",
    "sg:postcode":"48071",
    "sg:province":"MI",
    "sg:tags":[
        "carpet"
    ],
    "sg:website":"www.chetscleaning.com",
    "wof:name":"Chet's Cleaning Inc",
    "wof:placetype":"venue"
},
  "geometry": {"coordinates":[-83.084999,42.484402],"type":"Point"}
}