{
  "type": "Feature",
  "properties": {
    "iso:country":"US",
    "sg:address":"7323 Reuter St",
    "sg:city":"Dearborn",
    "sg:classifiers":[
        {
            "category":"Professional",
            "subcategory":"Computer Services",
            "type":"Services"
        }
    ],
    "sg:phone":"+1 313 846 9845",
    "sg:postcode":"48126",
    "sg:province":"MI",
    "sg:tags":[
        "consultant",
        "software"
    ],
    "wof:name":"Logan Utah",
    "wof:placetype":"venue"
},
  "geometry": {"coordinates":[-83.17215,42.344941],"type":"Point"}
}