{
  "type": "Feature",
  "properties": {
    "iso:country":"US",
    "sg:address":"15503 14th St",
    "sg:city":"Detroit",
    "sg:classifiers":[
        {
            "category":"Food & Beverages",
            "subcategory":"Groceries & Convenience Stores",
            "type":"Retail Goods"
        }
    ],
    "sg:phone":"+1 313 863 8771",
    "sg:postcode":"48238",
    "sg:province":"MI",
    "wof:name":"Cole's Market",
    "wof:placetype":"venue"
},
  "geometry": {"coordinates":[-83.12020099999999,42.4058],"type":"Point"}
}