{
  "type": "Feature",
  "properties": {
    "iso:country":"US",
    "sg:address":"19570 Kelly Rd",
    "sg:city":"Harper Woods",
    "sg:classifiers":[
        {
            "category":"Health Services",
            "subcategory":"Doctor",
            "type":"Services"
        }
    ],
    "sg:phone":"+1 313 371 5300",
    "sg:postcode":"48225",
    "sg:province":"MI",
    "sg:tags":[
        "podiatrist"
    ],
    "sg:website":"www.longlakepodiatrist.com",
    "wof:name":"Eastside Foot & Ankle Clinic PC",
    "wof:placetype":"venue"
},
  "geometry": {"coordinates":[-82.948097,42.440701],"type":"Point"}
}