{
  "type": "Feature",
  "properties": {
    "iso:country":"US",
    "sg:address":"G4226 Fenton Rd",
    "sg:city":"Flint",
    "sg:classifiers":[
        {
            "category":"Food & Beverages",
            "subcategory":"Liquor & Beverages",
            "type":"Retail Goods"
        }
    ],
    "sg:phone":"+1 810 235 5211",
    "sg:postcode":"48507",
    "sg:province":"MI",
    "sg:tags":[
        "beer",
        "spirit",
        "wine"
    ],
    "wof:name":"Starr Mart Food Store",
    "wof:placetype":"venue"
},
  "geometry": {"coordinates":[-83.69259599999999,42.967899],"type":"Point"}
}