{
  "type": "Feature",
  "properties": {
    "iso:country":"US",
    "sg:address":"3858 Francis St",
    "sg:city":"Jackson",
    "sg:classifiers":[
        {
            "category":"Building & Trades",
            "subcategory":"Construction",
            "type":"Services"
        }
    ],
    "sg:phone":"+1 517 789 8496",
    "sg:postcode":"49203",
    "sg:province":"MI",
    "sg:tags":[
        "designer",
        "dealer",
        "pool",
        "swimming"
    ],
    "wof:name":"Pool & Patio Inc",
    "wof:placetype":"venue"
},
  "geometry": {"coordinates":[-84.40042,42.205679],"type":"Point"}
}