{
  "type": "Feature",
  "properties": {
    "iso:country":"US",
    "sg:address":"24449 Olde Orchard St",
    "sg:city":"Novi",
    "sg:classifiers":[
        {
            "category":"Professional",
            "subcategory":"Business Services",
            "type":"Services"
        }
    ],
    "sg:phone":"+1 248 477 9614",
    "sg:postcode":"48375",
    "sg:province":"MI",
    "wof:name":"Michigan Solid Surface",
    "wof:placetype":"venue"
},
  "geometry": {"coordinates":[-83.441254,42.468917],"type":"Point"}
}