{
  "type": "Feature",
  "properties": {
    "iso:country":"US",
    "sg:address":"107 W Superior St",
    "sg:city":"Alma",
    "sg:classifiers":[
        {
            "category":"Real Estate",
            "subcategory":"Real Estate Agent",
            "type":"Services"
        }
    ],
    "sg:phone":"+1 989 463 8889",
    "sg:postcode":"48801",
    "sg:province":"MI",
    "wof:name":"American Dream Properties",
    "wof:placetype":"venue"
},
  "geometry": {"coordinates":[-84.66340099999999,43.378911],"type":"Point"}
}