{
  "type": "Feature",
  "properties": {
    "iso:country":"US",
    "sg:address":"300 W Morgan Rd",
    "sg:city":"Ann Arbor",
    "sg:classifiers":[
        {
            "category":"Travel",
            "subcategory":"Travel Agent",
            "type":"Entertainment"
        }
    ],
    "sg:phone":"+1 734 996 9400",
    "sg:postcode":"48108",
    "sg:province":"MI",
    "wof:name":"American Express",
    "wof:placetype":"venue"
},
  "geometry": {"coordinates":[-83.733615,42.214939],"type":"Point"}
}