{
  "type": "Feature",
  "properties": {
    "iso:country":"US",
    "sg:address":"39101 Webb Dr",
    "sg:city":"Westland",
    "sg:phone":"+1 734 729 6683",
    "sg:postcode":"48185",
    "sg:province":"MI",
    "sg:website":"http://www.michiganmovers.com",
    "wof:name":"Men On The Move",
    "wof:placetype":"venue"
},
  "geometry": {"coordinates":[-83.425842,42.328232],"type":"Point"}
}