{
  "type": "Feature",
  "properties": {
    "iso:country":"US",
    "sg:address":"1921 W Grand River Ave",
    "sg:city":"Okemos",
    "sg:classifiers":[
        {
            "category":"Personal",
            "subcategory":"Beauty Salon",
            "type":"Services"
        }
    ],
    "sg:phone":"+1 517 349 9088",
    "sg:postcode":"48864",
    "sg:province":"MI",
    "sg:tags":[
        "shop"
    ],
    "wof:name":"Fantastic Sam's",
    "wof:placetype":"venue"
},
  "geometry": {"coordinates":[-84.41924899999999,42.720244],"type":"Point"}
}