{
  "type": "Feature",
  "properties": {
    "iso:country":"US",
    "sg:address":"1720 Marion Ave",
    "sg:city":"Grand Haven",
    "sg:classifiers":[
        {
            "category":"Building & Trades",
            "subcategory":"Electrical",
            "type":"Services"
        }
    ],
    "sg:phone":"+1 616 842 7280",
    "sg:postcode":"49417",
    "sg:province":"MI",
    "sg:tags":[
        "electric",
        "contractor"
    ],
    "wof:name":"Holzinger & Pofahl Electric Co",
    "wof:placetype":"venue"
},
  "geometry": {"coordinates":[-86.203872,43.052984],"type":"Point"}
}