{
  "type": "Feature",
  "properties": {
    "iso:country":"US",
    "sg:address":"14400 Ivanhoe Dr",
    "sg:city":"Shelby Twp",
    "sg:classifiers":[
        {
            "category":"Home & Garden",
            "subcategory":"Garden Supply",
            "type":"Retail Goods"
        }
    ],
    "sg:phone":"+1 586 677 0428",
    "sg:postcode":"48315",
    "sg:province":"MI",
    "sg:tags":[
        "sprinkler"
    ],
    "wof:name":"Mr Mister Lawn Sprinkling",
    "wof:placetype":"venue"
},
  "geometry": {"coordinates":[-82.985776,42.693426],"type":"Point"}
}