{
  "type": "Feature",
  "properties": {
    "iso:country":"US",
    "sg:address":"699 Kentucky Dr",
    "sg:city":"Rochester",
    "sg:classifiers":[
        {
            "category":"Recreation",
            "type":"Entertainment"
        }
    ],
    "sg:phone":"+1 248 651 5263",
    "sg:postcode":"48307",
    "sg:province":"MI",
    "wof:name":"Kwilt Art",
    "wof:placetype":"venue"
},
  "geometry": {"coordinates":[-83.148031,42.644374],"type":"Point"}
}