{
  "type": "Feature",
  "properties": {
    "iso:country":"US",
    "sg:address":"1453 N Elms Rd",
    "sg:city":"Flint",
    "sg:classifiers":[
        {
            "category":"Real Estate",
            "subcategory":"Real Estate Agent",
            "type":"Services"
        }
    ],
    "sg:phone":"+1 810 733 3333",
    "sg:postcode":"48532",
    "sg:province":"MI",
    "sg:tags":[
        "house",
        "construct"
    ],
    "sg:website":"www.americanassociates.com",
    "wof:name":"American Associates Inc",
    "wof:placetype":"venue"
},
  "geometry": {"coordinates":[-83.81272199999999,43.029076],"type":"Point"}
}