{
  "type": "Feature",
  "properties": {
    "iso:country":"US",
    "sg:address":"1352 Plainfield Ave NE",
    "sg:city":"Grand Rapids",
    "sg:classifiers":[
        {
            "category":"Cinema",
            "subcategory":"Movie Rental",
            "type":"Entertainment"
        }
    ],
    "sg:phone":"+1 616 458 9047",
    "sg:postcode":"49505",
    "sg:province":"MI",
    "sg:tags":[
        "leasing",
        "video",
        "disc",
        "tape"
    ],
    "wof:name":"All Star Video",
    "wof:placetype":"venue"
},
  "geometry": {"coordinates":[-85.665126,42.987824],"type":"Point"}
}