{
  "type": "Feature",
  "properties": {
    "iso:country":"US",
    "sg:address":"7631 Gratiot Ave",
    "sg:city":"Detroit",
    "sg:classifiers":[
        {
            "category":"Shopping",
            "subcategory":"Clothing, Apparel, & Fashions",
            "type":"Retail Goods"
        }
    ],
    "sg:phone":"+1 313 924 0552",
    "sg:postcode":"48213",
    "sg:province":"MI",
    "sg:tags":[
        "accessory",
        "clothing",
        "women's"
    ],
    "wof:name":"Olam Trade Inc",
    "wof:placetype":"venue"
},
  "geometry": {"coordinates":[-83.016302,42.376688],"type":"Point"}
}