{
  "type": "Feature",
  "properties": {
    "iso:country":"US",
    "sg:address":"650 Shoppers Ln",
    "sg:city":"Kalamazoo",
    "sg:classifiers":[
        {
            "category":"Shopping",
            "subcategory":"Department Store",
            "type":"Retail Goods"
        }
    ],
    "sg:phone":"+1 269 381 0428",
    "sg:postcode":"49004",
    "sg:province":"MI",
    "sg:tags":[
        "shop"
    ],
    "wof:name":"Dollar General",
    "wof:placetype":"venue"
},
  "geometry": {"coordinates":[-85.57118800000001,42.319775],"type":"Point"}
}