{
  "type": "Feature",
  "properties": {
    "iso:country":"US",
    "sg:address":"56005 Blossom Rd",
    "sg:city":"Colon",
    "sg:classifiers":[
        {
            "category":"Recreation",
            "type":"Entertainment"
        }
    ],
    "sg:phone":"+1 269 432 3915",
    "sg:postcode":"49040",
    "sg:province":"MI",
    "wof:name":"Bruces Equine Services",
    "wof:placetype":"venue"
},
  "geometry": {"coordinates":[-85.326492,41.984367],"type":"Point"}
}