{
  "type": "Feature",
  "properties": {
    "iso:country":"US",
    "sg:address":"4060 Chicago Dr SW",
    "sg:city":"Grandville",
    "sg:classifiers":[
        {
            "category":"Banks & Credit Unions",
            "subcategory":"Investment Brokerage",
            "type":"Services"
        }
    ],
    "sg:phone":"+1 616 724 1880",
    "sg:postcode":"49418",
    "sg:province":"MI",
    "sg:tags":[
        "consultant",
        "planning",
        "financial"
    ],
    "wof:name":"VSR Financial Svc Inc",
    "wof:placetype":"venue"
},
  "geometry": {"coordinates":[-85.76526,42.908809],"type":"Point"}
}