{
  "type": "Feature",
  "properties": {
    "iso:country":"US",
    "sg:address":"42841 Sycamore Dr",
    "sg:city":"Sterling Heights",
    "sg:classifiers":[
        {
            "category":"Professional",
            "subcategory":"Management & Consulting",
            "type":"Services"
        }
    ],
    "sg:phone":"+1 586 247 3739",
    "sg:postcode":"48313",
    "sg:province":"MI",
    "sg:tags":[
        "business"
    ],
    "wof:name":"JP Marin Consultin",
    "wof:placetype":"venue"
},
  "geometry": {"coordinates":[-82.986163,42.608444],"type":"Point"}
}