{
  "type": "Feature",
  "properties": {
    "iso:country":"US",
    "sg:address":"16264 Pine Ridge Dr N",
    "sg:city":"Fraser",
    "sg:classifiers":[
        {
            "category":"Arts & Performance",
            "subcategory":"Theater",
            "type":"Entertainment"
        }
    ],
    "sg:phone":"+1 586 294 5843",
    "sg:postcode":"48026",
    "sg:province":"MI",
    "sg:tags":[
        "group"
    ],
    "wof:name":"Roscoe Detroit",
    "wof:placetype":"venue"
},
  "geometry": {"coordinates":[-82.959076,42.545562],"type":"Point"}
}