{
  "type": "Feature",
  "properties": {
    "iso:country":"US",
    "sg:address":"6588 Secor Rd",
    "sg:city":"Lambertville",
    "sg:classifiers":[
        {
            "category":"Health Services",
            "subcategory":"Chiropractor",
            "type":"Services"
        }
    ],
    "sg:phone":"+1 734 856 6411",
    "sg:postcode":"48144",
    "sg:province":"MI",
    "wof:name":"Schwanger & Assoc Chiro Ofcs",
    "wof:placetype":"venue"
},
  "geometry": {"coordinates":[-83.624515,41.728348],"type":"Point"}
}