{
  "type": "Feature",
  "properties": {
    "iso:country":"US",
    "sg:address":"2900 W Drahner Rd",
    "sg:city":"Oxford",
    "sg:classifiers":[
        {
            "category":"Farming",
            "subcategory":"Livestock Farm",
            "type":"Manufacturing & Wholesale Goods"
        }
    ],
    "sg:phone":"+1 248 628 0796",
    "sg:postcode":"48371",
    "sg:province":"MI",
    "sg:tags":[
        "beef",
        "feedlot",
        "cattle"
    ],
    "wof:name":"Harris Roy",
    "wof:placetype":"venue"
},
  "geometry": {"coordinates":[-83.314578,42.808797],"type":"Point"}
}