{
  "type": "Feature",
  "properties": {
    "iso:country":"US",
    "sg:address":"5674 W Price Rd",
    "sg:city":"St Johns",
    "sg:classifiers":[
        {
            "category":"Building & Trades",
            "subcategory":"Construction",
            "type":"Services"
        }
    ],
    "sg:phone":"+1 517 290 2458",
    "sg:postcode":"48879",
    "sg:province":"MI",
    "sg:tags":[
        "repairing",
        "remodeling",
        "contractor"
    ],
    "wof:name":"Rite-Way Remodeling",
    "wof:placetype":"venue"
},
  "geometry": {"coordinates":[-84.637018,42.929349],"type":"Point"}
}