{
  "type": "Feature",
  "properties": {
    "iso:country":"US",
    "sg:address":"105 Railroad St",
    "sg:city":"Romeo",
    "sg:classifiers":[
        {
            "category":"Building & Trades",
            "subcategory":"Construction",
            "type":"Services"
        }
    ],
    "sg:phone":"+1 586 752 0937",
    "sg:postcode":"48065",
    "sg:province":"MI",
    "sg:tags":[
        "carpenter"
    ],
    "wof:name":"Tri-County Finshed Carpentry",
    "wof:placetype":"venue"
},
  "geometry": {"coordinates":[-83.00668899999999,42.802709],"type":"Point"}
}