{
  "type": "Feature",
  "properties": {
    "iso:country":"US",
    "sg:address":"20609 Maxine St",
    "sg:city":"St Clair Shores",
    "sg:classifiers":[
        {
            "category":"Real Estate",
            "subcategory":"Real Estate Agent",
            "type":"Services"
        }
    ],
    "sg:phone":"+1 586 777 9800",
    "sg:postcode":"48080",
    "sg:province":"MI",
    "sg:website":"www.completechocolate.com",
    "wof:name":"Award Services Inc",
    "wof:placetype":"venue"
},
  "geometry": {"coordinates":[-82.91026100000001,42.461221],"type":"Point"}
}