{
  "type": "Feature",
  "properties": {
    "iso:country":"US",
    "sg:address":"1615 S Opdyke Rd",
    "sg:city":"Bloomfield Hills",
    "sg:classifiers":[
        {
            "category":"Restaurant",
            "type":"Food & Drink"
        }
    ],
    "sg:menulink":"http://www.allmenus.com/mi/bloomfield/247115-cedarland-restaurant/menu/",
    "sg:phone":"+1 248 858 2315",
    "sg:postcode":"48304",
    "sg:province":"MI",
    "sg:tags":[
        "middle",
        "eastern"
    ],
    "wof:name":"Cedarland Restaurant",
    "wof:placetype":"venue"
},
  "geometry": {"coordinates":[-83.248514,42.61867],"type":"Point"}
}