{
  "type": "Feature",
  "properties": {
    "iso:country":"US",
    "sg:address":"7860 Telegraph Rd",
    "sg:city":"Taylor",
    "sg:classifiers":[
        {
            "category":"Shopping",
            "subcategory":"Mobile Phones",
            "type":"Retail Goods"
        }
    ],
    "sg:phone":"+1 313 292 3850",
    "sg:postcode":"48180",
    "sg:province":"MI",
    "wof:name":"Radioshack-A Division of Tandy Corp",
    "wof:placetype":"venue"
},
  "geometry": {"coordinates":[-83.270302,42.250801],"type":"Point"}
}