{
  "type": "Feature",
  "properties": {
    "iso:country":"US",
    "sg:address":"883 North Ave",
    "sg:city":"Battle Creek",
    "sg:classifiers":[
        {
            "category":"Restaurant",
            "type":"Food & Drink"
        }
    ],
    "sg:phone":"+1 269 962 5561",
    "sg:postcode":"49017",
    "sg:province":"MI",
    "sg:tags":[
        "personal",
        "drinking",
        "eating"
    ],
    "sg:website":"www.theirish-pub.com",
    "wof:name":"Irish Pub",
    "wof:placetype":"venue"
},
  "geometry": {"coordinates":[-85.180774,42.348882],"type":"Point"}
}