{
  "type": "Feature",
  "properties": {
    "iso:country":"US",
    "sg:address":"1971 E Beltline Ave NE",
    "sg:city":"Grand Rapids",
    "sg:classifiers":[
        {
            "category":"Government",
            "subcategory":"Office",
            "type":"Public Place"
        }
    ],
    "sg:phone":"+1 616 364 5674",
    "sg:postcode":"49525",
    "sg:province":"MI",
    "sg:tags":[
        "armed",
        "force",
        "recruiting"
    ],
    "wof:name":"US Naval Recruiting",
    "wof:placetype":"venue"
},
  "geometry": {"coordinates":[-85.590639,42.993929],"type":"Point"}
}