{
  "type": "Feature",
  "properties": {
    "iso:country":"US",
    "sg:address":"36 W Flint St",
    "sg:city":"Lake Orion",
    "sg:classifiers":[
        {
            "category":"Restaurant",
            "type":"Food & Drink"
        }
    ],
    "sg:phone":"+1 248 693 6041",
    "sg:postcode":"48362",
    "sg:province":"MI",
    "wof:name":"Poppyseed Deli & Coffee",
    "wof:placetype":"venue"
},
  "geometry": {"coordinates":[-83.24023200000001,42.784722],"type":"Point"}
}