{
  "type": "Feature",
  "properties": {
    "iso:country":"US",
    "sg:address":"1215 8th St",
    "sg:city":"Mio",
    "sg:classifiers":[
        {
            "category":"Travel",
            "subcategory":"Hotels & Motels",
            "type":"Entertainment"
        }
    ],
    "sg:phone":"+1 989 826 5590",
    "sg:postcode":"48647",
    "sg:province":"MI",
    "sg:tags":[
        "operation"
    ],
    "wof:name":"Mio Pine Acres Cmpgrund Cabins",
    "wof:placetype":"venue"
},
  "geometry": {"coordinates":[-84.14699400000001,44.652182],"type":"Point"}
}