{
  "type": "Feature",
  "properties": {
    "iso:country":"US",
    "sg:address":"930 Washington Ave",
    "sg:city":"Muskegon",
    "sg:classifiers":[
        {
            "category":"Real Estate",
            "subcategory":"Real Estate Operator",
            "type":"Services"
        }
    ],
    "sg:phone":"+1 231 727 0805",
    "sg:postcode":"49441",
    "sg:province":"MI",
    "sg:tags":[
        "condominium"
    ],
    "wof:name":"Watermark Center",
    "wof:placetype":"venue"
},
  "geometry": {"coordinates":[-86.26535800000001,43.226758],"type":"Point"}
}