{
  "type": "Feature",
  "properties": {
    "iso:country":"US",
    "sg:address":"6220 Commerce Dr",
    "sg:city":"Westland",
    "sg:classifiers":[
        {
            "category":"Communications",
            "subcategory":"Newspaper",
            "type":"Services"
        }
    ],
    "sg:phone":"+1 734 721 2572",
    "sg:postcode":"48185",
    "sg:province":"MI",
    "sg:tags":[
        "magazine"
    ],
    "wof:name":"News Group Midwest the",
    "wof:placetype":"venue"
},
  "geometry": {"coordinates":[-83.421628,42.329401],"type":"Point"}
}