{
  "type": "Feature",
  "properties": {
    "iso:country":"US",
    "sg:address":"3035 Morrison Rd",
    "sg:city":"Rapid City",
    "sg:classifiers":[
        {
            "category":"Retail",
            "subcategory":"Auto Repair",
            "type":"Services"
        }
    ],
    "sg:phone":"+1 231 331 4306",
    "sg:postcode":"49676",
    "sg:province":"MI",
    "sg:tags":[
        "general"
    ],
    "wof:name":"Hilltop Garage",
    "wof:placetype":"venue"
},
  "geometry": {"coordinates":[-85.24741,44.801343],"type":"Point"}
}