{
  "type": "Feature",
  "properties": {
    "iso:country":"US",
    "sg:address":"269 Anchors Way",
    "sg:city":"St Joseph",
    "sg:classifiers":[
        {
            "category":"Government",
            "subcategory":"Office",
            "type":"Public Place"
        }
    ],
    "sg:phone":"+1 269 983 7719",
    "sg:postcode":"49085",
    "sg:province":"MI",
    "sg:tags":[
        "village"
    ],
    "wof:name":"Benton Harbor-St Joseph Wstwtr",
    "wof:placetype":"venue"
},
  "geometry": {"coordinates":[-86.47138099999999,42.102823],"type":"Point"}
}