{
  "type": "Feature",
  "properties": {
    "iso:country":"US",
    "sg:address":"221 Moran Rd",
    "sg:city":"Grosse Pointe",
    "sg:classifiers":[
        {
            "category":"Banks & Credit Unions",
            "subcategory":"Financial Services",
            "type":"Services"
        }
    ],
    "sg:phone":"+1 313 882 1296",
    "sg:postcode":"48236",
    "sg:province":"MI",
    "sg:tags":[
        "investment",
        "closed"
    ],
    "wof:name":"Harwood Family Ltd Partne",
    "wof:placetype":"venue"
},
  "geometry": {"coordinates":[-82.901843,42.400594],"type":"Point"}
}