{
  "type": "Feature",
  "properties": {
    "iso:country":"US",
    "sg:address":"30015 Utica Rd",
    "sg:city":"Roseville",
    "sg:classifiers":[
        {
            "category":"Restaurant",
            "type":"Food & Drink"
        }
    ],
    "sg:phone":"+1 586 445 8383",
    "sg:postcode":"48066",
    "sg:province":"MI",
    "sg:tags":[
        "pizza"
    ],
    "wof:name":"Papa Romano's Pizza",
    "wof:placetype":"venue"
},
  "geometry": {"coordinates":[-82.94059799999999,42.5172],"type":"Point"}
}