{
  "type": "Feature",
  "properties": {
    "iso:country":"US",
    "sg:address":"17615 Simmons Ave NE",
    "sg:city":"Cedar Springs",
    "sg:classifiers":[
        {
            "category":"Building & Trades",
            "subcategory":"Electrical",
            "type":"Services"
        }
    ],
    "sg:phone":"+1 616 696 4887",
    "sg:postcode":"49319",
    "sg:province":"MI",
    "sg:tags":[
        "electrical",
        "contractor"
    ],
    "wof:name":"Northwest Electric",
    "wof:placetype":"venue"
},
  "geometry": {"coordinates":[-85.596045,43.284787],"type":"Point"}
}