{
  "type": "Feature",
  "properties": {
    "iso:country":"US",
    "sg:address":"9075 N Haggerty Rd",
    "sg:city":"Plymouth",
    "sg:classifiers":[
        {
            "category":"Food & Beverages",
            "subcategory":"Groceries & Convenience Stores",
            "type":"Retail Goods"
        }
    ],
    "sg:phone":"+1 734 455 1400",
    "sg:postcode":"48170",
    "sg:province":"MI",
    "wof:name":"Spartan Stores Inc",
    "wof:placetype":"venue"
},
  "geometry": {"coordinates":[-83.444901,42.3536],"type":"Point"}
}