{
  "type": "Feature",
  "properties": {
    "iso:country":"US",
    "sg:address":"26350 W 8 Mile Rd",
    "sg:city":"Southfield",
    "sg:classifiers":[
        {
            "category":"Retail",
            "subcategory":"Auto Repair",
            "type":"Services"
        }
    ],
    "sg:phone":"+1 248 350 2820",
    "sg:postcode":"48034",
    "sg:province":"MI",
    "sg:tags":[
        "body",
        "shop"
    ],
    "wof:name":"Eastern Auto Company",
    "wof:placetype":"venue"
},
  "geometry": {"coordinates":[-83.304001,42.4426],"type":"Point"}
}