{
  "type": "Feature",
  "properties": {
    "iso:country":"US",
    "sg:address":"16903 Centralia",
    "sg:city":"Redford",
    "sg:classifiers":[
        {
            "category":"Wholesale",
            "subcategory":"Furniture",
            "type":"Manufacturing & Wholesale Goods"
        }
    ],
    "sg:phone":"+1 313 533 6899",
    "sg:postcode":"48240",
    "sg:province":"MI",
    "wof:name":"Seasoned Woodworks",
    "wof:placetype":"venue"
},
  "geometry": {"coordinates":[-83.29771,42.412654],"type":"Point"}
}