{
  "type": "Feature",
  "properties": {
    "iso:country":"US",
    "sg:address":"5910 Bullard Rd",
    "sg:city":"Fenton",
    "sg:classifiers":[
        {
            "category":"Building & Trades",
            "subcategory":"Landscaping Services",
            "type":"Services"
        }
    ],
    "sg:phone":"+1 810 632 7340",
    "sg:postcode":"48430",
    "sg:province":"MI",
    "wof:name":"Ulimate Lawn & Landscape",
    "wof:placetype":"venue"
},
  "geometry": {"coordinates":[-83.727897,42.692741],"type":"Point"}
}