{
  "type": "Feature",
  "properties": {
    "iso:country":"US",
    "sg:address":"2331 S State Rd",
    "sg:city":"Ionia",
    "sg:classifiers":[
        {
            "category":"Coffee & Tea",
            "type":"Food & Drink"
        }
    ],
    "sg:menulink":"http://www.allmenus.com/mi/ionia/248943-beaners/menu/",
    "sg:phone":"+1 616 522 0788",
    "sg:postcode":"48846",
    "sg:province":"MI",
    "sg:tags":[
        "american"
    ],
    "wof:name":"Beaners",
    "wof:placetype":"venue"
},
  "geometry": {"coordinates":[-85.074732,42.949055],"type":"Point"}
}