{
  "type": "Feature",
  "properties": {
    "iso:country":"US",
    "sg:address":"220 Anchors Way",
    "sg:city":"Saint Joseph",
    "sg:classifiers":[
        {
            "category":"Recreation",
            "type":"Entertainment"
        }
    ],
    "sg:phone":"+1 269 983 4140",
    "sg:postcode":"49085",
    "sg:province":"MI",
    "wof:name":"Captain Hoks PR-T-Tyme Chrters",
    "wof:placetype":"venue"
},
  "geometry": {"coordinates":[-86.471487,42.106545],"type":"Point"}
}