{
  "type": "Feature",
  "properties": {
    "iso:country":"US",
    "sg:address":"461 Monroe St",
    "sg:city":"Detroit",
    "sg:classifiers":[
        {
            "category":"Shopping",
            "subcategory":"Books",
            "type":"Retail Goods"
        }
    ],
    "sg:phone":"+1 313 961 0325",
    "sg:postcode":"48226",
    "sg:province":"MI",
    "wof:name":"Underground RR Reading Stn Bk",
    "wof:placetype":"venue"
},
  "geometry": {"coordinates":[-83.04312400000001,42.334673],"type":"Point"}
}