{
  "type": "Feature",
  "properties": {
    "iso:country":"US",
    "sg:address":"125 N Main St",
    "sg:city":"Capac",
    "sg:classifiers":[
        {
            "category":"Professional",
            "type":"Services"
        }
    ],
    "sg:phone":"+1 810 395 8800",
    "sg:postcode":"48014",
    "sg:province":"MI",
    "sg:tags":[
        "establishment"
    ],
    "wof:name":"Swingin D Fabricating",
    "wof:placetype":"venue"
},
  "geometry": {"coordinates":[-82.928551,43.013718],"type":"Point"}
}