{
  "type": "Feature",
  "properties": {
    "iso:country":"US",
    "sg:address":"300 S Front St",
    "sg:city":"Marquette",
    "sg:classifiers":[
        {
            "category":"Professional",
            "type":"Services"
        }
    ],
    "sg:phone":"+1 906 226 0413",
    "sg:postcode":"49855",
    "sg:province":"MI",
    "sg:tags":[
        "establishment"
    ],
    "wof:name":"Trident Associates",
    "wof:placetype":"venue"
},
  "geometry": {"coordinates":[-87.39334599999999,46.541582],"type":"Point"}
}