{
  "type": "Feature",
  "properties": {
    "iso:country":"US",
    "sg:address":"3576 Alpine Ave NW",
    "sg:city":"Grand Rapids",
    "sg:classifiers":[
        {
            "category":"Shopping",
            "subcategory":"Optical Goods",
            "type":"Retail Goods"
        }
    ],
    "sg:phone":"+1 616 784 4999",
    "sg:postcode":"49544",
    "sg:province":"MI",
    "wof:name":"Rx Optical",
    "wof:placetype":"venue"
},
  "geometry": {"coordinates":[-85.68929900000001,43.028773],"type":"Point"}
}