{
  "type": "Feature",
  "properties": {
    "iso:country":"US",
    "sg:address":"400 E Saginaw St",
    "sg:city":"Lansing",
    "sg:classifiers":[
        {
            "category":"Retail",
            "subcategory":"Repair Shop",
            "type":"Services"
        },
        {
            "category":"Shopping",
            "subcategory":"Music",
            "type":"Retail Goods"
        }
    ],
    "sg:phone":"+1 517 367 1111",
    "sg:postcode":"48906",
    "sg:province":"MI",
    "sg:tags":[
        "disc",
        "video",
        "cellular",
        "tape",
        "store",
        "cassette"
    ],
    "wof:name":"Video One Superstore",
    "wof:placetype":"venue"
},
  "geometry": {"coordinates":[-84.546493,42.740868],"type":"Point"}
}