{
  "type": "Feature",
  "properties": {
    "iso:country":"US",
    "sg:address":"8653 N 32nd St",
    "sg:city":"Richland",
    "sg:classifiers":[
        {
            "category":"Professional",
            "subcategory":"Management & Consulting",
            "type":"Services"
        },
        {
            "category":"Organizations",
            "subcategory":"Community Association",
            "type":"Services"
        }
    ],
    "sg:phone":"+1 269 629 0532",
    "sg:postcode":"49083",
    "sg:province":"MI",
    "sg:tags":[
        "consultant",
        "educational"
    ],
    "wof:name":"Flag",
    "wof:placetype":"venue"
},
  "geometry": {"coordinates":[-85.455348,42.385695],"type":"Point"}
}