{
  "type": "Feature",
  "properties": {
    "iso:country":"US",
    "sg:address":"24425 W M 60",
    "sg:city":"Homer",
    "sg:classifiers":[
        {
            "category":"Manufacturing",
            "subcategory":"Tools & Machinery",
            "type":"Manufacturing & Wholesale Goods"
        }
    ],
    "sg:phone":"+1 517 568 4171",
    "sg:postcode":"49245",
    "sg:province":"MI",
    "sg:tags":[
        "machine",
        "shop"
    ],
    "wof:name":"Miller Brothers Mfg Co",
    "wof:placetype":"venue"
},
  "geometry": {"coordinates":[-84.83504499999999,42.146131],"type":"Point"}
}