{
  "type": "Feature",
  "properties": {
    "iso:country":"US",
    "sg:address":"9200 E Highland Rd",
    "sg:city":"Howell",
    "sg:classifiers":[
        {
            "category":"Education",
            "subcategory":"Dance Studio",
            "type":"Public Place"
        }
    ],
    "sg:phone":"+1 810 632 3336",
    "sg:postcode":"48843",
    "sg:province":"MI",
    "sg:tags":[
        "instruction",
        "dancing"
    ],
    "wof:name":"Power Of Dance",
    "wof:placetype":"venue"
},
  "geometry": {"coordinates":[-83.76921400000001,42.63229],"type":"Point"}
}