{
  "type": "Feature",
  "properties": {
    "iso:country":"US",
    "sg:address":"1100 N Jenison Ave",
    "sg:city":"Lansing",
    "sg:classifiers":[
        {
            "category":"Building & Trades",
            "subcategory":"Construction",
            "type":"Services"
        }
    ],
    "sg:phone":"+1 517 702 0154",
    "sg:postcode":"48915",
    "sg:province":"MI",
    "sg:tags":[
        "house"
    ],
    "wof:name":"Cls Builders",
    "wof:placetype":"venue"
},
  "geometry": {"coordinates":[-84.572756,42.747495],"type":"Point"}
}