{
  "type": "Feature",
  "properties": {
    "iso:country":"US",
    "sg:address":"4705 Canal Ave SW",
    "sg:city":"Grandville",
    "sg:classifiers":[
        {
            "category":"Freight",
            "type":"Transportation"
        }
    ],
    "sg:phone":"+1 616 261 2913",
    "sg:postcode":"49418",
    "sg:province":"MI",
    "sg:tags":[
        "delivery"
    ],
    "wof:name":"Huffy",
    "wof:placetype":"venue"
},
  "geometry": {"coordinates":[-85.77242699999999,42.879601],"type":"Point"}
}