{
  "type": "Feature",
  "properties": {
    "iso:country":"US",
    "sg:address":"64207 Van Dyke Rd",
    "sg:city":"Washington",
    "sg:classifiers":[
        {
            "category":"Personal",
            "subcategory":"Tanning Parlor",
            "type":"Services"
        }
    ],
    "sg:phone":"+1 586 336 9922",
    "sg:postcode":"48095",
    "sg:province":"MI",
    "sg:tags":[
        "salon"
    ],
    "wof:name":"Sun Peach Tanning",
    "wof:placetype":"venue"
},
  "geometry": {"coordinates":[-83.01834100000001,42.766101],"type":"Point"}
}