{
  "type": "Feature",
  "properties": {
    "iso:country":"US",
    "sg:address":"111 E 9 Mile Rd",
    "sg:city":"Hazel Park",
    "sg:classifiers":[
        {
            "category":"Government",
            "subcategory":"Court House",
            "type":"Public Place"
        }
    ],
    "sg:phone":"+1 248 546 7000",
    "sg:postcode":"48030",
    "sg:province":"MI",
    "sg:tags":[
        "state"
    ],
    "wof:name":"District Court 43",
    "wof:placetype":"venue"
},
  "geometry": {"coordinates":[-83.103178,42.461496],"type":"Point"}
}