{
  "type": "Feature",
  "properties": {
    "iso:country":"US",
    "sg:address":"601 N Front St",
    "sg:city":"Dowagiac",
    "sg:classifiers":[
        {
            "category":"Government",
            "subcategory":"Office",
            "type":"Public Place"
        }
    ],
    "sg:phone":"+1 269 782 6512",
    "sg:postcode":"49047",
    "sg:province":"MI",
    "wof:name":"License Dept",
    "wof:placetype":"venue"
},
  "geometry": {"coordinates":[-86.10728,41.991852],"type":"Point"}
}