{
  "type": "Feature",
  "properties": {
    "iso:country":"US",
    "sg:address":"436 S Main St",
    "sg:city":"Lapeer",
    "sg:classifiers":[
        {
            "category":"Restaurant",
            "type":"Food & Drink"
        }
    ],
    "sg:phone":"+1 810 664 1641",
    "sg:postcode":"48446",
    "sg:province":"MI",
    "wof:name":"Wendy's Old Fashioned Hmbrgrs",
    "wof:placetype":"venue"
},
  "geometry": {"coordinates":[-83.31937000000001,43.045691],"type":"Point"}
}