{
  "type": "Feature",
  "properties": {
    "iso:country":"US",
    "sg:address":"2801 Parkway Pl",
    "sg:city":"Hartland",
    "sg:classifiers":[
        {
            "category":"Travel",
            "subcategory":"Hotels & Motels",
            "type":"Entertainment"
        }
    ],
    "sg:phone":"+1 248 889 3709",
    "sg:postcode":"48353",
    "sg:province":"MI",
    "sg:tags":[
        "operation"
    ],
    "wof:name":"K J Scraping",
    "wof:placetype":"venue"
},
  "geometry": {"coordinates":[-83.683746,42.64742],"type":"Point"}
}