{
  "type": "Feature",
  "properties": {
    "iso:country":"US",
    "sg:address":"221 S Jefferson St",
    "sg:city":"Hastings",
    "sg:classifiers":[
        {
            "category":"Autos & Motor Vehicles",
            "subcategory":"Auto Supplies",
            "type":"Retail Goods"
        }
    ],
    "sg:phone":"+1 269 818 0213",
    "sg:postcode":"49058",
    "sg:province":"MI",
    "sg:tags":[
        "battery"
    ],
    "wof:name":"Batteries Unlimited-Hastings",
    "wof:placetype":"venue"
},
  "geometry": {"coordinates":[-85.287526,42.647592],"type":"Point"}
}