{
  "type": "Feature",
  "properties": {
    "iso:country":"US",
    "sg:address":"482 Fisher Rd",
    "sg:city":"Grosse Pointe",
    "sg:classifiers":[
        {
            "category":"Professional",
            "subcategory":"Engineering",
            "type":"Services"
        }
    ],
    "sg:phone":"+1 313 881 3690",
    "sg:postcode":"48230",
    "sg:province":"MI",
    "wof:name":"Lcm Electronics Inc",
    "wof:placetype":"venue"
},
  "geometry": {"coordinates":[-82.913096,42.403973],"type":"Point"}
}