{
  "type": "Feature",
  "properties": {
    "iso:country":"US",
    "sg:address":"1820 Ridley Rd",
    "sg:city":"Palms",
    "sg:classifiers":[
        {
            "category":"Farming",
            "subcategory":"Farm",
            "type":"Manufacturing & Wholesale Goods"
        }
    ],
    "sg:phone":"+1 989 864 3802",
    "sg:postcode":"48465",
    "sg:province":"MI",
    "sg:tags":[
        "crop",
        "general"
    ],
    "wof:name":"Hilly Acres Inc",
    "wof:placetype":"venue"
},
  "geometry": {"coordinates":[-82.76463099999999,43.628244],"type":"Point"}
}