{
  "type": "Feature",
  "properties": {
    "iso:country":"US",
    "sg:address":"620 Eastern Ave",
    "sg:city":"Allegan",
    "sg:classifiers":[
        {
            "category":"Building & Trades",
            "subcategory":"Cleaning & Sanitation",
            "type":"Services"
        }
    ],
    "sg:phone":"+1 269 673 1583",
    "sg:postcode":"49010",
    "sg:province":"MI",
    "sg:tags":[
        "maintenance"
    ],
    "wof:name":"Davids Cleaning Service",
    "wof:placetype":"venue"
},
  "geometry": {"coordinates":[-85.83636300000001,42.52249],"type":"Point"}
}