{
  "type": "Feature",
  "properties": {
    "iso:country":"US",
    "sg:address":"257 N 30th St",
    "sg:city":"Springfield",
    "sg:classifiers":[
        {
            "category":"Wholesale",
            "subcategory":"Hardware",
            "type":"Manufacturing & Wholesale Goods"
        }
    ],
    "sg:phone":"+1 269 964 7149",
    "sg:postcode":"49015",
    "sg:province":"MI",
    "sg:tags":[
        "plumbing",
        "fixture",
        "supply"
    ],
    "wof:name":"Heffley Co",
    "wof:placetype":"venue"
},
  "geometry": {"coordinates":[-85.231695,42.315739],"type":"Point"}
}