{
  "type": "Feature",
  "properties": {
    "iso:country":"US",
    "sg:address":"20142 W Warren Ave",
    "sg:city":"Detroit",
    "sg:classifiers":[
        {
            "category":"Autos & Motor Vehicles",
            "subcategory":"Auto Supplies",
            "type":"Retail Goods"
        }
    ],
    "sg:phone":"+1 313 253 0300",
    "sg:postcode":"48228",
    "sg:province":"MI",
    "sg:tags":[
        "tire"
    ],
    "wof:name":"Dell Tire Auto Service",
    "wof:placetype":"venue"
},
  "geometry": {"coordinates":[-83.237127,42.343234],"type":"Point"}
}