{
  "type": "Feature",
  "properties": {
    "iso:country":"US",
    "sg:address":"606 E Shepherd St",
    "sg:city":"Charlotte",
    "sg:classifiers":[
        {
            "category":"Professional",
            "subcategory":"Business Services",
            "type":"Services"
        }
    ],
    "sg:phone":"+1 517 719 2874",
    "sg:postcode":"48813",
    "sg:province":"MI",
    "sg:tags":[
        "home",
        "inspection"
    ],
    "wof:name":"Castle Home Inspection Svcs",
    "wof:placetype":"venue"
},
  "geometry": {"coordinates":[-84.828402,42.553059],"type":"Point"}
}