{
  "type": "Feature",
  "properties": {
    "iso:country":"US",
    "sg:address":"201 Elliott St",
    "sg:city":"Grand Haven",
    "sg:classifiers":[
        {
            "category":"Building & Trades",
            "subcategory":"Construction",
            "type":"Services"
        }
    ],
    "sg:phone":"+1 616 842 6031",
    "sg:postcode":"49417",
    "sg:province":"MI",
    "sg:tags":[
        "roofing",
        "contractor"
    ],
    "wof:name":"Murphy Construction",
    "wof:placetype":"venue"
},
  "geometry": {"coordinates":[-86.229613,43.066525],"type":"Point"}
}