{
  "type": "Feature",
  "properties": {
    "iso:country":"US",
    "sg:address":"5050 Corunna Rd",
    "sg:city":"Flint",
    "sg:classifiers":[
        {
            "category":"Restaurant",
            "type":"Food & Drink"
        }
    ],
    "sg:menulink":"http://www.allmenus.com/mi/flint/142281-subway/menu/",
    "sg:phone":"+1 810 249 7281",
    "sg:postcode":"48532",
    "sg:province":"MI",
    "sg:tags":[
        "american",
        "sandwich"
    ],
    "wof:name":"Subway",
    "wof:placetype":"venue"
},
  "geometry": {"coordinates":[-83.773951,43.001992],"type":"Point"}
}