{
  "type": "Feature",
  "properties": {
    "iso:country":"US",
    "sg:address":"3814 W Jolly Rd",
    "sg:city":"Lansing",
    "sg:classifiers":[
        {
            "category":"Autos & Motor Vehicles",
            "subcategory":"Fuel & Gas Station",
            "type":"Retail Goods"
        }
    ],
    "sg:phone":"+1 517 882 1725",
    "sg:postcode":"48911",
    "sg:province":"MI",
    "sg:tags":[
        "oil"
    ],
    "wof:name":"Admiral Petroleum",
    "wof:placetype":"venue"
},
  "geometry": {"coordinates":[-84.602996,42.683224],"type":"Point"}
}