{
  "type": "Feature",
  "properties": {
    "iso:country":"US",
    "sg:address":"7060 Sells Rd",
    "sg:city":"Eau Claire",
    "sg:classifiers":[
        {
            "category":"Professional",
            "subcategory":"Business Services",
            "type":"Services"
        }
    ],
    "sg:phone":"+1 269 944 3735",
    "sg:postcode":"49111",
    "sg:province":"MI",
    "wof:name":"Designs By Silvia",
    "wof:placetype":"venue"
},
  "geometry": {"coordinates":[-86.28510300000001,42.071908],"type":"Point"}
}