{
  "type": "Feature",
  "properties": {
    "iso:country":"US",
    "sg:address":"556 S Cedar St",
    "sg:city":"Kalkaska",
    "sg:classifiers":[
        {
            "category":"Organizations",
            "subcategory":"Non-profit Organization",
            "type":"Services"
        }
    ],
    "sg:phone":"+1 231 258 2979",
    "sg:postcode":"49646",
    "sg:province":"MI",
    "sg:tags":[
        "information",
        "alcoholism",
        "treatment"
    ],
    "wof:name":"Interventions Counseling Svc",
    "wof:placetype":"venue"
},
  "geometry": {"coordinates":[-85.18167099999999,44.726807],"type":"Point"}
}