{
  "type": "Feature",
  "properties": {
    "iso:country":"US",
    "sg:address":"23 Mill Rd",
    "sg:city":"Shelby Twp",
    "sg:classifiers":[
        {
            "category":"Restaurant",
            "type":"Food & Drink"
        }
    ],
    "sg:phone":"+1 586 739 2491",
    "sg:postcode":"48386",
    "sg:province":"MI",
    "wof:name":"Ultimate King Inc",
    "wof:placetype":"venue"
},
  "geometry": {"coordinates":[-83.48759800000001,42.638901],"type":"Point"}
}