{
  "type": "Feature",
  "properties": {
    "iso:country":"US",
    "sg:address":"106 E Elizabeth St",
    "sg:city":"Fenton",
    "sg:classifiers":[
        {
            "category":"Organizations",
            "subcategory":"Religious Organization",
            "type":"Services"
        }
    ],
    "sg:phone":"+1 810 629 5681",
    "sg:postcode":"48430",
    "sg:province":"MI",
    "sg:tags":[
        "church"
    ],
    "wof:name":"Saint Judes Episcopal Church",
    "wof:placetype":"venue"
},
  "geometry": {"coordinates":[-83.70405,42.792478],"type":"Point"}
}