{
  "type": "Feature",
  "properties": {
    "iso:country":"US",
    "sg:address":"10427 Bertram St",
    "sg:city":"Dearborn",
    "sg:classifiers":[
        {
            "category":"Social Services",
            "type":"Services"
        }
    ],
    "sg:phone":"+1 313 933 7796",
    "sg:postcode":"48126",
    "sg:province":"MI",
    "wof:name":"Insight Counseling Center",
    "wof:placetype":"venue"
},
  "geometry": {"coordinates":[-83.163516,42.350621],"type":"Point"}
}