{
  "type": "Feature",
  "properties": {
    "iso:country":"US",
    "sg:address":"9461 Linden Rd",
    "sg:city":"Swartz Creek",
    "sg:classifiers":[
        {
            "category":"Building & Trades",
            "subcategory":"Construction",
            "type":"Services"
        }
    ],
    "sg:phone":"+1 810 655 6482",
    "sg:postcode":"48473",
    "sg:province":"MI",
    "sg:tags":[
        "carpentry",
        "contractor"
    ],
    "wof:name":"K&J Custom Carpentry",
    "wof:placetype":"venue"
},
  "geometry": {"coordinates":[-83.769263,42.892798],"type":"Point"}
}