{
  "type": "Feature",
  "properties": {
    "iso:country":"US",
    "sg:address":"14050 Joseph Campau St",
    "sg:city":"Hamtramck",
    "sg:classifiers":[
        {
            "category":"Food & Beverages",
            "subcategory":"Liquor & Beverages",
            "type":"Retail Goods"
        }
    ],
    "sg:phone":"+1 313 892 6232",
    "sg:postcode":"48212",
    "sg:province":"MI",
    "sg:tags":[
        "beer",
        "spirit",
        "wine"
    ],
    "wof:name":"Vip Liquor",
    "wof:placetype":"venue"
},
  "geometry": {"coordinates":[-83.071602,42.4174],"type":"Point"}
}