{
  "type": "Feature",
  "properties": {
    "iso:country":"US",
    "sg:address":"300 E Washington St",
    "sg:city":"Coldwater",
    "sg:classifiers":[
        {
            "category":"Health Services",
            "subcategory":"Nursing And Care Facility",
            "type":"Services"
        }
    ],
    "sg:phone":"+1 517 278 9494",
    "sg:postcode":"49036",
    "sg:province":"MI",
    "sg:tags":[
        "adult"
    ],
    "wof:name":"Drews Place Of Coldwater II",
    "wof:placetype":"venue"
},
  "geometry": {"coordinates":[-84.990059,41.936071],"type":"Point"}
}