{
  "type": "Feature",
  "properties": {
    "iso:country":"US",
    "sg:address":"2317 Hillsdale Ave",
    "sg:city":"Kalamazoo",
    "sg:classifiers":[
        {
            "category":"Professional",
            "subcategory":"Management & Consulting",
            "type":"Services"
        }
    ],
    "sg:phone":"+1 269 382 5713",
    "sg:postcode":"49006",
    "sg:province":"MI",
    "sg:tags":[
        "business"
    ],
    "wof:name":"Rch2",
    "wof:placetype":"venue"
},
  "geometry": {"coordinates":[-85.61814800000001,42.303116],"type":"Point"}
}