{
  "type": "Feature",
  "properties": {
    "iso:country":"US",
    "sg:address":"3832 Perrine Rd",
    "sg:city":"Rives Junction",
    "sg:classifiers":[
        {
            "category":"Organizations",
            "subcategory":"Religious Organization",
            "type":"Services"
        }
    ],
    "sg:phone":"+1 517 569 3715",
    "sg:postcode":"49277",
    "sg:province":"MI",
    "sg:tags":[
        "clergy"
    ],
    "wof:name":"Wilbur Silvernail",
    "wof:placetype":"venue"
},
  "geometry": {"coordinates":[-84.45962299999999,42.393374],"type":"Point"}
}