{
  "type": "Feature",
  "properties": {
    "iso:country":"US",
    "sg:address":"1913 W Main St",
    "sg:city":"Kalamazoo",
    "sg:classifiers":[
        {
            "category":"Retail",
            "subcategory":"Laundry & Dry Cleaning",
            "type":"Services"
        }
    ],
    "sg:phone":"+1 269 342 5848",
    "sg:postcode":"49006",
    "sg:province":"MI",
    "sg:tags":[
        "garment",
        "plant",
        "agent",
        "drycleaning"
    ],
    "wof:name":"One Hour Martinizing",
    "wof:placetype":"venue"
},
  "geometry": {"coordinates":[-85.613432,42.294555],"type":"Point"}
}