{
  "type": "Feature",
  "properties": {
    "iso:country":"US",
    "sg:address":"8782 Gull Rd",
    "sg:city":"Richland",
    "sg:classifiers":[
        {
            "category":"Wholesale",
            "subcategory":"Durable Goods & Equipment",
            "type":"Manufacturing & Wholesale Goods"
        }
    ],
    "sg:phone":"+1 269 629 5824",
    "sg:postcode":"49083",
    "sg:province":"MI",
    "sg:tags":[
        "representative",
        "manufacturer"
    ],
    "sg:website":"www.kalpaperchem.com",
    "wof:name":"Huygen Instrument Assoc",
    "wof:placetype":"venue"
},
  "geometry": {"coordinates":[-85.46017999999999,42.372314],"type":"Point"}
}