{
  "type": "Feature",
  "properties": {
    "iso:country":"US",
    "sg:address":"180 US Hwy 41",
    "sg:city":"Negaunee",
    "sg:classifiers":[
        {
            "category":"Government",
            "subcategory":"Police Station",
            "type":"Public Place"
        }
    ],
    "sg:phone":"+1 906 475 9922",
    "sg:postcode":"49866",
    "sg:province":"MI",
    "sg:tags":[
        "state"
    ],
    "wof:name":"Michigan State Police",
    "wof:placetype":"venue"
},
  "geometry": {"coordinates":[-87.616058,46.506917],"type":"Point"}
}