{
  "type": "Feature",
  "properties": {
    "iso:country":"US",
    "sg:address":"3599 E 9 Mile Rd",
    "sg:city":"Warren",
    "sg:classifiers":[
        {
            "category":"Retail",
            "subcategory":"Auto Repair",
            "type":"Services"
        }
    ],
    "sg:phone":"+1 586 756 1300",
    "sg:postcode":"48091",
    "sg:province":"MI",
    "sg:tags":[
        "repairing",
        "automobile"
    ],
    "wof:name":"White's Place Inc",
    "wof:placetype":"venue"
},
  "geometry": {"coordinates":[-83.07431699999999,42.462019],"type":"Point"}
}