{
  "type": "Feature",
  "properties": {
    "iso:country":"US",
    "sg:address":"4493 N Genesee Rd",
    "sg:city":"Flint",
    "sg:classifiers":[
        {
            "category":"Building & Trades",
            "subcategory":"Construction",
            "type":"Services"
        }
    ],
    "sg:phone":"+1 810 736 0465",
    "sg:postcode":"48506",
    "sg:province":"MI",
    "sg:tags":[
        "home",
        "builder"
    ],
    "wof:name":"Future Homes Inc",
    "wof:placetype":"venue"
},
  "geometry": {"coordinates":[-83.616719,43.07265],"type":"Point"}
}