{
  "type": "Feature",
  "properties": {
    "iso:country":"US",
    "sg:address":"22526 Garrison St",
    "sg:city":"Dearborn",
    "sg:classifiers":[
        {
            "category":"Retail",
            "subcategory":"Portrait Studio",
            "type":"Services"
        }
    ],
    "sg:phone":"+1 313 278 2376",
    "sg:postcode":"48124",
    "sg:province":"MI",
    "sg:tags":[
        "photo"
    ],
    "wof:name":"Hannahs Eyes Photography",
    "wof:placetype":"venue"
},
  "geometry": {"coordinates":[-83.25289100000001,42.30564],"type":"Point"}
}