{
  "type": "Feature",
  "properties": {
    "iso:country":"US",
    "sg:address":"2003 Allegan St",
    "sg:city":"Saginaw",
    "sg:classifiers":[
        {
            "category":"Food & Beverages",
            "subcategory":"Candy",
            "type":"Retail Goods"
        }
    ],
    "sg:phone":"+1 989 497 0401",
    "sg:postcode":"48602",
    "sg:province":"MI",
    "wof:name":"Human Arrow Resources",
    "wof:placetype":"venue"
},
  "geometry": {"coordinates":[-83.992985,43.415853],"type":"Point"}
}