{
  "type": "Feature",
  "properties": {
    "iso:country":"US",
    "sg:address":"512 N Main St",
    "sg:city":"Capac",
    "sg:classifiers":[
        {
            "category":"Restaurant",
            "type":"Food & Drink"
        }
    ],
    "sg:phone":"+1 810 395 7581",
    "sg:postcode":"48014",
    "sg:province":"MI",
    "sg:tags":[
        "pizza"
    ],
    "wof:name":"Paisano's Restaurant Pizzeria",
    "wof:placetype":"venue"
},
  "geometry": {"coordinates":[-82.928523,43.017608],"type":"Point"}
}