{
  "type": "Feature",
  "properties": {
    "iso:country":"US",
    "sg:address":"4059 Autumn Wood Dr",
    "sg:city":"Fenton",
    "sg:classifiers":[
        {
            "category":"Professional",
            "subcategory":"Business Services",
            "type":"Services"
        }
    ],
    "sg:phone":"+1 810 750 7850",
    "sg:postcode":"48430",
    "sg:province":"MI",
    "wof:name":"Centsible Creations Inc",
    "wof:placetype":"venue"
},
  "geometry": {"coordinates":[-83.75009,42.787478],"type":"Point"}
}