{
  "type": "Feature",
  "properties": {
    "iso:country":"US",
    "sg:address":"14464 120th Ave",
    "sg:city":"Rodney",
    "sg:classifiers":[
        {
            "category":"Farming",
            "subcategory":"Farm",
            "type":"Manufacturing & Wholesale Goods"
        }
    ],
    "sg:phone":"+1 231 972 8047",
    "sg:postcode":"49342",
    "sg:province":"MI",
    "wof:name":"Paul Main Farms",
    "wof:placetype":"venue"
},
  "geometry": {"coordinates":[-85.324026,43.681217],"type":"Point"}
}