{
  "type": "Feature",
  "properties": {
    "iso:country":"US",
    "sg:address":"648 Monroe Ave NW",
    "sg:city":"Grand Rapids",
    "sg:classifiers":[
        {
            "category":"Banks & Credit Unions",
            "subcategory":"Bank",
            "type":"Services"
        }
    ],
    "sg:phone":"+1 616 443 9572",
    "sg:postcode":"49503",
    "sg:province":"MI",
    "sg:tags":[
        "mortgage",
        "loan",
        "broker",
        "real estate"
    ],
    "wof:name":"Assurance Home Finance",
    "wof:placetype":"venue"
},
  "geometry": {"coordinates":[-85.672347,42.974335],"type":"Point"}
}