{
  "type": "Feature",
  "properties": {
    "iso:country":"US",
    "sg:address":"24463 Heritage Dr",
    "sg:city":"Trenton",
    "sg:classifiers":[
        {
            "category":"Professional",
            "subcategory":"Business Services",
            "type":"Services"
        }
    ],
    "sg:phone":"+1 734 692 0046",
    "sg:postcode":"48183",
    "sg:province":"MI",
    "wof:name":"X Celent Inspections",
    "wof:placetype":"venue"
},
  "geometry": {"coordinates":[-83.250038,42.128612],"type":"Point"}
}