{
  "type": "Feature",
  "properties": {
    "iso:country":"US",
    "sg:address":"24933 Newberry Dr",
    "sg:city":"Novi",
    "sg:classifiers":[
        {
            "category":"Professional",
            "subcategory":"Management & Consulting",
            "type":"Services"
        }
    ],
    "sg:phone":"+1 248 347 2957",
    "sg:postcode":"48375",
    "sg:province":"MI",
    "wof:name":"PCL Program Management Inc",
    "wof:placetype":"venue"
},
  "geometry": {"coordinates":[-83.488601,42.472384],"type":"Point"}
}