{
  "type": "Feature",
  "properties": {
    "iso:country":"US",
    "sg:address":"1505 Grant Ave",
    "sg:city":"Grand Haven",
    "sg:classifiers":[
        {
            "category":"Building & Trades",
            "subcategory":"Electrical",
            "type":"Services"
        }
    ],
    "sg:phone":"+1 616 842 3706",
    "sg:postcode":"49417",
    "sg:province":"MI",
    "sg:tags":[
        "electric",
        "contractor"
    ],
    "wof:name":"Erickson Electric Svc",
    "wof:placetype":"venue"
},
  "geometry": {"coordinates":[-86.203444,43.057717],"type":"Point"}
}