{
  "type": "Feature",
  "properties": {
    "iso:country":"US",
    "sg:address":"11021 Hyde Rd",
    "sg:city":"Clarklake",
    "sg:classifiers":[
        {
            "category":"Insurance",
            "subcategory":"Insurance Agent",
            "type":"Services"
        }
    ],
    "sg:phone":"+1 517 529 9070",
    "sg:postcode":"49234",
    "sg:province":"MI",
    "wof:name":"Vernier Agency",
    "wof:placetype":"venue"
},
  "geometry": {"coordinates":[-84.34496300000001,42.098715],"type":"Point"}
}