{
  "type": "Feature",
  "properties": {
    "iso:country":"US",
    "sg:address":"2750 W Big Beaver Rd",
    "sg:city":"Troy",
    "sg:classifiers":[
        {
            "category":"Shopping",
            "subcategory":"Optician",
            "type":"Retail Goods"
        }
    ],
    "sg:phone":"+1 248 614 9120",
    "sg:postcode":"48084",
    "sg:province":"MI",
    "sg:tags":[
        "eyewear"
    ],
    "sg:website":"www2.sunglasshut.com",
    "wof:name":"Sunglass Hut International",
    "wof:placetype":"venue"
},
  "geometry": {"coordinates":[-83.18235900000001,42.561623],"type":"Point"}
}