{
  "type": "Feature",
  "properties": {
    "iso:country":"US",
    "sg:address":"72400 Lassier Rd",
    "sg:city":"Bruce",
    "sg:classifiers":[
        {
            "category":"Wholesale",
            "subcategory":"Machinery & Supplies",
            "type":"Manufacturing & Wholesale Goods"
        },
        {
            "category":"Professional",
            "subcategory":"Business Services",
            "type":"Services"
        }
    ],
    "sg:phone":"+1 586 752 1810",
    "sg:postcode":"48065",
    "sg:province":"MI",
    "sg:tags":[
        "consulting",
        "aircraft",
        "broker"
    ],
    "wof:name":"Lindow Aircraft Associates",
    "wof:placetype":"venue"
},
  "geometry": {"coordinates":[-83.062358,42.827246],"type":"Point"}
}