{
  "type": "Feature",
  "properties": {
    "iso:country":"US",
    "sg:address":"1096 N Huron River Dr",
    "sg:city":"Ypsilanti",
    "sg:classifiers":[
        {
            "category":"Food & Beverages",
            "subcategory":"Groceries & Convenience Stores",
            "type":"Retail Goods"
        }
    ],
    "sg:phone":"+1 734 485 0599",
    "sg:postcode":"48197",
    "sg:province":"MI",
    "wof:name":"Em",
    "wof:placetype":"venue"
},
  "geometry": {"coordinates":[-83.623977,42.254833],"type":"Point"}
}