{
  "type": "Feature",
  "properties": {
    "iso:country":"US",
    "sg:address":"126 W 64th St",
    "sg:city":"Newaygo",
    "sg:classifiers":[
        {
            "category":"Building & Trades",
            "subcategory":"Construction",
            "type":"Services"
        }
    ],
    "sg:phone":"+1 231 652 3921",
    "sg:postcode":"49337",
    "sg:province":"MI",
    "sg:tags":[
        "contractor"
    ],
    "wof:name":"Kauffman Construction",
    "wof:placetype":"venue"
},
  "geometry": {"coordinates":[-85.80392999999999,43.438136],"type":"Point"}
}