{
  "type": "Feature",
  "properties": {
    "iso:country":"US",
    "sg:address":"6481 Faussett Rd",
    "sg:city":"Howell",
    "sg:classifiers":[
        {
            "category":"Organizations",
            "subcategory":"Religious Organization",
            "type":"Services"
        }
    ],
    "sg:phone":"+1 517 546 9807",
    "sg:postcode":"48855",
    "sg:province":"MI",
    "wof:name":"St Augustines Church",
    "wof:placetype":"venue"
},
  "geometry": {"coordinates":[-83.820903,42.705814],"type":"Point"}
}