{
  "type": "Feature",
  "properties": {
    "iso:country":"US",
    "sg:address":"9050 E Michigan Ave",
    "sg:city":"Galesburg",
    "sg:classifiers":[
        {
            "category":"Recreation",
            "type":"Entertainment"
        }
    ],
    "sg:phone":"+1 269 665 9608",
    "sg:postcode":"49053",
    "sg:province":"MI",
    "sg:tags":[
        "parks"
    ],
    "wof:name":"River Oaks Park",
    "wof:placetype":"venue"
},
  "geometry": {"coordinates":[-85.452851,42.288515],"type":"Point"}
}