{
  "type": "Feature",
  "properties": {
    "iso:country":"US",
    "sg:address":"755 Dollies Ln",
    "sg:city":"Hastings",
    "sg:classifiers":[
        {
            "category":"Retail",
            "subcategory":"Repair Shop",
            "type":"Services"
        }
    ],
    "sg:phone":"+1 269 945 8885",
    "sg:postcode":"49058",
    "sg:province":"MI",
    "wof:name":"Wildlife Taxidermy",
    "wof:placetype":"venue"
},
  "geometry": {"coordinates":[-85.27267500000001,42.69134],"type":"Point"}
}