{
  "type": "Feature",
  "properties": {
    "iso:country":"US",
    "sg:address":"11595 E Lakewood Blvd",
    "sg:city":"Holland",
    "sg:classifiers":[
        {
            "category":"Professional",
            "subcategory":"Computer Services",
            "type":"Services"
        }
    ],
    "sg:phone":"+1 616 396 4287",
    "sg:postcode":"49424",
    "sg:province":"MI",
    "sg:tags":[
        "repair"
    ],
    "wof:name":"Bp Computer",
    "wof:placetype":"venue"
},
  "geometry": {"coordinates":[-86.066507,42.805003],"type":"Point"}
}