{
  "type": "Feature",
  "properties": {
    "iso:country":"US",
    "sg:address":"23 E Front St",
    "sg:city":"Monroe",
    "sg:classifiers":[
        {
            "category":"Professional",
            "subcategory":"Advertising",
            "type":"Services"
        }
    ],
    "sg:phone":"+1 734 242 6605",
    "sg:postcode":"48161",
    "sg:province":"MI",
    "sg:tags":[
        "distribution"
    ],
    "sg:website":"www.slickpay.com",
    "wof:name":"Monroe Wholesale Distributors",
    "wof:placetype":"venue"
},
  "geometry": {"coordinates":[-83.397285,41.916472],"type":"Point"}
}