{
  "type": "Feature",
  "properties": {
    "iso:country":"US",
    "sg:address":"58210 Timothy Ln",
    "sg:city":"Washington",
    "sg:classifiers":[
        {
            "category":"Wholesale",
            "subcategory":"Machinery & Supplies",
            "type":"Manufacturing & Wholesale Goods"
        }
    ],
    "sg:phone":"+1 586 677 1044",
    "sg:postcode":"48094",
    "sg:province":"MI",
    "sg:tags":[
        "equipment",
        "industrial"
    ],
    "wof:name":"Beyed Inc",
    "wof:placetype":"venue"
},
  "geometry": {"coordinates":[-83.065066,42.721641],"type":"Point"}
}