{
  "type": "Feature",
  "properties": {
    "iso:country":"US",
    "sg:address":"6707 Highland Rd",
    "sg:city":"White Lake",
    "sg:classifiers":[
        {
            "category":"Restaurant",
            "type":"Food & Drink"
        }
    ],
    "sg:menulink":"http://www.allmenus.com/mi/white-lake/251411-billys-tip-n-inn/menu/",
    "sg:phone":"+1 248 889 7885",
    "sg:postcode":"48383",
    "sg:province":"MI",
    "sg:tags":[
        "barbecue",
        "american"
    ],
    "wof:name":"Billy's Tip N' Inn",
    "wof:placetype":"venue"
},
  "geometry": {"coordinates":[-83.52298999999999,42.649007],"type":"Point"}
}