{
  "type": "Feature",
  "properties": {
    "iso:country":"US",
    "sg:address":"14390 Wyoming St",
    "sg:city":"Detroit",
    "sg:classifiers":[
        {
            "category":"Professional",
            "subcategory":"Management & Consulting",
            "type":"Services"
        }
    ],
    "sg:phone":"+1 313 491 7700",
    "sg:postcode":"48238",
    "sg:province":"MI",
    "wof:name":"Nick-N-Willys World Famous",
    "wof:placetype":"venue"
},
  "geometry": {"coordinates":[-83.15926399999999,42.394857],"type":"Point"}
}