{
  "type": "Feature",
  "properties": {
    "iso:country":"US",
    "sg:address":"3535 Teeple Ave",
    "sg:city":"Fort Gratiot",
    "sg:classifiers":[
        {
            "category":"Professional",
            "subcategory":"Business Services",
            "type":"Services"
        }
    ],
    "sg:phone":"+1 810 982 3733",
    "sg:postcode":"48059",
    "sg:province":"MI",
    "sg:tags":[
        "appraiser"
    ],
    "wof:name":"Blue Water Appraisal Co",
    "wof:placetype":"venue"
},
  "geometry": {"coordinates":[-82.49224100000001,43.012341],"type":"Point"}
}