{
  "type": "Feature",
  "properties": {
    "iso:country":"US",
    "sg:address":"640 W 14 Mile Rd",
    "sg:city":"Clawson",
    "sg:classifiers":[
        {
            "category":"Banks & Credit Unions",
            "subcategory":"Bank",
            "type":"Services"
        }
    ],
    "sg:phone":"+1 248 435 0022",
    "sg:postcode":"48017",
    "sg:province":"MI",
    "sg:tags":[
        "cashing",
        "check"
    ],
    "wof:name":"Access To Cash",
    "wof:placetype":"venue"
},
  "geometry": {"coordinates":[-83.1559,42.533326],"type":"Point"}
}