{
  "type": "Feature",
  "properties": {
    "iso:country":"US",
    "sg:address":"1384 Birchfield Rd",
    "sg:city":"Saginaw",
    "sg:classifiers":[
        {
            "category":"Taxi",
            "type":"Transportation"
        }
    ],
    "sg:phone":"+1 989 781 0231",
    "sg:postcode":"48609",
    "sg:province":"MI",
    "sg:tags":[
        "taxicab"
    ],
    "wof:name":"At Your Svc",
    "wof:placetype":"venue"
},
  "geometry": {"coordinates":[-84.07568999999999,43.429451],"type":"Point"}
}