{
  "type": "Feature",
  "properties": {
    "iso:country":"US",
    "sg:address":"630 S Saginaw St",
    "sg:city":"Flint",
    "sg:classifiers":[
        {
            "category":"Government",
            "subcategory":"Office",
            "type":"Public Place"
        }
    ],
    "sg:phone":"+1 810 257 3010",
    "sg:postcode":"48502",
    "sg:province":"MI",
    "wof:name":"Genesee Home Improvement Prgrm",
    "wof:placetype":"venue"
},
  "geometry": {"coordinates":[-83.689317,43.014305],"type":"Point"}
}