{
  "type": "Feature",
  "properties": {
    "iso:country":"US",
    "sg:address":"15914 Jeanette",
    "sg:city":"Southfield",
    "sg:classifiers":[
        {
            "category":"Health Services",
            "subcategory":"Health Practitioner",
            "type":"Services"
        }
    ],
    "sg:phone":"+1 248 376 6046",
    "sg:postcode":"48075",
    "sg:province":"MI",
    "sg:tags":[
        "home",
        "care"
    ],
    "wof:name":"Eye Travel",
    "wof:placetype":"venue"
},
  "geometry": {"coordinates":[-83.20547500000001,42.475856],"type":"Point"}
}