{
  "type": "Feature",
  "properties": {
    "iso:country":"US",
    "sg:address":"619 Main St",
    "sg:city":"Essexville",
    "sg:classifiers":[
        {
            "category":"Organizations",
            "subcategory":"Religious Organization",
            "type":"Services"
        },
        {
            "category":"Education",
            "subcategory":"School",
            "type":"Public Place"
        }
    ],
    "sg:phone":"+1 989 892 0363",
    "sg:postcode":"48732",
    "sg:province":"MI",
    "wof:name":"Saint John School",
    "wof:placetype":"venue"
},
  "geometry": {"coordinates":[-83.840632,43.609707],"type":"Point"}
}