{
  "type": "Feature",
  "properties": {
    "iso:country":"US",
    "sg:address":"2055 28th St SE",
    "sg:city":"Grand Rapids",
    "sg:classifiers":[
        {
            "category":"Food & Beverages",
            "subcategory":"Bakery",
            "type":"Retail Goods"
        }
    ],
    "sg:phone":"+1 616 247 7633",
    "sg:postcode":"49508",
    "sg:province":"MI",
    "sg:tags":[
        "baker"
    ],
    "wof:name":"Bay Window Bakery",
    "wof:placetype":"venue"
},
  "geometry": {"coordinates":[-85.617434,42.91271],"type":"Point"}
}