{
  "type": "Feature",
  "properties": {
    "iso:country":"US",
    "sg:address":"935 W Lovell St",
    "sg:city":"Kalamazoo",
    "sg:classifiers":[
        {
            "category":"Education",
            "subcategory":"Dance Studio",
            "type":"Public Place"
        }
    ],
    "sg:phone":"+1 269 342 1571",
    "sg:postcode":"49007",
    "sg:province":"MI",
    "sg:tags":[
        "instruction",
        "dancing"
    ],
    "wof:name":"Weavers Dance Studio",
    "wof:placetype":"venue"
},
  "geometry": {"coordinates":[-85.597296,42.28867],"type":"Point"}
}