{
  "type": "Feature",
  "properties": {
    "iso:country":"US",
    "sg:address":"1100 Killmaster Dr",
    "sg:city":"Oscoda",
    "sg:classifiers":[
        {
            "category":"Real Estate",
            "subcategory":"Real Estate Operator",
            "type":"Services"
        }
    ],
    "sg:phone":"+1 989 739 1414",
    "sg:postcode":"48750",
    "sg:province":"MI",
    "sg:tags":[
        "owner"
    ],
    "wof:name":"Transition Ltd Housing Assn",
    "wof:placetype":"venue"
},
  "geometry": {"coordinates":[-83.356505,44.42692],"type":"Point"}
}