{
  "type": "Feature",
  "properties": {
    "iso:country":"US",
    "sg:address":"3753 Varsity Dr",
    "sg:city":"Ann Arbor",
    "sg:classifiers":[
        {
            "category":"Real Estate",
            "subcategory":"Real Estate Agent",
            "type":"Services"
        }
    ],
    "sg:phone":"+1 734 973 0300",
    "sg:postcode":"48108",
    "sg:province":"MI",
    "wof:name":"Varsity Group",
    "wof:placetype":"venue"
},
  "geometry": {"coordinates":[-83.72583400000001,42.231232],"type":"Point"}
}