{
  "type": "Feature",
  "properties": {
    "iso:country":"US",
    "sg:address":"7461 Woodland Rd",
    "sg:city":"Lexington",
    "sg:classifiers":[
        {
            "category":"Home & Garden",
            "subcategory":"Building Materials",
            "type":"Retail Goods"
        }
    ],
    "sg:phone":"+1 810 359 8502",
    "sg:postcode":"48450",
    "sg:province":"MI",
    "wof:name":"Sun Glass Factory Inc",
    "wof:placetype":"venue"
},
  "geometry": {"coordinates":[-82.521749,43.213134],"type":"Point"}
}