{
  "type": "Feature",
  "properties": {
    "iso:country":"US",
    "sg:address":"200 Saginaw St",
    "sg:city":"Ishpeming",
    "sg:classifiers":[
        {
            "category":"Social Services",
            "subcategory":"Adult Care",
            "type":"Services"
        }
    ],
    "sg:phone":"+1 906 485 1061",
    "sg:postcode":"49849",
    "sg:province":"MI",
    "sg:tags":[
        "home",
        "residential"
    ],
    "wof:name":"Marquette County Medical Care",
    "wof:placetype":"venue"
},
  "geometry": {"coordinates":[-87.681754,46.472727],"type":"Point"}
}