{
  "type": "Feature",
  "properties": {
    "iso:country":"US",
    "sg:address":"101 1st St",
    "sg:city":"Bay City",
    "sg:classifiers":[
        {
            "category":"Government",
            "subcategory":"Court House",
            "type":"Public Place"
        }
    ],
    "sg:phone":"+1 989 895 5712",
    "sg:postcode":"48708",
    "sg:province":"MI",
    "sg:tags":[
        "federal",
        "counsel"
    ],
    "wof:name":"US Attorney",
    "wof:placetype":"venue"
},
  "geometry": {"coordinates":[-83.88956899999999,43.603238],"type":"Point"}
}