{
  "type": "Feature",
  "properties": {
    "iso:country":"US",
    "sg:address":"1505 W Hamlin Rd",
    "sg:city":"Rochester Hills",
    "sg:classifiers":[
        {
            "category":"Manufacturing",
            "subcategory":"Tools & Machinery",
            "type":"Manufacturing & Wholesale Goods"
        }
    ],
    "sg:phone":"+1 248 853 5888",
    "sg:postcode":"48309",
    "sg:province":"MI",
    "sg:tags":[
        "industry",
        "special"
    ],
    "sg:website":"www.dphgage.com",
    "wof:name":"Detroit Precision Tool Co",
    "wof:placetype":"venue"
},
  "geometry": {"coordinates":[-83.16175200000001,42.651597],"type":"Point"}
}