{
  "type": "Feature",
  "properties": {
    "iso:country":"US",
    "sg:address":"4433 W Saginaw Hwy",
    "sg:city":"Lansing",
    "sg:classifiers":[
        {
            "category":"Health Services",
            "subcategory":"Health Practitioner",
            "type":"Services"
        }
    ],
    "sg:phone":"+1 517 321 6668",
    "sg:postcode":"48917",
    "sg:province":"MI",
    "sg:tags":[
        "psychologist"
    ],
    "wof:name":"Delta Psychological Svc",
    "wof:placetype":"venue"
},
  "geometry": {"coordinates":[-84.611375,42.741034],"type":"Point"}
}