{
  "type": "Feature",
  "properties": {
    "iso:country":"US",
    "sg:address":"16107 Baird Ct",
    "sg:city":"Spring Lake",
    "sg:classifiers":[
        {
            "category":"Building & Trades",
            "subcategory":"Landscaping Services",
            "type":"Services"
        }
    ],
    "sg:phone":"+1 616 842 8008",
    "sg:postcode":"49456",
    "sg:province":"MI",
    "sg:tags":[
        "designer",
        "landscape"
    ],
    "wof:name":"B & D Site Design",
    "wof:placetype":"venue"
},
  "geometry": {"coordinates":[-86.189807,43.110133],"type":"Point"}
}