{
  "type": "Feature",
  "properties": {
    "iso:country":"US",
    "sg:address":"33493 W 14 Mile Rd",
    "sg:city":"Farmington Hills",
    "sg:classifiers":[
        {
            "category":"Health Services",
            "subcategory":"Clinic",
            "type":"Services"
        }
    ],
    "sg:phone":"+1 248 661 3900",
    "sg:postcode":"48331",
    "sg:province":"MI",
    "sg:tags":[
        "counseling",
        "mental"
    ],
    "wof:name":"Levy-Larson Rhonda B PHD PC",
    "wof:placetype":"venue"
},
  "geometry": {"coordinates":[-83.38297300000001,42.527734],"type":"Point"}
}