{
  "type": "Feature",
  "properties": {
    "iso:country":"US",
    "sg:address":"10027 W 8 Mile Rd",
    "sg:city":"Detroit",
    "sg:classifiers":[
        {
            "category":"Building & Trades",
            "subcategory":"Pest Control",
            "type":"Services"
        }
    ],
    "sg:phone":"+1 313 861 7899",
    "sg:postcode":"48221",
    "sg:province":"MI",
    "wof:name":"Gold Star Pest Control",
    "wof:placetype":"venue"
},
  "geometry": {"coordinates":[-83.16201599999999,42.445366],"type":"Point"}
}