{
  "type": "Feature",
  "properties": {
    "iso:country":"US",
    "sg:address":"1350 N Elba Rd",
    "sg:city":"Lapeer",
    "sg:classifiers":[
        {
            "category":"Farming",
            "subcategory":"Farm",
            "type":"Manufacturing & Wholesale Goods"
        }
    ],
    "sg:phone":"+1 810 664 1619",
    "sg:postcode":"48446",
    "sg:province":"MI",
    "wof:name":"Jc Farms",
    "wof:placetype":"venue"
},
  "geometry": {"coordinates":[-83.441929,43.068071],"type":"Point"}
}