{
  "type": "Feature",
  "properties": {
    "iso:country":"US",
    "sg:address":"4408 W Walton Blvd",
    "sg:city":"Waterford",
    "sg:classifiers":[
        {
            "category":"Personal",
            "subcategory":"Beauty Salon",
            "type":"Services"
        }
    ],
    "sg:phone":"+1 248 674 4120",
    "sg:postcode":"48329",
    "sg:province":"MI",
    "sg:tags":[
        "shop"
    ],
    "wof:name":"Hair Emporium The",
    "wof:placetype":"venue"
},
  "geometry": {"coordinates":[-83.375339,42.689935],"type":"Point"}
}