{
  "type": "Feature",
  "properties": {
    "iso:country":"US",
    "sg:address":"21850 Melrose Ave Ste 7",
    "sg:city":"Southfield",
    "sg:classifiers":[
        {
            "category":"Education",
            "subcategory":"Special Training",
            "type":"Public Place"
        }
    ],
    "sg:phone":"+1 248 356 4236",
    "sg:postcode":"48075",
    "sg:province":"MI",
    "sg:tags":[
        "tutoring"
    ],
    "wof:name":"Sylvan Learning Center Southfield",
    "wof:placetype":"venue"
},
  "geometry": {"coordinates":[-83.258003,42.445801],"type":"Point"}
}