{
  "type": "Feature",
  "properties": {
    "iso:country":"US",
    "sg:address":"2115 Boston St SE",
    "sg:city":"Grand Rapids",
    "sg:classifiers":[
        {
            "category":"Health Services",
            "subcategory":"Clinic",
            "type":"Services"
        }
    ],
    "sg:phone":"+1 616 241 1134",
    "sg:postcode":"49506",
    "sg:province":"MI",
    "wof:name":"Venture Behavioral Health",
    "wof:placetype":"venue"
},
  "geometry": {"coordinates":[-85.61689800000001,42.934362],"type":"Point"}
}