{
  "type": "Feature",
  "properties": {
    "iso:country":"US",
    "sg:address":"7600 Holden Rd",
    "sg:city":"Stevensville",
    "sg:classifiers":[
        {
            "category":"Farming",
            "subcategory":"Vineyard",
            "type":"Manufacturing & Wholesale Goods"
        }
    ],
    "sg:phone":"+1 269 422 1428",
    "sg:postcode":"49127",
    "sg:province":"MI",
    "sg:tags":[
        "grape"
    ],
    "wof:name":"Gaul Adeline",
    "wof:placetype":"venue"
},
  "geometry": {"coordinates":[-86.514278,41.980303],"type":"Point"}
}