{
  "type": "Feature",
  "properties": {
    "iso:country":"US",
    "sg:address":"149 Vicary Rd",
    "sg:city":"Leslie",
    "sg:classifiers":[
        {
            "category":"Organizations",
            "subcategory":"Religious Organization",
            "type":"Services"
        }
    ],
    "sg:phone":"+1 517 589 0581",
    "sg:postcode":"49251",
    "sg:province":"MI",
    "wof:name":"National Spiritualist Asso",
    "wof:placetype":"venue"
},
  "geometry": {"coordinates":[-84.353702,42.431934],"type":"Point"}
}