{
  "type": "Feature",
  "properties": {
    "iso:country":"US",
    "sg:address":"3892 Division Ave S",
    "sg:city":"Wyoming",
    "sg:classifiers":[
        {
            "category":"Wholesale",
            "subcategory":"Auto Parts",
            "type":"Manufacturing & Wholesale Goods"
        }
    ],
    "sg:phone":"+1 616 261 9561",
    "sg:postcode":"49548",
    "sg:province":"MI",
    "sg:tags":[
        "automobile",
        "rebuilt"
    ],
    "wof:name":"Little's Towing & Auto Ctr",
    "wof:placetype":"venue"
},
  "geometry": {"coordinates":[-85.665015,42.893458],"type":"Point"}
}