{
  "type": "Feature",
  "properties": {
    "iso:country":"US",
    "sg:address":"3656 63rd St",
    "sg:city":"Saugatuck",
    "sg:classifiers":[
        {
            "category":"Social Services",
            "subcategory":"Adult Care",
            "type":"Services"
        }
    ],
    "sg:phone":"+1 269 857 1286",
    "sg:postcode":"49453",
    "sg:province":"MI",
    "sg:tags":[
        "residential"
    ],
    "sg:website":"www.thebelvedereinn.com",
    "wof:name":"Belvedere Inn & Restaurant",
    "wof:placetype":"venue"
},
  "geometry": {"coordinates":[-86.16486399999999,42.690355],"type":"Point"}
}