{
  "type": "Feature",
  "properties": {
    "iso:country":"US",
    "sg:address":"164 W Vienna St",
    "sg:city":"Clio",
    "sg:classifiers":[
        {
            "category":"Education",
            "subcategory":"Special Training",
            "type":"Public Place"
        }
    ],
    "sg:phone":"+1 810 670 0889",
    "sg:postcode":"48420",
    "sg:province":"MI",
    "sg:tags":[
        "instruction",
        "music"
    ],
    "wof:name":"Alpha Music Instruction",
    "wof:placetype":"venue"
},
  "geometry": {"coordinates":[-83.735687,43.177455],"type":"Point"}
}