{
  "type": "Feature",
  "properties": {
    "iso:country":"US",
    "sg:address":"201 Water St",
    "sg:city":"Paris",
    "sg:classifiers":[
        {
            "category":"Banks & Credit Unions",
            "subcategory":"Financial Services",
            "type":"Services"
        }
    ],
    "sg:phone":"+1 231 592 0431",
    "sg:postcode":"49338",
    "sg:province":"MI",
    "sg:tags":[
        "trust",
        "management"
    ],
    "wof:name":"Pawfect Cmpanions Therapy Dogs",
    "wof:placetype":"venue"
},
  "geometry": {"coordinates":[-85.506641,43.77513],"type":"Point"}
}