{
  "type": "Feature",
  "properties": {
    "iso:country":"US",
    "sg:address":"11792 Belleville Rd",
    "sg:city":"Belleville",
    "sg:classifiers":[
        {
            "category":"Personal",
            "subcategory":"Beauty Salon",
            "type":"Services"
        }
    ],
    "sg:phone":"+1 734 699 7610",
    "sg:postcode":"48111",
    "sg:province":"MI",
    "sg:tags":[
        "shop"
    ],
    "wof:name":"Derricks Hair Design",
    "wof:placetype":"venue"
},
  "geometry": {"coordinates":[-83.487016,42.214295],"type":"Point"}
}