{
  "type": "Feature",
  "properties": {
    "iso:country":"US",
    "sg:address":"6846 Kitson Dr NE",
    "sg:city":"Rockford",
    "sg:classifiers":[
        {
            "category":"Building & Trades",
            "subcategory":"Plumbing",
            "type":"Services"
        }
    ],
    "sg:phone":"+1 616 874 1480",
    "sg:postcode":"49341",
    "sg:province":"MI",
    "sg:tags":[
        "contractor"
    ],
    "wof:name":"Commercial Heating & Cooling",
    "wof:placetype":"venue"
},
  "geometry": {"coordinates":[-85.464538,43.091309],"type":"Point"}
}