{
  "type": "Feature",
  "properties": {
    "iso:country":"US",
    "sg:address":"603 Lansing Ave",
    "sg:city":"Jackson",
    "sg:classifiers":[
        {
            "category":"Health Services",
            "subcategory":"Doctor",
            "type":"Services"
        }
    ],
    "sg:phone":"+1 517 787 8371",
    "sg:postcode":"49202",
    "sg:province":"MI",
    "sg:tags":[
        "physician",
        "surgeon"
    ],
    "wof:name":"Central Clinic",
    "wof:placetype":"venue"
},
  "geometry": {"coordinates":[-84.414745,42.255595],"type":"Point"}
}