{
  "type": "Feature",
  "properties": {
    "iso:country":"US",
    "sg:address":"801 W Center Rd",
    "sg:city":"Essexville",
    "sg:classifiers":[
        {
            "category":"Government",
            "subcategory":"Office",
            "type":"Public Place"
        }
    ],
    "sg:phone":"+1 989 895 5968",
    "sg:postcode":"48732",
    "sg:province":"MI",
    "sg:tags":[
        "county",
        "resource"
    ],
    "wof:name":"Bay County Div-Aging Hampton",
    "wof:placetype":"venue"
},
  "geometry": {"coordinates":[-83.81339699999999,43.594028],"type":"Point"}
}