{
  "type": "Feature",
  "properties": {
    "iso:country":"US",
    "sg:address":"9473 Genesee St",
    "sg:city":"New Lothrop",
    "sg:classifiers":[
        {
            "category":"Professional",
            "subcategory":"Business Services",
            "type":"Services"
        }
    ],
    "sg:phone":"+1 810 638 7409",
    "sg:postcode":"48460",
    "sg:province":"MI",
    "sg:tags":[
        "sales",
        "estate"
    ],
    "wof:name":"Attic To Basement Cleanouts",
    "wof:placetype":"venue"
},
  "geometry": {"coordinates":[-83.97063300000001,43.116647],"type":"Point"}
}