{
  "type": "Feature",
  "properties": {
    "iso:country":"US",
    "sg:address":"548 Church St",
    "sg:city":"Ann Arbor",
    "sg:classifiers":[
        {
            "category":"Education",
            "subcategory":"Dance Studio",
            "type":"Public Place"
        }
    ],
    "sg:phone":"+1 734 668 1001",
    "sg:postcode":"48104",
    "sg:province":"MI",
    "sg:tags":[
        "instruction",
        "dancing"
    ],
    "wof:name":"Ann Arbor Ballet Theater",
    "wof:placetype":"venue"
},
  "geometry": {"coordinates":[-83.734466,42.27755],"type":"Point"}
}