{
  "type": "Feature",
  "properties": {
    "iso:country":"US",
    "sg:address":"7204 Sheldon Rd",
    "sg:city":"Whitmore Lake",
    "sg:classifiers":[
        {
            "category":"Retail",
            "subcategory":"Repair Shop",
            "type":"Services"
        }
    ],
    "sg:phone":"+1 810 231 8343",
    "sg:postcode":"48189",
    "sg:province":"MI",
    "wof:name":"Sharpening Service",
    "wof:placetype":"venue"
},
  "geometry": {"coordinates":[-83.805188,42.430729],"type":"Point"}
}