{
  "type": "Feature",
  "properties": {
    "iso:country":"US",
    "sg:address":"134 Hubbard St",
    "sg:city":"Allegan",
    "sg:classifiers":[
        {
            "category":"Shopping",
            "subcategory":"Gifts & Souvenirs",
            "type":"Retail Goods"
        }
    ],
    "sg:phone":"+1 269 686 0800",
    "sg:postcode":"49010",
    "sg:province":"MI",
    "sg:tags":[
        "shop"
    ],
    "wof:name":"Her Heart's Desire",
    "wof:placetype":"venue"
},
  "geometry": {"coordinates":[-85.850883,42.527711],"type":"Point"}
}