{
  "type": "Feature",
  "properties": {
    "iso:country":"US",
    "sg:address":"5600 W Maple Rd",
    "sg:city":"West Bloomfield",
    "sg:classifiers":[
        {
            "category":"Professional",
            "subcategory":"Business Services",
            "type":"Services"
        }
    ],
    "sg:phone":"+1 248 737 8777",
    "sg:postcode":"48322",
    "sg:province":"MI",
    "sg:tags":[
        "barricade"
    ],
    "wof:name":"Hydro-Guard Of Michigan",
    "wof:placetype":"venue"
},
  "geometry": {"coordinates":[-83.35641800000001,42.543138],"type":"Point"}
}