{
  "type": "Feature",
  "properties": {
    "iso:country":"US",
    "sg:address":"17940 Mayfield St",
    "sg:city":"Livonia",
    "sg:classifiers":[
        {
            "category":"Insurance",
            "subcategory":"Insurance Agent",
            "type":"Services"
        }
    ],
    "sg:phone":"+1 734 525 1625",
    "sg:postcode":"48152",
    "sg:province":"MI",
    "wof:name":"David Albright Agency",
    "wof:placetype":"venue"
},
  "geometry": {"coordinates":[-83.368348,42.417986],"type":"Point"}
}