{
  "type": "Feature",
  "properties": {
    "iso:country":"US",
    "sg:address":"6600 S Young Rd",
    "sg:city":"Falmouth",
    "sg:classifiers":[
        {
            "category":"Professional",
            "subcategory":"Business Services",
            "type":"Services"
        }
    ],
    "sg:phone":"+1 231 328 3000",
    "sg:postcode":"49632",
    "sg:province":"MI",
    "wof:name":"Dynamic Liquidators",
    "wof:placetype":"venue"
},
  "geometry": {"coordinates":[-84.962694,44.240172],"type":"Point"}
}