{
  "type": "Feature",
  "properties": {
    "iso:country":"US",
    "sg:address":"9843 Red Arrow Hwy",
    "sg:city":"Bridgman",
    "sg:classifiers":[
        {
            "category":"Insurance",
            "subcategory":"Insurance Agent",
            "type":"Services"
        }
    ],
    "sg:phone":"+1 269 465 6400",
    "sg:postcode":"49106",
    "sg:province":"MI",
    "wof:name":"Barnes Agency",
    "wof:placetype":"venue"
},
  "geometry": {"coordinates":[-86.564831,41.940531],"type":"Point"}
}