{
  "type": "Feature",
  "properties": {
    "iso:country":"US",
    "sg:address":"5744 Cannes Dr",
    "sg:city":"Sterling Heights",
    "sg:classifiers":[
        {
            "category":"Building & Trades",
            "subcategory":"Construction",
            "type":"Services"
        }
    ],
    "sg:phone":"+1 586 997 3942",
    "sg:postcode":"48314",
    "sg:province":"MI",
    "sg:tags":[
        "house"
    ],
    "wof:name":"Alex Lukasik Construction Co",
    "wof:placetype":"venue"
},
  "geometry": {"coordinates":[-83.053443,42.615807],"type":"Point"}
}