{
  "type": "Feature",
  "properties": {
    "iso:country":"US",
    "sg:address":"4262 Main St",
    "sg:city":"Brown City",
    "sg:classifiers":[
        {
            "category":"Personal",
            "subcategory":"Beauty Salon",
            "type":"Services"
        }
    ],
    "sg:phone":"+1 810 346 3150",
    "sg:postcode":"48416",
    "sg:province":"MI",
    "wof:name":"Hair Studio",
    "wof:placetype":"venue"
},
  "geometry": {"coordinates":[-82.989628,43.212231],"type":"Point"}
}