{
  "type": "Feature",
  "properties": {
    "iso:country":"US",
    "sg:address":"3760 Basswood Dr SW",
    "sg:city":"Grandville",
    "sg:classifiers":[
        {
            "category":"Insurance",
            "subcategory":"Insurance Agent",
            "type":"Services"
        }
    ],
    "sg:phone":"+1 616 538 4246",
    "sg:postcode":"49418",
    "sg:province":"MI",
    "wof:name":"Westwind Benefits Inc",
    "wof:placetype":"venue"
},
  "geometry": {"coordinates":[-85.737866,42.897407],"type":"Point"}
}