{
  "type": "Feature",
  "properties": {
    "iso:country":"US",
    "sg:address":"1535 Boardman Rd",
    "sg:city":"Jackson",
    "sg:classifiers":[
        {
            "category":"Home & Garden",
            "subcategory":"Building Materials",
            "type":"Retail Goods"
        }
    ],
    "sg:phone":"+1 517 796 5500",
    "sg:postcode":"49202",
    "sg:province":"MI",
    "sg:tags":[
        "center"
    ],
    "sg:website":"www.lowes.com",
    "wof:name":"Lowe's",
    "wof:placetype":"venue"
},
  "geometry": {"coordinates":[-84.431201,42.270671],"type":"Point"}
}