{
  "type": "Feature",
  "properties": {
    "iso:country":"US",
    "sg:address":"217 W Maumee St",
    "sg:city":"Adrian",
    "sg:classifiers":[
        {
            "category":"Building & Trades",
            "subcategory":"Electrical",
            "type":"Services"
        }
    ],
    "sg:phone":"+1 517 263 4666",
    "sg:postcode":"49221",
    "sg:province":"MI",
    "wof:name":"A T & T Broadband",
    "wof:placetype":"venue"
},
  "geometry": {"coordinates":[-84.03901399999999,41.899694],"type":"Point"}
}