{
  "type": "Feature",
  "properties": {
    "iso:country":"US",
    "sg:address":"10635 N Meridian Rd",
    "sg:city":"Pleasant Lake",
    "sg:classifiers":[
        {
            "category":"Food & Beverages",
            "subcategory":"Groceries & Convenience Stores",
            "type":"Retail Goods"
        }
    ],
    "sg:phone":"+1 517 769 6197",
    "sg:postcode":"49272",
    "sg:province":"MI",
    "wof:name":"Pleasant Lake Marina & General",
    "wof:placetype":"venue"
},
  "geometry": {"coordinates":[-84.35050200000001,42.388612],"type":"Point"}
}