{
  "type": "Feature",
  "properties": {
    "iso:country":"US",
    "sg:address":"117 Banner Ct SW",
    "sg:city":"Grand Rapids",
    "sg:classifiers":[
        {
            "category":"Banks & Credit Unions",
            "subcategory":"Investment Brokerage",
            "type":"Services"
        }
    ],
    "sg:phone":"+1 616 452 1266",
    "sg:postcode":"49507",
    "sg:province":"MI",
    "sg:tags":[
        "advisory",
        "financial"
    ],
    "wof:name":"Capital Resources",
    "wof:placetype":"venue"
},
  "geometry": {"coordinates":[-85.669957,42.923137],"type":"Point"}
}