{
  "type": "Feature",
  "properties": {
    "iso:country":"US",
    "sg:address":"19801 Webster St",
    "sg:city":"Clinton Twp",
    "sg:classifiers":[
        {
            "category":"Building & Trades",
            "subcategory":"Construction",
            "type":"Services"
        }
    ],
    "sg:phone":"+1 586 746 1664",
    "sg:postcode":"48035",
    "sg:province":"MI",
    "sg:tags":[
        "concrete",
        "contractor"
    ],
    "wof:name":"Carlini Construction",
    "wof:placetype":"venue"
},
  "geometry": {"coordinates":[-82.917249,42.543473],"type":"Point"}
}