{
  "type": "Feature",
  "properties": {
    "iso:country":"US",
    "sg:address":"3214 W Jefferson Ave",
    "sg:city":"Trenton",
    "sg:classifiers":[
        {
            "category":"Sports & Exercise",
            "subcategory":"Gym",
            "type":"Entertainment"
        }
    ],
    "sg:phone":"+1 734 692 3482",
    "sg:postcode":"48183",
    "sg:province":"MI",
    "sg:tags":[
        "trainer"
    ],
    "wof:name":"3Dfit",
    "wof:placetype":"venue"
},
  "geometry": {"coordinates":[-83.181354,42.138739],"type":"Point"}
}