{
  "type": "Feature",
  "properties": {
    "iso:country":"US",
    "sg:address":"3050 E Beaver Rd",
    "sg:city":"Bay City",
    "sg:classifiers":[
        {
            "category":"Wholesale",
            "subcategory":"Office Equipment",
            "type":"Manufacturing & Wholesale Goods"
        }
    ],
    "sg:phone":"+1 989 684 0470",
    "sg:postcode":"48706",
    "sg:province":"MI",
    "sg:tags":[
        "machine",
        "duplicating",
        "copying"
    ],
    "wof:name":"Copiers & More",
    "wof:placetype":"venue"
},
  "geometry": {"coordinates":[-83.925802,43.667404],"type":"Point"}
}