{
  "type": "Feature",
  "properties": {
    "iso:country":"US",
    "sg:address":"50875 Gratiot Ave",
    "sg:city":"New Baltimore",
    "sg:classifiers":[
        {
            "category":"Restaurant",
            "type":"Food & Drink"
        }
    ],
    "sg:menulink":"http://www.allmenus.com/mi/chesterfield/43916-dimitris/menu/",
    "sg:phone":"+1 586 949 9600",
    "sg:postcode":"48051",
    "sg:province":"MI",
    "sg:tags":[
        "american"
    ],
    "wof:name":"Dimitri's",
    "wof:placetype":"venue"
},
  "geometry": {"coordinates":[-82.833843,42.673917],"type":"Point"}
}