{
  "type": "Feature",
  "properties": {
    "iso:country":"US",
    "sg:address":"34946 Island View Dr E",
    "sg:city":"Harrison Township",
    "sg:classifiers":[
        {
            "category":"Real Estate",
            "subcategory":"Real Estate Operator",
            "type":"Services"
        }
    ],
    "sg:phone":"+1 586 791 7911",
    "sg:postcode":"48045",
    "sg:province":"MI",
    "sg:tags":[
        "building",
        "industrial",
        "operates"
    ],
    "wof:name":"Fecteau Inv A Mich Ltd Partnr",
    "wof:placetype":"venue"
},
  "geometry": {"coordinates":[-82.851922,42.549159],"type":"Point"}
}