{
  "type": "Feature",
  "properties": {
    "iso:country":"US",
    "sg:address":"9150 Holton Rd",
    "sg:city":"Holton",
    "sg:classifiers":[
        {
            "category":"Organizations",
            "subcategory":"Community Association",
            "type":"Services"
        }
    ],
    "sg:phone":"+1 231 821 2248",
    "sg:postcode":"49425",
    "sg:province":"MI",
    "sg:tags":[
        "military"
    ],
    "wof:name":"American Legion",
    "wof:placetype":"venue"
},
  "geometry": {"coordinates":[-86.05946,43.424068],"type":"Point"}
}