{
  "type": "Feature",
  "properties": {
    "iso:country":"US",
    "sg:address":"2725 Fairfield Rd",
    "sg:city":"Portage",
    "sg:classifiers":[
        {
            "category":"Insurance",
            "subcategory":"Life Insurance",
            "type":"Services"
        }
    ],
    "sg:phone":"+1 269 381 6480",
    "sg:postcode":"49002",
    "sg:province":"MI",
    "sg:tags":[
        "carrier"
    ],
    "wof:name":"MetLife",
    "wof:placetype":"venue"
},
  "geometry": {"coordinates":[-85.55735799999999,42.241905],"type":"Point"}
}