{
  "type": "Feature",
  "properties": {
    "iso:country":"US",
    "sg:address":"150 W Maple Rd",
    "sg:city":"Birmingham",
    "sg:classifiers":[
        {
            "category":"Utilities",
            "subcategory":"Mobile Phone",
            "type":"Services"
        }
    ],
    "sg:phone":"+1 248 290 3000",
    "sg:postcode":"48009",
    "sg:province":"MI",
    "sg:tags":[
        "telephone",
        "cellular"
    ],
    "wof:name":"Star 1 Communications",
    "wof:placetype":"venue"
},
  "geometry": {"coordinates":[-83.215779,42.546741],"type":"Point"}
}