{
  "type": "Feature",
  "properties": {
    "iso:country":"US",
    "sg:address":"2213 Bauer Rd",
    "sg:city":"Jenison",
    "sg:classifiers":[
        {
            "category":"Social Services",
            "subcategory":"Child Care",
            "type":"Services"
        }
    ],
    "sg:phone":"+1 616 457 9289",
    "sg:postcode":"49428",
    "sg:province":"MI",
    "sg:tags":[
        "day"
    ],
    "wof:name":"Bunny Tail Christian Day Care",
    "wof:placetype":"venue"
},
  "geometry": {"coordinates":[-85.838257,42.921769],"type":"Point"}
}