{
  "type": "Feature",
  "properties": {
    "iso:country":"US",
    "sg:address":"528 28th St",
    "sg:city":"Gladstone",
    "sg:classifiers":[
        {
            "category":"Organizations",
            "subcategory":"Religious Organization",
            "type":"Services"
        }
    ],
    "sg:phone":"+1 906 428 1331",
    "sg:postcode":"49837",
    "sg:province":"MI",
    "wof:name":"Grace Baptist Church",
    "wof:placetype":"venue"
},
  "geometry": {"coordinates":[-87.04695100000001,45.853981],"type":"Point"}
}