{
  "type": "Feature",
  "properties": {
    "iso:country":"US",
    "sg:address":"9265 Kenowa Ave SW",
    "sg:city":"Grand Rapids",
    "sg:classifiers":[
        {
            "category":"Food & Beverages",
            "subcategory":"Fruits & Vegetables",
            "type":"Retail Goods"
        }
    ],
    "sg:phone":"+1 616 453 2585",
    "sg:postcode":"49534",
    "sg:province":"MI",
    "sg:tags":[
        "farm",
        "market"
    ],
    "wof:name":"Moelker Orchards",
    "wof:placetype":"venue"
},
  "geometry": {"coordinates":[-85.783683,42.937871],"type":"Point"}
}