{
  "type": "Feature",
  "properties": {
    "iso:country":"US",
    "sg:address":"7505 Apple Creek Dr",
    "sg:city":"Swartz Creek",
    "sg:classifiers":[
        {
            "category":"Building & Trades",
            "subcategory":"Construction",
            "type":"Services"
        }
    ],
    "sg:phone":"+1 810 635 3729",
    "sg:postcode":"48473",
    "sg:province":"MI",
    "sg:tags":[
        "carpentry",
        "contractor"
    ],
    "wof:name":"Jims Custom Trim",
    "wof:placetype":"venue"
},
  "geometry": {"coordinates":[-83.828632,42.961361],"type":"Point"}
}