{
  "type": "Feature",
  "properties": {
    "iso:country":"US",
    "sg:address":"15555 S Telegraph Rd",
    "sg:city":"Monroe",
    "sg:classifiers":[
        {
            "category":"Social Services",
            "subcategory":"Job Training",
            "type":"Services"
        }
    ],
    "sg:phone":"+1 734 457 3447",
    "sg:postcode":"48161",
    "sg:province":"MI",
    "sg:tags":[
        "employment"
    ],
    "wof:name":"Goodwill Industries",
    "wof:placetype":"venue"
},
  "geometry": {"coordinates":[-83.426231,41.903954],"type":"Point"}
}