{
  "type": "Feature",
  "properties": {
    "iso:country":"US",
    "sg:address":"8111 Clyde Park Ave SW",
    "sg:city":"Byron Center",
    "sg:classifiers":[
        {
            "category":"Freight",
            "type":"Transportation"
        }
    ],
    "sg:phone":"+1 616 878 5500",
    "sg:postcode":"49315",
    "sg:province":"MI",
    "sg:tags":[
        "commercial",
        "storage"
    ],
    "wof:name":"Clyde Park Storage",
    "wof:placetype":"venue"
},
  "geometry": {"coordinates":[-85.68347300000001,42.813866],"type":"Point"}
}