{
  "type": "Feature",
  "properties": {
    "iso:country":"US",
    "sg:address":"1103 Old Tannery Creek",
    "sg:city":"Petoskey",
    "sg:classifiers":[
        {
            "category":"Insurance",
            "subcategory":"Insurance Agent",
            "type":"Services"
        }
    ],
    "sg:phone":"+1 231 347 3837",
    "sg:postcode":"49770",
    "sg:province":"MI",
    "wof:name":"Northwestern Mutual Financial",
    "wof:placetype":"venue"
},
  "geometry": {"coordinates":[-84.919837,45.390361],"type":"Point"}
}