{
  "type": "Feature",
  "properties": {
    "iso:country":"US",
    "sg:address":"1010 N Washington Ave",
    "sg:city":"Lansing",
    "sg:classifiers":[
        {
            "category":"Professional",
            "subcategory":"Lawyer & Legal Services",
            "type":"Services"
        }
    ],
    "sg:phone":"+1 517 374 0310",
    "sg:postcode":"48906",
    "sg:province":"MI",
    "sg:tags":[
        "criminal",
        "attorney",
        "injury",
        "estate",
        "personal",
        "divorce",
        "wills",
        "planning",
        "trust",
        "probate",
        "law"
    ],
    "wof:name":"Gerald J Cichocki PC",
    "wof:placetype":"venue"
},
  "geometry": {"coordinates":[-84.55213500000001,42.744916],"type":"Point"}
}