{
  "type": "Feature",
  "properties": {
    "iso:country":"US",
    "sg:address":"1685 68th St SE",
    "sg:city":"Caledonia",
    "sg:classifiers":[
        {
            "category":"Government",
            "subcategory":"Office",
            "type":"Public Place"
        }
    ],
    "sg:phone":"+1 616 698 6640",
    "sg:postcode":"49316",
    "sg:province":"MI",
    "sg:tags":[
        "village"
    ],
    "wof:name":"Gaines Twp Supervisor's Office",
    "wof:placetype":"venue"
},
  "geometry": {"coordinates":[-85.622338,42.841089],"type":"Point"}
}