{
  "type": "Feature",
  "properties": {
    "iso:country":"US",
    "sg:address":"1733 W John Beers Rd",
    "sg:city":"Stevensville",
    "sg:classifiers":[
        {
            "category":"Food & Beverages",
            "subcategory":"Liquor & Beverages",
            "type":"Retail Goods"
        }
    ],
    "sg:phone":"+1 269 428 4856",
    "sg:postcode":"49127",
    "sg:province":"MI",
    "wof:name":"Nick In Time Food & Beverage",
    "wof:placetype":"venue"
},
  "geometry": {"coordinates":[-86.496156,42.014464],"type":"Point"}
}