{
  "type": "Feature",
  "properties": {
    "iso:country":"US",
    "sg:address":"227 W 17th St",
    "sg:city":"Holland",
    "sg:classifiers":[
        {
            "category":"Professional",
            "subcategory":"Lawyer & Legal Services",
            "type":"Services"
        }
    ],
    "sg:phone":"+1 616 395 3777",
    "sg:postcode":"49423",
    "sg:province":"MI",
    "sg:tags":[
        "attorney"
    ],
    "wof:name":"Lakeshore Legal Office",
    "wof:placetype":"venue"
},
  "geometry": {"coordinates":[-86.117407,42.782129],"type":"Point"}
}