{
  "type": "Feature",
  "properties": {
    "iso:country":"US",
    "sg:address":"1930 W Milham Rd",
    "sg:city":"Portage",
    "sg:classifiers":[
        {
            "category":"Health Services",
            "subcategory":"Chiropractor",
            "type":"Services"
        }
    ],
    "sg:phone":"+1 269 345 2273",
    "sg:postcode":"49024",
    "sg:province":"MI",
    "wof:name":"Portage Family Chiropractic",
    "wof:placetype":"venue"
},
  "geometry": {"coordinates":[-85.613041,42.230187],"type":"Point"}
}