{
  "type": "Feature",
  "properties": {
    "iso:country":"US",
    "sg:address":"1709 Missouri Ave",
    "sg:city":"Flint",
    "sg:classifiers":[
        {
            "category":"Building & Trades",
            "subcategory":"Construction",
            "type":"Services"
        }
    ],
    "sg:phone":"+1 810 238 9695",
    "sg:postcode":"48506",
    "sg:province":"MI",
    "sg:tags":[
        "carpenter"
    ],
    "wof:name":"Gary Carpenrty",
    "wof:placetype":"venue"
},
  "geometry": {"coordinates":[-83.665981,43.028728],"type":"Point"}
}