{
  "type": "Feature",
  "properties": {
    "iso:country":"US",
    "sg:address":"1720 W Michigan Ave",
    "sg:city":"Kalamazoo",
    "sg:classifiers":[
        {
            "category":"Organizations",
            "subcategory":"Religious Organization",
            "type":"Services"
        }
    ],
    "sg:phone":"+1 269 349 1100",
    "sg:postcode":"49006",
    "sg:province":"MI",
    "sg:tags":[
        "church"
    ],
    "wof:name":"Solid Grounds Student Mnstry",
    "wof:placetype":"venue"
},
  "geometry": {"coordinates":[-85.608712,42.28538],"type":"Point"}
}