{
  "type": "Feature",
  "properties": {
    "iso:country":"US",
    "sg:address":"2777 Knapp St NE",
    "sg:city":"Grand Rapids",
    "sg:classifiers":[
        {
            "category":"Organizations",
            "subcategory":"Religious Organization",
            "type":"Services"
        }
    ],
    "sg:phone":"+1 616 364 7043",
    "sg:postcode":"49525",
    "sg:province":"MI",
    "wof:name":"New Life Christian Fellowship",
    "wof:placetype":"venue"
},
  "geometry": {"coordinates":[-85.60462099999999,42.998816],"type":"Point"}
}