{
  "type": "Feature",
  "properties": {
    "iso:country":"US",
    "sg:address":"32375 Howard Ave",
    "sg:city":"Madison Heights",
    "sg:classifiers":[
        {
            "category":"Retail",
            "subcategory":"Laundry & Dry Cleaning",
            "type":"Services"
        }
    ],
    "sg:phone":"+1 586 415 4545",
    "sg:postcode":"48071",
    "sg:province":"MI",
    "sg:tags":[
        "cleaners",
        "rug",
        "carpet"
    ],
    "wof:name":"Ron's Carpet Cleaning",
    "wof:placetype":"venue"
},
  "geometry": {"coordinates":[-83.09954,42.531102],"type":"Point"}
}