{
  "type": "Feature",
  "properties": {
    "iso:country":"US",
    "sg:address":"16246 Prest St",
    "sg:city":"Detroit",
    "sg:classifiers":[
        {
            "category":"Personal",
            "type":"Services"
        }
    ],
    "sg:phone":"+1 313 838 7847",
    "sg:postcode":"48235",
    "sg:province":"MI",
    "sg:tags":[
        "party",
        "planning",
        "event"
    ],
    "wof:name":"Floating Jewels",
    "wof:placetype":"venue"
},
  "geometry": {"coordinates":[-83.197701,42.410301],"type":"Point"}
}