{
  "type": "Feature",
  "properties": {
    "iso:country":"US",
    "sg:address":"2286 Academy Dr NE",
    "sg:city":"Grand Rapids",
    "sg:classifiers":[
        {
            "category":"Recreation",
            "type":"Entertainment"
        }
    ],
    "sg:phone":"+1 616 458 7102",
    "sg:postcode":"49503",
    "sg:province":"MI",
    "wof:name":"Grand Rapids Judo Club",
    "wof:placetype":"venue"
},
  "geometry": {"coordinates":[-85.614043,42.965749],"type":"Point"}
}