{
  "type": "Feature",
  "properties": {
    "iso:country":"US",
    "sg:address":"245 S Co Rd 557",
    "sg:city":"Gwinn",
    "sg:classifiers":[
        {
            "category":"Food & Beverages",
            "subcategory":"Groceries & Convenience Stores",
            "type":"Retail Goods"
        }
    ],
    "sg:phone":"+1 906 346 3462",
    "sg:postcode":"49841",
    "sg:province":"MI",
    "sg:tags":[
        "grocer"
    ],
    "wof:name":"Tall Timber Grocery",
    "wof:placetype":"venue"
},
  "geometry": {"coordinates":[-87.483698,46.266226],"type":"Point"}
}