{
  "type": "Feature",
  "properties": {
    "iso:country":"US",
    "sg:address":"9500 W Sterling Rd",
    "sg:city":"Litchfield",
    "sg:classifiers":[
        {
            "category":"Professional",
            "subcategory":"Testing Lab",
            "type":"Services"
        }
    ],
    "sg:phone":"+1 517 542 3020",
    "sg:postcode":"49252",
    "sg:province":"MI",
    "sg:tags":[
        "laboratory"
    ],
    "wof:name":"Met Labs",
    "wof:placetype":"venue"
},
  "geometry": {"coordinates":[-84.79159199999999,42.014773],"type":"Point"}
}