{
  "type": "Feature",
  "properties": {
    "iso:country":"US",
    "sg:address":"27405 Berkshire Dr",
    "sg:city":"Southfield",
    "sg:classifiers":[
        {
            "category":"Professional",
            "subcategory":"Detective & Security Services",
            "type":"Services"
        }
    ],
    "sg:phone":"+1 248 355 4929",
    "sg:postcode":"48076",
    "sg:province":"MI",
    "sg:tags":[
        "car"
    ],
    "wof:name":"Spoc Investigations",
    "wof:placetype":"venue"
},
  "geometry": {"coordinates":[-83.246003,42.490274],"type":"Point"}
}