{
  "type": "Feature",
  "properties": {
    "iso:country":"US",
    "sg:address":"11798 Willow Ave",
    "sg:city":"Grant",
    "sg:classifiers":[
        {
            "category":"Airport",
            "type":"Transportation"
        }
    ],
    "sg:phone":"+1 231 834 8000",
    "sg:postcode":"49327",
    "sg:province":"MI",
    "wof:name":"Grant Airport",
    "wof:placetype":"venue"
},
  "geometry": {"coordinates":[-85.78071,43.340457],"type":"Point"}
}