{
  "type": "Feature",
  "properties": {
    "iso:country":"US",
    "sg:address":"1401 Vermont St",
    "sg:city":"Detroit",
    "sg:classifiers":[
        {
            "category":"Professional",
            "subcategory":"Printing & Photocopies",
            "type":"Services"
        }
    ],
    "sg:phone":"+1 313 962 2900",
    "sg:postcode":"48216",
    "sg:province":"MI",
    "sg:tags":[
        "provides"
    ],
    "wof:name":"Hernandez Blue Print Services",
    "wof:placetype":"venue"
},
  "geometry": {"coordinates":[-83.07138399999999,42.327459],"type":"Point"}
}