{
  "type": "Feature",
  "properties": {
    "iso:country":"US",
    "sg:address":"207 W Wesley St",
    "sg:city":"Jackson",
    "sg:classifiers":[
        {
            "category":"Professional",
            "subcategory":"Lawyer & Legal Services",
            "type":"Services"
        }
    ],
    "sg:phone":"+1 517 788 7868",
    "sg:postcode":"49201",
    "sg:province":"MI",
    "sg:tags":[
        "attorney"
    ],
    "wof:name":"Richard D Zaharie Atty",
    "wof:placetype":"venue"
},
  "geometry": {"coordinates":[-84.41163400000001,42.244604],"type":"Point"}
}