{
  "type": "Feature",
  "properties": {
    "iso:country":"US",
    "sg:address":"136 S Chicago St",
    "sg:city":"Litchfield",
    "sg:classifiers":[
        {
            "category":"Retail",
            "subcategory":"Auto Repair",
            "type":"Services"
        }
    ],
    "sg:phone":"+1 517 542 3570",
    "sg:postcode":"49252",
    "sg:province":"MI",
    "sg:tags":[
        "automotive"
    ],
    "wof:name":"Clean Wheels",
    "wof:placetype":"venue"
},
  "geometry": {"coordinates":[-84.75837799999999,42.039679],"type":"Point"}
}