{
  "type": "Feature",
  "properties": {
    "iso:country":"US",
    "sg:address":"1509 N US Hwy 31",
    "sg:city":"Niles",
    "sg:classifiers":[
        {
            "category":"Manufacturing",
            "subcategory":"Metals",
            "type":"Manufacturing & Wholesale Goods"
        }
    ],
    "sg:phone":"+1 269 683 1870",
    "sg:postcode":"49120",
    "sg:province":"MI",
    "sg:tags":[
        "shop",
        "plate",
        "work",
        "fabricated"
    ],
    "wof:name":"Stilwell Co",
    "wof:placetype":"venue"
},
  "geometry": {"coordinates":[-86.27986199999999,41.869575],"type":"Point"}
}