{
  "type": "Feature",
  "properties": {
    "iso:country":"US",
    "sg:address":"6461 Pleasant River Dr",
    "sg:city":"Dimondale",
    "sg:classifiers":[
        {
            "category":"Shopping",
            "subcategory":"Computers & Home Electronics",
            "type":"Retail Goods"
        }
    ],
    "sg:phone":"+1 517 646 7995",
    "sg:postcode":"48821",
    "sg:province":"MI",
    "sg:tags":[
        "software"
    ],
    "wof:name":"Med Sports Systems",
    "wof:placetype":"venue"
},
  "geometry": {"coordinates":[-84.599476,42.621456],"type":"Point"}
}