{
  "type": "Feature",
  "properties": {
    "iso:country":"US",
    "sg:address":"123 W Washington St",
    "sg:city":"Marquette",
    "sg:classifiers":[
        {
            "category":"Shopping",
            "subcategory":"Hobbies, Toys, & Games",
            "type":"Retail Goods"
        }
    ],
    "sg:phone":"+1 906 228 9143",
    "sg:postcode":"49855",
    "sg:province":"MI",
    "sg:tags":[
        "craft",
        "supply"
    ],
    "wof:name":"Superior Scrapbooking Shop",
    "wof:placetype":"venue"
},
  "geometry": {"coordinates":[-87.39497900000001,46.543426],"type":"Point"}
}