{
  "type": "Feature",
  "properties": {
    "iso:country":"US",
    "sg:address":"2755 Dorr Rd",
    "sg:city":"Howell",
    "sg:classifiers":[
        {
            "category":"Government",
            "subcategory":"Fire Station",
            "type":"Public Place"
        }
    ],
    "sg:phone":"+1 810 225 6204",
    "sg:postcode":"48843",
    "sg:province":"MI",
    "sg:tags":[
        "department"
    ],
    "wof:name":"Brighton Area Fire Dept",
    "wof:placetype":"venue"
},
  "geometry": {"coordinates":[-83.83377900000001,42.560834],"type":"Point"}
}