{
  "type": "Feature",
  "properties": {
    "iso:country":"US",
    "sg:address":"7547 Radcliffe Ave",
    "sg:city":"Brighton",
    "sg:classifiers":[
        {
            "category":"Manufacturing",
            "subcategory":"Wood Products",
            "type":"Manufacturing & Wholesale Goods"
        }
    ],
    "sg:phone":"+1 810 220 1336",
    "sg:postcode":"48114",
    "sg:province":"MI",
    "sg:tags":[
        "mfg"
    ],
    "wof:name":"Good Wood Products",
    "wof:placetype":"venue"
},
  "geometry": {"coordinates":[-83.80370499999999,42.559755],"type":"Point"}
}