{
  "type": "Feature",
  "properties": {
    "iso:country":"US",
    "sg:address":"27209 Lahser Rd",
    "sg:city":"Southfield",
    "sg:classifiers":[
        {
            "category":"Health Services",
            "subcategory":"Doctor",
            "type":"Services"
        }
    ],
    "sg:phone":"+1 248 353 0200",
    "sg:postcode":"48034",
    "sg:province":"MI",
    "sg:tags":[
        "physician",
        "surgeon"
    ],
    "wof:name":"Northwest Surgical Assoc",
    "wof:placetype":"venue"
},
  "geometry": {"coordinates":[-83.261499,42.488296],"type":"Point"}
}