{
  "type": "Feature",
  "properties": {
    "iso:country":"US",
    "sg:address":"25 Truman Rd",
    "sg:city":"Barryton",
    "sg:classifiers":[
        {
            "category":"Shopping",
            "type":"Retail Goods"
        }
    ],
    "sg:phone":"+1 989 560 2789",
    "sg:postcode":"49305",
    "sg:province":"MI",
    "sg:tags":[
        "product",
        "wood"
    ],
    "wof:name":"Merrill Wood Products Inc",
    "wof:placetype":"venue"
},
  "geometry": {"coordinates":[-85.089038,43.791666],"type":"Point"}
}