{
  "type": "Feature",
  "properties": {
    "iso:country":"US",
    "sg:address":"2651 E Lansing Dr",
    "sg:city":"East Lansing",
    "sg:classifiers":[
        {
            "category":"Professional",
            "subcategory":"Management & Consulting",
            "type":"Services"
        }
    ],
    "sg:phone":"+1 517 324 9901",
    "sg:postcode":"48823",
    "sg:province":"MI",
    "sg:tags":[
        "consultant",
        "business"
    ],
    "wof:name":"Maximus Inc",
    "wof:placetype":"venue"
},
  "geometry": {"coordinates":[-84.45039,42.749673],"type":"Point"}
}