{
  "type": "Feature",
  "properties": {
    "iso:country":"US",
    "sg:address":"8991 W Grand Ledge Hwy",
    "sg:city":"Sunfield",
    "sg:classifiers":[
        {
            "category":"Wholesale",
            "subcategory":"Auto Parts",
            "type":"Manufacturing & Wholesale Goods"
        }
    ],
    "sg:phone":"+1 517 566 8162",
    "sg:postcode":"48890",
    "sg:province":"MI",
    "sg:tags":[
        "truck",
        "accessory"
    ],
    "wof:name":"Sunfield L & L Armacoating",
    "wof:placetype":"venue"
},
  "geometry": {"coordinates":[-85.009139,42.755893],"type":"Point"}
}