{
  "type": "Feature",
  "properties": {
    "iso:country":"US",
    "sg:address":"33702 Lyncroft St",
    "sg:city":"Farmington",
    "sg:classifiers":[
        {
            "category":"Recreation",
            "type":"Entertainment"
        }
    ],
    "sg:phone":"+1 248 471 4154",
    "sg:postcode":"48331",
    "sg:province":"MI",
    "wof:name":"Tee It Up North",
    "wof:placetype":"venue"
},
  "geometry": {"coordinates":[-83.382931,42.487127],"type":"Point"}
}