{
  "type": "Feature",
  "properties": {
    "iso:country":"US",
    "sg:address":"8468 Woodland Shore",
    "sg:city":"Brighton",
    "sg:classifiers":[
        {
            "category":"Building & Trades",
            "subcategory":"Landscaping Services",
            "type":"Services"
        }
    ],
    "sg:phone":"+1 810 225 7336",
    "sg:postcode":"48114",
    "sg:province":"MI",
    "sg:tags":[
        "landscape",
        "contractor"
    ],
    "wof:name":"Precision Lawn & Landscape",
    "wof:placetype":"venue"
},
  "geometry": {"coordinates":[-83.78291299999999,42.557657],"type":"Point"}
}