{
  "type": "Feature",
  "properties": {
    "iso:country":"US",
    "sg:address":"6650 Highland Rd",
    "sg:city":"Waterford",
    "sg:classifiers":[
        {
            "category":"Building & Trades",
            "subcategory":"Cleaning & Sanitation",
            "type":"Services"
        }
    ],
    "sg:phone":"+1 248 666 2801",
    "sg:postcode":"48327",
    "sg:province":"MI",
    "sg:tags":[
        "commercial",
        "janitor",
        "janitorial"
    ],
    "wof:name":"Thundermop Maintenance Company",
    "wof:placetype":"venue"
},
  "geometry": {"coordinates":[-83.420244,42.659553],"type":"Point"}
}