{
  "type": "Feature",
  "properties": {
    "iso:country":"US",
    "sg:address":"207 Jordan",
    "sg:city":"East Jordan",
    "sg:classifiers":[
        {
            "category":"Social Services",
            "subcategory":"Child Care",
            "type":"Services"
        }
    ],
    "sg:phone":"+1 231 536 2392",
    "sg:postcode":"49727",
    "sg:province":"MI",
    "sg:tags":[
        "kindergarten",
        "academic",
        "school"
    ],
    "wof:name":"East Jordan Co-Op Nursery",
    "wof:placetype":"venue"
},
  "geometry": {"coordinates":[-85.134576,45.152077],"type":"Point"}
}