{
  "type": "Feature",
  "properties": {
    "iso:country":"US",
    "sg:address":"3270 E Bevens Rd",
    "sg:city":"Caro",
    "sg:classifiers":[
        {
            "category":"Farming",
            "subcategory":"Farm",
            "type":"Manufacturing & Wholesale Goods"
        }
    ],
    "sg:phone":"+1 989 673 4719",
    "sg:postcode":"48723",
    "sg:province":"MI",
    "sg:tags":[
        "crop",
        "general"
    ],
    "wof:name":"Stewart Farms",
    "wof:placetype":"venue"
},
  "geometry": {"coordinates":[-83.305398,43.454026],"type":"Point"}
}