{
  "type": "Feature",
  "properties": {
    "iso:country":"US",
    "sg:address":"17877 Callen Ave",
    "sg:city":"Kent City",
    "sg:classifiers":[
        {
            "category":"Real Estate",
            "subcategory":"Real Estate Operator",
            "type":"Services"
        }
    ],
    "sg:phone":"+1 616 675 5247",
    "sg:postcode":"49330",
    "sg:province":"MI",
    "sg:tags":[
        "property",
        "lessor"
    ],
    "wof:name":"Roy Mc Vicker",
    "wof:placetype":"venue"
},
  "geometry": {"coordinates":[-85.761948,43.290193],"type":"Point"}
}