{
  "type": "Feature",
  "properties": {
    "iso:country":"US",
    "sg:address":"11180 E D Ave",
    "sg:city":"Richland",
    "sg:classifiers":[
        {
            "category":"Building & Trades",
            "subcategory":"Construction",
            "type":"Services"
        }
    ],
    "sg:phone":"+1 269 629 5247",
    "sg:postcode":"49083",
    "sg:province":"MI",
    "sg:tags":[
        "home",
        "builder"
    ],
    "wof:name":"Higdon Builders Inc",
    "wof:placetype":"venue"
},
  "geometry": {"coordinates":[-85.411708,42.37641],"type":"Point"}
}