{
  "type": "Feature",
  "properties": {
    "iso:country":"US",
    "sg:address":"880 Mid Bluff Dr",
    "sg:city":"Zeeland",
    "sg:classifiers":[
        {
            "category":"Building & Trades",
            "subcategory":"Construction",
            "type":"Services"
        }
    ],
    "sg:phone":"+1 616 772 6772",
    "sg:postcode":"49464",
    "sg:province":"MI",
    "sg:tags":[
        "home",
        "builder"
    ],
    "wof:name":"Countryside Builders",
    "wof:placetype":"venue"
},
  "geometry": {"coordinates":[-86.01130499999999,42.785506],"type":"Point"}
}