{
  "type": "Feature",
  "properties": {
    "iso:country":"US",
    "sg:address":"413 N Willowbrook Rd",
    "sg:city":"Coldwater",
    "sg:classifiers":[
        {
            "category":"Insurance",
            "subcategory":"Insurance Agent",
            "type":"Services"
        }
    ],
    "sg:phone":"+1 517 278 5409",
    "sg:postcode":"49036",
    "sg:province":"MI",
    "wof:name":"Harmon Insurance",
    "wof:placetype":"venue"
},
  "geometry": {"coordinates":[-84.971236,41.95044],"type":"Point"}
}