{
  "type": "Feature",
  "properties": {
    "iso:country":"US",
    "sg:address":"10248 Ashton Ct",
    "sg:city":"Middleville",
    "sg:classifiers":[
        {
            "category":"Building & Trades",
            "subcategory":"Construction",
            "type":"Services"
        }
    ],
    "sg:phone":"+1 269 795 4468",
    "sg:postcode":"49333",
    "sg:province":"MI",
    "sg:tags":[
        "home",
        "improvement"
    ],
    "wof:name":"Thornapple Home Improvement",
    "wof:placetype":"venue"
},
  "geometry": {"coordinates":[-85.49176199999999,42.730624],"type":"Point"}
}