{
  "type": "Feature",
  "properties": {
    "iso:country":"US",
    "sg:address":"29260 Pointe O Woods Pl",
    "sg:city":"Southfield",
    "sg:classifiers":[
        {
            "category":"Building & Trades",
            "subcategory":"Landscaping Services",
            "type":"Services"
        }
    ],
    "sg:phone":"+1 248 350 9546",
    "sg:postcode":"48034",
    "sg:province":"MI",
    "sg:tags":[
        "landscape"
    ],
    "wof:name":"Jeg Landscaping",
    "wof:placetype":"venue"
},
  "geometry": {"coordinates":[-83.28910500000001,42.503785],"type":"Point"}
}