{
  "type": "Feature",
  "properties": {
    "iso:country":"US",
    "sg:address":"9877 Sayers Rd",
    "sg:city":"Munith",
    "sg:classifiers":[
        {
            "category":"Building & Trades",
            "subcategory":"Construction",
            "type":"Services"
        }
    ],
    "sg:phone":"+1 517 596 3417",
    "sg:postcode":"49259",
    "sg:province":"MI",
    "sg:tags":[
        "house"
    ],
    "sg:website":"www.gipfertsconstruction.com",
    "wof:name":"Gipfert Construction",
    "wof:placetype":"venue"
},
  "geometry": {"coordinates":[-84.27991299999999,42.377195],"type":"Point"}
}