{
  "type": "Feature",
  "properties": {
    "iso:country":"US",
    "sg:address":"895 US Hwy 41",
    "sg:city":"Trenary",
    "sg:classifiers":[
        {
            "category":"Home & Garden",
            "subcategory":"Building Materials",
            "type":"Retail Goods"
        }
    ],
    "sg:phone":"+1 906 446 3229",
    "sg:postcode":"49891",
    "sg:province":"MI",
    "sg:tags":[
        "lumber"
    ],
    "wof:name":"Heinonen Sawmill",
    "wof:placetype":"venue"
},
  "geometry": {"coordinates":[-86.982978,46.195009],"type":"Point"}
}