{
  "type": "Feature",
  "properties": {
    "iso:country":"US",
    "sg:address":"95 W Main St",
    "sg:city":"Benton Harbor",
    "sg:classifiers":[
        {
            "category":"Professional",
            "type":"Services"
        }
    ],
    "sg:phone":"+1 269 428 0697",
    "sg:postcode":"49022",
    "sg:province":"MI",
    "wof:name":"Aws Environmental",
    "wof:placetype":"venue"
},
  "geometry": {"coordinates":[-86.456006,42.116],"type":"Point"}
}