{
  "type": "Feature",
  "properties": {
    "iso:country":"US",
    "sg:address":"952 E Ayer St",
    "sg:city":"Ironwood",
    "sg:classifiers":[
        {
            "category":"Professional",
            "subcategory":"Management & Consulting",
            "type":"Services"
        }
    ],
    "sg:phone":"+1 906 932 1316",
    "sg:postcode":"49938",
    "sg:province":"MI",
    "wof:name":"Humidirect Inc",
    "wof:placetype":"venue"
},
  "geometry": {"coordinates":[-90.125756,46.463014],"type":"Point"}
}