{
  "type": "Feature",
  "properties": {
    "iso:country":"US",
    "sg:address":"322 Lakewood Dr SE",
    "sg:city":"Grand Rapids",
    "sg:classifiers":[
        {
            "category":"Professional",
            "subcategory":"Research",
            "type":"Services"
        }
    ],
    "sg:phone":"+1 616 949 7024",
    "sg:postcode":"49506",
    "sg:province":"MI",
    "sg:tags":[
        "nonphysical",
        "commercial"
    ],
    "wof:name":"Isenberg Research",
    "wof:placetype":"venue"
},
  "geometry": {"coordinates":[-85.599267,42.958147],"type":"Point"}
}