{
  "type": "Feature",
  "properties": {
    "iso:country":"US",
    "sg:address":"3750 28th St SW",
    "sg:city":"Grandville",
    "sg:classifiers":[
        {
            "category":"Retail",
            "subcategory":"Auto Rental",
            "type":"Services"
        }
    ],
    "sg:phone":"+1 616 530 9944",
    "sg:postcode":"49418",
    "sg:province":"MI",
    "sg:tags":[
        "renting",
        "automobile"
    ],
    "sg:website":"www.enterprise.com",
    "wof:name":"Enterprise Rent-A-Car",
    "wof:placetype":"venue"
},
  "geometry": {"coordinates":[-85.76007,42.913604],"type":"Point"}
}