{
  "type": "Feature",
  "properties": {
    "iso:country":"US",
    "sg:address":"930 E Cloverland Dr",
    "sg:city":"Ironwood",
    "sg:classifiers":[
        {
            "category":"Professional",
            "subcategory":"Computer Services",
            "type":"Services"
        }
    ],
    "sg:phone":"+1 906 932 0880",
    "sg:postcode":"49938",
    "sg:province":"MI",
    "sg:tags":[
        "repair"
    ],
    "wof:name":"Computer Doctors",
    "wof:placetype":"venue"
},
  "geometry": {"coordinates":[-90.15432199999999,46.463369],"type":"Point"}
}