{
  "type": "Feature",
  "properties": {
    "iso:country":"US",
    "sg:address":"2247 S Center Rd",
    "sg:city":"Burton",
    "sg:classifiers":[
        {
            "category":"Travel",
            "subcategory":"Hotels & Motels",
            "type":"Entertainment"
        }
    ],
    "sg:phone":"+1 810 789 0061",
    "sg:postcode":"48519",
    "sg:province":"MI",
    "sg:tags":[
        "operation"
    ],
    "wof:name":"Wallis Motor Lodge Inc",
    "wof:placetype":"venue"
},
  "geometry": {"coordinates":[-83.633945,42.99714],"type":"Point"}
}