{
  "type": "Feature",
  "properties": {
    "iso:country":"US",
    "sg:address":"15920 Loveland St",
    "sg:city":"Livonia",
    "sg:classifiers":[
        {
            "category":"Organizations",
            "subcategory":"Religious Organization",
            "type":"Services"
        }
    ],
    "sg:phone":"+1 734 427 6242",
    "sg:postcode":"48154",
    "sg:province":"MI",
    "wof:name":"Als Conception Communicat",
    "wof:placetype":"venue"
},
  "geometry": {"coordinates":[-83.36884499999999,42.401488],"type":"Point"}
}