{
  "type": "Feature",
  "properties": {
    "iso:country":"US",
    "sg:address":"193 N Paw Paw St",
    "sg:city":"Coloma",
    "sg:classifiers":[
        {
            "category":"Travel",
            "subcategory":"Travel Agent",
            "type":"Entertainment"
        }
    ],
    "sg:phone":"+1 269 468 3161",
    "sg:postcode":"49038",
    "sg:province":"MI",
    "sg:tags":[
        "agency",
        "bureau"
    ],
    "wof:name":"Destinations Unlimited Inc",
    "wof:placetype":"venue"
},
  "geometry": {"coordinates":[-86.30615299999999,42.186873],"type":"Point"}
}