{
  "type": "Feature",
  "properties": {
    "iso:country":"US",
    "sg:address":"3016 S Westnedge Ave",
    "sg:city":"Kalamazoo",
    "sg:classifiers":[
        {
            "category":"Professional",
            "type":"Services"
        }
    ],
    "sg:phone":"+1 269 342 0385",
    "sg:postcode":"49008",
    "sg:province":"MI",
    "sg:tags":[
        "establishment"
    ],
    "wof:name":"First American Bankcard Inc",
    "wof:placetype":"venue"
},
  "geometry": {"coordinates":[-85.58968900000001,42.26076],"type":"Point"}
}