{
  "type": "Feature",
  "properties": {
    "iso:country":"US",
    "sg:address":"24213 Red Arrow Hwy",
    "sg:city":"Mattawan",
    "sg:classifiers":[
        {
            "category":"Home & Garden",
            "subcategory":"Building Materials",
            "type":"Retail Goods"
        }
    ],
    "sg:phone":"+1 269 668 7788",
    "sg:postcode":"49071",
    "sg:province":"MI",
    "wof:name":"Consolidated Construction",
    "wof:placetype":"venue"
},
  "geometry": {"coordinates":[-85.787571,42.236683],"type":"Point"}
}