{
  "type": "Feature",
  "properties": {
    "iso:country":"US",
    "sg:address":"5312 Dixie Hwy",
    "sg:city":"Waterford",
    "sg:classifiers":[
        {
            "category":"Wholesale",
            "subcategory":"Machinery & Supplies",
            "type":"Manufacturing & Wholesale Goods"
        }
    ],
    "sg:phone":"+1 248 623 0910",
    "sg:postcode":"48329",
    "sg:province":"MI",
    "sg:tags":[
        "salon",
        "beauty"
    ],
    "wof:name":"Nailco",
    "wof:placetype":"venue"
},
  "geometry": {"coordinates":[-83.396129,42.697517],"type":"Point"}
}