{
  "type": "Feature",
  "properties": {
    "iso:country":"US",
    "sg:address":"1781 S Garfield Ave",
    "sg:city":"Traverse City",
    "sg:classifiers":[
        {
            "category":"Professional",
            "subcategory":"Business Services",
            "type":"Services"
        }
    ],
    "sg:phone":"+1 231 946 0662",
    "sg:postcode":"49686",
    "sg:province":"MI",
    "sg:tags":[
        "interior",
        "consultant",
        "design",
        "decorator"
    ],
    "wof:name":"Nancy Gribi Interior Design",
    "wof:placetype":"venue"
},
  "geometry": {"coordinates":[-85.59527799999999,44.743312],"type":"Point"}
}