{
  "type": "Feature",
  "properties": {
    "iso:country":"US",
    "sg:address":"1666 Hilltop Rd",
    "sg:city":"St Joseph",
    "sg:classifiers":[
        {
            "category":"Restaurant",
            "type":"Food & Drink"
        }
    ],
    "sg:phone":"+1 269 983 1645",
    "sg:postcode":"49085",
    "sg:province":"MI",
    "wof:name":"KFC",
    "wof:placetype":"venue"
},
  "geometry": {"coordinates":[-86.49421599999999,42.079969],"type":"Point"}
}