{
  "type": "Feature",
  "properties": {
    "iso:country":"US",
    "sg:address":"5760 Drake Rd",
    "sg:city":"West Bloomfield",
    "sg:classifiers":[
        {
            "category":"Professional",
            "subcategory":"Advertising",
            "type":"Services"
        }
    ],
    "sg:phone":"+1 248 932 7100",
    "sg:postcode":"48322",
    "sg:province":"MI",
    "sg:tags":[
        "mailing",
        "list"
    ],
    "sg:website":"www.burnett.com",
    "wof:name":"Burnett Direct Inc",
    "wof:placetype":"venue"
},
  "geometry": {"coordinates":[-83.400481,42.55162],"type":"Point"}
}