{
  "type": "Feature",
  "properties": {
    "iso:country":"US",
    "sg:address":"6887 Piedmont St",
    "sg:city":"Detroit",
    "sg:classifiers":[
        {
            "category":"Shopping",
            "subcategory":"Gifts & Souvenirs",
            "type":"Retail Goods"
        }
    ],
    "sg:phone":"+1 313 271 2539",
    "sg:postcode":"48228",
    "sg:province":"MI",
    "wof:name":"More & More Gifts",
    "wof:placetype":"venue"
},
  "geometry": {"coordinates":[-83.22813600000001,42.341879],"type":"Point"}
}