{
  "type": "Feature",
  "properties": {
    "iso:country":"US",
    "sg:address":"2321 E Grand River Ave",
    "sg:city":"Howell",
    "sg:classifiers":[
        {
            "category":"Building & Trades",
            "subcategory":"Construction",
            "type":"Services"
        }
    ],
    "sg:phone":"+1 517 546 6281",
    "sg:postcode":"48843",
    "sg:province":"MI",
    "sg:tags":[
        "general",
        "contractor"
    ],
    "wof:name":"Livingston Excel Assoc LTD",
    "wof:placetype":"venue"
},
  "geometry": {"coordinates":[-83.90794,42.599214],"type":"Point"}
}