{
  "type": "Feature",
  "properties": {
    "iso:country":"US",
    "sg:address":"825 Golf Dr",
    "sg:city":"Pontiac",
    "sg:classifiers":[
        {
            "category":"Education",
            "subcategory":"College",
            "type":"Public Place"
        }
    ],
    "sg:phone":"+1 248 334 0961",
    "sg:postcode":"48341",
    "sg:province":"MI",
    "sg:tags":[
        "religious"
    ],
    "wof:name":"Midwestern Baptist College",
    "wof:placetype":"venue"
},
  "geometry": {"coordinates":[-83.301283,42.618066],"type":"Point"}
}