{
  "type": "Feature",
  "properties": {
    "iso:country":"US",
    "sg:address":"1831 W David Hwy",
    "sg:city":"Ionia",
    "sg:classifiers":[
        {
            "category":"Retail",
            "subcategory":"Animal Services",
            "type":"Services"
        }
    ],
    "sg:phone":"+1 616 527 9113",
    "sg:postcode":"48846",
    "sg:province":"MI",
    "wof:name":"Dog Place",
    "wof:placetype":"venue"
},
  "geometry": {"coordinates":[-85.106655,42.929525],"type":"Point"}
}