{
  "type": "Feature",
  "properties": {
    "iso:country":"US",
    "sg:address":"530 E Frederick Ave",
    "sg:city":"Lansing",
    "sg:classifiers":[
        {
            "category":"Social Services",
            "subcategory":"Child Care",
            "type":"Services"
        }
    ],
    "sg:phone":"+1 517 482 7539",
    "sg:postcode":"48906",
    "sg:province":"MI",
    "wof:name":"Cathy's Kids Day Care",
    "wof:placetype":"venue"
},
  "geometry": {"coordinates":[-84.544837,42.767785],"type":"Point"}
}