{
  "type": "Feature",
  "properties": {
    "iso:country":"US",
    "sg:address":"3648 Saratoga Ave",
    "sg:city":"Kalamazoo",
    "sg:classifiers":[
        {
            "category":"Building & Trades",
            "subcategory":"Landscaping Services",
            "type":"Services"
        },
        {
            "category":"Farming",
            "subcategory":"Nursery",
            "type":"Manufacturing & Wholesale Goods"
        }
    ],
    "sg:phone":"+1 269 744 5569",
    "sg:postcode":"49048",
    "sg:province":"MI",
    "sg:tags":[
        "lawn",
        "stump",
        "nurseries-plants",
        "tree",
        "grinding",
        "removal",
        "grower",
        "orchid"
    ],
    "sg:website":"http://www.kalamazootreeservice.com",
    "wof:name":"Kalamazoo Tree Service",
    "wof:placetype":"venue"
},
  "geometry": {"coordinates":[-85.529769,42.321081],"type":"Point"}
}