{
  "type": "Feature",
  "properties": {
    "iso:country":"US",
    "sg:address":"235 Quimby Rd",
    "sg:city":"Coldwater",
    "sg:classifiers":[
        {
            "category":"Freight",
            "type":"Transportation"
        }
    ],
    "sg:phone":"+1 517 279 0889",
    "sg:postcode":"49036",
    "sg:province":"MI",
    "wof:name":"Tj Transportation",
    "wof:placetype":"venue"
},
  "geometry": {"coordinates":[-84.95623399999999,41.875106],"type":"Point"}
}