{
  "type": "Feature",
  "properties": {
    "iso:country":"US",
    "sg:address":"3595 Pontiac Lake Rd",
    "sg:city":"Waterford",
    "sg:classifiers":[
        {
            "category":"Retail",
            "subcategory":"Self-service Laundry",
            "type":"Services"
        }
    ],
    "sg:phone":"+1 248 681 3332",
    "sg:postcode":"48328",
    "sg:province":"MI",
    "wof:name":"Town Tub",
    "wof:placetype":"venue"
},
  "geometry": {"coordinates":[-83.357817,42.653758],"type":"Point"}
}