{
  "type": "Feature",
  "properties": {
    "iso:country":"US",
    "sg:address":"19888 Kemp St",
    "sg:city":"Clinton Twp",
    "sg:classifiers":[
        {
            "category":"Wholesale",
            "subcategory":"Non-durable Goods",
            "type":"Manufacturing & Wholesale Goods"
        }
    ],
    "sg:phone":"+1 586 792 5357",
    "sg:postcode":"48035",
    "sg:province":"MI",
    "sg:tags":[
        "rubber",
        "sponge"
    ],
    "wof:name":"Specialty Foam Products",
    "wof:placetype":"venue"
},
  "geometry": {"coordinates":[-82.91489300000001,42.548907],"type":"Point"}
}