{
  "type": "Feature",
  "properties": {
    "iso:country":"US",
    "sg:address":"6785 Highland Rd",
    "sg:city":"White Lake",
    "sg:classifiers":[
        {
            "category":"Shopping",
            "type":"Retail Goods"
        }
    ],
    "sg:phone":"+1 248 887 9300",
    "sg:postcode":"48383",
    "sg:province":"MI",
    "sg:tags":[
        "trophy",
        "medal",
        "award"
    ],
    "wof:name":"Michael M Chevrie Co",
    "wof:placetype":"venue"
},
  "geometry": {"coordinates":[-83.52005,42.649116],"type":"Point"}
}