{
  "type": "Feature",
  "properties": {
    "iso:country":"US",
    "sg:address":"1148 W Western Ave",
    "sg:city":"Muskegon",
    "sg:classifiers":[
        {
            "category":"Manufacturing",
            "subcategory":"Metals",
            "type":"Manufacturing & Wholesale Goods"
        }
    ],
    "sg:phone":"+1 231 726 5177",
    "sg:postcode":"49441",
    "sg:province":"MI",
    "sg:tags":[
        "foundry"
    ],
    "wof:name":"Michigan Steel Inc",
    "wof:placetype":"venue"
},
  "geometry": {"coordinates":[-86.271475,43.22908],"type":"Point"}
}