{
  "type": "Feature",
  "properties": {
    "iso:country":"US",
    "sg:address":"46710 Gratiot Ave",
    "sg:city":"Chesterfield",
    "sg:classifiers":[
        {
            "category":"Building & Trades",
            "subcategory":"Construction",
            "type":"Services"
        }
    ],
    "sg:phone":"+1 586 598 5677",
    "sg:postcode":"48051",
    "sg:province":"MI",
    "sg:tags":[
        "contractor"
    ],
    "wof:name":"Socks & Assoc",
    "wof:placetype":"venue"
},
  "geometry": {"coordinates":[-82.854054,42.642858],"type":"Point"}
}