{
  "type": "Feature",
  "properties": {
    "iso:country":"US",
    "sg:address":"858 Caton Ave",
    "sg:city":"Adrian",
    "sg:classifiers":[
        {
            "category":"Wholesale",
            "subcategory":"Painting Supplies",
            "type":"Manufacturing & Wholesale Goods"
        }
    ],
    "sg:phone":"+1 517 263 0634",
    "sg:postcode":"49221",
    "sg:province":"MI",
    "sg:tags":[
        "equipment",
        "painter"
    ],
    "wof:name":"Painters Supply & Equipment",
    "wof:placetype":"venue"
},
  "geometry": {"coordinates":[-84.042333,41.886842],"type":"Point"}
}