{
  "type": "Feature",
  "properties": {
    "iso:country":"US",
    "sg:address":"1530 Waverly Ave",
    "sg:city":"Grand Haven",
    "sg:classifiers":[
        {
            "category":"Building & Trades",
            "subcategory":"Construction",
            "type":"Services"
        }
    ],
    "sg:phone":"+1 616 846 1353",
    "sg:postcode":"49417",
    "sg:province":"MI",
    "sg:tags":[
        "hanging",
        "contractor"
    ],
    "wof:name":"Scotts Parking Lot Painting",
    "wof:placetype":"venue"
},
  "geometry": {"coordinates":[-86.20385,43.055723],"type":"Point"}
}