{
  "type": "Feature",
  "properties": {
    "iso:country":"US",
    "sg:address":"29901 Middlebelt Rd",
    "sg:city":"Farmington Hills",
    "sg:classifiers":[
        {
            "category":"Professional",
            "type":"Services"
        }
    ],
    "sg:phone":"+1 248 626 5702",
    "sg:postcode":"48334",
    "sg:province":"MI",
    "sg:tags":[
        "caterer"
    ],
    "wof:name":"Farmington Hills Kosher Catering",
    "wof:placetype":"venue"
},
  "geometry": {"coordinates":[-83.340103,42.518002],"type":"Point"}
}