{
  "type": "Feature",
  "properties": {
    "iso:country":"US",
    "sg:address":"16038 E 8 Mile Rd",
    "sg:city":"Detroit",
    "sg:classifiers":[
        {
            "category":"Personal",
            "subcategory":"Barber",
            "type":"Services"
        }
    ],
    "sg:phone":"+1 313 526 7077",
    "sg:postcode":"48205",
    "sg:province":"MI",
    "wof:name":"Brotherhood Grooming Gallery",
    "wof:placetype":"venue"
},
  "geometry": {"coordinates":[-82.955195,42.449907],"type":"Point"}
}