{
  "type": "Feature",
  "properties": {
    "iso:country":"US",
    "sg:address":"1190 River Valley Dr",
    "sg:city":"Flint",
    "sg:classifiers":[
        {
            "category":"Retail",
            "subcategory":"Auto Repair",
            "type":"Services"
        }
    ],
    "sg:phone":"+1 810 230 9147",
    "sg:postcode":"48532",
    "sg:province":"MI",
    "sg:tags":[
        "body"
    ],
    "wof:name":"Showcase Paint Works",
    "wof:placetype":"venue"
},
  "geometry": {"coordinates":[-83.74271299999999,43.017506],"type":"Point"}
}