{
  "type": "Feature",
  "properties": {
    "iso:country":"US",
    "sg:address":"2990 W Grand Blvd Ste 201",
    "sg:city":"Detroit",
    "sg:classifiers":[
        {
            "category":"Professional",
            "subcategory":"Accounting & Tax Preparation",
            "type":"Services"
        }
    ],
    "sg:phone":"+1 313 871 4030",
    "sg:postcode":"48202",
    "sg:province":"MI",
    "sg:tags":[
        "accountant"
    ],
    "wof:name":"Brown Charles R & Co PC",
    "wof:placetype":"venue"
},
  "geometry": {"coordinates":[-83.07849899999999,42.368198],"type":"Point"}
}