{
  "type": "Feature",
  "properties": {
    "iso:country":"US",
    "sg:address":"23160 Coolidge Hwy",
    "sg:city":"Oak Park",
    "sg:classifiers":[
        {
            "category":"Restaurant",
            "type":"Food & Drink"
        }
    ],
    "sg:phone":"+1 248 398 8600",
    "sg:postcode":"48237",
    "sg:province":"MI",
    "wof:name":"Island Chicken",
    "wof:placetype":"venue"
},
  "geometry": {"coordinates":[-83.18199199999999,42.462007],"type":"Point"}
}