{
  "type": "Feature",
  "properties": {
    "iso:country":"US",
    "sg:address":"16881 E 14 Mile Rd",
    "sg:city":"Fraser",
    "sg:classifiers":[
        {
            "category":"Restaurant",
            "type":"Food & Drink"
        }
    ],
    "sg:phone":"+1 586 285 1106",
    "sg:postcode":"48026",
    "sg:province":"MI",
    "wof:name":"Cj's Country Kitchen",
    "wof:placetype":"venue"
},
  "geometry": {"coordinates":[-82.94699900000001,42.539001],"type":"Point"}
}