{
  "type": "Feature",
  "properties": {
    "iso:country":"US",
    "sg:address":"10 N Groesbeck Hwy",
    "sg:city":"Mount Clemens",
    "sg:classifiers":[
        {
            "category":"Cinema",
            "subcategory":"Movie Rental",
            "type":"Entertainment"
        }
    ],
    "sg:phone":"+1 586 469 9150",
    "sg:postcode":"48043",
    "sg:province":"MI",
    "sg:tags":[
        "tape",
        "game",
        "video"
    ],
    "sg:website":"www.hollywoodvideo.com",
    "wof:name":"Hollywood Video",
    "wof:placetype":"venue"
},
  "geometry": {"coordinates":[-82.89969600000001,42.599499],"type":"Point"}
}