{
  "type": "Feature",
  "properties": {
    "iso:country":"US",
    "sg:address":"3912 Douglas Ave",
    "sg:city":"Kalamazoo",
    "sg:classifiers":[
        {
            "category":"Restaurant",
            "type":"Food & Drink"
        }
    ],
    "sg:phone":"+1 269 978 1078",
    "sg:postcode":"49004",
    "sg:province":"MI",
    "wof:name":"Quizoli's Pizza & Oven Baked",
    "wof:placetype":"venue"
},
  "geometry": {"coordinates":[-85.60055800000001,42.328014],"type":"Point"}
}