{
  "type": "Feature",
  "properties": {
    "iso:country":"US",
    "sg:address":"6581 Balfour Ave",
    "sg:city":"Allen Park",
    "sg:classifiers":[
        {
            "category":"Retail",
            "subcategory":"Repair Shop",
            "type":"Services"
        }
    ],
    "sg:phone":"+1 313 386 8341",
    "sg:postcode":"48101",
    "sg:province":"MI",
    "wof:name":"First Impressions Win & Door",
    "wof:placetype":"venue"
},
  "geometry": {"coordinates":[-83.227662,42.259957],"type":"Point"}
}