{
  "type": "Feature",
  "properties": {
    "iso:country":"US",
    "sg:address":"6844 Anita Ct",
    "sg:city":"Fruitport",
    "sg:classifiers":[
        {
            "category":"Building & Trades",
            "subcategory":"Construction",
            "type":"Services"
        }
    ],
    "sg:phone":"+1 231 865 6247",
    "sg:postcode":"49415",
    "sg:province":"MI",
    "sg:tags":[
        "house"
    ],
    "wof:name":"Branch Construction Co",
    "wof:placetype":"venue"
},
  "geometry": {"coordinates":[-86.17372400000001,43.130943],"type":"Point"}
}