{
  "type": "Feature",
  "properties": {
    "iso:country":"US",
    "sg:address":"1580 S Garfield Ave",
    "sg:city":"Traverse City",
    "sg:classifiers":[
        {
            "category":"Building & Trades",
            "subcategory":"Construction",
            "type":"Services"
        }
    ],
    "sg:phone":"+1 231 929 4253",
    "sg:postcode":"49686",
    "sg:province":"MI",
    "sg:tags":[
        "contractor"
    ],
    "wof:name":"Emco Drywall",
    "wof:placetype":"venue"
},
  "geometry": {"coordinates":[-85.595426,44.743935],"type":"Point"}
}