{
  "type": "Feature",
  "properties": {
    "iso:country":"US",
    "sg:address":"4200 Colorado Ln",
    "sg:city":"West Bloomfield",
    "sg:classifiers":[
        {
            "category":"Professional",
            "type":"Services"
        }
    ],
    "sg:phone":"+1 248 737 2267",
    "sg:postcode":"48322",
    "sg:province":"MI",
    "wof:name":"Artbeat Specialties",
    "wof:placetype":"venue"
},
  "geometry": {"coordinates":[-83.36400500000001,42.543252],"type":"Point"}
}