{
  "type": "Feature",
  "properties": {
    "iso:country":"US",
    "sg:address":"1550 Gezon Pkwy SW",
    "sg:city":"Grand Rapids",
    "sg:classifiers":[
        {
            "category":"Wholesale",
            "subcategory":"Construction Materials",
            "type":"Manufacturing & Wholesale Goods"
        }
    ],
    "sg:phone":"+1 616 532 3800",
    "sg:postcode":"49509",
    "sg:province":"MI",
    "sg:tags":[
        "marble"
    ],
    "wof:name":"Pascucci Marble",
    "wof:placetype":"venue"
},
  "geometry": {"coordinates":[-85.702423,42.86054],"type":"Point"}
}