{
  "type": "Feature",
  "properties": {
    "iso:country":"US",
    "sg:address":"118 Englewood Ave",
    "sg:city":"Royal Oak",
    "sg:classifiers":[
        {
            "category":"Building & Trades",
            "subcategory":"Electrical",
            "type":"Services"
        }
    ],
    "sg:phone":"+1 248 585 4424",
    "sg:postcode":"48073",
    "sg:province":"MI",
    "sg:tags":[
        "electrician",
        "electric",
        "contractor"
    ],
    "wof:name":"Village Electric Inc",
    "wof:placetype":"venue"
},
  "geometry": {"coordinates":[-83.14510300000001,42.522598],"type":"Point"}
}