{
  "type": "Feature",
  "properties": {
    "iso:country":"US",
    "sg:address":"8065 Roosevelt Rd",
    "sg:city":"Mecosta",
    "sg:classifiers":[
        {
            "category":"Shopping",
            "type":"Retail Goods"
        }
    ],
    "sg:phone":"+1 231 972 1202",
    "sg:postcode":"49332",
    "sg:province":"MI",
    "sg:tags":[
        "candle"
    ],
    "wof:name":"Candle Lovers United",
    "wof:placetype":"venue"
},
  "geometry": {"coordinates":[-85.248198,43.675114],"type":"Point"}
}