{
  "type": "Feature",
  "properties": {
    "iso:country":"US",
    "sg:address":"5682 Millington Rd",
    "sg:city":"Millington",
    "sg:classifiers":[
        {
            "category":"Retail",
            "subcategory":"Auto Repair",
            "type":"Services"
        }
    ],
    "sg:phone":"+1 989 871 2902",
    "sg:postcode":"48746",
    "sg:province":"MI",
    "sg:tags":[
        "repairing",
        "tire"
    ],
    "wof:name":"P & S Tire Repair",
    "wof:placetype":"venue"
},
  "geometry": {"coordinates":[-83.56570499999999,43.281156],"type":"Point"}
}