{
  "type": "Feature",
  "properties": {
    "iso:country":"US",
    "sg:address":"2781 Garfield Rd N",
    "sg:city":"Traverse City",
    "sg:classifiers":[
        {
            "category":"Health Services",
            "subcategory":"Chiropractor",
            "type":"Services"
        }
    ],
    "sg:phone":"+1 231 946 1903",
    "sg:postcode":"49686",
    "sg:province":"MI",
    "wof:name":"White Chiropractic Clinic",
    "wof:placetype":"venue"
},
  "geometry": {"coordinates":[-85.595507,44.727071],"type":"Point"}
}