{
  "type": "Feature",
  "properties": {
    "iso:country":"US",
    "sg:address":"111 N Main St",
    "sg:city":"Berrien Springs",
    "sg:classifiers":[
        {
            "category":"Home & Garden",
            "subcategory":"Garden Supply",
            "type":"Retail Goods"
        }
    ],
    "sg:phone":"+1 269 471 4037",
    "sg:postcode":"49103",
    "sg:province":"MI",
    "sg:tags":[
        "center"
    ],
    "wof:name":"Green Wellies Garden Shop",
    "wof:placetype":"venue"
},
  "geometry": {"coordinates":[-86.33838900000001,41.947623],"type":"Point"}
}