{
  "type": "Feature",
  "properties": {
    "iso:country":"US",
    "sg:address":"1021 N Bridge St",
    "sg:city":"Linden",
    "sg:classifiers":[
        {
            "category":"Professional",
            "type":"Services"
        }
    ],
    "sg:phone":"+1 810 735 9075",
    "sg:postcode":"48451",
    "sg:province":"MI",
    "wof:name":"Vangoethem Michael Acctg Svc",
    "wof:placetype":"venue"
},
  "geometry": {"coordinates":[-83.782539,42.825002],"type":"Point"}
}