{
  "type": "Feature",
  "properties": {
    "iso:country":"US",
    "sg:address":"4923 Alpha St",
    "sg:city":"Lansing",
    "sg:classifiers":[
        {
            "category":"Retail",
            "subcategory":"Auto Repair",
            "type":"Services"
        }
    ],
    "sg:phone":"+1 517 882 7527",
    "sg:postcode":"48910",
    "sg:province":"MI",
    "sg:tags":[
        "automotive"
    ],
    "wof:name":"Stripe Man",
    "wof:placetype":"venue"
},
  "geometry": {"coordinates":[-84.536744,42.684796],"type":"Point"}
}