{
  "type": "Feature",
  "properties": {
    "iso:country":"US",
    "sg:address":"6479 Fulton St E",
    "sg:city":"Ada",
    "sg:classifiers":[
        {
            "category":"Professional",
            "subcategory":"Management & Consulting",
            "type":"Services"
        }
    ],
    "sg:phone":"+1 616 974 0095",
    "sg:postcode":"49301",
    "sg:province":"MI",
    "sg:tags":[
        "consultant",
        "safety"
    ],
    "wof:name":"Consultants At Work Inc",
    "wof:placetype":"venue"
},
  "geometry": {"coordinates":[-85.511185,42.962555],"type":"Point"}
}