{
  "type": "Feature",
  "properties": {
    "iso:country":"US",
    "sg:address":"7759 Auburn Rd",
    "sg:city":"Utica",
    "sg:classifiers":[
        {
            "category":"Restaurant",
            "type":"Food & Drink"
        }
    ],
    "sg:menulink":"http://www.allmenus.com/mi/utica/51052-hatchys/menu/",
    "sg:phone":"+1 586 991 0407",
    "sg:postcode":"48317",
    "sg:province":"MI",
    "sg:tags":[
        "wrap",
        "american",
        "sandwich"
    ],
    "wof:name":"Hatchy's",
    "wof:placetype":"venue"
},
  "geometry": {"coordinates":[-83.03389900000001,42.626059],"type":"Point"}
}