{
  "type": "Feature",
  "properties": {
    "iso:country":"US",
    "sg:address":"815 Johnston St",
    "sg:city":"Sault Sainte Marie",
    "sg:classifiers":[
        {
            "category":"Retail",
            "subcategory":"Repair Shop",
            "type":"Services"
        }
    ],
    "sg:phone":"+1 906 635 2715",
    "sg:postcode":"49783",
    "sg:province":"MI",
    "wof:name":"Rbs Repair Service",
    "wof:placetype":"venue"
},
  "geometry": {"coordinates":[-84.34196,46.491393],"type":"Point"}
}