{
  "type": "Feature",
  "properties": {
    "iso:country":"US",
    "sg:address":"335 E Maple Rd",
    "sg:city":"Birmingham",
    "sg:classifiers":[
        {
            "category":"Shopping",
            "subcategory":"Used Merchandise",
            "type":"Retail Goods"
        }
    ],
    "sg:phone":"+1 248 646 1695",
    "sg:postcode":"48009",
    "sg:province":"MI",
    "sg:tags":[
        "clothing"
    ],
    "wof:name":"Miss Kate Loc",
    "wof:placetype":"venue"
},
  "geometry": {"coordinates":[-83.21212,42.546745],"type":"Point"}
}