{
  "type": "Feature",
  "properties": {
    "iso:country":"US",
    "sg:address":"14156 E 12 Mile Rd",
    "sg:city":"Warren",
    "sg:classifiers":[
        {
            "category":"Restaurant",
            "type":"Food & Drink"
        }
    ],
    "sg:phone":"+1 586 777 9604",
    "sg:postcode":"48088",
    "sg:province":"MI",
    "wof:name":"Fran's Kitchen",
    "wof:placetype":"venue"
},
  "geometry": {"coordinates":[-82.981014,42.50795],"type":"Point"}
}