{
  "type": "Feature",
  "properties": {
    "iso:country":"US",
    "sg:address":"15700 138th Ave",
    "sg:city":"Spring Lake",
    "sg:classifiers":[
        {
            "category":"Farming",
            "subcategory":"Farm",
            "type":"Manufacturing & Wholesale Goods"
        }
    ],
    "sg:phone":"+1 616 846 7309",
    "sg:postcode":"49456",
    "sg:province":"MI",
    "sg:tags":[
        "crop",
        "general"
    ],
    "wof:name":"Rob Richert Farms",
    "wof:placetype":"venue"
},
  "geometry": {"coordinates":[-86.131665,43.053794],"type":"Point"}
}