{
  "type": "Feature",
  "properties": {
    "iso:country":"US",
    "sg:address":"203 W Mitchell St",
    "sg:city":"Petoskey",
    "sg:classifiers":[
        {
            "category":"Banks & Credit Unions",
            "subcategory":"Bank",
            "type":"Services"
        }
    ],
    "sg:phone":"+1 231 439 0920",
    "sg:postcode":"49770",
    "sg:province":"MI",
    "sg:tags":[
        "cashing",
        "check"
    ],
    "wof:name":"Cash Fast",
    "wof:placetype":"venue"
},
  "geometry": {"coordinates":[-84.963759,45.37393],"type":"Point"}
}