{
  "type": "Feature",
  "properties": {
    "iso:country":"US",
    "sg:address":"7633 Schaefer Rd",
    "sg:city":"Dearborn",
    "sg:classifiers":[
        {
            "category":"Retail",
            "subcategory":"Repair Shop",
            "type":"Services"
        }
    ],
    "sg:phone":"+1 313 581 7205",
    "sg:postcode":"48126",
    "sg:province":"MI",
    "sg:tags":[
        "industrial",
        "supply"
    ],
    "wof:name":"American Strapping Tl Repr Co",
    "wof:placetype":"venue"
},
  "geometry": {"coordinates":[-83.17717,42.349161],"type":"Point"}
}