{
  "type": "Feature",
  "properties": {
    "iso:country":"US",
    "sg:address":"4021 W Michigan Ave",
    "sg:city":"Lansing",
    "sg:classifiers":[
        {
            "category":"Social Services",
            "subcategory":"Job Training",
            "type":"Services"
        }
    ],
    "sg:phone":"+1 517 323 4878",
    "sg:postcode":"48917",
    "sg:province":"MI",
    "sg:tags":[
        "rehabilitation",
        "outpatient",
        "specialty"
    ],
    "wof:name":"Hostetler Fontaine and Assoc",
    "wof:placetype":"venue"
},
  "geometry": {"coordinates":[-84.603973,42.733833],"type":"Point"}
}