{
  "type": "Feature",
  "properties": {
    "iso:country":"US",
    "sg:address":"9900 Diamond Park Rd",
    "sg:city":"Interlochen",
    "sg:classifiers":[
        {
            "category":"Education",
            "subcategory":"School",
            "type":"Public Place"
        }
    ],
    "sg:phone":"+1 231 276 7200",
    "sg:postcode":"49643",
    "sg:province":"MI",
    "sg:website":"www.interlochen.org",
    "wof:name":"Interlochen Center-The Arts",
    "wof:placetype":"venue"
},
  "geometry": {"coordinates":[-85.77817899999999,44.633282],"type":"Point"}
}