{
  "type": "Feature",
  "properties": {
    "iso:country":"US",
    "sg:address":"1737 Council Dr",
    "sg:city":"Benton Harbor",
    "sg:classifiers":[
        {
            "category":"Social Services",
            "subcategory":"Child Care",
            "type":"Services"
        }
    ],
    "sg:phone":"+1 269 926 8477",
    "sg:postcode":"49022",
    "sg:province":"MI",
    "wof:name":"Tiny's Daycare",
    "wof:placetype":"venue"
},
  "geometry": {"coordinates":[-86.41661499999999,42.097527],"type":"Point"}
}