{
  "type": "Feature",
  "properties": {
    "iso:country":"US",
    "sg:address":"25484 Truckenmiller Rd",
    "sg:city":"Centreville",
    "sg:classifiers":[
        {
            "category":"Professional",
            "subcategory":"Business Services",
            "type":"Services"
        }
    ],
    "sg:phone":"+1 269 467 7292",
    "sg:postcode":"49032",
    "sg:province":"MI",
    "wof:name":"Schwartz Enterprise",
    "wof:placetype":"venue"
},
  "geometry": {"coordinates":[-85.457241,41.926445],"type":"Point"}
}