{
  "type": "Feature",
  "properties": {
    "iso:country":"US",
    "sg:address":"11050 Anchor Cove Dr",
    "sg:city":"Shelbyville",
    "sg:classifiers":[
        {
            "category":"Banks & Credit Unions",
            "subcategory":"Investment Brokerage",
            "type":"Services"
        }
    ],
    "sg:phone":"+1 269 672 5507",
    "sg:postcode":"49344",
    "sg:province":"MI",
    "sg:tags":[
        "advisory",
        "financial"
    ],
    "wof:name":"Lakeside Securities Inc",
    "wof:placetype":"venue"
},
  "geometry": {"coordinates":[-85.507215,42.578819],"type":"Point"}
}