{
  "type": "Feature",
  "properties": {
    "iso:country":"US",
    "sg:address":"1101 W Warren Ave Ofc",
    "sg:city":"Detroit",
    "sg:classifiers":[
        {
            "category":"Cinema",
            "subcategory":"Movie Rental",
            "type":"Entertainment"
        }
    ],
    "sg:phone":"+1 313 833 9542",
    "sg:postcode":"48201",
    "sg:province":"MI",
    "sg:tags":[
        "game",
        "video"
    ],
    "sg:website":"www.blockbuster.com",
    "wof:name":"Blockbuster Video",
    "wof:placetype":"venue"
},
  "geometry": {"coordinates":[-83.073898,42.3536],"type":"Point"}
}