{
  "type": "Feature",
  "properties": {
    "iso:country":"US",
    "sg:address":"8561 W Chicago",
    "sg:city":"Detroit",
    "sg:classifiers":[
        {
            "category":"Manufacturing",
            "subcategory":"Metals",
            "type":"Manufacturing & Wholesale Goods"
        },
        {
            "category":"Home & Garden",
            "subcategory":"Garden Supply",
            "type":"Retail Goods"
        },
        {
            "category":"Manufacturing",
            "subcategory":"Tools & Machinery",
            "type":"Manufacturing & Wholesale Goods"
        },
        {
            "category":"Manufacturing",
            "subcategory":"Building Materials",
            "type":"Manufacturing & Wholesale Goods"
        },
        {
            "category":"Manufacturing",
            "subcategory":"Paper Products",
            "type":"Manufacturing & Wholesale Goods"
        }
    ],
    "sg:phone":"+1 313 931 6880",
    "sg:postcode":"48204",
    "sg:province":"MI",
    "sg:tags":[
        "sheet",
        "spraying",
        "forming",
        "work",
        "equipment",
        "fabricator",
        "bamboo"
    ],
    "wof:name":"Savard Corporation",
    "wof:placetype":"venue"
},
  "geometry": {"coordinates":[-83.154381,42.36627],"type":"Point"}
}