{
  "type": "Feature",
  "properties": {
    "iso:country":"US",
    "sg:address":"2525 Crispell Rd",
    "sg:city":"Horton",
    "sg:classifiers":[
        {
            "category":"Manufacturing",
            "subcategory":"Electronics",
            "type":"Manufacturing & Wholesale Goods"
        }
    ],
    "sg:phone":"+1 517 529 4919",
    "sg:postcode":"49246",
    "sg:province":"MI",
    "sg:tags":[
        "control",
        "security",
        "system"
    ],
    "wof:name":"Eagle-Eye West",
    "wof:placetype":"venue"
},
  "geometry": {"coordinates":[-84.451645,42.116463],"type":"Point"}
}