{
  "type": "Feature",
  "properties": {
    "iso:country":"US",
    "sg:address":"32906 Middlebelt Rd",
    "sg:city":"Farmington Hills",
    "sg:classifiers":[
        {
            "category":"Food & Beverages",
            "subcategory":"Meat & Fish",
            "type":"Retail Goods"
        }
    ],
    "sg:phone":"+1 248 538 8193",
    "sg:postcode":"48334",
    "sg:province":"MI",
    "sg:tags":[
        "seafood",
        "market"
    ],
    "wof:name":"Marketplace Fishery II Inc",
    "wof:placetype":"venue"
},
  "geometry": {"coordinates":[-83.340401,42.528599],"type":"Point"}
}