{
  "type": "Feature",
  "properties": {
    "iso:country":"US",
    "sg:address":"214 State St",
    "sg:city":"Boyne City",
    "sg:classifiers":[
        {
            "category":"Wholesale",
            "subcategory":"Motor Vehicles",
            "type":"Manufacturing & Wholesale Goods"
        }
    ],
    "sg:phone":"+1 231 582 6796",
    "sg:postcode":"49712",
    "sg:province":"MI",
    "wof:name":"Auto Valu",
    "wof:placetype":"venue"
},
  "geometry": {"coordinates":[-85.012927,45.216002],"type":"Point"}
}