{
  "type": "Feature",
  "properties": {
    "iso:country":"US",
    "sg:address":"1421 Colorado Ave SE",
    "sg:city":"Grand Rapids",
    "sg:classifiers":[
        {
            "category":"Professional",
            "subcategory":"Management & Consulting",
            "type":"Services"
        }
    ],
    "sg:phone":"+1 616 245 3969",
    "sg:postcode":"49507",
    "sg:province":"MI",
    "wof:name":"Spitler Communications",
    "wof:placetype":"venue"
},
  "geometry": {"coordinates":[-85.63351,42.937552],"type":"Point"}
}