{
  "type": "Feature",
  "properties": {
    "iso:country":"US",
    "sg:address":"69505 Saxon Dr",
    "sg:city":"Romeo",
    "sg:classifiers":[
        {
            "category":"Manufacturing",
            "subcategory":"Food",
            "type":"Manufacturing & Wholesale Goods"
        }
    ],
    "sg:phone":"+1 586 752 6453",
    "sg:postcode":"48065",
    "sg:province":"MI",
    "sg:tags":[
        "preparation",
        "mfg",
        "potato"
    ],
    "wof:name":"Novak & Associates",
    "wof:placetype":"venue"
},
  "geometry": {"coordinates":[-83.055153,42.804015],"type":"Point"}
}