{
  "type": "Feature",
  "properties": {
    "iso:country":"US",
    "sg:address":"3675 12 Mile Rd",
    "sg:city":"Berkley",
    "sg:classifiers":[
        {
            "category":"Professional",
            "type":"Services"
        },
        {
            "category":"Restaurant",
            "type":"Food & Drink"
        }
    ],
    "sg:phone":"+1 248 545 1060",
    "sg:postcode":"48072",
    "sg:province":"MI",
    "sg:tags":[
        "pizza",
        "caterer"
    ],
    "wof:name":"Hungry Howie's",
    "wof:placetype":"venue"
},
  "geometry": {"coordinates":[-83.197098,42.5028],"type":"Point"}
}