{
  "type": "Feature",
  "properties": {
    "iso:country":"US",
    "sg:address":"34836 Bridge St.",
    "sg:city":"Livonia",
    "sg:classifiers":[
        {
            "category":"Professional",
            "subcategory":"Advertising",
            "type":"Services"
        }
    ],
    "sg:phone":"+1 248 943 1550",
    "sg:postcode":"48152",
    "sg:province":"MI",
    "sg:tags":[
        "marketing"
    ],
    "sg:website":"www.informationlighthouse.com",
    "wof:name":"Information Lighthouse",
    "wof:placetype":"venue"
},
  "geometry": {"coordinates":[-83.38894500000001,42.428145],"type":"Point"}
}