{
  "type": "Feature",
  "properties": {
    "iso:country":"US",
    "sg:address":"1040 N Towerline Rd",
    "sg:city":"Saginaw",
    "sg:classifiers":[
        {
            "category":"Government",
            "subcategory":"Office",
            "type":"Public Place"
        }
    ],
    "sg:phone":"+1 989 754 2288",
    "sg:postcode":"48601",
    "sg:province":"MI",
    "sg:tags":[
        "county",
        "program",
        "health"
    ],
    "wof:name":"Saginaw County Mental Health",
    "wof:placetype":"venue"
},
  "geometry": {"coordinates":[-83.87635899999999,43.42827],"type":"Point"}
}