{
  "type": "Feature",
  "properties": {
    "iso:country":"US",
    "sg:address":"52 N State St",
    "sg:city":"St Ignace",
    "sg:classifiers":[
        {
            "category":"Shopping",
            "subcategory":"Books",
            "type":"Retail Goods"
        }
    ],
    "sg:phone":"+1 906 643 7569",
    "sg:postcode":"49781",
    "sg:province":"MI",
    "sg:tags":[
        "dealer"
    ],
    "wof:name":"Book World",
    "wof:placetype":"venue"
},
  "geometry": {"coordinates":[-84.726079,45.86833],"type":"Point"}
}