{
  "type": "Feature",
  "properties": {
    "iso:country":"US",
    "sg:address":"3600 Tipton Hwy",
    "sg:city":"Adrian",
    "sg:classifiers":[
        {
            "category":"Building & Trades",
            "subcategory":"Construction",
            "type":"Services"
        }
    ],
    "sg:phone":"+1 517 263 2868",
    "sg:postcode":"49221",
    "sg:province":"MI",
    "sg:tags":[
        "hanging",
        "contractor"
    ],
    "wof:name":"Reist Painting",
    "wof:placetype":"venue"
},
  "geometry": {"coordinates":[-84.06515400000001,41.935376],"type":"Point"}
}