{
  "type": "Feature",
  "properties": {
    "iso:country":"US",
    "sg:address":"1902 Hammerburg Rd",
    "sg:city":"Flint",
    "sg:classifiers":[
        {
            "category":"Sports & Exercise",
            "subcategory":"Golf",
            "type":"Entertainment"
        }
    ],
    "sg:phone":"+1 810 766 7043",
    "sg:postcode":"48502",
    "sg:province":"MI",
    "wof:name":"Flint City of",
    "wof:placetype":"venue"
},
  "geometry": {"coordinates":[-83.708181,43.000885],"type":"Point"}
}