{
  "type": "Feature",
  "properties": {
    "iso:country":"US",
    "sg:address":"3500 Alpine Ave NW",
    "sg:city":"Grand Rapids",
    "sg:classifiers":[
        {
            "category":"Banks & Credit Unions",
            "subcategory":"Bank",
            "type":"Services"
        }
    ],
    "sg:phone":"+1 616 771 8706",
    "sg:postcode":"49544",
    "sg:province":"MI",
    "sg:tags":[
        "national",
        "commercial"
    ],
    "wof:name":"National City Bank",
    "wof:placetype":"venue"
},
  "geometry": {"coordinates":[-85.689345,43.028352],"type":"Point"}
}