{
  "type": "Feature",
  "properties": {
    "iso:country":"US",
    "sg:address":"11200 Herold Hwy",
    "sg:city":"Addison",
    "sg:classifiers":[
        {
            "category":"Home & Garden",
            "subcategory":"Building Materials",
            "type":"Retail Goods"
        }
    ],
    "sg:phone":"+1 517 547 7004",
    "sg:postcode":"49220",
    "sg:province":"MI",
    "sg:tags":[
        "mixed",
        "concrete"
    ],
    "wof:name":"Darby Ready Mix Concrete Co",
    "wof:placetype":"venue"
},
  "geometry": {"coordinates":[-84.330619,42.046508],"type":"Point"}
}