{
  "type": "Feature",
  "properties": {
    "iso:country":"US",
    "sg:address":"122 W Main St",
    "sg:city":"Elsie",
    "sg:classifiers":[
        {
            "category":"Insurance",
            "subcategory":"Insurance Agent",
            "type":"Services"
        }
    ],
    "sg:phone":"+1 989 862 4227",
    "sg:postcode":"48831",
    "sg:province":"MI",
    "wof:name":"Carter Melvin Insurance",
    "wof:placetype":"venue"
},
  "geometry": {"coordinates":[-84.389745,43.088798],"type":"Point"}
}