{
  "type": "Feature",
  "properties": {
    "iso:country":"US",
    "sg:address":"7097 M-72",
    "sg:city":"Williamsburg",
    "sg:classifiers":[
        {
            "category":"Travel",
            "subcategory":"Hotels & Motels",
            "type":"Entertainment"
        }
    ],
    "sg:phone":"+1 231 267 9711",
    "sg:postcode":"49690",
    "sg:province":"MI",
    "sg:tags":[
        "breakfast",
        "inn",
        "bed"
    ],
    "wof:name":"Barker Creek Bed & Breakfast",
    "wof:placetype":"venue"
},
  "geometry": {"coordinates":[-85.315799,44.779694],"type":"Point"}
}