{
  "type": "Feature",
  "properties": {
    "iso:country":"US",
    "sg:address":"1801 Eureka Rd",
    "sg:city":"Wyandotte",
    "sg:classifiers":[
        {
            "category":"Retail",
            "subcategory":"Auto Repair",
            "type":"Services"
        }
    ],
    "sg:phone":"+1 734 285 9585",
    "sg:postcode":"48192",
    "sg:province":"MI",
    "sg:tags":[
        "body",
        "shop"
    ],
    "sg:website":"www.eurekabody.com",
    "wof:name":"Eureka Body & Fender Inc",
    "wof:placetype":"venue"
},
  "geometry": {"coordinates":[-83.17379800000001,42.199501],"type":"Point"}
}