{
  "type": "Feature",
  "properties": {
    "iso:country":"US",
    "sg:address":"3215 Peshtigo Dr SW",
    "sg:city":"Grandville",
    "sg:classifiers":[
        {
            "category":"Building & Trades",
            "subcategory":"Construction",
            "type":"Services"
        }
    ],
    "sg:phone":"+1 616 538 4586",
    "sg:postcode":"49418",
    "sg:province":"MI",
    "sg:tags":[
        "heavy",
        "contractor"
    ],
    "wof:name":"Grandville Construction Inc",
    "wof:placetype":"venue"
},
  "geometry": {"coordinates":[-85.74342799999999,42.888456],"type":"Point"}
}