{
  "type": "Feature",
  "properties": {
    "iso:country":"US",
    "sg:address":"426 Naomi St",
    "sg:city":"Plainwell",
    "sg:classifiers":[
        {
            "category":"Professional",
            "subcategory":"Business Services",
            "type":"Services"
        }
    ],
    "sg:phone":"+1 269 685 6288",
    "sg:postcode":"49080",
    "sg:province":"MI",
    "wof:name":"Island City Graphics",
    "wof:placetype":"venue"
},
  "geometry": {"coordinates":[-85.652789,42.446688],"type":"Point"}
}