{
  "type": "Feature",
  "properties": {
    "iso:country":"US",
    "sg:address":"28820 Southfield Rd",
    "sg:city":"Lathrup Village",
    "sg:classifiers":[
        {
            "category":"Retail",
            "subcategory":"Repair Shop",
            "type":"Services"
        }
    ],
    "sg:phone":"+1 248 559 9610",
    "sg:postcode":"48076",
    "sg:province":"MI",
    "sg:tags":[
        "equipment",
        "conditioning",
        "air"
    ],
    "wof:name":"Carpenter-Cunningham & Assoc",
    "wof:placetype":"venue"
},
  "geometry": {"coordinates":[-83.222452,42.501257],"type":"Point"}
}