{
  "type": "Feature",
  "properties": {
    "iso:country":"US",
    "sg:address":"31031 Dequindre Rd",
    "sg:city":"Madison Heights",
    "sg:classifiers":[
        {
            "category":"Autos & Motor Vehicles",
            "subcategory":"Fuel & Gas Station",
            "type":"Retail Goods"
        }
    ],
    "sg:phone":"+1 248 583 2669",
    "sg:postcode":"48071",
    "sg:province":"MI",
    "wof:name":"Mobil",
    "wof:placetype":"venue"
},
  "geometry": {"coordinates":[-83.086432,42.520322],"type":"Point"}
}