{
  "type": "Feature",
  "properties": {
    "iso:country":"US",
    "sg:address":"9180 US Hwy 31",
    "sg:city":"Berrien Springs",
    "sg:classifiers":[
        {
            "category":"Building & Trades",
            "subcategory":"Plumbing",
            "type":"Services"
        }
    ],
    "sg:phone":"+1 269 471 2911",
    "sg:postcode":"49103",
    "sg:province":"MI",
    "sg:tags":[
        "heating",
        "contractor"
    ],
    "wof:name":"Ramzi Heating & Cooling",
    "wof:placetype":"venue"
},
  "geometry": {"coordinates":[-86.357637,41.955581],"type":"Point"}
}