{
  "type": "Feature",
  "properties": {
    "iso:country":"US",
    "sg:address":"8308 Officepark Dr",
    "sg:city":"Grand Blanc",
    "sg:classifiers":[
        {
            "category":"Professional",
            "subcategory":"Secretarial Services",
            "type":"Services"
        }
    ],
    "sg:phone":"+1 810 694 5216",
    "sg:postcode":"48439",
    "sg:province":"MI",
    "sg:tags":[
        "reporting",
        "court"
    ],
    "wof:name":"Your Secretary",
    "wof:placetype":"venue"
},
  "geometry": {"coordinates":[-83.604533,42.907716],"type":"Point"}
}