{
  "type": "Feature",
  "properties": {
    "iso:country":"US",
    "sg:address":"12040 Long Lake Dr",
    "sg:city":"Sparta",
    "sg:classifiers":[
        {
            "category":"Manufacturing",
            "subcategory":"Tools & Machinery",
            "type":"Manufacturing & Wholesale Goods"
        }
    ],
    "sg:phone":"+1 616 887 5246",
    "sg:postcode":"49345",
    "sg:province":"MI",
    "sg:tags":[
        "metalworking",
        "mfg"
    ],
    "wof:name":"Paul Monroe",
    "wof:placetype":"venue"
},
  "geometry": {"coordinates":[-85.680899,43.180086],"type":"Point"}
}