{
  "type": "Feature",
  "properties": {
    "iso:country":"US",
    "sg:address":"564 E Kennett St",
    "sg:city":"Pontiac",
    "sg:classifiers":[
        {
            "category":"Personal",
            "subcategory":"Beauty Salon",
            "type":"Services"
        }
    ],
    "sg:phone":"+1 248 332 6229",
    "sg:postcode":"48340",
    "sg:province":"MI",
    "sg:tags":[
        "shop"
    ],
    "wof:name":"Salon Solutions",
    "wof:placetype":"venue"
},
  "geometry": {"coordinates":[-83.278172,42.658429],"type":"Point"}
}