{
  "type": "Feature",
  "properties": {
    "iso:country":"US",
    "sg:address":"6537 Wendell St SE",
    "sg:city":"Grand Rapids",
    "sg:classifiers":[
        {
            "category":"Professional",
            "subcategory":"Management & Consulting",
            "type":"Services"
        }
    ],
    "sg:phone":"+1 616 942 8794",
    "sg:postcode":"49546",
    "sg:province":"MI",
    "sg:tags":[
        "business"
    ],
    "wof:name":"Chris Hautau Consulting",
    "wof:placetype":"venue"
},
  "geometry": {"coordinates":[-85.509373,42.918704],"type":"Point"}
}