{
  "type": "Feature",
  "properties": {
    "iso:country":"US",
    "sg:address":"835 N Lincoln Rd",
    "sg:city":"Escanaba",
    "sg:classifiers":[
        {
            "category":"Shopping",
            "subcategory":"Jewelry",
            "type":"Retail Goods"
        }
    ],
    "sg:phone":"+1 906 789 1143",
    "sg:postcode":"49829",
    "sg:province":"MI",
    "sg:tags":[
        "jeweler"
    ],
    "sg:website":"www.richardsonjewelers.com",
    "wof:name":"Richardson Jeweler",
    "wof:placetype":"venue"
},
  "geometry": {"coordinates":[-87.077185,45.75676],"type":"Point"}
}