{
  "type": "Feature",
  "properties": {
    "iso:country":"US",
    "sg:address":"5235 N Genesee Rd",
    "sg:city":"Flint",
    "sg:classifiers":[
        {
            "category":"Autos & Motor Vehicles",
            "subcategory":"Auto Supplies",
            "type":"Retail Goods"
        }
    ],
    "sg:phone":"+1 810 736 8460",
    "sg:postcode":"48506",
    "sg:province":"MI",
    "sg:tags":[
        "repair",
        "tire",
        "general"
    ],
    "wof:name":"Bentley Tire & Auto Svc Inc",
    "wof:placetype":"venue"
},
  "geometry": {"coordinates":[-83.61697700000001,43.080831],"type":"Point"}
}