{
  "type": "Feature",
  "properties": {
    "iso:country":"US",
    "sg:address":"5716 Eagle Dr SE",
    "sg:city":"Grand Rapids",
    "sg:classifiers":[
        {
            "category":"Wholesale",
            "subcategory":"Electrical",
            "type":"Manufacturing & Wholesale Goods"
        }
    ],
    "sg:phone":"+1 616 949 9614",
    "sg:postcode":"49512",
    "sg:province":"MI",
    "sg:tags":[
        "fire",
        "equipment",
        "protection"
    ],
    "wof:name":"Allstate Fire Protection",
    "wof:placetype":"venue"
},
  "geometry": {"coordinates":[-85.526764,42.900701],"type":"Point"}
}