{
  "type": "Feature",
  "properties": {
    "iso:country":"US",
    "sg:address":"1495 Center Ave",
    "sg:city":"Bay City",
    "sg:classifiers":[
        {
            "category":"Restaurant",
            "type":"Food & Drink"
        }
    ],
    "sg:phone":"+1 989 893 9771",
    "sg:postcode":"48708",
    "sg:province":"MI",
    "wof:name":"Mc Donald's",
    "wof:placetype":"venue"
},
  "geometry": {"coordinates":[-83.875603,43.597215],"type":"Point"}
}