{
  "type": "Feature",
  "properties": {
    "iso:country":"US",
    "sg:address":"2675 General Motors Rd",
    "sg:city":"Milford",
    "sg:classifiers":[
        {
            "category":"Professional",
            "type":"Services"
        },
        {
            "category":"Professional",
            "subcategory":"Art Services",
            "type":"Services"
        }
    ],
    "sg:phone":"+1 248 685 2422",
    "sg:postcode":"48380",
    "sg:province":"MI",
    "sg:tags":[
        "photographer",
        "photography",
        "studio"
    ],
    "sg:website":"www.carlsams.com",
    "wof:name":"Carl R Sams II Photography",
    "wof:placetype":"venue"
},
  "geometry": {"coordinates":[-83.64840599999999,42.578217],"type":"Point"}
}