{
  "type": "Feature",
  "properties": {
    "iso:country":"US",
    "sg:address":"34119 W 12 Mile Rd",
    "sg:city":"Farmington Hills",
    "sg:classifiers":[
        {
            "category":"Professional",
            "subcategory":"Management & Consulting",
            "type":"Services"
        }
    ],
    "sg:phone":"+1 248 553 6400",
    "sg:postcode":"48331",
    "sg:province":"MI",
    "sg:tags":[
        "consultant",
        "business"
    ],
    "wof:name":"Berlin & Assoc LTD",
    "wof:placetype":"venue"
},
  "geometry": {"coordinates":[-83.38554000000001,42.49834],"type":"Point"}
}