{
  "type": "Feature",
  "properties": {
    "iso:country":"US",
    "sg:address":"200 Industrial Dr NE",
    "sg:city":"Rockford",
    "sg:classifiers":[
        {
            "category":"Government",
            "subcategory":"Office",
            "type":"Public Place"
        }
    ],
    "sg:phone":"+1 616 866 6374",
    "sg:postcode":"49341",
    "sg:province":"MI",
    "sg:tags":[
        "village"
    ],
    "wof:name":"Public Services Garage",
    "wof:placetype":"venue"
},
  "geometry": {"coordinates":[-85.55473499999999,43.130905],"type":"Point"}
}