{
  "type": "Feature",
  "properties": {
    "iso:country":"US",
    "sg:address":"44 Forge Rd",
    "sg:city":"Negaunee",
    "sg:classifiers":[
        {
            "category":"Building & Trades",
            "subcategory":"Cleaning & Sanitation",
            "type":"Services"
        }
    ],
    "sg:phone":"+1 906 475 4092",
    "sg:postcode":"49866",
    "sg:province":"MI",
    "sg:tags":[
        "janitor"
    ],
    "wof:name":"North Country Technique Inc",
    "wof:placetype":"venue"
},
  "geometry": {"coordinates":[-87.552029,46.524343],"type":"Point"}
}