{
  "type": "Feature",
  "properties": {
    "iso:country":"US",
    "sg:address":"315 Bronco Way",
    "sg:city":"Lansing",
    "sg:classifiers":[
        {
            "category":"Professional",
            "subcategory":"Management & Consulting",
            "type":"Services"
        }
    ],
    "sg:phone":"+1 517 321 9534",
    "sg:postcode":"48917",
    "sg:province":"MI",
    "sg:tags":[
        "real estate"
    ],
    "wof:name":"Home Trek LLC",
    "wof:placetype":"venue"
},
  "geometry": {"coordinates":[-84.612179,42.73846],"type":"Point"}
}