{
  "type": "Feature",
  "properties": {
    "iso:country":"US",
    "sg:address":"258 S Cedar St",
    "sg:city":"Kalkaska",
    "sg:classifiers":[
        {
            "category":"Shopping",
            "subcategory":"Books",
            "type":"Retail Goods"
        }
    ],
    "sg:phone":"+1 231 258 1340",
    "sg:postcode":"49646",
    "sg:province":"MI",
    "sg:tags":[
        "dealer"
    ],
    "wof:name":"Higher Ground",
    "wof:placetype":"venue"
},
  "geometry": {"coordinates":[-85.176506,44.732863],"type":"Point"}
}