{
  "type": "Feature",
  "properties": {
    "iso:country":"US",
    "sg:address":"7100 Mather St",
    "sg:city":"Waterford",
    "sg:classifiers":[
        {
            "category":"Building & Trades",
            "subcategory":"Landscaping Services",
            "type":"Services"
        }
    ],
    "sg:phone":"+1 248 681 0664",
    "sg:postcode":"48327",
    "sg:province":"MI",
    "wof:name":"Envy Lawn Care LLC",
    "wof:placetype":"venue"
},
  "geometry": {"coordinates":[-83.42773099999999,42.63604],"type":"Point"}
}