{
  "type": "Feature",
  "properties": {
    "iso:country":"US",
    "sg:address":"23093 Commerce Dr",
    "sg:city":"Farmington Hills",
    "sg:classifiers":[
        {
            "category":"Manufacturing",
            "subcategory":"Tools & Machinery",
            "type":"Manufacturing & Wholesale Goods"
        }
    ],
    "sg:phone":"+1 248 478 5115",
    "sg:postcode":"48335",
    "sg:province":"MI",
    "sg:tags":[
        "oven"
    ],
    "wof:name":"Giffin International",
    "wof:placetype":"venue"
},
  "geometry": {"coordinates":[-83.426042,42.460531],"type":"Point"}
}