{
  "type": "Feature",
  "properties": {
    "iso:country":"US",
    "sg:address":"13732 Co Rd 462",
    "sg:city":"Newberry",
    "sg:classifiers":[
        {
            "category":"Farming",
            "subcategory":"Livestock Farm",
            "type":"Manufacturing & Wholesale Goods"
        }
    ],
    "sg:phone":"+1 906 293 8353",
    "sg:postcode":"49868",
    "sg:province":"MI",
    "sg:tags":[
        "beef",
        "feedlot",
        "cattle"
    ],
    "wof:name":"Craig Enterprises",
    "wof:placetype":"venue"
},
  "geometry": {"coordinates":[-85.50049300000001,46.361158],"type":"Point"}
}