{
  "type": "Feature",
  "properties": {
    "iso:country":"US",
    "sg:address":"3027 N Lakeshore Blvd",
    "sg:city":"Marquette",
    "sg:classifiers":[
        {
            "category":"Professional",
            "subcategory":"Management & Consulting",
            "type":"Services"
        }
    ],
    "sg:phone":"+1 906 228 9109",
    "sg:postcode":"49855",
    "sg:province":"MI",
    "sg:tags":[
        "consultant",
        "safety"
    ],
    "wof:name":"4 Safety",
    "wof:placetype":"venue"
},
  "geometry": {"coordinates":[-87.39036400000001,46.580371],"type":"Point"}
}