{
  "type": "Feature",
  "properties": {
    "iso:country":"US",
    "sg:address":"507 N Perry St",
    "sg:city":"Pontiac",
    "sg:classifiers":[
        {
            "category":"Shopping",
            "subcategory":"Discount & Variety Stores",
            "type":"Retail Goods"
        }
    ],
    "sg:phone":"+1 248 745 9303",
    "sg:postcode":"48342",
    "sg:province":"MI",
    "sg:tags":[
        "merchandise",
        "general"
    ],
    "wof:name":"Essex Specialty Products",
    "wof:placetype":"venue"
},
  "geometry": {"coordinates":[-83.28639200000001,42.64876],"type":"Point"}
}