{
  "type": "Feature",
  "properties": {
    "iso:country":"US",
    "sg:address":"1102 S Stephenson Ave",
    "sg:city":"Iron Mountain",
    "sg:classifiers":[
        {
            "category":"Shopping",
            "subcategory":"Books",
            "type":"Retail Goods"
        }
    ],
    "sg:phone":"+1 906 779 1416",
    "sg:postcode":"49801",
    "sg:province":"MI",
    "sg:tags":[
        "dealer"
    ],
    "wof:name":"Book World",
    "wof:placetype":"venue"
},
  "geometry": {"coordinates":[-88.06094,45.812552],"type":"Point"}
}