{
  "type": "Feature",
  "properties": {
    "iso:country":"US",
    "sg:address":"1010 Weber Ct",
    "sg:city":"White Lake",
    "sg:classifiers":[
        {
            "category":"Professional",
            "subcategory":"Management & Consulting",
            "type":"Services"
        }
    ],
    "sg:phone":"+1 248 889 3591",
    "sg:postcode":"48383",
    "sg:province":"MI",
    "sg:tags":[
        "public",
        "relations"
    ],
    "wof:name":"Modern Sports",
    "wof:placetype":"venue"
},
  "geometry": {"coordinates":[-83.53212499999999,42.637388],"type":"Point"}
}