{
  "type": "Feature",
  "properties": {
    "iso:country":"US",
    "sg:address":"28623 Ford Rd",
    "sg:city":"Garden City",
    "sg:classifiers":[
        {
            "category":"Professional",
            "subcategory":"Lawyer & Legal Services",
            "type":"Services"
        }
    ],
    "sg:phone":"+1 734 425 6700",
    "sg:postcode":"48135",
    "sg:province":"MI",
    "wof:name":"Montgomery William E",
    "wof:placetype":"venue"
},
  "geometry": {"coordinates":[-83.31860399999999,42.325901],"type":"Point"}
}