{
  "type": "Feature",
  "properties": {
    "iso:country":"US",
    "sg:address":"1839 4th St",
    "sg:city":"Wyandotte",
    "sg:classifiers":[
        {
            "category":"Building & Trades",
            "subcategory":"Construction",
            "type":"Services"
        }
    ],
    "sg:phone":"+1 734 283 9611",
    "sg:postcode":"48192",
    "sg:province":"MI",
    "sg:tags":[
        "hanging",
        "contractor"
    ],
    "wof:name":"Lamoureux Custom Painting",
    "wof:placetype":"venue"
},
  "geometry": {"coordinates":[-83.15539200000001,42.21437],"type":"Point"}
}