{
  "type": "Feature",
  "properties": {
    "iso:country":"US",
    "sg:address":"7975 Paepke Rd",
    "sg:city":"Howard City",
    "sg:classifiers":[
        {
            "category":"Real Estate",
            "subcategory":"Real Estate Agent",
            "type":"Services"
        }
    ],
    "sg:phone":"+1 231 937 5492",
    "sg:postcode":"49329",
    "sg:province":"MI",
    "wof:name":"Bradfords Appraisal Service",
    "wof:placetype":"venue"
},
  "geometry": {"coordinates":[-85.442851,43.399819],"type":"Point"}
}