{
  "type": "Feature",
  "properties": {
    "iso:country":"US",
    "sg:address":"420 W Vienna St",
    "sg:city":"Clio",
    "sg:classifiers":[
        {
            "category":"Home & Garden",
            "subcategory":"Hardware",
            "type":"Retail Goods"
        }
    ],
    "sg:phone":"+1 810 686 1600",
    "sg:postcode":"48420",
    "sg:province":"MI",
    "wof:name":"Gill-Roy's",
    "wof:placetype":"venue"
},
  "geometry": {"coordinates":[-83.739682,43.177498],"type":"Point"}
}