{
  "type": "Feature",
  "properties": {
    "iso:country":"US",
    "sg:address":"35000 Warren Rd Ste 43",
    "sg:city":"Westland",
    "sg:classifiers":[
        {
            "category":"Shopping",
            "subcategory":"Jewelry",
            "type":"Retail Goods"
        }
    ],
    "sg:phone":"+1 734 266 8461",
    "sg:postcode":"48185",
    "sg:province":"MI",
    "wof:name":"J B Robinson Jewelers",
    "wof:placetype":"venue"
},
  "geometry": {"coordinates":[-83.39124,42.34046],"type":"Point"}
}