{
  "type": "Feature",
  "properties": {
    "iso:country":"US",
    "sg:address":"525 Colfax Ave",
    "sg:city":"Grand Haven",
    "sg:classifiers":[
        {
            "category":"Real Estate",
            "subcategory":"Real Estate Agent",
            "type":"Services"
        }
    ],
    "sg:phone":"+1 616 842 5855",
    "sg:postcode":"49417",
    "sg:province":"MI",
    "sg:tags":[
        "inspection"
    ],
    "wof:name":"Brick Kicker",
    "wof:placetype":"venue"
},
  "geometry": {"coordinates":[-86.225982,43.056242],"type":"Point"}
}