{
  "type": "Feature",
  "properties": {
    "iso:country":"US",
    "sg:address":"901 Airport Access Rd",
    "sg:city":"Traverse City",
    "sg:classifiers":[
        {
            "category":"Government",
            "subcategory":"Office",
            "type":"Public Place"
        }
    ],
    "sg:phone":"+1 231 946 6756",
    "sg:postcode":"49686",
    "sg:province":"MI",
    "sg:tags":[
        "federal",
        "security"
    ],
    "wof:name":"US Army Reserve Ctr",
    "wof:placetype":"venue"
},
  "geometry": {"coordinates":[-85.58225899999999,44.750448],"type":"Point"}
}