{
  "type": "Feature",
  "properties": {
    "iso:country":"US",
    "sg:address":"3120 Flushing Rd",
    "sg:city":"Flint",
    "sg:classifiers":[
        {
            "category":"Restaurant",
            "type":"Food & Drink"
        }
    ],
    "sg:phone":"+1 810 766 8841",
    "sg:postcode":"48504",
    "sg:province":"MI",
    "wof:name":"Big Al's Jumbo Shrimp Hut",
    "wof:placetype":"venue"
},
  "geometry": {"coordinates":[-83.73668600000001,43.025916],"type":"Point"}
}