{
  "type": "Feature",
  "properties": {
    "iso:country":"US",
    "sg:address":"2100 E M 21",
    "sg:city":"Owosso",
    "sg:classifiers":[
        {
            "category":"Real Estate",
            "subcategory":"Real Estate Agent",
            "type":"Services"
        }
    ],
    "sg:phone":"+1 989 725 2914",
    "sg:postcode":"48867",
    "sg:province":"MI",
    "wof:name":"Ackels Realty Firm",
    "wof:placetype":"venue"
},
  "geometry": {"coordinates":[-84.12497500000001,42.998217],"type":"Point"}
}