{
  "type": "Feature",
  "properties": {
    "iso:country":"US",
    "sg:address":"1103 4th Ave",
    "sg:city":"Lake Odessa",
    "sg:classifiers":[
        {
            "category":"Farming",
            "subcategory":"Farm & Veterinary Services",
            "type":"Manufacturing & Wholesale Goods"
        }
    ],
    "sg:phone":"+1 616 374 3202",
    "sg:postcode":"48849",
    "sg:province":"MI",
    "sg:tags":[
        "management"
    ],
    "wof:name":"Smith Brothers",
    "wof:placetype":"venue"
},
  "geometry": {"coordinates":[-85.138246,42.78398],"type":"Point"}
}