{
  "type": "Feature",
  "properties": {
    "iso:country":"US",
    "sg:address":"5337 Scofield Carleton Rd",
    "sg:city":"Carleton",
    "sg:classifiers":[
        {
            "category":"Wholesale",
            "subcategory":"Metals & Minerals",
            "type":"Manufacturing & Wholesale Goods"
        }
    ],
    "sg:phone":"+1 734 587 3200",
    "sg:postcode":"48117",
    "sg:province":"MI",
    "sg:tags":[
        "consulting",
        "management",
        "center"
    ],
    "wof:name":"Steel Quality Service Inc",
    "wof:placetype":"venue"
},
  "geometry": {"coordinates":[-83.46302799999999,42.043684],"type":"Point"}
}