{
  "type": "Feature",
  "properties": {
    "iso:country":"US",
    "sg:address":"394 Eric Ave",
    "sg:city":"Muskegon",
    "sg:classifiers":[
        {
            "category":"Organizations",
            "subcategory":"Religious Organization",
            "type":"Services"
        }
    ],
    "sg:phone":"+1 231 733 1512",
    "sg:postcode":"49444",
    "sg:province":"MI",
    "wof:name":"Michigan Circuit 9",
    "wof:placetype":"venue"
},
  "geometry": {"coordinates":[-86.254469,43.189935],"type":"Point"}
}