{
  "type": "Feature",
  "properties": {
    "iso:country":"US",
    "sg:address":"409 W Ann Arbor Trl",
    "sg:city":"Plymouth",
    "sg:classifiers":[
        {
            "category":"Building & Trades",
            "subcategory":"Construction",
            "type":"Services"
        }
    ],
    "sg:phone":"+1 734 416 4241",
    "sg:postcode":"48170",
    "sg:province":"MI",
    "sg:tags":[
        "painter"
    ],
    "wof:name":"Royal Painting & Contracting",
    "wof:placetype":"venue"
},
  "geometry": {"coordinates":[-83.46520200000001,42.368999],"type":"Point"}
}