{
  "type": "Feature",
  "properties": {
    "iso:country":"US",
    "sg:address":"1241 Woodridge St",
    "sg:city":"Muskegon",
    "sg:classifiers":[
        {
            "category":"Building & Trades",
            "subcategory":"Construction",
            "type":"Services"
        }
    ],
    "sg:phone":"+1 231 788 4651",
    "sg:postcode":"49442",
    "sg:province":"MI",
    "sg:tags":[
        "general",
        "contractor"
    ],
    "wof:name":"Danny R Clarke II",
    "wof:placetype":"venue"
},
  "geometry": {"coordinates":[-86.101472,43.233919],"type":"Point"}
}