{
  "type": "Feature",
  "properties": {
    "iso:country":"US",
    "sg:address":"17219 Annchester Rd",
    "sg:city":"Detroit",
    "sg:classifiers":[
        {
            "category":"Social Services",
            "subcategory":"Child Care",
            "type":"Services"
        }
    ],
    "sg:phone":"+1 313 534 0569",
    "sg:postcode":"48219",
    "sg:province":"MI",
    "sg:tags":[
        "day"
    ],
    "wof:name":"Dianes Montessori Chld Ctr",
    "wof:placetype":"venue"
},
  "geometry": {"coordinates":[-83.235085,42.416152],"type":"Point"}
}