{
  "type": "Feature",
  "properties": {
    "iso:country":"US",
    "sg:address":"6879 Beech Creek Dr",
    "sg:city":"Fruitport",
    "sg:classifiers":[
        {
            "category":"Wholesale",
            "subcategory":"Machinery & Supplies",
            "type":"Manufacturing & Wholesale Goods"
        },
        {
            "category":"Professional",
            "subcategory":"Computer Services",
            "type":"Services"
        }
    ],
    "sg:phone":"+1 231 865 7550",
    "sg:postcode":"49415",
    "sg:province":"MI",
    "sg:tags":[
        "machine",
        "consultant",
        "tool",
        "technology"
    ],
    "wof:name":"V A Technologies Inc",
    "wof:placetype":"venue"
},
  "geometry": {"coordinates":[-86.183244,43.131997],"type":"Point"}
}