{
  "type": "Feature",
  "properties": {
    "iso:country":"US",
    "sg:address":"1496 Manitou Ln",
    "sg:city":"Middleville",
    "sg:classifiers":[
        {
            "category":"Professional",
            "subcategory":"Management & Consulting",
            "type":"Services"
        }
    ],
    "sg:phone":"+1 616 233 3291",
    "sg:postcode":"49333",
    "sg:province":"MI",
    "wof:name":"Polarity Management Assoc",
    "wof:placetype":"venue"
},
  "geometry": {"coordinates":[-85.51590899999999,42.671866],"type":"Point"}
}