{
  "type": "Feature",
  "properties": {
    "iso:country":"US",
    "sg:address":"4125 Dove Rd",
    "sg:city":"Port Huron",
    "sg:classifiers":[
        {
            "category":"Shopping",
            "type":"Retail Goods"
        }
    ],
    "sg:phone":"+1 810 388 0306",
    "sg:postcode":"48060",
    "sg:province":"MI",
    "sg:tags":[
        "merchandise"
    ],
    "wof:name":"Custome Car Accessories",
    "wof:placetype":"venue"
},
  "geometry": {"coordinates":[-82.48703,42.95088],"type":"Point"}
}