{
  "type": "Feature",
  "properties": {
    "iso:country":"US",
    "sg:address":"11926 Waycross St",
    "sg:city":"Brighton",
    "sg:classifiers":[
        {
            "category":"Freight",
            "type":"Transportation"
        }
    ],
    "sg:phone":"+1 810 225 0429",
    "sg:postcode":"48114",
    "sg:province":"MI",
    "sg:tags":[
        "trucking"
    ],
    "wof:name":"Hartland Transport",
    "wof:placetype":"venue"
},
  "geometry": {"coordinates":[-83.713184,42.559353],"type":"Point"}
}