{
  "type": "Feature",
  "properties": {
    "iso:country":"US",
    "sg:address":"2058 Fawnwood Way",
    "sg:city":"Bloomfield Hills",
    "sg:classifiers":[
        {
            "category":"Professional",
            "subcategory":"Management & Consulting",
            "type":"Services"
        }
    ],
    "sg:phone":"+1 248 737 8686",
    "sg:postcode":"48302",
    "sg:province":"MI",
    "wof:name":"Omega Marketing",
    "wof:placetype":"venue"
},
  "geometry": {"coordinates":[-83.324262,42.570055],"type":"Point"}
}