{
  "type": "Feature",
  "properties": {
    "iso:country":"US",
    "sg:address":"5212 S Martin Luther King Jr Blvd",
    "sg:city":"Lansing",
    "sg:classifiers":[
        {
            "category":"Personal",
            "subcategory":"Beauty Salon",
            "type":"Services"
        }
    ],
    "sg:phone":"+1 517 394 6591",
    "sg:postcode":"48911",
    "sg:province":"MI",
    "wof:name":"Pretty Nails",
    "wof:placetype":"venue"
},
  "geometry": {"coordinates":[-84.568935,42.681899],"type":"Point"}
}