{
  "type": "Feature",
  "properties": {
    "iso:country":"US",
    "sg:address":"17331 E Warren Ave",
    "sg:city":"Detroit",
    "sg:classifiers":[
        {
            "category":"Social Services",
            "subcategory":"Child Care",
            "type":"Services"
        }
    ],
    "sg:phone":"+1 313 423 0334",
    "sg:postcode":"48224",
    "sg:province":"MI",
    "sg:tags":[
        "day"
    ],
    "wof:name":"Dotties Daycare and Learning Center",
    "wof:placetype":"venue"
},
  "geometry": {"coordinates":[-82.9268,42.407326],"type":"Point"}
}