{
  "type": "Feature",
  "properties": {
    "iso:country":"US",
    "sg:address":"5023 W Main St",
    "sg:city":"Kalamazoo",
    "sg:classifiers":[
        {
            "category":"Banks & Credit Unions",
            "subcategory":"Bank",
            "type":"Services"
        }
    ],
    "sg:phone":"+1 269 342 2115",
    "sg:postcode":"49009",
    "sg:province":"MI",
    "sg:tags":[
        "financing"
    ],
    "wof:name":"Citi Financial",
    "wof:placetype":"venue"
},
  "geometry": {"coordinates":[-85.648703,42.29621],"type":"Point"}
}