{
  "type": "Feature",
  "properties": {
    "iso:country":"US",
    "sg:address":"1579 Edgewater St",
    "sg:city":"Muskegon",
    "sg:classifiers":[
        {
            "category":"Banks & Credit Unions",
            "subcategory":"Financial Services",
            "type":"Services"
        }
    ],
    "sg:phone":"+1 231 759 6119",
    "sg:postcode":"49441",
    "sg:province":"MI",
    "sg:tags":[
        "fund",
        "investment"
    ],
    "wof:name":"DAlcorn Family Ltd Partnr",
    "wof:placetype":"venue"
},
  "geometry": {"coordinates":[-86.322445,43.22523],"type":"Point"}
}