{
  "type": "Feature",
  "properties": {
    "iso:country":"US",
    "sg:address":"17200 W 10 Mile Rd",
    "sg:city":"Southfield",
    "sg:classifiers":[
        {
            "category":"Real Estate",
            "subcategory":"Real Estate Services",
            "type":"Services"
        }
    ],
    "sg:phone":"+1 248 557 0303",
    "sg:postcode":"48075",
    "sg:province":"MI",
    "wof:name":"Sheldon Alkon Real Estate",
    "wof:placetype":"venue"
},
  "geometry": {"coordinates":[-83.21410400000001,42.473701],"type":"Point"}
}