{
  "type": "Feature",
  "properties": {
    "iso:country":"US",
    "sg:address":"1515 Cedar St",
    "sg:city":"Port Huron",
    "sg:classifiers":[
        {
            "category":"Home & Garden",
            "subcategory":"Building Materials",
            "type":"Retail Goods"
        },
        {
            "category":"Retail",
            "subcategory":"Auto Repair",
            "type":"Services"
        }
    ],
    "sg:phone":"+1 810 966 1017",
    "sg:postcode":"48060",
    "sg:province":"MI",
    "sg:tags":[
        "glass",
        "window",
        "plate",
        "replacement"
    ],
    "wof:name":"G & G Auto Glass",
    "wof:placetype":"venue"
},
  "geometry": {"coordinates":[-82.440355,42.961457],"type":"Point"}
}