{
  "type": "Feature",
  "properties": {
    "iso:country":"US",
    "sg:address":"4657 18th St",
    "sg:city":"Wyandotte",
    "sg:classifiers":[
        {
            "category":"Shopping",
            "subcategory":"Bicycles & Sporting Goods",
            "type":"Retail Goods"
        }
    ],
    "sg:phone":"+1 734 281 1018",
    "sg:postcode":"48192",
    "sg:province":"MI",
    "wof:name":"All About Hockey",
    "wof:placetype":"venue"
},
  "geometry": {"coordinates":[-83.17341500000001,42.185622],"type":"Point"}
}