{
  "type": "Feature",
  "properties": {
    "iso:country":"US",
    "sg:address":"1099 W Grand River Ave",
    "sg:city":"Williamston",
    "sg:classifiers":[
        {
            "category":"Wholesale",
            "subcategory":"Durable Goods & Equipment",
            "type":"Manufacturing & Wholesale Goods"
        }
    ],
    "sg:phone":"+1 517 655 5616",
    "sg:postcode":"48895",
    "sg:province":"MI",
    "sg:tags":[
        "geophysical",
        "apparatus"
    ],
    "wof:name":"Geo Tech Environmental Equipme",
    "wof:placetype":"venue"
},
  "geometry": {"coordinates":[-84.296053,42.687757],"type":"Point"}
}