{
  "type": "Feature",
  "properties": {
    "iso:country":"US",
    "sg:address":"124 S Stewart Ave",
    "sg:city":"Fremont",
    "sg:classifiers":[
        {
            "category":"Personal",
            "subcategory":"Shoe Repair & Shine",
            "type":"Services"
        }
    ],
    "sg:phone":"+1 231 924 0190",
    "sg:postcode":"49412",
    "sg:province":"MI",
    "sg:tags":[
        "parlor"
    ],
    "wof:name":"Fremont Shoe Repair",
    "wof:placetype":"venue"
},
  "geometry": {"coordinates":[-85.93992299999999,43.46599],"type":"Point"}
}