{
  "type": "Feature",
  "properties": {
    "iso:country":"US",
    "sg:address":"20315 Van Antwerp St",
    "sg:city":"Harper Woods",
    "sg:classifiers":[
        {
            "category":"Social Services",
            "subcategory":"Child Care",
            "type":"Services"
        }
    ],
    "sg:phone":"+1 313 884 6968",
    "sg:postcode":"48225",
    "sg:province":"MI",
    "sg:tags":[
        "day"
    ],
    "wof:name":"Terry Lynn Coughlin",
    "wof:placetype":"venue"
},
  "geometry": {"coordinates":[-82.92247,42.446403],"type":"Point"}
}