{
  "type": "Feature",
  "properties": {
    "iso:country":"US",
    "sg:address":"280 Brighton Rd",
    "sg:city":"Howell",
    "sg:classifiers":[
        {
            "category":"Wholesale",
            "subcategory":"Construction Materials",
            "type":"Manufacturing & Wholesale Goods"
        }
    ],
    "sg:phone":"+1 517 548 4703",
    "sg:postcode":"48843",
    "sg:province":"MI",
    "sg:tags":[
        "marble"
    ],
    "wof:name":"Marblecraft",
    "wof:placetype":"venue"
},
  "geometry": {"coordinates":[-83.931724,42.528206],"type":"Point"}
}