{
  "type": "Feature",
  "properties": {
    "iso:country":"US",
    "sg:address":"9840 S Hamburg Rd",
    "sg:city":"Whitmore Lake",
    "sg:classifiers":[
        {
            "category":"Professional",
            "subcategory":"Management & Consulting",
            "type":"Services"
        }
    ],
    "sg:phone":"+1 734 449 2010",
    "sg:postcode":"48189",
    "sg:province":"MI",
    "wof:name":"Adr Limited",
    "wof:placetype":"venue"
},
  "geometry": {"coordinates":[-83.796038,42.42155],"type":"Point"}
}