{
  "type": "Feature",
  "properties": {
    "iso:country":"US",
    "sg:address":"2270 S Smith Crossing Rd",
    "sg:city":"Midland",
    "sg:classifiers":[
        {
            "category":"Recreation",
            "type":"Entertainment"
        }
    ],
    "sg:phone":"+1 989 832 5780",
    "sg:postcode":"48640",
    "sg:province":"MI",
    "sg:tags":[
        "parachute",
        "skydiving",
        "jumping"
    ],
    "sg:website":"www.wildwindskydivers.com",
    "wof:name":"Wild Wind Skydivers",
    "wof:placetype":"venue"
},
  "geometry": {"coordinates":[-84.18919099999999,43.546578],"type":"Point"}
}