{
  "type": "Feature",
  "properties": {
    "iso:country":"US",
    "sg:address":"1690 Airport Rd",
    "sg:city":"Waterford",
    "sg:classifiers":[
        {
            "category":"Organizations",
            "subcategory":"Community Association",
            "type":"Services"
        }
    ],
    "sg:phone":"+1 248 674 2826",
    "sg:postcode":"48327",
    "sg:province":"MI",
    "wof:name":"Heart of Lakes VFW 1008",
    "wof:placetype":"venue"
},
  "geometry": {"coordinates":[-83.4059,42.659989],"type":"Point"}
}