{
  "type": "Feature",
  "properties": {
    "iso:country":"US",
    "sg:address":"9501 Iris St",
    "sg:city":"Detroit",
    "sg:classifiers":[
        {
            "category":"Real Estate",
            "subcategory":"Real Estate Services",
            "type":"Services"
        },
        {
            "category":"Real Estate",
            "subcategory":"Real Estate Operator",
            "type":"Services"
        }
    ],
    "sg:phone":"+1 313 935 9197",
    "sg:postcode":"48227",
    "sg:province":"MI",
    "sg:tags":[
        "apartment",
        "property",
        "management"
    ],
    "wof:name":"Thornton Apartments",
    "wof:placetype":"venue"
},
  "geometry": {"coordinates":[-83.1698,42.366001],"type":"Point"}
}