{
  "type": "Feature",
  "properties": {
    "iso:country":"US",
    "sg:address":"21914 Letour St",
    "sg:city":"Romulus",
    "sg:classifiers":[
        {
            "category":"Building & Trades",
            "subcategory":"Construction",
            "type":"Services"
        }
    ],
    "sg:phone":"+1 734 783 8687",
    "sg:postcode":"48174",
    "sg:province":"MI",
    "sg:tags":[
        "house"
    ],
    "wof:name":"Hankins Construction Co",
    "wof:placetype":"venue"
},
  "geometry": {"coordinates":[-83.30919799999999,42.146341],"type":"Point"}
}