{
  "type": "Feature",
  "properties": {
    "iso:country":"US",
    "sg:address":"4441 E Maple Ave",
    "sg:city":"Grand Blanc",
    "sg:classifiers":[
        {
            "category":"Social Services",
            "subcategory":"Job Training",
            "type":"Services"
        }
    ],
    "sg:phone":"+1 810 743 2712",
    "sg:postcode":"48439",
    "sg:province":"MI",
    "sg:tags":[
        "consulting",
        "business"
    ],
    "wof:name":"Brown Resources Inc",
    "wof:placetype":"venue"
},
  "geometry": {"coordinates":[-83.61514200000001,42.9609],"type":"Point"}
}