{
  "type": "Feature",
  "properties": {
    "iso:country":"US",
    "sg:address":"1222 E Maumee St",
    "sg:city":"Adrian",
    "sg:classifiers":[
        {
            "category":"Autos & Motor Vehicles",
            "subcategory":"Auto Supplies",
            "type":"Retail Goods"
        }
    ],
    "sg:phone":"+1 517 263 2128",
    "sg:postcode":"49221",
    "sg:province":"MI",
    "sg:tags":[
        "tire"
    ],
    "wof:name":"Lenawee Tire & Supply Co",
    "wof:placetype":"venue"
},
  "geometry": {"coordinates":[-84.018669,41.896903],"type":"Point"}
}