{
  "type": "Feature",
  "properties": {
    "iso:country":"US",
    "sg:address":"213 E Cloverland Dr",
    "sg:city":"Ironwood",
    "sg:classifiers":[
        {
            "category":"Sports & Exercise",
            "subcategory":"Bowling",
            "type":"Entertainment"
        }
    ],
    "sg:phone":"+1 906 932 4132",
    "sg:postcode":"49938",
    "sg:province":"MI",
    "sg:tags":[
        "tavern",
        "alley"
    ],
    "wof:name":"Ironwood Sport Bowl Inc",
    "wof:placetype":"venue"
},
  "geometry": {"coordinates":[-90.169252,46.463159],"type":"Point"}
}