{
  "type": "Feature",
  "properties": {
    "iso:country":"US",
    "sg:address":"4111 Munson Hwy",
    "sg:city":"Hudson",
    "sg:classifiers":[
        {
            "category":"Manufacturing",
            "subcategory":"Metals",
            "type":"Manufacturing & Wholesale Goods"
        }
    ],
    "sg:phone":"+1 517 448 8954",
    "sg:postcode":"49247",
    "sg:province":"MI",
    "sg:tags":[
        "stamping"
    ],
    "wof:name":"Kecy Products Inc",
    "wof:placetype":"venue"
},
  "geometry": {"coordinates":[-84.33402,41.853757],"type":"Point"}
}