{
  "type": "Feature",
  "properties": {
    "iso:country":"US",
    "sg:address":"8712 Studebaker Ave",
    "sg:city":"Warren",
    "sg:classifiers":[
        {
            "category":"Building & Trades",
            "subcategory":"Construction",
            "type":"Services"
        }
    ],
    "sg:phone":"+1 586 855 2003",
    "sg:postcode":"48089",
    "sg:province":"MI",
    "sg:tags":[
        "home",
        "improvement"
    ],
    "wof:name":"Harvey's Home Improvement",
    "wof:placetype":"venue"
},
  "geometry": {"coordinates":[-83.015553,42.457378],"type":"Point"}
}