{
  "type": "Feature",
  "properties": {
    "iso:country":"US",
    "sg:address":"2536 Detroit Rd",
    "sg:city":"Niles",
    "sg:classifiers":[
        {
            "category":"Manufacturing",
            "subcategory":"Food",
            "type":"Manufacturing & Wholesale Goods"
        }
    ],
    "sg:phone":"+1 269 687 8983",
    "sg:postcode":"49120",
    "sg:province":"MI",
    "sg:tags":[
        "product",
        "manufacturer"
    ],
    "wof:name":"MPM Systems",
    "wof:placetype":"venue"
},
  "geometry": {"coordinates":[-86.19184300000001,41.828745],"type":"Point"}
}