{
  "type": "Feature",
  "properties": {
    "iso:country":"US",
    "sg:address":"34101 Jefferson Ave",
    "sg:city":"St Clair Shores",
    "sg:classifiers":[
        {
            "category":"Retail",
            "subcategory":"Repair Shop",
            "type":"Services"
        },
        {
            "category":"Manufacturing",
            "subcategory":"Printing",
            "type":"Manufacturing & Wholesale Goods"
        }
    ],
    "sg:phone":"+1 586 293 5454",
    "sg:postcode":"48082",
    "sg:province":"MI",
    "sg:tags":[
        "printer"
    ],
    "wof:name":"Jacob Printing Co",
    "wof:placetype":"venue"
},
  "geometry": {"coordinates":[-82.863051,42.539181],"type":"Point"}
}