{
  "type": "Feature",
  "properties": {
    "iso:country":"US",
    "sg:address":"3383 S Linden Rd",
    "sg:city":"Flint",
    "sg:classifiers":[
        {
            "category":"Restaurant",
            "type":"Food & Drink"
        }
    ],
    "sg:menulink":"http://www.allmenus.com/mi/flint/208669-taco-bell/menu/",
    "sg:phone":"+1 810 733 8560",
    "sg:postcode":"48507",
    "sg:province":"MI",
    "sg:tags":[
        "mexican"
    ],
    "wof:name":"Taco Bell",
    "wof:placetype":"venue"
},
  "geometry": {"coordinates":[-83.77201700000001,42.97742],"type":"Point"}
}