{
  "type": "Feature",
  "properties": {
    "iso:country":"US",
    "sg:address":"6350 Wall St",
    "sg:city":"Sterling Heights",
    "sg:classifiers":[
        {
            "category":"Shopping",
            "type":"Retail Goods"
        }
    ],
    "sg:phone":"+1 586 264 5550",
    "sg:postcode":"48312",
    "sg:province":"MI",
    "sg:tags":[
        "plastic"
    ],
    "wof:name":"Norton Performance Plastics",
    "wof:placetype":"venue"
},
  "geometry": {"coordinates":[-83.042863,42.570555],"type":"Point"}
}