{
  "type": "Feature",
  "properties": {
    "iso:country":"US",
    "sg:address":"41105 Capital",
    "sg:city":"Canton",
    "sg:classifiers":[
        {
            "category":"Building & Trades",
            "subcategory":"Construction",
            "type":"Services"
        }
    ],
    "sg:phone":"+1 734 459 6320",
    "sg:postcode":"48187",
    "sg:province":"MI",
    "sg:tags":[
        "bl",
        "engineering",
        "nonresidential",
        "mfg"
    ],
    "wof:name":"Clean Air Technology Inc",
    "wof:placetype":"venue"
},
  "geometry": {"coordinates":[-83.447114,42.342965],"type":"Point"}
}