{
  "type": "Feature",
  "properties": {
    "iso:country":"US",
    "sg:address":"1460 Walton Blvd",
    "sg:city":"Rochester Hills",
    "sg:classifiers":[
        {
            "category":"Professional",
            "subcategory":"Lawyer & Legal Services",
            "type":"Services"
        }
    ],
    "sg:phone":"+1 248 608 2700",
    "sg:postcode":"48309",
    "sg:province":"MI",
    "sg:tags":[
        "attorney"
    ],
    "wof:name":"Randall J Solomon Law Office",
    "wof:placetype":"venue"
},
  "geometry": {"coordinates":[-83.15428,42.68169],"type":"Point"}
}