{
  "type": "Feature",
  "properties": {
    "iso:country":"US",
    "sg:address":"5930 Ivan Rd",
    "sg:city":"Saranac",
    "sg:classifiers":[
        {
            "category":"Building & Trades",
            "subcategory":"Construction",
            "type":"Services"
        }
    ],
    "sg:phone":"+1 616 642 6414",
    "sg:postcode":"48881",
    "sg:province":"MI",
    "sg:tags":[
        "restoration",
        "cleaning",
        "patio",
        "deck"
    ],
    "wof:name":"Castlerock Mobile Wash",
    "wof:placetype":"venue"
},
  "geometry": {"coordinates":[-85.25282900000001,42.901593],"type":"Point"}
}