{
  "type": "Feature",
  "properties": {
    "iso:country":"US",
    "sg:address":"1000 Sainte Anne St",
    "sg:city":"Detroit",
    "sg:classifiers":[
        {
            "category":"Organizations",
            "subcategory":"Religious Organization",
            "type":"Services"
        }
    ],
    "sg:phone":"+1 313 496 1701",
    "sg:postcode":"48216",
    "sg:province":"MI",
    "sg:tags":[
        "catholic",
        "church"
    ],
    "wof:name":"Ste Anne Church",
    "wof:placetype":"venue"
},
  "geometry": {"coordinates":[-83.07721600000001,42.320924],"type":"Point"}
}