{
  "type": "Feature",
  "properties": {
    "iso:country":"US",
    "sg:address":"8501 180th Ave",
    "sg:city":"Reed City",
    "sg:classifiers":[
        {
            "category":"Organizations",
            "subcategory":"Religious Organization",
            "type":"Services"
        }
    ],
    "sg:phone":"+1 231 832 3916",
    "sg:postcode":"49677",
    "sg:province":"MI",
    "wof:name":"Pentecostal Church of God",
    "wof:placetype":"venue"
},
  "geometry": {"coordinates":[-85.443026,43.934001],"type":"Point"}
}