{
  "type": "Feature",
  "properties": {
    "iso:country":"US",
    "sg:address":"130 Ionia Ave SW",
    "sg:city":"Grand Rapids",
    "sg:classifiers":[
        {
            "category":"Home & Garden",
            "subcategory":"Furniture",
            "type":"Retail Goods"
        }
    ],
    "sg:phone":"+1 616 988 3333",
    "sg:postcode":"49503",
    "sg:province":"MI",
    "wof:name":"Eq3",
    "wof:placetype":"venue"
},
  "geometry": {"coordinates":[-85.670095,42.960076],"type":"Point"}
}