{
  "type": "Feature",
  "properties": {
    "iso:country":"US",
    "sg:address":"4791 Baldwin St",
    "sg:city":"Onondaga",
    "sg:classifiers":[
        {
            "category":"Building & Trades",
            "subcategory":"Construction",
            "type":"Services"
        }
    ],
    "sg:phone":"+1 517 628 3029",
    "sg:postcode":"49264",
    "sg:province":"MI",
    "sg:tags":[
        "contractor"
    ],
    "wof:name":"Gw Drywall",
    "wof:placetype":"venue"
},
  "geometry": {"coordinates":[-84.561607,42.443375],"type":"Point"}
}