{
  "type": "Feature",
  "properties": {
    "iso:country":"US",
    "sg:address":"64 Pine Ave",
    "sg:city":"Holland",
    "sg:classifiers":[
        {
            "category":"Government",
            "subcategory":"Office",
            "type":"Public Place"
        }
    ],
    "sg:phone":"+1 616 355 1200",
    "sg:postcode":"49423",
    "sg:province":"MI",
    "sg:tags":[
        "village"
    ],
    "wof:name":"James De Young Power Station",
    "wof:placetype":"venue"
},
  "geometry": {"coordinates":[-86.11214099999999,42.796757],"type":"Point"}
}