{
  "type": "Feature",
  "properties": {
    "iso:country":"US",
    "sg:address":"46733 Van Dyke Ave",
    "sg:city":"Shelby Twp",
    "sg:classifiers":[
        {
            "category":"Shopping",
            "type":"Retail Goods"
        }
    ],
    "sg:phone":"+1 586 323 4660",
    "sg:postcode":"48317",
    "sg:province":"MI",
    "sg:tags":[
        "pet",
        "shop"
    ],
    "wof:name":"Pets & Things",
    "wof:placetype":"venue"
},
  "geometry": {"coordinates":[-83.032988,42.63948],"type":"Point"}
}