{
  "type": "Feature",
  "properties": {
    "iso:country":"US",
    "sg:address":"1064 State Hwy 32",
    "sg:city":"Alpena",
    "sg:classifiers":[
        {
            "category":"Shopping",
            "subcategory":"Stationery & Office Supplies",
            "type":"Retail Goods"
        }
    ],
    "sg:phone":"+1 989 358 0310",
    "sg:postcode":"49707",
    "sg:province":"MI",
    "wof:name":"Staples The Office Superstore",
    "wof:placetype":"venue"
},
  "geometry": {"coordinates":[-83.472324,45.061756],"type":"Point"}
}