{
  "type": "Feature",
  "properties": {
    "iso:country":"US",
    "sg:address":"2522 Niles Ave",
    "sg:city":"Saint Joseph",
    "sg:classifiers":[
        {
            "category":"Health Services",
            "subcategory":"Doctor",
            "type":"Services"
        }
    ],
    "sg:phone":"+1 269 983 0571",
    "sg:postcode":"49085",
    "sg:province":"MI",
    "sg:tags":[
        "medical"
    ],
    "wof:name":"Andries Kathleen M MD",
    "wof:placetype":"venue"
},
  "geometry": {"coordinates":[-86.485426,42.089094],"type":"Point"}
}