{
  "type": "Feature",
  "properties": {
    "iso:country":"US",
    "sg:address":"111 State St",
    "sg:city":"Charlevoix",
    "sg:classifiers":[
        {
            "category":"Professional",
            "subcategory":"Lawyer & Legal Services",
            "type":"Services"
        }
    ],
    "sg:phone":"+1 231 547 4059",
    "sg:postcode":"49720",
    "sg:province":"MI",
    "sg:tags":[
        "attorney"
    ],
    "wof:name":"Scott T Beatty",
    "wof:placetype":"venue"
},
  "geometry": {"coordinates":[-85.260749,45.317992],"type":"Point"}
}