{
  "type": "Feature",
  "properties": {
    "iso:country":"US",
    "sg:address":"9178 Clark Rd",
    "sg:city":"Grand Ledge",
    "sg:classifiers":[
        {
            "category":"Personal",
            "type":"Services"
        }
    ],
    "sg:phone":"+1 517 626 2140",
    "sg:postcode":"48837",
    "sg:province":"MI",
    "wof:name":"A To Z Building Maint LLC",
    "wof:placetype":"venue"
},
  "geometry": {"coordinates":[-84.715457,42.813452],"type":"Point"}
}