{
  "type": "Feature",
  "properties": {
    "iso:country":"US",
    "sg:address":"592 Catalpa Dr",
    "sg:city":"Birmingham",
    "sg:classifiers":[
        {
            "category":"Wholesale",
            "subcategory":"Office Equipment",
            "type":"Manufacturing & Wholesale Goods"
        }
    ],
    "sg:phone":"+1 248 433 1712",
    "sg:postcode":"48009",
    "sg:province":"MI",
    "sg:tags":[
        "scanning",
        "code",
        "bar"
    ],
    "wof:name":"Intermec Technologies Corp",
    "wof:placetype":"venue"
},
  "geometry": {"coordinates":[-83.211179,42.535383],"type":"Point"}
}