{
  "type": "Feature",
  "properties": {
    "iso:country":"US",
    "sg:address":"45511 Warren Rd",
    "sg:city":"Canton",
    "sg:classifiers":[
        {
            "category":"Retail",
            "subcategory":"Auto Repair",
            "type":"Services"
        }
    ],
    "sg:phone":"+1 734 453 7959",
    "sg:postcode":"48187",
    "sg:province":"MI",
    "sg:tags":[
        "general"
    ],
    "wof:name":"Panko Saa Service",
    "wof:placetype":"venue"
},
  "geometry": {"coordinates":[-83.49291700000001,42.336385],"type":"Point"}
}