{
  "type": "Feature",
  "properties": {
    "iso:country":"US",
    "sg:address":"36291 S Gratiot Ave",
    "sg:city":"Clinton Township",
    "sg:classifiers":[
        {
            "category":"Autos & Motor Vehicles",
            "subcategory":"Fuel & Gas Station",
            "type":"Retail Goods"
        }
    ],
    "sg:phone":"+1 586 791 3599",
    "sg:postcode":"48035",
    "sg:province":"MI",
    "wof:name":"Abboud Incorporation",
    "wof:placetype":"venue"
},
  "geometry": {"coordinates":[-82.894764,42.564555],"type":"Point"}
}