{
  "type": "Feature",
  "properties": {
    "iso:country":"US",
    "sg:address":"581 Brakel Point Dr",
    "sg:city":"Traverse City",
    "sg:classifiers":[
        {
            "category":"Building & Trades",
            "subcategory":"Construction",
            "type":"Services"
        }
    ],
    "sg:phone":"+1 231 943 9570",
    "sg:postcode":"49684",
    "sg:province":"MI",
    "sg:tags":[
        "painter"
    ],
    "wof:name":"Conrady's Paint",
    "wof:placetype":"venue"
},
  "geometry": {"coordinates":[-85.675128,44.677084],"type":"Point"}
}