{
  "type": "Feature",
  "properties": {
    "iso:country":"US",
    "sg:address":"203 W Division St",
    "sg:city":"Rockford",
    "sg:classifiers":[
        {
            "category":"Shopping",
            "subcategory":"Computers & Home Electronics",
            "type":"Retail Goods"
        }
    ],
    "sg:phone":"+1 616 866 6598",
    "sg:postcode":"49341",
    "sg:province":"MI",
    "sg:tags":[
        "equipment",
        "satellite",
        "system"
    ],
    "wof:name":"Manciu Communications",
    "wof:placetype":"venue"
},
  "geometry": {"coordinates":[-85.567193,43.116802],"type":"Point"}
}