{
  "type": "Feature",
  "properties": {
    "iso:country":"US",
    "sg:address":"11280 Greentree Dr",
    "sg:city":"Warren",
    "sg:classifiers":[
        {
            "category":"Professional",
            "subcategory":"Lawyer & Legal Services",
            "type":"Services"
        }
    ],
    "sg:phone":"+1 586 558 5046",
    "sg:postcode":"48093",
    "sg:province":"MI",
    "wof:name":"Daniel N Garon",
    "wof:placetype":"venue"
},
  "geometry": {"coordinates":[-83.012597,42.5161],"type":"Point"}
}