{
  "type": "Feature",
  "properties": {
    "iso:country":"US",
    "sg:address":"225 Harper Ave",
    "sg:city":"Detroit",
    "sg:classifiers":[
        {
            "category":"Professional",
            "subcategory":"Accounting & Tax Preparation",
            "type":"Services"
        }
    ],
    "sg:phone":"+1 313 874 5276",
    "sg:postcode":"48202",
    "sg:province":"MI",
    "wof:name":"Daniel Griffin Enterprises",
    "wof:placetype":"venue"
},
  "geometry": {"coordinates":[-83.065656,42.367018],"type":"Point"}
}