{
  "type": "Feature",
  "properties": {
    "iso:country":"US",
    "sg:address":"1511 Birch Ave",
    "sg:city":"Marquette",
    "sg:classifiers":[
        {
            "category":"Professional",
            "subcategory":"Management & Consulting",
            "type":"Services"
        }
    ],
    "sg:phone":"+1 906 228 5959",
    "sg:postcode":"49855",
    "sg:province":"MI",
    "sg:tags":[
        "business"
    ],
    "wof:name":"Wiseman & Associates LLC",
    "wof:placetype":"venue"
},
  "geometry": {"coordinates":[-87.41338399999999,46.559266],"type":"Point"}
}