{
  "type": "Feature",
  "properties": {
    "iso:country":"US",
    "sg:address":"23337 S Woodward Ave",
    "sg:city":"Ferndale",
    "sg:classifiers":[
        {
            "category":"Manufacturing",
            "subcategory":"Tools & Machinery",
            "type":"Manufacturing & Wholesale Goods"
        },
        {
            "category":"Shopping",
            "subcategory":"Clothing, Apparel, & Fashions",
            "type":"Retail Goods"
        }
    ],
    "sg:phone":"+1 248 744 9447",
    "sg:postcode":"48220",
    "sg:province":"MI",
    "sg:tags":[
        "physician",
        "surgeon",
        "medical"
    ],
    "sg:website":"www.susansspecialneeds.com",
    "wof:name":"Susan's Special Needs",
    "wof:placetype":"venue"
},
  "geometry": {"coordinates":[-83.1386,42.466127],"type":"Point"}
}