{
  "type": "Feature",
  "properties": {
    "iso:country":"US",
    "sg:address":"930 E Maple Rd",
    "sg:city":"Birmingham",
    "sg:classifiers":[
        {
            "category":"Personal",
            "subcategory":"Beauty Salon",
            "type":"Services"
        }
    ],
    "sg:phone":"+1 248 540 4797",
    "sg:postcode":"48009",
    "sg:province":"MI",
    "sg:tags":[
        "shop"
    ],
    "wof:name":"John Marino Salon LLC",
    "wof:placetype":"venue"
},
  "geometry": {"coordinates":[-83.20793,42.546786],"type":"Point"}
}