{
  "type": "Feature",
  "properties": {
    "iso:country":"US",
    "sg:address":"35330 Phyllis St",
    "sg:city":"Wayne",
    "sg:classifiers":[
        {
            "category":"Organizations",
            "subcategory":"Non-profit Organization",
            "type":"Services"
        }
    ],
    "sg:phone":"+1 734 722 9319",
    "sg:postcode":"48184",
    "sg:province":"MI",
    "sg:tags":[
        "social"
    ],
    "wof:name":"City of Wayne Goodfellows",
    "wof:placetype":"venue"
},
  "geometry": {"coordinates":[-83.385555,42.267678],"type":"Point"}
}