{
  "type": "Feature",
  "properties": {
    "iso:country":"US",
    "sg:address":"1550 Oakman Blvd",
    "sg:city":"Detroit",
    "sg:classifiers":[
        {
            "category":"Education",
            "subcategory":"Special Training",
            "type":"Public Place"
        }
    ],
    "sg:phone":"+1 313 365 4673",
    "sg:postcode":"48238",
    "sg:province":"MI",
    "sg:tags":[
        "adult"
    ],
    "sg:website":"www.focushope.edu",
    "wof:name":"Focus Hope",
    "wof:placetype":"venue"
},
  "geometry": {"coordinates":[-83.12130000000001,42.399799],"type":"Point"}
}