{
  "type": "Feature",
  "properties": {
    "iso:country":"US",
    "sg:address":"21617 E 9 Mile Rd",
    "sg:city":"Saint Clair Shores",
    "sg:classifiers":[
        {
            "category":"Health Services",
            "subcategory":"Chiropractor",
            "type":"Services"
        }
    ],
    "sg:phone":"+1 586 774 7553",
    "sg:postcode":"48080",
    "sg:province":"MI",
    "wof:name":"Klida Gerald DC",
    "wof:placetype":"venue"
},
  "geometry": {"coordinates":[-82.906847,42.466189],"type":"Point"}
}