{
  "type": "Feature",
  "properties": {
    "iso:country":"US",
    "sg:address":"3895 Olds Rd",
    "sg:city":"Onondaga",
    "sg:classifiers":[
        {
            "category":"Building & Trades",
            "subcategory":"Construction",
            "type":"Services"
        }
    ],
    "sg:phone":"+1 517 589 8103",
    "sg:postcode":"49264",
    "sg:province":"MI",
    "sg:tags":[
        "contractor"
    ],
    "wof:name":"R F Drywall",
    "wof:placetype":"venue"
},
  "geometry": {"coordinates":[-84.526223,42.436488],"type":"Point"}
}