{
  "type": "Feature",
  "properties": {
    "iso:country":"US",
    "sg:address":"6039 Torrey Rd",
    "sg:city":"Flint",
    "sg:classifiers":[
        {
            "category":"Building & Trades",
            "subcategory":"Construction",
            "type":"Services"
        }
    ],
    "sg:phone":"+1 810 655 2718",
    "sg:postcode":"48507",
    "sg:province":"MI",
    "sg:tags":[
        "repair"
    ],
    "wof:name":"Jac Enterprises Inc",
    "wof:placetype":"venue"
},
  "geometry": {"coordinates":[-83.731573,42.941596],"type":"Point"}
}