{
  "type": "Feature",
  "properties": {
    "iso:country":"US",
    "sg:address":"69820 S Nottawa Rd",
    "sg:city":"Sturgis",
    "sg:classifiers":[
        {
            "category":"Organizations",
            "subcategory":"Religious Organization",
            "type":"Services"
        }
    ],
    "sg:phone":"+1 269 651 1589",
    "sg:postcode":"49091",
    "sg:province":"MI",
    "wof:name":"Kingdom Hall Jehovah Witness",
    "wof:placetype":"venue"
},
  "geometry": {"coordinates":[-85.418599,41.783838],"type":"Point"}
}