{
  "type": "Feature",
  "properties": {
    "iso:country":"US",
    "sg:address":"410 N Ionia St",
    "sg:city":"Gladwin",
    "sg:classifiers":[
        {
            "category":"Home & Garden",
            "subcategory":"Building Materials",
            "type":"Retail Goods"
        }
    ],
    "sg:phone":"+1 989 426 9931",
    "sg:postcode":"48624",
    "sg:province":"MI",
    "wof:name":"Capling Wallpaper & Paint Inc",
    "wof:placetype":"venue"
},
  "geometry": {"coordinates":[-84.492851,43.984282],"type":"Point"}
}