{
  "type": "Feature",
  "properties": {
    "iso:country":"US",
    "sg:address":"2211 N Center Rd",
    "sg:city":"Flint",
    "sg:classifiers":[
        {
            "category":"Organizations",
            "subcategory":"Religious Organization",
            "type":"Services"
        }
    ],
    "sg:phone":"+1 810 742 7060",
    "sg:postcode":"48506",
    "sg:province":"MI",
    "wof:name":"Central Baptist Church",
    "wof:placetype":"venue"
},
  "geometry": {"coordinates":[-83.635696,43.035801],"type":"Point"}
}