{
  "type": "Feature",
  "properties": {
    "iso:country":"US",
    "sg:address":"1500 W Lake Lansing Rd",
    "sg:city":"East Lansing",
    "sg:classifiers":[
        {
            "category":"Restaurant",
            "type":"Food & Drink"
        }
    ],
    "sg:menulink":"http://www.allmenus.com/mi/east-lansing/249825-ingcredible!/menu/",
    "sg:phone":"+1 517 333 3328",
    "sg:postcode":"48823",
    "sg:province":"MI",
    "sg:tags":[
        "asian",
        "chinese"
    ],
    "wof:name":"Ingcredible!",
    "wof:placetype":"venue"
},
  "geometry": {"coordinates":[-84.50425199999999,42.760825],"type":"Point"}
}