{
  "type": "Feature",
  "properties": {
    "iso:country":"US",
    "sg:address":"104 N Main St",
    "sg:city":"Lawton",
    "sg:classifiers":[
        {
            "category":"Banks & Credit Unions",
            "subcategory":"Bank",
            "type":"Services"
        }
    ],
    "sg:phone":"+1 269 624 4511",
    "sg:postcode":"49065",
    "sg:province":"MI",
    "wof:name":"Fifth Third Bank",
    "wof:placetype":"venue"
},
  "geometry": {"coordinates":[-85.849745,42.168603],"type":"Point"}
}