{
  "type": "Feature",
  "properties": {
    "iso:country":"US",
    "sg:address":"3269 Main St",
    "sg:city":"Marlette",
    "sg:classifiers":[
        {
            "category":"Autos & Motor Vehicles",
            "subcategory":"Fuel & Gas Station",
            "type":"Retail Goods"
        }
    ],
    "sg:phone":"+1 989 635 7043",
    "sg:postcode":"48453",
    "sg:province":"MI",
    "sg:tags":[
        "oil"
    ],
    "wof:name":"Emro Marketing",
    "wof:placetype":"venue"
},
  "geometry": {"coordinates":[-83.07977099999999,43.322786],"type":"Point"}
}