{
  "type": "Feature",
  "properties": {
    "iso:country":"US",
    "sg:address":"150 N Lowell St",
    "sg:city":"Ironwood",
    "sg:classifiers":[
        {
            "category":"Museum",
            "type":"Entertainment"
        }
    ],
    "sg:phone":"+1 906 932 0287",
    "sg:postcode":"49938",
    "sg:province":"MI",
    "wof:name":"Ironwood Area Historical Soc",
    "wof:placetype":"venue"
},
  "geometry": {"coordinates":[-90.17157899999999,46.455254],"type":"Point"}
}