{
  "type": "Feature",
  "properties": {
    "iso:country":"US",
    "sg:address":"7755 W Hayes Rd",
    "sg:city":"Shelby",
    "sg:phone":"+1 231 861 4489",
    "sg:postcode":"49455",
    "sg:province":"MI",
    "sg:tags":[
        "farm",
        "hog",
        "corn",
        "or",
        "feedlot"
    ],
    "wof:name":"Gordon Moschke",
    "wof:placetype":"venue"
},
  "geometry": {"coordinates":[-86.475391,43.573695],"type":"Point"}
}