{
  "type": "Feature",
  "properties": {
    "iso:country":"US",
    "sg:address":"124 S Cherry St",
    "sg:city":"Flushing",
    "sg:classifiers":[
        {
            "category":"Banks & Credit Unions",
            "subcategory":"Bank",
            "type":"Services"
        }
    ],
    "sg:phone":"+1 810 659 4062",
    "sg:postcode":"48433",
    "sg:province":"MI",
    "wof:name":"Bank One",
    "wof:placetype":"venue"
},
  "geometry": {"coordinates":[-83.8544,43.062353],"type":"Point"}
}