{
  "type": "Feature",
  "properties": {
    "iso:country":"US",
    "sg:address":"14615 Telegraph Rd",
    "sg:city":"Redford",
    "sg:classifiers":[
        {
            "category":"Education",
            "subcategory":"Music School",
            "type":"Public Place"
        },
        {
            "category":"Shopping",
            "subcategory":"Jewelry",
            "type":"Retail Goods"
        },
        {
            "category":"Shopping",
            "subcategory":"Pawn Shop",
            "type":"Retail Goods"
        }
    ],
    "sg:phone":"+1 313 533 1133",
    "sg:postcode":"48239",
    "sg:province":"MI",
    "sg:tags":[
        "instrument",
        "musical",
        "teacher"
    ],
    "wof:name":"Rose Jewelry & Exchange",
    "wof:placetype":"venue"
},
  "geometry": {"coordinates":[-83.276905,42.394223],"type":"Point"}
}