{
  "type": "Feature",
  "properties": {
    "iso:country":"US",
    "sg:address":"12909 S Straits Hwy",
    "sg:city":"Wolverine",
    "sg:classifiers":[
        {
            "category":"Shopping",
            "subcategory":"Gifts & Souvenirs",
            "type":"Retail Goods"
        }
    ],
    "sg:phone":"+1 231 525 9020",
    "sg:postcode":"49799",
    "sg:province":"MI",
    "sg:tags":[
        "shop"
    ],
    "wof:name":"Surprising Recoveries",
    "wof:placetype":"venue"
},
  "geometry": {"coordinates":[-84.603578,45.27452],"type":"Point"}
}