{
  "type": "Feature",
  "properties": {
    "iso:country":"US",
    "sg:address":"1283 State Hwy 139",
    "sg:city":"Benton Harbor",
    "sg:classifiers":[
        {
            "category":"Autos & Motor Vehicles",
            "subcategory":"Automobile Sales",
            "type":"Retail Goods"
        }
    ],
    "sg:phone":"+1 269 925 2277",
    "sg:postcode":"49022",
    "sg:province":"MI",
    "sg:tags":[
        "car",
        "dealer"
    ],
    "wof:name":"Jerry Hunt's Auto Ctr Inc",
    "wof:placetype":"venue"
},
  "geometry": {"coordinates":[-86.435091,42.095406],"type":"Point"}
}