{
  "type": "Feature",
  "properties": {
    "iso:country":"US",
    "sg:address":"67300 Van Dyke Rd",
    "sg:city":"Washington",
    "sg:classifiers":[
        {
            "category":"Shopping",
            "subcategory":"Gifts & Souvenirs",
            "type":"Retail Goods"
        }
    ],
    "sg:phone":"+1 586 752 6757",
    "sg:postcode":"48095",
    "sg:province":"MI",
    "sg:tags":[
        "shop"
    ],
    "wof:name":"Pewter Palace",
    "wof:placetype":"venue"
},
  "geometry": {"coordinates":[-83.013199,42.789285],"type":"Point"}
}