{
  "type": "Feature",
  "properties": {
    "iso:country":"US",
    "sg:address":"120 S Milford Rd",
    "sg:city":"Milford",
    "sg:classifiers":[
        {
            "category":"Restaurant",
            "type":"Food & Drink"
        }
    ],
    "sg:menulink":"http://www.allmenus.com/mi/milford/185741-mcdonalds/menu/",
    "sg:postcode":"48381",
    "sg:province":"MI",
    "sg:tags":[
        "burger",
        "american"
    ],
    "wof:name":"McDonald's",
    "wof:placetype":"venue"
},
  "geometry": {"coordinates":[-83.610741,42.581893],"type":"Point"}
}