{
  "type": "Feature",
  "properties": {
    "iso:country":"US",
    "sg:address":"3740 Moore Rd",
    "sg:city":"Tekonsha",
    "sg:phone":"+1 517 767 4287",
    "sg:postcode":"49092",
    "sg:province":"MI",
    "sg:tags":[
        "farm",
        "corn",
        "soybean"
    ],
    "wof:name":"Jeffrey Klingaman",
    "wof:placetype":"venue"
},
  "geometry": {"coordinates":[-85.01090600000001,42.130674],"type":"Point"}
}