{
  "type": "Feature",
  "properties": {
    "iso:country":"US",
    "sg:address":"720 W Wackerly St",
    "sg:city":"Midland",
    "sg:classifiers":[
        {
            "category":"Health Services",
            "subcategory":"Health Practitioner",
            "type":"Services"
        }
    ],
    "sg:phone":"+1 989 839 8230",
    "sg:postcode":"48640",
    "sg:province":"MI",
    "sg:tags":[
        "audiologists"
    ],
    "wof:name":"Bieri Hearing Clinic",
    "wof:placetype":"venue"
},
  "geometry": {"coordinates":[-84.236941,43.654962],"type":"Point"}
}