{
  "type": "Feature",
  "properties": {
    "iso:country":"US",
    "sg:address":"10125 Telegraph Rd",
    "sg:city":"Carleton",
    "sg:classifiers":[
        {
            "category":"Home & Garden",
            "subcategory":"Mobile Homes",
            "type":"Retail Goods"
        }
    ],
    "sg:phone":"+1 734 586 7477",
    "sg:postcode":"48117",
    "sg:province":"MI",
    "wof:name":"Superior Manufactured Homes",
    "wof:placetype":"venue"
},
  "geometry": {"coordinates":[-83.34333599999999,42.02373],"type":"Point"}
}