{
  "type": "Feature",
  "properties": {
    "iso:country":"US",
    "sg:address":"1841 Gratiot Ave",
    "sg:city":"Detroit",
    "sg:classifiers":[
        {
            "category":"Food & Beverages",
            "subcategory":"Meat & Fish",
            "type":"Retail Goods"
        }
    ],
    "sg:phone":"+1 313 259 8850",
    "sg:postcode":"48207",
    "sg:province":"MI",
    "sg:tags":[
        "shop"
    ],
    "wof:name":"Broadway Market Corned Beef Company",
    "wof:placetype":"venue"
},
  "geometry": {"coordinates":[-83.035797,42.347198],"type":"Point"}
}