{
  "type": "Feature",
  "properties": {
    "iso:country":"US",
    "sg:address":"755 E Maple Rd",
    "sg:city":"Birmingham",
    "sg:classifiers":[
        {
            "category":"Restaurant",
            "type":"Food & Drink"
        }
    ],
    "sg:menulink":"http://www.allmenus.com/mi/birmingham/161219-cheeburger-cheeburger/menu/",
    "sg:phone":"+1 248 203 4171",
    "sg:postcode":"48009",
    "sg:province":"MI",
    "sg:tags":[
        "burger",
        "american",
        "diner"
    ],
    "wof:name":"Cheeburger Cheeburger",
    "wof:placetype":"venue"
},
  "geometry": {"coordinates":[-83.20927,42.546838],"type":"Point"}
}