{
  "type": "Feature",
  "properties": {
    "iso:country":"US",
    "sg:address":"8545 Leslie Dr",
    "sg:city":"Sterling Heights",
    "sg:classifiers":[
        {
            "category":"Organizations",
            "subcategory":"Religious Organization",
            "type":"Services"
        }
    ],
    "sg:phone":"+1 586 997 1737",
    "sg:postcode":"48314",
    "sg:province":"MI",
    "sg:tags":[
        "church"
    ],
    "wof:name":"Utica United Methodist Church",
    "wof:placetype":"venue"
},
  "geometry": {"coordinates":[-83.025305,42.621365],"type":"Point"}
}