{
  "type": "Feature",
  "properties": {
    "iso:country":"US",
    "sg:address":"15563 45th Ave",
    "sg:city":"Barryton",
    "sg:classifiers":[
        {
            "category":"Home & Garden",
            "subcategory":"Garden Supply",
            "type":"Retail Goods"
        }
    ],
    "sg:phone":"+1 989 382 7535",
    "sg:postcode":"49305",
    "sg:province":"MI",
    "wof:name":"Perennial Patch",
    "wof:placetype":"venue"
},
  "geometry": {"coordinates":[-85.176616,43.690577],"type":"Point"}
}