{
  "type": "Feature",
  "properties": {
    "iso:country":"US",
    "sg:address":"32000 Northwestern Hwy",
    "sg:city":"Farmington Hills",
    "sg:classifiers":[
        {
            "category":"Real Estate",
            "subcategory":"Real Estate Services",
            "type":"Services"
        }
    ],
    "sg:phone":"+1 248 702 2400",
    "sg:postcode":"48334",
    "sg:province":"MI",
    "sg:tags":[
        "company",
        "title"
    ],
    "wof:name":"Land America Transnation Title",
    "wof:placetype":"venue"
},
  "geometry": {"coordinates":[-83.34531200000001,42.522264],"type":"Point"}
}