{
  "type": "Feature",
  "properties": {
    "iso:country":"US",
    "sg:address":"3919 E Gatzke Rd",
    "sg:city":"Cedar",
    "sg:classifiers":[
        {
            "category":"Organizations",
            "subcategory":"Religious Organization",
            "type":"Services"
        }
    ],
    "sg:phone":"+1 231 228 5429",
    "sg:postcode":"49621",
    "sg:province":"MI",
    "wof:name":"Holy Rosary Church",
    "wof:placetype":"venue"
},
  "geometry": {"coordinates":[-85.78136499999999,44.877495],"type":"Point"}
}