{
  "type": "Feature",
  "properties": {
    "iso:country":"US",
    "sg:address":"381 Houston Ave",
    "sg:city":"Muskegon",
    "sg:classifiers":[
        {
            "category":"Social Services",
            "subcategory":"Adult Care",
            "type":"Services"
        }
    ],
    "sg:phone":"+1 231 722 7022",
    "sg:postcode":"49441",
    "sg:province":"MI",
    "sg:tags":[
        "foster"
    ],
    "wof:name":"Lightfoot House A F C Homes",
    "wof:placetype":"venue"
},
  "geometry": {"coordinates":[-86.253449,43.23004],"type":"Point"}
}