{
  "type": "Feature",
  "properties": {
    "iso:country":"US",
    "sg:address":"942 Doster Rd",
    "sg:city":"Plainwell",
    "sg:classifiers":[
        {
            "category":"Food & Beverages",
            "subcategory":"Groceries & Convenience Stores",
            "type":"Retail Goods"
        }
    ],
    "sg:phone":"+1 269 685 5323",
    "sg:postcode":"49080",
    "sg:province":"MI",
    "sg:tags":[
        "grocer"
    ],
    "wof:name":"Pine Lake Grocery",
    "wof:placetype":"venue"
},
  "geometry": {"coordinates":[-85.543194,42.499862],"type":"Point"}
}