{
  "type": "Feature",
  "properties": {
    "iso:country":"US",
    "sg:address":"8196 S Shoreside Dr",
    "sg:city":"Traverse City",
    "sg:classifiers":[
        {
            "category":"Professional",
            "subcategory":"Computer Services",
            "type":"Services"
        }
    ],
    "sg:phone":"+1 231 946 7115",
    "sg:postcode":"49684",
    "sg:province":"MI",
    "sg:tags":[
        "datum"
    ],
    "wof:name":"Steve Bardenhagen",
    "wof:placetype":"venue"
},
  "geometry": {"coordinates":[-85.65150800000001,44.860685],"type":"Point"}
}