{
  "type": "Feature",
  "properties": {
    "iso:country":"US",
    "sg:address":"6258 River St",
    "sg:city":"Alanson",
    "sg:classifiers":[
        {
            "category":"Manufacturing",
            "subcategory":"Metals",
            "type":"Manufacturing & Wholesale Goods"
        }
    ],
    "sg:phone":"+1 231 548 2281",
    "sg:postcode":"49706",
    "sg:province":"MI",
    "sg:tags":[
        "fabricator",
        "sheet"
    ],
    "wof:name":"Karriger Engineering & Mfg Inc",
    "wof:placetype":"venue"
},
  "geometry": {"coordinates":[-84.787693,45.440484],"type":"Point"}
}