{
  "type": "Feature",
  "properties": {
    "iso:country":"US",
    "sg:address":"510 E 10 Mile Rd",
    "sg:city":"Hazel Park",
    "sg:classifiers":[
        {
            "category":"Shopping",
            "type":"Retail Goods"
        }
    ],
    "sg:phone":"+1 248 744 3580",
    "sg:postcode":"48030",
    "sg:province":"MI",
    "sg:tags":[
        "retailer",
        "novelty"
    ],
    "wof:name":"Shopinprivatecom",
    "wof:placetype":"venue"
},
  "geometry": {"coordinates":[-83.098786,42.476129],"type":"Point"}
}