{
  "type": "Feature",
  "properties": {
    "iso:country":"US",
    "sg:address":"401 S Burdick St",
    "sg:city":"Kalamazoo",
    "sg:classifiers":[
        {
            "category":"Professional",
            "type":"Services"
        }
    ],
    "sg:phone":"+1 269 345 4879",
    "sg:postcode":"49007",
    "sg:province":"MI",
    "sg:tags":[
        "establishment"
    ],
    "wof:name":"Gismo",
    "wof:placetype":"venue"
},
  "geometry": {"coordinates":[-85.58300699999999,42.287448],"type":"Point"}
}