{
  "type": "Feature",
  "properties": {
    "iso:country":"US",
    "sg:address":"11307 15 Mile Rd",
    "sg:city":"Sterling Heights",
    "sg:classifiers":[
        {
            "category":"Food & Beverages",
            "subcategory":"Liquor & Beverages",
            "type":"Retail Goods"
        }
    ],
    "sg:phone":"+1 586 977 3600",
    "sg:postcode":"48312",
    "sg:province":"MI",
    "sg:tags":[
        "beer",
        "spirit",
        "wine"
    ],
    "wof:name":"Venetian Liquor",
    "wof:placetype":"venue"
},
  "geometry": {"coordinates":[-83.01311099999999,42.551741],"type":"Point"}
}