{
  "type": "Feature",
  "properties": {
    "iso:country":"US",
    "sg:address":"4619 Mackinaw Rd",
    "sg:city":"Saginaw",
    "sg:classifiers":[
        {
            "category":"Education",
            "subcategory":"School",
            "type":"Public Place"
        }
    ],
    "sg:phone":"+1 989 793 2129",
    "sg:postcode":"48603",
    "sg:province":"MI",
    "wof:name":"Grace Baptist Christian School",
    "wof:placetype":"venue"
},
  "geometry": {"coordinates":[-83.99520699999999,43.47318],"type":"Point"}
}