{
  "type": "Feature",
  "properties": {
    "iso:country":"US",
    "sg:address":"1225 Graafschap Rd",
    "sg:city":"Holland",
    "sg:classifiers":[
        {
            "category":"Professional",
            "type":"Services"
        }
    ],
    "sg:phone":"+1 616 392 1144",
    "sg:postcode":"49423",
    "sg:province":"MI",
    "sg:tags":[
        "establishment"
    ],
    "wof:name":"Menken Electric",
    "wof:placetype":"venue"
},
  "geometry": {"coordinates":[-86.136757,42.758509],"type":"Point"}
}