{
  "type": "Feature",
  "properties": {
    "iso:country":"US",
    "sg:address":"39555 Orchard Hill Pl",
    "sg:city":"Novi",
    "sg:classifiers":[
        {
            "category":"Professional",
            "subcategory":"Accounting & Tax Preparation",
            "type":"Services"
        }
    ],
    "sg:phone":"+1 248 374 5025",
    "sg:postcode":"48375",
    "sg:province":"MI",
    "sg:tags":[
        "accountant"
    ],
    "wof:name":"Kearis & Assoc",
    "wof:placetype":"venue"
},
  "geometry": {"coordinates":[-83.438554,42.441209],"type":"Point"}
}