{
  "type": "Feature",
  "properties": {
    "iso:country":"US",
    "sg:address":"38110 Executive Dr N",
    "sg:city":"Westland",
    "sg:classifiers":[
        {
            "category":"Personal",
            "subcategory":"Beauty Salon",
            "type":"Services"
        }
    ],
    "sg:phone":"+1 734 595 7727",
    "sg:postcode":"48185",
    "sg:province":"MI",
    "sg:tags":[
        "shop"
    ],
    "wof:name":"Fantastic Sams",
    "wof:placetype":"venue"
},
  "geometry": {"coordinates":[-83.41732,42.3297],"type":"Point"}
}