{
  "type": "Feature",
  "properties": {
    "iso:country":"US",
    "sg:address":"50371 E Russell Schmidt Blvd",
    "sg:city":"Chesterfield",
    "sg:classifiers":[
        {
            "category":"Professional",
            "subcategory":"Engineering",
            "type":"Services"
        }
    ],
    "sg:phone":"+1 586 598 9495",
    "sg:postcode":"48051",
    "sg:province":"MI",
    "sg:tags":[
        "general",
        "contractor"
    ],
    "wof:name":"Wat Intl",
    "wof:placetype":"venue"
},
  "geometry": {"coordinates":[-82.848884,42.66542],"type":"Point"}
}