{
  "type": "Feature",
  "properties": {
    "iso:country":"US",
    "sg:address":"1888 High Lake Rd",
    "sg:city":"Traverse City",
    "sg:classifiers":[
        {
            "category":"Retail",
            "subcategory":"Repair Shop",
            "type":"Services"
        }
    ],
    "sg:phone":"+1 231 929 1601",
    "sg:postcode":"49686",
    "sg:province":"MI",
    "sg:tags":[
        "tool",
        "parts"
    ],
    "wof:name":"Airlex Service & Sales",
    "wof:placetype":"venue"
},
  "geometry": {"coordinates":[-85.516364,44.709521],"type":"Point"}
}