{
  "type": "Feature",
  "properties": {
    "iso:country":"US",
    "sg:address":"4868 Northview Ave NE",
    "sg:city":"Grand Rapids",
    "sg:classifiers":[
        {
            "category":"Professional",
            "subcategory":"Computer Services",
            "type":"Services"
        }
    ],
    "sg:phone":"+1 616 361 6230",
    "sg:postcode":"49525",
    "sg:province":"MI",
    "sg:tags":[
        "design",
        "system"
    ],
    "wof:name":"Tecreations",
    "wof:placetype":"venue"
},
  "geometry": {"coordinates":[-85.61532,43.052173],"type":"Point"}
}