{
  "type": "Feature",
  "properties": {
    "iso:country":"US",
    "sg:address":"5865 Jackelyn Ct",
    "sg:city":"Washington",
    "sg:classifiers":[
        {
            "category":"Building & Trades",
            "subcategory":"Construction",
            "type":"Services"
        }
    ],
    "sg:phone":"+1 586 992 1329",
    "sg:postcode":"48094",
    "sg:province":"MI",
    "sg:tags":[
        "contractor"
    ],
    "wof:name":"Torres Building Co Inc",
    "wof:placetype":"venue"
},
  "geometry": {"coordinates":[-83.05950900000001,42.714507],"type":"Point"}
}