{
  "type": "Feature",
  "properties": {
    "iso:country":"US",
    "sg:address":"9585 Mariner Dr",
    "sg:city":"Fair Haven",
    "sg:classifiers":[
        {
            "category":"Building & Trades",
            "subcategory":"Construction",
            "type":"Services"
        }
    ],
    "sg:phone":"+1 586 725 4274",
    "sg:postcode":"48023",
    "sg:province":"MI",
    "sg:tags":[
        "hanging",
        "contractor"
    ],
    "wof:name":"Prestige Exterior Clng",
    "wof:placetype":"venue"
},
  "geometry": {"coordinates":[-82.70528299999999,42.697073],"type":"Point"}
}