{
  "type": "Feature",
  "properties": {
    "iso:country":"US",
    "sg:address":"11 N Lake St",
    "sg:city":"Port Sanilac",
    "sg:classifiers":[
        {
            "category":"Wholesale",
            "subcategory":"Construction Materials",
            "type":"Manufacturing & Wholesale Goods"
        }
    ],
    "sg:phone":"+1 810 622 8993",
    "sg:postcode":"48469",
    "sg:province":"MI",
    "sg:tags":[
        "fence"
    ],
    "wof:name":"Brothers Fence Inc",
    "wof:placetype":"venue"
},
  "geometry": {"coordinates":[-82.54076499999999,43.433761],"type":"Point"}
}