{
  "type": "Feature",
  "properties": {
    "iso:country":"US",
    "sg:address":"2658 Roberts St",
    "sg:city":"Muskegon",
    "sg:classifiers":[
        {
            "category":"Social Services",
            "subcategory":"Child Care",
            "type":"Services"
        }
    ],
    "sg:phone":"+1 231 737 3214",
    "sg:postcode":"49444",
    "sg:province":"MI",
    "sg:tags":[
        "day",
        "provider"
    ],
    "wof:name":"ABC Day Care",
    "wof:placetype":"venue"
},
  "geometry": {"coordinates":[-86.213987,43.202456],"type":"Point"}
}