{
  "type": "Feature",
  "properties": {
    "iso:country":"US",
    "sg:address":"7129 Angling Rd",
    "sg:city":"Portage",
    "sg:classifiers":[
        {
            "category":"Professional",
            "subcategory":"Business Services",
            "type":"Services"
        }
    ],
    "sg:phone":"+1 269 329 1958",
    "sg:postcode":"49024",
    "sg:province":"MI",
    "wof:name":"Militzer Enterprises Inc",
    "wof:placetype":"venue"
},
  "geometry": {"coordinates":[-85.64238,42.206917],"type":"Point"}
}