{
  "type": "Feature",
  "properties": {
    "iso:country":"US",
    "sg:address":"15888 Groesbeck St",
    "sg:city":"Grand Haven",
    "sg:classifiers":[
        {
            "category":"Building & Trades",
            "subcategory":"Cleaning & Sanitation",
            "type":"Services"
        }
    ],
    "sg:phone":"+1 616 842 0426",
    "sg:postcode":"49417",
    "sg:province":"MI",
    "sg:tags":[
        "janitor"
    ],
    "wof:name":"P M Janitorial Svc",
    "wof:placetype":"venue"
},
  "geometry": {"coordinates":[-86.182913,43.026691],"type":"Point"}
}