{
  "type": "Feature",
  "properties": {
    "iso:country":"US",
    "sg:address":"1230 Rose St",
    "sg:city":"Traverse City",
    "sg:classifiers":[
        {
            "category":"Wholesale",
            "subcategory":"Machinery & Supplies",
            "type":"Manufacturing & Wholesale Goods"
        }
    ],
    "sg:phone":"+1 231 947 6852",
    "sg:postcode":"49686",
    "sg:province":"MI",
    "sg:tags":[
        "instrument",
        "surveying"
    ],
    "wof:name":"Wiley's Sales & Svc",
    "wof:placetype":"venue"
},
  "geometry": {"coordinates":[-85.600534,44.745128],"type":"Point"}
}