{
  "type": "Feature",
  "properties": {
    "iso:country":"US",
    "sg:address":"9270 Baumhoff Ave NW",
    "sg:city":"Sparta",
    "sg:classifiers":[
        {
            "category":"Professional",
            "subcategory":"Business Services",
            "type":"Services"
        }
    ],
    "sg:phone":"+1 616 887 8544",
    "sg:postcode":"49345",
    "sg:province":"MI",
    "wof:name":"Quality Formica Inc",
    "wof:placetype":"venue"
},
  "geometry": {"coordinates":[-85.720016,43.131781],"type":"Point"}
}