{
  "type": "Feature",
  "properties": {
    "iso:country":"US",
    "sg:address":"2780 E Highland Rd",
    "sg:city":"Highland",
    "sg:classifiers":[
        {
            "category":"Restaurant",
            "type":"Food & Drink"
        }
    ],
    "sg:menulink":"http://www.allmenus.com/mi/highland/146309-subway/menu/",
    "sg:phone":"+1 248 887 2625",
    "sg:postcode":"48356",
    "sg:province":"MI",
    "sg:tags":[
        "american",
        "sandwich"
    ],
    "wof:name":"Subway",
    "wof:placetype":"venue"
},
  "geometry": {"coordinates":[-83.575682,42.653728],"type":"Point"}
}