{
  "type": "Feature",
  "properties": {
    "iso:country":"US",
    "sg:address":"1174 Weeden Rd",
    "sg:city":"Caro",
    "sg:classifiers":[
        {
            "category":"Social Services",
            "type":"Services"
        }
    ],
    "sg:phone":"+1 989 673 5782",
    "sg:postcode":"48723",
    "sg:province":"MI",
    "wof:name":"Right To Life Tuscola County",
    "wof:placetype":"venue"
},
  "geometry": {"coordinates":[-83.376634,43.477074],"type":"Point"}
}