{
  "type": "Feature",
  "properties": {
    "iso:country":"US",
    "sg:address":"3643 Fenner Rd",
    "sg:city":"Muskegon",
    "sg:classifiers":[
        {
            "category":"Manufacturing",
            "subcategory":"Printing",
            "type":"Manufacturing & Wholesale Goods"
        }
    ],
    "sg:phone":"+1 231 744 6898",
    "sg:postcode":"49445",
    "sg:province":"MI",
    "sg:tags":[
        "periodical"
    ],
    "wof:name":"Townsend Press",
    "wof:placetype":"venue"
},
  "geometry": {"coordinates":[-86.339085,43.264257],"type":"Point"}
}