{
  "type": "Feature",
  "properties": {
    "iso:country":"US",
    "sg:address":"1111 Holden",
    "sg:city":"Milford",
    "sg:classifiers":[
        {
            "category":"Manufacturing",
            "subcategory":"Metals",
            "type":"Manufacturing & Wholesale Goods"
        }
    ],
    "sg:phone":"+1 248 685 3420",
    "sg:postcode":"48381",
    "sg:province":"MI",
    "sg:tags":[
        "treating",
        "heat"
    ],
    "wof:name":"Verticarb Heat Treat Div",
    "wof:placetype":"venue"
},
  "geometry": {"coordinates":[-83.614011,42.556147],"type":"Point"}
}