{
  "type": "Feature",
  "properties": {
    "iso:country":"US",
    "sg:address":"30010 W 12 Mile Rd",
    "sg:city":"Farmington Hills",
    "sg:classifiers":[
        {
            "category":"Bakery",
            "type":"Food & Drink"
        }
    ],
    "sg:phone":"+1 248 851 8181",
    "sg:postcode":"48334",
    "sg:province":"MI",
    "sg:website":"www.grafspastry.com/",
    "wof:name":"Graf's Pastry",
    "wof:placetype":"venue"
},
  "geometry": {"coordinates":[-83.348099,42.499599],"type":"Point"}
}