{
  "type": "Feature",
  "properties": {
    "iso:country":"US",
    "sg:address":"5478 S Saginaw Rd",
    "sg:city":"Flint",
    "sg:classifiers":[
        {
            "category":"Retail",
            "subcategory":"Repair Shop",
            "type":"Services"
        }
    ],
    "sg:phone":"+1 810 695 7474",
    "sg:postcode":"48507",
    "sg:province":"MI",
    "sg:tags":[
        "repairing",
        "lawn",
        "mower"
    ],
    "wof:name":"Beutler's Lawn & Garden",
    "wof:placetype":"venue"
},
  "geometry": {"coordinates":[-83.655689,42.94932],"type":"Point"}
}