{
  "type": "Feature",
  "properties": {
    "iso:country":"US",
    "sg:address":"29011 Glenarden St",
    "sg:city":"Farmington Hills",
    "sg:classifiers":[
        {
            "category":"Professional",
            "subcategory":"Computer Services",
            "type":"Services"
        }
    ],
    "sg:phone":"+1 248 488 2300",
    "sg:postcode":"48334",
    "sg:province":"MI",
    "sg:tags":[
        "repair"
    ],
    "sg:website":"www.compeopleinc.com",
    "wof:name":"Compeople",
    "wof:placetype":"venue"
},
  "geometry": {"coordinates":[-83.37305499999999,42.509594],"type":"Point"}
}