{
  "type": "Feature",
  "properties": {
    "iso:country":"US",
    "sg:address":"31400 Madison Ave",
    "sg:city":"Madison Heights",
    "sg:classifiers":[
        {
            "category":"Professional",
            "subcategory":"Business Services",
            "type":"Services"
        }
    ],
    "sg:phone":"+1 248 588 8382",
    "sg:postcode":"48071",
    "sg:province":"MI",
    "wof:name":"Rhonda El-Sheikh",
    "wof:placetype":"venue"
},
  "geometry": {"coordinates":[-83.12473300000001,42.522757],"type":"Point"}
}