{
  "type": "Feature",
  "properties": {
    "iso:country":"US",
    "sg:address":"6030 Pickerel Dr NE",
    "sg:city":"Rockford",
    "sg:classifiers":[
        {
            "category":"Farming",
            "subcategory":"Livestock Farm",
            "type":"Manufacturing & Wholesale Goods"
        }
    ],
    "sg:phone":"+1 616 874 1247",
    "sg:postcode":"49341",
    "sg:province":"MI",
    "sg:tags":[
        "animal",
        "general"
    ],
    "wof:name":"Northern Lights Alpaca Ranch",
    "wof:placetype":"venue"
},
  "geometry": {"coordinates":[-85.458476,43.069038],"type":"Point"}
}