{
  "type": "Feature",
  "properties": {
    "iso:country":"US",
    "sg:address":"2430 Geneva Hwy",
    "sg:city":"Manitou Beach",
    "sg:classifiers":[
        {
            "category":"Retail",
            "subcategory":"Repair Shop",
            "type":"Services"
        }
    ],
    "sg:phone":"+1 517 547 6692",
    "sg:postcode":"49253",
    "sg:province":"MI",
    "wof:name":"Geneva Marine Cancas Co",
    "wof:placetype":"venue"
},
  "geometry": {"coordinates":[-84.282848,41.963073],"type":"Point"}
}