{
  "type": "Feature",
  "properties": {
    "iso:country":"US",
    "sg:address":"315 Le Grand Blvd",
    "sg:city":"White Lake",
    "sg:classifiers":[
        {
            "category":"Building & Trades",
            "subcategory":"Cleaning & Sanitation",
            "type":"Services"
        }
    ],
    "sg:phone":"+1 248 887 1090",
    "sg:postcode":"48383",
    "sg:province":"MI",
    "sg:tags":[
        "janitor"
    ],
    "wof:name":"Brooms & Blooms Cleaning",
    "wof:placetype":"venue"
},
  "geometry": {"coordinates":[-83.53667299999999,42.644792],"type":"Point"}
}