{
  "type": "Feature",
  "properties": {
    "iso:country":"US",
    "sg:address":"2511 Ludington St",
    "sg:city":"Escanaba",
    "sg:classifiers":[
        {
            "category":"Autos & Motor Vehicles",
            "subcategory":"Automobile Sales",
            "type":"Retail Goods"
        }
    ],
    "sg:phone":"+1 906 786 6834",
    "sg:postcode":"49829",
    "sg:province":"MI",
    "sg:tags":[
        "car",
        "dealer"
    ],
    "wof:name":"Riverside Auto Sales Inc",
    "wof:placetype":"venue"
},
  "geometry": {"coordinates":[-87.083736,45.745679],"type":"Point"}
}