{
  "type": "Feature",
  "properties": {
    "iso:country":"US",
    "sg:address":"7500 Clyde Park Ave SW",
    "sg:city":"Byron Center",
    "sg:classifiers":[
        {
            "category":"Manufacturing",
            "subcategory":"Tools & Machinery",
            "type":"Manufacturing & Wholesale Goods"
        }
    ],
    "sg:phone":"+1 616 455 2593",
    "sg:postcode":"49315",
    "sg:province":"MI",
    "sg:tags":[
        "machine",
        "shop"
    ],
    "sg:website":"www.plasma-tec.com",
    "wof:name":"Plasma-Tec Inc",
    "wof:placetype":"venue"
},
  "geometry": {"coordinates":[-85.683483,42.830828],"type":"Point"}
}