{
  "type": "Feature",
  "properties": {
    "iso:country":"US",
    "sg:address":"5200 Van Wagnen Rd",
    "sg:city":"Vassar",
    "sg:classifiers":[
        {
            "category":"Education",
            "subcategory":"College",
            "type":"Public Place"
        }
    ],
    "sg:phone":"+1 989 823 8797",
    "sg:postcode":"48768",
    "sg:province":"MI",
    "wof:name":"Johnson & Wales",
    "wof:placetype":"venue"
},
  "geometry": {"coordinates":[-83.55712,43.380974],"type":"Point"}
}