{
  "type": "Feature",
  "properties": {
    "iso:country":"US",
    "sg:address":"6221 Surrey Ln",
    "sg:city":"Burton",
    "sg:classifiers":[
        {
            "category":"Professional",
            "type":"Services"
        }
    ],
    "sg:phone":"+1 810 744 4235",
    "sg:postcode":"48519",
    "sg:province":"MI",
    "wof:name":"Canfield Service Co",
    "wof:placetype":"venue"
},
  "geometry": {"coordinates":[-83.587458,43.004108],"type":"Point"}
}