{
  "type": "Feature",
  "properties": {
    "iso:country":"US",
    "sg:address":"3560 Greenfield Rd",
    "sg:city":"Dearborn",
    "sg:classifiers":[
        {
            "category":"Fast Food",
            "type":"Food & Drink"
        }
    ],
    "sg:phone":"+1 313 240 5295",
    "sg:postcode":"48120",
    "sg:province":"MI",
    "sg:website":"wendys.com",
    "wof:name":"Wendy's",
    "wof:placetype":"venue"
},
  "geometry": {"coordinates":[-83.187883,42.306748],"type":"Point"}
}