{
  "type": "Feature",
  "properties": {
    "iso:country":"US",
    "sg:address":"44456 Hanford Rd",
    "sg:city":"Canton",
    "sg:classifiers":[
        {
            "category":"Banks & Credit Unions",
            "subcategory":"Bank",
            "type":"Services"
        }
    ],
    "sg:phone":"+1 734 451 6200",
    "sg:postcode":"48187",
    "sg:province":"MI",
    "sg:tags":[
        "loan",
        "real estate"
    ],
    "wof:name":"Real Estate Professionals Inc",
    "wof:placetype":"venue"
},
  "geometry": {"coordinates":[-83.479984,42.329459],"type":"Point"}
}