{
  "type": "Feature",
  "properties": {
    "iso:country":"US",
    "sg:address":"5978 Bauer Rd",
    "sg:city":"Hudsonville",
    "sg:classifiers":[
        {
            "category":"Manufacturing",
            "subcategory":"Electronics",
            "type":"Manufacturing & Wholesale Goods"
        }
    ],
    "sg:phone":"+1 616 895 9288",
    "sg:postcode":"49426",
    "sg:province":"MI",
    "sg:tags":[
        "equipment",
        "electronic",
        "supply"
    ],
    "wof:name":"Perfection Electronic Products",
    "wof:placetype":"venue"
},
  "geometry": {"coordinates":[-85.934905,42.92141],"type":"Point"}
}