{
  "type": "Feature",
  "properties": {
    "iso:country":"US",
    "sg:address":"1428 Worcester Dr NE",
    "sg:city":"Grand Rapids",
    "sg:classifiers":[
        {
            "category":"Professional",
            "type":"Services"
        }
    ],
    "sg:phone":"+1 616 235 3698",
    "sg:postcode":"49505",
    "sg:province":"MI",
    "wof:name":"Mountaintop Adventures Inc",
    "wof:placetype":"venue"
},
  "geometry": {"coordinates":[-85.617031,42.989024],"type":"Point"}
}