{
  "type": "Feature",
  "properties": {
    "iso:country":"US",
    "sg:address":"22812 Walsingham Dr",
    "sg:city":"Farmington Hills",
    "sg:classifiers":[
        {
            "category":"Professional",
            "subcategory":"Advertising",
            "type":"Services"
        }
    ],
    "sg:phone":"+1 248 477 4330",
    "sg:postcode":"48335",
    "sg:province":"MI",
    "sg:tags":[
        "counselor",
        "agency"
    ],
    "wof:name":"Mac Marty Advertising Inc",
    "wof:placetype":"venue"
},
  "geometry": {"coordinates":[-83.401537,42.457811],"type":"Point"}
}