{
  "type": "Feature",
  "properties": {
    "iso:country":"US",
    "sg:address":"6215 Sashabaw Rd",
    "sg:city":"Clarkston",
    "sg:classifiers":[
        {
            "category":"Personal",
            "subcategory":"Beauty Salon",
            "type":"Services"
        }
    ],
    "sg:phone":"+1 248 620 3323",
    "sg:postcode":"48346",
    "sg:province":"MI",
    "wof:name":"Images By Renee",
    "wof:placetype":"venue"
},
  "geometry": {"coordinates":[-83.37947,42.733112],"type":"Point"}
}