{
  "type": "Feature",
  "properties": {
    "iso:country":"US",
    "sg:address":"3975 W Stoney Corners Rd",
    "sg:city":"Mc Bain",
    "sg:classifiers":[
        {
            "category":"Social Services",
            "subcategory":"Child Care",
            "type":"Services"
        }
    ],
    "sg:phone":"+1 231 825 9915",
    "sg:postcode":"49657",
    "sg:province":"MI",
    "sg:tags":[
        "day",
        "provider"
    ],
    "wof:name":"Holly Lynn Vandervlucht",
    "wof:placetype":"venue"
},
  "geometry": {"coordinates":[-85.166263,44.193473],"type":"Point"}
}