{
  "type": "Feature",
  "properties": {
    "iso:country":"US",
    "sg:address":"2135 Cliffside Dr",
    "sg:city":"Wixom",
    "sg:classifiers":[
        {
            "category":"Wholesale",
            "subcategory":"Non-durable Goods",
            "type":"Manufacturing & Wholesale Goods"
        }
    ],
    "sg:phone":"+1 248 926 6208",
    "sg:postcode":"48393",
    "sg:province":"MI",
    "wof:name":"Basket Bounty",
    "wof:placetype":"venue"
},
  "geometry": {"coordinates":[-83.530248,42.550294],"type":"Point"}
}