{
  "type": "Feature",
  "properties": {
    "iso:country":"US",
    "sg:address":"1123 13th St",
    "sg:city":"Menominee",
    "sg:classifiers":[
        {
            "category":"Organizations",
            "subcategory":"Religious Organization",
            "type":"Services"
        }
    ],
    "sg:phone":"+1 906 863 2753",
    "sg:postcode":"49858",
    "sg:province":"MI",
    "sg:tags":[
        "church"
    ],
    "wof:name":"Community Covenant Church",
    "wof:placetype":"venue"
},
  "geometry": {"coordinates":[-87.61843500000001,45.110199],"type":"Point"}
}