{
  "type": "Feature",
  "properties": {
    "iso:country":"US",
    "sg:address":"3515 Observatory Ln",
    "sg:city":"Holt",
    "sg:classifiers":[
        {
            "category":"Building & Trades",
            "subcategory":"Construction",
            "type":"Services"
        }
    ],
    "sg:phone":"+1 517 694 4494",
    "sg:postcode":"48842",
    "sg:province":"MI",
    "sg:tags":[
        "hanging",
        "contractor"
    ],
    "wof:name":"Fredrick Kunkel",
    "wof:placetype":"venue"
},
  "geometry": {"coordinates":[-84.485496,42.655471],"type":"Point"}
}