{
  "type": "Feature",
  "properties": {
    "iso:country":"US",
    "sg:address":"4026 Miller St",
    "sg:city":"Detroit",
    "sg:classifiers":[
        {
            "category":"Personal",
            "subcategory":"Beauty Salon",
            "type":"Services"
        }
    ],
    "sg:phone":"+1 313 922 8004",
    "sg:postcode":"48211",
    "sg:province":"MI",
    "sg:tags":[
        "shop"
    ],
    "wof:name":"Beyrouth Salon",
    "wof:placetype":"venue"
},
  "geometry": {"coordinates":[-83.040057,42.39055],"type":"Point"}
}