{
  "type": "Feature",
  "properties": {
    "iso:country":"US",
    "sg:address":"9176 Middlebelt Rd",
    "sg:city":"Livonia",
    "sg:classifiers":[
        {
            "category":"Banks & Credit Unions",
            "subcategory":"Bank",
            "type":"Services"
        }
    ],
    "sg:phone":"+1 734 427 0013",
    "sg:postcode":"48150",
    "sg:province":"MI",
    "sg:tags":[
        "state",
        "commercial"
    ],
    "wof:name":"Comerica",
    "wof:placetype":"venue"
},
  "geometry": {"coordinates":[-83.33250200000001,42.359109],"type":"Point"}
}