{
  "type": "Feature",
  "properties": {
    "iso:country":"US",
    "sg:address":"1828 Laurel Oak Dr",
    "sg:city":"Flint",
    "sg:classifiers":[
        {
            "category":"Education",
            "subcategory":"Special Training",
            "type":"Public Place"
        }
    ],
    "sg:phone":"+1 517 393 3500",
    "sg:postcode":"48507",
    "sg:province":"MI",
    "sg:tags":[
        "school",
        "specialty"
    ],
    "sg:website":"www.americanmedicalcareers.com",
    "wof:name":"American Medical Careers",
    "wof:placetype":"venue"
},
  "geometry": {"coordinates":[-83.708454,42.983074],"type":"Point"}
}