{
  "type": "Feature",
  "properties": {
    "iso:country":"US",
    "sg:address":"1477 Dix Hwy",
    "sg:city":"Lincoln Park",
    "sg:classifiers":[
        {
            "category":"Retail",
            "subcategory":"Repair Shop",
            "type":"Services"
        }
    ],
    "sg:phone":"+1 313 382 1111",
    "sg:postcode":"48146",
    "sg:province":"MI",
    "wof:name":"Sterling Electronics",
    "wof:placetype":"venue"
},
  "geometry": {"coordinates":[-83.18822400000001,42.261118],"type":"Point"}
}