{
  "type": "Feature",
  "properties": {
    "iso:country":"US",
    "sg:address":"27223 Gateway Dr W",
    "sg:city":"Farmington",
    "sg:classifiers":[
        {
            "category":"Professional",
            "subcategory":"Computer Services",
            "type":"Services"
        }
    ],
    "sg:phone":"+1 248 476 4699",
    "sg:postcode":"48334",
    "sg:province":"MI",
    "sg:tags":[
        "related"
    ],
    "wof:name":"Detroit Information Systems",
    "wof:placetype":"venue"
},
  "geometry": {"coordinates":[-83.343592,42.495974],"type":"Point"}
}