{
  "type": "Feature",
  "properties": {
    "iso:country":"US",
    "sg:address":"15963 New Holland St",
    "sg:city":"Holland",
    "sg:classifiers":[
        {
            "category":"Freight",
            "type":"Transportation"
        }
    ],
    "sg:phone":"+1 616 399 8968",
    "sg:postcode":"49424",
    "sg:province":"MI",
    "sg:tags":[
        "consultant",
        "trucking"
    ],
    "wof:name":"Mar-Mik Transport",
    "wof:placetype":"venue"
},
  "geometry": {"coordinates":[-86.17386,42.855812],"type":"Point"}
}