{
  "type": "Feature",
  "properties": {
    "iso:country":"US",
    "sg:address":"28000 Goddard Rd",
    "sg:city":"Romulus",
    "sg:classifiers":[
        {
            "category":"Transit Center",
            "subcategory":"Freight",
            "type":"Transportation"
        },
        {
            "category":"Professional",
            "subcategory":"Employment Agencies",
            "type":"Services"
        }
    ],
    "sg:phone":"+1 734 946 8750",
    "sg:postcode":"48174",
    "sg:province":"MI",
    "sg:tags":[
        "forwarding",
        "broker",
        "custom"
    ],
    "sg:website":"http://www.trans-overseas.com",
    "wof:name":"Trans Overseas Corporation",
    "wof:placetype":"venue"
},
  "geometry": {"coordinates":[-83.31155800000001,42.224735],"type":"Point"}
}