{
  "type": "Feature",
  "properties": {
    "iso:country":"US",
    "sg:address":"16163 E Q Ave",
    "sg:city":"Climax",
    "sg:classifiers":[
        {
            "category":"Professional",
            "type":"Services"
        }
    ],
    "sg:phone":"+1 269 746 4836",
    "sg:postcode":"49034",
    "sg:province":"MI",
    "wof:name":"Donlin Educational Services",
    "wof:placetype":"venue"
},
  "geometry": {"coordinates":[-85.2993,42.201956],"type":"Point"}
}