{
  "type": "Feature",
  "properties": {
    "iso:country":"US",
    "sg:address":"17200 E Warren Ave",
    "sg:city":"Detroit",
    "sg:classifiers":[
        {
            "category":"Building & Trades",
            "subcategory":"Construction",
            "type":"Services"
        }
    ],
    "sg:phone":"+1 313 640 8122",
    "sg:postcode":"48224",
    "sg:province":"MI",
    "sg:tags":[
        "drywall",
        "contractor"
    ],
    "wof:name":"Vasquez Drywall Inc",
    "wof:placetype":"venue"
},
  "geometry": {"coordinates":[-82.928938,42.406194],"type":"Point"}
}