{
  "type": "Feature",
  "properties": {
    "iso:country":"US",
    "sg:address":"904 River Ave",
    "sg:city":"Iron Mountain",
    "sg:classifiers":[
        {
            "category":"Retail",
            "subcategory":"Repair Shop",
            "type":"Services"
        },
        {
            "category":"Retail",
            "subcategory":"Auto Repair",
            "type":"Services"
        }
    ],
    "sg:phone":"+1 906 774 0344",
    "sg:postcode":"49801",
    "sg:province":"MI",
    "sg:tags":[
        "repairing",
        "automobile",
        "radiator",
        "welding"
    ],
    "wof:name":"Wickman Welding & Service Co",
    "wof:placetype":"venue"
},
  "geometry": {"coordinates":[-88.065988,45.814617],"type":"Point"}
}