{
  "type": "Feature",
  "properties": {
    "iso:country":"US",
    "sg:address":"6041 W Lennon Rd",
    "sg:city":"Swartz Creek",
    "sg:classifiers":[
        {
            "category":"Education",
            "subcategory":"Dance Studio",
            "type":"Public Place"
        }
    ],
    "sg:phone":"+1 810 635 4478",
    "sg:postcode":"48473",
    "sg:province":"MI",
    "sg:tags":[
        "instruction",
        "dancing"
    ],
    "wof:name":"Dolores' School Of Dance",
    "wof:placetype":"venue"
},
  "geometry": {"coordinates":[-83.805481,42.986957],"type":"Point"}
}