{
  "type": "Feature",
  "properties": {
    "iso:country":"US",
    "sg:address":"6035 East Rd",
    "sg:city":"Saginaw",
    "sg:classifiers":[
        {
            "category":"Travel",
            "subcategory":"Hotels & Motels",
            "type":"Entertainment"
        }
    ],
    "sg:phone":"+1 989 777 1020",
    "sg:postcode":"48601",
    "sg:province":"MI",
    "sg:tags":[
        "operation"
    ],
    "wof:name":"Paul's Motel Of Saginaw",
    "wof:placetype":"venue"
},
  "geometry": {"coordinates":[-83.953712,43.331733],"type":"Point"}
}