{
  "type": "Feature",
  "properties": {
    "iso:country":"US",
    "sg:address":"1790 Westwood Dr",
    "sg:city":"Troy",
    "sg:classifiers":[
        {
            "category":"Building & Trades",
            "subcategory":"Construction",
            "type":"Services"
        },
        {
            "category":"Building & Trades",
            "subcategory":"Landscaping Services",
            "type":"Services"
        }
    ],
    "sg:phone":"+1 248 526 1997",
    "sg:postcode":"48083",
    "sg:province":"MI",
    "sg:tags":[
        "house",
        "lawn",
        "maintenance",
        "grounds"
    ],
    "wof:name":"Doug's Mobile Home Maintenance",
    "wof:placetype":"venue"
},
  "geometry": {"coordinates":[-83.135672,42.549868],"type":"Point"}
}