{
  "type": "Feature",
  "properties": {
    "iso:country":"US",
    "sg:address":"18401 Warrington Dr",
    "sg:city":"Detroit",
    "sg:classifiers":[
        {
            "category":"Retail",
            "subcategory":"Laundry & Dry Cleaning",
            "type":"Services"
        }
    ],
    "sg:phone":"+1 313 864 2811",
    "sg:postcode":"48221",
    "sg:province":"MI",
    "sg:tags":[
        "drycleaning",
        "plant"
    ],
    "wof:name":"Neals Cleaning Service",
    "wof:placetype":"venue"
},
  "geometry": {"coordinates":[-83.13991799999999,42.428036],"type":"Point"}
}