{
  "type": "Feature",
  "properties": {
    "iso:country":"US",
    "sg:address":"9931 Briggs Hwy",
    "sg:city":"Addison",
    "sg:phone":"+1 517 547 7553",
    "sg:postcode":"49220",
    "sg:province":"MI",
    "sg:tags":[
        "wheat",
        "beef",
        "farm",
        "corn",
        "crop",
        "field",
        "cattle"
    ],
    "wof:name":"Halliwill Farms",
    "wof:placetype":"venue"
},
  "geometry": {"coordinates":[-84.344751,42.025901],"type":"Point"}
}