{
  "type": "Feature",
  "properties": {
    "iso:country":"US",
    "sg:address":"8420 Billwood Hwy",
    "sg:city":"Charlotte",
    "sg:classifiers":[
        {
            "category":"Banks & Credit Unions",
            "subcategory":"Bank",
            "type":"Services"
        }
    ],
    "sg:phone":"+1 517 267 7328",
    "sg:postcode":"48813",
    "sg:province":"MI",
    "wof:name":"State Employees Credit Union",
    "wof:placetype":"venue"
},
  "geometry": {"coordinates":[-84.67937000000001,42.669022],"type":"Point"}
}