{
  "type": "Feature",
  "properties": {
    "iso:country":"US",
    "sg:address":"147 Ruddiman Dr",
    "sg:city":"Muskegon",
    "sg:classifiers":[
        {
            "category":"Professional",
            "subcategory":"Business Services",
            "type":"Services"
        }
    ],
    "sg:phone":"+1 231 719 9353",
    "sg:postcode":"49445",
    "sg:province":"MI",
    "wof:name":"Gorc Innovative Packaging",
    "wof:placetype":"venue"
},
  "geometry": {"coordinates":[-86.30248899999999,43.245016],"type":"Point"}
}