{
  "type": "Feature",
  "properties": {
    "iso:country":"US",
    "sg:address":"677 Woods Edge Ln",
    "sg:city":"White Lake",
    "sg:classifiers":[
        {
            "category":"Personal",
            "type":"Services"
        }
    ],
    "sg:phone":"+1 248 698 7744",
    "sg:postcode":"48386",
    "sg:province":"MI",
    "wof:name":"Bam Technologies",
    "wof:placetype":"venue"
},
  "geometry": {"coordinates":[-83.45171499999999,42.633632],"type":"Point"}
}