{
  "type": "Feature",
  "properties": {
    "iso:country":"US",
    "sg:address":"515 Wayne St",
    "sg:city":"Niles",
    "sg:classifiers":[
        {
            "category":"Retail",
            "subcategory":"Auto Repair",
            "type":"Services"
        }
    ],
    "sg:phone":"+1 269 683 3727",
    "sg:postcode":"49120",
    "sg:province":"MI",
    "sg:tags":[
        "automotive"
    ],
    "wof:name":"Dexters Wayne Street Auto",
    "wof:placetype":"venue"
},
  "geometry": {"coordinates":[-86.25256899999999,41.835744],"type":"Point"}
}