{
  "type": "Feature",
  "properties": {
    "iso:country":"US",
    "sg:address":"32040 W M 28",
    "sg:city":"Eckerman",
    "sg:classifiers":[
        {
            "category":"Real Estate",
            "subcategory":"Real Estate Agent",
            "type":"Services"
        }
    ],
    "sg:phone":"+1 906 274 5405",
    "sg:postcode":"49728",
    "sg:province":"MI",
    "wof:name":"Line Credit Property V LLC",
    "wof:placetype":"venue"
},
  "geometry": {"coordinates":[-85.031688,46.345398],"type":"Point"}
}