{
  "type": "Feature",
  "properties": {
    "iso:country":"US",
    "sg:address":"6490 Sprinkle Rd",
    "sg:city":"Portage",
    "sg:classifiers":[
        {
            "category":"Wholesale",
            "subcategory":"Stationery",
            "type":"Manufacturing & Wholesale Goods"
        }
    ],
    "sg:phone":"+1 269 323 1333",
    "sg:postcode":"49002",
    "sg:province":"MI",
    "sg:tags":[
        "business",
        "form",
        "system"
    ],
    "wof:name":"Superior Business Solutions",
    "wof:placetype":"venue"
},
  "geometry": {"coordinates":[-85.54060800000001,42.229809],"type":"Point"}
}