{
  "type": "Feature",
  "properties": {
    "iso:country":"US",
    "sg:address":"5625 Fox Ridge Dr",
    "sg:city":"Clarkston",
    "sg:classifiers":[
        {
            "category":"Building & Trades",
            "subcategory":"Construction",
            "type":"Services"
        }
    ],
    "sg:phone":"+1 248 393 7700",
    "sg:postcode":"48348",
    "sg:province":"MI",
    "sg:tags":[
        "contractor"
    ],
    "wof:name":"Fenton Harbor Homes Inc",
    "wof:placetype":"venue"
},
  "geometry": {"coordinates":[-83.335821,42.726563],"type":"Point"}
}