{
  "type": "Feature",
  "properties": {
    "iso:country":"US",
    "sg:address":"16342 Forest Hill Rd",
    "sg:city":"Grand Ledge",
    "sg:classifiers":[
        {
            "category":"Retail",
            "subcategory":"Laundry & Dry Cleaning",
            "type":"Services"
        }
    ],
    "sg:phone":"+1 517 627 1414",
    "sg:postcode":"48837",
    "sg:province":"MI",
    "sg:tags":[
        "cleaners",
        "rug",
        "carpet"
    ],
    "wof:name":"L & N Carpet Cleaning",
    "wof:placetype":"venue"
},
  "geometry": {"coordinates":[-84.68141300000001,42.786722],"type":"Point"}
}