{
  "type": "Feature",
  "properties": {
    "iso:country":"US",
    "sg:address":"14311 W Warren Ave",
    "sg:city":"Dearborn",
    "sg:classifiers":[
        {
            "category":"Transit Center",
            "subcategory":"Freight",
            "type":"Transportation"
        }
    ],
    "sg:phone":"+1 313 943 3614",
    "sg:postcode":"48126",
    "sg:province":"MI",
    "sg:tags":[
        "forwarding"
    ],
    "wof:name":"Seastar",
    "wof:placetype":"venue"
},
  "geometry": {"coordinates":[-83.183048,42.343889],"type":"Point"}
}