{
  "type": "Feature",
  "properties": {
    "iso:country":"US",
    "sg:address":"6275 28th St SE",
    "sg:city":"Grand Rapids",
    "sg:classifiers":[
        {
            "category":"Coffee & Tea",
            "type":"Food & Drink"
        }
    ],
    "sg:menulink":"http://www.allmenus.com/mi/cascade/248937-beaners/menu/",
    "sg:phone":"+1 616 957 2326",
    "sg:postcode":"49546",
    "sg:province":"MI",
    "sg:tags":[
        "american"
    ],
    "wof:name":"Beaners",
    "wof:placetype":"venue"
},
  "geometry": {"coordinates":[-85.51390000000001,42.913099],"type":"Point"}
}