{
  "type": "Feature",
  "properties": {
    "iso:country":"US",
    "sg:address":"24275 Novi Rd",
    "sg:city":"Novi",
    "sg:classifiers":[
        {
            "category":"Health Services",
            "subcategory":"Doctor",
            "type":"Services"
        }
    ],
    "sg:phone":"+1 248 347 3030",
    "sg:postcode":"48375",
    "sg:province":"MI",
    "sg:tags":[
        "dentist"
    ],
    "wof:name":"Novi Oaks Dental Associates",
    "wof:placetype":"venue"
},
  "geometry": {"coordinates":[-83.475167,42.472665],"type":"Point"}
}