{
  "type": "Feature",
  "properties": {
    "iso:country":"US",
    "sg:address":"515 S Main St",
    "sg:city":"Vicksburg",
    "sg:classifiers":[
        {
            "category":"Recreation",
            "subcategory":"Campground",
            "type":"Entertainment"
        }
    ],
    "sg:phone":"+1 269 646 3336",
    "sg:postcode":"49097",
    "sg:province":"MI",
    "sg:tags":[
        "recreational",
        "park",
        "vehicle"
    ],
    "wof:name":"Cranberry Lake Campground",
    "wof:placetype":"venue"
},
  "geometry": {"coordinates":[-85.532342,42.115217],"type":"Point"}
}