{
  "type": "Feature",
  "properties": {
    "iso:country":"US",
    "sg:address":"5366 E Boardman Rd",
    "sg:city":"South Boardman",
    "sg:classifiers":[
        {
            "category":"Retail",
            "subcategory":"Portrait Studio",
            "type":"Services"
        }
    ],
    "sg:phone":"+1 231 369 2644",
    "sg:postcode":"49680",
    "sg:province":"MI",
    "sg:tags":[
        "photographer",
        "photo"
    ],
    "sg:website":"www.michiganphotographer.com",
    "wof:name":"Northern Exposures Photography",
    "wof:placetype":"venue"
},
  "geometry": {"coordinates":[-85.279707,44.641389],"type":"Point"}
}