{
  "type": "Feature",
  "properties": {
    "iso:country":"US",
    "sg:address":"4560 Cherokee Ln",
    "sg:city":"Bloomfield Hills",
    "sg:classifiers":[
        {
            "category":"Education",
            "subcategory":"Special Training",
            "type":"Public Place"
        }
    ],
    "sg:phone":"+1 248 865 9580",
    "sg:postcode":"48301",
    "sg:province":"MI",
    "sg:tags":[
        "educational"
    ],
    "wof:name":"Nextgen Education Corp",
    "wof:placetype":"venue"
},
  "geometry": {"coordinates":[-83.306074,42.545466],"type":"Point"}
}