{
  "type": "Feature",
  "properties": {
    "iso:country":"US",
    "sg:address":"3501 Woodward Ave Ofc",
    "sg:city":"Detroit",
    "sg:classifiers":[
        {
            "category":"Real Estate",
            "subcategory":"Real Estate Operator",
            "type":"Services"
        }
    ],
    "sg:phone":"+1 313 831 6643",
    "sg:postcode":"48201",
    "sg:province":"MI",
    "sg:tags":[
        "apartment"
    ],
    "wof:name":"Arcadia Apts",
    "wof:placetype":"venue"
},
  "geometry": {"coordinates":[-83.05729700000001,42.346401],"type":"Point"}
}