{
  "type": "Feature",
  "properties": {
    "iso:country":"US",
    "sg:address":"5905 Grand Haven Rd",
    "sg:city":"Muskegon",
    "sg:classifiers":[
        {
            "category":"Shopping",
            "subcategory":"Used Merchandise",
            "type":"Retail Goods"
        }
    ],
    "sg:phone":"+1 231 798 6441",
    "sg:postcode":"49441",
    "sg:province":"MI",
    "sg:tags":[
        "antique"
    ],
    "wof:name":"Muskegon Antique Mall",
    "wof:placetype":"venue"
},
  "geometry": {"coordinates":[-86.220713,43.14347],"type":"Point"}
}