{
  "type": "Feature",
  "properties": {
    "iso:country":"US",
    "sg:address":"3505 Wixson Rd",
    "sg:city":"Croswell",
    "sg:classifiers":[
        {
            "category":"Building & Trades",
            "subcategory":"Construction",
            "type":"Services"
        }
    ],
    "sg:phone":"+1 810 679 2687",
    "sg:postcode":"48422",
    "sg:province":"MI",
    "sg:tags":[
        "home",
        "improvement"
    ],
    "wof:name":"Hawks High Quality Svc",
    "wof:placetype":"venue"
},
  "geometry": {"coordinates":[-82.574292,43.324515],"type":"Point"}
}