{
  "type": "Feature",
  "properties": {
    "iso:country":"US",
    "sg:address":"225 S Main St",
    "sg:city":"Rochester",
    "sg:classifiers":[
        {
            "category":"Food & Beverages",
            "subcategory":"Bakery",
            "type":"Retail Goods"
        }
    ],
    "sg:phone":"+1 248 650 1954",
    "sg:postcode":"48307",
    "sg:province":"MI",
    "sg:tags":[
        "baker"
    ],
    "sg:website":"www.givethanksbakery.com",
    "wof:name":"Give Thanks Bakery & Cafe",
    "wof:placetype":"venue"
},
  "geometry": {"coordinates":[-83.13379500000001,42.679104],"type":"Point"}
}