{
  "type": "Feature",
  "properties": {
    "iso:country":"US",
    "sg:address":"399 S Lafayette St",
    "sg:city":"South Lyon",
    "sg:classifiers":[
        {
            "category":"Restaurant",
            "type":"Food & Drink"
        }
    ],
    "sg:phone":"+1 248 437 6376",
    "sg:postcode":"48178",
    "sg:province":"MI",
    "wof:name":"Brown's Root Beer & Sandwich",
    "wof:placetype":"venue"
},
  "geometry": {"coordinates":[-83.65112000000001,42.456682],"type":"Point"}
}