{
  "type": "Feature",
  "properties": {
    "iso:country":"US",
    "sg:address":"8916 Division Rd",
    "sg:city":"Columbus",
    "sg:classifiers":[
        {
            "category":"Professional",
            "type":"Services"
        }
    ],
    "sg:phone":"+1 586 727 6999",
    "sg:postcode":"48063",
    "sg:province":"MI",
    "sg:tags":[
        "establishment"
    ],
    "wof:name":"Katron Co",
    "wof:placetype":"venue"
},
  "geometry": {"coordinates":[-82.668015,42.811645],"type":"Point"}
}