{
  "type": "Feature",
  "properties": {
    "iso:country":"US",
    "sg:address":"3286 Middle Rd",
    "sg:city":"Harbor Springs",
    "sg:classifiers":[
        {
            "category":"Shopping",
            "subcategory":"Shoes",
            "type":"Retail Goods"
        }
    ],
    "sg:phone":"+1 231 526 6130",
    "sg:postcode":"49740",
    "sg:province":"MI",
    "wof:name":"Lauretta Reiss",
    "wof:placetype":"venue"
},
  "geometry": {"coordinates":[-84.98151799999999,45.464344],"type":"Point"}
}