{
  "type": "Feature",
  "properties": {
    "iso:country":"US",
    "sg:address":"30300 Hoover Ste 200",
    "sg:city":"Warren",
    "sg:classifiers":[
        {
            "category":"Health Services",
            "subcategory":"Optometrist",
            "type":"Services"
        }
    ],
    "sg:phone":"+1 586 573 3937",
    "sg:postcode":"48093",
    "sg:province":"MI",
    "sg:tags":[
        "laser",
        "eye",
        "surgery/lasik"
    ],
    "sg:website":"www.adelsoneye.com",
    "wof:name":"Adelson Eye & Laser Center",
    "wof:placetype":"venue"
},
  "geometry": {"coordinates":[-83.00733200000001,42.516101],"type":"Point"}
}