{
  "type": "Feature",
  "properties": {
    "iso:country":"US",
    "sg:address":"2243 33rd St",
    "sg:city":"Allegan",
    "sg:classifiers":[
        {
            "category":"Government",
            "subcategory":"Court House",
            "type":"Public Place"
        }
    ],
    "sg:phone":"+1 269 673 0250",
    "sg:postcode":"49010",
    "sg:province":"MI",
    "sg:tags":[
        "county"
    ],
    "wof:name":"Probate Court",
    "wof:placetype":"venue"
},
  "geometry": {"coordinates":[-85.86961100000001,42.58729],"type":"Point"}
}