{
  "type": "Feature",
  "properties": {
    "iso:country":"US",
    "sg:address":"23077 Greenfield Rd Ste 557",
    "sg:city":"Southfield",
    "sg:classifiers":[
        {
            "category":"Professional",
            "subcategory":"Lawyer & Legal Services",
            "type":"Services"
        }
    ],
    "sg:phone":"+1 248 557 1155",
    "sg:postcode":"48075",
    "sg:province":"MI",
    "wof:name":"Zamler Mellen & Shiffman PC",
    "wof:placetype":"venue"
},
  "geometry": {"coordinates":[-83.201302,42.460499],"type":"Point"}
}