{
  "type": "Feature",
  "properties": {
    "iso:country":"US",
    "sg:address":"129 Franklin St",
    "sg:city":"Hancock",
    "sg:classifiers":[
        {
            "category":"Manufacturing",
            "subcategory":"Printing",
            "type":"Manufacturing & Wholesale Goods"
        }
    ],
    "sg:phone":"+1 906 482 1250",
    "sg:postcode":"49930",
    "sg:province":"MI",
    "sg:tags":[
        "commercial"
    ],
    "wof:name":"Book Concern Printers",
    "wof:placetype":"venue"
},
  "geometry": {"coordinates":[-88.579363,47.127858],"type":"Point"}
}