{
  "type": "Feature",
  "properties": {
    "iso:country":"US",
    "sg:address":"173 S Mielens Rd",
    "sg:city":"Munger",
    "sg:classifiers":[
        {
            "category":"Retail",
            "subcategory":"Auto Repair",
            "type":"Services"
        }
    ],
    "sg:phone":"+1 989 892 4718",
    "sg:postcode":"48747",
    "sg:province":"MI",
    "sg:tags":[
        "transmission",
        "automotive",
        "road",
        "general"
    ],
    "wof:name":"Northern Mobile Truck Repair",
    "wof:placetype":"venue"
},
  "geometry": {"coordinates":[-83.76866200000001,43.562912],"type":"Point"}
}