{
  "type": "Feature",
  "properties": {
    "iso:country":"US",
    "sg:address":"850 S State St",
    "sg:city":"Saint Ignace",
    "sg:classifiers":[
        {
            "category":"Social Services",
            "subcategory":"Child Care",
            "type":"Services"
        }
    ],
    "sg:phone":"+1 906 643 7134",
    "sg:postcode":"49781",
    "sg:province":"MI",
    "sg:tags":[
        "day"
    ],
    "wof:name":"Patsy Wyers",
    "wof:placetype":"venue"
},
  "geometry": {"coordinates":[-84.70769300000001,45.85864],"type":"Point"}
}