{
  "type": "Feature",
  "properties": {
    "iso:country":"US",
    "sg:address":"281 Hastings Ave",
    "sg:city":"Benton Harbor",
    "sg:classifiers":[
        {
            "category":"Building & Trades",
            "subcategory":"Cleaning & Sanitation",
            "type":"Services"
        }
    ],
    "sg:phone":"+1 269 926 8210",
    "sg:postcode":"49022",
    "sg:province":"MI",
    "sg:tags":[
        "window"
    ],
    "wof:name":"Rite Now Window Cleaning Svc",
    "wof:placetype":"venue"
},
  "geometry": {"coordinates":[-86.459424,42.100821],"type":"Point"}
}