{
  "type": "Feature",
  "properties": {
    "iso:country":"US",
    "sg:address":"Livonia Mall",
    "sg:city":"Livonia",
    "sg:classifiers":[
        {
            "category":"Sports & Exercise",
            "subcategory":"Sports Center",
            "type":"Entertainment"
        }
    ],
    "sg:phone":"+1 248 471 1800",
    "sg:postcode":"48150",
    "sg:province":"MI",
    "sg:tags":[
        "amateur",
        "team"
    ],
    "wof:name":"Futureball Paintball Indoor Fortress & Proshop",
    "wof:placetype":"venue"
},
  "geometry": {"coordinates":[-83.369698,42.363602],"type":"Point"}
}