{
  "type": "Feature",
  "properties": {
    "iso:country":"US",
    "sg:address":"2524 Vanness St",
    "sg:city":"Port Huron",
    "sg:classifiers":[
        {
            "category":"Social Services",
            "type":"Services"
        }
    ],
    "sg:phone":"+1 810 989 7667",
    "sg:postcode":"48060",
    "sg:province":"MI",
    "sg:tags":[
        "youth",
        "organization",
        "center"
    ],
    "wof:name":"SONS Outreach Ctr",
    "wof:placetype":"venue"
},
  "geometry": {"coordinates":[-82.452628,42.946086],"type":"Point"}
}