{
  "type": "Feature",
  "properties": {
    "iso:country":"US",
    "sg:address":"501 Chanticleer Trl",
    "sg:city":"Lansing",
    "sg:classifiers":[
        {
            "category":"Professional",
            "type":"Services"
        }
    ],
    "sg:phone":"+1 517 321 4934",
    "sg:postcode":"48917",
    "sg:province":"MI",
    "wof:name":"Barrier Support Services",
    "wof:placetype":"venue"
},
  "geometry": {"coordinates":[-84.628063,42.731273],"type":"Point"}
}