{
  "type": "Feature",
  "properties": {
    "iso:country":"US",
    "sg:address":"27126 Sutherland St",
    "sg:city":"Southfield",
    "sg:classifiers":[
        {
            "category":"Banks & Credit Unions",
            "subcategory":"Investment Brokerage",
            "type":"Services"
        }
    ],
    "sg:phone":"+1 248 423 9708",
    "sg:postcode":"48076",
    "sg:province":"MI",
    "wof:name":"Merger One Investments",
    "wof:placetype":"venue"
},
  "geometry": {"coordinates":[-83.210284,42.489746],"type":"Point"}
}