{
  "type": "Feature",
  "properties": {
    "iso:country":"US",
    "sg:address":"15074 Mercury Dr",
    "sg:city":"Grand Haven",
    "sg:classifiers":[
        {
            "category":"Shopping",
            "subcategory":"Discount & Variety Stores",
            "type":"Retail Goods"
        }
    ],
    "sg:phone":"+1 616 842 8835",
    "sg:postcode":"49417",
    "sg:province":"MI",
    "sg:tags":[
        "merchandise",
        "general"
    ],
    "wof:name":"Roger Hartman",
    "wof:placetype":"venue"
},
  "geometry": {"coordinates":[-86.161694,43.032936],"type":"Point"}
}