{
  "type": "Feature",
  "properties": {
    "iso:country":"US",
    "sg:address":"4251 Locust Valley Ln",
    "sg:city":"Oxford",
    "sg:classifiers":[
        {
            "category":"Farming",
            "subcategory":"Farm",
            "type":"Manufacturing & Wholesale Goods"
        }
    ],
    "sg:phone":"+1 248 969 3063",
    "sg:postcode":"48370",
    "sg:province":"MI",
    "sg:tags":[
        "crop",
        "general"
    ],
    "wof:name":"Crinkly Bottom Farm",
    "wof:placetype":"venue"
},
  "geometry": {"coordinates":[-83.220304,42.85999],"type":"Point"}
}