{
  "type": "Feature",
  "properties": {
    "iso:country":"US",
    "sg:address":"474 Marlane St",
    "sg:city":"Muskegon",
    "sg:classifiers":[
        {
            "category":"Social Services",
            "subcategory":"Child Care",
            "type":"Services"
        },
        {
            "category":"Social Services",
            "type":"Services"
        }
    ],
    "sg:phone":"+1 231 773 2171",
    "sg:postcode":"49442",
    "sg:province":"MI",
    "sg:tags":[
        "guidance",
        "day"
    ],
    "wof:name":"I'm Thumbody Special Ink",
    "wof:placetype":"venue"
},
  "geometry": {"coordinates":[-86.19193300000001,43.242969],"type":"Point"}
}