{
  "type": "Feature",
  "properties": {
    "iso:country":"US",
    "sg:address":"48 E Center St",
    "sg:city":"Douglas",
    "sg:classifiers":[
        {
            "category":"Restaurant",
            "type":"Food & Drink"
        }
    ],
    "sg:phone":"+1 269 857 5411",
    "sg:postcode":"49406",
    "sg:province":"MI",
    "sg:tags":[
        "shop",
        "coffee"
    ],
    "wof:name":"Respite",
    "wof:placetype":"venue"
},
  "geometry": {"coordinates":[-86.200469,42.643744],"type":"Point"}
}