{
  "type": "Feature",
  "properties": {
    "iso:country":"US",
    "sg:address":"1687 S Riverside Ave",
    "sg:city":"Saint Clair",
    "sg:classifiers":[
        {
            "category":"Real Estate",
            "subcategory":"Real Estate Operator",
            "type":"Services"
        }
    ],
    "sg:phone":"+1 248 673 1622",
    "sg:postcode":"48079",
    "sg:province":"MI",
    "sg:tags":[
        "building",
        "apartment"
    ],
    "wof:name":"Marion Apartments",
    "wof:placetype":"venue"
},
  "geometry": {"coordinates":[-82.48847000000001,42.807591],"type":"Point"}
}