{
  "type": "Feature",
  "properties": {
    "iso:country":"US",
    "sg:address":"125 Washington St",
    "sg:city":"Prescott",
    "sg:classifiers":[
        {
            "category":"Health Services",
            "subcategory":"Doctor",
            "type":"Services"
        }
    ],
    "sg:phone":"+1 989 873 3352",
    "sg:postcode":"48756",
    "sg:province":"MI",
    "sg:tags":[
        "physician",
        "surgeon"
    ],
    "wof:name":"Prescott Clinic Inc",
    "wof:placetype":"venue"
},
  "geometry": {"coordinates":[-83.930387,44.192538],"type":"Point"}
}