{
  "type": "Feature",
  "properties": {
    "iso:country":"US",
    "sg:address":"14470 Livernois Ave",
    "sg:city":"Detroit",
    "sg:classifiers":[
        {
            "category":"Cinema",
            "subcategory":"Movie Rental",
            "type":"Entertainment"
        }
    ],
    "sg:phone":"+1 313 862 5910",
    "sg:postcode":"48238",
    "sg:province":"MI",
    "sg:tags":[
        "video",
        "tape"
    ],
    "wof:name":"Video Cave",
    "wof:placetype":"venue"
},
  "geometry": {"coordinates":[-83.139848,42.394942],"type":"Point"}
}