{
  "type": "Feature",
  "properties": {
    "iso:country":"US",
    "sg:address":"212 W 6th St",
    "sg:city":"Clare",
    "sg:classifiers":[
        {
            "category":"Health Services",
            "subcategory":"Doctor",
            "type":"Services"
        }
    ],
    "sg:phone":"+1 989 802 5030",
    "sg:postcode":"48617",
    "sg:province":"MI",
    "sg:tags":[
        "osteopathic"
    ],
    "wof:name":"David L Bremer Do",
    "wof:placetype":"venue"
},
  "geometry": {"coordinates":[-84.77225900000001,43.820654],"type":"Point"}
}