{
  "type": "Feature",
  "properties": {
    "iso:country":"US",
    "sg:address":"1615 Monroe St",
    "sg:city":"Saginaw",
    "sg:classifiers":[
        {
            "category":"Building & Trades",
            "subcategory":"Cleaning & Sanitation",
            "type":"Services"
        }
    ],
    "sg:phone":"+1 989 792 1687",
    "sg:postcode":"48602",
    "sg:province":"MI",
    "sg:tags":[
        "maintenance"
    ],
    "wof:name":"High Gloss",
    "wof:placetype":"venue"
},
  "geometry": {"coordinates":[-83.96863,43.42806],"type":"Point"}
}