{
  "type": "Feature",
  "properties": {
    "iso:country":"US",
    "sg:address":"5585 Cozy Point Dr",
    "sg:city":"Newaygo",
    "sg:classifiers":[
        {
            "category":"Organizations",
            "subcategory":"Community Association",
            "type":"Services"
        }
    ],
    "sg:phone":"+1 231 652 9908",
    "sg:postcode":"49337",
    "sg:province":"MI",
    "wof:name":"Voiture Nationale La Societe",
    "wof:placetype":"venue"
},
  "geometry": {"coordinates":[-85.657646,43.453326],"type":"Point"}
}