{
  "type": "Feature",
  "properties": {
    "iso:country":"US",
    "sg:address":"5039 Comstock Ave",
    "sg:city":"Kalamazoo",
    "sg:classifiers":[
        {
            "category":"Banks & Credit Unions",
            "subcategory":"Bank",
            "type":"Services"
        }
    ],
    "sg:phone":"+1 269 382 9859",
    "sg:postcode":"49048",
    "sg:province":"MI",
    "sg:tags":[
        "federal"
    ],
    "sg:website":"www.1ft.com.org",
    "wof:name":"First Community Federal Cr Un",
    "wof:placetype":"venue"
},
  "geometry": {"coordinates":[-85.52542200000001,42.283737],"type":"Point"}
}