{
  "type": "Feature",
  "properties": {
    "iso:country":"US",
    "sg:address":"15130 Inkster Rd",
    "sg:city":"Redford",
    "sg:classifiers":[
        {
            "category":"Coffee & Tea",
            "type":"Food & Drink"
        }
    ],
    "sg:phone":"+1 313 255 4200",
    "sg:postcode":"48239",
    "sg:province":"MI",
    "sg:website":"www.firstcuporganiccoffee.com/",
    "wof:name":"First Cup Organic Coffee Shop",
    "wof:placetype":"venue"
},
  "geometry": {"coordinates":[-83.314891,42.397893],"type":"Point"}
}