{
  "type": "Feature",
  "properties": {
    "iso:country":"US",
    "sg:address":"506 Parkdale Ave",
    "sg:city":"Royal Oak",
    "sg:classifiers":[
        {
            "category":"Shopping",
            "subcategory":"Computers & Home Electronics",
            "type":"Retail Goods"
        }
    ],
    "sg:phone":"+1 248 547 9076",
    "sg:postcode":"48073",
    "sg:province":"MI",
    "sg:website":"www.castleavi.com",
    "wof:name":"Castle A V I",
    "wof:placetype":"venue"
},
  "geometry": {"coordinates":[-83.13856199999999,42.50986],"type":"Point"}
}