{
  "type": "Feature",
  "properties": {
    "iso:country":"US",
    "sg:address":"1707 Georgetown Blvd",
    "sg:city":"Lansing",
    "sg:classifiers":[
        {
            "category":"Social Services",
            "subcategory":"Child Care",
            "type":"Services"
        }
    ],
    "sg:phone":"+1 517 393 0627",
    "sg:postcode":"48911",
    "sg:province":"MI",
    "sg:tags":[
        "day"
    ],
    "wof:name":"Price Tari",
    "wof:placetype":"venue"
},
  "geometry": {"coordinates":[-84.575688,42.664273],"type":"Point"}
}