{
  "type": "Feature",
  "properties": {
    "iso:country":"US",
    "sg:address":"251 8 Mile Rd",
    "sg:city":"Linwood",
    "sg:classifiers":[
        {
            "category":"Home & Garden",
            "subcategory":"Home Furnishings",
            "type":"Retail Goods"
        }
    ],
    "sg:phone":"+1 989 697 3356",
    "sg:postcode":"48634",
    "sg:province":"MI",
    "wof:name":"Rms Custom Curtains",
    "wof:placetype":"venue"
},
  "geometry": {"coordinates":[-84.702539,44.428488],"type":"Point"}
}