{
  "type": "Feature",
  "properties": {
    "iso:country":"US",
    "sg:address":"2241 W Vienna Rd",
    "sg:city":"Clio",
    "sg:classifiers":[
        {
            "category":"Shopping",
            "subcategory":"Crafts & Fabrics",
            "type":"Retail Goods"
        }
    ],
    "sg:phone":"+1 810 686 6018",
    "sg:postcode":"48420",
    "sg:province":"MI",
    "sg:tags":[
        "shop"
    ],
    "sg:website":"www.joann.com",
    "wof:name":"Jo-Ann Fabrics & Crafts",
    "wof:placetype":"venue"
},
  "geometry": {"coordinates":[-83.718705,43.177555],"type":"Point"}
}