{
  "type": "Feature",
  "properties": {
    "iso:country":"US",
    "sg:address":"1725 Willard Ave SE",
    "sg:city":"Grand Rapids",
    "sg:classifiers":[
        {
            "category":"Building & Trades",
            "subcategory":"Construction",
            "type":"Services"
        }
    ],
    "sg:phone":"+1 616 241 0499",
    "sg:postcode":"49507",
    "sg:province":"MI",
    "sg:tags":[
        "hanging",
        "contractor"
    ],
    "wof:name":"Brooks Commercial Paintin",
    "wof:placetype":"venue"
},
  "geometry": {"coordinates":[-85.652124,42.931397],"type":"Point"}
}