{
  "type": "Feature",
  "properties": {
    "iso:country":"US",
    "sg:address":"7350 Grand River Ave",
    "sg:city":"Detroit",
    "sg:classifiers":[
        {
            "category":"Shopping",
            "subcategory":"Pharmacy",
            "type":"Retail Goods"
        }
    ],
    "sg:phone":"+1 313 895 0357",
    "sg:postcode":"48204",
    "sg:province":"MI",
    "sg:tags":[
        "drugstore"
    ],
    "wof:name":"Fraser Drug Inc",
    "wof:placetype":"venue"
},
  "geometry": {"coordinates":[-83.12220000000001,42.362],"type":"Point"}
}