{
  "type": "Feature",
  "properties": {
    "iso:country":"US",
    "sg:address":"600 E Lakeshore Dr",
    "sg:city":"Houghton",
    "sg:classifiers":[
        {
            "category":"Utilities",
            "subcategory":"Electric",
            "type":"Services"
        }
    ],
    "sg:phone":"+1 906 483 4500",
    "sg:postcode":"49931",
    "sg:province":"MI",
    "sg:tags":[
        "company"
    ],
    "wof:name":"Upper Peninsula Power Co",
    "wof:placetype":"venue"
},
  "geometry": {"coordinates":[-88.56689,47.122431],"type":"Point"}
}