{
  "type": "Feature",
  "properties": {
    "iso:country":"US",
    "sg:address":"9429 N Dort Hwy",
    "sg:city":"Mt Morris",
    "sg:classifiers":[
        {
            "category":"Professional",
            "subcategory":"Computer Services",
            "type":"Services"
        }
    ],
    "sg:phone":"+1 810 687 8718",
    "sg:postcode":"48458",
    "sg:province":"MI",
    "sg:tags":[
        "repair"
    ],
    "wof:name":"K J Solutions",
    "wof:placetype":"venue"
},
  "geometry": {"coordinates":[-83.69145399999999,43.146357],"type":"Point"}
}