{
  "type": "Feature",
  "properties": {
    "iso:country":"US",
    "sg:address":"21370 Cass Ave",
    "sg:city":"Clinton Twp",
    "sg:classifiers":[
        {
            "category":"Personal",
            "subcategory":"Beauty Salon",
            "type":"Services"
        }
    ],
    "sg:phone":"+1 586 954 9993",
    "sg:postcode":"48036",
    "sg:province":"MI",
    "sg:tags":[
        "shop",
        "manicuring"
    ],
    "wof:name":"Pro Touch Nail Salon",
    "wof:placetype":"venue"
},
  "geometry": {"coordinates":[-82.901667,42.599258],"type":"Point"}
}