{
  "type": "Feature",
  "properties": {
    "iso:country":"US",
    "sg:address":"2777 W Bloomfield Oaks Dr",
    "sg:city":"West Bloomfield",
    "sg:classifiers":[
        {
            "category":"Banks & Credit Unions",
            "subcategory":"Bank",
            "type":"Services"
        }
    ],
    "sg:phone":"+1 248 682 3267",
    "sg:postcode":"48324",
    "sg:province":"MI",
    "sg:tags":[
        "company",
        "investment"
    ],
    "wof:name":"Americo Investment Company Ltd",
    "wof:placetype":"venue"
},
  "geometry": {"coordinates":[-83.42496,42.594429],"type":"Point"}
}