{
  "type": "Feature",
  "properties": {
    "iso:country":"US",
    "sg:address":"7760 20th Ave",
    "sg:city":"Jenison",
    "sg:classifiers":[
        {
            "category":"Personal",
            "subcategory":"Beauty Salon",
            "type":"Services"
        }
    ],
    "sg:phone":"+1 616 667 3155",
    "sg:postcode":"49428",
    "sg:province":"MI",
    "sg:tags":[
        "manicuring"
    ],
    "wof:name":"Hollywood Nails",
    "wof:placetype":"venue"
},
  "geometry": {"coordinates":[-85.831855,42.907309],"type":"Point"}
}