{
  "type": "Feature",
  "properties": {
    "iso:country":"US",
    "sg:address":"22616 Petersburg Ave",
    "sg:city":"Eastpointe",
    "sg:classifiers":[
        {
            "category":"Social Services",
            "subcategory":"Child Care",
            "type":"Services"
        }
    ],
    "sg:phone":"+1 586 771 0901",
    "sg:postcode":"48021",
    "sg:province":"MI",
    "sg:tags":[
        "day"
    ],
    "wof:name":"B & E Childcare Center Inc",
    "wof:placetype":"venue"
},
  "geometry": {"coordinates":[-82.925586,42.465293],"type":"Point"}
}