{
  "type": "Feature",
  "properties": {
    "iso:country":"US",
    "sg:address":"200 N Main St",
    "sg:city":"Roscommon",
    "sg:classifiers":[
        {
            "category":"Cinema",
            "subcategory":"Movie Theater",
            "type":"Entertainment"
        }
    ],
    "sg:phone":"+1 989 275 5959",
    "sg:postcode":"48653",
    "sg:province":"MI",
    "sg:tags":[
        "motion",
        "picture"
    ],
    "wof:name":"Roscommon Cinema Inc",
    "wof:placetype":"venue"
},
  "geometry": {"coordinates":[-84.593733,44.500606],"type":"Point"}
}