{
  "type": "Feature",
  "properties": {
    "iso:country":"US",
    "sg:address":"26442 Haggerty Rd",
    "sg:city":"Farmington Hills",
    "sg:classifiers":[
        {
            "category":"Professional",
            "subcategory":"Business Services",
            "type":"Services"
        }
    ],
    "sg:phone":"+1 248 489 9240",
    "sg:postcode":"48331",
    "sg:province":"MI",
    "sg:tags":[
        "interior",
        "consultant",
        "design",
        "decorator"
    ],
    "sg:website":"www.offconn.com",
    "wof:name":"Office Connection the",
    "wof:placetype":"venue"
},
  "geometry": {"coordinates":[-83.435699,42.487701],"type":"Point"}
}