{
  "type": "Feature",
  "properties": {
    "iso:country":"US",
    "sg:address":"3437 Dale Dr",
    "sg:city":"Wayland",
    "sg:classifiers":[
        {
            "category":"Retail",
            "subcategory":"Laundry & Dry Cleaning",
            "type":"Services"
        }
    ],
    "sg:phone":"+1 616 877 3425",
    "sg:postcode":"49348",
    "sg:province":"MI",
    "sg:tags":[
        "cleaners",
        "rug",
        "carpet"
    ],
    "wof:name":"Tru-Clean All Star Cleaning",
    "wof:placetype":"venue"
},
  "geometry": {"coordinates":[-85.61965499999999,42.670415],"type":"Point"}
}