{
  "type": "Feature",
  "properties": {
    "iso:country":"US",
    "sg:address":"17400 Cedar Lake Cir",
    "sg:city":"Northville",
    "sg:classifiers":[
        {
            "category":"Real Estate",
            "subcategory":"Real Estate Agent",
            "type":"Services"
        }
    ],
    "sg:phone":"+1 248 348 1830",
    "sg:postcode":"48168",
    "sg:province":"MI",
    "sg:tags":[
        "manager",
        "multiple",
        "housing"
    ],
    "wof:name":"Cedar Lake",
    "wof:placetype":"venue"
},
  "geometry": {"coordinates":[-83.46686200000001,42.413025],"type":"Point"}
}