{
  "type": "Feature",
  "properties": {
    "iso:country":"US",
    "sg:address":"4528 W US Hwy 10",
    "sg:city":"Ludington",
    "sg:classifiers":[
        {
            "category":"Food & Beverages",
            "subcategory":"Groceries & Convenience Stores",
            "type":"Retail Goods"
        }
    ],
    "sg:phone":"+1 231 845 1060",
    "sg:postcode":"49431",
    "sg:province":"MI",
    "wof:name":"Freeway EZ Mart",
    "wof:placetype":"venue"
},
  "geometry": {"coordinates":[-86.393995,43.95562],"type":"Point"}
}