{
  "type": "Feature",
  "properties": {
    "iso:country":"US",
    "sg:address":"709 Lake Ave",
    "sg:city":"Grand Haven",
    "sg:classifiers":[
        {
            "category":"Social Services",
            "subcategory":"Child Care",
            "type":"Services"
        }
    ],
    "sg:phone":"+1 616 842 6847",
    "sg:postcode":"49417",
    "sg:province":"MI",
    "sg:tags":[
        "day"
    ],
    "wof:name":"Donna Vanhall",
    "wof:placetype":"venue"
},
  "geometry": {"coordinates":[-86.233023,43.057095],"type":"Point"}
}