{
  "type": "Feature",
  "properties": {
    "iso:country":"US",
    "sg:address":"2065 Gates St",
    "sg:city":"Reese",
    "sg:classifiers":[
        {
            "category":"Education",
            "subcategory":"Library",
            "type":"Public Place"
        }
    ],
    "sg:phone":"+1 989 868 4120",
    "sg:postcode":"48757",
    "sg:province":"MI",
    "wof:name":"Unity District Library",
    "wof:placetype":"venue"
},
  "geometry": {"coordinates":[-83.69649200000001,43.448812],"type":"Point"}
}