{
  "type": "Feature",
  "properties": {
    "iso:country":"US",
    "sg:address":"1720 Star-Batt Dr",
    "sg:city":"Rochester",
    "sg:classifiers":[
        {
            "category":"Professional",
            "subcategory":"Engineering",
            "type":"Services"
        }
    ],
    "sg:phone":"+1 248 853 7925",
    "sg:postcode":"48309",
    "sg:province":"MI",
    "sg:tags":[
        "design"
    ],
    "wof:name":"Wilhelm Engineering Group",
    "wof:placetype":"venue"
},
  "geometry": {"coordinates":[-83.16533699999999,42.647694],"type":"Point"}
}