{
  "type": "Feature",
  "properties": {
    "iso:country":"US",
    "sg:address":"455 Bay St",
    "sg:city":"Petoskey",
    "sg:classifiers":[
        {
            "category":"Insurance",
            "subcategory":"Insurance Agent",
            "type":"Services"
        }
    ],
    "sg:phone":"+1 231 347 4610",
    "sg:postcode":"49770",
    "sg:province":"MI",
    "wof:name":"Top Omichigan Insurance Agency",
    "wof:placetype":"venue"
},
  "geometry": {"coordinates":[-84.953344,45.375978],"type":"Point"}
}