{
  "type": "Feature",
  "properties": {
    "iso:country":"US",
    "sg:address":"2382 60th St",
    "sg:city":"Fennville",
    "sg:classifiers":[
        {
            "category":"Farming",
            "subcategory":"Orchard",
            "type":"Manufacturing & Wholesale Goods"
        }
    ],
    "sg:phone":"+1 269 561 8651",
    "sg:postcode":"49408",
    "sg:province":"MI",
    "sg:tags":[
        "grove",
        "management"
    ],
    "wof:name":"Crane Orchards U-Pick",
    "wof:placetype":"venue"
},
  "geometry": {"coordinates":[-86.13287099999999,42.590581],"type":"Point"}
}