{
  "type": "Feature",
  "properties": {
    "iso:country":"US",
    "sg:address":"39153 Co Rd 681",
    "sg:city":"Bangor",
    "sg:classifiers":[
        {
            "category":"Farming",
            "subcategory":"Farm",
            "type":"Manufacturing & Wholesale Goods"
        }
    ],
    "sg:phone":"+1 269 427 8578",
    "sg:postcode":"49013",
    "sg:province":"MI",
    "sg:tags":[
        "crop",
        "general"
    ],
    "wof:name":"Charles Mc Coy",
    "wof:placetype":"venue"
},
  "geometry": {"coordinates":[-86.10869099999999,42.276767],"type":"Point"}
}