{
  "type": "Feature",
  "properties": {
    "iso:country":"US",
    "sg:address":"2618 Portage St",
    "sg:city":"Kalamazoo",
    "sg:classifiers":[
        {
            "category":"Insurance",
            "subcategory":"Insurance Agent",
            "type":"Services"
        }
    ],
    "sg:phone":"+1 269 342 0204",
    "sg:postcode":"49001",
    "sg:province":"MI",
    "wof:name":"State Farm Insurance",
    "wof:placetype":"venue"
},
  "geometry": {"coordinates":[-85.569132,42.264347],"type":"Point"}
}