{
  "type": "Feature",
  "properties": {
    "iso:country":"US",
    "sg:address":"56015 Parkview Dr",
    "sg:city":"Shelby Twp",
    "sg:classifiers":[
        {
            "category":"Building & Trades",
            "subcategory":"Construction",
            "type":"Services"
        }
    ],
    "sg:phone":"+1 248 969 1600",
    "sg:postcode":"48316",
    "sg:province":"MI",
    "sg:tags":[
        "home",
        "builder"
    ],
    "wof:name":"Bay Village Of Waterstone",
    "wof:placetype":"venue"
},
  "geometry": {"coordinates":[-83.076194,42.704162],"type":"Point"}
}