{
  "type": "Feature",
  "properties": {
    "iso:country":"US",
    "sg:address":"3346 E Dodge Rd",
    "sg:city":"Clio",
    "sg:classifiers":[
        {
            "category":"Building & Trades",
            "subcategory":"Construction",
            "type":"Services"
        }
    ],
    "sg:phone":"+1 810 241 6904",
    "sg:postcode":"48420",
    "sg:province":"MI",
    "sg:tags":[
        "excavation",
        "contractor"
    ],
    "wof:name":"RC Excavating",
    "wof:placetype":"venue"
},
  "geometry": {"coordinates":[-83.64384800000001,43.149741],"type":"Point"}
}