{
  "type": "Feature",
  "properties": {
    "iso:country":"US",
    "sg:address":"29 Beverly Rd",
    "sg:city":"Grosse Pointe",
    "sg:classifiers":[
        {
            "category":"Professional",
            "subcategory":"Management & Consulting",
            "type":"Services"
        }
    ],
    "sg:phone":"+1 313 886 4067",
    "sg:postcode":"48236",
    "sg:province":"MI",
    "wof:name":"R C Paschke",
    "wof:placetype":"venue"
},
  "geometry": {"coordinates":[-82.90221699999999,42.388726],"type":"Point"}
}