{
  "type": "Feature",
  "properties": {
    "iso:country":"US",
    "sg:address":"4843 Runway Blvd",
    "sg:city":"Ann Arbor",
    "sg:classifiers":[
        {
            "category":"Manufacturing",
            "subcategory":"Tools & Machinery",
            "type":"Manufacturing & Wholesale Goods"
        }
    ],
    "sg:phone":"+1 734 930 0300",
    "sg:postcode":"48108",
    "sg:province":"MI",
    "sg:tags":[
        "machine",
        "mfg"
    ],
    "wof:name":"Lindenmaier Machine",
    "wof:placetype":"venue"
},
  "geometry": {"coordinates":[-83.729123,42.217238],"type":"Point"}
}