{
  "type": "Feature",
  "properties": {
    "iso:country":"US",
    "sg:address":"7923 Rodao Dr SE",
    "sg:city":"Caledonia",
    "sg:classifiers":[
        {
            "category":"Building & Trades",
            "subcategory":"Construction",
            "type":"Services"
        }
    ],
    "sg:phone":"+1 616 891 2272",
    "sg:postcode":"49316",
    "sg:province":"MI",
    "sg:tags":[
        "contractor"
    ],
    "wof:name":"Prime Homes",
    "wof:placetype":"venue"
},
  "geometry": {"coordinates":[-85.46907400000001,42.804284],"type":"Point"}
}