{
  "type": "Feature",
  "properties": {
    "iso:country":"US",
    "sg:address":"111 N 5th St",
    "sg:city":"Roscommon",
    "sg:classifiers":[
        {
            "category":"Retail",
            "subcategory":"Auto Repair",
            "type":"Services"
        }
    ],
    "sg:phone":"+1 989 275 7800",
    "sg:postcode":"48653",
    "sg:province":"MI",
    "sg:tags":[
        "general"
    ],
    "wof:name":"Birchwood Automotive",
    "wof:placetype":"venue"
},
  "geometry": {"coordinates":[-84.59354500000001,44.499051],"type":"Point"}
}