{
  "type": "Feature",
  "properties": {
    "iso:country":"US",
    "sg:address":"4425 24th Ave",
    "sg:city":"Fort Gratiot",
    "sg:classifiers":[
        {
            "category":"Restaurant",
            "type":"Food & Drink"
        }
    ],
    "sg:phone":"+1 810 385 8880",
    "sg:postcode":"48059",
    "sg:province":"MI",
    "wof:name":"Coney Island North",
    "wof:placetype":"venue"
},
  "geometry": {"coordinates":[-82.456813,43.039009],"type":"Point"}
}