{
  "type": "Feature",
  "properties": {
    "iso:country":"US",
    "sg:address":"2248 Union Lake Rd",
    "sg:city":"Commerce Township",
    "sg:classifiers":[
        {
            "category":"Shopping",
            "subcategory":"Mobile Phones",
            "type":"Retail Goods"
        }
    ],
    "sg:phone":"+1 248 360 9400",
    "sg:postcode":"48382",
    "sg:province":"MI",
    "wof:name":"Cellular Source",
    "wof:placetype":"venue"
},
  "geometry": {"coordinates":[-83.446529,42.604142],"type":"Point"}
}