{
  "type": "Feature",
  "properties": {
    "iso:country":"US",
    "sg:address":"4290 W Walton Blvd",
    "sg:city":"Waterford",
    "sg:classifiers":[
        {
            "category":"Autos & Motor Vehicles",
            "subcategory":"Fuel & Gas Station",
            "type":"Retail Goods"
        }
    ],
    "sg:phone":"+1 248 674 4076",
    "sg:postcode":"48329",
    "sg:province":"MI",
    "sg:tags":[
        "oil"
    ],
    "wof:name":"Walton Sashabaw Mobil",
    "wof:placetype":"venue"
},
  "geometry": {"coordinates":[-83.370825,42.69006],"type":"Point"}
}