{
  "type": "Feature",
  "properties": {
    "iso:country":"US",
    "sg:address":"288 N Ray Quincy Rd",
    "sg:city":"Quincy",
    "sg:classifiers":[
        {
            "category":"Food & Beverages",
            "subcategory":"Groceries & Convenience Stores",
            "type":"Retail Goods"
        }
    ],
    "sg:phone":"+1 517 639 3213",
    "sg:postcode":"49082",
    "sg:province":"MI",
    "sg:tags":[
        "grocer"
    ],
    "wof:name":"Quincy Heights Grocery",
    "wof:placetype":"venue"
},
  "geometry": {"coordinates":[-84.88387299999999,41.92494],"type":"Point"}
}