{
  "type": "Feature",
  "properties": {
    "iso:country":"US",
    "sg:address":"50985 Hayes Rd",
    "sg:city":"Shelby Twp",
    "sg:classifiers":[
        {
            "category":"Restaurant",
            "type":"Food & Drink"
        }
    ],
    "sg:phone":"+1 586 247 4444",
    "sg:postcode":"48315",
    "sg:province":"MI",
    "wof:name":"Grand Dimitre's Family Dining",
    "wof:placetype":"venue"
},
  "geometry": {"coordinates":[-82.975024,42.666409],"type":"Point"}
}