{
  "type": "Feature",
  "properties": {
    "iso:country":"US",
    "sg:address":"4201 Saint Antoine St",
    "sg:city":"Detroit",
    "sg:classifiers":[
        {
            "category":"Health Services",
            "subcategory":"Hospital",
            "type":"Services"
        }
    ],
    "sg:phone":"+1 313 745 3000",
    "sg:postcode":"48201",
    "sg:province":"MI",
    "sg:website":"www.dmc.org",
    "wof:name":"Detroit Receiving Hospital and University Health Ctr",
    "wof:placetype":"venue"
},
  "geometry": {"coordinates":[-83.05619799999999,42.3582],"type":"Point"}
}