{
  "type": "Feature",
  "properties": {
    "iso:country":"US",
    "sg:address":"3345 Four Seasons Dr",
    "sg:city":"Iron Mountain",
    "sg:classifiers":[
        {
            "category":"Airport",
            "type":"Transportation"
        }
    ],
    "sg:phone":"+1 906 774 2368",
    "sg:postcode":"49801",
    "sg:province":"MI",
    "wof:name":"Eagle Air Cargo Inc",
    "wof:placetype":"venue"
},
  "geometry": {"coordinates":[-88.099384,45.845278],"type":"Point"}
}