{
  "type": "Feature",
  "properties": {
    "iso:country":"US",
    "sg:address":"1034 Devonshire Rd",
    "sg:city":"Grosse Pointe",
    "sg:classifiers":[
        {
            "category":"Professional",
            "type":"Services"
        }
    ],
    "sg:phone":"+1 313 640 0027",
    "sg:postcode":"48230",
    "sg:province":"MI",
    "wof:name":"Scillian Creative Inc",
    "wof:placetype":"venue"
},
  "geometry": {"coordinates":[-82.929028,42.38129],"type":"Point"}
}