{
  "type": "Feature",
  "properties": {
    "iso:country":"US",
    "sg:address":"11179 Hall Rd",
    "sg:city":"Utica",
    "sg:classifiers":[
        {
            "category":"Building & Trades",
            "subcategory":"Construction",
            "type":"Services"
        }
    ],
    "sg:phone":"+1 586 731 6900",
    "sg:postcode":"48317",
    "sg:province":"MI",
    "sg:tags":[
        "dry wall",
        "contractor"
    ],
    "wof:name":"Custom Drywall Inc",
    "wof:placetype":"venue"
},
  "geometry": {"coordinates":[-83.010661,42.626385],"type":"Point"}
}