{
  "type": "Feature",
  "properties": {
    "iso:country":"US",
    "sg:address":"11010 Janet St",
    "sg:city":"Taylor",
    "sg:classifiers":[
        {
            "category":"Education",
            "subcategory":"School",
            "type":"Public Place"
        }
    ],
    "sg:phone":"+1 734 946 6616",
    "sg:postcode":"48180",
    "sg:province":"MI",
    "sg:tags":[
        "high",
        "middle",
        "elementary"
    ],
    "wof:name":"Taylor School District",
    "wof:placetype":"venue"
},
  "geometry": {"coordinates":[-83.286029,42.225961],"type":"Point"}
}