{
  "type": "Feature",
  "properties": {
    "iso:country":"US",
    "sg:address":"6818 Saline Dr",
    "sg:city":"Waterford",
    "sg:classifiers":[
        {
            "category":"Professional",
            "subcategory":"Business Services",
            "type":"Services"
        }
    ],
    "sg:phone":"+1 248 623 1173",
    "sg:postcode":"48329",
    "sg:province":"MI",
    "sg:tags":[
        "inspection"
    ],
    "wof:name":"Patrick Inspections",
    "wof:placetype":"venue"
},
  "geometry": {"coordinates":[-83.424369,42.701954],"type":"Point"}
}