{
  "type": "Feature",
  "properties": {
    "iso:country":"US",
    "sg:address":"1681 Benzie Hwy",
    "sg:city":"Benzonia",
    "sg:classifiers":[
        {
            "category":"Restaurant",
            "type":"Food & Drink"
        }
    ],
    "sg:phone":"+1 231 882 9565",
    "sg:postcode":"49616",
    "sg:province":"MI",
    "wof:name":"Crystal Cafe",
    "wof:placetype":"venue"
},
  "geometry": {"coordinates":[-86.099248,44.60745],"type":"Point"}
}