{
  "type": "Feature",
  "properties": {
    "iso:country":"US",
    "sg:address":"49001 North Ave",
    "sg:city":"Macomb",
    "sg:classifiers":[
        {
            "category":"Sports & Exercise",
            "subcategory":"Golf",
            "type":"Entertainment"
        }
    ],
    "sg:phone":"+1 586 949 9033",
    "sg:postcode":"48042",
    "sg:province":"MI",
    "sg:tags":[
        "course",
        "public"
    ],
    "sg:website":"www.hickoryhollowgolf.com",
    "wof:name":"Hickory Hollow Golf Course",
    "wof:placetype":"venue"
},
  "geometry": {"coordinates":[-82.87739500000001,42.661603],"type":"Point"}
}