{
  "type": "Feature",
  "properties": {
    "iso:country":"US",
    "sg:address":"36264 Freedom Rd",
    "sg:city":"Farmington",
    "sg:classifiers":[
        {
            "category":"Professional",
            "subcategory":"Art Services",
            "type":"Services"
        }
    ],
    "sg:phone":"+1 248 478 3666",
    "sg:postcode":"48335",
    "sg:province":"MI",
    "sg:tags":[
        "photography",
        "commercial"
    ],
    "wof:name":"Clark Junebug Photography",
    "wof:placetype":"venue"
},
  "geometry": {"coordinates":[-83.40465,42.462192],"type":"Point"}
}