{
  "type": "Feature",
  "properties": {
    "iso:country":"US",
    "sg:address":"3768 Pine Meadow Dr",
    "sg:city":"Holland",
    "sg:classifiers":[
        {
            "category":"Restaurant",
            "type":"Food & Drink"
        }
    ],
    "sg:phone":"+1 616 786 0204",
    "sg:postcode":"49424",
    "sg:province":"MI",
    "sg:tags":[
        "eating"
    ],
    "wof:name":"Mr You Chinese Food",
    "wof:placetype":"venue"
},
  "geometry": {"coordinates":[-86.133921,42.837053],"type":"Point"}
}