{
  "type": "Feature",
  "properties": {
    "iso:country":"US",
    "sg:address":"1904 Ferrol St",
    "sg:city":"Lansing",
    "sg:classifiers":[
        {
            "category":"Professional",
            "subcategory":"Detective & Security Services",
            "type":"Services"
        }
    ],
    "sg:phone":"+1 517 393 5261",
    "sg:postcode":"48910",
    "sg:province":"MI",
    "sg:tags":[
        "investigator"
    ],
    "wof:name":"Eagle Investigations",
    "wof:placetype":"venue"
},
  "geometry": {"coordinates":[-84.582212,42.694917],"type":"Point"}
}