{
  "type": "Feature",
  "properties": {
    "iso:country":"US",
    "sg:address":"6589 Orion Rd",
    "sg:city":"Rochester",
    "sg:classifiers":[
        {
            "category":"Banks & Credit Unions",
            "subcategory":"Investment Brokerage",
            "type":"Services"
        }
    ],
    "sg:phone":"+1 248 601 6018",
    "sg:postcode":"48306",
    "sg:province":"MI",
    "sg:tags":[
        "advisory"
    ],
    "wof:name":"Newport Financial Services",
    "wof:placetype":"venue"
},
  "geometry": {"coordinates":[-83.14064399999999,42.703956],"type":"Point"}
}