{
  "type": "Feature",
  "properties": {
    "iso:country":"US",
    "sg:address":"402 S Brown St",
    "sg:city":"Jackson",
    "sg:classifiers":[
        {
            "category":"Education",
            "subcategory":"Special Training",
            "type":"Public Place"
        }
    ],
    "sg:phone":"+1 517 783 4415",
    "sg:postcode":"49203",
    "sg:province":"MI",
    "sg:tags":[
        "center"
    ],
    "wof:name":"D & A Learning Ctr Inc",
    "wof:placetype":"venue"
},
  "geometry": {"coordinates":[-84.433251,42.24471],"type":"Point"}
}