{
  "type": "Feature",
  "properties": {
    "iso:country":"US",
    "sg:address":"619 E Hazel St",
    "sg:city":"Lansing",
    "sg:classifiers":[
        {
            "category":"Manufacturing",
            "subcategory":"Printing",
            "type":"Manufacturing & Wholesale Goods"
        }
    ],
    "sg:phone":"+1 517 485 9933",
    "sg:postcode":"48912",
    "sg:province":"MI",
    "sg:tags":[
        "commercial"
    ],
    "sg:website":"www.foresightgr.com",
    "wof:name":"Foresight Group",
    "wof:placetype":"venue"
},
  "geometry": {"coordinates":[-84.542874,42.723232],"type":"Point"}
}