{
  "type": "Feature",
  "properties": {
    "iso:country":"US",
    "sg:address":"3804 Raven Ave SW",
    "sg:city":"Grand Rapids",
    "sg:classifiers":[
        {
            "category":"Professional",
            "subcategory":"Art Services",
            "type":"Services"
        }
    ],
    "sg:phone":"+1 616 534 8819",
    "sg:postcode":"49509",
    "sg:province":"MI",
    "sg:tags":[
        "commercial",
        "design"
    ],
    "wof:name":"Thomas Adams Graphics",
    "wof:placetype":"venue"
},
  "geometry": {"coordinates":[-85.697035,42.891632],"type":"Point"}
}