{
  "type": "Feature",
  "properties": {
    "iso:country":"US",
    "sg:address":"2488 Rocky Top Ct",
    "sg:city":"Commerce Twp",
    "sg:classifiers":[
        {
            "category":"Real Estate",
            "subcategory":"Real Estate Agent",
            "type":"Services"
        }
    ],
    "sg:phone":"+1 248 685 3336",
    "sg:postcode":"48382",
    "sg:province":"MI",
    "wof:name":"Guidance Real Estate Company",
    "wof:placetype":"venue"
},
  "geometry": {"coordinates":[-83.550527,42.557862],"type":"Point"}
}