{
  "type": "Feature",
  "properties": {
    "iso:country":"US",
    "sg:address":"11100 Dunnigan Rd",
    "sg:city":"Emmett",
    "sg:classifiers":[
        {
            "category":"Government",
            "subcategory":"Office",
            "type":"Public Place"
        }
    ],
    "sg:phone":"+1 810 384 8070",
    "sg:postcode":"48022",
    "sg:province":"MI",
    "sg:tags":[
        "executive",
        "village"
    ],
    "wof:name":"Emmett Township Hall",
    "wof:placetype":"venue"
},
  "geometry": {"coordinates":[-82.771148,43.000989],"type":"Point"}
}