{
  "type": "Feature",
  "properties": {
    "iso:country":"US",
    "sg:address":"1350 Kirts Blvd",
    "sg:city":"Troy",
    "sg:classifiers":[
        {
            "category":"Health Services",
            "subcategory":"Doctor",
            "type":"Services"
        }
    ],
    "sg:phone":"+1 248 244 9426",
    "sg:postcode":"48084",
    "sg:province":"MI",
    "sg:tags":[
        "physician",
        "surgeon"
    ],
    "wof:name":"Troy Orthopaedic Assoc",
    "wof:placetype":"venue"
},
  "geometry": {"coordinates":[-83.162841,42.556675],"type":"Point"}
}