{
  "type": "Feature",
  "properties": {
    "iso:country":"US",
    "sg:address":"10611 Estola St",
    "sg:city":"White Lake",
    "sg:classifiers":[
        {
            "category":"Building & Trades",
            "subcategory":"Cleaning & Sanitation",
            "type":"Services"
        }
    ],
    "sg:phone":"+1 248 363 1129",
    "sg:postcode":"48386",
    "sg:province":"MI",
    "sg:tags":[
        "maintenance"
    ],
    "wof:name":"J & M Presige Cleaning Svcs",
    "wof:placetype":"venue"
},
  "geometry": {"coordinates":[-83.491231,42.618429],"type":"Point"}
}