{
  "type": "Feature",
  "properties": {
    "iso:country":"US",
    "sg:address":"131 Bancroft St",
    "sg:city":"Imlay City",
    "sg:classifiers":[
        {
            "category":"Education",
            "subcategory":"Dance Studio",
            "type":"Public Place"
        }
    ],
    "sg:phone":"+1 810 724 8414",
    "sg:postcode":"48444",
    "sg:province":"MI",
    "sg:tags":[
        "instruction",
        "dancing"
    ],
    "wof:name":"Extreme Cheer & Dance Studio",
    "wof:placetype":"venue"
},
  "geometry": {"coordinates":[-83.07607400000001,43.02525],"type":"Point"}
}