{
  "type": "Feature",
  "properties": {
    "iso:country":"US",
    "sg:address":"637 E Big Beaver Rd",
    "sg:city":"Troy",
    "sg:classifiers":[
        {
            "category":"Insurance",
            "subcategory":"Insurance Agent",
            "type":"Services"
        }
    ],
    "sg:phone":"+1 248 524 1500",
    "sg:postcode":"48083",
    "sg:province":"MI",
    "sg:tags":[
        "tracking"
    ],
    "wof:name":"Insurance Confirmation Systems",
    "wof:placetype":"venue"
},
  "geometry": {"coordinates":[-83.129248,42.563087],"type":"Point"}
}