{
  "type": "Feature",
  "properties": {
    "iso:country":"US",
    "sg:address":"5580 W State Rd",
    "sg:city":"Lansing",
    "sg:classifiers":[
        {
            "category":"Health Services",
            "subcategory":"Doctor",
            "type":"Services"
        }
    ],
    "sg:phone":"+1 517 321 1746",
    "sg:postcode":"48906",
    "sg:province":"MI",
    "wof:name":"Michigan Oral History Assn",
    "wof:placetype":"venue"
},
  "geometry": {"coordinates":[-84.633599,42.784405],"type":"Point"}
}