{
  "type": "Feature",
  "properties": {
    "iso:country":"US",
    "sg:address":"1808 W Columbia Rd",
    "sg:city":"Mason",
    "sg:classifiers":[
        {
            "category":"Building & Trades",
            "subcategory":"Construction",
            "type":"Services"
        }
    ],
    "sg:phone":"+1 517 676 9549",
    "sg:postcode":"48854",
    "sg:province":"MI",
    "sg:tags":[
        "paving",
        "asphalt"
    ],
    "wof:name":"Quality Asphalt Patching",
    "wof:placetype":"venue"
},
  "geometry": {"coordinates":[-84.411432,42.582211],"type":"Point"}
}