{
  "type": "Feature",
  "properties": {
    "iso:country":"US",
    "sg:address":"14299 Crescent Dr",
    "sg:city":"Detroit",
    "sg:classifiers":[
        {
            "category":"Manufacturing",
            "subcategory":"Retail Goods",
            "type":"Manufacturing & Wholesale Goods"
        }
    ],
    "sg:phone":"+1 313 532 1347",
    "sg:postcode":"48223",
    "sg:province":"MI",
    "sg:tags":[
        "product",
        "mfg"
    ],
    "wof:name":"Freestyles",
    "wof:placetype":"venue"
},
  "geometry": {"coordinates":[-83.237769,42.390895],"type":"Point"}
}