{
  "type": "Feature",
  "properties": {
    "iso:country":"US",
    "sg:address":"303 Madison Ave SE",
    "sg:city":"Grand Rapids",
    "sg:classifiers":[
        {
            "category":"Real Estate",
            "subcategory":"Real Estate Operator",
            "type":"Services"
        }
    ],
    "sg:phone":"+1 616 454 3232",
    "sg:postcode":"49503",
    "sg:province":"MI",
    "sg:tags":[
        "building",
        "apartment"
    ],
    "sg:website":"www.kennedyhousebed-breakfast.com",
    "wof:name":"Kennedy House",
    "wof:placetype":"venue"
},
  "geometry": {"coordinates":[-85.659244,42.957648],"type":"Point"}
}