{
  "type": "Feature",
  "properties": {
    "iso:country":"US",
    "sg:address":"111 Lansing St",
    "sg:city":"Charlotte",
    "sg:classifiers":[
        {
            "category":"Health Services",
            "subcategory":"Doctor",
            "type":"Services"
        }
    ],
    "sg:phone":"+1 517 543 9564",
    "sg:postcode":"48813",
    "sg:province":"MI",
    "sg:tags":[
        "physician",
        "surgeon"
    ],
    "wof:name":"Capital Area Surgeons",
    "wof:placetype":"venue"
},
  "geometry": {"coordinates":[-84.82945100000001,42.56619],"type":"Point"}
}