{
  "type": "Feature",
  "properties": {
    "iso:country":"US",
    "sg:address":"12721 Corbett Ave",
    "sg:city":"Detroit",
    "sg:classifiers":[
        {
            "category":"Social Services",
            "subcategory":"Adult Care",
            "type":"Services"
        }
    ],
    "sg:phone":"+1 313 372 0047",
    "sg:postcode":"48213",
    "sg:province":"MI",
    "sg:tags":[
        "foster"
    ],
    "wof:name":"Roseberry Manor 3",
    "wof:placetype":"venue"
},
  "geometry": {"coordinates":[-82.975955,42.406529],"type":"Point"}
}