{
  "type": "Feature",
  "properties": {
    "iso:country":"US",
    "sg:address":"20301 Ellis St",
    "sg:city":"Roseville",
    "sg:classifiers":[
        {
            "category":"Building & Trades",
            "subcategory":"Cleaning & Sanitation",
            "type":"Services"
        }
    ],
    "sg:phone":"+1 586 296 5299",
    "sg:postcode":"48066",
    "sg:province":"MI",
    "sg:tags":[
        "maintenance"
    ],
    "wof:name":"Akw Floor Cleaning",
    "wof:placetype":"venue"
},
  "geometry": {"coordinates":[-82.914435,42.526254],"type":"Point"}
}