{
  "type": "Feature",
  "properties": {
    "iso:country":"US",
    "sg:address":"3233 Deckerville Rd",
    "sg:city":"Cass City",
    "sg:classifiers":[
        {
            "category":"Retail",
            "subcategory":"Portrait Studio",
            "type":"Services"
        }
    ],
    "sg:phone":"+1 989 673 3328",
    "sg:postcode":"48726",
    "sg:province":"MI",
    "sg:tags":[
        "photographer",
        "photography",
        "commercial",
        "photo"
    ],
    "wof:name":"Sattler Photo LLC",
    "wof:placetype":"venue"
},
  "geometry": {"coordinates":[-83.290683,43.511628],"type":"Point"}
}