{
  "type": "Feature",
  "properties": {
    "iso:country":"US",
    "sg:address":"3320 Van Zandt Rd",
    "sg:city":"Waterford",
    "sg:classifiers":[
        {
            "category":"Building & Trades",
            "subcategory":"Construction",
            "type":"Services"
        }
    ],
    "sg:phone":"+1 248 673 7558",
    "sg:postcode":"48329",
    "sg:province":"MI",
    "sg:tags":[
        "house",
        "industrial"
    ],
    "wof:name":"Technical Building Services",
    "wof:placetype":"venue"
},
  "geometry": {"coordinates":[-83.39793400000001,42.685472],"type":"Point"}
}