{
  "type": "Feature",
  "properties": {
    "iso:country":"US",
    "sg:address":"1208 Hyland St",
    "sg:city":"Lansing",
    "sg:classifiers":[
        {
            "category":"Social Services",
            "subcategory":"Child Care",
            "type":"Services"
        }
    ],
    "sg:phone":"+1 517 372 5113",
    "sg:postcode":"48915",
    "sg:province":"MI",
    "sg:tags":[
        "day"
    ],
    "wof:name":"Raes Romper Room",
    "wof:placetype":"venue"
},
  "geometry": {"coordinates":[-84.570483,42.745134],"type":"Point"}
}