{
  "type": "Feature",
  "properties": {
    "iso:country":"US",
    "sg:address":"660 Macomb St",
    "sg:city":"Detroit",
    "sg:classifiers":[
        {
            "category":"Parking",
            "type":"Transportation"
        }
    ],
    "sg:phone":"+1 313 961 6102",
    "sg:postcode":"48226",
    "sg:province":"MI",
    "sg:tags":[
        "automobile"
    ],
    "wof:name":"National Garages Inc",
    "wof:placetype":"venue"
},
  "geometry": {"coordinates":[-83.04100800000001,42.336411],"type":"Point"}
}