{
  "type": "Feature",
  "properties": {
    "iso:country":"US",
    "sg:address":"113 E Michigan Ave",
    "sg:city":"Marshall",
    "sg:classifiers":[
        {
            "category":"Restaurant",
            "type":"Food & Drink"
        }
    ],
    "sg:phone":"+1 269 781 0018",
    "sg:postcode":"49068",
    "sg:province":"MI",
    "wof:name":"Mancino's Rollo's Pizza",
    "wof:placetype":"venue"
},
  "geometry": {"coordinates":[-84.95862200000001,42.272119],"type":"Point"}
}