{
  "type": "Feature",
  "properties": {
    "iso:country":"US",
    "sg:address":"12347 Quail Ct",
    "sg:city":"Utica",
    "sg:classifiers":[
        {
            "category":"Retail",
            "subcategory":"Auto Repair",
            "type":"Services"
        }
    ],
    "sg:phone":"+1 586 997 6120",
    "sg:postcode":"48315",
    "sg:province":"MI",
    "sg:tags":[
        "glass",
        "replacement"
    ],
    "wof:name":"On Site Windshield Repair",
    "wof:placetype":"venue"
},
  "geometry": {"coordinates":[-83.006124,42.656647],"type":"Point"}
}