{
  "type": "Feature",
  "properties": {
    "iso:country":"US",
    "sg:address":"747 Orchard Lake Rd",
    "sg:city":"Pontiac",
    "sg:classifiers":[
        {
            "category":"Building & Trades",
            "subcategory":"Construction",
            "type":"Services"
        }
    ],
    "sg:phone":"+1 248 335 9285",
    "sg:postcode":"48341",
    "sg:province":"MI",
    "sg:tags":[
        "equipment",
        "station"
    ],
    "wof:name":"Hawkins Equipment Co",
    "wof:placetype":"venue"
},
  "geometry": {"coordinates":[-83.315532,42.62438],"type":"Point"}
}