{
  "type": "Feature",
  "properties": {
    "iso:country":"US",
    "sg:address":"763 Burroughs St",
    "sg:city":"Plymouth",
    "sg:classifiers":[
        {
            "category":"Retail",
            "subcategory":"Portrait Studio",
            "type":"Services"
        }
    ],
    "sg:phone":"+1 734 451 0868",
    "sg:postcode":"48170",
    "sg:province":"MI",
    "sg:tags":[
        "photo"
    ],
    "wof:name":"Wink Casual Candid Photos",
    "wof:placetype":"venue"
},
  "geometry": {"coordinates":[-83.469762,42.364071],"type":"Point"}
}