{
  "type": "Feature",
  "properties": {
    "iso:country":"US",
    "sg:address":"35180 Nankin Blvd",
    "sg:city":"Westland",
    "sg:classifiers":[
        {
            "category":"Professional",
            "subcategory":"Accounting & Tax Preparation",
            "type":"Services"
        }
    ],
    "sg:phone":"+1 734 261 4443",
    "sg:postcode":"48185",
    "sg:province":"MI",
    "sg:tags":[
        "return"
    ],
    "wof:name":"H & R Block",
    "wof:placetype":"venue"
},
  "geometry": {"coordinates":[-83.388419,42.345357],"type":"Point"}
}