{
  "type": "Feature",
  "properties": {
    "iso:country":"US",
    "sg:address":"1044 Hayden Rd",
    "sg:city":"Muir",
    "sg:classifiers":[
        {
            "category":"Health Services",
            "subcategory":"Doctor",
            "type":"Services"
        }
    ],
    "sg:phone":"+1 989 855 3700",
    "sg:postcode":"48860",
    "sg:province":"MI",
    "sg:tags":[
        "physician",
        "surgeon"
    ],
    "wof:name":"Ionia County Health System",
    "wof:placetype":"venue"
},
  "geometry": {"coordinates":[-84.946063,43.001897],"type":"Point"}
}