{
  "type": "Feature",
  "properties": {
    "iso:country":"US",
    "sg:address":"45265 Gateway Rd",
    "sg:city":"Novi",
    "sg:classifiers":[
        {
            "category":"Real Estate",
            "subcategory":"Real Estate Operator",
            "type":"Services"
        }
    ],
    "sg:phone":"+1 248 624 8555",
    "sg:postcode":"48377",
    "sg:province":"MI",
    "sg:tags":[
        "building",
        "apartment"
    ],
    "wof:name":"Westgate Vi Apartments",
    "wof:placetype":"venue"
},
  "geometry": {"coordinates":[-83.49738000000001,42.522755],"type":"Point"}
}