{
  "type": "Feature",
  "properties": {
    "iso:country":"US",
    "sg:address":"888 Ford Ave",
    "sg:city":"Wyandotte",
    "sg:classifiers":[
        {
            "category":"Shopping",
            "subcategory":"Tobacco",
            "type":"Retail Goods"
        }
    ],
    "sg:phone":"+1 734 225 4748",
    "sg:postcode":"48192",
    "sg:province":"MI",
    "sg:tags":[
        "shop"
    ],
    "wof:name":"Georges Wholesale Inc",
    "wof:placetype":"venue"
},
  "geometry": {"coordinates":[-83.163291,42.214077],"type":"Point"}
}