{
  "type": "Feature",
  "properties": {
    "iso:country":"US",
    "sg:address":"207 S Oak St",
    "sg:city":"Buchanan",
    "sg:classifiers":[
        {
            "category":"Food & Beverages",
            "subcategory":"Groceries & Convenience Stores",
            "type":"Retail Goods"
        }
    ],
    "sg:phone":"+1 269 695 2632",
    "sg:postcode":"49107",
    "sg:province":"MI",
    "wof:name":"Pit Stop",
    "wof:placetype":"venue"
},
  "geometry": {"coordinates":[-86.361036,41.824988],"type":"Point"}
}