{
  "type": "Feature",
  "properties": {
    "iso:country":"US",
    "sg:address":"1491 Pyle Dr",
    "sg:city":"Kingsford",
    "sg:classifiers":[
        {
            "category":"Freight",
            "type":"Transportation"
        }
    ],
    "sg:phone":"+1 906 774 3312",
    "sg:postcode":"49802",
    "sg:province":"MI",
    "sg:tags":[
        "commercial",
        "storage"
    ],
    "wof:name":"Noel's Mini-Storage",
    "wof:placetype":"venue"
},
  "geometry": {"coordinates":[-88.089209,45.80401],"type":"Point"}
}