{
  "type": "Feature",
  "properties": {
    "iso:country":"US",
    "sg:address":"3633 W Big Beaver Rd",
    "sg:city":"Troy",
    "sg:classifiers":[
        {
            "category":"Social Services",
            "subcategory":"Child Care",
            "type":"Services"
        },
        {
            "category":"Education",
            "subcategory":"Preschool",
            "type":"Public Place"
        },
        {
            "category":"Education",
            "subcategory":"School",
            "type":"Public Place"
        }
    ],
    "sg:phone":"+1 248 645 6448",
    "sg:postcode":"48084",
    "sg:province":"MI",
    "sg:tags":[
        "elementary",
        "day"
    ],
    "wof:name":"Discovery Corner Learning Center",
    "wof:placetype":"venue"
},
  "geometry": {"coordinates":[-83.1996,42.560699],"type":"Point"}
}