{
  "type": "Feature",
  "properties": {
    "iso:country":"US",
    "sg:address":"46522 Erb Dr",
    "sg:city":"Macomb",
    "sg:classifiers":[
        {
            "category":"Wholesale",
            "subcategory":"Machinery & Supplies",
            "type":"Manufacturing & Wholesale Goods"
        }
    ],
    "sg:phone":"+1 586 598 7781",
    "sg:postcode":"48042",
    "sg:province":"MI",
    "wof:name":"Design Validation",
    "wof:placetype":"venue"
},
  "geometry": {"coordinates":[-82.857888,42.6425],"type":"Point"}
}