{
  "type": "Feature",
  "properties": {
    "iso:country":"US",
    "sg:address":"33980 Groesbeck Hwy",
    "sg:city":"Clinton Township",
    "sg:classifiers":[
        {
            "category":"Insurance",
            "subcategory":"Health Insurance",
            "type":"Services"
        }
    ],
    "sg:phone":"+1 586 791 7922",
    "sg:postcode":"48035",
    "sg:province":"MI",
    "sg:tags":[
        "market"
    ],
    "wof:name":"Seattle Suttons Healthy Eating",
    "wof:placetype":"venue"
},
  "geometry": {"coordinates":[-82.928746,42.54731],"type":"Point"}
}