{
  "type": "Feature",
  "properties": {
    "iso:country":"US",
    "sg:address":"14734 Park Ave",
    "sg:city":"Charlevoix",
    "sg:classifiers":[
        {
            "category":"Health Services",
            "subcategory":"Doctor",
            "type":"Services"
        }
    ],
    "sg:phone":"+1 231 547 3840",
    "sg:postcode":"49720",
    "sg:province":"MI",
    "sg:tags":[
        "medical"
    ],
    "wof:name":"Roderic E Tinney MD Faap",
    "wof:placetype":"venue"
},
  "geometry": {"coordinates":[-85.276501,45.313375],"type":"Point"}
}