{
  "type": "Feature",
  "properties": {
    "iso:country":"US",
    "sg:address":"431 School St",
    "sg:city":"Hudson",
    "sg:classifiers":[
        {
            "category":"Wholesale",
            "subcategory":"Machinery & Supplies",
            "type":"Manufacturing & Wholesale Goods"
        }
    ],
    "sg:phone":"+1 517 448 8868",
    "sg:postcode":"49247",
    "sg:province":"MI",
    "sg:tags":[
        "burial",
        "vault"
    ],
    "wof:name":"Paschal Burial Vaults",
    "wof:placetype":"venue"
},
  "geometry": {"coordinates":[-84.341138,41.853976],"type":"Point"}
}