{
  "type": "Feature",
  "properties": {
    "iso:country":"US",
    "sg:address":"4527 Garfield Rd",
    "sg:city":"Auburn",
    "sg:classifiers":[
        {
            "category":"Retail",
            "subcategory":"Auto Repair",
            "type":"Services"
        }
    ],
    "sg:phone":"+1 989 662 7091",
    "sg:postcode":"48611",
    "sg:province":"MI",
    "sg:tags":[
        "transmission"
    ],
    "wof:name":"First Transmission Svc",
    "wof:placetype":"venue"
},
  "geometry": {"coordinates":[-84.089254,43.608228],"type":"Point"}
}