{
  "type": "Feature",
  "properties": {
    "iso:country":"US",
    "sg:address":"3504 Highland Dr",
    "sg:city":"Hudsonville",
    "sg:classifiers":[
        {
            "category":"Wholesale",
            "subcategory":"Electrical",
            "type":"Manufacturing & Wholesale Goods"
        }
    ],
    "sg:phone":"+1 616 379 4100",
    "sg:postcode":"49426",
    "sg:province":"MI",
    "sg:tags":[
        "equipment",
        "electric",
        "supply"
    ],
    "sg:website":"www.northcoastcomponents.com",
    "wof:name":"North Coast Components Inc",
    "wof:placetype":"venue"
},
  "geometry": {"coordinates":[-85.867338,42.851836],"type":"Point"}
}