{
  "type": "Feature",
  "properties": {
    "iso:country":"US",
    "sg:address":"9562 59th St",
    "sg:city":"Grand Junction",
    "sg:classifiers":[
        {
            "category":"Social Services",
            "subcategory":"Adult Care",
            "type":"Services"
        }
    ],
    "sg:phone":"+1 269 253 4511",
    "sg:postcode":"49056",
    "sg:province":"MI",
    "sg:tags":[
        "foster"
    ],
    "wof:name":"Saffells Pine Rest Afc",
    "wof:placetype":"venue"
},
  "geometry": {"coordinates":[-86.119715,42.382929],"type":"Point"}
}