{
  "type": "Feature",
  "properties": {
    "iso:country":"US",
    "sg:address":"9542 W 48th St",
    "sg:city":"Fremont",
    "sg:classifiers":[
        {
            "category":"Wholesale",
            "subcategory":"Machinery & Supplies",
            "type":"Manufacturing & Wholesale Goods"
        }
    ],
    "sg:phone":"+1 231 924 2510",
    "sg:postcode":"49412",
    "sg:province":"MI",
    "sg:tags":[
        "farm",
        "repair",
        "equipment"
    ],
    "wof:name":"Pells Farm Service Inc",
    "wof:placetype":"venue"
},
  "geometry": {"coordinates":[-86.03930699999999,43.467371],"type":"Point"}
}