{
  "type": "Feature",
  "properties": {
    "iso:country":"US",
    "sg:address":"5278 Rossiter Ave",
    "sg:city":"Waterford",
    "sg:classifiers":[
        {
            "category":"Social Services",
            "subcategory":"Child Care",
            "type":"Services"
        }
    ],
    "sg:phone":"+1 248 623 5009",
    "sg:postcode":"48329",
    "sg:province":"MI",
    "wof:name":"C & J Home Daycare",
    "wof:placetype":"venue"
},
  "geometry": {"coordinates":[-83.39216500000001,42.695839],"type":"Point"}
}