{
  "type": "Feature",
  "properties": {
    "iso:country":"US",
    "sg:address":"37805 Woodridge Dr Apt 204",
    "sg:city":"Westland",
    "sg:classifiers":[
        {
            "category":"Communications",
            "type":"Services"
        }
    ],
    "sg:phone":"+1 734 454 7630",
    "sg:postcode":"48185",
    "sg:province":"MI",
    "sg:tags":[
        "web",
        "design"
    ],
    "wof:name":"Electronics Consultants",
    "wof:placetype":"venue"
},
  "geometry": {"coordinates":[-83.416496,42.350899],"type":"Point"}
}