{
  "type": "Feature",
  "properties": {
    "iso:country":"US",
    "sg:address":"3601 Washtenaw Ave",
    "sg:city":"Ann Arbor",
    "sg:classifiers":[
        {
            "category":"Retail",
            "subcategory":"Repair Shop",
            "type":"Services"
        }
    ],
    "sg:phone":"+1 734 975 1050",
    "sg:postcode":"48104",
    "sg:province":"MI",
    "sg:tags":[
        "picture",
        "framing"
    ],
    "wof:name":"Frameology",
    "wof:placetype":"venue"
},
  "geometry": {"coordinates":[-83.690022,42.255803],"type":"Point"}
}