{
  "type": "Feature",
  "properties": {
    "iso:country":"US",
    "sg:address":"6652 Clear Lake Rd",
    "sg:city":"Imlay City",
    "sg:classifiers":[
        {
            "category":"Farming",
            "subcategory":"Livestock Farm",
            "type":"Manufacturing & Wholesale Goods"
        }
    ],
    "sg:phone":"+1 810 724 8898",
    "sg:postcode":"48444",
    "sg:province":"MI",
    "sg:tags":[
        "beef",
        "feedlot",
        "cattle"
    ],
    "wof:name":"Lloyd Ragatz",
    "wof:placetype":"venue"
},
  "geometry": {"coordinates":[-83.091339,43.152284],"type":"Point"}
}