{
  "type": "Feature",
  "properties": {
    "iso:country":"US",
    "sg:address":"1516 W Pierson Rd",
    "sg:city":"Flint",
    "sg:classifiers":[
        {
            "category":"Food & Beverages",
            "subcategory":"Groceries & Convenience Stores",
            "type":"Retail Goods"
        }
    ],
    "sg:phone":"+1 810 787 5561",
    "sg:postcode":"48505",
    "sg:province":"MI",
    "sg:tags":[
        "grocer"
    ],
    "wof:name":"Shop & Go Mini Mart",
    "wof:placetype":"venue"
},
  "geometry": {"coordinates":[-83.72349800000001,43.060789],"type":"Point"}
}