{
  "type": "Feature",
  "properties": {
    "iso:country":"US",
    "sg:address":"7501 W Saginaw Hwy",
    "sg:city":"Lansing",
    "sg:classifiers":[
        {
            "category":"Travel",
            "subcategory":"Hotels & Motels",
            "type":"Entertainment"
        }
    ],
    "sg:phone":"+1 517 627 3211",
    "sg:postcode":"48917",
    "sg:province":"MI",
    "sg:tags":[
        "operation",
        "eating"
    ],
    "wof:name":"Holiday Inn",
    "wof:placetype":"venue"
},
  "geometry": {"coordinates":[-84.66018699999999,42.740974],"type":"Point"}
}