{
  "type": "Feature",
  "properties": {
    "iso:country":"US",
    "sg:address":"4377 N Waldo Rd",
    "sg:city":"Midland",
    "sg:classifiers":[
        {
            "category":"Farming",
            "subcategory":"Nursery",
            "type":"Manufacturing & Wholesale Goods"
        }
    ],
    "sg:phone":"+1 989 832 3522",
    "sg:postcode":"48642",
    "sg:province":"MI",
    "sg:tags":[
        "greenhouse"
    ],
    "wof:name":"Russell's Greenhouse",
    "wof:placetype":"venue"
},
  "geometry": {"coordinates":[-84.187006,43.736836],"type":"Point"}
}