{
  "type": "Feature",
  "properties": {
    "iso:country":"US",
    "sg:address":"20600 Eureka Rd",
    "sg:city":"Taylor",
    "sg:classifiers":[
        {
            "category":"Professional",
            "subcategory":"Detective & Security Services",
            "type":"Services"
        }
    ],
    "sg:phone":"+1 734 285 7772",
    "sg:postcode":"48180",
    "sg:province":"MI",
    "sg:tags":[
        "electrical",
        "contractor"
    ],
    "wof:name":"Initial Security",
    "wof:placetype":"venue"
},
  "geometry": {"coordinates":[-83.237217,42.198372],"type":"Point"}
}