{
  "type": "Feature",
  "properties": {
    "iso:country":"US",
    "sg:address":"320 Union St",
    "sg:city":"Milford",
    "sg:classifiers":[
        {
            "category":"Building & Trades",
            "subcategory":"Equipment Rental",
            "type":"Services"
        }
    ],
    "sg:phone":"+1 248 685 7788",
    "sg:postcode":"48381",
    "sg:province":"MI",
    "wof:name":"Milford Crane Rental Inc",
    "wof:placetype":"venue"
},
  "geometry": {"coordinates":[-83.599034,42.590493],"type":"Point"}
}