{
  "type": "Feature",
  "properties": {
    "iso:country":"US",
    "sg:address":"18212 B Dr N",
    "sg:city":"Marshall",
    "sg:classifiers":[
        {
            "category":"Professional",
            "subcategory":"Credit Reporting & Collection",
            "type":"Services"
        }
    ],
    "sg:phone":"+1 269 781 3121",
    "sg:postcode":"49068",
    "sg:province":"MI",
    "sg:tags":[
        "agency"
    ],
    "wof:name":"Dealer Services",
    "wof:placetype":"venue"
},
  "geometry": {"coordinates":[-84.94299599999999,42.262344],"type":"Point"}
}