{
  "type": "Feature",
  "properties": {
    "iso:country":"US",
    "sg:address":"2285 Pine Ridge Dr",
    "sg:city":"Jenison",
    "sg:classifiers":[
        {
            "category":"Building & Trades",
            "subcategory":"Construction",
            "type":"Services"
        }
    ],
    "sg:phone":"+1 616 662 0687",
    "sg:postcode":"49428",
    "sg:province":"MI",
    "sg:tags":[
        "concrete",
        "contractor"
    ],
    "sg:website":"www.hovinghconcrete.com",
    "wof:name":"Hovingh Concrete Inc",
    "wof:placetype":"venue"
},
  "geometry": {"coordinates":[-85.837583,42.891786],"type":"Point"}
}