{
  "type": "Feature",
  "properties": {
    "iso:country":"US",
    "sg:address":"807 Judd Rd",
    "sg:city":"Saline",
    "sg:classifiers":[
        {
            "category":"Building & Trades",
            "subcategory":"Construction",
            "type":"Services"
        }
    ],
    "sg:phone":"+1 734 429 5503",
    "sg:postcode":"48176",
    "sg:province":"MI",
    "sg:tags":[
        "residential"
    ],
    "wof:name":"Able Gable LLC",
    "wof:placetype":"venue"
},
  "geometry": {"coordinates":[-83.723877,42.141432],"type":"Point"}
}