{
  "type": "Feature",
  "properties": {
    "iso:country":"US",
    "sg:address":"28744 Townley St",
    "sg:city":"Madison Heights",
    "sg:classifiers":[
        {
            "category":"Freight",
            "type":"Transportation"
        }
    ],
    "sg:phone":"+1 248 547 1905",
    "sg:postcode":"48071",
    "sg:province":"MI",
    "sg:tags":[
        "delivery"
    ],
    "wof:name":"Ron Starzyk Delivery Svc",
    "wof:placetype":"venue"
},
  "geometry": {"coordinates":[-83.103213,42.495459],"type":"Point"}
}