{
  "type": "Feature",
  "properties": {
    "iso:country":"US",
    "sg:address":"22024 Trombly St",
    "sg:city":"Saint Clair Shores",
    "sg:classifiers":[
        {
            "category":"Food & Beverages",
            "subcategory":"Meat & Fish",
            "type":"Retail Goods"
        }
    ],
    "sg:phone":"+1 586 771 4906",
    "sg:postcode":"48080",
    "sg:province":"MI",
    "wof:name":"Werbroucks Market",
    "wof:placetype":"venue"
},
  "geometry": {"coordinates":[-82.900931,42.47598],"type":"Point"}
}