{
  "type": "Feature",
  "properties": {
    "iso:country":"US",
    "sg:address":"3512 Creekwood Dr",
    "sg:city":"Saginaw",
    "sg:classifiers":[
        {
            "category":"Organizations",
            "subcategory":"Religious Organization",
            "type":"Services"
        }
    ],
    "sg:phone":"+1 989 777 9023",
    "sg:postcode":"48601",
    "sg:province":"MI",
    "wof:name":"Grace Pentecostal Church Inc",
    "wof:placetype":"venue"
},
  "geometry": {"coordinates":[-83.90519,43.374511],"type":"Point"}
}