{
  "type": "Feature",
  "properties": {
    "iso:country":"US",
    "sg:address":"640 W Main St",
    "sg:city":"Stockbridge",
    "sg:classifiers":[
        {
            "category":"Home & Garden",
            "subcategory":"Hardware",
            "type":"Retail Goods"
        }
    ],
    "sg:phone":"+1 517 851 4404",
    "sg:postcode":"49285",
    "sg:province":"MI",
    "wof:name":"Byrum Hardware",
    "wof:placetype":"venue"
},
  "geometry": {"coordinates":[-84.18826900000001,42.453428],"type":"Point"}
}