{
  "type": "Feature",
  "properties": {
    "iso:country":"US",
    "sg:address":"6057 Hill Rd",
    "sg:city":"Swartz Creek",
    "sg:classifiers":[
        {
            "category":"Building & Trades",
            "subcategory":"Landscaping Services",
            "type":"Services"
        }
    ],
    "sg:phone":"+1 810 235 4624",
    "sg:postcode":"48473",
    "sg:province":"MI",
    "sg:tags":[
        "tree"
    ],
    "wof:name":"Jerry's Complete Yard & Tree",
    "wof:placetype":"venue"
},
  "geometry": {"coordinates":[-83.808712,42.942589],"type":"Point"}
}