{
  "type": "Feature",
  "properties": {
    "iso:country":"US",
    "sg:address":"1550 Fonger St NE",
    "sg:city":"Sparta",
    "sg:classifiers":[
        {
            "category":"Building & Trades",
            "subcategory":"Construction",
            "type":"Services"
        }
    ],
    "sg:phone":"+1 616 887 7793",
    "sg:postcode":"49345",
    "sg:province":"MI",
    "sg:tags":[
        "house"
    ],
    "wof:name":"Sandys Remodeling",
    "wof:placetype":"venue"
},
  "geometry": {"coordinates":[-85.636314,43.138646],"type":"Point"}
}