{
  "type": "Feature",
  "properties": {
    "iso:country":"US",
    "sg:address":"906 N Lafayette St",
    "sg:city":"Greenville",
    "sg:classifiers":[
        {
            "category":"Restaurant",
            "type":"Food & Drink"
        }
    ],
    "sg:menulink":"http://www.allmenus.com/mi/greenville/186123-mcdonalds/menu/",
    "sg:postcode":"48838",
    "sg:province":"MI",
    "sg:tags":[
        "burger",
        "american"
    ],
    "wof:name":"McDonald's",
    "wof:placetype":"venue"
},
  "geometry": {"coordinates":[-85.25302000000001,43.189362],"type":"Point"}
}