{
  "type": "Feature",
  "properties": {
    "iso:country":"US",
    "sg:address":"13049 Independence Ave",
    "sg:city":"Shelby Twp",
    "sg:classifiers":[
        {
            "category":"Professional",
            "subcategory":"Secretarial Services",
            "type":"Services"
        }
    ],
    "sg:phone":"+1 586 997 9757",
    "sg:postcode":"48315",
    "sg:province":"MI",
    "sg:tags":[
        "transcription",
        "medical"
    ],
    "wof:name":"ASAP Medical Transcription",
    "wof:placetype":"venue"
},
  "geometry": {"coordinates":[-82.99934,42.648002],"type":"Point"}
}