{
  "type": "Feature",
  "properties": {
    "iso:country":"US",
    "sg:address":"6346 Orchard Lake Rd",
    "sg:city":"West Bloomfield",
    "sg:classifiers":[
        {
            "category":"Real Estate",
            "subcategory":"Real Estate Services",
            "type":"Services"
        }
    ],
    "sg:phone":"+1 248 855 2577",
    "sg:postcode":"48322",
    "sg:province":"MI",
    "wof:name":"Paramount Acquisitions Llc",
    "wof:placetype":"venue"
},
  "geometry": {"coordinates":[-83.361014,42.545301],"type":"Point"}
}