{
  "type": "Feature",
  "properties": {
    "iso:country":"US",
    "sg:address":"103 Main",
    "sg:city":"Lake City",
    "sg:classifiers":[
        {
            "category":"Personal",
            "type":"Services"
        }
    ],
    "sg:phone":"+1 231 839 7704",
    "sg:postcode":"49651",
    "sg:province":"MI",
    "wof:name":"Baked Beans",
    "wof:placetype":"venue"
},
  "geometry": {"coordinates":[-85.21462099999999,44.33412],"type":"Point"}
}