{
  "type": "Feature",
  "properties": {
    "iso:country":"US",
    "sg:address":"312 Michigan Ave",
    "sg:city":"Detroit",
    "sg:classifiers":[
        {
            "category":"Shopping",
            "subcategory":"Photographic Equipment",
            "type":"Retail Goods"
        }
    ],
    "sg:phone":"+1 313 961 0142",
    "sg:postcode":"48226",
    "sg:province":"MI",
    "sg:tags":[
        "photofinishing",
        "supply"
    ],
    "wof:name":"Ritz Camera 140",
    "wof:placetype":"venue"
},
  "geometry": {"coordinates":[-83.052296,42.331674],"type":"Point"}
}