{
  "type": "Feature",
  "properties": {
    "iso:country":"US",
    "sg:address":"13836 Hendricks Ave",
    "sg:city":"Warren",
    "sg:classifiers":[
        {
            "category":"Wholesale",
            "subcategory":"Home Furnishings",
            "type":"Manufacturing & Wholesale Goods"
        }
    ],
    "sg:phone":"+1 586 778 1075",
    "sg:postcode":"48089",
    "sg:province":"MI",
    "sg:tags":[
        "housewares"
    ],
    "wof:name":"Arden Corp",
    "wof:placetype":"venue"
},
  "geometry": {"coordinates":[-82.98203700000001,42.460671],"type":"Point"}
}