{
  "type": "Feature",
  "properties": {
    "iso:country":"US",
    "sg:address":"14900 Ashton Rd",
    "sg:city":"Detroit",
    "sg:classifiers":[
        {
            "category":"Professional",
            "subcategory":"Management & Consulting",
            "type":"Services"
        }
    ],
    "sg:phone":"+1 313 838 0347",
    "sg:postcode":"48223",
    "sg:province":"MI",
    "wof:name":"Glory Building Bridges LLC",
    "wof:placetype":"venue"
},
  "geometry": {"coordinates":[-83.2191,42.397394],"type":"Point"}
}