{
  "type": "Feature",
  "properties": {
    "iso:country":"US",
    "sg:address":"2144 Fletcher Rd",
    "sg:city":"Erie",
    "sg:classifiers":[
        {
            "category":"Retail",
            "subcategory":"Auto Repair",
            "type":"Services"
        }
    ],
    "sg:phone":"+1 734 848 4245",
    "sg:postcode":"48133",
    "sg:province":"MI",
    "sg:tags":[
        "general"
    ],
    "wof:name":"Turner Repair",
    "wof:placetype":"venue"
},
  "geometry": {"coordinates":[-83.496979,41.791219],"type":"Point"}
}