{
  "type": "Feature",
  "properties": {
    "iso:country":"US",
    "sg:address":"21095 Goddard Rd",
    "sg:city":"Taylor",
    "sg:classifiers":[
        {
            "category":"Banks & Credit Unions",
            "subcategory":"Bank",
            "type":"Services"
        }
    ],
    "sg:phone":"+1 734 287 8980",
    "sg:postcode":"48180",
    "sg:province":"MI",
    "sg:tags":[
        "state",
        "commercial"
    ],
    "wof:name":"Bank One",
    "wof:placetype":"venue"
},
  "geometry": {"coordinates":[-83.238877,42.227293],"type":"Point"}
}