{
  "type": "Feature",
  "properties": {
    "iso:country":"US",
    "sg:address":"1832 Fitch Ave",
    "sg:city":"Marquette",
    "sg:classifiers":[
        {
            "category":"Retail",
            "subcategory":"Repair Shop",
            "type":"Services"
        }
    ],
    "sg:phone":"+1 906 226 2548",
    "sg:postcode":"49855",
    "sg:province":"MI",
    "wof:name":"Dons Gas Repair",
    "wof:placetype":"venue"
},
  "geometry": {"coordinates":[-87.397465,46.563399],"type":"Point"}
}