{
  "type": "Feature",
  "properties": {
    "iso:country":"US",
    "sg:address":"30700 Telegraph Rd",
    "sg:city":"Bingham Farms",
    "sg:classifiers":[
        {
            "category":"Professional",
            "subcategory":"Lawyer & Legal Services",
            "type":"Services"
        }
    ],
    "sg:phone":"+1 248 540 1222",
    "sg:postcode":"48025",
    "sg:province":"MI",
    "wof:name":"Grant Donna B Atty",
    "wof:placetype":"venue"
},
  "geometry": {"coordinates":[-83.2854,42.513302],"type":"Point"}
}