{
  "type": "Feature",
  "properties": {
    "iso:country":"US",
    "sg:address":"119 E Maple St",
    "sg:city":"Mason",
    "sg:classifiers":[
        {
            "category":"Sports & Exercise",
            "subcategory":"Gym",
            "type":"Entertainment"
        }
    ],
    "sg:phone":"+1 517 676 8680",
    "sg:postcode":"48854",
    "sg:province":"MI",
    "sg:tags":[
        "fitness",
        "consulting",
        "management",
        "physical",
        "facility"
    ],
    "wof:name":"Curves For Women",
    "wof:placetype":"venue"
},
  "geometry": {"coordinates":[-84.441667,42.580264],"type":"Point"}
}