{
  "type": "Feature",
  "properties": {
    "iso:country":"US",
    "sg:address":"1838 Megans Meadow Dr",
    "sg:city":"Commerce Twp",
    "sg:classifiers":[
        {
            "category":"Professional",
            "subcategory":"Computer Services",
            "type":"Services"
        }
    ],
    "sg:phone":"+1 248 926 0585",
    "sg:postcode":"48390",
    "sg:province":"MI",
    "sg:tags":[
        "consultant",
        "designer"
    ],
    "wof:name":"Sundree System Solutions",
    "wof:placetype":"venue"
},
  "geometry": {"coordinates":[-83.506096,42.565085],"type":"Point"}
}