{
  "type": "Feature",
  "properties": {
    "iso:country":"US",
    "sg:address":"1476 W Sherman Blvd",
    "sg:city":"Muskegon",
    "sg:classifiers":[
        {
            "category":"Social Services",
            "subcategory":"Child Care",
            "type":"Services"
        }
    ],
    "sg:phone":"+1 231 755 2010",
    "sg:postcode":"49441",
    "sg:province":"MI",
    "wof:name":"Kelly Shijuan's",
    "wof:placetype":"venue"
},
  "geometry": {"coordinates":[-86.279267,43.205634],"type":"Point"}
}