{
  "type": "Feature",
  "properties": {
    "iso:country":"US",
    "sg:address":"2764 Bransford Dr SE",
    "sg:city":"Grand Rapids",
    "sg:classifiers":[
        {
            "category":"Building & Trades",
            "subcategory":"Construction",
            "type":"Services"
        }
    ],
    "sg:phone":"+1 616 464 3335",
    "sg:postcode":"49512",
    "sg:province":"MI",
    "sg:tags":[
        "house"
    ],
    "wof:name":"Demaagd Construction Services",
    "wof:placetype":"venue"
},
  "geometry": {"coordinates":[-85.598099,42.899848],"type":"Point"}
}