{
  "type": "Feature",
  "properties": {
    "iso:country":"US",
    "sg:address":"4217 Ray Mar Ct",
    "sg:city":"Onsted",
    "sg:classifiers":[
        {
            "category":"Home & Garden",
            "subcategory":"Building Materials",
            "type":"Retail Goods"
        }
    ],
    "sg:phone":"+1 517 467 6315",
    "sg:postcode":"49265",
    "sg:province":"MI",
    "wof:name":"Pelham Garage Doors",
    "wof:placetype":"venue"
},
  "geometry": {"coordinates":[-84.143,42.055144],"type":"Point"}
}