{
  "type": "Feature",
  "properties": {
    "iso:country":"US",
    "sg:address":"5421 Shabbona Rd",
    "sg:city":"Decker",
    "sg:classifiers":[
        {
            "category":"Education",
            "subcategory":"School",
            "type":"Public Place"
        }
    ],
    "sg:phone":"+1 810 672 9611",
    "sg:postcode":"48426",
    "sg:province":"MI",
    "wof:name":"Bethany Christian School",
    "wof:placetype":"venue"
},
  "geometry": {"coordinates":[-83.048739,43.531697],"type":"Point"}
}