{
  "type": "Feature",
  "properties": {
    "iso:country":"US",
    "sg:address":"14979 State Hwy 68",
    "sg:city":"Millersburg",
    "sg:classifiers":[
        {
            "category":"Retail",
            "subcategory":"Repair Shop",
            "type":"Services"
        }
    ],
    "sg:phone":"+1 989 733 4444",
    "sg:postcode":"49765",
    "sg:province":"MI",
    "sg:tags":[
        "taxidermist"
    ],
    "wof:name":"3-D Taxidermy",
    "wof:placetype":"venue"
},
  "geometry": {"coordinates":[-84.109842,45.35476],"type":"Point"}
}