{
  "type": "Feature",
  "properties": {
    "iso:country":"US",
    "sg:address":"150 Orval St",
    "sg:city":"Sandusky",
    "sg:classifiers":[
        {
            "category":"Wholesale",
            "subcategory":"Scrap",
            "type":"Manufacturing & Wholesale Goods"
        }
    ],
    "sg:phone":"+1 810 648 3590",
    "sg:postcode":"48471",
    "sg:province":"MI",
    "sg:tags":[
        "recycling",
        "center"
    ],
    "wof:name":"Sanilac County Recycling Ctr",
    "wof:placetype":"venue"
},
  "geometry": {"coordinates":[-82.816366,43.420155],"type":"Point"}
}