{
  "type": "Feature",
  "properties": {
    "iso:country":"US",
    "sg:address":"4100 Broadmoor Ave SE",
    "sg:city":"Grand Rapids",
    "sg:classifiers":[
        {
            "category":"Manufacturing",
            "subcategory":"Metals",
            "type":"Manufacturing & Wholesale Goods"
        }
    ],
    "sg:phone":"+1 616 698 7550",
    "sg:postcode":"49512",
    "sg:province":"MI",
    "sg:tags":[
        "plating"
    ],
    "wof:name":"Allied Finishing Inc",
    "wof:placetype":"venue"
},
  "geometry": {"coordinates":[-85.568404,42.888234],"type":"Point"}
}