{
  "type": "Feature",
  "properties": {
    "iso:country":"US",
    "sg:address":"10118 Curtis Dr",
    "sg:city":"Pinckney",
    "sg:classifiers":[
        {
            "category":"Wholesale",
            "subcategory":"Machinery & Supplies",
            "type":"Manufacturing & Wholesale Goods"
        }
    ],
    "sg:phone":"+1 734 954 0452",
    "sg:postcode":"48169",
    "sg:province":"MI",
    "sg:tags":[
        "equipment",
        "industrial"
    ],
    "wof:name":"Vibro Synamics",
    "wof:placetype":"venue"
},
  "geometry": {"coordinates":[-83.941805,42.451397],"type":"Point"}
}