{
  "type": "Feature",
  "properties": {
    "iso:country":"US",
    "sg:address":"103 E Church St",
    "sg:city":"Capac",
    "sg:classifiers":[
        {
            "category":"Government",
            "subcategory":"Police Station",
            "type":"Public Place"
        }
    ],
    "sg:phone":"+1 810 395 4351",
    "sg:postcode":"48014",
    "sg:province":"MI",
    "sg:tags":[
        "department"
    ],
    "wof:name":"Capac Village Police Dept",
    "wof:placetype":"venue"
},
  "geometry": {"coordinates":[-82.92846400000001,43.014153],"type":"Point"}
}