{
  "type": "Feature",
  "properties": {
    "iso:country":"US",
    "sg:address":"7491 State Rte 403",
    "sg:city":"Dilltown",
    "sg:classifiers":[
        {
            "category":"Government",
            "subcategory":"Post Office",
            "type":"Public Place"
        }
    ],
    "sg:phone":"+1 814 000 1111",
    "sg:postcode":"99999",
    "sg:province":"MI",
    "sg:tags":[
        "postal",
        "us"
    ],
    "wof:name":"US Post Office",
    "wof:placetype":"venue"
},
  "geometry": {"coordinates":[-85.97388100000001,43.06615],"type":"Point"}
}