{
  "type": "Feature",
  "properties": {
    "iso:country":"US",
    "sg:address":"1400 E Hile Rd",
    "sg:city":"Muskegon",
    "sg:classifiers":[
        {
            "category":"Organizations",
            "subcategory":"Religious Organization",
            "type":"Services"
        }
    ],
    "sg:phone":"+1 231 798 1187",
    "sg:postcode":"49441",
    "sg:province":"MI",
    "sg:tags":[
        "church"
    ],
    "sg:website":"www.muskegon.freemethodistchurch.org",
    "wof:name":"First Free Methodist Church",
    "wof:placetype":"venue"
},
  "geometry": {"coordinates":[-86.209667,43.168915],"type":"Point"}
}