{
  "type": "Feature",
  "properties": {
    "iso:country":"US",
    "sg:address":"4045 Lincoln Rd",
    "sg:city":"Bloomfield Hills",
    "sg:classifiers":[
        {
            "category":"Shopping",
            "subcategory":"Hobbies, Toys, & Games",
            "type":"Retail Goods"
        }
    ],
    "sg:phone":"+1 248 540 2195",
    "sg:postcode":"48301",
    "sg:province":"MI",
    "wof:name":"Natures Impressions",
    "wof:placetype":"venue"
},
  "geometry": {"coordinates":[-83.281631,42.536793],"type":"Point"}
}