{
  "type": "Feature",
  "properties": {
    "iso:country":"US",
    "sg:address":"701 E Michigan St",
    "sg:city":"Mount Pleasant",
    "sg:classifiers":[
        {
            "category":"Personal",
            "subcategory":"Beauty Salon",
            "type":"Services"
        }
    ],
    "sg:phone":"+1 989 772 2089",
    "sg:postcode":"48858",
    "sg:province":"MI",
    "sg:tags":[
        "shop"
    ],
    "wof:name":"Nadines Beauty Salon",
    "wof:placetype":"venue"
},
  "geometry": {"coordinates":[-84.768996,43.603589],"type":"Point"}
}