{
  "type": "Feature",
  "properties": {
    "iso:country":"US",
    "sg:address":"1985 Yorway Dr",
    "sg:city":"Howell",
    "sg:classifiers":[
        {
            "category":"Professional",
            "subcategory":"Business Services",
            "type":"Services"
        }
    ],
    "sg:phone":"+1 517 546 8577",
    "sg:postcode":"48843",
    "sg:province":"MI",
    "wof:name":"Chartier Interiors",
    "wof:placetype":"venue"
},
  "geometry": {"coordinates":[-83.951746,42.567591],"type":"Point"}
}