{
  "type": "Feature",
  "properties": {
    "iso:country":"US",
    "sg:address":"5226 S Cedar St",
    "sg:city":"Lansing",
    "sg:classifiers":[
        {
            "category":"Banks & Credit Unions",
            "subcategory":"Bank",
            "type":"Services"
        }
    ],
    "sg:phone":"+1 517 394 0734",
    "sg:postcode":"48911",
    "sg:province":"MI",
    "wof:name":"Comerica Bank",
    "wof:placetype":"venue"
},
  "geometry": {"coordinates":[-84.548129,42.679548],"type":"Point"}
}