{
  "type": "Feature",
  "properties": {
    "iso:country":"US",
    "sg:address":"212 E Paw Paw St",
    "sg:city":"Paw Paw",
    "sg:classifiers":[
        {
            "category":"Government",
            "subcategory":"Court House",
            "type":"Public Place"
        }
    ],
    "sg:phone":"+1 269 657 8260",
    "sg:postcode":"49079",
    "sg:province":"MI",
    "sg:tags":[
        "county"
    ],
    "wof:name":"Judge William C Buhl's Office",
    "wof:placetype":"venue"
},
  "geometry": {"coordinates":[-85.89090899999999,42.216631],"type":"Point"}
}