{
  "type": "Feature",
  "properties": {
    "iso:country":"US",
    "sg:address":"8830 Whitmore Lake Rd",
    "sg:city":"Brighton",
    "sg:classifiers":[
        {
            "category":"Manufacturing",
            "subcategory":"Tools & Machinery",
            "type":"Manufacturing & Wholesale Goods"
        }
    ],
    "sg:phone":"+1 810 231 0212",
    "sg:postcode":"48116",
    "sg:province":"MI",
    "sg:tags":[
        "die",
        "maker"
    ],
    "wof:name":"Matrix Engineering Inc",
    "wof:placetype":"venue"
},
  "geometry": {"coordinates":[-83.75625100000001,42.472575],"type":"Point"}
}