{
  "type": "Feature",
  "properties": {
    "iso:country":"US",
    "sg:address":"3123 Crooks Rd",
    "sg:city":"Royal Oak",
    "sg:classifiers":[
        {
            "category":"Professional",
            "subcategory":"Lawyer & Legal Services",
            "type":"Services"
        }
    ],
    "sg:phone":"+1 248 288 2080",
    "sg:postcode":"48073",
    "sg:province":"MI",
    "wof:name":"Anderson Chisolm & Shuttie",
    "wof:placetype":"venue"
},
  "geometry": {"coordinates":[-83.164597,42.516499],"type":"Point"}
}