{
  "type": "Feature",
  "properties": {
    "iso:country":"US",
    "sg:address":"461 S Main St",
    "sg:city":"Plymouth",
    "sg:classifiers":[
        {
            "category":"Professional",
            "subcategory":"Employment Agencies",
            "type":"Services"
        }
    ],
    "sg:phone":"+1 734 207 1501",
    "sg:postcode":"48170",
    "sg:province":"MI",
    "sg:website":"www.ultimatestaffing.com",
    "wof:name":"Ultimate Staffing",
    "wof:placetype":"venue"
},
  "geometry": {"coordinates":[-83.469346,42.369132],"type":"Point"}
}