{
  "type": "Feature",
  "properties": {
    "iso:country":"US",
    "sg:address":"8651 Mohawk Ct",
    "sg:city":"Stanwood",
    "sg:classifiers":[
        {
            "category":"Travel",
            "subcategory":"Hotels & Motels",
            "type":"Entertainment"
        }
    ],
    "sg:phone":"+1 231 972 7175",
    "sg:postcode":"49346",
    "sg:province":"MI",
    "sg:tags":[
        "operation"
    ],
    "wof:name":"Swains Lake Farms Inc",
    "wof:placetype":"venue"
},
  "geometry": {"coordinates":[-85.29652,43.593016],"type":"Point"}
}