{
  "type": "Feature",
  "properties": {
    "iso:country":"US",
    "sg:address":"2420 W C Ave",
    "sg:city":"Kalamazoo",
    "sg:classifiers":[
        {
            "category":"Health Services",
            "subcategory":"Medical Lab",
            "type":"Services"
        }
    ],
    "sg:phone":"+1 269 373 6181",
    "sg:postcode":"49009",
    "sg:province":"MI",
    "sg:tags":[
        "laboratory"
    ],
    "wof:name":"Medlink Clinical Consultants",
    "wof:placetype":"venue"
},
  "geometry": {"coordinates":[-85.63033299999999,42.391107],"type":"Point"}
}