{
  "type": "Feature",
  "properties": {
    "iso:country":"US",
    "sg:address":"10891 Tamarack Rd",
    "sg:city":"Lakeview",
    "sg:classifiers":[
        {
            "category":"Building & Trades",
            "subcategory":"Equipment Rental",
            "type":"Services"
        }
    ],
    "sg:phone":"+1 989 352 7526",
    "sg:postcode":"48850",
    "sg:province":"MI",
    "wof:name":"Shaw Aviation Inc",
    "wof:placetype":"venue"
},
  "geometry": {"coordinates":[-85.29933,43.438562],"type":"Point"}
}