{
  "type": "Feature",
  "properties": {
    "iso:country":"US",
    "sg:address":"1260 Ekhart St NE",
    "sg:city":"Grand Rapids",
    "sg:classifiers":[
        {
            "category":"Health Services",
            "subcategory":"Clinic",
            "type":"Services"
        }
    ],
    "sg:phone":"+1 616 356 5202",
    "sg:postcode":"49503",
    "sg:province":"MI",
    "sg:tags":[
        "home"
    ],
    "sg:website":"www.visitingphysicians.com",
    "wof:name":"Visiting Physicians Assoc",
    "wof:placetype":"venue"
},
  "geometry": {"coordinates":[-85.64027299999999,42.982988],"type":"Point"}
}