{
  "type": "Feature",
  "properties": {
    "iso:country":"US",
    "sg:address":"2317 W Michigan Ave",
    "sg:city":"Lansing",
    "sg:classifiers":[
        {
            "category":"Food & Beverages",
            "subcategory":"Groceries & Convenience Stores",
            "type":"Retail Goods"
        }
    ],
    "sg:phone":"+1 517 482 8488",
    "sg:postcode":"48917",
    "sg:province":"MI",
    "sg:tags":[
        "grocer"
    ],
    "wof:name":"Sav-Way Food Ctr",
    "wof:placetype":"venue"
},
  "geometry": {"coordinates":[-84.583097,42.733786],"type":"Point"}
}