{
  "type": "Feature",
  "properties": {
    "iso:country":"US",
    "sg:address":"213 N East St",
    "sg:city":"Mason",
    "sg:classifiers":[
        {
            "category":"Personal",
            "type":"Services"
        }
    ],
    "sg:phone":"+1 517 676 9256",
    "sg:postcode":"48854",
    "sg:province":"MI",
    "wof:name":"Trellis",
    "wof:placetype":"venue"
},
  "geometry": {"coordinates":[-84.44656999999999,42.584069],"type":"Point"}
}