{
  "type": "Feature",
  "properties": {
    "iso:country":"US",
    "sg:address":"11888 Long Lake Dr",
    "sg:city":"Sparta",
    "sg:classifiers":[
        {
            "category":"Retail",
            "subcategory":"Repair Shop",
            "type":"Services"
        }
    ],
    "sg:phone":"+1 616 887 9139",
    "sg:postcode":"49345",
    "sg:province":"MI",
    "wof:name":"Royal Parts Works",
    "wof:placetype":"venue"
},
  "geometry": {"coordinates":[-85.680955,43.182684],"type":"Point"}
}