{
  "type": "Feature",
  "properties": {
    "iso:country":"US",
    "sg:address":"473 E Remus Rd",
    "sg:city":"Mt Pleasant",
    "sg:classifiers":[
        {
            "category":"Freight",
            "type":"Transportation"
        }
    ],
    "sg:phone":"+1 989 772 2053",
    "sg:postcode":"48858",
    "sg:province":"MI",
    "sg:tags":[
        "operator",
        "sanitary",
        "local",
        "trucking"
    ],
    "wof:name":"Gostola Trucking",
    "wof:placetype":"venue"
},
  "geometry": {"coordinates":[-84.843757,43.596749],"type":"Point"}
}