{
  "type": "Feature",
  "properties": {
    "iso:country":"US",
    "sg:address":"8600 W 9 Mile Rd",
    "sg:city":"Oak Park",
    "sg:classifiers":[
        {
            "category":"Autos & Motor Vehicles",
            "subcategory":"Fuel & Gas Station",
            "type":"Retail Goods"
        },
        {
            "category":"Food & Beverages",
            "subcategory":"Groceries & Convenience Stores",
            "type":"Retail Goods"
        }
    ],
    "sg:phone":"+1 248 399 0799",
    "sg:postcode":"48237",
    "sg:province":"MI",
    "wof:name":"Fast Track of Oak Park",
    "wof:placetype":"venue"
},
  "geometry": {"coordinates":[-83.15852,42.460297],"type":"Point"}
}