{
  "type": "Feature",
  "properties": {
    "iso:country":"US",
    "sg:address":"1107 W Chicago Blvd",
    "sg:city":"Tecumseh",
    "sg:classifiers":[
        {
            "category":"Professional",
            "subcategory":"Lawyer & Legal Services",
            "type":"Services"
        }
    ],
    "sg:phone":"+1 517 423 2797",
    "sg:postcode":"49286",
    "sg:province":"MI",
    "sg:tags":[
        "attorney"
    ],
    "wof:name":"Michael J Brooks",
    "wof:placetype":"venue"
},
  "geometry": {"coordinates":[-83.961921,42.006338],"type":"Point"}
}