{
  "type": "Feature",
  "properties": {
    "iso:country":"US",
    "sg:address":"606 Fenton Sq",
    "sg:city":"Fenton",
    "sg:classifiers":[
        {
            "category":"Personal",
            "subcategory":"Barber",
            "type":"Services"
        }
    ],
    "sg:phone":"+1 810 629 2613",
    "sg:postcode":"48430",
    "sg:province":"MI",
    "wof:name":"Fenton Family Hair Care",
    "wof:placetype":"venue"
},
  "geometry": {"coordinates":[-83.704702,42.796862],"type":"Point"}
}