{
  "type": "Feature",
  "properties": {
    "iso:country":"US",
    "sg:address":"2893 Dixie Hwy",
    "sg:city":"Waterford",
    "sg:classifiers":[
        {
            "category":"Manufacturing",
            "subcategory":"Tools & Machinery",
            "type":"Manufacturing & Wholesale Goods"
        }
    ],
    "sg:phone":"+1 248 618 0629",
    "sg:postcode":"48328",
    "sg:province":"MI",
    "sg:tags":[
        "control",
        "business",
        "mfg"
    ],
    "wof:name":"Micro Logic Inc",
    "wof:placetype":"venue"
},
  "geometry": {"coordinates":[-83.343537,42.674832],"type":"Point"}
}