{
  "type": "Feature",
  "properties": {
    "iso:country":"US",
    "sg:address":"606 Riverview Dr",
    "sg:city":"Kalamazoo",
    "sg:classifiers":[
        {
            "category":"Autos & Motor Vehicles",
            "subcategory":"Auto Supplies",
            "type":"Retail Goods"
        }
    ],
    "sg:phone":"+1 269 349 0111",
    "sg:postcode":"49048",
    "sg:province":"MI",
    "sg:tags":[
        "automobile",
        "parts"
    ],
    "wof:name":"Autozone",
    "wof:placetype":"venue"
},
  "geometry": {"coordinates":[-85.568724,42.298195],"type":"Point"}
}