{
  "type": "Feature",
  "properties": {
    "iso:country":"US",
    "sg:address":"252 Grandville Ave SW",
    "sg:city":"Grand Rapids",
    "sg:classifiers":[
        {
            "category":"Organizations",
            "subcategory":"Religious Organization",
            "type":"Services"
        }
    ],
    "sg:phone":"+1 616 735 2405",
    "sg:postcode":"49503",
    "sg:province":"MI",
    "sg:tags":[
        "clergy"
    ],
    "wof:name":"Living Water Ministry Network",
    "wof:placetype":"venue"
},
  "geometry": {"coordinates":[-85.67326300000001,42.957883],"type":"Point"}
}