{
  "type": "Feature",
  "properties": {
    "iso:country":"US",
    "sg:address":"1229 Division St",
    "sg:city":"Port Huron",
    "sg:classifiers":[
        {
            "category":"Freight",
            "type":"Transportation"
        },
        {
            "category":"Utilities",
            "subcategory":"Refuse",
            "type":"Services"
        }
    ],
    "sg:phone":"+1 810 982 2610",
    "sg:postcode":"48060",
    "sg:province":"MI",
    "sg:tags":[
        "garbage",
        "system",
        "collection",
        "trucking",
        "operator",
        "local"
    ],
    "wof:name":"J R's Trash Removal",
    "wof:placetype":"venue"
},
  "geometry": {"coordinates":[-82.436199,42.965363],"type":"Point"}
}