{
  "type": "Feature",
  "properties": {
    "iso:country":"US",
    "sg:address":"3840 Morrice Rd",
    "sg:city":"Webberville",
    "sg:classifiers":[
        {
            "category":"Building & Trades",
            "subcategory":"Construction",
            "type":"Services"
        }
    ],
    "sg:phone":"+1 517 468 2260",
    "sg:postcode":"48892",
    "sg:province":"MI",
    "sg:tags":[
        "contractor"
    ],
    "wof:name":"Lott Brothers Drywall",
    "wof:placetype":"venue"
},
  "geometry": {"coordinates":[-84.171031,42.697203],"type":"Point"}
}