{
  "type": "Feature",
  "properties": {
    "iso:country":"US",
    "sg:address":"26789 Woodward Ave Ste 106",
    "sg:city":"Huntington Wd",
    "sg:classifiers":[
        {
            "category":"Health Services",
            "subcategory":"Doctor",
            "type":"Services"
        },
        {
            "category":"Health Services",
            "subcategory":"Clinic",
            "type":"Services"
        }
    ],
    "sg:phone":"+1 248 548 1860",
    "sg:postcode":"48070",
    "sg:province":"MI",
    "sg:tags":[
        "counseling",
        "mental"
    ],
    "wof:name":"Caprio Richard A PHD",
    "wof:placetype":"venue"
},
  "geometry": {"coordinates":[-83.15720399999999,42.487598],"type":"Point"}
}