{
  "type": "Feature",
  "properties": {
    "iso:country":"US",
    "sg:address":"4000 Town Ctr",
    "sg:city":"Southfield",
    "sg:classifiers":[
        {
            "category":"Banks & Credit Unions",
            "subcategory":"Atm",
            "type":"Services"
        }
    ],
    "sg:phone":"+1 248 355 5300",
    "sg:postcode":"48075",
    "sg:province":"MI",
    "sg:tags":[
        "bankruptcy"
    ],
    "wof:name":"Cohen Steven J",
    "wof:placetype":"venue"
},
  "geometry": {"coordinates":[-83.243103,42.477402],"type":"Point"}
}