{
  "type": "Feature",
  "properties": {
    "iso:country":"US",
    "sg:address":"48465 Van Dyke Ave",
    "sg:city":"Shelby Twp",
    "sg:classifiers":[
        {
            "category":"Professional",
            "subcategory":"Accounting & Tax Preparation",
            "type":"Services"
        }
    ],
    "sg:phone":"+1 586 739 0099",
    "sg:postcode":"48317",
    "sg:province":"MI",
    "sg:tags":[
        "accountant"
    ],
    "wof:name":"Mark R Pasternak CPA",
    "wof:placetype":"venue"
},
  "geometry": {"coordinates":[-83.03341500000001,42.652315],"type":"Point"}
}