{
  "type": "Feature",
  "properties": {
    "iso:country":"US",
    "sg:address":"19 S 3rd St",
    "sg:city":"Niles",
    "sg:classifiers":[
        {
            "category":"Professional",
            "subcategory":"Lawyer & Legal Services",
            "type":"Services"
        }
    ],
    "sg:phone":"+1 269 683 6500",
    "sg:postcode":"49120",
    "sg:province":"MI",
    "sg:tags":[
        "attorney"
    ],
    "wof:name":"Hadsell Landgraf Lynch & Drew",
    "wof:placetype":"venue"
},
  "geometry": {"coordinates":[-86.255453,41.826303],"type":"Point"}
}