{
  "type": "Feature",
  "properties": {
    "iso:country":"US",
    "sg:address":"204 Hillcrest Ct",
    "sg:city":"Jonesville",
    "sg:classifiers":[
        {
            "category":"Organizations",
            "subcategory":"Non-profit Organization",
            "type":"Services"
        }
    ],
    "sg:phone":"+1 517 849 2515",
    "sg:postcode":"49250",
    "sg:province":"MI",
    "sg:tags":[
        "medical",
        "management"
    ],
    "wof:name":"Regional EMS",
    "wof:placetype":"venue"
},
  "geometry": {"coordinates":[-84.657518,41.98332],"type":"Point"}
}