{
  "type": "Feature",
  "properties": {
    "iso:country":"US",
    "sg:address":"727 Airport Blvd",
    "sg:city":"Ann Arbor",
    "sg:classifiers":[
        {
            "category":"Professional",
            "subcategory":"Research",
            "type":"Services"
        }
    ],
    "sg:phone":"+1 734 668 2567",
    "sg:postcode":"48108",
    "sg:province":"MI",
    "sg:tags":[
        "development",
        "robotics"
    ],
    "wof:name":"Cybernet Systems Corporation",
    "wof:placetype":"venue"
},
  "geometry": {"coordinates":[-83.745406,42.229409],"type":"Point"}
}