{
  "type": "Feature",
  "properties": {
    "iso:country":"US",
    "sg:address":"10000 McPherson Dr",
    "sg:city":"White Lake",
    "sg:classifiers":[
        {
            "category":"Building & Trades",
            "subcategory":"Construction",
            "type":"Services"
        }
    ],
    "sg:phone":"+1 248 363 6464",
    "sg:postcode":"48386",
    "sg:province":"MI",
    "sg:tags":[
        "water",
        "well",
        "drilling"
    ],
    "wof:name":"Mc Pherson Well Drilling Inc",
    "wof:placetype":"venue"
},
  "geometry": {"coordinates":[-83.484133,42.619231],"type":"Point"}
}