{
  "type": "Feature",
  "properties": {
    "iso:country":"US",
    "sg:address":"2143 Reneer Ave",
    "sg:city":"Muskegon",
    "sg:classifiers":[
        {
            "category":"Wholesale",
            "subcategory":"Electrical",
            "type":"Manufacturing & Wholesale Goods"
        }
    ],
    "sg:phone":"+1 231 755 3891",
    "sg:postcode":"49441",
    "sg:province":"MI",
    "sg:tags":[
        "fire",
        "equipment",
        "protection"
    ],
    "wof:name":"FDC Group",
    "wof:placetype":"venue"
},
  "geometry": {"coordinates":[-86.297534,43.196122],"type":"Point"}
}