{
  "type": "Feature",
  "properties": {
    "iso:country":"US",
    "sg:address":"32050 Harper Ave",
    "sg:city":"St Clair Shores",
    "sg:classifiers":[
        {
            "category":"Shopping",
            "subcategory":"Florist",
            "type":"Retail Goods"
        }
    ],
    "sg:phone":"+1 586 293 0227",
    "sg:postcode":"48082",
    "sg:province":"MI",
    "sg:website":"www.viviano.com",
    "wof:name":"Viviano Flower Shop",
    "wof:placetype":"venue"
},
  "geometry": {"coordinates":[-82.88890499999999,42.531326],"type":"Point"}
}