{
  "type": "Feature",
  "properties": {
    "iso:country":"US",
    "sg:address":"30843 Plymouth Rd",
    "sg:city":"Livonia",
    "sg:classifiers":[
        {
            "category":"Restaurant",
            "type":"Food & Drink"
        }
    ],
    "sg:menulink":"http://www.allmenus.com/mi/livonia/43435-the-boneyard/menu/",
    "sg:phone":"+1 734 427 6500",
    "sg:postcode":"48150",
    "sg:province":"MI",
    "sg:tags":[
        "barbecue",
        "american"
    ],
    "wof:name":"The BoneYard III",
    "wof:placetype":"venue"
},
  "geometry": {"coordinates":[-83.349767,42.368769],"type":"Point"}
}