{
  "type": "Feature",
  "properties": {
    "iso:country":"US",
    "sg:address":"2693 Lambeth Park",
    "sg:city":"Rochester",
    "sg:classifiers":[
        {
            "category":"Recreation",
            "type":"Entertainment"
        }
    ],
    "sg:phone":"+1 248 334 6233",
    "sg:postcode":"48306",
    "sg:province":"MI",
    "sg:tags":[
        "club",
        "membership"
    ],
    "wof:name":"Woodland Springs Club Inc",
    "wof:placetype":"venue"
},
  "geometry": {"coordinates":[-83.18785099999999,42.703475],"type":"Point"}
}