{
  "type": "Feature",
  "properties": {
    "iso:country":"US",
    "sg:address":"10484 Range Line Rd",
    "sg:city":"Berrien Springs",
    "sg:classifiers":[
        {
            "category":"Real Estate",
            "subcategory":"Architect",
            "type":"Services"
        }
    ],
    "sg:phone":"+1 269 471 3011",
    "sg:postcode":"49103",
    "sg:province":"MI",
    "wof:name":"CHR Visualization",
    "wof:placetype":"venue"
},
  "geometry": {"coordinates":[-86.331857,41.931381],"type":"Point"}
}