{
  "type": "Feature",
  "properties": {
    "iso:country":"US",
    "sg:address":"30488 Prescott St",
    "sg:city":"Romulus",
    "sg:classifiers":[
        {
            "category":"Building & Trades",
            "subcategory":"Cleaning & Sanitation",
            "type":"Services"
        }
    ],
    "sg:phone":"+1 734 753 4838",
    "sg:postcode":"48174",
    "sg:province":"MI",
    "sg:tags":[
        "maintenance"
    ],
    "wof:name":"Auntie Ms Cleaning Service",
    "wof:placetype":"venue"
},
  "geometry": {"coordinates":[-83.32532399999999,42.175765],"type":"Point"}
}