{
  "type": "Feature",
  "properties": {
    "iso:country":"US",
    "sg:address":"1105 24th St",
    "sg:city":"Port Huron",
    "sg:classifiers":[
        {
            "category":"Manufacturing",
            "subcategory":"Tools & Machinery",
            "type":"Manufacturing & Wholesale Goods"
        }
    ],
    "sg:phone":"+1 810 987 4700",
    "sg:postcode":"48060",
    "sg:province":"MI",
    "sg:tags":[
        "ind",
        "general"
    ],
    "sg:website":"www.wirtzusa.com",
    "wof:name":"Wirtz Mfg Co",
    "wof:placetype":"venue"
},
  "geometry": {"coordinates":[-82.452752,42.971518],"type":"Point"}
}