{
  "type": "Feature",
  "properties": {
    "iso:country":"US",
    "sg:address":"44800 N Groesbeck Hwy",
    "sg:city":"Clinton Township",
    "sg:classifiers":[
        {
            "category":"Home & Garden",
            "subcategory":"Hardware",
            "type":"Retail Goods"
        }
    ],
    "sg:phone":"+1 586 469 4444",
    "sg:postcode":"48036",
    "sg:province":"MI",
    "sg:tags":[
        "store"
    ],
    "wof:name":"Consumers Lumber & Home Improvement Center",
    "wof:placetype":"venue"
},
  "geometry": {"coordinates":[-82.87640399999999,42.627201],"type":"Point"}
}