{
  "type": "Feature",
  "properties": {
    "iso:country":"US",
    "sg:address":"2151 Graves Xing",
    "sg:city":"Mancelona",
    "sg:classifiers":[
        {
            "category":"Professional",
            "subcategory":"Business Services",
            "type":"Services"
        }
    ],
    "sg:phone":"+1 231 675 0691",
    "sg:postcode":"49659",
    "sg:province":"MI",
    "wof:name":"No Burn",
    "wof:placetype":"venue"
},
  "geometry": {"coordinates":[-85.059631,45.032458],"type":"Point"}
}