{
  "type": "Feature",
  "properties": {
    "iso:country":"US",
    "sg:address":"32643 Crystal Lake Ct",
    "sg:city":"Romulus",
    "sg:classifiers":[
        {
            "category":"Real Estate",
            "subcategory":"Real Estate Services",
            "type":"Services"
        },
        {
            "category":"Banks & Credit Unions",
            "subcategory":"Financial Services",
            "type":"Services"
        }
    ],
    "sg:phone":"+1 734 728 8611",
    "sg:postcode":"48174",
    "sg:province":"MI",
    "sg:tags":[
        "loan",
        "processing"
    ],
    "wof:name":"Tampa Mortgage Inc",
    "wof:placetype":"venue"
},
  "geometry": {"coordinates":[-83.35897900000001,42.261419],"type":"Point"}
}