{
  "type": "Feature",
  "properties": {
    "iso:country":"US",
    "sg:address":"8417 State Rd",
    "sg:city":"Millington",
    "sg:classifiers":[
        {
            "category":"Shopping",
            "subcategory":"Gifts & Souvenirs",
            "type":"Retail Goods"
        }
    ],
    "sg:phone":"+1 989 871 2992",
    "sg:postcode":"48746",
    "sg:province":"MI",
    "sg:tags":[
        "shop"
    ],
    "wof:name":"Honey's House Woodcrafts",
    "wof:placetype":"venue"
},
  "geometry": {"coordinates":[-83.529838,43.283365],"type":"Point"}
}