{
  "type": "Feature",
  "properties": {
    "iso:country":"US",
    "sg:address":"4307 Marywood Dr",
    "sg:city":"Troy",
    "sg:classifiers":[
        {
            "category":"Shopping",
            "subcategory":"Pets & Pet Supplies",
            "type":"Retail Goods"
        },
        {
            "category":"Retail",
            "subcategory":"Pet Boarding",
            "type":"Services"
        }
    ],
    "sg:phone":"+1 248 736 0879",
    "sg:postcode":"48085",
    "sg:province":"MI",
    "sg:tags":[
        "walker",
        "dog",
        "boarding/pet",
        "sitting"
    ],
    "wof:name":"Wiggle Butts Pet Sitting East",
    "wof:placetype":"venue"
},
  "geometry": {"coordinates":[-83.10790799999999,42.582606],"type":"Point"}
}