{
  "type": "Feature",
  "properties": {
    "iso:country":"US",
    "sg:address":"315 Prospect Ave",
    "sg:city":"Alma",
    "sg:classifiers":[
        {
            "category":"Social Services",
            "type":"Services"
        }
    ],
    "sg:phone":"+1 989 463 5693",
    "sg:postcode":"48801",
    "sg:province":"MI",
    "sg:tags":[
        "organization",
        "welfare"
    ],
    "wof:name":"Eightcap Inc",
    "wof:placetype":"venue"
},
  "geometry": {"coordinates":[-84.663549,43.378796],"type":"Point"}
}