{
  "type": "Feature",
  "properties": {
    "iso:country":"US",
    "sg:address":"9809 Cherry Valley Ave SE",
    "sg:city":"Caledonia",
    "sg:classifiers":[
        {
            "category":"Professional",
            "subcategory":"Art Services",
            "type":"Services"
        }
    ],
    "sg:phone":"+1 616 891 8881",
    "sg:postcode":"49316",
    "sg:province":"MI",
    "sg:tags":[
        "artist"
    ],
    "wof:name":"Overholt & Assoc",
    "wof:placetype":"venue"
},
  "geometry": {"coordinates":[-85.50690899999999,42.788628],"type":"Point"}
}