{
  "type": "Feature",
  "properties": {
    "iso:country":"US",
    "sg:address":"1800 W 14 Mile Rd Ste B",
    "sg:city":"Royal Oak",
    "sg:classifiers":[
        {
            "category":"Retail",
            "subcategory":"Laundry & Dry Cleaning",
            "type":"Services"
        }
    ],
    "sg:phone":"+1 248 435 2555",
    "sg:postcode":"48073",
    "sg:province":"MI",
    "wof:name":"Kelly Cleaners",
    "wof:placetype":"venue"
},
  "geometry": {"coordinates":[-83.166809,42.532959],"type":"Point"}
}