{
  "type": "Feature",
  "properties": {
    "iso:country":"US",
    "sg:address":"Vernor Hwy and Lansing St.",
    "sg:city":"Detroit",
    "sg:classifiers":[
        {
            "category":"Food Court",
            "type":"Food & Drink"
        },
        {
            "category":"Restaurant",
            "type":"Food & Drink"
        }
    ],
    "sg:postcode":"48209",
    "sg:province":"MI",
    "sg:tags":[
        "mexican",
        "stand"
    ],
    "wof:name":"El Paisa Taqueria Truck",
    "wof:placetype":"venue"
},
  "geometry": {"coordinates":[-83.098338,42.319265],"type":"Point"}
}