{
  "type": "Feature",
  "properties": {
    "iso:country":"US",
    "sg:address":"1592 W Cadillac Rd",
    "sg:city":"Mc Bain",
    "sg:classifiers":[
        {
            "category":"Building & Trades",
            "subcategory":"Construction",
            "type":"Services"
        }
    ],
    "sg:phone":"+1 231 826 3304",
    "sg:postcode":"49657",
    "sg:province":"MI",
    "sg:tags":[
        "house",
        "improvement",
        "home"
    ],
    "wof:name":"Randy's Repair",
    "wof:placetype":"venue"
},
  "geometry": {"coordinates":[-85.12879700000001,44.251565],"type":"Point"}
}