{
  "type": "Feature",
  "properties": {
    "iso:country":"US",
    "sg:address":"573 College Ave",
    "sg:city":"Holland",
    "sg:classifiers":[
        {
            "category":"Retail",
            "subcategory":"Animal Services",
            "type":"Services"
        }
    ],
    "sg:phone":"+1 616 395 5488",
    "sg:postcode":"49423",
    "sg:province":"MI",
    "sg:tags":[
        "pet",
        "grooming",
        "washing"
    ],
    "wof:name":"Luckydog Pet Salon",
    "wof:placetype":"venue"
},
  "geometry": {"coordinates":[-86.104147,42.775898],"type":"Point"}
}