{
  "type": "Feature",
  "properties": {
    "iso:country":"US",
    "sg:address":"701 Eastern Ave SE",
    "sg:city":"Grand Rapids",
    "sg:classifiers":[
        {
            "category":"Personal",
            "subcategory":"Beauty Salon",
            "type":"Services"
        }
    ],
    "sg:phone":"+1 616 452 0671",
    "sg:postcode":"49503",
    "sg:province":"MI",
    "sg:tags":[
        "shop"
    ],
    "wof:name":"Mika's Boutique",
    "wof:placetype":"venue"
},
  "geometry": {"coordinates":[-85.64924999999999,42.949279],"type":"Point"}
}