{
  "type": "Feature",
  "properties": {
    "iso:country":"US",
    "sg:address":"906 Winifred St",
    "sg:city":"Jackson",
    "sg:classifiers":[
        {
            "category":"Museum",
            "type":"Entertainment"
        }
    ],
    "sg:phone":"+1 517 796 8809",
    "sg:postcode":"49202",
    "sg:province":"MI",
    "sg:tags":[
        "gallery"
    ],
    "wof:name":"Time Capsule Museum Inc",
    "wof:placetype":"venue"
},
  "geometry": {"coordinates":[-84.435917,42.261899],"type":"Point"}
}