{
  "type": "Feature",
  "properties": {
    "iso:country":"US",
    "sg:address":"19215 Rutherford St",
    "sg:city":"Detroit",
    "sg:classifiers":[
        {
            "category":"Banks & Credit Unions",
            "subcategory":"Financial Services",
            "type":"Services"
        }
    ],
    "sg:phone":"+1 313 838 9096",
    "sg:postcode":"48235",
    "sg:province":"MI",
    "sg:tags":[
        "investor"
    ],
    "wof:name":"Juanabear Investments Inc",
    "wof:placetype":"venue"
},
  "geometry": {"coordinates":[-83.205365,42.431099],"type":"Point"}
}