{
  "type": "Feature",
  "properties": {
    "iso:country":"US",
    "sg:address":"452 S Getty St",
    "sg:city":"Muskegon",
    "sg:classifiers":[
        {
            "category":"Retail",
            "subcategory":"Auto Repair",
            "type":"Services"
        }
    ],
    "sg:phone":"+1 231 773 5395",
    "sg:postcode":"49442",
    "sg:province":"MI",
    "sg:tags":[
        "repairing",
        "automobile"
    ],
    "wof:name":"Jolman Fleet Svc",
    "wof:placetype":"venue"
},
  "geometry": {"coordinates":[-86.22393599999999,43.245095],"type":"Point"}
}