{
  "type": "Feature",
  "properties": {
    "iso:country":"US",
    "sg:address":"408 W Main St",
    "sg:city":"Benton Harbor",
    "sg:classifiers":[
        {
            "category":"Professional",
            "subcategory":"Testing Lab",
            "type":"Services"
        }
    ],
    "sg:phone":"+1 269 927 2434",
    "sg:postcode":"49022",
    "sg:province":"MI",
    "sg:tags":[
        "asbestos"
    ],
    "wof:name":"Villa Environmental Consultant",
    "wof:placetype":"venue"
},
  "geometry": {"coordinates":[-86.46232000000001,42.114455],"type":"Point"}
}