{
  "type": "Feature",
  "properties": {
    "iso:country":"US",
    "sg:address":"3200 River Oaks Blvd",
    "sg:city":"Rochester Hills",
    "sg:classifiers":[
        {
            "category":"Real Estate",
            "subcategory":"Real Estate Operator",
            "type":"Services"
        }
    ],
    "sg:phone":"+1 248 370 0500",
    "sg:postcode":"48309",
    "sg:province":"MI",
    "sg:tags":[
        "apartment",
        "complex"
    ],
    "wof:name":"River Oaks Apartments",
    "wof:placetype":"venue"
},
  "geometry": {"coordinates":[-83.203262,42.657655],"type":"Point"}
}