{
  "type": "Feature",
  "properties": {
    "iso:country":"US",
    "sg:address":"102 E B St",
    "sg:city":"Iron Mountain",
    "sg:classifiers":[
        {
            "category":"Bars & Pubs",
            "type":"Food & Drink"
        }
    ],
    "sg:phone":"+1 906 774 7611",
    "sg:postcode":"49801",
    "sg:province":"MI",
    "sg:tags":[
        "lounge",
        "cocktail"
    ],
    "wof:name":"Polly's Underground Pub",
    "wof:placetype":"venue"
},
  "geometry": {"coordinates":[-88.06678700000001,45.817614],"type":"Point"}
}