{
  "type": "Feature",
  "properties": {
    "iso:country":"US",
    "sg:address":"4080 US Hwy 2",
    "sg:city":"Vulcan",
    "sg:classifiers":[
        {
            "category":"Building & Trades",
            "subcategory":"Construction",
            "type":"Services"
        }
    ],
    "sg:phone":"+1 906 563 7350",
    "sg:postcode":"49892",
    "sg:province":"MI",
    "sg:tags":[
        "home",
        "builder"
    ],
    "wof:name":"Carpentry Unlimited & Dev Inc",
    "wof:placetype":"venue"
},
  "geometry": {"coordinates":[-87.82392299999999,45.777155],"type":"Point"}
}