{
  "type": "Feature",
  "properties": {
    "iso:country":"US",
    "sg:address":"37211 Harper Ave",
    "sg:city":"Clinton Twp",
    "sg:classifiers":[
        {
            "category":"Personal",
            "subcategory":"Beauty Salon",
            "type":"Services"
        }
    ],
    "sg:phone":"+1 586 463 4567",
    "sg:postcode":"48036",
    "sg:province":"MI",
    "sg:tags":[
        "shop"
    ],
    "wof:name":"Gregory's Total Hair Care",
    "wof:placetype":"venue"
},
  "geometry": {"coordinates":[-82.871652,42.571216],"type":"Point"}
}