{
  "type": "Feature",
  "properties": {
    "iso:country":"US",
    "sg:address":"7500 S Waldron Rd",
    "sg:city":"Pittsford",
    "sg:classifiers":[
        {
            "category":"Retail",
            "subcategory":"Auto Repair",
            "type":"Services"
        }
    ],
    "sg:phone":"+1 517 383 2226",
    "sg:postcode":"49271",
    "sg:province":"MI",
    "sg:tags":[
        "body",
        "automobile",
        "painting"
    ],
    "wof:name":"D & L Body Shop",
    "wof:placetype":"venue"
},
  "geometry": {"coordinates":[-84.419731,41.820082],"type":"Point"}
}