{
  "type": "Feature",
  "properties": {
    "iso:country":"US",
    "sg:address":"4070 Johnson Rd",
    "sg:city":"Frankfort",
    "sg:classifiers":[
        {
            "category":"Manufacturing",
            "subcategory":"Lumber",
            "type":"Manufacturing & Wholesale Goods"
        }
    ],
    "sg:phone":"+1 231 889 3621",
    "sg:postcode":"49635",
    "sg:province":"MI",
    "sg:tags":[
        "operation",
        "timber",
        "tract"
    ],
    "wof:name":"Advanced Tree Removal",
    "wof:placetype":"venue"
},
  "geometry": {"coordinates":[-86.17849099999999,44.57136],"type":"Point"}
}