{
  "type": "Feature",
  "properties": {
    "iso:country":"US",
    "sg:address":"2020 Ford Ave",
    "sg:city":"Wyandotte",
    "sg:classifiers":[
        {
            "category":"Retail",
            "subcategory":"Auto Repair",
            "type":"Services"
        }
    ],
    "sg:phone":"+1 734 284 2780",
    "sg:postcode":"48192",
    "sg:province":"MI",
    "sg:tags":[
        "automotive",
        "part",
        "supply"
    ],
    "wof:name":"Simmons Auto Electric",
    "wof:placetype":"venue"
},
  "geometry": {"coordinates":[-83.177058,42.213877],"type":"Point"}
}