{
  "type": "Feature",
  "properties": {
    "iso:country":"US",
    "sg:address":"3009 Corunna Rd",
    "sg:city":"Flint",
    "sg:classifiers":[
        {
            "category":"Professional",
            "subcategory":"Computer Services",
            "type":"Services"
        }
    ],
    "sg:phone":"+1 810 235 3111",
    "sg:postcode":"48503",
    "sg:province":"MI",
    "wof:name":"Discount Computers",
    "wof:placetype":"venue"
},
  "geometry": {"coordinates":[-83.72729699999999,43.002438],"type":"Point"}
}