{
  "type": "Feature",
  "properties": {
    "iso:country":"US",
    "sg:address":"105 W Fleshiem St",
    "sg:city":"Iron Mountain",
    "sg:classifiers":[
        {
            "category":"Organizations",
            "subcategory":"Non-profit Organization",
            "type":"Services"
        }
    ],
    "sg:phone":"+1 906 774 0492",
    "sg:postcode":"49801",
    "sg:province":"MI",
    "sg:tags":[
        "info",
        "addiction",
        "abuse",
        "treatment",
        "drug"
    ],
    "wof:name":"Alano Club Of Iron Mt",
    "wof:placetype":"venue"
},
  "geometry": {"coordinates":[-88.068203,45.822068],"type":"Point"}
}