{
  "type": "Feature",
  "properties": {
    "iso:country":"US",
    "sg:address":"10 N Division St",
    "sg:city":"Battle Creek",
    "sg:classifiers":[
        {
            "category":"Government",
            "subcategory":"Office",
            "type":"Public Place"
        }
    ],
    "sg:phone":"+1 269 966 3390",
    "sg:postcode":"49014",
    "sg:province":"MI",
    "sg:tags":[
        "village"
    ],
    "wof:name":"Battle Creek Purchasing",
    "wof:placetype":"venue"
},
  "geometry": {"coordinates":[-85.179799,42.316675],"type":"Point"}
}