{
  "type": "Feature",
  "properties": {
    "iso:country":"US",
    "sg:address":"1539 Chapel Rd",
    "sg:city":"Muskegon",
    "sg:classifiers":[
        {
            "category":"Shopping",
            "type":"Retail Goods"
        }
    ],
    "sg:phone":"+1 231 755 1839",
    "sg:postcode":"49441",
    "sg:province":"MI",
    "sg:tags":[
        "cosmetic",
        "perfume"
    ],
    "wof:name":"Mary Kay Cosmetics",
    "wof:placetype":"venue"
},
  "geometry": {"coordinates":[-86.279546,43.196934],"type":"Point"}
}