{
  "type": "Feature",
  "properties": {
    "iso:country":"US",
    "sg:address":"9811 Dixie Hwy",
    "sg:city":"Clarkston",
    "sg:classifiers":[
        {
            "category":"Food & Beverages",
            "subcategory":"Groceries & Convenience Stores",
            "type":"Retail Goods"
        }
    ],
    "sg:phone":"+1 248 620 4440",
    "sg:postcode":"48348",
    "sg:province":"MI",
    "wof:name":"Davisburg & Dixie Market",
    "wof:placetype":"venue"
},
  "geometry": {"coordinates":[-83.482497,42.759578],"type":"Point"}
}