{
  "type": "Feature",
  "properties": {
    "iso:country":"US",
    "sg:address":"114 N Saginaw St",
    "sg:city":"Holly",
    "sg:classifiers":[
        {
            "category":"Food & Beverages",
            "subcategory":"Groceries & Convenience Stores",
            "type":"Retail Goods"
        }
    ],
    "sg:phone":"+1 248 634 2249",
    "sg:postcode":"48442",
    "sg:province":"MI",
    "wof:name":"Holly Gas",
    "wof:placetype":"venue"
},
  "geometry": {"coordinates":[-83.627602,42.792017],"type":"Point"}
}