{
  "type": "Feature",
  "properties": {
    "iso:country":"US",
    "sg:address":"27 E Hannum Blvd",
    "sg:city":"Saginaw",
    "sg:classifiers":[
        {
            "category":"Education",
            "subcategory":"Special Training",
            "type":"Public Place"
        }
    ],
    "sg:phone":"+1 989 797 3360",
    "sg:postcode":"48602",
    "sg:province":"MI",
    "wof:name":"Medical Modeling Int",
    "wof:placetype":"venue"
},
  "geometry": {"coordinates":[-83.997415,43.413158],"type":"Point"}
}