{
  "type": "Feature",
  "properties": {
    "iso:country":"US",
    "sg:address":"30260 John R Rd",
    "sg:city":"Madison Heights",
    "sg:classifiers":[
        {
            "category":"Insurance",
            "subcategory":"Insurance Agent",
            "type":"Services"
        }
    ],
    "sg:phone":"+1 248 583 3303",
    "sg:postcode":"48071",
    "sg:province":"MI",
    "wof:name":"State Farm Insurance",
    "wof:placetype":"venue"
},
  "geometry": {"coordinates":[-83.106072,42.513719],"type":"Point"}
}