{
  "type": "Feature",
  "properties": {
    "iso:country":"US",
    "sg:address":"605 71st St",
    "sg:city":"South Haven",
    "sg:classifiers":[
        {
            "category":"Building & Trades",
            "subcategory":"Cleaning & Sanitation",
            "type":"Services"
        }
    ],
    "sg:phone":"+1 269 637 2520",
    "sg:postcode":"49090",
    "sg:province":"MI",
    "sg:tags":[
        "maintenance"
    ],
    "wof:name":"Ceil Bright",
    "wof:placetype":"venue"
},
  "geometry": {"coordinates":[-86.236362,42.464425],"type":"Point"}
}