{
  "type": "Feature",
  "properties": {
    "iso:country":"US",
    "sg:address":"8395 Sparling Rd",
    "sg:city":"Goodells",
    "sg:classifiers":[
        {
            "category":"Building & Trades",
            "subcategory":"Construction",
            "type":"Services"
        }
    ],
    "sg:phone":"+1 810 325 1487",
    "sg:postcode":"48027",
    "sg:province":"MI",
    "sg:tags":[
        "house"
    ],
    "wof:name":"Michael Duncan Builders",
    "wof:placetype":"venue"
},
  "geometry": {"coordinates":[-82.657782,42.967799],"type":"Point"}
}