{
  "type": "Feature",
  "properties": {
    "iso:country":"US",
    "sg:address":"15940 US Hwy 41",
    "sg:city":"Powers",
    "sg:classifiers":[
        {
            "category":"Personal",
            "subcategory":"Beauty Salon",
            "type":"Services"
        }
    ],
    "sg:phone":"+1 906 497 5569",
    "sg:postcode":"49874",
    "sg:province":"MI",
    "wof:name":"Judy's Mirror Image",
    "wof:placetype":"venue"
},
  "geometry": {"coordinates":[-87.52617499999999,45.687332],"type":"Point"}
}