{
  "type": "Feature",
  "properties": {
    "iso:country":"US",
    "sg:address":"14900 E Old US Hwy 12",
    "sg:city":"Chelsea",
    "sg:classifiers":[
        {
            "category":"Organizations",
            "subcategory":"Religious Organization",
            "type":"Services"
        }
    ],
    "sg:phone":"+1 734 475 2615",
    "sg:postcode":"48118",
    "sg:province":"MI",
    "sg:tags":[
        "church"
    ],
    "wof:name":"First Assembly Of God",
    "wof:placetype":"venue"
},
  "geometry": {"coordinates":[-84.013802,42.305039],"type":"Point"}
}