{
  "type": "Feature",
  "properties": {
    "iso:country":"US",
    "sg:address":"1275 S Huron St",
    "sg:city":"Ypsilanti",
    "sg:classifiers":[
        {
            "category":"Travel",
            "subcategory":"Hotels & Motels",
            "type":"Entertainment"
        }
    ],
    "sg:phone":"+1 734 487 2000",
    "sg:postcode":"48197",
    "sg:province":"MI",
    "sg:website":"http://www.marriott.com",
    "wof:name":"Marriott Hotel Ann Arbor Ypsilanti at Eagle Crest",
    "wof:placetype":"venue"
},
  "geometry": {"coordinates":[-83.617851,42.22411],"type":"Point"}
}