{
  "type": "Feature",
  "properties": {
    "iso:country":"US",
    "sg:address":"35121 Warren Rd",
    "sg:city":"Westland",
    "sg:classifiers":[
        {
            "category":"Shopping",
            "subcategory":"Bicycles & Sporting Goods",
            "type":"Retail Goods"
        }
    ],
    "sg:phone":"+1 734 326 3930",
    "sg:postcode":"48185",
    "sg:province":"MI",
    "wof:name":"Play Ball",
    "wof:placetype":"venue"
},
  "geometry": {"coordinates":[-83.38510100000001,42.338799],"type":"Point"}
}