{
  "type": "Feature",
  "properties": {
    "iso:country":"US",
    "sg:address":"29 S Greenville Rd",
    "sg:city":"Greenville",
    "sg:classifiers":[
        {
            "category":"Retail",
            "subcategory":"Repair Shop",
            "type":"Services"
        }
    ],
    "sg:phone":"+1 616 754 6826",
    "sg:postcode":"48838",
    "sg:province":"MI",
    "sg:tags":[
        "equipment",
        "hydraulic"
    ],
    "wof:name":"North Kent Hydraulics",
    "wof:placetype":"venue"
},
  "geometry": {"coordinates":[-85.25216,43.293178],"type":"Point"}
}