{
  "type": "Feature",
  "properties": {
    "iso:country":"US",
    "sg:address":"325 S Michigan Ave",
    "sg:city":"Howell",
    "sg:classifiers":[
        {
            "category":"Government",
            "subcategory":"Post Office",
            "type":"Public Place"
        }
    ],
    "sg:phone":"+1 517 546 2560",
    "sg:postcode":"48843",
    "sg:province":"MI",
    "wof:name":"US Post Office",
    "wof:placetype":"venue"
},
  "geometry": {"coordinates":[-83.93073,42.605248],"type":"Point"}
}