{
  "type": "Feature",
  "properties": {
    "iso:country":"US",
    "sg:address":"11051 Hall Rd",
    "sg:city":"Utica",
    "sg:classifiers":[
        {
            "category":"Health Services",
            "subcategory":"Doctor",
            "type":"Services"
        }
    ],
    "sg:phone":"+1 586 991 0700",
    "sg:postcode":"48317",
    "sg:province":"MI",
    "sg:tags":[
        "physician",
        "surgeon"
    ],
    "wof:name":"Great Lakes Cancer Mgmt Spec",
    "wof:placetype":"venue"
},
  "geometry": {"coordinates":[-83.010513,42.626408],"type":"Point"}
}