{
  "type": "Feature",
  "properties": {
    "iso:country":"US",
    "sg:address":"1410 S Washington Ave",
    "sg:city":"Lansing",
    "sg:classifiers":[
        {
            "category":"Food & Beverages",
            "subcategory":"Groceries & Convenience Stores",
            "type":"Retail Goods"
        }
    ],
    "sg:phone":"+1 517 319 4185",
    "sg:postcode":"48910",
    "sg:province":"MI",
    "sg:tags":[
        "grocer"
    ],
    "sg:website":"www.qualitydairy.com",
    "wof:name":"Quality Dairy Co",
    "wof:placetype":"venue"
},
  "geometry": {"coordinates":[-84.552432,42.717029],"type":"Point"}
}