{
  "type": "Feature",
  "properties": {
    "iso:country":"US",
    "sg:address":"3401 S Burdick St",
    "sg:city":"Kalamazoo",
    "sg:classifiers":[
        {
            "category":"Retail",
            "subcategory":"Repair Shop",
            "type":"Services"
        },
        {
            "category":"Restaurant",
            "type":"Food & Drink"
        },
        {
            "category":"Wholesale",
            "subcategory":"Machinery & Supplies",
            "type":"Manufacturing & Wholesale Goods"
        },
        {
            "category":"Building & Trades",
            "subcategory":"Construction",
            "type":"Services"
        },
        {
            "category":"Home & Garden",
            "subcategory":"Kitchen Supply",
            "type":"Retail Goods"
        }
    ],
    "sg:phone":"+1 269 343 1240",
    "sg:postcode":"49001",
    "sg:province":"MI",
    "sg:tags":[
        "equipment-commercial",
        "specialty",
        "equipment",
        "heating",
        "system",
        "supplies-refrigeration",
        "industrial",
        "refrigeration",
        "air conditioning",
        "contractor",
        "freezers-repair",
        "refrigerator"
    ],
    "sg:website":"http://www.staffordsmith.com",
    "wof:name":"Stafford-Smith Inc",
    "wof:placetype":"venue"
},
  "geometry": {"coordinates":[-85.57985600000001,42.257095],"type":"Point"}
}