{
  "type": "Feature",
  "properties": {
    "iso:country":"US",
    "sg:address":"674 Baldwin St",
    "sg:city":"Jenison",
    "sg:classifiers":[
        {
            "category":"Restaurant",
            "type":"Food & Drink"
        }
    ],
    "sg:phone":"+1 616 667 8901",
    "sg:postcode":"49428",
    "sg:province":"MI",
    "wof:name":"Bangkok Taste",
    "wof:placetype":"venue"
},
  "geometry": {"coordinates":[-85.797932,42.907111],"type":"Point"}
}