{
  "type": "Feature",
  "properties": {
    "iso:country":"US",
    "sg:address":"9875 Arthur Rd",
    "sg:city":"Rodney",
    "sg:classifiers":[
        {
            "category":"Retail",
            "subcategory":"Repair Shop",
            "type":"Services"
        }
    ],
    "sg:phone":"+1 231 972 7746",
    "sg:postcode":"49342",
    "sg:province":"MI",
    "wof:name":"Canopener",
    "wof:placetype":"venue"
},
  "geometry": {"coordinates":[-85.28367,43.662419],"type":"Point"}
}