{
  "type": "Feature",
  "properties": {
    "iso:country":"US",
    "sg:address":"7201 Golf Club Rd",
    "sg:city":"Howell",
    "sg:classifiers":[
        {
            "category":"Home & Garden",
            "subcategory":"Garden Supply",
            "type":"Retail Goods"
        },
        {
            "category":"Building & Trades",
            "subcategory":"Landscaping Services",
            "type":"Services"
        }
    ],
    "sg:phone":"+1 517 546 9990",
    "sg:postcode":"48843",
    "sg:province":"MI",
    "sg:tags":[
        "sprinkler"
    ],
    "wof:name":"Alyn's Services",
    "wof:placetype":"venue"
},
  "geometry": {"coordinates":[-83.807458,42.601888],"type":"Point"}
}