{
  "type": "Feature",
  "properties": {
    "iso:country":"US",
    "sg:address":"116 Antrim St",
    "sg:city":"Charlevoix",
    "sg:classifiers":[
        {
            "category":"Shopping",
            "subcategory":"Florist",
            "type":"Retail Goods"
        }
    ],
    "sg:phone":"+1 231 547 2056",
    "sg:postcode":"49720",
    "sg:province":"MI",
    "wof:name":"Charlevoix Floral",
    "wof:placetype":"venue"
},
  "geometry": {"coordinates":[-85.258897,45.315153],"type":"Point"}
}