{
  "type": "Feature",
  "properties": {
    "iso:country":"US",
    "sg:address":"541 Industrial Pkwy",
    "sg:city":"Jonesville",
    "sg:classifiers":[
        {
            "category":"Manufacturing",
            "subcategory":"Tools & Machinery",
            "type":"Manufacturing & Wholesale Goods"
        }
    ],
    "sg:phone":"+1 517 849 9750",
    "sg:postcode":"49250",
    "sg:province":"MI",
    "sg:tags":[
        "machine",
        "shop"
    ],
    "wof:name":"American Machine & Assembly",
    "wof:placetype":"venue"
},
  "geometry": {"coordinates":[-84.675568,41.968532],"type":"Point"}
}