{
  "type": "Feature",
  "properties": {
    "iso:country":"US",
    "sg:address":"5085 Eugene St",
    "sg:city":"Dearborn",
    "sg:classifiers":[
        {
            "category":"Autos & Motor Vehicles",
            "subcategory":"Fuel & Gas Station",
            "type":"Retail Goods"
        }
    ],
    "sg:phone":"+1 313 846 2136",
    "sg:postcode":"48126",
    "sg:province":"MI",
    "sg:tags":[
        "station",
        "gasoline"
    ],
    "wof:name":"Haj Investment Inc",
    "wof:placetype":"venue"
},
  "geometry": {"coordinates":[-83.157668,42.326231],"type":"Point"}
}