{
  "type": "Feature",
  "properties": {
    "iso:country":"US",
    "sg:address":"39201 Schoolcraft Rd",
    "sg:city":"Livonia",
    "sg:classifiers":[
        {
            "category":"Communications",
            "subcategory":"Film & Video Production",
            "type":"Services"
        }
    ],
    "sg:phone":"+1 734 542 7000",
    "sg:postcode":"48150",
    "sg:province":"MI",
    "wof:name":"Blue Sky Productions Inc",
    "wof:placetype":"venue"
},
  "geometry": {"coordinates":[-83.42994299999999,42.381438],"type":"Point"}
}