{
  "type": "Feature",
  "properties": {
    "iso:country":"US",
    "sg:address":"213 E 5th St",
    "sg:city":"Clare",
    "sg:classifiers":[
        {
            "category":"Retail",
            "subcategory":"Auto Repair",
            "type":"Services"
        }
    ],
    "sg:phone":"+1 989 386 1100",
    "sg:postcode":"48617",
    "sg:province":"MI",
    "sg:tags":[
        "repairing",
        "automobile",
        "general"
    ],
    "wof:name":"Fifth Street Auto Service",
    "wof:placetype":"venue"
},
  "geometry": {"coordinates":[-84.76606200000001,43.819762],"type":"Point"}
}