{
  "type": "Feature",
  "properties": {
    "iso:country":"US",
    "sg:address":"8481 Keller Rd",
    "sg:city":"Delton",
    "sg:classifiers":[
        {
            "category":"Building & Trades",
            "subcategory":"Plumbing",
            "type":"Services"
        }
    ],
    "sg:phone":"+1 269 623 3171",
    "sg:postcode":"49046",
    "sg:province":"MI",
    "sg:tags":[
        "plumbing",
        "contractor"
    ],
    "wof:name":"Patriot Plumbing Svc",
    "wof:placetype":"venue"
},
  "geometry": {"coordinates":[-85.455296,42.559259],"type":"Point"}
}