{
  "type": "Feature",
  "properties": {
    "iso:country":"US",
    "sg:address":"1312 S Waverly Rd",
    "sg:city":"Lansing",
    "sg:classifiers":[
        {
            "category":"Manufacturing",
            "subcategory":"Metals",
            "type":"Manufacturing & Wholesale Goods"
        }
    ],
    "sg:phone":"+1 517 322 2050",
    "sg:postcode":"48917",
    "sg:province":"MI",
    "sg:tags":[
        "steel"
    ],
    "sg:website":"www.douglassteel.com",
    "wof:name":"Douglas Steel Fabricating Corp",
    "wof:placetype":"venue"
},
  "geometry": {"coordinates":[-84.602934,42.71795],"type":"Point"}
}