{
  "type": "Feature",
  "properties": {
    "iso:country":"US",
    "sg:address":"24631 Pineview St",
    "sg:city":"Oak Park",
    "sg:classifiers":[
        {
            "category":"Banks & Credit Unions",
            "subcategory":"Financial Services",
            "type":"Services"
        }
    ],
    "sg:phone":"+1 248 541 8825",
    "sg:postcode":"48237",
    "sg:province":"MI",
    "sg:tags":[
        "investment",
        "closed"
    ],
    "wof:name":"Annie Bee Smart Investments",
    "wof:placetype":"venue"
},
  "geometry": {"coordinates":[-83.166281,42.473106],"type":"Point"}
}