{
  "type": "Feature",
  "properties": {
    "iso:country":"US",
    "sg:address":"14943 Melrose St",
    "sg:city":"Livonia",
    "sg:classifiers":[
        {
            "category":"Professional",
            "type":"Services"
        }
    ],
    "sg:phone":"+1 734 525 2904",
    "sg:postcode":"48154",
    "sg:province":"MI",
    "wof:name":"Wendy Piasentin",
    "wof:placetype":"venue"
},
  "geometry": {"coordinates":[-83.356476,42.395409],"type":"Point"}
}