{
  "type": "Feature",
  "properties": {
    "iso:country":"US",
    "sg:address":"769 E Mount Morris Rd",
    "sg:city":"Mt Morris",
    "sg:classifiers":[
        {
            "category":"Building & Trades",
            "subcategory":"Construction",
            "type":"Services"
        }
    ],
    "sg:phone":"+1 810 687 0910",
    "sg:postcode":"48458",
    "sg:province":"MI",
    "sg:tags":[
        "waterproofing",
        "contractor"
    ],
    "wof:name":"Refined Concrete Waterproofing",
    "wof:placetype":"venue"
},
  "geometry": {"coordinates":[-83.69271000000001,43.119405],"type":"Point"}
}