{
  "type": "Feature",
  "properties": {
    "iso:country":"US",
    "sg:address":"47410 Pontiac Trl",
    "sg:city":"Wixom",
    "sg:classifiers":[
        {
            "category":"Cinema",
            "subcategory":"Movie Rental",
            "type":"Entertainment"
        }
    ],
    "sg:phone":"+1 248 669 3200",
    "sg:postcode":"48393",
    "sg:province":"MI",
    "sg:tags":[
        "video",
        "tape"
    ],
    "wof:name":"Blockbuster",
    "wof:placetype":"venue"
},
  "geometry": {"coordinates":[-83.51630900000001,42.524983],"type":"Point"}
}