{
  "type": "Feature",
  "properties": {
    "iso:country":"US",
    "sg:address":"414 E Main St",
    "sg:city":"Edmore",
    "sg:classifiers":[
        {
            "category":"Professional",
            "subcategory":"Lawyer & Legal Services",
            "type":"Services"
        }
    ],
    "sg:phone":"+1 989 427 3048",
    "sg:postcode":"48829",
    "sg:province":"MI",
    "sg:tags":[
        "attorney"
    ],
    "wof:name":"Dennis L Moore",
    "wof:placetype":"venue"
},
  "geometry": {"coordinates":[-85.040333,43.407986],"type":"Point"}
}