{
  "type": "Feature",
  "properties": {
    "iso:country":"US",
    "sg:address":"3700 Rivertown Pkwy",
    "sg:city":"Grandville",
    "sg:classifiers":[
        {
            "category":"Shopping",
            "subcategory":"Department Store",
            "type":"Retail Goods"
        }
    ],
    "sg:phone":"+1 616 532 7650",
    "sg:postcode":"49418",
    "sg:province":"MI",
    "sg:website":"www.rue21.com",
    "wof:name":"Rue 21",
    "wof:placetype":"venue"
},
  "geometry": {"coordinates":[-85.757884,42.882193],"type":"Point"}
}