{
  "type": "Feature",
  "properties": {
    "iso:country":"US",
    "sg:address":"10118 California Rd",
    "sg:city":"Bridgman",
    "sg:classifiers":[
        {
            "category":"Retail",
            "subcategory":"Repair Shop",
            "type":"Services"
        }
    ],
    "sg:phone":"+1 269 465 6914",
    "sg:postcode":"49106",
    "sg:province":"MI",
    "sg:tags":[
        "sharpening"
    ],
    "wof:name":"Tjader Sharpening Svc",
    "wof:placetype":"venue"
},
  "geometry": {"coordinates":[-86.552757,41.933511],"type":"Point"}
}