{
  "type": "Feature",
  "properties": {
    "iso:country":"US",
    "sg:address":"380 Oaks Xing",
    "sg:city":"Plainwell",
    "sg:classifiers":[
        {
            "category":"Personal",
            "type":"Services"
        },
        {
            "category":"Professional",
            "subcategory":"Management & Consulting",
            "type":"Services"
        }
    ],
    "sg:phone":"+1 269 685 9739",
    "sg:postcode":"49080",
    "sg:province":"MI",
    "sg:tags":[
        "counseling",
        "debt",
        "credit"
    ],
    "wof:name":"Debt Relief of Michigan",
    "wof:placetype":"venue"
},
  "geometry": {"coordinates":[-85.66724499999999,42.44897],"type":"Point"}
}