{
  "type": "Feature",
  "properties": {
    "iso:country":"US",
    "sg:address":"76842 Territorial Rd",
    "sg:city":"Decatur",
    "sg:classifiers":[
        {
            "category":"Autos & Motor Vehicles",
            "subcategory":"Fuel & Gas Station",
            "type":"Retail Goods"
        }
    ],
    "sg:phone":"+1 269 423 9883",
    "sg:postcode":"49045",
    "sg:province":"MI",
    "sg:tags":[
        "station",
        "gasoline"
    ],
    "wof:name":"Monitors Service Centers",
    "wof:placetype":"venue"
},
  "geometry": {"coordinates":[-86.029325,42.140146],"type":"Point"}
}