{
  "type": "Feature",
  "properties": {
    "iso:country":"US",
    "sg:address":"1780 S Ortonville Rd",
    "sg:city":"Ortonville",
    "sg:classifiers":[
        {
            "category":"Shopping",
            "type":"Retail Goods"
        }
    ],
    "sg:phone":"+1 248 627 9400",
    "sg:postcode":"48462",
    "sg:province":"MI",
    "sg:tags":[
        "picture",
        "frame"
    ],
    "wof:name":"Plumtree Art & Framing",
    "wof:placetype":"venue"
},
  "geometry": {"coordinates":[-83.44420599999999,42.827935],"type":"Point"}
}