{
  "type": "Feature",
  "properties": {
    "iso:country":"US",
    "sg:address":"8812 Schock Rd",
    "sg:city":"Minden City",
    "sg:classifiers":[
        {
            "category":"Farming",
            "subcategory":"Farm",
            "type":"Manufacturing & Wholesale Goods"
        }
    ],
    "sg:phone":"+1 989 864 5447",
    "sg:postcode":"48456",
    "sg:province":"MI",
    "sg:tags":[
        "crop",
        "general"
    ],
    "wof:name":"R Weber",
    "wof:placetype":"venue"
},
  "geometry": {"coordinates":[-82.65964,43.686317],"type":"Point"}
}