{
  "type": "Feature",
  "properties": {
    "iso:country":"US",
    "sg:address":"6765 E Sanilac Rd",
    "sg:city":"Port Sanilac",
    "sg:classifiers":[
        {
            "category":"Retail",
            "subcategory":"Repair Shop",
            "type":"Services"
        }
    ],
    "sg:phone":"+1 810 622 9450",
    "sg:postcode":"48469",
    "sg:province":"MI",
    "sg:tags":[
        "marine"
    ],
    "wof:name":"Lakeview Marine Service",
    "wof:placetype":"venue"
},
  "geometry": {"coordinates":[-82.554135,43.430675],"type":"Point"}
}