{
  "type": "Feature",
  "properties": {
    "iso:country":"US",
    "sg:address":"1125 N Sherman Dr",
    "sg:city":"Royal Oak",
    "sg:classifiers":[
        {
            "category":"Real Estate",
            "subcategory":"Real Estate Agent",
            "type":"Services"
        }
    ],
    "sg:phone":"+1 248 548 9242",
    "sg:postcode":"48067",
    "sg:province":"MI",
    "sg:tags":[
        "management"
    ],
    "wof:name":"B & B Property Management",
    "wof:placetype":"venue"
},
  "geometry": {"coordinates":[-83.154884,42.491679],"type":"Point"}
}