{
  "type": "Feature",
  "properties": {
    "iso:country":"US",
    "sg:address":"24246 Roxana Ave",
    "sg:city":"Eastpointe",
    "sg:classifiers":[
        {
            "category":"Building & Trades",
            "subcategory":"Construction",
            "type":"Services"
        }
    ],
    "sg:phone":"+1 586 530 5099",
    "sg:postcode":"48021",
    "sg:province":"MI",
    "sg:tags":[
        "floor",
        "laying",
        "contractor"
    ],
    "wof:name":"OBrien Floor Service",
    "wof:placetype":"venue"
},
  "geometry": {"coordinates":[-82.930286,42.473969],"type":"Point"}
}