{
  "type": "Feature",
  "properties": {
    "iso:country":"US",
    "sg:address":"4336 Coolidge Hwy",
    "sg:city":"Royal Oak",
    "sg:classifiers":[
        {
            "category":"Manufacturing",
            "subcategory":"Metals",
            "type":"Manufacturing & Wholesale Goods"
        }
    ],
    "sg:phone":"+1 248 549 3801",
    "sg:postcode":"48073",
    "sg:province":"MI",
    "sg:tags":[
        "stamping"
    ],
    "wof:name":"Hawthorne Metal Products Co",
    "wof:placetype":"venue"
},
  "geometry": {"coordinates":[-83.184062,42.525525],"type":"Point"}
}