{
  "type": "Feature",
  "properties": {
    "iso:country":"US",
    "sg:address":"1646 Andrew St SE",
    "sg:city":"Grand Rapids",
    "sg:classifiers":[
        {
            "category":"Professional",
            "subcategory":"Engineering",
            "type":"Services"
        }
    ],
    "sg:phone":"+1 616 862 4239",
    "sg:postcode":"49508",
    "sg:province":"MI",
    "sg:tags":[
        "building",
        "construction"
    ],
    "wof:name":"Solid Rock Construction Co",
    "wof:placetype":"venue"
},
  "geometry": {"coordinates":[-85.619597,42.874066],"type":"Point"}
}