{
  "type": "Feature",
  "properties": {
    "iso:country":"US",
    "sg:address":"206 S 5th Ave",
    "sg:city":"Ann Arbor",
    "sg:classifiers":[
        {
            "category":"Health Services",
            "subcategory":"Health Practitioner",
            "type":"Services"
        }
    ],
    "sg:phone":"+1 734 663 1272",
    "sg:postcode":"48104",
    "sg:province":"MI",
    "wof:name":"Ann Arbor Psychological Svc",
    "wof:placetype":"venue"
},
  "geometry": {"coordinates":[-83.746172,42.27957],"type":"Point"}
}