{
  "type": "Feature",
  "properties": {
    "iso:country":"US",
    "sg:address":"6033 Middlebelt Rd",
    "sg:city":"Garden City",
    "sg:classifiers":[
        {
            "category":"Health Services",
            "subcategory":"Medical Lab",
            "type":"Services"
        }
    ],
    "sg:phone":"+1 734 522 1588",
    "sg:postcode":"48135",
    "sg:province":"MI",
    "sg:tags":[
        "laboratory"
    ],
    "wof:name":"Quest Diagnostics",
    "wof:placetype":"venue"
},
  "geometry": {"coordinates":[-83.331188,42.329699],"type":"Point"}
}