{
  "type": "Feature",
  "properties": {
    "iso:country":"US",
    "sg:address":"3959 Barrington Dr",
    "sg:city":"Saginaw",
    "sg:classifiers":[
        {
            "category":"Building & Trades",
            "subcategory":"Construction",
            "type":"Services"
        }
    ],
    "sg:phone":"+1 989 249 8565",
    "sg:postcode":"48603",
    "sg:province":"MI",
    "sg:tags":[
        "house"
    ],
    "wof:name":"Tribble Builders LLC",
    "wof:placetype":"venue"
},
  "geometry": {"coordinates":[-83.993927,43.455373],"type":"Point"}
}