{
  "type": "Feature",
  "properties": {
    "iso:country":"US",
    "sg:address":"9711 Monroe Blvd",
    "sg:city":"Taylor",
    "sg:classifiers":[
        {
            "category":"Professional",
            "subcategory":"Business Services",
            "type":"Services"
        }
    ],
    "sg:phone":"+1 313 292 1422",
    "sg:postcode":"48180",
    "sg:province":"MI",
    "wof:name":"Ramik Enterprises",
    "wof:placetype":"venue"
},
  "geometry": {"coordinates":[-83.249396,42.234366],"type":"Point"}
}