{
  "type": "Feature",
  "properties": {
    "iso:country":"US",
    "sg:address":"1201 Creekview Ct",
    "sg:city":"Rochester",
    "sg:classifiers":[
        {
            "category":"Banks & Credit Unions",
            "subcategory":"Financial Services",
            "type":"Services"
        }
    ],
    "sg:phone":"+1 248 652 2646",
    "sg:postcode":"48306",
    "sg:province":"MI",
    "sg:tags":[
        "investor"
    ],
    "wof:name":"Oakland Investments Partnr",
    "wof:placetype":"venue"
},
  "geometry": {"coordinates":[-83.114013,42.742045],"type":"Point"}
}