{
  "type": "Feature",
  "properties": {
    "iso:country":"US",
    "sg:address":"801 Mann Ave",
    "sg:city":"Flint",
    "sg:classifiers":[
        {
            "category":"Professional",
            "subcategory":"Computer Services",
            "type":"Services"
        }
    ],
    "sg:phone":"+1 810 239 8781",
    "sg:postcode":"48503",
    "sg:province":"MI",
    "wof:name":"Full Conexion",
    "wof:placetype":"venue"
},
  "geometry": {"coordinates":[-83.73033700000001,43.00757],"type":"Point"}
}