{
  "type": "Feature",
  "properties": {
    "iso:country":"US",
    "sg:address":"28860 Kirkside Ln",
    "sg:city":"Farmington",
    "sg:classifiers":[
        {
            "category":"Insurance",
            "subcategory":"Insurance Agent",
            "type":"Services"
        }
    ],
    "sg:phone":"+1 248 553 3866",
    "sg:postcode":"48334",
    "sg:province":"MI",
    "wof:name":"Edward Azar",
    "wof:placetype":"venue"
},
  "geometry": {"coordinates":[-83.37564399999999,42.509038],"type":"Point"}
}