{
  "type": "Feature",
  "properties": {
    "iso:country":"US",
    "sg:address":"58751 Romeo Plank Rd",
    "sg:city":"Ray",
    "sg:classifiers":[
        {
            "category":"Professional",
            "subcategory":"Accounting & Tax Preparation",
            "type":"Services"
        }
    ],
    "sg:phone":"+1 586 781 9815",
    "sg:postcode":"48096",
    "sg:province":"MI",
    "wof:name":"Jarvis Accounting & Tax Svc",
    "wof:placetype":"venue"
},
  "geometry": {"coordinates":[-82.960069,42.729219],"type":"Point"}
}