{
  "type": "Feature",
  "properties": {
    "iso:country":"US",
    "sg:address":"1985 W Big Beaver Rd",
    "sg:city":"Troy",
    "sg:classifiers":[
        {
            "category":"Professional",
            "subcategory":"Computer Services",
            "type":"Services"
        }
    ],
    "sg:phone":"+1 248 822 3122",
    "sg:postcode":"48084",
    "sg:province":"MI",
    "wof:name":"Integrity Networks",
    "wof:placetype":"venue"
},
  "geometry": {"coordinates":[-83.17369100000001,42.561555],"type":"Point"}
}