{
  "type": "Feature",
  "properties": {
    "iso:country":"US",
    "sg:address":"1235 W 14 Mile Rd",
    "sg:city":"Madison Heights",
    "sg:classifiers":[
        {
            "category":"Restaurant",
            "type":"Food & Drink"
        }
    ],
    "sg:menulink":"http://www.allmenus.com/mi/madison-heights/48229-new-york-red-hots-coney-island/menu/",
    "sg:phone":"+1 248 589 1470",
    "sg:postcode":"48071",
    "sg:province":"MI",
    "sg:tags":[
        "american",
        "hot",
        "dog"
    ],
    "wof:name":"New York Red Hots Coney Island",
    "wof:placetype":"venue"
},
  "geometry": {"coordinates":[-83.12138299999999,42.53356],"type":"Point"}
}