{
  "type": "Feature",
  "properties": {
    "iso:country":"US",
    "sg:address":"1376 N Lapeer Rd",
    "sg:city":"Oxford",
    "sg:classifiers":[
        {
            "category":"Personal",
            "subcategory":"Beauty Salon",
            "type":"Services"
        }
    ],
    "sg:phone":"+1 248 969 1329",
    "sg:postcode":"48371",
    "sg:province":"MI",
    "sg:tags":[
        "shop"
    ],
    "wof:name":"Modern Nails",
    "wof:placetype":"venue"
},
  "geometry": {"coordinates":[-83.270872,42.83396],"type":"Point"}
}