{
  "type": "Feature",
  "properties": {
    "iso:country":"US",
    "sg:address":"401 S Haven St",
    "sg:city":"South Haven",
    "sg:classifiers":[
        {
            "category":"Travel",
            "subcategory":"Hotels & Motels",
            "type":"Entertainment"
        }
    ],
    "sg:phone":"+1 269 637 2727",
    "sg:postcode":"49090",
    "sg:province":"MI",
    "sg:tags":[
        "cottage",
        "cabin"
    ],
    "wof:name":"Sunset Cottages",
    "wof:placetype":"venue"
},
  "geometry": {"coordinates":[-86.275774,42.396442],"type":"Point"}
}