{
  "type": "Feature",
  "properties": {
    "iso:country":"US",
    "sg:address":"7128 S Brucker Ave",
    "sg:city":"Fremont",
    "sg:classifiers":[
        {
            "category":"Building & Trades",
            "subcategory":"Construction",
            "type":"Services"
        }
    ],
    "sg:phone":"+1 231 924 9884",
    "sg:postcode":"49412",
    "sg:province":"MI",
    "sg:tags":[
        "dry wall",
        "contractor"
    ],
    "wof:name":"Gibson Drywall Co",
    "wof:placetype":"venue"
},
  "geometry": {"coordinates":[-85.989243,43.425118],"type":"Point"}
}