{
  "type": "Feature",
  "properties": {
    "iso:country":"US",
    "sg:address":"2936 Niles Ave",
    "sg:city":"St Joseph",
    "sg:classifiers":[
        {
            "category":"Restaurant",
            "type":"Food & Drink"
        }
    ],
    "sg:phone":"+1 269 983 3818",
    "sg:postcode":"49085",
    "sg:province":"MI",
    "wof:name":"Hong Kong House",
    "wof:placetype":"venue"
},
  "geometry": {"coordinates":[-86.48553200000001,42.082228],"type":"Point"}
}