{
  "type": "Feature",
  "properties": {
    "iso:country":"US",
    "sg:address":"436 Liberty St",
    "sg:city":"Sturgis",
    "sg:classifiers":[
        {
            "category":"Professional",
            "subcategory":"Business Services",
            "type":"Services"
        }
    ],
    "sg:phone":"+1 269 651 8987",
    "sg:postcode":"49091",
    "sg:province":"MI",
    "wof:name":"Tracy Stone Acctg Service",
    "wof:placetype":"venue"
},
  "geometry": {"coordinates":[-85.41095799999999,41.787709],"type":"Point"}
}