{
  "type": "Feature",
  "properties": {
    "iso:country":"US",
    "sg:address":"9094 N Genesee Rd",
    "sg:city":"Mount Morris",
    "sg:classifiers":[
        {
            "category":"Retail",
            "subcategory":"Auto Repair",
            "type":"Services"
        }
    ],
    "sg:phone":"+1 810 686 8419",
    "sg:postcode":"48458",
    "sg:province":"MI",
    "sg:tags":[
        "automotive"
    ],
    "wof:name":"Gregs Hook 24 Hour Towing",
    "wof:placetype":"venue"
},
  "geometry": {"coordinates":[-83.618533,43.138125],"type":"Point"}
}