{
  "type": "Feature",
  "properties": {
    "iso:country":"US",
    "sg:address":"4675 Munson Hwy",
    "sg:city":"Hudson",
    "sg:classifiers":[
        {
            "category":"Retail",
            "subcategory":"Repair Shop",
            "type":"Services"
        }
    ],
    "sg:phone":"+1 517 448 8396",
    "sg:postcode":"49247",
    "sg:province":"MI",
    "sg:tags":[
        "antique",
        "restoring"
    ],
    "wof:name":"Wood 'n Art",
    "wof:placetype":"venue"
},
  "geometry": {"coordinates":[-84.33314300000001,41.841656],"type":"Point"}
}