{
  "type": "Feature",
  "properties": {
    "iso:country":"US",
    "sg:address":"5258 Plainfield Ave NE",
    "sg:city":"Grand Rapids",
    "sg:classifiers":[
        {
            "category":"Social Services",
            "type":"Services"
        }
    ],
    "sg:phone":"+1 616 365 0015",
    "sg:postcode":"49525",
    "sg:province":"MI",
    "sg:tags":[
        "development",
        "education",
        "child"
    ],
    "wof:name":"Gymboree Play & Music Ctr",
    "wof:placetype":"venue"
},
  "geometry": {"coordinates":[-85.585842,43.055309],"type":"Point"}
}