{
  "type": "Feature",
  "properties": {
    "iso:country":"US",
    "sg:address":"8818 Portage Rd",
    "sg:city":"Portage",
    "sg:classifiers":[
        {
            "category":"Cinema",
            "subcategory":"Movie Rental",
            "type":"Entertainment"
        }
    ],
    "sg:phone":"+1 269 329 0300",
    "sg:postcode":"49002",
    "sg:province":"MI",
    "sg:tags":[
        "leasing",
        "video",
        "disc",
        "tape"
    ],
    "wof:name":"Movie Stars Inc",
    "wof:placetype":"venue"
},
  "geometry": {"coordinates":[-85.56254800000001,42.188479],"type":"Point"}
}