{
  "type": "Feature",
  "properties": {
    "iso:country":"US",
    "sg:address":"3715 Stadium Dr",
    "sg:city":"Kalamazoo",
    "sg:classifiers":[
        {
            "category":"Retail",
            "subcategory":"Auto Repair",
            "type":"Services"
        }
    ],
    "sg:phone":"+1 269 372 3281",
    "sg:postcode":"49008",
    "sg:province":"MI",
    "sg:tags":[
        "automotive"
    ],
    "wof:name":"Uncle Eds Oil Shoppe 1103",
    "wof:placetype":"venue"
},
  "geometry": {"coordinates":[-85.642765,42.270468],"type":"Point"}
}