{
  "type": "Feature",
  "properties": {
    "iso:country":"US",
    "sg:address":"41350 Garfield Rd",
    "sg:city":"Clinton Twp",
    "sg:classifiers":[
        {
            "category":"Retail",
            "subcategory":"Auto Repair",
            "type":"Services"
        }
    ],
    "sg:phone":"+1 586 263 7851",
    "sg:postcode":"48038",
    "sg:province":"MI",
    "sg:tags":[
        "automobile",
        "lubrication",
        "automotive"
    ],
    "wof:name":"Snappy Oil & Lube Inc",
    "wof:placetype":"venue"
},
  "geometry": {"coordinates":[-82.952561,42.604456],"type":"Point"}
}