{
  "type": "Feature",
  "properties": {
    "iso:country":"US",
    "sg:address":"30250 Mound Rd",
    "sg:city":"Warren",
    "sg:classifiers":[
        {
            "category":"Restaurant",
            "type":"Food & Drink"
        }
    ],
    "sg:menulink":"http://www.allmenus.com/mi/warren/122077-quiznos-sub/menu/",
    "sg:phone":"+1 586 986 0948",
    "sg:postcode":"48092",
    "sg:province":"MI",
    "sg:tags":[
        "wrap",
        "american",
        "sandwich"
    ],
    "wof:name":"Quiznos Sub",
    "wof:placetype":"venue"
},
  "geometry": {"coordinates":[-83.046606,42.515414],"type":"Point"}
}