{
  "type": "Feature",
  "properties": {
    "iso:country":"US",
    "sg:address":"628 W Adrian St",
    "sg:city":"Blissfield",
    "sg:classifiers":[
        {
            "category":"Food & Beverages",
            "subcategory":"Groceries & Convenience Stores",
            "type":"Retail Goods"
        }
    ],
    "sg:phone":"+1 517 486 2960",
    "sg:postcode":"49228",
    "sg:province":"MI",
    "sg:tags":[
        "grocer"
    ],
    "sg:website":"www.spartanstores.com",
    "wof:name":"Borchardt Brothers Market",
    "wof:placetype":"venue"
},
  "geometry": {"coordinates":[-83.87894799999999,41.836717],"type":"Point"}
}