{
  "type": "Feature",
  "properties": {
    "iso:country":"US",
    "sg:address":"18401 Farmington Rd",
    "sg:city":"Livonia",
    "sg:classifiers":[
        {
            "category":"Banks & Credit Unions",
            "subcategory":"Investment Brokerage",
            "type":"Services"
        }
    ],
    "sg:phone":"+1 248 615 4391",
    "sg:postcode":"48152",
    "sg:province":"MI",
    "sg:tags":[
        "investing"
    ],
    "wof:name":"Lyon Kenneth Cfp",
    "wof:placetype":"venue"
},
  "geometry": {"coordinates":[-83.375086,42.421173],"type":"Point"}
}