{
  "type": "Feature",
  "properties": {
    "iso:country":"US",
    "sg:address":"7173 Oak Highlands Dr",
    "sg:city":"Kalamazoo",
    "sg:classifiers":[
        {
            "category":"Professional",
            "type":"Services"
        }
    ],
    "sg:phone":"+1 269 375 6084",
    "sg:postcode":"49009",
    "sg:province":"MI",
    "sg:tags":[
        "writer"
    ],
    "wof:name":"Diana M Hoyt Writer",
    "wof:placetype":"venue"
},
  "geometry": {"coordinates":[-85.691019,42.312878],"type":"Point"}
}