{
  "type": "Feature",
  "properties": {
    "iso:country":"US",
    "sg:address":"28004 Center Oaks Ct",
    "sg:city":"Wixom",
    "sg:classifiers":[
        {
            "category":"Professional",
            "subcategory":"Business Services",
            "type":"Services"
        }
    ],
    "sg:phone":"+1 248 344 4327",
    "sg:postcode":"48393",
    "sg:province":"MI",
    "wof:name":"Complete Business Svc",
    "wof:placetype":"venue"
},
  "geometry": {"coordinates":[-83.546684,42.499346],"type":"Point"}
}