{
  "type": "Feature",
  "properties": {
    "iso:country":"US",
    "sg:address":"2089 US Hwy 23 N",
    "sg:city":"Alpena",
    "sg:classifiers":[
        {
            "category":"Retail",
            "subcategory":"Auto Repair",
            "type":"Services"
        }
    ],
    "sg:phone":"+1 989 354 5350",
    "sg:postcode":"49707",
    "sg:province":"MI",
    "sg:tags":[
        "repairing",
        "automobile"
    ],
    "wof:name":"A J's Auto Svc & Repair Shop",
    "wof:placetype":"venue"
},
  "geometry": {"coordinates":[-83.457476,45.091762],"type":"Point"}
}