{
  "type": "Feature",
  "properties": {
    "iso:country":"US",
    "sg:address":"21185 Sunnydale St",
    "sg:city":"Farmington",
    "sg:classifiers":[
        {
            "category":"Freight",
            "type":"Transportation"
        }
    ],
    "sg:phone":"+1 248 442 7190",
    "sg:postcode":"48336",
    "sg:province":"MI",
    "sg:tags":[
        "operator",
        "local",
        "trucking"
    ],
    "wof:name":"He Eddwards Hauling Ltd",
    "wof:placetype":"venue"
},
  "geometry": {"coordinates":[-83.358056,42.448169],"type":"Point"}
}