{
  "type": "Feature",
  "properties": {
    "iso:country":"US",
    "sg:address":"2579 Deborah Dr",
    "sg:city":"Monroe",
    "sg:classifiers":[
        {
            "category":"Professional",
            "subcategory":"Management & Consulting",
            "type":"Services"
        }
    ],
    "sg:phone":"+1 734 242 1255",
    "sg:postcode":"48162",
    "sg:province":"MI",
    "sg:tags":[
        "business"
    ],
    "wof:name":"Koesel Consulting Services",
    "wof:placetype":"venue"
},
  "geometry": {"coordinates":[-83.418781,41.96468],"type":"Point"}
}