{
  "type": "Feature",
  "properties": {
    "iso:country":"US",
    "sg:address":"1353 US Hwy 2",
    "sg:city":"Crystal Falls",
    "sg:classifiers":[
        {
            "category":"Shopping",
            "subcategory":"Florist",
            "type":"Retail Goods"
        }
    ],
    "sg:phone":"+1 906 875 7444",
    "sg:postcode":"49920",
    "sg:province":"MI",
    "wof:name":"Flower Garden & Gifts",
    "wof:placetype":"venue"
},
  "geometry": {"coordinates":[-88.35321399999999,46.09772],"type":"Point"}
}