{
  "type": "Feature",
  "properties": {
    "iso:country":"US",
    "sg:address":"1654 Stony Creek Dr",
    "sg:city":"Rochester",
    "sg:classifiers":[
        {
            "category":"Professional",
            "type":"Services"
        }
    ],
    "sg:phone":"+1 248 601 8040",
    "sg:postcode":"48307",
    "sg:province":"MI",
    "wof:name":"Tonia D Haag",
    "wof:placetype":"venue"
},
  "geometry": {"coordinates":[-83.11277200000001,42.690441],"type":"Point"}
}