{
  "type": "Feature",
  "properties": {
    "iso:country":"US",
    "sg:address":"560 S Rochester Rd",
    "sg:city":"Rochester",
    "sg:classifiers":[
        {
            "category":"Home & Garden",
            "subcategory":"Building Materials",
            "type":"Retail Goods"
        }
    ],
    "sg:phone":"+1 248 299 5660",
    "sg:postcode":"48307",
    "sg:province":"MI",
    "sg:tags":[
        "glass",
        "window",
        "plate"
    ],
    "wof:name":"National Auto Glass & Mirror",
    "wof:placetype":"venue"
},
  "geometry": {"coordinates":[-83.13345099999999,42.672446],"type":"Point"}
}