{
  "type": "Feature",
  "properties": {
    "iso:country":"US",
    "sg:address":"51500 Birch St",
    "sg:city":"New Baltimore",
    "sg:classifiers":[
        {
            "category":"Building & Trades",
            "subcategory":"Cleaning & Sanitation",
            "type":"Services"
        }
    ],
    "sg:phone":"+1 586 716 2388",
    "sg:postcode":"48047",
    "sg:province":"MI",
    "sg:tags":[
        "janitor"
    ],
    "wof:name":"Cleanall Janitorial Supply Inc",
    "wof:placetype":"venue"
},
  "geometry": {"coordinates":[-82.750817,42.678865],"type":"Point"}
}