{
  "type": "Feature",
  "properties": {
    "iso:country":"US",
    "sg:address":"15204 Martin Rd",
    "sg:city":"Roseville",
    "sg:classifiers":[
        {
            "category":"Home & Garden",
            "subcategory":"Building Materials",
            "type":"Retail Goods"
        }
    ],
    "sg:phone":"+1 586 777 7740",
    "sg:postcode":"48066",
    "sg:province":"MI",
    "sg:tags":[
        "mixed",
        "concrete"
    ],
    "wof:name":"American Transit Mix",
    "wof:placetype":"venue"
},
  "geometry": {"coordinates":[-82.968025,42.501443],"type":"Point"}
}