{
  "type": "Feature",
  "properties": {
    "iso:country":"US",
    "sg:address":"105 W Water St",
    "sg:city":"Sault Ste Marie",
    "sg:classifiers":[
        {
            "category":"Insurance",
            "subcategory":"Insurance Agent",
            "type":"Services"
        }
    ],
    "sg:phone":"+1 906 635 5238",
    "sg:postcode":"49783",
    "sg:province":"MI",
    "wof:name":"Northern Michigan Insurance",
    "wof:placetype":"venue"
},
  "geometry": {"coordinates":[-84.346383,46.501186],"type":"Point"}
}