{
  "type": "Feature",
  "properties": {
    "iso:country":"US",
    "sg:address":"1753 Union St",
    "sg:city":"Benton Harbor",
    "sg:classifiers":[
        {
            "category":"Organizations",
            "subcategory":"Religious Organization",
            "type":"Services"
        }
    ],
    "sg:phone":"+1 269 925 2670",
    "sg:postcode":"49022",
    "sg:province":"MI",
    "sg:tags":[
        "church"
    ],
    "wof:name":"St Augustine's Episcopal Chr",
    "wof:placetype":"venue"
},
  "geometry": {"coordinates":[-86.44139699999999,42.085176],"type":"Point"}
}