{
  "type": "Feature",
  "properties": {
    "iso:country":"US",
    "sg:address":"80 Cherokee Rd",
    "sg:city":"Pontiac",
    "sg:classifiers":[
        {
            "category":"Professional",
            "subcategory":"Business Services",
            "type":"Services"
        }
    ],
    "sg:phone":"+1 248 454 0431",
    "sg:postcode":"48341",
    "sg:province":"MI",
    "sg:tags":[
        "planning",
        "meeting",
        "event"
    ],
    "wof:name":"Moons Event Management Inc",
    "wof:placetype":"venue"
},
  "geometry": {"coordinates":[-83.315354,42.632101],"type":"Point"}
}