{
  "type": "Feature",
  "properties": {
    "iso:country":"US",
    "sg:address":"3201 Walton Rd",
    "sg:city":"Buchanan",
    "sg:classifiers":[
        {
            "category":"Retail",
            "subcategory":"Repair Shop",
            "type":"Services"
        }
    ],
    "sg:phone":"+1 269 695 2374",
    "sg:postcode":"49107",
    "sg:province":"MI",
    "wof:name":"Marvs Lock Shop",
    "wof:placetype":"venue"
},
  "geometry": {"coordinates":[-86.334306,41.844851],"type":"Point"}
}