{
  "type": "Feature",
  "properties": {
    "iso:country":"US",
    "sg:address":"135 W Grant St",
    "sg:city":"Gwinn",
    "sg:classifiers":[
        {
            "category":"Social Services",
            "subcategory":"Child Care",
            "type":"Services"
        }
    ],
    "sg:phone":"+1 906 346 5735",
    "sg:postcode":"49801",
    "sg:province":"MI",
    "sg:tags":[
        "day"
    ],
    "wof:name":"Gwinn Head Start",
    "wof:placetype":"venue"
},
  "geometry": {"coordinates":[-88.066276,45.834157],"type":"Point"}
}