{
  "type": "Feature",
  "properties": {
    "iso:country":"US",
    "sg:address":"12457 Hill Rd",
    "sg:city":"Swartz Creek",
    "sg:classifiers":[
        {
            "category":"Building & Trades",
            "subcategory":"Construction",
            "type":"Services"
        }
    ],
    "sg:phone":"+1 810 621 3110",
    "sg:postcode":"48473",
    "sg:province":"MI",
    "sg:tags":[
        "house"
    ],
    "wof:name":"Harvey L Taylor Builder",
    "wof:placetype":"venue"
},
  "geometry": {"coordinates":[-83.92631,42.941283],"type":"Point"}
}