{
  "type": "Feature",
  "properties": {
    "iso:country":"US",
    "sg:address":"9177 W Grand River Ave",
    "sg:city":"Fowlerville",
    "sg:classifiers":[
        {
            "category":"Retail",
            "subcategory":"Auto Repair",
            "type":"Services"
        }
    ],
    "sg:phone":"+1 517 223 0793",
    "sg:postcode":"48836",
    "sg:province":"MI",
    "sg:tags":[
        "wrecker"
    ],
    "wof:name":"Nelson's A-1 Towing",
    "wof:placetype":"venue"
},
  "geometry": {"coordinates":[-84.09304299999999,42.661553],"type":"Point"}
}