{
  "type": "Feature",
  "properties": {
    "iso:country":"US",
    "sg:address":"25822 Van Born Rd",
    "sg:city":"Dearborn Heights",
    "sg:classifiers":[
        {
            "category":"Retail",
            "subcategory":"Auto Repair",
            "type":"Services"
        }
    ],
    "sg:phone":"+1 313 292 0080",
    "sg:postcode":"48125",
    "sg:province":"MI",
    "wof:name":"Gary's Auto Service",
    "wof:placetype":"venue"
},
  "geometry": {"coordinates":[-83.290398,42.2686],"type":"Point"}
}