{
  "type": "Feature",
  "properties": {
    "iso:country":"US",
    "sg:address":"1233 Rochester Rd",
    "sg:city":"Troy",
    "sg:classifiers":[
        {
            "category":"Retail",
            "subcategory":"Auto Repair",
            "type":"Services"
        }
    ],
    "sg:phone":"+1 248 585 0032",
    "sg:postcode":"48083",
    "sg:province":"MI",
    "sg:tags":[
        "automotive",
        "general"
    ],
    "wof:name":"D JS Strut & Brake Shop",
    "wof:placetype":"venue"
},
  "geometry": {"coordinates":[-83.132972,42.545784],"type":"Point"}
}