{
  "type": "Feature",
  "properties": {
    "iso:country":"US",
    "sg:address":"3365 Associates Dr",
    "sg:city":"Burton",
    "sg:classifiers":[
        {
            "category":"Social Services",
            "type":"Services"
        }
    ],
    "sg:phone":"+1 810 743 0918",
    "sg:postcode":"48529",
    "sg:province":"MI",
    "sg:tags":[
        "counselor",
        "marriage",
        "family"
    ],
    "sg:website":"www.lcfsmi.org",
    "wof:name":"Lutheran Child & Family Svc",
    "wof:placetype":"venue"
},
  "geometry": {"coordinates":[-83.667754,42.981195],"type":"Point"}
}