{
  "type": "Feature",
  "properties": {
    "iso:country":"US",
    "sg:address":"5858 Enterprise Dr",
    "sg:city":"Lansing",
    "sg:classifiers":[
        {
            "category":"Professional",
            "subcategory":"Engineering",
            "type":"Services"
        }
    ],
    "sg:phone":"+1 517 492 1900",
    "sg:postcode":"48911",
    "sg:province":"MI",
    "sg:tags":[
        "manufacturing"
    ],
    "wof:name":"Lectronix Inc",
    "wof:placetype":"venue"
},
  "geometry": {"coordinates":[-84.52485799999999,42.671694],"type":"Point"}
}