{
  "type": "Feature",
  "properties": {
    "iso:country":"US",
    "sg:address":"38351 Wooster St",
    "sg:city":"Clinton Township",
    "sg:classifiers":[
        {
            "category":"Recreation",
            "type":"Entertainment"
        }
    ],
    "sg:phone":"+1 586 615 3238",
    "sg:postcode":"48036",
    "sg:province":"MI",
    "sg:tags":[
        "soccer",
        "official"
    ],
    "wof:name":"Kristine Youth Officials",
    "wof:placetype":"venue"
},
  "geometry": {"coordinates":[-82.871364,42.57899],"type":"Point"}
}