{
  "type": "Feature",
  "properties": {
    "iso:country":"US",
    "sg:address":"906 Lakeview Dr",
    "sg:city":"Lake Odessa",
    "sg:classifiers":[
        {
            "category":"Banks & Credit Unions",
            "subcategory":"Bank",
            "type":"Services"
        }
    ],
    "sg:phone":"+1 616 374 0885",
    "sg:postcode":"48849",
    "sg:province":"MI",
    "sg:tags":[
        "loan",
        "real estate"
    ],
    "wof:name":"Wheeler Financial Svc Inc",
    "wof:placetype":"venue"
},
  "geometry": {"coordinates":[-85.139735,42.773714],"type":"Point"}
}