{
  "type": "Feature",
  "properties": {
    "iso:country":"US",
    "sg:address":"50367 Oregon Ave",
    "sg:city":"Novi",
    "sg:classifiers":[
        {
            "category":"Retail",
            "subcategory":"Repair Shop",
            "type":"Services"
        }
    ],
    "sg:phone":"+1 248 735 8037",
    "sg:postcode":"48374",
    "sg:province":"MI",
    "wof:name":"HB Carpet Furniture Care",
    "wof:placetype":"venue"
},
  "geometry": {"coordinates":[-83.547591,42.48109],"type":"Point"}
}