{
  "type": "Feature",
  "properties": {
    "iso:country":"US",
    "sg:address":"227 Jackson St",
    "sg:city":"Coleman",
    "sg:classifiers":[
        {
            "category":"Communications",
            "subcategory":"Radio Station",
            "type":"Services"
        }
    ],
    "sg:phone":"+1 989 465 9775",
    "sg:postcode":"48618",
    "sg:province":"MI",
    "sg:tags":[
        "company",
        "broadcasting"
    ],
    "sg:website":"www.wprj.org",
    "wof:name":"WPRJ",
    "wof:placetype":"venue"
},
  "geometry": {"coordinates":[-84.589162,43.755024],"type":"Point"}
}