{
  "type": "Feature",
  "properties": {
    "iso:country":"US",
    "sg:address":"2785 N 168th Ave",
    "sg:city":"Holland",
    "sg:classifiers":[
        {
            "category":"Building & Trades",
            "subcategory":"Construction",
            "type":"Services"
        }
    ],
    "sg:phone":"+1 616 399 3376",
    "sg:postcode":"49424",
    "sg:province":"MI",
    "sg:tags":[
        "concrete",
        "contractor"
    ],
    "wof:name":"Ken Topp",
    "wof:placetype":"venue"
},
  "geometry": {"coordinates":[-86.197727,42.819387],"type":"Point"}
}