{
  "type": "Feature",
  "properties": {
    "iso:country":"US",
    "sg:address":"462 E Edgewood Blvd",
    "sg:city":"Lansing",
    "sg:classifiers":[
        {
            "category":"Shopping",
            "subcategory":"Clothing, Apparel, & Fashions",
            "type":"Retail Goods"
        }
    ],
    "sg:phone":"+1 517 887 0830",
    "sg:postcode":"48911",
    "sg:province":"MI",
    "wof:name":"Fashion Bug",
    "wof:placetype":"venue"
},
  "geometry": {"coordinates":[-84.547568,42.663215],"type":"Point"}
}