{
  "type": "Feature",
  "properties": {
    "iso:country":"US",
    "sg:address":"11885 E 12 Mile Rd",
    "sg:city":"Warren",
    "sg:classifiers":[
        {
            "category":"Health Services",
            "subcategory":"Clinic",
            "type":"Services"
        }
    ],
    "sg:phone":"+1 586 558 9112",
    "sg:postcode":"48093",
    "sg:province":"MI",
    "sg:tags":[
        "home"
    ],
    "wof:name":"Life Link Home Health Care",
    "wof:placetype":"venue"
},
  "geometry": {"coordinates":[-83.003006,42.507259],"type":"Point"}
}