{
  "type": "Feature",
  "properties": {
    "iso:country":"US",
    "sg:address":"4552 Newcroft St",
    "sg:city":"Commerce Twp",
    "sg:classifiers":[
        {
            "category":"Building & Trades",
            "subcategory":"Construction",
            "type":"Services"
        }
    ],
    "sg:phone":"+1 248 366 6245",
    "sg:postcode":"48382",
    "sg:province":"MI",
    "sg:tags":[
        "planning",
        "remodeling",
        "kitchen"
    ],
    "wof:name":"Old Sawmill Woodworking Co",
    "wof:placetype":"venue"
},
  "geometry": {"coordinates":[-83.497255,42.588551],"type":"Point"}
}