{
  "type": "Feature",
  "properties": {
    "iso:country":"US",
    "sg:address":"2795 Rosewood St",
    "sg:city":"Jenison",
    "sg:classifiers":[
        {
            "category":"Organizations",
            "subcategory":"Religious Organization",
            "type":"Services"
        }
    ],
    "sg:phone":"+1 616 669 6690",
    "sg:postcode":"49428",
    "sg:province":"MI",
    "sg:tags":[
        "church"
    ],
    "sg:website":"www.rosewoodchurch.org",
    "wof:name":"Rosewood Reformed Church",
    "wof:placetype":"venue"
},
  "geometry": {"coordinates":[-85.85004600000001,42.896408],"type":"Point"}
}