{
  "type": "Feature",
  "properties": {
    "iso:country":"US",
    "sg:address":"247 Railroad St",
    "sg:city":"Dundee",
    "sg:classifiers":[
        {
            "category":"Shopping",
            "type":"Retail Goods"
        }
    ],
    "sg:phone":"+1 734 529 3492",
    "sg:postcode":"48131",
    "sg:province":"MI",
    "sg:tags":[
        "merchandise"
    ],
    "wof:name":"Mikes Place",
    "wof:placetype":"venue"
},
  "geometry": {"coordinates":[-83.64846199999999,41.957415],"type":"Point"}
}