{
  "type": "Feature",
  "properties": {
    "iso:country":"US",
    "sg:address":"515 E Liberty St",
    "sg:city":"Ann Arbor",
    "sg:classifiers":[
        {
            "category":"Professional",
            "subcategory":"Engineering",
            "type":"Services"
        }
    ],
    "sg:phone":"+1 734 995 5010",
    "sg:postcode":"48104",
    "sg:province":"MI",
    "wof:name":"Acuson Corporation",
    "wof:placetype":"venue"
},
  "geometry": {"coordinates":[-83.742148,42.279458],"type":"Point"}
}