{
  "type": "Feature",
  "properties": {
    "iso:country":"US",
    "sg:address":"201 W 9 Mile",
    "sg:city":"Ferndale",
    "sg:classifiers":[
        {
            "category":"Restaurant",
            "type":"Food & Drink"
        }
    ],
    "sg:phone":"+1 248 542 6458",
    "sg:postcode":"48220",
    "sg:province":"MI",
    "sg:tags":[
        "japanese"
    ],
    "wof:name":"Nami Sushi",
    "wof:placetype":"venue"
},
  "geometry": {"coordinates":[-83.136312,42.460292],"type":"Point"}
}