{
  "type": "Feature",
  "properties": {
    "iso:country":"US",
    "sg:address":"9923 Sharon Hollow Rd",
    "sg:city":"Manchester",
    "sg:classifiers":[
        {
            "category":"Professional",
            "subcategory":"Secretarial Services",
            "type":"Services"
        }
    ],
    "sg:phone":"+1 734 428 9200",
    "sg:postcode":"48158",
    "sg:province":"MI",
    "sg:tags":[
        "reporting"
    ],
    "wof:name":"Write Standards",
    "wof:placetype":"venue"
},
  "geometry": {"coordinates":[-84.08877699999999,42.122537],"type":"Point"}
}