{
  "type": "Feature",
  "properties": {
    "iso:country":"US",
    "sg:address":"1302 Carpenter Ave",
    "sg:city":"Iron Mountain",
    "sg:classifiers":[
        {
            "category":"Professional",
            "subcategory":"Business Services",
            "type":"Services"
        }
    ],
    "sg:phone":"+1 906 774 3010",
    "sg:postcode":"49801",
    "sg:province":"MI",
    "sg:tags":[
        "embroidery"
    ],
    "wof:name":"Signature Design",
    "wof:placetype":"venue"
},
  "geometry": {"coordinates":[-88.068702,45.809741],"type":"Point"}
}