{
  "type": "Feature",
  "properties": {
    "iso:country":"US",
    "sg:address":"13801 W 9 Mile Rd",
    "sg:city":"Oak Park",
    "sg:classifiers":[
        {
            "category":"Health Services",
            "subcategory":"Doctor",
            "type":"Services"
        }
    ],
    "sg:phone":"+1 248 547 3535",
    "sg:postcode":"48237",
    "sg:province":"MI",
    "sg:tags":[
        "medicine",
        "medical",
        "internal"
    ],
    "wof:name":"Garg Gobind L MD",
    "wof:placetype":"venue"
},
  "geometry": {"coordinates":[-83.184601,42.459702],"type":"Point"}
}