{
  "type": "Feature",
  "properties": {
    "iso:country":"US",
    "sg:address":"2761 E Apple Ave",
    "sg:city":"Muskegon",
    "sg:classifiers":[
        {
            "category":"Autos & Motor Vehicles",
            "subcategory":"Auto Supplies",
            "type":"Retail Goods"
        }
    ],
    "sg:phone":"+1 231 767 8217",
    "sg:postcode":"49442",
    "sg:province":"MI",
    "sg:tags":[
        "tire"
    ],
    "wof:name":"Tire Wholesalers",
    "wof:placetype":"venue"
},
  "geometry": {"coordinates":[-86.178135,43.234154],"type":"Point"}
}