{
  "type": "Feature",
  "properties": {
    "iso:country":"US",
    "sg:address":"7020 Michigan Ave",
    "sg:city":"Detroit",
    "sg:classifiers":[
        {
            "category":"Retail",
            "subcategory":"Portrait Studio",
            "type":"Services"
        }
    ],
    "sg:phone":"+1 313 551 0825",
    "sg:postcode":"48210",
    "sg:province":"MI",
    "sg:tags":[
        "photo"
    ],
    "wof:name":"Mora Portrait Studio",
    "wof:placetype":"venue"
},
  "geometry": {"coordinates":[-83.13187499999999,42.331186],"type":"Point"}
}