{
  "type": "Feature",
  "properties": {
    "iso:country":"US",
    "sg:address":"6800 S Westnedge Ave",
    "sg:city":"Portage",
    "sg:classifiers":[
        {
            "category":"Home & Garden",
            "subcategory":"Household Appliances",
            "type":"Retail Goods"
        }
    ],
    "sg:phone":"+1 269 321 8324",
    "sg:postcode":"49002",
    "sg:province":"MI",
    "sg:tags":[
        "cleaners",
        "vacuum"
    ],
    "wof:name":"Oreck Floor Care Ctr",
    "wof:placetype":"venue"
},
  "geometry": {"coordinates":[-85.58942999999999,42.219443],"type":"Point"}
}