{
  "type": "Feature",
  "properties": {
    "iso:country":"US",
    "sg:address":"15003 Greenview Rd",
    "sg:city":"Detroit",
    "sg:classifiers":[
        {
            "category":"Social Services",
            "subcategory":"Adult Care",
            "type":"Services"
        }
    ],
    "sg:phone":"+1 313 273 9375",
    "sg:postcode":"48223",
    "sg:province":"MI",
    "sg:tags":[
        "foster",
        "provider"
    ],
    "wof:name":"Lorraine Burton",
    "wof:placetype":"venue"
},
  "geometry": {"coordinates":[-83.22410600000001,42.400947],"type":"Point"}
}