{
  "type": "Feature",
  "properties": {
    "iso:country":"US",
    "sg:address":"38490 Hayes Rd",
    "sg:city":"Clinton Township",
    "sg:classifiers":[
        {
            "category":"Personal",
            "subcategory":"Beauty Salon",
            "type":"Services"
        }
    ],
    "sg:phone":"+1 586 412 0099",
    "sg:postcode":"48038",
    "sg:province":"MI",
    "sg:tags":[
        "shop"
    ],
    "wof:name":"Hair Power",
    "wof:placetype":"venue"
},
  "geometry": {"coordinates":[-82.97124599999999,42.577492],"type":"Point"}
}