{
  "type": "Feature",
  "properties": {
    "iso:country":"US",
    "sg:address":"14821 Eleanor Ave",
    "sg:city":"Warren",
    "sg:classifiers":[
        {
            "category":"Professional",
            "subcategory":"Secretarial Services",
            "type":"Services"
        }
    ],
    "sg:phone":"+1 586 776 1020",
    "sg:postcode":"48089",
    "sg:province":"MI",
    "sg:tags":[
        "transcription",
        "medical"
    ],
    "wof:name":"M & M Medical Secretarial Svc",
    "wof:placetype":"venue"
},
  "geometry": {"coordinates":[-82.969757,42.474376],"type":"Point"}
}