{
  "type": "Feature",
  "properties": {
    "iso:country":"US",
    "sg:address":"18000 Vernier Rd Ste 727",
    "sg:city":"Harper Woods",
    "sg:classifiers":[
        {
            "category":"Education",
            "subcategory":"Special Training",
            "type":"Public Place"
        }
    ],
    "sg:phone":"+1 313 839 6487",
    "sg:postcode":"48225",
    "sg:province":"MI",
    "sg:tags":[
        "school",
        "specialty"
    ],
    "wof:name":"M-K Fashions",
    "wof:placetype":"venue"
},
  "geometry": {"coordinates":[-82.934197,42.449746],"type":"Point"}
}