{
  "type": "Feature",
  "properties": {
    "iso:country":"US",
    "sg:address":"3741 Wilder Rd",
    "sg:city":"Bay City",
    "sg:classifiers":[
        {
            "category":"Retail",
            "subcategory":"Repair Shop",
            "type":"Services"
        }
    ],
    "sg:phone":"+1 989 686 6442",
    "sg:postcode":"48706",
    "sg:province":"MI",
    "sg:tags":[
        "equipment",
        "material",
        "handling"
    ],
    "wof:name":"Koch Materials Co",
    "wof:placetype":"venue"
},
  "geometry": {"coordinates":[-83.905136,43.623824],"type":"Point"}
}