{
  "type": "Feature",
  "properties": {
    "iso:country":"US",
    "sg:address":"50058 Peggy Ln",
    "sg:city":"Chesterfield",
    "sg:classifiers":[
        {
            "category":"Recreation",
            "type":"Entertainment"
        }
    ],
    "sg:phone":"+1 586 949 0956",
    "sg:postcode":"48047",
    "sg:province":"MI",
    "sg:tags":[
        "guide"
    ],
    "wof:name":"Sea J Sportfishing",
    "wof:placetype":"venue"
},
  "geometry": {"coordinates":[-82.79503699999999,42.666645],"type":"Point"}
}