{
  "type": "Feature",
  "properties": {
    "iso:country":"US",
    "sg:address":"585 E Larned St Ste 200",
    "sg:city":"Detroit",
    "sg:classifiers":[
        {
            "category":"Professional",
            "subcategory":"Lawyer & Legal Services",
            "type":"Services"
        }
    ],
    "sg:phone":"+1 313 965 4292",
    "sg:postcode":"48226",
    "sg:province":"MI",
    "wof:name":"Keel Alvin Atty",
    "wof:placetype":"venue"
},
  "geometry": {"coordinates":[-83.037201,42.333],"type":"Point"}
}