{
  "type": "Feature",
  "properties": {
    "iso:country":"US",
    "sg:address":"527 S Ave B",
    "sg:city":"Athens",
    "sg:classifiers":[
        {
            "category":"Social Services",
            "subcategory":"Adult Care",
            "type":"Services"
        }
    ],
    "sg:phone":"+1 269 729 4526",
    "sg:postcode":"49011",
    "sg:province":"MI",
    "sg:tags":[
        "residential"
    ],
    "wof:name":"Allen Afc",
    "wof:placetype":"venue"
},
  "geometry": {"coordinates":[-85.232525,42.08403],"type":"Point"}
}