{
  "type": "Feature",
  "properties": {
    "iso:country":"US",
    "sg:address":"6470 Williamson St",
    "sg:city":"Dearborn",
    "sg:classifiers":[
        {
            "category":"Professional",
            "subcategory":"Engineering",
            "type":"Services"
        }
    ],
    "sg:phone":"+1 313 846 4400",
    "sg:postcode":"48126",
    "sg:province":"MI",
    "wof:name":"American Engineers Inc",
    "wof:placetype":"venue"
},
  "geometry": {"coordinates":[-83.182317,42.338024],"type":"Point"}
}