{
  "type": "Feature",
  "properties": {
    "iso:country":"US",
    "sg:address":"123 E 9 Mile Rd",
    "sg:city":"Hazel Park",
    "sg:classifiers":[
        {
            "category":"Education",
            "subcategory":"Library",
            "type":"Public Place"
        }
    ],
    "sg:phone":"+1 248 542 0940",
    "sg:postcode":"48030",
    "sg:province":"MI",
    "wof:name":"Hazel Park City Public Library",
    "wof:placetype":"venue"
},
  "geometry": {"coordinates":[-83.103212,42.461495],"type":"Point"}
}