{
  "type": "Feature",
  "properties": {
    "iso:country":"US",
    "sg:address":"7425 Capac Rd",
    "sg:city":"Lynn",
    "sg:classifiers":[
        {
            "category":"Professional",
            "type":"Services"
        }
    ],
    "sg:phone":"+1 810 395 2622",
    "sg:postcode":"48097",
    "sg:province":"MI",
    "sg:tags":[
        "establishment"
    ],
    "wof:name":"Gerlach",
    "wof:placetype":"venue"
},
  "geometry": {"coordinates":[-82.933245,43.11363],"type":"Point"}
}