{
  "type": "Feature",
  "properties": {
    "iso:country":"US",
    "sg:address":"13479 E 14 Mile Rd",
    "sg:city":"Sterling Heights",
    "sg:classifiers":[
        {
            "category":"Health Services",
            "subcategory":"Doctor",
            "type":"Services"
        }
    ],
    "sg:phone":"+1 586 264 7300",
    "sg:postcode":"48312",
    "sg:province":"MI",
    "sg:tags":[
        "podiatrist"
    ],
    "wof:name":"Aronovitz Daniel DPM",
    "wof:placetype":"venue"
},
  "geometry": {"coordinates":[-82.99009700000001,42.537899],"type":"Point"}
}