{
  "type": "Feature",
  "properties": {
    "iso:country":"US",
    "sg:address":"3160 S Gera Rd",
    "sg:city":"Frankenmuth",
    "sg:phone":"+1 989 652 9302",
    "sg:postcode":"48734",
    "sg:province":"MI",
    "sg:tags":[
        "farm",
        "field",
        "crop"
    ],
    "wof:name":"Daniel Weiss",
    "wof:placetype":"venue"
},
  "geometry": {"coordinates":[-83.73855399999999,43.377346],"type":"Point"}
}