{
  "type": "Feature",
  "properties": {
    "iso:country":"US",
    "sg:address":"37156 Dequindre Rd",
    "sg:city":"Sterling Heights",
    "sg:classifiers":[
        {
            "category":"Restaurant",
            "type":"Food & Drink"
        }
    ],
    "sg:phone":"+1 586 979 9900",
    "sg:postcode":"48310",
    "sg:province":"MI",
    "wof:name":"Giulio's The Italian Star Take",
    "wof:placetype":"venue"
},
  "geometry": {"coordinates":[-83.088785,42.564081],"type":"Point"}
}