{
  "type": "Feature",
  "properties": {
    "iso:country":"US",
    "sg:address":"3520 Pontaluna Rd",
    "sg:city":"Fruitport",
    "sg:classifiers":[
        {
            "category":"Organizations",
            "subcategory":"Religious Organization",
            "type":"Services"
        }
    ],
    "sg:phone":"+1 231 865 6548",
    "sg:postcode":"49415",
    "sg:province":"MI",
    "wof:name":"C R C",
    "wof:placetype":"venue"
},
  "geometry": {"coordinates":[-86.15884800000001,43.13215],"type":"Point"}
}