{
  "type": "Feature",
  "properties": {
    "iso:country":"US",
    "sg:address":"8441 Park Ave",
    "sg:city":"Allen Park",
    "sg:classifiers":[
        {
            "category":"Shopping",
            "subcategory":"Florist",
            "type":"Retail Goods"
        }
    ],
    "sg:phone":"+1 313 383 5100",
    "sg:postcode":"48101",
    "sg:province":"MI",
    "wof:name":"Benedict's Flowers",
    "wof:placetype":"venue"
},
  "geometry": {"coordinates":[-83.213402,42.246498],"type":"Point"}
}