{
  "type": "Feature",
  "properties": {
    "iso:country":"US",
    "sg:address":"9609 Rolling Ridge Dr",
    "sg:city":"Traverse City",
    "sg:classifiers":[
        {
            "category":"Professional",
            "type":"Services"
        }
    ],
    "sg:phone":"+1 231 932 0153",
    "sg:postcode":"49686",
    "sg:province":"MI",
    "wof:name":"Walters Handyman Service",
    "wof:placetype":"venue"
},
  "geometry": {"coordinates":[-85.55217500000001,44.826399],"type":"Point"}
}