{
  "type": "Feature",
  "properties": {
    "iso:country":"US",
    "sg:address":"2702 E Rick Dr",
    "sg:city":"Port Huron",
    "sg:classifiers":[
        {
            "category":"Social Services",
            "subcategory":"Adult Care",
            "type":"Services"
        }
    ],
    "sg:phone":"+1 810 982 7609",
    "sg:postcode":"48060",
    "sg:province":"MI",
    "sg:tags":[
        "foster",
        "provider"
    ],
    "wof:name":"Allen & Lynda McLeod",
    "wof:placetype":"venue"
},
  "geometry": {"coordinates":[-82.437889,42.954164],"type":"Point"}
}