{
  "type": "Feature",
  "properties": {
    "iso:country":"US",
    "sg:address":"31692 Allerton Dr",
    "sg:city":"Beverly Hills",
    "sg:classifiers":[
        {
            "category":"Building & Trades",
            "subcategory":"Landscaping Services",
            "type":"Services"
        }
    ],
    "sg:phone":"+1 248 645 0460",
    "sg:postcode":"48025",
    "sg:province":"MI",
    "sg:tags":[
        "landscape",
        "contractor"
    ],
    "wof:name":"Johnson Landscaping",
    "wof:placetype":"venue"
},
  "geometry": {"coordinates":[-83.22877,42.52318],"type":"Point"}
}