{
  "type": "Feature",
  "properties": {
    "iso:country":"US",
    "sg:address":"3782 W Conrad Rd",
    "sg:city":"Ludington",
    "sg:classifiers":[
        {
            "category":"Social Services",
            "subcategory":"Child Care",
            "type":"Services"
        }
    ],
    "sg:phone":"+1 231 843 8187",
    "sg:postcode":"49431",
    "sg:province":"MI",
    "sg:tags":[
        "day",
        "provider"
    ],
    "wof:name":"Rosemary Lou Soberalski",
    "wof:placetype":"venue"
},
  "geometry": {"coordinates":[-86.372078,43.934341],"type":"Point"}
}