{
  "type": "Feature",
  "properties": {
    "iso:country":"US",
    "sg:address":"1720 S Otsego Ave",
    "sg:city":"Gaylord",
    "sg:classifiers":[
        {
            "category":"Retail",
            "subcategory":"Auto Rental",
            "type":"Services"
        }
    ],
    "sg:phone":"+1 989 731 9726",
    "sg:postcode":"49735",
    "sg:province":"MI",
    "sg:tags":[
        "passenger",
        "car"
    ],
    "wof:name":"Enterpise Rental",
    "wof:placetype":"venue"
},
  "geometry": {"coordinates":[-84.67765300000001,45.01308],"type":"Point"}
}