{
  "type": "Feature",
  "properties": {
    "iso:country":"US",
    "sg:address":"3005 1st St",
    "sg:city":"Wyandotte",
    "sg:classifiers":[
        {
            "category":"Personal",
            "subcategory":"Beauty Salon",
            "type":"Services"
        }
    ],
    "sg:phone":"+1 734 283 3272",
    "sg:postcode":"48192",
    "sg:province":"MI",
    "sg:tags":[
        "shop"
    ],
    "wof:name":"Barry-N-Company Inc",
    "wof:placetype":"venue"
},
  "geometry": {"coordinates":[-83.149939,42.202155],"type":"Point"}
}