{
  "type": "Feature",
  "properties": {
    "iso:country":"US",
    "sg:address":"4334 Brockton Dr SE",
    "sg:city":"Grand Rapids",
    "sg:classifiers":[
        {
            "category":"Manufacturing",
            "subcategory":"Furniture",
            "type":"Manufacturing & Wholesale Goods"
        }
    ],
    "sg:phone":"+1 616 942 9222",
    "sg:postcode":"49512",
    "sg:province":"MI",
    "sg:tags":[
        "material",
        "fixture",
        "display"
    ],
    "wof:name":"Marketing Communications",
    "wof:placetype":"venue"
},
  "geometry": {"coordinates":[-85.55867600000001,42.884953],"type":"Point"}
}