{
  "type": "Feature",
  "properties": {
    "iso:country":"US",
    "sg:address":"2 Woodward Ave",
    "sg:city":"Detroit",
    "sg:classifiers":[
        {
            "category":"Government",
            "subcategory":"Office",
            "type":"Public Place"
        }
    ],
    "sg:phone":"+1 313 224 3450",
    "sg:postcode":"48226",
    "sg:province":"MI",
    "sg:tags":[
        "general"
    ],
    "wof:name":"Neighborhood City Halls-NCH",
    "wof:placetype":"venue"
},
  "geometry": {"coordinates":[-83.04504300000001,42.32951],"type":"Point"}
}