{
  "type": "Feature",
  "properties": {
    "iso:country":"US",
    "sg:address":"9875 S Dixie Hwy",
    "sg:city":"Erie",
    "sg:classifiers":[
        {
            "category":"Food & Beverages",
            "subcategory":"Groceries & Convenience Stores",
            "type":"Retail Goods"
        }
    ],
    "sg:phone":"+1 734 848 4920",
    "sg:postcode":"48133",
    "sg:province":"MI",
    "sg:tags":[
        "grocer"
    ],
    "wof:name":"Erie IGA",
    "wof:placetype":"venue"
},
  "geometry": {"coordinates":[-83.49393600000001,41.799234],"type":"Point"}
}