{
  "type": "Feature",
  "properties": {
    "iso:country":"US",
    "sg:address":"309 E Hackley Ave",
    "sg:city":"Muskegon",
    "sg:classifiers":[
        {
            "category":"Professional",
            "subcategory":"Business Services",
            "type":"Services"
        }
    ],
    "sg:phone":"+1 231 830 9111",
    "sg:postcode":"49444",
    "sg:province":"MI",
    "wof:name":"Duncan Care Center LLC",
    "wof:placetype":"venue"
},
  "geometry": {"coordinates":[-86.23591,43.212218],"type":"Point"}
}