{
  "type": "Feature",
  "properties": {
    "iso:country":"US",
    "sg:address":"220 Bagley St",
    "sg:city":"Detroit",
    "sg:classifiers":[
        {
            "category":"Communications",
            "type":"Services"
        }
    ],
    "sg:phone":"+1 313 965 3108",
    "sg:postcode":"48226",
    "sg:province":"MI",
    "sg:tags":[
        "web",
        "design"
    ],
    "wof:name":"X Copy",
    "wof:placetype":"venue"
},
  "geometry": {"coordinates":[-83.052904,42.334856],"type":"Point"}
}