{
  "type": "Feature",
  "properties": {
    "iso:country":"US",
    "sg:address":"8128 Dodge Rd",
    "sg:city":"Montrose",
    "sg:classifiers":[
        {
            "category":"Freight",
            "type":"Transportation"
        }
    ],
    "sg:phone":"+1 810 639 7574",
    "sg:postcode":"48457",
    "sg:province":"MI",
    "sg:tags":[
        "warehouse",
        "self",
        "storage"
    ],
    "wof:name":"House Phones Warehouse",
    "wof:placetype":"venue"
},
  "geometry": {"coordinates":[-83.83986299999999,43.147929],"type":"Point"}
}