{
  "type": "Feature",
  "properties": {
    "iso:country":"US",
    "sg:address":"2580 N Squirrel Rd",
    "sg:city":"Auburn Hills",
    "sg:classifiers":[
        {
            "category":"Restaurant",
            "type":"Food & Drink"
        }
    ],
    "sg:menulink":"http://www.allmenus.com/mi/auburn-hills/24014-olgas-kitchen/menu/",
    "sg:phone":"+1 248 555 1212",
    "sg:postcode":"48326",
    "sg:province":"MI",
    "sg:tags":[
        "wrap",
        "new",
        "american",
        "sandwich"
    ],
    "wof:name":"Olga's Kitchen",
    "wof:placetype":"venue"
},
  "geometry": {"coordinates":[-83.221137,42.680399],"type":"Point"}
}