{
  "type": "Feature",
  "properties": {
    "iso:country":"US",
    "sg:address":"5812 Southward Ave",
    "sg:city":"Waterford",
    "sg:classifiers":[
        {
            "category":"Organizations",
            "subcategory":"Religious Organization",
            "type":"Services"
        }
    ],
    "sg:phone":"+1 248 623 1827",
    "sg:postcode":"48329",
    "sg:province":"MI",
    "wof:name":"Local Sprtl Assmbly of The Bah",
    "wof:placetype":"venue"
},
  "geometry": {"coordinates":[-83.407445,42.696913],"type":"Point"}
}