{
  "type": "Feature",
  "properties": {
    "iso:country":"US",
    "sg:address":"200 Taft St",
    "sg:city":"Zeeland",
    "sg:classifiers":[
        {
            "category":"Health Services",
            "subcategory":"Doctor",
            "type":"Services"
        }
    ],
    "sg:phone":"+1 616 772 9121",
    "sg:postcode":"49464",
    "sg:province":"MI",
    "sg:tags":[
        "physician",
        "surgeon"
    ],
    "wof:name":"Zeeland Medical Ctr",
    "wof:placetype":"venue"
},
  "geometry": {"coordinates":[-86.02459899999999,42.808702],"type":"Point"}
}