{
  "type": "Feature",
  "properties": {
    "iso:country":"US",
    "sg:address":"36854 Ryan Rd",
    "sg:city":"Sterling Heights",
    "sg:classifiers":[
        {
            "category":"Personal",
            "subcategory":"Beauty Salon",
            "type":"Services"
        }
    ],
    "sg:phone":"+1 586 978 0981",
    "sg:postcode":"48310",
    "sg:province":"MI",
    "sg:tags":[
        "shop"
    ],
    "wof:name":"Sam's Style",
    "wof:placetype":"venue"
},
  "geometry": {"coordinates":[-83.069846,42.563823],"type":"Point"}
}