{
  "type": "Feature",
  "properties": {
    "iso:country":"US",
    "sg:address":"37151 S Groesbeck Hwy",
    "sg:city":"Clinton Township",
    "sg:classifiers":[
        {
            "category":"Health Services",
            "subcategory":"Clinic",
            "type":"Services"
        },
        {
            "category":"Food & Beverages",
            "subcategory":"Specialty",
            "type":"Retail Goods"
        }
    ],
    "sg:phone":"+1 586 466 4444",
    "sg:postcode":"48036",
    "sg:province":"MI",
    "sg:tags":[
        "market",
        "diet"
    ],
    "wof:name":"Discount Nutrition Center Inc",
    "wof:placetype":"venue"
},
  "geometry": {"coordinates":[-82.910797,42.5714],"type":"Point"}
}