{
  "type": "Feature",
  "properties": {
    "iso:country":"US",
    "sg:address":"10620 Morang Dr",
    "sg:city":"Detroit",
    "sg:classifiers":[
        {
            "category":"Shopping",
            "subcategory":"Florist",
            "type":"Retail Goods"
        }
    ],
    "sg:phone":"+1 313 527 5266",
    "sg:postcode":"48224",
    "sg:province":"MI",
    "wof:name":"Willas Floral Design",
    "wof:placetype":"venue"
},
  "geometry": {"coordinates":[-82.940242,42.422189],"type":"Point"}
}