{
  "type": "Feature",
  "properties": {
    "iso:country":"US",
    "sg:address":"4 Pioneer St",
    "sg:city":"Battle Creek",
    "sg:classifiers":[
        {
            "category":"Professional",
            "subcategory":"Management & Consulting",
            "type":"Services"
        }
    ],
    "sg:phone":"+1 269 964 8292",
    "sg:postcode":"49015",
    "sg:province":"MI",
    "wof:name":"Financial Resolutions",
    "wof:placetype":"venue"
},
  "geometry": {"coordinates":[-85.205393,42.303987],"type":"Point"}
}