{
  "type": "Feature",
  "properties": {
    "iso:country":"US",
    "sg:address":"501 Avery St",
    "sg:city":"Alpena",
    "sg:classifiers":[
        {
            "category":"Building & Trades",
            "subcategory":"Construction",
            "type":"Services"
        }
    ],
    "sg:phone":"+1 989 354 9136",
    "sg:postcode":"49707",
    "sg:province":"MI",
    "sg:tags":[
        "contractor"
    ],
    "wof:name":"McDonald Pete",
    "wof:placetype":"venue"
},
  "geometry": {"coordinates":[-83.427199,45.076189],"type":"Point"}
}