{
  "type": "Feature",
  "properties": {
    "iso:country":"US",
    "sg:address":"8696 3rd St",
    "sg:city":"Vestaburg",
    "sg:classifiers":[
        {
            "category":"Restaurant",
            "type":"Food & Drink"
        }
    ],
    "sg:phone":"+1 989 268 9699",
    "sg:postcode":"48891",
    "sg:province":"MI",
    "wof:name":"Brecht's Hometown Pizza",
    "wof:placetype":"venue"
},
  "geometry": {"coordinates":[-84.911384,43.398918],"type":"Point"}
}