{
  "type": "Feature",
  "properties": {
    "iso:country":"US",
    "sg:address":"1985 Gratiot Blvd",
    "sg:city":"Marysville",
    "sg:classifiers":[
        {
            "category":"Health Services",
            "subcategory":"Clinic",
            "type":"Services"
        },
        {
            "category":"Social Services",
            "type":"Services"
        }
    ],
    "sg:phone":"+1 810 388 0096",
    "sg:postcode":"48040",
    "sg:province":"MI",
    "sg:tags":[
        "home"
    ],
    "sg:website":"www.aaa1b.org",
    "wof:name":"Area Agency On Aging 1-B",
    "wof:placetype":"venue"
},
  "geometry": {"coordinates":[-82.483993,42.916658],"type":"Point"}
}