{
  "type": "Feature",
  "properties": {
    "iso:country":"US",
    "sg:address":"7652 Red Arrow Hwy",
    "sg:city":"Watervliet",
    "sg:classifiers":[
        {
            "category":"Health Services",
            "subcategory":"Chiropractor",
            "type":"Services"
        }
    ],
    "sg:phone":"+1 269 463 4100",
    "sg:postcode":"49098",
    "sg:province":"MI",
    "wof:name":"Lifestyle Chiropractic",
    "wof:placetype":"venue"
},
  "geometry": {"coordinates":[-86.275009,42.186068],"type":"Point"}
}