{
  "type": "Feature",
  "properties": {
    "iso:country":"US",
    "sg:address":"2150 Lake Michigan Dr NW",
    "sg:city":"Grand Rapids",
    "sg:classifiers":[
        {
            "category":"Health Services",
            "subcategory":"Health Practitioner",
            "type":"Services"
        }
    ],
    "sg:phone":"+1 616 791 7206",
    "sg:postcode":"49504",
    "sg:province":"MI",
    "wof:name":"Novacare",
    "wof:placetype":"venue"
},
  "geometry": {"coordinates":[-85.722216,42.971433],"type":"Point"}
}