{
  "type": "Feature",
  "properties": {
    "iso:country":"US",
    "sg:address":"2794 North Dr",
    "sg:city":"Traverse City",
    "sg:classifiers":[
        {
            "category":"Retail",
            "subcategory":"Portrait Studio",
            "type":"Services"
        }
    ],
    "sg:phone":"+1 231 943 8036",
    "sg:postcode":"49684",
    "sg:province":"MI",
    "sg:tags":[
        "photo"
    ],
    "wof:name":"K M A Photographic",
    "wof:placetype":"venue"
},
  "geometry": {"coordinates":[-85.65997299999999,44.645774],"type":"Point"}
}