{
  "type": "Feature",
  "properties": {
    "iso:country":"US",
    "sg:address":"2900 Golfside Dr",
    "sg:city":"Ann Arbor",
    "sg:classifiers":[
        {
            "category":"Health Services",
            "subcategory":"Doctor",
            "type":"Services"
        }
    ],
    "sg:phone":"+1 734 434 5600",
    "sg:postcode":"48197",
    "sg:province":"MI",
    "sg:tags":[
        "medical"
    ],
    "wof:name":"P Meghnot MD PC",
    "wof:placetype":"venue"
},
  "geometry": {"coordinates":[-83.660882,42.246837],"type":"Point"}
}