{
  "type": "Feature",
  "properties": {
    "iso:country":"US",
    "sg:address":"1161 S Colling Rd",
    "sg:city":"Caro",
    "sg:classifiers":[
        {
            "category":"Home & Garden",
            "subcategory":"Household Appliances",
            "type":"Retail Goods"
        }
    ],
    "sg:phone":"+1 989 673 2233",
    "sg:postcode":"48723",
    "sg:province":"MI",
    "sg:tags":[
        "repair",
        "electrical"
    ],
    "wof:name":"Home Service",
    "wof:placetype":"venue"
},
  "geometry": {"coordinates":[-83.406379,43.476968],"type":"Point"}
}