{
  "type": "Feature",
  "properties": {
    "iso:country":"US",
    "sg:address":"758 Edge Creek Ct",
    "sg:city":"Wayland",
    "sg:classifiers":[
        {
            "category":"Building & Trades",
            "subcategory":"Construction",
            "type":"Services"
        }
    ],
    "sg:phone":"+1 616 893 1535",
    "sg:postcode":"49348",
    "sg:province":"MI",
    "sg:tags":[
        "home",
        "builder"
    ],
    "wof:name":"Affordable Home Renovations",
    "wof:placetype":"venue"
},
  "geometry": {"coordinates":[-85.521467,42.641819],"type":"Point"}
}