{
  "type": "Feature",
  "properties": {
    "iso:country":"US",
    "sg:address":"68 N Williams Lake Rd",
    "sg:city":"Waterford",
    "sg:classifiers":[
        {
            "category":"Health Services",
            "subcategory":"Doctor",
            "type":"Services"
        }
    ],
    "sg:phone":"+1 248 698 1150",
    "sg:postcode":"48327",
    "sg:province":"MI",
    "sg:tags":[
        "dentist"
    ],
    "wof:name":"John Kochanowski DDS",
    "wof:placetype":"venue"
},
  "geometry": {"coordinates":[-83.44332199999999,42.646044],"type":"Point"}
}