{
  "type": "Feature",
  "properties": {
    "iso:country":"US",
    "sg:address":"6714 Clear Lake Rd",
    "sg:city":"Grass Lake",
    "sg:classifiers":[
        {
            "category":"Travel",
            "subcategory":"Hotels & Motels",
            "type":"Entertainment"
        }
    ],
    "sg:phone":"+1 734 433 9744",
    "sg:postcode":"49240",
    "sg:province":"MI",
    "sg:tags":[
        "resort"
    ],
    "wof:name":"Clearlake Moose Lodge",
    "wof:placetype":"venue"
},
  "geometry": {"coordinates":[-84.15499800000001,42.331709],"type":"Point"}
}