{
  "type": "Feature",
  "properties": {
    "iso:country":"US",
    "sg:address":"534 E 8th St",
    "sg:city":"Traverse City",
    "sg:classifiers":[
        {
            "category":"Real Estate",
            "subcategory":"Surveying",
            "type":"Services"
        }
    ],
    "sg:phone":"+1 231 947 2555",
    "sg:postcode":"49686",
    "sg:province":"MI",
    "sg:tags":[
        "surveyor",
        "land"
    ],
    "wof:name":"Grand Traverse Surveying Co",
    "wof:placetype":"venue"
},
  "geometry": {"coordinates":[-85.612872,44.759326],"type":"Point"}
}