{
  "type": "Feature",
  "properties": {
    "iso:country":"US",
    "sg:address":"3814 Brookfield Dr",
    "sg:city":"White Lake",
    "sg:classifiers":[
        {
            "category":"Building & Trades",
            "subcategory":"Construction",
            "type":"Services"
        }
    ],
    "sg:phone":"+1 248 887 9643",
    "sg:postcode":"48383",
    "sg:province":"MI",
    "sg:tags":[
        "home",
        "improvement"
    ],
    "wof:name":"Smitty Home Improvements",
    "wof:placetype":"venue"
},
  "geometry": {"coordinates":[-83.56068399999999,42.684132],"type":"Point"}
}