{
  "type": "Feature",
  "properties": {
    "iso:country":"US",
    "sg:address":"13251 Watson Rd",
    "sg:city":"Bath",
    "sg:classifiers":[
        {
            "category":"Retail",
            "subcategory":"Portrait Studio",
            "type":"Services"
        }
    ],
    "sg:phone":"+1 517 641 6414",
    "sg:postcode":"48808",
    "sg:province":"MI",
    "sg:tags":[
        "photo"
    ],
    "wof:name":"Natural Images",
    "wof:placetype":"venue"
},
  "geometry": {"coordinates":[-84.463261,42.827617],"type":"Point"}
}