{
  "type": "Feature",
  "properties": {
    "iso:country":"US",
    "sg:address":"1800 Maplelawn Dr",
    "sg:city":"Troy",
    "sg:classifiers":[
        {
            "category":"Autos & Motor Vehicles",
            "subcategory":"Automobile Sales",
            "type":"Retail Goods"
        }
    ],
    "sg:phone":"+1 248 649 2892",
    "sg:postcode":"48084",
    "sg:province":"MI",
    "sg:tags":[
        "car"
    ],
    "sg:website":"www.nissanusa.com",
    "wof:name":"Suburban Nissan",
    "wof:placetype":"venue"
},
  "geometry": {"coordinates":[-83.174054,42.552754],"type":"Point"}
}