{
  "type": "Feature",
  "properties": {
    "iso:country":"US",
    "sg:address":"1570 36th Ave",
    "sg:city":"Hudsonville",
    "sg:classifiers":[
        {
            "category":"Food & Beverages",
            "subcategory":"Meat & Fish",
            "type":"Retail Goods"
        }
    ],
    "sg:phone":"+1 616 896 9359",
    "sg:postcode":"49426",
    "sg:province":"MI",
    "sg:tags":[
        "shop"
    ],
    "wof:name":"Mypac Inc",
    "wof:placetype":"venue"
},
  "geometry": {"coordinates":[-85.87130000000001,42.795799],"type":"Point"}
}