{
  "type": "Feature",
  "properties": {
    "iso:country":"US",
    "sg:address":"7076 N Harrison Ave",
    "sg:city":"Harrison",
    "sg:classifiers":[
        {
            "category":"Shopping",
            "type":"Retail Goods"
        }
    ],
    "sg:phone":"+1 989 539 8246",
    "sg:postcode":"48625",
    "sg:province":"MI",
    "sg:tags":[
        "merchandise"
    ],
    "wof:name":"Northern Water Treatment",
    "wof:placetype":"venue"
},
  "geometry": {"coordinates":[-84.82875,44.088995],"type":"Point"}
}