{
  "type": "Feature",
  "properties": {
    "iso:country":"US",
    "sg:address":"112 Radcliff St",
    "sg:city":"Garden City",
    "sg:classifiers":[
        {
            "category":"Restaurant",
            "type":"Food & Drink"
        }
    ],
    "sg:phone":"+1 734 522 5322",
    "sg:postcode":"48135",
    "sg:province":"MI",
    "sg:tags":[
        "eating"
    ],
    "wof:name":"Kitchen Fats Charcoal N Blues",
    "wof:placetype":"venue"
},
  "geometry": {"coordinates":[-83.373484,42.310376],"type":"Point"}
}