{
  "type": "Feature",
  "properties": {
    "iso:country":"US",
    "sg:address":"1611 W Centre Ave",
    "sg:city":"Portage",
    "sg:classifiers":[
        {
            "category":"Wholesale",
            "subcategory":"Photographic Equipment",
            "type":"Manufacturing & Wholesale Goods"
        }
    ],
    "sg:phone":"+1 269 323 0310",
    "sg:postcode":"49024",
    "sg:province":"MI",
    "sg:tags":[
        "identification"
    ],
    "wof:name":"Time Systems Inc",
    "wof:placetype":"venue"
},
  "geometry": {"coordinates":[-85.60820699999999,42.200941],"type":"Point"}
}