{
  "type": "Feature",
  "properties": {
    "iso:country":"US",
    "sg:address":"12045 Dix Toledo Rd",
    "sg:city":"Southgate",
    "sg:classifiers":[
        {
            "category":"Bars & Pubs",
            "type":"Food & Drink"
        }
    ],
    "sg:phone":"+1 734 283 0005",
    "sg:postcode":"48195",
    "sg:province":"MI",
    "sg:tags":[
        "brew",
        "tavern"
    ],
    "wof:name":"Shot Makers Sports Bar & Grill",
    "wof:placetype":"venue"
},
  "geometry": {"coordinates":[-83.19407200000001,42.220618],"type":"Point"}
}