{
  "type": "Feature",
  "properties": {
    "iso:country":"US",
    "sg:address":"400 N Main St",
    "sg:city":"Milford",
    "sg:classifiers":[
        {
            "category":"Building & Trades",
            "subcategory":"Construction",
            "type":"Services"
        }
    ],
    "sg:phone":"+1 248 685 2288",
    "sg:postcode":"48381",
    "sg:province":"MI",
    "sg:tags":[
        "general",
        "contractor"
    ],
    "wof:name":"Marietti Inc",
    "wof:placetype":"venue"
},
  "geometry": {"coordinates":[-83.600387,42.591657],"type":"Point"}
}