{
  "type": "Feature",
  "properties": {
    "iso:country":"US",
    "sg:address":"6275 N 5 Rd",
    "sg:city":"Mesick",
    "sg:classifiers":[
        {
            "category":"Wholesale",
            "subcategory":"Durable Goods & Equipment",
            "type":"Manufacturing & Wholesale Goods"
        }
    ],
    "sg:phone":"+1 231 885 1319",
    "sg:postcode":"49668",
    "sg:province":"MI",
    "sg:tags":[
        "product",
        "timber"
    ],
    "wof:name":"Cascagnett Inc",
    "wof:placetype":"venue"
},
  "geometry": {"coordinates":[-85.778907,44.427074],"type":"Point"}
}