{
  "type": "Feature",
  "properties": {
    "iso:country":"US",
    "sg:address":"15467 160th Ave",
    "sg:city":"Grand Haven",
    "sg:classifiers":[
        {
            "category":"Social Services",
            "subcategory":"Child Care",
            "type":"Services"
        }
    ],
    "sg:phone":"+1 616 842 2967",
    "sg:postcode":"49417",
    "sg:province":"MI",
    "sg:tags":[
        "day"
    ],
    "wof:name":"Roberta Howard",
    "wof:placetype":"venue"
},
  "geometry": {"coordinates":[-86.185636,43.049816],"type":"Point"}
}