{
  "type": "Feature",
  "properties": {
    "iso:country":"US",
    "sg:address":"1673 68th St",
    "sg:city":"Fennville",
    "sg:classifiers":[
        {
            "category":"Shopping",
            "subcategory":"Used Merchandise",
            "type":"Retail Goods"
        }
    ],
    "sg:phone":"+1 269 227 3200",
    "sg:postcode":"49408",
    "sg:province":"MI",
    "sg:tags":[
        "antique"
    ],
    "wof:name":"Willow Bend Antiques & Estate",
    "wof:placetype":"venue"
},
  "geometry": {"coordinates":[-86.208209,42.536285],"type":"Point"}
}