{
  "type": "Feature",
  "properties": {
    "iso:country":"US",
    "sg:address":"7622 Goshen Dr",
    "sg:city":"West Bloomfield",
    "sg:classifiers":[
        {
            "category":"Banks & Credit Unions",
            "subcategory":"Investment Brokerage",
            "type":"Services"
        }
    ],
    "sg:phone":"+1 248 624 8114",
    "sg:postcode":"48322",
    "sg:province":"MI",
    "sg:tags":[
        "consultant",
        "planning",
        "financial"
    ],
    "wof:name":"E M Capital",
    "wof:placetype":"venue"
},
  "geometry": {"coordinates":[-83.435705,42.536094],"type":"Point"}
}