{
  "type": "Feature",
  "properties": {
    "iso:country":"US",
    "sg:address":"1248 Eastern Pl NE",
    "sg:city":"Grand Rapids",
    "sg:classifiers":[
        {
            "category":"Building & Trades",
            "subcategory":"Cleaning & Sanitation",
            "type":"Services"
        }
    ],
    "sg:phone":"+1 616 776 9794",
    "sg:postcode":"49505",
    "sg:province":"MI",
    "sg:tags":[
        "maintenance"
    ],
    "wof:name":"High Quality Professional Clg",
    "wof:placetype":"venue"
},
  "geometry": {"coordinates":[-85.649416,42.986683],"type":"Point"}
}