{
  "type": "Feature",
  "properties": {
    "iso:country":"US",
    "sg:address":"2020 Dixie Pl",
    "sg:city":"Kalamazoo",
    "sg:classifiers":[
        {
            "category":"Professional",
            "subcategory":"Computer Services",
            "type":"Services"
        }
    ],
    "sg:phone":"+1 269 343 0383",
    "sg:postcode":"49001",
    "sg:province":"MI",
    "sg:tags":[
        "consultant",
        "designer"
    ],
    "wof:name":"Pixel Quest Inc",
    "wof:placetype":"venue"
},
  "geometry": {"coordinates":[-85.58389200000001,42.270547],"type":"Point"}
}