{
  "type": "Feature",
  "properties": {
    "iso:country":"US",
    "sg:address":"1818 Monroe St",
    "sg:city":"Carleton",
    "sg:classifiers":[
        {
            "category":"Retail",
            "subcategory":"Auto Repair",
            "type":"Services"
        }
    ],
    "sg:phone":"+1 734 654 6924",
    "sg:postcode":"48117",
    "sg:province":"MI",
    "sg:tags":[
        "automotive"
    ],
    "wof:name":"Hamlet Towing Automotive Repair",
    "wof:placetype":"venue"
},
  "geometry": {"coordinates":[-83.398201,42.0592],"type":"Point"}
}