{
  "type": "Feature",
  "properties": {
    "iso:country":"US",
    "sg:address":"2040 Monroe St",
    "sg:city":"Dearborn",
    "sg:classifiers":[
        {
            "category":"Health Services",
            "subcategory":"Health Practitioner",
            "type":"Services"
        }
    ],
    "sg:phone":"+1 313 277 4100",
    "sg:postcode":"48124",
    "sg:province":"MI",
    "sg:tags":[
        "therapy",
        "physical"
    ],
    "wof:name":"Healthland",
    "wof:placetype":"venue"
},
  "geometry": {"coordinates":[-83.245434,42.298242],"type":"Point"}
}