{
  "type": "Feature",
  "properties": {
    "iso:country":"US",
    "sg:address":"32100 Telegraph Rd",
    "sg:city":"Bingham Farms",
    "sg:classifiers":[
        {
            "category":"Professional",
            "subcategory":"Lawyer & Legal Services",
            "type":"Services"
        }
    ],
    "sg:phone":"+1 248 642 7733",
    "sg:postcode":"48025",
    "sg:province":"MI",
    "wof:name":"Payne Thomas W Atty",
    "wof:placetype":"venue"
},
  "geometry": {"coordinates":[-83.2855,42.5228],"type":"Point"}
}