{
  "type": "Feature",
  "properties": {
    "iso:country":"US",
    "sg:address":"926 E Tinkham Ave",
    "sg:city":"Ludington",
    "sg:classifiers":[
        {
            "category":"Real Estate",
            "subcategory":"Real Estate Operator",
            "type":"Services"
        }
    ],
    "sg:phone":"+1 231 843 4997",
    "sg:postcode":"49431",
    "sg:province":"MI",
    "sg:tags":[
        "building",
        "apartment"
    ],
    "wof:name":"Birch Lake Apts",
    "wof:placetype":"venue"
},
  "geometry": {"coordinates":[-86.429545,43.963208],"type":"Point"}
}