{
  "type": "Feature",
  "properties": {
    "iso:country":"US",
    "sg:address":"7190 Bingham Ave",
    "sg:city":"Newaygo",
    "sg:classifiers":[
        {
            "category":"Government",
            "subcategory":"Office",
            "type":"Public Place"
        }
    ],
    "sg:phone":"+1 231 652 4251",
    "sg:postcode":"49337",
    "sg:province":"MI",
    "sg:tags":[
        "executive"
    ],
    "wof:name":"Garfield Township Hall",
    "wof:placetype":"venue"
},
  "geometry": {"coordinates":[-85.86035099999999,43.423931],"type":"Point"}
}