{
  "type": "Feature",
  "properties": {
    "iso:country":"US",
    "sg:address":"30500 Commerce Blvd",
    "sg:city":"Chesterfield",
    "sg:classifiers":[
        {
            "category":"Manufacturing",
            "subcategory":"Tools & Machinery",
            "type":"Manufacturing & Wholesale Goods"
        }
    ],
    "sg:phone":"+1 586 749 6616",
    "sg:postcode":"48051",
    "sg:province":"MI",
    "sg:tags":[
        "die",
        "maker"
    ],
    "wof:name":"Fisher Kellering Chesterfield",
    "wof:placetype":"venue"
},
  "geometry": {"coordinates":[-82.806448,42.709277],"type":"Point"}
}