{
  "type": "Feature",
  "properties": {
    "iso:country":"US",
    "sg:address":"49110 Grand River Ave",
    "sg:city":"Wixom",
    "sg:classifiers":[
        {
            "category":"Bars & Pubs",
            "type":"Food & Drink"
        }
    ],
    "sg:phone":"+1 248 348 4404",
    "sg:postcode":"48393",
    "sg:province":"MI",
    "sg:tags":[
        "lounge",
        "cocktail"
    ],
    "wof:name":"Hennessey's Pub",
    "wof:placetype":"venue"
},
  "geometry": {"coordinates":[-83.53395999999999,42.493814],"type":"Point"}
}