{
  "type": "Feature",
  "properties": {
    "iso:country":"US",
    "sg:address":"23300 Ecorse Rd",
    "sg:city":"Taylor",
    "sg:classifiers":[
        {
            "category":"Health Services",
            "subcategory":"Doctor",
            "type":"Services"
        }
    ],
    "sg:phone":"+1 313 291 9500",
    "sg:postcode":"48180",
    "sg:province":"MI",
    "wof:name":"Lupu Viorel Mm",
    "wof:placetype":"venue"
},
  "geometry": {"coordinates":[-83.261398,42.255798],"type":"Point"}
}