{
  "type": "Feature",
  "properties": {
    "iso:country":"US",
    "sg:address":"1985 Gratiot Blvd",
    "sg:city":"Marysville",
    "sg:classifiers":[
        {
            "category":"Insurance",
            "subcategory":"Insurance Agent",
            "type":"Services"
        }
    ],
    "sg:phone":"+1 810 364 7200",
    "sg:postcode":"48040",
    "sg:province":"MI",
    "wof:name":"Ray F Sohn Prudential Insur",
    "wof:placetype":"venue"
},
  "geometry": {"coordinates":[-82.483993,42.916658],"type":"Point"}
}