{
  "type": "Feature",
  "properties": {
    "iso:country":"US",
    "sg:address":"247 W Hamilton Ln",
    "sg:city":"Battle Creek",
    "sg:classifiers":[
        {
            "category":"Professional",
            "subcategory":"Computer Services",
            "type":"Services"
        }
    ],
    "sg:phone":"+1 269 965 9802",
    "sg:postcode":"49015",
    "sg:province":"MI",
    "sg:tags":[
        "datum"
    ],
    "wof:name":"Tly Group",
    "wof:placetype":"venue"
},
  "geometry": {"coordinates":[-85.202406,42.269952],"type":"Point"}
}