{
  "type": "Feature",
  "properties": {
    "iso:country":"US",
    "sg:address":"503 W Montcalm St",
    "sg:city":"Greenville",
    "sg:classifiers":[
        {
            "category":"Social Services",
            "subcategory":"Adult Care",
            "type":"Services"
        }
    ],
    "sg:phone":"+1 616 225 9671",
    "sg:postcode":"48838",
    "sg:province":"MI",
    "sg:tags":[
        "home",
        "residential"
    ],
    "wof:name":"Quality Adult Foster Care Home",
    "wof:placetype":"venue"
},
  "geometry": {"coordinates":[-85.26161,43.182353],"type":"Point"}
}