{
  "type": "Feature",
  "properties": {
    "iso:country":"US",
    "sg:address":"1202 W Oak St",
    "sg:city":"Greenville",
    "sg:classifiers":[
        {
            "category":"Health Services",
            "subcategory":"Doctor",
            "type":"Services"
        }
    ],
    "sg:phone":"+1 616 225 2966",
    "sg:postcode":"48838",
    "sg:province":"MI",
    "sg:tags":[
        "physician",
        "surgeon"
    ],
    "wof:name":"Ambulatory United",
    "wof:placetype":"venue"
},
  "geometry": {"coordinates":[-85.271067,43.17555],"type":"Point"}
}