{
  "type": "Feature",
  "properties": {
    "iso:country":"US",
    "sg:address":"21516 Dequindre Rd",
    "sg:city":"Warren",
    "sg:classifiers":[
        {
            "category":"Real Estate",
            "subcategory":"Real Estate Operator",
            "type":"Services"
        }
    ],
    "sg:phone":"+1 586 756 7171",
    "sg:postcode":"48091",
    "sg:province":"MI",
    "sg:tags":[
        "apartment"
    ],
    "wof:name":"Warren Manor Apartments",
    "wof:placetype":"venue"
},
  "geometry": {"coordinates":[-83.05529799999999,42.465801],"type":"Point"}
}