{
  "type": "Feature",
  "properties": {
    "iso:country":"US",
    "sg:address":"535 N Clippert St",
    "sg:city":"Lansing",
    "sg:classifiers":[
        {
            "category":"Health Services",
            "subcategory":"Chiropractor",
            "type":"Services"
        }
    ],
    "sg:phone":"+1 517 336 8880",
    "sg:postcode":"48912",
    "sg:province":"MI",
    "sg:website":"www.motionx-ray.com",
    "wof:name":"Rassel Daigneault Chiro",
    "wof:placetype":"venue"
},
  "geometry": {"coordinates":[-84.508377,42.739433],"type":"Point"}
}