{
  "type": "Feature",
  "properties": {
    "iso:country":"US",
    "sg:address":"37370 S Gratiot Ave",
    "sg:city":"Clinton Township",
    "sg:classifiers":[
        {
            "category":"Banks & Credit Unions",
            "subcategory":"Bank",
            "type":"Services"
        }
    ],
    "sg:phone":"+1 586 463 3042",
    "sg:postcode":"48036",
    "sg:province":"MI",
    "wof:name":"Standard Federal Bank",
    "wof:placetype":"venue"
},
  "geometry": {"coordinates":[-82.889503,42.5728],"type":"Point"}
}