{
  "type": "Feature",
  "properties": {
    "iso:country":"US",
    "sg:address":"2431 Pritchard Dr",
    "sg:city":"Niles",
    "sg:classifiers":[
        {
            "category":"Building & Trades",
            "subcategory":"Construction",
            "type":"Services"
        }
    ],
    "sg:phone":"+1 269 684 7114",
    "sg:postcode":"49120",
    "sg:province":"MI",
    "sg:tags":[
        "house"
    ],
    "wof:name":"Njs Construction & Painti",
    "wof:placetype":"venue"
},
  "geometry": {"coordinates":[-86.275054,41.863402],"type":"Point"}
}