{
  "type": "Feature",
  "properties": {
    "iso:country":"US",
    "sg:address":"2620 S Cleveland Ave",
    "sg:city":"St Joseph",
    "sg:classifiers":[
        {
            "category":"Professional",
            "subcategory":"Employment Agencies",
            "type":"Services"
        }
    ],
    "sg:phone":"+1 269 428 0055",
    "sg:postcode":"49085",
    "sg:province":"MI",
    "sg:tags":[
        "temporary",
        "help",
        "contractor"
    ],
    "sg:website":"www.kellyservices.com",
    "wof:name":"Kelly Services Inc",
    "wof:placetype":"venue"
},
  "geometry": {"coordinates":[-86.49491399999999,42.070567],"type":"Point"}
}