{
  "type": "Feature",
  "properties": {
    "iso:country":"US",
    "sg:address":"446 Grandville Ave SW",
    "sg:city":"Grand Rapids",
    "sg:classifiers":[
        {
            "category":"Shopping",
            "subcategory":"Used Merchandise",
            "type":"Retail Goods"
        }
    ],
    "sg:phone":"+1 616 235 3540",
    "sg:postcode":"49503",
    "sg:province":"MI",
    "wof:name":"Crosby Antique Restoration",
    "wof:placetype":"venue"
},
  "geometry": {"coordinates":[-85.675442,42.954395],"type":"Point"}
}