{
  "type": "Feature",
  "properties": {
    "iso:country":"US",
    "sg:address":"2281 US Hwy 23 N",
    "sg:city":"Alpena",
    "sg:classifiers":[
        {
            "category":"Real Estate",
            "subcategory":"Real Estate Agent",
            "type":"Services"
        }
    ],
    "sg:phone":"+1 989 356 5833",
    "sg:postcode":"49707",
    "sg:province":"MI",
    "wof:name":"Sparling Lori Assoc Broker",
    "wof:placetype":"venue"
},
  "geometry": {"coordinates":[-83.456301,45.095682],"type":"Point"}
}