{
  "type": "Feature",
  "properties": {
    "iso:country":"US",
    "sg:address":"45829 Kensington St",
    "sg:city":"Utica",
    "sg:classifiers":[
        {
            "category":"Building & Trades",
            "subcategory":"Plumbing",
            "type":"Services"
        }
    ],
    "sg:phone":"+1 586 739 6675",
    "sg:postcode":"48317",
    "sg:province":"MI",
    "sg:tags":[
        "contractor"
    ],
    "wof:name":"Smith Donald Heating & Air Con",
    "wof:placetype":"venue"
},
  "geometry": {"coordinates":[-83.015376,42.634715],"type":"Point"}
}