{
  "type": "Feature",
  "properties": {
    "iso:country":"US",
    "sg:address":"9645 Red Maple Dr",
    "sg:city":"Plymouth",
    "sg:classifiers":[
        {
            "category":"Building & Trades",
            "subcategory":"Construction",
            "type":"Services"
        }
    ],
    "sg:phone":"+1 734 320 3962",
    "sg:postcode":"48170",
    "sg:province":"MI",
    "sg:tags":[
        "hanging",
        "contractor"
    ],
    "wof:name":"Vanerian Painting",
    "wof:placetype":"venue"
},
  "geometry": {"coordinates":[-83.527356,42.357819],"type":"Point"}
}