{
  "type": "Feature",
  "properties": {
    "iso:country":"US",
    "sg:address":"10163 Horton Rd",
    "sg:city":"Goodrich",
    "sg:classifiers":[
        {
            "category":"Organizations",
            "subcategory":"Religious Organization",
            "type":"Services"
        }
    ],
    "sg:phone":"+1 810 636 6783",
    "sg:postcode":"48438",
    "sg:province":"MI",
    "wof:name":"His 2 Overcome Ministries Inc",
    "wof:placetype":"venue"
},
  "geometry": {"coordinates":[-83.506264,42.882426],"type":"Point"}
}