{
  "type": "Feature",
  "properties": {
    "iso:country":"US",
    "sg:address":"27355 Ann Arbor Trl",
    "sg:city":"Dearborn Heights",
    "sg:classifiers":[
        {
            "category":"Organizations",
            "subcategory":"Membership Organization",
            "type":"Services"
        }
    ],
    "sg:phone":"+1 313 730 8900",
    "sg:postcode":"48127",
    "sg:province":"MI",
    "wof:name":"World Community Impact Inc",
    "wof:placetype":"venue"
},
  "geometry": {"coordinates":[-83.31146099999999,42.351286],"type":"Point"}
}