{
  "type": "Feature",
  "properties": {
    "iso:country":"US",
    "sg:address":"881 Ada Ave",
    "sg:city":"Muskegon",
    "sg:classifiers":[
        {
            "category":"Building & Trades",
            "subcategory":"Cleaning & Sanitation",
            "type":"Services"
        }
    ],
    "sg:phone":"+1 231 773 9548",
    "sg:postcode":"49442",
    "sg:province":"MI",
    "sg:tags":[
        "janitor"
    ],
    "wof:name":"Great Lakes Janitorial Svc",
    "wof:placetype":"venue"
},
  "geometry": {"coordinates":[-86.223162,43.233072],"type":"Point"}
}