{
  "type": "Feature",
  "properties": {
    "iso:country":"US",
    "sg:address":"6364 Ave I",
    "sg:city":"La Salle",
    "sg:classifiers":[
        {
            "category":"Building & Trades",
            "subcategory":"Construction",
            "type":"Services"
        }
    ],
    "sg:phone":"+1 734 243 5373",
    "sg:postcode":"48145",
    "sg:province":"MI",
    "sg:tags":[
        "house"
    ],
    "wof:name":"Davison W Christopher Builder",
    "wof:placetype":"venue"
},
  "geometry": {"coordinates":[-83.41005,41.832957],"type":"Point"}
}