{
  "type": "Feature",
  "properties": {
    "iso:country":"US",
    "sg:address":"4530 Goldenrod Dr",
    "sg:city":"Traverse City",
    "sg:classifiers":[
        {
            "category":"Professional",
            "subcategory":"Computer Services",
            "type":"Services"
        }
    ],
    "sg:phone":"+1 231 933 9963",
    "sg:postcode":"49684",
    "sg:province":"MI",
    "sg:tags":[
        "repair"
    ],
    "wof:name":"Overam Laptops",
    "wof:placetype":"venue"
},
  "geometry": {"coordinates":[-85.66734599999999,44.699458],"type":"Point"}
}