{
  "type": "Feature",
  "properties": {
    "iso:country":"US",
    "sg:address":"6619 Division Ave S",
    "sg:city":"Grand Rapids",
    "sg:classifiers":[
        {
            "category":"Home & Garden",
            "subcategory":"Furniture",
            "type":"Retail Goods"
        }
    ],
    "sg:phone":"+1 616 281 1300",
    "sg:postcode":"49548",
    "sg:province":"MI",
    "sg:tags":[
        "equipment",
        "kitchen",
        "cabinet"
    ],
    "sg:website":"www.woodlandkitchens.net",
    "wof:name":"Woodland House Of Kitchens",
    "wof:placetype":"venue"
},
  "geometry": {"coordinates":[-85.66377799999999,42.844063],"type":"Point"}
}