{
  "type": "Feature",
  "properties": {
    "iso:country":"US",
    "sg:address":"6580 Little St",
    "sg:city":"Marlette",
    "sg:classifiers":[
        {
            "category":"Professional",
            "subcategory":"Business Services",
            "type":"Services"
        }
    ],
    "sg:phone":"+1 989 635 3205",
    "sg:postcode":"48453",
    "sg:province":"MI",
    "wof:name":"Worthy Home Inspections",
    "wof:placetype":"venue"
},
  "geometry": {"coordinates":[-83.08260900000001,43.325079],"type":"Point"}
}