{
  "type": "Feature",
  "properties": {
    "iso:country":"US",
    "sg:address":"6830 Lea-Pick Dr",
    "sg:city":"Mt Pleasant",
    "sg:classifiers":[
        {
            "category":"Wholesale",
            "subcategory":"Machinery & Supplies",
            "type":"Manufacturing & Wholesale Goods"
        }
    ],
    "sg:phone":"+1 989 772 4391",
    "sg:postcode":"48858",
    "sg:province":"MI",
    "sg:tags":[
        "boring",
        "drilling"
    ],
    "wof:name":"Stockdale Mine Supply Inc",
    "wof:placetype":"venue"
},
  "geometry": {"coordinates":[-84.708298,43.613559],"type":"Point"}
}