{
  "type": "Feature",
  "properties": {
    "iso:country":"US",
    "sg:address":"20915 Melrose St",
    "sg:city":"Southfield",
    "sg:classifiers":[
        {
            "category":"Building & Trades",
            "subcategory":"Construction",
            "type":"Services"
        }
    ],
    "sg:phone":"+1 248 355 2815",
    "sg:postcode":"48075",
    "sg:province":"MI",
    "sg:tags":[
        "floor",
        "laying",
        "contractor"
    ],
    "wof:name":"Bullocks Hardwood Floor Svc",
    "wof:placetype":"venue"
},
  "geometry": {"coordinates":[-83.248394,42.448512],"type":"Point"}
}