{
  "type": "Feature",
  "properties": {
    "iso:country":"US",
    "sg:address":"1615 Lake Shore Dr",
    "sg:city":"Gladstone",
    "sg:classifiers":[
        {
            "category":"Health Services",
            "subcategory":"Nursing And Care Facility",
            "type":"Services"
        }
    ],
    "sg:phone":"+1 906 428 7071",
    "sg:postcode":"49837",
    "sg:province":"MI",
    "wof:name":"Lakeview Assisted Living",
    "wof:placetype":"venue"
},
  "geometry": {"coordinates":[-87.029056,45.838337],"type":"Point"}
}