{
  "type": "Feature",
  "properties": {
    "iso:country":"US",
    "sg:address":"16141 W 8 Mile Rd",
    "sg:city":"Detroit",
    "sg:classifiers":[
        {
            "category":"Social Services",
            "subcategory":"Child Care",
            "type":"Services"
        }
    ],
    "sg:phone":"+1 313 835 8936",
    "sg:postcode":"48235",
    "sg:province":"MI",
    "sg:tags":[
        "day"
    ],
    "wof:name":"Jari-Chas Day Care",
    "wof:placetype":"venue"
},
  "geometry": {"coordinates":[-83.207233,42.444518],"type":"Point"}
}