{
  "type": "Feature",
  "properties": {
    "iso:country":"US",
    "sg:address":"24527 Bethany Way",
    "sg:city":"Novi",
    "sg:classifiers":[
        {
            "category":"Professional",
            "subcategory":"Computer Services",
            "type":"Services"
        }
    ],
    "sg:phone":"+1 248 477 0317",
    "sg:postcode":"48375",
    "sg:province":"MI",
    "sg:tags":[
        "prepackaged",
        "software"
    ],
    "wof:name":"Autox Software Inc",
    "wof:placetype":"venue"
},
  "geometry": {"coordinates":[-83.449006,42.468667],"type":"Point"}
}