{
  "type": "Feature",
  "properties": {
    "iso:country":"US",
    "sg:address":"4057 S Dort Hwy",
    "sg:city":"Burton",
    "sg:classifiers":[
        {
            "category":"Wholesale",
            "subcategory":"Motor Vehicles",
            "type":"Manufacturing & Wholesale Goods"
        }
    ],
    "sg:phone":"+1 810 744 1930",
    "sg:postcode":"48529",
    "sg:province":"MI",
    "sg:tags":[
        "automobile",
        "truck",
        "broker"
    ],
    "wof:name":"Executive Auto Brokers",
    "wof:placetype":"venue"
},
  "geometry": {"coordinates":[-83.652815,42.974629],"type":"Point"}
}