{
  "type": "Feature",
  "properties": {
    "iso:country":"US",
    "sg:address":"812 Saginaw St",
    "sg:city":"Bay City",
    "sg:classifiers":[
        {
            "category":"Shopping",
            "subcategory":"Gifts & Souvenirs",
            "type":"Retail Goods"
        }
    ],
    "sg:phone":"+1 989 893 7661",
    "sg:postcode":"48708",
    "sg:province":"MI",
    "sg:tags":[
        "shop"
    ],
    "wof:name":"Euc Inc",
    "wof:placetype":"venue"
},
  "geometry": {"coordinates":[-83.88871399999999,43.599047],"type":"Point"}
}