{
  "type": "Feature",
  "properties": {
    "iso:country":"US",
    "sg:address":"3813 Belmont St",
    "sg:city":"Hamtramck",
    "sg:classifiers":[
        {
            "category":"Building & Trades",
            "subcategory":"Locksmith",
            "type":"Services"
        }
    ],
    "sg:phone":"+1 313 989 0291",
    "sg:postcode":"48212",
    "sg:province":"MI",
    "sg:tags":[
        "key"
    ],
    "wof:name":"Locks 24 Locksmith",
    "wof:placetype":"venue"
},
  "geometry": {"coordinates":[-83.051767,42.401203],"type":"Point"}
}