{
  "type": "Feature",
  "properties": {
    "iso:country":"US",
    "sg:address":"847 S Latson Rd",
    "sg:city":"Howell",
    "sg:classifiers":[
        {
            "category":"Restaurant",
            "type":"Food & Drink"
        }
    ],
    "sg:menulink":"http://www.allmenus.com/mi/oceola/142416-subway/menu/",
    "sg:phone":"+1 517 540 0927",
    "sg:postcode":"48843",
    "sg:province":"MI",
    "sg:tags":[
        "american",
        "sandwich"
    ],
    "wof:name":"Subway",
    "wof:placetype":"venue"
},
  "geometry": {"coordinates":[-83.87496899999999,42.613565],"type":"Point"}
}