{
  "type": "Feature",
  "properties": {
    "iso:country":"US",
    "sg:address":"2045 South Blvd W",
    "sg:city":"Troy",
    "sg:classifiers":[
        {
            "category":"Shopping",
            "subcategory":"Pharmacy",
            "type":"Retail Goods"
        }
    ],
    "sg:phone":"+1 248 879 2463",
    "sg:postcode":"48098",
    "sg:province":"MI",
    "sg:tags":[
        "drugstore"
    ],
    "wof:name":"Cvs Pharmacy",
    "wof:placetype":"venue"
},
  "geometry": {"coordinates":[-83.170303,42.621899],"type":"Point"}
}