{
  "type": "Feature",
  "properties": {
    "iso:country":"US",
    "sg:address":"101 W Maumee St",
    "sg:city":"Adrian",
    "sg:classifiers":[
        {
            "category":"Professional",
            "subcategory":"Lawyer & Legal Services",
            "type":"Services"
        }
    ],
    "sg:phone":"+1 517 263 7822",
    "sg:postcode":"49221",
    "sg:province":"MI",
    "wof:name":"Ballards Travis Attorney",
    "wof:placetype":"venue"
},
  "geometry": {"coordinates":[-84.03771399999999,41.899308],"type":"Point"}
}