{
  "type": "Feature",
  "properties": {
    "iso:country":"US",
    "sg:address":"330 W Tienken Rd",
    "sg:city":"Rochester Hills",
    "sg:classifiers":[
        {
            "category":"Health Services",
            "subcategory":"Doctor",
            "type":"Services"
        }
    ],
    "sg:phone":"+1 248 651 2640",
    "sg:postcode":"48306",
    "sg:province":"MI",
    "sg:tags":[
        "medicine",
        "physician",
        "oncology",
        "internal",
        "surgeon"
    ],
    "wof:name":"Donald M Birch MD PC",
    "wof:placetype":"venue"
},
  "geometry": {"coordinates":[-83.140942,42.695617],"type":"Point"}
}