{
  "type": "Feature",
  "properties": {
    "iso:country":"US",
    "sg:address":"15116 Telegraph Rd",
    "sg:city":"Redford",
    "sg:classifiers":[
        {
            "category":"Home & Garden",
            "subcategory":"Carpets & Floor Coverings",
            "type":"Retail Goods"
        }
    ],
    "sg:phone":"+1 313 592 3964",
    "sg:postcode":"48239",
    "sg:province":"MI",
    "wof:name":"Redford Floor Covering",
    "wof:placetype":"venue"
},
  "geometry": {"coordinates":[-83.27634500000001,42.398345],"type":"Point"}
}