{
  "type": "Feature",
  "properties": {
    "iso:country":"US",
    "sg:address":"28008 Florence St",
    "sg:city":"Saint Clair Shores",
    "sg:classifiers":[
        {
            "category":"Shopping",
            "type":"Retail Goods"
        }
    ],
    "sg:phone":"+1 586 772 3740",
    "sg:postcode":"48081",
    "sg:province":"MI",
    "sg:tags":[
        "florist",
        "merchandise"
    ],
    "wof:name":"Straw Flower Haus",
    "wof:placetype":"venue"
},
  "geometry": {"coordinates":[-82.893956,42.500569],"type":"Point"}
}