{
  "type": "Feature",
  "properties": {
    "iso:country":"US",
    "sg:address":"65 State Hwy 35",
    "sg:city":"Gwinn",
    "sg:classifiers":[
        {
            "category":"Retail",
            "subcategory":"Animal Services",
            "type":"Services"
        }
    ],
    "sg:phone":"+1 906 372 9011",
    "sg:postcode":"49841",
    "sg:province":"MI",
    "sg:tags":[
        "pet",
        "grooming",
        "washing"
    ],
    "wof:name":"Purrfect Pet",
    "wof:placetype":"venue"
},
  "geometry": {"coordinates":[-87.426029,46.277348],"type":"Point"}
}