{
  "type": "Feature",
  "properties": {
    "iso:country":"US",
    "sg:address":"26400 W 12 Mile Rd",
    "sg:city":"Southfield",
    "sg:classifiers":[
        {
            "category":"Health Services",
            "subcategory":"Doctor",
            "type":"Services"
        }
    ],
    "sg:phone":"+1 248 353 0818",
    "sg:postcode":"48034",
    "sg:province":"MI",
    "wof:name":"Kohen Laurie L MD",
    "wof:placetype":"venue"
},
  "geometry": {"coordinates":[-83.306749,42.50071],"type":"Point"}
}