{
  "type": "Feature",
  "properties": {
    "iso:country":"US",
    "sg:address":"26433 Harper Ave",
    "sg:city":"Saint Clair Shores",
    "sg:classifiers":[
        {
            "category":"Shopping",
            "subcategory":"Stationery & Office Supplies",
            "type":"Retail Goods"
        }
    ],
    "sg:phone":"+1 586 774 5270",
    "sg:postcode":"48081",
    "sg:province":"MI",
    "sg:tags":[
        "equipment"
    ],
    "wof:name":"Unique Ofc & School Supply Co Inc",
    "wof:placetype":"venue"
},
  "geometry": {"coordinates":[-82.89830000000001,42.4883],"type":"Point"}
}