{
  "type": "Feature",
  "properties": {
    "iso:country":"US",
    "sg:address":"4217 Okemos Rd",
    "sg:city":"Okemos",
    "sg:classifiers":[
        {
            "category":"Building & Trades",
            "subcategory":"Construction",
            "type":"Services"
        }
    ],
    "sg:phone":"+1 517 349 2180",
    "sg:postcode":"48864",
    "sg:province":"MI",
    "sg:tags":[
        "contractor"
    ],
    "wof:name":"HDI Builders",
    "wof:placetype":"venue"
},
  "geometry": {"coordinates":[-84.432433,42.703336],"type":"Point"}
}