{
  "type": "Feature",
  "properties": {
    "iso:country":"US",
    "sg:address":"6591 Sassafrass Rd",
    "sg:city":"Ludington",
    "sg:classifiers":[
        {
            "category":"Communications",
            "subcategory":"Film & Video Production",
            "type":"Services"
        }
    ],
    "sg:phone":"+1 231 845 9198",
    "sg:postcode":"49431",
    "sg:province":"MI",
    "sg:tags":[
        "motion"
    ],
    "wof:name":"Alway Photography",
    "wof:placetype":"venue"
},
  "geometry": {"coordinates":[-86.44424600000001,44.040922],"type":"Point"}
}