{
  "type": "Feature",
  "properties": {
    "iso:country":"US",
    "sg:address":"9200 W 6 Mile Rd",
    "sg:city":"Brimley",
    "sg:classifiers":[
        {
            "category":"Recreation",
            "type":"Entertainment"
        }
    ],
    "sg:phone":"+1 906 248 3422",
    "sg:postcode":"49715",
    "sg:province":"MI",
    "sg:tags":[
        "parks"
    ],
    "wof:name":"Brimley State Park",
    "wof:placetype":"venue"
},
  "geometry": {"coordinates":[-84.553877,46.412967],"type":"Point"}
}