{
  "type": "Feature",
  "properties": {
    "iso:country":"US",
    "sg:address":"25120 Michigan Ave",
    "sg:city":"Dearborn",
    "sg:classifiers":[
        {
            "category":"Restaurant",
            "type":"Food & Drink"
        }
    ],
    "sg:menulink":"http://www.allmenus.com/mi/dearborn/207811-taco-bell/menu/",
    "sg:phone":"+1 313 563 9299",
    "sg:postcode":"48124",
    "sg:province":"MI",
    "sg:tags":[
        "mexican"
    ],
    "wof:name":"Taco Bell",
    "wof:placetype":"venue"
},
  "geometry": {"coordinates":[-83.282196,42.298193],"type":"Point"}
}