{
  "type": "Feature",
  "properties": {
    "iso:country":"US",
    "sg:address":"33025 Industrial Rd",
    "sg:city":"Livonia",
    "sg:classifiers":[
        {
            "category":"Building & Trades",
            "subcategory":"Electrical",
            "type":"Services"
        },
        {
            "category":"Wholesale",
            "subcategory":"Home Furnishings",
            "type":"Manufacturing & Wholesale Goods"
        }
    ],
    "sg:phone":"+1 734 522 9973",
    "sg:postcode":"48150",
    "sg:province":"MI",
    "sg:tags":[
        "industrial",
        "electrician",
        "electric",
        "fixtures-wholesale",
        "lighting",
        "contractors-commercial",
        "manufacturer"
    ],
    "wof:name":"Custom Lighting Services",
    "wof:placetype":"venue"
},
  "geometry": {"coordinates":[-83.369574,42.379554],"type":"Point"}
}