{
  "type": "Feature",
  "properties": {
    "iso:country":"US",
    "sg:address":"1613 Mall Dr",
    "sg:city":"Benton Harbor",
    "sg:classifiers":[
        {
            "category":"Banks & Credit Unions",
            "subcategory":"Bank",
            "type":"Services"
        }
    ],
    "sg:phone":"+1 269 926 9200",
    "sg:postcode":"49022",
    "sg:province":"MI",
    "sg:tags":[
        "institution",
        "business"
    ],
    "wof:name":"Access 2 Cash",
    "wof:placetype":"venue"
},
  "geometry": {"coordinates":[-86.420939,42.078943],"type":"Point"}
}