{
  "type": "Feature",
  "properties": {
    "iso:country":"US",
    "sg:address":"221 E Lake St",
    "sg:city":"Petoskey",
    "sg:classifiers":[
        {
            "category":"Shopping",
            "type":"Retail Goods"
        }
    ],
    "sg:phone":"+1 231 347 3157",
    "sg:postcode":"49770",
    "sg:province":"MI",
    "sg:tags":[
        "art",
        "gallery",
        "dealer"
    ],
    "wof:name":"Luciano Studios",
    "wof:placetype":"venue"
},
  "geometry": {"coordinates":[-84.95740499999999,45.375032],"type":"Point"}
}