{
  "type": "Feature",
  "properties": {
    "iso:country":"US",
    "sg:address":"3065 N Genesee Rd",
    "sg:city":"Flint",
    "sg:classifiers":[
        {
            "category":"Government",
            "subcategory":"Office",
            "type":"Public Place"
        }
    ],
    "sg:phone":"+1 810 250 5000",
    "sg:postcode":"48506",
    "sg:province":"MI",
    "sg:tags":[
        "housing"
    ],
    "wof:name":"Eastside Village Inc",
    "wof:placetype":"venue"
},
  "geometry": {"coordinates":[-83.61593499999999,43.047501],"type":"Point"}
}