{
  "type": "Feature",
  "properties": {
    "iso:country":"US",
    "sg:address":"3093 N Meridian Rd",
    "sg:city":"Sanford",
    "sg:classifiers":[
        {
            "category":"Retail",
            "subcategory":"Auto Repair",
            "type":"Services"
        }
    ],
    "sg:phone":"+1 989 687 5046",
    "sg:postcode":"48657",
    "sg:province":"MI",
    "wof:name":"Sanford Auto Electric",
    "wof:placetype":"venue"
},
  "geometry": {"coordinates":[-84.368313,43.699576],"type":"Point"}
}