{
  "type": "Feature",
  "properties": {
    "iso:country":"US",
    "sg:address":"14070 Mellville St",
    "sg:city":"Engadine",
    "sg:classifiers":[
        {
            "category":"Organizations",
            "subcategory":"Religious Organization",
            "type":"Services"
        }
    ],
    "sg:phone":"+1 906 477 6731",
    "sg:postcode":"49827",
    "sg:province":"MI",
    "wof:name":"Catholic Missions",
    "wof:placetype":"venue"
},
  "geometry": {"coordinates":[-85.573579,46.116385],"type":"Point"}
}