{
  "type": "Feature",
  "properties": {
    "iso:country":"US",
    "sg:address":"44175 W 12 Mile Rd",
    "sg:city":"Novi",
    "sg:classifiers":[
        {
            "category":"Home & Garden",
            "subcategory":"Furniture",
            "type":"Retail Goods"
        }
    ],
    "sg:phone":"+1 248 344 0774",
    "sg:postcode":"48377",
    "sg:province":"MI",
    "sg:tags":[
        "builder",
        "custom"
    ],
    "wof:name":"Cost Plus World Market",
    "wof:placetype":"venue"
},
  "geometry": {"coordinates":[-83.484689,42.495288],"type":"Point"}
}