{
  "type": "Feature",
  "properties": {
    "iso:country":"US",
    "sg:address":"216 Newberry Ave",
    "sg:city":"Newberry",
    "sg:classifiers":[
        {
            "category":"Shopping",
            "subcategory":"Jewelry",
            "type":"Retail Goods"
        }
    ],
    "sg:phone":"+1 906 293 3242",
    "sg:postcode":"49868",
    "sg:province":"MI",
    "sg:tags":[
        "jeweler"
    ],
    "wof:name":"Billie's Little Store",
    "wof:placetype":"venue"
},
  "geometry": {"coordinates":[-85.509866,46.355933],"type":"Point"}
}