{
  "type": "Feature",
  "properties": {
    "iso:country":"US",
    "sg:address":"35661 Smith Rd",
    "sg:city":"Romulus",
    "sg:classifiers":[
        {
            "category":"Real Estate",
            "subcategory":"Real Estate Operator",
            "type":"Services"
        }
    ],
    "sg:phone":"+1 734 729 3328",
    "sg:postcode":"48174",
    "sg:province":"MI",
    "sg:tags":[
        "apartment"
    ],
    "wof:name":"Wellesley Townhouses",
    "wof:placetype":"venue"
},
  "geometry": {"coordinates":[-83.38960299999999,42.244099],"type":"Point"}
}