{
  "type": "Feature",
  "properties": {
    "iso:country":"US",
    "sg:address":"401 8th St",
    "sg:city":"Benton Harbor",
    "sg:classifiers":[
        {
            "category":"Government",
            "subcategory":"Office",
            "type":"Public Place"
        }
    ],
    "sg:phone":"+1 269 934 2056",
    "sg:postcode":"49022",
    "sg:province":"MI",
    "sg:tags":[
        "executive"
    ],
    "wof:name":"Family Independence Agcy Mich",
    "wof:placetype":"venue"
},
  "geometry": {"coordinates":[-86.457274,42.110821],"type":"Point"}
}