{
  "type": "Feature",
  "properties": {
    "iso:country":"US",
    "sg:address":"1219 S Poseyville Rd",
    "sg:city":"Midland",
    "sg:classifiers":[
        {
            "category":"Personal",
            "subcategory":"Barber",
            "type":"Services"
        }
    ],
    "sg:phone":"+1 989 631 1900",
    "sg:postcode":"48640",
    "sg:province":"MI",
    "sg:tags":[
        "shop"
    ],
    "wof:name":"Mallery's Barber Shop",
    "wof:placetype":"venue"
},
  "geometry": {"coordinates":[-84.247668,43.577902],"type":"Point"}
}