{
  "type": "Feature",
  "properties": {
    "iso:country":"US",
    "sg:address":"29629 M 152",
    "sg:city":"Dowagiac",
    "sg:classifiers":[
        {
            "category":"Building & Trades",
            "subcategory":"Construction",
            "type":"Services"
        }
    ],
    "sg:phone":"+1 269 424 3225",
    "sg:postcode":"49047",
    "sg:province":"MI",
    "sg:tags":[
        "bulldozing"
    ],
    "wof:name":"Secor Excavating",
    "wof:placetype":"venue"
},
  "geometry": {"coordinates":[-86.130758,42.056183],"type":"Point"}
}