{
  "type": "Feature",
  "properties": {
    "iso:country":"US",
    "sg:address":"5751 Eastman Blvd",
    "sg:city":"West Bloomfield",
    "sg:classifiers":[
        {
            "category":"Organizations",
            "subcategory":"Non-profit Organization",
            "type":"Services"
        }
    ],
    "sg:phone":"+1 248 851 3629",
    "sg:postcode":"48323",
    "sg:province":"MI",
    "sg:tags":[
        "fund",
        "counselor",
        "raising"
    ],
    "wof:name":"Elite Sports & Entertainment",
    "wof:placetype":"venue"
},
  "geometry": {"coordinates":[-83.323815,42.553869],"type":"Point"}
}