{
  "type": "Feature",
  "properties": {
    "iso:country":"US",
    "sg:address":"3674 E Huron Rd",
    "sg:city":"Au Gres",
    "sg:classifiers":[
        {
            "category":"Autos & Motor Vehicles",
            "subcategory":"Boat Sales",
            "type":"Retail Goods"
        }
    ],
    "sg:phone":"+1 989 876 8587",
    "sg:postcode":"48703",
    "sg:province":"MI",
    "sg:tags":[
        "dealer",
        "sales"
    ],
    "wof:name":"Port Au Gres Sports Ctr",
    "wof:placetype":"venue"
},
  "geometry": {"coordinates":[-83.657674,44.054606],"type":"Point"}
}