{
  "type": "Feature",
  "properties": {
    "iso:country":"US",
    "sg:address":"10200 W 8 Mile Rd",
    "sg:city":"Ferndale",
    "sg:classifiers":[
        {
            "category":"Retail",
            "subcategory":"Auto Repair",
            "type":"Services"
        }
    ],
    "sg:phone":"+1 248 542 1100",
    "sg:postcode":"48220",
    "sg:province":"MI",
    "sg:tags":[
        "body",
        "automotive",
        "motor",
        "mfg"
    ],
    "wof:name":"Ideal Customizing & Sun Roofs",
    "wof:placetype":"venue"
},
  "geometry": {"coordinates":[-83.160589,42.44603],"type":"Point"}
}