{
  "type": "Feature",
  "properties": {
    "iso:country":"US",
    "sg:address":"4457 N W Torch Lake Dr",
    "sg:city":"Kewadin",
    "sg:classifiers":[
        {
            "category":"Autos & Motor Vehicles",
            "subcategory":"Automobile Sales",
            "type":"Retail Goods"
        }
    ],
    "sg:phone":"+1 231 264 6361",
    "sg:postcode":"49648",
    "sg:province":"MI",
    "sg:tags":[
        "car",
        "dealer"
    ],
    "wof:name":"General Motors Tom Stephens",
    "wof:placetype":"venue"
},
  "geometry": {"coordinates":[-85.324107,44.975029],"type":"Point"}
}