{
  "type": "Feature",
  "properties": {
    "iso:country":"US",
    "sg:address":"1196 Falcon Dr",
    "sg:city":"Troy",
    "sg:classifiers":[
        {
            "category":"Shopping",
            "subcategory":"Hobbies, Toys, & Games",
            "type":"Retail Goods"
        }
    ],
    "sg:phone":"+1 248 879 3893",
    "sg:postcode":"48098",
    "sg:province":"MI",
    "sg:tags":[
        "craft"
    ],
    "wof:name":"Hand Crafts Bazaar LLC",
    "wof:placetype":"venue"
},
  "geometry": {"coordinates":[-83.171786,42.607002],"type":"Point"}
}