{
  "type": "Feature",
  "properties": {
    "iso:country":"US",
    "sg:address":"8267 S State Rd",
    "sg:city":"Goodrich",
    "sg:classifiers":[
        {
            "category":"Manufacturing",
            "subcategory":"Metals",
            "type":"Manufacturing & Wholesale Goods"
        }
    ],
    "sg:phone":"+1 810 636 2226",
    "sg:postcode":"48438",
    "sg:province":"MI",
    "sg:tags":[
        "production",
        "primary",
        "aluminum"
    ],
    "wof:name":"Goodrich Manufacturing Co",
    "wof:placetype":"venue"
},
  "geometry": {"coordinates":[-83.501499,42.914201],"type":"Point"}
}