{
  "type": "Feature",
  "properties": {
    "iso:country":"US",
    "sg:address":"1401 E Cloverland Dr",
    "sg:city":"Ironwood",
    "sg:classifiers":[
        {
            "category":"Government",
            "subcategory":"Office",
            "type":"Public Place"
        }
    ],
    "sg:phone":"+1 906 932 1003",
    "sg:postcode":"49938",
    "sg:province":"MI",
    "sg:tags":[
        "federal",
        "human"
    ],
    "wof:name":"US Social Security Adm",
    "wof:placetype":"venue"
},
  "geometry": {"coordinates":[-90.14201,46.463242],"type":"Point"}
}