{
  "type": "Feature",
  "properties": {
    "iso:country":"US",
    "sg:address":"10555 N Black River Rd",
    "sg:city":"Cheboygan",
    "sg:classifiers":[
        {
            "category":"Retail",
            "subcategory":"Veterinary Services",
            "type":"Services"
        }
    ],
    "sg:phone":"+1 231 627 7077",
    "sg:postcode":"49721",
    "sg:province":"MI",
    "sg:tags":[
        "veterinarian"
    ],
    "wof:name":"Black River Veterinary Hsptl",
    "wof:placetype":"venue"
},
  "geometry": {"coordinates":[-84.44436399999999,45.61136],"type":"Point"}
}