{
  "type": "Feature",
  "properties": {
    "iso:country":"US",
    "sg:address":"3571 W Shore Dr",
    "sg:city":"Battle Creek",
    "sg:classifiers":[
        {
            "category":"Building & Trades",
            "subcategory":"Construction",
            "type":"Services"
        }
    ],
    "sg:phone":"+1 269 209 6430",
    "sg:postcode":"49017",
    "sg:province":"MI",
    "sg:tags":[
        "home",
        "improvement"
    ],
    "wof:name":"Mike Mccarthy Builders LLC",
    "wof:placetype":"venue"
},
  "geometry": {"coordinates":[-85.30022,42.448724],"type":"Point"}
}