{
  "type": "Feature",
  "properties": {
    "iso:country":"US",
    "sg:address":"1819 Harwood Dr",
    "sg:city":"Oxford",
    "sg:classifiers":[
        {
            "category":"Manufacturing",
            "subcategory":"Textiles",
            "type":"Manufacturing & Wholesale Goods"
        },
        {
            "category":"Wholesale",
            "subcategory":"Motor Vehicles",
            "type":"Manufacturing & Wholesale Goods"
        }
    ],
    "sg:phone":"+1 248 969 4260",
    "sg:postcode":"48371",
    "sg:province":"MI",
    "sg:tags":[
        "finish",
        "mfg",
        "automobile",
        "broker",
        "warp",
        "truck",
        "knit"
    ],
    "wof:name":"Tietex International Ltd",
    "wof:placetype":"venue"
},
  "geometry": {"coordinates":[-83.304041,42.818155],"type":"Point"}
}