{
  "type": "Feature",
  "properties": {
    "iso:country":"US",
    "sg:address":"208 State St",
    "sg:city":"Harbor Beach",
    "sg:classifiers":[
        {
            "category":"Home & Garden",
            "subcategory":"Hardware",
            "type":"Retail Goods"
        }
    ],
    "sg:phone":"+1 989 479 6038",
    "sg:postcode":"48441",
    "sg:province":"MI",
    "wof:name":"Harbor Beach True Value Hdwr",
    "wof:placetype":"venue"
},
  "geometry": {"coordinates":[-82.652754,43.844251],"type":"Point"}
}