{
  "type": "Feature",
  "properties": {
    "iso:country":"US",
    "sg:address":"4587 Williamsburg Rd",
    "sg:city":"Williamsburg",
    "sg:classifiers":[
        {
            "category":"Professional",
            "subcategory":"Management & Consulting",
            "type":"Services"
        }
    ],
    "sg:phone":"+1 231 267 5259",
    "sg:postcode":"49690",
    "sg:province":"MI",
    "wof:name":"Pilates Place",
    "wof:placetype":"venue"
},
  "geometry": {"coordinates":[-85.40404100000001,44.749609],"type":"Point"}
}