{
  "type": "Feature",
  "properties": {
    "iso:country":"US",
    "sg:address":"13877 S Custer Rd",
    "sg:city":"Dundee",
    "sg:classifiers":[
        {
            "category":"Recreation",
            "subcategory":"Amusement Park",
            "type":"Entertainment"
        }
    ],
    "sg:phone":"+1 734 529 3427",
    "sg:postcode":"48131",
    "sg:province":"MI",
    "wof:name":"Bounce N Buddies Moonwalks",
    "wof:placetype":"venue"
},
  "geometry": {"coordinates":[-83.63055,41.950977],"type":"Point"}
}