{
  "type": "Feature",
  "properties": {
    "iso:country":"US",
    "sg:address":"1337 Rickett Rd",
    "sg:city":"Brighton",
    "sg:classifiers":[
        {
            "category":"Wholesale",
            "subcategory":"Electrical",
            "type":"Manufacturing & Wholesale Goods"
        }
    ],
    "sg:phone":"+1 810 229 0006",
    "sg:postcode":"48116",
    "sg:province":"MI",
    "sg:tags":[
        "control"
    ],
    "wof:name":"Temcor Systems Inc",
    "wof:placetype":"venue"
},
  "geometry": {"coordinates":[-83.77133499999999,42.517173],"type":"Point"}
}