{
  "type": "Feature",
  "properties": {
    "iso:country":"US",
    "sg:address":"1434 Mansfield St",
    "sg:city":"Port Huron",
    "sg:classifiers":[
        {
            "category":"Banks & Credit Unions",
            "subcategory":"Bank",
            "type":"Services"
        }
    ],
    "sg:phone":"+1 810 984 4560",
    "sg:postcode":"48060",
    "sg:province":"MI",
    "wof:name":"Flagship Federal Credit Union",
    "wof:placetype":"venue"
},
  "geometry": {"coordinates":[-82.43492000000001,42.996659],"type":"Point"}
}