{
  "type": "Feature",
  "properties": {
    "iso:country":"US",
    "sg:address":"206 S Main St",
    "sg:city":"Leslie",
    "sg:classifiers":[
        {
            "category":"Personal",
            "subcategory":"Barber",
            "type":"Services"
        }
    ],
    "sg:phone":"+1 517 589 9545",
    "sg:postcode":"49251",
    "sg:province":"MI",
    "sg:tags":[
        "shop"
    ],
    "wof:name":"Kents Style Shop",
    "wof:placetype":"venue"
},
  "geometry": {"coordinates":[-84.431988,42.447811],"type":"Point"}
}