{
  "type": "Feature",
  "properties": {
    "iso:country":"US",
    "sg:address":"202 Cummings Ave NW",
    "sg:city":"Grand Rapids",
    "sg:classifiers":[
        {
            "category":"Social Services",
            "subcategory":"Child Care",
            "type":"Services"
        }
    ],
    "sg:phone":"+1 616 453 2863",
    "sg:postcode":"49534",
    "sg:province":"MI",
    "sg:tags":[
        "day"
    ],
    "wof:name":"Kids Connection",
    "wof:placetype":"venue"
},
  "geometry": {"coordinates":[-85.77125100000001,42.970022],"type":"Point"}
}