{
  "type": "Feature",
  "properties": {
    "iso:country":"US",
    "sg:address":"364 Creyts Rd",
    "sg:city":"Dimondale",
    "sg:classifiers":[
        {
            "category":"Food & Beverages",
            "subcategory":"Groceries & Convenience Stores",
            "type":"Retail Goods"
        }
    ],
    "sg:phone":"+1 517 646 2361",
    "sg:postcode":"48821",
    "sg:province":"MI",
    "wof:name":"Dimondale Express Mart",
    "wof:placetype":"venue"
},
  "geometry": {"coordinates":[-84.642028,42.648158],"type":"Point"}
}