{
  "type": "Feature",
  "properties": {
    "iso:country":"US",
    "sg:address":"2619 N Washington Ave",
    "sg:city":"Saginaw",
    "sg:classifiers":[
        {
            "category":"Autos & Motor Vehicles",
            "subcategory":"Automobile Sales",
            "type":"Retail Goods"
        }
    ],
    "sg:phone":"+1 989 753 4481",
    "sg:postcode":"48607",
    "sg:province":"MI",
    "sg:tags":[
        "truck"
    ],
    "sg:website":"www.dieseltrucksales.net",
    "wof:name":"Diesel Truck Sales Inc",
    "wof:placetype":"venue"
},
  "geometry": {"coordinates":[-83.91036699999999,43.450754],"type":"Point"}
}