{
  "type": "Feature",
  "properties": {
    "iso:country":"US",
    "sg:address":"2241 Hilton Rd Ste 1",
    "sg:city":"Ferndale",
    "sg:classifiers":[
        {
            "category":"Health Services",
            "subcategory":"Doctor",
            "type":"Services"
        }
    ],
    "sg:phone":"+1 248 545 6400",
    "sg:postcode":"48220",
    "sg:province":"MI",
    "sg:tags":[
        "surgeon",
        "oral"
    ],
    "sg:website":"drmartella.com/",
    "wof:name":"Ronald Martella, DDS",
    "wof:placetype":"venue"
},
  "geometry": {"coordinates":[-83.12332499999999,42.466561],"type":"Point"}
}