{
  "type": "Feature",
  "properties": {
    "iso:country":"US",
    "sg:address":"32 N Walnut St",
    "sg:city":"Mount Clemens",
    "sg:classifiers":[
        {
            "category":"Shopping",
            "subcategory":"Jewelry",
            "type":"Retail Goods"
        }
    ],
    "sg:phone":"+1 586 463 9848",
    "sg:postcode":"48043",
    "sg:province":"MI",
    "sg:tags":[
        "mate",
        "mfg"
    ],
    "wof:name":"House of Diamonds",
    "wof:placetype":"venue"
},
  "geometry": {"coordinates":[-82.87882399999999,42.597212],"type":"Point"}
}