{
  "type": "Feature",
  "properties": {
    "iso:country":"US",
    "sg:address":"42730 Hayes Rd",
    "sg:city":"Clinton Twp",
    "sg:classifiers":[
        {
            "category":"Travel",
            "subcategory":"Hotels & Motels",
            "type":"Entertainment"
        }
    ],
    "sg:phone":"+1 586 226 3249",
    "sg:postcode":"48038",
    "sg:province":"MI",
    "sg:tags":[
        "breakfast",
        "accommodation",
        "bed"
    ],
    "wof:name":"B & B Marathon",
    "wof:placetype":"venue"
},
  "geometry": {"coordinates":[-82.97261,42.612144],"type":"Point"}
}