{
  "type": "Feature",
  "properties": {
    "iso:country":"US",
    "sg:address":"327 Tawas St",
    "sg:city":"East Tawas",
    "sg:classifiers":[
        {
            "category":"Government",
            "subcategory":"Office",
            "type":"Public Place"
        }
    ],
    "sg:phone":"+1 989 362 2398",
    "sg:postcode":"48730",
    "sg:province":"MI",
    "sg:tags":[
        "national",
        "security"
    ],
    "wof:name":"Civil Air Patrol Inc",
    "wof:placetype":"venue"
},
  "geometry": {"coordinates":[-83.488962,44.283163],"type":"Point"}
}