{
  "type": "Feature",
  "properties": {
    "iso:country":"US",
    "sg:address":"20205 Boardwalk Blvd",
    "sg:city":"Southfield",
    "sg:classifiers":[
        {
            "category":"Real Estate",
            "subcategory":"Real Estate Agent",
            "type":"Services"
        }
    ],
    "sg:phone":"+1 248 213 4700",
    "sg:postcode":"48075",
    "sg:province":"MI",
    "wof:name":"Park Place",
    "wof:placetype":"venue"
},
  "geometry": {"coordinates":[-83.24298899999999,42.478016],"type":"Point"}
}