{
  "type": "Feature",
  "properties": {
    "iso:country":"US",
    "sg:address":"1141 S Mission St",
    "sg:city":"Mount Pleasant",
    "sg:classifiers":[
        {
            "category":"Personal",
            "subcategory":"Beauty Salon",
            "type":"Services"
        }
    ],
    "sg:phone":"+1 989 773 5989",
    "sg:postcode":"48858",
    "sg:province":"MI",
    "sg:tags":[
        "shop"
    ],
    "wof:name":"Nails & More",
    "wof:placetype":"venue"
},
  "geometry": {"coordinates":[-84.76747,43.592797],"type":"Point"}
}