{
  "type": "Feature",
  "properties": {
    "iso:country":"US",
    "sg:address":"5588 Crystal Rd",
    "sg:city":"Carson City",
    "sg:phone":"+1 989 235 6824",
    "sg:postcode":"48811",
    "sg:province":"MI",
    "sg:tags":[
        "farm"
    ],
    "wof:name":"Ryan John",
    "wof:placetype":"venue"
},
  "geometry": {"coordinates":[-84.915685,43.212149],"type":"Point"}
}