{
  "type": "Feature",
  "properties": {
    "iso:country":"US",
    "sg:address":"637 Ottawa Dr",
    "sg:city":"Troy",
    "sg:classifiers":[
        {
            "category":"Building & Trades",
            "subcategory":"Construction",
            "type":"Services"
        }
    ],
    "sg:phone":"+1 248 879 1045",
    "sg:postcode":"48085",
    "sg:province":"MI",
    "sg:tags":[
        "house"
    ],
    "wof:name":"Sahara Construction Co",
    "wof:placetype":"venue"
},
  "geometry": {"coordinates":[-83.13605,42.610693],"type":"Point"}
}