{
  "type": "Feature",
  "properties": {
    "iso:country":"US",
    "sg:address":"1506 Maguire St",
    "sg:city":"Jackson",
    "sg:classifiers":[
        {
            "category":"Professional",
            "subcategory":"Accounting & Tax Preparation",
            "type":"Services"
        }
    ],
    "sg:phone":"+1 517 784 2687",
    "sg:postcode":"49202",
    "sg:province":"MI",
    "wof:name":"Teegardin John Field Audit",
    "wof:placetype":"venue"
},
  "geometry": {"coordinates":[-84.384434,42.259998],"type":"Point"}
}