{
  "type": "Feature",
  "properties": {
    "iso:country":"US",
    "sg:address":"708 Sherman Ln",
    "sg:city":"Cassopolis",
    "sg:classifiers":[
        {
            "category":"Manufacturing",
            "subcategory":"Building Materials",
            "type":"Manufacturing & Wholesale Goods"
        }
    ],
    "sg:phone":"+1 269 445 4000",
    "sg:postcode":"49031",
    "sg:province":"MI",
    "sg:tags":[
        "cabinet"
    ],
    "wof:name":"Custom Woodworking",
    "wof:placetype":"venue"
},
  "geometry": {"coordinates":[-86.000288,41.905522],"type":"Point"}
}