{
  "type": "Feature",
  "properties": {
    "iso:country":"US",
    "sg:address":"2727 2nd St",
    "sg:city":"Detroit",
    "sg:classifiers":[
        {
            "category":"Education",
            "subcategory":"Special Training",
            "type":"Public Place"
        }
    ],
    "sg:phone":"+1 313 963 2321",
    "sg:postcode":"48201",
    "sg:province":"MI",
    "sg:tags":[
        "on",
        "integrated",
        "science",
        "st",
        "to",
        "hands",
        "teaching",
        "teacher"
    ],
    "wof:name":"Kaykim Labs",
    "wof:placetype":"venue"
},
  "geometry": {"coordinates":[-83.066142,42.34006],"type":"Point"}
}