{
  "type": "Feature",
  "properties": {
    "iso:country":"US",
    "sg:address":"3990 Wilder Rd",
    "sg:city":"Bay City",
    "sg:classifiers":[
        {
            "category":"Restaurant",
            "type":"Food & Drink"
        }
    ],
    "sg:menulink":"http://www.allmenus.com/mi/bay-city/163033-rallys/menu/",
    "sg:phone":"+1 989 686 6877",
    "sg:postcode":"48706",
    "sg:province":"MI",
    "sg:tags":[
        "sandwich",
        "dog",
        "burger",
        "hot",
        "wrap",
        "american"
    ],
    "wof:name":"Rally's",
    "wof:placetype":"venue"
},
  "geometry": {"coordinates":[-83.89470300000001,43.623794],"type":"Point"}
}