{
  "type": "Feature",
  "properties": {
    "iso:country":"US",
    "sg:address":"1120 Deer Creek Trl",
    "sg:city":"Grand Blanc",
    "sg:classifiers":[
        {
            "category":"Professional",
            "subcategory":"Business Services",
            "type":"Services"
        }
    ],
    "sg:phone":"+1 810 655 2223",
    "sg:postcode":"48439",
    "sg:province":"MI",
    "wof:name":"GBA Productions",
    "wof:placetype":"venue"
},
  "geometry": {"coordinates":[-83.693579,42.905241],"type":"Point"}
}