{
  "type": "Feature",
  "properties": {
    "iso:country":"US",
    "sg:address":"1619 Margaret Ave SE",
    "sg:city":"Grand Rapids",
    "sg:classifiers":[
        {
            "category":"Social Services",
            "subcategory":"Child Care",
            "type":"Services"
        }
    ],
    "sg:phone":"+1 616 475 0692",
    "sg:postcode":"49507",
    "sg:province":"MI",
    "sg:tags":[
        "day"
    ],
    "wof:name":"Adventures In Learning Child",
    "wof:placetype":"venue"
},
  "geometry": {"coordinates":[-85.63238200000001,42.932839],"type":"Point"}
}