{
  "type": "Feature",
  "properties": {
    "iso:country":"US",
    "sg:address":"4329 Kalamazoo Ave SE",
    "sg:city":"Grand Rapids",
    "sg:classifiers":[
        {
            "category":"Personal",
            "subcategory":"Barber",
            "type":"Services"
        }
    ],
    "sg:phone":"+1 616 455 7440",
    "sg:postcode":"49508",
    "sg:province":"MI",
    "sg:tags":[
        "shop"
    ],
    "wof:name":"Towne & Country Barbour Shoppe",
    "wof:placetype":"venue"
},
  "geometry": {"coordinates":[-85.62612,42.88509],"type":"Point"}
}