{
  "type": "Feature",
  "properties": {
    "iso:country":"US",
    "sg:address":"19964 Harned St",
    "sg:city":"Detroit",
    "sg:classifiers":[
        {
            "category":"Social Services",
            "subcategory":"Child Care",
            "type":"Services"
        }
    ],
    "sg:phone":"+1 313 368 0416",
    "sg:postcode":"48234",
    "sg:province":"MI",
    "sg:tags":[
        "center",
        "day"
    ],
    "wof:name":"Rosalyn Early Childhood Center",
    "wof:placetype":"venue"
},
  "geometry": {"coordinates":[-83.07379,42.4419],"type":"Point"}
}