{
  "type": "Feature",
  "properties": {
    "iso:country":"US",
    "sg:address":"1987 Alhambra Dr",
    "sg:city":"Ann Arbor",
    "sg:classifiers":[
        {
            "category":"Professional",
            "subcategory":"Management & Consulting",
            "type":"Services"
        }
    ],
    "sg:phone":"+1 734 996 1202",
    "sg:postcode":"48103",
    "sg:province":"MI",
    "wof:name":"John Turck Consulting Group",
    "wof:placetype":"venue"
},
  "geometry": {"coordinates":[-83.770218,42.265015],"type":"Point"}
}