{
  "type": "Feature",
  "properties": {
    "iso:country":"US",
    "sg:address":"621 E Columbia St",
    "sg:city":"Mason",
    "sg:classifiers":[
        {
            "category":"Retail",
            "subcategory":"Repair Shop",
            "type":"Services"
        }
    ],
    "sg:phone":"+1 517 676 2131",
    "sg:postcode":"48854",
    "sg:province":"MI",
    "wof:name":"Yanosky Upholstery",
    "wof:placetype":"venue"
},
  "geometry": {"coordinates":[-84.43455,42.582342],"type":"Point"}
}