{
  "type": "Feature",
  "properties": {
    "iso:country":"US",
    "sg:address":"5912 Parkridge Dr",
    "sg:city":"East China",
    "sg:classifiers":[
        {
            "category":"Building & Trades",
            "subcategory":"Landscaping Services",
            "type":"Services"
        }
    ],
    "sg:phone":"+1 810 765 1190",
    "sg:postcode":"48054",
    "sg:province":"MI",
    "sg:tags":[
        "lawn",
        "maintenance",
        "grounds"
    ],
    "wof:name":"All American Lawn Care",
    "wof:placetype":"venue"
},
  "geometry": {"coordinates":[-82.492498,42.740024],"type":"Point"}
}