{
  "type": "Feature",
  "properties": {
    "iso:country":"US",
    "sg:address":"2315 Beacon Hill Dr",
    "sg:city":"Lansing",
    "sg:classifiers":[
        {
            "category":"Building & Trades",
            "subcategory":"Construction",
            "type":"Services"
        }
    ],
    "sg:phone":"+1 517 323 0277",
    "sg:postcode":"48906",
    "sg:province":"MI",
    "sg:tags":[
        "product",
        "asphalt"
    ],
    "wof:name":"Mr Seal & Mr Asphalt",
    "wof:placetype":"venue"
},
  "geometry": {"coordinates":[-84.592429,42.758689],"type":"Point"}
}