{
  "type": "Feature",
  "properties": {
    "iso:country":"US",
    "sg:address":"35780 Groesbeck Hwy",
    "sg:city":"Clinton Township",
    "sg:classifiers":[
        {
            "category":"Retail",
            "subcategory":"Auto Repair",
            "type":"Services"
        }
    ],
    "sg:phone":"+1 586 790 5553",
    "sg:postcode":"48035",
    "sg:province":"MI",
    "sg:tags":[
        "automotive"
    ],
    "wof:name":"Oil Exchange 10 The",
    "wof:placetype":"venue"
},
  "geometry": {"coordinates":[-82.91693100000001,42.562827],"type":"Point"}
}