{
  "type": "Feature",
  "properties": {
    "iso:country":"US",
    "sg:address":"8862 US Hwy 31",
    "sg:city":"Beulah",
    "sg:classifiers":[
        {
            "category":"Manufacturing",
            "subcategory":"Metals",
            "type":"Manufacturing & Wholesale Goods"
        }
    ],
    "sg:phone":"+1 231 882 4374",
    "sg:postcode":"49617",
    "sg:province":"MI",
    "sg:tags":[
        "extruded",
        "product",
        "aluminum"
    ],
    "wof:name":"B & D Mfg",
    "wof:placetype":"venue"
},
  "geometry": {"coordinates":[-86.048868,44.66681],"type":"Point"}
}