{
  "type": "Feature",
  "properties": {
    "iso:country":"US",
    "sg:address":"2360 Edwin St",
    "sg:city":"Detroit",
    "sg:classifiers":[
        {
            "category":"Food & Beverages",
            "subcategory":"Groceries & Convenience Stores",
            "type":"Retail Goods"
        }
    ],
    "sg:phone":"+1 313 873 2822",
    "sg:postcode":"48212",
    "sg:province":"MI",
    "wof:name":"Bangla Town Grocery Store",
    "wof:placetype":"venue"
},
  "geometry": {"coordinates":[-83.06143299999999,42.394832],"type":"Point"}
}