{
  "type": "Feature",
  "properties": {
    "iso:country":"US",
    "sg:address":"6799 Wing Lake Rd",
    "sg:city":"Bloomfield Hills",
    "sg:classifiers":[
        {
            "category":"Health Services",
            "subcategory":"Doctor",
            "type":"Services"
        }
    ],
    "sg:phone":"+1 248 538 9979",
    "sg:postcode":"48301",
    "sg:province":"MI",
    "sg:tags":[
        "medical"
    ],
    "wof:name":"Lin John Quan MD PC",
    "wof:placetype":"venue"
},
  "geometry": {"coordinates":[-83.296622,42.539074],"type":"Point"}
}