{
  "type": "Feature",
  "properties": {
    "iso:country":"US",
    "sg:address":"224 N 4th St",
    "sg:city":"Niles",
    "sg:classifiers":[
        {
            "category":"Professional",
            "subcategory":"Business Services",
            "type":"Services"
        }
    ],
    "sg:phone":"+1 269 683 8200",
    "sg:postcode":"49120",
    "sg:province":"MI",
    "wof:name":"Clover Assoc Inc",
    "wof:placetype":"venue"
},
  "geometry": {"coordinates":[-86.254942,41.830148],"type":"Point"}
}