{
  "type": "Feature",
  "properties": {
    "iso:country":"US",
    "sg:address":"3375 Dellar Rd",
    "sg:city":"Harrisville",
    "sg:classifiers":[
        {
            "category":"Government",
            "subcategory":"Office",
            "type":"Public Place"
        }
    ],
    "sg:phone":"+1 989 724 5603",
    "sg:postcode":"48740",
    "sg:province":"MI",
    "sg:tags":[
        "development"
    ],
    "wof:name":"Harrisville Township Zoning",
    "wof:placetype":"venue"
},
  "geometry": {"coordinates":[-83.380318,44.620258],"type":"Point"}
}