{
  "type": "Feature",
  "properties": {
    "iso:country":"US",
    "sg:address":"505 Cleveland Ave",
    "sg:city":"Owosso",
    "sg:classifiers":[
        {
            "category":"Social Services",
            "subcategory":"Child Care",
            "type":"Services"
        }
    ],
    "sg:phone":"+1 989 723 5167",
    "sg:postcode":"48867",
    "sg:province":"MI",
    "sg:tags":[
        "day"
    ],
    "wof:name":"Simpsons Floral Greenhouse",
    "wof:placetype":"venue"
},
  "geometry": {"coordinates":[-84.19888400000001,43.00455],"type":"Point"}
}