{
  "type": "Feature",
  "properties": {
    "iso:country":"US",
    "sg:address":"24273 Middlebelt Rd",
    "sg:city":"Farmington",
    "sg:classifiers":[
        {
            "category":"Fast Food",
            "type":"Food & Drink"
        },
        {
            "category":"Restaurant",
            "type":"Food & Drink"
        }
    ],
    "sg:phone":"+1 248 987 4736",
    "sg:postcode":"48336",
    "sg:province":"MI",
    "sg:tags":[
        "burger",
        "indian",
        "pizza"
    ],
    "wof:name":"RBC Pizza and Chicken",
    "wof:placetype":"venue"
},
  "geometry": {"coordinates":[-83.33820900000001,42.471482],"type":"Point"}
}