{
  "type": "Feature",
  "properties": {
    "iso:country":"US",
    "sg:address":"7820 Hailey Ct SE",
    "sg:city":"Caledonia",
    "sg:classifiers":[
        {
            "category":"Building & Trades",
            "subcategory":"Construction",
            "type":"Services"
        }
    ],
    "sg:phone":"+1 616 891 8544",
    "sg:postcode":"49316",
    "sg:province":"MI",
    "sg:tags":[
        "masonry",
        "contractor"
    ],
    "wof:name":"Saladino Masonry LLC",
    "wof:placetype":"venue"
},
  "geometry": {"coordinates":[-85.47153,42.80972],"type":"Point"}
}