{
  "type": "Feature",
  "properties": {
    "iso:country":"US",
    "sg:address":"7424 W US Hwy 10",
    "sg:city":"Branch",
    "sg:classifiers":[
        {
            "category":"Travel",
            "subcategory":"Hotels & Motels",
            "type":"Entertainment"
        }
    ],
    "sg:phone":"+1 231 757 2735",
    "sg:postcode":"49402",
    "sg:province":"MI",
    "sg:tags":[
        "resort"
    ],
    "wof:name":"All Seasons Resort",
    "wof:placetype":"venue"
},
  "geometry": {"coordinates":[-86.014996,43.945243],"type":"Point"}
}