{
  "type": "Feature",
  "properties": {
    "iso:country":"US",
    "sg:address":"12058 Chandler Dr",
    "sg:city":"Plymouth",
    "sg:classifiers":[
        {
            "category":"Professional",
            "type":"Services"
        }
    ],
    "sg:phone":"+1 734 459 9359",
    "sg:postcode":"48170",
    "sg:province":"MI",
    "wof:name":"Marc Gattoni Services Inc",
    "wof:placetype":"venue"
},
  "geometry": {"coordinates":[-83.54336499999999,42.366708],"type":"Point"}
}