{
  "type": "Feature",
  "properties": {
    "iso:country":"US",
    "sg:address":"7830 Junction Rd",
    "sg:city":"Frankenmuth",
    "sg:classifiers":[
        {
            "category":"Building & Trades",
            "subcategory":"Landscaping Services",
            "type":"Services"
        }
    ],
    "sg:phone":"+1 989 652 6052",
    "sg:postcode":"48734",
    "sg:province":"MI",
    "wof:name":"Proscape Prof Ldscpg Contra",
    "wof:placetype":"venue"
},
  "geometry": {"coordinates":[-83.806732,43.335686],"type":"Point"}
}