{
  "type": "Feature",
  "properties": {
    "iso:country":"US",
    "sg:address":"22 S Main St",
    "sg:city":"Clawson",
    "sg:classifiers":[
        {
            "category":"Place Of Worship",
            "subcategory":"Temple",
            "type":"Public Place"
        },
        {
            "category":"Arena",
            "subcategory":"Sports Club",
            "type":"Entertainment"
        }
    ],
    "sg:phone":"+1 248 288 5894",
    "sg:postcode":"48017",
    "sg:province":"MI",
    "sg:tags":[
        "martial art",
        "buddhist"
    ],
    "wof:name":"Shitokan International",
    "wof:placetype":"venue"
},
  "geometry": {"coordinates":[-83.14630099999999,42.5331],"type":"Point"}
}