{
  "type": "Feature",
  "properties": {
    "iso:country":"US",
    "sg:address":"12400 W Herbison Rd",
    "sg:city":"Eagle",
    "sg:classifiers":[
        {
            "category":"Freight",
            "type":"Transportation"
        }
    ],
    "sg:phone":"+1 517 626 6331",
    "sg:postcode":"48822",
    "sg:province":"MI",
    "sg:tags":[
        "operator",
        "local",
        "trucking"
    ],
    "wof:name":"Gregory J Thom Trucking",
    "wof:placetype":"venue"
},
  "geometry": {"coordinates":[-84.762001,42.829911],"type":"Point"}
}