{
  "type": "Feature",
  "properties": {
    "iso:country":"US",
    "sg:address":"2894 Territorial Rd",
    "sg:city":"Benton Harbor",
    "sg:classifiers":[
        {
            "category":"Farming",
            "subcategory":"Farm",
            "type":"Manufacturing & Wholesale Goods"
        }
    ],
    "sg:phone":"+1 269 926 9553",
    "sg:postcode":"49022",
    "sg:province":"MI",
    "sg:tags":[
        "crop",
        "general"
    ],
    "wof:name":"Rogers Farm",
    "wof:placetype":"venue"
},
  "geometry": {"coordinates":[-86.38991900000001,42.124545],"type":"Point"}
}