{
  "type": "Feature",
  "properties": {
    "iso:country":"US",
    "sg:address":"43955 N Groesbeck Hwy",
    "sg:city":"Clinton Township",
    "sg:classifiers":[
        {
            "category":"Retail",
            "subcategory":"Auto Repair",
            "type":"Services"
        }
    ],
    "sg:phone":"+1 586 463 7800",
    "sg:postcode":"48036",
    "sg:province":"MI",
    "wof:name":"Northern Spring",
    "wof:placetype":"venue"
},
  "geometry": {"coordinates":[-82.881699,42.6199],"type":"Point"}
}