{
  "type": "Feature",
  "properties": {
    "iso:country":"US",
    "sg:address":"527 Greenwich St",
    "sg:city":"Howell",
    "sg:classifiers":[
        {
            "category":"Real Estate",
            "subcategory":"Real Estate Operator",
            "type":"Services"
        }
    ],
    "sg:phone":"+1 517 548 3733",
    "sg:postcode":"48843",
    "sg:province":"MI",
    "sg:tags":[
        "building",
        "apartment"
    ],
    "wof:name":"Quail Creek Apartments",
    "wof:placetype":"venue"
},
  "geometry": {"coordinates":[-83.93518,42.612918],"type":"Point"}
}