{
  "type": "Feature",
  "properties": {
    "iso:country":"US",
    "sg:address":"2690 Crooks Rd",
    "sg:city":"Troy",
    "sg:classifiers":[
        {
            "category":"Personal",
            "type":"Services"
        }
    ],
    "sg:phone":"+1 248 244 2213",
    "sg:postcode":"48084",
    "sg:province":"MI",
    "sg:tags":[
        "consultant",
        "program",
        "health",
        "fitness"
    ],
    "wof:name":"Nutrition Therapy",
    "wof:placetype":"venue"
},
  "geometry": {"coordinates":[-83.166967,42.557394],"type":"Point"}
}