{
  "type": "Feature",
  "properties": {
    "iso:country":"US",
    "sg:address":"101 Michigan Ave",
    "sg:city":"Charlevoix",
    "sg:classifiers":[
        {
            "category":"Real Estate",
            "subcategory":"Real Estate Agent",
            "type":"Services"
        },
        {
            "category":"Real Estate",
            "subcategory":"Real Estate Operator",
            "type":"Services"
        }
    ],
    "sg:phone":"+1 231 547 0055",
    "sg:postcode":"49720",
    "sg:province":"MI",
    "sg:tags":[
        "operation",
        "condominium"
    ],
    "wof:name":"Pointes North Inn Inc",
    "wof:placetype":"venue"
},
  "geometry": {"coordinates":[-85.25876100000001,45.319469],"type":"Point"}
}