{
  "type": "Feature",
  "properties": {
    "iso:country":"US",
    "sg:address":"526 N Lake St",
    "sg:city":"Boyne City",
    "sg:classifiers":[
        {
            "category":"Building & Trades",
            "subcategory":"Construction",
            "type":"Services"
        }
    ],
    "sg:phone":"+1 231 582 0017",
    "sg:postcode":"49712",
    "sg:province":"MI",
    "sg:tags":[
        "home",
        "improvement"
    ],
    "wof:name":"Total Home Repair",
    "wof:placetype":"venue"
},
  "geometry": {"coordinates":[-85.015884,45.221042],"type":"Point"}
}