{
  "type": "Feature",
  "properties": {
    "iso:country":"US",
    "sg:address":"26285 Novi Rd",
    "sg:city":"Novi",
    "sg:classifiers":[
        {
            "category":"Home & Garden",
            "subcategory":"Building Materials",
            "type":"Retail Goods"
        }
    ],
    "sg:phone":"+1 248 449 5295",
    "sg:postcode":"48375",
    "sg:province":"MI",
    "sg:tags":[
        "windows"
    ],
    "wof:name":"Blinds To Go",
    "wof:placetype":"venue"
},
  "geometry": {"coordinates":[-83.475604,42.482637],"type":"Point"}
}