{
  "type": "Feature",
  "properties": {
    "iso:country":"US",
    "sg:address":"3270 Rodesiler Hwy",
    "sg:city":"Deerfield",
    "sg:classifiers":[
        {
            "category":"Shopping",
            "subcategory":"Luggage & Leather Goods",
            "type":"Retail Goods"
        }
    ],
    "sg:phone":"+1 517 447 3925",
    "sg:postcode":"49238",
    "sg:province":"MI",
    "wof:name":"Sher's Leather Emporium",
    "wof:placetype":"venue"
},
  "geometry": {"coordinates":[-83.788282,41.872279],"type":"Point"}
}