{
  "type": "Feature",
  "properties": {
    "iso:country":"US",
    "sg:address":"609 Larkspur Ave",
    "sg:city":"Portage",
    "sg:classifiers":[
        {
            "category":"Shopping",
            "subcategory":"Catalog Store",
            "type":"Retail Goods"
        }
    ],
    "sg:phone":"+1 269 327 0427",
    "sg:postcode":"49002",
    "sg:province":"MI",
    "sg:tags":[
        "mail",
        "order",
        "online"
    ],
    "wof:name":"Stanley Home Products",
    "wof:placetype":"venue"
},
  "geometry": {"coordinates":[-85.58300800000001,42.195099],"type":"Point"}
}