{
  "type": "Feature",
  "properties": {
    "iso:country":"US",
    "sg:address":"3822 Baywood Dr SE",
    "sg:city":"Grand Rapids",
    "sg:classifiers":[
        {
            "category":"Sports & Exercise",
            "subcategory":"Gym",
            "type":"Entertainment"
        }
    ],
    "sg:phone":"+1 616 988 9393",
    "sg:postcode":"49546",
    "sg:province":"MI",
    "sg:tags":[
        "club",
        "health",
        "studio",
        "gymnasium"
    ],
    "wof:name":"Contours Express Enterprises",
    "wof:placetype":"venue"
},
  "geometry": {"coordinates":[-85.564781,42.957793],"type":"Point"}
}