{
  "type": "Feature",
  "properties": {
    "iso:country":"US",
    "sg:address":"107 W State St",
    "sg:city":"Mancelona",
    "sg:classifiers":[
        {
            "category":"Shopping",
            "subcategory":"Bicycles & Sporting Goods",
            "type":"Retail Goods"
        }
    ],
    "sg:phone":"+1 231 587 0691",
    "sg:postcode":"49659",
    "sg:province":"MI",
    "sg:tags":[
        "saddlery",
        "harness"
    ],
    "wof:name":"Stilson Saddle & Tack Shop",
    "wof:placetype":"venue"
},
  "geometry": {"coordinates":[-85.06227800000001,44.902334],"type":"Point"}
}