{
  "type": "Feature",
  "properties": {
    "iso:country":"US",
    "sg:address":"292 Baldwin St",
    "sg:city":"Lake City",
    "sg:classifiers":[
        {
            "category":"Professional",
            "subcategory":"Business Services",
            "type":"Services"
        }
    ],
    "sg:phone":"+1 231 775 4300",
    "sg:postcode":"49651",
    "sg:province":"MI",
    "wof:name":"Spencer Enterprises",
    "wof:placetype":"venue"
},
  "geometry": {"coordinates":[-85.299661,44.335403],"type":"Point"}
}