{
  "type": "Feature",
  "properties": {
    "iso:country":"US",
    "sg:address":"2101 Haggerty Rd",
    "sg:city":"Canton",
    "sg:classifiers":[
        {
            "category":"Retail",
            "subcategory":"Auto Rental",
            "type":"Services"
        }
    ],
    "sg:phone":"+1 734 981 0239",
    "sg:postcode":"48187",
    "sg:province":"MI",
    "sg:tags":[
        "truck"
    ],
    "wof:name":"Ryder",
    "wof:placetype":"venue"
},
  "geometry": {"coordinates":[-83.449011,42.322056],"type":"Point"}
}