{
  "type": "Feature",
  "properties": {
    "iso:country":"US",
    "sg:address":"3257 Linden Rd",
    "sg:city":"Flint",
    "sg:classifiers":[
        {
            "category":"Shopping",
            "subcategory":"Gifts & Souvenirs",
            "type":"Retail Goods"
        }
    ],
    "sg:phone":"+1 810 230 2675",
    "sg:postcode":"48507",
    "sg:province":"MI",
    "sg:tags":[
        "engraving",
        "custom"
    ],
    "wof:name":"Things Remembered",
    "wof:placetype":"venue"
},
  "geometry": {"coordinates":[-83.772093,42.983618],"type":"Point"}
}