{
  "type": "Feature",
  "properties": {
    "iso:country":"US",
    "sg:address":"4148 Baldwin Rd",
    "sg:city":"Auburn Hills",
    "sg:classifiers":[
        {
            "category":"Professional",
            "subcategory":"Lawyer & Legal Services",
            "type":"Services"
        }
    ],
    "sg:phone":"+1 248 745 9300",
    "sg:postcode":"48326",
    "sg:province":"MI",
    "wof:name":"Colburn Colburn & Associates",
    "wof:placetype":"venue"
},
  "geometry": {"coordinates":[-83.306752,42.701213],"type":"Point"}
}