{
  "type": "Feature",
  "properties": {
    "iso:country":"US",
    "sg:address":"1856 Ruddiman Dr",
    "sg:city":"Muskegon",
    "sg:classifiers":[
        {
            "category":"Restaurant",
            "type":"Food & Drink"
        }
    ],
    "sg:phone":"+1 231 719 5555",
    "sg:postcode":"49445",
    "sg:province":"MI",
    "wof:name":"Greek Tony's",
    "wof:placetype":"venue"
},
  "geometry": {"coordinates":[-86.26168199999999,43.26066],"type":"Point"}
}