{
  "type": "Feature",
  "properties": {
    "iso:country":"US",
    "sg:address":"2655 Pinetree Dr",
    "sg:city":"Flint",
    "sg:classifiers":[
        {
            "category":"Professional",
            "subcategory":"Management & Consulting",
            "type":"Services"
        }
    ],
    "sg:phone":"+1 810 742 0073",
    "sg:postcode":"48507",
    "sg:province":"MI",
    "sg:tags":[
        "retail",
        "direct",
        "sales"
    ],
    "wof:name":"Maxis 2000",
    "wof:placetype":"venue"
},
  "geometry": {"coordinates":[-83.658474,42.99818],"type":"Point"}
}