{
  "type": "Feature",
  "properties": {
    "iso:country":"US",
    "sg:address":"1950 Crystal Lake Ct W",
    "sg:city":"Shelby Twp",
    "sg:classifiers":[
        {
            "category":"Banks & Credit Unions",
            "subcategory":"Investment Brokerage",
            "type":"Services"
        }
    ],
    "sg:phone":"+1 586 739 1222",
    "sg:postcode":"48316",
    "sg:province":"MI",
    "sg:tags":[
        "security"
    ],
    "wof:name":"ICMA",
    "wof:placetype":"venue"
},
  "geometry": {"coordinates":[-83.09299300000001,42.676321],"type":"Point"}
}