{
  "type": "Feature",
  "properties": {
    "iso:country":"US",
    "sg:address":"859 N Telegraph Rd",
    "sg:city":"Monroe",
    "sg:classifiers":[
        {
            "category":"Shopping",
            "type":"Retail Goods"
        }
    ],
    "sg:phone":"+1 734 384 9888",
    "sg:postcode":"48162",
    "sg:province":"MI",
    "sg:tags":[
        "pet",
        "food",
        "supply"
    ],
    "sg:website":"www.royalpets.com",
    "wof:name":"Pet Supplies Plus",
    "wof:placetype":"venue"
},
  "geometry": {"coordinates":[-83.40888200000001,41.934285],"type":"Point"}
}