{
  "type": "Feature",
  "properties": {
    "iso:country":"US",
    "sg:address":"340 W Maplehurst Ave",
    "sg:city":"Ferndale",
    "sg:classifiers":[
        {
            "category":"Home & Garden",
            "subcategory":"Home Furnishings",
            "type":"Retail Goods"
        }
    ],
    "sg:phone":"+1 248 548 3993",
    "sg:postcode":"48220",
    "sg:province":"MI",
    "sg:tags":[
        "pillow"
    ],
    "wof:name":"Rinz-L-O Pillow Co",
    "wof:placetype":"venue"
},
  "geometry": {"coordinates":[-83.14021,42.46535],"type":"Point"}
}