{
  "type": "Feature",
  "properties": {
    "iso:country":"US",
    "sg:address":"19803 E 9 Mile Rd",
    "sg:city":"St Clair Shores",
    "sg:classifiers":[
        {
            "category":"Wholesale",
            "subcategory":"Machinery & Supplies",
            "type":"Manufacturing & Wholesale Goods"
        }
    ],
    "sg:phone":"+1 586 775 7990",
    "sg:postcode":"48080",
    "sg:province":"MI",
    "sg:tags":[
        "equipment",
        "laminating"
    ],
    "sg:website":"www.lamseal.com",
    "wof:name":"Astoria Laminations",
    "wof:placetype":"venue"
},
  "geometry": {"coordinates":[-82.917147,42.465839],"type":"Point"}
}