{
  "type": "Feature",
  "properties": {
    "iso:country":"US",
    "sg:address":"229 Highland Ave",
    "sg:city":"Clawson",
    "sg:classifiers":[
        {
            "category":"Professional",
            "subcategory":"Secretarial Services",
            "type":"Services"
        }
    ],
    "sg:phone":"+1 248 288 6337",
    "sg:postcode":"48017",
    "sg:province":"MI",
    "sg:tags":[
        "reporting",
        "court"
    ],
    "wof:name":"Typing & Graphic Concepts Inc",
    "wof:placetype":"venue"
},
  "geometry": {"coordinates":[-83.152783,42.539372],"type":"Point"}
}