{
  "type": "Feature",
  "properties": {
    "iso:country":"US",
    "sg:address":"3870 Division Ave",
    "sg:city":"Wayland",
    "sg:classifiers":[
        {
            "category":"Banks & Credit Unions",
            "subcategory":"Bank",
            "type":"Services"
        }
    ],
    "sg:phone":"+1 269 792 9710",
    "sg:postcode":"49348",
    "sg:province":"MI",
    "sg:tags":[
        "loan",
        "real estate"
    ],
    "wof:name":"Sunset Mortgage",
    "wof:placetype":"venue"
},
  "geometry": {"coordinates":[-85.653626,42.698534],"type":"Point"}
}