{
  "type": "Feature",
  "properties": {
    "iso:country":"US",
    "sg:address":"10688 Liske Rd",
    "sg:city":"Herron",
    "sg:classifiers":[
        {
            "category":"Professional",
            "subcategory":"Art Services",
            "type":"Services"
        }
    ],
    "sg:phone":"+1 989 727 2499",
    "sg:postcode":"49744",
    "sg:province":"MI",
    "sg:tags":[
        "commercial",
        "design"
    ],
    "wof:name":"B D Graphic Design",
    "wof:placetype":"venue"
},
  "geometry": {"coordinates":[-83.66436,44.953144],"type":"Point"}
}