{
  "type": "Feature",
  "properties": {
    "iso:country":"US",
    "sg:address":"3887 S Huron Rd",
    "sg:city":"Standish",
    "sg:classifiers":[
        {
            "category":"Banks & Credit Unions",
            "subcategory":"Bank",
            "type":"Services"
        }
    ],
    "sg:phone":"+1 989 846 9750",
    "sg:postcode":"48658",
    "sg:province":"MI",
    "sg:tags":[
        "personal",
        "institution"
    ],
    "sg:website":"www.sunrisefamilycu.org",
    "wof:name":"Sunrise Family Credit Union",
    "wof:placetype":"venue"
},
  "geometry": {"coordinates":[-83.95902599999999,43.964786],"type":"Point"}
}