{
  "type": "Feature",
  "properties": {
    "iso:country":"US",
    "sg:address":"1504 Yorkshire Dr",
    "sg:city":"Howell",
    "sg:classifiers":[
        {
            "category":"Real Estate",
            "subcategory":"Real Estate Operator",
            "type":"Services"
        }
    ],
    "sg:phone":"+1 517 546 5900",
    "sg:postcode":"48843",
    "sg:province":"MI",
    "sg:tags":[
        "apartment",
        "complex"
    ],
    "wof:name":"Yorkshire Place Apartments",
    "wof:placetype":"venue"
},
  "geometry": {"coordinates":[-83.955895,42.61631],"type":"Point"}
}