{
  "type": "Feature",
  "properties": {
    "iso:country":"US",
    "sg:address":"6673 Pine Ridge Ct",
    "sg:city":"Jenison",
    "sg:classifiers":[
        {
            "category":"Professional",
            "subcategory":"Employment Agencies",
            "type":"Services"
        }
    ],
    "sg:phone":"+1 616 662 2167",
    "sg:postcode":"49428",
    "sg:province":"MI",
    "sg:tags":[
        "truck",
        "driver"
    ],
    "wof:name":"ALS Inc",
    "wof:placetype":"venue"
},
  "geometry": {"coordinates":[-85.830017,42.890383],"type":"Point"}
}