{
  "type": "Feature",
  "properties": {
    "iso:country":"US",
    "sg:address":"1050 Allouez Dr",
    "sg:city":"Niles",
    "sg:classifiers":[
        {
            "category":"Professional",
            "subcategory":"Management & Consulting",
            "type":"Services"
        }
    ],
    "sg:phone":"+1 269 683 7522",
    "sg:postcode":"49120",
    "sg:province":"MI",
    "wof:name":"Apex Technical Training",
    "wof:placetype":"venue"
},
  "geometry": {"coordinates":[-86.27272000000001,41.79694],"type":"Point"}
}