{
  "type": "Feature",
  "properties": {
    "iso:country":"US",
    "sg:address":"2064 Baldwin St",
    "sg:city":"Jenison",
    "sg:classifiers":[
        {
            "category":"Health Services",
            "subcategory":"Doctor",
            "type":"Services"
        }
    ],
    "sg:phone":"+1 616 457 5320",
    "sg:postcode":"49428",
    "sg:province":"MI",
    "wof:name":"McIntyre Jack Douglas DDS",
    "wof:placetype":"venue"
},
  "geometry": {"coordinates":[-85.834001,42.907097],"type":"Point"}
}