{
  "type": "Feature",
  "properties": {
    "iso:country":"US",
    "sg:address":"344 Lafayette St",
    "sg:city":"Manchester",
    "sg:classifiers":[
        {
            "category":"Retail",
            "subcategory":"Auto Repair",
            "type":"Services"
        }
    ],
    "sg:phone":"+1 734 428 7454",
    "sg:postcode":"48158",
    "sg:province":"MI",
    "sg:tags":[
        "automotive"
    ],
    "wof:name":"Solid State Elcrs",
    "wof:placetype":"venue"
},
  "geometry": {"coordinates":[-84.04337700000001,42.154323],"type":"Point"}
}