{
  "type": "Feature",
  "properties": {
    "iso:country":"US",
    "sg:address":"23995 Greater Mack Ave",
    "sg:city":"St Clair Shores",
    "sg:classifiers":[
        {
            "category":"Health Services",
            "subcategory":"Doctor",
            "type":"Services"
        }
    ],
    "sg:phone":"+1 586 775 1040",
    "sg:postcode":"48080",
    "sg:province":"MI",
    "sg:tags":[
        "dentist"
    ],
    "wof:name":"Zouhrob & Roney",
    "wof:placetype":"venue"
},
  "geometry": {"coordinates":[-82.896536,42.469151],"type":"Point"}
}