{
  "type": "Feature",
  "properties": {
    "iso:country":"US",
    "sg:address":"2623 Raymond Ave SE",
    "sg:city":"Grand Rapids",
    "sg:classifiers":[
        {
            "category":"Professional",
            "subcategory":"Business Services",
            "type":"Services"
        }
    ],
    "sg:phone":"+1 616 245 9216",
    "sg:postcode":"49507",
    "sg:province":"MI",
    "sg:tags":[
        "notary",
        "public"
    ],
    "wof:name":"Kristin Clark",
    "wof:placetype":"venue"
},
  "geometry": {"coordinates":[-85.63947400000001,42.916052],"type":"Point"}
}