{
  "type": "Feature",
  "properties": {
    "iso:country":"US",
    "sg:address":"951 Brown Rd",
    "sg:city":"Lake Orion",
    "sg:classifiers":[
        {
            "category":"Professional",
            "subcategory":"Business Services",
            "type":"Services"
        },
        {
            "category":"Manufacturing",
            "subcategory":"Printing",
            "type":"Manufacturing & Wholesale Goods"
        }
    ],
    "sg:phone":"+1 248 391 8377",
    "sg:postcode":"48359",
    "sg:province":"MI",
    "sg:tags":[
        "publishing"
    ],
    "sg:website":"www.theexplorationcompany.com",
    "wof:name":"Exploration Co The",
    "wof:placetype":"venue"
},
  "geometry": {"coordinates":[-83.26616799999999,42.70848],"type":"Point"}
}