{
  "type": "Feature",
  "properties": {
    "iso:country":"US",
    "sg:address":"22201 W Outer Dr",
    "sg:city":"Dearborn",
    "sg:classifiers":[
        {
            "category":"Real Estate",
            "subcategory":"Real Estate Agent",
            "type":"Services"
        }
    ],
    "sg:phone":"+1 313 565 7157",
    "sg:postcode":"48124",
    "sg:province":"MI",
    "wof:name":"Mariann Jafar",
    "wof:placetype":"venue"
},
  "geometry": {"coordinates":[-83.23013400000001,42.283857],"type":"Point"}
}