{
  "type": "Feature",
  "properties": {
    "iso:country":"US",
    "sg:address":"29218 Barrington St",
    "sg:city":"Inkster",
    "sg:classifiers":[
        {
            "category":"Professional",
            "subcategory":"Business Services",
            "type":"Services"
        }
    ],
    "sg:phone":"+1 734 641 8971",
    "sg:postcode":"48141",
    "sg:province":"MI",
    "sg:tags":[
        "fashion",
        "merchandising"
    ],
    "wof:name":"Briana Christen",
    "wof:placetype":"venue"
},
  "geometry": {"coordinates":[-83.329064,42.298529],"type":"Point"}
}