{
  "type": "Feature",
  "properties": {
    "iso:country":"US",
    "sg:address":"7343 Steeplechase Dr",
    "sg:city":"Saline",
    "sg:classifiers":[
        {
            "category":"Health Services",
            "subcategory":"Medical Lab",
            "type":"Services"
        }
    ],
    "sg:phone":"+1 734 429 8145",
    "sg:postcode":"48176",
    "sg:province":"MI",
    "sg:tags":[
        "laboratory"
    ],
    "wof:name":"Clinical Research Consulting",
    "wof:placetype":"venue"
},
  "geometry": {"coordinates":[-83.72185500000001,42.180189],"type":"Point"}
}