{
  "type": "Feature",
  "properties": {
    "iso:country":"US",
    "sg:address":"4023 Red Arrow Hwy",
    "sg:city":"St Joseph",
    "sg:classifiers":[
        {
            "category":"Restaurant",
            "type":"Food & Drink"
        }
    ],
    "sg:phone":"+1 269 429 2600",
    "sg:postcode":"49085",
    "sg:province":"MI",
    "wof:name":"Mark III Express",
    "wof:placetype":"venue"
},
  "geometry": {"coordinates":[-86.514082,42.043949],"type":"Point"}
}