{
  "type": "Feature",
  "properties": {
    "iso:country":"US",
    "sg:address":"930 Fleming Ave",
    "sg:city":"Jackson",
    "sg:classifiers":[
        {
            "category":"Social Services",
            "subcategory":"Adult Care",
            "type":"Services"
        },
        {
            "category":"Government",
            "subcategory":"Office",
            "type":"Public Place"
        }
    ],
    "sg:phone":"+1 517 788 4460",
    "sg:postcode":"49202",
    "sg:province":"MI",
    "sg:tags":[
        "residential",
        "center",
        "detention",
        "treatment"
    ],
    "sg:website":"www.jacksoncounty.com",
    "wof:name":"Jackson County Youth Center",
    "wof:placetype":"venue"
},
  "geometry": {"coordinates":[-84.386899,42.263354],"type":"Point"}
}