{
  "type": "Feature",
  "properties": {
    "iso:country":"US",
    "sg:address":"7935 Main St",
    "sg:city":"Birch Run",
    "sg:classifiers":[
        {
            "category":"Food & Beverages",
            "subcategory":"Groceries & Convenience Stores",
            "type":"Retail Goods"
        }
    ],
    "sg:phone":"+1 989 624 5432",
    "sg:postcode":"48415",
    "sg:province":"MI",
    "sg:tags":[
        "grocer"
    ],
    "wof:name":"Don's Foodland",
    "wof:placetype":"venue"
},
  "geometry": {"coordinates":[-83.795451,43.25021],"type":"Point"}
}