{
  "type": "Feature",
  "properties": {
    "iso:country":"US",
    "sg:address":"31700 Smith Rd",
    "sg:city":"Romulus",
    "sg:classifiers":[
        {
            "category":"Travel",
            "subcategory":"Hotels & Motels",
            "type":"Entertainment"
        }
    ],
    "sg:phone":"+1 734 595 0033",
    "sg:postcode":"48174",
    "sg:province":"MI",
    "wof:name":"Hampton Inn & Suites",
    "wof:placetype":"venue"
},
  "geometry": {"coordinates":[-83.35138600000001,42.245946],"type":"Point"}
}