{
  "type": "Feature",
  "properties": {
    "iso:country":"US",
    "sg:address":"1815 Maplelawn Dr",
    "sg:city":"Troy",
    "sg:classifiers":[
        {
            "category":"Autos & Motor Vehicles",
            "subcategory":"Automobile Sales",
            "type":"Retail Goods"
        }
    ],
    "sg:phone":"+1 248 643 6900",
    "sg:postcode":"48084",
    "sg:province":"MI",
    "sg:tags":[
        "car"
    ],
    "wof:name":"Falvey of Troy",
    "wof:placetype":"venue"
},
  "geometry": {"coordinates":[-83.174599,42.5522],"type":"Point"}
}