{
  "type": "Feature",
  "properties": {
    "iso:country":"US",
    "sg:address":"3460 Mann Rd",
    "sg:city":"Clarkston",
    "sg:classifiers":[
        {
            "category":"Building & Trades",
            "subcategory":"Construction",
            "type":"Services"
        }
    ],
    "sg:phone":"+1 248 673 2170",
    "sg:postcode":"48346",
    "sg:province":"MI",
    "sg:tags":[
        "home",
        "builder"
    ],
    "wof:name":"Cote Homes Inc",
    "wof:placetype":"venue"
},
  "geometry": {"coordinates":[-83.358566,42.703283],"type":"Point"}
}