{
  "type": "Feature",
  "properties": {
    "iso:country":"US",
    "sg:address":"437 Briar Ln NE",
    "sg:city":"Grand Rapids",
    "sg:classifiers":[
        {
            "category":"Professional",
            "subcategory":"Management & Consulting",
            "type":"Services"
        }
    ],
    "sg:phone":"+1 616 458 3312",
    "sg:postcode":"49503",
    "sg:province":"MI",
    "wof:name":"Major Link Ltd Inc",
    "wof:placetype":"venue"
},
  "geometry": {"coordinates":[-85.620771,42.972349],"type":"Point"}
}