{
  "type": "Feature",
  "properties": {
    "iso:country":"US",
    "sg:address":"9505 Crawford Rd",
    "sg:city":"Columbus",
    "sg:classifiers":[
        {
            "category":"Social Services",
            "subcategory":"Adult Care",
            "type":"Services"
        }
    ],
    "sg:phone":"+1 586 727 7322",
    "sg:postcode":"48063",
    "sg:province":"MI",
    "sg:tags":[
        "home",
        "group"
    ],
    "wof:name":"Impact Crawford Road Home",
    "wof:placetype":"venue"
},
  "geometry": {"coordinates":[-82.689775,42.856399],"type":"Point"}
}