{
  "type": "Feature",
  "properties": {
    "iso:country":"US",
    "sg:address":"2350 Rochester Ct",
    "sg:city":"Troy",
    "sg:classifiers":[
        {
            "category":"Arts & Performance",
            "subcategory":"Theater",
            "type":"Entertainment"
        }
    ],
    "sg:phone":"+1 248 740 7620",
    "sg:postcode":"48083",
    "sg:province":"MI",
    "sg:tags":[
        "bureau"
    ],
    "wof:name":"Lodgenet Entertainment",
    "wof:placetype":"venue"
},
  "geometry": {"coordinates":[-83.13038299999999,42.555807],"type":"Point"}
}