{
  "type": "Feature",
  "properties": {
    "iso:country":"US",
    "sg:address":"4417 S Westnedge Ave",
    "sg:city":"Kalamazoo",
    "sg:classifiers":[
        {
            "category":"Shopping",
            "subcategory":"Hobbies, Toys, & Games",
            "type":"Retail Goods"
        }
    ],
    "sg:phone":"+1 269 349 2666",
    "sg:postcode":"49008",
    "sg:province":"MI",
    "sg:tags":[
        "model",
        "supply"
    ],
    "sg:website":"www.riders.com",
    "wof:name":"Rider's Hobby Shops",
    "wof:placetype":"venue"
},
  "geometry": {"coordinates":[-85.589553,42.245568],"type":"Point"}
}