{
  "type": "Feature",
  "properties": {
    "iso:country":"US",
    "sg:address":"120 W Highland Rd",
    "sg:city":"Howell",
    "sg:classifiers":[
        {
            "category":"Utilities",
            "subcategory":"Mobile Phone",
            "type":"Services"
        }
    ],
    "sg:phone":"+1 517 545 4100",
    "sg:postcode":"48843",
    "sg:province":"MI",
    "sg:tags":[
        "telephone",
        "cellular"
    ],
    "wof:name":"Cingular Wireless",
    "wof:placetype":"venue"
},
  "geometry": {"coordinates":[-83.927876,42.622647],"type":"Point"}
}