{
  "type": "Feature",
  "properties": {
    "iso:country":"US",
    "sg:address":"4985 Oberlin Rd",
    "sg:city":"Gladwin",
    "sg:classifiers":[
        {
            "category":"Shopping",
            "subcategory":"Hobbies, Toys, & Games",
            "type":"Retail Goods"
        }
    ],
    "sg:phone":"+1 989 426 7007",
    "sg:postcode":"48624",
    "sg:province":"MI",
    "wof:name":"Oberlin Woods",
    "wof:placetype":"venue"
},
  "geometry": {"coordinates":[-84.506907,44.117214],"type":"Point"}
}