{
  "type": "Feature",
  "properties": {
    "iso:country":"US",
    "sg:address":"1557 W Hamlin Rd",
    "sg:city":"Rochester Hills",
    "sg:classifiers":[
        {
            "category":"Retail",
            "subcategory":"Repair Shop",
            "type":"Services"
        }
    ],
    "sg:phone":"+1 248 299 5837",
    "sg:postcode":"48309",
    "sg:province":"MI",
    "sg:tags":[
        "tool",
        "grinding"
    ],
    "wof:name":"DMB Tool Co",
    "wof:placetype":"venue"
},
  "geometry": {"coordinates":[-83.170101,42.651275],"type":"Point"}
}