{
  "type": "Feature",
  "properties": {
    "iso:country":"US",
    "sg:address":"69232 N Main St",
    "sg:city":"Richmond",
    "sg:classifiers":[
        {
            "category":"Restaurant",
            "type":"Food & Drink"
        }
    ],
    "sg:phone":"+1 586 727 4747",
    "sg:postcode":"48062",
    "sg:province":"MI",
    "wof:name":"Ken's Country Kitchen North",
    "wof:placetype":"venue"
},
  "geometry": {"coordinates":[-82.75705499999999,42.810884],"type":"Point"}
}