{
  "type": "Feature",
  "properties": {
    "iso:country":"US",
    "sg:address":"6811 Sparling Rd",
    "sg:city":"Kimball",
    "sg:classifiers":[
        {
            "category":"Professional",
            "type":"Services"
        }
    ],
    "sg:phone":"+1 810 367 3552",
    "sg:postcode":"48074",
    "sg:province":"MI",
    "sg:tags":[
        "establishment"
    ],
    "wof:name":"R A Engel Co",
    "wof:placetype":"venue"
},
  "geometry": {"coordinates":[-82.58747700000001,42.969588],"type":"Point"}
}