{
  "type": "Feature",
  "properties": {
    "iso:country":"US",
    "sg:address":"2081 E 8 Mile Rd",
    "sg:city":"Warren",
    "sg:classifiers":[
        {
            "category":"Professional",
            "subcategory":"Accounting & Tax Preparation",
            "type":"Services"
        }
    ],
    "sg:phone":"+1 586 758 2300",
    "sg:postcode":"48091",
    "sg:province":"MI",
    "sg:tags":[
        "return",
        "filing"
    ],
    "wof:name":"J & J Tax Svc",
    "wof:placetype":"venue"
},
  "geometry": {"coordinates":[-83.082365,42.447295],"type":"Point"}
}