{
  "type": "Feature",
  "properties": {
    "iso:country":"US",
    "sg:address":"8457 W Hazel Rd",
    "sg:city":"Mears",
    "sg:classifiers":[
        {
            "category":"Recreation",
            "subcategory":"Arcade",
            "type":"Entertainment"
        }
    ],
    "sg:phone":"+1 231 873 0276",
    "sg:postcode":"49436",
    "sg:province":"MI",
    "sg:tags":[
        "fun",
        "park"
    ],
    "wof:name":"Silver Lake Amusements",
    "wof:placetype":"venue"
},
  "geometry": {"coordinates":[-86.489558,43.667723],"type":"Point"}
}