{
  "type": "Feature",
  "properties": {
    "iso:country":"US",
    "sg:address":"722 W Montcalm St",
    "sg:city":"Greenville",
    "sg:classifiers":[
        {
            "category":"Social Services",
            "subcategory":"Adult Care",
            "type":"Services"
        }
    ],
    "sg:phone":"+1 616 754 0902",
    "sg:postcode":"48838",
    "sg:province":"MI",
    "sg:tags":[
        "foster",
        "provider"
    ],
    "wof:name":"Christina J Foote",
    "wof:placetype":"venue"
},
  "geometry": {"coordinates":[-85.26461999999999,43.183074],"type":"Point"}
}