{
  "type": "Feature",
  "properties": {
    "iso:country":"US",
    "sg:address":"5570 Gull Rd",
    "sg:city":"Kalamazoo",
    "sg:classifiers":[
        {
            "category":"Shopping",
            "subcategory":"Clothing, Apparel, & Fashions",
            "type":"Retail Goods"
        },
        {
            "category":"Bars & Pubs",
            "subcategory":"Lounge",
            "type":"Food & Drink"
        },
        {
            "category":"Restaurant",
            "type":"Food & Drink"
        },
        {
            "category":"Sports & Exercise",
            "subcategory":"Bowling",
            "type":"Entertainment"
        }
    ],
    "sg:phone":"+1 269 382 4077",
    "sg:postcode":"49048",
    "sg:province":"MI",
    "sg:tags":[
        "equipment",
        "sportswear",
        "cocktail",
        "accessory"
    ],
    "wof:name":"Eastland Bowl",
    "wof:placetype":"venue"
},
  "geometry": {"coordinates":[-85.520979,42.323794],"type":"Point"}
}