{
  "type": "Feature",
  "properties": {
    "iso:country":"US",
    "sg:address":"64837 Windrose Way",
    "sg:city":"Lawton",
    "sg:classifiers":[
        {
            "category":"Real Estate",
            "subcategory":"Real Estate Agent",
            "type":"Services"
        }
    ],
    "sg:phone":"+1 269 624 3606",
    "sg:postcode":"49065",
    "sg:province":"MI",
    "wof:name":"JV Properties Inc",
    "wof:placetype":"venue"
},
  "geometry": {"coordinates":[-85.85471099999999,42.185036],"type":"Point"}
}