{
  "type": "Feature",
  "properties": {
    "iso:country":"US",
    "sg:address":"2581 Andover St",
    "sg:city":"Trenton",
    "sg:classifiers":[
        {
            "category":"Professional",
            "subcategory":"Computer Services",
            "type":"Services"
        }
    ],
    "sg:phone":"+1 734 671 9031",
    "sg:postcode":"48183",
    "sg:province":"MI",
    "sg:tags":[
        "datum"
    ],
    "wof:name":"L P Processing",
    "wof:placetype":"venue"
},
  "geometry": {"coordinates":[-83.199797,42.145017],"type":"Point"}
}