{
  "type": "Feature",
  "properties": {
    "iso:country":"US",
    "sg:address":"2338 Coolidge Hwy",
    "sg:city":"Berkley",
    "sg:classifiers":[
        {
            "category":"Insurance",
            "subcategory":"Insurance Agent",
            "type":"Services"
        }
    ],
    "sg:phone":"+1 248 399 2242",
    "sg:postcode":"48072",
    "sg:province":"MI",
    "wof:name":"State Farm Insurance",
    "wof:placetype":"venue"
},
  "geometry": {"coordinates":[-83.183521,42.494349],"type":"Point"}
}