{
  "type": "Feature",
  "properties": {
    "iso:country":"US",
    "sg:address":"309 N Main St",
    "sg:city":"Davison",
    "sg:classifiers":[
        {
            "category":"Shopping",
            "subcategory":"Used Merchandise",
            "type":"Retail Goods"
        }
    ],
    "sg:phone":"+1 810 658 7702",
    "sg:postcode":"48423",
    "sg:province":"MI",
    "sg:tags":[
        "shop",
        "consignment"
    ],
    "wof:name":"Wear It Again",
    "wof:placetype":"venue"
},
  "geometry": {"coordinates":[-83.516847,43.032798],"type":"Point"}
}