{
  "type": "Feature",
  "properties": {
    "iso:country":"US",
    "sg:address":"2411 Iroquois St",
    "sg:city":"Detroit",
    "sg:classifiers":[
        {
            "category":"Organizations",
            "subcategory":"Religious Organization",
            "type":"Services"
        }
    ],
    "sg:phone":"+1 313 921 2667",
    "sg:postcode":"48214",
    "sg:province":"MI",
    "wof:name":"Iroquois Avenue Christ Lutheran Church",
    "wof:placetype":"venue"
},
  "geometry": {"coordinates":[-82.997398,42.362202],"type":"Point"}
}