{
  "type": "Feature",
  "properties": {
    "iso:country":"US",
    "sg:address":"34064 James J Pompo Dr",
    "sg:city":"Fraser",
    "sg:classifiers":[
        {
            "category":"Wholesale",
            "subcategory":"Machinery & Supplies",
            "type":"Manufacturing & Wholesale Goods"
        }
    ],
    "sg:phone":"+1 586 293 8388",
    "sg:postcode":"48026",
    "sg:province":"MI",
    "sg:tags":[
        "equipment",
        "plastic"
    ],
    "wof:name":"New Era Plastics",
    "wof:placetype":"venue"
},
  "geometry": {"coordinates":[-82.936222,42.545539],"type":"Point"}
}