{
  "type": "Feature",
  "properties": {
    "iso:country":"US",
    "sg:address":"3305 Remembrance Rd NW",
    "sg:city":"Grand Rapids",
    "sg:classifiers":[
        {
            "category":"Building & Trades",
            "subcategory":"Construction",
            "type":"Services"
        }
    ],
    "sg:phone":"+1 616 453 1659",
    "sg:postcode":"49534",
    "sg:province":"MI",
    "sg:tags":[
        "installs",
        "wall",
        "access",
        "partition",
        "flooring"
    ],
    "wof:name":"Richmond Interior Systems",
    "wof:placetype":"venue"
},
  "geometry": {"coordinates":[-85.749658,42.987834],"type":"Point"}
}