{
  "type": "Feature",
  "properties": {
    "iso:country":"US",
    "sg:address":"2022 Roods Lake Rd",
    "sg:city":"Lapeer",
    "sg:classifiers":[
        {
            "category":"Retail",
            "subcategory":"Portrait Studio",
            "type":"Services"
        }
    ],
    "sg:phone":"+1 810 667 9267",
    "sg:postcode":"48446",
    "sg:province":"MI",
    "sg:tags":[
        "photographer"
    ],
    "wof:name":"Creative Images By TL Atwell",
    "wof:placetype":"venue"
},
  "geometry": {"coordinates":[-83.277925,43.090711],"type":"Point"}
}