{
  "type": "Feature",
  "properties": {
    "iso:country":"US",
    "sg:address":"7170 E Apple Ave",
    "sg:city":"Muskegon",
    "sg:classifiers":[
        {
            "category":"Shopping",
            "subcategory":"Bicycles & Sporting Goods",
            "type":"Retail Goods"
        }
    ],
    "sg:phone":"+1 231 788 4474",
    "sg:postcode":"49442",
    "sg:province":"MI",
    "sg:tags":[
        "gun",
        "gunsmith"
    ],
    "wof:name":"500 Guns-Barnes Hardware",
    "wof:placetype":"venue"
},
  "geometry": {"coordinates":[-86.05675599999999,43.235148],"type":"Point"}
}