{
  "type": "Feature",
  "properties": {
    "iso:country":"US",
    "sg:address":"3216 Holiday Village Rd",
    "sg:city":"Traverse City",
    "sg:classifiers":[
        {
            "category":"Wholesale",
            "subcategory":"Machinery & Supplies",
            "type":"Manufacturing & Wholesale Goods"
        }
    ],
    "sg:phone":"+1 231 938 2579",
    "sg:postcode":"49686",
    "sg:province":"MI",
    "sg:tags":[
        "contractor"
    ],
    "wof:name":"Greenblock Grand Traverse",
    "wof:placetype":"venue"
},
  "geometry": {"coordinates":[-85.508989,44.733981],"type":"Point"}
}