{
  "type": "Feature",
  "properties": {
    "iso:country":"US",
    "sg:address":"34901 Division Rd",
    "sg:city":"Richmond",
    "sg:classifiers":[
        {
            "category":"Health Services",
            "subcategory":"Nursing And Care Facility",
            "type":"Services"
        }
    ],
    "sg:phone":"+1 586 727 7562",
    "sg:postcode":"48062",
    "sg:province":"MI",
    "sg:tags":[
        "home",
        "convalescent"
    ],
    "wof:name":"Medi Lodge Of Richmond",
    "wof:placetype":"venue"
},
  "geometry": {"coordinates":[-82.769964,42.808918],"type":"Point"}
}