{
  "type": "Feature",
  "properties": {
    "iso:country":"US",
    "sg:address":"190 Wealthy St SW",
    "sg:city":"Grand Rapids",
    "sg:classifiers":[
        {
            "category":"Professional",
            "type":"Services"
        }
    ],
    "sg:phone":"+1 616 459 1089",
    "sg:postcode":"49503",
    "sg:province":"MI",
    "sg:tags":[
        "establishment"
    ],
    "wof:name":"Greyhound Package Express",
    "wof:placetype":"venue"
},
  "geometry": {"coordinates":[-85.673466,42.956093],"type":"Point"}
}