{
  "type": "Feature",
  "properties": {
    "iso:country":"US",
    "sg:address":"33891 Doreka Dr",
    "sg:city":"Fraser",
    "sg:classifiers":[
        {
            "category":"Manufacturing",
            "subcategory":"Tools & Machinery",
            "type":"Manufacturing & Wholesale Goods"
        }
    ],
    "sg:phone":"+1 586 294 1850",
    "sg:postcode":"48026",
    "sg:province":"MI",
    "sg:tags":[
        "machine"
    ],
    "wof:name":"A W Carbide Fabrications Inc",
    "wof:placetype":"venue"
},
  "geometry": {"coordinates":[-82.936317,42.546093],"type":"Point"}
}