{
  "type": "Feature",
  "properties": {
    "iso:country":"US",
    "sg:address":"47430 Pontiac Trl",
    "sg:city":"Wixom",
    "sg:classifiers":[
        {
            "category":"Restaurant",
            "type":"Food & Drink"
        }
    ],
    "sg:menulink":"http://www.allmenus.com/mi/wixom/84457-papa-johns-pizza/menu/",
    "sg:phone":"+1 248 669 7272",
    "sg:postcode":"48393",
    "sg:province":"MI",
    "sg:tags":[
        "american",
        "pizza"
    ],
    "wof:name":"Papa John's Pizza",
    "wof:placetype":"venue"
},
  "geometry": {"coordinates":[-83.518147,42.524924],"type":"Point"}
}