{
  "type": "Feature",
  "properties": {
    "iso:country":"US",
    "sg:address":"1228 Coplin Rd",
    "sg:city":"Litchfield",
    "sg:classifiers":[
        {
            "category":"Farming",
            "subcategory":"Livestock Farm",
            "type":"Manufacturing & Wholesale Goods"
        }
    ],
    "sg:phone":"+1 517 542 3604",
    "sg:postcode":"49252",
    "sg:province":"MI",
    "sg:tags":[
        "animal",
        "general"
    ],
    "wof:name":"Gary Abbeg",
    "wof:placetype":"venue"
},
  "geometry": {"coordinates":[-84.826223,42.022056],"type":"Point"}
}