{
  "type": "Feature",
  "properties": {
    "iso:country":"US",
    "sg:address":"2820 E Grand Blvd",
    "sg:city":"Detroit",
    "sg:classifiers":[
        {
            "category":"Professional",
            "subcategory":"Art Services",
            "type":"Services"
        }
    ],
    "sg:phone":"+1 313 875 3123",
    "sg:postcode":"48211",
    "sg:province":"MI",
    "sg:tags":[
        "photography",
        "commercial"
    ],
    "wof:name":"Howrani Ameen Photography",
    "wof:placetype":"venue"
},
  "geometry": {"coordinates":[-83.063813,42.373953],"type":"Point"}
}