{
  "type": "Feature",
  "properties": {
    "iso:country":"US",
    "sg:address":"4071 Richfield Rd",
    "sg:city":"Flint",
    "sg:classifiers":[
        {
            "category":"Health Services",
            "subcategory":"Doctor",
            "type":"Services"
        }
    ],
    "sg:phone":"+1 810 736 2440",
    "sg:postcode":"48506",
    "sg:province":"MI",
    "sg:tags":[
        "medicine",
        "practice",
        "internal",
        "family"
    ],
    "wof:name":"Richfield Family Medicine",
    "wof:placetype":"venue"
},
  "geometry": {"coordinates":[-83.63329400000001,43.051354],"type":"Point"}
}