{
  "type": "Feature",
  "properties": {
    "iso:country":"US",
    "sg:address":"21885 Dunham Rd",
    "sg:city":"Clinton Twp",
    "sg:classifiers":[
        {
            "category":"Government",
            "subcategory":"Office",
            "type":"Public Place"
        }
    ],
    "sg:phone":"+1 586 469 7700",
    "sg:postcode":"48036",
    "sg:province":"MI",
    "sg:tags":[
        "state",
        "resource"
    ],
    "wof:name":"Social Service Dept",
    "wof:placetype":"venue"
},
  "geometry": {"coordinates":[-82.89049799999999,42.617878],"type":"Point"}
}