{
  "type": "Feature",
  "properties": {
    "iso:country":"US",
    "sg:address":"21527 Harper Ave",
    "sg:city":"Saint Clair Shores",
    "sg:classifiers":[
        {
            "category":"Shopping",
            "subcategory":"Optical Goods",
            "type":"Retail Goods"
        }
    ],
    "sg:phone":"+1 586 776 3333",
    "sg:postcode":"48080",
    "sg:province":"MI",
    "sg:tags":[
        "optician",
        "eyewear"
    ],
    "wof:name":"Dolan Optical Co",
    "wof:placetype":"venue"
},
  "geometry": {"coordinates":[-82.9132,42.454201],"type":"Point"}
}