{
  "type": "Feature",
  "properties": {
    "iso:country":"US",
    "sg:address":"205 S Lincoln St",
    "sg:city":"Charlotte",
    "sg:classifiers":[
        {
            "category":"Professional",
            "subcategory":"Business Services",
            "type":"Services"
        }
    ],
    "sg:phone":"+1 517 543 9020",
    "sg:postcode":"48813",
    "sg:province":"MI",
    "wof:name":"Homant Quality Water Inc",
    "wof:placetype":"venue"
},
  "geometry": {"coordinates":[-84.845613,42.562222],"type":"Point"}
}