{
  "type": "Feature",
  "properties": {
    "iso:country":"US",
    "sg:address":"1914 Territorial Rd",
    "sg:city":"Benton Harbor",
    "sg:classifiers":[
        {
            "category":"Real Estate",
            "subcategory":"Real Estate Operator",
            "type":"Services"
        }
    ],
    "sg:phone":"+1 269 926 4000",
    "sg:postcode":"49022",
    "sg:province":"MI",
    "sg:tags":[
        "building",
        "apartment"
    ],
    "wof:name":"Cogic Village Apartments",
    "wof:placetype":"venue"
},
  "geometry": {"coordinates":[-86.41383500000001,42.123081],"type":"Point"}
}