{
  "type": "Feature",
  "properties": {
    "iso:country":"US",
    "sg:address":"1549 Howard City Edmore Rd NE",
    "sg:city":"Edmore",
    "sg:classifiers":[
        {
            "category":"Sports & Exercise",
            "subcategory":"Golf",
            "type":"Entertainment"
        }
    ],
    "sg:phone":"+1 989 427 3241",
    "sg:postcode":"48829",
    "sg:province":"MI",
    "sg:tags":[
        "course"
    ],
    "wof:name":"Links Of Edmore Inc",
    "wof:placetype":"venue"
},
  "geometry": {"coordinates":[-85.058566,43.408212],"type":"Point"}
}