{
  "type": "Feature",
  "properties": {
    "iso:country":"US",
    "sg:address":"4482 Long Rapids Rd",
    "sg:city":"Alpena",
    "sg:classifiers":[
        {
            "category":"Manufacturing",
            "subcategory":"Tools & Machinery",
            "type":"Manufacturing & Wholesale Goods"
        }
    ],
    "sg:phone":"+1 989 354 0715",
    "sg:postcode":"49707",
    "sg:province":"MI",
    "sg:tags":[
        "industrial",
        "mfg"
    ],
    "wof:name":"G S Machine Inc",
    "wof:placetype":"venue"
},
  "geometry": {"coordinates":[-83.54573600000001,45.111837],"type":"Point"}
}