{
  "type": "Feature",
  "properties": {
    "iso:country":"US",
    "sg:address":"23301 Ford Rd",
    "sg:city":"Dearborn",
    "sg:classifiers":[
        {
            "category":"Personal",
            "subcategory":"Beauty Salon",
            "type":"Services"
        }
    ],
    "sg:phone":"+1 313 562 7317",
    "sg:postcode":"48128",
    "sg:province":"MI",
    "sg:tags":[
        "shop"
    ],
    "wof:name":"Gemmas Hair Salon",
    "wof:placetype":"venue"
},
  "geometry": {"coordinates":[-83.266131,42.327076],"type":"Point"}
}