{
  "type": "Feature",
  "properties": {
    "iso:country":"US",
    "sg:address":"63474 Union Rd",
    "sg:city":"Vandalia",
    "sg:classifiers":[
        {
            "category":"Wholesale",
            "subcategory":"Electrical",
            "type":"Manufacturing & Wholesale Goods"
        }
    ],
    "sg:phone":"+1 269 476 2220",
    "sg:postcode":"49095",
    "sg:province":"MI",
    "sg:tags":[
        "electric",
        "motor"
    ],
    "wof:name":"Carter's Electric Motor Svc",
    "wof:placetype":"venue"
},
  "geometry": {"coordinates":[-85.880422,41.874455],"type":"Point"}
}