{
  "type": "Feature",
  "properties": {
    "iso:country":"US",
    "sg:address":"3340 Ranger Rd",
    "sg:city":"Lansing",
    "sg:classifiers":[
        {
            "category":"Professional",
            "subcategory":"Research",
            "type":"Services"
        }
    ],
    "sg:phone":"+1 517 485 3333",
    "sg:postcode":"48906",
    "sg:province":"MI",
    "sg:tags":[
        "environmental",
        "ecological"
    ],
    "wof:name":"P M Environmental Inc",
    "wof:placetype":"venue"
},
  "geometry": {"coordinates":[-84.578783,42.767319],"type":"Point"}
}