{
  "type": "Feature",
  "properties": {
    "iso:country":"US",
    "sg:address":"2202 Spruce Rd",
    "sg:city":"Eaton Rapids",
    "sg:classifiers":[
        {
            "category":"Manufacturing",
            "subcategory":"Signs",
            "type":"Manufacturing & Wholesale Goods"
        }
    ],
    "sg:phone":"+1 517 646 7285",
    "sg:postcode":"48827",
    "sg:province":"MI",
    "sg:tags":[
        "specialty",
        "mfg"
    ],
    "wof:name":"A Plus Signs",
    "wof:placetype":"venue"
},
  "geometry": {"coordinates":[-84.671221,42.600902],"type":"Point"}
}