{
  "type": "Feature",
  "properties": {
    "iso:country":"US",
    "sg:address":"37000 Grand River Ave",
    "sg:city":"Farmington Hills",
    "sg:classifiers":[
        {
            "category":"Professional",
            "subcategory":"Lawyer & Legal Services",
            "type":"Services"
        }
    ],
    "sg:phone":"+1 248 442 9150",
    "sg:postcode":"48335",
    "sg:province":"MI",
    "sg:tags":[
        "attorney"
    ],
    "wof:name":"Dennis Cleary PC",
    "wof:placetype":"venue"
},
  "geometry": {"coordinates":[-83.411655,42.468786],"type":"Point"}
}