{
  "type": "Feature",
  "properties": {
    "iso:country":"US",
    "sg:address":"240 Richards Ave SW",
    "sg:city":"Grand Rapids",
    "sg:classifiers":[
        {
            "category":"Building & Trades",
            "subcategory":"Construction",
            "type":"Services"
        }
    ],
    "sg:phone":"+1 616 776 9929",
    "sg:postcode":"49504",
    "sg:province":"MI",
    "sg:tags":[
        "general",
        "contractor"
    ],
    "wof:name":"Woodworking Construction Svc",
    "wof:placetype":"venue"
},
  "geometry": {"coordinates":[-85.69962599999999,42.958886],"type":"Point"}
}