{
  "type": "Feature",
  "properties": {
    "iso:country":"US",
    "sg:address":"1273 State Hwy 211",
    "sg:city":"Onaway",
    "sg:classifiers":[
        {
            "category":"Utilities",
            "subcategory":"Refuse",
            "type":"Services"
        }
    ],
    "sg:phone":"+1 989 733 2598",
    "sg:postcode":"49765",
    "sg:province":"MI",
    "sg:tags":[
        "garbage",
        "collection"
    ],
    "wof:name":"PAC Inc",
    "wof:placetype":"venue"
},
  "geometry": {"coordinates":[-84.227934,45.39238],"type":"Point"}
}