{
  "type": "Feature",
  "properties": {
    "iso:country":"US",
    "sg:address":"26100 Hawthorne Dr",
    "sg:city":"Franklin",
    "sg:classifiers":[
        {
            "category":"Government",
            "subcategory":"Office",
            "type":"Public Place"
        }
    ],
    "sg:phone":"+1 248 737 1932",
    "sg:postcode":"48025",
    "sg:province":"MI",
    "sg:tags":[
        "combined"
    ],
    "wof:name":"Reserve Officers Assoc",
    "wof:placetype":"venue"
},
  "geometry": {"coordinates":[-83.30367699999999,42.520601],"type":"Point"}
}