{
  "type": "Feature",
  "properties": {
    "iso:country":"US",
    "sg:address":"932 4th Ave",
    "sg:city":"Lake Odessa",
    "sg:classifiers":[
        {
            "category":"Professional",
            "subcategory":"Lawyer & Legal Services",
            "type":"Services"
        }
    ],
    "sg:phone":"+1 616 374 8816",
    "sg:postcode":"48849",
    "sg:province":"MI",
    "sg:tags":[
        "attorney"
    ],
    "wof:name":"Lincoln's Law Office",
    "wof:placetype":"venue"
},
  "geometry": {"coordinates":[-85.138103,42.781906],"type":"Point"}
}