{
  "type": "Feature",
  "properties": {
    "iso:country":"US",
    "sg:address":"137 W Grand River Ave",
    "sg:city":"Williamston",
    "sg:classifiers":[
        {
            "category":"Shopping",
            "type":"Retail Goods"
        }
    ],
    "sg:phone":"+1 517 655 4765",
    "sg:postcode":"48895",
    "sg:province":"MI",
    "sg:tags":[
        "art",
        "gallery",
        "dealer"
    ],
    "wof:name":"Sharon Emrick Handweaver",
    "wof:placetype":"venue"
},
  "geometry": {"coordinates":[-84.28490499999999,42.688832],"type":"Point"}
}