{
  "type": "Feature",
  "properties": {
    "iso:country":"US",
    "sg:address":"18411 W 12 Mile Rd Ste 202",
    "sg:city":"Lathrup Village",
    "sg:classifiers":[
        {
            "category":"Banks & Credit Unions",
            "subcategory":"Atm",
            "type":"Services"
        }
    ],
    "sg:phone":"+1 248 569 5120",
    "sg:postcode":"48076",
    "sg:province":"MI",
    "sg:tags":[
        "bankruptcy"
    ],
    "wof:name":"Salinger & Associates",
    "wof:placetype":"venue"
},
  "geometry": {"coordinates":[-83.225998,42.5023],"type":"Point"}
}