{
  "type": "Feature",
  "properties": {
    "iso:country":"US",
    "sg:address":"41740 Garfield Rd",
    "sg:city":"Clinton Township",
    "sg:classifiers":[
        {
            "category":"Shopping",
            "subcategory":"Jewelry",
            "type":"Retail Goods"
        },
        {
            "category":"Wholesale",
            "subcategory":"Stationery",
            "type":"Manufacturing & Wholesale Goods"
        }
    ],
    "sg:phone":"+1 586 263 1233",
    "sg:postcode":"48038",
    "sg:province":"MI",
    "sg:tags":[
        "card"
    ],
    "sg:website":"www.bonaldis.net",
    "wof:name":"Bonaldi's Italian Imports",
    "wof:placetype":"venue"
},
  "geometry": {"coordinates":[-82.9524,42.604301],"type":"Point"}
}