{
  "type": "Feature",
  "properties": {
    "iso:country":"US",
    "sg:address":"1106 S Washington St",
    "sg:city":"Owosso",
    "sg:classifiers":[
        {
            "category":"Real Estate",
            "subcategory":"Developer",
            "type":"Services"
        }
    ],
    "sg:phone":"+1 989 725 5322",
    "sg:postcode":"48867",
    "sg:province":"MI",
    "sg:tags":[
        "cemetery"
    ],
    "wof:name":"Hillcrest Memorial Gardens",
    "wof:placetype":"venue"
},
  "geometry": {"coordinates":[-84.170199,42.986629],"type":"Point"}
}