{
  "type": "Feature",
  "properties": {
    "iso:country":"US",
    "sg:address":"810 E Front St",
    "sg:city":"Traverse City",
    "sg:classifiers":[
        {
            "category":"Restaurant",
            "type":"Food & Drink"
        }
    ],
    "sg:phone":"+1 231 946 1991",
    "sg:postcode":"49686",
    "sg:province":"MI",
    "wof:name":"Hard Luck Cafe",
    "wof:placetype":"venue"
},
  "geometry": {"coordinates":[-85.60137,44.764077],"type":"Point"}
}