{
  "type": "Feature",
  "properties": {
    "iso:country":"US",
    "sg:address":"7132 Highland Rd",
    "sg:city":"Waterford",
    "sg:classifiers":[
        {
            "category":"Retail",
            "subcategory":"Laundry & Dry Cleaning",
            "type":"Services"
        }
    ],
    "sg:phone":"+1 248 666 3266",
    "sg:postcode":"48327",
    "sg:province":"MI",
    "sg:tags":[
        "plant"
    ],
    "wof:name":"Father & Son Cleaners",
    "wof:placetype":"venue"
},
  "geometry": {"coordinates":[-83.422978,42.659475],"type":"Point"}
}