{
  "type": "Feature",
  "properties": {
    "iso:country":"US",
    "sg:address":"9071 24th Rd",
    "sg:city":"Rapid River",
    "sg:classifiers":[
        {
            "category":"Building & Trades",
            "subcategory":"Construction",
            "type":"Services"
        }
    ],
    "sg:phone":"+1 906 474 5003",
    "sg:postcode":"49878",
    "sg:province":"MI",
    "sg:tags":[
        "general",
        "contractor"
    ],
    "wof:name":"Anderson Excavating",
    "wof:placetype":"venue"
},
  "geometry": {"coordinates":[-86.90702400000001,45.882696],"type":"Point"}
}