{
  "type": "Feature",
  "properties": {
    "iso:country":"US",
    "sg:address":"17432 N Key Dr",
    "sg:city":"Spring Lake",
    "sg:classifiers":[
        {
            "category":"Retail",
            "subcategory":"Portrait Studio",
            "type":"Services"
        }
    ],
    "sg:phone":"+1 616 846 8603",
    "sg:postcode":"49456",
    "sg:province":"MI",
    "sg:tags":[
        "photo"
    ],
    "wof:name":"Paw Prints Photography",
    "wof:placetype":"venue"
},
  "geometry": {"coordinates":[-86.221419,43.113362],"type":"Point"}
}