{
  "type": "Feature",
  "properties": {
    "iso:country":"US",
    "sg:address":"1024 11th Ave",
    "sg:city":"Port Huron",
    "sg:classifiers":[
        {
            "category":"Freight",
            "type":"Transportation"
        }
    ],
    "sg:phone":"+1 810 987 9281",
    "sg:postcode":"48060",
    "sg:province":"MI",
    "sg:tags":[
        "hauling",
        "trucking"
    ],
    "wof:name":"Holmes Quick & Safe",
    "wof:placetype":"venue"
},
  "geometry": {"coordinates":[-82.43550500000001,42.984911],"type":"Point"}
}