{
  "type": "Feature",
  "properties": {
    "iso:country":"US",
    "sg:address":"3148 Plainfield Ave NE",
    "sg:city":"Grand Rapids",
    "sg:classifiers":[
        {
            "category":"Professional",
            "subcategory":"Art Services",
            "type":"Services"
        }
    ],
    "sg:phone":"+1 616 774 9511",
    "sg:postcode":"49525",
    "sg:province":"MI",
    "sg:tags":[
        "photography",
        "commercial"
    ],
    "wof:name":"Labakk Studio",
    "wof:placetype":"venue"
},
  "geometry": {"coordinates":[-85.634833,43.020043],"type":"Point"}
}