{
  "type": "Feature",
  "properties": {
    "iso:country":"US",
    "sg:address":"1258 Woodland Ave NW",
    "sg:city":"Grand Rapids",
    "sg:classifiers":[
        {
            "category":"Manufacturing",
            "subcategory":"Tools & Machinery",
            "type":"Manufacturing & Wholesale Goods"
        }
    ],
    "sg:phone":"+1 616 791 8400",
    "sg:postcode":"49504",
    "sg:province":"MI",
    "sg:tags":[
        "mfg",
        "general"
    ],
    "wof:name":"Woodland Machinery Sales",
    "wof:placetype":"venue"
},
  "geometry": {"coordinates":[-85.732382,42.987174],"type":"Point"}
}