{
  "type": "Feature",
  "properties": {
    "iso:country":"US",
    "sg:address":"29159 Helman Blvd",
    "sg:city":"Trenton",
    "sg:classifiers":[
        {
            "category":"Health Services",
            "subcategory":"Doctor",
            "type":"Services"
        }
    ],
    "sg:phone":"+1 734 671 5100",
    "sg:postcode":"48183",
    "sg:province":"MI",
    "sg:tags":[
        "medicine",
        "internal"
    ],
    "wof:name":"Southeast Internal Medicine",
    "wof:placetype":"venue"
},
  "geometry": {"coordinates":[-83.23554799999999,42.093997],"type":"Point"}
}