{
  "type": "Feature",
  "properties": {
    "iso:country":"US",
    "sg:address":"102 N Main St",
    "sg:city":"Evart",
    "sg:classifiers":[
        {
            "category":"Building & Trades",
            "subcategory":"Construction",
            "type":"Services"
        }
    ],
    "sg:phone":"+1 231 734 3082",
    "sg:postcode":"49631",
    "sg:province":"MI",
    "sg:tags":[
        "excavating",
        "contractor"
    ],
    "wof:name":"Triple C Excavating",
    "wof:placetype":"venue"
},
  "geometry": {"coordinates":[-85.259401,43.901873],"type":"Point"}
}