{
  "type": "Feature",
  "properties": {
    "iso:country":"US",
    "sg:address":"8304 Jaclyn Ann Dr",
    "sg:city":"Flushing",
    "sg:classifiers":[
        {
            "category":"Professional",
            "subcategory":"Advertising",
            "type":"Services"
        }
    ],
    "sg:phone":"+1 810 659 0390",
    "sg:postcode":"48433",
    "sg:province":"MI",
    "wof:name":"McIntosh Disributors",
    "wof:placetype":"venue"
},
  "geometry": {"coordinates":[-83.844442,43.084594],"type":"Point"}
}