{
  "type": "Feature",
  "properties": {
    "iso:country":"US",
    "sg:address":"2427 Spring Arbor Rd",
    "sg:city":"Jackson",
    "sg:classifiers":[
        {
            "category":"Social Services",
            "type":"Services"
        }
    ],
    "sg:phone":"+1 517 780 9981",
    "sg:postcode":"49203",
    "sg:province":"MI",
    "wof:name":"Family Dynamics",
    "wof:placetype":"venue"
},
  "geometry": {"coordinates":[-84.443057,42.234305],"type":"Point"}
}