{
  "type": "Feature",
  "properties": {
    "iso:country":"US",
    "sg:address":"552 25th St",
    "sg:city":"Otsego",
    "sg:classifiers":[
        {
            "category":"Manufacturing",
            "subcategory":"Printing",
            "type":"Manufacturing & Wholesale Goods"
        }
    ],
    "sg:phone":"+1 269 694 5463",
    "sg:postcode":"49078",
    "sg:province":"MI",
    "sg:tags":[
        "commercial"
    ],
    "wof:name":"Paw Prints Plus",
    "wof:placetype":"venue"
},
  "geometry": {"coordinates":[-85.788518,42.462358],"type":"Point"}
}