{
  "type": "Feature",
  "properties": {
    "iso:country":"US",
    "sg:address":"6705 Bloomfield Ln",
    "sg:city":"West Bloomfield",
    "sg:classifiers":[
        {
            "category":"Professional",
            "subcategory":"Lawyer & Legal Services",
            "type":"Services"
        }
    ],
    "sg:phone":"+1 248 788 2507",
    "sg:postcode":"48322",
    "sg:province":"MI",
    "sg:tags":[
        "plan"
    ],
    "wof:name":"Pre-Paid Legal Svc Inc",
    "wof:placetype":"venue"
},
  "geometry": {"coordinates":[-83.332633,42.542491],"type":"Point"}
}