{
  "type": "Feature",
  "properties": {
    "iso:country":"US",
    "sg:address":"4112 M 129",
    "sg:city":"Sault Sainte Marie",
    "sg:classifiers":[
        {
            "category":"Wholesale",
            "subcategory":"Medical Equipment & Supplies",
            "type":"Manufacturing & Wholesale Goods"
        }
    ],
    "sg:phone":"+1 906 632 4826",
    "sg:postcode":"49783",
    "sg:province":"MI",
    "wof:name":"Crashcards Inc",
    "wof:placetype":"venue"
},
  "geometry": {"coordinates":[-84.35368200000001,46.446678],"type":"Point"}
}