{
  "type": "Feature",
  "properties": {
    "iso:country":"US",
    "sg:address":"2073 S Custer Rd",
    "sg:city":"Monroe",
    "sg:classifiers":[
        {
            "category":"Building & Trades",
            "subcategory":"Cleaning & Sanitation",
            "type":"Services"
        }
    ],
    "sg:phone":"+1 734 243 7888",
    "sg:postcode":"48161",
    "sg:province":"MI",
    "sg:tags":[
        "janitor"
    ],
    "wof:name":"Advanced Professional Cleaning",
    "wof:placetype":"venue"
},
  "geometry": {"coordinates":[-83.42981899999999,41.921884],"type":"Point"}
}