{
  "type": "Feature",
  "properties": {
    "iso:country":"US",
    "sg:address":"6622 Sparling Rd",
    "sg:city":"Kimball",
    "sg:classifiers":[
        {
            "category":"Retail",
            "subcategory":"Auto Repair",
            "type":"Services"
        }
    ],
    "sg:phone":"+1 810 367 2050",
    "sg:postcode":"48074",
    "sg:province":"MI",
    "sg:tags":[
        "repairing",
        "automobile",
        "general"
    ],
    "wof:name":"Santa Auto & Truck Repair",
    "wof:placetype":"venue"
},
  "geometry": {"coordinates":[-82.59298,42.969488],"type":"Point"}
}