{
  "type": "Feature",
  "properties": {
    "iso:country":"US",
    "sg:address":"53544 Christy Dr",
    "sg:city":"New Baltimore",
    "sg:classifiers":[
        {
            "category":"Professional",
            "subcategory":"Accounting & Tax Preparation",
            "type":"Services"
        }
    ],
    "sg:phone":"+1 586 749 8787",
    "sg:postcode":"48051",
    "sg:province":"MI",
    "wof:name":"Shelley Mitrak CPA",
    "wof:placetype":"venue"
},
  "geometry": {"coordinates":[-82.843259,42.693971],"type":"Point"}
}