{
  "type": "Feature",
  "properties": {
    "iso:country":"US",
    "sg:address":"403 W 3rd St",
    "sg:city":"Charlotte",
    "sg:classifiers":[
        {
            "category":"Retail",
            "subcategory":"Repair Shop",
            "type":"Services"
        }
    ],
    "sg:phone":"+1 517 543 8211",
    "sg:postcode":"48813",
    "sg:province":"MI",
    "sg:tags":[
        "lock",
        "locksmith"
    ],
    "wof:name":"Lock Doctor",
    "wof:placetype":"venue"
},
  "geometry": {"coordinates":[-84.841007,42.550187],"type":"Point"}
}