{
  "type": "Feature",
  "properties": {
    "iso:country":"US",
    "sg:address":"4525 Gray Fox Ln NE",
    "sg:city":"Ada",
    "sg:classifiers":[
        {
            "category":"Professional",
            "subcategory":"Business Services",
            "type":"Services"
        }
    ],
    "sg:phone":"+1 616 364 2006",
    "sg:postcode":"49301",
    "sg:province":"MI",
    "wof:name":"Wealth Management Solutions",
    "wof:placetype":"venue"
},
  "geometry": {"coordinates":[-85.556983,42.997437],"type":"Point"}
}