{
  "type": "Feature",
  "properties": {
    "iso:country":"US",
    "sg:address":"2415 Abbott Rd",
    "sg:city":"East Lansing",
    "sg:classifiers":[
        {
            "category":"Organizations",
            "subcategory":"Religious Organization",
            "type":"Services"
        }
    ],
    "sg:phone":"+1 517 351 3140",
    "sg:postcode":"48823",
    "sg:province":"MI",
    "wof:name":"Way of Michigan",
    "wof:placetype":"venue"
},
  "geometry": {"coordinates":[-84.48375799999999,42.762111],"type":"Point"}
}