{
  "type": "Feature",
  "properties": {
    "iso:country":"US",
    "sg:address":"2267 Reum Rd",
    "sg:city":"Niles",
    "sg:classifiers":[
        {
            "category":"Autos & Motor Vehicles",
            "subcategory":"Auto Supplies",
            "type":"Retail Goods"
        }
    ],
    "sg:phone":"+1 269 683 6106",
    "sg:postcode":"49120",
    "sg:province":"MI",
    "sg:tags":[
        "automobile",
        "parts"
    ],
    "wof:name":"Holt's Auto Parts",
    "wof:placetype":"venue"
},
  "geometry": {"coordinates":[-86.22138099999999,41.812139],"type":"Point"}
}