{
  "type": "Feature",
  "properties": {
    "iso:country":"US",
    "sg:address":"725 S Adams Rd",
    "sg:city":"Birmingham",
    "sg:classifiers":[
        {
            "category":"Arts & Performance",
            "subcategory":"Theater",
            "type":"Entertainment"
        }
    ],
    "sg:phone":"+1 248 540 4900",
    "sg:postcode":"48009",
    "sg:province":"MI",
    "sg:tags":[
        "group",
        "live",
        "music"
    ],
    "sg:website":"www.cobrien.com",
    "wof:name":"Chris O'Brien Productions Inc",
    "wof:placetype":"venue"
},
  "geometry": {"coordinates":[-83.205423,42.541771],"type":"Point"}
}