{
  "type": "Feature",
  "properties": {
    "iso:country":"US",
    "sg:address":"220 S State St",
    "sg:city":"Caro",
    "sg:classifiers":[
        {
            "category":"Professional",
            "subcategory":"Employment Agencies",
            "type":"Services"
        }
    ],
    "sg:phone":"+1 989 672 4500",
    "sg:postcode":"48723",
    "sg:province":"MI",
    "wof:name":"Select Staffing Inc",
    "wof:placetype":"venue"
},
  "geometry": {"coordinates":[-83.397525,43.488078],"type":"Point"}
}