{
  "type": "Feature",
  "properties": {
    "iso:country":"US",
    "sg:address":"29209 Northwestern Hwy",
    "sg:city":"Southfield",
    "sg:classifiers":[
        {
            "category":"Banks & Credit Unions",
            "subcategory":"Financial Services",
            "type":"Services"
        }
    ],
    "sg:phone":"+1 248 355 2076",
    "sg:postcode":"48034",
    "sg:province":"MI",
    "sg:tags":[
        "investor"
    ],
    "wof:name":"Imperial Investment Corp",
    "wof:placetype":"venue"
},
  "geometry": {"coordinates":[-83.316006,42.505196],"type":"Point"}
}