{
  "type": "Feature",
  "properties": {
    "iso:country":"US",
    "sg:address":"7998 Walker Rd",
    "sg:city":"Ovid",
    "sg:classifiers":[
        {
            "category":"Building & Trades",
            "subcategory":"Cleaning & Sanitation",
            "type":"Services"
        }
    ],
    "sg:phone":"+1 989 834 5831",
    "sg:postcode":"48866",
    "sg:province":"MI",
    "sg:tags":[
        "janitorial"
    ],
    "wof:name":"Ecm",
    "wof:placetype":"venue"
},
  "geometry": {"coordinates":[-84.40807100000001,43.015584],"type":"Point"}
}