{
  "type": "Feature",
  "properties": {
    "iso:country":"US",
    "sg:address":"3586 Plymouth Rd",
    "sg:city":"Ann Arbor",
    "sg:classifiers":[
        {
            "category":"Restaurant",
            "type":"Food & Drink"
        }
    ],
    "sg:menulink":"http://www.allmenus.com/mi/ann-arbor/247722-marks-midtown-coney-island/menu/",
    "sg:phone":"+1 734 998 0067",
    "sg:postcode":"48105",
    "sg:province":"MI",
    "sg:tags":[
        "american",
        "diner"
    ],
    "wof:name":"Mark's Midtown Coney Island",
    "wof:placetype":"venue"
},
  "geometry": {"coordinates":[-83.690421,42.305687],"type":"Point"}
}