{
  "type": "Feature",
  "properties": {
    "iso:country":"US",
    "sg:address":"726 Crescent Lake Rd",
    "sg:city":"Waterford",
    "sg:classifiers":[
        {
            "category":"Retail",
            "subcategory":"Auto Repair",
            "type":"Services"
        }
    ],
    "sg:phone":"+1 248 738 0370",
    "sg:postcode":"48327",
    "sg:province":"MI",
    "sg:tags":[
        "automotive"
    ],
    "wof:name":"P & P Glass",
    "wof:placetype":"venue"
},
  "geometry": {"coordinates":[-83.3857,42.651204],"type":"Point"}
}