{
  "type": "Feature",
  "properties": {
    "iso:country":"US",
    "sg:address":"950 Market Ave SW",
    "sg:city":"Grand Rapids",
    "sg:classifiers":[
        {
            "category":"Wholesale",
            "subcategory":"Machinery & Supplies",
            "type":"Manufacturing & Wholesale Goods"
        }
    ],
    "sg:phone":"+1 616 235 3210",
    "sg:postcode":"49503",
    "sg:province":"MI",
    "sg:tags":[
        "incinerator"
    ],
    "sg:website":"www.covantaenergy.com",
    "wof:name":"Covanta Energy",
    "wof:placetype":"venue"
},
  "geometry": {"coordinates":[-85.68902799999999,42.95155],"type":"Point"}
}