{
  "type": "Feature",
  "properties": {
    "iso:country":"US",
    "sg:address":"11767 Fisk Rd",
    "sg:city":"Belding",
    "sg:classifiers":[
        {
            "category":"Manufacturing",
            "subcategory":"Food",
            "type":"Manufacturing & Wholesale Goods"
        }
    ],
    "sg:phone":"+1 616 794 0467",
    "sg:postcode":"48809",
    "sg:province":"MI",
    "sg:tags":[
        "product",
        "grain",
        "pack"
    ],
    "wof:name":"Grower Service",
    "wof:placetype":"venue"
},
  "geometry": {"coordinates":[-85.305888,43.109737],"type":"Point"}
}