{
  "type": "Feature",
  "properties": {
    "iso:country":"US",
    "sg:address":"5191 Fenton Rd",
    "sg:city":"Flint",
    "sg:classifiers":[
        {
            "category":"Travel",
            "subcategory":"Travel Agent",
            "type":"Entertainment"
        }
    ],
    "sg:phone":"+1 810 238 1000",
    "sg:postcode":"48507",
    "sg:province":"MI",
    "sg:tags":[
        "agency",
        "bureau"
    ],
    "wof:name":"Discount Travel & Tours",
    "wof:placetype":"venue"
},
  "geometry": {"coordinates":[-83.692258,42.952586],"type":"Point"}
}