{
  "type": "Feature",
  "properties": {
    "iso:country":"US",
    "sg:address":"9460 Conner St",
    "sg:city":"Detroit",
    "sg:classifiers":[
        {
            "category":"Personal",
            "subcategory":"Beauty Salon",
            "type":"Services"
        }
    ],
    "sg:phone":"+1 313 839 1065",
    "sg:postcode":"48213",
    "sg:province":"MI",
    "sg:tags":[
        "shop"
    ],
    "wof:name":"Posey Unisex Salon",
    "wof:placetype":"venue"
},
  "geometry": {"coordinates":[-82.99261199999999,42.400572],"type":"Point"}
}