{
  "type": "Feature",
  "properties": {
    "iso:country":"US",
    "sg:address":"512 N Franklin St",
    "sg:city":"Frankenmuth",
    "sg:classifiers":[
        {
            "category":"Retail",
            "subcategory":"Veterinary Services",
            "type":"Services"
        }
    ],
    "sg:phone":"+1 989 652 4461",
    "sg:postcode":"48734",
    "sg:province":"MI",
    "sg:tags":[
        "veterinarian"
    ],
    "wof:name":"Luhring/Mars Vet Clinic",
    "wof:placetype":"venue"
},
  "geometry": {"coordinates":[-83.74046300000001,43.343311],"type":"Point"}
}