{
  "type": "Feature",
  "properties": {
    "iso:country":"US",
    "sg:address":"13735 Indian Rd",
    "sg:city":"Kewadin",
    "sg:classifiers":[
        {
            "category":"Organizations",
            "subcategory":"Religious Organization",
            "type":"Services"
        }
    ],
    "sg:phone":"+1 231 264 0527",
    "sg:postcode":"49648",
    "sg:province":"MI",
    "wof:name":"Kewadin Indian Mission",
    "wof:placetype":"venue"
},
  "geometry": {"coordinates":[-85.369964,44.932076],"type":"Point"}
}