{
  "type": "Feature",
  "properties": {
    "iso:country":"US",
    "sg:address":"529 N Hughes Rd",
    "sg:city":"Howell",
    "sg:classifiers":[
        {
            "category":"Professional",
            "subcategory":"Research",
            "type":"Services"
        }
    ],
    "sg:phone":"+1 517 548 3200",
    "sg:postcode":"48843",
    "sg:province":"MI",
    "sg:tags":[
        "foundation",
        "philanthropic"
    ],
    "wof:name":"Angelo & Sons Foundation",
    "wof:placetype":"venue"
},
  "geometry": {"coordinates":[-83.855035,42.602272],"type":"Point"}
}