{
  "type": "Feature",
  "properties": {
    "iso:country":"US",
    "sg:address":"3535 Ronald St",
    "sg:city":"Lansing",
    "sg:classifiers":[
        {
            "category":"Retail",
            "subcategory":"Repair Shop",
            "type":"Services"
        }
    ],
    "sg:phone":"+1 517 882 4180",
    "sg:postcode":"48911",
    "sg:province":"MI",
    "wof:name":"Top Flight Cleaning",
    "wof:placetype":"venue"
},
  "geometry": {"coordinates":[-84.599187,42.687337],"type":"Point"}
}