{
  "type": "Feature",
  "properties": {
    "iso:country":"US",
    "sg:address":"36101 Woodward Ave",
    "sg:city":"Birmingham",
    "sg:classifiers":[
        {
            "category":"Autos & Motor Vehicles",
            "subcategory":"Fuel & Gas Station",
            "type":"Retail Goods"
        }
    ],
    "sg:phone":"+1 248 647 0020",
    "sg:postcode":"48009",
    "sg:province":"MI",
    "wof:name":"Ghafari Mobile 1",
    "wof:placetype":"venue"
},
  "geometry": {"coordinates":[-83.220367,42.554808],"type":"Point"}
}