{
  "type": "Feature",
  "properties": {
    "iso:country":"US",
    "sg:address":"548 Superior St",
    "sg:city":"River Rouge",
    "sg:classifiers":[
        {
            "category":"Building & Trades",
            "subcategory":"Construction",
            "type":"Services"
        }
    ],
    "sg:phone":"+1 313 383 6864",
    "sg:postcode":"48218",
    "sg:province":"MI",
    "sg:tags":[
        "contractor"
    ],
    "wof:name":"Carmax Enterprises",
    "wof:placetype":"venue"
},
  "geometry": {"coordinates":[-83.145599,42.261902],"type":"Point"}
}