{
  "type": "Feature",
  "properties": {
    "iso:country":"US",
    "sg:address":"2125 S Telegraph Rd",
    "sg:city":"Bloomfield Hills",
    "sg:classifiers":[
        {
            "category":"Retail",
            "subcategory":"Auto Repair",
            "type":"Services"
        }
    ],
    "sg:phone":"+1 248 334 3600",
    "sg:postcode":"48302",
    "sg:province":"MI",
    "sg:tags":[
        "body",
        "automobile",
        "painting"
    ],
    "sg:website":"www.golling.com",
    "wof:name":"Golling Chrysler",
    "wof:placetype":"venue"
},
  "geometry": {"coordinates":[-83.29597800000001,42.606253],"type":"Point"}
}