{
  "type": "Feature",
  "properties": {
    "iso:country":"US",
    "sg:address":"77 Hancock St",
    "sg:city":"Manistee",
    "sg:classifiers":[
        {
            "category":"Recreation",
            "type":"Entertainment"
        }
    ],
    "sg:phone":"+1 231 723 2811",
    "sg:postcode":"49660",
    "sg:province":"MI",
    "sg:tags":[
        "paint",
        "ball",
        "sport"
    ],
    "wof:name":"Paintball Extreme & Arcade",
    "wof:placetype":"venue"
},
  "geometry": {"coordinates":[-86.31612199999999,44.24655],"type":"Point"}
}