{
  "type": "Feature",
  "properties": {
    "iso:country":"US",
    "sg:address":"21 S Glenwood Ave",
    "sg:city":"Pontiac",
    "sg:classifiers":[
        {
            "category":"Health Services",
            "subcategory":"Hospital",
            "type":"Services"
        }
    ],
    "sg:phone":"+1 248 334 6667",
    "sg:postcode":"48342",
    "sg:province":"MI",
    "sg:tags":[
        "mental"
    ],
    "wof:name":"Fair",
    "wof:placetype":"venue"
},
  "geometry": {"coordinates":[-83.283939,42.649963],"type":"Point"}
}