{
  "type": "Feature",
  "properties": {
    "iso:country":"US",
    "sg:address":"336 Dana St NW",
    "sg:city":"Comstock Park",
    "sg:classifiers":[
        {
            "category":"Building & Trades",
            "subcategory":"Cleaning & Sanitation",
            "type":"Services"
        }
    ],
    "sg:phone":"+1 616 784 6157",
    "sg:postcode":"49321",
    "sg:province":"MI",
    "sg:tags":[
        "maintenance"
    ],
    "wof:name":"Cmd Cleaning",
    "wof:placetype":"venue"
},
  "geometry": {"coordinates":[-85.67125799999999,43.031542],"type":"Point"}
}