{
  "type": "Feature",
  "properties": {
    "iso:country":"US",
    "sg:address":"201 Bridge Park Dr",
    "sg:city":"Charlevoix",
    "sg:classifiers":[
        {
            "category":"Health Services",
            "subcategory":"Doctor",
            "type":"Services"
        }
    ],
    "sg:phone":"+1 231 547 9516",
    "sg:postcode":"49720",
    "sg:province":"MI",
    "sg:tags":[
        "dentist"
    ],
    "wof:name":"Porter & Assoc Inc",
    "wof:placetype":"venue"
},
  "geometry": {"coordinates":[-85.25818099999999,45.317908],"type":"Point"}
}