{
  "type": "Feature",
  "properties": {
    "iso:country":"US",
    "sg:address":"5704 Lakeview Dr",
    "sg:city":"Interlochen",
    "sg:classifiers":[
        {
            "category":"Freight",
            "type":"Transportation"
        }
    ],
    "sg:phone":"+1 231 276 9697",
    "sg:postcode":"49643",
    "sg:province":"MI",
    "sg:tags":[
        "hauling",
        "trucking"
    ],
    "wof:name":"Graybeard Express",
    "wof:placetype":"venue"
},
  "geometry": {"coordinates":[-85.77342899999999,44.609706],"type":"Point"}
}