{
  "type": "Feature",
  "properties": {
    "iso:country":"US",
    "sg:address":"53441 Odilon Ave",
    "sg:city":"Utica",
    "sg:classifiers":[
        {
            "category":"Manufacturing",
            "subcategory":"Retail Goods",
            "type":"Manufacturing & Wholesale Goods"
        }
    ],
    "sg:phone":"+1 586 781 4381",
    "sg:postcode":"48316",
    "sg:province":"MI",
    "sg:tags":[
        "lead",
        "mfg"
    ],
    "wof:name":"Watercolors By Barbara",
    "wof:placetype":"venue"
},
  "geometry": {"coordinates":[-83.047747,42.690857],"type":"Point"}
}