{
  "type": "Feature",
  "properties": {
    "iso:country":"US",
    "sg:address":"2086 Werth Rd",
    "sg:city":"Alpena",
    "sg:classifiers":[
        {
            "category":"Organizations",
            "subcategory":"Religious Organization",
            "type":"Services"
        }
    ],
    "sg:phone":"+1 989 358 0338",
    "sg:postcode":"49707",
    "sg:province":"MI",
    "sg:tags":[
        "church"
    ],
    "sg:website":"www.livinghopealpena.com",
    "wof:name":"Living Hope Church",
    "wof:placetype":"venue"
},
  "geometry": {"coordinates":[-83.462633,45.041121],"type":"Point"}
}