{
  "type": "Feature",
  "properties": {
    "iso:country":"US",
    "sg:address":"1131 N Summers Rd",
    "sg:city":"Imlay City",
    "sg:classifiers":[
        {
            "category":"Retail",
            "subcategory":"Repair Shop",
            "type":"Services"
        }
    ],
    "sg:phone":"+1 810 724 1765",
    "sg:postcode":"48444",
    "sg:province":"MI",
    "sg:tags":[
        "welding"
    ],
    "wof:name":"Granz Welding",
    "wof:placetype":"venue"
},
  "geometry": {"coordinates":[-83.109939,43.074742],"type":"Point"}
}