{
  "type": "Feature",
  "properties": {
    "iso:country":"US",
    "sg:address":"48751 Heydenreich Rd",
    "sg:city":"Macomb",
    "sg:classifiers":[
        {
            "category":"Building & Trades",
            "subcategory":"Cleaning & Sanitation",
            "type":"Services"
        }
    ],
    "sg:phone":"+1 586 226 1655",
    "sg:postcode":"48044",
    "sg:province":"MI",
    "sg:tags":[
        "maintenance"
    ],
    "wof:name":"Great Lakes Air Tech Inc",
    "wof:placetype":"venue"
},
  "geometry": {"coordinates":[-82.91708800000001,42.654576],"type":"Point"}
}