{
  "type": "Feature",
  "properties": {
    "iso:country":"US",
    "sg:address":"3035 Flushing Rd",
    "sg:city":"Flint",
    "sg:classifiers":[
        {
            "category":"Personal",
            "subcategory":"Beauty Salon",
            "type":"Services"
        }
    ],
    "sg:phone":"+1 810 424 0322",
    "sg:postcode":"48504",
    "sg:province":"MI",
    "sg:tags":[
        "shop"
    ],
    "wof:name":"Connie's Place",
    "wof:placetype":"venue"
},
  "geometry": {"coordinates":[-83.733256,43.024782],"type":"Point"}
}