{
  "type": "Feature",
  "properties": {
    "iso:country":"US",
    "sg:address":"42054 Duxbury Dr",
    "sg:city":"Sterling Heights",
    "sg:classifiers":[
        {
            "category":"Health Services",
            "subcategory":"Clinic",
            "type":"Services"
        }
    ],
    "sg:phone":"+1 586 532 7185",
    "sg:postcode":"48313",
    "sg:province":"MI",
    "sg:tags":[
        "specialty",
        "outpatient"
    ],
    "wof:name":"Pleasant Rehab Services Inc",
    "wof:placetype":"venue"
},
  "geometry": {"coordinates":[-82.98812100000001,42.604212],"type":"Point"}
}