{
  "type": "Feature",
  "properties": {
    "iso:country":"US",
    "sg:address":"4190 S 39 Rd",
    "sg:city":"Cadillac",
    "sg:classifiers":[
        {
            "category":"Building & Trades",
            "subcategory":"Construction",
            "type":"Services"
        }
    ],
    "sg:phone":"+1 231 779 4077",
    "sg:postcode":"49601",
    "sg:province":"MI",
    "sg:tags":[
        "concrete",
        "cutting",
        "breaking",
        "sawing"
    ],
    "wof:name":"Cadillac Concrete Sawing",
    "wof:placetype":"venue"
},
  "geometry": {"coordinates":[-85.436487,44.228136],"type":"Point"}
}