{
  "type": "Feature",
  "properties": {
    "iso:country":"US",
    "sg:address":"6130 Idlewyle Rd",
    "sg:city":"Bloomfield Hills",
    "sg:classifiers":[
        {
            "category":"Professional",
            "subcategory":"Management & Consulting",
            "type":"Services"
        }
    ],
    "sg:phone":"+1 248 851 3121",
    "sg:postcode":"48301",
    "sg:province":"MI",
    "sg:tags":[
        "public",
        "relations"
    ],
    "wof:name":"Rose Communications",
    "wof:placetype":"venue"
},
  "geometry": {"coordinates":[-83.310636,42.548169],"type":"Point"}
}