{
  "type": "Feature",
  "properties": {
    "iso:country":"US",
    "sg:address":"792 S Main St",
    "sg:city":"Chelsea",
    "sg:classifiers":[
        {
            "category":"Building & Trades",
            "subcategory":"Construction",
            "type":"Services"
        }
    ],
    "sg:phone":"+1 734 475 1146",
    "sg:postcode":"48118",
    "sg:province":"MI",
    "sg:tags":[
        "hanging",
        "contractor"
    ],
    "wof:name":"J & S Painting",
    "wof:placetype":"venue"
},
  "geometry": {"coordinates":[-84.020961,42.310755],"type":"Point"}
}