{
  "type": "Feature",
  "properties": {
    "iso:country":"US",
    "sg:address":"4785 Osborne Rd",
    "sg:city":"Delton",
    "sg:classifiers":[
        {
            "category":"Building & Trades",
            "subcategory":"Electrical",
            "type":"Services"
        }
    ],
    "sg:phone":"+1 269 671 4788",
    "sg:postcode":"49046",
    "sg:province":"MI",
    "sg:tags":[
        "contractor"
    ],
    "wof:name":"EPC Electric LLC",
    "wof:placetype":"venue"
},
  "geometry": {"coordinates":[-85.381664,42.47053],"type":"Point"}
}