{
  "type": "Feature",
  "properties": {
    "iso:country":"US",
    "sg:address":"3980 Crooks Rd",
    "sg:city":"Rochester Hills",
    "sg:classifiers":[
        {
            "category":"Autos & Motor Vehicles",
            "subcategory":"Fuel & Gas Station",
            "type":"Retail Goods"
        }
    ],
    "sg:phone":"+1 248 852 2191",
    "sg:postcode":"48309",
    "sg:province":"MI",
    "sg:tags":[
        "oil"
    ],
    "wof:name":"Frank's Fast Break",
    "wof:placetype":"venue"
},
  "geometry": {"coordinates":[-83.170134,42.62373],"type":"Point"}
}