{
  "type": "Feature",
  "properties": {
    "iso:country":"US",
    "sg:address":"1529 W Hamlin Rd",
    "sg:city":"Rochester Hills",
    "sg:classifiers":[
        {
            "category":"Manufacturing",
            "subcategory":"Tools & Machinery",
            "type":"Manufacturing & Wholesale Goods"
        }
    ],
    "sg:phone":"+1 248 853 2300",
    "sg:postcode":"48309",
    "sg:province":"MI",
    "sg:tags":[
        "equipment",
        "system",
        "automation"
    ],
    "wof:name":"MNJ Automation",
    "wof:placetype":"venue"
},
  "geometry": {"coordinates":[-83.160307,42.651639],"type":"Point"}
}