{
  "type": "Feature",
  "properties": {
    "iso:country":"US",
    "sg:address":"923 S Farragut St",
    "sg:city":"Bay City",
    "sg:classifiers":[
        {
            "category":"Building & Trades",
            "subcategory":"Construction",
            "type":"Services"
        }
    ],
    "sg:phone":"+1 989 893 7373",
    "sg:postcode":"48708",
    "sg:province":"MI",
    "sg:tags":[
        "designer",
        "dealer",
        "pool",
        "swimming"
    ],
    "wof:name":"Tri-City Pools",
    "wof:placetype":"venue"
},
  "geometry": {"coordinates":[-83.88024900000001,43.580405],"type":"Point"}
}