{
  "type": "Feature",
  "properties": {
    "iso:country":"US",
    "sg:address":"3410 Wells Rd",
    "sg:city":"Petersburg",
    "sg:classifiers":[
        {
            "category":"Building & Trades",
            "subcategory":"Construction",
            "type":"Services"
        }
    ],
    "sg:phone":"+1 734 279 1873",
    "sg:postcode":"49270",
    "sg:province":"MI",
    "sg:tags":[
        "excavating",
        "contractor"
    ],
    "wof:name":"Lewis Roe Excavating",
    "wof:placetype":"venue"
},
  "geometry": {"coordinates":[-83.651445,41.900736],"type":"Point"}
}