{
  "type": "Feature",
  "properties": {
    "iso:country":"US",
    "sg:address":"285 12th St",
    "sg:city":"Plainwell",
    "sg:classifiers":[
        {
            "category":"Building & Trades",
            "subcategory":"Construction",
            "type":"Services"
        }
    ],
    "sg:phone":"+1 269 685 9470",
    "sg:postcode":"49080",
    "sg:province":"MI",
    "sg:tags":[
        "concrete",
        "contractor"
    ],
    "wof:name":"Cherry Valley Concrete Inc",
    "wof:placetype":"venue"
},
  "geometry": {"coordinates":[-85.662387,42.44104],"type":"Point"}
}