{
  "type": "Feature",
  "properties": {
    "iso:country":"US",
    "sg:address":"206 N Main St",
    "sg:city":"Davison",
    "sg:classifiers":[
        {
            "category":"Shopping",
            "subcategory":"Gifts & Souvenirs",
            "type":"Retail Goods"
        }
    ],
    "sg:phone":"+1 810 658 8388",
    "sg:postcode":"48423",
    "sg:province":"MI",
    "sg:tags":[
        "shop"
    ],
    "wof:name":"Country Life",
    "wof:placetype":"venue"
},
  "geometry": {"coordinates":[-83.516693,43.031752],"type":"Point"}
}