{
  "type": "Feature",
  "properties": {
    "iso:country":"US",
    "sg:address":"9945 Spicer Rd",
    "sg:city":"Brighton",
    "sg:classifiers":[
        {
            "category":"Building & Trades",
            "subcategory":"Landscaping Services",
            "type":"Services"
        }
    ],
    "sg:phone":"+1 734 449 2449",
    "sg:postcode":"48116",
    "sg:province":"MI",
    "wof:name":"Gordons Lawn & Tree Service",
    "wof:placetype":"venue"
},
  "geometry": {"coordinates":[-83.75438699999999,42.453679],"type":"Point"}
}