{
  "type": "Feature",
  "properties": {
    "iso:country":"US",
    "sg:address":"5131 Maple Grove Rd",
    "sg:city":"Charlevoix",
    "sg:classifiers":[
        {
            "category":"Retail",
            "subcategory":"Laundry & Dry Cleaning",
            "type":"Services"
        }
    ],
    "sg:phone":"+1 231 237 0000",
    "sg:postcode":"49720",
    "sg:province":"MI",
    "sg:tags":[
        "cleaners",
        "rug",
        "carpet"
    ],
    "wof:name":"Service Master Pro Clng Svc",
    "wof:placetype":"venue"
},
  "geometry": {"coordinates":[-85.13850100000001,45.284683],"type":"Point"}
}