{
  "type": "Feature",
  "properties": {
    "iso:country":"US",
    "sg:address":"4556 N Branch Rd",
    "sg:city":"North Branch",
    "sg:phone":"+1 810 688 2918",
    "sg:postcode":"48461",
    "sg:province":"MI",
    "sg:tags":[
        "farm",
        "corn"
    ],
    "wof:name":"Rocky Ridge Pine",
    "wof:placetype":"venue"
},
  "geometry": {"coordinates":[-83.160008,43.230273],"type":"Point"}
}