{
  "type": "Feature",
  "properties": {
    "iso:country":"US",
    "sg:address":"408 W River Rd",
    "sg:city":"Oscoda",
    "sg:classifiers":[
        {
            "category":"Shopping",
            "subcategory":"Computers & Home Electronics",
            "type":"Retail Goods"
        }
    ],
    "sg:phone":"+1 989 305 0596",
    "sg:postcode":"48750",
    "sg:province":"MI",
    "sg:tags":[
        "equipment",
        "dealer"
    ],
    "wof:name":"Den's Computers Inc",
    "wof:placetype":"venue"
},
  "geometry": {"coordinates":[-83.337259,44.420458],"type":"Point"}
}