{
  "type": "Feature",
  "properties": {
    "iso:country":"US",
    "sg:address":"1498 N Goetze Rd",
    "sg:city":"Carsonville",
    "sg:phone":"+1 810 622 8765",
    "sg:postcode":"48419",
    "sg:province":"MI",
    "sg:tags":[
        "farm",
        "grain",
        "cash"
    ],
    "wof:name":"Thomas Twiss",
    "wof:placetype":"venue"
},
  "geometry": {"coordinates":[-82.63322599999999,43.466311],"type":"Point"}
}