{
  "type": "Feature",
  "properties": {
    "iso:country":"US",
    "sg:address":"4459 Paul Fortino Dr",
    "sg:city":"Swartz Creek",
    "sg:classifiers":[
        {
            "category":"Banks & Credit Unions",
            "subcategory":"Bank",
            "type":"Services"
        }
    ],
    "sg:phone":"+1 810 635 4466",
    "sg:postcode":"48473",
    "sg:province":"MI",
    "sg:tags":[
        "commercial"
    ],
    "wof:name":"Bank One",
    "wof:placetype":"venue"
},
  "geometry": {"coordinates":[-83.83358800000001,42.958129],"type":"Point"}
}