{
  "type": "Feature",
  "properties": {
    "iso:country":"US",
    "sg:address":"400 W Hamlin Rd",
    "sg:city":"Rochester Hills",
    "sg:classifiers":[
        {
            "category":"Organizations",
            "subcategory":"Religious Organization",
            "type":"Services"
        }
    ],
    "sg:phone":"+1 248 656 1630",
    "sg:postcode":"48307",
    "sg:province":"MI",
    "sg:tags":[
        "church"
    ],
    "wof:name":"St Mark Orthodox Church",
    "wof:placetype":"venue"
},
  "geometry": {"coordinates":[-83.139129,42.652381],"type":"Point"}
}