{
  "type": "Feature",
  "properties": {
    "iso:country":"US",
    "sg:address":"104 E May St",
    "sg:city":"Mt Pleasant",
    "sg:classifiers":[
        {
            "category":"Food & Beverages",
            "subcategory":"Groceries & Convenience Stores",
            "type":"Retail Goods"
        }
    ],
    "sg:phone":"+1 989 773 7993",
    "sg:postcode":"48858",
    "sg:province":"MI",
    "wof:name":"Big Mike's Food & Beverage",
    "wof:placetype":"venue"
},
  "geometry": {"coordinates":[-84.776549,43.596186],"type":"Point"}
}