{
  "type": "Feature",
  "properties": {
    "iso:country":"US",
    "sg:address":"4500 E Grand Lake Rd",
    "sg:city":"Presque Isle",
    "sg:classifiers":[
        {
            "category":"Recreation",
            "type":"Entertainment"
        }
    ],
    "sg:phone":"+1 989 595 9917",
    "sg:postcode":"49777",
    "sg:province":"MI",
    "sg:tags":[
        "historical"
    ],
    "wof:name":"Presque Isle Light House",
    "wof:placetype":"venue"
},
  "geometry": {"coordinates":[-83.49029400000001,45.354498],"type":"Point"}
}