{
  "type": "Feature",
  "properties": {
    "iso:country":"US",
    "sg:address":"1201 Wohlert St",
    "sg:city":"Angola",
    "sg:classifiers":[
        {
            "category":"Wholesale",
            "subcategory":"Machinery & Supplies",
            "type":"Manufacturing & Wholesale Goods"
        }
    ],
    "sg:phone":"+1 260 665 5396",
    "sg:postcode":"46703",
    "sg:province":"MI",
    "sg:tags":[
        "engine"
    ],
    "wof:name":"Dave's Diesel",
    "wof:placetype":"venue"
},
  "geometry": {"coordinates":[-85.00442,41.65602],"type":"Point"}
}