{
  "type": "Feature",
  "properties": {
    "iso:country":"US",
    "sg:address":"919 Baldwin Rd",
    "sg:city":"Lapeer",
    "sg:classifiers":[
        {
            "category":"Building & Trades",
            "subcategory":"Construction",
            "type":"Services"
        }
    ],
    "sg:phone":"+1 810 664 4707",
    "sg:postcode":"48446",
    "sg:province":"MI",
    "sg:tags":[
        "house"
    ],
    "wof:name":"J&R Construction & Laid O",
    "wof:placetype":"venue"
},
  "geometry": {"coordinates":[-83.32354100000001,43.037997],"type":"Point"}
}