{
  "type": "Feature",
  "properties": {
    "iso:country":"US",
    "sg:address":"1403 E 5th St",
    "sg:city":"Royal Oak",
    "sg:classifiers":[
        {
            "category":"Organizations",
            "subcategory":"Community Association",
            "type":"Services"
        }
    ],
    "sg:phone":"+1 248 398 7003",
    "sg:postcode":"48067",
    "sg:province":"MI",
    "wof:name":"Detroit Chapter American Stats",
    "wof:placetype":"venue"
},
  "geometry": {"coordinates":[-83.127966,42.486753],"type":"Point"}
}