{
  "type": "Feature",
  "properties": {
    "iso:country":"US",
    "sg:address":"6625 3rd St",
    "sg:city":"Gagetown",
    "sg:classifiers":[
        {
            "category":"Restaurant",
            "type":"Food & Drink"
        }
    ],
    "sg:phone":"+1 989 665 9971",
    "sg:postcode":"48735",
    "sg:province":"MI",
    "wof:name":"Sherwood On The Hill Golf Crse",
    "wof:placetype":"venue"
},
  "geometry": {"coordinates":[-83.24667700000001,43.657253],"type":"Point"}
}