{
  "type": "Feature",
  "properties": {
    "iso:country":"US",
    "sg:address":"48 Market St",
    "sg:city":"Mt Clemens",
    "sg:classifiers":[
        {
            "category":"Banks & Credit Unions",
            "subcategory":"Investment Brokerage",
            "type":"Services"
        }
    ],
    "sg:phone":"+1 586 463 3633",
    "sg:postcode":"48043",
    "sg:province":"MI",
    "sg:tags":[
        "advisory",
        "financial"
    ],
    "wof:name":"M B Squared Financial Svc Co",
    "wof:placetype":"venue"
},
  "geometry": {"coordinates":[-82.875176,42.598046],"type":"Point"}
}