{
  "type": "Feature",
  "properties": {
    "iso:country":"US",
    "sg:address":"200 Ottawa Ave NW",
    "sg:city":"Grand Rapids",
    "sg:classifiers":[
        {
            "category":"Professional",
            "subcategory":"Lawyer & Legal Services",
            "type":"Services"
        }
    ],
    "sg:phone":"+1 616 459 3200",
    "sg:postcode":"49503",
    "sg:province":"MI",
    "sg:tags":[
        "attorney"
    ],
    "wof:name":"Ronald M Redick",
    "wof:placetype":"venue"
},
  "geometry": {"coordinates":[-85.670084,42.970428],"type":"Point"}
}