{
  "type": "Feature",
  "properties": {
    "iso:country":"US",
    "sg:address":"720 W Main St",
    "sg:city":"Farwell",
    "sg:classifiers":[
        {
            "category":"Food & Beverages",
            "subcategory":"Groceries & Convenience Stores",
            "type":"Retail Goods"
        }
    ],
    "sg:phone":"+1 989 588 4161",
    "sg:postcode":"48622",
    "sg:province":"MI",
    "wof:name":"Farwell Trading Post",
    "wof:placetype":"venue"
},
  "geometry": {"coordinates":[-84.874359,43.835837],"type":"Point"}
}