{
  "type": "Feature",
  "properties": {
    "iso:country":"US",
    "sg:address":"2716 Gary St",
    "sg:city":"Midland",
    "sg:classifiers":[
        {
            "category":"Shopping",
            "type":"Retail Goods"
        }
    ],
    "sg:phone":"+1 989 832 0284",
    "sg:postcode":"48642",
    "sg:province":"MI",
    "sg:tags":[
        "cosmetic",
        "perfume"
    ],
    "wof:name":"Mary Kay Cosmetics",
    "wof:placetype":"venue"
},
  "geometry": {"coordinates":[-84.20129900000001,43.624347],"type":"Point"}
}