{
  "type": "Feature",
  "properties": {
    "iso:country":"US",
    "sg:address":"333 Market Ave SW",
    "sg:city":"Grand Rapids",
    "sg:classifiers":[
        {
            "category":"Government",
            "subcategory":"Office",
            "type":"Public Place"
        }
    ],
    "sg:phone":"+1 616 456 3223",
    "sg:postcode":"49503",
    "sg:province":"MI",
    "sg:tags":[
        "executive"
    ],
    "wof:name":"Motor Equipment Systems",
    "wof:placetype":"venue"
},
  "geometry": {"coordinates":[-85.678071,42.957811],"type":"Point"}
}