{
  "type": "Feature",
  "properties": {
    "iso:country":"US",
    "sg:address":"483 Gros Cap Rd",
    "sg:city":"Saint Ignace",
    "sg:classifiers":[
        {
            "category":"Manufacturing",
            "subcategory":"Lumber",
            "type":"Manufacturing & Wholesale Goods"
        }
    ],
    "sg:phone":"+1 906 643 7515",
    "sg:postcode":"49781",
    "sg:province":"MI",
    "sg:tags":[
        "forestry",
        "consulting"
    ],
    "wof:name":"D & S Forestry Services Co",
    "wof:placetype":"venue"
},
  "geometry": {"coordinates":[-84.82613499999999,45.870636],"type":"Point"}
}