{
  "type": "Feature",
  "properties": {
    "iso:country":"US",
    "sg:address":"9550 Downes St NE",
    "sg:city":"Lowell",
    "sg:classifiers":[
        {
            "category":"Professional",
            "type":"Services"
        }
    ],
    "sg:phone":"+1 616 676 3330",
    "sg:postcode":"49331",
    "sg:province":"MI",
    "sg:tags":[
        "establishment"
    ],
    "sg:website":"www.vantagegroupinc.com",
    "wof:name":"Vantage Group",
    "wof:placetype":"venue"
},
  "geometry": {"coordinates":[-85.438996,42.994275],"type":"Point"}
}