{
  "type": "Feature",
  "properties": {
    "iso:country":"US",
    "sg:address":"8835 Red Arrow Hwy",
    "sg:city":"Bridgman",
    "sg:classifiers":[
        {
            "category":"Building & Trades",
            "subcategory":"Electrical",
            "type":"Services"
        }
    ],
    "sg:phone":"+1 269 465 7039",
    "sg:postcode":"49106",
    "sg:province":"MI",
    "sg:tags":[
        "electric",
        "contractor"
    ],
    "wof:name":"Calbrit Electrical Contracting",
    "wof:placetype":"venue"
},
  "geometry": {"coordinates":[-86.55266899999999,41.960057],"type":"Point"}
}