{
  "type": "Feature",
  "properties": {
    "iso:country":"US",
    "sg:address":"1002 Bianchi Ln",
    "sg:city":"Gwinn",
    "sg:classifiers":[
        {
            "category":"Organizations",
            "subcategory":"Religious Organization",
            "type":"Services"
        }
    ],
    "sg:phone":"+1 906 346 7512",
    "sg:postcode":"49841",
    "sg:province":"MI",
    "sg:tags":[
        "monastery",
        "convent"
    ],
    "wof:name":"Sisters Of St Paul De Chart",
    "wof:placetype":"venue"
},
  "geometry": {"coordinates":[-87.36741499999999,46.261243],"type":"Point"}
}