{
  "type": "Feature",
  "properties": {
    "iso:country":"US",
    "sg:address":"206 E Rose Lake Rd",
    "sg:city":"Coldwater",
    "sg:classifiers":[
        {
            "category":"Manufacturing",
            "subcategory":"Signs",
            "type":"Manufacturing & Wholesale Goods"
        },
        {
            "category":"Retail",
            "subcategory":"Auto Repair",
            "type":"Services"
        }
    ],
    "sg:phone":"+1 517 238 4475",
    "sg:postcode":"49036",
    "sg:province":"MI",
    "sg:tags":[
        "body",
        "equipment",
        "r",
        "business"
    ],
    "wof:name":"Haylett Signs Inc",
    "wof:placetype":"venue"
},
  "geometry": {"coordinates":[-85.038977,41.859094],"type":"Point"}
}