{
  "type": "Feature",
  "properties": {
    "iso:country":"US",
    "sg:address":"1418 Hall St SE",
    "sg:city":"Grand Rapids",
    "sg:classifiers":[
        {
            "category":"Manufacturing",
            "subcategory":"Paper Products",
            "type":"Manufacturing & Wholesale Goods"
        }
    ],
    "sg:phone":"+1 616 241 2761",
    "sg:postcode":"49506",
    "sg:province":"MI",
    "sg:tags":[
        "mill"
    ],
    "wof:name":"N S A C Spotlight",
    "wof:placetype":"venue"
},
  "geometry": {"coordinates":[-85.63451499999999,42.941012],"type":"Point"}
}