{
  "type": "Feature",
  "properties": {
    "iso:country":"US",
    "sg:address":"1518 E Lansing Dr",
    "sg:city":"East Lansing",
    "sg:classifiers":[
        {
            "category":"Retail",
            "subcategory":"Laundry & Dry Cleaning",
            "type":"Services"
        }
    ],
    "sg:phone":"+1 517 332 5009",
    "sg:postcode":"48823",
    "sg:province":"MI",
    "sg:tags":[
        "garment",
        "pressing",
        "agent",
        "cleaners"
    ],
    "wof:name":"Bary Ames Cleaners",
    "wof:placetype":"venue"
},
  "geometry": {"coordinates":[-84.45224399999999,42.748563],"type":"Point"}
}