{
  "type": "Feature",
  "properties": {
    "iso:country":"US",
    "sg:address":"4296 E River Rd",
    "sg:city":"Oscoda",
    "sg:classifiers":[
        {
            "category":"Manufacturing",
            "subcategory":"Tools & Machinery",
            "type":"Manufacturing & Wholesale Goods"
        }
    ],
    "sg:phone":"+1 989 739 7181",
    "sg:postcode":"48750",
    "sg:province":"MI",
    "sg:tags":[
        "machine"
    ],
    "wof:name":"Fine Manufacturing Co",
    "wof:placetype":"venue"
},
  "geometry": {"coordinates":[-83.34659499999999,44.423462],"type":"Point"}
}