{
  "type": "Feature",
  "properties": {
    "iso:country":"US",
    "sg:address":"1959 E Stoney Corners Rd",
    "sg:city":"Mc Bain",
    "sg:classifiers":[
        {
            "category":"Building & Trades",
            "subcategory":"Plumbing",
            "type":"Services"
        }
    ],
    "sg:phone":"+1 231 825 2455",
    "sg:postcode":"49657",
    "sg:province":"MI",
    "sg:tags":[
        "conditioning",
        "air",
        "system",
        "contractor"
    ],
    "wof:name":"DJS Heating & Cooling",
    "wof:placetype":"venue"
},
  "geometry": {"coordinates":[-85.05470200000001,44.192583],"type":"Point"}
}