{
  "type": "Feature",
  "properties": {
    "iso:country":"US",
    "sg:address":"18045 McDougall St",
    "sg:city":"Detroit",
    "sg:classifiers":[
        {
            "category":"Organizations",
            "subcategory":"Religious Organization",
            "type":"Services"
        }
    ],
    "sg:phone":"+1 313 891 1524",
    "sg:postcode":"48234",
    "sg:province":"MI",
    "wof:name":"Antioch Mssonary Baptst Church",
    "wof:placetype":"venue"
},
  "geometry": {"coordinates":[-83.070741,42.426691],"type":"Point"}
}