{
  "type": "Feature",
  "properties": {
    "iso:country":"US",
    "sg:address":"39843 Memory Ln",
    "sg:city":"Harrison Twp",
    "sg:classifiers":[
        {
            "category":"Recreation",
            "type":"Entertainment"
        }
    ],
    "sg:phone":"+1 586 468 2572",
    "sg:postcode":"48045",
    "sg:province":"MI",
    "sg:tags":[
        "guide"
    ],
    "wof:name":"Canvasback Charters",
    "wof:placetype":"venue"
},
  "geometry": {"coordinates":[-82.82971000000001,42.592579],"type":"Point"}
}