{
  "type": "Feature",
  "properties": {
    "iso:country":"US",
    "sg:address":"6671 10th Ave",
    "sg:city":"Blanchard",
    "sg:classifiers":[
        {
            "category":"Professional",
            "subcategory":"Lawyer & Legal Services",
            "type":"Services"
        }
    ],
    "sg:phone":"+1 989 561 2459",
    "sg:postcode":"49310",
    "sg:province":"MI",
    "wof:name":"Prepaid Legal",
    "wof:placetype":"venue"
},
  "geometry": {"coordinates":[-85.105576,43.567077],"type":"Point"}
}