{
  "type": "Feature",
  "properties": {
    "iso:country":"US",
    "sg:address":"17 Park St",
    "sg:city":"Traverse City",
    "sg:classifiers":[
        {
            "category":"Professional",
            "subcategory":"Business Services",
            "type":"Services"
        }
    ],
    "sg:phone":"+1 231 943 4475",
    "sg:postcode":"49684",
    "sg:province":"MI",
    "wof:name":"Cynthias Business",
    "wof:placetype":"venue"
},
  "geometry": {"coordinates":[-85.677763,44.686416],"type":"Point"}
}