{
  "type": "Feature",
  "properties": {
    "iso:country":"US",
    "sg:address":"10814 Lincoln Dr",
    "sg:city":"Huntington Woods",
    "sg:classifiers":[
        {
            "category":"Organizations",
            "subcategory":"Community Association",
            "type":"Services"
        }
    ],
    "sg:phone":"+1 248 545 7495",
    "sg:postcode":"48070",
    "sg:province":"MI",
    "wof:name":"Rose Acrution Order",
    "wof:placetype":"venue"
},
  "geometry": {"coordinates":[-83.170721,42.482361],"type":"Point"}
}