{
  "type": "Feature",
  "properties": {
    "iso:country":"US",
    "sg:address":"18500 Grand River Ave",
    "sg:city":"Detroit",
    "sg:classifiers":[
        {
            "category":"Shopping",
            "subcategory":"Pharmacy",
            "type":"Retail Goods"
        }
    ],
    "sg:phone":"+1 313 272 4766",
    "sg:postcode":"48223",
    "sg:province":"MI",
    "sg:tags":[
        "drugstore"
    ],
    "wof:name":"Cvs Pharmacy",
    "wof:placetype":"venue"
},
  "geometry": {"coordinates":[-83.22380099999999,42.403],"type":"Point"}
}