{
  "type": "Feature",
  "properties": {
    "iso:country":"US",
    "sg:address":"261 E 9 Mile Rd",
    "sg:city":"Ferndale",
    "sg:classifiers":[
        {
            "category":"Arts & Performance",
            "subcategory":"Comedy Club",
            "type":"Entertainment"
        }
    ],
    "sg:phone":"+1 248 327 0575",
    "sg:postcode":"48220",
    "sg:province":"MI",
    "sg:website":"www.gocomedy.net",
    "wof:name":"Go Comedy! Improv Theater",
    "wof:placetype":"venue"
},
  "geometry": {"coordinates":[-83.13173999999999,42.460637],"type":"Point"}
}