{
  "type": "Feature",
  "properties": {
    "iso:country":"US",
    "sg:address":"1060 Grenoble Dr",
    "sg:city":"Lansing",
    "sg:classifiers":[
        {
            "category":"Social Services",
            "subcategory":"Child Care",
            "type":"Services"
        }
    ],
    "sg:phone":"+1 517 327 2987",
    "sg:postcode":"48917",
    "sg:province":"MI",
    "sg:tags":[
        "day"
    ],
    "wof:name":"Harris Betty Jean Day Care",
    "wof:placetype":"venue"
},
  "geometry": {"coordinates":[-84.63311299999999,42.722128],"type":"Point"}
}