{
  "type": "Feature",
  "properties": {
    "iso:country":"US",
    "sg:address":"42755 Romeo Plank Rd",
    "sg:city":"Clinton Township",
    "sg:classifiers":[
        {
            "category":"Education",
            "subcategory":"School",
            "type":"Public Place"
        }
    ],
    "sg:phone":"+1 586 226 8261",
    "sg:postcode":"48038",
    "sg:province":"MI",
    "sg:tags":[
        "high",
        "middle",
        "elementary"
    ],
    "wof:name":"Seneca Elementary",
    "wof:placetype":"venue"
},
  "geometry": {"coordinates":[-82.9328,42.611],"type":"Point"}
}