{
  "type": "Feature",
  "properties": {
    "iso:country":"US",
    "sg:address":"623 Kalamazoo Ave",
    "sg:city":"Petoskey",
    "sg:classifiers":[
        {
            "category":"Social Services",
            "subcategory":"Child Care",
            "type":"Services"
        }
    ],
    "sg:phone":"+1 231 347 5361",
    "sg:postcode":"49770",
    "sg:province":"MI",
    "sg:tags":[
        "home",
        "day"
    ],
    "wof:name":"Mary Alton",
    "wof:placetype":"venue"
},
  "geometry": {"coordinates":[-84.94523100000001,45.371743],"type":"Point"}
}