{
  "type": "Feature",
  "properties": {
    "iso:country":"US",
    "sg:address":"716 Lansing Ave",
    "sg:city":"Jackson",
    "sg:classifiers":[
        {
            "category":"Retail",
            "subcategory":"Portrait Studio",
            "type":"Services"
        }
    ],
    "sg:phone":"+1 517 788 5334",
    "sg:postcode":"49202",
    "sg:province":"MI",
    "sg:tags":[
        "photo"
    ],
    "wof:name":"Greta Picklesimer Photogr",
    "wof:placetype":"venue"
},
  "geometry": {"coordinates":[-84.416442,42.258324],"type":"Point"}
}