{
  "type": "Feature",
  "properties": {
    "iso:country":"US",
    "sg:address":"50202 Dennis Ct",
    "sg:city":"Wixom",
    "sg:classifiers":[
        {
            "category":"Shopping",
            "subcategory":"Pharmacy",
            "type":"Retail Goods"
        }
    ],
    "sg:phone":"+1 248 926 8660",
    "sg:postcode":"48393",
    "sg:province":"MI",
    "sg:tags":[
        "aid",
        "first",
        "supply"
    ],
    "wof:name":"Quality First Aid & Safety Inc",
    "wof:placetype":"venue"
},
  "geometry": {"coordinates":[-83.54675,42.524071],"type":"Point"}
}