{
  "type": "Feature",
  "properties": {
    "iso:country":"US",
    "sg:address":"411 Harrison Blvd",
    "sg:city":"Roscommon",
    "sg:classifiers":[
        {
            "category":"Banks & Credit Unions",
            "subcategory":"Bank",
            "type":"Services"
        }
    ],
    "sg:phone":"+1 989 821 4003",
    "sg:postcode":"48653",
    "sg:province":"MI",
    "sg:tags":[
        "mortgage"
    ],
    "wof:name":"Mortgage Institute of MI",
    "wof:placetype":"venue"
},
  "geometry": {"coordinates":[-84.71279,44.442899],"type":"Point"}
}