{
  "type": "Feature",
  "properties": {
    "iso:country":"US",
    "sg:address":"7696 Worden Rd",
    "sg:city":"Beulah",
    "sg:classifiers":[
        {
            "category":"Farming",
            "subcategory":"Farm",
            "type":"Manufacturing & Wholesale Goods"
        }
    ],
    "sg:phone":"+1 231 882 4371",
    "sg:postcode":"49617",
    "sg:province":"MI",
    "wof:name":"Stone & Sons Farm Shop",
    "wof:placetype":"venue"
},
  "geometry": {"coordinates":[-86.087474,44.653817],"type":"Point"}
}