{
  "type": "Feature",
  "properties": {
    "iso:country":"US",
    "sg:address":"9880 E Grand River Ave",
    "sg:city":"Brighton",
    "sg:classifiers":[
        {
            "category":"Professional",
            "subcategory":"Lawyer & Legal Services",
            "type":"Services"
        }
    ],
    "sg:phone":"+1 810 227 6665",
    "sg:postcode":"48116",
    "sg:province":"MI",
    "sg:tags":[
        "attorney"
    ],
    "wof:name":"District Court Defenders Inc",
    "wof:placetype":"venue"
},
  "geometry": {"coordinates":[-83.761785,42.52144],"type":"Point"}
}