{
  "type": "Feature",
  "properties": {
    "iso:country":"US",
    "sg:address":"3777 Sparks Dr SE",
    "sg:city":"Grand Rapids",
    "sg:classifiers":[
        {
            "category":"Real Estate",
            "subcategory":"Real Estate Services",
            "type":"Services"
        }
    ],
    "sg:phone":"+1 616 957 4500",
    "sg:postcode":"49546",
    "sg:province":"MI",
    "sg:tags":[
        "company",
        "title"
    ],
    "wof:name":"Unified Title & Settlement",
    "wof:placetype":"venue"
},
  "geometry": {"coordinates":[-85.570357,42.915592],"type":"Point"}
}