{
  "type": "Feature",
  "properties": {
    "iso:country":"US",
    "sg:address":"11769 Wolf Creek Rd",
    "sg:city":"Hubbard Lake",
    "sg:classifiers":[
        {
            "category":"Building & Trades",
            "subcategory":"Plumbing",
            "type":"Services"
        }
    ],
    "sg:phone":"+1 989 727 4200",
    "sg:postcode":"49747",
    "sg:province":"MI",
    "sg:tags":[
        "heating",
        "contractor"
    ],
    "wof:name":"Hubbard Lake Heating",
    "wof:placetype":"venue"
},
  "geometry": {"coordinates":[-83.62831799999999,44.904866],"type":"Point"}
}