{
  "type": "Feature",
  "properties": {
    "iso:country":"US",
    "sg:address":"2653 Olthoff Dr",
    "sg:city":"Muskegon",
    "sg:classifiers":[
        {
            "category":"Professional",
            "type":"Services"
        }
    ],
    "sg:phone":"+1 231 773 5252",
    "sg:postcode":"49444",
    "sg:province":"MI",
    "sg:tags":[
        "establishment"
    ],
    "wof:name":"SCC LLC",
    "wof:placetype":"venue"
},
  "geometry": {"coordinates":[-86.17428700000001,43.207583],"type":"Point"}
}