{
  "type": "Feature",
  "properties": {
    "iso:country":"US",
    "sg:address":"630 W Ruth Ave",
    "sg:city":"Flint",
    "sg:classifiers":[
        {
            "category":"Building & Trades",
            "subcategory":"Equipment Rental",
            "type":"Services"
        }
    ],
    "sg:phone":"+1 810 785 7539",
    "sg:postcode":"48505",
    "sg:province":"MI",
    "wof:name":"Macks Maintenance",
    "wof:placetype":"venue"
},
  "geometry": {"coordinates":[-83.713472,43.07021],"type":"Point"}
}