{
  "type": "Feature",
  "properties": {
    "iso:country":"US",
    "sg:address":"250 W Church St",
    "sg:city":"Adrian",
    "sg:classifiers":[
        {
            "category":"Taxi",
            "type":"Transportation"
        }
    ],
    "sg:phone":"+1 517 266 8912",
    "sg:postcode":"49221",
    "sg:province":"MI",
    "sg:tags":[
        "taxicab"
    ],
    "wof:name":"Adrian Taxi",
    "wof:placetype":"venue"
},
  "geometry": {"coordinates":[-84.03980799999999,41.898257],"type":"Point"}
}