{
  "type": "Feature",
  "properties": {
    "iso:country":"US",
    "sg:address":"3906 N Euclid Ave",
    "sg:city":"Bay City",
    "sg:classifiers":[
        {
            "category":"Real Estate",
            "subcategory":"Real Estate Agent",
            "type":"Services"
        }
    ],
    "sg:phone":"+1 989 667 3343",
    "sg:postcode":"48706",
    "sg:province":"MI",
    "sg:website":"www.watersedgerealty.com",
    "wof:name":"Waters Edge Realty",
    "wof:placetype":"venue"
},
  "geometry": {"coordinates":[-83.91427,43.625362],"type":"Point"}
}