{
  "type": "Feature",
  "properties": {
    "iso:country":"US",
    "sg:address":"4935 Brookestone Dr NE",
    "sg:city":"Rockford",
    "sg:classifiers":[
        {
            "category":"Shopping",
            "subcategory":"Hobbies, Toys, & Games",
            "type":"Retail Goods"
        }
    ],
    "sg:phone":"+1 616 866 1952",
    "sg:postcode":"49341",
    "sg:province":"MI",
    "wof:name":"Cathy Rinck",
    "wof:placetype":"venue"
},
  "geometry": {"coordinates":[-85.54513300000001,43.16525],"type":"Point"}
}