{
  "type": "Feature",
  "properties": {
    "iso:country":"US",
    "sg:address":"1200 E Michigan Ave Ste 415",
    "sg:city":"Lansing",
    "sg:classifiers":[
        {
            "category":"Health Services",
            "subcategory":"Doctor",
            "type":"Services"
        }
    ],
    "sg:phone":"+1 517 484 2760",
    "sg:postcode":"48912",
    "sg:province":"MI",
    "sg:tags":[
        "physician",
        "pulmonary",
        "surgeon",
        "surgeons",
        "disease"
    ],
    "sg:website":"http://www.pulmonaryandcriticalcareconsultants.com",
    "wof:name":"Pulmonary & Critical Care Consultants",
    "wof:placetype":"venue"
},
  "geometry": {"coordinates":[-84.535713,42.73357],"type":"Point"}
}