{
  "type": "Feature",
  "properties": {
    "iso:country":"US",
    "sg:address":"29085 Fairfax St",
    "sg:city":"Southfield",
    "sg:classifiers":[
        {
            "category":"Building & Trades",
            "subcategory":"Cleaning & Sanitation",
            "type":"Services"
        }
    ],
    "sg:phone":"+1 248 559 3649",
    "sg:postcode":"48076",
    "sg:province":"MI",
    "sg:tags":[
        "maintenance"
    ],
    "wof:name":"Dynamic Cleaning System",
    "wof:placetype":"venue"
},
  "geometry": {"coordinates":[-83.20649899999999,42.504941],"type":"Point"}
}