{
  "type": "Feature",
  "properties": {
    "iso:country":"US",
    "sg:address":"3201 Bay City Rd",
    "sg:city":"Midland",
    "sg:classifiers":[
        {
            "category":"Wholesale",
            "subcategory":"Electrical",
            "type":"Manufacturing & Wholesale Goods"
        }
    ],
    "sg:phone":"+1 989 496 3600",
    "sg:postcode":"48642",
    "sg:province":"MI",
    "sg:tags":[
        "equipment",
        "electric",
        "supply"
    ],
    "wof:name":"Kendall Electric Inc",
    "wof:placetype":"venue"
},
  "geometry": {"coordinates":[-84.18927100000001,43.605016],"type":"Point"}
}