{
  "type": "Feature",
  "properties": {
    "iso:country":"US",
    "sg:address":"3958 Rochester Rd",
    "sg:city":"Troy",
    "sg:classifiers":[
        {
            "category":"Personal",
            "type":"Services"
        }
    ],
    "sg:phone":"+1 248 528 8473",
    "sg:postcode":"48083",
    "sg:province":"MI",
    "wof:name":"Beach Co Inc",
    "wof:placetype":"venue"
},
  "geometry": {"coordinates":[-83.12819,42.57422],"type":"Point"}
}