{
  "type": "Feature",
  "properties": {
    "iso:country":"US",
    "sg:address":"1067 E 12 Mile Rd",
    "sg:city":"Dafter",
    "sg:classifiers":[
        {
            "category":"Building & Trades",
            "subcategory":"Construction",
            "type":"Services"
        }
    ],
    "sg:phone":"+1 906 632 4708",
    "sg:postcode":"49724",
    "sg:province":"MI",
    "sg:tags":[
        "house"
    ],
    "wof:name":"Lone Wolf Construction",
    "wof:placetype":"venue"
},
  "geometry": {"coordinates":[-84.331424,46.331457],"type":"Point"}
}