{
  "type": "Feature",
  "properties": {
    "iso:country":"US",
    "sg:address":"3510 Indian Lakes Rd NE",
    "sg:city":"Cedar Springs",
    "sg:classifiers":[
        {
            "category":"Wholesale",
            "subcategory":"Sporting Goods",
            "type":"Manufacturing & Wholesale Goods"
        }
    ],
    "sg:phone":"+1 616 696 4261",
    "sg:postcode":"49319",
    "sg:province":"MI",
    "sg:tags":[
        "equipment",
        "archery",
        "supply"
    ],
    "wof:name":"Grandpa Joe's",
    "wof:placetype":"venue"
},
  "geometry": {"coordinates":[-85.58841700000001,43.197354],"type":"Point"}
}