{
  "type": "Feature",
  "properties": {
    "iso:country":"US",
    "sg:address":"3425 Yellowstone Dr",
    "sg:city":"Ann Arbor",
    "sg:classifiers":[
        {
            "category":"Professional",
            "subcategory":"Art Services",
            "type":"Services"
        }
    ],
    "sg:phone":"+1 734 994 8423",
    "sg:postcode":"48105",
    "sg:province":"MI",
    "sg:tags":[
        "commercial",
        "design"
    ],
    "wof:name":"Hesseltine & Demason",
    "wof:placetype":"venue"
},
  "geometry": {"coordinates":[-83.696298,42.314985],"type":"Point"}
}