{
  "type": "Feature",
  "properties": {
    "iso:country":"US",
    "sg:address":"17130 Juliana Ave",
    "sg:city":"Eastpointe",
    "sg:classifiers":[
        {
            "category":"Building & Trades",
            "subcategory":"Equipment Rental",
            "type":"Services"
        }
    ],
    "sg:phone":"+1 586 777 2466",
    "sg:postcode":"48021",
    "sg:province":"MI",
    "sg:tags":[
        "dental",
        "supply"
    ],
    "wof:name":"PDQ Handpiece Repair",
    "wof:placetype":"venue"
},
  "geometry": {"coordinates":[-82.944093,42.452063],"type":"Point"}
}