{
  "type": "Feature",
  "properties": {
    "iso:country":"US",
    "sg:address":"3507 Kent Ct",
    "sg:city":"Royal Oak",
    "sg:classifiers":[
        {
            "category":"Shopping",
            "subcategory":"Optical Goods",
            "type":"Retail Goods"
        }
    ],
    "sg:phone":"+1 248 549 0806",
    "sg:postcode":"48073",
    "sg:province":"MI",
    "sg:tags":[
        "sun",
        "goggles",
        "sunglasses"
    ],
    "wof:name":"Shadyland Sunglasses",
    "wof:placetype":"venue"
},
  "geometry": {"coordinates":[-83.17348200000001,42.519732],"type":"Point"}
}