{
  "type": "Feature",
  "properties": {
    "iso:country":"US",
    "sg:address":"12855 Levan Rd",
    "sg:city":"Livonia",
    "sg:classifiers":[
        {
            "category":"Retail",
            "subcategory":"Auto Repair",
            "type":"Services"
        }
    ],
    "sg:phone":"+1 734 591 0505",
    "sg:postcode":"48150",
    "sg:province":"MI",
    "sg:tags":[
        "body",
        "shop"
    ],
    "wof:name":"Gales Body Shop",
    "wof:placetype":"venue"
},
  "geometry": {"coordinates":[-83.4021,42.377102],"type":"Point"}
}