{
  "type": "Feature",
  "properties": {
    "iso:country":"US",
    "sg:address":"539 Tecumseh St",
    "sg:city":"Dundee",
    "sg:classifiers":[
        {
            "category":"Restaurant",
            "type":"Food & Drink"
        }
    ],
    "sg:menulink":"http://www.allmenus.com/mi/dundee/208707-taco-bell/menu/",
    "sg:phone":"+1 734 529 5726",
    "sg:postcode":"48131",
    "sg:province":"MI",
    "sg:tags":[
        "mexican"
    ],
    "wof:name":"Taco Bell",
    "wof:placetype":"venue"
},
  "geometry": {"coordinates":[-83.667813,41.958586],"type":"Point"}
}