{
  "type": "Feature",
  "properties": {
    "iso:country":"US",
    "sg:address":"58 N Walnut St",
    "sg:city":"Mount Clemens",
    "sg:classifiers":[
        {
            "category":"Personal",
            "subcategory":"Beauty Salon",
            "type":"Services"
        },
        {
            "category":"Personal",
            "subcategory":"Nail Salon",
            "type":"Services"
        }
    ],
    "sg:phone":"+1 586 463 8660",
    "sg:postcode":"48043",
    "sg:province":"MI",
    "sg:tags":[
        "hair"
    ],
    "wof:name":"Studio 58",
    "wof:placetype":"venue"
},
  "geometry": {"coordinates":[-82.877899,42.598099],"type":"Point"}
}