{
  "type": "Feature",
  "properties": {
    "iso:country":"US",
    "sg:address":"2830 Chicago Dr SW",
    "sg:city":"Grandville",
    "sg:classifiers":[
        {
            "category":"Freight",
            "type":"Transportation"
        }
    ],
    "sg:phone":"+1 616 249 0902",
    "sg:postcode":"49418",
    "sg:province":"MI",
    "sg:tags":[
        "trucking"
    ],
    "wof:name":"77 Express LLC",
    "wof:placetype":"venue"
},
  "geometry": {"coordinates":[-85.737707,42.923045],"type":"Point"}
}