{
  "type": "Feature",
  "properties": {
    "iso:country":"US",
    "sg:address":"2153 W Vienna Rd",
    "sg:city":"Clio",
    "sg:classifiers":[
        {
            "category":"Shopping",
            "subcategory":"Gifts & Souvenirs",
            "type":"Retail Goods"
        }
    ],
    "sg:phone":"+1 810 687 1188",
    "sg:postcode":"48420",
    "sg:province":"MI",
    "sg:tags":[
        "novelty"
    ],
    "wof:name":"Dollar & Cents",
    "wof:placetype":"venue"
},
  "geometry": {"coordinates":[-83.719792,43.177526],"type":"Point"}
}