{
  "type": "Feature",
  "properties": {
    "iso:country":"US",
    "sg:address":"32677 Utica Rd",
    "sg:city":"Fraser",
    "sg:classifiers":[
        {
            "category":"Building & Trades",
            "subcategory":"Construction",
            "type":"Services"
        }
    ],
    "sg:phone":"+1 586 293 6926",
    "sg:postcode":"48026",
    "sg:province":"MI",
    "sg:tags":[
        "roofing",
        "contractor"
    ],
    "wof:name":"Rubber Baby Roofing",
    "wof:placetype":"venue"
},
  "geometry": {"coordinates":[-82.95139399999999,42.535962],"type":"Point"}
}