{
  "type": "Feature",
  "properties": {
    "iso:country":"US",
    "sg:address":"816 Pleasant Valley Ave",
    "sg:city":"Boyne City",
    "sg:classifiers":[
        {
            "category":"Personal",
            "subcategory":"Beauty Salon",
            "type":"Services"
        }
    ],
    "sg:phone":"+1 231 582 9398",
    "sg:postcode":"49712",
    "sg:province":"MI",
    "sg:tags":[
        "shop"
    ],
    "wof:name":"Hair Shop",
    "wof:placetype":"venue"
},
  "geometry": {"coordinates":[-85.014145,45.191219],"type":"Point"}
}