{
  "type": "Feature",
  "properties": {
    "iso:country":"US",
    "sg:address":"3300 Prospect St",
    "sg:city":"Hudsonville",
    "sg:classifiers":[
        {
            "category":"Real Estate",
            "subcategory":"Real Estate Agent",
            "type":"Services"
        }
    ],
    "sg:phone":"+1 616 669 6379",
    "sg:postcode":"49426",
    "sg:province":"MI",
    "sg:tags":[
        "cooperative"
    ],
    "wof:name":"Farmer's Co Op Svc Station",
    "wof:placetype":"venue"
},
  "geometry": {"coordinates":[-85.86468499999999,42.868109],"type":"Point"}
}