{
  "type": "Feature",
  "properties": {
    "iso:country":"US",
    "sg:address":"25291 Telegraph Rd",
    "sg:city":"Southfield",
    "sg:classifiers":[
        {
            "category":"Shopping",
            "subcategory":"Department Store",
            "type":"Retail Goods"
        }
    ],
    "sg:phone":"+1 248 208 7552",
    "sg:postcode":"48033",
    "sg:province":"MI",
    "wof:name":"Citi Trends",
    "wof:placetype":"venue"
},
  "geometry": {"coordinates":[-83.28363,42.474311],"type":"Point"}
}