{
  "type": "Feature",
  "properties": {
    "iso:country":"US",
    "sg:address":"6370 Dixie Hwy",
    "sg:city":"Bridgeport",
    "sg:classifiers":[
        {
            "category":"Food & Beverages",
            "subcategory":"Groceries & Convenience Stores",
            "type":"Retail Goods"
        }
    ],
    "sg:phone":"+1 989 777 0881",
    "sg:postcode":"48722",
    "sg:province":"MI",
    "sg:tags":[
        "grocer"
    ],
    "wof:name":"Kroger",
    "wof:placetype":"venue"
},
  "geometry": {"coordinates":[-83.870768,43.353594],"type":"Point"}
}