{
  "type": "Feature",
  "properties": {
    "iso:country":"US",
    "sg:address":"334 N 20th St",
    "sg:city":"Springfield",
    "sg:classifiers":[
        {
            "category":"Autos & Motor Vehicles",
            "subcategory":"Fuel & Gas Station",
            "type":"Retail Goods"
        }
    ],
    "sg:phone":"+1 269 965 4785",
    "sg:postcode":"49015",
    "sg:province":"MI",
    "sg:tags":[
        "oil"
    ],
    "wof:name":"Terry's Citgo",
    "wof:placetype":"venue"
},
  "geometry": {"coordinates":[-85.21928800000001,42.31719],"type":"Point"}
}