{
  "type": "Feature",
  "properties": {
    "iso:country":"US",
    "sg:address":"2420 White St",
    "sg:city":"Port Huron",
    "sg:classifiers":[
        {
            "category":"Building & Trades",
            "subcategory":"Electrical",
            "type":"Services"
        }
    ],
    "sg:phone":"+1 810 985 6361",
    "sg:postcode":"48060",
    "sg:province":"MI",
    "sg:tags":[
        "electric",
        "contractor"
    ],
    "wof:name":"Sopha Electric Inc",
    "wof:placetype":"venue"
},
  "geometry": {"coordinates":[-82.453693,42.967342],"type":"Point"}
}