{
  "type": "Feature",
  "properties": {
    "iso:country":"US",
    "sg:address":"369 W Grand River Ave",
    "sg:city":"Williamston",
    "sg:classifiers":[
        {
            "category":"Professional",
            "type":"Services"
        }
    ],
    "sg:phone":"+1 517 655 5704",
    "sg:postcode":"48895",
    "sg:province":"MI",
    "sg:tags":[
        "establishment"
    ],
    "wof:name":"Williamston Depot",
    "wof:placetype":"venue"
},
  "geometry": {"coordinates":[-84.28864900000001,42.687935],"type":"Point"}
}