{
  "type": "Feature",
  "properties": {
    "iso:country":"US",
    "sg:address":"300 Wyngate Dr",
    "sg:city":"Rochester",
    "sg:classifiers":[
        {
            "category":"Real Estate",
            "subcategory":"Developer",
            "type":"Services"
        }
    ],
    "sg:phone":"+1 248 608 0727",
    "sg:postcode":"48307",
    "sg:province":"MI",
    "wof:name":"Rochester Properties LLC",
    "wof:placetype":"venue"
},
  "geometry": {"coordinates":[-83.103258,42.687226],"type":"Point"}
}