{
  "type": "Feature",
  "properties": {
    "iso:country":"US",
    "sg:address":"13011 Blueberry Ln",
    "sg:city":"Holland",
    "sg:classifiers":[
        {
            "category":"Professional",
            "subcategory":"Management & Consulting",
            "type":"Services"
        }
    ],
    "sg:phone":"+1 616 738 9282",
    "sg:postcode":"49424",
    "sg:province":"MI",
    "wof:name":"Kamm Consulting",
    "wof:placetype":"venue"
},
  "geometry": {"coordinates":[-86.10511200000001,42.822358],"type":"Point"}
}