{
  "type": "Feature",
  "properties": {
    "iso:country":"US",
    "sg:address":"45559 Van Dyke Ave",
    "sg:city":"Utica",
    "sg:classifiers":[
        {
            "category":"Food & Beverages",
            "subcategory":"Groceries & Convenience Stores",
            "type":"Retail Goods"
        }
    ],
    "sg:phone":"+1 586 323 5990",
    "sg:postcode":"48317",
    "sg:province":"MI",
    "sg:tags":[
        "grocer"
    ],
    "wof:name":"LA Calera Grocery",
    "wof:placetype":"venue"
},
  "geometry": {"coordinates":[-83.032644,42.629982],"type":"Point"}
}