{
  "type": "Feature",
  "properties": {
    "iso:country":"US",
    "sg:address":"910 E Lincoln Ave",
    "sg:city":"Ionia",
    "sg:classifiers":[
        {
            "category":"Health Services",
            "subcategory":"Health Practitioner",
            "type":"Services"
        }
    ],
    "sg:phone":"+1 616 669 0447",
    "sg:postcode":"48846",
    "sg:province":"MI",
    "wof:name":"Optimal Health Services LLC",
    "wof:placetype":"venue"
},
  "geometry": {"coordinates":[-85.04421600000001,42.987441],"type":"Point"}
}