{
  "type": "Feature",
  "properties": {
    "iso:country":"US",
    "sg:address":"1359 Hidden Creek N",
    "sg:city":"Saline",
    "sg:classifiers":[
        {
            "category":"Professional",
            "subcategory":"Management & Consulting",
            "type":"Services"
        }
    ],
    "sg:phone":"+1 734 944 1177",
    "sg:postcode":"48176",
    "sg:province":"MI",
    "sg:tags":[
        "business"
    ],
    "wof:name":"Teris Consulting Group",
    "wof:placetype":"venue"
},
  "geometry": {"coordinates":[-83.70093900000001,42.195408],"type":"Point"}
}