{
  "type": "Feature",
  "properties": {
    "iso:country":"US",
    "sg:address":"22690 Civic Center Dr",
    "sg:city":"Southfield",
    "sg:classifiers":[
        {
            "category":"Professional",
            "subcategory":"Computer Services",
            "type":"Services"
        }
    ],
    "sg:phone":"+1 248 208 1662",
    "sg:postcode":"48033",
    "sg:province":"MI",
    "sg:tags":[
        "website",
        "consulting",
        "design"
    ],
    "wof:name":"Liam Moor Associates",
    "wof:placetype":"venue"
},
  "geometry": {"coordinates":[-83.26558199999999,42.478942],"type":"Point"}
}