{
  "type": "Feature",
  "properties": {
    "iso:country":"US",
    "sg:address":"241 E. Michigan Ave.",
    "sg:city":"Kalamazoo",
    "sg:classifiers":[
        {
            "category":"Professional",
            "subcategory":"Research",
            "type":"Services"
        }
    ],
    "sg:phone":"+1 269 998 3706",
    "sg:postcode":"49007",
    "sg:province":"MI",
    "sg:website":"http://www.realbiotechnology.com/",
    "wof:name":"RealBio Technology",
    "wof:placetype":"venue"
},
  "geometry": {"coordinates":[-85.58270899999999,42.291756],"type":"Point"}
}