{
  "type": "Feature",
  "properties": {
    "iso:country":"US",
    "sg:address":"1201 Janice St",
    "sg:city":"Holland",
    "sg:classifiers":[
        {
            "category":"Social Services",
            "subcategory":"Child Care",
            "type":"Services"
        }
    ],
    "sg:phone":"+1 616 335 3032",
    "sg:postcode":"49423",
    "sg:province":"MI",
    "sg:tags":[
        "day"
    ],
    "wof:name":"Shari L McCarthy",
    "wof:placetype":"venue"
},
  "geometry": {"coordinates":[-86.161293,42.77058],"type":"Point"}
}