{
  "type": "Feature",
  "properties": {
    "iso:country":"US",
    "sg:address":"1100 W Ann Arbor Trl",
    "sg:city":"Plymouth",
    "sg:classifiers":[
        {
            "category":"Organizations",
            "subcategory":"Religious Organization",
            "type":"Services"
        }
    ],
    "sg:phone":"+1 734 453 0970",
    "sg:postcode":"48170",
    "sg:province":"MI",
    "wof:name":"First Church Christ Scientist",
    "wof:placetype":"venue"
},
  "geometry": {"coordinates":[-83.47373899999999,42.370556],"type":"Point"}
}