{
  "type": "Feature",
  "properties": {
    "iso:country":"US",
    "sg:address":"321 Kirk Lane Dr",
    "sg:city":"Troy",
    "sg:classifiers":[
        {
            "category":"Building & Trades",
            "subcategory":"Landscaping Services",
            "type":"Services"
        }
    ],
    "sg:phone":"+1 248 526 0866",
    "sg:postcode":"48084",
    "sg:province":"MI",
    "wof:name":"Prairie Rose Grdns Distinction",
    "wof:placetype":"venue"
},
  "geometry": {"coordinates":[-83.154194,42.572104],"type":"Point"}
}