{
  "type": "Feature",
  "properties": {
    "iso:country":"US",
    "sg:address":"6650 Highland Rd",
    "sg:city":"Waterford",
    "sg:classifiers":[
        {
            "category":"Health Services",
            "subcategory":"Optometrist",
            "type":"Services"
        }
    ],
    "sg:phone":"+1 248 666 3377",
    "sg:postcode":"48327",
    "sg:province":"MI",
    "wof:name":"Js Dudovitz",
    "wof:placetype":"venue"
},
  "geometry": {"coordinates":[-83.420244,42.659553],"type":"Point"}
}