{
  "type": "Feature",
  "properties": {
    "iso:country":"US",
    "sg:address":"25345 W 6 Mile Rd",
    "sg:city":"Redford",
    "sg:classifiers":[
        {
            "category":"Sports & Exercise",
            "subcategory":"Golf",
            "type":"Entertainment"
        }
    ],
    "sg:phone":"+1 313 592 8758",
    "sg:postcode":"48240",
    "sg:province":"MI",
    "wof:name":"Glenhurst Golf Course",
    "wof:placetype":"venue"
},
  "geometry": {"coordinates":[-83.29070299999999,42.414001],"type":"Point"}
}