{
  "type": "Feature",
  "properties": {
    "iso:country":"US",
    "sg:address":"22 S 3rd Ave",
    "sg:city":"Fruitport",
    "sg:classifiers":[
        {
            "category":"Restaurant",
            "type":"Food & Drink"
        }
    ],
    "sg:phone":"+1 231 865 6776",
    "sg:postcode":"49415",
    "sg:province":"MI",
    "sg:tags":[
        "pizza"
    ],
    "wof:name":"Peppie's Pizza & Sub Shop",
    "wof:placetype":"venue"
},
  "geometry": {"coordinates":[-86.15518299999999,43.123417],"type":"Point"}
}