{
  "type": "Feature",
  "properties": {
    "iso:country":"US",
    "sg:address":"544 Eckschtay",
    "sg:city":"Novi",
    "sg:classifiers":[
        {
            "category":"Building & Trades",
            "subcategory":"Cleaning & Sanitation",
            "type":"Services"
        }
    ],
    "sg:phone":"+1 248 374 0180",
    "sg:postcode":"48374",
    "sg:province":"MI",
    "sg:tags":[
        "janitor"
    ],
    "wof:name":"Spotless Interiors Inc",
    "wof:placetype":"venue"
},
  "geometry": {"coordinates":[-83.550674,42.48534],"type":"Point"}
}