{
  "type": "Feature",
  "properties": {
    "iso:country":"US",
    "sg:address":"39425 Garfield Rd",
    "sg:city":"Clinton Township",
    "sg:classifiers":[
        {
            "category":"Professional",
            "subcategory":"Lawyer & Legal Services",
            "type":"Services"
        }
    ],
    "sg:phone":"+1 586 226 2627",
    "sg:postcode":"48038",
    "sg:province":"MI",
    "sg:website":"www.burgesslegal-discrimination....",
    "wof:name":"Law Offices of Burgess & Sharp",
    "wof:placetype":"venue"
},
  "geometry": {"coordinates":[-82.952431,42.586787],"type":"Point"}
}