{
  "type": "Feature",
  "properties": {
    "iso:country":"US",
    "sg:address":"110 W Golf Ave",
    "sg:city":"Jackson",
    "sg:classifiers":[
        {
            "category":"Recreation",
            "type":"Entertainment"
        }
    ],
    "sg:phone":"+1 517 784 5099",
    "sg:postcode":"49203",
    "sg:province":"MI",
    "sg:tags":[
        "personal"
    ],
    "wof:name":"Office Perks",
    "wof:placetype":"venue"
},
  "geometry": {"coordinates":[-84.403052,42.199804],"type":"Point"}
}