{
  "type": "Feature",
  "properties": {
    "iso:country":"US",
    "sg:address":"5286 Wynn Rd",
    "sg:city":"Comstock",
    "sg:classifiers":[
        {
            "category":"Professional",
            "subcategory":"Management & Consulting",
            "type":"Services"
        }
    ],
    "sg:phone":"+1 269 382 0029",
    "sg:postcode":"49048",
    "sg:province":"MI",
    "sg:tags":[
        "consultant",
        "safety"
    ],
    "wof:name":"Safety Serivce Inc",
    "wof:placetype":"venue"
},
  "geometry": {"coordinates":[-85.52164999999999,42.270029],"type":"Point"}
}