{
  "type": "Feature",
  "properties": {
    "iso:country":"US",
    "sg:address":"3193 Round Lake Hwy",
    "sg:city":"Manitou Beach",
    "sg:classifiers":[
        {
            "category":"Real Estate",
            "subcategory":"Real Estate Agent",
            "type":"Services"
        }
    ],
    "sg:phone":"+1 517 547 5553",
    "sg:postcode":"49253",
    "sg:province":"MI",
    "wof:name":"Lake Devils Realty",
    "wof:placetype":"venue"
},
  "geometry": {"coordinates":[-84.27620400000001,41.976283],"type":"Point"}
}