{
  "type": "Feature",
  "properties": {
    "iso:country":"US",
    "sg:address":"15158 A Dr N",
    "sg:city":"Marshall",
    "sg:classifiers":[
        {
            "category":"Retail",
            "subcategory":"Repair Shop",
            "type":"Services"
        }
    ],
    "sg:phone":"+1 269 781 4471",
    "sg:postcode":"49068",
    "sg:province":"MI",
    "wof:name":"Hanchetts Septic Systems",
    "wof:placetype":"venue"
},
  "geometry": {"coordinates":[-85.00152799999999,42.253777],"type":"Point"}
}