{
  "type": "Feature",
  "properties": {
    "iso:country":"US",
    "sg:address":"5676 Elm Valley Rd",
    "sg:city":"Suttons Bay",
    "sg:classifiers":[
        {
            "category":"Travel",
            "subcategory":"Hotels & Motels",
            "type":"Entertainment"
        }
    ],
    "sg:phone":"+1 231 271 4478",
    "sg:postcode":"49682",
    "sg:province":"MI",
    "sg:tags":[
        "operation"
    ],
    "wof:name":"Country House",
    "wof:placetype":"venue"
},
  "geometry": {"coordinates":[-85.650139,44.897527],"type":"Point"}
}