{
  "type": "Feature",
  "properties": {
    "iso:country":"US",
    "sg:address":"2847 Gratiot Blvd",
    "sg:city":"Marysville",
    "sg:classifiers":[
        {
            "category":"Professional",
            "subcategory":"Lawyer & Legal Services",
            "type":"Services"
        }
    ],
    "sg:phone":"+1 810 326 0441",
    "sg:postcode":"48040",
    "sg:province":"MI",
    "sg:tags":[
        "attorney"
    ],
    "wof:name":"Damman Sheridan Law Firm",
    "wof:placetype":"venue"
},
  "geometry": {"coordinates":[-82.491646,42.913154],"type":"Point"}
}