{
  "type": "Feature",
  "properties": {
    "iso:country":"US",
    "sg:address":"37155 Harper Ave",
    "sg:city":"Clinton Township",
    "sg:classifiers":[
        {
            "category":"Food & Beverages",
            "subcategory":"Groceries & Convenience Stores",
            "type":"Retail Goods"
        }
    ],
    "sg:phone":"+1 586 954 1000",
    "sg:postcode":"48036",
    "sg:province":"MI",
    "sg:website":"www.valuecentermarket.com",
    "wof:name":"Value Center Market",
    "wof:placetype":"venue"
},
  "geometry": {"coordinates":[-82.871843,42.570551],"type":"Point"}
}