{
  "type": "Feature",
  "properties": {
    "iso:country":"US",
    "sg:address":"118 E Division St",
    "sg:city":"Ishpeming",
    "sg:classifiers":[
        {
            "category":"Manufacturing",
            "subcategory":"Printing",
            "type":"Manufacturing & Wholesale Goods"
        }
    ],
    "sg:phone":"+1 906 486 4401",
    "sg:postcode":"49849",
    "sg:province":"MI",
    "sg:tags":[
        "newspaper"
    ],
    "wof:name":"Mining Journel",
    "wof:placetype":"venue"
},
  "geometry": {"coordinates":[-87.66871,46.488537],"type":"Point"}
}