{
  "type": "Feature",
  "properties": {
    "iso:country":"US",
    "sg:address":"31 S Main",
    "sg:city":"Cedar Springs",
    "sg:classifiers":[
        {
            "category":"Restaurant",
            "type":"Food & Drink"
        }
    ],
    "sg:phone":"+1 616 696 9814",
    "sg:postcode":"49319",
    "sg:province":"MI",
    "wof:name":"Jose's Restaurant",
    "wof:placetype":"venue"
},
  "geometry": {"coordinates":[-85.551253,43.223037],"type":"Point"}
}