{
  "type": "Feature",
  "properties": {
    "iso:country":"US",
    "sg:address":"26428 Ford Rd",
    "sg:city":"Dearborn",
    "sg:classifiers":[
        {
            "category":"Shopping",
            "subcategory":"Mobile Phones",
            "type":"Retail Goods"
        }
    ],
    "sg:phone":"+1 313 724 0931",
    "sg:postcode":"48120",
    "sg:province":"MI",
    "sg:website":"t-mobile.com",
    "wof:name":"T-Mobile",
    "wof:placetype":"venue"
},
  "geometry": {"coordinates":[-83.18499799999999,42.301701],"type":"Point"}
}