{
  "type": "Feature",
  "properties": {
    "iso:country":"US",
    "sg:address":"21550 Edison St",
    "sg:city":"Dearborn",
    "sg:classifiers":[
        {
            "category":"Real Estate",
            "subcategory":"Real Estate Agent",
            "type":"Services"
        }
    ],
    "sg:phone":"+1 313 561 4517",
    "sg:postcode":"48124",
    "sg:province":"MI",
    "wof:name":"Juliandanita Inc",
    "wof:placetype":"venue"
},
  "geometry": {"coordinates":[-83.246116,42.296888],"type":"Point"}
}