{
  "type": "Feature",
  "properties": {
    "iso:country":"US",
    "sg:address":"217 E Hughitt St",
    "sg:city":"Iron Mountain",
    "sg:classifiers":[
        {
            "category":"Shopping",
            "subcategory":"Clothing, Apparel, & Fashions",
            "type":"Retail Goods"
        }
    ],
    "sg:phone":"+1 906 779 5113",
    "sg:postcode":"49801",
    "sg:province":"MI",
    "sg:tags":[
        "shop",
        "bridal"
    ],
    "sg:website":"www.juliarosecreations.com",
    "wof:name":"Julia Rose Creations",
    "wof:placetype":"venue"
},
  "geometry": {"coordinates":[-88.065493,45.819302],"type":"Point"}
}