{
  "type": "Feature",
  "properties": {
    "iso:country":"US",
    "sg:address":"21701 John R Rd",
    "sg:city":"Hazel Park",
    "sg:classifiers":[
        {
            "category":"Retail",
            "subcategory":"Auto Repair",
            "type":"Services"
        }
    ],
    "sg:phone":"+1 248 629 9464",
    "sg:postcode":"48030",
    "sg:province":"MI",
    "wof:name":"Chris Car Care",
    "wof:placetype":"venue"
},
  "geometry": {"coordinates":[-83.103585,42.454607],"type":"Point"}
}