{
  "type": "Feature",
  "properties": {
    "iso:country":"US",
    "sg:address":"6101 Drexel St",
    "sg:city":"Dearborn Heights",
    "sg:classifiers":[
        {
            "category":"Farming",
            "subcategory":"Farm & Veterinary Services",
            "type":"Manufacturing & Wholesale Goods"
        }
    ],
    "sg:phone":"+1 313 277 3435",
    "sg:postcode":"48127",
    "sg:province":"MI",
    "sg:tags":[
        "crop"
    ],
    "wof:name":"F&A Services Inc",
    "wof:placetype":"venue"
},
  "geometry": {"coordinates":[-83.275105,42.332443],"type":"Point"}
}