{
  "type": "Feature",
  "properties": {
    "iso:country":"US",
    "sg:address":"43588 W Oaks Dr",
    "sg:city":"Novi",
    "sg:classifiers":[
        {
            "category":"Restaurant",
            "type":"Food & Drink"
        }
    ],
    "sg:menulink":"http://www.allmenus.com/mi/novi/9749-cherry-blossom/menu/",
    "sg:phone":"+1 248 380 9160",
    "sg:postcode":"48377",
    "sg:province":"MI",
    "sg:tags":[
        "japanese",
        "asian"
    ],
    "wof:name":"Cherry Blossom",
    "wof:placetype":"venue"
},
  "geometry": {"coordinates":[-83.47913200000001,42.491575],"type":"Point"}
}