{
  "type": "Feature",
  "properties": {
    "iso:country":"US",
    "sg:address":"5275 Marine City Hwy",
    "sg:city":"Cottrellville",
    "sg:classifiers":[
        {
            "category":"Wholesale",
            "subcategory":"Electrical",
            "type":"Manufacturing & Wholesale Goods"
        }
    ],
    "sg:phone":"+1 810 765 6789",
    "sg:postcode":"48039",
    "sg:province":"MI",
    "sg:tags":[
        "intercommunication"
    ],
    "wof:name":"Comstar Intercom Co",
    "wof:placetype":"venue"
},
  "geometry": {"coordinates":[-82.519897,42.727295],"type":"Point"}
}