{
  "type": "Feature",
  "properties": {
    "iso:country":"US",
    "sg:address":"6741 Bloomfield Ln",
    "sg:city":"West Bloomfield",
    "sg:classifiers":[
        {
            "category":"Professional",
            "type":"Services"
        }
    ],
    "sg:phone":"+1 248 539 1781",
    "sg:postcode":"48322",
    "sg:province":"MI",
    "wof:name":"Accutech Civil Services Inc",
    "wof:placetype":"venue"
},
  "geometry": {"coordinates":[-83.332795,42.542941],"type":"Point"}
}