{
  "type": "Feature",
  "properties": {
    "iso:country":"US",
    "sg:address":"1100 Owendale Dr",
    "sg:city":"Troy",
    "sg:classifiers":[
        {
            "category":"Wholesale",
            "subcategory":"Office Equipment",
            "type":"Manufacturing & Wholesale Goods"
        }
    ],
    "sg:phone":"+1 248 524 9240",
    "sg:postcode":"48083",
    "sg:province":"MI",
    "sg:tags":[
        "machine",
        "duplicating",
        "copying"
    ],
    "wof:name":"CBI Copy Products Inc",
    "wof:placetype":"venue"
},
  "geometry": {"coordinates":[-83.127551,42.561025],"type":"Point"}
}