{
  "type": "Feature",
  "properties": {
    "iso:country":"US",
    "sg:address":"7637 Treat Hwy",
    "sg:city":"Jasper",
    "sg:classifiers":[
        {
            "category":"Farming",
            "subcategory":"Farm",
            "type":"Manufacturing & Wholesale Goods"
        }
    ],
    "sg:phone":"+1 517 443 5295",
    "sg:postcode":"49248",
    "sg:province":"MI",
    "wof:name":"Uloth's Golden Valley Farms",
    "wof:placetype":"venue"
},
  "geometry": {"coordinates":[-84.002246,41.807541],"type":"Point"}
}