{
  "type": "Feature",
  "properties": {
    "iso:country":"US",
    "sg:address":"4100 Knapp St NE",
    "sg:city":"Grand Rapids",
    "sg:classifiers":[
        {
            "category":"Home & Garden",
            "subcategory":"Garden Supply",
            "type":"Retail Goods"
        }
    ],
    "sg:phone":"+1 616 363 8086",
    "sg:postcode":"49525",
    "sg:province":"MI",
    "sg:tags":[
        "nursery",
        "gardening"
    ],
    "sg:website":"www.knappvalley.com",
    "wof:name":"Knapp Valley Landscaping",
    "wof:placetype":"venue"
},
  "geometry": {"coordinates":[-85.570099,42.9995],"type":"Point"}
}