{
  "type": "Feature",
  "properties": {
    "iso:country":"US",
    "sg:address":"54393 Blue Cloud Dr",
    "sg:city":"Shelby Twp",
    "sg:classifiers":[
        {
            "category":"Professional",
            "subcategory":"Computer Services",
            "type":"Services"
        }
    ],
    "sg:phone":"+1 586 781 8479",
    "sg:postcode":"48315",
    "sg:province":"MI",
    "wof:name":"Computer Solutions Idiehl",
    "wof:placetype":"venue"
},
  "geometry": {"coordinates":[-83.00976300000001,42.693526],"type":"Point"}
}