{
  "type": "Feature",
  "properties": {
    "iso:country":"US",
    "sg:address":"1050 W Western Ave",
    "sg:city":"Muskegon",
    "sg:classifiers":[
        {
            "category":"Restaurant",
            "type":"Food & Drink"
        }
    ],
    "sg:phone":"+1 231 725 7555",
    "sg:postcode":"49441",
    "sg:province":"MI",
    "wof:name":"Waterfront Galley",
    "wof:placetype":"venue"
},
  "geometry": {"coordinates":[-86.266336,43.228871],"type":"Point"}
}