{
  "type": "Feature",
  "properties": {
    "iso:country":"US",
    "sg:address":"24230 Karim Blvd Ste 150",
    "sg:city":"Novi",
    "sg:classifiers":[
        {
            "category":"Health Services",
            "subcategory":"Optometrist",
            "type":"Services"
        }
    ],
    "sg:phone":"+1 248 473 9410",
    "sg:postcode":"48375",
    "sg:province":"MI",
    "sg:tags":[
        "ophthalmologist"
    ],
    "wof:name":"Boyman Ruth MD PC Opthalmlgy",
    "wof:placetype":"venue"
},
  "geometry": {"coordinates":[-83.453796,42.465401],"type":"Point"}
}