{
  "type": "Feature",
  "properties": {
    "iso:country":"US",
    "sg:address":"6930 Babcock Rd",
    "sg:city":"Fort Gratiot",
    "sg:classifiers":[
        {
            "category":"Freight",
            "type":"Transportation"
        }
    ],
    "sg:phone":"+1 810 385 4889",
    "sg:postcode":"48059",
    "sg:province":"MI",
    "sg:tags":[
        "operator",
        "trucking"
    ],
    "wof:name":"William Jones Trucking",
    "wof:placetype":"venue"
},
  "geometry": {"coordinates":[-82.54028099999999,43.108409],"type":"Point"}
}