{
  "type": "Feature",
  "properties": {
    "iso:country":"US",
    "sg:address":"1118 Centennial Way",
    "sg:city":"Lansing",
    "sg:classifiers":[
        {
            "category":"Wholesale",
            "subcategory":"Construction Materials",
            "type":"Manufacturing & Wholesale Goods"
        }
    ],
    "sg:phone":"+1 517 321 3130",
    "sg:postcode":"48917",
    "sg:province":"MI",
    "sg:website":"www.maxc.com",
    "wof:name":"Maxco Inc",
    "wof:placetype":"venue"
},
  "geometry": {"coordinates":[-84.64661099999999,42.721241],"type":"Point"}
}