{
  "type": "Feature",
  "properties": {
    "iso:country":"US",
    "sg:address":"185 W Maple Rd",
    "sg:city":"Birmingham",
    "sg:classifiers":[
        {
            "category":"Professional",
            "subcategory":"Business Services",
            "type":"Services"
        }
    ],
    "sg:phone":"+1 248 540 3945",
    "sg:postcode":"48009",
    "sg:province":"MI",
    "sg:tags":[
        "interior",
        "consultant",
        "design",
        "decorator"
    ],
    "wof:name":"LA Belle Maison",
    "wof:placetype":"venue"
},
  "geometry": {"coordinates":[-83.21538200000001,42.546605],"type":"Point"}
}