{
  "type": "Feature",
  "properties": {
    "iso:country":"US",
    "sg:address":"2027 Rust St",
    "sg:city":"Saginaw",
    "sg:classifiers":[
        {
            "category":"Freight",
            "type":"Transportation"
        }
    ],
    "sg:phone":"+1 989 752 4191",
    "sg:postcode":"48601",
    "sg:province":"MI",
    "sg:tags":[
        "assembly",
        "light",
        "ma",
        "contract"
    ],
    "wof:name":"Central Whse Operations Inc",
    "wof:placetype":"venue"
},
  "geometry": {"coordinates":[-83.938907,43.410185],"type":"Point"}
}