{
  "type": "Feature",
  "properties": {
    "iso:country":"US",
    "sg:address":"31030 Grand River Ave",
    "sg:city":"Farmington",
    "sg:classifiers":[
        {
            "category":"Bars & Pubs",
            "type":"Food & Drink"
        }
    ],
    "sg:phone":"+1 248 474 6140",
    "sg:postcode":"48336",
    "sg:province":"MI",
    "wof:name":"Rustic Pub",
    "wof:placetype":"venue"
},
  "geometry": {"coordinates":[-83.354984,42.455816],"type":"Point"}
}