{
  "type": "Feature",
  "properties": {
    "iso:country":"US",
    "sg:address":"4555 Investment Dr",
    "sg:city":"Troy",
    "sg:classifiers":[
        {
            "category":"Banks & Credit Unions",
            "subcategory":"Bank",
            "type":"Services"
        }
    ],
    "sg:phone":"+1 248 641 0088",
    "sg:postcode":"48098",
    "sg:province":"MI",
    "wof:name":"S O C Credit Union",
    "wof:placetype":"venue"
},
  "geometry": {"coordinates":[-83.169403,42.5881],"type":"Point"}
}