{
  "type": "Feature",
  "properties": {
    "iso:country":"US",
    "sg:address":"211 W Main St",
    "sg:city":"Stanton",
    "sg:classifiers":[
        {
            "category":"Government",
            "subcategory":"Court House",
            "type":"Public Place"
        }
    ],
    "sg:phone":"+1 989 831 7343",
    "sg:postcode":"48888",
    "sg:province":"MI",
    "sg:tags":[
        "county"
    ],
    "wof:name":"8 Judicial Circuit Court",
    "wof:placetype":"venue"
},
  "geometry": {"coordinates":[-85.083851,43.292516],"type":"Point"}
}