{
  "type": "Feature",
  "properties": {
    "iso:country":"US",
    "sg:address":"33830 Harper Ave",
    "sg:city":"Clinton Township",
    "sg:classifiers":[
        {
            "category":"Professional",
            "subcategory":"Lawyer & Legal Services",
            "type":"Services"
        }
    ],
    "sg:phone":"+1 586 415 0093",
    "sg:postcode":"48035",
    "sg:province":"MI",
    "sg:tags":[
        "divorce",
        "law",
        "family"
    ],
    "wof:name":"Julie Hlywa",
    "wof:placetype":"venue"
},
  "geometry": {"coordinates":[-82.878184,42.544946],"type":"Point"}
}