{
  "type": "Feature",
  "properties": {
    "iso:country":"US",
    "sg:address":"3110 Claystone St SE",
    "sg:city":"Grand Rapids",
    "sg:classifiers":[
        {
            "category":"Recreation",
            "type":"Entertainment"
        }
    ],
    "sg:phone":"+1 616 942 0334",
    "sg:postcode":"49546",
    "sg:province":"MI",
    "sg:tags":[
        "amusement"
    ],
    "wof:name":"Michigan Motor Kaddy",
    "wof:placetype":"venue"
},
  "geometry": {"coordinates":[-85.592303,42.9242],"type":"Point"}
}