{
  "type": "Feature",
  "properties": {
    "iso:country":"US",
    "sg:address":"106 N River Ave",
    "sg:city":"Holland",
    "sg:classifiers":[
        {
            "category":"Organizations",
            "subcategory":"Community Association",
            "type":"Services"
        }
    ],
    "sg:phone":"+1 616 396 6163",
    "sg:postcode":"49424",
    "sg:province":"MI",
    "wof:name":"Lodge 1116 - Holland",
    "wof:placetype":"venue"
},
  "geometry": {"coordinates":[-86.111958,42.800715],"type":"Point"}
}