{
  "type": "Feature",
  "properties": {
    "iso:country":"US",
    "sg:address":"3800 E 8 Mile Rd",
    "sg:city":"Detroit",
    "sg:classifiers":[
        {
            "category":"Bars & Pubs",
            "type":"Food & Drink"
        }
    ],
    "sg:phone":"+1 313 892 5203",
    "sg:postcode":"48234",
    "sg:province":"MI",
    "sg:tags":[
        "drinking"
    ],
    "wof:name":"Sugarbakers Inc",
    "wof:placetype":"venue"
},
  "geometry": {"coordinates":[-83.066603,42.447227],"type":"Point"}
}