{
  "type": "Feature",
  "properties": {
    "iso:country":"US",
    "sg:address":"9800 M 89",
    "sg:city":"Richland",
    "sg:classifiers":[
        {
            "category":"Restaurant",
            "type":"Food & Drink"
        }
    ],
    "sg:phone":"+1 269 629 5832",
    "sg:postcode":"49083",
    "sg:province":"MI",
    "sg:tags":[
        "pizza"
    ],
    "wof:name":"Sajo's Pizza",
    "wof:placetype":"venue"
},
  "geometry": {"coordinates":[-85.437591,42.375381],"type":"Point"}
}