{
  "type": "Feature",
  "properties": {
    "iso:country":"US",
    "sg:address":"143 S Main St",
    "sg:city":"Reading",
    "sg:classifiers":[
        {
            "category":"Social Services",
            "subcategory":"Job Training",
            "type":"Services"
        },
        {
            "category":"Health Services",
            "subcategory":"Hospital",
            "type":"Services"
        }
    ],
    "sg:phone":"+1 517 437 1772",
    "sg:postcode":"49274",
    "sg:province":"MI",
    "sg:tags":[
        "nursing",
        "homes-skilled",
        "facility"
    ],
    "wof:name":"Reading Health Clinic",
    "wof:placetype":"venue"
},
  "geometry": {"coordinates":[-84.747893,41.839255],"type":"Point"}
}