{
  "type": "Feature",
  "properties": {
    "iso:country":"US",
    "sg:address":"646 Inkster Rd",
    "sg:city":"Inkster",
    "sg:classifiers":[
        {
            "category":"Personal",
            "subcategory":"Beauty Salon",
            "type":"Services"
        }
    ],
    "sg:phone":"+1 313 791 0083",
    "sg:postcode":"48141",
    "sg:province":"MI",
    "sg:tags":[
        "shop"
    ],
    "wof:name":"Marcel Hair Salon",
    "wof:placetype":"venue"
},
  "geometry": {"coordinates":[-83.31063899999999,42.305486],"type":"Point"}
}