{
  "type": "Feature",
  "properties": {
    "iso:country":"US",
    "sg:address":"2375 Cedar St",
    "sg:city":"Holt",
    "sg:classifiers":[
        {
            "category":"Retail",
            "subcategory":"Laundry & Dry Cleaning",
            "type":"Services"
        }
    ],
    "sg:phone":"+1 517 694 7744",
    "sg:postcode":"48842",
    "sg:province":"MI",
    "sg:tags":[
        "cleaners",
        "plant",
        "drycleaning"
    ],
    "wof:name":"Holt Cleaners",
    "wof:placetype":"venue"
},
  "geometry": {"coordinates":[-84.527644,42.650036],"type":"Point"}
}