{
  "type": "Feature",
  "properties": {
    "iso:country":"US",
    "sg:address":"455 Kenowa Ave SW",
    "sg:city":"Byron Center",
    "sg:classifiers":[
        {
            "category":"Building & Trades",
            "subcategory":"Construction",
            "type":"Services"
        }
    ],
    "sg:phone":"+1 616 878 5150",
    "sg:postcode":"49315",
    "sg:province":"MI",
    "sg:tags":[
        "general",
        "contractor"
    ],
    "wof:name":"Sroka Installation Inc",
    "wof:placetype":"venue"
},
  "geometry": {"coordinates":[-85.78267099999999,42.776543],"type":"Point"}
}