{
  "type": "Feature",
  "properties": {
    "iso:country":"US",
    "sg:address":"27236 Southfield Rd Ste 1",
    "sg:city":"Lathrup Village",
    "sg:classifiers":[
        {
            "category":"Food & Beverages",
            "subcategory":"Groceries & Convenience Stores",
            "type":"Retail Goods"
        }
    ],
    "sg:phone":"+1 248 395 3663",
    "sg:postcode":"48076",
    "sg:province":"MI",
    "wof:name":"Food Source the",
    "wof:placetype":"venue"
},
  "geometry": {"coordinates":[-83.221914,42.489283],"type":"Point"}
}