{
  "type": "Feature",
  "properties": {
    "iso:country":"US",
    "sg:address":"7441 W 7 Mile Rd",
    "sg:city":"Detroit",
    "sg:classifiers":[
        {
            "category":"Health Services",
            "subcategory":"Doctor",
            "type":"Services"
        }
    ],
    "sg:phone":"+1 313 864 4452",
    "sg:postcode":"48221",
    "sg:province":"MI",
    "wof:name":"Maitland Conrad C MD",
    "wof:placetype":"venue"
},
  "geometry": {"coordinates":[-83.14659899999999,42.4314],"type":"Point"}
}