{
  "type": "Feature",
  "properties": {
    "iso:country":"US",
    "sg:address":"4501 Pleasant Grove Rd",
    "sg:city":"Lansing",
    "sg:classifiers":[
        {
            "category":"Education",
            "subcategory":"School",
            "type":"Public Place"
        }
    ],
    "sg:phone":"+1 517 325 6859",
    "sg:postcode":"48910",
    "sg:province":"MI",
    "wof:name":"Pleasant View Elementary Schl",
    "wof:placetype":"venue"
},
  "geometry": {"coordinates":[-84.582256,42.689051],"type":"Point"}
}