{
  "type": "Feature",
  "properties": {
    "iso:country":"US",
    "sg:address":"605 N Eastern Ave",
    "sg:city":"Allegan",
    "sg:classifiers":[
        {
            "category":"Manufacturing",
            "subcategory":"Printing",
            "type":"Manufacturing & Wholesale Goods"
        }
    ],
    "sg:phone":"+1 269 673 3372",
    "sg:postcode":"49010",
    "sg:province":"MI",
    "sg:tags":[
        "commercial"
    ],
    "wof:name":"P J Printing Inc",
    "wof:placetype":"venue"
},
  "geometry": {"coordinates":[-85.835211,42.539047],"type":"Point"}
}