{
  "type": "Feature",
  "properties": {
    "iso:country":"US",
    "sg:address":"780 Brooks Rd",
    "sg:city":"Muskegon",
    "sg:classifiers":[
        {
            "category":"Building & Trades",
            "subcategory":"Construction",
            "type":"Services"
        }
    ],
    "sg:phone":"+1 231 777 2443",
    "sg:postcode":"49442",
    "sg:province":"MI",
    "sg:tags":[
        "house"
    ],
    "wof:name":"Snyder Construction",
    "wof:placetype":"venue"
},
  "geometry": {"coordinates":[-86.14427000000001,43.238181],"type":"Point"}
}