{
  "type": "Feature",
  "properties": {
    "iso:country":"US",
    "sg:address":"2712 Niles Ave",
    "sg:city":"St Joseph",
    "sg:classifiers":[
        {
            "category":"Autos & Motor Vehicles",
            "subcategory":"Automobile Sales",
            "type":"Retail Goods"
        }
    ],
    "sg:phone":"+1 269 982 4113",
    "sg:postcode":"49085",
    "sg:province":"MI",
    "sg:tags":[
        "car",
        "dealer"
    ],
    "wof:name":"Siemans Mazda Jeep",
    "wof:placetype":"venue"
},
  "geometry": {"coordinates":[-86.485466,42.086754],"type":"Point"}
}