{
  "type": "Feature",
  "properties": {
    "iso:country":"US",
    "sg:address":"37001 Schoolcraft Rd",
    "sg:city":"Livonia",
    "sg:classifiers":[
        {
            "category":"Building & Trades",
            "subcategory":"Construction",
            "type":"Services"
        }
    ],
    "sg:phone":"+1 313 538 1955",
    "sg:postcode":"48150",
    "sg:province":"MI",
    "sg:tags":[
        "painter"
    ],
    "wof:name":"Skylite Painting Co Inc",
    "wof:placetype":"venue"
},
  "geometry": {"coordinates":[-83.40979799999999,42.381199],"type":"Point"}
}