{
  "type": "Feature",
  "properties": {
    "iso:country":"US",
    "sg:address":"524 E Milham Ave",
    "sg:city":"Portage",
    "sg:classifiers":[
        {
            "category":"Real Estate",
            "subcategory":"Real Estate Services",
            "type":"Services"
        }
    ],
    "sg:phone":"+1 269 343 0633",
    "sg:postcode":"49002",
    "sg:province":"MI",
    "sg:tags":[
        "company",
        "title"
    ],
    "wof:name":"Unified Solutions",
    "wof:placetype":"venue"
},
  "geometry": {"coordinates":[-85.583484,42.230043],"type":"Point"}
}