{
  "type": "Feature",
  "properties": {
    "iso:country":"US",
    "sg:address":"14000 Lakeside Cir",
    "sg:city":"Sterling Heights",
    "sg:classifiers":[
        {
            "category":"Shopping",
            "subcategory":"Jewelry",
            "type":"Retail Goods"
        }
    ],
    "sg:phone":"+1 586 566 2510",
    "sg:postcode":"48313",
    "sg:province":"MI",
    "sg:tags":[
        "jeweler"
    ],
    "wof:name":"Noah's Silver",
    "wof:placetype":"venue"
},
  "geometry": {"coordinates":[-82.989693,42.625065],"type":"Point"}
}