{
  "type": "Feature",
  "properties": {
    "iso:country":"US",
    "sg:address":"31 Heritage Dr",
    "sg:city":"Negaunee",
    "sg:classifiers":[
        {
            "category":"Professional",
            "subcategory":"Secretarial Services",
            "type":"Services"
        }
    ],
    "sg:phone":"+1 906 475 5655",
    "sg:postcode":"49866",
    "sg:province":"MI",
    "sg:tags":[
        "convention",
        "court",
        "reporter"
    ],
    "wof:name":"Northern Reporters",
    "wof:placetype":"venue"
},
  "geometry": {"coordinates":[-87.575942,46.524176],"type":"Point"}
}