{
  "type": "Feature",
  "properties": {
    "iso:country":"US",
    "sg:address":"1500 Wealthy St SE",
    "sg:city":"Grand Rapids",
    "sg:classifiers":[
        {
            "category":"Shopping",
            "subcategory":"Music",
            "type":"Retail Goods"
        }
    ],
    "sg:phone":"+1 616 458 9560",
    "sg:postcode":"49506",
    "sg:province":"MI",
    "sg:tags":[
        "compact",
        "record",
        "disc",
        "tape"
    ],
    "wof:name":"Easytunes",
    "wof:placetype":"venue"
},
  "geometry": {"coordinates":[-85.63163900000001,42.955506],"type":"Point"}
}