{
  "type": "Feature",
  "properties": {
    "iso:country":"US",
    "sg:address":"1720 Braidwood Rd",
    "sg:city":"Memphis",
    "sg:classifiers":[
        {
            "category":"Building & Trades",
            "subcategory":"Cleaning & Sanitation",
            "type":"Services"
        }
    ],
    "sg:phone":"+1 810 392 9377",
    "sg:postcode":"48041",
    "sg:province":"MI",
    "sg:tags":[
        "maintenance"
    ],
    "wof:name":"Clean Sweep",
    "wof:placetype":"venue"
},
  "geometry": {"coordinates":[-82.80196599999999,42.948662],"type":"Point"}
}