{
  "type": "Feature",
  "properties": {
    "iso:country":"US",
    "sg:address":"38807 Ann Arbor Rd",
    "sg:city":"Livonia",
    "sg:classifiers":[
        {
            "category":"Banks & Credit Unions",
            "subcategory":"Financial Services",
            "type":"Services"
        }
    ],
    "sg:phone":"+1 734 464 1415",
    "sg:postcode":"48150",
    "sg:province":"MI",
    "sg:tags":[
        "broker",
        "mortgage"
    ],
    "wof:name":"Park Place Mortgage",
    "wof:placetype":"venue"
},
  "geometry": {"coordinates":[-83.424599,42.359901],"type":"Point"}
}