{
  "type": "Feature",
  "properties": {
    "iso:country":"US",
    "sg:address":"7247 Fay Dr",
    "sg:city":"Belleville",
    "sg:classifiers":[
        {
            "category":"Professional",
            "subcategory":"Management & Consulting",
            "type":"Services"
        }
    ],
    "sg:phone":"+1 734 699 8262",
    "sg:postcode":"48111",
    "sg:province":"MI",
    "wof:name":"Primerica",
    "wof:placetype":"venue"
},
  "geometry": {"coordinates":[-83.48356800000001,42.249336],"type":"Point"}
}