{
  "type": "Feature",
  "properties": {
    "iso:country":"US",
    "sg:address":"16636 Harper Ave",
    "sg:city":"Detroit",
    "sg:classifiers":[
        {
            "category":"Food & Beverages",
            "subcategory":"Liquor & Beverages",
            "type":"Retail Goods"
        }
    ],
    "sg:phone":"+1 313 881 3242",
    "sg:postcode":"48224",
    "sg:province":"MI",
    "sg:tags":[
        "beer",
        "spirit",
        "wine"
    ],
    "wof:name":"McDonnell Drugs",
    "wof:placetype":"venue"
},
  "geometry": {"coordinates":[-82.94090300000001,42.413399],"type":"Point"}
}