{
  "type": "Feature",
  "properties": {
    "iso:country":"US",
    "sg:address":"13046 Gratiot Ave",
    "sg:city":"Detroit",
    "sg:classifiers":[
        {
            "category":"Shopping",
            "subcategory":"Beauty & Cosmetics",
            "type":"Retail Goods"
        },
        {
            "category":"Personal",
            "subcategory":"Barber",
            "type":"Services"
        }
    ],
    "sg:phone":"+1 313 372 9485",
    "sg:postcode":"48205",
    "sg:province":"MI",
    "sg:tags":[
        "equipment",
        "perfume",
        "salons-equipment",
        "supply"
    ],
    "wof:name":"Lee S Y Beauty Supply Company",
    "wof:placetype":"venue"
},
  "geometry": {"coordinates":[-82.986397,42.4216],"type":"Point"}
}