{
  "type": "Feature",
  "properties": {
    "iso:country":"US",
    "sg:address":"8221 Grand Oaks Ct",
    "sg:city":"Washington",
    "sg:classifiers":[
        {
            "category":"Retail",
            "subcategory":"Car Wash",
            "type":"Services"
        }
    ],
    "sg:phone":"+1 586 336 0302",
    "sg:postcode":"48095",
    "sg:province":"MI",
    "sg:tags":[
        "carwash"
    ],
    "wof:name":"Easy Clean Carwash",
    "wof:placetype":"venue"
},
  "geometry": {"coordinates":[-83.030135,42.794223],"type":"Point"}
}