{
  "type": "Feature",
  "properties": {
    "iso:country":"US",
    "sg:address":"601 Michigan Ave",
    "sg:city":"Gladstone",
    "sg:classifiers":[
        {
            "category":"Organizations",
            "subcategory":"Community Association",
            "type":"Services"
        }
    ],
    "sg:phone":"+1 906 428 1184",
    "sg:postcode":"49837",
    "sg:province":"MI",
    "sg:tags":[
        "club"
    ],
    "wof:name":"Delta Alano Club",
    "wof:placetype":"venue"
},
  "geometry": {"coordinates":[-87.014889,45.845589],"type":"Point"}
}