{
  "type": "Feature",
  "properties": {
    "iso:country":"US",
    "sg:address":"337 E Huron St",
    "sg:city":"Ann Arbor",
    "sg:classifiers":[
        {
            "category":"Real Estate",
            "subcategory":"Real Estate Operator",
            "type":"Services"
        }
    ],
    "sg:phone":"+1 734 662 7787",
    "sg:postcode":"48104",
    "sg:province":"MI",
    "sg:tags":[
        "building",
        "apartment"
    ],
    "wof:name":"Campus Management Inc",
    "wof:placetype":"venue"
},
  "geometry": {"coordinates":[-83.744586,42.281381],"type":"Point"}
}