{
  "type": "Feature",
  "properties": {
    "iso:country":"US",
    "sg:address":"1661 Franklin St SE",
    "sg:city":"Grand Rapids",
    "sg:classifiers":[
        {
            "category":"Organizations",
            "subcategory":"Community Association",
            "type":"Services"
        }
    ],
    "sg:phone":"+1 616 248 3722",
    "sg:postcode":"49506",
    "sg:province":"MI",
    "wof:name":"Rock Inner City Boys Club",
    "wof:placetype":"venue"
},
  "geometry": {"coordinates":[-85.62731100000001,42.948334],"type":"Point"}
}