{
  "type": "Feature",
  "properties": {
    "iso:country":"US",
    "sg:address":"19432 W Warren Ave",
    "sg:city":"Detroit",
    "sg:classifiers":[
        {
            "category":"Bars & Pubs",
            "subcategory":"Nightclub",
            "type":"Food & Drink"
        }
    ],
    "sg:phone":"+1 313 336 6655",
    "sg:postcode":"48228",
    "sg:province":"MI",
    "sg:tags":[
        "nightlife"
    ],
    "wof:name":"Last Call",
    "wof:placetype":"venue"
},
  "geometry": {"coordinates":[-83.23110200000001,42.3433],"type":"Point"}
}