{
  "type": "Feature",
  "properties": {
    "iso:country":"US",
    "sg:address":"1926 W Saginaw St",
    "sg:city":"Lansing",
    "sg:classifiers":[
        {
            "category":"Retail",
            "subcategory":"Auto Repair",
            "type":"Services"
        }
    ],
    "sg:phone":"+1 517 371 7838",
    "sg:postcode":"48915",
    "sg:province":"MI",
    "sg:tags":[
        "automotive",
        "general"
    ],
    "wof:name":"Accurate Auto Inc",
    "wof:placetype":"venue"
},
  "geometry": {"coordinates":[-84.578309,42.740977],"type":"Point"}
}