{
  "type": "Feature",
  "properties": {
    "iso:country":"US",
    "sg:address":"1250 S Getty St",
    "sg:city":"Muskegon",
    "sg:classifiers":[
        {
            "category":"Building & Trades",
            "subcategory":"Equipment Rental",
            "type":"Services"
        }
    ],
    "sg:phone":"+1 231 722 1089",
    "sg:postcode":"49442",
    "sg:province":"MI",
    "sg:tags":[
        "store"
    ],
    "sg:website":"www.redirental.com",
    "wof:name":"Redi Rental",
    "wof:placetype":"venue"
},
  "geometry": {"coordinates":[-86.22419600000001,43.230213],"type":"Point"}
}