{
  "type": "Feature",
  "properties": {
    "iso:country":"US",
    "sg:address":"920 Abingdon St",
    "sg:city":"Oxford",
    "sg:classifiers":[
        {
            "category":"Building & Trades",
            "subcategory":"Electrical",
            "type":"Services"
        }
    ],
    "sg:phone":"+1 248 628 6700",
    "sg:postcode":"48371",
    "sg:province":"MI",
    "sg:tags":[
        "electric",
        "contractor"
    ],
    "wof:name":"Grampian Corp",
    "wof:placetype":"venue"
},
  "geometry": {"coordinates":[-83.250435,42.822179],"type":"Point"}
}