{
  "type": "Feature",
  "properties": {
    "iso:country":"US",
    "sg:address":"712 E Superior St",
    "sg:city":"Alma",
    "sg:classifiers":[
        {
            "category":"Freight",
            "type":"Transportation"
        }
    ],
    "sg:phone":"+1 989 463 1151",
    "sg:postcode":"48801",
    "sg:province":"MI",
    "sg:tags":[
        "warehouse"
    ],
    "wof:name":"Apco Air",
    "wof:placetype":"venue"
},
  "geometry": {"coordinates":[-84.65192399999999,43.378883],"type":"Point"}
}