{
  "type": "Feature",
  "properties": {
    "iso:country":"US",
    "sg:address":"575 Grass Lake Rd",
    "sg:city":"Coldwater",
    "sg:classifiers":[
        {
            "category":"Real Estate",
            "subcategory":"Real Estate Operator",
            "type":"Services"
        }
    ],
    "sg:phone":"+1 517 278 8870",
    "sg:postcode":"49036",
    "sg:province":"MI",
    "sg:tags":[
        "building",
        "apartment"
    ],
    "wof:name":"Virginia Manor Apartments",
    "wof:placetype":"venue"
},
  "geometry": {"coordinates":[-85.038962,41.827356],"type":"Point"}
}