{
  "type": "Feature",
  "properties": {
    "iso:country":"US",
    "sg:address":"20266 Woodward Ave",
    "sg:city":"Highland Park",
    "sg:classifiers":[
        {
            "category":"Travel",
            "subcategory":"Hotels & Motels",
            "type":"Entertainment"
        }
    ],
    "sg:phone":"+1 313 368 2900",
    "sg:postcode":"48203",
    "sg:province":"MI",
    "wof:name":"Delido Motel",
    "wof:placetype":"venue"
},
  "geometry": {"coordinates":[-83.120796,42.441002],"type":"Point"}
}