{
  "type": "Feature",
  "properties": {
    "iso:country":"US",
    "sg:address":"3200 Greenfield Rd",
    "sg:city":"Detroit",
    "sg:classifiers":[
        {
            "category":"Professional",
            "subcategory":"Employment Agencies",
            "type":"Services"
        }
    ],
    "sg:phone":"+1 313 271 5300",
    "sg:postcode":"48204",
    "sg:province":"MI",
    "sg:website":"www.kellyservices.us",
    "wof:name":"Kelly Services",
    "wof:placetype":"venue"
},
  "geometry": {"coordinates":[-83.185408,42.303386],"type":"Point"}
}