{
  "type": "Feature",
  "properties": {
    "iso:country":"US",
    "sg:address":"5255 Alpine Ave NW",
    "sg:city":"Comstock Park",
    "sg:classifiers":[
        {
            "category":"Education",
            "subcategory":"Library",
            "type":"Public Place"
        }
    ],
    "sg:phone":"+1 616 647 3810",
    "sg:postcode":"49321",
    "sg:province":"MI",
    "wof:name":"Alpine Branch Library",
    "wof:placetype":"venue"
},
  "geometry": {"coordinates":[-85.69015400000001,43.059106],"type":"Point"}
}