{
  "type": "Feature",
  "properties": {
    "iso:country":"US",
    "sg:address":"6316 3rd St",
    "sg:city":"Holton",
    "sg:classifiers":[
        {
            "category":"Professional",
            "subcategory":"Secretarial Services",
            "type":"Services"
        }
    ],
    "sg:phone":"+1 231 821 2585",
    "sg:postcode":"49425",
    "sg:province":"MI",
    "sg:tags":[
        "reporting"
    ],
    "wof:name":"Jane of All Trades",
    "wof:placetype":"venue"
},
  "geometry": {"coordinates":[-86.080299,43.414476],"type":"Point"}
}