{
  "type": "Feature",
  "properties": {
    "iso:country":"US",
    "sg:address":"2034 Horton Ave SE",
    "sg:city":"Grand Rapids",
    "sg:classifiers":[
        {
            "category":"Organizations",
            "subcategory":"Religious Organization",
            "type":"Services"
        }
    ],
    "sg:phone":"+1 616 245 3899",
    "sg:postcode":"49507",
    "sg:province":"MI",
    "sg:tags":[
        "church"
    ],
    "wof:name":"Temple Of Christ Church",
    "wof:placetype":"venue"
},
  "geometry": {"coordinates":[-85.66525,42.926217],"type":"Point"}
}