{
  "type": "Feature",
  "properties": {
    "iso:country":"US",
    "sg:address":"40820 Ryan Rd",
    "sg:city":"Sterling Heights",
    "sg:classifiers":[
        {
            "category":"Personal",
            "subcategory":"Nail Salon",
            "type":"Services"
        }
    ],
    "sg:phone":"+1 586 264 0630",
    "sg:postcode":"48310",
    "sg:province":"MI",
    "wof:name":"Five Star Nail",
    "wof:placetype":"venue"
},
  "geometry": {"coordinates":[-83.07061400000001,42.592663],"type":"Point"}
}