{
  "type": "Feature",
  "properties": {
    "iso:country":"US",
    "sg:address":"21609 Newcastle Rd",
    "sg:city":"Harper Woods",
    "sg:classifiers":[
        {
            "category":"Professional",
            "subcategory":"Art Services",
            "type":"Services"
        }
    ],
    "sg:phone":"+1 313 881 8939",
    "sg:postcode":"48225",
    "sg:province":"MI",
    "sg:tags":[
        "commercial",
        "design"
    ],
    "wof:name":"Geodesign Incorporated",
    "wof:placetype":"venue"
},
  "geometry": {"coordinates":[-82.916928,42.424618],"type":"Point"}
}