{
  "type": "Feature",
  "properties": {
    "iso:country":"US",
    "sg:address":"4119 Wolf Lake Rd",
    "sg:city":"Grass Lake",
    "sg:classifiers":[
        {
            "category":"Professional",
            "subcategory":"Detective & Security Services",
            "type":"Services"
        }
    ],
    "sg:phone":"+1 517 522 4887",
    "sg:postcode":"49240",
    "sg:province":"MI",
    "sg:tags":[
        "car"
    ],
    "wof:name":"Jak Enterprises",
    "wof:placetype":"venue"
},
  "geometry": {"coordinates":[-84.220162,42.199384],"type":"Point"}
}