{
  "type": "Feature",
  "properties": {
    "iso:country":"US",
    "sg:address":"1954 Liberty Ave",
    "sg:city":"Lincoln Park",
    "sg:classifiers":[
        {
            "category":"Retail",
            "subcategory":"Repair Shop",
            "type":"Services"
        }
    ],
    "sg:phone":"+1 313 928 7065",
    "sg:postcode":"48146",
    "sg:province":"MI",
    "wof:name":"Refuse & Recycling Equipment",
    "wof:placetype":"venue"
},
  "geometry": {"coordinates":[-83.19695299999999,42.234051],"type":"Point"}
}