{
  "type": "Feature",
  "properties": {
    "iso:country":"US",
    "sg:address":"639 S Mill St",
    "sg:city":"Plymouth",
    "sg:classifiers":[
        {
            "category":"Home & Garden",
            "subcategory":"Building Materials",
            "type":"Retail Goods"
        }
    ],
    "sg:phone":"+1 734 453 7300",
    "sg:postcode":"48170",
    "sg:province":"MI",
    "sg:tags":[
        "lumber"
    ],
    "wof:name":"Lumber Mart",
    "wof:placetype":"venue"
},
  "geometry": {"coordinates":[-83.460027,42.367412],"type":"Point"}
}