{
  "type": "Feature",
  "properties": {
    "iso:country":"US",
    "sg:address":"5221 122nd Ave",
    "sg:city":"Fennville",
    "sg:classifiers":[
        {
            "category":"Building & Trades",
            "subcategory":"Plumbing",
            "type":"Services"
        }
    ],
    "sg:phone":"+1 269 561 5658",
    "sg:postcode":"49408",
    "sg:province":"MI",
    "sg:tags":[
        "conditioning",
        "air",
        "system",
        "contractor"
    ],
    "wof:name":"Hobbs Heating & Air Cond Svc",
    "wof:placetype":"venue"
},
  "geometry": {"coordinates":[-86.057396,42.579232],"type":"Point"}
}