{
  "type": "Feature",
  "properties": {
    "iso:country":"US",
    "sg:address":"35551 Ford Rd",
    "sg:city":"Westland",
    "sg:classifiers":[
        {
            "category":"Professional",
            "subcategory":"Lawyer & Legal Services",
            "type":"Services"
        }
    ],
    "sg:phone":"+1 734 326 2101",
    "sg:postcode":"48185",
    "sg:province":"MI",
    "wof:name":"Clos Charles E Atty",
    "wof:placetype":"venue"
},
  "geometry": {"coordinates":[-83.3909,42.324402],"type":"Point"}
}