{
  "type": "Feature",
  "properties": {
    "iso:country":"US",
    "sg:address":"20714 Cedar St",
    "sg:city":"Onaway",
    "sg:classifiers":[
        {
            "category":"Real Estate",
            "subcategory":"Real Estate Agent",
            "type":"Services"
        }
    ],
    "sg:phone":"+1 989 733 9947",
    "sg:postcode":"49765",
    "sg:province":"MI",
    "wof:name":"Cardinal Real Estate",
    "wof:placetype":"venue"
},
  "geometry": {"coordinates":[-84.22880000000001,45.361219],"type":"Point"}
}