{
  "type": "Feature",
  "properties": {
    "iso:country":"US",
    "sg:address":"1137 3rd St",
    "sg:city":"Muskegon",
    "sg:classifiers":[
        {
            "category":"Shopping",
            "subcategory":"Clothing, Apparel, & Fashions",
            "type":"Retail Goods"
        }
    ],
    "sg:phone":"+1 231 728 3352",
    "sg:postcode":"49441",
    "sg:province":"MI",
    "sg:tags":[
        "theatrical",
        "costume"
    ],
    "wof:name":"Glitteratti Theatricals",
    "wof:placetype":"venue"
},
  "geometry": {"coordinates":[-86.24953499999999,43.232065],"type":"Point"}
}