{
  "type": "Feature",
  "properties": {
    "iso:country":"US",
    "sg:address":"462 W Sanilac Rd",
    "sg:city":"Sandusky",
    "sg:classifiers":[
        {
            "category":"Shopping",
            "subcategory":"Computers & Home Electronics",
            "type":"Retail Goods"
        },
        {
            "category":"Cinema",
            "subcategory":"Movie Rental",
            "type":"Entertainment"
        }
    ],
    "sg:phone":"+1 810 648 4111",
    "sg:postcode":"48471",
    "sg:province":"MI",
    "sg:tags":[
        "leasing",
        "video",
        "disc",
        "tape",
        "supply"
    ],
    "wof:name":"Real Video Of Sandusky",
    "wof:placetype":"venue"
},
  "geometry": {"coordinates":[-82.839265,43.421134],"type":"Point"}
}