{
  "type": "Feature",
  "properties": {
    "iso:country":"US",
    "sg:address":"10867 W Jefferson Ave",
    "sg:city":"River Rouge",
    "sg:classifiers":[
        {
            "category":"Food & Beverages",
            "subcategory":"Groceries & Convenience Stores",
            "type":"Retail Goods"
        }
    ],
    "sg:phone":"+1 313 842 0580",
    "sg:postcode":"48218",
    "sg:province":"MI",
    "wof:name":"Bi-Rite Supermarket",
    "wof:placetype":"venue"
},
  "geometry": {"coordinates":[-83.1353,42.269402],"type":"Point"}
}