{
  "type": "Feature",
  "properties": {
    "iso:country":"US",
    "sg:address":"887 Oakcrest Ln",
    "sg:city":"Jenison",
    "sg:classifiers":[
        {
            "category":"Health Services",
            "subcategory":"Nursing And Care Facility",
            "type":"Services"
        }
    ],
    "sg:phone":"+1 616 457 3576",
    "sg:postcode":"49428",
    "sg:province":"MI",
    "sg:tags":[
        "intermediate"
    ],
    "wof:name":"Maplewood Manor",
    "wof:placetype":"venue"
},
  "geometry": {"coordinates":[-85.80276600000001,42.914038],"type":"Point"}
}