{
  "type": "Feature",
  "properties": {
    "iso:country":"US",
    "sg:address":"22250 Schmeman Ave",
    "sg:city":"Warren",
    "sg:classifiers":[
        {
            "category":"Manufacturing",
            "subcategory":"Metals",
            "type":"Manufacturing & Wholesale Goods"
        }
    ],
    "sg:phone":"+1 586 445 8950",
    "sg:postcode":"48089",
    "sg:province":"MI",
    "sg:tags":[
        "copper",
        "foundry"
    ],
    "wof:name":"Special Bushings Pins & Sleeve",
    "wof:placetype":"venue"
},
  "geometry": {"coordinates":[-82.99323800000001,42.457881],"type":"Point"}
}