{
  "type": "Feature",
  "properties": {
    "iso:country":"US",
    "sg:address":"18748 Susanna Dr",
    "sg:city":"Livonia",
    "sg:classifiers":[
        {
            "category":"Wholesale",
            "subcategory":"Metals & Minerals",
            "type":"Manufacturing & Wholesale Goods"
        }
    ],
    "sg:phone":"+1 734 542 0892",
    "sg:postcode":"48152",
    "sg:province":"MI",
    "sg:tags":[
        "steel",
        "consulting",
        "metallurgical",
        "trading",
        "broker"
    ],
    "wof:name":"Linick International",
    "wof:placetype":"venue"
},
  "geometry": {"coordinates":[-83.420959,42.423664],"type":"Point"}
}