{
  "type": "Feature",
  "properties": {
    "iso:country":"US",
    "sg:address":"27508 Sutherland Ave",
    "sg:city":"Warren",
    "sg:classifiers":[
        {
            "category":"Retail",
            "subcategory":"Laundry & Dry Cleaning",
            "type":"Services"
        }
    ],
    "sg:phone":"+1 586 773 0735",
    "sg:postcode":"48088",
    "sg:province":"MI",
    "wof:name":"Dedicated Carpet",
    "wof:placetype":"venue"
},
  "geometry": {"coordinates":[-82.982776,42.497894],"type":"Point"}
}