{
  "type": "Feature",
  "properties": {
    "iso:country":"US",
    "sg:address":"17617 Sorrento St",
    "sg:city":"Detroit",
    "sg:classifiers":[
        {
            "category":"Professional",
            "subcategory":"Detective & Security Services",
            "type":"Services"
        }
    ],
    "sg:phone":"+1 313 862 3333",
    "sg:postcode":"48235",
    "sg:province":"MI",
    "sg:tags":[
        "car"
    ],
    "wof:name":"Accident Analis Reconstruction",
    "wof:placetype":"venue"
},
  "geometry": {"coordinates":[-83.17386500000001,42.421679],"type":"Point"}
}