{
  "type": "Feature",
  "properties": {
    "iso:country":"US",
    "sg:address":"1799 R W Berends Dr SW",
    "sg:city":"Wyoming",
    "sg:classifiers":[
        {
            "category":"Banks & Credit Unions",
            "subcategory":"Investment Brokerage",
            "type":"Services"
        }
    ],
    "sg:phone":"+1 616 940 3373",
    "sg:postcode":"49519",
    "sg:province":"MI",
    "sg:tags":[
        "consultant",
        "planning",
        "financial"
    ],
    "wof:name":"Financial Network Investment",
    "wof:placetype":"venue"
},
  "geometry": {"coordinates":[-85.708361,42.882687],"type":"Point"}
}