{
  "type": "Feature",
  "properties": {
    "iso:country":"US",
    "sg:address":"7676 N Canton Center Rd",
    "sg:city":"Canton",
    "sg:classifiers":[
        {
            "category":"Health Services",
            "subcategory":"Dentist",
            "type":"Services"
        }
    ],
    "sg:phone":"+1 734 207 1800",
    "sg:postcode":"48187",
    "sg:province":"MI",
    "sg:tags":[
        "orthodontist",
        "cosmetic"
    ],
    "sg:website":"www.BrightsideDental.com",
    "wof:name":"Bright Side Dental",
    "wof:placetype":"venue"
},
  "geometry": {"coordinates":[-83.48818300000001,42.341053],"type":"Point"}
}