{
  "type": "Feature",
  "properties": {
    "iso:country":"US",
    "sg:address":"6215 Clyde Park Ave SW",
    "sg:city":"Byron Center",
    "sg:classifiers":[
        {
            "category":"Building & Trades",
            "subcategory":"Landscaping Services",
            "type":"Services"
        }
    ],
    "sg:phone":"+1 616 530 9724",
    "sg:postcode":"49315",
    "sg:province":"MI",
    "sg:tags":[
        "lawn",
        "maintenance",
        "grounds"
    ],
    "wof:name":"Green Master Landscape Mntnc",
    "wof:placetype":"venue"
},
  "geometry": {"coordinates":[-85.68369,42.854044],"type":"Point"}
}