{
  "type": "Feature",
  "properties": {
    "iso:country":"US",
    "sg:address":"24600 Northwestern Hwy",
    "sg:city":"Southfield",
    "sg:classifiers":[
        {
            "category":"Professional",
            "subcategory":"Business Services",
            "type":"Services"
        },
        {
            "category":"Insurance",
            "subcategory":"Insurance Agent",
            "type":"Services"
        }
    ],
    "sg:phone":"+1 248 356 3366",
    "sg:postcode":"48075",
    "sg:province":"MI",
    "sg:website":"www.actionbenefits.com",
    "wof:name":"Association Benefits Co",
    "wof:placetype":"venue"
},
  "geometry": {"coordinates":[-83.2353,42.468588],"type":"Point"}
}