{
  "type": "Feature",
  "properties": {
    "iso:country":"US",
    "sg:address":"287 Lincoln Ave",
    "sg:city":"Holland",
    "sg:classifiers":[
        {
            "category":"Retail",
            "subcategory":"Auto Repair",
            "type":"Services"
        }
    ],
    "sg:phone":"+1 616 546 3196",
    "sg:postcode":"49423",
    "sg:province":"MI",
    "sg:tags":[
        "wrecker"
    ],
    "wof:name":"Ottawa Area Fair Housing",
    "wof:placetype":"venue"
},
  "geometry": {"coordinates":[-86.0973,42.786744],"type":"Point"}
}