{
  "type": "Feature",
  "properties": {
    "iso:country":"US",
    "sg:address":"8811 Ward St",
    "sg:city":"Holton",
    "sg:classifiers":[
        {
            "category":"Recreation",
            "type":"Entertainment"
        }
    ],
    "sg:phone":"+1 231 821 0770",
    "sg:postcode":"49425",
    "sg:province":"MI",
    "sg:tags":[
        "club",
        "membership"
    ],
    "wof:name":"Holton Youth Soccer",
    "wof:placetype":"venue"
},
  "geometry": {"coordinates":[-86.08301899999999,43.413129],"type":"Point"}
}