{
  "type": "Feature",
  "properties": {
    "iso:country":"US",
    "sg:address":"69 W Carleton Rd",
    "sg:city":"Hillsdale",
    "sg:classifiers":[
        {
            "category":"Government",
            "subcategory":"Post Office",
            "type":"Public Place"
        }
    ],
    "sg:phone":"+1 517 000 1111",
    "sg:postcode":"49242",
    "sg:province":"MI",
    "wof:name":"US Post Office",
    "wof:placetype":"venue"
},
  "geometry": {"coordinates":[-84.639229,41.926706],"type":"Point"}
}