{
  "type": "Feature",
  "properties": {
    "iso:country":"US",
    "sg:address":"210 N Michigan Ave",
    "sg:city":"Big Rapids",
    "sg:classifiers":[
        {
            "category":"Home & Garden",
            "subcategory":"Building Materials",
            "type":"Retail Goods"
        }
    ],
    "sg:phone":"+1 231 796 8492",
    "sg:postcode":"49307",
    "sg:province":"MI",
    "sg:tags":[
        "paint"
    ],
    "wof:name":"Sherwin-Williams Paints",
    "wof:placetype":"venue"
},
  "geometry": {"coordinates":[-85.481951,43.700845],"type":"Point"}
}