{
  "type": "Feature",
  "properties": {
    "iso:country":"US",
    "sg:address":"131 Lafayette St",
    "sg:city":"Hudson",
    "sg:classifiers":[
        {
            "category":"Social Services",
            "subcategory":"Adult Care",
            "type":"Services"
        }
    ],
    "sg:phone":"+1 517 448 8045",
    "sg:postcode":"49247",
    "sg:province":"MI",
    "sg:tags":[
        "foster"
    ],
    "wof:name":"Lees Afc Home",
    "wof:placetype":"venue"
},
  "geometry": {"coordinates":[-84.35596700000001,41.852469],"type":"Point"}
}