{
  "type": "Feature",
  "properties": {
    "iso:country":"US",
    "sg:address":"12197 Crockery Creek Dr",
    "sg:city":"Ravenna",
    "sg:classifiers":[
        {
            "category":"Home & Garden",
            "subcategory":"Building Materials",
            "type":"Retail Goods"
        }
    ],
    "sg:phone":"+1 231 853 2248",
    "sg:postcode":"49451",
    "sg:province":"MI",
    "sg:tags":[
        "lumber"
    ],
    "wof:name":"Ravenna Lumber Co",
    "wof:placetype":"venue"
},
  "geometry": {"coordinates":[-85.94336300000001,43.184245],"type":"Point"}
}