{
  "type": "Feature",
  "properties": {
    "iso:country":"US",
    "sg:address":"25287 Island View Ln",
    "sg:city":"Sturgis",
    "sg:classifiers":[
        {
            "category":"Building & Trades",
            "subcategory":"Construction",
            "type":"Services"
        }
    ],
    "sg:phone":"+1 269 467 7142",
    "sg:postcode":"49091",
    "sg:province":"MI",
    "sg:tags":[
        "excavation",
        "contractor"
    ],
    "wof:name":"Susan Leist",
    "wof:placetype":"venue"
},
  "geometry": {"coordinates":[-85.461764,41.907329],"type":"Point"}
}