{
  "type": "Feature",
  "properties": {
    "iso:country":"US",
    "sg:address":"105 W Center St",
    "sg:city":"Linwood",
    "sg:classifiers":[
        {
            "category":"Personal",
            "subcategory":"Tanning Parlor",
            "type":"Services"
        }
    ],
    "sg:phone":"+1 989 697 4688",
    "sg:postcode":"48634",
    "sg:province":"MI",
    "sg:tags":[
        "salon"
    ],
    "wof:name":"Tropics",
    "wof:placetype":"venue"
},
  "geometry": {"coordinates":[-83.959919,43.738603],"type":"Point"}
}