{
  "type": "Feature",
  "properties": {
    "iso:country":"US",
    "sg:address":"27300 Southfield Rd",
    "sg:city":"Lathrup Village",
    "sg:classifiers":[
        {
            "category":"Wholesale",
            "subcategory":"Electrical",
            "type":"Manufacturing & Wholesale Goods"
        }
    ],
    "sg:phone":"+1 248 557 5445",
    "sg:postcode":"48076",
    "sg:province":"MI",
    "sg:tags":[
        "video",
        "disc",
        "tape"
    ],
    "wof:name":"Discount Video Wholesale",
    "wof:placetype":"venue"
},
  "geometry": {"coordinates":[-83.222014,42.490854],"type":"Point"}
}