{
  "type": "Feature",
  "properties": {
    "iso:country":"US",
    "sg:address":"475 E Chippewa River Rd",
    "sg:city":"Midland",
    "sg:classifiers":[
        {
            "category":"Building & Trades",
            "subcategory":"Cleaning & Sanitation",
            "type":"Services"
        }
    ],
    "sg:phone":"+1 989 835 8238",
    "sg:postcode":"48640",
    "sg:province":"MI",
    "sg:tags":[
        "janitor"
    ],
    "wof:name":"Shirley's Quality Cleaning",
    "wof:placetype":"venue"
},
  "geometry": {"coordinates":[-84.350838,43.600125],"type":"Point"}
}