{
  "type": "Feature",
  "properties": {
    "iso:country":"US",
    "sg:address":"26400 Little Mack Ave",
    "sg:city":"St Clair Shores",
    "sg:classifiers":[
        {
            "category":"Organizations",
            "subcategory":"Religious Organization",
            "type":"Services"
        }
    ],
    "sg:phone":"+1 586 778 0021",
    "sg:postcode":"48081",
    "sg:province":"MI",
    "sg:tags":[
        "church"
    ],
    "sg:website":"www.bethelscs.org",
    "wof:name":"Bethel Lutheran Church",
    "wof:placetype":"venue"
},
  "geometry": {"coordinates":[-82.907421,42.488018],"type":"Point"}
}