{
  "type": "Feature",
  "properties": {
    "iso:country":"US",
    "sg:address":"23780 Hoover Rd",
    "sg:city":"Warren",
    "sg:classifiers":[
        {
            "category":"Retail",
            "subcategory":"Laundry & Dry Cleaning",
            "type":"Services"
        }
    ],
    "sg:phone":"+1 586 759 0207",
    "sg:postcode":"48089",
    "sg:province":"MI",
    "sg:tags":[
        "linen",
        "supply"
    ],
    "wof:name":"Best Textile Svc",
    "wof:placetype":"venue"
},
  "geometry": {"coordinates":[-83.00583899999999,42.468513],"type":"Point"}
}