{
  "type": "Feature",
  "properties": {
    "iso:country":"US",
    "sg:address":"1210 S Front St",
    "sg:city":"Marquette",
    "sg:classifiers":[
        {
            "category":"Shopping",
            "subcategory":"Computers & Home Electronics",
            "type":"Retail Goods"
        }
    ],
    "sg:phone":"+1 906 226 1186",
    "sg:postcode":"49855",
    "sg:province":"MI",
    "sg:tags":[
        "audio"
    ],
    "wof:name":"Audio Video Gear",
    "wof:placetype":"venue"
},
  "geometry": {"coordinates":[-87.396618,46.532834],"type":"Point"}
}