{
  "type": "Feature",
  "properties": {
    "iso:country":"US",
    "sg:address":"11410 S West View Dr",
    "sg:city":"Empire",
    "sg:classifiers":[
        {
            "category":"Professional",
            "subcategory":"Management & Consulting",
            "type":"Services"
        }
    ],
    "sg:phone":"+1 231 326 3611",
    "sg:postcode":"49630",
    "sg:province":"MI",
    "sg:tags":[
        "consultant",
        "business"
    ],
    "wof:name":"Steckler Assoc Consulting LLC",
    "wof:placetype":"venue"
},
  "geometry": {"coordinates":[-86.040547,44.816056],"type":"Point"}
}