{
  "type": "Feature",
  "properties": {
    "iso:country":"US",
    "sg:address":"80195 Co Rd 358 S",
    "sg:city":"Decatur",
    "sg:classifiers":[
        {
            "category":"Social Services",
            "subcategory":"Child Care",
            "type":"Services"
        }
    ],
    "sg:phone":"+1 269 423 6137",
    "sg:postcode":"49045",
    "sg:province":"MI",
    "sg:tags":[
        "kindergarten",
        "academic",
        "school"
    ],
    "sg:website":"www.telamon.org",
    "wof:name":"Decatur Migrant Headstart",
    "wof:placetype":"venue"
},
  "geometry": {"coordinates":[-86.011585,42.12777],"type":"Point"}
}