{
  "type": "Feature",
  "properties": {
    "iso:country":"US",
    "sg:address":"5192 E Davison St",
    "sg:city":"Hamtramck",
    "sg:classifiers":[
        {
            "category":"Retail",
            "subcategory":"Event Space",
            "type":"Services"
        }
    ],
    "sg:phone":"+1 313 893 3300",
    "sg:postcode":"48212",
    "sg:province":"MI",
    "sg:tags":[
        "venue"
    ],
    "wof:name":"The Millennium All Occasion Hall",
    "wof:placetype":"venue"
},
  "geometry": {"coordinates":[-83.050499,42.419601],"type":"Point"}
}