{
  "type": "Feature",
  "properties": {
    "iso:country":"US",
    "sg:address":"304 N 9th Ave",
    "sg:city":"Alpena",
    "sg:classifiers":[
        {
            "category":"Shopping",
            "subcategory":"Bicycles & Sporting Goods",
            "type":"Retail Goods"
        }
    ],
    "sg:phone":"+1 989 354 2070",
    "sg:postcode":"49707",
    "sg:province":"MI",
    "sg:tags":[
        "tackle",
        "fishing"
    ],
    "wof:name":"Clem's Live Bait & Tackle",
    "wof:placetype":"venue"
},
  "geometry": {"coordinates":[-83.43809,45.070698],"type":"Point"}
}