{
  "type": "Feature",
  "properties": {
    "iso:country":"US",
    "sg:address":"6266 Oakhurst St",
    "sg:city":"Holland",
    "sg:classifiers":[
        {
            "category":"Insurance",
            "subcategory":"Health Insurance",
            "type":"Services"
        }
    ],
    "sg:phone":"+1 616 335 3618",
    "sg:postcode":"49423",
    "sg:province":"MI",
    "sg:tags":[
        "carrier"
    ],
    "wof:name":"Hmx Employee Association",
    "wof:placetype":"venue"
},
  "geometry": {"coordinates":[-86.162627,42.767143],"type":"Point"}
}