{
  "type": "Feature",
  "properties": {
    "iso:country":"US",
    "sg:address":"1919 Birchwood Dr",
    "sg:city":"Troy",
    "sg:classifiers":[
        {
            "category":"Banks & Credit Unions",
            "subcategory":"Bank",
            "type":"Services"
        }
    ],
    "sg:phone":"+1 248 528 3770",
    "sg:postcode":"48083",
    "sg:province":"MI",
    "sg:tags":[
        "consulting",
        "computer"
    ],
    "wof:name":"Professional Computer Services",
    "wof:placetype":"venue"
},
  "geometry": {"coordinates":[-83.10806700000001,42.550874],"type":"Point"}
}