{
  "type": "Feature",
  "properties": {
    "iso:country":"US",
    "sg:address":"12825 Eureka Rd",
    "sg:city":"Southgate",
    "sg:classifiers":[
        {
            "category":"Restaurant",
            "type":"Food & Drink"
        }
    ],
    "sg:menulink":"http://www.allmenus.com/mi/southgate/176536-kfc---kentucky-fried-chicken/menu/",
    "sg:phone":"+1 734 285 9080",
    "sg:postcode":"48195",
    "sg:province":"MI",
    "sg:tags":[
        "american",
        "chicken"
    ],
    "wof:name":"KFC - Kentucky Fried Chicken",
    "wof:placetype":"venue"
},
  "geometry": {"coordinates":[-83.181749,42.199414],"type":"Point"}
}