{
  "type": "Feature",
  "properties": {
    "iso:country":"US",
    "sg:address":"10800 E Canfield St",
    "sg:city":"Detroit",
    "sg:classifiers":[
        {
            "category":"Education",
            "subcategory":"School",
            "type":"Public Place"
        }
    ],
    "sg:phone":"+1 313 866 3101",
    "sg:postcode":"48214",
    "sg:province":"MI",
    "wof:name":"Damon Keith Elementary School",
    "wof:placetype":"venue"
},
  "geometry": {"coordinates":[-82.985604,42.381429],"type":"Point"}
}