{
  "type": "Feature",
  "properties": {
    "iso:country":"US",
    "sg:address":"23159 Colgate St",
    "sg:city":"Farmington",
    "sg:classifiers":[
        {
            "category":"Building & Trades",
            "subcategory":"Construction",
            "type":"Services"
        }
    ],
    "sg:phone":"+1 248 476 6635",
    "sg:postcode":"48336",
    "sg:province":"MI",
    "sg:tags":[
        "hanging",
        "contractor"
    ],
    "wof:name":"S&D Painting",
    "wof:placetype":"venue"
},
  "geometry": {"coordinates":[-83.34063399999999,42.461805],"type":"Point"}
}