{
  "type": "Feature",
  "properties": {
    "iso:country":"US",
    "sg:address":"17854 Maumee Ave",
    "sg:city":"Grosse Pointe",
    "sg:classifiers":[
        {
            "category":"Health Services",
            "subcategory":"Doctor",
            "type":"Services"
        },
        {
            "category":"Health Services",
            "subcategory":"Clinic",
            "type":"Services"
        }
    ],
    "sg:phone":"+1 313 886 2580",
    "sg:postcode":"48230",
    "sg:province":"MI",
    "sg:tags":[
        "counseling",
        "mental"
    ],
    "wof:name":"Cappas A Thomas PHD",
    "wof:placetype":"venue"
},
  "geometry": {"coordinates":[-82.903642,42.389117],"type":"Point"}
}