{
  "type": "Feature",
  "properties": {
    "iso:country":"US",
    "sg:address":"5717 Lincoln Ave",
    "sg:city":"Stevensville",
    "sg:classifiers":[
        {
            "category":"Building & Trades",
            "subcategory":"Construction",
            "type":"Services"
        }
    ],
    "sg:phone":"+1 269 429 8395",
    "sg:postcode":"49127",
    "sg:province":"MI",
    "sg:tags":[
        "painter"
    ],
    "wof:name":"Mead Painting",
    "wof:placetype":"venue"
},
  "geometry": {"coordinates":[-86.47529900000001,42.000626],"type":"Point"}
}