{
  "type": "Feature",
  "properties": {
    "iso:country":"US",
    "sg:address":"212 Washington Sq S",
    "sg:city":"Lansing",
    "sg:classifiers":[
        {
            "category":"Shopping",
            "subcategory":"Gifts & Souvenirs",
            "type":"Retail Goods"
        }
    ],
    "sg:phone":"+1 517 485 2369",
    "sg:postcode":"48933",
    "sg:province":"MI",
    "sg:tags":[
        "collectible"
    ],
    "wof:name":"Clem's Collectibles",
    "wof:placetype":"venue"
},
  "geometry": {"coordinates":[-84.55233200000001,42.731487],"type":"Point"}
}