{
  "type": "Feature",
  "properties": {
    "iso:country":"US",
    "sg:address":"16945 W Warren Ave",
    "sg:city":"Detroit",
    "sg:classifiers":[
        {
            "category":"Food & Beverages",
            "subcategory":"Liquor & Beverages",
            "type":"Retail Goods"
        }
    ],
    "sg:phone":"+1 313 581 6610",
    "sg:postcode":"48228",
    "sg:province":"MI",
    "sg:tags":[
        "beer",
        "spirit",
        "wine"
    ],
    "wof:name":"Serv-U-Well",
    "wof:placetype":"venue"
},
  "geometry": {"coordinates":[-83.211749,42.3433],"type":"Point"}
}