{
  "type": "Feature",
  "properties": {
    "iso:country":"US",
    "sg:address":"7426 Lindsey Rd",
    "sg:city":"East China",
    "sg:classifiers":[
        {
            "category":"Professional",
            "subcategory":"Business Services",
            "type":"Services"
        }
    ],
    "sg:phone":"+1 810 357 1719",
    "sg:postcode":"48054",
    "sg:province":"MI",
    "sg:tags":[
        "home",
        "inspection"
    ],
    "wof:name":"JGM Inspections Inc",
    "wof:placetype":"venue"
},
  "geometry": {"coordinates":[-82.608487,42.769467],"type":"Point"}
}