{
  "type": "Feature",
  "properties": {
    "iso:country":"US",
    "sg:address":"221 S Lincoln Ave",
    "sg:city":"Lakeview",
    "sg:classifiers":[
        {
            "category":"Personal",
            "subcategory":"Beauty Salon",
            "type":"Services"
        }
    ],
    "sg:phone":"+1 989 352 1300",
    "sg:postcode":"48850",
    "sg:province":"MI",
    "wof:name":"Hair Bendors",
    "wof:placetype":"venue"
},
  "geometry": {"coordinates":[-85.280331,43.443545],"type":"Point"}
}