{
  "type": "Feature",
  "properties": {
    "iso:country":"US",
    "sg:address":"850 N Adams Rd",
    "sg:city":"Birmingham",
    "sg:classifiers":[
        {
            "category":"Retail",
            "subcategory":"Auto Repair",
            "type":"Services"
        }
    ],
    "sg:phone":"+1 248 645 1724",
    "sg:postcode":"48009",
    "sg:province":"MI",
    "sg:tags":[
        "industry",
        "manufacturing"
    ],
    "wof:name":"Baxter Associates",
    "wof:placetype":"venue"
},
  "geometry": {"coordinates":[-83.206064,42.553745],"type":"Point"}
}