{
  "type": "Feature",
  "properties": {
    "iso:country":"US",
    "sg:address":"1295 S Center Rd Ste 101",
    "sg:city":"Flint",
    "sg:classifiers":[
        {
            "category":"Shopping",
            "subcategory":"Mobile Phones",
            "type":"Retail Goods"
        }
    ],
    "sg:phone":"+1 810 743 4846",
    "sg:postcode":"48509",
    "sg:province":"MI",
    "sg:website":"verizonwireless.com/Bestnetwork|...",
    "wof:name":"Verizon Wireless",
    "wof:placetype":"venue"
},
  "geometry": {"coordinates":[-83.63444699999999,43.010132],"type":"Point"}
}