{
  "type": "Feature",
  "properties": {
    "iso:country":"US",
    "sg:address":"1290 N Monroe St",
    "sg:city":"Monroe",
    "sg:classifiers":[
        {
            "category":"Autos & Motor Vehicles",
            "subcategory":"Auto Supplies",
            "type":"Retail Goods"
        }
    ],
    "sg:phone":"+1 734 243 8594",
    "sg:postcode":"48162",
    "sg:province":"MI",
    "sg:tags":[
        "tire"
    ],
    "wof:name":"Big O Tires",
    "wof:placetype":"venue"
},
  "geometry": {"coordinates":[-83.389717,41.933359],"type":"Point"}
}