{
  "type": "Feature",
  "properties": {
    "iso:country":"US",
    "sg:address":"3259 N Reese Rd",
    "sg:city":"Fairgrove",
    "sg:classifiers":[
        {
            "category":"Autos & Motor Vehicles",
            "subcategory":"Automobile Sales",
            "type":"Retail Goods"
        }
    ],
    "sg:phone":"+1 989 693 6879",
    "sg:postcode":"48733",
    "sg:province":"MI",
    "sg:tags":[
        "used"
    ],
    "wof:name":"Docs Auto Sales",
    "wof:placetype":"venue"
},
  "geometry": {"coordinates":[-83.69923799999999,43.558257],"type":"Point"}
}