{
  "type": "Feature",
  "properties": {
    "iso:country":"US",
    "sg:address":"901 Wilshire Dr",
    "sg:city":"Troy",
    "sg:classifiers":[
        {
            "category":"Professional",
            "subcategory":"Advertising",
            "type":"Services"
        }
    ],
    "sg:phone":"+1 248 244 8005",
    "sg:postcode":"48084",
    "sg:province":"MI",
    "sg:tags":[
        "counselor"
    ],
    "wof:name":"Mc Elfish & Co",
    "wof:placetype":"venue"
},
  "geometry": {"coordinates":[-83.165316,42.564493],"type":"Point"}
}