{
  "type": "Feature",
  "properties": {
    "iso:country":"US",
    "sg:address":"1390 N Bagley St",
    "sg:city":"Alpena",
    "sg:classifiers":[
        {
            "category":"Professional",
            "subcategory":"Detective & Security Services",
            "type":"Services"
        }
    ],
    "sg:phone":"+1 989 356 6364",
    "sg:postcode":"49707",
    "sg:province":"MI",
    "wof:name":"North Central Security Ltd",
    "wof:placetype":"venue"
},
  "geometry": {"coordinates":[-83.472087,45.06682],"type":"Point"}
}