{
  "type": "Feature",
  "properties": {
    "iso:country":"US",
    "sg:address":"2418 Ludington St",
    "sg:city":"Escanaba",
    "sg:classifiers":[
        {
            "category":"Restaurant",
            "type":"Food & Drink"
        }
    ],
    "sg:phone":"+1 906 786 7363",
    "sg:postcode":"49829",
    "sg:province":"MI",
    "sg:tags":[
        "out"
    ],
    "wof:name":"Gram's Pastries",
    "wof:placetype":"venue"
},
  "geometry": {"coordinates":[-87.084761,45.745823],"type":"Point"}
}