{
  "type": "Feature",
  "properties": {
    "iso:country":"US",
    "sg:address":"19781 15 Mile Rd",
    "sg:city":"Clinton Township",
    "sg:classifiers":[
        {
            "category":"Sports & Exercise",
            "subcategory":"Sports Center",
            "type":"Entertainment"
        }
    ],
    "sg:phone":"+1 586 792 4190",
    "sg:postcode":"48035",
    "sg:province":"MI",
    "sg:tags":[
        "amateur",
        "team"
    ],
    "wof:name":"Whirly Ball",
    "wof:placetype":"venue"
},
  "geometry": {"coordinates":[-82.91909800000001,42.554401],"type":"Point"}
}