{
  "type": "Feature",
  "properties": {
    "iso:country":"US",
    "sg:address":"31101 Dequindre Rd",
    "sg:city":"Madison Heights",
    "sg:classifiers":[
        {
            "category":"Cafe",
            "type":"Food & Drink"
        }
    ],
    "sg:menulink":"http://www.allmenus.com/mi/madison-heights/45817-cheers-grand-cafe/menu/",
    "sg:phone":"+1 248 733 1712",
    "sg:postcode":"48071",
    "sg:province":"MI",
    "sg:tags":[
        "wrap",
        "american",
        "sandwich"
    ],
    "wof:name":"Cheers Grand Cafe",
    "wof:placetype":"venue"
},
  "geometry": {"coordinates":[-83.08714999999999,42.521101],"type":"Point"}
}