{
  "type": "Feature",
  "properties": {
    "iso:country":"US",
    "sg:address":"23498 Michigan Ave",
    "sg:city":"Dearborn",
    "sg:classifiers":[
        {
            "category":"Insurance",
            "subcategory":"Hazard Insurance",
            "type":"Services"
        }
    ],
    "sg:phone":"+1 313 277 4600",
    "sg:postcode":"48124",
    "sg:province":"MI",
    "sg:website":"www.karcheragency.com",
    "wof:name":"Karcher Insurance Agency",
    "wof:placetype":"venue"
},
  "geometry": {"coordinates":[-83.263901,42.301899],"type":"Point"}
}