{
  "type": "Feature",
  "properties": {
    "iso:country":"US",
    "sg:address":"4532 Page Ave",
    "sg:city":"Michigan Center",
    "sg:classifiers":[
        {
            "category":"Retail",
            "subcategory":"Car Wash",
            "type":"Services"
        }
    ],
    "sg:phone":"+1 517 764 0782",
    "sg:postcode":"49254",
    "sg:province":"MI",
    "sg:tags":[
        "automobile",
        "detail",
        "clean"
    ],
    "wof:name":"D & G Detailing",
    "wof:placetype":"venue"
},
  "geometry": {"coordinates":[-84.329641,42.233504],"type":"Point"}
}