{
  "type": "Feature",
  "properties": {
    "iso:country":"US",
    "sg:address":"1910 W Pierson Rd",
    "sg:city":"Flint",
    "sg:classifiers":[
        {
            "category":"Real Estate",
            "subcategory":"Real Estate Operator",
            "type":"Services"
        }
    ],
    "sg:phone":"+1 810 789 2828",
    "sg:postcode":"48504",
    "sg:province":"MI",
    "sg:tags":[
        "apartment"
    ],
    "wof:name":"Orchard Ridge Apartments",
    "wof:placetype":"venue"
},
  "geometry": {"coordinates":[-83.728218,43.060768],"type":"Point"}
}