{
  "type": "Feature",
  "properties": {
    "iso:country":"US",
    "sg:address":"43100 W 9 Mile Rd",
    "sg:city":"Novi",
    "sg:classifiers":[
        {
            "category":"Wholesale",
            "subcategory":"Machinery & Supplies",
            "type":"Manufacturing & Wholesale Goods"
        }
    ],
    "sg:phone":"+1 248 380 6350",
    "sg:postcode":"48375",
    "sg:province":"MI",
    "sg:tags":[
        "tool",
        "industrial"
    ],
    "wof:name":"Ingersoll-Rand",
    "wof:placetype":"venue"
},
  "geometry": {"coordinates":[-83.473896,42.45223],"type":"Point"}
}