{
  "type": "Feature",
  "properties": {
    "iso:country":"US",
    "sg:address":"28000 Woodward Ave",
    "sg:city":"Royal Oak",
    "sg:classifiers":[
        {
            "category":"Professional",
            "subcategory":"Business Services",
            "type":"Services"
        }
    ],
    "sg:phone":"+1 248 399 1600",
    "sg:postcode":"48067",
    "sg:province":"MI",
    "sg:tags":[
        "interior",
        "consultant",
        "design",
        "decorator"
    ],
    "sg:website":"www.iscginc.com",
    "wof:name":"ISCG Inc",
    "wof:placetype":"venue"
},
  "geometry": {"coordinates":[-83.16659199999999,42.49778],"type":"Point"}
}