{
  "type": "Feature",
  "properties": {
    "iso:country":"US",
    "sg:address":"2975 Hickory Ln",
    "sg:city":"Ann Arbor",
    "sg:classifiers":[
        {
            "category":"Shopping",
            "subcategory":"Books",
            "type":"Retail Goods"
        }
    ],
    "sg:phone":"+1 734 975 1182",
    "sg:postcode":"48104",
    "sg:province":"MI",
    "wof:name":"1 800 Bookstore Co Inc",
    "wof:placetype":"venue"
},
  "geometry": {"coordinates":[-83.700811,42.271696],"type":"Point"}
}