{
  "type": "Feature",
  "properties": {
    "iso:country":"US",
    "sg:address":"110 N Broadway St",
    "sg:city":"Cassopolis",
    "sg:classifiers":[
        {
            "category":"Government",
            "subcategory":"Office",
            "type":"Public Place"
        }
    ],
    "sg:phone":"+1 269 445 4472",
    "sg:postcode":"49031",
    "sg:province":"MI",
    "sg:tags":[
        "county",
        "affairs",
        "admin"
    ],
    "wof:name":"Cass County Veterans Affairs",
    "wof:placetype":"venue"
},
  "geometry": {"coordinates":[-86.01245299999999,41.913195],"type":"Point"}
}