{
  "type": "Feature",
  "properties": {
    "iso:country":"US",
    "sg:address":"2710 S M 52",
    "sg:city":"Owosso",
    "sg:classifiers":[
        {
            "category":"Manufacturing",
            "subcategory":"Watercraft",
            "type":"Manufacturing & Wholesale Goods"
        }
    ],
    "sg:phone":"+1 989 725 5188",
    "sg:postcode":"48867",
    "sg:province":"MI",
    "sg:tags":[
        "rebuilt",
        "part",
        "boat"
    ],
    "wof:name":"Maurell Products",
    "wof:placetype":"venue"
},
  "geometry": {"coordinates":[-84.207404,42.958212],"type":"Point"}
}