{
  "type": "Feature",
  "properties": {
    "iso:country":"US",
    "sg:address":"2211 S Telegraph Rd",
    "sg:city":"Dearborn",
    "sg:classifiers":[
        {
            "category":"Travel",
            "subcategory":"Hotels & Motels",
            "type":"Entertainment"
        }
    ],
    "sg:phone":"+1 313 278 0140",
    "sg:postcode":"48124",
    "sg:province":"MI",
    "wof:name":"Dearborn Motor Lodge",
    "wof:placetype":"venue"
},
  "geometry": {"coordinates":[-83.271141,42.295374],"type":"Point"}
}