{
  "type": "Feature",
  "properties": {
    "iso:country":"US",
    "sg:address":"6741 Luana Ave",
    "sg:city":"Allen Park",
    "sg:classifiers":[
        {
            "category":"Local Transit",
            "type":"Transportation"
        }
    ],
    "sg:phone":"+1 313 382 0943",
    "sg:postcode":"48101",
    "sg:province":"MI",
    "sg:tags":[
        "passenger"
    ],
    "wof:name":"Executive Limousine Service",
    "wof:placetype":"venue"
},
  "geometry": {"coordinates":[-83.21910800000001,42.257009],"type":"Point"}
}