{
  "type": "Feature",
  "properties": {
    "iso:country":"US",
    "sg:address":"713 Fairbanks St",
    "sg:city":"Iron Mountain",
    "sg:classifiers":[
        {
            "category":"Personal",
            "subcategory":"Beauty Salon",
            "type":"Services"
        }
    ],
    "sg:phone":"+1 906 779 0060",
    "sg:postcode":"49801",
    "sg:province":"MI",
    "sg:tags":[
        "shop"
    ],
    "wof:name":"Options Hair Design",
    "wof:placetype":"venue"
},
  "geometry": {"coordinates":[-88.076278,45.825345],"type":"Point"}
}