{
  "type": "Feature",
  "properties": {
    "iso:country":"US",
    "sg:address":"58024 Van Dyke Rd Ste 200",
    "sg:city":"Washington",
    "sg:classifiers":[
        {
            "category":"Insurance",
            "subcategory":"Hazard Insurance",
            "type":"Services"
        }
    ],
    "sg:phone":"+1 586 781 9600",
    "sg:postcode":"48094",
    "sg:province":"MI",
    "sg:website":"http://statefarm.mqgroup.com/url.asp?usr=226943",
    "wof:name":"State Farm Insurance Agent-Mike Mather",
    "wof:placetype":"venue"
},
  "geometry": {"coordinates":[-83.035746,42.72112],"type":"Point"}
}