{
  "type": "Feature",
  "properties": {
    "iso:country":"US",
    "sg:address":"38600 Garfield Rd",
    "sg:city":"Clinton Township",
    "sg:classifiers":[
        {
            "category":"Wholesale",
            "subcategory":"Computers",
            "type":"Manufacturing & Wholesale Goods"
        },
        {
            "category":"Professional",
            "subcategory":"Computer Services",
            "type":"Services"
        }
    ],
    "sg:phone":"+1 586 286 6666",
    "sg:postcode":"48038",
    "sg:province":"MI",
    "sg:tags":[
        "repair"
    ],
    "sg:website":"www.cplus-inc.com",
    "wof:name":"Computer Plus Inc-Used",
    "wof:placetype":"venue"
},
  "geometry": {"coordinates":[-82.951599,42.581001],"type":"Point"}
}