{
  "type": "Feature",
  "properties": {
    "iso:country":"US",
    "sg:address":"52322 M 51 N",
    "sg:city":"Dowagiac",
    "sg:classifiers":[
        {
            "category":"Wholesale",
            "subcategory":"Beer",
            "type":"Manufacturing & Wholesale Goods"
        }
    ],
    "sg:phone":"+1 269 782 3141",
    "sg:postcode":"49047",
    "sg:province":"MI",
    "sg:tags":[
        "ale"
    ],
    "sg:website":"www.buddistributing.com",
    "wof:name":"Bud Distributing",
    "wof:placetype":"venue"
},
  "geometry": {"coordinates":[-86.10771699999999,42.037143],"type":"Point"}
}