{
  "type": "Feature",
  "properties": {
    "iso:country":"US",
    "sg:address":"29777 Telegraph Rd",
    "sg:city":"Southfield",
    "sg:classifiers":[
        {
            "category":"Banks & Credit Unions",
            "subcategory":"Atm",
            "type":"Services"
        }
    ],
    "sg:phone":"+1 248 352 8722",
    "sg:postcode":"48034",
    "sg:province":"MI",
    "sg:tags":[
        "bankruptcy"
    ],
    "wof:name":"Cartwright Andrea Attorney At Law",
    "wof:placetype":"venue"
},
  "geometry": {"coordinates":[-83.285599,42.5061],"type":"Point"}
}