{
  "type": "Feature",
  "properties": {
    "iso:country":"US",
    "sg:address":"7037 Windsor Hwy",
    "sg:city":"Potterville",
    "sg:classifiers":[
        {
            "category":"Building & Trades",
            "subcategory":"Construction",
            "type":"Services"
        }
    ],
    "sg:phone":"+1 517 645 2740",
    "sg:postcode":"48876",
    "sg:province":"MI",
    "sg:tags":[
        "roofing",
        "contractor"
    ],
    "wof:name":"A & W Roofing Co",
    "wof:placetype":"venue"
},
  "geometry": {"coordinates":[-84.70052200000001,42.647378],"type":"Point"}
}