{
  "type": "Feature",
  "properties": {
    "iso:country":"US",
    "sg:address":"11525 Brougham Dr",
    "sg:city":"Sterling Heights",
    "sg:classifiers":[
        {
            "category":"Shopping",
            "type":"Retail Goods"
        }
    ],
    "sg:phone":"+1 586 978 9572",
    "sg:postcode":"48312",
    "sg:province":"MI",
    "sg:tags":[
        "pet",
        "shop"
    ],
    "wof:name":"Bonanni Enterprises Inc",
    "wof:placetype":"venue"
},
  "geometry": {"coordinates":[-83.01049,42.558676],"type":"Point"}
}