{
  "type": "Feature",
  "properties": {
    "iso:country":"US",
    "sg:address":"3000 Hillcroft Ave SW",
    "sg:city":"Grand Rapids",
    "sg:classifiers":[
        {
            "category":"Manufacturing",
            "subcategory":"Metals",
            "type":"Manufacturing & Wholesale Goods"
        }
    ],
    "sg:phone":"+1 616 241 2233",
    "sg:postcode":"49548",
    "sg:province":"MI",
    "sg:tags":[
        "polishing",
        "buffing"
    ],
    "wof:name":"Grand Rapids Polishing",
    "wof:placetype":"venue"
},
  "geometry": {"coordinates":[-85.673378,42.9072],"type":"Point"}
}