{
  "type": "Feature",
  "properties": {
    "iso:country":"US",
    "sg:address":"1051 Halley Rd",
    "sg:city":"Alpena",
    "sg:classifiers":[
        {
            "category":"Social Services",
            "type":"Services"
        }
    ],
    "sg:phone":"+1 989 356 3224",
    "sg:postcode":"49707",
    "sg:province":"MI",
    "sg:tags":[
        "child",
        "day",
        "care"
    ],
    "wof:name":"Hope House",
    "wof:placetype":"venue"
},
  "geometry": {"coordinates":[-83.485163,45.061102],"type":"Point"}
}