{
  "type": "Feature",
  "properties": {
    "iso:country":"US",
    "sg:address":"45593 Kenmore St",
    "sg:city":"Utica",
    "sg:classifiers":[
        {
            "category":"Retail",
            "subcategory":"Repair Shop",
            "type":"Services"
        }
    ],
    "sg:phone":"+1 586 726 1665",
    "sg:postcode":"48317",
    "sg:province":"MI",
    "sg:tags":[
        "welding"
    ],
    "wof:name":"Lonnie Welding",
    "wof:placetype":"venue"
},
  "geometry": {"coordinates":[-83.080308,42.629408],"type":"Point"}
}