{
  "type": "Feature",
  "properties": {
    "iso:country":"US",
    "sg:address":"6368 Ridge Hollow Ln",
    "sg:city":"Davisburg",
    "sg:classifiers":[
        {
            "category":"Professional",
            "subcategory":"Business Services",
            "type":"Services"
        }
    ],
    "sg:phone":"+1 248 328 0453",
    "sg:postcode":"48350",
    "sg:province":"MI",
    "wof:name":"Edge Automation Group",
    "wof:placetype":"venue"
},
  "geometry": {"coordinates":[-83.53987600000001,42.726507],"type":"Point"}
}