{
  "type": "Feature",
  "properties": {
    "iso:country":"US",
    "sg:address":"885 Robin Wood Ct",
    "sg:city":"Traverse City",
    "sg:classifiers":[
        {
            "category":"Manufacturing",
            "subcategory":"Printing",
            "type":"Manufacturing & Wholesale Goods"
        }
    ],
    "sg:phone":"+1 231 947 7610",
    "sg:postcode":"49686",
    "sg:province":"MI",
    "sg:tags":[
        "commercial"
    ],
    "wof:name":"Robinwood Press Inc",
    "wof:placetype":"venue"
},
  "geometry": {"coordinates":[-85.603938,44.743306],"type":"Point"}
}