{
  "type": "Feature",
  "properties": {
    "iso:country":"US",
    "sg:address":"5090 W Dickman Rd",
    "sg:city":"Battle Creek",
    "sg:classifiers":[
        {
            "category":"Wholesale",
            "subcategory":"Groceries",
            "type":"Manufacturing & Wholesale Goods"
        }
    ],
    "sg:phone":"+1 269 962 4089",
    "sg:postcode":"49015",
    "sg:province":"MI",
    "sg:tags":[
        "food",
        "broker"
    ],
    "wof:name":"Burdick Packing Co",
    "wof:placetype":"venue"
},
  "geometry": {"coordinates":[-85.279793,42.338532],"type":"Point"}
}