{
  "type": "Feature",
  "properties": {
    "iso:country":"US",
    "sg:address":"22535 Grabowski Rd",
    "sg:city":"Merrill",
    "sg:phone":"+1 989 643 5269",
    "sg:postcode":"48637",
    "sg:province":"MI",
    "sg:tags":[
        "farm",
        "soybean"
    ],
    "wof:name":"Don Rohn",
    "wof:placetype":"venue"
},
  "geometry": {"coordinates":[-84.36016100000001,43.317113],"type":"Point"}
}