{
  "type": "Feature",
  "properties": {
    "iso:country":"US",
    "sg:address":"33316 Grand River Ave ",
    "sg:city":"Farmington",
    "sg:classifiers":[
        {
            "category":"Restaurant",
            "type":"Food & Drink"
        }
    ],
    "sg:menulink":"http://www.allmenus.com/mi/farmington/279725-gala-restaurant/menu/",
    "sg:phone":"+1 248 478 2355",
    "sg:postcode":"48336",
    "sg:province":"MI",
    "sg:tags":[
        "american"
    ],
    "wof:name":"Gala Restaurant",
    "wof:placetype":"venue"
},
  "geometry": {"coordinates":[-83.375686,42.464836],"type":"Point"}
}