{
  "type": "Feature",
  "properties": {
    "iso:country":"US",
    "sg:address":"4491 N 88th Ave",
    "sg:city":"Hart",
    "sg:classifiers":[
        {
            "category":"Building & Trades",
            "subcategory":"Equipment Rental",
            "type":"Services"
        }
    ],
    "sg:phone":"+1 231 873 3774",
    "sg:postcode":"49420",
    "sg:province":"MI",
    "sg:tags":[
        "toilet"
    ],
    "wof:name":"Swihart's Septic & Port-A-Ptty",
    "wof:placetype":"venue"
},
  "geometry": {"coordinates":[-86.338499,43.730066],"type":"Point"}
}