{
  "type": "Feature",
  "properties": {
    "iso:country":"US",
    "sg:address":"14919 E 7 Mile Rd",
    "sg:city":"Detroit",
    "sg:classifiers":[
        {
            "category":"Real Estate",
            "subcategory":"Real Estate Services",
            "type":"Services"
        }
    ],
    "sg:phone":"+1 313 371 3500",
    "sg:postcode":"48205",
    "sg:province":"MI",
    "sg:tags":[
        "management",
        "property"
    ],
    "wof:name":"Cusimano Brothers",
    "wof:placetype":"venue"
},
  "geometry": {"coordinates":[-82.96820099999999,42.435501],"type":"Point"}
}