{
  "type": "Feature",
  "properties": {
    "iso:country":"US",
    "sg:address":"12131 Reyburn Dr NE",
    "sg:city":"Sparta",
    "sg:classifiers":[
        {
            "category":"Manufacturing",
            "subcategory":"Signs",
            "type":"Manufacturing & Wholesale Goods"
        }
    ],
    "sg:phone":"+1 616 887 4020",
    "sg:postcode":"49345",
    "sg:province":"MI",
    "sg:tags":[
        "specialty",
        "mfg"
    ],
    "wof:name":"Level Image",
    "wof:placetype":"venue"
},
  "geometry": {"coordinates":[-85.6666,43.183606],"type":"Point"}
}