{
  "type": "Feature",
  "properties": {
    "iso:country":"US",
    "sg:address":"3671 Waldon Rd",
    "sg:city":"Lake Orion",
    "sg:classifiers":[
        {
            "category":"Building & Trades",
            "subcategory":"Cleaning & Sanitation",
            "type":"Services"
        }
    ],
    "sg:phone":"+1 248 391 8956",
    "sg:postcode":"48360",
    "sg:province":"MI",
    "sg:tags":[
        "maintenance"
    ],
    "wof:name":"Paradise Building Services",
    "wof:placetype":"venue"
},
  "geometry": {"coordinates":[-83.321676,42.735841],"type":"Point"}
}