{
  "type": "Feature",
  "properties": {
    "iso:country":"US",
    "sg:address":"76532 Co Rd 376",
    "sg:city":"Covert",
    "sg:classifiers":[
        {
            "category":"Building & Trades",
            "subcategory":"Construction",
            "type":"Services"
        }
    ],
    "sg:phone":"+1 269 849 2323",
    "sg:postcode":"49043",
    "sg:province":"MI",
    "sg:tags":[
        "general",
        "contractor"
    ],
    "wof:name":"King & Smith Roofing Inc",
    "wof:placetype":"venue"
},
  "geometry": {"coordinates":[-86.28648,42.258008],"type":"Point"}
}