{
  "type": "Feature",
  "properties": {
    "iso:country":"US",
    "sg:address":"22583 Park St",
    "sg:city":"Dearborn",
    "sg:classifiers":[
        {
            "category":"Professional",
            "subcategory":"Computer Services",
            "type":"Services"
        }
    ],
    "sg:phone":"+1 313 792 1222",
    "sg:postcode":"48124",
    "sg:province":"MI",
    "sg:tags":[
        "specializing",
        "programming"
    ],
    "wof:name":"White Ware Inc",
    "wof:placetype":"venue"
},
  "geometry": {"coordinates":[-83.253255,42.301849],"type":"Point"}
}