{
  "type": "Feature",
  "properties": {
    "iso:country":"US",
    "sg:address":"2221 N Van Dyke Rd",
    "sg:city":"Bad Axe",
    "sg:classifiers":[
        {
            "category":"Personal",
            "subcategory":"Beauty Salon",
            "type":"Services"
        }
    ],
    "sg:phone":"+1 989 269 9411",
    "sg:postcode":"48413",
    "sg:province":"MI",
    "sg:tags":[
        "shop"
    ],
    "wof:name":"Judy's Beauty Salon",
    "wof:placetype":"venue"
},
  "geometry": {"coordinates":[-83.002252,43.858597],"type":"Point"}
}