{
  "type": "Feature",
  "properties": {
    "iso:country":"US",
    "sg:address":"35 Boyer Dr",
    "sg:city":"Battle Creek",
    "sg:classifiers":[
        {
            "category":"Health Services",
            "subcategory":"Nursing And Care Facility",
            "type":"Services"
        }
    ],
    "sg:phone":"+1 269 962 7640",
    "sg:postcode":"49014",
    "sg:province":"MI",
    "wof:name":"P F R Hms",
    "wof:placetype":"venue"
},
  "geometry": {"coordinates":[-85.116544,42.302515],"type":"Point"}
}