{
  "type": "Feature",
  "properties": {
    "iso:country":"US",
    "sg:address":"2100 4th St",
    "sg:city":"Jackson",
    "sg:classifiers":[
        {
            "category":"Health Services",
            "subcategory":"Doctor",
            "type":"Services"
        }
    ],
    "sg:phone":"+1 517 796 8365",
    "sg:postcode":"49203",
    "sg:province":"MI",
    "sg:tags":[
        "physician"
    ],
    "wof:name":"Jackson Pediactrics",
    "wof:placetype":"venue"
},
  "geometry": {"coordinates":[-84.418252,42.222629],"type":"Point"}
}