{
  "type": "Feature",
  "properties": {
    "iso:country":"US",
    "sg:address":"16731 Ferris St",
    "sg:city":"Grand Haven",
    "sg:classifiers":[
        {
            "category":"Government",
            "subcategory":"Office",
            "type":"Public Place"
        }
    ],
    "sg:phone":"+1 616 842 5869",
    "sg:postcode":"49417",
    "sg:province":"MI",
    "sg:tags":[
        "federal"
    ],
    "wof:name":"Natural Resources Conservation",
    "wof:placetype":"venue"
},
  "geometry": {"coordinates":[-86.20363,43.008539],"type":"Point"}
}