{
  "type": "Feature",
  "properties": {
    "iso:country":"US",
    "sg:address":"34796 Van Dyke Avenue",
    "sg:city":"Sterling Heights",
    "sg:classifiers":[
        {
            "category":"Restaurant",
            "type":"Food & Drink"
        }
    ],
    "sg:phone":"+1 586 826 3737",
    "sg:postcode":"48312",
    "sg:province":"MI",
    "sg:tags":[
        "mediterranean"
    ],
    "wof:name":"Joe's Kabob & Cafe",
    "wof:placetype":"venue"
},
  "geometry": {"coordinates":[-83.028716,42.549768],"type":"Point"}
}