{
  "type": "Feature",
  "properties": {
    "iso:country":"US",
    "sg:address":"1491 Baldwin Ave",
    "sg:city":"Pontiac",
    "sg:classifiers":[
        {
            "category":"Autos & Motor Vehicles",
            "subcategory":"Automobile Sales",
            "type":"Retail Goods"
        }
    ],
    "sg:phone":"+1 248 454 0711",
    "sg:postcode":"48340",
    "sg:province":"MI",
    "sg:tags":[
        "new",
        "used",
        "car"
    ],
    "wof:name":"Giovanni Motors",
    "wof:placetype":"venue"
},
  "geometry": {"coordinates":[-83.300702,42.678009],"type":"Point"}
}