{
  "type": "Feature",
  "properties": {
    "iso:country":"US",
    "sg:address":"6533 Fruit Ridge Ave NW",
    "sg:city":"Grand Rapids",
    "sg:classifiers":[
        {
            "category":"Retail",
            "subcategory":"Auto Repair",
            "type":"Services"
        }
    ],
    "sg:phone":"+1 616 735 9172",
    "sg:postcode":"49544",
    "sg:province":"MI",
    "sg:tags":[
        "automotive"
    ],
    "wof:name":"Performance Plus Quick Lube",
    "wof:placetype":"venue"
},
  "geometry": {"coordinates":[-85.76814899999999,43.084279],"type":"Point"}
}