{
  "type": "Feature",
  "properties": {
    "iso:country":"US",
    "sg:address":"4408 Red Arrow Hwy",
    "sg:city":"Stevensville",
    "sg:classifiers":[
        {
            "category":"Professional",
            "type":"Services"
        }
    ],
    "sg:phone":"+1 269 429 0736",
    "sg:postcode":"49127",
    "sg:province":"MI",
    "sg:tags":[
        "establishment"
    ],
    "wof:name":"Smiley's Pak Inc",
    "wof:placetype":"venue"
},
  "geometry": {"coordinates":[-86.514257,42.041794],"type":"Point"}
}