{
  "type": "Feature",
  "properties": {
    "iso:country":"US",
    "sg:address":"9683 Springville Hwy",
    "sg:city":"Onsted",
    "sg:classifiers":[
        {
            "category":"Building & Trades",
            "subcategory":"Pest Control",
            "type":"Services"
        }
    ],
    "sg:phone":"+1 517 467 7490",
    "sg:postcode":"49265",
    "sg:province":"MI",
    "wof:name":"Buckeye Exterminating Inc",
    "wof:placetype":"venue"
},
  "geometry": {"coordinates":[-84.170525,42.024784],"type":"Point"}
}