{
  "type": "Feature",
  "properties": {
    "iso:country":"US",
    "sg:address":"1916 E Britain Ave",
    "sg:city":"Benton Harbor",
    "sg:classifiers":[
        {
            "category":"Food & Beverages",
            "subcategory":"Candy",
            "type":"Retail Goods"
        }
    ],
    "sg:phone":"+1 269 927 1844",
    "sg:postcode":"49022",
    "sg:province":"MI",
    "sg:tags":[
        "confectionery"
    ],
    "wof:name":"Richy's Candyhouse",
    "wof:placetype":"venue"
},
  "geometry": {"coordinates":[-86.41172899999999,42.108654],"type":"Point"}
}