{
  "type": "Feature",
  "properties": {
    "iso:country":"US",
    "sg:address":"26026 Southfield Rd",
    "sg:city":"Lathrup Village",
    "sg:classifiers":[
        {
            "category":"Banks & Credit Unions",
            "subcategory":"Financial Services",
            "type":"Services"
        }
    ],
    "sg:phone":"+1 248 440 6161",
    "sg:postcode":"48076",
    "sg:province":"MI",
    "sg:tags":[
        "broker",
        "mortgage"
    ],
    "sg:website":"www.primerica.com",
    "wof:name":"Primerica",
    "wof:placetype":"venue"
},
  "geometry": {"coordinates":[-83.221397,42.480801],"type":"Point"}
}