{
  "type": "Feature",
  "properties": {
    "iso:country":"US",
    "sg:address":"6907 Toboggan Ln",
    "sg:city":"Lansing",
    "sg:classifiers":[
        {
            "category":"Recreation",
            "type":"Entertainment"
        }
    ],
    "sg:phone":"+1 517 321 8978",
    "sg:postcode":"48917",
    "sg:province":"MI",
    "wof:name":"One Man & Roller Pan",
    "wof:placetype":"venue"
},
  "geometry": {"coordinates":[-84.64883,42.757728],"type":"Point"}
}