{
  "type": "Feature",
  "properties": {
    "iso:country":"US",
    "sg:address":"321 E Holmes Rd",
    "sg:city":"Lansing",
    "sg:classifiers":[
        {
            "category":"Organizations",
            "subcategory":"Religious Organization",
            "type":"Services"
        }
    ],
    "sg:phone":"+1 517 882 8105",
    "sg:postcode":"48910",
    "sg:province":"MI",
    "wof:name":"Church Christ At Holmes Road",
    "wof:placetype":"venue"
},
  "geometry": {"coordinates":[-84.54961,42.697508],"type":"Point"}
}