{
  "type": "Feature",
  "properties": {
    "iso:country":"US",
    "sg:address":"1411 State Hwy 32",
    "sg:city":"Alpena",
    "sg:classifiers":[
        {
            "category":"Building & Trades",
            "subcategory":"Plumbing",
            "type":"Services"
        }
    ],
    "sg:phone":"+1 989 354 5427",
    "sg:postcode":"49707",
    "sg:province":"MI",
    "sg:tags":[
        "plumbing",
        "contractor"
    ],
    "wof:name":"Weinkauf Plumbing & Heating",
    "wof:placetype":"venue"
},
  "geometry": {"coordinates":[-83.46439599999999,45.06178],"type":"Point"}
}