{
  "type": "Feature",
  "properties": {
    "iso:country":"US",
    "sg:address":"48 State Rd",
    "sg:city":"Newaygo",
    "sg:classifiers":[
        {
            "category":"Shopping",
            "subcategory":"Clothing, Apparel, & Fashions",
            "type":"Retail Goods"
        }
    ],
    "sg:phone":"+1 231 652 6106",
    "sg:postcode":"49337",
    "sg:province":"MI",
    "sg:tags":[
        "sportswear"
    ],
    "wof:name":"Powers Outdoors",
    "wof:placetype":"venue"
},
  "geometry": {"coordinates":[-85.800335,43.419306],"type":"Point"}
}