{
  "type": "Feature",
  "properties": {
    "iso:country":"US",
    "sg:address":"3909 Fort St",
    "sg:city":"Lincoln Park",
    "sg:classifiers":[
        {
            "category":"Retail",
            "subcategory":"Veterinary Services",
            "type":"Services"
        }
    ],
    "sg:phone":"+1 313 389 2222",
    "sg:postcode":"48146",
    "sg:province":"MI",
    "sg:tags":[
        "veterinarian"
    ],
    "wof:name":"First Veterinary Clinic of Lincoln Park",
    "wof:placetype":"venue"
},
  "geometry": {"coordinates":[-83.180603,42.227798],"type":"Point"}
}