{
  "type": "Feature",
  "properties": {
    "iso:country":"US",
    "sg:address":"822 E Front St",
    "sg:city":"Traverse City",
    "sg:classifiers":[
        {
            "category":"Personal",
            "subcategory":"Beauty Salon",
            "type":"Services"
        }
    ],
    "sg:phone":"+1 231 946 2425",
    "sg:postcode":"49686",
    "sg:province":"MI",
    "wof:name":"Signature Salon",
    "wof:placetype":"venue"
},
  "geometry": {"coordinates":[-85.60178399999999,44.764075],"type":"Point"}
}