{
  "type": "Feature",
  "properties": {
    "iso:country":"US",
    "sg:address":"107 S Main St",
    "sg:city":"Vicksburg",
    "sg:classifiers":[
        {
            "category":"Shopping",
            "subcategory":"Discount & Variety Stores",
            "type":"Retail Goods"
        }
    ],
    "sg:phone":"+1 269 649 0100",
    "sg:postcode":"49097",
    "sg:province":"MI",
    "wof:name":"Weezy's Village Variety",
    "wof:placetype":"venue"
},
  "geometry": {"coordinates":[-85.53231599999999,42.119879],"type":"Point"}
}