{
  "type": "Feature",
  "properties": {
    "iso:country":"US",
    "sg:address":"6823 S 34th St",
    "sg:city":"Scotts",
    "sg:classifiers":[
        {
            "category":"Wholesale",
            "subcategory":"Farm Supplies",
            "type":"Manufacturing & Wholesale Goods"
        }
    ],
    "sg:phone":"+1 269 626 8932",
    "sg:postcode":"49088",
    "sg:province":"MI",
    "sg:tags":[
        "raw",
        "product",
        "material"
    ],
    "wof:name":"Nick Stermer Farm Account",
    "wof:placetype":"venue"
},
  "geometry": {"coordinates":[-85.432598,42.218709],"type":"Point"}
}