{
  "type": "Feature",
  "properties": {
    "iso:country":"US",
    "sg:address":"435 N Main St",
    "sg:city":"Frankenmuth",
    "sg:phone":"+1 989 652 2621",
    "sg:postcode":"48734",
    "sg:province":"MI",
    "sg:website":"http://www.kroger.com/",
    "wof:name":"Kroger",
    "wof:placetype":"venue"
},
  "geometry": {"coordinates":[-83.73819399999999,43.340475],"type":"Point"}
}