{
  "type": "Feature",
  "properties": {
    "iso:country":"US",
    "sg:address":"2562 Dixie Hwy",
    "sg:city":"Waterford",
    "sg:classifiers":[
        {
            "category":"Organizations",
            "subcategory":"Religious Organization",
            "type":"Services"
        }
    ],
    "sg:phone":"+1 248 673 9274",
    "sg:postcode":"48328",
    "sg:province":"MI",
    "wof:name":"Silvercrest Baptist Church",
    "wof:placetype":"venue"
},
  "geometry": {"coordinates":[-83.33829,42.672158],"type":"Point"}
}