{
  "type": "Feature",
  "properties": {
    "iso:country":"US",
    "sg:address":"34203 Ford Rd",
    "sg:city":"Westland",
    "sg:classifiers":[
        {
            "category":"Social Services",
            "subcategory":"Child Care",
            "type":"Services"
        },
        {
            "category":"Education",
            "subcategory":"Preschool",
            "type":"Public Place"
        },
        {
            "category":"Education",
            "subcategory":"School",
            "type":"Public Place"
        }
    ],
    "sg:phone":"+1 734 729 3434",
    "sg:postcode":"48185",
    "sg:province":"MI",
    "sg:tags":[
        "elementary",
        "day"
    ],
    "sg:website":"www.childtime.com",
    "wof:name":"Childtime Learning Centers",
    "wof:placetype":"venue"
},
  "geometry": {"coordinates":[-83.377409,42.324526],"type":"Point"}
}