{
  "type": "Feature",
  "properties": {
    "iso:country":"US",
    "sg:address":"30100 Van Dyke Ave",
    "sg:city":"Warren",
    "sg:classifiers":[
        {
            "category":"Professional",
            "subcategory":"Employment Agencies",
            "type":"Services"
        }
    ],
    "sg:phone":"+1 586 751 5314",
    "sg:postcode":"48093",
    "sg:province":"MI",
    "sg:tags":[
        "help",
        "supply"
    ],
    "wof:name":"Spherion Corporation",
    "wof:placetype":"venue"
},
  "geometry": {"coordinates":[-83.028548,42.512456],"type":"Point"}
}