{
  "type": "Feature",
  "properties": {
    "iso:country":"US",
    "sg:address":"2220 Allen Rd",
    "sg:city":"Ortonville",
    "sg:classifiers":[
        {
            "category":"Personal",
            "type":"Services"
        }
    ],
    "sg:phone":"+1 248 627 3849",
    "sg:postcode":"48462",
    "sg:province":"MI",
    "sg:tags":[
        "pet",
        "exercising"
    ],
    "wof:name":"Burney's Ark Pet Sitting",
    "wof:placetype":"venue"
},
  "geometry": {"coordinates":[-83.438194,42.81997],"type":"Point"}
}