{
  "type": "Feature",
  "properties": {
    "iso:country":"US",
    "sg:address":"7458 W Lincoln Rd",
    "sg:city":"Elwell",
    "sg:classifiers":[
        {
            "category":"Social Services",
            "subcategory":"Child Care",
            "type":"Services"
        }
    ],
    "sg:phone":"+1 989 463 5118",
    "sg:postcode":"48832",
    "sg:province":"MI",
    "sg:tags":[
        "day"
    ],
    "wof:name":"Sheila Wilson",
    "wof:placetype":"venue"
},
  "geometry": {"coordinates":[-84.747731,43.379326],"type":"Point"}
}