{
  "type": "Feature",
  "properties": {
    "iso:country":"US",
    "sg:address":"9100 Kestrel Ridge Rd",
    "sg:city":"Brighton",
    "sg:phone":"+1 734 834 1611",
    "sg:postcode":"48116",
    "sg:province":"MI",
    "sg:tags":[
        "machine",
        "vending"
    ],
    "wof:name":"Superior Svc Snack & Pop LLC",
    "wof:placetype":"venue"
},
  "geometry": {"coordinates":[-83.81071300000001,42.46712],"type":"Point"}
}