{
  "type": "Feature",
  "properties": {
    "iso:country":"US",
    "sg:address":"80 N Union St",
    "sg:city":"Sparta",
    "sg:classifiers":[
        {
            "category":"Education",
            "subcategory":"Library",
            "type":"Public Place"
        }
    ],
    "sg:phone":"+1 616 887 9937",
    "sg:postcode":"49345",
    "sg:province":"MI",
    "wof:name":"Sparta Carnegie Twp Library",
    "wof:placetype":"venue"
},
  "geometry": {"coordinates":[-85.707083,43.162027],"type":"Point"}
}