{
  "type": "Feature",
  "properties": {
    "iso:country":"US",
    "sg:address":"23077 Greenfield Rd Ste 308",
    "sg:city":"Southfield",
    "sg:classifiers":[
        {
            "category":"Shopping",
            "subcategory":"Jewelry",
            "type":"Retail Goods"
        }
    ],
    "sg:phone":"+1 248 750 0047",
    "sg:postcode":"48075",
    "sg:province":"MI",
    "wof:name":"Milano Jewelers",
    "wof:placetype":"venue"
},
  "geometry": {"coordinates":[-83.201302,42.460499],"type":"Point"}
}