{
  "type": "Feature",
  "properties": {
    "iso:country":"US",
    "sg:address":"18161 E 8 Mile Rd",
    "sg:city":"Eastpointe",
    "sg:classifiers":[
        {
            "category":"Professional",
            "subcategory":"Management & Consulting",
            "type":"Services"
        }
    ],
    "sg:phone":"+1 586 774 5580",
    "sg:postcode":"48021",
    "sg:province":"MI",
    "sg:tags":[
        "consultant",
        "business"
    ],
    "sg:website":"www.mctevia.com",
    "wof:name":"Mctevia & Assoc",
    "wof:placetype":"venue"
},
  "geometry": {"coordinates":[-82.932817,42.450615],"type":"Point"}
}