{
  "type": "Feature",
  "properties": {
    "iso:country":"US",
    "sg:address":"195 S Ray Quincy Rd",
    "sg:city":"Quincy",
    "sg:classifiers":[
        {
            "category":"Building & Trades",
            "subcategory":"Construction",
            "type":"Services"
        }
    ],
    "sg:phone":"+1 517 639 8042",
    "sg:postcode":"49082",
    "sg:province":"MI",
    "sg:tags":[
        "excavating",
        "contractor"
    ],
    "wof:name":"Jim's Excavating Svc",
    "wof:placetype":"venue"
},
  "geometry": {"coordinates":[-84.883359,41.884487],"type":"Point"}
}