{
  "type": "Feature",
  "properties": {
    "iso:country":"US",
    "sg:address":"15 Mill Rd",
    "sg:city":"Sterling Heights",
    "sg:classifiers":[
        {
            "category":"Home & Garden",
            "subcategory":"Household Appliances",
            "type":"Retail Goods"
        }
    ],
    "sg:phone":"+1 586 979 8383",
    "sg:postcode":"48386",
    "sg:province":"MI",
    "sg:tags":[
        "machine",
        "sewing"
    ],
    "wof:name":"U-Sew Ctr Viking Sewing Mach",
    "wof:placetype":"venue"
},
  "geometry": {"coordinates":[-83.487602,42.638901],"type":"Point"}
}