{
  "type": "Feature",
  "properties": {
    "iso:country":"US",
    "sg:address":"18900 Michigan Ave Ste M118",
    "sg:city":"Dearborn",
    "sg:classifiers":[
        {
            "category":"Sports & Exercise",
            "subcategory":"Bicycle Rental",
            "type":"Entertainment"
        }
    ],
    "sg:phone":"+1 313 323 3600",
    "sg:postcode":"48126",
    "sg:province":"MI",
    "sg:tags":[
        "wear"
    ],
    "wof:name":"4 Men Fairlane Inc",
    "wof:placetype":"venue"
},
  "geometry": {"coordinates":[-83.22229799999999,42.309644],"type":"Point"}
}