{
  "type": "Feature",
  "properties": {
    "iso:country":"US",
    "sg:address":"7160 Summerfield Rd",
    "sg:city":"Lambertville",
    "sg:classifiers":[
        {
            "category":"Manufacturing",
            "subcategory":"Tools & Machinery",
            "type":"Manufacturing & Wholesale Goods"
        }
    ],
    "sg:phone":"+1 734 854 7978",
    "sg:postcode":"48144",
    "sg:province":"MI",
    "sg:tags":[
        "equipment",
        "conveyor",
        "conveying"
    ],
    "wof:name":"Prestige",
    "wof:placetype":"venue"
},
  "geometry": {"coordinates":[-83.608166,41.744681],"type":"Point"}
}