{
  "type": "Feature",
  "properties": {
    "iso:country":"US",
    "sg:address":"14661 Cedargrove St",
    "sg:city":"Detroit",
    "sg:classifiers":[
        {
            "category":"Shopping",
            "subcategory":"Catalog Store",
            "type":"Retail Goods"
        }
    ],
    "sg:phone":"+1 313 372 5041",
    "sg:postcode":"48205",
    "sg:province":"MI",
    "sg:tags":[
        "mail",
        "house"
    ],
    "wof:name":"KB Doll Emporium",
    "wof:placetype":"venue"
},
  "geometry": {"coordinates":[-82.970664,42.425598],"type":"Point"}
}