{
  "type": "Feature",
  "properties": {
    "iso:country":"US",
    "sg:address":"81 Three Oaks Dr",
    "sg:city":"Okemos",
    "sg:classifiers":[
        {
            "category":"Professional",
            "subcategory":"Business Services",
            "type":"Services"
        }
    ],
    "sg:phone":"+1 269 671 4192",
    "sg:postcode":"48864",
    "sg:province":"MI",
    "sg:tags":[
        "brokerage"
    ],
    "wof:name":"Cole Logistics Inc",
    "wof:placetype":"venue"
},
  "geometry": {"coordinates":[-84.359149,42.675471],"type":"Point"}
}