{
  "type": "Feature",
  "properties": {
    "iso:country":"US",
    "sg:address":"580 N Main St",
    "sg:city":"Frankenmuth",
    "sg:classifiers":[
        {
            "category":"Banks & Credit Unions",
            "subcategory":"Bank",
            "type":"Services"
        }
    ],
    "sg:phone":"+1 989 652 6413",
    "sg:postcode":"48734",
    "sg:province":"MI",
    "sg:tags":[
        "loan",
        "real estate"
    ],
    "wof:name":"American Home Mortgage",
    "wof:placetype":"venue"
},
  "geometry": {"coordinates":[-83.738277,43.340881],"type":"Point"}
}