{
  "type": "Feature",
  "properties": {
    "iso:country":"US",
    "sg:address":"1430 Nakomis Rd",
    "sg:city":"Lake Orion",
    "sg:classifiers":[
        {
            "category":"Building & Trades",
            "subcategory":"Construction",
            "type":"Services"
        }
    ],
    "sg:phone":"+1 248 343 4871",
    "sg:postcode":"48362",
    "sg:province":"MI",
    "sg:tags":[
        "home",
        "builder"
    ],
    "wof:name":"Lauryn Properties Corp",
    "wof:placetype":"venue"
},
  "geometry": {"coordinates":[-83.270426,42.79609],"type":"Point"}
}