{
  "type": "Feature",
  "properties": {
    "iso:country":"US",
    "sg:address":"124 E Chisholm St",
    "sg:city":"Alpena",
    "sg:classifiers":[
        {
            "category":"Professional",
            "subcategory":"Lawyer & Legal Services",
            "type":"Services"
        }
    ],
    "sg:phone":"+1 989 358 9266",
    "sg:postcode":"49707",
    "sg:province":"MI",
    "sg:tags":[
        "attorney"
    ],
    "wof:name":"William D Yahne",
    "wof:placetype":"venue"
},
  "geometry": {"coordinates":[-83.43306699999999,45.061773],"type":"Point"}
}