{
  "type": "Feature",
  "properties": {
    "iso:country":"US",
    "sg:address":"15000 Metropolitan Pkwy",
    "sg:city":"Sterling Heights",
    "sg:classifiers":[
        {
            "category":"Professional",
            "type":"Services"
        },
        {
            "category":"Retail",
            "subcategory":"Event Space",
            "type":"Services"
        }
    ],
    "sg:phone":"+1 586 979 7010",
    "sg:postcode":"48312",
    "sg:province":"MI",
    "sg:tags":[
        "venue",
        "caterer"
    ],
    "wof:name":"Freedom Hill-Macomb County Parks & Recreation",
    "wof:placetype":"venue"
},
  "geometry": {"coordinates":[-82.973297,42.566399],"type":"Point"}
}