{
  "type": "Feature",
  "properties": {
    "iso:country":"US",
    "sg:address":"110 S Nursery St",
    "sg:city":"Lawton",
    "sg:classifiers":[
        {
            "category":"Education",
            "subcategory":"School",
            "type":"Public Place"
        }
    ],
    "sg:phone":"+1 269 624 4581",
    "sg:postcode":"49065",
    "sg:province":"MI",
    "wof:name":"Lawton Middle School",
    "wof:placetype":"venue"
},
  "geometry": {"coordinates":[-85.84241,42.167863],"type":"Point"}
}