{
  "type": "Feature",
  "properties": {
    "iso:country":"US",
    "sg:address":"211 W Fort St Ste 510",
    "sg:city":"Detroit",
    "sg:classifiers":[
        {
            "category":"Banks & Credit Unions",
            "subcategory":"Atm",
            "type":"Services"
        }
    ],
    "sg:phone":"+1 866 704 1515",
    "sg:postcode":"48226",
    "sg:province":"MI",
    "sg:tags":[
        "bankruptcy"
    ],
    "sg:website":"www.abetterwaybankruptcy.com",
    "wof:name":"A Better Way Bankruptcy Centers",
    "wof:placetype":"venue"
},
  "geometry": {"coordinates":[-83.04879099999999,42.329958],"type":"Point"}
}