{
  "type": "Feature",
  "properties": {
    "iso:country":"US",
    "sg:address":"7707 Dyke Rd",
    "sg:city":"Ira",
    "sg:classifiers":[
        {
            "category":"Restaurant",
            "type":"Food & Drink"
        }
    ],
    "sg:phone":"+1 586 725 9100",
    "sg:postcode":"48023",
    "sg:province":"MI",
    "wof:name":"Raft",
    "wof:placetype":"venue"
},
  "geometry": {"coordinates":[-82.620803,42.668552],"type":"Point"}
}