{
  "type": "Feature",
  "properties": {
    "iso:country":"US",
    "sg:address":"636 Hackett St",
    "sg:city":"Ionia",
    "sg:classifiers":[
        {
            "category":"Personal",
            "subcategory":"Beauty Salon",
            "type":"Services"
        }
    ],
    "sg:phone":"+1 616 522 9870",
    "sg:postcode":"48846",
    "sg:province":"MI",
    "sg:tags":[
        "shop"
    ],
    "wof:name":"Manciu's Hair Styling Salon",
    "wof:placetype":"venue"
},
  "geometry": {"coordinates":[-85.073137,42.984608],"type":"Point"}
}