{
  "type": "Feature",
  "properties": {
    "iso:country":"US",
    "sg:address":"656 S Main St",
    "sg:city":"Frankenmuth",
    "sg:classifiers":[
        {
            "category":"Restaurant",
            "type":"Food & Drink"
        }
    ],
    "sg:phone":"+1 989 652 6881",
    "sg:postcode":"48734",
    "sg:province":"MI",
    "wof:name":"Tiffany's",
    "wof:placetype":"venue"
},
  "geometry": {"coordinates":[-83.739895,43.328038],"type":"Point"}
}