{
  "type": "Feature",
  "properties": {
    "iso:country":"US",
    "sg:address":"2522 S Woodlawn Dr",
    "sg:city":"West Branch",
    "sg:classifiers":[
        {
            "category":"Real Estate",
            "subcategory":"Real Estate Operator",
            "type":"Services"
        }
    ],
    "sg:phone":"+1 989 345 7780",
    "sg:postcode":"48661",
    "sg:province":"MI",
    "sg:tags":[
        "mobile",
        "home",
        "site"
    ],
    "wof:name":"Country Village Estates",
    "wof:placetype":"venue"
},
  "geometry": {"coordinates":[-84.216511,44.261483],"type":"Point"}
}