{
  "type": "Feature",
  "properties": {
    "iso:country":"US",
    "sg:address":"34500 Plymouth Rd",
    "sg:city":"Livonia",
    "sg:classifiers":[
        {
            "category":"Retail",
            "subcategory":"Auto Rental",
            "type":"Services"
        }
    ],
    "sg:phone":"+1 734 853 0398",
    "sg:postcode":"48150",
    "sg:province":"MI",
    "sg:tags":[
        "car"
    ],
    "wof:name":"Budget Car & Truck Rental",
    "wof:placetype":"venue"
},
  "geometry": {"coordinates":[-83.382103,42.368198],"type":"Point"}
}