{
  "type": "Feature",
  "properties": {
    "iso:country":"US",
    "sg:address":"2443 S Michigan Rd",
    "sg:city":"Eaton Rapids",
    "sg:classifiers":[
        {
            "category":"Personal",
            "subcategory":"Beauty Salon",
            "type":"Services"
        }
    ],
    "sg:phone":"+1 517 663 6880",
    "sg:postcode":"48827",
    "sg:province":"MI",
    "sg:tags":[
        "shop"
    ],
    "wof:name":"Expression's By Marcia",
    "wof:placetype":"venue"
},
  "geometry": {"coordinates":[-84.639455,42.530449],"type":"Point"}
}