{
  "type": "Feature",
  "properties": {
    "iso:country":"US",
    "sg:address":"8530 E Maple Rapids Rd",
    "sg:city":"Elsie",
    "sg:classifiers":[
        {
            "category":"Retail",
            "subcategory":"Auto Repair",
            "type":"Services"
        }
    ],
    "sg:phone":"+1 989 862 6033",
    "sg:postcode":"48831",
    "sg:province":"MI",
    "sg:tags":[
        "general"
    ],
    "wof:name":"Big Dog Racing",
    "wof:placetype":"venue"
},
  "geometry": {"coordinates":[-84.39345,43.103124],"type":"Point"}
}