{
  "type": "Feature",
  "properties": {
    "iso:country":"US",
    "sg:address":"173 54th St SW",
    "sg:city":"Grand Rapids",
    "sg:classifiers":[
        {
            "category":"Education",
            "subcategory":"School",
            "type":"Public Place"
        }
    ],
    "sg:phone":"+1 616 531 7433",
    "sg:postcode":"49548",
    "sg:province":"MI",
    "wof:name":"Discovery High School",
    "wof:placetype":"venue"
},
  "geometry": {"coordinates":[-85.670075,42.865983],"type":"Point"}
}