{
  "type": "Feature",
  "properties": {
    "iso:country":"US",
    "sg:address":"5025 S Pennsylvania Ave",
    "sg:city":"Lansing",
    "sg:classifiers":[
        {
            "category":"Food & Beverages",
            "subcategory":"Groceries & Convenience Stores",
            "type":"Retail Goods"
        }
    ],
    "sg:phone":"+1 517 882 0705",
    "sg:postcode":"48910",
    "sg:province":"MI",
    "wof:name":"Buddy's Mini Mart Inc",
    "wof:placetype":"venue"
},
  "geometry": {"coordinates":[-84.538071,42.685565],"type":"Point"}
}