{
  "type": "Feature",
  "properties": {
    "iso:country":"US",
    "sg:address":"316 Harrison St",
    "sg:city":"Marquette",
    "sg:classifiers":[
        {
            "category":"Professional",
            "type":"Services"
        }
    ],
    "sg:phone":"+1 906 228 4010",
    "sg:postcode":"49855",
    "sg:province":"MI",
    "wof:name":"Magnetic Materials",
    "wof:placetype":"venue"
},
  "geometry": {"coordinates":[-87.40046,46.549885],"type":"Point"}
}