{
  "type": "Feature",
  "properties": {
    "iso:country":"US",
    "sg:address":"386 S Ford Blvd",
    "sg:city":"Ypsilanti",
    "sg:classifiers":[
        {
            "category":"Retail",
            "subcategory":"Auto Repair",
            "type":"Services"
        }
    ],
    "sg:phone":"+1 734 482 1650",
    "sg:postcode":"48198",
    "sg:province":"MI",
    "sg:tags":[
        "general"
    ],
    "wof:name":"Eds Garage",
    "wof:placetype":"venue"
},
  "geometry": {"coordinates":[-83.580226,42.239242],"type":"Point"}
}