{
  "type": "Feature",
  "properties": {
    "iso:country":"US",
    "sg:address":"14202 Murthum Ave",
    "sg:city":"Warren",
    "sg:classifiers":[
        {
            "category":"Building & Trades",
            "subcategory":"Construction",
            "type":"Services"
        }
    ],
    "sg:phone":"+1 586 293 4543",
    "sg:postcode":"48088",
    "sg:province":"MI",
    "sg:tags":[
        "contractor"
    ],
    "wof:name":"Lakeview Window Fashions",
    "wof:placetype":"venue"
},
  "geometry": {"coordinates":[-82.979732,42.531577],"type":"Point"}
}