{
  "type": "Feature",
  "properties": {
    "iso:country":"US",
    "sg:address":"94 Sylvan Dr",
    "sg:city":"Sandusky",
    "sg:classifiers":[
        {
            "category":"Manufacturing",
            "subcategory":"Building Materials",
            "type":"Manufacturing & Wholesale Goods"
        }
    ],
    "sg:phone":"+1 810 648 2632",
    "sg:postcode":"48471",
    "sg:province":"MI",
    "sg:tags":[
        "mfg"
    ],
    "wof:name":"Owl Woodworks",
    "wof:placetype":"venue"
},
  "geometry": {"coordinates":[-82.827378,43.393581],"type":"Point"}
}