{
  "type": "Feature",
  "properties": {
    "iso:country":"US",
    "sg:address":"6800 Merton Dr",
    "sg:city":"Jackson",
    "sg:classifiers":[
        {
            "category":"Building & Trades",
            "subcategory":"Construction",
            "type":"Services"
        }
    ],
    "sg:phone":"+1 517 787 7048",
    "sg:postcode":"49201",
    "sg:province":"MI",
    "sg:tags":[
        "contractor"
    ],
    "wof:name":"Zeda Restoration",
    "wof:placetype":"venue"
},
  "geometry": {"coordinates":[-84.479542,42.331534],"type":"Point"}
}