{
  "type": "Feature",
  "properties": {
    "iso:country":"US",
    "sg:address":"14155 Eureka Rd",
    "sg:city":"Southgate",
    "sg:classifiers":[
        {
            "category":"Shopping",
            "subcategory":"Department Store",
            "type":"Retail Goods"
        }
    ],
    "sg:phone":"+1 734 324 8960",
    "sg:postcode":"48195",
    "sg:province":"MI",
    "sg:website":"www.biglots.com",
    "wof:name":"Big Lots",
    "wof:placetype":"venue"
},
  "geometry": {"coordinates":[-83.19450399999999,42.199402],"type":"Point"}
}