{
  "type": "Feature",
  "properties": {
    "iso:country":"US",
    "sg:address":"645 Cherry St SE",
    "sg:city":"Grand Rapids",
    "sg:classifiers":[
        {
            "category":"Banks & Credit Unions",
            "subcategory":"Investment Brokerage",
            "type":"Services"
        }
    ],
    "sg:phone":"+1 616 451 8645",
    "sg:postcode":"49503",
    "sg:province":"MI",
    "sg:tags":[
        "security"
    ],
    "sg:website":"www.edwardjones.com",
    "wof:name":"Edward Jones Investments",
    "wof:placetype":"venue"
},
  "geometry": {"coordinates":[-85.652039,42.959553],"type":"Point"}
}