{
  "type": "Feature",
  "properties": {
    "iso:country":"US",
    "sg:address":"43 E Bacon St",
    "sg:city":"Hillsdale",
    "sg:classifiers":[
        {
            "category":"Personal",
            "subcategory":"Barber",
            "type":"Services"
        }
    ],
    "sg:phone":"+1 517 437 3204",
    "sg:postcode":"49242",
    "sg:province":"MI",
    "sg:tags":[
        "shop"
    ],
    "wof:name":"Jamie's Barber Shop",
    "wof:placetype":"venue"
},
  "geometry": {"coordinates":[-84.633307,41.920059],"type":"Point"}
}