{
  "type": "Feature",
  "properties": {
    "iso:country":"US",
    "sg:address":"2050 N Lapeer Rd",
    "sg:city":"Lapeer",
    "sg:classifiers":[
        {
            "category":"Home & Garden",
            "subcategory":"Household Appliances",
            "type":"Retail Goods"
        }
    ],
    "sg:phone":"+1 810 538 0205",
    "sg:postcode":"48446",
    "sg:province":"MI",
    "sg:tags":[
        "cleaners",
        "vacuum"
    ],
    "wof:name":"Quality Vacuum & Sewing",
    "wof:placetype":"venue"
},
  "geometry": {"coordinates":[-83.307553,43.090603],"type":"Point"}
}