{
  "type": "Feature",
  "properties": {
    "iso:country":"US",
    "sg:address":"180 N 1st St",
    "sg:city":"Brighton",
    "sg:classifiers":[
        {
            "category":"Restaurant",
            "type":"Food & Drink"
        }
    ],
    "sg:phone":"+1 810 227 5284",
    "sg:postcode":"48116",
    "sg:province":"MI",
    "wof:name":"Main Street Cafe",
    "wof:placetype":"venue"
},
  "geometry": {"coordinates":[-83.78517100000001,42.531294],"type":"Point"}
}