{
  "type": "Feature",
  "properties": {
    "iso:country":"US",
    "sg:address":"34968 Mill Lake Rd",
    "sg:city":"Gobles",
    "sg:classifiers":[
        {
            "category":"Utilities",
            "subcategory":"Telephone",
            "type":"Services"
        }
    ],
    "sg:phone":"+1 269 628 4944",
    "sg:postcode":"49055",
    "sg:province":"MI",
    "sg:tags":[
        "telecommunication"
    ],
    "wof:name":"QIC",
    "wof:placetype":"venue"
},
  "geometry": {"coordinates":[-85.88711000000001,42.368272],"type":"Point"}
}