{
  "type": "Feature",
  "properties": {
    "iso:country":"US",
    "sg:address":"1495 S Maple Rd",
    "sg:city":"Ann Arbor",
    "sg:classifiers":[
        {
            "category":"Building & Trades",
            "subcategory":"Cleaning & Sanitation",
            "type":"Services"
        }
    ],
    "sg:phone":"+1 734 662 5658",
    "sg:postcode":"48103",
    "sg:province":"MI",
    "sg:tags":[
        "maintenance"
    ],
    "wof:name":"Chamelion Concepts",
    "wof:placetype":"venue"
},
  "geometry": {"coordinates":[-83.779582,42.261507],"type":"Point"}
}