{
  "type": "Feature",
  "properties": {
    "iso:country":"US",
    "sg:address":"43638 Elizabeth St",
    "sg:city":"Clinton Twp",
    "sg:classifiers":[
        {
            "category":"Building & Trades",
            "subcategory":"Landscaping Services",
            "type":"Services"
        }
    ],
    "sg:phone":"+1 586 463 1941",
    "sg:postcode":"48036",
    "sg:province":"MI",
    "sg:tags":[
        "lawn",
        "maintenance",
        "grounds"
    ],
    "wof:name":"Lawn Barber Inc",
    "wof:placetype":"venue"
},
  "geometry": {"coordinates":[-82.88691900000001,42.615703],"type":"Point"}
}