{
  "type": "Feature",
  "properties": {
    "iso:country":"US",
    "sg:address":"2105 Partridge Point Rd N",
    "sg:city":"Alpena",
    "sg:classifiers":[
        {
            "category":"Building & Trades",
            "subcategory":"Construction",
            "type":"Services"
        }
    ],
    "sg:phone":"+1 989 354 7969",
    "sg:postcode":"49707",
    "sg:province":"MI",
    "sg:tags":[
        "general",
        "contractor"
    ],
    "wof:name":"Multi Construction Co Inc",
    "wof:placetype":"venue"
},
  "geometry": {"coordinates":[-83.453087,45.015257],"type":"Point"}
}