{
  "type": "Feature",
  "properties": {
    "iso:country":"US",
    "sg:address":"100 E Midland St",
    "sg:city":"Bay City",
    "sg:classifiers":[
        {
            "category":"Education",
            "subcategory":"Library",
            "type":"Public Place"
        }
    ],
    "sg:phone":"+1 989 892 8555",
    "sg:postcode":"48706",
    "sg:province":"MI",
    "wof:name":"Sage Branch Library",
    "wof:placetype":"venue"
},
  "geometry": {"coordinates":[-83.905148,43.602],"type":"Point"}
}