{
  "type": "Feature",
  "properties": {
    "iso:country":"US",
    "sg:address":"44811 Hayes Rd",
    "sg:city":"Sterling Heights",
    "sg:classifiers":[
        {
            "category":"Banks & Credit Unions",
            "subcategory":"Investment Brokerage",
            "type":"Services"
        }
    ],
    "sg:phone":"+1 586 566 7852",
    "sg:postcode":"48313",
    "sg:province":"MI",
    "sg:tags":[
        "investing"
    ],
    "sg:website":"www.edwardjones.com",
    "wof:name":"Edward Jones & Co",
    "wof:placetype":"venue"
},
  "geometry": {"coordinates":[-82.973417,42.625846],"type":"Point"}
}