{
  "type": "Feature",
  "properties": {
    "iso:country":"US",
    "sg:address":"565 W Mount Hope Hwy",
    "sg:city":"Grand Ledge",
    "sg:classifiers":[
        {
            "category":"Farming",
            "subcategory":"Farm",
            "type":"Manufacturing & Wholesale Goods"
        }
    ],
    "sg:phone":"+1 517 627 2685",
    "sg:postcode":"48837",
    "sg:province":"MI",
    "sg:tags":[
        "crop",
        "general"
    ],
    "wof:name":"Tom Potter",
    "wof:placetype":"venue"
},
  "geometry": {"coordinates":[-84.845403,42.711978],"type":"Point"}
}