{
  "type": "Feature",
  "properties": {
    "iso:country":"US",
    "sg:address":"2409 Marjorie Ln",
    "sg:city":"Clio",
    "sg:classifiers":[
        {
            "category":"Shopping",
            "subcategory":"Computers & Home Electronics",
            "type":"Retail Goods"
        }
    ],
    "sg:phone":"+1 810 686 0693",
    "sg:postcode":"48420",
    "sg:province":"MI",
    "sg:tags":[
        "equipment",
        "dealer"
    ],
    "wof:name":"Sysport",
    "wof:placetype":"venue"
},
  "geometry": {"coordinates":[-83.669663,43.202724],"type":"Point"}
}