{
  "type": "Feature",
  "properties": {
    "iso:country":"US",
    "sg:address":"2469 Cedar St",
    "sg:city":"Holt",
    "sg:classifiers":[
        {
            "category":"Banks & Credit Unions",
            "subcategory":"Bank",
            "type":"Services"
        }
    ],
    "sg:phone":"+1 517 694 5083",
    "sg:postcode":"48842",
    "sg:province":"MI",
    "sg:website":"www.dartbank.com",
    "wof:name":"Dart National Bank",
    "wof:placetype":"venue"
},
  "geometry": {"coordinates":[-84.53054299999999,42.65219],"type":"Point"}
}