{
  "type": "Feature",
  "properties": {
    "iso:country":"US",
    "sg:address":"9100 S Lake Shore Dr",
    "sg:city":"Cedar",
    "sg:classifiers":[
        {
            "category":"Farming",
            "subcategory":"Vineyard",
            "type":"Manufacturing & Wholesale Goods"
        }
    ],
    "sg:phone":"+1 231 334 6744",
    "sg:postcode":"49621",
    "sg:province":"MI",
    "wof:name":"Isidore's Choice Vineyard",
    "wof:placetype":"venue"
},
  "geometry": {"coordinates":[-85.760991,44.851349],"type":"Point"}
}