{
  "type": "Feature",
  "properties": {
    "iso:country":"US",
    "sg:address":"19076 Allen Rd",
    "sg:city":"Flat Rock",
    "sg:classifiers":[
        {
            "category":"Banks & Credit Unions",
            "subcategory":"Bank",
            "type":"Services"
        }
    ],
    "sg:phone":"+1 734 479 0050",
    "sg:postcode":"48134",
    "sg:province":"MI",
    "sg:website":"www.nationalcity.com",
    "wof:name":"National City",
    "wof:placetype":"venue"
},
  "geometry": {"coordinates":[-83.28830000000001,42.1068],"type":"Point"}
}