{
  "type": "Feature",
  "properties": {
    "iso:country":"US",
    "sg:address":"1663 W Lemon Creek Rd",
    "sg:city":"Baroda",
    "sg:classifiers":[
        {
            "category":"Wholesale",
            "subcategory":"Toys & Hobbies",
            "type":"Manufacturing & Wholesale Goods"
        }
    ],
    "sg:phone":"+1 269 422 5429",
    "sg:postcode":"49101",
    "sg:province":"MI",
    "sg:tags":[
        "wholesaler"
    ],
    "wof:name":"Lakeshore Wholesalers LLC",
    "wof:placetype":"venue"
},
  "geometry": {"coordinates":[-86.49251599999999,41.957438],"type":"Point"}
}