{
  "type": "Feature",
  "properties": {
    "iso:country":"US",
    "sg:address":"14778 Syracuse St",
    "sg:city":"Taylor",
    "sg:classifiers":[
        {
            "category":"Building & Trades",
            "subcategory":"Landscaping Services",
            "type":"Services"
        }
    ],
    "sg:phone":"+1 734 287 2135",
    "sg:postcode":"48180",
    "sg:province":"MI",
    "wof:name":"Finished Edge Lawn & Landscape",
    "wof:placetype":"venue"
},
  "geometry": {"coordinates":[-83.264161,42.198854],"type":"Point"}
}