{
  "type": "Feature",
  "properties": {
    "iso:country":"US",
    "sg:address":"6259 Coleman St",
    "sg:city":"Dearborn",
    "sg:classifiers":[
        {
            "category":"Arts & Performance",
            "subcategory":"Theater",
            "type":"Entertainment"
        }
    ],
    "sg:phone":"+1 313 836 8528",
    "sg:postcode":"48126",
    "sg:province":"MI",
    "sg:tags":[
        "group"
    ],
    "wof:name":"Bagpipe Music Unlimited",
    "wof:placetype":"venue"
},
  "geometry": {"coordinates":[-83.193845,42.33594],"type":"Point"}
}