{
  "type": "Feature",
  "properties": {
    "iso:country":"US",
    "sg:address":"115 Bidwell St",
    "sg:city":"Tecumseh",
    "sg:classifiers":[
        {
            "category":"Education",
            "subcategory":"Dance Studio",
            "type":"Public Place"
        }
    ],
    "sg:phone":"+1 517 423 3937",
    "sg:postcode":"49286",
    "sg:province":"MI",
    "sg:tags":[
        "instruction",
        "dancing"
    ],
    "wof:name":"Tecumseh Dance Workshop",
    "wof:placetype":"venue"
},
  "geometry": {"coordinates":[-83.944819,42.008569],"type":"Point"}
}