{
  "type": "Feature",
  "properties": {
    "iso:country":"US",
    "sg:address":"12021 Harper Ave",
    "sg:city":"Detroit",
    "sg:classifiers":[
        {
            "category":"Food & Beverages",
            "subcategory":"Groceries & Convenience Stores",
            "type":"Retail Goods"
        }
    ],
    "sg:phone":"+1 313 527 0050",
    "sg:postcode":"48213",
    "sg:province":"MI",
    "wof:name":"Thrifty Scot",
    "wof:placetype":"venue"
},
  "geometry": {"coordinates":[-82.98400100000001,42.398998],"type":"Point"}
}