{
  "type": "Feature",
  "properties": {
    "iso:country":"US",
    "sg:address":"820 Byron Rd",
    "sg:city":"Howell",
    "sg:classifiers":[
        {
            "category":"Health Services",
            "subcategory":"Doctor",
            "type":"Services"
        }
    ],
    "sg:phone":"+1 517 546 2240",
    "sg:postcode":"48843",
    "sg:province":"MI",
    "wof:name":"Robert A Hyland DDS PC",
    "wof:placetype":"venue"
},
  "geometry": {"coordinates":[-83.94093599999999,42.61907],"type":"Point"}
}