{
  "type": "Feature",
  "properties": {
    "iso:country":"US",
    "sg:address":"36045 S Whitney Bay Rd",
    "sg:city":"Drummond Island",
    "sg:classifiers":[
        {
            "category":"Building & Trades",
            "subcategory":"Construction",
            "type":"Services"
        }
    ],
    "sg:phone":"+1 906 493 5585",
    "sg:postcode":"49726",
    "sg:province":"MI",
    "sg:tags":[
        "general",
        "contractor"
    ],
    "wof:name":"T G Ellis Plumbing",
    "wof:placetype":"venue"
},
  "geometry": {"coordinates":[-83.848878,45.985171],"type":"Point"}
}