{
  "type": "Feature",
  "properties": {
    "iso:country":"US",
    "sg:address":"4938 Division Ave S",
    "sg:city":"Grand Rapids",
    "sg:classifiers":[
        {
            "category":"Personal",
            "type":"Services"
        }
    ],
    "sg:phone":"+1 616 538 8044",
    "sg:postcode":"49548",
    "sg:province":"MI",
    "wof:name":"Anew Look",
    "wof:placetype":"venue"
},
  "geometry": {"coordinates":[-85.664267,42.873164],"type":"Point"}
}