{
  "type": "Feature",
  "properties": {
    "iso:country":"US",
    "sg:address":"1600 Terminal Dr",
    "sg:city":"Saginaw",
    "sg:classifiers":[
        {
            "category":"Manufacturing",
            "subcategory":"Metals",
            "type":"Manufacturing & Wholesale Goods"
        }
    ],
    "sg:phone":"+1 989 753 8100",
    "sg:postcode":"48601",
    "sg:province":"MI",
    "sg:tags":[
        "steel"
    ],
    "wof:name":"MKR Fabricators Inc",
    "wof:placetype":"venue"
},
  "geometry": {"coordinates":[-83.88491999999999,43.429343],"type":"Point"}
}