{
  "type": "Feature",
  "properties": {
    "iso:country":"US",
    "sg:address":"1614 Lansing St",
    "sg:city":"Detroit",
    "sg:classifiers":[
        {
            "category":"Home & Garden",
            "subcategory":"Hardware",
            "type":"Retail Goods"
        }
    ],
    "sg:phone":"+1 313 297 7174",
    "sg:postcode":"48209",
    "sg:province":"MI",
    "sg:tags":[
        "store"
    ],
    "wof:name":"Vernor DO It Best Hardware",
    "wof:placetype":"venue"
},
  "geometry": {"coordinates":[-83.098,42.318802],"type":"Point"}
}