{
  "type": "Feature",
  "properties": {
    "iso:country":"US",
    "sg:address":"2502 Rochester Rd",
    "sg:city":"Royal Oak",
    "sg:classifiers":[
        {
            "category":"Building & Trades",
            "subcategory":"Construction",
            "type":"Services"
        }
    ],
    "sg:phone":"+1 248 546 7870",
    "sg:postcode":"48073",
    "sg:province":"MI",
    "sg:tags":[
        "home",
        "builder"
    ],
    "wof:name":"Fantuzzi Homes",
    "wof:placetype":"venue"
},
  "geometry": {"coordinates":[-83.140917,42.512916],"type":"Point"}
}