{
  "type": "Feature",
  "properties": {
    "iso:country":"US",
    "sg:address":"4600 Allen Rd",
    "sg:city":"Allen Park",
    "sg:classifiers":[
        {
            "category":"Social Services",
            "subcategory":"Adult Care",
            "type":"Services"
        }
    ],
    "sg:phone":"+1 313 383 6226",
    "sg:postcode":"48101",
    "sg:province":"MI",
    "sg:tags":[
        "home",
        "retirement"
    ],
    "wof:name":"Maple Heights Retirement Cmnty",
    "wof:placetype":"venue"
},
  "geometry": {"coordinates":[-83.198252,42.268487],"type":"Point"}
}