{
  "type": "Feature",
  "properties": {
    "iso:country":"US",
    "sg:address":"6936 Post Oak Dr",
    "sg:city":"West Bloomfield",
    "sg:classifiers":[
        {
            "category":"Professional",
            "subcategory":"Computer Services",
            "type":"Services"
        }
    ],
    "sg:phone":"+1 248 626 5025",
    "sg:postcode":"48322",
    "sg:province":"MI",
    "sg:tags":[
        "datum"
    ],
    "wof:name":"Isaac Lakritz",
    "wof:placetype":"venue"
},
  "geometry": {"coordinates":[-83.34833999999999,42.536607],"type":"Point"}
}