{
  "type": "Feature",
  "properties": {
    "iso:country":"US",
    "sg:address":"1954 Berville Rd",
    "sg:city":"Berlin",
    "sg:classifiers":[
        {
            "category":"Manufacturing",
            "subcategory":"Metals",
            "type":"Manufacturing & Wholesale Goods"
        }
    ],
    "sg:phone":"+1 810 395 8665",
    "sg:postcode":"48002",
    "sg:province":"MI",
    "sg:tags":[
        "fabricator",
        "sheet"
    ],
    "wof:name":"Custom Designs",
    "wof:placetype":"venue"
},
  "geometry": {"coordinates":[-82.88596,42.951919],"type":"Point"}
}