{
  "type": "Feature",
  "properties": {
    "iso:country":"US",
    "sg:address":"29405 Hoover Rd",
    "sg:city":"Warren",
    "sg:classifiers":[
        {
            "category":"Professional",
            "subcategory":"Lawyer & Legal Services",
            "type":"Services"
        }
    ],
    "sg:phone":"+1 586 291 2541",
    "sg:postcode":"48093",
    "sg:province":"MI",
    "sg:tags":[
        "personal",
        "injury"
    ],
    "wof:name":"Injury Assistance Center",
    "wof:placetype":"venue"
},
  "geometry": {"coordinates":[-83.007233,42.510189],"type":"Point"}
}