{
  "type": "Feature",
  "properties": {
    "iso:country":"US",
    "sg:address":"6086 Belford Rd",
    "sg:city":"Holly",
    "sg:classifiers":[
        {
            "category":"Professional",
            "type":"Services"
        }
    ],
    "sg:phone":"+1 248 634 8691",
    "sg:postcode":"48442",
    "sg:province":"MI",
    "sg:tags":[
        "establishment"
    ],
    "wof:name":"Sorensen Harvey Applnc",
    "wof:placetype":"venue"
},
  "geometry": {"coordinates":[-83.58229799999999,42.860568],"type":"Point"}
}