{
  "type": "Feature",
  "properties": {
    "iso:country":"US",
    "sg:address":"914 Lane Dr",
    "sg:city":"St Joseph",
    "sg:classifiers":[
        {
            "category":"Organizations",
            "subcategory":"Religious Organization",
            "type":"Services"
        }
    ],
    "sg:phone":"+1 269 983 4761",
    "sg:postcode":"49085",
    "sg:province":"MI",
    "sg:tags":[
        "church"
    ],
    "sg:website":"www.stpaulstjoe.org",
    "wof:name":"St Paul S Episcopal Church",
    "wof:placetype":"venue"
},
  "geometry": {"coordinates":[-86.480583,42.092864],"type":"Point"}
}