{
  "type": "Feature",
  "properties": {
    "iso:country":"US",
    "sg:address":"28200 Franklin Rd",
    "sg:city":"Southfield",
    "sg:classifiers":[
        {
            "category":"Banks & Credit Unions",
            "subcategory":"Bank",
            "type":"Services"
        }
    ],
    "sg:phone":"+1 248 799 5120",
    "sg:postcode":"48034",
    "sg:province":"MI",
    "sg:tags":[
        "mortgage",
        "loan",
        "broker",
        "real estate"
    ],
    "sg:website":"www.remingtonloan.com",
    "wof:name":"Remington Mortgage Inc",
    "wof:placetype":"venue"
},
  "geometry": {"coordinates":[-83.301102,42.494801],"type":"Point"}
}