{
  "type": "Feature",
  "properties": {
    "iso:country":"US",
    "sg:address":"36203 60th Ave",
    "sg:city":"Paw Paw",
    "sg:classifiers":[
        {
            "category":"Farming",
            "subcategory":"Dairy Farm",
            "type":"Manufacturing & Wholesale Goods"
        }
    ],
    "sg:phone":"+1 269 657 4728",
    "sg:postcode":"49079",
    "sg:province":"MI",
    "wof:name":"Clifford Price Farm",
    "wof:placetype":"venue"
},
  "geometry": {"coordinates":[-85.91407599999999,42.200697],"type":"Point"}
}