{
  "type": "Feature",
  "properties": {
    "iso:country":"US",
    "sg:address":"3080 McKinley St",
    "sg:city":"Kalamazoo",
    "sg:classifiers":[
        {
            "category":"Arts & Performance",
            "subcategory":"Theater",
            "type":"Entertainment"
        }
    ],
    "sg:phone":"+1 269 349 6483",
    "sg:postcode":"49004",
    "sg:province":"MI",
    "sg:tags":[
        "group"
    ],
    "wof:name":"Green Valley Band",
    "wof:placetype":"venue"
},
  "geometry": {"coordinates":[-85.553619,42.349615],"type":"Point"}
}