{
  "type": "Feature",
  "properties": {
    "iso:country":"US",
    "sg:address":"7904 S Francis Rd",
    "sg:city":"Dewitt",
    "sg:classifiers":[
        {
            "category":"Freight",
            "type":"Transportation"
        }
    ],
    "sg:phone":"+1 517 668 9925",
    "sg:postcode":"48820",
    "sg:province":"MI",
    "sg:tags":[
        "trucking"
    ],
    "wof:name":"Victoria Transport LLC",
    "wof:placetype":"venue"
},
  "geometry": {"coordinates":[-84.66132899999999,42.90173],"type":"Point"}
}