{
  "type": "Feature",
  "properties": {
    "iso:country":"US",
    "sg:address":"3922 Euclid St",
    "sg:city":"Brutus",
    "sg:classifiers":[
        {
            "category":"Organizations",
            "subcategory":"Religious Organization",
            "type":"Services"
        }
    ],
    "sg:phone":"+1 231 529 7330",
    "sg:postcode":"49716",
    "sg:province":"MI",
    "sg:tags":[
        "church"
    ],
    "wof:name":"Calvary Baptist Church",
    "wof:placetype":"venue"
},
  "geometry": {"coordinates":[-84.78338100000001,45.494226],"type":"Point"}
}