{
  "type": "Feature",
  "properties": {
    "iso:country":"US",
    "sg:address":"106 E Lincoln Ave",
    "sg:city":"Ionia",
    "sg:classifiers":[
        {
            "category":"Health Services",
            "subcategory":"Doctor",
            "type":"Services"
        }
    ],
    "sg:phone":"+1 616 527 1377",
    "sg:postcode":"48846",
    "sg:province":"MI",
    "sg:tags":[
        "physician",
        "surgeon"
    ],
    "wof:name":"Leonard Vangelder MD",
    "wof:placetype":"venue"
},
  "geometry": {"coordinates":[-85.063705,42.987464],"type":"Point"}
}