{
  "type": "Feature",
  "properties": {
    "iso:country":"US",
    "sg:address":"36601 Ford Rd",
    "sg:city":"Westland",
    "sg:classifiers":[
        {
            "category":"Government",
            "subcategory":"Office",
            "type":"Public Place"
        }
    ],
    "sg:phone":"+1 734 467 3190",
    "sg:postcode":"48185",
    "sg:province":"MI",
    "sg:tags":[
        "general"
    ],
    "wof:name":"City Clerks Office",
    "wof:placetype":"venue"
},
  "geometry": {"coordinates":[-83.402925,42.324094],"type":"Point"}
}