{
  "type": "Feature",
  "properties": {
    "iso:country":"US",
    "sg:address":"3063 Follmer St",
    "sg:city":"Niles",
    "sg:classifiers":[
        {
            "category":"Museum",
            "type":"Entertainment"
        }
    ],
    "sg:phone":"+1 269 663 8423",
    "sg:postcode":"49120",
    "sg:province":"MI",
    "sg:tags":[
        "gallery"
    ],
    "wof:name":"Smiths Chapel Historical",
    "wof:placetype":"venue"
},
  "geometry": {"coordinates":[-86.14364,41.796973],"type":"Point"}
}