{
  "type": "Feature",
  "properties": {
    "iso:country":"US",
    "sg:address":"19136 Joy Rd",
    "sg:city":"Detroit",
    "sg:classifiers":[
        {
            "category":"Organizations",
            "subcategory":"Religious Organization",
            "type":"Services"
        }
    ],
    "sg:phone":"+1 313 273 2550",
    "sg:postcode":"48228",
    "sg:province":"MI",
    "wof:name":"Greater Works Family Ministries",
    "wof:placetype":"venue"
},
  "geometry": {"coordinates":[-83.227868,42.35782],"type":"Point"}
}