{
  "type": "Feature",
  "properties": {
    "iso:country":"US",
    "sg:address":"12702 Nash Hwy",
    "sg:city":"Clarksville",
    "sg:classifiers":[
        {
            "category":"Recreation",
            "subcategory":"Marina",
            "type":"Entertainment"
        }
    ],
    "sg:phone":"+1 616 693 3283",
    "sg:postcode":"48815",
    "sg:province":"MI",
    "wof:name":"Dave's Dry Dock",
    "wof:placetype":"venue"
},
  "geometry": {"coordinates":[-85.242096,42.802653],"type":"Point"}
}