{
  "type": "Feature",
  "properties": {
    "iso:country":"US",
    "sg:address":"2015 Ridge Ave",
    "sg:city":"Ann Arbor",
    "sg:classifiers":[
        {
            "category":"Professional",
            "subcategory":"Management & Consulting",
            "type":"Services"
        }
    ],
    "sg:phone":"+1 734 971 8393",
    "sg:postcode":"48104",
    "sg:province":"MI",
    "sg:tags":[
        "business"
    ],
    "wof:name":"Forbes Link Consulting",
    "wof:placetype":"venue"
},
  "geometry": {"coordinates":[-83.716036,42.254826],"type":"Point"}
}