{
  "type": "Feature",
  "properties": {
    "iso:country":"US",
    "sg:address":"427 Rachel Marie Ct",
    "sg:city":"Pinckney",
    "sg:classifiers":[
        {
            "category":"Shopping",
            "subcategory":"Crafts & Fabrics",
            "type":"Retail Goods"
        }
    ],
    "sg:phone":"+1 734 878 4665",
    "sg:postcode":"48169",
    "sg:province":"MI",
    "sg:tags":[
        "sewing"
    ],
    "wof:name":"Sharis Sew Shop",
    "wof:placetype":"venue"
},
  "geometry": {"coordinates":[-83.936279,42.436614],"type":"Point"}
}