{
  "type": "Feature",
  "properties": {
    "iso:country":"US",
    "sg:address":"5507 W Houghton Lake Rd",
    "sg:city":"Lake City",
    "sg:classifiers":[
        {
            "category":"Manufacturing",
            "subcategory":"Petroleum Products",
            "type":"Manufacturing & Wholesale Goods"
        }
    ],
    "sg:phone":"+1 231 839 4641",
    "sg:postcode":"49651",
    "sg:province":"MI",
    "sg:tags":[
        "oil"
    ],
    "wof:name":"Johnson Oil Co",
    "wof:placetype":"venue"
},
  "geometry": {"coordinates":[-85.20714700000001,44.339097],"type":"Point"}
}