{
  "type": "Feature",
  "properties": {
    "iso:country":"US",
    "sg:address":"1415 Sugar River Rd",
    "sg:city":"Gladwin",
    "sg:classifiers":[
        {
            "category":"Real Estate",
            "subcategory":"Real Estate Agent",
            "type":"Services"
        }
    ],
    "sg:phone":"+1 989 426 9239",
    "sg:postcode":"48624",
    "sg:province":"MI",
    "wof:name":"Sugar Springs Sales Inc",
    "wof:placetype":"venue"
},
  "geometry": {"coordinates":[-84.42245800000001,44.131474],"type":"Point"}
}