{
  "type": "Feature",
  "properties": {
    "iso:country":"US",
    "sg:address":"9978 Saginaw St",
    "sg:city":"Reese",
    "sg:classifiers":[
        {
            "category":"Cinema",
            "subcategory":"Movie Rental",
            "type":"Entertainment"
        }
    ],
    "sg:phone":"+1 989 868 9911",
    "sg:postcode":"48757",
    "sg:province":"MI",
    "sg:tags":[
        "leasing",
        "video",
        "disc",
        "tape"
    ],
    "wof:name":"Video Venture",
    "wof:placetype":"venue"
},
  "geometry": {"coordinates":[-83.697632,43.450508],"type":"Point"}
}