{
  "type": "Feature",
  "properties": {
    "iso:country":"US",
    "sg:address":"91 N Caseville Rd",
    "sg:city":"Pigeon",
    "sg:classifiers":[
        {
            "category":"Wholesale",
            "subcategory":"Machinery & Supplies",
            "type":"Manufacturing & Wholesale Goods"
        }
    ],
    "sg:phone":"+1 989 453 3332",
    "sg:postcode":"48755",
    "sg:province":"MI",
    "sg:tags":[
        "farm",
        "equipment"
    ],
    "wof:name":"Gettel & Co",
    "wof:placetype":"venue"
},
  "geometry": {"coordinates":[-83.279483,43.830378],"type":"Point"}
}