{
  "type": "Feature",
  "properties": {
    "iso:country":"US",
    "sg:address":"5202 E Center Rd",
    "sg:city":"Hastings",
    "sg:classifiers":[
        {
            "category":"Retail",
            "subcategory":"Repair Shop",
            "type":"Services"
        }
    ],
    "sg:phone":"+1 269 948 8659",
    "sg:postcode":"49058",
    "sg:province":"MI",
    "sg:tags":[
        "scooter",
        "motorcycle",
        "motor"
    ],
    "wof:name":"Strow's Cycle Works",
    "wof:placetype":"venue"
},
  "geometry": {"coordinates":[-85.18889900000001,42.639539],"type":"Point"}
}