{
  "type": "Feature",
  "properties": {
    "iso:country":"US",
    "sg:address":"237 N Fremont Rd",
    "sg:city":"Coldwater",
    "sg:classifiers":[
        {
            "category":"Freight",
            "type":"Transportation"
        }
    ],
    "sg:phone":"+1 517 278 5138",
    "sg:postcode":"49036",
    "sg:province":"MI",
    "sg:tags":[
        "operator",
        "local",
        "trucking"
    ],
    "wof:name":"Ksh Company",
    "wof:placetype":"venue"
},
  "geometry": {"coordinates":[-84.931996,41.916012],"type":"Point"}
}