{
  "type": "Feature",
  "properties": {
    "iso:country":"US",
    "sg:address":"4969 Mohawk Rd",
    "sg:city":"Okemos",
    "sg:classifiers":[
        {
            "category":"Insurance",
            "subcategory":"Insurance Agent",
            "type":"Services"
        }
    ],
    "sg:phone":"+1 517 347 0488",
    "sg:postcode":"48864",
    "sg:province":"MI",
    "wof:name":"Empire Fire & Marine Insurance",
    "wof:placetype":"venue"
},
  "geometry": {"coordinates":[-84.43982099999999,42.724402],"type":"Point"}
}