{
  "type": "Feature",
  "properties": {
    "iso:country":"US",
    "sg:address":"1106 Kentwood Dr NE",
    "sg:city":"Grand Rapids",
    "sg:classifiers":[
        {
            "category":"Social Services",
            "subcategory":"Child Care",
            "type":"Services"
        }
    ],
    "sg:phone":"+1 616 364 5480",
    "sg:postcode":"49505",
    "sg:province":"MI",
    "sg:tags":[
        "day"
    ],
    "wof:name":"Aprils Angels Daycare",
    "wof:placetype":"venue"
},
  "geometry": {"coordinates":[-85.641007,42.994793],"type":"Point"}
}