{
  "type": "Feature",
  "properties": {
    "iso:country":"US",
    "sg:address":"1321 Suffield Ave",
    "sg:city":"Birmingham",
    "sg:classifiers":[
        {
            "category":"Professional",
            "subcategory":"Business Services",
            "type":"Services"
        }
    ],
    "sg:phone":"+1 248 645 5248",
    "sg:postcode":"48009",
    "sg:province":"MI",
    "sg:tags":[
        "notary",
        "public"
    ],
    "wof:name":"Douglas J Paquin",
    "wof:placetype":"venue"
},
  "geometry": {"coordinates":[-83.23279700000001,42.555875],"type":"Point"}
}