{
  "type": "Feature",
  "properties": {
    "iso:country":"US",
    "sg:address":"1431 N Creyts Rd",
    "sg:city":"Lansing",
    "sg:classifiers":[
        {
            "category":"Building & Trades",
            "subcategory":"Landscaping Services",
            "type":"Services"
        }
    ],
    "sg:phone":"+1 517 323 3678",
    "sg:postcode":"48917",
    "sg:province":"MI",
    "sg:tags":[
        "tree"
    ],
    "wof:name":"Total Lawn & Tree Care Inc",
    "wof:placetype":"venue"
},
  "geometry": {"coordinates":[-84.64229,42.748704],"type":"Point"}
}