{
  "type": "Feature",
  "properties": {
    "iso:country":"US",
    "sg:address":"5870 Salisbury Rd",
    "sg:city":"Hale",
    "sg:classifiers":[
        {
            "category":"Building & Trades",
            "subcategory":"Construction",
            "type":"Services"
        }
    ],
    "sg:phone":"+1 989 728 7389",
    "sg:postcode":"48739",
    "sg:province":"MI",
    "sg:tags":[
        "general",
        "contractor"
    ],
    "wof:name":"TLP Construction",
    "wof:placetype":"venue"
},
  "geometry": {"coordinates":[-83.758531,44.384397],"type":"Point"}
}