{
  "type": "Feature",
  "properties": {
    "iso:country":"US",
    "sg:address":"359 Reagon St",
    "sg:city":"St Ignace",
    "sg:classifiers":[
        {
            "category":"Manufacturing",
            "subcategory":"Printing",
            "type":"Manufacturing & Wholesale Goods"
        }
    ],
    "sg:phone":"+1 906 643 9150",
    "sg:postcode":"49781",
    "sg:province":"MI",
    "sg:tags":[
        "newspaper"
    ],
    "wof:name":"St Ignace News",
    "wof:placetype":"venue"
},
  "geometry": {"coordinates":[-84.733914,45.873936],"type":"Point"}
}