{
  "type": "Feature",
  "properties": {
    "iso:country":"US",
    "sg:address":"1540 40th St SW",
    "sg:city":"Grand Rapids",
    "sg:classifiers":[
        {
            "category":"Organizations",
            "subcategory":"Religious Organization",
            "type":"Services"
        }
    ],
    "sg:phone":"+1 616 531 9131",
    "sg:postcode":"49509",
    "sg:province":"MI",
    "sg:tags":[
        "church"
    ],
    "wof:name":"Oriole Park Baptist Church",
    "wof:placetype":"venue"
},
  "geometry": {"coordinates":[-85.70119200000001,42.891523],"type":"Point"}
}