{
  "type": "Feature",
  "properties": {
    "iso:country":"US",
    "sg:address":"410 S Union St",
    "sg:city":"Traverse City",
    "sg:classifiers":[
        {
            "category":"Manufacturing",
            "subcategory":"Printing",
            "type":"Manufacturing & Wholesale Goods"
        }
    ],
    "sg:phone":"+1 231 946 3055",
    "sg:postcode":"49684",
    "sg:province":"MI",
    "sg:tags":[
        "newspaper"
    ],
    "wof:name":"Preview Community Weekly",
    "wof:placetype":"venue"
},
  "geometry": {"coordinates":[-85.62388799999999,44.76037],"type":"Point"}
}