{
  "type": "Feature",
  "properties": {
    "iso:country":"US",
    "sg:address":"267 Norway St",
    "sg:city":"Gladwin",
    "sg:classifiers":[
        {
            "category":"Organizations",
            "subcategory":"Community Association",
            "type":"Services"
        }
    ],
    "sg:phone":"+1 989 426 4612",
    "sg:postcode":"48624",
    "sg:province":"MI",
    "sg:tags":[
        "military"
    ],
    "wof:name":"American Legion",
    "wof:placetype":"venue"
},
  "geometry": {"coordinates":[-84.358746,44.154141],"type":"Point"}
}