{
  "type": "Feature",
  "properties": {
    "iso:country":"US",
    "sg:address":"3223 52nd St SE",
    "sg:city":"Grand Rapids",
    "sg:classifiers":[
        {
            "category":"Building & Trades",
            "subcategory":"Construction",
            "type":"Services"
        }
    ],
    "sg:phone":"+1 616 698 7820",
    "sg:postcode":"49512",
    "sg:province":"MI",
    "sg:tags":[
        "dry wall",
        "contractor"
    ],
    "wof:name":"Dykstra Tile & Drywall Co",
    "wof:placetype":"venue"
},
  "geometry": {"coordinates":[-85.58913099999999,42.86914],"type":"Point"}
}