{
  "type": "Feature",
  "properties": {
    "iso:country":"US",
    "sg:address":"20164 W 8 Mile Rd",
    "sg:city":"Southfield",
    "sg:classifiers":[
        {
            "category":"Shopping",
            "subcategory":"Shoes",
            "type":"Retail Goods"
        }
    ],
    "sg:phone":"+1 248 304 9976",
    "sg:postcode":"48075",
    "sg:province":"MI",
    "wof:name":"Payless Shoe Source",
    "wof:placetype":"venue"
},
  "geometry": {"coordinates":[-83.24038400000001,42.444126],"type":"Point"}
}