{
  "type": "Feature",
  "properties": {
    "iso:country":"US",
    "sg:address":"20840 W Chicago St",
    "sg:city":"Detroit",
    "sg:classifiers":[
        {
            "category":"Food & Beverages",
            "subcategory":"Liquor & Beverages",
            "type":"Retail Goods"
        }
    ],
    "sg:phone":"+1 313 838 7420",
    "sg:postcode":"48228",
    "sg:province":"MI",
    "sg:tags":[
        "beer",
        "spirit",
        "wine"
    ],
    "wof:name":"Scotty J Liquor Shoppe",
    "wof:placetype":"venue"
},
  "geometry": {"coordinates":[-83.24520099999999,42.3647],"type":"Point"}
}