{
  "type": "Feature",
  "properties": {
    "iso:country":"US",
    "sg:address":"2727 Old Horton Bay Rd",
    "sg:city":"Boyne City",
    "sg:classifiers":[
        {
            "category":"Building & Trades",
            "subcategory":"Construction",
            "type":"Services"
        }
    ],
    "sg:phone":"+1 231 582 1015",
    "sg:postcode":"49712",
    "sg:province":"MI",
    "sg:tags":[
        "house"
    ],
    "wof:name":"Lewin Construction",
    "wof:placetype":"venue"
},
  "geometry": {"coordinates":[-85.036433,45.248501],"type":"Point"}
}