{
  "type": "Feature",
  "properties": {
    "iso:country":"US",
    "sg:address":"609 May St",
    "sg:city":"Lansing",
    "sg:classifiers":[
        {
            "category":"Autos & Motor Vehicles",
            "subcategory":"Fuel & Gas Station",
            "type":"Retail Goods"
        }
    ],
    "sg:phone":"+1 517 332 1391",
    "sg:postcode":"48906",
    "sg:province":"MI",
    "sg:tags":[
        "oil"
    ],
    "wof:name":"Frandor Shell",
    "wof:placetype":"venue"
},
  "geometry": {"coordinates":[-84.5429,42.742379],"type":"Point"}
}