{
  "type": "Feature",
  "properties": {
    "iso:country":"US",
    "sg:address":"1341 S Colling Rd",
    "sg:city":"Caro",
    "sg:classifiers":[
        {
            "category":"Social Services",
            "subcategory":"Adult Care",
            "type":"Services"
        }
    ],
    "sg:phone":"+1 989 673 7812",
    "sg:postcode":"48723",
    "sg:province":"MI",
    "sg:tags":[
        "residential"
    ],
    "wof:name":"Rendons Yng At HRT Adlt Fstr",
    "wof:placetype":"venue"
},
  "geometry": {"coordinates":[-83.406113,43.471434],"type":"Point"}
}