{
  "type": "Feature",
  "properties": {
    "iso:country":"US",
    "sg:address":"24525 Harper Ave Ste 2",
    "sg:city":"Saint Clair Shores",
    "sg:classifiers":[
        {
            "category":"Banks & Credit Unions",
            "subcategory":"Atm",
            "type":"Services"
        }
    ],
    "sg:phone":"+1 586 777 0770",
    "sg:postcode":"48080",
    "sg:province":"MI",
    "sg:tags":[
        "bankruptcy"
    ],
    "wof:name":"Butler Butler & Associates",
    "wof:placetype":"venue"
},
  "geometry": {"coordinates":[-82.903503,42.4758],"type":"Point"}
}