{
  "type": "Feature",
  "properties": {
    "iso:country":"US",
    "sg:address":"8424 US Hwy 12",
    "sg:city":"Brooklyn",
    "sg:classifiers":[
        {
            "category":"Restaurant",
            "type":"Food & Drink"
        }
    ],
    "sg:phone":"+1 517 467 2850",
    "sg:postcode":"49230",
    "sg:province":"MI",
    "sg:tags":[
        "drinking",
        "eating"
    ],
    "wof:name":"Kellys On Hill",
    "wof:placetype":"venue"
},
  "geometry": {"coordinates":[-84.164277,42.056602],"type":"Point"}
}