{
  "type": "Feature",
  "properties": {
    "iso:country":"US",
    "sg:address":"31300 Utica Rd",
    "sg:city":"Fraser",
    "sg:classifiers":[
        {
            "category":"Wholesale",
            "subcategory":"Machinery & Supplies",
            "type":"Manufacturing & Wholesale Goods"
        }
    ],
    "sg:phone":"+1 586 294 5351",
    "sg:postcode":"48026",
    "sg:province":"MI",
    "sg:tags":[
        "gage"
    ],
    "wof:name":"Quality Measuring Tool Repair",
    "wof:placetype":"venue"
},
  "geometry": {"coordinates":[-82.945808,42.526419],"type":"Point"}
}