{
  "type": "Feature",
  "properties": {
    "iso:country":"US",
    "sg:address":"525 Samantha St",
    "sg:city":"Lansing",
    "sg:classifiers":[
        {
            "category":"Organizations",
            "subcategory":"Religious Organization",
            "type":"Services"
        }
    ],
    "sg:phone":"+1 517 394 3123",
    "sg:postcode":"48910",
    "sg:province":"MI",
    "wof:name":"Lansing Mong Alliance Church",
    "wof:placetype":"venue"
},
  "geometry": {"coordinates":[-84.545508,42.688493],"type":"Point"}
}