{
  "type": "Feature",
  "properties": {
    "iso:country":"US",
    "sg:address":"106 W Smith St",
    "sg:city":"Iron Mountain",
    "sg:classifiers":[
        {
            "category":"Manufacturing",
            "subcategory":"Furniture",
            "type":"Manufacturing & Wholesale Goods"
        }
    ],
    "sg:phone":"+1 906 774 0020",
    "sg:postcode":"49801",
    "sg:province":"MI",
    "sg:tags":[
        "wood",
        "radio"
    ],
    "wof:name":"Les-Cove Inc",
    "wof:placetype":"venue"
},
  "geometry": {"coordinates":[-88.06458000000001,45.828954],"type":"Point"}
}