{
  "type": "Feature",
  "properties": {
    "iso:country":"US",
    "sg:address":"605 Mac Ave",
    "sg:city":"East Lansing",
    "sg:classifiers":[
        {
            "category":"Organizations",
            "subcategory":"Community Association",
            "type":"Services"
        }
    ],
    "sg:phone":"+1 517 337 1305",
    "sg:postcode":"48823",
    "sg:province":"MI",
    "wof:name":"Delta Gamma Chapter",
    "wof:placetype":"venue"
},
  "geometry": {"coordinates":[-84.480722,42.740644],"type":"Point"}
}