{
  "type": "Feature",
  "properties": {
    "iso:country":"US",
    "sg:address":"18044 E 13 Mile Rd",
    "sg:city":"Roseville",
    "sg:classifiers":[
        {
            "category":"Home & Garden",
            "subcategory":"Garden Supply",
            "type":"Retail Goods"
        }
    ],
    "sg:phone":"+1 586 774 8890",
    "sg:postcode":"48066",
    "sg:province":"MI",
    "sg:tags":[
        "sprinkler"
    ],
    "wof:name":"Schick Sprinkling Systems Inc",
    "wof:placetype":"venue"
},
  "geometry": {"coordinates":[-82.93375899999999,42.524286],"type":"Point"}
}