{
  "type": "Feature",
  "properties": {
    "iso:country":"US",
    "sg:address":"29187 Autumn Ridge",
    "sg:city":"Farmington Hills",
    "sg:classifiers":[
        {
            "category":"Professional",
            "subcategory":"Management & Consulting",
            "type":"Services"
        }
    ],
    "sg:phone":"+1 248 476 0098",
    "sg:postcode":"48334",
    "sg:province":"MI",
    "wof:name":"Relise Management Inc",
    "wof:placetype":"venue"
},
  "geometry": {"coordinates":[-83.33529799999999,42.498258],"type":"Point"}
}