{
  "type": "Feature",
  "properties": {
    "iso:country":"US",
    "sg:address":"1071 Kenwood Dr",
    "sg:city":"Saginaw",
    "sg:classifiers":[
        {
            "category":"Building & Trades",
            "subcategory":"Electrical",
            "type":"Services"
        }
    ],
    "sg:phone":"+1 989 777 3867",
    "sg:postcode":"48601",
    "sg:province":"MI",
    "sg:tags":[
        "electric",
        "contractor"
    ],
    "wof:name":"Alaniz Electric",
    "wof:placetype":"venue"
},
  "geometry": {"coordinates":[-83.935772,43.372101],"type":"Point"}
}