{
  "type": "Feature",
  "properties": {
    "iso:country":"US",
    "sg:address":"5922 S Main St",
    "sg:city":"Clarkston",
    "sg:classifiers":[
        {
            "category":"Restaurant",
            "type":"Food & Drink"
        }
    ],
    "sg:menulink":"http://www.allmenus.com/mi/independence/86729-little-caesars-carry-out-clarkston/menu/",
    "sg:phone":"+1 248 625 4001",
    "sg:postcode":"48346",
    "sg:province":"MI",
    "sg:tags":[
        "american",
        "pizza"
    ],
    "wof:name":"Little Caesars Carry-Out Clarkston",
    "wof:placetype":"venue"
},
  "geometry": {"coordinates":[-83.418513,42.724963],"type":"Point"}
}