{
  "type": "Feature",
  "properties": {
    "iso:country":"US",
    "sg:address":"500 W McMillan Ave",
    "sg:city":"Newberry",
    "sg:classifiers":[
        {
            "category":"Government",
            "subcategory":"Office",
            "type":"Public Place"
        }
    ],
    "sg:phone":"+1 906 293 5144",
    "sg:postcode":"49868",
    "sg:province":"MI",
    "wof:name":"Family Independence Agency",
    "wof:placetype":"venue"
},
  "geometry": {"coordinates":[-85.516485,46.351759],"type":"Point"}
}