{
  "type": "Feature",
  "properties": {
    "iso:country":"US",
    "sg:address":"5286 E Vienna Rd",
    "sg:city":"Clio",
    "sg:classifiers":[
        {
            "category":"Social Services",
            "subcategory":"Adult Care",
            "type":"Services"
        }
    ],
    "sg:phone":"+1 810 687 2051",
    "sg:postcode":"48420",
    "sg:province":"MI",
    "sg:tags":[
        "home",
        "residential"
    ],
    "wof:name":"Gross Adult Foster Care",
    "wof:placetype":"venue"
},
  "geometry": {"coordinates":[-83.613542,43.179675],"type":"Point"}
}