{
  "type": "Feature",
  "properties": {
    "iso:country":"US",
    "sg:address":"45201 Owen St",
    "sg:city":"Belleville",
    "sg:classifiers":[
        {
            "category":"Education",
            "subcategory":"School",
            "type":"Public Place"
        }
    ],
    "sg:phone":"+1 734 697 8711",
    "sg:postcode":"48111",
    "sg:province":"MI",
    "sg:tags":[
        "high",
        "middle",
        "elementary"
    ],
    "wof:name":"South Middle School",
    "wof:placetype":"venue"
},
  "geometry": {"coordinates":[-83.456596,42.198799],"type":"Point"}
}