{
  "type": "Feature",
  "properties": {
    "iso:country":"US",
    "sg:address":"1715 Grandview Dr",
    "sg:city":"Rochester",
    "sg:classifiers":[
        {
            "category":"Health Services",
            "subcategory":"Clinic",
            "type":"Services"
        }
    ],
    "sg:phone":"+1 248 652 4160",
    "sg:postcode":"48306",
    "sg:province":"MI",
    "wof:name":"Wellness 101",
    "wof:placetype":"venue"
},
  "geometry": {"coordinates":[-83.17689799999999,42.705142],"type":"Point"}
}