{
  "type": "Feature",
  "properties": {
    "iso:country":"US",
    "sg:address":"96 Monroe Center St NW",
    "sg:city":"Grand Rapids",
    "sg:classifiers":[
        {
            "category":"Coffee & Tea",
            "type":"Food & Drink"
        }
    ],
    "sg:menulink":"http://www.allmenus.com/mi/grand-rapids/58291-local-mocha/menu/",
    "sg:phone":"+1 616 459 0082",
    "sg:postcode":"49503",
    "sg:province":"MI",
    "sg:tags":[
        "american"
    ],
    "wof:name":"Local Mocha",
    "wof:placetype":"venue"
},
  "geometry": {"coordinates":[-85.670439,42.965249],"type":"Point"}
}