{
  "type": "Feature",
  "properties": {
    "iso:country":"US",
    "sg:address":"9488 Green Rd",
    "sg:city":"Goodells",
    "sg:classifiers":[
        {
            "category":"Professional",
            "type":"Services"
        }
    ],
    "sg:phone":"+1 810 392 2739",
    "sg:postcode":"48027",
    "sg:province":"MI",
    "wof:name":"Jo Waters",
    "wof:placetype":"venue"
},
  "geometry": {"coordinates":[-82.704246,42.951199],"type":"Point"}
}