{
  "type": "Feature",
  "properties": {
    "iso:country":"US",
    "sg:address":"32270 Campbell Rd",
    "sg:city":"Madison Heights",
    "sg:classifiers":[
        {
            "category":"Sports & Exercise",
            "subcategory":"Gym",
            "type":"Entertainment"
        }
    ],
    "sg:phone":"+1 248 616 9331",
    "sg:postcode":"48071",
    "sg:province":"MI",
    "sg:tags":[
        "club",
        "health",
        "studio",
        "gymnasium"
    ],
    "wof:name":"Body In Mind",
    "wof:placetype":"venue"
},
  "geometry": {"coordinates":[-83.126064,42.529676],"type":"Point"}
}