{
  "type": "Feature",
  "properties": {
    "iso:country":"US",
    "sg:address":"7973 E Grand River Ave",
    "sg:city":"Portland",
    "sg:classifiers":[
        {
            "category":"Utilities",
            "subcategory":"Electric",
            "type":"Services"
        }
    ],
    "sg:phone":"+1 517 647 7554",
    "sg:postcode":"48875",
    "sg:province":"MI",
    "sg:tags":[
        "company"
    ],
    "sg:website":"www.homeworks.org",
    "wof:name":"Homeworks Tri-County Electric",
    "wof:placetype":"venue"
},
  "geometry": {"coordinates":[-84.918291,42.871624],"type":"Point"}
}