{
  "type": "Feature",
  "properties": {
    "iso:country":"US",
    "sg:address":"1600 Graefield Rd",
    "sg:city":"Birmingham",
    "sg:classifiers":[
        {
            "category":"Travel",
            "subcategory":"Campground",
            "type":"Entertainment"
        }
    ],
    "sg:phone":"+1 248 816 8290",
    "sg:postcode":"48009",
    "sg:province":"MI",
    "sg:tags":[
        "camp"
    ],
    "wof:name":"American Baseball Camp",
    "wof:placetype":"venue"
},
  "geometry": {"coordinates":[-83.19865900000001,42.551311],"type":"Point"}
}