{
  "type": "Feature",
  "properties": {
    "iso:country":"US",
    "sg:address":"2206 Benston Rd",
    "sg:city":"Whitehall",
    "sg:classifiers":[
        {
            "category":"Farming",
            "subcategory":"Farm",
            "type":"Manufacturing & Wholesale Goods"
        }
    ],
    "sg:phone":"+1 231 893 3564",
    "sg:postcode":"49461",
    "sg:province":"MI",
    "sg:tags":[
        "crop",
        "general"
    ],
    "wof:name":"Phillips Farms",
    "wof:placetype":"venue"
},
  "geometry": {"coordinates":[-86.295863,43.391527],"type":"Point"}
}