{
  "type": "Feature",
  "properties": {
    "iso:country":"US",
    "sg:address":"4415 Duke St",
    "sg:city":"Kalamazoo",
    "sg:classifiers":[
        {
            "category":"Health Services",
            "subcategory":"Health Practitioner",
            "type":"Services"
        }
    ],
    "sg:phone":"+1 269 349 1799",
    "sg:postcode":"49008",
    "sg:province":"MI",
    "sg:tags":[
        "psychologist"
    ],
    "wof:name":"Campbell & Brooks",
    "wof:placetype":"venue"
},
  "geometry": {"coordinates":[-85.595061,42.246814],"type":"Point"}
}