{
  "type": "Feature",
  "properties": {
    "iso:country":"US",
    "sg:address":"546 Washington St",
    "sg:city":"Chelsea",
    "sg:classifiers":[
        {
            "category":"Real Estate",
            "subcategory":"Architect",
            "type":"Services"
        }
    ],
    "sg:phone":"+1 734 475 6142",
    "sg:postcode":"48118",
    "sg:province":"MI",
    "sg:tags":[
        "architectural"
    ],
    "wof:name":"Kingscott Associates Inc",
    "wof:placetype":"venue"
},
  "geometry": {"coordinates":[-84.006483,42.313617],"type":"Point"}
}