{
  "type": "Feature",
  "properties": {
    "iso:country":"US",
    "sg:address":"2211 Presque Isle Ave",
    "sg:city":"Marquette",
    "sg:classifiers":[
        {
            "category":"Building & Trades",
            "subcategory":"Construction",
            "type":"Services"
        }
    ],
    "sg:phone":"+1 906 228 5876",
    "sg:postcode":"49855",
    "sg:province":"MI",
    "sg:tags":[
        "residential"
    ],
    "wof:name":"Ted Sura Construction Inc",
    "wof:placetype":"venue"
},
  "geometry": {"coordinates":[-87.39618,46.569855],"type":"Point"}
}