{
  "type": "Feature",
  "properties": {
    "iso:country":"US",
    "sg:address":"4511 Willford Rd",
    "sg:city":"Gladwin",
    "sg:classifiers":[
        {
            "category":"Retail",
            "subcategory":"Auto Repair",
            "type":"Services"
        }
    ],
    "sg:phone":"+1 989 426 1984",
    "sg:postcode":"48624",
    "sg:province":"MI",
    "sg:tags":[
        "body"
    ],
    "wof:name":"Grimmetts Auto Body",
    "wof:placetype":"venue"
},
  "geometry": {"coordinates":[-84.545789,43.987809],"type":"Point"}
}