{
  "type": "Feature",
  "properties": {
    "iso:country":"US",
    "sg:address":"516 W Genesee Ave",
    "sg:city":"Saginaw",
    "sg:classifiers":[
        {
            "category":"Restaurant",
            "type":"Food & Drink"
        }
    ],
    "sg:phone":"+1 989 753 1462",
    "sg:postcode":"48602",
    "sg:province":"MI",
    "wof:name":"Bringer Inn",
    "wof:placetype":"venue"
},
  "geometry": {"coordinates":[-83.95014,43.435349],"type":"Point"}
}