{
  "type": "Feature",
  "properties": {
    "iso:country":"US",
    "sg:address":"6789 Chirco Dr",
    "sg:city":"Shelby Twp",
    "sg:classifiers":[
        {
            "category":"Insurance",
            "subcategory":"Insurance Agent",
            "type":"Services"
        }
    ],
    "sg:phone":"+1 586 323 4444",
    "sg:postcode":"48316",
    "sg:province":"MI",
    "wof:name":"Chalker & Assoc-Michigan",
    "wof:placetype":"venue"
},
  "geometry": {"coordinates":[-83.044257,42.679843],"type":"Point"}
}