{
  "type": "Feature",
  "properties": {
    "iso:country":"US",
    "sg:address":"7000 N Sheldon Rd",
    "sg:city":"Canton",
    "sg:classifiers":[
        {
            "category":"Organizations",
            "subcategory":"Religious Organization",
            "type":"Services"
        }
    ],
    "sg:phone":"+1 734 459 3333",
    "sg:postcode":"48187",
    "sg:province":"MI",
    "sg:tags":[
        "lutheran",
        "church"
    ],
    "sg:website":"www.stmichael-church.org",
    "wof:name":"St Michael Lutheran Church",
    "wof:placetype":"venue"
},
  "geometry": {"coordinates":[-83.4786,42.334702],"type":"Point"}
}