{
  "type": "Feature",
  "properties": {
    "iso:country":"US",
    "sg:address":"12629 Raleigh Dr",
    "sg:city":"Sterling Heights",
    "sg:classifiers":[
        {
            "category":"Building & Trades",
            "subcategory":"Construction",
            "type":"Services"
        }
    ],
    "sg:phone":"+1 586 323 2783",
    "sg:postcode":"48313",
    "sg:province":"MI",
    "sg:tags":[
        "contractor"
    ],
    "wof:name":"Radio Pet Fence",
    "wof:placetype":"venue"
},
  "geometry": {"coordinates":[-83.001696,42.599349],"type":"Point"}
}