{
  "type": "Feature",
  "properties": {
    "iso:country":"US",
    "sg:address":"2875 E Jordan Rd",
    "sg:city":"Mount Pleasant",
    "sg:classifiers":[
        {
            "category":"Manufacturing",
            "subcategory":"Lumber",
            "type":"Manufacturing & Wholesale Goods"
        }
    ],
    "sg:phone":"+1 989 773 5693",
    "sg:postcode":"48858",
    "sg:province":"MI",
    "sg:tags":[
        "logging"
    ],
    "wof:name":"Bruce Clare",
    "wof:placetype":"venue"
},
  "geometry": {"coordinates":[-84.788085,43.655283],"type":"Point"}
}