{
  "type": "Feature",
  "properties": {
    "iso:country":"US",
    "sg:address":"910 Spring St",
    "sg:city":"Petoskey",
    "sg:classifiers":[
        {
            "category":"Shopping",
            "subcategory":"Music",
            "type":"Retail Goods"
        }
    ],
    "sg:phone":"+1 231 348 5666",
    "sg:postcode":"49770",
    "sg:province":"MI",
    "sg:tags":[
        "compact",
        "record",
        "disc",
        "tape"
    ],
    "wof:name":"Sam Goody",
    "wof:placetype":"venue"
},
  "geometry": {"coordinates":[-84.97075599999999,45.367217],"type":"Point"}
}