{
  "type": "Feature",
  "properties": {
    "iso:country":"US",
    "sg:address":"54870 N Main St",
    "sg:city":"Mattawan",
    "sg:classifiers":[
        {
            "category":"Banks & Credit Unions",
            "subcategory":"Investment Brokerage",
            "type":"Services"
        }
    ],
    "sg:phone":"+1 269 668 7526",
    "sg:postcode":"49071",
    "sg:province":"MI",
    "wof:name":"Comprehensive Investment Svc",
    "wof:placetype":"venue"
},
  "geometry": {"coordinates":[-85.78542400000001,42.220931],"type":"Point"}
}