{
  "type": "Feature",
  "properties": {
    "iso:country":"US",
    "sg:address":"101 Lucy St",
    "sg:city":"Howell",
    "sg:classifiers":[
        {
            "category":"Personal",
            "subcategory":"Beauty Salon",
            "type":"Services"
        }
    ],
    "sg:phone":"+1 517 546 7119",
    "sg:postcode":"48843",
    "sg:province":"MI",
    "sg:tags":[
        "shop"
    ],
    "wof:name":"Allison Susan M",
    "wof:placetype":"venue"
},
  "geometry": {"coordinates":[-83.91439200000001,42.601555],"type":"Point"}
}