{
  "type": "Feature",
  "properties": {
    "iso:country":"US",
    "sg:address":"1400 W Grand River Ave",
    "sg:city":"Howell",
    "sg:classifiers":[
        {
            "category":"Education",
            "subcategory":"School",
            "type":"Public Place"
        }
    ],
    "sg:phone":"+1 517 548 6398",
    "sg:postcode":"48843",
    "sg:province":"MI",
    "sg:website":"www.howellschools.com",
    "wof:name":"Little Howeller's",
    "wof:placetype":"venue"
},
  "geometry": {"coordinates":[-83.953823,42.61342],"type":"Point"}
}