{
  "type": "Feature",
  "properties": {
    "iso:country":"US",
    "sg:address":"106 Devonshire Ct",
    "sg:city":"Battle Creek",
    "sg:classifiers":[
        {
            "category":"Home & Garden",
            "subcategory":"Hardware",
            "type":"Retail Goods"
        }
    ],
    "sg:phone":"+1 269 964 6921",
    "sg:postcode":"49015",
    "sg:province":"MI",
    "sg:tags":[
        "tool"
    ],
    "wof:name":"Snap-On Tools",
    "wof:placetype":"venue"
},
  "geometry": {"coordinates":[-85.22962,42.276135],"type":"Point"}
}