{
  "type": "Feature",
  "properties": {
    "iso:country":"US",
    "sg:address":"28025 Samuel Linden Ct",
    "sg:city":"Novi",
    "sg:classifiers":[
        {
            "category":"Building & Trades",
            "subcategory":"Landscaping Services",
            "type":"Services"
        }
    ],
    "sg:phone":"+1 248 349 8555",
    "sg:postcode":"48377",
    "sg:province":"MI",
    "sg:tags":[
        "consultant",
        "lawn",
        "designer",
        "landscape",
        "contractor"
    ],
    "wof:name":"Grat Oak Landscape & Associates",
    "wof:placetype":"venue"
},
  "geometry": {"coordinates":[-83.50706099999999,42.494722],"type":"Point"}
}