{
  "type": "Feature",
  "properties": {
    "iso:country":"US",
    "sg:address":"65284 Gramer Rd",
    "sg:city":"New Haven",
    "sg:classifiers":[
        {
            "category":"Professional",
            "subcategory":"Business Services",
            "type":"Services"
        }
    ],
    "sg:phone":"+1 586 727 3636",
    "sg:postcode":"48050",
    "sg:province":"MI",
    "wof:name":"Black Dog Enterprises",
    "wof:placetype":"venue"
},
  "geometry": {"coordinates":[-82.81360599999999,42.780736],"type":"Point"}
}