{
  "type": "Feature",
  "properties": {
    "iso:country":"US",
    "sg:address":"1201 E Colby St",
    "sg:city":"Whitehall",
    "sg:classifiers":[
        {
            "category":"Real Estate",
            "subcategory":"Real Estate Operator",
            "type":"Services"
        }
    ],
    "sg:phone":"+1 231 893 3279",
    "sg:postcode":"49461",
    "sg:province":"MI",
    "sg:tags":[
        "apartment"
    ],
    "wof:name":"West Shore Apartments",
    "wof:placetype":"venue"
},
  "geometry": {"coordinates":[-86.33252899999999,43.40925],"type":"Point"}
}