{
  "type": "Feature",
  "properties": {
    "iso:country":"US",
    "sg:address":"31505 Groesbeck Hwy",
    "sg:city":"Fraser",
    "sg:classifiers":[
        {
            "category":"Personal",
            "type":"Services"
        }
    ],
    "sg:phone":"+1 586 279 1410",
    "sg:postcode":"48026",
    "sg:province":"MI",
    "sg:tags":[
        "mover"
    ],
    "sg:website":"www.fastmovesusa.com",
    "wof:name":"Fast Moves USA",
    "wof:placetype":"venue"
},
  "geometry": {"coordinates":[-82.943629,42.527937],"type":"Point"}
}