{
  "type": "Feature",
  "properties": {
    "iso:country":"US",
    "sg:address":"1203 Washington Ave",
    "sg:city":"Port Huron",
    "sg:classifiers":[
        {
            "category":"Personal",
            "subcategory":"Tattoo Parlor",
            "type":"Services"
        }
    ],
    "sg:phone":"+1 810 987 3941",
    "sg:postcode":"48060",
    "sg:province":"MI",
    "sg:tags":[
        "tattooing"
    ],
    "wof:name":"Fleshworks Tattoo",
    "wof:placetype":"venue"
},
  "geometry": {"coordinates":[-82.432873,42.988726],"type":"Point"}
}