{
  "type": "Feature",
  "properties": {
    "iso:country":"US",
    "sg:address":"6706 Premier St",
    "sg:city":"Flint",
    "sg:classifiers":[
        {
            "category":"Freight",
            "type":"Transportation"
        }
    ],
    "sg:phone":"+1 810 787 0096",
    "sg:postcode":"48505",
    "sg:province":"MI",
    "sg:tags":[
        "general"
    ],
    "wof:name":"Foss Avenue Baptist Church",
    "wof:placetype":"venue"
},
  "geometry": {"coordinates":[-83.68052299999999,43.073194],"type":"Point"}
}