{
  "type": "Feature",
  "properties": {
    "iso:country":"US",
    "sg:address":"1550 E Colby Rd",
    "sg:city":"Stanton",
    "sg:classifiers":[
        {
            "category":"Building & Trades",
            "subcategory":"Cleaning & Sanitation",
            "type":"Services"
        }
    ],
    "sg:phone":"+1 989 831 4837",
    "sg:postcode":"48888",
    "sg:province":"MI",
    "sg:tags":[
        "maintenance"
    ],
    "wof:name":"A Lot A Clean Window Serv",
    "wof:placetype":"venue"
},
  "geometry": {"coordinates":[-85.03912200000001,43.264174],"type":"Point"}
}