{
  "type": "Feature",
  "properties": {
    "iso:country":"US",
    "sg:address":"5311 Bunker Hill Rd",
    "sg:city":"Williamsburg",
    "sg:classifiers":[
        {
            "category":"Retail",
            "subcategory":"Animal Services",
            "type":"Services"
        }
    ],
    "sg:phone":"+1 231 938 9518",
    "sg:postcode":"49690",
    "sg:province":"MI",
    "sg:tags":[
        "pet",
        "boarding",
        "sitting"
    ],
    "wof:name":"Acme Creek Kennels",
    "wof:placetype":"venue"
},
  "geometry": {"coordinates":[-85.468971,44.758476],"type":"Point"}
}