{
  "type": "Feature",
  "properties": {
    "iso:country":"US",
    "sg:address":"4235 24th Ave",
    "sg:city":"Fort Gratiot",
    "sg:classifiers":[
        {
            "category":"Shopping",
            "subcategory":"Hobbies, Toys, & Games",
            "type":"Retail Goods"
        }
    ],
    "sg:phone":"+1 810 385 8886",
    "sg:postcode":"48059",
    "sg:province":"MI",
    "wof:name":"Toys R Us",
    "wof:placetype":"venue"
},
  "geometry": {"coordinates":[-82.456396,43.031357],"type":"Point"}
}