{
  "type": "Feature",
  "properties": {
    "iso:country":"US",
    "sg:address":"62657 North Ave",
    "sg:city":"Ray",
    "sg:classifiers":[
        {
            "category":"Organizations",
            "subcategory":"Religious Organization",
            "type":"Services"
        }
    ],
    "sg:phone":"+1 586 749 5286",
    "sg:postcode":"48096",
    "sg:province":"MI",
    "sg:tags":[
        "church"
    ],
    "wof:name":"St John's Lutheran Church",
    "wof:placetype":"venue"
},
  "geometry": {"coordinates":[-82.881439,42.75918],"type":"Point"}
}