{
  "type": "Feature",
  "properties": {
    "iso:country":"US",
    "sg:address":"1565 N Opdyke Rd",
    "sg:city":"Auburn Hills",
    "sg:classifiers":[
        {
            "category":"Travel",
            "subcategory":"Hotels & Motels",
            "type":"Entertainment"
        }
    ],
    "sg:phone":"+1 248 370 0200",
    "sg:postcode":"48326",
    "sg:province":"MI",
    "wof:name":"Comfort Inn",
    "wof:placetype":"venue"
},
  "geometry": {"coordinates":[-83.245869,42.664064],"type":"Point"}
}