{
  "type": "Feature",
  "properties": {
    "iso:country":"US",
    "sg:address":"13845 Elmira St",
    "sg:city":"Detroit",
    "sg:classifiers":[
        {
            "category":"Building & Trades",
            "subcategory":"Landscaping Services",
            "type":"Services"
        },
        {
            "category":"Home & Garden",
            "subcategory":"Garden Supply",
            "type":"Retail Goods"
        }
    ],
    "sg:phone":"+1 313 931 6820",
    "sg:postcode":"48227",
    "sg:province":"MI",
    "sg:tags":[
        "lawn",
        "designer",
        "consultant",
        "contractor",
        "equipment",
        "landscape"
    ],
    "wof:name":"J R Lawrence & Associates Inc",
    "wof:placetype":"venue"
},
  "geometry": {"coordinates":[-83.180713,42.371012],"type":"Point"}
}