{
  "type": "Feature",
  "properties": {
    "iso:country":"US",
    "sg:address":"12450 Warner Rd",
    "sg:city":"Concord",
    "sg:classifiers":[
        {
            "category":"Building & Trades",
            "subcategory":"Construction",
            "type":"Services"
        }
    ],
    "sg:phone":"+1 517 524 8333",
    "sg:postcode":"49237",
    "sg:province":"MI",
    "wof:name":"Schultz Steel Structures",
    "wof:placetype":"venue"
},
  "geometry": {"coordinates":[-84.642602,42.196272],"type":"Point"}
}