{
  "type": "Feature",
  "properties": {
    "iso:country":"US",
    "sg:address":"6809 W Kl Ave",
    "sg:city":"Kalamazoo",
    "sg:classifiers":[
        {
            "category":"Retail",
            "subcategory":"Auto Repair",
            "type":"Services"
        }
    ],
    "sg:phone":"+1 269 372 3205",
    "sg:postcode":"49009",
    "sg:province":"MI",
    "sg:tags":[
        "repairing",
        "automobile"
    ],
    "wof:name":"Roberts Corvette Ctr",
    "wof:placetype":"venue"
},
  "geometry": {"coordinates":[-85.68281,42.281268],"type":"Point"}
}