{
  "type": "Feature",
  "properties": {
    "iso:country":"US",
    "sg:address":"13890 Bernier Dr",
    "sg:city":"Bath",
    "sg:classifiers":[
        {
            "category":"Real Estate",
            "subcategory":"Real Estate Agent",
            "type":"Services"
        }
    ],
    "sg:phone":"+1 517 641 9978",
    "sg:postcode":"48808",
    "sg:province":"MI",
    "wof:name":"Michael Piper",
    "wof:placetype":"venue"
},
  "geometry": {"coordinates":[-84.47836599999999,42.81684],"type":"Point"}
}