{
  "type": "Feature",
  "properties": {
    "iso:country":"US",
    "sg:address":"947 Donovan St",
    "sg:city":"Vanderbilt",
    "sg:classifiers":[
        {
            "category":"Education",
            "subcategory":"School",
            "type":"Public Place"
        }
    ],
    "sg:phone":"+1 989 983 2561",
    "sg:postcode":"49795",
    "sg:province":"MI",
    "wof:name":"Vanderbilt Area Schools",
    "wof:placetype":"venue"
},
  "geometry": {"coordinates":[-84.656716,45.143483],"type":"Point"}
}