{
  "type": "Feature",
  "properties": {
    "iso:country":"US",
    "sg:address":"42005 Co Rd 352",
    "sg:city":"Decatur",
    "sg:classifiers":[
        {
            "category":"Food & Beverages",
            "subcategory":"Specialty",
            "type":"Retail Goods"
        }
    ],
    "sg:phone":"+1 269 423 8166",
    "sg:postcode":"49045",
    "sg:province":"MI",
    "sg:tags":[
        "health",
        "diet"
    ],
    "wof:name":"Kocsis Lifestyles",
    "wof:placetype":"venue"
},
  "geometry": {"coordinates":[-85.95948799999999,42.105986],"type":"Point"}
}