{
  "type": "Feature",
  "properties": {
    "iso:country":"US",
    "sg:address":"1010 N 3rd St",
    "sg:city":"Marquette",
    "sg:classifiers":[
        {
            "category":"Health Services",
            "subcategory":"Doctor",
            "type":"Services"
        }
    ],
    "sg:phone":"+1 906 228 7087",
    "sg:postcode":"49855",
    "sg:province":"MI",
    "wof:name":"Donn G Kipka DDS",
    "wof:placetype":"venue"
},
  "geometry": {"coordinates":[-87.394706,46.55351],"type":"Point"}
}