{
  "type": "Feature",
  "properties": {
    "iso:country":"US",
    "sg:address":"10191 Cook Rd",
    "sg:city":"Gaines",
    "sg:classifiers":[
        {
            "category":"Building & Trades",
            "subcategory":"Construction",
            "type":"Services"
        }
    ],
    "sg:phone":"+1 989 271 9246",
    "sg:postcode":"48436",
    "sg:province":"MI",
    "sg:tags":[
        "contractor"
    ],
    "wof:name":"Robinson Builders",
    "wof:placetype":"venue"
},
  "geometry": {"coordinates":[-83.872494,42.898206],"type":"Point"}
}