{
  "type": "Feature",
  "properties": {
    "iso:country":"US",
    "sg:address":"7996 Longview Dr",
    "sg:city":"Clarkston",
    "sg:classifiers":[
        {
            "category":"Wholesale",
            "subcategory":"Hardware",
            "type":"Manufacturing & Wholesale Goods"
        },
        {
            "category":"Building & Trades",
            "subcategory":"Plumbing",
            "type":"Services"
        }
    ],
    "sg:phone":"+1 248 394 0964",
    "sg:postcode":"48348",
    "sg:province":"MI",
    "sg:tags":[
        "furnace",
        "contractor"
    ],
    "wof:name":"Tom's Heating & Cooling Co",
    "wof:placetype":"venue"
},
  "geometry": {"coordinates":[-83.343036,42.756876],"type":"Point"}
}