{
  "type": "Feature",
  "properties": {
    "iso:country":"US",
    "sg:address":"3399 E Grand River Ave",
    "sg:city":"Howell",
    "sg:classifiers":[
        {
            "category":"Professional",
            "subcategory":"Lawyer & Legal Services",
            "type":"Services"
        }
    ],
    "sg:phone":"+1 517 546 8840",
    "sg:postcode":"48843",
    "sg:province":"MI",
    "wof:name":"Law Offices of Reader David J",
    "wof:placetype":"venue"
},
  "geometry": {"coordinates":[-83.88649100000001,42.591056],"type":"Point"}
}