{
  "type": "Feature",
  "properties": {
    "iso:country":"US",
    "sg:address":"11330 Homer Rd",
    "sg:city":"Litchfield",
    "sg:classifiers":[
        {
            "category":"Health Services",
            "subcategory":"Chiropractor",
            "type":"Services"
        }
    ],
    "sg:phone":"+1 517 542 2336",
    "sg:postcode":"49252",
    "sg:province":"MI",
    "wof:name":"Jones Chiropractic Ctr",
    "wof:placetype":"venue"
},
  "geometry": {"coordinates":[-84.79555499999999,42.071349],"type":"Point"}
}