{
  "type": "Feature",
  "properties": {
    "iso:country":"US",
    "sg:address":"27800 Southfield Rd",
    "sg:city":"Lathrup Village",
    "sg:classifiers":[
        {
            "category":"Education",
            "subcategory":"Preschool",
            "type":"Public Place"
        },
        {
            "category":"Education",
            "subcategory":"School",
            "type":"Public Place"
        }
    ],
    "sg:phone":"+1 248 557 0045",
    "sg:postcode":"48076",
    "sg:province":"MI",
    "sg:tags":[
        "elementary"
    ],
    "wof:name":"Village Early Learning Center",
    "wof:placetype":"venue"
},
  "geometry": {"coordinates":[-83.221964,42.494008],"type":"Point"}
}