{
  "type": "Feature",
  "properties": {
    "iso:country":"US",
    "sg:address":"200 W D Ave",
    "sg:city":"Kalamazoo",
    "sg:classifiers":[
        {
            "category":"Professional",
            "subcategory":"Management & Consulting",
            "type":"Services"
        }
    ],
    "sg:phone":"+1 269 345 0794",
    "sg:postcode":"49009",
    "sg:province":"MI",
    "wof:name":"Forestry Management Svcs",
    "wof:placetype":"venue"
},
  "geometry": {"coordinates":[-85.592372,42.376614],"type":"Point"}
}