{
  "type": "Feature",
  "properties": {
    "iso:country":"US",
    "sg:address":"2515 Windemere Ave",
    "sg:city":"Flint",
    "sg:classifiers":[
        {
            "category":"Wholesale",
            "subcategory":"Vending Machines",
            "type":"Manufacturing & Wholesale Goods"
        }
    ],
    "sg:phone":"+1 810 235 1730",
    "sg:postcode":"48503",
    "sg:province":"MI",
    "sg:tags":[
        "operator"
    ],
    "wof:name":"Varsity Vending",
    "wof:placetype":"venue"
},
  "geometry": {"coordinates":[-83.657123,43.01994],"type":"Point"}
}