{
  "type": "Feature",
  "properties": {
    "iso:country":"US",
    "sg:address":"12760 State Hwy 60",
    "sg:city":"Jones",
    "sg:classifiers":[
        {
            "category":"Wholesale",
            "subcategory":"Farm Supplies",
            "type":"Manufacturing & Wholesale Goods"
        }
    ],
    "sg:phone":"+1 269 244 8145",
    "sg:postcode":"49031",
    "sg:province":"MI",
    "sg:tags":[
        "buyer",
        "livestock"
    ],
    "wof:name":"Heinhold Hog Marketing",
    "wof:placetype":"venue"
},
  "geometry": {"coordinates":[-85.80403099999999,41.90452],"type":"Point"}
}