{
  "type": "Feature",
  "properties": {
    "iso:country":"US",
    "sg:address":"313 Shamrock Dr",
    "sg:city":"Niles",
    "sg:classifiers":[
        {
            "category":"Retail",
            "subcategory":"Portrait Studio",
            "type":"Services"
        }
    ],
    "sg:phone":"+1 269 683 4814",
    "sg:postcode":"49120",
    "sg:province":"MI",
    "sg:tags":[
        "photo"
    ],
    "wof:name":"Hartline Photography",
    "wof:placetype":"venue"
},
  "geometry": {"coordinates":[-86.285006,41.830187],"type":"Point"}
}