{
  "type": "Feature",
  "properties": {
    "iso:country":"US",
    "sg:address":"18276 Littlefield St",
    "sg:city":"Detroit",
    "sg:classifiers":[
        {
            "category":"Social Services",
            "subcategory":"Child Care",
            "type":"Services"
        }
    ],
    "sg:phone":"+1 313 342 9199",
    "sg:postcode":"48235",
    "sg:province":"MI",
    "sg:tags":[
        "day"
    ],
    "wof:name":"Haynes of The Loving Care",
    "wof:placetype":"venue"
},
  "geometry": {"coordinates":[-83.176615,42.425031],"type":"Point"}
}