{
  "type": "Feature",
  "properties": {
    "iso:country":"US",
    "sg:address":"24624 Brittany Ave",
    "sg:city":"Eastpointe",
    "sg:classifiers":[
        {
            "category":"Manufacturing",
            "subcategory":"Textiles",
            "type":"Manufacturing & Wholesale Goods"
        }
    ],
    "sg:phone":"+1 586 776 4718",
    "sg:postcode":"48021",
    "sg:province":"MI",
    "sg:tags":[
        "mill",
        "fabric",
        "cotton"
    ],
    "wof:name":"Creative Mobile Cnvs",
    "wof:placetype":"venue"
},
  "geometry": {"coordinates":[-82.939419,42.475966],"type":"Point"}
}