{
  "type": "Feature",
  "properties": {
    "iso:country":"US",
    "sg:address":"3061 Pine St SW",
    "sg:city":"Grandville",
    "sg:classifiers":[
        {
            "category":"Shopping",
            "subcategory":"Stationery & Office Supplies",
            "type":"Retail Goods"
        }
    ],
    "sg:phone":"+1 616 534 8400",
    "sg:postcode":"49418",
    "sg:province":"MI",
    "sg:website":"www.grandofficesupply.com",
    "wof:name":"Grand Office Supply",
    "wof:placetype":"venue"
},
  "geometry": {"coordinates":[-85.77059800000001,42.907579],"type":"Point"}
}