{
  "type": "Feature",
  "properties": {
    "iso:country":"US",
    "sg:address":"3514 Wilcox Ave",
    "sg:city":"Muskegon",
    "sg:classifiers":[
        {
            "category":"Health Services",
            "subcategory":"Doctor",
            "type":"Services"
        }
    ],
    "sg:phone":"+1 231 759 2286",
    "sg:postcode":"49441",
    "sg:province":"MI",
    "wof:name":"Phil Mulder DDS",
    "wof:placetype":"venue"
},
  "geometry": {"coordinates":[-86.32973800000001,43.220269],"type":"Point"}
}