{
  "type": "Feature",
  "properties": {
    "iso:country":"US",
    "sg:address":"2568 Dix Hwy",
    "sg:city":"Lincoln Park",
    "sg:classifiers":[
        {
            "category":"Food & Beverages",
            "subcategory":"Liquor & Beverages",
            "type":"Retail Goods"
        }
    ],
    "sg:phone":"+1 313 382 2203",
    "sg:postcode":"48146",
    "sg:province":"MI",
    "sg:tags":[
        "beer",
        "spirit",
        "wine"
    ],
    "wof:name":"Freeway Pizza Station",
    "wof:placetype":"venue"
},
  "geometry": {"coordinates":[-83.195503,42.247299],"type":"Point"}
}