{
  "type": "Feature",
  "properties": {
    "iso:country":"US",
    "sg:address":"9039 W X Y Ave",
    "sg:city":"Schoolcraft",
    "sg:classifiers":[
        {
            "category":"Real Estate",
            "subcategory":"Real Estate Operator",
            "type":"Services"
        }
    ],
    "sg:phone":"+1 269 679 3291",
    "sg:postcode":"49087",
    "sg:province":"MI",
    "sg:tags":[
        "property",
        "lessor"
    ],
    "wof:name":"Erin Brown Conroy",
    "wof:placetype":"venue"
},
  "geometry": {"coordinates":[-85.724818,42.091349],"type":"Point"}
}