{
  "type": "Feature",
  "properties": {
    "iso:country":"US",
    "sg:address":"3350 Condensery Rd",
    "sg:city":"Sheridan",
    "sg:classifiers":[
        {
            "category":"Building & Trades",
            "subcategory":"Construction",
            "type":"Services"
        }
    ],
    "sg:phone":"+1 989 261 4375",
    "sg:postcode":"48884",
    "sg:province":"MI",
    "sg:tags":[
        "housing",
        "general",
        "contractor"
    ],
    "wof:name":"Reed Construction Co",
    "wof:placetype":"venue"
},
  "geometry": {"coordinates":[-85.015705,43.206177],"type":"Point"}
}