{
  "type": "Feature",
  "properties": {
    "iso:country":"US",
    "sg:address":"23815 Industrial Park Dr",
    "sg:city":"Farmington",
    "sg:classifiers":[
        {
            "category":"Communications",
            "subcategory":"Film & Video Production",
            "type":"Services"
        }
    ],
    "sg:phone":"+1 248 474 3900",
    "sg:postcode":"48335",
    "sg:province":"MI",
    "sg:tags":[
        "process",
        "produce"
    ],
    "wof:name":"Grace & Wild Inc",
    "wof:placetype":"venue"
},
  "geometry": {"coordinates":[-83.42205800000001,42.462356],"type":"Point"}
}