{
  "type": "Feature",
  "properties": {
    "iso:country":"US",
    "sg:address":"1730 S Meridian Rd",
    "sg:city":"Midland",
    "sg:classifiers":[
        {
            "category":"Retail",
            "subcategory":"Repair Shop",
            "type":"Services"
        }
    ],
    "sg:phone":"+1 989 832 8480",
    "sg:postcode":"48640",
    "sg:province":"MI",
    "sg:tags":[
        "related"
    ],
    "wof:name":"Bovee Auto Repair",
    "wof:placetype":"venue"
},
  "geometry": {"coordinates":[-84.36970700000001,43.562169],"type":"Point"}
}