{
  "type": "Feature",
  "properties": {
    "iso:country":"US",
    "sg:address":"1411 Maryland Blvd",
    "sg:city":"Birmingham",
    "sg:classifiers":[
        {
            "category":"Professional",
            "subcategory":"Accounting & Tax Preparation",
            "type":"Services"
        }
    ],
    "sg:phone":"+1 248 647 3345",
    "sg:postcode":"48009",
    "sg:province":"MI",
    "sg:tags":[
        "bookkeeping",
        "return",
        "general"
    ],
    "wof:name":"Staley & Associates",
    "wof:placetype":"venue"
},
  "geometry": {"coordinates":[-83.22033999999999,42.533998],"type":"Point"}
}