{
  "type": "Feature",
  "properties": {
    "iso:country":"US",
    "sg:address":"23849 Groesbeck Hwy",
    "sg:city":"Warren",
    "sg:classifiers":[
        {
            "category":"Manufacturing",
            "subcategory":"Metals",
            "type":"Manufacturing & Wholesale Goods"
        }
    ],
    "sg:phone":"+1 586 771 9191",
    "sg:postcode":"48089",
    "sg:province":"MI",
    "sg:tags":[
        "plating"
    ],
    "sg:website":"www.cad-plating.com",
    "wof:name":"Cadillac Plating Corp",
    "wof:placetype":"venue"
},
  "geometry": {"coordinates":[-82.987076,42.469981],"type":"Point"}
}