{
  "type": "Feature",
  "properties": {
    "iso:country":"US",
    "sg:address":"8064 Grand River Rd",
    "sg:city":"Brighton",
    "sg:classifiers":[
        {
            "category":"Restaurant",
            "type":"Food & Drink"
        }
    ],
    "sg:phone":"+1 810 227 6999",
    "sg:postcode":"48114",
    "sg:province":"MI",
    "sg:tags":[
        "delicatessen"
    ],
    "wof:name":"Woodland Party Store",
    "wof:placetype":"venue"
},
  "geometry": {"coordinates":[-83.79289799999999,42.556749],"type":"Point"}
}