{
  "type": "Feature",
  "properties": {
    "iso:country":"US",
    "sg:address":"118 W Chicago Blvd",
    "sg:city":"Tecumseh",
    "sg:classifiers":[
        {
            "category":"Health Services",
            "subcategory":"Health Practitioner",
            "type":"Services"
        }
    ],
    "sg:phone":"+1 517 423 3963",
    "sg:postcode":"49286",
    "sg:province":"MI",
    "wof:name":"L Wesley Loesch",
    "wof:placetype":"venue"
},
  "geometry": {"coordinates":[-83.94546200000001,42.003975],"type":"Point"}
}