{
  "type": "Feature",
  "properties": {
    "iso:country":"US",
    "sg:address":"3052 Greenwood St",
    "sg:city":"Rochester",
    "sg:classifiers":[
        {
            "category":"Professional",
            "subcategory":"Business Services",
            "type":"Services"
        }
    ],
    "sg:phone":"+1 248 299 5959",
    "sg:postcode":"48309",
    "sg:province":"MI",
    "wof:name":"AAAA Certified",
    "wof:placetype":"venue"
},
  "geometry": {"coordinates":[-83.20312699999999,42.633046],"type":"Point"}
}