{
  "type": "Feature",
  "properties": {
    "iso:country":"US",
    "sg:address":"552 N Perry St",
    "sg:city":"Pontiac",
    "sg:classifiers":[
        {
            "category":"Food & Beverages",
            "subcategory":"Groceries & Convenience Stores",
            "type":"Retail Goods"
        }
    ],
    "sg:phone":"+1 248 334 4311",
    "sg:postcode":"48342",
    "sg:province":"MI",
    "wof:name":"B & M Spring Valley Market",
    "wof:placetype":"venue"
},
  "geometry": {"coordinates":[-83.285085,42.649542],"type":"Point"}
}