{
  "type": "Feature",
  "properties": {
    "iso:country":"US",
    "sg:address":"4328 Heatherstone Dr",
    "sg:city":"Waterford",
    "sg:classifiers":[
        {
            "category":"Building & Trades",
            "subcategory":"Construction",
            "type":"Services"
        }
    ],
    "sg:phone":"+1 248 674 0436",
    "sg:postcode":"48329",
    "sg:province":"MI",
    "sg:tags":[
        "house"
    ],
    "wof:name":"Nilo Construction",
    "wof:placetype":"venue"
},
  "geometry": {"coordinates":[-83.33559099999999,42.699561],"type":"Point"}
}