{
  "type": "Feature",
  "properties": {
    "iso:country":"US",
    "sg:address":"150 E Brockton Ave",
    "sg:city":"Madison Heights",
    "sg:classifiers":[
        {
            "category":"Building & Trades",
            "subcategory":"Cleaning & Sanitation",
            "type":"Services"
        }
    ],
    "sg:phone":"+1 248 543 5955",
    "sg:postcode":"48071",
    "sg:province":"MI",
    "sg:tags":[
        "carpet"
    ],
    "wof:name":"Classic Carpet Cleaning",
    "wof:placetype":"venue"
},
  "geometry": {"coordinates":[-83.103798,42.4804],"type":"Point"}
}