{
  "type": "Feature",
  "properties": {
    "iso:country":"US",
    "sg:address":"25800 Northwestern Hwy Ste 890",
    "sg:city":"Southfield",
    "sg:classifiers":[
        {
            "category":"Professional",
            "subcategory":"Lawyer & Legal Services",
            "type":"Services"
        }
    ],
    "sg:phone":"+1 248 569 4646",
    "sg:postcode":"48075",
    "sg:province":"MI",
    "sg:tags":[
        "personal",
        "injury"
    ],
    "sg:website":"www.buckfirelaw.com",
    "wof:name":"Buckfire and Buckfire, PC",
    "wof:placetype":"venue"
},
  "geometry": {"coordinates":[-83.249876,42.478991],"type":"Point"}
}