{
  "type": "Feature",
  "properties": {
    "iso:country":"US",
    "sg:address":"1127 E State St",
    "sg:city":"Cassopolis",
    "sg:classifiers":[
        {
            "category":"Government",
            "subcategory":"Office",
            "type":"Public Place"
        }
    ],
    "sg:phone":"+1 269 445 8642",
    "sg:postcode":"49031",
    "sg:province":"MI",
    "sg:tags":[
        "federal",
        "planning",
        "dev"
    ],
    "wof:name":"USDA Rural Development",
    "wof:placetype":"venue"
},
  "geometry": {"coordinates":[-86.00211,41.911625],"type":"Point"}
}