{
  "type": "Feature",
  "properties": {
    "iso:country":"US",
    "sg:address":"2019 W Nurnberg Rd",
    "sg:city":"Free Soil",
    "sg:classifiers":[
        {
            "category":"Food & Beverages",
            "subcategory":"Groceries & Convenience Stores",
            "type":"Retail Goods"
        }
    ],
    "sg:phone":"+1 231 464 5455",
    "sg:postcode":"49411",
    "sg:province":"MI",
    "wof:name":"Betty's Deer Trail",
    "wof:placetype":"venue"
},
  "geometry": {"coordinates":[-86.33081799999999,44.109114],"type":"Point"}
}