{
  "type": "Feature",
  "properties": {
    "iso:country":"US",
    "sg:address":"55025 Co Rd 380",
    "sg:city":"Grand Junction",
    "sg:classifiers":[
        {
            "category":"Wholesale",
            "subcategory":"Farm Supplies",
            "type":"Manufacturing & Wholesale Goods"
        }
    ],
    "sg:phone":"+1 269 427 8246",
    "sg:postcode":"49013",
    "sg:province":"MI",
    "wof:name":"Bangor Elevator",
    "wof:placetype":"venue"
},
  "geometry": {"coordinates":[-86.086017,42.346618],"type":"Point"}
}