{
  "type": "Feature",
  "properties": {
    "iso:country":"US",
    "sg:address":"460 Post Rd",
    "sg:city":"Buchanan",
    "sg:classifiers":[
        {
            "category":"Manufacturing",
            "subcategory":"Metals",
            "type":"Manufacturing & Wholesale Goods"
        }
    ],
    "sg:phone":"+1 269 695 5000",
    "sg:postcode":"49107",
    "sg:province":"MI",
    "sg:website":"www.metalstamp.com",
    "wof:name":"Berrien Metal Products Inc",
    "wof:placetype":"venue"
},
  "geometry": {"coordinates":[-86.381196,41.822589],"type":"Point"}
}