{
  "type": "Feature",
  "properties": {
    "iso:country":"US",
    "sg:address":"17005 Hamilton Ave",
    "sg:city":"Allen Park",
    "sg:classifiers":[
        {
            "category":"Building & Trades",
            "subcategory":"Cleaning & Sanitation",
            "type":"Services"
        }
    ],
    "sg:phone":"+1 313 278 1355",
    "sg:postcode":"48101",
    "sg:province":"MI",
    "sg:tags":[
        "maintenance"
    ],
    "wof:name":"2 Moms &A Mop Inc",
    "wof:placetype":"venue"
},
  "geometry": {"coordinates":[-83.21304000000001,42.275404],"type":"Point"}
}