{
  "type": "Feature",
  "properties": {
    "iso:country":"US",
    "sg:address":"48841 Greenwich Cir",
    "sg:city":"Canton",
    "sg:classifiers":[
        {
            "category":"Education",
            "subcategory":"Special Training",
            "type":"Public Place"
        }
    ],
    "sg:phone":"+1 734 844 7724",
    "sg:postcode":"48188",
    "sg:province":"MI",
    "sg:tags":[
        "tutoring"
    ],
    "wof:name":"Professional Inhome Tutoring the Learner Group",
    "wof:placetype":"venue"
},
  "geometry": {"coordinates":[-83.469902,42.290001],"type":"Point"}
}