{
  "type": "Feature",
  "properties": {
    "iso:country":"US",
    "sg:address":"489 W Huron Rd",
    "sg:city":"Omer",
    "sg:classifiers":[
        {
            "category":"Food & Beverages",
            "subcategory":"Groceries & Convenience Stores",
            "type":"Retail Goods"
        }
    ],
    "sg:phone":"+1 989 653 2759",
    "sg:postcode":"48749",
    "sg:province":"MI",
    "wof:name":"Mariner Market",
    "wof:placetype":"venue"
},
  "geometry": {"coordinates":[-83.82967499999999,44.047736],"type":"Point"}
}