{
  "type": "Feature",
  "properties": {
    "iso:country":"US",
    "sg:address":"361 River St",
    "sg:city":"Manistee",
    "sg:classifiers":[
        {
            "category":"Professional",
            "subcategory":"Business Services",
            "type":"Services"
        }
    ],
    "sg:phone":"+1 231 398 3047",
    "sg:postcode":"49660",
    "sg:province":"MI",
    "sg:tags":[
        "information",
        "referral"
    ],
    "wof:name":"Bayside Information Tech",
    "wof:placetype":"venue"
},
  "geometry": {"coordinates":[-86.32149200000001,44.248052],"type":"Point"}
}