{
  "type": "Feature",
  "properties": {
    "iso:country":"US",
    "sg:address":"11690 Coyle St",
    "sg:city":"Detroit",
    "sg:classifiers":[
        {
            "category":"Building & Trades",
            "subcategory":"Construction",
            "type":"Services"
        }
    ],
    "sg:phone":"+1 313 837 9233",
    "sg:postcode":"48227",
    "sg:province":"MI",
    "sg:tags":[
        "house"
    ],
    "wof:name":"Cascade Builder",
    "wof:placetype":"venue"
},
  "geometry": {"coordinates":[-83.193184,42.37437],"type":"Point"}
}