{
  "type": "Feature",
  "properties": {
    "iso:country":"US",
    "sg:address":"30555 Northwestern Hwy",
    "sg:city":"Farmington Hills",
    "sg:classifiers":[
        {
            "category":"Shopping",
            "subcategory":"Jewelry",
            "type":"Retail Goods"
        }
    ],
    "sg:phone":"+1 248 932 6800",
    "sg:postcode":"48334",
    "sg:province":"MI",
    "sg:tags":[
        "diamond"
    ],
    "wof:name":"Gala Diamonds",
    "wof:placetype":"venue"
},
  "geometry": {"coordinates":[-83.330561,42.513466],"type":"Point"}
}