{
  "type": "Feature",
  "properties": {
    "iso:country":"US",
    "sg:address":"1520 Horton Rd",
    "sg:city":"Jackson",
    "sg:classifiers":[
        {
            "category":"Health Services",
            "subcategory":"Doctor",
            "type":"Services"
        }
    ],
    "sg:phone":"+1 517 782 4101",
    "sg:postcode":"49203",
    "sg:province":"MI",
    "wof:name":"Raymond Clark DDS",
    "wof:placetype":"venue"
},
  "geometry": {"coordinates":[-84.43261099999999,42.205412],"type":"Point"}
}