{
  "type": "Feature",
  "properties": {
    "iso:country":"US",
    "sg:address":"1102 Page Ave",
    "sg:city":"Jackson",
    "sg:classifiers":[
        {
            "category":"Bars & Pubs",
            "type":"Food & Drink"
        }
    ],
    "sg:phone":"+1 517 783 4012",
    "sg:postcode":"49203",
    "sg:province":"MI",
    "sg:tags":[
        "drinking"
    ],
    "wof:name":"Barb's Star Bar",
    "wof:placetype":"venue"
},
  "geometry": {"coordinates":[-84.379598,42.242098],"type":"Point"}
}