{
  "type": "Feature",
  "properties": {
    "iso:country":"US",
    "sg:address":"650 Spruce St",
    "sg:city":"Dowagiac",
    "sg:classifiers":[
        {
            "category":"Autos & Motor Vehicles",
            "subcategory":"Fuel & Gas Station",
            "type":"Retail Goods"
        }
    ],
    "sg:phone":"+1 269 782 9368",
    "sg:postcode":"49047",
    "sg:province":"MI",
    "sg:tags":[
        "oil"
    ],
    "wof:name":"Speedway",
    "wof:placetype":"venue"
},
  "geometry": {"coordinates":[-86.11833,41.985351],"type":"Point"}
}