{
  "type": "Feature",
  "properties": {
    "iso:country":"US",
    "sg:address":"310 Mulholland St",
    "sg:city":"Ann Arbor",
    "sg:classifiers":[
        {
            "category":"Retail",
            "subcategory":"Photofinishing",
            "type":"Services"
        }
    ],
    "sg:phone":"+1 734 741 9755",
    "sg:postcode":"48103",
    "sg:province":"MI",
    "sg:tags":[
        "laboratory"
    ],
    "wof:name":"Photofind",
    "wof:placetype":"venue"
},
  "geometry": {"coordinates":[-83.757299,42.279086],"type":"Point"}
}