{
  "type": "Feature",
  "properties": {
    "iso:country":"US",
    "sg:address":"4624 Oscoda St",
    "sg:city":"Oscoda",
    "sg:classifiers":[
        {
            "category":"Building & Trades",
            "subcategory":"Construction",
            "type":"Services"
        }
    ],
    "sg:phone":"+1 989 739 8515",
    "sg:postcode":"48750",
    "sg:province":"MI",
    "sg:tags":[
        "floor",
        "laying",
        "contractor"
    ],
    "wof:name":"Marks Floor Company",
    "wof:placetype":"venue"
},
  "geometry": {"coordinates":[-83.335527,44.451582],"type":"Point"}
}