{
  "type": "Feature",
  "properties": {
    "iso:country":"US",
    "sg:address":"29935 Utica Rd",
    "sg:city":"Roseville",
    "sg:classifiers":[
        {
            "category":"Real Estate",
            "subcategory":"Real Estate Operator",
            "type":"Services"
        }
    ],
    "sg:phone":"+1 586 773 6677",
    "sg:postcode":"48066",
    "sg:province":"MI",
    "sg:tags":[
        "apartment"
    ],
    "wof:name":"Common Manor Apartments",
    "wof:placetype":"venue"
},
  "geometry": {"coordinates":[-82.940201,42.516499],"type":"Point"}
}