{
  "type": "Feature",
  "properties": {
    "iso:country":"US",
    "sg:address":"207 Hawthorne Ave",
    "sg:city":"Saint Joseph",
    "sg:classifiers":[
        {
            "category":"Real Estate",
            "subcategory":"Real Estate Operator",
            "type":"Services"
        }
    ],
    "sg:phone":"+1 269 983 7330",
    "sg:postcode":"49085",
    "sg:province":"MI",
    "sg:tags":[
        "building",
        "apartment",
        "management"
    ],
    "wof:name":"Superior Property Management",
    "wof:placetype":"venue"
},
  "geometry": {"coordinates":[-86.502892,42.072621],"type":"Point"}
}