{
  "type": "Feature",
  "properties": {
    "iso:country":"US",
    "sg:address":"140 E Liberty St",
    "sg:city":"Plymouth",
    "sg:classifiers":[
        {
            "category":"Wholesale",
            "subcategory":"Auto Parts",
            "type":"Manufacturing & Wholesale Goods"
        }
    ],
    "sg:phone":"+1 734 416 6204",
    "sg:postcode":"48170",
    "sg:province":"MI",
    "sg:tags":[
        "body",
        "equipment",
        "straightening"
    ],
    "wof:name":"Detroit Auto Body Equipment",
    "wof:placetype":"venue"
},
  "geometry": {"coordinates":[-83.45989,42.379312],"type":"Point"}
}