{
  "type": "Feature",
  "properties": {
    "iso:country":"US",
    "sg:address":"2553 Huron St",
    "sg:city":"Marquette",
    "sg:classifiers":[
        {
            "category":"Freight",
            "type":"Transportation"
        }
    ],
    "sg:phone":"+1 906 225 1955",
    "sg:postcode":"49855",
    "sg:province":"MI",
    "sg:tags":[
        "local",
        "trucking"
    ],
    "wof:name":"Joe Huron Trucking",
    "wof:placetype":"venue"
},
  "geometry": {"coordinates":[-87.443377,46.563274],"type":"Point"}
}