{
  "type": "Feature",
  "properties": {
    "iso:country":"US",
    "sg:address":"1286 64th St",
    "sg:city":"Fennville",
    "sg:classifiers":[
        {
            "category":"Travel",
            "subcategory":"Hotels & Motels",
            "type":"Entertainment"
        }
    ],
    "sg:phone":"+1 269 227 3045",
    "sg:postcode":"49408",
    "sg:province":"MI",
    "sg:tags":[
        "operation"
    ],
    "wof:name":"Glenn Country Inn The",
    "wof:placetype":"venue"
},
  "geometry": {"coordinates":[-86.168818,42.507251],"type":"Point"}
}