{
  "type": "Feature",
  "properties": {
    "iso:country":"US",
    "sg:address":"13441 Hall Rd",
    "sg:city":"Utica",
    "sg:classifiers":[
        {
            "category":"Shopping",
            "subcategory":"Clothing, Apparel, & Fashions",
            "type":"Retail Goods"
        }
    ],
    "sg:phone":"+1 586 731 6570",
    "sg:postcode":"48315",
    "sg:province":"MI",
    "sg:tags":[
        "accessory",
        "clothing",
        "women's"
    ],
    "sg:website":"fashionbug.charmingshoppes.com",
    "wof:name":"Fashion Bug",
    "wof:placetype":"venue"
},
  "geometry": {"coordinates":[-82.995003,42.627499],"type":"Point"}
}