{
  "type": "Feature",
  "properties": {
    "iso:country":"US",
    "sg:address":"217 Howard St",
    "sg:city":"Petoskey",
    "sg:classifiers":[
        {
            "category":"Home & Garden",
            "subcategory":"Home Furnishings",
            "type":"Retail Goods"
        }
    ],
    "sg:phone":"+1 231 348 7577",
    "sg:postcode":"49770",
    "sg:province":"MI",
    "sg:tags":[
        "pottery"
    ],
    "wof:name":"Funky Frog Art Studio",
    "wof:placetype":"venue"
},
  "geometry": {"coordinates":[-84.95549699999999,45.375745],"type":"Point"}
}