{
  "type": "Feature",
  "properties": {
    "iso:country":"US",
    "sg:address":"1232 10th Ave",
    "sg:city":"Menominee",
    "sg:classifiers":[
        {
            "category":"Restaurant",
            "type":"Food & Drink"
        }
    ],
    "sg:phone":"+1 906 863 6714",
    "sg:postcode":"49858",
    "sg:province":"MI",
    "wof:name":"Mc Donald's",
    "wof:placetype":"venue"
},
  "geometry": {"coordinates":[-87.617391,45.107925],"type":"Point"}
}