{
  "type": "Feature",
  "properties": {
    "iso:country":"US",
    "sg:address":"143 24th St N",
    "sg:city":"Battle Creek",
    "sg:classifiers":[
        {
            "category":"Social Services",
            "subcategory":"Child Care",
            "type":"Services"
        }
    ],
    "sg:phone":"+1 269 965 2351",
    "sg:postcode":"49015",
    "sg:province":"MI",
    "sg:tags":[
        "day"
    ],
    "wof:name":"Sugar and Spice 2",
    "wof:placetype":"venue"
},
  "geometry": {"coordinates":[-85.22412300000001,42.310095],"type":"Point"}
}