{
  "type": "Feature",
  "properties": {
    "iso:country":"US",
    "sg:address":"30 Coldbrook St NE",
    "sg:city":"Grand Rapids",
    "sg:classifiers":[
        {
            "category":"Government",
            "subcategory":"Office",
            "type":"Public Place"
        }
    ],
    "sg:phone":"+1 616 235 0303",
    "sg:postcode":"49503",
    "sg:province":"MI",
    "sg:tags":[
        "village"
    ],
    "wof:name":"Griff's Icehouse",
    "wof:placetype":"venue"
},
  "geometry": {"coordinates":[-85.66569699999999,42.982212],"type":"Point"}
}