{
  "type": "Feature",
  "properties": {
    "iso:country":"US",
    "sg:address":"309 S Walnut St",
    "sg:city":"Bangor",
    "sg:classifiers":[
        {
            "category":"Education",
            "subcategory":"School",
            "type":"Public Place"
        }
    ],
    "sg:phone":"+1 269 427 7977",
    "sg:postcode":"49013",
    "sg:province":"MI",
    "wof:name":"Bangor Alternative High School",
    "wof:placetype":"venue"
},
  "geometry": {"coordinates":[-86.111379,42.306144],"type":"Point"}
}