{
  "type": "Feature",
  "properties": {
    "iso:country":"US",
    "sg:address":"26627 Hoover Rd",
    "sg:city":"Warren",
    "sg:classifiers":[
        {
            "category":"Restaurant",
            "type":"Food & Drink"
        }
    ],
    "sg:menulink":"http://www.allmenus.com/mi/warren/146274-subway/menu/",
    "sg:phone":"+1 586 754 8205",
    "sg:postcode":"48089",
    "sg:province":"MI",
    "sg:tags":[
        "american",
        "sandwich"
    ],
    "wof:name":"Subway",
    "wof:placetype":"venue"
},
  "geometry": {"coordinates":[-83.00650400000001,42.489862],"type":"Point"}
}