{
  "type": "Feature",
  "properties": {
    "iso:country":"US",
    "sg:address":"15017 Shadowood Dr",
    "sg:city":"Monroe",
    "sg:classifiers":[
        {
            "category":"Social Services",
            "subcategory":"Child Care",
            "type":"Services"
        }
    ],
    "sg:phone":"+1 734 242 5667",
    "sg:postcode":"48161",
    "sg:province":"MI",
    "sg:tags":[
        "day",
        "provider"
    ],
    "wof:name":"A Mothers Heart",
    "wof:placetype":"venue"
},
  "geometry": {"coordinates":[-83.421785,41.886822],"type":"Point"}
}