{
  "type": "Feature",
  "properties": {
    "iso:country":"US",
    "sg:address":"3810 US Hwy 23 N",
    "sg:city":"Alpena",
    "sg:classifiers":[
        {
            "category":"Manufacturing",
            "subcategory":"Retail Goods",
            "type":"Manufacturing & Wholesale Goods"
        }
    ],
    "sg:phone":"+1 989 358 7070",
    "sg:postcode":"49707",
    "sg:province":"MI",
    "sg:tags":[
        "manufacturer"
    ],
    "sg:website":"www.pcimfg.com",
    "wof:name":"PCI",
    "wof:placetype":"venue"
},
  "geometry": {"coordinates":[-83.45289099999999,45.104946],"type":"Point"}
}