{
  "type": "Feature",
  "properties": {
    "iso:country":"US",
    "sg:address":"2302 S Dort Hwy",
    "sg:city":"Flint",
    "sg:phone":"+1 810 239 6060",
    "sg:postcode":"48507",
    "sg:province":"MI",
    "sg:website":"http://www.milexmrtrans.com",
    "wof:name":"Milex Mr Transmission",
    "wof:placetype":"venue"
},
  "geometry": {"coordinates":[-83.653998,43.001903],"type":"Point"}
}