{
  "type": "Feature",
  "properties": {
    "iso:country":"US",
    "sg:address":"595 E 16th St",
    "sg:city":"Holland",
    "sg:classifiers":[
        {
            "category":"Government",
            "subcategory":"Office",
            "type":"Public Place"
        }
    ],
    "sg:phone":"+1 616 392 4404",
    "sg:postcode":"49423",
    "sg:province":"MI",
    "sg:tags":[
        "federal",
        "human"
    ],
    "wof:name":"US Social Security Adm",
    "wof:placetype":"venue"
},
  "geometry": {"coordinates":[-86.081481,42.783273],"type":"Point"}
}