{
  "type": "Feature",
  "properties": {
    "iso:country":"US",
    "sg:address":"27622 Little Mack Ave",
    "sg:city":"Saint Clair Shores",
    "sg:classifiers":[
        {
            "category":"Banks & Credit Unions",
            "subcategory":"Financial Services",
            "type":"Services"
        }
    ],
    "sg:phone":"+1 586 498 0836",
    "sg:postcode":"48081",
    "sg:province":"MI",
    "sg:tags":[
        "broker",
        "mortgage"
    ],
    "sg:website":"www.citifinancial.com",
    "wof:name":"Citifinancial",
    "wof:placetype":"venue"
},
  "geometry": {"coordinates":[-82.907501,42.4949],"type":"Point"}
}