{
  "type": "Feature",
  "properties": {
    "iso:country":"US",
    "sg:address":"7160 40th Ave",
    "sg:city":"Hudsonville",
    "sg:classifiers":[
        {
            "category":"Building & Trades",
            "subcategory":"Electrical",
            "type":"Services"
        }
    ],
    "sg:phone":"+1 616 669 5453",
    "sg:postcode":"49426",
    "sg:province":"MI",
    "sg:tags":[
        "electrician"
    ],
    "wof:name":"Haeck Electric Inc",
    "wof:placetype":"venue"
},
  "geometry": {"coordinates":[-85.882143,42.901658],"type":"Point"}
}