{
  "type": "Feature",
  "properties": {
    "iso:country":"US",
    "sg:address":"1116 N Linden Rd",
    "sg:city":"Flint",
    "sg:classifiers":[
        {
            "category":"Health Services",
            "subcategory":"Doctor",
            "type":"Services"
        }
    ],
    "sg:phone":"+1 810 732 9888",
    "sg:postcode":"48532",
    "sg:province":"MI",
    "sg:tags":[
        "physician",
        "surgeon",
        "medical"
    ],
    "wof:name":"Flint Cardiovascular Assoc PLC",
    "wof:placetype":"venue"
},
  "geometry": {"coordinates":[-83.773009,43.017453],"type":"Point"}
}