{
  "type": "Feature",
  "properties": {
    "iso:country":"US",
    "sg:address":"2163 N Wixom Rd",
    "sg:city":"Wixom",
    "sg:classifiers":[
        {
            "category":"Shopping",
            "type":"Retail Goods"
        }
    ],
    "sg:phone":"+1 248 926 1100",
    "sg:postcode":"48393",
    "sg:province":"MI",
    "sg:tags":[
        "telephone",
        "cellular"
    ],
    "wof:name":"World Cellular",
    "wof:placetype":"venue"
},
  "geometry": {"coordinates":[-83.53768100000001,42.54901],"type":"Point"}
}