{
  "type": "Feature",
  "properties": {
    "iso:country":"US",
    "sg:address":"8875 Dixie Hwy",
    "sg:city":"Ira",
    "sg:classifiers":[
        {
            "category":"Food & Beverages",
            "subcategory":"Liquor & Beverages",
            "type":"Retail Goods"
        }
    ],
    "sg:phone":"+1 586 716 7966",
    "sg:postcode":"48023",
    "sg:province":"MI",
    "wof:name":"Fairhaven Liquor",
    "wof:placetype":"venue"
},
  "geometry": {"coordinates":[-82.65947199999999,42.680587],"type":"Point"}
}