{
  "type": "Feature",
  "properties": {
    "iso:country":"US",
    "sg:address":"14411 W 8 Mile Rd",
    "sg:city":"Detroit",
    "sg:classifiers":[
        {
            "category":"Health Services",
            "subcategory":"Doctor",
            "type":"Services"
        },
        {
            "category":"Health Services",
            "subcategory":"Dentist",
            "type":"Services"
        }
    ],
    "sg:phone":"+1 313 861 4220",
    "sg:postcode":"48235",
    "sg:province":"MI",
    "sg:tags":[
        "surgeon",
        "oral"
    ],
    "wof:name":"Echols Bobby R DDS",
    "wof:placetype":"venue"
},
  "geometry": {"coordinates":[-83.188445,42.444908],"type":"Point"}
}