{
  "type": "Feature",
  "properties": {
    "iso:country":"US",
    "sg:address":"1250 Ro Dic Don Dr",
    "sg:city":"Dewitt",
    "sg:classifiers":[
        {
            "category":"Professional",
            "subcategory":"Management & Consulting",
            "type":"Services"
        }
    ],
    "sg:phone":"+1 517 669 1096",
    "sg:postcode":"48820",
    "sg:province":"MI",
    "wof:name":"Total Management Consulting",
    "wof:placetype":"venue"
},
  "geometry": {"coordinates":[-84.54758,42.834493],"type":"Point"}
}