{
  "type": "Feature",
  "properties": {
    "iso:country":"US",
    "sg:address":"2600 Miller Ave NW",
    "sg:city":"Grand Rapids",
    "sg:classifiers":[
        {
            "category":"Professional",
            "subcategory":"Testing Lab",
            "type":"Services"
        }
    ],
    "sg:phone":"+1 616 364 9200",
    "sg:postcode":"49544",
    "sg:province":"MI",
    "sg:tags":[
        "asbestos"
    ],
    "wof:name":"AAA Lead Inspections Inc",
    "wof:placetype":"venue"
},
  "geometry": {"coordinates":[-85.685053,43.008992],"type":"Point"}
}