{
  "type": "Feature",
  "properties": {
    "iso:country":"US",
    "sg:address":"115 Union St",
    "sg:city":"Marine City",
    "sg:classifiers":[
        {
            "category":"Shopping",
            "subcategory":"Pharmacy",
            "type":"Retail Goods"
        }
    ],
    "sg:phone":"+1 810 765 1900",
    "sg:postcode":"48039",
    "sg:province":"MI",
    "wof:name":"Canadian Rx",
    "wof:placetype":"venue"
},
  "geometry": {"coordinates":[-82.493939,42.714784],"type":"Point"}
}