{
  "type": "Feature",
  "properties": {
    "iso:country":"US",
    "sg:address":"50 W Big Beaver Rd",
    "sg:city":"Troy",
    "sg:classifiers":[
        {
            "category":"Shopping",
            "subcategory":"Discount & Variety Stores",
            "type":"Retail Goods"
        }
    ],
    "sg:phone":"+1 248 619 0800",
    "sg:postcode":"48084",
    "sg:province":"MI",
    "sg:tags":[
        "merchandise",
        "general"
    ],
    "wof:name":"Tidi Products",
    "wof:placetype":"venue"
},
  "geometry": {"coordinates":[-83.14902499999999,42.562542],"type":"Point"}
}