{
  "type": "Feature",
  "properties": {
    "iso:country":"US",
    "sg:address":"11867 Greenway Dr",
    "sg:city":"Holland",
    "sg:classifiers":[
        {
            "category":"Manufacturing",
            "subcategory":"Aerospace",
            "type":"Manufacturing & Wholesale Goods"
        }
    ],
    "sg:phone":"+1 616 355 2900",
    "sg:postcode":"49424",
    "sg:province":"MI",
    "sg:tags":[
        "propeller"
    ],
    "wof:name":"Holland Propeller Inc",
    "wof:placetype":"venue"
},
  "geometry": {"coordinates":[-86.07305700000001,42.807234],"type":"Point"}
}