{
  "type": "Feature",
  "properties": {
    "iso:country":"US",
    "sg:address":"6299 Haggerty Rd",
    "sg:city":"West Bloomfield",
    "sg:classifiers":[
        {
            "category":"Restaurant",
            "type":"Food & Drink"
        }
    ],
    "sg:phone":"+1 248 669 2255",
    "sg:postcode":"48322",
    "sg:province":"MI",
    "wof:name":"J & J Tubby's",
    "wof:placetype":"venue"
},
  "geometry": {"coordinates":[-83.4384,42.546101],"type":"Point"}
}