{
  "type": "Feature",
  "properties": {
    "iso:country":"US",
    "sg:address":"9552 Chaumont Dr",
    "sg:city":"Commerce Township",
    "sg:classifiers":[
        {
            "category":"Professional",
            "subcategory":"Computer Services",
            "type":"Services"
        }
    ],
    "sg:phone":"+1 248 396 0845",
    "sg:postcode":"48382",
    "sg:province":"MI",
    "sg:tags":[
        "programing",
        "custom"
    ],
    "wof:name":"Utropicmedia LLC",
    "wof:placetype":"venue"
},
  "geometry": {"coordinates":[-83.47216,42.610366],"type":"Point"}
}