{
  "type": "Feature",
  "properties": {
    "iso:country":"US",
    "sg:address":"3610 Windmill Dr",
    "sg:city":"Waterford",
    "sg:classifiers":[
        {
            "category":"Building & Trades",
            "subcategory":"Construction",
            "type":"Services"
        }
    ],
    "sg:phone":"+1 248 673 9661",
    "sg:postcode":"48329",
    "sg:province":"MI",
    "sg:tags":[
        "dry wall",
        "contractor"
    ],
    "wof:name":"5 Star Drywall",
    "wof:placetype":"venue"
},
  "geometry": {"coordinates":[-83.38113800000001,42.690211],"type":"Point"}
}