{
  "type": "Feature",
  "properties": {
    "iso:country":"US",
    "sg:address":"415 Main St",
    "sg:city":"Saint Joseph",
    "sg:classifiers":[
        {
            "category":"Insurance",
            "subcategory":"Insurance Agent",
            "type":"Services"
        }
    ],
    "sg:phone":"+1 269 983 0633",
    "sg:postcode":"49085",
    "sg:province":"MI",
    "sg:tags":[
        "broker"
    ],
    "wof:name":"Ted Foster Associates",
    "wof:placetype":"venue"
},
  "geometry": {"coordinates":[-86.481855,42.107451],"type":"Point"}
}