{
  "type": "Feature",
  "properties": {
    "iso:country":"US",
    "sg:address":"18544 W 8 Mile Rd",
    "sg:city":"Southfield",
    "sg:classifiers":[
        {
            "category":"Health Services",
            "subcategory":"Doctor",
            "type":"Services"
        }
    ],
    "sg:phone":"+1 248 569 1729",
    "sg:postcode":"48075",
    "sg:province":"MI",
    "sg:tags":[
        "clinic"
    ],
    "sg:website":"www.gambrohealthcare.com",
    "wof:name":"Gambro Healthcare",
    "wof:placetype":"venue"
},
  "geometry": {"coordinates":[-83.22447200000001,42.444476],"type":"Point"}
}