{
  "type": "Feature",
  "properties": {
    "iso:country":"US",
    "sg:address":"45510 Kensington St",
    "sg:city":"Utica",
    "sg:classifiers":[
        {
            "category":"Real Estate",
            "subcategory":"Real Estate Operator",
            "type":"Services"
        }
    ],
    "sg:phone":"+1 586 739 7570",
    "sg:postcode":"48317",
    "sg:province":"MI",
    "sg:tags":[
        "apartment"
    ],
    "wof:name":"Village Square Co-Operative",
    "wof:placetype":"venue"
},
  "geometry": {"coordinates":[-83.014503,42.632702],"type":"Point"}
}