{
  "type": "Feature",
  "properties": {
    "iso:country":"US",
    "sg:address":"13553 Stover Rd",
    "sg:city":"Charlevoix",
    "sg:classifiers":[
        {
            "category":"Real Estate",
            "subcategory":"Real Estate Agent",
            "type":"Services"
        }
    ],
    "sg:phone":"+1 231 237 0747",
    "sg:postcode":"49720",
    "sg:province":"MI",
    "wof:name":"Parkwood Properties",
    "wof:placetype":"venue"
},
  "geometry": {"coordinates":[-85.253658,45.302099],"type":"Point"}
}