{
  "type": "Feature",
  "properties": {
    "iso:country":"US",
    "sg:address":"37742 Carson St",
    "sg:city":"Farmington Hills",
    "sg:classifiers":[
        {
            "category":"Wholesale",
            "subcategory":"Toys & Hobbies",
            "type":"Manufacturing & Wholesale Goods"
        }
    ],
    "sg:phone":"+1 248 478 7846",
    "sg:postcode":"48331",
    "sg:province":"MI",
    "sg:tags":[
        "model",
        "supply"
    ],
    "wof:name":"Campbell Model Supply Co",
    "wof:placetype":"venue"
},
  "geometry": {"coordinates":[-83.422786,42.487208],"type":"Point"}
}