{
  "type": "Feature",
  "properties": {
    "iso:country":"US",
    "sg:address":"916 Washington Ave",
    "sg:city":"Bay City",
    "sg:classifiers":[
        {
            "category":"Insurance",
            "subcategory":"Insurance Agent",
            "type":"Services"
        }
    ],
    "sg:phone":"+1 989 893 4521",
    "sg:postcode":"48708",
    "sg:province":"MI",
    "wof:name":"Equitable Life Assurance Soc",
    "wof:placetype":"venue"
},
  "geometry": {"coordinates":[-83.887427,43.599905],"type":"Point"}
}