{
  "type": "Feature",
  "properties": {
    "iso:country":"US",
    "sg:address":"14401 Frazho Rd",
    "sg:city":"Warren",
    "sg:classifiers":[
        {
            "category":"Banks & Credit Unions",
            "subcategory":"Investment Brokerage",
            "type":"Services"
        }
    ],
    "sg:phone":"+1 586 774 6840",
    "sg:postcode":"48089",
    "sg:province":"MI",
    "wof:name":"Blue Chip Investments Incorp",
    "wof:placetype":"venue"
},
  "geometry": {"coordinates":[-82.974909,42.48642],"type":"Point"}
}