{
  "type": "Feature",
  "properties": {
    "iso:country":"US",
    "sg:address":"18685 Oakfield St",
    "sg:city":"Detroit",
    "sg:classifiers":[
        {
            "category":"Banks & Credit Unions",
            "subcategory":"Financial Services",
            "type":"Services"
        }
    ],
    "sg:phone":"+1 313 387 0853",
    "sg:postcode":"48235",
    "sg:province":"MI",
    "sg:tags":[
        "investor"
    ],
    "wof:name":"Regchristi Investment Inc",
    "wof:placetype":"venue"
},
  "geometry": {"coordinates":[-83.215018,42.427799],"type":"Point"}
}