{
  "type": "Feature",
  "properties": {
    "iso:country":"US",
    "sg:address":"830 Clay St",
    "sg:city":"Niles",
    "sg:classifiers":[
        {
            "category":"Retail",
            "subcategory":"Car Wash",
            "type":"Services"
        }
    ],
    "sg:phone":"+1 269 683 7579",
    "sg:postcode":"49120",
    "sg:province":"MI",
    "sg:tags":[
        "carwash"
    ],
    "wof:name":"Haynes Power Wash",
    "wof:placetype":"venue"
},
  "geometry": {"coordinates":[-86.26746199999999,41.825285],"type":"Point"}
}