{
  "type": "Feature",
  "properties": {
    "iso:country":"US",
    "sg:address":"14265 Northland Dr",
    "sg:city":"Big Rapids",
    "sg:classifiers":[
        {
            "category":"Shopping",
            "subcategory":"Department Store",
            "type":"Retail Goods"
        }
    ],
    "sg:phone":"+1 231 592 3350",
    "sg:postcode":"49307",
    "sg:province":"MI",
    "sg:tags":[
        "shop"
    ],
    "sg:website":"www.dollargeneral.com",
    "wof:name":"Dollar General",
    "wof:placetype":"venue"
},
  "geometry": {"coordinates":[-85.48345,43.671892],"type":"Point"}
}