{
  "type": "Feature",
  "properties": {
    "iso:country":"US",
    "sg:address":"15606 Colfax Cove",
    "sg:city":"Big Rapids",
    "sg:classifiers":[
        {
            "category":"Wholesale",
            "subcategory":"Electrical",
            "type":"Manufacturing & Wholesale Goods"
        }
    ],
    "sg:phone":"+1 231 796 2978",
    "sg:postcode":"49307",
    "sg:province":"MI",
    "sg:tags":[
        "equipment",
        "lighting"
    ],
    "wof:name":"Clear Vision Sales",
    "wof:placetype":"venue"
},
  "geometry": {"coordinates":[-85.39771,43.675411],"type":"Point"}
}