{
  "type": "Feature",
  "properties": {
    "iso:country":"US",
    "sg:address":"1535 E State Fair",
    "sg:city":"Highland Park",
    "sg:classifiers":[
        {
            "category":"Health Services",
            "subcategory":"Doctor",
            "type":"Services"
        }
    ],
    "sg:phone":"+1 313 891 2740",
    "sg:postcode":"48203",
    "sg:province":"MI",
    "wof:name":"Upfall Noel H DO",
    "wof:placetype":"venue"
},
  "geometry": {"coordinates":[-83.08850099999999,42.440102],"type":"Point"}
}