{
  "type": "Feature",
  "properties": {
    "iso:country":"US",
    "sg:address":"3189 Stager Dr",
    "sg:city":"Middleville",
    "sg:classifiers":[
        {
            "category":"Building & Trades",
            "subcategory":"Construction",
            "type":"Services"
        }
    ],
    "sg:phone":"+1 269 948 2061",
    "sg:postcode":"49333",
    "sg:province":"MI",
    "sg:tags":[
        "paving",
        "asphalt",
        "contractor"
    ],
    "wof:name":"Affordable Asphalt LLC",
    "wof:placetype":"venue"
},
  "geometry": {"coordinates":[-85.35475700000001,42.691139],"type":"Point"}
}