{
  "type": "Feature",
  "properties": {
    "iso:country":"US",
    "sg:address":"1027 Church St",
    "sg:city":"Flint",
    "sg:classifiers":[
        {
            "category":"Wholesale",
            "subcategory":"Computers",
            "type":"Manufacturing & Wholesale Goods"
        },
        {
            "category":"Shopping",
            "subcategory":"Mobile Phones",
            "type":"Retail Goods"
        },
        {
            "category":"Utilities",
            "type":"Services"
        },
        {
            "category":"Professional",
            "subcategory":"Computer Services",
            "type":"Services"
        }
    ],
    "sg:phone":"+1 866 929 3278",
    "sg:postcode":"48502",
    "sg:province":"MI",
    "sg:tags":[
        "repair",
        "provider",
        "internet"
    ],
    "wof:name":"Intouch Internet & Wireless",
    "wof:placetype":"venue"
},
  "geometry": {"coordinates":[-83.688984,43.01007],"type":"Point"}
}