{
  "type": "Feature",
  "properties": {
    "iso:country":"US",
    "sg:address":"23275 Cornerstone Village Dr",
    "sg:city":"Southfield",
    "sg:classifiers":[
        {
            "category":"Building & Trades",
            "subcategory":"Construction",
            "type":"Services"
        }
    ],
    "sg:phone":"+1 248 559 1915",
    "sg:postcode":"48075",
    "sg:province":"MI",
    "sg:tags":[
        "home",
        "builder"
    ],
    "wof:name":"Tadian Homes",
    "wof:placetype":"venue"
},
  "geometry": {"coordinates":[-83.204232,42.461587],"type":"Point"}
}