{
  "type": "Feature",
  "properties": {
    "iso:country":"US",
    "sg:address":"30555 Northwestern Hwy",
    "sg:city":"Farmington Hills",
    "sg:classifiers":[
        {
            "category":"Professional",
            "subcategory":"Business Services",
            "type":"Services"
        }
    ],
    "sg:phone":"+1 248 865 9841",
    "sg:postcode":"48334",
    "sg:province":"MI",
    "sg:tags":[
        "record",
        "document"
    ],
    "wof:name":"Iron Mountain Record Mgmt Svc",
    "wof:placetype":"venue"
},
  "geometry": {"coordinates":[-83.330561,42.513466],"type":"Point"}
}