{
  "type": "Feature",
  "properties": {
    "iso:country":"US",
    "sg:address":"200 Cinama Dr",
    "sg:city":"Brighton",
    "sg:classifiers":[
        {
            "category":"Home & Garden",
            "subcategory":"Home Furnishings",
            "type":"Retail Goods"
        }
    ],
    "sg:phone":"+1 810 225 6034",
    "sg:postcode":"48116",
    "sg:province":"MI",
    "sg:tags":[
        "fireplace"
    ],
    "wof:name":"Mr Fireplace Patio & Spa",
    "wof:placetype":"venue"
},
  "geometry": {"coordinates":[-83.787494,42.54401],"type":"Point"}
}