{
  "type": "Feature",
  "properties": {
    "iso:country":"US",
    "sg:address":"29477 Cherry Hill Rd Ofc",
    "sg:city":"Inkster",
    "sg:classifiers":[
        {
            "category":"Real Estate",
            "subcategory":"Real Estate Operator",
            "type":"Services"
        }
    ],
    "sg:phone":"+1 734 595 2882",
    "sg:postcode":"48141",
    "sg:province":"MI",
    "sg:tags":[
        "apartment"
    ],
    "wof:name":"Cherry Hill Place",
    "wof:placetype":"venue"
},
  "geometry": {"coordinates":[-83.331596,42.311199],"type":"Point"}
}