{
  "type": "Feature",
  "properties": {
    "iso:country":"US",
    "sg:address":"3950 S Rochester Rd",
    "sg:city":"Rochester Hills",
    "sg:classifiers":[
        {
            "category":"Health Services",
            "subcategory":"Doctor",
            "type":"Services"
        }
    ],
    "sg:phone":"+1 248 852 0303",
    "sg:postcode":"48307",
    "sg:province":"MI",
    "wof:name":"Purohit Sudha N MD",
    "wof:placetype":"venue"
},
  "geometry": {"coordinates":[-83.130798,42.623402],"type":"Point"}
}