{
  "type": "Feature",
  "properties": {
    "iso:country":"US",
    "sg:address":"509 Nylon St",
    "sg:city":"Saginaw",
    "sg:classifiers":[
        {
            "category":"Building & Trades",
            "subcategory":"Construction",
            "type":"Services"
        }
    ],
    "sg:phone":"+1 989 752 8516",
    "sg:postcode":"48604",
    "sg:province":"MI",
    "sg:tags":[
        "house"
    ],
    "wof:name":"Jasons Subcontracting",
    "wof:placetype":"venue"
},
  "geometry": {"coordinates":[-83.949803,43.456912],"type":"Point"}
}