{
  "type": "Feature",
  "properties": {
    "iso:country":"US",
    "sg:address":"8635 N 39th St",
    "sg:city":"Augusta",
    "sg:classifiers":[
        {
            "category":"Personal",
            "subcategory":"Beauty Salon",
            "type":"Services"
        }
    ],
    "sg:phone":"+1 269 731 4127",
    "sg:postcode":"49012",
    "sg:province":"MI",
    "sg:tags":[
        "shop"
    ],
    "wof:name":"Indulgence Day Spa LLC",
    "wof:placetype":"venue"
},
  "geometry": {"coordinates":[-85.382098,42.388737],"type":"Point"}
}