{
  "type": "Feature",
  "properties": {
    "iso:country":"US",
    "sg:address":"3905 Remembrance Rd NW",
    "sg:city":"Grand Rapids",
    "sg:classifiers":[
        {
            "category":"Building & Trades",
            "subcategory":"Construction",
            "type":"Services"
        }
    ],
    "sg:phone":"+1 616 453 9176",
    "sg:postcode":"49534",
    "sg:province":"MI",
    "sg:tags":[
        "builder",
        "stair"
    ],
    "wof:name":"Stairway Concepts",
    "wof:placetype":"venue"
},
  "geometry": {"coordinates":[-85.76553699999999,42.999821],"type":"Point"}
}