{
  "type": "Feature",
  "properties": {
    "iso:country":"US",
    "sg:address":"5464 Horton St",
    "sg:city":"Flint",
    "sg:classifiers":[
        {
            "category":"Education",
            "subcategory":"School",
            "type":"Public Place"
        }
    ],
    "sg:phone":"+1 810 591 4788",
    "sg:postcode":"48505",
    "sg:province":"MI",
    "sg:tags":[
        "elementary"
    ],
    "wof:name":"Harrow Elementary School",
    "wof:placetype":"venue"
},
  "geometry": {"coordinates":[-83.685975,43.089396],"type":"Point"}
}