{
  "type": "Feature",
  "properties": {
    "iso:country":"US",
    "sg:address":"19527 Shadowoods",
    "sg:city":"Roseville",
    "sg:classifiers":[
        {
            "category":"Shopping",
            "subcategory":"Computers & Home Electronics",
            "type":"Retail Goods"
        }
    ],
    "sg:phone":"+1 586 294 4800",
    "sg:postcode":"48066",
    "sg:province":"MI",
    "sg:tags":[
        "software"
    ],
    "wof:name":"Legal Software & Secretarial",
    "wof:placetype":"venue"
},
  "geometry": {"coordinates":[-82.91943499999999,42.527693],"type":"Point"}
}