{
  "type": "Feature",
  "properties": {
    "iso:country":"US",
    "sg:address":"103 S 2nd St",
    "sg:city":"Lawrence",
    "sg:classifiers":[
        {
            "category":"Building & Trades",
            "subcategory":"Plumbing",
            "type":"Services"
        }
    ],
    "sg:phone":"+1 269 674 3640",
    "sg:postcode":"49064",
    "sg:province":"MI",
    "sg:tags":[
        "contractor"
    ],
    "wof:name":"Bowsers Plumbing",
    "wof:placetype":"venue"
},
  "geometry": {"coordinates":[-86.054125,42.219232],"type":"Point"}
}