{
  "type": "Feature",
  "properties": {
    "iso:country":"US",
    "sg:address":"501 Velvet Ave",
    "sg:city":"Portage",
    "sg:classifiers":[
        {
            "category":"Building & Trades",
            "subcategory":"Construction",
            "type":"Services"
        }
    ],
    "sg:phone":"+1 269 323 7265",
    "sg:postcode":"49002",
    "sg:province":"MI",
    "sg:tags":[
        "contractor"
    ],
    "wof:name":"C Siding Roofing",
    "wof:placetype":"venue"
},
  "geometry": {"coordinates":[-85.58273699999999,42.180363],"type":"Point"}
}