{
  "type": "Feature",
  "properties": {
    "iso:country":"US",
    "sg:address":"10 Delaware St SW",
    "sg:city":"Grand Rapids",
    "sg:classifiers":[
        {
            "category":"Real Estate",
            "subcategory":"Real Estate Operator",
            "type":"Services"
        }
    ],
    "sg:phone":"+1 616 452 3703",
    "sg:postcode":"49507",
    "sg:province":"MI",
    "sg:tags":[
        "apartment"
    ],
    "wof:name":"Delaware Manor",
    "wof:placetype":"venue"
},
  "geometry": {"coordinates":[-85.67050999999999,42.945965],"type":"Point"}
}