{
  "type": "Feature",
  "properties": {
    "iso:country":"US",
    "sg:address":"11917 Conant St",
    "sg:city":"Hamtramck",
    "sg:classifiers":[
        {
            "category":"Restaurant",
            "type":"Food & Drink"
        }
    ],
    "sg:phone":"+1 313 893 9902",
    "sg:postcode":"48212",
    "sg:province":"MI",
    "sg:tags":[
        "indian"
    ],
    "wof:name":"ZamZam Restaurant",
    "wof:placetype":"venue"
},
  "geometry": {"coordinates":[-83.055502,42.406226],"type":"Point"}
}