{
  "type": "Feature",
  "properties": {
    "iso:country":"US",
    "sg:address":"5042 Cascade Rd SE",
    "sg:city":"Grand Rapids",
    "sg:classifiers":[
        {
            "category":"Building & Trades",
            "subcategory":"Landscaping Services",
            "type":"Services"
        }
    ],
    "sg:phone":"+1 616 285 9502",
    "sg:postcode":"49546",
    "sg:province":"MI",
    "sg:tags":[
        "landscape",
        "contractor"
    ],
    "sg:website":"www.stormhillnursery.com",
    "wof:name":"Storm Hill Nursery",
    "wof:placetype":"venue"
},
  "geometry": {"coordinates":[-85.540459,42.942291],"type":"Point"}
}