{
  "type": "Feature",
  "properties": {
    "iso:country":"US",
    "sg:address":"1419 Kearney Rd",
    "sg:city":"Ann Arbor",
    "sg:classifiers":[
        {
            "category":"Professional",
            "type":"Services"
        }
    ],
    "sg:phone":"+1 734 678 0044",
    "sg:postcode":"48104",
    "sg:province":"MI",
    "sg:tags":[
        "preparation",
        "toilet",
        "g",
        "mfg"
    ],
    "wof:name":"Jacques Dubois Company",
    "wof:placetype":"venue"
},
  "geometry": {"coordinates":[-83.71511599999999,42.264971],"type":"Point"}
}