{
  "type": "Feature",
  "properties": {
    "iso:country":"US",
    "sg:address":"1430 Hendrick Rd",
    "sg:city":"Muskegon",
    "sg:classifiers":[
        {
            "category":"Organizations",
            "subcategory":"Religious Organization",
            "type":"Services"
        }
    ],
    "sg:phone":"+1 231 798 2131",
    "sg:postcode":"49441",
    "sg:province":"MI",
    "sg:tags":[
        "church"
    ],
    "wof:name":"West Shore Missionary Church",
    "wof:placetype":"venue"
},
  "geometry": {"coordinates":[-86.283477,43.162241],"type":"Point"}
}