{
  "type": "Feature",
  "properties": {
    "iso:country":"US",
    "sg:address":"7148 Glacier Point Dr",
    "sg:city":"Ypsilanti",
    "sg:classifiers":[
        {
            "category":"Professional",
            "subcategory":"Accounting & Tax Preparation",
            "type":"Services"
        }
    ],
    "sg:phone":"+1 734 480 1716",
    "sg:postcode":"48197",
    "sg:province":"MI",
    "wof:name":"Hbr",
    "wof:placetype":"venue"
},
  "geometry": {"coordinates":[-83.619462,42.18523],"type":"Point"}
}