{
  "type": "Feature",
  "properties": {
    "iso:country":"US",
    "sg:address":"7150 Dixie Hwy",
    "sg:city":"Clarkston",
    "sg:classifiers":[
        {
            "category":"Building & Trades",
            "subcategory":"Cleaning & Sanitation",
            "type":"Services"
        }
    ],
    "sg:phone":"+1 248 625 0016",
    "sg:postcode":"48346",
    "sg:province":"MI",
    "sg:tags":[
        "maid"
    ],
    "wof:name":"Molly Maid",
    "wof:placetype":"venue"
},
  "geometry": {"coordinates":[-83.433333,42.726856],"type":"Point"}
}