{
  "type": "Feature",
  "properties": {
    "iso:country":"US",
    "sg:address":"13223 S West-Bay Shore Dr",
    "sg:city":"Traverse City",
    "sg:classifiers":[
        {
            "category":"Professional",
            "type":"Services"
        }
    ],
    "sg:phone":"+1 231 941 9667",
    "sg:postcode":"49684",
    "sg:province":"MI",
    "sg:tags":[
        "establishment"
    ],
    "wof:name":"Maritime Heritage Alliance",
    "wof:placetype":"venue"
},
  "geometry": {"coordinates":[-85.637694,44.786628],"type":"Point"}
}