{
  "type": "Feature",
  "properties": {
    "iso:country":"US",
    "sg:address":"3615 S Towerline Rd",
    "sg:city":"Bridgeport",
    "sg:classifiers":[
        {
            "category":"Restaurant",
            "type":"Food & Drink"
        },
        {
            "category":"Real Estate",
            "subcategory":"Real Estate Operator",
            "type":"Services"
        }
    ],
    "sg:phone":"+1 989 777 7390",
    "sg:postcode":"48722",
    "sg:province":"MI",
    "sg:tags":[
        "building",
        "personal",
        "rooms",
        "banquet",
        "nonresidential"
    ],
    "wof:name":"Veterans Foreign Wars No 9931",
    "wof:placetype":"venue"
},
  "geometry": {"coordinates":[-83.876086,43.369318],"type":"Point"}
}