{
  "type": "Feature",
  "properties": {
    "iso:country":"US",
    "sg:address":"9620 US Hwy 23",
    "sg:city":"Ossineke",
    "sg:classifiers":[
        {
            "category":"Building & Trades",
            "subcategory":"Landscaping Services",
            "type":"Services"
        }
    ],
    "sg:phone":"+1 989 471 2874",
    "sg:postcode":"49766",
    "sg:province":"MI",
    "wof:name":"Jeffrey PS Lawn Care & Ldscpg",
    "wof:placetype":"venue"
},
  "geometry": {"coordinates":[-83.440943,44.938197],"type":"Point"}
}