{
  "type": "Feature",
  "properties": {
    "iso:country":"US",
    "sg:address":"25801 Wiseman St",
    "sg:city":"Roseville",
    "sg:classifiers":[
        {
            "category":"Insurance",
            "subcategory":"Insurance Agent",
            "type":"Services"
        }
    ],
    "sg:phone":"+1 586 445 9526",
    "sg:postcode":"48066",
    "sg:province":"MI",
    "wof:name":"Terry Mergenthaler",
    "wof:placetype":"venue"
},
  "geometry": {"coordinates":[-82.961156,42.484778],"type":"Point"}
}