{
  "type": "Feature",
  "properties": {
    "iso:country":"US",
    "sg:address":"26090 Greenfield Rd",
    "sg:city":"Oak Park",
    "sg:classifiers":[
        {
            "category":"Personal",
            "subcategory":"Barber",
            "type":"Services"
        }
    ],
    "sg:phone":"+1 248 968 9866",
    "sg:postcode":"48237",
    "sg:province":"MI",
    "wof:name":"Lincoln Center Barber Shop",
    "wof:placetype":"venue"
},
  "geometry": {"coordinates":[-83.201897,42.482101],"type":"Point"}
}