{
  "type": "Feature",
  "properties": {
    "iso:country":"US",
    "sg:address":"30481 Plymouth Rd",
    "sg:city":"Livonia",
    "sg:classifiers":[
        {
            "category":"Autos & Motor Vehicles",
            "subcategory":"Auto Supplies",
            "type":"Retail Goods"
        },
        {
            "category":"Retail",
            "subcategory":"Auto Repair",
            "type":"Services"
        }
    ],
    "sg:phone":"+1 734 261 9150",
    "sg:postcode":"48150",
    "sg:province":"MI",
    "sg:tags":[
        "tire"
    ],
    "sg:website":"www.midas.com",
    "wof:name":"Midas Auto Service Experts",
    "wof:placetype":"venue"
},
  "geometry": {"coordinates":[-83.345398,42.368801],"type":"Point"}
}