{
  "type": "Feature",
  "properties": {
    "iso:country":"US",
    "sg:address":"6450 E 12 Mile Rd",
    "sg:city":"Warren",
    "sg:classifiers":[
        {
            "category":"Retail",
            "subcategory":"Repair Shop",
            "type":"Services"
        }
    ],
    "sg:phone":"+1 586 947 2328",
    "sg:postcode":"48092",
    "sg:province":"MI",
    "sg:tags":[
        "electrical"
    ],
    "wof:name":"Pitney Bowes",
    "wof:placetype":"venue"
},
  "geometry": {"coordinates":[-83.041939,42.506009],"type":"Point"}
}