{
  "type": "Feature",
  "properties": {
    "iso:country":"US",
    "sg:address":"5144 W Briggs Rd",
    "sg:city":"Stanton",
    "sg:classifiers":[
        {
            "category":"Home & Garden",
            "subcategory":"Garden Supply",
            "type":"Retail Goods"
        }
    ],
    "sg:phone":"+1 989 831 4953",
    "sg:postcode":"48888",
    "sg:province":"MI",
    "wof:name":"Decker Tree Farm & Nursery",
    "wof:placetype":"venue"
},
  "geometry": {"coordinates":[-85.18912,43.322157],"type":"Point"}
}