{
  "type": "Feature",
  "properties": {
    "iso:country":"US",
    "sg:address":"65 W Borden Rd",
    "sg:city":"Rose City",
    "sg:classifiers":[
        {
            "category":"Retail",
            "subcategory":"Repair Shop",
            "type":"Services"
        }
    ],
    "sg:phone":"+1 989 685 3299",
    "sg:postcode":"48654",
    "sg:province":"MI",
    "sg:tags":[
        "equipment",
        "hydraulic"
    ],
    "wof:name":"Bee Independent Hydraulics",
    "wof:placetype":"venue"
},
  "geometry": {"coordinates":[-84.146069,44.464333],"type":"Point"}
}