{
  "type": "Feature",
  "properties": {
    "iso:country":"US",
    "sg:address":"21700 Greenfield Rd Ste 354",
    "sg:city":"Oak Park",
    "sg:classifiers":[
        {
            "category":"Shopping",
            "subcategory":"Jewelry",
            "type":"Retail Goods"
        }
    ],
    "sg:phone":"+1 248 968 2784",
    "sg:postcode":"48237",
    "sg:province":"MI",
    "wof:name":"Armani Jewelers Gold Spot",
    "wof:placetype":"venue"
},
  "geometry": {"coordinates":[-83.200711,42.452336],"type":"Point"}
}