{
  "type": "Feature",
  "properties": {
    "iso:country":"US",
    "sg:address":"3802 L 15",
    "sg:city":"Escanaba",
    "sg:classifiers":[
        {
            "category":"Manufacturing",
            "subcategory":"Lumber",
            "type":"Manufacturing & Wholesale Goods"
        }
    ],
    "sg:phone":"+1 906 789 9404",
    "sg:postcode":"49829",
    "sg:province":"MI",
    "sg:tags":[
        "logging"
    ],
    "wof:name":"Carlson Forest Products",
    "wof:placetype":"venue"
},
  "geometry": {"coordinates":[-87.139979,45.683223],"type":"Point"}
}