{
  "type": "Feature",
  "properties": {
    "iso:country":"US",
    "sg:address":"201 W Arch St",
    "sg:city":"Marquette",
    "sg:classifiers":[
        {
            "category":"Professional",
            "subcategory":"Printing & Photocopies",
            "type":"Services"
        }
    ],
    "sg:phone":"+1 906 228 4856",
    "sg:postcode":"49855",
    "sg:province":"MI",
    "sg:tags":[
        "photocopying",
        "r"
    ],
    "wof:name":"Answers Wordprocessing Inc",
    "wof:placetype":"venue"
},
  "geometry": {"coordinates":[-87.396918,46.546154],"type":"Point"}
}