{
  "type": "Feature",
  "properties": {
    "iso:country":"US",
    "sg:address":"385 N Lapeer Rd",
    "sg:city":"Oxford",
    "sg:classifiers":[
        {
            "category":"Health Services",
            "subcategory":"Doctor",
            "type":"Services"
        }
    ],
    "sg:phone":"+1 248 969 7350",
    "sg:postcode":"48371",
    "sg:province":"MI",
    "sg:tags":[
        "physician",
        "surgeon"
    ],
    "wof:name":"Pontiac Osteopathic Hospital",
    "wof:placetype":"venue"
},
  "geometry": {"coordinates":[-83.269565,42.830796],"type":"Point"}
}