{
  "type": "Feature",
  "properties": {
    "iso:country":"US",
    "sg:address":"106 S Main St",
    "sg:city":"Tekonsha",
    "sg:classifiers":[
        {
            "category":"Food & Beverages",
            "subcategory":"Groceries & Convenience Stores",
            "type":"Retail Goods"
        }
    ],
    "sg:phone":"+1 517 767 4780",
    "sg:postcode":"49092",
    "sg:province":"MI",
    "wof:name":"Logan #4",
    "wof:placetype":"venue"
},
  "geometry": {"coordinates":[-84.986135,42.092313],"type":"Point"}
}