{
  "type": "Feature",
  "properties": {
    "iso:country":"US",
    "sg:address":"535 Edenville Lake Rd",
    "sg:city":"Hope",
    "sg:classifiers":[
        {
            "category":"Health Services",
            "subcategory":"Health Practitioner",
            "type":"Services"
        }
    ],
    "sg:phone":"+1 989 615 6809",
    "sg:postcode":"48628",
    "sg:province":"MI",
    "sg:tags":[
        "registered",
        "nurse"
    ],
    "wof:name":"Diane Espinoza",
    "wof:placetype":"venue"
},
  "geometry": {"coordinates":[-84.347308,43.825133],"type":"Point"}
}