{
  "type": "Feature",
  "properties": {
    "iso:country":"US",
    "sg:address":"124 N Lincoln St",
    "sg:city":"Charlotte",
    "sg:classifiers":[
        {
            "category":"Retail",
            "subcategory":"Repair Shop",
            "type":"Services"
        }
    ],
    "sg:phone":"+1 517 543 4080",
    "sg:postcode":"48813",
    "sg:province":"MI",
    "sg:tags":[
        "armature",
        "rewinding",
        "merchandise"
    ],
    "wof:name":"Charlotte Electric Motors",
    "wof:placetype":"venue"
},
  "geometry": {"coordinates":[-84.845641,42.564659],"type":"Point"}
}