{
  "type": "Feature",
  "properties": {
    "iso:country":"US",
    "sg:address":"2105 W Ludington Dr",
    "sg:city":"Farwell",
    "sg:classifiers":[
        {
            "category":"Restaurant",
            "type":"Food & Drink"
        }
    ],
    "sg:phone":"+1 989 588 6651",
    "sg:postcode":"48622",
    "sg:province":"MI",
    "wof:name":"George's Country Kitchen",
    "wof:placetype":"venue"
},
  "geometry": {"coordinates":[-84.893327,43.850545],"type":"Point"}
}