{
  "type": "Feature",
  "properties": {
    "iso:country":"US",
    "sg:address":"3082 S 9th St",
    "sg:city":"Kalamazoo",
    "sg:classifiers":[
        {
            "category":"Restaurant",
            "type":"Food & Drink"
        }
    ],
    "sg:phone":"+1 269 375 4993",
    "sg:postcode":"49009",
    "sg:province":"MI",
    "sg:tags":[
        "banquet",
        "rooms"
    ],
    "wof:name":"Birches Bingo",
    "wof:placetype":"venue"
},
  "geometry": {"coordinates":[-85.677627,42.260946],"type":"Point"}
}