{
  "type": "Feature",
  "properties": {
    "iso:country":"US",
    "sg:address":"419 E High St",
    "sg:city":"Jackson",
    "sg:classifiers":[
        {
            "category":"Organizations",
            "subcategory":"Religious Organization",
            "type":"Services"
        }
    ],
    "sg:phone":"+1 517 789 6202",
    "sg:postcode":"49203",
    "sg:province":"MI",
    "sg:tags":[
        "church"
    ],
    "wof:name":"Southside Baptist Church",
    "wof:placetype":"venue"
},
  "geometry": {"coordinates":[-84.392702,42.232943],"type":"Point"}
}