{
  "type": "Feature",
  "properties": {
    "iso:country":"US",
    "sg:address":"1878 Oldtown Ave",
    "sg:city":"West Bloomfield",
    "sg:classifiers":[
        {
            "category":"Wholesale",
            "subcategory":"Construction Materials",
            "type":"Manufacturing & Wholesale Goods"
        },
        {
            "category":"Freight",
            "type":"Transportation"
        }
    ],
    "sg:phone":"+1 248 682 8220",
    "sg:postcode":"48324",
    "sg:province":"MI",
    "sg:tags":[
        "operator",
        "sand",
        "gravel",
        "local",
        "trucking"
    ],
    "wof:name":"Tom Bliss Trucking",
    "wof:placetype":"venue"
},
  "geometry": {"coordinates":[-83.378822,42.611647],"type":"Point"}
}