{
  "type": "Feature",
  "properties": {
    "iso:country":"US",
    "sg:address":"819 W Big Beaver Rd",
    "sg:city":"Troy",
    "sg:classifiers":[
        {
            "category":"Shopping",
            "subcategory":"Clothing, Apparel, & Fashions",
            "type":"Retail Goods"
        }
    ],
    "sg:phone":"+1 248 244 8480",
    "sg:postcode":"48084",
    "sg:province":"MI",
    "sg:tags":[
        "infant",
        "wear"
    ],
    "wof:name":"Carter Children Wear",
    "wof:placetype":"venue"
},
  "geometry": {"coordinates":[-83.166946,42.561765],"type":"Point"}
}