{
  "type": "Feature",
  "properties": {
    "iso:country":"US",
    "sg:address":"3028 Caniff St",
    "sg:city":"Hamtramck",
    "sg:classifiers":[
        {
            "category":"Restaurant",
            "type":"Food & Drink"
        }
    ],
    "sg:phone":"+1 313 875 2722",
    "sg:postcode":"48212",
    "sg:province":"MI",
    "wof:name":"Bosnia Specialties Restaurant",
    "wof:placetype":"venue"
},
  "geometry": {"coordinates":[-83.058302,42.400226],"type":"Point"}
}