{
  "type": "Feature",
  "properties": {
    "iso:country":"US",
    "sg:address":"4453 Clintonville Rd",
    "sg:city":"Waterford",
    "sg:classifiers":[
        {
            "category":"Organizations",
            "subcategory":"Religious Organization",
            "type":"Services"
        }
    ],
    "sg:phone":"+1 248 618 9273",
    "sg:postcode":"48329",
    "sg:province":"MI",
    "wof:name":"Mount Zion Hispanic Services",
    "wof:placetype":"venue"
},
  "geometry": {"coordinates":[-83.34889099999999,42.703557],"type":"Point"}
}