{
  "type": "Feature",
  "properties": {
    "iso:country":"US",
    "sg:address":"1110 28th St SW",
    "sg:city":"Wyoming",
    "sg:classifiers":[
        {
            "category":"Food & Beverages",
            "subcategory":"Groceries & Convenience Stores",
            "type":"Retail Goods"
        }
    ],
    "sg:phone":"+1 616 724 1940",
    "sg:postcode":"49509",
    "sg:province":"MI",
    "sg:tags":[
        "grocer"
    ],
    "wof:name":"Family Fare",
    "wof:placetype":"venue"
},
  "geometry": {"coordinates":[-85.69284,42.913314],"type":"Point"}
}