{
  "type": "Feature",
  "properties": {
    "iso:country":"US",
    "sg:address":"36801 Woodward Ave Ste 300",
    "sg:city":"Birmingham",
    "sg:classifiers":[
        {
            "category":"Building & Trades",
            "subcategory":"Construction",
            "type":"Services"
        }
    ],
    "sg:phone":"+1 248 644 4919",
    "sg:postcode":"48009",
    "sg:province":"MI",
    "sg:tags":[
        "interior",
        "design"
    ],
    "sg:website":"www.maddalenadesign.com",
    "wof:name":"Maddalena Design Ltd",
    "wof:placetype":"venue"
},
  "geometry": {"coordinates":[-83.224197,42.559799],"type":"Point"}
}