{
  "type": "Feature",
  "properties": {
    "iso:country":"US",
    "sg:address":"21335 Ecorse Rd",
    "sg:city":"Taylor",
    "sg:classifiers":[
        {
            "category":"Restaurant",
            "type":"Food & Drink"
        }
    ],
    "sg:phone":"+1 313 291 4164",
    "sg:postcode":"48180",
    "sg:province":"MI",
    "wof:name":"Original Philips Restaurant the",
    "wof:placetype":"venue"
},
  "geometry": {"coordinates":[-83.245598,42.256001],"type":"Point"}
}