{
  "type": "Feature",
  "properties": {
    "iso:country":"US",
    "sg:address":"1951 Hess Rd",
    "sg:city":"Galien",
    "sg:classifiers":[
        {
            "category":"Building & Trades",
            "subcategory":"Construction",
            "type":"Services"
        }
    ],
    "sg:phone":"+1 269 545 8108",
    "sg:postcode":"49113",
    "sg:province":"MI",
    "sg:tags":[
        "hanging",
        "contractor"
    ],
    "wof:name":"Jeff Mech Painting",
    "wof:placetype":"venue"
},
  "geometry": {"coordinates":[-86.49894999999999,41.812653],"type":"Point"}
}