{
  "type": "Feature",
  "properties": {
    "iso:country":"US",
    "sg:address":"3225 E G Ave",
    "sg:city":"Kalamazoo",
    "sg:classifiers":[
        {
            "category":"Insurance",
            "subcategory":"Insurance Agent",
            "type":"Services"
        }
    ],
    "sg:phone":"+1 269 342 0744",
    "sg:postcode":"49004",
    "sg:province":"MI",
    "wof:name":"Robert Essar Insurance",
    "wof:placetype":"venue"
},
  "geometry": {"coordinates":[-85.537128,42.332845],"type":"Point"}
}