{
  "type": "Feature",
  "properties": {
    "iso:country":"US",
    "sg:address":"6230 N McKinley Rd",
    "sg:city":"Flushing",
    "sg:classifiers":[
        {
            "category":"Utilities",
            "subcategory":"Water",
            "type":"Services"
        }
    ],
    "sg:phone":"+1 810 659 7218",
    "sg:postcode":"48433",
    "sg:province":"MI",
    "sg:tags":[
        "professional",
        "operation",
        "maintenance"
    ],
    "wof:name":"O & M Concepts Ltd",
    "wof:placetype":"venue"
},
  "geometry": {"coordinates":[-83.853021,43.095645],"type":"Point"}
}