{
  "type": "Feature",
  "properties": {
    "iso:country":"US",
    "sg:address":"6230 N Irons Rd",
    "sg:city":"Irons",
    "sg:classifiers":[
        {
            "category":"Travel",
            "subcategory":"Hotels & Motels",
            "type":"Entertainment"
        }
    ],
    "sg:phone":"+1 231 745 2111",
    "sg:postcode":"49644",
    "sg:province":"MI",
    "sg:tags":[
        "operation"
    ],
    "wof:name":"Day Star Motel",
    "wof:placetype":"venue"
},
  "geometry": {"coordinates":[-85.898815,44.077472],"type":"Point"}
}