{
  "type": "Feature",
  "properties": {
    "iso:country":"US",
    "sg:address":"4600 136th Ave",
    "sg:city":"Holland",
    "sg:classifiers":[
        {
            "category":"Retail",
            "subcategory":"Auto Repair",
            "type":"Services"
        }
    ],
    "sg:phone":"+1 616 399 6522",
    "sg:postcode":"49424",
    "sg:province":"MI",
    "sg:tags":[
        "automotive",
        "general"
    ],
    "wof:name":"Beechwood Automotive",
    "wof:placetype":"venue"
},
  "geometry": {"coordinates":[-86.118431,42.854447],"type":"Point"}
}