{
  "type": "Feature",
  "properties": {
    "iso:country":"US",
    "sg:address":"2604 Freeman",
    "sg:city":"Lake Orion",
    "sg:classifiers":[
        {
            "category":"Banks & Credit Unions",
            "subcategory":"Investment Brokerage",
            "type":"Services"
        }
    ],
    "sg:phone":"+1 248 393 2810",
    "sg:postcode":"48360",
    "sg:province":"MI",
    "sg:tags":[
        "advisory",
        "financial"
    ],
    "wof:name":"Hazen Associates",
    "wof:placetype":"venue"
},
  "geometry": {"coordinates":[-83.238146,42.744927],"type":"Point"}
}