{
  "type": "Feature",
  "properties": {
    "iso:country":"US",
    "sg:address":"10151 Gainey Rd",
    "sg:city":"Holly",
    "sg:classifiers":[
        {
            "category":"Professional",
            "subcategory":"Business Services",
            "type":"Services"
        }
    ],
    "sg:phone":"+1 810 694 6000",
    "sg:postcode":"48442",
    "sg:province":"MI",
    "sg:tags":[
        "process",
        "server"
    ],
    "sg:website":"www.shinsho.com",
    "wof:name":"Grand Blanc Processing",
    "wof:placetype":"venue"
},
  "geometry": {"coordinates":[-83.611796,42.884608],"type":"Point"}
}