{
  "type": "Feature",
  "properties": {
    "iso:country":"US",
    "sg:address":"16300 N Park Dr",
    "sg:city":"Southfield",
    "sg:classifiers":[
        {
            "category":"Shopping",
            "subcategory":"Catalog Store",
            "type":"Retail Goods"
        }
    ],
    "sg:phone":"+1 248 443 0376",
    "sg:postcode":"48075",
    "sg:province":"MI",
    "sg:tags":[
        "mail",
        "order"
    ],
    "wof:name":"Bob's Cupboard",
    "wof:placetype":"venue"
},
  "geometry": {"coordinates":[-83.21033,42.45549],"type":"Point"}
}