{
  "type": "Feature",
  "properties": {
    "iso:country":"US",
    "sg:address":"29900 Franklin Rd",
    "sg:city":"Southfield",
    "sg:classifiers":[
        {
            "category":"Real Estate",
            "subcategory":"Real Estate Operator",
            "type":"Services"
        }
    ],
    "sg:phone":"+1 248 350 1296",
    "sg:postcode":"48034",
    "sg:province":"MI",
    "sg:tags":[
        "apartment"
    ],
    "wof:name":"Weatherstone Townhouses North",
    "wof:placetype":"venue"
},
  "geometry": {"coordinates":[-83.309814,42.506043],"type":"Point"}
}