{
  "type": "Feature",
  "properties": {
    "iso:country":"US",
    "sg:address":"14025 Rutland St",
    "sg:city":"Detroit",
    "sg:classifiers":[
        {
            "category":"Sports & Exercise",
            "subcategory":"Race Track",
            "type":"Entertainment"
        }
    ],
    "sg:phone":"+1 313 836 2307",
    "sg:postcode":"48227",
    "sg:province":"MI",
    "sg:tags":[
        "operation",
        "racing",
        "or"
    ],
    "wof:name":"R P 1 Motorsports",
    "wof:placetype":"venue"
},
  "geometry": {"coordinates":[-83.21336700000001,42.387664],"type":"Point"}
}