{
  "type": "Feature",
  "properties": {
    "iso:country":"US",
    "sg:address":"8496 Cedar Run Rd",
    "sg:city":"Traverse City",
    "sg:classifiers":[
        {
            "category":"Insurance",
            "subcategory":"Insurance Agent",
            "type":"Services"
        }
    ],
    "sg:phone":"+1 231 946 5272",
    "sg:postcode":"49684",
    "sg:province":"MI",
    "sg:tags":[
        "processing"
    ],
    "wof:name":"Statscript",
    "wof:placetype":"venue"
},
  "geometry": {"coordinates":[-85.747905,44.76039],"type":"Point"}
}