{
  "type": "Feature",
  "properties": {
    "iso:country":"US",
    "sg:address":"14520 Sharon Valley Rd",
    "sg:city":"Grass Lake",
    "sg:classifiers":[
        {
            "category":"Government",
            "subcategory":"Office",
            "type":"Public Place"
        }
    ],
    "sg:phone":"+1 734 428 8035",
    "sg:postcode":"49240",
    "sg:province":"MI",
    "sg:tags":[
        "conservation"
    ],
    "wof:name":"Sharonville Shooting Range",
    "wof:placetype":"venue"
},
  "geometry": {"coordinates":[-84.143089,42.172185],"type":"Point"}
}