{
  "type": "Feature",
  "properties": {
    "iso:country":"US",
    "sg:address":"1322 S Coldwater Rd",
    "sg:city":"Mount Pleasant",
    "sg:classifiers":[
        {
            "category":"Farming",
            "subcategory":"Livestock Farm",
            "type":"Manufacturing & Wholesale Goods"
        }
    ],
    "sg:phone":"+1 989 644 2803",
    "sg:postcode":"48858",
    "sg:province":"MI",
    "sg:tags":[
        "beef",
        "feedlot",
        "cattle"
    ],
    "wof:name":"Reckers Limousine",
    "wof:placetype":"venue"
},
  "geometry": {"coordinates":[-84.98759,43.620491],"type":"Point"}
}