{
  "type": "Feature",
  "properties": {
    "iso:country":"US",
    "sg:address":"6301 Stadium Dr",
    "sg:city":"Kalamazoo",
    "sg:classifiers":[
        {
            "category":"Health Services",
            "subcategory":"Doctor",
            "type":"Services"
        }
    ],
    "sg:phone":"+1 269 375 1060",
    "sg:postcode":"49009",
    "sg:province":"MI",
    "wof:name":"Donald E Daenzer DDS",
    "wof:placetype":"venue"
},
  "geometry": {"coordinates":[-85.67227800000001,42.26239],"type":"Point"}
}