{
  "type": "Feature",
  "properties": {
    "iso:country":"US",
    "sg:address":"68574 56th St",
    "sg:city":"Lawrence",
    "sg:classifiers":[
        {
            "category":"Farming",
            "subcategory":"Farm",
            "type":"Manufacturing & Wholesale Goods"
        }
    ],
    "sg:phone":"+1 269 674 3334",
    "sg:postcode":"49064",
    "sg:province":"MI",
    "sg:tags":[
        "crop",
        "general"
    ],
    "wof:name":"Ronald Kurzmann",
    "wof:placetype":"venue"
},
  "geometry": {"coordinates":[-86.090005,42.168347],"type":"Point"}
}