{
  "type": "Feature",
  "properties": {
    "iso:country":"US",
    "sg:address":"1620 Gladstone St",
    "sg:city":"Detroit",
    "sg:classifiers":[
        {
            "category":"Real Estate",
            "subcategory":"Real Estate Operator",
            "type":"Services"
        }
    ],
    "sg:phone":"+1 313 758 0910",
    "sg:postcode":"48206",
    "sg:province":"MI",
    "sg:tags":[
        "apartment"
    ],
    "wof:name":"Park Square Apartments",
    "wof:placetype":"venue"
},
  "geometry": {"coordinates":[-83.096001,42.374599],"type":"Point"}
}