{
  "type": "Feature",
  "properties": {
    "iso:country":"US",
    "sg:address":"624 E State St",
    "sg:city":"Cheboygan",
    "sg:classifiers":[
        {
            "category":"Autos & Motor Vehicles",
            "subcategory":"Auto Supplies",
            "type":"Retail Goods"
        }
    ],
    "sg:phone":"+1 231 627 2453",
    "sg:postcode":"49721",
    "sg:province":"MI",
    "sg:tags":[
        "tire"
    ],
    "wof:name":"Manning's Northern Tire Svc",
    "wof:placetype":"venue"
},
  "geometry": {"coordinates":[-84.466465,45.643071],"type":"Point"}
}