{
  "type": "Feature",
  "properties": {
    "iso:country":"US",
    "sg:address":"2429 Welch Blvd",
    "sg:city":"Flint",
    "sg:classifiers":[
        {
            "category":"Personal",
            "subcategory":"Beauty Salon",
            "type":"Services"
        }
    ],
    "sg:phone":"+1 810 235 5037",
    "sg:postcode":"48504",
    "sg:province":"MI",
    "wof:name":"Designers Essentials",
    "wof:placetype":"venue"
},
  "geometry": {"coordinates":[-83.730977,43.037326],"type":"Point"}
}