{
  "type": "Feature",
  "properties": {
    "iso:country":"US",
    "sg:address":"2625 Benston Rd",
    "sg:city":"Whitehall",
    "sg:classifiers":[
        {
            "category":"Building & Trades",
            "subcategory":"Construction",
            "type":"Services"
        }
    ],
    "sg:phone":"+1 231 893 5203",
    "sg:postcode":"49461",
    "sg:province":"MI",
    "sg:tags":[
        "roofing",
        "contractor"
    ],
    "wof:name":"Harris Brothers Construction",
    "wof:placetype":"venue"
},
  "geometry": {"coordinates":[-86.31006600000001,43.391776],"type":"Point"}
}