{
  "type": "Feature",
  "properties": {
    "iso:country":"US",
    "sg:address":"15400 Grand River Ave",
    "sg:city":"Detroit",
    "sg:classifiers":[
        {
            "category":"Health Services",
            "subcategory":"Dentist",
            "type":"Services"
        }
    ],
    "sg:phone":"+1 313 837 3000",
    "sg:postcode":"48227",
    "sg:province":"MI",
    "wof:name":"Tower Dental",
    "wof:placetype":"venue"
},
  "geometry": {"coordinates":[-83.19740299999999,42.3923],"type":"Point"}
}