{
  "type": "Feature",
  "properties": {
    "iso:country":"US",
    "sg:address":"17431 Allen Rd",
    "sg:city":"Melvindale",
    "sg:classifiers":[
        {
            "category":"Organizations",
            "subcategory":"Religious Organization",
            "type":"Services"
        }
    ],
    "sg:phone":"+1 313 383 4506",
    "sg:postcode":"48122",
    "sg:province":"MI",
    "wof:name":"Conerstone Baptst Church Melvn",
    "wof:placetype":"venue"
},
  "geometry": {"coordinates":[-83.179616,42.292279],"type":"Point"}
}