{
  "type": "Feature",
  "properties": {
    "iso:country":"US",
    "sg:address":"701 16th Ave",
    "sg:city":"Norway",
    "sg:classifiers":[
        {
            "category":"Home & Garden",
            "subcategory":"Garden Supply",
            "type":"Retail Goods"
        }
    ],
    "sg:phone":"+1 906 563 8976",
    "sg:postcode":"49870",
    "sg:province":"MI",
    "sg:tags":[
        "engine"
    ],
    "wof:name":"Vivio's Small Engine",
    "wof:placetype":"venue"
},
  "geometry": {"coordinates":[-87.902952,45.796903],"type":"Point"}
}