{
  "type": "Feature",
  "properties": {
    "iso:country":"US",
    "sg:address":"7240 State Rd",
    "sg:city":"Millington",
    "sg:classifiers":[
        {
            "category":"Manufacturing",
            "subcategory":"Metals",
            "type":"Manufacturing & Wholesale Goods"
        }
    ],
    "sg:phone":"+1 989 871 5582",
    "sg:postcode":"48746",
    "sg:province":"MI",
    "sg:tags":[
        "steel"
    ],
    "wof:name":"Loudon Steel Transportation",
    "wof:placetype":"venue"
},
  "geometry": {"coordinates":[-83.549404,43.31529],"type":"Point"}
}