{
  "type": "Feature",
  "properties": {
    "iso:country":"US",
    "sg:address":"12226 Ithaca Rd",
    "sg:city":"St Charles",
    "sg:classifiers":[
        {
            "category":"Real Estate",
            "subcategory":"Real Estate Operator",
            "type":"Services"
        }
    ],
    "sg:phone":"+1 989 865 9256",
    "sg:postcode":"48655",
    "sg:province":"MI",
    "sg:tags":[
        "apartment"
    ],
    "wof:name":"Summer Ridge Apartments",
    "wof:placetype":"venue"
},
  "geometry": {"coordinates":[-84.15741,43.29013],"type":"Point"}
}