{
  "type": "Feature",
  "properties": {
    "iso:country":"US",
    "sg:address":"54128 Co Rd 388",
    "sg:city":"Grand Junction",
    "sg:classifiers":[
        {
            "category":"Organizations",
            "subcategory":"Religious Organization",
            "type":"Services"
        }
    ],
    "sg:phone":"+1 269 434 6117",
    "sg:postcode":"49056",
    "sg:province":"MI",
    "sg:tags":[
        "church"
    ],
    "wof:name":"First Congregational Church",
    "wof:placetype":"venue"
},
  "geometry": {"coordinates":[-86.072914,42.404482],"type":"Point"}
}