{
  "type": "Feature",
  "properties": {
    "iso:country":"US",
    "sg:address":"415 S Superior St",
    "sg:city":"Albion",
    "sg:classifiers":[
        {
            "category":"Education",
            "subcategory":"Library",
            "type":"Public Place"
        }
    ],
    "sg:phone":"+1 517 629 9469",
    "sg:postcode":"49224",
    "sg:province":"MI",
    "wof:name":"Woodlands Library Co-Op",
    "wof:placetype":"venue"
},
  "geometry": {"coordinates":[-84.753113,42.242871],"type":"Point"}
}