{
  "type": "Feature",
  "properties": {
    "iso:country":"US",
    "sg:address":"16849 Kercheval Ave",
    "sg:city":"Grosse Pointe Park",
    "sg:classifiers":[
        {
            "category":"Shopping",
            "subcategory":"Pets & Pet Supplies",
            "type":"Retail Goods"
        }
    ],
    "sg:phone":"+1 313 343 0443",
    "sg:postcode":"48230",
    "sg:province":"MI",
    "sg:tags":[
        "store"
    ],
    "sg:website":"www.barkerygp.com",
    "wof:name":"Barkery the",
    "wof:placetype":"venue"
},
  "geometry": {"coordinates":[-82.91833699999999,42.389514],"type":"Point"}
}