{
  "type": "Feature",
  "properties": {
    "iso:country":"US",
    "sg:address":"10593 W Jefferson Ave Ofc",
    "sg:city":"River Rouge",
    "sg:classifiers":[
        {
            "category":"Real Estate",
            "subcategory":"Real Estate Operator",
            "type":"Services"
        }
    ],
    "sg:phone":"+1 313 843 8299",
    "sg:postcode":"48218",
    "sg:province":"MI",
    "sg:tags":[
        "apartment"
    ],
    "wof:name":"Reno Building",
    "wof:placetype":"venue"
},
  "geometry": {"coordinates":[-83.1343,42.273201],"type":"Point"}
}