{
  "type": "Feature",
  "properties": {
    "iso:country":"US",
    "sg:address":"3371 York Rd",
    "sg:city":"Rochester",
    "sg:classifiers":[
        {
            "category":"Social Services",
            "subcategory":"Child Care",
            "type":"Services"
        }
    ],
    "sg:phone":"+1 248 853 7475",
    "sg:postcode":"48309",
    "sg:province":"MI",
    "sg:tags":[
        "day"
    ],
    "wof:name":"Lori M Stevens",
    "wof:placetype":"venue"
},
  "geometry": {"coordinates":[-83.20432,42.627553],"type":"Point"}
}