{
  "type": "Feature",
  "properties": {
    "iso:country":"US",
    "sg:address":"4104 Bonisteel Dr",
    "sg:city":"Fort Gratiot",
    "sg:classifiers":[
        {
            "category":"Building & Trades",
            "subcategory":"Construction",
            "type":"Services"
        }
    ],
    "sg:phone":"+1 810 385 9377",
    "sg:postcode":"48059",
    "sg:province":"MI",
    "sg:tags":[
        "general",
        "contractor"
    ],
    "wof:name":"Woolman & Sons Construction",
    "wof:placetype":"venue"
},
  "geometry": {"coordinates":[-82.468372,43.027507],"type":"Point"}
}