{
  "type": "Feature",
  "properties": {
    "iso:country":"US",
    "sg:address":"43424 N I- 94 Svc Rd",
    "sg:city":"Belleville",
    "sg:classifiers":[
        {
            "category":"Retail",
            "subcategory":"Repair Shop",
            "type":"Services"
        }
    ],
    "sg:phone":"+1 734 699 4220",
    "sg:postcode":"48111",
    "sg:province":"MI",
    "sg:tags":[
        "reupholstery"
    ],
    "wof:name":"Fanchers Opholstry Inc",
    "wof:placetype":"venue"
},
  "geometry": {"coordinates":[-83.47506799999999,42.220466],"type":"Point"}
}