{
  "type": "Feature",
  "properties": {
    "iso:country":"US",
    "sg:address":"20224 Eureka Rd",
    "sg:city":"Taylor",
    "sg:classifiers":[
        {
            "category":"Retail",
            "subcategory":"Veterinary Services",
            "type":"Services"
        },
        {
            "category":"Retail",
            "subcategory":"Pet Boarding",
            "type":"Services"
        }
    ],
    "sg:phone":"+1 734 720 0021",
    "sg:postcode":"48180",
    "sg:province":"MI",
    "sg:tags":[
        "veterinarian",
        "boarding/pet",
        "sitting"
    ],
    "sg:website":"www.vcasouthland.com",
    "wof:name":"VCA Southland Animal Hospital",
    "wof:placetype":"venue"
},
  "geometry": {"coordinates":[-83.232018,42.198916],"type":"Point"}
}