{
  "type": "Feature",
  "properties": {
    "iso:country":"US",
    "sg:address":"3350 N Rochester Rd",
    "sg:city":"Rochester Hills",
    "sg:classifiers":[
        {
            "category":"Shopping",
            "subcategory":"Bicycles & Sporting Goods",
            "type":"Retail Goods"
        }
    ],
    "sg:phone":"+1 248 852 6664",
    "sg:postcode":"48306",
    "sg:province":"MI",
    "sg:tags":[
        "equipment",
        "exercise"
    ],
    "wof:name":"American Home Fitness",
    "wof:placetype":"venue"
},
  "geometry": {"coordinates":[-83.137038,42.752954],"type":"Point"}
}