{
  "type": "Feature",
  "properties": {
    "iso:country":"US",
    "sg:address":"1466 Michigan St NE",
    "sg:city":"Grand Rapids",
    "sg:classifiers":[
        {
            "category":"Restaurant",
            "type":"Food & Drink"
        }
    ],
    "sg:menulink":"http://www.allmenus.com/mi/grand-rapids/59554-new-beginnings/menu/",
    "sg:phone":"+1 616 774 8772",
    "sg:postcode":"49503",
    "sg:province":"MI",
    "sg:tags":[
        "american"
    ],
    "wof:name":"New Beginnings",
    "wof:placetype":"venue"
},
  "geometry": {"coordinates":[-85.632588,42.969964],"type":"Point"}
}