{
  "type": "Feature",
  "properties": {
    "iso:country":"US",
    "sg:address":"518 Mark Dr",
    "sg:city":"Flushing",
    "sg:classifiers":[
        {
            "category":"Shopping",
            "subcategory":"Bicycles & Sporting Goods",
            "type":"Retail Goods"
        }
    ],
    "sg:phone":"+1 810 659 1464",
    "sg:postcode":"48433",
    "sg:province":"MI",
    "sg:tags":[
        "equipment",
        "archery",
        "supply"
    ],
    "wof:name":"American Broadhead",
    "wof:placetype":"venue"
},
  "geometry": {"coordinates":[-83.84901600000001,43.058759],"type":"Point"}
}