{
  "type": "Feature",
  "properties": {
    "iso:country":"US",
    "sg:address":"3335 Clinton Way",
    "sg:city":"Jackson",
    "sg:classifiers":[
        {
            "category":"Real Estate",
            "subcategory":"Real Estate Agent",
            "type":"Services"
        }
    ],
    "sg:phone":"+1 517 782 1100",
    "sg:postcode":"49201",
    "sg:province":"MI",
    "wof:name":"Access Realty",
    "wof:placetype":"venue"
},
  "geometry": {"coordinates":[-84.435243,42.296325],"type":"Point"}
}