{
  "type": "Feature",
  "properties": {
    "iso:country":"US",
    "sg:address":"1317 Fulton St E",
    "sg:city":"Grand Rapids",
    "sg:classifiers":[
        {
            "category":"Shopping",
            "subcategory":"Computers & Home Electronics",
            "type":"Retail Goods"
        }
    ],
    "sg:phone":"+1 616 988 0893",
    "sg:postcode":"49503",
    "sg:province":"MI",
    "sg:tags":[
        "equipment",
        "dealer"
    ],
    "wof:name":"Usereasy Computer Systems Inc",
    "wof:placetype":"venue"
},
  "geometry": {"coordinates":[-85.63737500000001,42.962798],"type":"Point"}
}