{
  "type": "Feature",
  "properties": {
    "iso:country":"US",
    "sg:address":"20811 Kraft Blvd",
    "sg:city":"Roseville",
    "sg:classifiers":[
        {
            "category":"Building & Trades",
            "subcategory":"Plumbing",
            "type":"Services"
        }
    ],
    "sg:phone":"+1 586 293 4455",
    "sg:postcode":"48066",
    "sg:province":"MI",
    "sg:tags":[
        "plumbing",
        "contractor"
    ],
    "wof:name":"BMB Plumbing",
    "wof:placetype":"venue"
},
  "geometry": {"coordinates":[-82.906735,42.515359],"type":"Point"}
}