{
  "type": "Feature",
  "properties": {
    "iso:country":"US",
    "sg:address":"9845 Telegraph Rd",
    "sg:city":"Taylor",
    "sg:classifiers":[
        {
            "category":"Restaurant",
            "type":"Food & Drink"
        }
    ],
    "sg:menulink":"http://www.allmenus.com/mi/taylor/141044-leos-coney-island/menu/",
    "sg:phone":"+1 313 295 8487",
    "sg:postcode":"48180",
    "sg:province":"MI",
    "sg:tags":[
        "american",
        "diner"
    ],
    "wof:name":"Leo's Coney Island",
    "wof:placetype":"venue"
},
  "geometry": {"coordinates":[-83.269288,42.235509],"type":"Point"}
}