{
  "type": "Feature",
  "properties": {
    "iso:country":"US",
    "sg:address":"341 W State St",
    "sg:city":"Montrose",
    "sg:classifiers":[
        {
            "category":"Organizations",
            "subcategory":"Religious Organization",
            "type":"Services"
        }
    ],
    "sg:phone":"+1 810 639 6476",
    "sg:postcode":"48457",
    "sg:province":"MI",
    "sg:tags":[
        "church"
    ],
    "wof:name":"Montrose Wesleyan Church Inc",
    "wof:placetype":"venue"
},
  "geometry": {"coordinates":[-83.900961,43.176118],"type":"Point"}
}