{
  "type": "Feature",
  "properties": {
    "iso:country":"US",
    "sg:address":"911 N Lake George Rd",
    "sg:city":"Attica",
    "sg:classifiers":[
        {
            "category":"Organizations",
            "subcategory":"Religious Organization",
            "type":"Services"
        }
    ],
    "sg:phone":"+1 810 245 1716",
    "sg:postcode":"48412",
    "sg:province":"MI",
    "sg:tags":[
        "church"
    ],
    "wof:name":"Word Of Life Community",
    "wof:placetype":"venue"
},
  "geometry": {"coordinates":[-83.187815,43.053962],"type":"Point"}
}