{
  "type": "Feature",
  "properties": {
    "iso:country":"US",
    "sg:address":"2880 E Beltline Ave NE",
    "sg:city":"Grand Rapids",
    "sg:classifiers":[
        {
            "category":"Professional",
            "subcategory":"Business Services",
            "type":"Services"
        }
    ],
    "sg:phone":"+1 616 361 1139",
    "sg:postcode":"49525",
    "sg:province":"MI",
    "wof:name":"Lectra USA Incorporated",
    "wof:placetype":"venue"
},
  "geometry": {"coordinates":[-85.589985,43.013728],"type":"Point"}
}