{
  "type": "Feature",
  "properties": {
    "iso:country":"US",
    "sg:address":"754 S Michigan Ave",
    "sg:city":"Howell",
    "sg:classifiers":[
        {
            "category":"Wholesale",
            "subcategory":"Auto Parts",
            "type":"Manufacturing & Wholesale Goods"
        }
    ],
    "sg:phone":"+1 517 552 2770",
    "sg:postcode":"48843",
    "sg:province":"MI",
    "sg:tags":[
        "body",
        "automobile",
        "shop"
    ],
    "wof:name":"Painter's Supply-Howell",
    "wof:placetype":"venue"
},
  "geometry": {"coordinates":[-83.933716,42.600855],"type":"Point"}
}