{
  "type": "Feature",
  "properties": {
    "iso:country":"US",
    "sg:address":"4055 N Meadow Ln",
    "sg:city":"Mt Morris",
    "sg:classifiers":[
        {
            "category":"Building & Trades",
            "subcategory":"Construction",
            "type":"Services"
        }
    ],
    "sg:phone":"+1 810 640 1640",
    "sg:postcode":"48458",
    "sg:province":"MI",
    "sg:tags":[
        "general",
        "contractor"
    ],
    "wof:name":"Top Quality Constr & Rmdlng",
    "wof:placetype":"venue"
},
  "geometry": {"coordinates":[-83.76006599999999,43.107359],"type":"Point"}
}