{
  "type": "Feature",
  "properties": {
    "iso:country":"US",
    "sg:address":"1770 W Clarkston Rd",
    "sg:city":"Lake Orion",
    "sg:classifiers":[
        {
            "category":"Professional",
            "type":"Services"
        }
    ],
    "sg:phone":"+1 248 693 4090",
    "sg:postcode":"48362",
    "sg:province":"MI",
    "sg:tags":[
        "establishment"
    ],
    "wof:name":"Electro Diamond Tools",
    "wof:placetype":"venue"
},
  "geometry": {"coordinates":[-83.27513,42.766443],"type":"Point"}
}