{
  "type": "Feature",
  "properties": {
    "iso:country":"US",
    "sg:address":"7156 US Hwy 41",
    "sg:city":"Gladstone",
    "sg:classifiers":[
        {
            "category":"Travel",
            "subcategory":"Hotels & Motels",
            "type":"Entertainment"
        }
    ],
    "sg:phone":"+1 906 786 7092",
    "sg:postcode":"49837",
    "sg:province":"MI",
    "sg:tags":[
        "operation"
    ],
    "wof:name":"Sleepy Hollow Motel",
    "wof:placetype":"venue"
},
  "geometry": {"coordinates":[-87.062905,45.804551],"type":"Point"}
}