{
  "type": "Feature",
  "properties": {
    "iso:country":"US",
    "sg:address":"9904 Red Bud Trl",
    "sg:city":"Berrien Springs",
    "sg:classifiers":[
        {
            "category":"Social Services",
            "subcategory":"Adult Care",
            "type":"Services"
        },
        {
            "category":"Health Services",
            "subcategory":"Clinic",
            "type":"Services"
        }
    ],
    "sg:phone":"+1 269 471 0066",
    "sg:postcode":"49103",
    "sg:province":"MI",
    "sg:tags":[
        "home",
        "residential"
    ],
    "wof:name":"Assisted Living At Red Bud Est",
    "wof:placetype":"venue"
},
  "geometry": {"coordinates":[-86.378666,41.939588],"type":"Point"}
}