{
  "type": "Feature",
  "properties": {
    "iso:country":"US",
    "sg:address":"1634 Gull Rd",
    "sg:city":"Kalamazoo",
    "sg:classifiers":[
        {
            "category":"Health Services",
            "subcategory":"Doctor",
            "type":"Services"
        }
    ],
    "sg:phone":"+1 269 341 9200",
    "sg:postcode":"49048",
    "sg:province":"MI",
    "sg:tags":[
        "physician",
        "surgeon",
        "medical"
    ],
    "wof:name":"Kalamazoo Hematology & Onocolo",
    "wof:placetype":"venue"
},
  "geometry": {"coordinates":[-85.559703,42.305462],"type":"Point"}
}