{
  "type": "Feature",
  "properties": {
    "iso:country":"US",
    "sg:address":"32615 Meadowbrook St",
    "sg:city":"Livonia",
    "sg:classifiers":[
        {
            "category":"Arts & Performance",
            "subcategory":"Arts Center",
            "type":"Entertainment"
        },
        {
            "category":"Manufacturing",
            "subcategory":"Textiles",
            "type":"Manufacturing & Wholesale Goods"
        }
    ],
    "sg:phone":"+1 734 522 4798",
    "sg:postcode":"48154",
    "sg:province":"MI",
    "sg:tags":[
        "decorating",
        "painting",
        "hand"
    ],
    "wof:name":"Mark Welsh",
    "wof:placetype":"venue"
},
  "geometry": {"coordinates":[-83.36502299999999,42.392845],"type":"Point"}
}