{
  "type": "Feature",
  "properties": {
    "iso:country":"US",
    "sg:address":"1585 Pleasant St",
    "sg:city":"Lapeer",
    "sg:classifiers":[
        {
            "category":"Social Services",
            "subcategory":"Child Care",
            "type":"Services"
        }
    ],
    "sg:phone":"+1 810 667 4925",
    "sg:postcode":"48446",
    "sg:province":"MI",
    "sg:tags":[
        "day"
    ],
    "wof:name":"Teddy Bear Care",
    "wof:placetype":"venue"
},
  "geometry": {"coordinates":[-83.322185,43.049666],"type":"Point"}
}