{
  "type": "Feature",
  "properties": {
    "iso:country":"US",
    "sg:address":"6465 Livernois Rd",
    "sg:city":"Troy",
    "sg:classifiers":[
        {
            "category":"Education",
            "subcategory":"School",
            "type":"Public Place"
        }
    ],
    "sg:phone":"+1 248 828 9661",
    "sg:postcode":"48098",
    "sg:province":"MI",
    "wof:name":"Avondale School District Woodland Elementary",
    "wof:placetype":"venue"
},
  "geometry": {"coordinates":[-83.1502,42.6134],"type":"Point"}
}