{
  "type": "Feature",
  "properties": {
    "iso:country":"US",
    "sg:address":"4424 Parnell St",
    "sg:city":"Clarkston",
    "sg:classifiers":[
        {
            "category":"Health Services",
            "subcategory":"Doctor",
            "type":"Services"
        }
    ],
    "sg:phone":"+1 248 933 5488",
    "sg:postcode":"48346",
    "sg:province":"MI",
    "sg:tags":[
        "medical"
    ],
    "wof:name":"Donald G Martus",
    "wof:placetype":"venue"
},
  "geometry": {"coordinates":[-83.36125800000001,42.703269],"type":"Point"}
}