{
  "type": "Feature",
  "properties": {
    "iso:country":"US",
    "sg:address":"4812 Leafdale Blvd",
    "sg:city":"Royal Oak",
    "sg:classifiers":[
        {
            "category":"Autos & Motor Vehicles",
            "subcategory":"Auto Supplies",
            "type":"Retail Goods"
        }
    ],
    "sg:phone":"+1 248 280 0240",
    "sg:postcode":"48073",
    "sg:province":"MI",
    "sg:tags":[
        "equipment",
        "racing",
        "car",
        "automobile"
    ],
    "wof:name":"Lukovich Motorsports",
    "wof:placetype":"venue"
},
  "geometry": {"coordinates":[-83.175855,42.535151],"type":"Point"}
}