{
  "type": "Feature",
  "properties": {
    "iso:country":"US",
    "sg:address":"1950 Inwood Rd",
    "sg:city":"Rochester",
    "sg:classifiers":[
        {
            "category":"Home & Garden",
            "subcategory":"Building Materials",
            "type":"Retail Goods"
        }
    ],
    "sg:phone":"+1 586 752 7917",
    "sg:postcode":"48306",
    "sg:province":"MI",
    "wof:name":"Oakland Sand & Gravel",
    "wof:placetype":"venue"
},
  "geometry": {"coordinates":[-83.09864,42.763212],"type":"Point"}
}