{
  "type": "Feature",
  "properties": {
    "iso:country":"US",
    "sg:address":"7556 Miller Rd",
    "sg:city":"Swartz Creek",
    "sg:classifiers":[
        {
            "category":"Shopping",
            "subcategory":"Musical Instruments",
            "type":"Retail Goods"
        }
    ],
    "sg:phone":"+1 810 635 4734",
    "sg:postcode":"48473",
    "sg:province":"MI",
    "sg:tags":[
        "who"
    ],
    "sg:website":"www.jeffsmusic.com",
    "wof:name":"Jeff's Music",
    "wof:placetype":"venue"
},
  "geometry": {"coordinates":[-83.828801,42.957298],"type":"Point"}
}