{
  "type": "Feature",
  "properties": {
    "iso:country":"US",
    "sg:address":"2270 Greendale Dr",
    "sg:city":"Jenison",
    "sg:classifiers":[
        {
            "category":"Professional",
            "subcategory":"Business Services",
            "type":"Services"
        }
    ],
    "sg:phone":"+1 616 662 1399",
    "sg:postcode":"49428",
    "sg:province":"MI",
    "wof:name":"Fays Embroidery",
    "wof:placetype":"venue"
},
  "geometry": {"coordinates":[-85.839867,42.895057],"type":"Point"}
}