{
  "type": "Feature",
  "properties": {
    "iso:country":"US",
    "sg:address":"4700 Greenfield Rd",
    "sg:city":"Dearborn",
    "sg:classifiers":[
        {
            "category":"Health Services",
            "subcategory":"Doctor",
            "type":"Services"
        }
    ],
    "sg:phone":"+1 313 582 2688",
    "sg:postcode":"48126",
    "sg:province":"MI",
    "sg:tags":[
        "dentist"
    ],
    "wof:name":"Oakman Family Dentistry",
    "wof:placetype":"venue"
},
  "geometry": {"coordinates":[-83.19499999999999,42.319199],"type":"Point"}
}