{
  "type": "Feature",
  "properties": {
    "iso:country":"US",
    "sg:address":"15782 Hooker Rd",
    "sg:city":"Lake Ann",
    "sg:classifiers":[
        {
            "category":"Shopping",
            "subcategory":"Bicycles & Sporting Goods",
            "type":"Retail Goods"
        }
    ],
    "sg:phone":"+1 231 275 5900",
    "sg:postcode":"49650",
    "sg:province":"MI",
    "sg:tags":[
        "repair"
    ],
    "wof:name":"Arrowhead Taxidermy",
    "wof:placetype":"venue"
},
  "geometry": {"coordinates":[-85.923368,44.703708],"type":"Point"}
}