{
  "type": "Feature",
  "properties": {
    "iso:country":"US",
    "sg:address":"117 S Kalamazoo Ave",
    "sg:city":"Vicksburg",
    "sg:classifiers":[
        {
            "category":"Personal",
            "subcategory":"Beauty Salon",
            "type":"Services"
        }
    ],
    "sg:phone":"+1 269 649 5527",
    "sg:postcode":"49097",
    "sg:province":"MI",
    "wof:name":"Headlines Hair Design",
    "wof:placetype":"venue"
},
  "geometry": {"coordinates":[-85.53087600000001,42.119796],"type":"Point"}
}