{
  "type": "Feature",
  "properties": {
    "iso:country":"US",
    "sg:address":"302 N Huron St",
    "sg:city":"Ypsilanti",
    "sg:classifiers":[
        {
            "category":"Organizations",
            "subcategory":"Professional Association",
            "type":"Services"
        }
    ],
    "sg:phone":"+1 734 487 5522",
    "sg:postcode":"48197",
    "sg:province":"MI",
    "sg:tags":[
        "business"
    ],
    "wof:name":"Plant Protection Assn Nat",
    "wof:placetype":"venue"
},
  "geometry": {"coordinates":[-83.61353099999999,42.245833],"type":"Point"}
}