{
  "type": "Feature",
  "properties": {
    "iso:country":"US",
    "sg:address":"46365 Greenridge Dr",
    "sg:city":"Northville",
    "sg:classifiers":[
        {
            "category":"Professional",
            "type":"Services"
        }
    ],
    "sg:phone":"+1 248 380 0006",
    "sg:postcode":"48167",
    "sg:province":"MI",
    "wof:name":"Can Connection",
    "wof:placetype":"venue"
},
  "geometry": {"coordinates":[-83.503821,42.434595],"type":"Point"}
}