{
  "type": "Feature",
  "properties": {
    "iso:country":"US",
    "sg:address":"55024 M 51 N",
    "sg:city":"Dowagiac",
    "sg:classifiers":[
        {
            "category":"Personal",
            "subcategory":"Beauty Salon",
            "type":"Services"
        }
    ],
    "sg:phone":"+1 269 782 3755",
    "sg:postcode":"49047",
    "sg:province":"MI",
    "wof:name":"Natural Concept",
    "wof:placetype":"venue"
},
  "geometry": {"coordinates":[-86.107421,41.998117],"type":"Point"}
}