{
  "type": "Feature",
  "properties": {
    "iso:country":"US",
    "sg:address":"33505 Schoolcraft Rd Ste 2",
    "sg:city":"Livonia",
    "sg:classifiers":[
        {
            "category":"Professional",
            "subcategory":"Accounting & Tax Preparation",
            "type":"Services"
        }
    ],
    "sg:phone":"+1 734 422 7471",
    "sg:postcode":"48150",
    "sg:province":"MI",
    "sg:tags":[
        "accountant"
    ],
    "wof:name":"Scott W Sanders CPA",
    "wof:placetype":"venue"
},
  "geometry": {"coordinates":[-83.374199,42.382],"type":"Point"}
}