{
  "type": "Feature",
  "properties": {
    "iso:country":"US",
    "sg:address":"1055 28th St SW",
    "sg:city":"Wyoming",
    "sg:classifiers":[
        {
            "category":"Education",
            "subcategory":"Special Training",
            "type":"Public Place"
        }
    ],
    "sg:phone":"+1 616 531 7592",
    "sg:postcode":"49509",
    "sg:province":"MI",
    "sg:tags":[
        "educational"
    ],
    "wof:name":"Educational Outfitters",
    "wof:placetype":"venue"
},
  "geometry": {"coordinates":[-85.694534,42.913474],"type":"Point"}
}