{
  "type": "Feature",
  "properties": {
    "iso:country":"US",
    "sg:address":"4159 Brubaker Rd",
    "sg:city":"Petoskey",
    "sg:classifiers":[
        {
            "category":"Building & Trades",
            "subcategory":"Cleaning & Sanitation",
            "type":"Services"
        }
    ],
    "sg:phone":"+1 231 348 5854",
    "sg:postcode":"49770",
    "sg:province":"MI",
    "sg:tags":[
        "maintenance"
    ],
    "wof:name":"Up North Maintenance",
    "wof:placetype":"venue"
},
  "geometry": {"coordinates":[-84.8866,45.341246],"type":"Point"}
}