{
  "type": "Feature",
  "properties": {
    "iso:country":"US",
    "sg:address":"1223 S Belsay Rd",
    "sg:city":"Burton",
    "sg:classifiers":[
        {
            "category":"Organizations",
            "subcategory":"Religious Organization",
            "type":"Services"
        }
    ],
    "sg:phone":"+1 810 742 6343",
    "sg:postcode":"48509",
    "sg:province":"MI",
    "wof:name":"Anchor Baptist Church",
    "wof:placetype":"venue"
},
  "geometry": {"coordinates":[-83.59533,43.016795],"type":"Point"}
}