{
  "type": "Feature",
  "properties": {
    "iso:country":"US",
    "sg:address":"70745 Powell Rd",
    "sg:city":"Bruce",
    "sg:classifiers":[
        {
            "category":"Manufacturing",
            "subcategory":"Retail Goods",
            "type":"Manufacturing & Wholesale Goods"
        }
    ],
    "sg:phone":"+1 586 752 3099",
    "sg:postcode":"48065",
    "sg:province":"MI",
    "sg:tags":[
        "manufacturer"
    ],
    "wof:name":"Sharp Model Co",
    "wof:placetype":"venue"
},
  "geometry": {"coordinates":[-82.980677,42.819505],"type":"Point"}
}