{
  "type": "Feature",
  "properties": {
    "iso:country":"US",
    "sg:address":"28888 Goddard Rd",
    "sg:city":"Romulus",
    "sg:classifiers":[
        {
            "category":"Building & Trades",
            "subcategory":"Cleaning & Sanitation",
            "type":"Services"
        }
    ],
    "sg:phone":"+1 734 947 4015",
    "sg:postcode":"48174",
    "sg:province":"MI",
    "wof:name":"White Cleaning Service Inc",
    "wof:placetype":"venue"
},
  "geometry": {"coordinates":[-83.325593,42.224541],"type":"Point"}
}