{
  "type": "Feature",
  "properties": {
    "iso:country":"US",
    "sg:address":"41756 Broquet Dr",
    "sg:city":"Northville",
    "sg:classifiers":[
        {
            "category":"Building & Trades",
            "subcategory":"Cleaning & Sanitation",
            "type":"Services"
        }
    ],
    "sg:phone":"+1 248 305 5474",
    "sg:postcode":"48167",
    "sg:province":"MI",
    "sg:tags":[
        "maintenance"
    ],
    "wof:name":"T&M United Industrial Developm",
    "wof:placetype":"venue"
},
  "geometry": {"coordinates":[-83.457686,42.44479],"type":"Point"}
}