{
  "type": "Feature",
  "properties": {
    "iso:country":"US",
    "sg:address":"24277 Middlebelt Rd",
    "sg:city":"Farmington Hills",
    "sg:classifiers":[
        {
            "category":"Insurance",
            "subcategory":"Insurance Agent",
            "type":"Services"
        }
    ],
    "sg:phone":"+1 248 615 5404",
    "sg:postcode":"48336",
    "sg:province":"MI",
    "wof:name":"State Farm Insurance",
    "wof:placetype":"venue"
},
  "geometry": {"coordinates":[-83.337847,42.471809],"type":"Point"}
}