{
  "type": "Feature",
  "properties": {
    "iso:country":"US",
    "sg:address":"3341 Round Lake Hwy",
    "sg:city":"Manitou Beach",
    "sg:classifiers":[
        {
            "category":"Professional",
            "subcategory":"Accounting & Tax Preparation",
            "type":"Services"
        }
    ],
    "sg:phone":"+1 517 547 6615",
    "sg:postcode":"49253",
    "sg:province":"MI",
    "sg:tags":[
        "return"
    ],
    "wof:name":"C T G Assoc",
    "wof:placetype":"venue"
},
  "geometry": {"coordinates":[-84.27533099999999,41.978279],"type":"Point"}
}