{
  "type": "Feature",
  "properties": {
    "iso:country":"US",
    "sg:address":"39467 Willmarth St",
    "sg:city":"Harrison Twp",
    "sg:classifiers":[
        {
            "category":"Autos & Motor Vehicles",
            "subcategory":"Auto Supplies",
            "type":"Retail Goods"
        }
    ],
    "sg:phone":"+1 586 465 9220",
    "sg:postcode":"48045",
    "sg:province":"MI",
    "sg:tags":[
        "equipment",
        "racing",
        "car",
        "automobile"
    ],
    "wof:name":"Leader Racing",
    "wof:placetype":"venue"
},
  "geometry": {"coordinates":[-82.81579000000001,42.592799],"type":"Point"}
}