{
  "type": "Feature",
  "properties": {
    "iso:country":"US",
    "sg:address":"4511 Billmar St SW",
    "sg:city":"Grandville",
    "sg:classifiers":[
        {
            "category":"Social Services",
            "subcategory":"Child Care",
            "type":"Services"
        }
    ],
    "sg:phone":"+1 616 531 9823",
    "sg:postcode":"49418",
    "sg:province":"MI",
    "sg:tags":[
        "day"
    ],
    "wof:name":"Luanne Armstrong",
    "wof:placetype":"venue"
},
  "geometry": {"coordinates":[-85.774726,42.89459],"type":"Point"}
}