{
  "type": "Feature",
  "properties": {
    "iso:country":"US",
    "sg:address":"24717 Red Arrow Hwy",
    "sg:city":"Mattawan",
    "sg:classifiers":[
        {
            "category":"Retail",
            "subcategory":"Auto Repair",
            "type":"Services"
        }
    ],
    "sg:phone":"+1 269 668 3441",
    "sg:postcode":"49071",
    "sg:province":"MI",
    "sg:tags":[
        "radiator"
    ],
    "wof:name":"Dundon Radiator Service",
    "wof:placetype":"venue"
},
  "geometry": {"coordinates":[-85.79406,42.235499],"type":"Point"}
}