{
  "type": "Feature",
  "properties": {
    "iso:country":"US",
    "sg:address":"18615 Moenart St",
    "sg:city":"Detroit",
    "sg:classifiers":[
        {
            "category":"Social Services",
            "subcategory":"Adult Care",
            "type":"Services"
        }
    ],
    "sg:phone":"+1 313 892 2145",
    "sg:postcode":"48234",
    "sg:province":"MI",
    "sg:tags":[
        "foster",
        "provider"
    ],
    "wof:name":"Marion Rutland",
    "wof:placetype":"venue"
},
  "geometry": {"coordinates":[-83.050247,42.431422],"type":"Point"}
}