{
  "type": "Feature",
  "properties": {
    "iso:country":"US",
    "sg:address":"123 Lawrence St NE",
    "sg:city":"Grand Rapids",
    "sg:classifiers":[
        {
            "category":"Professional",
            "subcategory":"Business Services",
            "type":"Services"
        }
    ],
    "sg:phone":"+1 616 365 8508",
    "sg:postcode":"49505",
    "sg:province":"MI",
    "wof:name":"Christopher Alan Tusch",
    "wof:placetype":"venue"
},
  "geometry": {"coordinates":[-85.664967,43.004808],"type":"Point"}
}