{
  "type": "Feature",
  "properties": {
    "iso:country":"US",
    "sg:address":"20031 W Warren Ave",
    "sg:city":"Detroit",
    "sg:classifiers":[
        {
            "category":"Autos & Motor Vehicles",
            "subcategory":"Fuel & Gas Station",
            "type":"Retail Goods"
        }
    ],
    "sg:phone":"+1 313 982 3023",
    "sg:postcode":"48228",
    "sg:province":"MI",
    "wof:name":"Speedy Gas",
    "wof:placetype":"venue"
},
  "geometry": {"coordinates":[-83.236176,42.342978],"type":"Point"}
}