{
  "type": "Feature",
  "properties": {
    "iso:country":"US",
    "sg:address":"2038 Cass Lake Rd",
    "sg:city":"Keego Harbor",
    "sg:classifiers":[
        {
            "category":"Retail",
            "subcategory":"Animal Services",
            "type":"Services"
        }
    ],
    "sg:phone":"+1 248 683 1204",
    "sg:postcode":"48320",
    "sg:province":"MI",
    "sg:tags":[
        "pet",
        "grooming",
        "washing",
        "boarding/pet",
        "sitting"
    ],
    "wof:name":"Razzle Dazzle Pet Grooming",
    "wof:placetype":"venue"
},
  "geometry": {"coordinates":[-83.344002,42.6092],"type":"Point"}
}