{
  "type": "Feature",
  "properties": {
    "iso:country":"US",
    "sg:address":"2525 Wolf Creek Hwy",
    "sg:city":"Adrian",
    "sg:classifiers":[
        {
            "category":"Freight",
            "type":"Transportation"
        }
    ],
    "sg:phone":"+1 517 265 6605",
    "sg:postcode":"49221",
    "sg:province":"MI",
    "sg:tags":[
        "operator",
        "local",
        "trucking"
    ],
    "wof:name":"Samuel S Sanderson Trucking",
    "wof:placetype":"venue"
},
  "geometry": {"coordinates":[-84.09226099999999,41.923948],"type":"Point"}
}