{
  "type": "Feature",
  "properties": {
    "iso:country":"US",
    "sg:address":"1410 Greenwood Ave",
    "sg:city":"Jackson",
    "sg:classifiers":[
        {
            "category":"Real Estate",
            "subcategory":"Real Estate Agent",
            "type":"Services"
        }
    ],
    "sg:phone":"+1 517 783 5007",
    "sg:postcode":"49203",
    "sg:province":"MI",
    "wof:name":"Charles M Ahronheim",
    "wof:placetype":"venue"
},
  "geometry": {"coordinates":[-84.41841700000001,42.230151],"type":"Point"}
}