{
  "type": "Feature",
  "properties": {
    "iso:country":"US",
    "sg:address":"25164 Loretta Ave",
    "sg:city":"Warren",
    "sg:classifiers":[
        {
            "category":"Freight",
            "type":"Transportation"
        }
    ],
    "sg:phone":"+1 586 757 1478",
    "sg:postcode":"48091",
    "sg:province":"MI",
    "sg:tags":[
        "operator",
        "local",
        "trucking"
    ],
    "wof:name":"Dons Expediting Co",
    "wof:placetype":"venue"
},
  "geometry": {"coordinates":[-83.058441,42.479313],"type":"Point"}
}