{
  "type": "Feature",
  "properties": {
    "iso:country":"US",
    "sg:address":"6248 E Dunbar Rd",
    "sg:city":"Monroe",
    "sg:classifiers":[
        {
            "category":"Organizations",
            "subcategory":"Religious Organization",
            "type":"Services"
        }
    ],
    "sg:phone":"+1 734 243 0025",
    "sg:postcode":"48161",
    "sg:province":"MI",
    "sg:tags":[
        "church"
    ],
    "wof:name":"First Free Will Baptist Church",
    "wof:placetype":"venue"
},
  "geometry": {"coordinates":[-83.409719,41.898565],"type":"Point"}
}