{
  "type": "Feature",
  "properties": {
    "iso:country":"US",
    "sg:address":"250 N Holbrook St",
    "sg:city":"Plymouth",
    "sg:classifiers":[
        {
            "category":"Professional",
            "subcategory":"Lawyer & Legal Services",
            "type":"Services"
        }
    ],
    "sg:phone":"+1 734 354 8550",
    "sg:postcode":"48170",
    "sg:province":"MI",
    "wof:name":"Gerald M Conley",
    "wof:placetype":"venue"
},
  "geometry": {"coordinates":[-83.459261,42.375019],"type":"Point"}
}