{
  "type": "Feature",
  "properties": {
    "iso:country":"US",
    "sg:address":"26877 Northwestern Hwy",
    "sg:city":"Southfield",
    "sg:classifiers":[
        {
            "category":"Professional",
            "subcategory":"Lawyer & Legal Services",
            "type":"Services"
        }
    ],
    "sg:phone":"+1 248 353 7620",
    "sg:postcode":"48034",
    "sg:province":"MI",
    "wof:name":"Urban Jeffrey C Attys",
    "wof:placetype":"venue"
},
  "geometry": {"coordinates":[-83.268303,42.4841],"type":"Point"}
}