{
  "type": "Feature",
  "properties": {
    "iso:country":"US",
    "sg:address":"39800 West Fourteen Mile Rd",
    "sg:city":"Walled Lake",
    "sg:classifiers":[
        {
            "category":"Personal",
            "subcategory":"Beauty Salon",
            "type":"Services"
        },
        {
            "category":"Personal",
            "subcategory":"Day Spa",
            "type":"Services"
        }
    ],
    "sg:phone":"+1 248 624 4700",
    "sg:postcode":"48390",
    "sg:province":"MI",
    "sg:tags":[
        "hair"
    ],
    "sg:website":"www.puresalondayspa.com/",
    "wof:name":"Pure Salon and Day Spa",
    "wof:placetype":"venue"
},
  "geometry": {"coordinates":[-83.439652,42.527086],"type":"Point"}
}