{
  "type": "Feature",
  "properties": {
    "iso:country":"US",
    "sg:address":"991 Treasure Island Dr",
    "sg:city":"Mattawan",
    "sg:classifiers":[
        {
            "category":"Shopping",
            "subcategory":"Gifts & Souvenirs",
            "type":"Retail Goods"
        }
    ],
    "sg:phone":"+1 269 372 1361",
    "sg:postcode":"49071",
    "sg:province":"MI",
    "sg:tags":[
        "basket"
    ],
    "wof:name":"Jas Enterprises Inc",
    "wof:placetype":"venue"
},
  "geometry": {"coordinates":[-85.723595,42.214544],"type":"Point"}
}