{
  "type": "Feature",
  "properties": {
    "iso:country":"US",
    "sg:address":"111 Pine River Ln",
    "sg:city":"Charlevoix",
    "sg:classifiers":[
        {
            "category":"Travel",
            "subcategory":"Hotels & Motels",
            "type":"Entertainment"
        }
    ],
    "sg:phone":"+1 231 547 9955",
    "sg:postcode":"49720",
    "sg:province":"MI",
    "sg:website":"www.weathervane-chx.com",
    "wof:name":"Weathervane Terrace Inn",
    "wof:placetype":"venue"
},
  "geometry": {"coordinates":[-85.26113599999999,45.319763],"type":"Point"}
}