{
  "type": "Feature",
  "properties": {
    "iso:country":"US",
    "sg:address":"400 Ada Dr SE",
    "sg:city":"Ada",
    "sg:classifiers":[
        {
            "category":"Cinema",
            "subcategory":"Movie Rental",
            "type":"Entertainment"
        }
    ],
    "sg:phone":"+1 616 676 4444",
    "sg:postcode":"49301",
    "sg:province":"MI",
    "sg:tags":[
        "leasing",
        "video",
        "disc",
        "tape"
    ],
    "wof:name":"Box Office Hits Video",
    "wof:placetype":"venue"
},
  "geometry": {"coordinates":[-85.48356,42.955887],"type":"Point"}
}