{
  "type": "Feature",
  "properties": {
    "iso:country":"US",
    "sg:address":"1311 Henrietta St",
    "sg:city":"Birmingham",
    "sg:classifiers":[
        {
            "category":"Professional",
            "subcategory":"Business Services",
            "type":"Services"
        }
    ],
    "sg:phone":"+1 248 723 6410",
    "sg:postcode":"48009",
    "sg:province":"MI",
    "sg:tags":[
        "appraiser"
    ],
    "wof:name":"Dart Appraisal Svc Inc",
    "wof:placetype":"venue"
},
  "geometry": {"coordinates":[-83.215664,42.538233],"type":"Point"}
}