{
  "type": "Feature",
  "properties": {
    "iso:country":"US",
    "sg:address":"12136 Crowe Rd",
    "sg:city":"Milan",
    "sg:classifiers":[
        {
            "category":"Building & Trades",
            "subcategory":"Cleaning & Sanitation",
            "type":"Services"
        }
    ],
    "sg:phone":"+1 734 944 7414",
    "sg:postcode":"48160",
    "sg:province":"MI",
    "sg:tags":[
        "maintenance"
    ],
    "wof:name":"Authentic Cleaning Inc",
    "wof:placetype":"venue"
},
  "geometry": {"coordinates":[-83.675104,42.04962],"type":"Point"}
}