{
  "type": "Feature",
  "properties": {
    "iso:country":"US",
    "sg:address":"17 Chestnut Dr",
    "sg:city":"Fenton",
    "sg:classifiers":[
        {
            "category":"Home & Garden",
            "subcategory":"Mobile Homes",
            "type":"Retail Goods"
        }
    ],
    "sg:phone":"+1 810 629 5898",
    "sg:postcode":"48430",
    "sg:province":"MI",
    "wof:name":"Fenton Oaks LLC",
    "wof:placetype":"venue"
},
  "geometry": {"coordinates":[-83.745823,42.786311],"type":"Point"}
}