{
  "type": "Feature",
  "properties": {
    "iso:country":"US",
    "sg:address":"18767 Hall Rd",
    "sg:city":"Macomb",
    "sg:classifiers":[
        {
            "category":"Food & Beverages",
            "subcategory":"Groceries & Convenience Stores",
            "type":"Retail Goods"
        }
    ],
    "sg:phone":"+1 586 286 5280",
    "sg:postcode":"48044",
    "sg:province":"MI",
    "wof:name":"BP",
    "wof:placetype":"venue"
},
  "geometry": {"coordinates":[-82.93434000000001,42.628722],"type":"Point"}
}