{
  "type": "Feature",
  "properties": {
    "iso:country":"US",
    "sg:address":"16000 Ten Mile Rd",
    "sg:city":"Eastpointe",
    "sg:classifiers":[
        {
            "category":"Shopping",
            "subcategory":"Pharmacy",
            "type":"Retail Goods"
        }
    ],
    "sg:phone":"+1 586 777 7570",
    "sg:postcode":"48021",
    "sg:province":"MI",
    "sg:tags":[
        "drugstore"
    ],
    "sg:website":"www.cvs.com",
    "wof:name":"CVS Pharmacy",
    "wof:placetype":"venue"
},
  "geometry": {"coordinates":[-82.958009,42.479569],"type":"Point"}
}