{
  "type": "Feature",
  "properties": {
    "iso:country":"US",
    "sg:address":"47601 Winthrop St",
    "sg:city":"Utica",
    "sg:classifiers":[
        {
            "category":"Food & Beverages",
            "subcategory":"Groceries & Convenience Stores",
            "type":"Retail Goods"
        }
    ],
    "sg:phone":"+1 586 254 9198",
    "sg:postcode":"48317",
    "sg:province":"MI",
    "wof:name":"Genes Super Market Coupons",
    "wof:placetype":"venue"
},
  "geometry": {"coordinates":[-83.06576200000001,42.64141],"type":"Point"}
}