{
  "type": "Feature",
  "properties": {
    "iso:country":"US",
    "sg:address":"14450 Ashton Rd",
    "sg:city":"Detroit",
    "sg:classifiers":[
        {
            "category":"Organizations",
            "subcategory":"Religious Organization",
            "type":"Services"
        }
    ],
    "sg:phone":"+1 313 838 3600",
    "sg:postcode":"48223",
    "sg:province":"MI",
    "wof:name":"St James Lutheran Church Inc",
    "wof:placetype":"venue"
},
  "geometry": {"coordinates":[-83.218874,42.392557],"type":"Point"}
}