{
  "type": "Feature",
  "properties": {
    "iso:country":"US",
    "sg:address":"11811 Bonet Ct W",
    "sg:city":"Fair Haven",
    "sg:classifiers":[
        {
            "category":"Professional",
            "subcategory":"Art Services",
            "type":"Services"
        }
    ],
    "sg:phone":"+1 586 716 1873",
    "sg:postcode":"48023",
    "sg:province":"MI",
    "sg:tags":[
        "commercial",
        "design"
    ],
    "wof:name":"Louise Custom Tees",
    "wof:placetype":"venue"
},
  "geometry": {"coordinates":[-82.715827,42.697641],"type":"Point"}
}