{
  "type": "Feature",
  "properties": {
    "iso:country":"US",
    "sg:address":"8270 Old Mill Dr",
    "sg:city":"Pinckney",
    "sg:classifiers":[
        {
            "category":"Professional",
            "subcategory":"Business Services",
            "type":"Services"
        }
    ],
    "sg:phone":"+1 734 954 8502",
    "sg:postcode":"48169",
    "sg:province":"MI",
    "wof:name":"Cleland Cold Heading Design",
    "wof:placetype":"venue"
},
  "geometry": {"coordinates":[-83.859348,42.481559],"type":"Point"}
}