{
  "type": "Feature",
  "properties": {
    "iso:country":"US",
    "sg:address":"44 N Dennis Rd",
    "sg:city":"Ludington",
    "sg:classifiers":[
        {
            "category":"Shopping",
            "subcategory":"Clothing, Apparel, & Fashions",
            "type":"Retail Goods"
        }
    ],
    "sg:phone":"+1 231 843 0700",
    "sg:postcode":"49431",
    "sg:province":"MI",
    "wof:name":"Jan's Nook Of The North",
    "wof:placetype":"venue"
},
  "geometry": {"coordinates":[-86.369809,43.959615],"type":"Point"}
}