{
  "type": "Feature",
  "properties": {
    "iso:country":"US",
    "sg:address":"1356 Portage St",
    "sg:city":"Kalamazoo",
    "sg:classifiers":[
        {
            "category":"Organizations",
            "subcategory":"Non-profit Organization",
            "type":"Services"
        },
        {
            "category":"Government",
            "subcategory":"Office",
            "type":"Public Place"
        }
    ],
    "sg:phone":"+1 269 382 0916",
    "sg:postcode":"49001",
    "sg:province":"MI",
    "sg:tags":[
        "program",
        "administrative"
    ],
    "wof:name":"Edison Neighborhood Assn",
    "wof:placetype":"venue"
},
  "geometry": {"coordinates":[-85.57001099999999,42.277803],"type":"Point"}
}