{
  "type": "Feature",
  "properties": {
    "iso:country":"US",
    "sg:address":"10403 Horton Rd",
    "sg:city":"Goodrich",
    "sg:classifiers":[
        {
            "category":"Personal",
            "subcategory":"Beauty Salon",
            "type":"Services"
        }
    ],
    "sg:phone":"+1 810 636 4212",
    "sg:postcode":"48438",
    "sg:province":"MI",
    "sg:tags":[
        "shop"
    ],
    "wof:name":"Glitz Salons",
    "wof:placetype":"venue"
},
  "geometry": {"coordinates":[-83.499438,42.882523],"type":"Point"}
}