{
  "type": "Feature",
  "properties": {
    "iso:country":"US",
    "sg:address":"6251 Camden Rd",
    "sg:city":"Waldron",
    "sg:classifiers":[
        {
            "category":"Organizations",
            "subcategory":"Religious Organization",
            "type":"Services"
        }
    ],
    "sg:phone":"+1 517 567 4374",
    "sg:postcode":"49288",
    "sg:province":"MI",
    "sg:tags":[
        "clergy"
    ],
    "wof:name":"Max K Masters",
    "wof:placetype":"venue"
},
  "geometry": {"coordinates":[-84.527665,41.752987],"type":"Point"}
}