{
  "type": "Feature",
  "properties": {
    "iso:country":"US",
    "sg:address":"2203 W Holmes Rd",
    "sg:city":"Lansing",
    "sg:classifiers":[
        {
            "category":"Food & Beverages",
            "subcategory":"Meat & Fish",
            "type":"Retail Goods"
        }
    ],
    "sg:phone":"+1 517 887 0404",
    "sg:postcode":"48911",
    "sg:province":"MI",
    "wof:name":"Nineteen Ten Meat Co",
    "wof:placetype":"venue"
},
  "geometry": {"coordinates":[-84.58369500000001,42.697494],"type":"Point"}
}