{
  "type": "Feature",
  "properties": {
    "iso:country":"US",
    "sg:address":"10201 E Jefferson Ave",
    "sg:city":"Detroit",
    "sg:classifiers":[
        {
            "category":"Health Services",
            "subcategory":"Hospital",
            "type":"Services"
        }
    ],
    "sg:phone":"+1 313 823 0750",
    "sg:postcode":"48214",
    "sg:province":"MI",
    "wof:name":"Dmc Health Gr-Jefferson",
    "wof:placetype":"venue"
},
  "geometry": {"coordinates":[-82.980763,42.362195],"type":"Point"}
}