{
  "type": "Feature",
  "properties": {
    "iso:country":"US",
    "sg:address":"1617 Ravenswood Dr",
    "sg:city":"Lansing",
    "sg:classifiers":[
        {
            "category":"Professional",
            "subcategory":"Management & Consulting",
            "type":"Services"
        }
    ],
    "sg:phone":"+1 517 886 4596",
    "sg:postcode":"48917",
    "sg:province":"MI",
    "sg:tags":[
        "business"
    ],
    "wof:name":"Ravenswood Consulting",
    "wof:placetype":"venue"
},
  "geometry": {"coordinates":[-84.599116,42.751664],"type":"Point"}
}