{
  "type": "Feature",
  "properties": {
    "iso:country":"US",
    "sg:address":"69 S 3rd Ave",
    "sg:city":"Fruitport",
    "sg:classifiers":[
        {
            "category":"Wholesale",
            "subcategory":"Machinery & Supplies",
            "type":"Manufacturing & Wholesale Goods"
        }
    ],
    "sg:phone":"+1 231 865 8989",
    "sg:postcode":"49415",
    "sg:province":"MI",
    "sg:tags":[
        "abrasive"
    ],
    "wof:name":"Helveston Co",
    "wof:placetype":"venue"
},
  "geometry": {"coordinates":[-86.155328,43.124292],"type":"Point"}
}