{
  "type": "Feature",
  "properties": {
    "iso:country":"US",
    "sg:address":"3016 1st St",
    "sg:city":"Wyandotte",
    "sg:classifiers":[
        {
            "category":"Shopping",
            "subcategory":"Gifts & Souvenirs",
            "type":"Retail Goods"
        }
    ],
    "sg:phone":"+1 734 283 0663",
    "sg:postcode":"48192",
    "sg:province":"MI",
    "sg:tags":[
        "gourmet",
        "food"
    ],
    "wof:name":"Treasure Alley Mini Mall",
    "wof:placetype":"venue"
},
  "geometry": {"coordinates":[-83.15008899999999,42.202284],"type":"Point"}
}