{
  "type": "Feature",
  "properties": {
    "iso:country":"US",
    "sg:address":"19173 Edinborough Rd",
    "sg:city":"Detroit",
    "sg:classifiers":[
        {
            "category":"Retail",
            "subcategory":"Auto Repair",
            "type":"Services"
        }
    ],
    "sg:phone":"+1 313 533 2067",
    "sg:postcode":"48219",
    "sg:province":"MI",
    "sg:tags":[
        "automotive"
    ],
    "wof:name":"Big Red Towing and Recovery",
    "wof:placetype":"venue"
},
  "geometry": {"coordinates":[-83.234663,42.430806],"type":"Point"}
}