{
  "type": "Feature",
  "properties": {
    "iso:country":"US",
    "sg:address":"41962 Plumtree Dr",
    "sg:city":"Sterling Heights",
    "sg:classifiers":[
        {
            "category":"Freight",
            "type":"Transportation"
        }
    ],
    "sg:phone":"+1 586 997 1049",
    "sg:postcode":"48314",
    "sg:province":"MI",
    "sg:tags":[
        "operator",
        "local",
        "trucking"
    ],
    "wof:name":"Hallak Food Delivery",
    "wof:placetype":"venue"
},
  "geometry": {"coordinates":[-83.06707,42.600518],"type":"Point"}
}