{
  "type": "Feature",
  "properties": {
    "iso:country":"US",
    "sg:address":"27631 Southfield Rd",
    "sg:city":"Lathrup Village",
    "sg:classifiers":[
        {
            "category":"Retail",
            "subcategory":"Portrait Studio",
            "type":"Services"
        }
    ],
    "sg:phone":"+1 248 855 4300",
    "sg:postcode":"48076",
    "sg:province":"MI",
    "sg:tags":[
        "photographer",
        "photo"
    ],
    "wof:name":"Fox Portrait Studio Inc",
    "wof:placetype":"venue"
},
  "geometry": {"coordinates":[-83.222227,42.493698],"type":"Point"}
}