{
  "type": "Feature",
  "properties": {
    "iso:country":"US",
    "sg:address":"629 N Main St",
    "sg:city":"Cheboygan",
    "sg:classifiers":[
        {
            "category":"Retail",
            "subcategory":"Funeral Services",
            "type":"Services"
        }
    ],
    "sg:phone":"+1 231 627 9987",
    "sg:postcode":"49721",
    "sg:province":"MI",
    "sg:tags":[
        "director"
    ],
    "wof:name":"Christian Funeral Home Inc",
    "wof:placetype":"venue"
},
  "geometry": {"coordinates":[-84.473884,45.647935],"type":"Point"}
}