{
  "type": "Feature",
  "properties": {
    "iso:country":"US",
    "sg:address":"6850 Mill Wheel Dr",
    "sg:city":"Lansing",
    "sg:classifiers":[
        {
            "category":"Social Services",
            "subcategory":"Child Care",
            "type":"Services"
        }
    ],
    "sg:phone":"+1 517 699 5036",
    "sg:postcode":"48911",
    "sg:province":"MI",
    "sg:tags":[
        "day"
    ],
    "wof:name":"Cindy Ousley",
    "wof:placetype":"venue"
},
  "geometry": {"coordinates":[-84.529963,42.657311],"type":"Point"}
}