{
  "type": "Feature",
  "properties": {
    "iso:country":"US",
    "sg:address":"16100 J Dr S",
    "sg:city":"Marshall",
    "sg:classifiers":[
        {
            "category":"Building & Trades",
            "subcategory":"Construction",
            "type":"Services"
        }
    ],
    "sg:phone":"+1 269 781 9708",
    "sg:postcode":"49068",
    "sg:province":"MI",
    "sg:tags":[
        "house"
    ],
    "wof:name":"Mike Cole Builder",
    "wof:placetype":"venue"
},
  "geometry": {"coordinates":[-84.963846,42.173957],"type":"Point"}
}