{
  "type": "Feature",
  "properties": {
    "iso:country":"US",
    "sg:address":"12980 Hubbard Lake Rd",
    "sg:city":"Hubbard Lake",
    "sg:classifiers":[
        {
            "category":"Real Estate",
            "subcategory":"Developer",
            "type":"Services"
        }
    ],
    "sg:phone":"+1 989 727 2471",
    "sg:postcode":"49747",
    "sg:province":"MI",
    "wof:name":"A & G Land Inc",
    "wof:placetype":"venue"
},
  "geometry": {"coordinates":[-83.587389,44.888705],"type":"Point"}
}