{
  "type": "Feature",
  "properties": {
    "iso:country":"US",
    "sg:address":"11345 Challion Dr",
    "sg:city":"Fair Haven",
    "sg:classifiers":[
        {
            "category":"Wholesale",
            "subcategory":"Vending Machines",
            "type":"Manufacturing & Wholesale Goods"
        }
    ],
    "sg:phone":"+1 586 725 0728",
    "sg:postcode":"48023",
    "sg:province":"MI",
    "sg:tags":[
        "operator"
    ],
    "wof:name":"Dan Kel Inc",
    "wof:placetype":"venue"
},
  "geometry": {"coordinates":[-82.713425,42.695698],"type":"Point"}
}