{
  "type": "Feature",
  "properties": {
    "iso:country":"US",
    "sg:address":"10216 Huron St",
    "sg:city":"Goodrich",
    "sg:classifiers":[
        {
            "category":"Organizations",
            "subcategory":"Religious Organization",
            "type":"Services"
        }
    ],
    "sg:phone":"+1 810 636 2182",
    "sg:postcode":"48438",
    "sg:province":"MI",
    "sg:tags":[
        "church"
    ],
    "wof:name":"Goodrich Assembly Of God",
    "wof:placetype":"venue"
},
  "geometry": {"coordinates":[-83.506315,42.915534],"type":"Point"}
}