{
  "type": "Feature",
  "properties": {
    "iso:country":"US",
    "sg:address":"901 Michigan St",
    "sg:city":"Port Huron",
    "sg:classifiers":[
        {
            "category":"Social Services",
            "subcategory":"Child Care",
            "type":"Services"
        }
    ],
    "sg:phone":"+1 810 364 3165",
    "sg:postcode":"48060",
    "sg:province":"MI",
    "wof:name":"Marysville Children's Ctr",
    "wof:placetype":"venue"
},
  "geometry": {"coordinates":[-82.423498,42.984265],"type":"Point"}
}