{
  "type": "Feature",
  "properties": {
    "iso:country":"US",
    "sg:address":"510 Simons St",
    "sg:city":"Coleman",
    "sg:classifiers":[
        {
            "category":"Shopping",
            "type":"Retail Goods"
        },
        {
            "category":"Building & Trades",
            "subcategory":"Construction",
            "type":"Services"
        }
    ],
    "sg:phone":"+1 989 465 0000",
    "sg:postcode":"48618",
    "sg:province":"MI",
    "sg:tags":[
        "excavation",
        "miscellaneous",
        "store",
        "contractor"
    ],
    "wof:name":"Whitman Clipper Sharpening",
    "wof:placetype":"venue"
},
  "geometry": {"coordinates":[-84.587818,43.762348],"type":"Point"}
}