{
  "type": "Feature",
  "properties": {
    "iso:country":"US",
    "sg:address":"2953 Walsh Dr",
    "sg:city":"Rochester",
    "sg:classifiers":[
        {
            "category":"Professional",
            "subcategory":"Business Services",
            "type":"Services"
        }
    ],
    "sg:phone":"+1 248 852 2303",
    "sg:postcode":"48309",
    "sg:province":"MI",
    "sg:tags":[
        "marketing"
    ],
    "wof:name":"Kittyhawk Studios",
    "wof:placetype":"venue"
},
  "geometry": {"coordinates":[-83.15543599999999,42.638672],"type":"Point"}
}