{
  "type": "Feature",
  "properties": {
    "iso:country":"US",
    "sg:address":"26755 Ballard St",
    "sg:city":"Harrison Township",
    "sg:classifiers":[
        {
            "category":"Health Services",
            "subcategory":"Doctor",
            "type":"Services"
        }
    ],
    "sg:phone":"+1 586 463 6411",
    "sg:postcode":"48045",
    "sg:province":"MI",
    "sg:tags":[
        "osteopathic"
    ],
    "wof:name":"Bruce D Miller Do PC",
    "wof:placetype":"venue"
},
  "geometry": {"coordinates":[-82.855507,42.56893],"type":"Point"}
}