{
  "type": "Feature",
  "properties": {
    "iso:country":"US",
    "sg:address":"328 S Jefferson St",
    "sg:city":"Hastings",
    "sg:classifiers":[
        {
            "category":"Organizations",
            "subcategory":"Political Organization",
            "type":"Services"
        },
        {
            "category":"Recreation",
            "type":"Entertainment"
        }
    ],
    "sg:phone":"+1 269 945 3345",
    "sg:postcode":"49058",
    "sg:province":"MI",
    "sg:tags":[
        "hall",
        "auditorium"
    ],
    "wof:name":"Barry County Democratic Party",
    "wof:placetype":"venue"
},
  "geometry": {"coordinates":[-85.287639,42.646594],"type":"Point"}
}