{
  "type": "Feature",
  "properties": {
    "iso:country":"US",
    "sg:address":"65 Schroeder Park Dr",
    "sg:city":"Howell",
    "sg:classifiers":[
        {
            "category":"Retail",
            "subcategory":"Auto Rental",
            "type":"Services"
        }
    ],
    "sg:phone":"+1 517 545 1519",
    "sg:postcode":"48843",
    "sg:province":"MI",
    "sg:tags":[
        "renting",
        "automobile"
    ],
    "wof:name":"Quality Car Rental",
    "wof:placetype":"venue"
},
  "geometry": {"coordinates":[-83.93314100000001,42.58561],"type":"Point"}
}