{
  "type": "Feature",
  "properties": {
    "iso:country":"US",
    "sg:address":"6430 Appoline St",
    "sg:city":"Dearborn",
    "sg:classifiers":[
        {
            "category":"Home & Garden",
            "subcategory":"Hardware",
            "type":"Retail Goods"
        }
    ],
    "sg:phone":"+1 313 581 4471",
    "sg:postcode":"48126",
    "sg:province":"MI",
    "wof:name":"True Comfort",
    "wof:placetype":"venue"
},
  "geometry": {"coordinates":[-83.167888,42.337721],"type":"Point"}
}