{
  "type": "Feature",
  "properties": {
    "iso:country":"US",
    "sg:address":"47517 Putney Ct",
    "sg:city":"Canton",
    "sg:classifiers":[
        {
            "category":"Manufacturing",
            "subcategory":"Tools & Machinery",
            "type":"Manufacturing & Wholesale Goods"
        }
    ],
    "sg:phone":"+1 734 495 0095",
    "sg:postcode":"48188",
    "sg:province":"MI",
    "sg:tags":[
        "electric",
        "mfg",
        "residential",
        "fixture",
        "lamp",
        "lighting"
    ],
    "wof:name":"Brightlights Technologies",
    "wof:placetype":"venue"
},
  "geometry": {"coordinates":[-83.509045,42.29696],"type":"Point"}
}