{
  "type": "Feature",
  "properties": {
    "iso:country":"US",
    "sg:address":"19 Gerber Ave",
    "sg:city":"Fremont",
    "sg:classifiers":[
        {
            "category":"Home & Garden",
            "subcategory":"Household Appliances",
            "type":"Retail Goods"
        }
    ],
    "sg:phone":"+1 231 924 2090",
    "sg:postcode":"49412",
    "sg:province":"MI",
    "sg:tags":[
        "cleaners",
        "vacuum"
    ],
    "wof:name":"Vac Shop",
    "wof:placetype":"venue"
},
  "geometry": {"coordinates":[-85.952547,43.466967],"type":"Point"}
}