{
  "type": "Feature",
  "properties": {
    "iso:country":"US",
    "sg:address":"803 10th St",
    "sg:city":"Port Huron",
    "sg:classifiers":[
        {
            "category":"Professional",
            "subcategory":"Lawyer & Legal Services",
            "type":"Services"
        }
    ],
    "sg:phone":"+1 810 985 5107",
    "sg:postcode":"48060",
    "sg:province":"MI",
    "wof:name":"Legal Aid",
    "wof:placetype":"venue"
},
  "geometry": {"coordinates":[-82.433162,42.975402],"type":"Point"}
}