{
  "type": "Feature",
  "properties": {
    "iso:country":"US",
    "sg:address":"1210 E Columbia Ave",
    "sg:city":"Battle Creek",
    "sg:classifiers":[
        {
            "category":"Shopping",
            "subcategory":"Musical Instruments",
            "type":"Retail Goods"
        }
    ],
    "sg:phone":"+1 269 965 7044",
    "sg:postcode":"49014",
    "sg:province":"MI",
    "wof:name":"Music Place",
    "wof:placetype":"venue"
},
  "geometry": {"coordinates":[-85.164181,42.301521],"type":"Point"}
}