{
  "type": "Feature",
  "properties": {
    "iso:country":"US",
    "sg:address":"1267 Hudson St SW",
    "sg:city":"Grand Rapids",
    "sg:classifiers":[
        {
            "category":"Building & Trades",
            "subcategory":"Landscaping Services",
            "type":"Services"
        }
    ],
    "sg:phone":"+1 616 245 8098",
    "sg:postcode":"49509",
    "sg:province":"MI",
    "sg:tags":[
        "landscape",
        "contractor"
    ],
    "wof:name":"Grand View Lawn Care",
    "wof:placetype":"venue"
},
  "geometry": {"coordinates":[-85.69874,42.929476],"type":"Point"}
}