{
  "type": "Feature",
  "properties": {
    "iso:country":"US",
    "sg:address":"19794 Capital Ave NE",
    "sg:city":"Battle Creek",
    "sg:classifiers":[
        {
            "category":"Sports & Exercise",
            "subcategory":"Bowling",
            "type":"Entertainment"
        }
    ],
    "sg:phone":"+1 269 962 9597",
    "sg:postcode":"49017",
    "sg:province":"MI",
    "sg:tags":[
        "drinking",
        "center"
    ],
    "wof:name":"M-66 Bowl Inc",
    "wof:placetype":"venue"
},
  "geometry": {"coordinates":[-85.15060800000001,42.357598],"type":"Point"}
}