{
  "type": "Feature",
  "properties": {
    "iso:country":"US",
    "sg:address":"1100 Otter Ave",
    "sg:city":"Waterford",
    "sg:classifiers":[
        {
            "category":"Wholesale",
            "subcategory":"Fruits & Vegetables",
            "type":"Manufacturing & Wholesale Goods"
        }
    ],
    "sg:phone":"+1 248 681 9020",
    "sg:postcode":"48328",
    "sg:province":"MI",
    "sg:tags":[
        "produce",
        "broker"
    ],
    "wof:name":"AAA Produce Exchange",
    "wof:placetype":"venue"
},
  "geometry": {"coordinates":[-83.347932,42.621455],"type":"Point"}
}