{
  "type": "Feature",
  "properties": {
    "iso:country":"US",
    "sg:address":"5655 Pingree Rd",
    "sg:city":"Howell",
    "sg:classifiers":[
        {
            "category":"Professional",
            "type":"Services"
        }
    ],
    "sg:phone":"+1 734 878 0862",
    "sg:postcode":"48843",
    "sg:province":"MI",
    "wof:name":"D-Tec Svc",
    "wof:placetype":"venue"
},
  "geometry": {"coordinates":[-84.019023,42.515953],"type":"Point"}
}