{
  "type": "Feature",
  "properties": {
    "iso:country":"US",
    "sg:address":"6614 Cypress St",
    "sg:city":"Portage",
    "sg:classifiers":[
        {
            "category":"Organizations",
            "subcategory":"Community Association",
            "type":"Services"
        }
    ],
    "sg:phone":"+1 269 329 4071",
    "sg:postcode":"49024",
    "sg:province":"MI",
    "sg:tags":[
        "club"
    ],
    "wof:name":"West Michigan Elite",
    "wof:placetype":"venue"
},
  "geometry": {"coordinates":[-85.620698,42.222247],"type":"Point"}
}