{
  "type": "Feature",
  "properties": {
    "iso:country":"US",
    "sg:address":"24361 Greenfield Rd",
    "sg:city":"Southfield",
    "sg:classifiers":[
        {
            "category":"Banks & Credit Unions",
            "subcategory":"Investment Brokerage",
            "type":"Services"
        }
    ],
    "sg:phone":"+1 248 443 7412",
    "sg:postcode":"48075",
    "sg:province":"MI",
    "sg:tags":[
        "consultant",
        "financing"
    ],
    "wof:name":"K B & Kb Intl",
    "wof:placetype":"venue"
},
  "geometry": {"coordinates":[-83.201632,42.469817],"type":"Point"}
}