{
  "type": "Feature",
  "properties": {
    "iso:country":"US",
    "sg:address":"4078 W Shore Ct",
    "sg:city":"Newport",
    "sg:classifiers":[
        {
            "category":"Organizations",
            "subcategory":"Community Association",
            "type":"Services"
        }
    ],
    "sg:phone":"+1 734 289 3354",
    "sg:postcode":"48166",
    "sg:province":"MI",
    "wof:name":"Bay West Est Homeowners",
    "wof:placetype":"venue"
},
  "geometry": {"coordinates":[-83.29673200000001,41.947953],"type":"Point"}
}