{
  "type": "Feature",
  "properties": {
    "iso:country":"US",
    "sg:address":"23980 Meadowbrook Rd",
    "sg:city":"Novi",
    "sg:classifiers":[
        {
            "category":"Building & Trades",
            "subcategory":"Construction",
            "type":"Services"
        }
    ],
    "sg:phone":"+1 248 474 7012",
    "sg:postcode":"48375",
    "sg:province":"MI",
    "sg:tags":[
        "carpentry",
        "contractor"
    ],
    "wof:name":"Sherwood Services",
    "wof:placetype":"venue"
},
  "geometry": {"coordinates":[-83.455063,42.466454],"type":"Point"}
}