{
  "type": "Feature",
  "properties": {
    "iso:country":"US",
    "sg:address":"53700 N Foster Rd",
    "sg:city":"Chesterfield",
    "sg:classifiers":[
        {
            "category":"Building & Trades",
            "subcategory":"Cleaning & Sanitation",
            "type":"Services"
        }
    ],
    "sg:phone":"+1 586 749 8272",
    "sg:postcode":"48051",
    "sg:province":"MI",
    "sg:tags":[
        "fireplace",
        "chimney"
    ],
    "wof:name":"A Chimney Repairs Of Macomb",
    "wof:placetype":"venue"
},
  "geometry": {"coordinates":[-82.79792,42.693719],"type":"Point"}
}