{
  "type": "Feature",
  "properties": {
    "iso:country":"US",
    "sg:address":"8350 Jenks Rd",
    "sg:city":"Harbor Beach",
    "sg:classifiers":[
        {
            "category":"Building & Trades",
            "subcategory":"Construction",
            "type":"Services"
        }
    ],
    "sg:phone":"+1 989 479 9918",
    "sg:postcode":"48441",
    "sg:province":"MI",
    "sg:tags":[
        "house"
    ],
    "wof:name":"Ruppel Construction & Sand Co",
    "wof:placetype":"venue"
},
  "geometry": {"coordinates":[-82.69221899999999,43.818034],"type":"Point"}
}