{
  "type": "Feature",
  "properties": {
    "iso:country":"US",
    "sg:address":"8178 23 Mile Rd",
    "sg:city":"Utica",
    "sg:classifiers":[
        {
            "category":"Restaurant",
            "type":"Food & Drink"
        }
    ],
    "sg:menulink":"http://www.allmenus.com/mi/shelby/142407-subway/menu/",
    "sg:phone":"+1 586 739 4100",
    "sg:postcode":"48316",
    "sg:province":"MI",
    "sg:tags":[
        "american",
        "sandwich"
    ],
    "wof:name":"Subway",
    "wof:placetype":"venue"
},
  "geometry": {"coordinates":[-83.031873,42.669585],"type":"Point"}
}