{
  "type": "Feature",
  "properties": {
    "iso:country":"US",
    "sg:address":"2895 Main St",
    "sg:city":"Marlette",
    "sg:classifiers":[
        {
            "category":"Restaurant",
            "type":"Food & Drink"
        }
    ],
    "sg:menulink":"http://www.allmenus.com/mi/marlette/146337-subway/menu/",
    "sg:phone":"+1 989 635 5481",
    "sg:postcode":"48453",
    "sg:province":"MI",
    "sg:tags":[
        "american",
        "sandwich"
    ],
    "wof:name":"Subway",
    "wof:placetype":"venue"
},
  "geometry": {"coordinates":[-83.079947,43.33113],"type":"Point"}
}