{
  "type": "Feature",
  "properties": {
    "iso:country":"US",
    "sg:address":"801 S Adams Rd",
    "sg:city":"Birmingham",
    "sg:classifiers":[
        {
            "category":"Real Estate",
            "subcategory":"Developer",
            "type":"Services"
        }
    ],
    "sg:phone":"+1 248 723 1770",
    "sg:postcode":"48009",
    "sg:province":"MI",
    "wof:name":"Timlin Building & Development",
    "wof:placetype":"venue"
},
  "geometry": {"coordinates":[-83.205439,42.540701],"type":"Point"}
}