{
  "type": "Feature",
  "properties": {
    "iso:country":"US",
    "sg:address":"2727 Walker Ave NW",
    "sg:city":"Grand Rapids",
    "sg:classifiers":[
        {
            "category":"Banks & Credit Unions",
            "subcategory":"Investment Brokerage",
            "type":"Services"
        }
    ],
    "sg:phone":"+1 616 791 4037",
    "sg:postcode":"49544",
    "sg:province":"MI",
    "sg:tags":[
        "advisory",
        "financial"
    ],
    "wof:name":"GE Consumer Finance",
    "wof:placetype":"venue"
},
  "geometry": {"coordinates":[-85.72277099999999,43.011818],"type":"Point"}
}