{
  "type": "Feature",
  "properties": {
    "iso:country":"US",
    "sg:address":"225 W Houghton Lake Dr",
    "sg:city":"Prudenville",
    "sg:classifiers":[
        {
            "category":"Retail",
            "subcategory":"Car Wash",
            "type":"Services"
        }
    ],
    "sg:phone":"+1 989 366 4828",
    "sg:postcode":"48651",
    "sg:province":"MI",
    "sg:tags":[
        "carwash"
    ],
    "wof:name":"Eastbay Car Wash LLC",
    "wof:placetype":"venue"
},
  "geometry": {"coordinates":[-84.64264300000001,44.303673],"type":"Point"}
}