{
  "type": "Feature",
  "properties": {
    "iso:country":"US",
    "sg:address":"7815 E Jefferson Ave",
    "sg:city":"Detroit",
    "sg:classifiers":[
        {
            "category":"Health Services",
            "subcategory":"Doctor",
            "type":"Services"
        }
    ],
    "sg:phone":"+1 313 499 4170",
    "sg:postcode":"48214",
    "sg:province":"MI",
    "sg:tags":[
        "medical"
    ],
    "wof:name":"Detroit Riverview Hospital",
    "wof:placetype":"venue"
},
  "geometry": {"coordinates":[-82.995358,42.35108],"type":"Point"}
}