{
  "type": "Feature",
  "properties": {
    "iso:country":"US",
    "sg:address":"1423 S Milford Rd",
    "sg:city":"Highland",
    "sg:classifiers":[
        {
            "category":"Banks & Credit Unions",
            "subcategory":"Bank",
            "type":"Services"
        }
    ],
    "sg:phone":"+1 248 889 9797",
    "sg:postcode":"48357",
    "sg:province":"MI",
    "sg:tags":[
        "broker",
        "mortgage"
    ],
    "wof:name":"Holly Financial Inc",
    "wof:placetype":"venue"
},
  "geometry": {"coordinates":[-83.616359,42.628248],"type":"Point"}
}