{
  "type": "Feature",
  "properties": {
    "iso:country":"US",
    "sg:address":"3556 Cambria Rd",
    "sg:city":"Hillsdale",
    "sg:classifiers":[
        {
            "category":"Retail",
            "subcategory":"Auto Repair",
            "type":"Services"
        }
    ],
    "sg:phone":"+1 517 437 9353",
    "sg:postcode":"49242",
    "sg:province":"MI",
    "sg:tags":[
        "body",
        "automobile",
        "painting"
    ],
    "wof:name":"Zekes Collision",
    "wof:placetype":"venue"
},
  "geometry": {"coordinates":[-84.650868,41.875097],"type":"Point"}
}