{
  "type": "Feature",
  "properties": {
    "iso:country":"US",
    "sg:address":"213 N Angola Rd",
    "sg:city":"Coldwater",
    "sg:classifiers":[
        {
            "category":"Autos & Motor Vehicles",
            "subcategory":"Auto Supplies",
            "type":"Retail Goods"
        }
    ],
    "sg:phone":"+1 517 279 9383",
    "sg:postcode":"49036",
    "sg:province":"MI",
    "sg:tags":[
        "tire"
    ],
    "wof:name":"Pell's Tire Svc Large Tire Ctr",
    "wof:placetype":"venue"
},
  "geometry": {"coordinates":[-85.004915,41.906669],"type":"Point"}
}