{
  "type": "Feature",
  "properties": {
    "iso:country":"US",
    "sg:address":"2849 Miller Rd",
    "sg:city":"Flint",
    "sg:classifiers":[
        {
            "category":"Real Estate",
            "subcategory":"Real Estate Agent",
            "type":"Services"
        },
        {
            "category":"Professional",
            "subcategory":"Business Services",
            "type":"Services"
        }
    ],
    "sg:phone":"+1 810 234 8007",
    "sg:postcode":"48503",
    "sg:province":"MI",
    "sg:tags":[
        "appraiser"
    ],
    "wof:name":"John Biff Snyder & Associates",
    "wof:placetype":"venue"
},
  "geometry": {"coordinates":[-83.723528,42.996574],"type":"Point"}
}