{
  "type": "Feature",
  "properties": {
    "iso:country":"US",
    "sg:address":"31226 Fraser Dr",
    "sg:city":"Fraser",
    "sg:classifiers":[
        {
            "category":"Building & Trades",
            "subcategory":"Plumbing",
            "type":"Services"
        }
    ],
    "sg:phone":"+1 586 293 4300",
    "sg:postcode":"48026",
    "sg:province":"MI",
    "wof:name":"Eastern Mechanical Inc",
    "wof:placetype":"venue"
},
  "geometry": {"coordinates":[-82.951599,42.525799],"type":"Point"}
}