{
  "type": "Feature",
  "properties": {
    "iso:country":"US",
    "sg:address":"2279 N Park Dr",
    "sg:city":"Holland",
    "sg:classifiers":[
        {
            "category":"Professional",
            "subcategory":"Accounting & Tax Preparation",
            "type":"Services"
        }
    ],
    "sg:phone":"+1 616 355 6200",
    "sg:postcode":"49424",
    "sg:province":"MI",
    "sg:tags":[
        "return",
        "filing"
    ],
    "wof:name":"H & R Block Tax Svc",
    "wof:placetype":"venue"
},
  "geometry": {"coordinates":[-86.08923299999999,42.810522],"type":"Point"}
}