{
  "type": "Feature",
  "properties": {
    "iso:country":"US",
    "sg:address":"4157 Bronson Blvd",
    "sg:city":"Kalamazoo",
    "sg:classifiers":[
        {
            "category":"Professional",
            "subcategory":"Management & Consulting",
            "type":"Services"
        }
    ],
    "sg:phone":"+1 269 345 3329",
    "sg:postcode":"49008",
    "sg:province":"MI",
    "sg:tags":[
        "consultant",
        "health",
        "care"
    ],
    "wof:name":"Healthcare Consulting Assoc",
    "wof:placetype":"venue"
},
  "geometry": {"coordinates":[-85.60068800000001,42.249385],"type":"Point"}
}