{
  "type": "Feature",
  "properties": {
    "iso:country":"US",
    "sg:address":"7125 Orchard Lake Rd",
    "sg:city":"West Bloomfield",
    "sg:classifiers":[
        {
            "category":"Building & Trades",
            "subcategory":"Construction",
            "type":"Services"
        }
    ],
    "sg:phone":"+1 248 865 1600",
    "sg:postcode":"48322",
    "sg:province":"MI",
    "sg:tags":[
        "contractor"
    ],
    "wof:name":"Singh Development",
    "wof:placetype":"venue"
},
  "geometry": {"coordinates":[-83.36019899999999,42.533401],"type":"Point"}
}