{
  "type": "Feature",
  "properties": {
    "iso:country":"US",
    "sg:address":"2500 Brockman Blvd",
    "sg:city":"Ann Arbor",
    "sg:classifiers":[
        {
            "category":"Professional",
            "subcategory":"Research",
            "type":"Services"
        }
    ],
    "sg:phone":"+1 734 332 6064",
    "sg:postcode":"48104",
    "sg:province":"MI",
    "sg:tags":[
        "occupational",
        "health"
    ],
    "wof:name":"White Pine OCC Hlth Rsrch LLC",
    "wof:placetype":"venue"
},
  "geometry": {"coordinates":[-83.71986699999999,42.259896],"type":"Point"}
}