{
  "type": "Feature",
  "properties": {
    "iso:country":"US",
    "sg:address":"13970 Golfview St",
    "sg:city":"Livonia",
    "sg:classifiers":[
        {
            "category":"Social Services",
            "subcategory":"Child Care",
            "type":"Services"
        }
    ],
    "sg:phone":"+1 734 591 1367",
    "sg:postcode":"48154",
    "sg:province":"MI",
    "sg:tags":[
        "home",
        "day"
    ],
    "wof:name":"Sues Daycare",
    "wof:placetype":"venue"
},
  "geometry": {"coordinates":[-83.397131,42.382835],"type":"Point"}
}