{
  "type": "Feature",
  "properties": {
    "iso:country":"US",
    "sg:address":"200 S Washington Ave",
    "sg:city":"Royal Oak",
    "sg:classifiers":[
        {
            "category":"Communications",
            "type":"Services"
        }
    ],
    "sg:phone":"+1 248 548 1662",
    "sg:postcode":"48067",
    "sg:province":"MI",
    "sg:tags":[
        "web",
        "design"
    ],
    "wof:name":"What Webs We and Weave Llc",
    "wof:placetype":"venue"
},
  "geometry": {"coordinates":[-83.146806,42.488895],"type":"Point"}
}