{
  "type": "Feature",
  "properties": {
    "iso:country":"US",
    "sg:address":"900 Auburn Ave",
    "sg:city":"Pontiac",
    "sg:classifiers":[
        {
            "category":"Health Services",
            "subcategory":"Health Practitioner",
            "type":"Services"
        }
    ],
    "sg:phone":"+1 248 332 8600",
    "sg:postcode":"48342",
    "sg:province":"MI",
    "sg:tags":[
        "therapy",
        "physical"
    ],
    "wof:name":"W B Sterling & Associates",
    "wof:placetype":"venue"
},
  "geometry": {"coordinates":[-83.258797,42.634998],"type":"Point"}
}