{
  "type": "Feature",
  "properties": {
    "iso:country":"US",
    "sg:address":"2141 Plainfield Ave NE",
    "sg:city":"Grand Rapids",
    "sg:classifiers":[
        {
            "category":"Shopping",
            "type":"Retail Goods"
        }
    ],
    "sg:phone":"+1 616 363 5151",
    "sg:postcode":"49505",
    "sg:province":"MI",
    "sg:tags":[
        "monument"
    ],
    "wof:name":"Grand Rapids Monument Inc",
    "wof:placetype":"venue"
},
  "geometry": {"coordinates":[-85.654302,43.001986],"type":"Point"}
}