{
  "type": "Feature",
  "properties": {
    "iso:country":"US",
    "sg:address":"738 64th Ave",
    "sg:city":"Zeeland",
    "sg:classifiers":[
        {
            "category":"Utilities",
            "subcategory":"Telephone",
            "type":"Services"
        }
    ],
    "sg:phone":"+1 616 688 5571",
    "sg:postcode":"49464",
    "sg:province":"MI",
    "sg:tags":[
        "company"
    ],
    "sg:website":"www.drenthe.com",
    "wof:name":"Drenthe Telephone & Comms",
    "wof:placetype":"venue"
},
  "geometry": {"coordinates":[-85.940456,42.778491],"type":"Point"}
}