{
  "type": "Feature",
  "properties": {
    "iso:country":"US",
    "sg:address":"6732 Maxwell Ave",
    "sg:city":"Warren",
    "sg:classifiers":[
        {
            "category":"Retail",
            "subcategory":"Auto Repair",
            "type":"Services"
        }
    ],
    "sg:phone":"+1 586 757 0295",
    "sg:postcode":"48091",
    "sg:province":"MI",
    "sg:tags":[
        "repairing",
        "automobile"
    ],
    "wof:name":"T Q Automotive Inc",
    "wof:placetype":"venue"
},
  "geometry": {"coordinates":[-83.03257000000001,42.461243],"type":"Point"}
}