{
  "type": "Feature",
  "properties": {
    "iso:country":"US",
    "sg:address":"9222 Marine City Hwy",
    "sg:city":"Casco",
    "sg:classifiers":[
        {
            "category":"Building & Trades",
            "subcategory":"Electrical",
            "type":"Services"
        }
    ],
    "sg:phone":"+1 586 716 9422",
    "sg:postcode":"48064",
    "sg:province":"MI",
    "sg:tags":[
        "electric",
        "contractor"
    ],
    "wof:name":"Mc Kenzie's Electric",
    "wof:placetype":"venue"
},
  "geometry": {"coordinates":[-82.676337,42.722817],"type":"Point"}
}