{
  "type": "Feature",
  "properties": {
    "iso:country":"US",
    "sg:address":"536 Bingham Ave",
    "sg:city":"Sault Ste Marie",
    "sg:classifiers":[
        {
            "category":"Banks & Credit Unions",
            "subcategory":"Bank",
            "type":"Services"
        }
    ],
    "sg:phone":"+1 906 632 6819",
    "sg:postcode":"49783",
    "sg:province":"MI",
    "sg:website":"www.soocoop.com",
    "wof:name":"Soo Co-Op Credit Union",
    "wof:placetype":"venue"
},
  "geometry": {"coordinates":[-84.347026,46.494886],"type":"Point"}
}