{
  "type": "Feature",
  "properties": {
    "iso:country":"US",
    "sg:address":"214 N 2nd St",
    "sg:city":"Niles",
    "sg:classifiers":[
        {
            "category":"Building & Trades",
            "subcategory":"Equipment Rental",
            "type":"Services"
        }
    ],
    "sg:phone":"+1 269 684 2646",
    "sg:postcode":"49120",
    "sg:province":"MI",
    "sg:tags":[
        "leasing"
    ],
    "wof:name":"Chansage",
    "wof:placetype":"venue"
},
  "geometry": {"coordinates":[-86.257475,41.83005],"type":"Point"}
}