{
  "type": "Feature",
  "properties": {
    "iso:country":"US",
    "sg:address":"6271 Patagonia Dr SE",
    "sg:city":"Grand Rapids",
    "sg:classifiers":[
        {
            "category":"Building & Trades",
            "subcategory":"Landscaping Services",
            "type":"Services"
        }
    ],
    "sg:phone":"+1 616 575 0727",
    "sg:postcode":"49546",
    "sg:province":"MI",
    "sg:tags":[
        "landscape",
        "contractor"
    ],
    "wof:name":"JLH Lawncare & Landscaping",
    "wof:placetype":"venue"
},
  "geometry": {"coordinates":[-85.512327,42.919053],"type":"Point"}
}