{
  "type": "Feature",
  "properties": {
    "iso:country":"US",
    "sg:address":"22041 Woodward Ave",
    "sg:city":"Ferndale",
    "sg:classifiers":[
        {
            "category":"Arts & Performance",
            "subcategory":"Arts Center",
            "type":"Entertainment"
        },
        {
            "category":"Personal",
            "type":"Services"
        },
        {
            "category":"Communications",
            "subcategory":"Newspaper",
            "type":"Services"
        }
    ],
    "sg:phone":"+1 248 398 3400",
    "sg:postcode":"48220",
    "sg:province":"MI",
    "sg:tags":[
        "print",
        "medium",
        "local"
    ],
    "sg:website":"www.metroparent.com",
    "wof:name":"Metro Parent Magazine",
    "wof:placetype":"venue"
},
  "geometry": {"coordinates":[-83.131229,42.455011],"type":"Point"}
}