{
  "type": "Feature",
  "properties": {
    "iso:country":"US",
    "sg:address":"27566 Northwestern Hwy",
    "sg:city":"Southfield",
    "sg:classifiers":[
        {
            "category":"Restaurant",
            "type":"Food & Drink"
        }
    ],
    "sg:phone":"+1 248 827 1600",
    "sg:postcode":"48034",
    "sg:province":"MI",
    "sg:tags":[
        "korean"
    ],
    "sg:website":"www.newseoulgarden.com/",
    "wof:name":"New Seoul Garden Restaurant",
    "wof:placetype":"venue"
},
  "geometry": {"coordinates":[-83.28243000000001,42.491836],"type":"Point"}
}