{
  "type": "Feature",
  "properties": {
    "iso:country":"US",
    "sg:address":"4141 Ramblewood Dr",
    "sg:city":"Troy",
    "sg:classifiers":[
        {
            "category":"Building & Trades",
            "subcategory":"Construction",
            "type":"Services"
        }
    ],
    "sg:phone":"+1 248 740 2782",
    "sg:postcode":"48085",
    "sg:province":"MI",
    "sg:tags":[
        "hanging",
        "contractor"
    ],
    "wof:name":"Evergreen Painting & Decoratin",
    "wof:placetype":"venue"
},
  "geometry": {"coordinates":[-83.10093999999999,42.580975],"type":"Point"}
}