{
  "type": "Feature",
  "properties": {
    "iso:country":"US",
    "sg:address":"28558-B Dequindre",
    "sg:city":"Warren",
    "sg:classifiers":[
        {
            "category":"Personal",
            "type":"Services"
        }
    ],
    "sg:phone":"+1 586 751 3303",
    "sg:postcode":"48092",
    "sg:province":"MI",
    "sg:tags":[
        "planning",
        "alteration",
        "sewing",
        "wedding"
    ],
    "wof:name":"Universal Tailors",
    "wof:placetype":"venue"
},
  "geometry": {"coordinates":[-83.0855,42.502183],"type":"Point"}
}