{
  "type": "Feature",
  "properties": {
    "iso:country":"US",
    "sg:address":"27670 Wagner Dr",
    "sg:city":"Warren",
    "sg:classifiers":[
        {
            "category":"Professional",
            "subcategory":"Business Services",
            "type":"Services"
        }
    ],
    "sg:phone":"+1 586 754 6059",
    "sg:postcode":"48093",
    "sg:province":"MI",
    "sg:tags":[
        "repair",
        "on",
        "ground",
        "pool",
        "swimming"
    ],
    "wof:name":"Sardelli Mike Pool Service",
    "wof:placetype":"venue"
},
  "geometry": {"coordinates":[-83.00106700000001,42.499572],"type":"Point"}
}