{
  "type": "Feature",
  "properties": {
    "iso:country":"US",
    "sg:address":"118 Midway Dr",
    "sg:city":"Negaunee",
    "sg:classifiers":[
        {
            "category":"Wholesale",
            "subcategory":"Construction Materials",
            "type":"Manufacturing & Wholesale Goods"
        }
    ],
    "sg:phone":"+1 906 475 9816",
    "sg:postcode":"49866",
    "sg:province":"MI",
    "sg:tags":[
        "concrete",
        "product"
    ],
    "wof:name":"Rudy Goupille & Sons Inc",
    "wof:placetype":"venue"
},
  "geometry": {"coordinates":[-87.523415,46.539529],"type":"Point"}
}