{
  "type": "Feature",
  "properties": {
    "iso:country":"US",
    "sg:address":"22622 Clairwood St",
    "sg:city":"Saint Clair Shores",
    "sg:classifiers":[
        {
            "category":"Retail",
            "subcategory":"Repair Shop",
            "type":"Services"
        }
    ],
    "sg:phone":"+1 586 775 0832",
    "sg:postcode":"48080",
    "sg:province":"MI",
    "wof:name":"G & C Sewer Service",
    "wof:placetype":"venue"
},
  "geometry": {"coordinates":[-82.892399,42.464022],"type":"Point"}
}