{
  "type": "Feature",
  "properties": {
    "iso:country":"US",
    "sg:address":"510 Butler St",
    "sg:city":"Saugatuck",
    "sg:classifiers":[
        {
            "category":"Travel",
            "subcategory":"Hotels & Motels",
            "type":"Entertainment"
        }
    ],
    "sg:phone":"+1 269 857 1465",
    "sg:postcode":"49453",
    "sg:province":"MI",
    "sg:tags":[
        "breakfast",
        "accommodation",
        "bed"
    ],
    "sg:website":"www.wickwoodinn.com",
    "wof:name":"Wickwood Inn",
    "wof:placetype":"venue"
},
  "geometry": {"coordinates":[-86.204251,42.65922],"type":"Point"}
}