{
  "type": "Feature",
  "properties": {
    "iso:country":"US",
    "sg:address":"205 Parkwood Ave",
    "sg:city":"Kalamazoo",
    "sg:classifiers":[
        {
            "category":"Professional",
            "subcategory":"Art Services",
            "type":"Services"
        }
    ],
    "sg:phone":"+1 269 344 3686",
    "sg:postcode":"49001",
    "sg:province":"MI",
    "sg:tags":[
        "photographer"
    ],
    "wof:name":"Will Panich Photography",
    "wof:placetype":"venue"
},
  "geometry": {"coordinates":[-85.58596300000001,42.268517],"type":"Point"}
}