{
  "type": "Feature",
  "properties": {
    "iso:country":"US",
    "sg:address":"10281 Winsted Ln",
    "sg:city":"Brighton",
    "sg:classifiers":[
        {
            "category":"Health Services",
            "subcategory":"Health Practitioner",
            "type":"Services"
        }
    ],
    "sg:phone":"+1 810 227 4389",
    "sg:postcode":"48114",
    "sg:province":"MI",
    "wof:name":"Michael M Katz",
    "wof:placetype":"venue"
},
  "geometry": {"coordinates":[-83.74651799999999,42.545455],"type":"Point"}
}