{
  "type": "Feature",
  "properties": {
    "iso:country":"US",
    "sg:address":"1200 Garfield Ave",
    "sg:city":"Bay City",
    "sg:classifiers":[
        {
            "category":"Retail",
            "subcategory":"Funeral Services",
            "type":"Services"
        }
    ],
    "sg:phone":"+1 989 895 9601",
    "sg:postcode":"48708",
    "sg:province":"MI",
    "wof:name":"Ambrose Funeral Home",
    "wof:placetype":"venue"
},
  "geometry": {"coordinates":[-83.89079,43.578573],"type":"Point"}
}