{
  "type": "Feature",
  "properties": {
    "iso:country":"US",
    "sg:address":"524 W Huron Ave",
    "sg:city":"Bad Axe",
    "sg:classifiers":[
        {
            "category":"Real Estate",
            "subcategory":"Real Estate Agent",
            "type":"Services"
        }
    ],
    "sg:phone":"+1 989 269 9832",
    "sg:postcode":"48413",
    "sg:province":"MI",
    "wof:name":"Denise Hewens",
    "wof:placetype":"venue"
},
  "geometry": {"coordinates":[-83.007644,43.801831],"type":"Point"}
}