{
  "type": "Feature",
  "properties": {
    "iso:country":"US",
    "sg:address":"8935 E Jefferson Ave",
    "sg:city":"Detroit",
    "sg:classifiers":[
        {
            "category":"Restaurant",
            "type":"Food & Drink"
        }
    ],
    "sg:phone":"+1 313 822 1771",
    "sg:postcode":"48214",
    "sg:province":"MI",
    "sg:tags":[
        "pizza"
    ],
    "wof:name":"Deangelo's Pizza & Subs",
    "wof:placetype":"venue"
},
  "geometry": {"coordinates":[-82.98690000000001,42.357201],"type":"Point"}
}