{
  "type": "Feature",
  "properties": {
    "iso:country":"US",
    "sg:address":"2118 Marshall Ct",
    "sg:city":"Saginaw",
    "sg:classifiers":[
        {
            "category":"Shopping",
            "subcategory":"Computers & Home Electronics",
            "type":"Retail Goods"
        }
    ],
    "sg:phone":"+1 989 799 8510",
    "sg:postcode":"48602",
    "sg:province":"MI",
    "sg:tags":[
        "equipment",
        "satellite",
        "system"
    ],
    "wof:name":"Digital Satellite Inc",
    "wof:placetype":"venue"
},
  "geometry": {"coordinates":[-83.99123,43.437759],"type":"Point"}
}