{
  "type": "Feature",
  "properties": {
    "iso:country":"US",
    "sg:address":"701 Homestead St",
    "sg:city":"Marquette",
    "sg:classifiers":[
        {
            "category":"Social Services",
            "subcategory":"Adult Care",
            "type":"Services"
        }
    ],
    "sg:phone":"+1 906 228 9252",
    "sg:postcode":"49855",
    "sg:province":"MI",
    "sg:tags":[
        "home",
        "residential"
    ],
    "wof:name":"Norlite Nursing Ctr",
    "wof:placetype":"venue"
},
  "geometry": {"coordinates":[-87.408615,46.541095],"type":"Point"}
}