{
  "type": "Feature",
  "properties": {
    "iso:country":"US",
    "sg:address":"3355 West Rd",
    "sg:city":"Trenton",
    "sg:classifiers":[
        {
            "category":"Restaurant",
            "type":"Food & Drink"
        }
    ],
    "sg:phone":"+1 734 675 2940",
    "sg:postcode":"48183",
    "sg:province":"MI",
    "wof:name":"McDonald's Restaurant",
    "wof:placetype":"venue"
},
  "geometry": {"coordinates":[-83.209503,42.1409],"type":"Point"}
}