{
  "type": "Feature",
  "properties": {
    "iso:country":"US",
    "sg:address":"2408 E Baker Rd",
    "sg:city":"Midland",
    "sg:classifiers":[
        {
            "category":"Building & Trades",
            "subcategory":"Construction",
            "type":"Services"
        }
    ],
    "sg:phone":"+1 989 689 3944",
    "sg:postcode":"48642",
    "sg:province":"MI",
    "sg:tags":[
        "residential"
    ],
    "wof:name":"Dallen Enterprises",
    "wof:placetype":"venue"
},
  "geometry": {"coordinates":[-84.27098599999999,43.770536],"type":"Point"}
}