{
  "type": "Feature",
  "properties": {
    "iso:country":"US",
    "sg:address":"38110 Versailles St",
    "sg:city":"Clinton Township",
    "sg:classifiers":[
        {
            "category":"Professional",
            "subcategory":"Business Services",
            "type":"Services"
        }
    ],
    "sg:phone":"+1 586 263 5113",
    "sg:postcode":"48038",
    "sg:province":"MI",
    "wof:name":"Festival Lighting",
    "wof:placetype":"venue"
},
  "geometry": {"coordinates":[-82.95683699999999,42.577676],"type":"Point"}
}