{
  "type": "Feature",
  "properties": {
    "iso:country":"US",
    "sg:address":"7980 Sheridan Trl NE",
    "sg:city":"Rockford",
    "sg:classifiers":[
        {
            "category":"Professional",
            "subcategory":"Business Services",
            "type":"Services"
        }
    ],
    "sg:phone":"+1 616 874 5025",
    "sg:postcode":"49341",
    "sg:province":"MI",
    "wof:name":"Reliant Sales & Marketing",
    "wof:placetype":"venue"
},
  "geometry": {"coordinates":[-85.50705499999999,43.109887],"type":"Point"}
}