{
  "type": "Feature",
  "properties": {
    "iso:country":"US",
    "sg:address":"39310 Eliot St",
    "sg:city":"Clinton Township",
    "sg:classifiers":[
        {
            "category":"Freight",
            "type":"Transportation"
        }
    ],
    "sg:phone":"+1 586 468 8824",
    "sg:postcode":"48036",
    "sg:province":"MI",
    "sg:tags":[
        "trucking"
    ],
    "wof:name":"Lawrence Vohs Trucking",
    "wof:placetype":"venue"
},
  "geometry": {"coordinates":[-82.909193,42.589177],"type":"Point"}
}