{
  "type": "Feature",
  "properties": {
    "iso:country":"US",
    "sg:address":"22735 Shader St",
    "sg:city":"Clinton Twp",
    "sg:classifiers":[
        {
            "category":"Freight",
            "type":"Transportation"
        }
    ],
    "sg:phone":"+1 586 783 6733",
    "sg:postcode":"48036",
    "sg:province":"MI",
    "sg:tags":[
        "mover"
    ],
    "wof:name":"Kiser Moving",
    "wof:placetype":"venue"
},
  "geometry": {"coordinates":[-82.88419,42.573216],"type":"Point"}
}