{
  "type": "Feature",
  "properties": {
    "iso:country":"US",
    "sg:address":"17752 Marcellus Hwy",
    "sg:city":"Marcellus",
    "sg:classifiers":[
        {
            "category":"Farming",
            "subcategory":"Farm",
            "type":"Manufacturing & Wholesale Goods"
        }
    ],
    "sg:phone":"+1 269 646 9750",
    "sg:postcode":"49067",
    "sg:province":"MI",
    "sg:tags":[
        "crop",
        "general"
    ],
    "wof:name":"Han Witten",
    "wof:placetype":"venue"
},
  "geometry": {"coordinates":[-85.904573,42.026894],"type":"Point"}
}