{
  "type": "Feature",
  "properties": {
    "iso:country":"US",
    "sg:address":"9 W Main St",
    "sg:city":"Hartford",
    "sg:classifiers":[
        {
            "category":"Personal",
            "subcategory":"Beauty Salon",
            "type":"Services"
        }
    ],
    "sg:phone":"+1 269 621 6615",
    "sg:postcode":"49057",
    "sg:province":"MI",
    "sg:tags":[
        "shop"
    ],
    "wof:name":"Scissor Shack",
    "wof:placetype":"venue"
},
  "geometry": {"coordinates":[-86.16686300000001,42.206982],"type":"Point"}
}