{
  "type": "Feature",
  "properties": {
    "iso:country":"US",
    "sg:address":"1600 Barlow St",
    "sg:city":"Traverse City",
    "sg:classifiers":[
        {
            "category":"Banks & Credit Unions",
            "subcategory":"Bank",
            "type":"Services"
        }
    ],
    "sg:phone":"+1 231 932 9388",
    "sg:postcode":"49686",
    "sg:province":"MI",
    "sg:tags":[
        "loan",
        "real estate"
    ],
    "sg:website":"www.goodharbormortgage.com",
    "wof:name":"Good Harbor Mortgage Co",
    "wof:placetype":"venue"
},
  "geometry": {"coordinates":[-85.60553299999999,44.739802],"type":"Point"}
}