{
  "type": "Feature",
  "properties": {
    "iso:country":"US",
    "sg:address":"4600 Colonial Ln",
    "sg:city":"Trenton",
    "sg:classifiers":[
        {
            "category":"Organizations",
            "subcategory":"Community Association",
            "type":"Services"
        }
    ],
    "sg:phone":"+1 734 675 5683",
    "sg:postcode":"48183",
    "sg:province":"MI",
    "wof:name":"Trenton Leisure Meadows",
    "wof:placetype":"venue"
},
  "geometry": {"coordinates":[-83.21450299999999,42.124638],"type":"Point"}
}