{
  "type": "Feature",
  "properties": {
    "iso:country":"US",
    "sg:address":"36800 Plymouth Rd",
    "sg:city":"Livonia",
    "sg:classifiers":[
        {
            "category":"Professional",
            "subcategory":"Engineering",
            "type":"Services"
        }
    ],
    "sg:phone":"+1 734 523 3000",
    "sg:postcode":"48150",
    "sg:province":"MI",
    "sg:tags":[
        "mfg",
        "motor",
        "vehicle"
    ],
    "wof:name":"Visteon Telephone Information",
    "wof:placetype":"venue"
},
  "geometry": {"coordinates":[-83.409387,42.367937],"type":"Point"}
}