{
  "type": "Feature",
  "properties": {
    "iso:country":"US",
    "sg:address":"32049 Riverpoint St",
    "sg:city":"Chesterfield",
    "sg:classifiers":[
        {
            "category":"Freight",
            "type":"Transportation"
        }
    ],
    "sg:phone":"+1 586 949 1244",
    "sg:postcode":"48047",
    "sg:province":"MI",
    "sg:tags":[
        "operator",
        "local",
        "hauling",
        "trucking"
    ],
    "wof:name":"C L H Hauling & Grading",
    "wof:placetype":"venue"
},
  "geometry": {"coordinates":[-82.78464,42.658437],"type":"Point"}
}