{
  "type": "Feature",
  "properties": {
    "iso:country":"US",
    "sg:address":"1039 W Wackerly Rd",
    "sg:city":"Sanford",
    "sg:classifiers":[
        {
            "category":"Restaurant",
            "type":"Food & Drink"
        }
    ],
    "sg:phone":"+1 989 687 7645",
    "sg:postcode":"48657",
    "sg:province":"MI",
    "sg:tags":[
        "eating"
    ],
    "wof:name":"Yvonnes Cuisine",
    "wof:placetype":"venue"
},
  "geometry": {"coordinates":[-84.41208899999999,43.65479],"type":"Point"}
}