{
  "type": "Feature",
  "properties": {
    "iso:country":"US",
    "sg:address":"2823 Security Ln",
    "sg:city":"Bay City",
    "sg:classifiers":[
        {
            "category":"Professional",
            "subcategory":"Business Services",
            "type":"Services"
        }
    ],
    "sg:phone":"+1 989 686 0311",
    "sg:postcode":"48706",
    "sg:province":"MI",
    "sg:tags":[
        "repair"
    ],
    "wof:name":"J & D Turf Equipment",
    "wof:placetype":"venue"
},
  "geometry": {"coordinates":[-83.94092000000001,43.58327],"type":"Point"}
}