{
  "type": "Feature",
  "properties": {
    "iso:country":"US",
    "sg:address":"124 E Washington St Ste B",
    "sg:city":"Dewitt",
    "sg:classifiers":[
        {
            "category":"Personal",
            "subcategory":"Beauty Salon",
            "type":"Services"
        },
        {
            "category":"Personal",
            "subcategory":"Barber",
            "type":"Services"
        },
        {
            "category":"Personal",
            "subcategory":"Day Spa",
            "type":"Services"
        }
    ],
    "sg:phone":"+1 517 668 0904",
    "sg:postcode":"48820",
    "sg:province":"MI",
    "wof:name":"Water's Edge Day Spa & Salon",
    "wof:placetype":"venue"
},
  "geometry": {"coordinates":[-84.56885200000001,42.84137],"type":"Point"}
}