{
  "type": "Feature",
  "properties": {
    "iso:country":"US",
    "sg:address":"14111 Telegraph Rd",
    "sg:city":"Taylor",
    "sg:classifiers":[
        {
            "category":"Travel",
            "subcategory":"Hotels & Motels",
            "type":"Entertainment"
        }
    ],
    "sg:phone":"+1 734 287 3680",
    "sg:postcode":"48180",
    "sg:province":"MI",
    "wof:name":"Tiki Motel",
    "wof:placetype":"venue"
},
  "geometry": {"coordinates":[-83.268097,42.203899],"type":"Point"}
}