{
  "type": "Feature",
  "properties": {
    "iso:country":"US",
    "sg:address":"236 Stevens St SW",
    "sg:city":"Grand Rapids",
    "sg:classifiers":[
        {
            "category":"Manufacturing",
            "subcategory":"Motor Vehicles & Parts",
            "type":"Manufacturing & Wholesale Goods"
        }
    ],
    "sg:phone":"+1 616 247 4046",
    "sg:postcode":"49507",
    "sg:province":"MI",
    "sg:tags":[
        "automobile",
        "supply"
    ],
    "wof:name":"Keeler Die Cast",
    "wof:placetype":"venue"
},
  "geometry": {"coordinates":[-85.672535,42.938302],"type":"Point"}
}