{
  "type": "Feature",
  "properties": {
    "iso:country":"US",
    "sg:address":"6601 Cooley Lake Rd",
    "sg:city":"Waterford",
    "sg:classifiers":[
        {
            "category":"Professional",
            "type":"Services"
        }
    ],
    "sg:phone":"+1 248 363 2789",
    "sg:postcode":"48327",
    "sg:province":"MI",
    "sg:tags":[
        "establishment"
    ],
    "wof:name":"Dahl",
    "wof:placetype":"venue"
},
  "geometry": {"coordinates":[-83.41552900000001,42.616425],"type":"Point"}
}