{
  "type": "Feature",
  "properties": {
    "iso:country":"US",
    "sg:address":"2279 Railroad St",
    "sg:city":"Boyne Falls",
    "sg:classifiers":[
        {
            "category":"Building & Trades",
            "subcategory":"Construction",
            "type":"Services"
        }
    ],
    "sg:phone":"+1 231 549 2425",
    "sg:postcode":"49713",
    "sg:province":"MI",
    "sg:tags":[
        "marking",
        "maintenance",
        "parking"
    ],
    "wof:name":"Boyne Falls City Public Works",
    "wof:placetype":"venue"
},
  "geometry": {"coordinates":[-84.91376099999999,45.172376],"type":"Point"}
}