{
  "type": "Feature",
  "properties": {
    "iso:country":"US",
    "sg:address":"7405 E West Maple Rd",
    "sg:city":"West Bloomfield",
    "sg:classifiers":[
        {
            "category":"Travel",
            "subcategory":"Hotels & Motels",
            "type":"Entertainment"
        },
        {
            "category":"Travel",
            "subcategory":"Bed & Breakfast",
            "type":"Entertainment"
        }
    ],
    "sg:phone":"+1 248 624 9869",
    "sg:postcode":"48323",
    "sg:province":"MI",
    "wof:name":"Wren's Nest the",
    "wof:placetype":"venue"
},
  "geometry": {"coordinates":[-83.367203,42.5704],"type":"Point"}
}