{
  "type": "Feature",
  "properties": {
    "iso:country":"US",
    "sg:address":"4554 E Monroe St",
    "sg:city":"Holt",
    "sg:classifiers":[
        {
            "category":"Social Services",
            "type":"Services"
        }
    ],
    "sg:phone":"+1 517 694 9689",
    "sg:postcode":"48842",
    "sg:province":"MI",
    "sg:tags":[
        "counselor",
        "marriage",
        "family"
    ],
    "wof:name":"Rowe Family Resources PC",
    "wof:placetype":"venue"
},
  "geometry": {"coordinates":[-84.524953,42.649726],"type":"Point"}
}