{
  "type": "Feature",
  "properties": {
    "iso:country":"US",
    "sg:address":"22255 Greenfield Rd Ste 128",
    "sg:city":"Southfield",
    "sg:classifiers":[
        {
            "category":"Health Services",
            "subcategory":"Doctor",
            "type":"Services"
        }
    ],
    "sg:phone":"+1 248 569 0150",
    "sg:postcode":"48075",
    "sg:province":"MI",
    "wof:name":"Kam E MD",
    "wof:placetype":"venue"
},
  "geometry": {"coordinates":[-83.201103,42.4566],"type":"Point"}
}