{
  "type": "Feature",
  "properties": {
    "iso:country":"US",
    "sg:address":"30554 Elmira St",
    "sg:city":"Livonia",
    "sg:classifiers":[
        {
            "category":"Building & Trades",
            "subcategory":"Construction",
            "type":"Services"
        }
    ],
    "sg:phone":"+1 734 522 2690",
    "sg:postcode":"48150",
    "sg:province":"MI",
    "sg:tags":[
        "painter"
    ],
    "wof:name":"Bill Kelly Painting",
    "wof:placetype":"venue"
},
  "geometry": {"coordinates":[-83.34549699999999,42.367199],"type":"Point"}
}