{
  "type": "Feature",
  "properties": {
    "iso:country":"US",
    "sg:address":"146 Tamarack St",
    "sg:city":"Laurium",
    "sg:classifiers":[
        {
            "category":"Organizations",
            "subcategory":"Religious Organization",
            "type":"Services"
        }
    ],
    "sg:phone":"+1 906 337 3810",
    "sg:postcode":"49913",
    "sg:province":"MI",
    "sg:tags":[
        "church"
    ],
    "wof:name":"St Paul Lutheran Church",
    "wof:placetype":"venue"
},
  "geometry": {"coordinates":[-88.438715,47.238807],"type":"Point"}
}