{
  "type": "Feature",
  "properties": {
    "iso:country":"US",
    "sg:address":"37826 Lanse Creuse St",
    "sg:city":"Harrison Township",
    "sg:classifiers":[
        {
            "category":"Health Services",
            "subcategory":"Medical Lab",
            "type":"Services"
        }
    ],
    "sg:phone":"+1 586 791 9934",
    "sg:postcode":"48045",
    "sg:province":"MI",
    "sg:tags":[
        "laboratory",
        "dental"
    ],
    "wof:name":"Sterling Dental Ceramics",
    "wof:placetype":"venue"
},
  "geometry": {"coordinates":[-82.845558,42.575554],"type":"Point"}
}