{
  "type": "Feature",
  "properties": {
    "iso:country":"US",
    "sg:address":"2755 E Dexter Dr",
    "sg:city":"Saginaw",
    "sg:classifiers":[
        {
            "category":"Social Services",
            "subcategory":"Child Care",
            "type":"Services"
        }
    ],
    "sg:phone":"+1 989 790 1230",
    "sg:postcode":"48603",
    "sg:province":"MI",
    "sg:tags":[
        "day"
    ],
    "wof:name":"Charlotte Reimers",
    "wof:placetype":"venue"
},
  "geometry": {"coordinates":[-83.978273,43.444734],"type":"Point"}
}