{
  "type": "Feature",
  "properties": {
    "iso:country":"US",
    "sg:address":"102 E Main St",
    "sg:city":"Carson City",
    "sg:classifiers":[
        {
            "category":"Utilities",
            "subcategory":"Fuel Oil & Lpg",
            "type":"Services"
        }
    ],
    "sg:phone":"+1 989 584 3213",
    "sg:postcode":"48811",
    "sg:province":"MI",
    "sg:tags":[
        "propane",
        "gas"
    ],
    "wof:name":"NCI Oil & Propane",
    "wof:placetype":"venue"
},
  "geometry": {"coordinates":[-84.84645500000001,43.176917],"type":"Point"}
}