{
  "type": "Feature",
  "properties": {
    "iso:country":"US",
    "sg:address":"113 W Grand River Ave",
    "sg:city":"Brighton",
    "sg:classifiers":[
        {
            "category":"Personal",
            "subcategory":"Beauty Salon",
            "type":"Services"
        }
    ],
    "sg:phone":"+1 810 844 0866",
    "sg:postcode":"48116",
    "sg:province":"MI",
    "sg:tags":[
        "treatment",
        "skin"
    ],
    "wof:name":"Omorphea",
    "wof:placetype":"venue"
},
  "geometry": {"coordinates":[-83.780829,42.530265],"type":"Point"}
}