{
  "type": "Feature",
  "properties": {
    "iso:country":"US",
    "sg:address":"124 Red Bird Ln",
    "sg:city":"Battle Creek",
    "sg:classifiers":[
        {
            "category":"Professional",
            "subcategory":"Business Services",
            "type":"Services"
        }
    ],
    "sg:phone":"+1 269 964 3832",
    "sg:postcode":"49017",
    "sg:province":"MI",
    "wof:name":"Learnin & Earnin Group",
    "wof:placetype":"venue"
},
  "geometry": {"coordinates":[-85.184164,42.382716],"type":"Point"}
}