{
  "type": "Feature",
  "properties": {
    "iso:country":"US",
    "sg:address":"20315 Farmington Rd",
    "sg:city":"Livonia",
    "sg:classifiers":[
        {
            "category":"Health Services",
            "subcategory":"Doctor",
            "type":"Services"
        }
    ],
    "sg:phone":"+1 248 476 2140",
    "sg:postcode":"48152",
    "sg:province":"MI",
    "sg:tags":[
        "medical"
    ],
    "wof:name":"Zaven Oskanian MD",
    "wof:placetype":"venue"
},
  "geometry": {"coordinates":[-83.37536900000001,42.436992],"type":"Point"}
}