{
  "type": "Feature",
  "properties": {
    "iso:country":"US",
    "sg:address":"705 E Broad St",
    "sg:city":"Bellaire",
    "sg:classifiers":[
        {
            "category":"Professional",
            "subcategory":"Business Services",
            "type":"Services"
        }
    ],
    "sg:phone":"+1 231 533 6194",
    "sg:postcode":"49615",
    "sg:province":"MI",
    "sg:tags":[
        "notary",
        "public"
    ],
    "wof:name":"Evelyn F Depew",
    "wof:placetype":"venue"
},
  "geometry": {"coordinates":[-85.197626,44.976627],"type":"Point"}
}