{
  "type": "Feature",
  "properties": {
    "iso:country":"US",
    "sg:address":"1699 S Pere Marquette Hwy",
    "sg:city":"Ludington",
    "sg:classifiers":[
        {
            "category":"Government",
            "subcategory":"Office",
            "type":"Public Place"
        }
    ],
    "sg:phone":"+1 231 845 7640",
    "sg:postcode":"49431",
    "sg:province":"MI",
    "sg:tags":[
        "village"
    ],
    "wof:name":"Pere Marquette Twp Sewer Mntnc",
    "wof:placetype":"venue"
},
  "geometry": {"coordinates":[-86.417597,43.92648],"type":"Point"}
}