{
  "type": "Feature",
  "properties": {
    "iso:country":"US",
    "sg:address":"3163 28th St SE",
    "sg:city":"Grand Rapids",
    "sg:classifiers":[
        {
            "category":"Personal",
            "subcategory":"Beauty Salon",
            "type":"Services"
        }
    ],
    "sg:phone":"+1 616 974 3333",
    "sg:postcode":"49512",
    "sg:province":"MI",
    "wof:name":"Master Cuts",
    "wof:placetype":"venue"
},
  "geometry": {"coordinates":[-85.58972900000001,42.912593],"type":"Point"}
}