{
  "type": "Feature",
  "properties": {
    "iso:country":"US",
    "sg:address":"1306 N Clare Ave",
    "sg:city":"Harrison",
    "sg:classifiers":[
        {
            "category":"Travel",
            "subcategory":"Hotels & Motels",
            "type":"Entertainment"
        }
    ],
    "sg:phone":"+1 989 539 2238",
    "sg:postcode":"48625",
    "sg:province":"MI",
    "sg:tags":[
        "operation"
    ],
    "wof:name":"Acorn Motel",
    "wof:placetype":"venue"
},
  "geometry": {"coordinates":[-84.787835,44.006565],"type":"Point"}
}