{
  "type": "Feature",
  "properties": {
    "iso:country":"US",
    "sg:address":"2244 W Warren Ave",
    "sg:city":"Detroit",
    "sg:classifiers":[
        {
            "category":"Retail",
            "subcategory":"Laundry & Dry Cleaning",
            "type":"Services"
        }
    ],
    "sg:phone":"+1 313 897 2812",
    "sg:postcode":"48208",
    "sg:province":"MI",
    "sg:tags":[
        "industrial"
    ],
    "wof:name":"Mechanics Uniform Rental Co",
    "wof:placetype":"venue"
},
  "geometry": {"coordinates":[-83.087537,42.349396],"type":"Point"}
}