{
  "type": "Feature",
  "properties": {
    "iso:country":"US",
    "sg:address":"1701 S Airport Rd W",
    "sg:city":"Traverse City",
    "sg:classifiers":[
        {
            "category":"Home & Garden",
            "subcategory":"Furniture",
            "type":"Retail Goods"
        }
    ],
    "sg:phone":"+1 231 946 9394",
    "sg:postcode":"49686",
    "sg:province":"MI",
    "sg:tags":[
        "equipment",
        "kitchen",
        "cabinet"
    ],
    "wof:name":"Standard Kitchens",
    "wof:placetype":"venue"
},
  "geometry": {"coordinates":[-85.610224,44.733502],"type":"Point"}
}