{
  "type": "Feature",
  "properties": {
    "iso:country":"US",
    "sg:address":"18530 Dix Rd",
    "sg:city":"Melvindale",
    "sg:classifiers":[
        {
            "category":"Home & Garden",
            "subcategory":"Building Materials",
            "type":"Retail Goods"
        }
    ],
    "sg:phone":"+1 313 928 3888",
    "sg:postcode":"48122",
    "sg:province":"MI",
    "sg:tags":[
        "supply"
    ],
    "wof:name":"Downriver Glass Block Inc",
    "wof:placetype":"venue"
},
  "geometry": {"coordinates":[-83.17585699999999,42.275396],"type":"Point"}
}