{
  "type": "Feature",
  "properties": {
    "iso:country":"US",
    "sg:address":"244 N Rose St",
    "sg:city":"Kalamazoo",
    "sg:classifiers":[
        {
            "category":"Insurance",
            "subcategory":"Insurance Agent",
            "type":"Services"
        }
    ],
    "sg:phone":"+1 269 552 3200",
    "sg:postcode":"49007",
    "sg:province":"MI",
    "sg:website":"www.sdmg-ncb.com",
    "wof:name":"National City Insurance Group",
    "wof:placetype":"venue"
},
  "geometry": {"coordinates":[-85.58474,42.293112],"type":"Point"}
}