{
  "type": "Feature",
  "properties": {
    "iso:country":"US",
    "sg:address":"1356 Linden Dr",
    "sg:city":"Saint Joseph",
    "sg:classifiers":[
        {
            "category":"Professional",
            "subcategory":"Art Services",
            "type":"Services"
        }
    ],
    "sg:phone":"+1 269 429 1958",
    "sg:postcode":"49085",
    "sg:province":"MI",
    "sg:tags":[
        "commercial",
        "design"
    ],
    "wof:name":"Propaganda Art Design",
    "wof:placetype":"venue"
},
  "geometry": {"coordinates":[-86.423687,42.060138],"type":"Point"}
}