{
  "type": "Feature",
  "properties": {
    "iso:country":"US",
    "sg:address":"9433 S Wise Rd",
    "sg:city":"Shepherd",
    "sg:classifiers":[
        {
            "category":"Social Services",
            "subcategory":"Adult Care",
            "type":"Services"
        }
    ],
    "sg:phone":"+1 989 681 3297",
    "sg:postcode":"48883",
    "sg:province":"MI",
    "sg:tags":[
        "foster"
    ],
    "wof:name":"Denman Adult Foster Care Home",
    "wof:placetype":"venue"
},
  "geometry": {"coordinates":[-84.647401,43.504258],"type":"Point"}
}