{
  "type": "Feature",
  "properties": {
    "iso:country":"US",
    "sg:address":"517 E Wood St",
    "sg:city":"Flint",
    "sg:classifiers":[
        {
            "category":"Real Estate",
            "subcategory":"Real Estate Agent",
            "type":"Services"
        }
    ],
    "sg:phone":"+1 810 232 2682",
    "sg:postcode":"48503",
    "sg:province":"MI",
    "wof:name":"Wc Ross & Son",
    "wof:placetype":"venue"
},
  "geometry": {"coordinates":[-83.69639599999999,43.029434],"type":"Point"}
}