{
  "type": "Feature",
  "properties": {
    "iso:country":"US",
    "sg:address":"130 Jefferson Ave",
    "sg:city":"Harrison Township",
    "sg:classifiers":[
        {
            "category":"Personal",
            "subcategory":"Barber",
            "type":"Services"
        }
    ],
    "sg:phone":"+1 586 954 3497",
    "sg:postcode":"48045",
    "sg:province":"MI",
    "wof:name":"Gino Morena Enterprises",
    "wof:placetype":"venue"
},
  "geometry": {"coordinates":[-82.833702,42.579899],"type":"Point"}
}