{
  "type": "Feature",
  "properties": {
    "iso:country":"US",
    "sg:address":"4716 Roundtree Dr",
    "sg:city":"Brighton",
    "sg:classifiers":[
        {
            "category":"Professional",
            "subcategory":"Computer Services",
            "type":"Services"
        }
    ],
    "sg:phone":"+1 810 220 0801",
    "sg:postcode":"48116",
    "sg:province":"MI",
    "sg:tags":[
        "related"
    ],
    "wof:name":"Exclusively Yours Salon",
    "wof:placetype":"venue"
},
  "geometry": {"coordinates":[-83.85359699999999,42.531289],"type":"Point"}
}