{
  "type": "Feature",
  "properties": {
    "iso:country":"US",
    "sg:address":"2536 Detroit Rd",
    "sg:city":"Niles",
    "sg:classifiers":[
        {
            "category":"Home & Garden",
            "subcategory":"Building Materials",
            "type":"Retail Goods"
        }
    ],
    "sg:phone":"+1 269 687 8911",
    "sg:postcode":"49120",
    "sg:province":"MI",
    "wof:name":"D & S Distributing",
    "wof:placetype":"venue"
},
  "geometry": {"coordinates":[-86.19184300000001,41.828745],"type":"Point"}
}