{
  "type": "Feature",
  "properties": {
    "iso:country":"US",
    "sg:address":"1106 Newberry Ave",
    "sg:city":"Newberry",
    "sg:classifiers":[
        {
            "category":"Restaurant",
            "type":"Food & Drink"
        }
    ],
    "sg:phone":"+1 906 293 8772",
    "sg:postcode":"49868",
    "sg:province":"MI",
    "sg:tags":[
        "eating",
        "cleaning",
        "carpet"
    ],
    "wof:name":"Dittrich Dining",
    "wof:placetype":"venue"
},
  "geometry": {"coordinates":[-85.509766,46.344674],"type":"Point"}
}