{
  "type": "Feature",
  "properties": {
    "iso:country":"US",
    "sg:address":"43855 Plymouth Oaks Blvd",
    "sg:city":"Plymouth",
    "sg:classifiers":[
        {
            "category":"Manufacturing",
            "subcategory":"Tools & Machinery",
            "type":"Manufacturing & Wholesale Goods"
        }
    ],
    "sg:phone":"+1 734 453 0800",
    "sg:postcode":"48170",
    "sg:province":"MI",
    "sg:tags":[
        "analytical",
        "laboratory",
        "instrument"
    ],
    "sg:website":"www.linkengineering.com",
    "wof:name":"Link Engineering",
    "wof:placetype":"venue"
},
  "geometry": {"coordinates":[-83.47412799999999,42.382234],"type":"Point"}
}