{
  "type": "Feature",
  "properties": {
    "iso:country":"US",
    "sg:address":"45678 Helm St",
    "sg:city":"Plymouth",
    "sg:classifiers":[
        {
            "category":"Social Services",
            "subcategory":"Child Care",
            "type":"Services"
        }
    ],
    "sg:phone":"+1 734 455 5490",
    "sg:postcode":"48170",
    "sg:province":"MI",
    "sg:tags":[
        "day"
    ],
    "wof:name":"Childtime Learning Center",
    "wof:placetype":"venue"
},
  "geometry": {"coordinates":[-83.493961,42.391615],"type":"Point"}
}