{
  "type": "Feature",
  "properties": {
    "iso:country":"US",
    "sg:address":"4300 James Savage Rd",
    "sg:city":"Midland",
    "sg:classifiers":[
        {
            "category":"Food & Beverages",
            "subcategory":"Groceries & Convenience Stores",
            "type":"Retail Goods"
        }
    ],
    "sg:phone":"+1 989 496 0511",
    "sg:postcode":"48642",
    "sg:province":"MI",
    "sg:website":"www.circlekservice.com",
    "wof:name":"Circle K Svc",
    "wof:placetype":"venue"
},
  "geometry": {"coordinates":[-84.17668,43.610872],"type":"Point"}
}