{
  "type": "Feature",
  "properties": {
    "iso:country":"US",
    "sg:address":"1200 Academy St",
    "sg:city":"Kalamazoo",
    "sg:classifiers":[
        {
            "category":"Arts & Performance",
            "subcategory":"Theater",
            "type":"Entertainment"
        }
    ],
    "sg:phone":"+1 269 337 7333",
    "sg:postcode":"49006",
    "sg:province":"MI",
    "wof:name":"Festival Playhouse Kalamazoo",
    "wof:placetype":"venue"
},
  "geometry": {"coordinates":[-85.60115399999999,42.290366],"type":"Point"}
}