{
  "type": "Feature",
  "properties": {
    "iso:country":"US",
    "sg:address":"15116 Hemlock Rd",
    "sg:city":"Chesaning",
    "sg:classifiers":[
        {
            "category":"Building & Trades",
            "subcategory":"Construction",
            "type":"Services"
        }
    ],
    "sg:phone":"+1 989 845 7546",
    "sg:postcode":"48616",
    "sg:province":"MI",
    "sg:tags":[
        "house"
    ],
    "wof:name":"Richard Tompa Builders",
    "wof:placetype":"venue"
},
  "geometry": {"coordinates":[-84.22805700000001,43.199635],"type":"Point"}
}