{
  "type": "Feature",
  "properties": {
    "iso:country":"US",
    "sg:address":"3571 Baywood Pl",
    "sg:city":"Saginaw",
    "sg:classifiers":[
        {
            "category":"Social Services",
            "subcategory":"Child Care",
            "type":"Services"
        }
    ],
    "sg:phone":"+1 989 799 0419",
    "sg:postcode":"48603",
    "sg:province":"MI",
    "sg:tags":[
        "home",
        "day"
    ],
    "wof:name":"Dolores Giacoletti",
    "wof:placetype":"venue"
},
  "geometry": {"coordinates":[-83.981168,43.459545],"type":"Point"}
}