{
  "type": "Feature",
  "properties": {
    "iso:country":"US",
    "sg:address":"7377 Evanston Ave",
    "sg:city":"Muskegon",
    "sg:classifiers":[
        {
            "category":"Professional",
            "subcategory":"Engineering",
            "type":"Services"
        }
    ],
    "sg:phone":"+1 231 788 5148",
    "sg:postcode":"49442",
    "sg:province":"MI",
    "wof:name":"Diversified Engineer",
    "wof:placetype":"venue"
},
  "geometry": {"coordinates":[-86.056651,43.213126],"type":"Point"}
}