{
  "type": "Feature",
  "properties": {
    "iso:country":"US",
    "sg:address":"1556 Chalmers St",
    "sg:city":"Martin",
    "sg:classifiers":[
        {
            "category":"Education",
            "subcategory":"School",
            "type":"Public Place"
        }
    ],
    "sg:phone":"+1 269 672 7253",
    "sg:postcode":"49070",
    "sg:province":"MI",
    "wof:name":"Brandon Elementary School",
    "wof:placetype":"venue"
},
  "geometry": {"coordinates":[-85.636188,42.53736],"type":"Point"}
}