{
  "type": "Feature",
  "properties": {
    "iso:country":"US",
    "sg:address":"200 E Broad St",
    "sg:city":"Linden",
    "sg:classifiers":[
        {
            "category":"Restaurant",
            "type":"Food & Drink"
        }
    ],
    "sg:menulink":"http://www.allmenus.com/mi/linden/146102-subway/menu/",
    "sg:phone":"+1 810 735 5381",
    "sg:postcode":"48451",
    "sg:province":"MI",
    "sg:tags":[
        "american",
        "sandwich"
    ],
    "wof:name":"Subway",
    "wof:placetype":"venue"
},
  "geometry": {"coordinates":[-83.781009,42.814788],"type":"Point"}
}