{
  "type": "Feature",
  "properties": {
    "iso:country":"US",
    "sg:address":"8875 Homer Rd",
    "sg:city":"Jonesville",
    "sg:classifiers":[
        {
            "category":"Building & Trades",
            "subcategory":"Electrical",
            "type":"Services"
        }
    ],
    "sg:phone":"+1 517 542 3586",
    "sg:postcode":"49250",
    "sg:province":"MI",
    "sg:tags":[
        "electric",
        "contractor"
    ],
    "wof:name":"Lucas Electric Co",
    "wof:placetype":"venue"
},
  "geometry": {"coordinates":[-84.700834,42.024362],"type":"Point"}
}