{
  "type": "Feature",
  "properties": {
    "iso:country":"US",
    "sg:address":"10166 Strasburg Rd",
    "sg:city":"Erie",
    "sg:classifiers":[
        {
            "category":"Freight",
            "type":"Transportation"
        }
    ],
    "sg:phone":"+1 734 848 4542",
    "sg:postcode":"48133",
    "sg:province":"MI",
    "sg:tags":[
        "operator",
        "trucking"
    ],
    "wof:name":"Richard A Carter Trucking",
    "wof:placetype":"venue"
},
  "geometry": {"coordinates":[-83.510806,41.800756],"type":"Point"}
}