{
  "type": "Feature",
  "properties": {
    "iso:country":"US",
    "sg:address":"3617 N Two Mile Rd",
    "sg:city":"Pinconning",
    "sg:classifiers":[
        {
            "category":"Wholesale",
            "subcategory":"Hardware",
            "type":"Manufacturing & Wholesale Goods"
        }
    ],
    "sg:phone":"+1 989 879 5642",
    "sg:postcode":"48650",
    "sg:province":"MI",
    "sg:tags":[
        "plumbing"
    ],
    "wof:name":"R A Townsend Company",
    "wof:placetype":"venue"
},
  "geometry": {"coordinates":[-83.927198,43.84217],"type":"Point"}
}