{
  "type": "Feature",
  "properties": {
    "iso:country":"US",
    "sg:address":"2531 Ore Valley Dr",
    "sg:city":"Hartland",
    "sg:classifiers":[
        {
            "category":"Professional",
            "type":"Services"
        }
    ],
    "sg:phone":"+1 810 632 5506",
    "sg:postcode":"48353",
    "sg:province":"MI",
    "wof:name":"Fleischman Services",
    "wof:placetype":"venue"
},
  "geometry": {"coordinates":[-83.726501,42.641903],"type":"Point"}
}