{
  "type": "Feature",
  "properties": {
    "iso:country":"US",
    "sg:address":"6100 B Dr N",
    "sg:city":"Battle Creek",
    "sg:classifiers":[
        {
            "category":"Home & Garden",
            "subcategory":"Furniture",
            "type":"Retail Goods"
        }
    ],
    "sg:phone":"+1 269 979 1091",
    "sg:postcode":"49014",
    "sg:province":"MI",
    "wof:name":"Art Van Furniture",
    "wof:placetype":"venue"
},
  "geometry": {"coordinates":[-85.17675800000001,42.260976],"type":"Point"}
}