{
  "type": "Feature",
  "properties": {
    "iso:country":"US",
    "sg:address":"2409 Charlevoix Ave",
    "sg:city":"Petoskey",
    "sg:phone":"+1 231 347 2131",
    "sg:postcode":"49770",
    "sg:province":"MI",
    "sg:tags":[
        "transmission",
        "facsimile"
    ],
    "wof:name":"Public Letter Shop",
    "wof:placetype":"venue"
},
  "geometry": {"coordinates":[-85.00031300000001,45.366815],"type":"Point"}
}