{
  "type": "Feature",
  "properties": {
    "iso:country":"US",
    "sg:address":"7981 Springborn Rd",
    "sg:city":"Casco",
    "sg:classifiers":[
        {
            "category":"Real Estate",
            "subcategory":"Real Estate Agent",
            "type":"Services"
        }
    ],
    "sg:phone":"+1 810 765 7298",
    "sg:postcode":"48064",
    "sg:province":"MI",
    "sg:tags":[
        "agency",
        "rental"
    ],
    "wof:name":"D & S Rentals",
    "wof:placetype":"venue"
},
  "geometry": {"coordinates":[-82.630453,42.739005],"type":"Point"}
}