{
  "type": "Feature",
  "properties": {
    "iso:country":"US",
    "sg:address":"67503 38th St",
    "sg:city":"Paw Paw",
    "sg:classifiers":[
        {
            "category":"Recreation",
            "type":"Entertainment"
        }
    ],
    "sg:phone":"+1 269 657 3415",
    "sg:postcode":"49079",
    "sg:province":"MI",
    "wof:name":"Model Farm Stables",
    "wof:placetype":"venue"
},
  "geometry": {"coordinates":[-85.916854,42.177762],"type":"Point"}
}