{
  "type": "Feature",
  "properties": {
    "iso:country":"US",
    "sg:address":"3035 Carrigan Rd",
    "sg:city":"Fort Gratiot",
    "sg:classifiers":[
        {
            "category":"Building & Trades",
            "subcategory":"Landscaping Services",
            "type":"Services"
        }
    ],
    "sg:phone":"+1 810 385 7890",
    "sg:postcode":"48059",
    "sg:province":"MI",
    "sg:tags":[
        "topsoil"
    ],
    "wof:name":"Brag Inc",
    "wof:placetype":"venue"
},
  "geometry": {"coordinates":[-82.458693,43.054099],"type":"Point"}
}