{
  "type": "Feature",
  "properties": {
    "iso:country":"US",
    "sg:address":"1890 S Rochester Rd",
    "sg:city":"Rochester",
    "sg:classifiers":[
        {
            "category":"Professional",
            "subcategory":"Accounting & Tax Preparation",
            "type":"Services"
        }
    ],
    "sg:phone":"+1 248 656 0022",
    "sg:postcode":"48307",
    "sg:province":"MI",
    "sg:tags":[
        "return"
    ],
    "wof:name":"H & R Block",
    "wof:placetype":"venue"
},
  "geometry": {"coordinates":[-83.13263600000001,42.652488],"type":"Point"}
}