{
  "type": "Feature",
  "properties": {
    "iso:country":"US",
    "sg:address":"17199 N Laurel Park Dr",
    "sg:city":"Livonia",
    "sg:classifiers":[
        {
            "category":"Insurance",
            "subcategory":"Hazard Insurance",
            "type":"Services"
        }
    ],
    "sg:phone":"+1 734 542 7360",
    "sg:postcode":"48152",
    "sg:province":"MI",
    "sg:tags":[
        "carrier"
    ],
    "wof:name":"Foresters",
    "wof:placetype":"venue"
},
  "geometry": {"coordinates":[-83.417968,42.411437],"type":"Point"}
}