{
  "type": "Feature",
  "properties": {
    "iso:country":"US",
    "sg:address":"3903 Voice Rd",
    "sg:city":"Kingsley",
    "sg:classifiers":[
        {
            "category":"Organizations",
            "subcategory":"Religious Organization",
            "type":"Services"
        }
    ],
    "sg:phone":"+1 231 263 4596",
    "sg:postcode":"49649",
    "sg:province":"MI",
    "wof:name":"Cherry Blossom Mennonite",
    "wof:placetype":"venue"
},
  "geometry": {"coordinates":[-85.49543,44.611776],"type":"Point"}
}