{
  "type": "Feature",
  "properties": {
    "iso:country":"US",
    "sg:address":"322 E Main St",
    "sg:city":"Michigamme",
    "sg:classifiers":[
        {
            "category":"Shopping",
            "subcategory":"Gifts & Souvenirs",
            "type":"Retail Goods"
        }
    ],
    "sg:phone":"+1 906 323 0050",
    "sg:postcode":"49861",
    "sg:province":"MI",
    "sg:tags":[
        "shop"
    ],
    "wof:name":"End Of The Line",
    "wof:placetype":"venue"
},
  "geometry": {"coordinates":[-88.10498800000001,46.535745],"type":"Point"}
}