{
  "type": "Feature",
  "properties": {
    "iso:country":"US",
    "sg:address":"1829 Northwood Blvd",
    "sg:city":"Royal Oak",
    "sg:classifiers":[
        {
            "category":"Professional",
            "subcategory":"Management & Consulting",
            "type":"Services"
        }
    ],
    "sg:phone":"+1 248 548 0356",
    "sg:postcode":"48073",
    "sg:province":"MI",
    "sg:tags":[
        "interior",
        "energy",
        "construction",
        "design"
    ],
    "wof:name":"Engery Saver",
    "wof:placetype":"venue"
},
  "geometry": {"coordinates":[-83.166546,42.506986],"type":"Point"}
}