{
  "type": "Feature",
  "properties": {
    "iso:country":"US",
    "sg:address":"2488 S Wisner Ave",
    "sg:city":"Fremont",
    "sg:classifiers":[
        {
            "category":"Restaurant",
            "type":"Food & Drink"
        }
    ],
    "sg:phone":"+1 231 924 5281",
    "sg:postcode":"49412",
    "sg:province":"MI",
    "sg:tags":[
        "eating"
    ],
    "wof:name":"Goal Post Inc",
    "wof:placetype":"venue"
},
  "geometry": {"coordinates":[-85.870546,43.508525],"type":"Point"}
}