{
  "type": "Feature",
  "properties": {
    "iso:country":"US",
    "sg:address":"300 Renaissance Ctr",
    "sg:city":"Detroit",
    "sg:classifiers":[
        {
            "category":"Shopping",
            "subcategory":"Mobile Phones",
            "type":"Retail Goods"
        }
    ],
    "sg:phone":"+1 313 567 4055",
    "sg:postcode":"48243",
    "sg:province":"MI",
    "sg:website":"www.verizonwireless.com",
    "wof:name":"Verizon Wireless",
    "wof:placetype":"venue"
},
  "geometry": {"coordinates":[-83.040486,42.329756],"type":"Point"}
}