{
  "type": "Feature",
  "properties": {
    "iso:country":"US",
    "sg:address":"6670 Dixie Hwy",
    "sg:city":"Clarkston",
    "sg:classifiers":[
        {
            "category":"Banks & Credit Unions",
            "subcategory":"Bank",
            "type":"Services"
        }
    ],
    "sg:phone":"+1 248 625 3776",
    "sg:postcode":"48346",
    "sg:province":"MI",
    "wof:name":"Bank One",
    "wof:placetype":"venue"
},
  "geometry": {"coordinates":[-83.41687400000001,42.719023],"type":"Point"}
}