{
  "type": "Feature",
  "properties": {
    "iso:country":"US",
    "sg:address":"820 N Jones Rd",
    "sg:city":"Essexville",
    "sg:classifiers":[
        {
            "category":"Recreation",
            "type":"Entertainment"
        }
    ],
    "sg:phone":"+1 989 892 7861",
    "sg:postcode":"48732",
    "sg:province":"MI",
    "sg:tags":[
        "club",
        "membership",
        "sport"
    ],
    "wof:name":"Hampton Essexville Amer",
    "wof:placetype":"venue"
},
  "geometry": {"coordinates":[-83.816751,43.588296],"type":"Point"}
}