{
  "type": "Feature",
  "properties": {
    "iso:country":"US",
    "sg:address":"31950 Kelly Rd",
    "sg:city":"Roseville",
    "sg:classifiers":[
        {
            "category":"Professional",
            "subcategory":"Management & Consulting",
            "type":"Services"
        },
        {
            "category":"Social Services",
            "subcategory":"Job Training",
            "type":"Services"
        }
    ],
    "sg:phone":"+1 586 294 0770",
    "sg:postcode":"48066",
    "sg:province":"MI",
    "sg:tags":[
        "medical",
        "rehabilitation"
    ],
    "wof:name":"Medical Care Coordinators Inc",
    "wof:placetype":"venue"
},
  "geometry": {"coordinates":[-82.929286,42.531687],"type":"Point"}
}