{
  "type": "Feature",
  "properties": {
    "iso:country":"US",
    "sg:address":"21901 Eureka Rd",
    "sg:city":"Taylor",
    "sg:classifiers":[
        {
            "category":"Health Services",
            "subcategory":"Doctor",
            "type":"Services"
        }
    ],
    "sg:phone":"+1 734 287 9102",
    "sg:postcode":"48180",
    "sg:province":"MI",
    "sg:tags":[
        "medical"
    ],
    "wof:name":"Henry Ford Med Center-Taylor",
    "wof:placetype":"venue"
},
  "geometry": {"coordinates":[-83.24709,42.197916],"type":"Point"}
}