{
  "type": "Feature",
  "properties": {
    "iso:country":"US",
    "sg:address":"5481 E Apple Ave",
    "sg:city":"Muskegon",
    "sg:classifiers":[
        {
            "category":"Personal",
            "subcategory":"Beauty Salon",
            "type":"Services"
        }
    ],
    "sg:phone":"+1 231 788 5700",
    "sg:postcode":"49442",
    "sg:province":"MI",
    "wof:name":"Sharp Cuts & Design",
    "wof:placetype":"venue"
},
  "geometry": {"coordinates":[-86.111211,43.234773],"type":"Point"}
}