{
  "type": "Feature",
  "properties": {
    "iso:country":"US",
    "sg:address":"1111 S Lincoln Ave",
    "sg:city":"Niles",
    "sg:classifiers":[
        {
            "category":"Professional",
            "subcategory":"Engineering",
            "type":"Services"
        }
    ],
    "sg:phone":"+1 269 683 7224",
    "sg:postcode":"49120",
    "sg:province":"MI",
    "wof:name":"Frieling & Assoc",
    "wof:placetype":"venue"
},
  "geometry": {"coordinates":[-86.26389,41.815605],"type":"Point"}
}