{
  "type": "Feature",
  "properties": {
    "iso:country":"US",
    "sg:address":"265 Elk Lake Rd",
    "sg:city":"Attica",
    "sg:classifiers":[
        {
            "category":"Recreation",
            "subcategory":"Marina",
            "type":"Entertainment"
        }
    ],
    "sg:phone":"+1 810 724 1598",
    "sg:postcode":"48412",
    "sg:province":"MI",
    "sg:tags":[
        "repairing",
        "boat"
    ],
    "wof:name":"Total Fiberglass Repair",
    "wof:placetype":"venue"
},
  "geometry": {"coordinates":[-83.16222999999999,43.041403],"type":"Point"}
}