{
  "type": "Feature",
  "properties": {
    "iso:country":"US",
    "sg:address":"13180 Shire Rd",
    "sg:city":"Wolverine",
    "sg:classifiers":[
        {
            "category":"Manufacturing",
            "subcategory":"Lumber",
            "type":"Manufacturing & Wholesale Goods"
        }
    ],
    "sg:phone":"+1 231 525 6592",
    "sg:postcode":"49799",
    "sg:province":"MI",
    "sg:tags":[
        "logging"
    ],
    "wof:name":"D & M Logging",
    "wof:placetype":"venue"
},
  "geometry": {"coordinates":[-84.620572,45.270801],"type":"Point"}
}