{
  "type": "Feature",
  "properties": {
    "iso:country":"US",
    "sg:address":"13181 160th Ave",
    "sg:city":"Big Rapids",
    "sg:classifiers":[
        {
            "category":"Wholesale",
            "subcategory":"Machinery & Supplies",
            "type":"Manufacturing & Wholesale Goods"
        }
    ],
    "sg:phone":"+1 231 796 8600",
    "sg:postcode":"49307",
    "sg:province":"MI",
    "sg:tags":[
        "equipment",
        "industrial"
    ],
    "wof:name":"Mannix Co",
    "wof:placetype":"venue"
},
  "geometry": {"coordinates":[-85.40468300000001,43.654893],"type":"Point"}
}