{
  "type": "Feature",
  "properties": {
    "iso:country":"US",
    "sg:address":"15600 Orchard St",
    "sg:city":"Romulus",
    "sg:classifiers":[
        {
            "category":"Building & Trades",
            "subcategory":"Construction",
            "type":"Services"
        }
    ],
    "sg:phone":"+1 734 942 0515",
    "sg:postcode":"48174",
    "sg:province":"MI",
    "sg:tags":[
        "house"
    ],
    "wof:name":"Shelly N Corum",
    "wof:placetype":"venue"
},
  "geometry": {"coordinates":[-83.313045,42.19136],"type":"Point"}
}