{
  "type": "Feature",
  "properties": {
    "iso:country":"US",
    "sg:address":"16353 E Warren Ave",
    "sg:city":"Detroit",
    "sg:classifiers":[
        {
            "category":"Restaurant",
            "type":"Food & Drink"
        }
    ],
    "sg:phone":"+1 313 885 3349",
    "sg:postcode":"48224",
    "sg:province":"MI",
    "wof:name":"Gino's Coney Island",
    "wof:placetype":"venue"
},
  "geometry": {"coordinates":[-82.939301,42.402699],"type":"Point"}
}