{
  "type": "Feature",
  "properties": {
    "iso:country":"US",
    "sg:address":"6758 E Price Rd",
    "sg:city":"St Johns",
    "sg:classifiers":[
        {
            "category":"Organizations",
            "subcategory":"Religious Organization",
            "type":"Services"
        }
    ],
    "sg:phone":"+1 517 651 6153",
    "sg:postcode":"48879",
    "sg:province":"MI",
    "sg:tags":[
        "church"
    ],
    "wof:name":"Grove Bible Missionary Hse 1",
    "wof:placetype":"venue"
},
  "geometry": {"coordinates":[-84.439547,42.929],"type":"Point"}
}