{
  "type": "Feature",
  "properties": {
    "iso:country":"US",
    "sg:address":"1415 Lay Blvd",
    "sg:city":"Kalamazoo",
    "sg:classifiers":[
        {
            "category":"Building & Trades",
            "subcategory":"Construction",
            "type":"Services"
        }
    ],
    "sg:phone":"+1 269 382 2723",
    "sg:postcode":"49001",
    "sg:province":"MI",
    "sg:tags":[
        "hanging",
        "contractor"
    ],
    "wof:name":"Brown Painting",
    "wof:placetype":"venue"
},
  "geometry": {"coordinates":[-85.560593,42.273296],"type":"Point"}
}