{
  "type": "Feature",
  "properties": {
    "iso:country":"US",
    "sg:address":"525 Woodward Ave",
    "sg:city":"Rochester",
    "sg:classifiers":[
        {
            "category":"Recreation",
            "type":"Entertainment"
        }
    ],
    "sg:phone":"+1 248 652 1798",
    "sg:postcode":"48307",
    "sg:province":"MI",
    "sg:tags":[
        "parks"
    ],
    "wof:name":"Rochester Avon Recreation Auth",
    "wof:placetype":"venue"
},
  "geometry": {"coordinates":[-83.13979,42.688713],"type":"Point"}
}