{
  "type": "Feature",
  "properties": {
    "iso:country":"US",
    "sg:address":"1360 Southfield Rd",
    "sg:city":"Lincoln Park",
    "sg:classifiers":[
        {
            "category":"Restaurant",
            "type":"Food & Drink"
        }
    ],
    "sg:phone":"+1 313 383 7824",
    "sg:postcode":"48146",
    "sg:province":"MI",
    "sg:website":"www.timhortons.com",
    "wof:name":"Tim Hortons",
    "wof:placetype":"venue"
},
  "geometry": {"coordinates":[-83.17910000000001,42.251099],"type":"Point"}
}