{
  "type": "Feature",
  "properties": {
    "iso:country":"US",
    "sg:address":"356 Golden Ave",
    "sg:city":"Battle Creek",
    "sg:classifiers":[
        {
            "category":"Professional",
            "subcategory":"Business Services",
            "type":"Services"
        }
    ],
    "sg:phone":"+1 269 965 5351",
    "sg:postcode":"49015",
    "sg:province":"MI",
    "sg:tags":[
        "notary",
        "public"
    ],
    "wof:name":"Kristina E Smith",
    "wof:placetype":"venue"
},
  "geometry": {"coordinates":[-85.186071,42.293687],"type":"Point"}
}