{
  "type": "Feature",
  "properties": {
    "iso:country":"US",
    "sg:address":"11878 Ramsay Rd",
    "sg:city":"Thompsonville",
    "sg:classifiers":[
        {
            "category":"Professional",
            "subcategory":"Management & Consulting",
            "type":"Services"
        }
    ],
    "sg:phone":"+1 231 269 3163",
    "sg:postcode":"49683",
    "sg:province":"MI",
    "wof:name":"Michele Beeman Maintenance",
    "wof:placetype":"venue"
},
  "geometry": {"coordinates":[-85.815449,44.527427],"type":"Point"}
}