{
  "type": "Feature",
  "properties": {
    "iso:country":"US",
    "sg:address":"426 Edgewater Ave",
    "sg:city":"Algonac",
    "sg:classifiers":[
        {
            "category":"Retail",
            "subcategory":"Auto Repair",
            "type":"Services"
        }
    ],
    "sg:phone":"+1 810 794 9810",
    "sg:postcode":"48001",
    "sg:province":"MI",
    "sg:tags":[
        "exchanging",
        "engine"
    ],
    "wof:name":"At Your Place Auto Repair",
    "wof:placetype":"venue"
},
  "geometry": {"coordinates":[-82.539305,42.609614],"type":"Point"}
}