{
  "type": "Feature",
  "properties": {
    "iso:country":"US",
    "sg:address":"1415 Lane Blvd",
    "sg:city":"Kalamazoo",
    "sg:classifiers":[
        {
            "category":"Building & Trades",
            "subcategory":"Landscaping Services",
            "type":"Services"
        }
    ],
    "sg:phone":"+1 269 373 1946",
    "sg:postcode":"49001",
    "sg:province":"MI",
    "sg:tags":[
        "lawn",
        "maintenance",
        "grounds"
    ],
    "wof:name":"Cut Rite Lawn Care",
    "wof:placetype":"venue"
},
  "geometry": {"coordinates":[-85.560597,42.272365],"type":"Point"}
}