{
  "type": "Feature",
  "properties": {
    "iso:country":"US",
    "sg:address":"2610 Sherwood St SW",
    "sg:city":"Byron Center",
    "sg:classifiers":[
        {
            "category":"Social Services",
            "subcategory":"Adult Care",
            "type":"Services"
        }
    ],
    "sg:phone":"+1 616 878 1831",
    "sg:postcode":"49315",
    "sg:province":"MI",
    "sg:tags":[
        "foster",
        "provider"
    ],
    "wof:name":"Price Thomas & Joyce",
    "wof:placetype":"venue"
},
  "geometry": {"coordinates":[-85.728008,42.813141],"type":"Point"}
}