{
  "type": "Feature",
  "properties": {
    "iso:country":"US",
    "sg:address":"2010 Chicago Dr",
    "sg:city":"Jenison",
    "sg:classifiers":[
        {
            "category":"Professional",
            "subcategory":"Advertising",
            "type":"Services"
        }
    ],
    "sg:phone":"+1 616 669 9955",
    "sg:postcode":"49428",
    "sg:province":"MI",
    "wof:name":"Our Town Of West Michigan",
    "wof:placetype":"venue"
},
  "geometry": {"coordinates":[-85.829194,42.888547],"type":"Point"}
}