{
  "type": "Feature",
  "properties": {
    "iso:country":"US",
    "sg:address":"4153 Courtney St",
    "sg:city":"Saint Joseph",
    "sg:classifiers":[
        {
            "category":"Professional",
            "subcategory":"Engineering",
            "type":"Services"
        }
    ],
    "sg:phone":"+1 269 428 0148",
    "sg:postcode":"49085",
    "sg:province":"MI",
    "wof:name":"STS Services",
    "wof:placetype":"venue"
},
  "geometry": {"coordinates":[-86.429299,42.041857],"type":"Point"}
}