{
  "type": "Feature",
  "properties": {
    "iso:country":"US",
    "sg:address":"13959 Hall Rd",
    "sg:city":"Utica",
    "sg:classifiers":[
        {
            "category":"Home & Garden",
            "subcategory":"Household Appliances",
            "type":"Retail Goods"
        }
    ],
    "sg:phone":"+1 586 566 9988",
    "sg:postcode":"48315",
    "sg:province":"MI",
    "sg:tags":[
        "machine",
        "repair",
        "vacuum",
        "sewing",
        "cleaners"
    ],
    "wof:name":"Banks Vacuum & Sewing",
    "wof:placetype":"venue"
},
  "geometry": {"coordinates":[-82.990287,42.627531],"type":"Point"}
}