{
  "type": "Feature",
  "properties": {
    "iso:country":"US",
    "sg:address":"5850 Comstock Park Dr NW",
    "sg:city":"Comstock Park",
    "sg:classifiers":[
        {
            "category":"Building & Trades",
            "subcategory":"Construction",
            "type":"Services"
        }
    ],
    "sg:phone":"+1 616 785 8003",
    "sg:postcode":"49321",
    "sg:province":"MI",
    "sg:tags":[
        "tennis",
        "court"
    ],
    "wof:name":"Racquet Sports",
    "wof:placetype":"venue"
},
  "geometry": {"coordinates":[-85.68198,43.070677],"type":"Point"}
}