{
  "type": "Feature",
  "properties": {
    "iso:country":"US",
    "sg:address":"3049 N Linden Rd",
    "sg:city":"Flint",
    "sg:classifiers":[
        {
            "category":"Personal",
            "subcategory":"Beauty Salon",
            "type":"Services"
        }
    ],
    "sg:phone":"+1 810 720 7180",
    "sg:postcode":"48504",
    "sg:province":"MI",
    "wof:name":"Exquizit Hair Suites",
    "wof:placetype":"venue"
},
  "geometry": {"coordinates":[-83.772885,43.053367],"type":"Point"}
}