{
  "type": "Feature",
  "properties": {
    "iso:country":"US",
    "sg:address":"61899 State Hwy 43",
    "sg:city":"Bangor",
    "sg:classifiers":[
        {
            "category":"Home & Garden",
            "subcategory":"Building Materials",
            "type":"Retail Goods"
        }
    ],
    "sg:phone":"+1 269 637 5403",
    "sg:postcode":"49013",
    "sg:province":"MI",
    "sg:tags":[
        "glass",
        "leaded"
    ],
    "wof:name":"Alice's Looking Glass",
    "wof:placetype":"venue"
},
  "geometry": {"coordinates":[-86.147397,42.327453],"type":"Point"}
}