{
  "type": "Feature",
  "properties": {
    "iso:country":"US",
    "sg:address":"953 S Eton St",
    "sg:city":"Birmingham",
    "sg:classifiers":[
        {
            "category":"Wholesale",
            "subcategory":"Machinery & Supplies",
            "type":"Manufacturing & Wholesale Goods"
        }
    ],
    "sg:phone":"+1 248 647 6750",
    "sg:postcode":"48009",
    "sg:province":"MI",
    "sg:tags":[
        "contractor"
    ],
    "sg:website":"www.advancedsystems.biz",
    "wof:name":"Advanced Specialties Inc",
    "wof:placetype":"venue"
},
  "geometry": {"coordinates":[-83.195567,42.540895],"type":"Point"}
}