{
  "type": "Feature",
  "properties": {
    "iso:country":"US",
    "sg:address":"935 State Hwy 189",
    "sg:city":"Iron River",
    "sg:classifiers":[
        {
            "category":"Manufacturing",
            "subcategory":"Paper Products",
            "type":"Manufacturing & Wholesale Goods"
        }
    ],
    "sg:phone":"+1 906 265 4638",
    "sg:postcode":"49935",
    "sg:province":"MI",
    "sg:tags":[
        "pulp"
    ],
    "wof:name":"Stora Enso North America Corp",
    "wof:placetype":"venue"
},
  "geometry": {"coordinates":[-88.642768,46.074733],"type":"Point"}
}