{
  "type": "Feature",
  "properties": {
    "iso:country":"US",
    "sg:address":"318 E Slosson Ave",
    "sg:city":"Reed City",
    "sg:classifiers":[
        {
            "category":"Manufacturing",
            "subcategory":"Tools & Machinery",
            "type":"Manufacturing & Wholesale Goods"
        }
    ],
    "sg:phone":"+1 231 832 9605",
    "sg:postcode":"49677",
    "sg:province":"MI",
    "sg:tags":[
        "machine"
    ],
    "wof:name":"Professional Machine Solutions",
    "wof:placetype":"venue"
},
  "geometry": {"coordinates":[-85.506288,43.874778],"type":"Point"}
}