{
  "type": "Feature",
  "properties": {
    "iso:country":"US",
    "sg:address":"11116 Quirk Rd",
    "sg:city":"Belleville",
    "sg:classifiers":[
        {
            "category":"Building & Trades",
            "subcategory":"Construction",
            "type":"Services"
        }
    ],
    "sg:phone":"+1 734 697 9643",
    "sg:postcode":"48111",
    "sg:province":"MI",
    "sg:tags":[
        "house"
    ],
    "wof:name":"Rods Construction Inc",
    "wof:placetype":"venue"
},
  "geometry": {"coordinates":[-83.494326,42.221702],"type":"Point"}
}