{
  "type": "Feature",
  "properties": {
    "iso:country":"US",
    "sg:address":"21 44th St SW",
    "sg:city":"Grand Rapids",
    "sg:classifiers":[
        {
            "category":"Personal",
            "subcategory":"Beauty Salon",
            "type":"Services"
        }
    ],
    "sg:phone":"+1 616 531 7717",
    "sg:postcode":"49548",
    "sg:province":"MI",
    "sg:tags":[
        "shop",
        "manicuring"
    ],
    "wof:name":"Fancy Nails",
    "wof:placetype":"venue"
},
  "geometry": {"coordinates":[-85.66518000000001,42.884078],"type":"Point"}
}