{
  "type": "Feature",
  "properties": {
    "iso:country":"US",
    "sg:address":"323 Saginaw St",
    "sg:city":"Norway",
    "sg:classifiers":[
        {
            "category":"Home & Garden",
            "subcategory":"Building Materials",
            "type":"Retail Goods"
        }
    ],
    "sg:phone":"+1 906 563 5710",
    "sg:postcode":"49870",
    "sg:province":"MI",
    "sg:tags":[
        "windows"
    ],
    "wof:name":"Up Window Specialist",
    "wof:placetype":"venue"
},
  "geometry": {"coordinates":[-87.91113900000001,45.783344],"type":"Point"}
}