{
  "type": "Feature",
  "properties": {
    "iso:country":"US",
    "sg:address":"3350 Main St",
    "sg:city":"Ravenna",
    "sg:classifiers":[
        {
            "category":"Manufacturing",
            "subcategory":"Printing",
            "type":"Manufacturing & Wholesale Goods"
        }
    ],
    "sg:phone":"+1 231 853 2244",
    "sg:postcode":"49451",
    "sg:province":"MI",
    "sg:tags":[
        "printer"
    ],
    "sg:website":"www.rogersprinting.net",
    "wof:name":"Rogers Printing Inc",
    "wof:placetype":"venue"
},
  "geometry": {"coordinates":[-85.936544,43.191847],"type":"Point"}
}