{
  "type": "Feature",
  "properties": {
    "iso:country":"US",
    "sg:address":"607 Cascade West Pkwy SE",
    "sg:city":"Grand Rapids",
    "sg:classifiers":[
        {
            "category":"Professional",
            "subcategory":"Accounting & Tax Preparation",
            "type":"Services"
        }
    ],
    "sg:phone":"+1 616 575 5611",
    "sg:postcode":"49546",
    "sg:province":"MI",
    "sg:tags":[
        "accountant"
    ],
    "wof:name":"Accounting Offices-Lisa M Ward",
    "wof:placetype":"venue"
},
  "geometry": {"coordinates":[-85.569761,42.950638],"type":"Point"}
}