{
  "type": "Feature",
  "properties": {
    "iso:country":"US",
    "sg:address":"1442 Bowers Rd",
    "sg:city":"Lapeer",
    "sg:classifiers":[
        {
            "category":"Shopping",
            "subcategory":"Computers & Home Electronics",
            "type":"Retail Goods"
        }
    ],
    "sg:phone":"+1 810 664 6548",
    "sg:postcode":"48446",
    "sg:province":"MI",
    "sg:tags":[
        "equipment",
        "satellite",
        "system"
    ],
    "wof:name":"Lynx's Satellite Svc",
    "wof:placetype":"venue"
},
  "geometry": {"coordinates":[-83.286597,43.058891],"type":"Point"}
}