{
  "type": "Feature",
  "properties": {
    "iso:country":"US",
    "sg:address":"111 N 1st",
    "sg:city":"Harrison",
    "sg:classifiers":[
        {
            "category":"Food & Beverages",
            "subcategory":"Groceries & Convenience Stores",
            "type":"Retail Goods"
        }
    ],
    "sg:phone":"+1 989 539 2134",
    "sg:postcode":"48625",
    "sg:province":"MI",
    "wof:name":"Sunrise Convenience Stores",
    "wof:placetype":"venue"
},
  "geometry": {"coordinates":[-85.02847199999999,43.996055],"type":"Point"}
}