{
  "type": "Feature",
  "properties": {
    "iso:country":"US",
    "sg:address":"7410 Expressway Dr SW",
    "sg:city":"Grand Rapids",
    "sg:classifiers":[
        {
            "category":"Freight",
            "type":"Transportation"
        }
    ],
    "sg:phone":"+1 616 827 3340",
    "sg:postcode":"49548",
    "sg:province":"MI",
    "sg:tags":[
        "intrastate",
        "trucking"
    ],
    "wof:name":"E L Hollingsworth and Co",
    "wof:placetype":"venue"
},
  "geometry": {"coordinates":[-85.670666,42.829932],"type":"Point"}
}