{
  "type": "Feature",
  "properties": {
    "iso:country":"US",
    "sg:address":"44600 Ecorse Rd",
    "sg:city":"Belleville",
    "sg:classifiers":[
        {
            "category":"Building & Trades",
            "subcategory":"Construction",
            "type":"Services"
        }
    ],
    "sg:phone":"+1 734 699 9497",
    "sg:postcode":"48111",
    "sg:province":"MI",
    "sg:tags":[
        "contractor"
    ],
    "wof:name":"Zaborowski Mike Builder",
    "wof:placetype":"venue"
},
  "geometry": {"coordinates":[-83.47199999999999,42.248901],"type":"Point"}
}