{
  "type": "Feature",
  "properties": {
    "iso:country":"US",
    "sg:address":"413 W Ruth Ave",
    "sg:city":"Flint",
    "sg:classifiers":[
        {
            "category":"Social Services",
            "subcategory":"Child Care",
            "type":"Services"
        }
    ],
    "sg:phone":"+1 810 787 1279",
    "sg:postcode":"48505",
    "sg:province":"MI",
    "sg:tags":[
        "day"
    ],
    "wof:name":"Jw's Day Care",
    "wof:placetype":"venue"
},
  "geometry": {"coordinates":[-83.7114,43.070071],"type":"Point"}
}