{
  "type": "Feature",
  "properties": {
    "iso:country":"US",
    "sg:address":"6718 Bloomfield Ln",
    "sg:city":"West Bloomfield",
    "sg:classifiers":[
        {
            "category":"Home & Garden",
            "subcategory":"Furniture",
            "type":"Retail Goods"
        }
    ],
    "sg:phone":"+1 734 732 5861",
    "sg:postcode":"48322",
    "sg:province":"MI",
    "sg:tags":[
        "bed"
    ],
    "wof:name":"Migun",
    "wof:placetype":"venue"
},
  "geometry": {"coordinates":[-83.332855,42.54262],"type":"Point"}
}