{
  "type": "Feature",
  "properties": {
    "iso:country":"US",
    "sg:address":"5180 37th Ave",
    "sg:city":"Hudsonville",
    "sg:classifiers":[
        {
            "category":"Retail",
            "subcategory":"Auto Repair",
            "type":"Services"
        }
    ],
    "sg:phone":"+1 616 669 9614",
    "sg:postcode":"49426",
    "sg:province":"MI",
    "wof:name":"Dykstra Auto Service Inc",
    "wof:placetype":"venue"
},
  "geometry": {"coordinates":[-85.873813,42.862989],"type":"Point"}
}