{
  "type": "Feature",
  "properties": {
    "iso:country":"US",
    "sg:address":"126 E Saginaw St",
    "sg:city":"Saint Louis",
    "sg:classifiers":[
        {
            "category":"Organizations",
            "subcategory":"Religious Organization",
            "type":"Services"
        }
    ],
    "sg:phone":"+1 989 681 2353",
    "sg:postcode":"48880",
    "sg:province":"MI",
    "wof:name":"Parkside Assmbly of God Church",
    "wof:placetype":"venue"
},
  "geometry": {"coordinates":[-84.60684999999999,43.409146],"type":"Point"}
}