{
  "type": "Feature",
  "properties": {
    "iso:country":"US",
    "sg:address":"6543 Stadium Dr",
    "sg:city":"Kalamazoo",
    "sg:classifiers":[
        {
            "category":"Building & Trades",
            "subcategory":"Construction",
            "type":"Services"
        }
    ],
    "sg:phone":"+1 269 375 7149",
    "sg:postcode":"49009",
    "sg:province":"MI",
    "sg:tags":[
        "paving",
        "asphalt",
        "contractor"
    ],
    "wof:name":"Pavement Restoration Of Mi",
    "wof:placetype":"venue"
},
  "geometry": {"coordinates":[-85.677537,42.259141],"type":"Point"}
}