{
  "type": "Feature",
  "properties": {
    "iso:country":"US",
    "sg:address":"22410 S Woodward Ave",
    "sg:city":"Ferndale",
    "sg:classifiers":[
        {
            "category":"Retail",
            "subcategory":"Laundry & Dry Cleaning",
            "type":"Services"
        }
    ],
    "sg:phone":"+1 248 542 3638",
    "sg:postcode":"48220",
    "sg:province":"MI",
    "sg:tags":[
        "floor",
        "covering"
    ],
    "wof:name":"Capital Carpet Clg & Dye Co",
    "wof:placetype":"venue"
},
  "geometry": {"coordinates":[-83.132575,42.458112],"type":"Point"}
}