{
  "type": "Feature",
  "properties": {
    "iso:country":"US",
    "sg:address":"15500 Knobhill Dr",
    "sg:city":"Linden",
    "sg:classifiers":[
        {
            "category":"Professional",
            "subcategory":"Accounting & Tax Preparation",
            "type":"Services"
        }
    ],
    "sg:phone":"+1 810 735 7373",
    "sg:postcode":"48451",
    "sg:province":"MI",
    "sg:tags":[
        "return"
    ],
    "wof:name":"Burts Tax Svc",
    "wof:placetype":"venue"
},
  "geometry": {"coordinates":[-83.82588699999999,42.797853],"type":"Point"}
}