{
  "type": "Feature",
  "properties": {
    "iso:country":"US",
    "sg:address":"851 S Garfield Ave",
    "sg:city":"Traverse City",
    "sg:classifiers":[
        {
            "category":"Restaurant",
            "type":"Food & Drink"
        }
    ],
    "sg:menulink":"http://www.allmenus.com/mi/traverse-city/141353-agave-mexican-grill/menu/",
    "sg:phone":"+1 231 929 4408",
    "sg:postcode":"49686",
    "sg:province":"MI",
    "sg:tags":[
        "mexican"
    ],
    "wof:name":"Agave Mexican Grill",
    "wof:placetype":"venue"
},
  "geometry": {"coordinates":[-85.595313,44.752318],"type":"Point"}
}