{
  "type": "Feature",
  "properties": {
    "iso:country":"US",
    "sg:address":"1174 Robert T Longwy Blvd",
    "sg:city":"Flint",
    "sg:classifiers":[
        {
            "category":"Restaurant",
            "type":"Food & Drink"
        }
    ],
    "sg:phone":"+1 810 235 1588",
    "sg:postcode":"48503",
    "sg:province":"MI",
    "sg:tags":[
        "chinese"
    ],
    "wof:name":"China 1 Buffet",
    "wof:placetype":"venue"
},
  "geometry": {"coordinates":[-83.68240400000001,43.025799],"type":"Point"}
}