{
  "type": "Feature",
  "properties": {
    "iso:country":"US",
    "sg:address":"736 S Michigan Ave",
    "sg:city":"Howell",
    "sg:classifiers":[
        {
            "category":"Wholesale",
            "subcategory":"Durable Goods & Equipment",
            "type":"Manufacturing & Wholesale Goods"
        }
    ],
    "sg:phone":"+1 517 546 7931",
    "sg:postcode":"48843",
    "sg:province":"MI",
    "sg:tags":[
        "representative",
        "manufacturer"
    ],
    "wof:name":"Martin R Nelson & Assoc",
    "wof:placetype":"venue"
},
  "geometry": {"coordinates":[-83.93368100000001,42.601107],"type":"Point"}
}