{
  "type": "Feature",
  "properties": {
    "iso:country":"US",
    "sg:address":"11870 Calendar Rd",
    "sg:city":"Battle Creek",
    "sg:classifiers":[
        {
            "category":"Freight",
            "type":"Transportation"
        }
    ],
    "sg:phone":"+1 269 965 5323",
    "sg:postcode":"49014",
    "sg:province":"MI",
    "sg:tags":[
        "operator",
        "local",
        "trucking"
    ],
    "wof:name":"R&S Tree Service",
    "wof:placetype":"venue"
},
  "geometry": {"coordinates":[-85.074647,42.371799],"type":"Point"}
}