{
  "type": "Feature",
  "properties": {
    "iso:country":"US",
    "sg:address":"52411 Gratiot Ave",
    "sg:city":"Chesterfield",
    "sg:classifiers":[
        {
            "category":"Manufacturing",
            "subcategory":"Food",
            "type":"Manufacturing & Wholesale Goods"
        }
    ],
    "sg:phone":"+1 586 598 8282",
    "sg:postcode":"48051",
    "sg:province":"MI",
    "sg:tags":[
        "product",
        "manufacturer"
    ],
    "wof:name":"Safie Specialty Foods",
    "wof:placetype":"venue"
},
  "geometry": {"coordinates":[-82.82575799999999,42.68433],"type":"Point"}
}