{
  "type": "Feature",
  "properties": {
    "iso:country":"US",
    "sg:address":"36691 Jefferson Ave",
    "sg:city":"Harrison Township",
    "sg:classifiers":[
        {
            "category":"Restaurant",
            "type":"Food & Drink"
        }
    ],
    "sg:phone":"+1 586 468 7711",
    "sg:postcode":"48045",
    "sg:province":"MI",
    "sg:tags":[
        "pizza"
    ],
    "sg:website":"www.luigisoriginal.com",
    "wof:name":"Luigi's Original Restaurant",
    "wof:placetype":"venue"
},
  "geometry": {"coordinates":[-82.8395,42.569099],"type":"Point"}
}