{
  "type": "Feature",
  "properties": {
    "iso:country":"US",
    "sg:address":"6330 Holton Rd",
    "sg:city":"Twin Lake",
    "sg:classifiers":[
        {
            "category":"Communications",
            "type":"Services"
        }
    ],
    "sg:phone":"+1 231 828 4976",
    "sg:postcode":"49457",
    "sg:province":"MI",
    "wof:name":"4m Communications",
    "wof:placetype":"venue"
},
  "geometry": {"coordinates":[-86.152636,43.369269],"type":"Point"}
}