{
  "type": "Feature",
  "properties": {
    "iso:country":"US",
    "sg:address":"672 Birchwood Dr",
    "sg:city":"Manistee",
    "sg:classifiers":[
        {
            "category":"Professional",
            "subcategory":"Business Services",
            "type":"Services"
        }
    ],
    "sg:phone":"+1 231 723 6899",
    "sg:postcode":"49660",
    "sg:province":"MI",
    "wof:name":"Eclipse Engineering Solutions",
    "wof:placetype":"venue"
},
  "geometry": {"coordinates":[-86.29122700000001,44.303808],"type":"Point"}
}