{
  "type": "Feature",
  "properties": {
    "iso:country":"US",
    "sg:address":"223 Phillips St",
    "sg:city":"Nashville",
    "sg:classifiers":[
        {
            "category":"Building & Trades",
            "subcategory":"Construction",
            "type":"Services"
        }
    ],
    "sg:phone":"+1 517 852 9264",
    "sg:postcode":"49073",
    "sg:province":"MI",
    "sg:tags":[
        "hanging",
        "contractor"
    ],
    "wof:name":"E Mason Richd",
    "wof:placetype":"venue"
},
  "geometry": {"coordinates":[-85.088683,42.604016],"type":"Point"}
}