{
  "type": "Feature",
  "properties": {
    "iso:country":"US",
    "sg:address":"4041 Gratiot Ave",
    "sg:city":"Fort Gratiot",
    "sg:classifiers":[
        {
            "category":"Professional",
            "subcategory":"Accounting & Tax Preparation",
            "type":"Services"
        }
    ],
    "sg:phone":"+1 810 385 5607",
    "sg:postcode":"48059",
    "sg:province":"MI",
    "sg:tags":[
        "return"
    ],
    "wof:name":"Richard Axford",
    "wof:placetype":"venue"
},
  "geometry": {"coordinates":[-82.435712,43.025745],"type":"Point"}
}