{
  "type": "Feature",
  "properties": {
    "iso:country":"US",
    "sg:address":"5914 S Ray St",
    "sg:city":"Glen Arbor",
    "sg:classifiers":[
        {
            "category":"Shopping",
            "subcategory":"Bicycles & Sporting Goods",
            "type":"Retail Goods"
        }
    ],
    "sg:phone":"+1 231 334 3872",
    "sg:postcode":"49636",
    "sg:province":"MI",
    "sg:tags":[
        "tackle",
        "fishing"
    ],
    "wof:name":"Sportsman Shop",
    "wof:placetype":"venue"
},
  "geometry": {"coordinates":[-85.990538,44.897708],"type":"Point"}
}