{
  "type": "Feature",
  "properties": {
    "iso:country":"US",
    "sg:address":"135 S Front St",
    "sg:city":"Dowagiac",
    "sg:classifiers":[
        {
            "category":"Banks & Credit Unions",
            "subcategory":"Bank",
            "type":"Services"
        }
    ],
    "sg:phone":"+1 269 782 5121",
    "sg:postcode":"49047",
    "sg:province":"MI",
    "sg:tags":[
        "state",
        "commercial"
    ],
    "wof:name":"First Source",
    "wof:placetype":"venue"
},
  "geometry": {"coordinates":[-86.10797599999999,41.983188],"type":"Point"}
}