{
  "type": "Feature",
  "properties": {
    "iso:country":"US",
    "sg:address":"33535 Woodward Ave",
    "sg:city":"Birmingham",
    "sg:classifiers":[
        {
            "category":"Shopping",
            "subcategory":"Computers & Home Electronics",
            "type":"Retail Goods"
        }
    ],
    "sg:phone":"+1 248 642 9777",
    "sg:postcode":"48009",
    "sg:province":"MI",
    "sg:tags":[
        "high",
        "fidelity",
        "stereophonic"
    ],
    "wof:name":"Gramophone",
    "wof:placetype":"venue"
},
  "geometry": {"coordinates":[-83.202808,42.535478],"type":"Point"}
}