{
  "type": "Feature",
  "properties": {
    "iso:country":"US",
    "sg:address":"122 E Miller Rd",
    "sg:city":"Midland",
    "sg:classifiers":[
        {
            "category":"Professional",
            "subcategory":"Accounting & Tax Preparation",
            "type":"Services"
        }
    ],
    "sg:phone":"+1 989 832 2763",
    "sg:postcode":"48640",
    "sg:province":"MI",
    "sg:tags":[
        "payroll"
    ],
    "wof:name":"Paychex Inc",
    "wof:placetype":"venue"
},
  "geometry": {"coordinates":[-84.366057,43.583217],"type":"Point"}
}