{
  "type": "Feature",
  "properties": {
    "iso:country":"US",
    "sg:address":"16207 Mott Dr",
    "sg:city":"Macomb",
    "sg:classifiers":[
        {
            "category":"Arts & Performance",
            "subcategory":"Theater",
            "type":"Entertainment"
        }
    ],
    "sg:phone":"+1 586 226 1820",
    "sg:postcode":"48044",
    "sg:province":"MI",
    "sg:tags":[
        "entertainer",
        "business"
    ],
    "wof:name":"Richard Paul & Assoc",
    "wof:placetype":"venue"
},
  "geometry": {"coordinates":[-82.960902,42.651562],"type":"Point"}
}