{
  "type": "Feature",
  "properties": {
    "iso:country":"US",
    "sg:address":"13980 Schavey Rd",
    "sg:city":"Dewitt",
    "sg:classifiers":[
        {
            "category":"Social Services",
            "subcategory":"Child Care",
            "type":"Services"
        }
    ],
    "sg:phone":"+1 517 669 7612",
    "sg:postcode":"48820",
    "sg:province":"MI",
    "sg:tags":[
        "kindergarten",
        "academic",
        "school"
    ],
    "wof:name":"Prime Time Preschool",
    "wof:placetype":"venue"
},
  "geometry": {"coordinates":[-84.590107,42.814286],"type":"Point"}
}