{
  "type": "Feature",
  "properties": {
    "iso:country":"US",
    "sg:address":"3878 Lucille Dr",
    "sg:city":"Lambertville",
    "sg:classifiers":[
        {
            "category":"Building & Trades",
            "subcategory":"Construction",
            "type":"Services"
        }
    ],
    "sg:phone":"+1 734 854 5850",
    "sg:postcode":"48144",
    "sg:province":"MI",
    "sg:tags":[
        "contractor"
    ],
    "wof:name":"Prestige Powerwashing",
    "wof:placetype":"venue"
},
  "geometry": {"coordinates":[-83.63713,41.753397],"type":"Point"}
}