{
  "type": "Feature",
  "properties": {
    "iso:country":"US",
    "sg:address":"520 Briarwood Cir",
    "sg:city":"Ann Arbor",
    "sg:classifiers":[
        {
            "category":"Autos & Motor Vehicles",
            "subcategory":"Auto Supplies",
            "type":"Retail Goods"
        }
    ],
    "sg:phone":"+1 734 769 1485",
    "sg:postcode":"48108",
    "sg:province":"MI",
    "sg:tags":[
        "tire"
    ],
    "wof:name":"Firestone Tire & Auto Ctr",
    "wof:placetype":"venue"
},
  "geometry": {"coordinates":[-83.745666,42.237881],"type":"Point"}
}