{
  "type": "Feature",
  "properties": {
    "iso:country":"US",
    "sg:address":"9309 Hubbell St",
    "sg:city":"Detroit",
    "sg:classifiers":[
        {
            "category":"Retail",
            "subcategory":"Auto Repair",
            "type":"Services"
        }
    ],
    "sg:phone":"+1 313 836 5000",
    "sg:postcode":"48228",
    "sg:province":"MI",
    "sg:tags":[
        "automotive",
        "used",
        "parts"
    ],
    "wof:name":"Ryans Hubbell Auto Parts",
    "wof:placetype":"venue"
},
  "geometry": {"coordinates":[-83.18754300000001,42.364326],"type":"Point"}
}