{
  "type": "Feature",
  "properties": {
    "iso:country":"US",
    "sg:address":"400 Hobart St",
    "sg:city":"Cadillac",
    "sg:classifiers":[
        {
            "category":"Health Services",
            "subcategory":"Doctor",
            "type":"Services"
        }
    ],
    "sg:phone":"+1 231 876 7911",
    "sg:postcode":"49601",
    "sg:province":"MI",
    "sg:tags":[
        "physician",
        "surgeon"
    ],
    "wof:name":"Preferred Choices",
    "wof:placetype":"venue"
},
  "geometry": {"coordinates":[-85.39054899999999,44.24612],"type":"Point"}
}