{
  "type": "Feature",
  "properties": {
    "iso:country":"US",
    "sg:address":"104 E Main St",
    "sg:city":"Fremont",
    "sg:classifiers":[
        {
            "category":"Education",
            "subcategory":"Library",
            "type":"Public Place"
        }
    ],
    "sg:phone":"+1 231 924 3480",
    "sg:postcode":"49412",
    "sg:province":"MI",
    "wof:name":"Fremont Area District Library",
    "wof:placetype":"venue"
},
  "geometry": {"coordinates":[-85.943129,43.467035],"type":"Point"}
}