{
  "type": "Feature",
  "properties": {
    "iso:country":"US",
    "sg:address":"7 N Main St",
    "sg:city":"Mount Clemens",
    "sg:classifiers":[
        {
            "category":"Professional",
            "subcategory":"Lawyer & Legal Services",
            "type":"Services"
        }
    ],
    "sg:phone":"+1 586 463 9590",
    "sg:postcode":"48043",
    "sg:province":"MI",
    "sg:tags":[
        "attorney"
    ],
    "wof:name":"Toia PC",
    "wof:placetype":"venue"
},
  "geometry": {"coordinates":[-82.878304,42.597],"type":"Point"}
}