{
  "type": "Feature",
  "properties": {
    "iso:country":"US",
    "sg:address":"8950 Macomb St",
    "sg:city":"Grosse Ile",
    "sg:classifiers":[
        {
            "category":"Retail",
            "subcategory":"Auto Rental",
            "type":"Services"
        }
    ],
    "sg:phone":"+1 734 676 9090",
    "sg:postcode":"48138",
    "sg:province":"MI",
    "sg:tags":[
        "passenger",
        "leasing",
        "car"
    ],
    "wof:name":"McQ Leasing Inc",
    "wof:placetype":"venue"
},
  "geometry": {"coordinates":[-83.15700200000001,42.130702],"type":"Point"}
}