{
  "type": "Feature",
  "properties": {
    "iso:country":"US",
    "sg:address":"5161 E Court St N",
    "sg:city":"Burton",
    "sg:classifiers":[
        {
            "category":"Banks & Credit Unions",
            "subcategory":"Investment Brokerage",
            "type":"Services"
        }
    ],
    "sg:phone":"+1 810 744 4450",
    "sg:postcode":"48509",
    "sg:province":"MI",
    "sg:tags":[
        "consultant",
        "planning",
        "financial"
    ],
    "wof:name":"Complete Financial Concept",
    "wof:placetype":"venue"
},
  "geometry": {"coordinates":[-83.610005,43.019801],"type":"Point"}
}