{
  "type": "Feature",
  "properties": {
    "iso:country":"US",
    "sg:address":"3750 Meldrum Rd",
    "sg:city":"Casco",
    "sg:classifiers":[
        {
            "category":"Organizations",
            "subcategory":"Religious Organization",
            "type":"Services"
        }
    ],
    "sg:phone":"+1 586 727 7023",
    "sg:postcode":"48064",
    "sg:province":"MI",
    "wof:name":"Upper Room Church",
    "wof:placetype":"venue"
},
  "geometry": {"coordinates":[-82.673571,42.783811],"type":"Point"}
}