{
  "type": "Feature",
  "properties": {
    "iso:country":"US",
    "sg:address":"3305 Remembrance Rd NW",
    "sg:city":"Grand Rapids",
    "sg:classifiers":[
        {
            "category":"Professional",
            "subcategory":"Business Services",
            "type":"Services"
        }
    ],
    "sg:phone":"+1 616 791 9780",
    "sg:postcode":"49534",
    "sg:province":"MI",
    "sg:tags":[
        "water",
        "treatment"
    ],
    "wof:name":"Water Specifications Inc",
    "wof:placetype":"venue"
},
  "geometry": {"coordinates":[-85.749658,42.987834],"type":"Point"}
}