{
  "type": "Feature",
  "properties": {
    "iso:country":"US",
    "sg:address":"29297 Southfield Rd",
    "sg:city":"Southfield",
    "sg:classifiers":[
        {
            "category":"Shopping",
            "subcategory":"Clothing, Apparel, & Fashions",
            "type":"Retail Goods"
        },
        {
            "category":"Shopping",
            "subcategory":"Adult",
            "type":"Retail Goods"
        }
    ],
    "sg:phone":"+1 248 557 7165",
    "sg:postcode":"48076",
    "sg:province":"MI",
    "sg:tags":[
        "girdle",
        "lingerie",
        "corset",
        "bra"
    ],
    "sg:website":"http://www.tinamarieshop.com",
    "wof:name":"Tina Marie Shop",
    "wof:placetype":"venue"
},
  "geometry": {"coordinates":[-83.2229,42.5051],"type":"Point"}
}