{
  "type": "Feature",
  "properties": {
    "iso:country":"US",
    "sg:address":"20900 Oakwood Blvd",
    "sg:city":"Dearborn",
    "sg:classifiers":[
        {
            "category":"Landmark",
            "subcategory":"Historic",
            "type":"Public Place"
        },
        {
            "category":"Museum",
            "type":"Entertainment"
        }
    ],
    "sg:phone":"+1 313 271 1620",
    "sg:postcode":"48124",
    "sg:province":"MI",
    "sg:tags":[
        "building",
        "historical"
    ],
    "sg:website":"thehenryford.org/",
    "wof:name":"The Henry Ford",
    "wof:placetype":"venue"
},
  "geometry": {"coordinates":[-83.234703,42.3008],"type":"Point"}
}