{
  "type": "Feature",
  "properties": {
    "iso:country":"US",
    "sg:address":"9000 Marilyn Ter",
    "sg:city":"Commerce Township",
    "sg:classifiers":[
        {
            "category":"Personal",
            "subcategory":"Beauty Salon",
            "type":"Services"
        }
    ],
    "sg:phone":"+1 248 363 8952",
    "sg:postcode":"48382",
    "sg:province":"MI",
    "sg:tags":[
        "shop"
    ],
    "wof:name":"Seagrens Hair Styling",
    "wof:placetype":"venue"
},
  "geometry": {"coordinates":[-83.462569,42.59019],"type":"Point"}
}