{
  "type": "Feature",
  "properties": {
    "iso:country":"US",
    "sg:address":"260 N Klug Rd",
    "sg:city":"Harbor Beach",
    "sg:classifiers":[
        {
            "category":"Recreation",
            "type":"Entertainment"
        }
    ],
    "sg:phone":"+1 989 479 3553",
    "sg:postcode":"48441",
    "sg:province":"MI",
    "sg:tags":[
        "club",
        "membership"
    ],
    "wof:name":"New Image Racquetball & Fitnes",
    "wof:placetype":"venue"
},
  "geometry": {"coordinates":[-82.683387,43.842522],"type":"Point"}
}