{
  "type": "Feature",
  "properties": {
    "iso:country":"US",
    "sg:address":"905 E Brickley Ave",
    "sg:city":"Hazel Park",
    "sg:classifiers":[
        {
            "category":"Retail",
            "subcategory":"Repair Shop",
            "type":"Services"
        }
    ],
    "sg:phone":"+1 248 547 1509",
    "sg:postcode":"48030",
    "sg:province":"MI",
    "wof:name":"Clawson Plumbing & Sewer Svc",
    "wof:placetype":"venue"
},
  "geometry": {"coordinates":[-83.095007,42.474781],"type":"Point"}
}