{
  "type": "Feature",
  "properties": {
    "iso:country":"US",
    "sg:address":"2868 E Carlton Center Rd",
    "sg:city":"Hastings",
    "sg:classifiers":[
        {
            "category":"Building & Trades",
            "subcategory":"Construction",
            "type":"Services"
        }
    ],
    "sg:phone":"+1 269 948 0489",
    "sg:postcode":"49058",
    "sg:province":"MI",
    "sg:tags":[
        "contractor"
    ],
    "wof:name":"Lakewood Builders",
    "wof:placetype":"venue"
},
  "geometry": {"coordinates":[-85.234185,42.72636],"type":"Point"}
}