{
  "type": "Feature",
  "properties": {
    "iso:country":"US",
    "sg:address":"2870 Heritage Dr",
    "sg:city":"Tecumseh",
    "sg:classifiers":[
        {
            "category":"Manufacturing",
            "subcategory":"Jewelry",
            "type":"Manufacturing & Wholesale Goods"
        }
    ],
    "sg:phone":"+1 517 423 7991",
    "sg:postcode":"49286",
    "sg:province":"MI",
    "sg:tags":[
        "material",
        "mfg"
    ],
    "wof:name":"Kim Just",
    "wof:placetype":"venue"
},
  "geometry": {"coordinates":[-83.96778500000001,41.990935],"type":"Point"}
}