{
  "type": "Feature",
  "properties": {
    "iso:country":"US",
    "sg:address":"5793 W Maple Rd Ste 147",
    "sg:city":"West Bloomfield",
    "sg:classifiers":[
        {
            "category":"Health Services",
            "subcategory":"Chiropractor",
            "type":"Services"
        }
    ],
    "sg:phone":"+1 248 626 0001",
    "sg:postcode":"48322",
    "sg:province":"MI",
    "wof:name":"Budaj David PC",
    "wof:placetype":"venue"
},
  "geometry": {"coordinates":[-83.367086,42.542623],"type":"Point"}
}