{
  "type": "Feature",
  "properties": {
    "iso:country":"US",
    "sg:address":"33739 Elford Dr",
    "sg:city":"Sterling Heights",
    "sg:classifiers":[
        {
            "category":"Freight",
            "type":"Transportation"
        }
    ],
    "sg:phone":"+1 586 264 4191",
    "sg:postcode":"48312",
    "sg:province":"MI",
    "sg:tags":[
        "operator",
        "local",
        "trucking"
    ],
    "wof:name":"Karic Fahrudin Trucking",
    "wof:placetype":"venue"
},
  "geometry": {"coordinates":[-83.024962,42.542823],"type":"Point"}
}