{
  "type": "Feature",
  "properties": {
    "iso:country":"US",
    "sg:address":"115 State St",
    "sg:city":"Detroit",
    "sg:classifiers":[
        {
            "category":"Health Services",
            "subcategory":"Dentist",
            "type":"Services"
        }
    ],
    "sg:phone":"+1 313 963 3336",
    "sg:postcode":"48226",
    "sg:province":"MI",
    "wof:name":"Johnson David R",
    "wof:placetype":"venue"
},
  "geometry": {"coordinates":[-83.04940000000001,42.332401],"type":"Point"}
}