{
  "type": "Feature",
  "properties": {
    "iso:country":"US",
    "sg:address":"40795 Garfield Rd",
    "sg:city":"Clinton Township",
    "sg:classifiers":[
        {
            "category":"Restaurant",
            "type":"Food & Drink"
        }
    ],
    "sg:phone":"+1 586 228 3808",
    "sg:postcode":"48038",
    "sg:province":"MI",
    "sg:tags":[
        "chinese"
    ],
    "wof:name":"Oriental Wok",
    "wof:placetype":"venue"
},
  "geometry": {"coordinates":[-82.95252499999999,42.596893],"type":"Point"}
}