{
  "type": "Feature",
  "properties": {
    "iso:country":"US",
    "sg:address":"13335 15 Mile Rd Ste 226",
    "sg:city":"Sterling Heights",
    "sg:classifiers":[
        {
            "category":"Professional",
            "subcategory":"Advertising",
            "type":"Services"
        }
    ],
    "sg:phone":"+1 800 648 5158",
    "sg:postcode":"48312",
    "sg:province":"MI",
    "sg:tags":[
        "marketing"
    ],
    "sg:website":"wordsforhirellc.com",
    "wof:name":"Words For Hire",
    "wof:placetype":"venue"
},
  "geometry": {"coordinates":[-82.993668,42.552138],"type":"Point"}
}