{
  "type": "Feature",
  "properties": {
    "iso:country":"US",
    "sg:address":"23430 Forest St",
    "sg:city":"Oak Park",
    "sg:classifiers":[
        {
            "category":"Building & Trades",
            "subcategory":"Landscaping Services",
            "type":"Services"
        }
    ],
    "sg:phone":"+1 248 548 3164",
    "sg:postcode":"48237",
    "sg:province":"MI",
    "sg:tags":[
        "landscape",
        "contractor"
    ],
    "wof:name":"T S Landscaping",
    "wof:placetype":"venue"
},
  "geometry": {"coordinates":[-83.154656,42.466153],"type":"Point"}
}