{
  "type": "Feature",
  "properties": {
    "iso:country":"US",
    "sg:address":"1974 Breton Rd SE",
    "sg:city":"Grand Rapids",
    "sg:classifiers":[
        {
            "category":"Retail",
            "subcategory":"Laundry & Dry Cleaning",
            "type":"Services"
        }
    ],
    "sg:phone":"+1 616 301 1289",
    "sg:postcode":"49506",
    "sg:province":"MI",
    "sg:tags":[
        "cleaners"
    ],
    "wof:name":"Sheldon Cleaners",
    "wof:placetype":"venue"
},
  "geometry": {"coordinates":[-85.60934899999999,42.929401],"type":"Point"}
}