{
  "type": "Feature",
  "properties": {
    "iso:country":"US",
    "sg:address":"2711 Rowley Rd",
    "sg:city":"Williamston",
    "sg:classifiers":[
        {
            "category":"Real Estate",
            "subcategory":"Real Estate Operator",
            "type":"Services"
        }
    ],
    "sg:phone":"+1 517 655 3736",
    "sg:postcode":"48895",
    "sg:province":"MI",
    "sg:tags":[
        "property",
        "lessor"
    ],
    "wof:name":"Clifford Poland",
    "wof:placetype":"venue"
},
  "geometry": {"coordinates":[-84.254082,42.693778],"type":"Point"}
}