{
  "type": "Feature",
  "properties": {
    "iso:country":"US",
    "sg:address":"1801 N 26th St",
    "sg:city":"Escanaba",
    "sg:classifiers":[
        {
            "category":"Wholesale",
            "subcategory":"Machinery & Supplies",
            "type":"Manufacturing & Wholesale Goods"
        }
    ],
    "sg:phone":"+1 906 786 3695",
    "sg:postcode":"49829",
    "sg:province":"MI",
    "sg:tags":[
        "equipment",
        "industrial"
    ],
    "wof:name":"Central UP Ind Supply",
    "wof:placetype":"venue"
},
  "geometry": {"coordinates":[-87.084959,45.768275],"type":"Point"}
}