{
  "type": "Feature",
  "properties": {
    "iso:country":"US",
    "sg:address":"2800 Baltane Rd",
    "sg:city":"West Bloomfield",
    "sg:classifiers":[
        {
            "category":"Manufacturing",
            "subcategory":"Printing",
            "type":"Manufacturing & Wholesale Goods"
        }
    ],
    "sg:phone":"+1 248 626 7942",
    "sg:postcode":"48323",
    "sg:province":"MI",
    "sg:tags":[
        "commercial"
    ],
    "wof:name":"Pattis Parties",
    "wof:placetype":"venue"
},
  "geometry": {"coordinates":[-83.340013,42.582107],"type":"Point"}
}