{
  "type": "Feature",
  "properties": {
    "iso:country":"US",
    "sg:address":"322 N Court Ave",
    "sg:city":"Alma",
    "sg:classifiers":[
        {
            "category":"Building & Trades",
            "subcategory":"Construction",
            "type":"Services"
        }
    ],
    "sg:phone":"+1 989 463 1880",
    "sg:postcode":"48801",
    "sg:province":"MI",
    "sg:tags":[
        "fire",
        "restoration",
        "damage"
    ],
    "sg:website":"www.clovercarpetcleaning.com",
    "wof:name":"Clover Carpet Cleaning Inc",
    "wof:placetype":"venue"
},
  "geometry": {"coordinates":[-84.65370799999999,43.378724],"type":"Point"}
}