{
  "type": "Feature",
  "properties": {
    "iso:country":"US",
    "sg:address":"26010 Crocker Blvd",
    "sg:city":"Harrison Township",
    "sg:classifiers":[
        {
            "category":"Banks & Credit Unions",
            "subcategory":"Bank",
            "type":"Services"
        }
    ],
    "sg:phone":"+1 586 783 9888",
    "sg:postcode":"48045",
    "sg:province":"MI",
    "sg:tags":[
        "depository",
        "banking"
    ],
    "wof:name":"Check n Go",
    "wof:placetype":"venue"
},
  "geometry": {"coordinates":[-82.850585,42.571224],"type":"Point"}
}