{
  "type": "Feature",
  "properties": {
    "iso:country":"US",
    "sg:address":"1986 28th St SW",
    "sg:city":"Wyoming",
    "sg:classifiers":[
        {
            "category":"Health Services",
            "subcategory":"Clinic",
            "type":"Services"
        }
    ],
    "sg:phone":"+1 616 531 9973",
    "sg:postcode":"49519",
    "sg:province":"MI",
    "sg:tags":[
        "home"
    ],
    "sg:website":"www.healthcareassociates.net",
    "wof:name":"Healthcare Associates",
    "wof:placetype":"venue"
},
  "geometry": {"coordinates":[-85.713544,42.913587],"type":"Point"}
}