{
  "type": "Feature",
  "properties": {
    "iso:country":"US",
    "sg:address":"84 W Chicago Ave",
    "sg:city":"Pontiac",
    "sg:classifiers":[
        {
            "category":"Retail",
            "subcategory":"Auto Repair",
            "type":"Services"
        }
    ],
    "sg:phone":"+1 248 332 6553",
    "sg:postcode":"48340",
    "sg:province":"MI",
    "sg:tags":[
        "glass",
        "replacement"
    ],
    "wof:name":"Carr Auto Glass",
    "wof:placetype":"venue"
},
  "geometry": {"coordinates":[-83.30700299999999,42.679607],"type":"Point"}
}