{
  "type": "Feature",
  "properties": {
    "iso:country":"US",
    "sg:address":"3508 W Sterns Rd",
    "sg:city":"Lambertville",
    "sg:classifiers":[
        {
            "category":"Banks & Credit Unions",
            "subcategory":"Investment Brokerage",
            "type":"Services"
        }
    ],
    "sg:phone":"+1 734 854 5623",
    "sg:postcode":"48144",
    "sg:province":"MI",
    "sg:tags":[
        "security"
    ],
    "wof:name":"Edward Jones 08966",
    "wof:placetype":"venue"
},
  "geometry": {"coordinates":[-83.628855,41.749108],"type":"Point"}
}