{
  "type": "Feature",
  "properties": {
    "iso:country":"US",
    "sg:address":"820 Byron Rd",
    "sg:city":"Howell",
    "sg:classifiers":[
        {
            "category":"Health Services",
            "subcategory":"Doctor",
            "type":"Services"
        }
    ],
    "sg:phone":"+1 517 546 8741",
    "sg:postcode":"48843",
    "sg:province":"MI",
    "sg:tags":[
        "osteopathic"
    ],
    "wof:name":"MD Eric Facs Stockal",
    "wof:placetype":"venue"
},
  "geometry": {"coordinates":[-83.94093599999999,42.61907],"type":"Point"}
}