{
  "type": "Feature",
  "properties": {
    "iso:country":"US",
    "sg:address":"407 W Harrie St",
    "sg:city":"Newberry",
    "sg:classifiers":[
        {
            "category":"Government",
            "subcategory":"Office",
            "type":"Public Place"
        }
    ],
    "sg:phone":"+1 906 293 5982",
    "sg:postcode":"49868",
    "sg:province":"MI",
    "sg:tags":[
        "county",
        "program",
        "adm"
    ],
    "wof:name":"Luce County Economic Dev",
    "wof:placetype":"venue"
},
  "geometry": {"coordinates":[-85.514377,46.352842],"type":"Point"}
}