{
  "type": "Feature",
  "properties": {
    "iso:country":"US",
    "sg:address":"20917 Richardson Rd",
    "sg:city":"Lake Ann",
    "sg:classifiers":[
        {
            "category":"Banks & Credit Unions",
            "subcategory":"Investment Brokerage",
            "type":"Services"
        }
    ],
    "sg:phone":"+1 231 275 8030",
    "sg:postcode":"49650",
    "sg:province":"MI",
    "sg:tags":[
        "advisory",
        "financial"
    ],
    "wof:name":"Money River USA",
    "wof:placetype":"venue"
},
  "geometry": {"coordinates":[-85.81907099999999,44.739864],"type":"Point"}
}