{
  "type": "Feature",
  "properties": {
    "iso:country":"US",
    "sg:address":"136 S Chicago St",
    "sg:city":"Litchfield",
    "sg:classifiers":[
        {
            "category":"Wholesale",
            "subcategory":"Durable Goods & Equipment",
            "type":"Manufacturing & Wholesale Goods"
        }
    ],
    "sg:phone":"+1 517 542 2224",
    "sg:postcode":"49252",
    "sg:province":"MI",
    "sg:tags":[
        "representative",
        "manufacturer"
    ],
    "wof:name":"Packer Assembly",
    "wof:placetype":"venue"
},
  "geometry": {"coordinates":[-84.75837799999999,42.039679],"type":"Point"}
}