{
  "type": "Feature",
  "properties": {
    "iso:country":"US",
    "sg:address":"3910 Corunna Rd",
    "sg:city":"Flint",
    "sg:classifiers":[
        {
            "category":"Shopping",
            "subcategory":"Used Merchandise",
            "type":"Retail Goods"
        }
    ],
    "sg:phone":"+1 810 237 7296",
    "sg:postcode":"48532",
    "sg:province":"MI",
    "sg:tags":[
        "pawnbroker"
    ],
    "wof:name":"National Pawnbrokers Outlet II",
    "wof:placetype":"venue"
},
  "geometry": {"coordinates":[-83.752405,43.002207],"type":"Point"}
}