{
  "type": "Feature",
  "properties": {
    "iso:country":"US",
    "sg:address":"351 Durkalic Rd",
    "sg:city":"Pellston",
    "sg:classifiers":[
        {
            "category":"Manufacturing",
            "subcategory":"Tools & Machinery",
            "type":"Manufacturing & Wholesale Goods"
        }
    ],
    "sg:phone":"+1 231 539 7017",
    "sg:postcode":"49769",
    "sg:province":"MI",
    "sg:tags":[
        "woodworking",
        "mfg"
    ],
    "wof:name":"Wally Wood",
    "wof:placetype":"venue"
},
  "geometry": {"coordinates":[-84.832854,45.54575],"type":"Point"}
}