{
  "type": "Feature",
  "properties": {
    "iso:country":"US",
    "sg:address":"1985 S Graham Rd",
    "sg:city":"Saginaw",
    "sg:classifiers":[
        {
            "category":"Building & Trades",
            "subcategory":"Landscaping Services",
            "type":"Services"
        }
    ],
    "sg:phone":"+1 989 781 8733",
    "sg:postcode":"48609",
    "sg:province":"MI",
    "sg:tags":[
        "tree"
    ],
    "wof:name":"Trudell's Northern Tree Care",
    "wof:placetype":"venue"
},
  "geometry": {"coordinates":[-84.131024,43.39517],"type":"Point"}
}