{
  "type": "Feature",
  "properties": {
    "iso:country":"US",
    "sg:address":"3917 Research Park Drive Suite B1",
    "sg:city":"Ann Arbor",
    "sg:classifiers":[
        {
            "category":"Professional",
            "subcategory":"Computer Services",
            "type":"Services"
        }
    ],
    "sg:phone":"+1 734 213 3715",
    "sg:postcode":"48108",
    "sg:province":"MI",
    "sg:website":"http://www.pixel-velocity.com/",
    "wof:name":"Pixel Velocity",
    "wof:placetype":"venue"
},
  "geometry": {"coordinates":[-83.73405200000001,42.235743],"type":"Point"}
}