{
  "type": "Feature",
  "properties": {
    "iso:country":"US",
    "sg:address":"3003 Stadium Dr",
    "sg:city":"Kalamazoo",
    "sg:classifiers":[
        {
            "category":"Autos & Motor Vehicles",
            "subcategory":"Automobile Sales",
            "type":"Retail Goods"
        },
        {
            "category":"Autos & Motor Vehicles",
            "subcategory":"Auto Supplies",
            "type":"Retail Goods"
        },
        {
            "category":"Retail",
            "subcategory":"Auto Repair",
            "type":"Services"
        }
    ],
    "sg:phone":"+1 269 342 9800",
    "sg:postcode":"49008",
    "sg:province":"MI",
    "sg:tags":[
        "used",
        "leasing",
        "car",
        "part",
        "truck",
        "new"
    ],
    "sg:website":"http://national.citysearch.com/profile/external/601564904/kalamazoo_mi/cole_nissan.html?publisher=yellowpages&reference_id=1&placement=ypwebsitemip",
    "wof:name":"Cole Nissan",
    "wof:placetype":"venue"
},
  "geometry": {"coordinates":[-85.627257,42.272074],"type":"Point"}
}