{
  "type": "Feature",
  "properties": {
    "iso:country":"US",
    "sg:address":"13046 Center Rd",
    "sg:city":"Traverse City",
    "sg:classifiers":[
        {
            "category":"Farming",
            "subcategory":"Farm",
            "type":"Manufacturing & Wholesale Goods"
        }
    ],
    "sg:phone":"+1 231 223 4387",
    "sg:postcode":"49686",
    "sg:province":"MI",
    "wof:name":"Cold Water Farm",
    "wof:placetype":"venue"
},
  "geometry": {"coordinates":[-85.51525100000001,44.880325],"type":"Point"}
}