{
  "type": "Feature",
  "properties": {
    "iso:country":"US",
    "sg:address":"430 W Clay Ave",
    "sg:city":"Muskegon",
    "sg:classifiers":[
        {
            "category":"Shopping",
            "subcategory":"Gifts & Souvenirs",
            "type":"Retail Goods"
        }
    ],
    "sg:phone":"+1 231 726 6908",
    "sg:postcode":"49440",
    "sg:province":"MI",
    "sg:tags":[
        "shop"
    ],
    "wof:name":"Muskegon Mercantile",
    "wof:placetype":"venue"
},
  "geometry": {"coordinates":[-86.254773,43.233201],"type":"Point"}
}