{
  "type": "Feature",
  "properties": {
    "iso:country":"US",
    "sg:address":"2211 Cole St",
    "sg:city":"Birmingham",
    "sg:classifiers":[
        {
            "category":"Home & Garden",
            "subcategory":"Carpets & Floor Coverings",
            "type":"Retail Goods"
        }
    ],
    "sg:phone":"+1 248 644 4483",
    "sg:postcode":"48009",
    "sg:province":"MI",
    "sg:tags":[
        "material"
    ],
    "wof:name":"Edward Jones Floor Coverings",
    "wof:placetype":"venue"
},
  "geometry": {"coordinates":[-83.19378500000001,42.540252],"type":"Point"}
}