{
  "type": "Feature",
  "properties": {
    "iso:country":"US",
    "sg:address":"148 W Washington St",
    "sg:city":"Marquette",
    "sg:classifiers":[
        {
            "category":"Professional",
            "subcategory":"Lawyer & Legal Services",
            "type":"Services"
        }
    ],
    "sg:phone":"+1 906 226 6700",
    "sg:postcode":"49855",
    "sg:province":"MI",
    "wof:name":"William R Rekshan",
    "wof:placetype":"venue"
},
  "geometry": {"coordinates":[-87.394491,46.543475],"type":"Point"}
}