{
  "type": "Feature",
  "properties": {
    "iso:country":"US",
    "sg:address":"2929 Covington Ct",
    "sg:city":"Lansing",
    "sg:classifiers":[
        {
            "category":"Building & Trades",
            "subcategory":"Cleaning & Sanitation",
            "type":"Services"
        }
    ],
    "sg:phone":"+1 517 316 7868",
    "sg:postcode":"48912",
    "sg:province":"MI",
    "sg:tags":[
        "butler",
        "maid"
    ],
    "wof:name":"Quality Maid",
    "wof:placetype":"venue"
},
  "geometry": {"coordinates":[-84.50991500000001,42.744485],"type":"Point"}
}