{
  "type": "Feature",
  "properties": {
    "iso:country":"US",
    "sg:address":"4830 Division Ave S",
    "sg:city":"Grand Rapids",
    "sg:classifiers":[
        {
            "category":"Wholesale",
            "subcategory":"Machinery & Supplies",
            "type":"Manufacturing & Wholesale Goods"
        }
    ],
    "sg:phone":"+1 616 530 7479",
    "sg:postcode":"49548",
    "sg:province":"MI",
    "sg:tags":[
        "die",
        "tool",
        "maker"
    ],
    "wof:name":"Jr's Outlet",
    "wof:placetype":"venue"
},
  "geometry": {"coordinates":[-85.664344,42.875594],"type":"Point"}
}