{
  "type": "Feature",
  "properties": {
    "iso:country":"US",
    "sg:address":"1965 Hardwick Dr",
    "sg:city":"Lapeer",
    "sg:classifiers":[
        {
            "category":"Professional",
            "subcategory":"Business Services",
            "type":"Services"
        }
    ],
    "sg:phone":"+1 810 667 3784",
    "sg:postcode":"48446",
    "sg:province":"MI",
    "sg:tags":[
        "water",
        "treatment"
    ],
    "wof:name":"Velvet Soft Water",
    "wof:placetype":"venue"
},
  "geometry": {"coordinates":[-83.432503,42.999345],"type":"Point"}
}