{
  "type": "Feature",
  "properties": {
    "iso:country":"US",
    "sg:address":"13136 New Holland St",
    "sg:city":"Holland",
    "sg:classifiers":[
        {
            "category":"Building & Trades",
            "subcategory":"Construction",
            "type":"Services"
        }
    ],
    "sg:phone":"+1 616 218 3934",
    "sg:postcode":"49424",
    "sg:province":"MI",
    "sg:tags":[
        "general",
        "contractor"
    ],
    "wof:name":"Gregory L Ward Builder",
    "wof:placetype":"venue"
},
  "geometry": {"coordinates":[-86.106774,42.856094],"type":"Point"}
}