{
  "type": "Feature",
  "properties": {
    "iso:country":"US",
    "sg:address":"953 Garfield Ave NW",
    "sg:city":"Grand Rapids",
    "sg:classifiers":[
        {
            "category":"Building & Trades",
            "subcategory":"Construction",
            "type":"Services"
        }
    ],
    "sg:phone":"+1 616 456 6184",
    "sg:postcode":"49504",
    "sg:province":"MI",
    "sg:tags":[
        "house"
    ],
    "wof:name":"Simon Simple Construction",
    "wof:placetype":"venue"
},
  "geometry": {"coordinates":[-85.698536,42.980582],"type":"Point"}
}