{
  "type": "Feature",
  "properties": {
    "iso:country":"US",
    "sg:address":"3805 Fenton Rd",
    "sg:city":"Flint",
    "sg:classifiers":[
        {
            "category":"Personal",
            "subcategory":"Nail Salon",
            "type":"Services"
        }
    ],
    "sg:phone":"+1 810 235 6612",
    "sg:postcode":"48507",
    "sg:province":"MI",
    "wof:name":"First Impressions by Joy",
    "wof:placetype":"venue"
},
  "geometry": {"coordinates":[-83.692902,42.988602],"type":"Point"}
}