{
  "type": "Feature",
  "properties": {
    "iso:country":"US",
    "sg:address":"9322 Marine City Hwy",
    "sg:city":"Casco",
    "sg:classifiers":[
        {
            "category":"Wholesale",
            "subcategory":"Auto Parts",
            "type":"Manufacturing & Wholesale Goods"
        }
    ],
    "sg:phone":"+1 586 716 0162",
    "sg:postcode":"48064",
    "sg:province":"MI",
    "sg:tags":[
        "truck",
        "accessory"
    ],
    "wof:name":"LLC Greystone",
    "wof:placetype":"venue"
},
  "geometry": {"coordinates":[-82.681585,42.722692],"type":"Point"}
}