{
  "type": "Feature",
  "properties": {
    "iso:country":"US",
    "sg:address":"1600 N Shore Dr",
    "sg:city":"Crystal",
    "sg:phone":"+1 989 235 6302",
    "sg:postcode":"48818",
    "sg:province":"MI",
    "sg:tags":[
        "beef",
        "farm",
        "corn",
        "soybean",
        "cattle",
        "feedlot"
    ],
    "wof:name":"Charles Braman",
    "wof:placetype":"venue"
},
  "geometry": {"coordinates":[-84.94578199999999,43.264699],"type":"Point"}
}