{
  "type": "Feature",
  "properties": {
    "iso:country":"US",
    "sg:address":"1950 S Industrial Hwy",
    "sg:city":"Ann Arbor",
    "sg:classifiers":[
        {
            "category":"Sports & Exercise",
            "subcategory":"Bowling",
            "type":"Entertainment"
        }
    ],
    "sg:phone":"+1 734 665 4474",
    "sg:postcode":"48104",
    "sg:province":"MI",
    "sg:tags":[
        "center"
    ],
    "wof:name":"Colonial Lanes Bowling Center",
    "wof:placetype":"venue"
},
  "geometry": {"coordinates":[-83.735708,42.256117],"type":"Point"}
}