{
  "type": "Feature",
  "properties": {
    "iso:country":"US",
    "sg:address":"230 Watts St",
    "sg:city":"Battle Creek",
    "sg:classifiers":[
        {
            "category":"Professional",
            "subcategory":"Accounting & Tax Preparation",
            "type":"Services"
        }
    ],
    "sg:phone":"+1 269 965 2738",
    "sg:postcode":"49014",
    "sg:province":"MI",
    "sg:tags":[
        "return",
        "filing"
    ],
    "wof:name":"Michielsen Bookkeeping Tax Svc",
    "wof:placetype":"venue"
},
  "geometry": {"coordinates":[-85.132007,42.307979],"type":"Point"}
}