{
  "type": "Feature",
  "properties": {
    "iso:country":"US",
    "sg:address":"455 Marshall St",
    "sg:city":"Brooklyn",
    "sg:classifiers":[
        {
            "category":"Banks & Credit Unions",
            "subcategory":"Investment Brokerage",
            "type":"Services"
        }
    ],
    "sg:phone":"+1 517 592 5452",
    "sg:postcode":"49230",
    "sg:province":"MI",
    "sg:tags":[
        "security"
    ],
    "wof:name":"Edward Jones 28134",
    "wof:placetype":"venue"
},
  "geometry": {"coordinates":[-84.2568,42.10786],"type":"Point"}
}