{
  "type": "Feature",
  "properties": {
    "iso:country":"US",
    "sg:address":"4253 Howard City Edmore Rd",
    "sg:city":"Edmore",
    "sg:classifiers":[
        {
            "category":"Retail",
            "subcategory":"Repair Shop",
            "type":"Services"
        }
    ],
    "sg:phone":"+1 989 427 5069",
    "sg:postcode":"48829",
    "sg:province":"MI",
    "wof:name":"A C P Repair Services",
    "wof:placetype":"venue"
},
  "geometry": {"coordinates":[-84.990646,43.408073],"type":"Point"}
}