{
  "type": "Feature",
  "properties": {
    "iso:country":"US",
    "sg:address":"6146 Klam Rd",
    "sg:city":"Otter Lake",
    "sg:classifiers":[
        {
            "category":"Personal",
            "subcategory":"Beauty Salon",
            "type":"Services"
        }
    ],
    "sg:phone":"+1 810 793 1640",
    "sg:postcode":"48464",
    "sg:province":"MI",
    "wof:name":"Holloway Hair",
    "wof:placetype":"venue"
},
  "geometry": {"coordinates":[-83.390613,43.209988],"type":"Point"}
}