{
  "type": "Feature",
  "properties": {
    "iso:country":"US",
    "sg:address":"1130 Tienken Ct",
    "sg:city":"Rochester Hills",
    "sg:classifiers":[
        {
            "category":"Organizations",
            "subcategory":"Religious Organization",
            "type":"Services"
        }
    ],
    "sg:phone":"+1 248 651 8114",
    "sg:postcode":"48306",
    "sg:province":"MI",
    "sg:tags":[
        "church"
    ],
    "wof:name":"Just Give Me Jesus Greator",
    "wof:placetype":"venue"
},
  "geometry": {"coordinates":[-83.138443,42.69669],"type":"Point"}
}