{
  "type": "Feature",
  "properties": {
    "iso:country":"US",
    "sg:address":"1537 N Leroy St",
    "sg:city":"Fenton",
    "sg:classifiers":[
        {
            "category":"Shopping",
            "subcategory":"Clothing, Apparel, & Fashions",
            "type":"Retail Goods"
        }
    ],
    "sg:phone":"+1 810 750 2033",
    "sg:postcode":"48430",
    "sg:province":"MI",
    "sg:tags":[
        "shop",
        "bridal"
    ],
    "wof:name":"Brides & More",
    "wof:placetype":"venue"
},
  "geometry": {"coordinates":[-83.707639,42.818396],"type":"Point"}
}