{
  "type": "Feature",
  "properties": {
    "iso:country":"US",
    "sg:address":"1610 Atlantic St",
    "sg:city":"Hancock",
    "sg:classifiers":[
        {
            "category":"Freight",
            "type":"Transportation"
        }
    ],
    "sg:phone":"+1 906 482 7487",
    "sg:postcode":"49930",
    "sg:province":"MI",
    "sg:tags":[
        "operator",
        "local",
        "trucking"
    ],
    "wof:name":"Bernard Trucking Inc",
    "wof:placetype":"venue"
},
  "geometry": {"coordinates":[-88.61327199999999,47.129251],"type":"Point"}
}