{
  "type": "Feature",
  "properties": {
    "iso:country":"US",
    "sg:address":"22600 Hall Rd Ste 201",
    "sg:city":"Clinton Township",
    "sg:classifiers":[
        {
            "category":"Professional",
            "subcategory":"Employment Agencies",
            "type":"Services"
        }
    ],
    "sg:phone":"+1 586 465 4600",
    "sg:postcode":"48036",
    "sg:province":"MI",
    "sg:website":"www.addstaff.com",
    "wof:name":"Add Staff",
    "wof:placetype":"venue"
},
  "geometry": {"coordinates":[-82.8853,42.628601],"type":"Point"}
}