{
  "type": "Feature",
  "properties": {
    "iso:country":"US",
    "sg:address":"1151 Taylor St Rm 236C",
    "sg:city":"Detroit",
    "sg:classifiers":[
        {
            "category":"Government",
            "subcategory":"Fire Station",
            "type":"Public Place"
        },
        {
            "category":"Government",
            "subcategory":"Office",
            "type":"Public Place"
        }
    ],
    "sg:phone":"+1 313 876 4513",
    "sg:postcode":"48202",
    "sg:province":"MI",
    "sg:tags":[
        "department",
        "township",
        "protection",
        "government-city",
        "village"
    ],
    "sg:website":"http://www.cobocenter.com",
    "wof:name":"City Of Detroit",
    "wof:placetype":"venue"
},
  "geometry": {"coordinates":[-83.090643,42.378597],"type":"Point"}
}