{
  "type": "Feature",
  "properties": {
    "iso:country":"US",
    "sg:address":"4981 Eastman Ave",
    "sg:city":"Midland",
    "sg:classifiers":[
        {
            "category":"Restaurant",
            "type":"Food & Drink"
        }
    ],
    "sg:phone":"+1 989 839 2164",
    "sg:postcode":"48640",
    "sg:province":"MI",
    "sg:tags":[
        "eating"
    ],
    "wof:name":"Korean House Inc",
    "wof:placetype":"venue"
},
  "geometry": {"coordinates":[-84.24688999999999,43.643409],"type":"Point"}
}