{
  "type": "Feature",
  "properties": {
    "iso:country":"US",
    "sg:address":"2921 S Luce Ave",
    "sg:city":"Fremont",
    "sg:phone":"+1 231 924 2599",
    "sg:postcode":"49412",
    "sg:province":"MI",
    "sg:tags":[
        "wheat",
        "farm",
        "corn",
        "crop",
        "field",
        "soybean"
    ],
    "wof:name":"Carl Pearson",
    "wof:placetype":"venue"
},
  "geometry": {"coordinates":[-85.920225,43.501541],"type":"Point"}
}