{
  "type": "Feature",
  "properties": {
    "iso:country":"US",
    "sg:address":"27925 Elba St",
    "sg:city":"St Clair Shores",
    "sg:classifiers":[
        {
            "category":"Wholesale",
            "subcategory":"Construction Materials",
            "type":"Manufacturing & Wholesale Goods"
        }
    ],
    "sg:phone":"+1 586 774 2045",
    "sg:postcode":"48081",
    "sg:province":"MI",
    "sg:tags":[
        "fence"
    ],
    "wof:name":"Tom's Fence Co",
    "wof:placetype":"venue"
},
  "geometry": {"coordinates":[-82.88865699999999,42.497556],"type":"Point"}
}