{
  "type": "Feature",
  "properties": {
    "iso:country":"US",
    "sg:address":"4564 W Walton Blvd",
    "sg:city":"Waterford",
    "sg:classifiers":[
        {
            "category":"Banks & Credit Unions",
            "subcategory":"Bank",
            "type":"Services"
        }
    ],
    "sg:phone":"+1 248 673 7216",
    "sg:postcode":"48329",
    "sg:province":"MI",
    "sg:tags":[
        "loan",
        "real estate"
    ],
    "wof:name":"Sure Financial",
    "wof:placetype":"venue"
},
  "geometry": {"coordinates":[-83.37904399999999,42.689848],"type":"Point"}
}