{
  "type": "Feature",
  "properties": {
    "iso:country":"US",
    "sg:address":"19194 Theresa Blvd",
    "sg:city":"Rockwood",
    "sg:classifiers":[
        {
            "category":"Building & Trades",
            "subcategory":"Plumbing",
            "type":"Services"
        }
    ],
    "sg:phone":"+1 734 379 0122",
    "sg:postcode":"48173",
    "sg:province":"MI",
    "sg:tags":[
        "contractor"
    ],
    "wof:name":"Aquatech Irrigation",
    "wof:placetype":"venue"
},
  "geometry": {"coordinates":[-83.222769,42.074111],"type":"Point"}
}