{
  "type": "Feature",
  "properties": {
    "iso:country":"US",
    "sg:address":"24650 Armada Center Rd",
    "sg:city":"Armada",
    "sg:classifiers":[
        {
            "category":"Insurance",
            "subcategory":"Insurance Agent",
            "type":"Services"
        }
    ],
    "sg:phone":"+1 586 784 8147",
    "sg:postcode":"48005",
    "sg:province":"MI",
    "wof:name":"Mutual Of Omaha Insurance Co",
    "wof:placetype":"venue"
},
  "geometry": {"coordinates":[-82.869703,42.850554],"type":"Point"}
}