{
  "type": "Feature",
  "properties": {
    "iso:country":"US",
    "sg:address":"3434 State Hwy 119",
    "sg:city":"Harbor Springs",
    "sg:classifiers":[
        {
            "category":"Government",
            "subcategory":"Office",
            "type":"Public Place"
        }
    ],
    "sg:phone":"+1 231 348 1780",
    "sg:postcode":"49740",
    "sg:province":"MI",
    "sg:tags":[
        "county",
        "affairs",
        "admin"
    ],
    "wof:name":"Emmet County Veterans Affairs",
    "wof:placetype":"venue"
},
  "geometry": {"coordinates":[-85.090469,45.598454],"type":"Point"}
}