{
  "type": "Feature",
  "properties": {
    "iso:country":"US",
    "sg:address":"8326 Shaver Rd",
    "sg:city":"Portage",
    "sg:classifiers":[
        {
            "category":"Home & Garden",
            "subcategory":"Building Materials",
            "type":"Retail Goods"
        }
    ],
    "sg:phone":"+1 269 492 1120",
    "sg:postcode":"49024",
    "sg:province":"MI",
    "sg:tags":[
        "glass",
        "window",
        "plate"
    ],
    "wof:name":"Leaders Autoglass",
    "wof:placetype":"venue"
},
  "geometry": {"coordinates":[-85.59733,42.193886],"type":"Point"}
}