{
  "type": "Feature",
  "properties": {
    "iso:country":"US",
    "sg:address":"4901 Pointe Dr",
    "sg:city":"East China",
    "sg:classifiers":[
        {
            "category":"Building & Trades",
            "subcategory":"Cleaning & Sanitation",
            "type":"Services"
        }
    ],
    "sg:phone":"+1 810 329 3507",
    "sg:postcode":"48054",
    "sg:province":"MI",
    "sg:tags":[
        "janitor"
    ],
    "wof:name":"Independent Buildings Maint",
    "wof:placetype":"venue"
},
  "geometry": {"coordinates":[-82.476006,42.760099],"type":"Point"}
}