{
  "type": "Feature",
  "properties": {
    "iso:country":"US",
    "sg:address":"22522 Clairwood St",
    "sg:city":"St Clair Shores",
    "sg:classifiers":[
        {
            "category":"Building & Trades",
            "subcategory":"Construction",
            "type":"Services"
        }
    ],
    "sg:phone":"+1 586 775 2111",
    "sg:postcode":"48080",
    "sg:province":"MI",
    "sg:tags":[
        "home",
        "improvement"
    ],
    "wof:name":"Cardinal Construction",
    "wof:placetype":"venue"
},
  "geometry": {"coordinates":[-82.891428,42.463701],"type":"Point"}
}