{
  "type": "Feature",
  "properties": {
    "iso:country":"US",
    "sg:address":"2412 State Hwy 139",
    "sg:city":"Benton Harbor",
    "sg:classifiers":[
        {
            "category":"Local Transit",
            "type":"Transportation"
        }
    ],
    "sg:phone":"+1 269 925 1121",
    "sg:postcode":"49022",
    "sg:province":"MI",
    "sg:tags":[
        "bus",
        "line"
    ],
    "wof:name":"Greyhound Bus Lines",
    "wof:placetype":"venue"
},
  "geometry": {"coordinates":[-86.436617,42.075637],"type":"Point"}
}