{
  "type": "Feature",
  "properties": {
    "iso:country":"US",
    "sg:address":"8199 Ormes Rd",
    "sg:city":"Vassar",
    "sg:classifiers":[
        {
            "category":"Building & Trades",
            "subcategory":"Construction",
            "type":"Services"
        }
    ],
    "sg:phone":"+1 989 871 3454",
    "sg:postcode":"48768",
    "sg:province":"MI",
    "sg:tags":[
        "contractor"
    ],
    "wof:name":"Poulos Contracting",
    "wof:placetype":"venue"
},
  "geometry": {"coordinates":[-83.62876799999999,43.321552],"type":"Point"}
}