{
  "type": "Feature",
  "properties": {
    "iso:country":"US",
    "sg:address":"55 Jennings Rd",
    "sg:city":"Whitmore Lake",
    "sg:classifiers":[
        {
            "category":"Health Services",
            "subcategory":"Doctor",
            "type":"Services"
        }
    ],
    "sg:phone":"+1 734 449 4451",
    "sg:postcode":"48189",
    "sg:province":"MI",
    "wof:name":"Vanderluis Robert W DDS",
    "wof:placetype":"venue"
},
  "geometry": {"coordinates":[-83.76854299999999,42.421495],"type":"Point"}
}