{
  "type": "Feature",
  "properties": {
    "iso:country":"US",
    "sg:address":"3501 Lake Eastbrook Blvd SE",
    "sg:city":"Grand Rapids",
    "sg:classifiers":[
        {
            "category":"Professional",
            "subcategory":"Management & Consulting",
            "type":"Services"
        }
    ],
    "sg:phone":"+1 616 940 1344",
    "sg:postcode":"49546",
    "sg:province":"MI",
    "sg:tags":[
        "consultant",
        "medical"
    ],
    "wof:name":"Genex Services Inc",
    "wof:placetype":"venue"
},
  "geometry": {"coordinates":[-85.58004,42.917736],"type":"Point"}
}