{
  "type": "Feature",
  "properties": {
    "iso:country":"US",
    "sg:address":"646 Maple Hill Dr",
    "sg:city":"Kalamazoo",
    "sg:classifiers":[
        {
            "category":"Banks & Credit Unions",
            "subcategory":"Bank",
            "type":"Services"
        }
    ],
    "sg:phone":"+1 269 488 7100",
    "sg:postcode":"49009",
    "sg:province":"MI",
    "sg:tags":[
        "loan",
        "real estate"
    ],
    "wof:name":"Apollo Home Mortgage",
    "wof:placetype":"venue"
},
  "geometry": {"coordinates":[-85.65780100000001,42.296307],"type":"Point"}
}