{
  "type": "Feature",
  "properties": {
    "iso:country":"US",
    "sg:address":"6020 Peachtree St",
    "sg:city":"Portage",
    "sg:classifiers":[
        {
            "category":"Organizations",
            "subcategory":"Political Organization",
            "type":"Services"
        }
    ],
    "sg:phone":"+1 269 327 4585",
    "sg:postcode":"49024",
    "sg:province":"MI",
    "wof:name":"National Society of Daugh",
    "wof:placetype":"venue"
},
  "geometry": {"coordinates":[-85.598742,42.229661],"type":"Point"}
}