{
  "type": "Feature",
  "properties": {
    "iso:country":"US",
    "sg:address":"24567 Northwestern Hwy",
    "sg:city":"Southfield",
    "sg:classifiers":[
        {
            "category":"Banks & Credit Unions",
            "subcategory":"Investment Brokerage",
            "type":"Services"
        }
    ],
    "sg:phone":"+1 248 355 4443",
    "sg:postcode":"48075",
    "sg:province":"MI",
    "sg:tags":[
        "stock",
        "bond"
    ],
    "wof:name":"Champion Group",
    "wof:placetype":"venue"
},
  "geometry": {"coordinates":[-83.238631,42.469767],"type":"Point"}
}