{
  "type": "Feature",
  "properties": {
    "iso:country":"US",
    "sg:address":"3054 Windcrest Way NE",
    "sg:city":"Grand Rapids",
    "sg:classifiers":[
        {
            "category":"Professional",
            "subcategory":"Business Services",
            "type":"Services"
        }
    ],
    "sg:phone":"+1 616 957 1697",
    "sg:postcode":"49525",
    "sg:province":"MI",
    "sg:tags":[
        "notary",
        "public"
    ],
    "wof:name":"Intrinsic Technology",
    "wof:placetype":"venue"
},
  "geometry": {"coordinates":[-85.59455,42.988246],"type":"Point"}
}