{
  "type": "Feature",
  "properties": {
    "iso:country":"US",
    "sg:address":"5206 Bay Rd",
    "sg:city":"Saginaw",
    "sg:classifiers":[
        {
            "category":"Shopping",
            "subcategory":"Department Store",
            "type":"Retail Goods"
        }
    ],
    "sg:phone":"+1 989 790 9115",
    "sg:postcode":"48604",
    "sg:province":"MI",
    "sg:tags":[
        "shop"
    ],
    "wof:name":"Dollar Tree",
    "wof:placetype":"venue"
},
  "geometry": {"coordinates":[-83.97469700000001,43.484891],"type":"Point"}
}