{
  "type": "Feature",
  "properties": {
    "iso:country":"US",
    "sg:address":"1925 W Maple Rd",
    "sg:city":"Troy",
    "sg:classifiers":[
        {
            "category":"Wholesale",
            "subcategory":"Non-durable Goods",
            "type":"Manufacturing & Wholesale Goods"
        }
    ],
    "sg:phone":"+1 248 284 0002",
    "sg:postcode":"48084",
    "sg:province":"MI",
    "sg:tags":[
        "rubber",
        "sponge"
    ],
    "wof:name":"Foam N' More Upholstery Inc",
    "wof:placetype":"venue"
},
  "geometry": {"coordinates":[-83.174837,42.547705],"type":"Point"}
}