{
  "type": "Feature",
  "properties": {
    "iso:country":"US",
    "sg:address":"4363 Budziak Rd",
    "sg:city":"Oscoda",
    "sg:classifiers":[
        {
            "category":"Real Estate",
            "subcategory":"Real Estate Operator",
            "type":"Services"
        }
    ],
    "sg:phone":"+1 989 739 7451",
    "sg:postcode":"48730",
    "sg:province":"MI",
    "sg:tags":[
        "apartment"
    ],
    "wof:name":"Lanhurst Apartments",
    "wof:placetype":"venue"
},
  "geometry": {"coordinates":[-83.34722499999999,44.450381],"type":"Point"}
}