{
  "type": "Feature",
  "properties": {
    "iso:country":"US",
    "sg:address":"4204 Ann Arbor Rd",
    "sg:city":"Jackson",
    "sg:classifiers":[
        {
            "category":"Bars & Pubs",
            "type":"Food & Drink"
        }
    ],
    "sg:phone":"+1 517 764 3480",
    "sg:postcode":"49202",
    "sg:province":"MI",
    "wof:name":"Ludwig's",
    "wof:placetype":"venue"
},
  "geometry": {"coordinates":[-84.33945199999999,42.262532],"type":"Point"}
}