{
  "type": "Feature",
  "properties": {
    "iso:country":"US",
    "sg:address":"4100 Capitol City Blvd",
    "sg:city":"Lansing",
    "sg:classifiers":[
        {
            "category":"Professional",
            "subcategory":"Engineering",
            "type":"Services"
        }
    ],
    "sg:phone":"+1 517 327 1980",
    "sg:postcode":"48906",
    "sg:province":"MI",
    "sg:tags":[
        "architectural",
        "engineer"
    ],
    "wof:name":"R W Armstrong & Associates",
    "wof:placetype":"venue"
},
  "geometry": {"coordinates":[-84.588982,42.774635],"type":"Point"}
}