{
  "type": "Feature",
  "properties": {
    "iso:country":"US",
    "sg:address":"1224 Boston Ave",
    "sg:city":"Flint",
    "sg:classifiers":[
        {
            "category":"Building & Trades",
            "subcategory":"Construction",
            "type":"Services"
        }
    ],
    "sg:phone":"+1 810 238 1131",
    "sg:postcode":"48503",
    "sg:province":"MI",
    "sg:tags":[
        "concrete",
        "contractor"
    ],
    "wof:name":"Precision Footings & Poured",
    "wof:placetype":"venue"
},
  "geometry": {"coordinates":[-83.710649,43.002768],"type":"Point"}
}