{
  "type": "Feature",
  "properties": {
    "iso:country":"US",
    "sg:address":"18450 Maryland Dr",
    "sg:city":"Southfield",
    "sg:classifiers":[
        {
            "category":"Banks & Credit Unions",
            "subcategory":"Financial Services",
            "type":"Services"
        }
    ],
    "sg:phone":"+1 248 552 0407",
    "sg:postcode":"48075",
    "sg:province":"MI",
    "sg:tags":[
        "investor"
    ],
    "wof:name":"Craft Interprises of Michigan",
    "wof:placetype":"venue"
},
  "geometry": {"coordinates":[-83.224464,42.467649],"type":"Point"}
}