{
  "type": "Feature",
  "properties": {
    "iso:country":"US",
    "sg:address":"43985 Hayes Rd",
    "sg:city":"Sterling Heights",
    "sg:classifiers":[
        {
            "category":"Restaurant",
            "type":"Food & Drink"
        },
        {
            "category":"Retail",
            "subcategory":"Event Space",
            "type":"Services"
        }
    ],
    "sg:phone":"+1 586 566 9900",
    "sg:postcode":"48313",
    "sg:province":"MI",
    "sg:tags":[
        "venue"
    ],
    "sg:website":"www.pennasbanquets.com",
    "wof:name":"Villa Penna's Ristorante",
    "wof:placetype":"venue"
},
  "geometry": {"coordinates":[-82.973099,42.619301],"type":"Point"}
}