{
  "type": "Feature",
  "properties": {
    "iso:country":"US",
    "sg:address":"2334 Tamrack St",
    "sg:city":"Kalamazoo",
    "sg:classifiers":[
        {
            "category":"Professional",
            "subcategory":"Management & Consulting",
            "type":"Services"
        }
    ],
    "sg:phone":"+1 269 345 9118",
    "sg:postcode":"49006",
    "sg:province":"MI",
    "sg:tags":[
        "business"
    ],
    "wof:name":"People Builders",
    "wof:placetype":"venue"
},
  "geometry": {"coordinates":[-85.6367,42.315544],"type":"Point"}
}