{
  "type": "Feature",
  "properties": {
    "iso:country":"US",
    "sg:address":"555 W Wackerly St",
    "sg:city":"Midland",
    "sg:classifiers":[
        {
            "category":"Health Services",
            "subcategory":"Doctor",
            "type":"Services"
        }
    ],
    "sg:phone":"+1 989 839 8806",
    "sg:postcode":"48640",
    "sg:province":"MI",
    "sg:tags":[
        "medical"
    ],
    "wof:name":"Jerry L Ferrell",
    "wof:placetype":"venue"
},
  "geometry": {"coordinates":[-84.23285199999999,43.654748],"type":"Point"}
}