{
  "type": "Feature",
  "properties": {
    "iso:country":"US",
    "sg:address":"801 W Ganson St",
    "sg:city":"Jackson",
    "sg:classifiers":[
        {
            "category":"Restaurant",
            "type":"Food & Drink"
        }
    ],
    "sg:menulink":"http://www.allmenus.com/mi/jackson/208734-taco-bell/menu/",
    "sg:phone":"+1 517 788 9888",
    "sg:postcode":"49202",
    "sg:province":"MI",
    "sg:tags":[
        "mexican"
    ],
    "wof:name":"Taco Bell",
    "wof:placetype":"venue"
},
  "geometry": {"coordinates":[-84.423429,42.254733],"type":"Point"}
}