{
  "type": "Feature",
  "properties": {
    "iso:country":"US",
    "sg:address":"8325 N Lilley Rd",
    "sg:city":"Canton",
    "sg:classifiers":[
        {
            "category":"Building & Trades",
            "subcategory":"Landscaping Services",
            "type":"Services"
        },
        {
            "category":"Building & Trades",
            "subcategory":"Construction",
            "type":"Services"
        }
    ],
    "sg:phone":"+1 734 416 7080",
    "sg:postcode":"48187",
    "sg:province":"MI",
    "sg:tags":[
        "mason",
        "landscape",
        "contractor"
    ],
    "sg:website":"http://www.metrostarbrickpavers.com",
    "wof:name":"Metro Star Brick Pavers",
    "wof:placetype":"venue"
},
  "geometry": {"coordinates":[-83.45997199999999,42.348668],"type":"Point"}
}