{
  "type": "Feature",
  "properties": {
    "iso:country":"US",
    "sg:address":"590 Tennyson",
    "sg:city":"Rochester",
    "sg:classifiers":[
        {
            "category":"Building & Trades",
            "subcategory":"Electrical",
            "type":"Services"
        }
    ],
    "sg:phone":"+1 248 852 6527",
    "sg:postcode":"48307",
    "sg:province":"MI",
    "sg:tags":[
        "security",
        "installation",
        "telephone"
    ],
    "wof:name":"Assured Protection Bureau Inc",
    "wof:placetype":"venue"
},
  "geometry": {"coordinates":[-83.120746,42.649844],"type":"Point"}
}