{
  "type": "Feature",
  "properties": {
    "iso:country":"US",
    "sg:address":"42 Waldron St",
    "sg:city":"Hillsdale",
    "sg:classifiers":[
        {
            "category":"Retail",
            "subcategory":"Auto Repair",
            "type":"Services"
        }
    ],
    "sg:phone":"+1 517 437 3821",
    "sg:postcode":"49242",
    "sg:province":"MI",
    "sg:tags":[
        "general"
    ],
    "wof:name":"Laymans Service Center Inc",
    "wof:placetype":"venue"
},
  "geometry": {"coordinates":[-84.632706,41.918815],"type":"Point"}
}