{
  "type": "Feature",
  "properties": {
    "iso:country":"US",
    "sg:address":"8144 Grand River Rd",
    "sg:city":"Brighton",
    "sg:classifiers":[
        {
            "category":"Shopping",
            "subcategory":"Gifts & Souvenirs",
            "type":"Retail Goods"
        }
    ],
    "sg:phone":"+1 810 220 0110",
    "sg:postcode":"48114",
    "sg:province":"MI",
    "sg:tags":[
        "party",
        "supply"
    ],
    "wof:name":"Gordon Food Svc Marketplace",
    "wof:placetype":"venue"
},
  "geometry": {"coordinates":[-83.79142899999999,42.554209],"type":"Point"}
}