{
  "type": "Feature",
  "properties": {
    "iso:country":"US",
    "sg:address":"4641 21st Rd",
    "sg:city":"Cornell",
    "sg:classifiers":[
        {
            "category":"Farming",
            "subcategory":"Farm",
            "type":"Manufacturing & Wholesale Goods"
        }
    ],
    "sg:phone":"+1 906 786 6985",
    "sg:postcode":"49837",
    "sg:province":"MI",
    "sg:tags":[
        "crop",
        "general"
    ],
    "wof:name":"Rappette John",
    "wof:placetype":"venue"
},
  "geometry": {"coordinates":[-87.134552,45.840822],"type":"Point"}
}