{
  "type": "Feature",
  "properties": {
    "iso:country":"US",
    "sg:address":"325 Clyde Rd",
    "sg:city":"Highland",
    "sg:classifiers":[
        {
            "category":"Organizations",
            "subcategory":"Membership Organization",
            "type":"Services"
        }
    ],
    "sg:phone":"+1 248 889 4520",
    "sg:postcode":"48357",
    "sg:province":"MI",
    "wof:name":"American Wildlife Relocation",
    "wof:placetype":"venue"
},
  "geometry": {"coordinates":[-83.626138,42.681337],"type":"Point"}
}