{
  "type": "Feature",
  "properties": {
    "iso:country":"US",
    "sg:address":"10424 Patterson Ave SE",
    "sg:city":"Caledonia",
    "sg:classifiers":[
        {
            "category":"Home & Garden",
            "subcategory":"Mobile Homes",
            "type":"Retail Goods"
        }
    ],
    "sg:phone":"+1 616 891 2174",
    "sg:postcode":"49316",
    "sg:province":"MI",
    "wof:name":"Km Distributing",
    "wof:placetype":"venue"
},
  "geometry": {"coordinates":[-85.545495,42.775838],"type":"Point"}
}