{
  "type": "Feature",
  "properties": {
    "iso:country":"US",
    "sg:address":"21319 Carlo Dr",
    "sg:city":"Clinton Twp",
    "sg:classifiers":[
        {
            "category":"Professional",
            "subcategory":"Business Services",
            "type":"Services"
        }
    ],
    "sg:phone":"+1 586 783 5113",
    "sg:postcode":"48038",
    "sg:province":"MI",
    "sg:tags":[
        "packaging"
    ],
    "wof:name":"Zajac Industries",
    "wof:placetype":"venue"
},
  "geometry": {"coordinates":[-82.90082099999999,42.626727],"type":"Point"}
}