{
  "type": "Feature",
  "properties": {
    "iso:country":"US",
    "sg:address":"823 E Michigan Ave",
    "sg:city":"Ypsilanti",
    "sg:classifiers":[
        {
            "category":"Restaurant",
            "type":"Food & Drink"
        }
    ],
    "sg:menulink":"http://www.allmenus.com/mi/ypsilanti/197274-burger-king/menu/",
    "sg:phone":"+1 734 484 1140",
    "sg:postcode":"48198",
    "sg:province":"MI",
    "sg:tags":[
        "burger",
        "american"
    ],
    "wof:name":"Burger King",
    "wof:placetype":"venue"
},
  "geometry": {"coordinates":[-83.595958,42.242503],"type":"Point"}
}