{
  "type": "Feature",
  "properties": {
    "iso:country":"US",
    "sg:address":"215 W Page St",
    "sg:city":"Rose City",
    "sg:classifiers":[
        {
            "category":"Education",
            "subcategory":"School",
            "type":"Public Place"
        }
    ],
    "sg:phone":"+1 989 685 2484",
    "sg:postcode":"48654",
    "sg:province":"MI",
    "sg:website":"www.wbrc.org",
    "wof:name":"Rose City Elementary School",
    "wof:placetype":"venue"
},
  "geometry": {"coordinates":[-84.119129,44.420497],"type":"Point"}
}