{
  "type": "Feature",
  "properties": {
    "iso:country":"US",
    "sg:address":"15665 W McNichols Rd",
    "sg:city":"Detroit",
    "sg:classifiers":[
        {
            "category":"Home & Garden",
            "subcategory":"Household Appliances",
            "type":"Retail Goods"
        }
    ],
    "sg:phone":"+1 313 273 7110",
    "sg:postcode":"48235",
    "sg:province":"MI",
    "sg:tags":[
        "repair",
        "electrical"
    ],
    "wof:name":"Bronson Vacuum Inc",
    "wof:placetype":"venue"
},
  "geometry": {"coordinates":[-83.201801,42.415843],"type":"Point"}
}