{
  "type": "Feature",
  "properties": {
    "iso:country":"US",
    "sg:address":"214 N Vermont Ave",
    "sg:city":"Royal Oak",
    "sg:classifiers":[
        {
            "category":"Wholesale",
            "subcategory":"Machinery & Supplies",
            "type":"Manufacturing & Wholesale Goods"
        }
    ],
    "sg:phone":"+1 248 414 9339",
    "sg:postcode":"48067",
    "sg:province":"MI",
    "sg:tags":[
        "equipment"
    ],
    "wof:name":"Nationwide Equipment",
    "wof:placetype":"venue"
},
  "geometry": {"coordinates":[-83.12819500000001,42.491138],"type":"Point"}
}