{
  "type": "Feature",
  "properties": {
    "iso:country":"US",
    "sg:address":"32930 Middlebelt Rd",
    "sg:city":"Farmington Hills",
    "sg:classifiers":[
        {
            "category":"Shopping",
            "subcategory":"Clothing, Apparel, & Fashions",
            "type":"Retail Goods"
        }
    ],
    "sg:phone":"+1 248 626 0611",
    "sg:postcode":"48334",
    "sg:province":"MI",
    "sg:tags":[
        "hosiery"
    ],
    "wof:name":"Sock Shop LTD",
    "wof:placetype":"venue"
},
  "geometry": {"coordinates":[-83.340434,42.527994],"type":"Point"}
}