{
  "type": "Feature",
  "properties": {
    "iso:country":"US",
    "sg:address":"7188 Eagle Heights Dr",
    "sg:city":"Mattawan",
    "sg:classifiers":[
        {
            "category":"Insurance",
            "subcategory":"Insurance Agent",
            "type":"Services"
        }
    ],
    "sg:phone":"+1 269 372 1330",
    "sg:postcode":"49071",
    "sg:province":"MI",
    "sg:tags":[
        "accident"
    ],
    "wof:name":"Amity Associates Inc",
    "wof:placetype":"venue"
},
  "geometry": {"coordinates":[-85.72841200000001,42.212498],"type":"Point"}
}