{
  "type": "Feature",
  "properties": {
    "iso:country":"US",
    "sg:address":"4261 Lake St",
    "sg:city":"Bridgman",
    "sg:classifiers":[
        {
            "category":"Personal",
            "type":"Services"
        }
    ],
    "sg:phone":"+1 269 465 6394",
    "sg:postcode":"49106",
    "sg:province":"MI",
    "sg:tags":[
        "wedding",
        "chapel"
    ],
    "wof:name":"Small Town Weddings",
    "wof:placetype":"venue"
},
  "geometry": {"coordinates":[-86.55515,41.942913],"type":"Point"}
}