{
  "type": "Feature",
  "properties": {
    "iso:country":"US",
    "sg:address":"2770 Carpenter Rd",
    "sg:city":"Ann Arbor",
    "sg:classifiers":[
        {
            "category":"Health Services",
            "subcategory":"Clinic",
            "type":"Services"
        }
    ],
    "sg:phone":"+1 734 971 6300",
    "sg:postcode":"48108",
    "sg:province":"MI",
    "sg:tags":[
        "home"
    ],
    "sg:website":"www.friendswhocare.com",
    "wof:name":"Friends Who Care",
    "wof:placetype":"venue"
},
  "geometry": {"coordinates":[-83.68061,42.247527],"type":"Point"}
}