{
  "type": "Feature",
  "properties": {
    "iso:country":"US",
    "sg:address":"5509 Fenton Rd",
    "sg:city":"Flint",
    "sg:classifiers":[
        {
            "category":"Health Services",
            "subcategory":"Doctor",
            "type":"Services"
        },
        {
            "category":"Arena",
            "subcategory":"Sports Club",
            "type":"Entertainment"
        }
    ],
    "sg:phone":"+1 810 767 8536",
    "sg:postcode":"48507",
    "sg:province":"MI",
    "sg:tags":[
        "martial art"
    ],
    "wof:name":"Flint Tang Soo DO",
    "wof:placetype":"venue"
},
  "geometry": {"coordinates":[-83.692001,42.945599],"type":"Point"}
}