{
  "type": "Feature",
  "properties": {
    "iso:country":"US",
    "sg:address":"10063 Dixie Hwy",
    "sg:city":"Clarkston",
    "sg:classifiers":[
        {
            "category":"Restaurant",
            "type":"Food & Drink"
        }
    ],
    "sg:phone":"+1 248 922 9020",
    "sg:postcode":"48348",
    "sg:province":"MI",
    "wof:name":"Baker Street Restaurant",
    "wof:placetype":"venue"
},
  "geometry": {"coordinates":[-83.48885799999999,42.769277],"type":"Point"}
}