{
  "type": "Feature",
  "properties": {
    "iso:country":"US",
    "sg:address":"63563 Brick Church Rd",
    "sg:city":"Cassopolis",
    "sg:classifiers":[
        {
            "category":"Organizations",
            "subcategory":"Religious Organization",
            "type":"Services"
        }
    ],
    "sg:phone":"+1 269 445 2846",
    "sg:postcode":"49031",
    "sg:province":"MI",
    "sg:tags":[
        "church"
    ],
    "wof:name":"House Of Prayer Church",
    "wof:placetype":"venue"
},
  "geometry": {"coordinates":[-86.01036000000001,41.873077],"type":"Point"}
}