{
  "type": "Feature",
  "properties": {
    "iso:country":"US",
    "sg:address":"418 E Arthur Rd",
    "sg:city":"Rothbury",
    "sg:classifiers":[
        {
            "category":"Home & Garden",
            "subcategory":"Garden Supply",
            "type":"Retail Goods"
        }
    ],
    "sg:phone":"+1 231 861 5322",
    "sg:postcode":"49452",
    "sg:province":"MI",
    "sg:tags":[
        "nurseryman"
    ],
    "wof:name":"Fischer Trees",
    "wof:placetype":"venue"
},
  "geometry": {"coordinates":[-86.29317500000001,43.542741],"type":"Point"}
}