{
  "type": "Feature",
  "properties": {
    "iso:country":"US",
    "sg:address":"4920 W Albain Rd",
    "sg:city":"Monroe",
    "sg:classifiers":[
        {
            "category":"Retail",
            "subcategory":"Auto Repair",
            "type":"Services"
        }
    ],
    "sg:phone":"+1 734 241 0379",
    "sg:postcode":"48161",
    "sg:province":"MI",
    "sg:tags":[
        "maintenance"
    ],
    "wof:name":"First Vehicle Service",
    "wof:placetype":"venue"
},
  "geometry": {"coordinates":[-83.453785,41.8924],"type":"Point"}
}