{
  "type": "Feature",
  "properties": {
    "iso:country":"US",
    "sg:address":"15211 Channel Rd",
    "sg:city":"Grand Haven",
    "sg:classifiers":[
        {
            "category":"Shopping",
            "subcategory":"Computers & Home Electronics",
            "type":"Retail Goods"
        }
    ],
    "sg:phone":"+1 616 846 8910",
    "sg:postcode":"49417",
    "sg:province":"MI",
    "wof:name":"Alberdas Computer Service",
    "wof:placetype":"venue"
},
  "geometry": {"coordinates":[-86.17378600000001,43.044972],"type":"Point"}
}