{
  "type": "Feature",
  "properties": {
    "iso:country":"US",
    "sg:address":"23255 Greenfield Rd",
    "sg:city":"Southfield",
    "sg:classifiers":[
        {
            "category":"Food & Beverages",
            "subcategory":"Bakery",
            "type":"Retail Goods"
        }
    ],
    "sg:phone":"+1 248 552 5446",
    "sg:postcode":"48075",
    "sg:province":"MI",
    "sg:tags":[
        "sandwich"
    ],
    "wof:name":"Jimmy Johns Gourmet Sandwich Shop",
    "wof:placetype":"venue"
},
  "geometry": {"coordinates":[-83.201426,42.462974],"type":"Point"}
}