{
  "type": "Feature",
  "properties": {
    "iso:country":"US",
    "sg:address":"814 W Maumee St",
    "sg:city":"Adrian",
    "sg:classifiers":[
        {
            "category":"Restaurant",
            "type":"Food & Drink"
        }
    ],
    "sg:phone":"+1 517 263 9101",
    "sg:postcode":"49221",
    "sg:province":"MI",
    "wof:name":"Zelda's Tip Top Cafe",
    "wof:placetype":"venue"
},
  "geometry": {"coordinates":[-84.049021,41.90004],"type":"Point"}
}