{
  "type": "Feature",
  "properties": {
    "iso:country":"US",
    "sg:address":"210 W Carleton Rd",
    "sg:city":"Hillsdale",
    "sg:classifiers":[
        {
            "category":"Shopping",
            "subcategory":"Pharmacy",
            "type":"Retail Goods"
        }
    ],
    "sg:phone":"+1 517 439 9325",
    "sg:postcode":"49242",
    "sg:province":"MI",
    "wof:name":"Hillsdale Market Pharmacy",
    "wof:placetype":"venue"
},
  "geometry": {"coordinates":[-84.641504,41.933462],"type":"Point"}
}