{
  "type": "Feature",
  "properties": {
    "iso:country":"US",
    "sg:address":"1071 Ann Arbor Rd W",
    "sg:city":"Plymouth",
    "sg:classifiers":[
        {
            "category":"Personal",
            "subcategory":"Massage",
            "type":"Services"
        }
    ],
    "sg:phone":"+1 734 454 5600",
    "sg:postcode":"48170",
    "sg:province":"MI",
    "sg:tags":[
        "therapist"
    ],
    "wof:name":"Plymouth Wellness Ctr",
    "wof:placetype":"venue"
},
  "geometry": {"coordinates":[-83.47254,42.358679],"type":"Point"}
}