{
  "type": "Feature",
  "properties": {
    "iso:country":"US",
    "sg:address":"1675 E Apple Ave",
    "sg:city":"Muskegon",
    "sg:classifiers":[
        {
            "category":"Communications",
            "type":"Services"
        }
    ],
    "sg:phone":"+1 231 777 7465",
    "sg:postcode":"49442",
    "sg:province":"MI",
    "wof:name":"4 M Communications Inc",
    "wof:placetype":"venue"
},
  "geometry": {"coordinates":[-86.20255,43.234161],"type":"Point"}
}