{
  "type": "Feature",
  "properties": {
    "iso:country":"US",
    "sg:address":"4099 Pine Grove Ave",
    "sg:city":"Fort Gratiot",
    "sg:classifiers":[
        {
            "category":"Social Services",
            "subcategory":"Child Care",
            "type":"Services"
        }
    ],
    "sg:phone":"+1 810 385 5652",
    "sg:postcode":"48059",
    "sg:province":"MI",
    "sg:tags":[
        "day"
    ],
    "wof:name":"Karolyns Kids",
    "wof:placetype":"venue"
},
  "geometry": {"coordinates":[-82.464405,43.027909],"type":"Point"}
}