{
  "type": "Feature",
  "properties": {
    "iso:country":"US",
    "sg:address":"37603 S Groesbeck Hwy",
    "sg:city":"Clinton Township",
    "sg:classifiers":[
        {
            "category":"Building & Trades",
            "subcategory":"Construction",
            "type":"Services"
        }
    ],
    "sg:phone":"+1 586 783 3200",
    "sg:postcode":"48036",
    "sg:province":"MI",
    "sg:tags":[
        "contractor"
    ],
    "wof:name":"Casavilla Builders",
    "wof:placetype":"venue"
},
  "geometry": {"coordinates":[-82.907117,42.576251],"type":"Point"}
}