{
  "type": "Feature",
  "properties": {
    "iso:country":"US",
    "sg:address":"1550 E Beltline Ave SE",
    "sg:city":"Grand Rapids",
    "sg:classifiers":[
        {
            "category":"Professional",
            "subcategory":"Computer Services",
            "type":"Services"
        }
    ],
    "sg:phone":"+1 616 575 6040",
    "sg:postcode":"49506",
    "sg:province":"MI",
    "sg:tags":[
        "consultant",
        "designer"
    ],
    "wof:name":"Bethk Corp",
    "wof:placetype":"venue"
},
  "geometry": {"coordinates":[-85.584825,42.936512],"type":"Point"}
}