{
  "type": "Feature",
  "properties": {
    "iso:country":"US",
    "sg:address":"227 W 19th St",
    "sg:city":"Holland",
    "sg:classifiers":[
        {
            "category":"Arts & Performance",
            "subcategory":"Theater",
            "type":"Entertainment"
        }
    ],
    "sg:phone":"+1 616 396 5772",
    "sg:postcode":"49423",
    "sg:province":"MI",
    "sg:tags":[
        "play",
        "performs",
        "history"
    ],
    "wof:name":"Womens History Alive",
    "wof:placetype":"venue"
},
  "geometry": {"coordinates":[-86.117357,42.780322],"type":"Point"}
}