{
  "type": "Feature",
  "properties": {
    "iso:country":"US",
    "sg:address":"25267 Castlewood Dr",
    "sg:city":"Trenton",
    "sg:classifiers":[
        {
            "category":"Professional",
            "subcategory":"Art Services",
            "type":"Services"
        }
    ],
    "sg:phone":"+1 734 671 6640",
    "sg:postcode":"48183",
    "sg:province":"MI",
    "sg:tags":[
        "commercial",
        "design",
        "business"
    ],
    "wof:name":"Marlin Associates Inc",
    "wof:placetype":"venue"
},
  "geometry": {"coordinates":[-83.220215,42.123343],"type":"Point"}
}