{
  "type": "Feature",
  "properties": {
    "iso:country":"US",
    "sg:address":"3561 28th St SE",
    "sg:city":"Grand Rapids",
    "sg:classifiers":[
        {
            "category":"Restaurant",
            "type":"Food & Drink"
        }
    ],
    "sg:phone":"+1 616 956 7901",
    "sg:postcode":"49512",
    "sg:province":"MI",
    "wof:name":"Arnie's Bakery Restaurant",
    "wof:placetype":"venue"
},
  "geometry": {"coordinates":[-85.57592099999999,42.9126],"type":"Point"}
}