{
  "type": "Feature",
  "properties": {
    "iso:country":"US",
    "sg:address":"11021 Green Ave",
    "sg:city":"Grant",
    "sg:classifiers":[
        {
            "category":"Building & Trades",
            "subcategory":"Construction",
            "type":"Services"
        }
    ],
    "sg:phone":"+1 231 924 5557",
    "sg:postcode":"49327",
    "sg:province":"MI",
    "sg:tags":[
        "house"
    ],
    "wof:name":"Eddies Handyman Service",
    "wof:placetype":"venue"
},
  "geometry": {"coordinates":[-85.979426,43.355351],"type":"Point"}
}