{
  "type": "Feature",
  "properties": {
    "iso:country":"US",
    "sg:address":"5059 W Weidman Rd",
    "sg:city":"Weidman",
    "sg:classifiers":[
        {
            "category":"Manufacturing",
            "subcategory":"Retail Goods",
            "type":"Manufacturing & Wholesale Goods"
        }
    ],
    "sg:phone":"+1 989 644 8109",
    "sg:postcode":"48893",
    "sg:province":"MI",
    "sg:tags":[
        "manufacturer"
    ],
    "wof:name":"Dynamic Manufacturing Corp",
    "wof:placetype":"venue"
},
  "geometry": {"coordinates":[-84.95164,43.683455],"type":"Point"}
}