{
  "type": "Feature",
  "properties": {
    "iso:country":"US",
    "sg:address":"3266 Richfield Rd",
    "sg:city":"Flint",
    "sg:classifiers":[
        {
            "category":"Social Services",
            "subcategory":"Child Care",
            "type":"Services"
        }
    ],
    "sg:phone":"+1 810 736 3686",
    "sg:postcode":"48506",
    "sg:province":"MI",
    "sg:tags":[
        "day"
    ],
    "wof:name":"T's Daycare",
    "wof:placetype":"venue"
},
  "geometry": {"coordinates":[-83.64586199999999,43.050723],"type":"Point"}
}