{
  "type": "Feature",
  "properties": {
    "iso:country":"US",
    "sg:address":"4651 Indianwood Rd",
    "sg:city":"Clarkston",
    "sg:classifiers":[
        {
            "category":"Building & Trades",
            "subcategory":"Construction",
            "type":"Services"
        }
    ],
    "sg:phone":"+1 248 628 3228",
    "sg:postcode":"48348",
    "sg:province":"MI",
    "sg:tags":[
        "hanging",
        "contractor"
    ],
    "wof:name":"Dennis G Wolff & Ambassador",
    "wof:placetype":"venue"
},
  "geometry": {"coordinates":[-83.33988600000001,42.785658],"type":"Point"}
}