{
  "type": "Feature",
  "properties": {
    "iso:country":"US",
    "sg:address":"822 Wadhams Rd",
    "sg:city":"Kimball",
    "sg:classifiers":[
        {
            "category":"Building & Trades",
            "subcategory":"Landscaping Services",
            "type":"Services"
        }
    ],
    "sg:phone":"+1 810 367 6755",
    "sg:postcode":"48074",
    "sg:province":"MI",
    "sg:tags":[
        "landscape",
        "contractor"
    ],
    "wof:name":"Kingscape Landscape Contrs",
    "wof:placetype":"venue"
},
  "geometry": {"coordinates":[-82.54156,42.93366],"type":"Point"}
}