{
  "type": "Feature",
  "properties": {
    "iso:country":"US",
    "sg:address":"28800 Hayes Rd",
    "sg:city":"Roseville",
    "sg:classifiers":[
        {
            "category":"Retail",
            "subcategory":"Car Wash",
            "type":"Services"
        }
    ],
    "sg:phone":"+1 586 778 4238",
    "sg:postcode":"48066",
    "sg:province":"MI",
    "wof:name":"Htwoo",
    "wof:placetype":"venue"
},
  "geometry": {"coordinates":[-82.96796399999999,42.507199],"type":"Point"}
}