{
  "type": "Feature",
  "properties": {
    "iso:country":"US",
    "sg:address":"501 W Cedar Ave",
    "sg:city":"Beaverton",
    "sg:classifiers":[
        {
            "category":"Government",
            "subcategory":"Fire Station",
            "type":"Public Place"
        }
    ],
    "sg:phone":"+1 989 000 1111",
    "sg:postcode":"48624",
    "sg:province":"MI",
    "sg:tags":[
        "department"
    ],
    "wof:name":"Beaverton Fire Dept",
    "wof:placetype":"venue"
},
  "geometry": {"coordinates":[-84.49428899999999,43.980761],"type":"Point"}
}