{
  "type": "Feature",
  "properties": {
    "iso:country":"US",
    "sg:address":"24915 Hoover Rd",
    "sg:city":"Warren",
    "sg:classifiers":[
        {
            "category":"Retail",
            "subcategory":"Auto Repair",
            "type":"Services"
        }
    ],
    "sg:phone":"+1 586 755 1230",
    "sg:postcode":"48089",
    "sg:province":"MI",
    "wof:name":"Champs Automotive",
    "wof:placetype":"venue"
},
  "geometry": {"coordinates":[-83.00629499999999,42.477531],"type":"Point"}
}