{
  "type": "Feature",
  "properties": {
    "iso:country":"US",
    "sg:address":"132 Kirksway Ln",
    "sg:city":"Lake Orion",
    "sg:classifiers":[
        {
            "category":"Professional",
            "type":"Services"
        }
    ],
    "sg:phone":"+1 248 475 8842",
    "sg:postcode":"48362",
    "sg:province":"MI",
    "wof:name":"George P Janson",
    "wof:placetype":"venue"
},
  "geometry": {"coordinates":[-83.27679999999999,42.786183],"type":"Point"}
}