{
  "type": "Feature",
  "properties": {
    "iso:country":"US",
    "sg:address":"3949 N River Rd",
    "sg:city":"Freeland",
    "sg:classifiers":[
        {
            "category":"Professional",
            "subcategory":"Business Services",
            "type":"Services"
        }
    ],
    "sg:phone":"+1 989 781 2500",
    "sg:postcode":"48623",
    "sg:province":"MI",
    "sg:tags":[
        "drafting"
    ],
    "wof:name":"DAB Technical Svc LTD",
    "wof:placetype":"venue"
},
  "geometry": {"coordinates":[-84.084642,43.454213],"type":"Point"}
}