{
  "type": "Feature",
  "properties": {
    "iso:country":"US",
    "sg:address":"1522 Saint Joseph Rd",
    "sg:city":"Saint Joseph",
    "sg:classifiers":[
        {
            "category":"Professional",
            "subcategory":"Management & Consulting",
            "type":"Services"
        }
    ],
    "sg:phone":"+1 269 429 1205",
    "sg:postcode":"49030",
    "sg:province":"MI",
    "wof:name":"Square One Groupe Inc",
    "wof:placetype":"venue"
},
  "geometry": {"coordinates":[-85.291996,41.782586],"type":"Point"}
}