{
  "type": "Feature",
  "properties": {
    "iso:country":"US",
    "sg:address":"9247 Trey Blvd",
    "sg:city":"Hesperia",
    "sg:classifiers":[
        {
            "category":"Real Estate",
            "subcategory":"Developer",
            "type":"Services"
        }
    ],
    "sg:phone":"+1 231 854 4405",
    "sg:postcode":"49421",
    "sg:province":"MI",
    "wof:name":"New Horizon Property Mgmt",
    "wof:placetype":"venue"
},
  "geometry": {"coordinates":[-86.042372,43.556822],"type":"Point"}
}