{
  "type": "Feature",
  "properties": {
    "iso:country":"US",
    "sg:address":"2776 Cedar Key Dr",
    "sg:city":"Lake Orion",
    "sg:classifiers":[
        {
            "category":"Shopping",
            "subcategory":"Music",
            "type":"Retail Goods"
        }
    ],
    "sg:phone":"+1 248 391 5913",
    "sg:postcode":"48360",
    "sg:province":"MI",
    "sg:tags":[
        "video",
        "recorder",
        "cassette",
        "rent",
        "equipment"
    ],
    "wof:name":"Discount Video of Lake Orion",
    "wof:placetype":"venue"
},
  "geometry": {"coordinates":[-83.299913,42.751634],"type":"Point"}
}