{
  "type": "Feature",
  "properties": {
    "iso:country":"US",
    "sg:address":"923 Spring St",
    "sg:city":"Petoskey",
    "sg:classifiers":[
        {
            "category":"Professional",
            "subcategory":"Accounting & Tax Preparation",
            "type":"Services"
        }
    ],
    "sg:phone":"+1 231 347 4136",
    "sg:postcode":"49770",
    "sg:province":"MI",
    "sg:tags":[
        "accountant"
    ],
    "wof:name":"Hill Schroderus & Co",
    "wof:placetype":"venue"
},
  "geometry": {"coordinates":[-84.97082399999999,45.366521],"type":"Point"}
}