{
  "type": "Feature",
  "properties": {
    "iso:country":"US",
    "sg:address":"2831 Bay Rd",
    "sg:city":"Saginaw",
    "sg:classifiers":[
        {
            "category":"Food & Beverages",
            "subcategory":"Specialty",
            "type":"Retail Goods"
        }
    ],
    "sg:phone":"+1 989 790 9353",
    "sg:postcode":"48603",
    "sg:province":"MI",
    "sg:tags":[
        "health",
        "diet"
    ],
    "wof:name":"Low Carb Warehouse & More",
    "wof:placetype":"venue"
},
  "geometry": {"coordinates":[-83.97556299999999,43.446602],"type":"Point"}
}