{
  "type": "Feature",
  "properties": {
    "iso:country":"US",
    "sg:address":"128 Ames St",
    "sg:city":"Elk Rapids",
    "sg:classifiers":[
        {
            "category":"Health Services",
            "subcategory":"Health Practitioner",
            "type":"Services"
        }
    ],
    "sg:phone":"+1 231 264 6682",
    "sg:postcode":"49629",
    "sg:province":"MI",
    "sg:tags":[
        "therapist",
        "physical"
    ],
    "wof:name":"Elk Rapids Physical Therapy",
    "wof:placetype":"venue"
},
  "geometry": {"coordinates":[-85.408231,44.900962],"type":"Point"}
}