{
  "type": "Feature",
  "properties": {
    "iso:country":"US",
    "sg:address":"5400 Scio Church Rd",
    "sg:city":"Ann Arbor",
    "sg:classifiers":[
        {
            "category":"Wholesale",
            "subcategory":"Machinery & Supplies",
            "type":"Manufacturing & Wholesale Goods"
        }
    ],
    "sg:phone":"+1 734 971 8860",
    "sg:postcode":"48103",
    "sg:province":"MI",
    "sg:tags":[
        "equipment",
        "industrial"
    ],
    "wof:name":"James F Walters",
    "wof:placetype":"venue"
},
  "geometry": {"coordinates":[-83.83453799999999,42.254852],"type":"Point"}
}