{
  "type": "Feature",
  "properties": {
    "iso:country":"US",
    "sg:address":"1045 Cook Rd",
    "sg:city":"Grosse Pointe",
    "sg:classifiers":[
        {
            "category":"Education",
            "subcategory":"Preschool",
            "type":"Public Place"
        },
        {
            "category":"Education",
            "subcategory":"School",
            "type":"Public Place"
        }
    ],
    "sg:phone":"+1 313 343 0688",
    "sg:postcode":"48236",
    "sg:province":"MI",
    "sg:tags":[
        "elementary"
    ],
    "wof:name":"University Liggett School",
    "wof:placetype":"venue"
},
  "geometry": {"coordinates":[-82.900398,42.424301],"type":"Point"}
}