{
  "type": "Feature",
  "properties": {
    "iso:country":"US",
    "sg:address":"2254 N Branch Rd",
    "sg:city":"North Branch",
    "sg:classifiers":[
        {
            "category":"Wholesale",
            "subcategory":"Machinery & Supplies",
            "type":"Manufacturing & Wholesale Goods"
        }
    ],
    "sg:phone":"+1 810 688 8051",
    "sg:postcode":"48461",
    "sg:province":"MI",
    "sg:tags":[
        "washer",
        "dryer",
        "commercial"
    ],
    "wof:name":"Commercial Laundry Equipment",
    "wof:placetype":"venue"
},
  "geometry": {"coordinates":[-83.25464599999999,43.228387],"type":"Point"}
}