{
  "type": "Feature",
  "properties": {
    "iso:country":"US",
    "sg:address":"535 S Stage Rd",
    "sg:city":"Ionia",
    "sg:classifiers":[
        {
            "category":"Retail",
            "subcategory":"Repair Shop",
            "type":"Services"
        }
    ],
    "sg:phone":"+1 616 527 4571",
    "sg:postcode":"48846",
    "sg:province":"MI",
    "wof:name":"Ionia Machine",
    "wof:placetype":"venue"
},
  "geometry": {"coordinates":[-84.995453,42.996507],"type":"Point"}
}