{
  "type": "Feature",
  "properties": {
    "iso:country":"US",
    "sg:address":"642 Redruth Ave",
    "sg:city":"Clawson",
    "sg:classifiers":[
        {
            "category":"Manufacturing",
            "subcategory":"Apparel",
            "type":"Manufacturing & Wholesale Goods"
        }
    ],
    "sg:phone":"+1 248 435 7280",
    "sg:postcode":"48017",
    "sg:province":"MI",
    "wof:name":"In Stitches",
    "wof:placetype":"venue"
},
  "geometry": {"coordinates":[-83.15508,42.528962],"type":"Point"}
}