{
  "type": "Feature",
  "properties": {
    "iso:country":"US",
    "sg:address":"943 N River St",
    "sg:city":"Ypsilanti",
    "sg:classifiers":[
        {
            "category":"Real Estate",
            "subcategory":"Developer",
            "type":"Services"
        }
    ],
    "sg:phone":"+1 734 482 9490",
    "sg:postcode":"48198",
    "sg:province":"MI",
    "sg:tags":[
        "cemetery"
    ],
    "wof:name":"Highland Cemetery",
    "wof:placetype":"venue"
},
  "geometry": {"coordinates":[-83.60844,42.254933],"type":"Point"}
}