{
  "type": "Feature",
  "properties": {
    "iso:country":"US",
    "sg:address":"42598 78th St",
    "sg:city":"Covert",
    "sg:classifiers":[
        {
            "category":"Retail",
            "subcategory":"Auto Repair",
            "type":"Services"
        }
    ],
    "sg:phone":"+1 269 764 1440",
    "sg:postcode":"49043",
    "sg:province":"MI",
    "sg:tags":[
        "automotive",
        "wrecker"
    ],
    "wof:name":"Triple S Transferring",
    "wof:placetype":"venue"
},
  "geometry": {"coordinates":[-86.30138599999999,42.262632],"type":"Point"}
}