{
  "type": "Feature",
  "properties": {
    "iso:country":"US",
    "sg:address":"9125 Banwell Rd",
    "sg:city":"Alanson",
    "sg:classifiers":[
        {
            "category":"Building & Trades",
            "subcategory":"Construction",
            "type":"Services"
        }
    ],
    "sg:phone":"+1 231 548 5934",
    "sg:postcode":"49706",
    "sg:province":"MI",
    "sg:tags":[
        "house"
    ],
    "wof:name":"Thad T Hofbauer Custom Builder",
    "wof:placetype":"venue"
},
  "geometry": {"coordinates":[-84.768603,45.419966],"type":"Point"}
}