{
  "type": "Feature",
  "properties": {
    "iso:country":"US",
    "sg:address":"900 Union Ave NE",
    "sg:city":"Grand Rapids",
    "sg:classifiers":[
        {
            "category":"School Buses",
            "type":"Transportation"
        }
    ],
    "sg:phone":"+1 616 771 3000",
    "sg:postcode":"49503",
    "sg:province":"MI",
    "wof:name":"Grand Rapids Schools Pub Trnsp",
    "wof:placetype":"venue"
},
  "geometry": {"coordinates":[-85.65459799999999,42.979727],"type":"Point"}
}