{
  "type": "Feature",
  "properties": {
    "iso:country":"US",
    "sg:address":"16261 Lancaster Way",
    "sg:city":"Holly",
    "sg:classifiers":[
        {
            "category":"Professional",
            "subcategory":"Art Services",
            "type":"Services"
        }
    ],
    "sg:phone":"+1 248 475 9123",
    "sg:postcode":"48442",
    "sg:province":"MI",
    "sg:tags":[
        "commercial",
        "design"
    ],
    "wof:name":"Northstar Production",
    "wof:placetype":"venue"
},
  "geometry": {"coordinates":[-83.596458,42.793077],"type":"Point"}
}