{
  "type": "Feature",
  "properties": {
    "iso:country":"US",
    "sg:address":"16390 Allen Rd",
    "sg:city":"Lachine",
    "sg:phone":"+1 989 379 4089",
    "sg:postcode":"49753",
    "sg:province":"MI",
    "sg:tags":[
        "wheat",
        "beef",
        "farm",
        "cash",
        "crop",
        "grain",
        "berry",
        "cattle"
    ],
    "wof:name":"Glen Herron",
    "wof:placetype":"venue"
},
  "geometry": {"coordinates":[-83.776702,44.958544],"type":"Point"}
}