{
  "type": "Feature",
  "properties": {
    "iso:country":"US",
    "sg:address":"5979 Williams Rd",
    "sg:city":"Newport",
    "sg:classifiers":[
        {
            "category":"Professional",
            "subcategory":"Management & Consulting",
            "type":"Services"
        }
    ],
    "sg:phone":"+1 734 586 3434",
    "sg:postcode":"48166",
    "sg:province":"MI",
    "sg:tags":[
        "business"
    ],
    "wof:name":"Files Driver Testing",
    "wof:placetype":"venue"
},
  "geometry": {"coordinates":[-83.31058899999999,41.967458],"type":"Point"}
}