{
  "type": "Feature",
  "properties": {
    "iso:country":"US",
    "sg:address":"26666 Stanford Dr W",
    "sg:city":"Southfield",
    "sg:classifiers":[
        {
            "category":"Real Estate",
            "subcategory":"Real Estate Operator",
            "type":"Services"
        }
    ],
    "sg:phone":"+1 248 356 8633",
    "sg:postcode":"48034",
    "sg:province":"MI",
    "sg:tags":[
        "apartment"
    ],
    "wof:name":"Stanford Townhouses",
    "wof:placetype":"venue"
},
  "geometry": {"coordinates":[-83.31819900000001,42.472301],"type":"Point"}
}