{
  "type": "Feature",
  "properties": {
    "iso:country":"US",
    "sg:address":"4025 North Rd",
    "sg:city":"Clyde",
    "sg:classifiers":[
        {
            "category":"Organizations",
            "subcategory":"Religious Organization",
            "type":"Services"
        }
    ],
    "sg:phone":"+1 810 982 8720",
    "sg:postcode":"48049",
    "sg:province":"MI",
    "sg:tags":[
        "church"
    ],
    "sg:website":"www.thecornerstonechurch.org",
    "wof:name":"Cornerstone Church The",
    "wof:placetype":"venue"
},
  "geometry": {"coordinates":[-82.525395,43.027382],"type":"Point"}
}