{
  "type": "Feature",
  "properties": {
    "iso:country":"US",
    "sg:address":"8670 Grand River Ave",
    "sg:city":"Detroit",
    "sg:classifiers":[
        {
            "category":"Organizations",
            "subcategory":"Membership Organization",
            "type":"Services"
        }
    ],
    "sg:phone":"+1 313 894 0303",
    "sg:postcode":"48204",
    "sg:province":"MI",
    "wof:name":"Trade Union Leadership Council",
    "wof:placetype":"venue"
},
  "geometry": {"coordinates":[-83.123487,42.362452],"type":"Point"}
}