{
  "type": "Feature",
  "properties": {
    "iso:country":"US",
    "sg:address":"1515 E Maple Rd",
    "sg:city":"Troy",
    "sg:classifiers":[
        {
            "category":"Restaurant",
            "type":"Food & Drink"
        }
    ],
    "sg:phone":"+1 248 689 2332",
    "sg:postcode":"48083",
    "sg:province":"MI",
    "sg:tags":[
        "fusion",
        "sushi",
        "bar",
        "asian",
        "chinese"
    ],
    "sg:website":"www.monjinlau.com/",
    "wof:name":"Mon Jin Lau",
    "wof:placetype":"venue"
},
  "geometry": {"coordinates":[-83.121002,42.549],"type":"Point"}
}