{
  "type": "Feature",
  "properties": {
    "iso:country":"US",
    "sg:address":"327 Minkler Lake Rd",
    "sg:city":"Allegan",
    "sg:classifiers":[
        {
            "category":"Building & Trades",
            "subcategory":"Construction",
            "type":"Services"
        }
    ],
    "sg:phone":"+1 269 686 9248",
    "sg:postcode":"49010",
    "sg:province":"MI",
    "sg:tags":[
        "house"
    ],
    "wof:name":"Emmons Construction",
    "wof:placetype":"venue"
},
  "geometry": {"coordinates":[-85.84366799999999,42.448123],"type":"Point"}
}