{
  "type": "Feature",
  "properties": {
    "iso:country":"US",
    "sg:address":"409 Brown St",
    "sg:city":"Tecumseh",
    "sg:classifiers":[
        {
            "category":"Building & Trades",
            "subcategory":"Plumbing",
            "type":"Services"
        }
    ],
    "sg:phone":"+1 517 423 7792",
    "sg:postcode":"49286",
    "sg:province":"MI",
    "sg:tags":[
        "plumbing",
        "contractor"
    ],
    "wof:name":"Brown Street Rooter Svc",
    "wof:placetype":"venue"
},
  "geometry": {"coordinates":[-83.952201,42.014109],"type":"Point"}
}