{
  "type": "Feature",
  "properties": {
    "iso:country":"US",
    "sg:address":"2302 Junction St",
    "sg:city":"Detroit",
    "sg:classifiers":[
        {
            "category":"Home & Garden",
            "subcategory":"Hardware",
            "type":"Retail Goods"
        }
    ],
    "sg:phone":"+1 313 554 4367",
    "sg:postcode":"48209",
    "sg:province":"MI",
    "sg:tags":[
        "store"
    ],
    "wof:name":"Sonnenberg Hardware",
    "wof:placetype":"venue"
},
  "geometry": {"coordinates":[-83.10410299999999,42.321201],"type":"Point"}
}