{
  "type": "Feature",
  "properties": {
    "iso:country":"US",
    "sg:address":"221 E Michigan Ave",
    "sg:city":"Saline",
    "sg:classifiers":[
        {
            "category":"Autos & Motor Vehicles",
            "subcategory":"Fuel & Gas Station",
            "type":"Retail Goods"
        }
    ],
    "sg:phone":"+1 734 429 9930",
    "sg:postcode":"48176",
    "sg:province":"MI",
    "sg:tags":[
        "repair",
        "station",
        "gasoline",
        "general"
    ],
    "wof:name":"Harrys Service",
    "wof:placetype":"venue"
},
  "geometry": {"coordinates":[-83.778854,42.167857],"type":"Point"}
}