{
  "type": "Feature",
  "properties": {
    "iso:country":"US",
    "sg:address":"905 John St",
    "sg:city":"Kalamazoo",
    "sg:classifiers":[
        {
            "category":"Health Services",
            "subcategory":"Doctor",
            "type":"Services"
        }
    ],
    "sg:phone":"+1 269 343 0978",
    "sg:postcode":"49001",
    "sg:province":"MI",
    "sg:tags":[
        "medical"
    ],
    "wof:name":"Alkema H Dale MD",
    "wof:placetype":"venue"
},
  "geometry": {"coordinates":[-85.5812,42.282825],"type":"Point"}
}