{
  "type": "Feature",
  "properties": {
    "iso:country":"US",
    "sg:address":"38585 Hayes Rd",
    "sg:city":"Sterling Heights",
    "sg:classifiers":[
        {
            "category":"Personal",
            "type":"Services"
        }
    ],
    "sg:phone":"+1 586 262 3054",
    "sg:postcode":"48313",
    "sg:province":"MI",
    "sg:tags":[
        "sewing",
        "alteration"
    ],
    "wof:name":"Tailoring Katy",
    "wof:placetype":"venue"
},
  "geometry": {"coordinates":[-82.971547,42.57955],"type":"Point"}
}