{
  "type": "Feature",
  "properties": {
    "iso:country":"US",
    "sg:address":"7217 S Garlock Rd",
    "sg:city":"Carson City",
    "sg:classifiers":[
        {
            "category":"Organizations",
            "subcategory":"Religious Organization",
            "type":"Services"
        }
    ],
    "sg:phone":"+1 989 584 6006",
    "sg:postcode":"48811",
    "sg:province":"MI",
    "wof:name":"Church At Carson City",
    "wof:placetype":"venue"
},
  "geometry": {"coordinates":[-84.861155,43.188222],"type":"Point"}
}