{
  "type": "Feature",
  "properties": {
    "iso:country":"US",
    "sg:address":"20382 Van Born Rd",
    "sg:city":"Dearborn Heights",
    "sg:classifiers":[
        {
            "category":"Social Services",
            "type":"Services"
        }
    ],
    "sg:phone":"+1 313 792 9286",
    "sg:postcode":"48125",
    "sg:province":"MI",
    "wof:name":"Catholic Scial Svcs Wayne Cnty",
    "wof:placetype":"venue"
},
  "geometry": {"coordinates":[-83.23716,42.269755],"type":"Point"}
}