{
  "type": "Feature",
  "properties": {
    "iso:country":"US",
    "sg:address":"6113 Woodpark Dr",
    "sg:city":"Midland",
    "sg:classifiers":[
        {
            "category":"Professional",
            "subcategory":"Management & Consulting",
            "type":"Services"
        }
    ],
    "sg:phone":"+1 989 835 5943",
    "sg:postcode":"48640",
    "sg:province":"MI",
    "sg:tags":[
        "retail",
        "merchandise",
        "direct",
        "business",
        "sales"
    ],
    "wof:name":"Mary Kay Cosmetics",
    "wof:placetype":"venue"
},
  "geometry": {"coordinates":[-84.245001,43.654051],"type":"Point"}
}