{
  "type": "Feature",
  "properties": {
    "iso:country":"US",
    "sg:address":"16496 124th Ave",
    "sg:city":"Nunica",
    "sg:classifiers":[
        {
            "category":"Wholesale",
            "subcategory":"Machinery & Supplies",
            "type":"Manufacturing & Wholesale Goods"
        }
    ],
    "sg:phone":"+1 616 837 5839",
    "sg:postcode":"49448",
    "sg:province":"MI",
    "sg:tags":[
        "agricultural",
        "implement"
    ],
    "wof:name":"Troyers Growers Supply",
    "wof:placetype":"venue"
},
  "geometry": {"coordinates":[-86.09684799999999,43.067944],"type":"Point"}
}