{
  "type": "Feature",
  "properties": {
    "iso:country":"US",
    "sg:address":"132 N Old Woodward Ave",
    "sg:city":"Birmingham",
    "sg:classifiers":[
        {
            "category":"Insurance",
            "subcategory":"Insurance Agent",
            "type":"Services"
        }
    ],
    "sg:phone":"+1 248 258 3222",
    "sg:postcode":"48009",
    "sg:province":"MI",
    "sg:tags":[
        "consultant"
    ],
    "wof:name":"Mangelsdorf Companies Assoc",
    "wof:placetype":"venue"
},
  "geometry": {"coordinates":[-83.21435,42.546928],"type":"Point"}
}