{
  "type": "Feature",
  "properties": {
    "iso:country":"US",
    "sg:address":"53 College St",
    "sg:city":"Kent City",
    "sg:classifiers":[
        {
            "category":"Building & Trades",
            "subcategory":"Construction",
            "type":"Services"
        }
    ],
    "sg:phone":"+1 616 678 4101",
    "sg:postcode":"49330",
    "sg:province":"MI",
    "sg:tags":[
        "house"
    ],
    "wof:name":"John Wellman Builders",
    "wof:placetype":"venue"
},
  "geometry": {"coordinates":[-85.750288,43.221318],"type":"Point"}
}