{
  "type": "Feature",
  "properties": {
    "iso:country":"US",
    "sg:address":"1253 Stone Barn Rd",
    "sg:city":"Milford",
    "sg:classifiers":[
        {
            "category":"Building & Trades",
            "subcategory":"Construction",
            "type":"Services"
        }
    ],
    "sg:phone":"+1 248 887 1965",
    "sg:postcode":"48380",
    "sg:province":"MI",
    "sg:tags":[
        "general",
        "contractor"
    ],
    "wof:name":"Lizzet Builders Inc",
    "wof:placetype":"venue"
},
  "geometry": {"coordinates":[-83.668505,42.623238],"type":"Point"}
}