{
  "type": "Feature",
  "properties": {
    "iso:country":"US",
    "sg:address":"403 E Saint Clair St",
    "sg:city":"Romeo",
    "sg:classifiers":[
        {
            "category":"Home & Garden",
            "subcategory":"Carpets & Floor Coverings",
            "type":"Retail Goods"
        }
    ],
    "sg:phone":"+1 586 752 6550",
    "sg:postcode":"48065",
    "sg:province":"MI",
    "sg:tags":[
        "dealer",
        "rug"
    ],
    "wof:name":"Romeo Floor Covering",
    "wof:placetype":"venue"
},
  "geometry": {"coordinates":[-83.005877,42.802838],"type":"Point"}
}