{
  "type": "Feature",
  "properties": {
    "iso:country":"US",
    "sg:address":"4370 Beckon Rd",
    "sg:city":"Harbor Springs",
    "sg:classifiers":[
        {
            "category":"Building & Trades",
            "subcategory":"Cleaning & Sanitation",
            "type":"Services"
        }
    ],
    "sg:phone":"+1 231 526 0286",
    "sg:postcode":"49740",
    "sg:province":"MI",
    "sg:tags":[
        "maintenance"
    ],
    "wof:name":"C Through Window Cleaning",
    "wof:placetype":"venue"
},
  "geometry": {"coordinates":[-84.998704,45.615157],"type":"Point"}
}