{
  "type": "Feature",
  "properties": {
    "iso:country":"US",
    "sg:address":"301 W Main St",
    "sg:city":"Midland",
    "sg:classifiers":[
        {
            "category":"Government",
            "subcategory":"Court House",
            "type":"Public Place"
        }
    ],
    "sg:phone":"+1 989 832 6760",
    "sg:postcode":"48640",
    "sg:province":"MI",
    "sg:tags":[
        "county"
    ],
    "wof:name":"Circuit Court-Probation-Parole",
    "wof:placetype":"venue"
},
  "geometry": {"coordinates":[-84.24802,43.615006],"type":"Point"}
}