{
  "type": "Feature",
  "properties": {
    "iso:country":"US",
    "sg:address":"51644 Oro",
    "sg:city":"Shelby Twp",
    "sg:classifiers":[
        {
            "category":"Building & Trades",
            "subcategory":"Electrical",
            "type":"Services"
        }
    ],
    "sg:phone":"+1 586 532 2071",
    "sg:postcode":"48315",
    "sg:province":"MI",
    "sg:tags":[
        "electric",
        "contractor"
    ],
    "wof:name":"Sebesta Brothers Electric Inc",
    "wof:placetype":"venue"
},
  "geometry": {"coordinates":[-82.98611200000001,42.67194],"type":"Point"}
}