{
  "type": "Feature",
  "properties": {
    "iso:country":"US",
    "sg:address":"11400 Lansdowne St",
    "sg:city":"Detroit",
    "sg:classifiers":[
        {
            "category":"Wholesale",
            "subcategory":"Vending Machines",
            "type":"Manufacturing & Wholesale Goods"
        }
    ],
    "sg:phone":"+1 313 839 9678",
    "sg:postcode":"48224",
    "sg:province":"MI",
    "sg:tags":[
        "operator"
    ],
    "wof:name":"Tme Enterprises",
    "wof:placetype":"venue"
},
  "geometry": {"coordinates":[-82.954302,42.422205],"type":"Point"}
}