{
  "type": "Feature",
  "properties": {
    "iso:country":"US",
    "sg:address":"7223 Velte Rd",
    "sg:city":"Lake Odessa",
    "sg:classifiers":[
        {
            "category":"Education",
            "subcategory":"School",
            "type":"Public Place"
        }
    ],
    "sg:phone":"+1 616 693 2175",
    "sg:postcode":"48849",
    "sg:province":"MI",
    "wof:name":"Lakewood Clarksville Elem Schl",
    "wof:placetype":"venue"
},
  "geometry": {"coordinates":[-85.113955,42.762202],"type":"Point"}
}