{
  "type": "Feature",
  "properties": {
    "iso:country":"US",
    "sg:address":"2450 Van Ommen Dr",
    "sg:city":"Holland",
    "sg:classifiers":[
        {
            "category":"Insurance",
            "subcategory":"Insurance Agent",
            "type":"Services"
        }
    ],
    "sg:phone":"+1 616 399 0900",
    "sg:postcode":"49424",
    "sg:province":"MI",
    "wof:name":"Miller Benefits Group",
    "wof:placetype":"venue"
},
  "geometry": {"coordinates":[-86.09129900000001,42.814741],"type":"Point"}
}