{
  "type": "Feature",
  "properties": {
    "iso:country":"US",
    "sg:address":"610 Sunbrook St SE",
    "sg:city":"Grand Rapids",
    "sg:classifiers":[
        {
            "category":"Professional",
            "subcategory":"Computer Services",
            "type":"Services"
        }
    ],
    "sg:phone":"+1 616 554 1207",
    "sg:postcode":"49508",
    "sg:province":"MI",
    "sg:tags":[
        "programing",
        "custom"
    ],
    "wof:name":"Axis Computer Services Inc",
    "wof:placetype":"venue"
},
  "geometry": {"coordinates":[-85.650446,42.828422],"type":"Point"}
}