{
  "type": "Feature",
  "properties": {
    "iso:country":"US",
    "sg:address":"10153 Walnut Shores Dr",
    "sg:city":"Fenton",
    "sg:classifiers":[
        {
            "category":"Wholesale",
            "subcategory":"Durable Goods & Equipment",
            "type":"Manufacturing & Wholesale Goods"
        }
    ],
    "sg:phone":"+1 810 629 8788",
    "sg:postcode":"48430",
    "sg:province":"MI",
    "sg:tags":[
        "representative",
        "manufacturer"
    ],
    "wof:name":"Ron Kramer Industries",
    "wof:placetype":"venue"
},
  "geometry": {"coordinates":[-83.751892,42.754663],"type":"Point"}
}