{
  "type": "Feature",
  "properties": {
    "iso:country":"US",
    "sg:address":"51458 Oro",
    "sg:city":"Shelby Twp",
    "sg:classifiers":[
        {
            "category":"Home & Garden",
            "subcategory":"Furniture",
            "type":"Retail Goods"
        }
    ],
    "sg:phone":"+1 586 247 7771",
    "sg:postcode":"48315",
    "sg:province":"MI",
    "sg:tags":[
        "top",
        "counter"
    ],
    "wof:name":"Creative Counters Inc",
    "wof:placetype":"venue"
},
  "geometry": {"coordinates":[-82.986368,42.67343],"type":"Point"}
}