{
  "type": "Feature",
  "properties": {
    "iso:country":"US",
    "sg:address":"414 N St Mary's St",
    "sg:city":"Suttons Bay",
    "sg:classifiers":[
        {
            "category":"Building & Trades",
            "subcategory":"Construction",
            "type":"Services"
        }
    ],
    "sg:phone":"+1 231 271 4680",
    "sg:postcode":"49682",
    "sg:province":"MI",
    "sg:tags":[
        "house"
    ],
    "wof:name":"Northwest Builders",
    "wof:placetype":"venue"
},
  "geometry": {"coordinates":[-85.650474,44.978857],"type":"Point"}
}