{
  "type": "Feature",
  "properties": {
    "iso:country":"US",
    "sg:address":"5269 N McKinley Rd",
    "sg:city":"Flushing",
    "sg:classifiers":[
        {
            "category":"Personal",
            "subcategory":"Barber",
            "type":"Services"
        }
    ],
    "sg:phone":"+1 810 659 3963",
    "sg:postcode":"48433",
    "sg:province":"MI",
    "sg:tags":[
        "shop"
    ],
    "wof:name":"Nina's Heads Up",
    "wof:placetype":"venue"
},
  "geometry": {"coordinates":[-83.85317999999999,43.08246],"type":"Point"}
}