{
  "type": "Feature",
  "properties": {
    "iso:country":"US",
    "sg:address":"6800 Gregory Rd",
    "sg:city":"Dexter",
    "sg:classifiers":[
        {
            "category":"Retail",
            "subcategory":"Repair Shop",
            "type":"Services"
        }
    ],
    "sg:phone":"+1 734 426 2485",
    "sg:postcode":"48130",
    "sg:province":"MI",
    "wof:name":"Buckies Taxidermy",
    "wof:placetype":"venue"
},
  "geometry": {"coordinates":[-83.87284,42.369316],"type":"Point"}
}