{
  "type": "Feature",
  "properties": {
    "iso:country":"US",
    "sg:address":"6172 Adacroft Dr SE",
    "sg:city":"Ada",
    "sg:classifiers":[
        {
            "category":"Personal",
            "type":"Services"
        }
    ],
    "sg:phone":"+1 616 682 0423",
    "sg:postcode":"49301",
    "sg:province":"MI",
    "sg:tags":[
        "reporting"
    ],
    "wof:name":"Advanced Custom Designs",
    "wof:placetype":"venue"
},
  "geometry": {"coordinates":[-85.516184,42.950822],"type":"Point"}
}