{
  "type": "Feature",
  "properties": {
    "iso:country":"US",
    "sg:address":"1452 42nd St SE",
    "sg:city":"Grand Rapids",
    "sg:classifiers":[
        {
            "category":"Real Estate",
            "subcategory":"Real Estate Operator",
            "type":"Services"
        }
    ],
    "sg:phone":"+1 616 949 9485",
    "sg:postcode":"49508",
    "sg:province":"MI",
    "sg:tags":[
        "apartment"
    ],
    "wof:name":"42nd Street Apartments",
    "wof:placetype":"venue"
},
  "geometry": {"coordinates":[-85.63000599999999,42.887485],"type":"Point"}
}