{
  "type": "Feature",
  "properties": {
    "iso:country":"US",
    "sg:address":"1483 Eden Gardens Dr",
    "sg:city":"Fenton",
    "sg:classifiers":[
        {
            "category":"Manufacturing",
            "subcategory":"Food",
            "type":"Manufacturing & Wholesale Goods"
        }
    ],
    "sg:phone":"+1 810 694 7893",
    "sg:postcode":"48430",
    "sg:province":"MI",
    "sg:tags":[
        "product",
        "mfg"
    ],
    "wof:name":"Jcs Distributing Inc",
    "wof:placetype":"venue"
},
  "geometry": {"coordinates":[-83.70387100000001,42.849675],"type":"Point"}
}