{
  "type": "Feature",
  "properties": {
    "iso:country":"US",
    "sg:address":"4150 Broadmoor Ave SE",
    "sg:city":"Grand Rapids",
    "sg:classifiers":[
        {
            "category":"Manufacturing",
            "subcategory":"Rubber & Plastics",
            "type":"Manufacturing & Wholesale Goods"
        }
    ],
    "sg:phone":"+1 616 656 2820",
    "sg:postcode":"49512",
    "sg:province":"MI",
    "sg:tags":[
        "product"
    ],
    "sg:website":"www.alro.com",
    "wof:name":"Alro Plastics",
    "wof:placetype":"venue"
},
  "geometry": {"coordinates":[-85.56881,42.888931],"type":"Point"}
}