{
  "type": "Feature",
  "properties": {
    "iso:country":"US",
    "sg:address":"3817 Thorncrest Dr",
    "sg:city":"Jackson",
    "sg:classifiers":[
        {
            "category":"Building & Trades",
            "subcategory":"Construction",
            "type":"Services"
        }
    ],
    "sg:phone":"+1 517 750 3792",
    "sg:postcode":"49203",
    "sg:province":"MI",
    "sg:tags":[
        "house"
    ],
    "wof:name":"R & D Custom Homes",
    "wof:placetype":"venue"
},
  "geometry": {"coordinates":[-84.465244,42.236549],"type":"Point"}
}