{
  "type": "Feature",
  "properties": {
    "iso:country":"US",
    "sg:address":"4747 Haggerty Rd",
    "sg:city":"West Bloomfield",
    "sg:classifiers":[
        {
            "category":"Banks & Credit Unions",
            "subcategory":"Bank",
            "type":"Services"
        }
    ],
    "sg:phone":"+1 248 960 0593",
    "sg:postcode":"48323",
    "sg:province":"MI",
    "sg:website":"www.53.com",
    "wof:name":"Fifth Third Bank",
    "wof:placetype":"venue"
},
  "geometry": {"coordinates":[-83.439306,42.564541],"type":"Point"}
}