{
  "type": "Feature",
  "properties": {
    "iso:country":"US",
    "sg:address":"1695 Bloomfield Dr SE",
    "sg:city":"Grand Rapids",
    "sg:classifiers":[
        {
            "category":"Real Estate",
            "subcategory":"Real Estate Operator",
            "type":"Services"
        }
    ],
    "sg:phone":"+1 616 281 7120",
    "sg:postcode":"49508",
    "sg:province":"MI",
    "sg:tags":[
        "building",
        "apartment"
    ],
    "wof:name":"Bloomfield Townhomes",
    "wof:placetype":"venue"
},
  "geometry": {"coordinates":[-85.624398,42.854656],"type":"Point"}
}