{
  "type": "Feature",
  "properties": {
    "iso:country":"US",
    "sg:address":"31851 Gratiot Ave",
    "sg:city":"Roseville",
    "sg:classifiers":[
        {
            "category":"Home & Garden",
            "subcategory":"Carpets & Floor Coverings",
            "type":"Retail Goods"
        }
    ],
    "sg:phone":"+1 586 296 3363",
    "sg:postcode":"48066",
    "sg:province":"MI",
    "sg:tags":[
        "mattress"
    ],
    "wof:name":"The Futon Don",
    "wof:placetype":"venue"
},
  "geometry": {"coordinates":[-82.914841,42.531129],"type":"Point"}
}