{
  "type": "Feature",
  "properties": {
    "iso:country":"US",
    "sg:address":"346 E Michigan Ave",
    "sg:city":"Battle Creek",
    "sg:classifiers":[
        {
            "category":"Wholesale",
            "subcategory":"Durable Goods & Equipment",
            "type":"Manufacturing & Wholesale Goods"
        }
    ],
    "sg:phone":"+1 269 968 4711",
    "sg:postcode":"49014",
    "sg:province":"MI",
    "sg:tags":[
        "representative",
        "manufacturer"
    ],
    "wof:name":"Braetec",
    "wof:placetype":"venue"
},
  "geometry": {"coordinates":[-85.17106200000001,42.313932],"type":"Point"}
}