{
  "type": "Feature",
  "properties": {
    "iso:country":"US",
    "sg:address":"2054 Milford St NW",
    "sg:city":"Grand Rapids",
    "sg:classifiers":[
        {
            "category":"Professional",
            "subcategory":"Management & Consulting",
            "type":"Services"
        }
    ],
    "sg:phone":"+1 616 735 0924",
    "sg:postcode":"49504",
    "sg:province":"MI",
    "wof:name":"Heitzmans Consulting",
    "wof:placetype":"venue"
},
  "geometry": {"coordinates":[-85.719212,42.98919],"type":"Point"}
}