{
  "type": "Feature",
  "properties": {
    "iso:country":"US",
    "sg:address":"1245 E Grand River Ave",
    "sg:city":"Lansing",
    "sg:classifiers":[
        {
            "category":"Food & Beverages",
            "subcategory":"Groceries & Convenience Stores",
            "type":"Retail Goods"
        }
    ],
    "sg:phone":"+1 517 484 8386",
    "sg:postcode":"48906",
    "sg:province":"MI",
    "wof:name":"One Stop Food Mart",
    "wof:placetype":"venue"
},
  "geometry": {"coordinates":[-84.534614,42.747475],"type":"Point"}
}