{
  "type": "Feature",
  "properties": {
    "iso:country":"US",
    "sg:address":"902 Ashmun St",
    "sg:city":"Sault Sainte Marie",
    "sg:classifiers":[
        {
            "category":"Retail",
            "subcategory":"Auto Repair",
            "type":"Services"
        }
    ],
    "sg:phone":"+1 906 632 4489",
    "sg:postcode":"49783",
    "sg:province":"MI",
    "sg:tags":[
        "general"
    ],
    "wof:name":"Midas Muffler",
    "wof:placetype":"venue"
},
  "geometry": {"coordinates":[-84.351319,46.49295],"type":"Point"}
}