{
  "type": "Feature",
  "properties": {
    "iso:country":"US",
    "sg:address":"2566 Chilson Meadows",
    "sg:city":"Howell",
    "sg:classifiers":[
        {
            "category":"Building & Trades",
            "subcategory":"Construction",
            "type":"Services"
        }
    ],
    "sg:phone":"+1 517 552 4932",
    "sg:postcode":"48843",
    "sg:province":"MI",
    "sg:tags":[
        "builder",
        "operative"
    ],
    "wof:name":"McGrath Works",
    "wof:placetype":"venue"
},
  "geometry": {"coordinates":[-83.90007300000001,42.580986],"type":"Point"}
}