{
  "type": "Feature",
  "properties": {
    "iso:country":"US",
    "sg:address":"3131 Smugglers Ridge",
    "sg:city":"Walled Lake",
    "sg:classifiers":[
        {
            "category":"Professional",
            "type":"Services"
        }
    ],
    "sg:phone":"+1 248 669 2355",
    "sg:postcode":"48390",
    "sg:province":"MI",
    "wof:name":"Write To Point",
    "wof:placetype":"venue"
},
  "geometry": {"coordinates":[-83.491686,42.567571],"type":"Point"}
}