{
  "type": "Feature",
  "properties": {
    "iso:country":"US",
    "sg:address":"41830 Hayes Rd",
    "sg:city":"Clinton Twp",
    "sg:classifiers":[
        {
            "category":"Restaurant",
            "type":"Food & Drink"
        }
    ],
    "sg:phone":"+1 586 228 8022",
    "sg:postcode":"48038",
    "sg:province":"MI",
    "wof:name":"Restauraunte Venezia",
    "wof:placetype":"venue"
},
  "geometry": {"coordinates":[-82.97222499999999,42.603226],"type":"Point"}
}