{
  "type": "Feature",
  "properties": {
    "iso:country":"US",
    "sg:address":"810 Broadus St",
    "sg:city":"Sturgis",
    "sg:classifiers":[
        {
            "category":"Retail",
            "subcategory":"Auto Repair",
            "type":"Services"
        }
    ],
    "sg:phone":"+1 269 651 7816",
    "sg:postcode":"49091",
    "sg:province":"MI",
    "sg:tags":[
        "modification",
        "vehicle",
        "center",
        "motor",
        "customizing"
    ],
    "wof:name":"Lux-Liner Seating",
    "wof:placetype":"venue"
},
  "geometry": {"coordinates":[-85.43344399999999,41.804751],"type":"Point"}
}