{
  "type": "Feature",
  "properties": {
    "iso:country":"US",
    "sg:address":"1681 New Castle Dr",
    "sg:city":"Jenison",
    "sg:classifiers":[
        {
            "category":"Wholesale",
            "subcategory":"Groceries",
            "type":"Manufacturing & Wholesale Goods"
        }
    ],
    "sg:phone":"+1 616 667 2848",
    "sg:postcode":"49428",
    "sg:province":"MI",
    "sg:tags":[
        "food",
        "broker"
    ],
    "wof:name":"Challenge Marketing",
    "wof:placetype":"venue"
},
  "geometry": {"coordinates":[-85.823606,42.913657],"type":"Point"}
}