{
  "type": "Feature",
  "properties": {
    "iso:country":"US",
    "sg:address":"2554 W Roosevelt Rd",
    "sg:city":"Perrinton",
    "sg:phone":"+1 989 838 4472",
    "sg:postcode":"48871",
    "sg:province":"MI",
    "sg:tags":[
        "farm",
        "soybean"
    ],
    "wof:name":"Raymond Towslee",
    "wof:placetype":"venue"
},
  "geometry": {"coordinates":[-84.650291,43.161526],"type":"Point"}
}