{
  "type": "Feature",
  "properties": {
    "iso:country":"US",
    "sg:address":"208 S State St",
    "sg:city":"Oscoda",
    "sg:classifiers":[
        {
            "category":"Personal",
            "subcategory":"Beauty Salon",
            "type":"Services"
        }
    ],
    "sg:phone":"+1 989 739 3168",
    "sg:postcode":"48740",
    "sg:province":"MI",
    "sg:tags":[
        "shop"
    ],
    "wof:name":"Ahead Of Time Hair Designs",
    "wof:placetype":"venue"
},
  "geometry": {"coordinates":[-83.29725000000001,44.654621],"type":"Point"}
}