{
  "type": "Feature",
  "properties": {
    "iso:country":"US",
    "sg:address":"1122 Goodwood Ct",
    "sg:city":"Holland",
    "sg:classifiers":[
        {
            "category":"Organizations",
            "subcategory":"Non-profit Organization",
            "type":"Services"
        }
    ],
    "sg:phone":"+1 616 399 3556",
    "sg:postcode":"49424",
    "sg:province":"MI",
    "sg:tags":[
        "social"
    ],
    "wof:name":"Catalina 25 National Asso",
    "wof:placetype":"venue"
},
  "geometry": {"coordinates":[-86.156306,42.787941],"type":"Point"}
}