{
  "type": "Feature",
  "properties": {
    "iso:country":"US",
    "sg:address":"6414 N Merriman Rd",
    "sg:city":"Westland",
    "sg:classifiers":[
        {
            "category":"Home & Garden",
            "subcategory":"Garden Supply",
            "type":"Retail Goods"
        },
        {
            "category":"Shopping",
            "subcategory":"Florist",
            "type":"Retail Goods"
        }
    ],
    "sg:phone":"+1 734 421 5959",
    "sg:postcode":"48185",
    "sg:province":"MI",
    "sg:tags":[
        "nursery",
        "gardening"
    ],
    "wof:name":"Barson Green House",
    "wof:placetype":"venue"
},
  "geometry": {"coordinates":[-83.375702,42.335899],"type":"Point"}
}