{
  "type": "Feature",
  "properties": {
    "iso:country":"US",
    "sg:address":"1433 E Tuttle Rd",
    "sg:city":"Ionia",
    "sg:classifiers":[
        {
            "category":"Recreation",
            "type":"Entertainment"
        }
    ],
    "sg:phone":"+1 616 527 2902",
    "sg:postcode":"48846",
    "sg:province":"MI",
    "wof:name":"Rocky Top Driving Range",
    "wof:placetype":"venue"
},
  "geometry": {"coordinates":[-85.048215,42.951168],"type":"Point"}
}