{
  "type": "Feature",
  "properties": {
    "iso:country":"US",
    "sg:address":"1220 Lincoln Rd",
    "sg:city":"Allegan",
    "sg:classifiers":[
        {
            "category":"Autos & Motor Vehicles",
            "subcategory":"Automobile Sales",
            "type":"Retail Goods"
        }
    ],
    "sg:phone":"+1 269 686 1311",
    "sg:postcode":"49010",
    "sg:province":"MI",
    "sg:tags":[
        "car",
        "dealer"
    ],
    "wof:name":"Woody's M-89 Auto Sales",
    "wof:placetype":"venue"
},
  "geometry": {"coordinates":[-85.807497,42.506235],"type":"Point"}
}