{
  "type": "Feature",
  "properties": {
    "iso:country":"US",
    "sg:address":"6812 Old 27 Hwy N",
    "sg:city":"Frederic",
    "sg:classifiers":[
        {
            "category":"Retail",
            "subcategory":"Auto Repair",
            "type":"Services"
        }
    ],
    "sg:phone":"+1 989 344 9400",
    "sg:postcode":"49735",
    "sg:province":"MI",
    "sg:tags":[
        "repairing",
        "automobile"
    ],
    "wof:name":"S & B Auto Repair & Svc",
    "wof:placetype":"venue"
},
  "geometry": {"coordinates":[-84.689379,44.926949],"type":"Point"}
}