{
  "type": "Feature",
  "properties": {
    "iso:country":"US",
    "sg:address":"6830 Becker Rd",
    "sg:city":"Saginaw",
    "sg:classifiers":[
        {
            "category":"Building & Trades",
            "subcategory":"Construction",
            "type":"Services"
        }
    ],
    "sg:phone":"+1 989 754 4469",
    "sg:postcode":"48601",
    "sg:province":"MI",
    "sg:tags":[
        "sandblasting"
    ],
    "wof:name":"A & J Svc",
    "wof:placetype":"venue"
},
  "geometry": {"coordinates":[-83.823927,43.471683],"type":"Point"}
}