{
  "type": "Feature",
  "properties": {
    "iso:country":"US",
    "sg:address":"2100 Holton Whitehall Rd",
    "sg:city":"Whitehall",
    "sg:classifiers":[
        {
            "category":"Utilities",
            "subcategory":"Refuse",
            "type":"Services"
        }
    ],
    "sg:phone":"+1 231 893 2405",
    "sg:postcode":"49461",
    "sg:province":"MI",
    "sg:tags":[
        "garbage",
        "collection"
    ],
    "wof:name":"White Lake Area Solid Waste",
    "wof:placetype":"venue"
},
  "geometry": {"coordinates":[-86.29521099999999,43.409637],"type":"Point"}
}