{
  "type": "Feature",
  "properties": {
    "iso:country":"US",
    "sg:address":"21579 Schoenherr Rd",
    "sg:city":"Warren",
    "sg:classifiers":[
        {
            "category":"Retail",
            "subcategory":"Auto Repair",
            "type":"Services"
        }
    ],
    "sg:phone":"+1 586 777 7330",
    "sg:postcode":"48089",
    "sg:province":"MI",
    "sg:tags":[
        "repairing",
        "automobile"
    ],
    "wof:name":"Starr Motor",
    "wof:placetype":"venue"
},
  "geometry": {"coordinates":[-82.986099,42.455502],"type":"Point"}
}