{
  "type": "Feature",
  "properties": {
    "iso:country":"US",
    "sg:address":"2962 S Decker Rd",
    "sg:city":"Marlette",
    "sg:classifiers":[
        {
            "category":"Professional",
            "type":"Services"
        }
    ],
    "sg:phone":"+1 989 635 7088",
    "sg:postcode":"48453",
    "sg:province":"MI",
    "sg:tags":[
        "establishment"
    ],
    "wof:name":"Laser Connection",
    "wof:placetype":"venue"
},
  "geometry": {"coordinates":[-83.04445,43.328944],"type":"Point"}
}