{
  "type": "Feature",
  "properties": {
    "iso:country":"US",
    "sg:address":"5054 Heights Ravenna Rd",
    "sg:city":"Fruitport",
    "sg:classifiers":[
        {
            "category":"Social Services",
            "subcategory":"Child Care",
            "type":"Services"
        }
    ],
    "sg:phone":"+1 231 788 5152",
    "sg:postcode":"49415",
    "sg:province":"MI",
    "sg:tags":[
        "day",
        "provider"
    ],
    "wof:name":"Home Away From Home Child Care",
    "wof:placetype":"venue"
},
  "geometry": {"coordinates":[-86.10817299999999,43.190772],"type":"Point"}
}