{
  "type": "Feature",
  "properties": {
    "iso:country":"US",
    "sg:address":"1386 Mall Dr",
    "sg:city":"Benton Harbor",
    "sg:classifiers":[
        {
            "category":"Shopping",
            "subcategory":"Department Store",
            "type":"Retail Goods"
        }
    ],
    "sg:phone":"+1 269 926 1676",
    "sg:postcode":"49022",
    "sg:province":"MI",
    "sg:tags":[
        "shop"
    ],
    "sg:website":"www.dollartreestores.com",
    "wof:name":"Dollar Tree",
    "wof:placetype":"venue"
},
  "geometry": {"coordinates":[-86.423947,42.079717],"type":"Point"}
}