{
  "type": "Feature",
  "properties": {
    "iso:country":"US",
    "sg:address":"18616 Allen Rd",
    "sg:city":"Melvindale",
    "sg:classifiers":[
        {
            "category":"Organizations",
            "subcategory":"Community Association",
            "type":"Services"
        }
    ],
    "sg:phone":"+1 313 381 3434",
    "sg:postcode":"48122",
    "sg:province":"MI",
    "sg:tags":[
        "venue",
        "event",
        "space"
    ],
    "sg:website":"www.sloveneamericanclub.com",
    "wof:name":"Slovene American Club",
    "wof:placetype":"venue"
},
  "geometry": {"coordinates":[-83.189499,42.2799],"type":"Point"}
}