{
  "type": "Feature",
  "properties": {
    "iso:country":"US",
    "sg:address":"3112 Daggitt Dr",
    "sg:city":"Spring Arbor",
    "sg:classifiers":[
        {
            "category":"Professional",
            "subcategory":"Business Services",
            "type":"Services"
        }
    ],
    "sg:phone":"+1 517 750 3251",
    "sg:postcode":"49283",
    "sg:province":"MI",
    "wof:name":"Advanced Digital Technologies",
    "wof:placetype":"venue"
},
  "geometry": {"coordinates":[-84.525436,42.21812],"type":"Point"}
}