{
  "type": "Feature",
  "properties": {
    "iso:country":"US",
    "sg:address":"980 Cypress Dr",
    "sg:city":"Jenison",
    "sg:classifiers":[
        {
            "category":"Professional",
            "subcategory":"Business Services",
            "type":"Services"
        }
    ],
    "sg:phone":"+1 616 240 4970",
    "sg:postcode":"49428",
    "sg:province":"MI",
    "wof:name":"Smith Brandy",
    "wof:placetype":"venue"
},
  "geometry": {"coordinates":[-85.807931,42.915864],"type":"Point"}
}