{
  "type": "Feature",
  "properties": {
    "iso:country":"US",
    "sg:address":"1827 Whitmore Ave NW",
    "sg:city":"Grand Rapids",
    "sg:classifiers":[
        {
            "category":"Professional",
            "subcategory":"Business Services",
            "type":"Services"
        }
    ],
    "sg:phone":"+1 616 453 3476",
    "sg:postcode":"49534",
    "sg:province":"MI",
    "sg:tags":[
        "embroidery"
    ],
    "wof:name":"J & B Embroidery",
    "wof:placetype":"venue"
},
  "geometry": {"coordinates":[-85.746538,42.998952],"type":"Point"}
}