{
  "type": "Feature",
  "properties": {
    "iso:country":"US",
    "sg:address":"4408 Hancock Dr",
    "sg:city":"Midland",
    "sg:classifiers":[
        {
            "category":"Communications",
            "subcategory":"Film & Video Production",
            "type":"Services"
        }
    ],
    "sg:phone":"+1 989 633 9204",
    "sg:postcode":"48642",
    "sg:province":"MI",
    "sg:tags":[
        "motion"
    ],
    "wof:name":"Rebant Productions",
    "wof:placetype":"venue"
},
  "geometry": {"coordinates":[-84.174302,43.615306],"type":"Point"}
}