{
  "type": "Feature",
  "properties": {
    "iso:country":"US",
    "sg:address":"603 Heritage Dr",
    "sg:city":"Milford",
    "sg:classifiers":[
        {
            "category":"Wholesale",
            "subcategory":"Machinery & Supplies",
            "type":"Manufacturing & Wholesale Goods"
        }
    ],
    "sg:phone":"+1 248 685 7879",
    "sg:postcode":"48381",
    "sg:province":"MI",
    "wof:name":"R & J Machinery Sales Inc",
    "wof:placetype":"venue"
},
  "geometry": {"coordinates":[-83.61161199999999,42.573391],"type":"Point"}
}