{
  "type": "Feature",
  "properties": {
    "iso:country":"US",
    "sg:address":"2390 Miami Beach Dr",
    "sg:city":"Flint",
    "sg:classifiers":[
        {
            "category":"Banks & Credit Unions",
            "subcategory":"Financial Services",
            "type":"Services"
        }
    ],
    "sg:phone":"+1 810 733 8715",
    "sg:postcode":"48507",
    "sg:province":"MI",
    "sg:tags":[
        "trust",
        "management"
    ],
    "wof:name":"Lisa Putman Memorial Fund",
    "wof:placetype":"venue"
},
  "geometry": {"coordinates":[-83.77032199999999,42.991579],"type":"Point"}
}