{
  "type": "Feature",
  "properties": {
    "iso:country":"US",
    "sg:address":"5809 Laparte Dr",
    "sg:city":"Lansing",
    "sg:classifiers":[
        {
            "category":"Social Services",
            "subcategory":"Child Care",
            "type":"Services"
        }
    ],
    "sg:phone":"+1 517 394 2467",
    "sg:postcode":"48911",
    "sg:province":"MI",
    "sg:tags":[
        "day",
        "provider"
    ],
    "wof:name":"Michele Gauthier",
    "wof:placetype":"venue"
},
  "geometry": {"coordinates":[-84.551163,42.673426],"type":"Point"}
}