{
  "type": "Feature",
  "properties": {
    "iso:country":"US",
    "sg:address":"811 Saginaw St",
    "sg:city":"Bay City",
    "sg:classifiers":[
        {
            "category":"Personal",
            "type":"Services"
        }
    ],
    "sg:phone":"+1 989 894 6005",
    "sg:postcode":"48708",
    "sg:province":"MI",
    "sg:tags":[
        "therapist",
        "massage"
    ],
    "wof:name":"Certified Massage Therapy",
    "wof:placetype":"venue"
},
  "geometry": {"coordinates":[-83.88886100000001,43.599085],"type":"Point"}
}