{
  "type": "Feature",
  "properties": {
    "iso:country":"US",
    "sg:address":"9201 Bedford St",
    "sg:city":"Detroit",
    "sg:classifiers":[
        {
            "category":"Personal",
            "subcategory":"Beauty Salon",
            "type":"Services"
        }
    ],
    "sg:phone":"+1 313 640 5718",
    "sg:postcode":"48224",
    "sg:province":"MI",
    "sg:tags":[
        "shop"
    ],
    "wof:name":"Cassie Braids & Others",
    "wof:placetype":"venue"
},
  "geometry": {"coordinates":[-82.946876,42.410909],"type":"Point"}
}