{
  "type": "Feature",
  "properties": {
    "iso:country":"US",
    "sg:address":"524 W 7 Mile Rd",
    "sg:city":"Highland Park",
    "sg:classifiers":[
        {
            "category":"Restaurant",
            "type":"Food & Drink"
        }
    ],
    "sg:phone":"+1 313 368 5400",
    "sg:postcode":"48203",
    "sg:province":"MI",
    "wof:name":"Bahi Restaurant",
    "wof:placetype":"venue"
},
  "geometry": {"coordinates":[-83.108704,42.432301],"type":"Point"}
}