{
  "type": "Feature",
  "properties": {
    "iso:country":"US",
    "sg:address":"1020 Krust Dr",
    "sg:city":"Owosso",
    "sg:classifiers":[
        {
            "category":"Professional",
            "subcategory":"Management & Consulting",
            "type":"Services"
        }
    ],
    "sg:phone":"+1 989 725 2296",
    "sg:postcode":"48867",
    "sg:province":"MI",
    "sg:tags":[
        "packaging"
    ],
    "wof:name":"Packaging Design Plus Inc",
    "wof:placetype":"venue"
},
  "geometry": {"coordinates":[-84.16160000000001,43.008405],"type":"Point"}
}