{
  "type": "Feature",
  "properties": {
    "iso:country":"US",
    "sg:address":"2321 Pine Grove Ave",
    "sg:city":"Port Huron",
    "sg:classifiers":[
        {
            "category":"Professional",
            "type":"Services"
        }
    ],
    "sg:phone":"+1 810 966 8129",
    "sg:postcode":"48060",
    "sg:province":"MI",
    "sg:tags":[
        "establishment"
    ],
    "wof:name":"Air Express",
    "wof:placetype":"venue"
},
  "geometry": {"coordinates":[-82.436533,42.99805],"type":"Point"}
}