{
  "type": "Feature",
  "properties": {
    "iso:country":"US",
    "sg:address":"200 Fairbanks St",
    "sg:city":"Iron Mountain",
    "sg:classifiers":[
        {
            "category":"Health Services",
            "subcategory":"Chiropractor",
            "type":"Services"
        }
    ],
    "sg:phone":"+1 906 774 5824",
    "sg:postcode":"49801",
    "sg:province":"MI",
    "wof:name":"Adam Chiropractic Ctr",
    "wof:placetype":"venue"
},
  "geometry": {"coordinates":[-88.071844,45.825416],"type":"Point"}
}