{
  "type": "Feature",
  "properties": {
    "iso:country":"US",
    "sg:address":"23382 Linne St",
    "sg:city":"Clinton Twp",
    "sg:classifiers":[
        {
            "category":"Shopping",
            "subcategory":"Crafts & Fabrics",
            "type":"Retail Goods"
        }
    ],
    "sg:phone":"+1 586 792 0929",
    "sg:postcode":"48035",
    "sg:province":"MI",
    "sg:tags":[
        "material",
        "needlework",
        "sewing"
    ],
    "wof:name":"Mernie's Creations",
    "wof:placetype":"venue"
},
  "geometry": {"coordinates":[-82.87994,42.565191],"type":"Point"}
}