{
  "type": "Feature",
  "properties": {
    "iso:country":"US",
    "sg:address":"2905 Hilton Rd",
    "sg:city":"Ferndale",
    "sg:classifiers":[
        {
            "category":"Professional",
            "subcategory":"Testing Lab",
            "type":"Services"
        },
        {
            "category":"Professional",
            "subcategory":"Research",
            "type":"Services"
        }
    ],
    "sg:phone":"+1 248 591 6660",
    "sg:postcode":"48220",
    "sg:province":"MI",
    "sg:tags":[
        "independent",
        "environmental",
        "ecological",
        "analytical",
        "laboratory",
        "chemist"
    ],
    "wof:name":"Midwest Analytical Services",
    "wof:placetype":"venue"
},
  "geometry": {"coordinates":[-83.12361900000001,42.471493],"type":"Point"}
}