{
  "type": "Feature",
  "properties": {
    "iso:country":"US",
    "sg:address":"1012 Maycroft Rd",
    "sg:city":"Lansing",
    "sg:classifiers":[
        {
            "category":"Building & Trades",
            "subcategory":"Cleaning & Sanitation",
            "type":"Services"
        }
    ],
    "sg:phone":"+1 517 321 6562",
    "sg:postcode":"48917",
    "sg:province":"MI",
    "sg:tags":[
        "maintenance"
    ],
    "wof:name":"TBG Cleaning Services",
    "wof:placetype":"venue"
},
  "geometry": {"coordinates":[-84.616708,42.746285],"type":"Point"}
}