{
  "type": "Feature",
  "properties": {
    "iso:country":"US",
    "sg:address":"4515 Imlay City Rd",
    "sg:city":"Attica",
    "sg:classifiers":[
        {
            "category":"Banks & Credit Unions",
            "subcategory":"Bank",
            "type":"Services"
        }
    ],
    "sg:phone":"+1 810 724 6436",
    "sg:postcode":"48412",
    "sg:province":"MI",
    "wof:name":"Lapeer County Bank & Trust Co",
    "wof:placetype":"venue"
},
  "geometry": {"coordinates":[-83.164841,43.047283],"type":"Point"}
}