{
  "type": "Feature",
  "properties": {
    "iso:country":"US",
    "sg:address":"5100 Jackson Rd",
    "sg:city":"Ann Arbor",
    "sg:classifiers":[
        {
            "category":"Personal",
            "subcategory":"Beauty Salon",
            "type":"Services"
        }
    ],
    "sg:phone":"+1 734 669 0087",
    "sg:postcode":"48103",
    "sg:province":"MI",
    "sg:tags":[
        "spa"
    ],
    "wof:name":"Cypress Spa",
    "wof:placetype":"venue"
},
  "geometry": {"coordinates":[-83.828748,42.287308],"type":"Point"}
}