{
  "type": "Feature",
  "properties": {
    "iso:country":"US",
    "sg:address":"2976 Fruit St",
    "sg:city":"Algonac",
    "sg:classifiers":[
        {
            "category":"Building & Trades",
            "subcategory":"Construction",
            "type":"Services"
        }
    ],
    "sg:phone":"+1 586 725 7017",
    "sg:postcode":"48001",
    "sg:province":"MI",
    "sg:tags":[
        "house",
        "c",
        "hanging",
        "contractor"
    ],
    "wof:name":"D&R Painting",
    "wof:placetype":"venue"
},
  "geometry": {"coordinates":[-82.552813,42.623256],"type":"Point"}
}