{
  "type": "Feature",
  "properties": {
    "iso:country":"US",
    "sg:address":"337 State St",
    "sg:city":"Boyne City",
    "sg:classifiers":[
        {
            "category":"Social Services",
            "type":"Services"
        }
    ],
    "sg:phone":"+1 231 582 6406",
    "sg:postcode":"49712",
    "sg:province":"MI",
    "wof:name":"Roman Cthlic Dcese Grnd Rapids",
    "wof:placetype":"venue"
},
  "geometry": {"coordinates":[-85.00932299999999,45.216174],"type":"Point"}
}