{
  "type": "Feature",
  "properties": {
    "iso:country":"US",
    "sg:address":"9979 Weber St",
    "sg:city":"Brighton",
    "sg:classifiers":[
        {
            "category":"Autos & Motor Vehicles",
            "subcategory":"Auto Supplies",
            "type":"Retail Goods"
        },
        {
            "category":"Autos & Motor Vehicles",
            "subcategory":"Motorcycle Sales",
            "type":"Retail Goods"
        },
        {
            "category":"Autos & Motor Vehicles",
            "subcategory":"Recreational Vehicle Sales",
            "type":"Retail Goods"
        },
        {
            "category":"Retail",
            "subcategory":"Auto Repair",
            "type":"Services"
        }
    ],
    "sg:phone":"+1 810 229 2746",
    "sg:postcode":"48116",
    "sg:province":"MI",
    "sg:tags":[
        "body",
        "antique",
        "motorcycles-customizing",
        "classic",
        "automobile",
        "part",
        "customizing",
        "car",
        "painting",
        "repairing",
        "restoration-antique"
    ],
    "sg:website":"http://www.bodybymark1.com",
    "wof:name":"Body By Mark LLC",
    "wof:placetype":"venue"
},
  "geometry": {"coordinates":[-83.75958,42.522166],"type":"Point"}
}