{
  "type": "Feature",
  "properties": {
    "iso:country":"US",
    "sg:address":"215 E Main St SE",
    "sg:city":"Lowell",
    "sg:classifiers":[
        {
            "category":"Home & Garden",
            "subcategory":"Home Furnishings",
            "type":"Retail Goods"
        }
    ],
    "sg:phone":"+1 616 897 8702",
    "sg:postcode":"49331",
    "sg:province":"MI",
    "sg:tags":[
        "bathroom",
        "ware",
        "design",
        "kitchen"
    ],
    "wof:name":"Hearthstone Design Studio LLC",
    "wof:placetype":"venue"
},
  "geometry": {"coordinates":[-85.337052,42.934681],"type":"Point"}
}