{
  "type": "Feature",
  "properties": {
    "iso:country":"US",
    "sg:address":"203 S 3rd Ave",
    "sg:city":"Big Rapids",
    "sg:classifiers":[
        {
            "category":"Professional",
            "subcategory":"Lawyer & Legal Services",
            "type":"Services"
        }
    ],
    "sg:phone":"+1 231 796 4878",
    "sg:postcode":"49307",
    "sg:province":"MI",
    "sg:tags":[
        "attorney"
    ],
    "wof:name":"Western Michigan Legal Svc",
    "wof:placetype":"venue"
},
  "geometry": {"coordinates":[-85.472172,43.699454],"type":"Point"}
}