{
  "type": "Feature",
  "properties": {
    "iso:country":"US",
    "sg:address":"1721 Timberlane Ln NE",
    "sg:city":"Grand Rapids",
    "sg:classifiers":[
        {
            "category":"Professional",
            "subcategory":"Business Services",
            "type":"Services"
        }
    ],
    "sg:phone":"+1 616 364 9066",
    "sg:postcode":"49505",
    "sg:province":"MI",
    "sg:tags":[
        "notary",
        "public"
    ],
    "wof:name":"De Wolf Realty",
    "wof:placetype":"venue"
},
  "geometry": {"coordinates":[-85.626086,43.005337],"type":"Point"}
}