{
  "type": "Feature",
  "properties": {
    "iso:country":"US",
    "sg:address":"27276 Novi Rd",
    "sg:city":"Novi",
    "sg:classifiers":[
        {
            "category":"Shopping",
            "subcategory":"Clothing, Apparel, & Fashions",
            "type":"Retail Goods"
        }
    ],
    "sg:phone":"+1 248 465 1806",
    "sg:postcode":"48377",
    "sg:province":"MI",
    "sg:tags":[
        "infant",
        "wear"
    ],
    "wof:name":"Limited Too",
    "wof:placetype":"venue"
},
  "geometry": {"coordinates":[-83.475932,42.488721],"type":"Point"}
}