{
  "type": "Feature",
  "properties": {
    "iso:country":"US",
    "sg:address":"14200 Frazho Rd",
    "sg:city":"Warren",
    "sg:classifiers":[
        {
            "category":"Manufacturing",
            "subcategory":"Tools & Machinery",
            "type":"Manufacturing & Wholesale Goods"
        }
    ],
    "sg:phone":"+1 586 779 7914",
    "sg:postcode":"48089",
    "sg:province":"MI",
    "sg:tags":[
        "automatic"
    ],
    "wof:name":"Con-Syst-Int Group Inc",
    "wof:placetype":"venue"
},
  "geometry": {"coordinates":[-82.97889600000001,42.485983],"type":"Point"}
}