{
  "type": "Feature",
  "properties": {
    "iso:country":"US",
    "sg:address":"715 N Old Mackinaw Rd",
    "sg:city":"Cheboygan",
    "sg:classifiers":[
        {
            "category":"Professional",
            "subcategory":"Business Services",
            "type":"Services"
        }
    ],
    "sg:phone":"+1 231 597 9332",
    "sg:postcode":"49721",
    "sg:province":"MI",
    "wof:name":"Sheldon Enterprises",
    "wof:placetype":"venue"
},
  "geometry": {"coordinates":[-84.506156,45.659593],"type":"Point"}
}