{
  "type": "Feature",
  "properties": {
    "iso:country":"US",
    "sg:address":"5402 E Lincoln Creek Rd",
    "sg:city":"Luther",
    "sg:classifiers":[
        {
            "category":"Building & Trades",
            "subcategory":"Construction",
            "type":"Services"
        }
    ],
    "sg:phone":"+1 231 797 9079",
    "sg:postcode":"49656",
    "sg:province":"MI",
    "sg:tags":[
        "general",
        "contractor"
    ],
    "wof:name":"Little River Construction",
    "wof:placetype":"venue"
},
  "geometry": {"coordinates":[-85.69263599999999,44.034665],"type":"Point"}
}