{
  "type": "Feature",
  "properties": {
    "iso:country":"US",
    "sg:address":"11942 Main St",
    "sg:city":"Lennon",
    "sg:classifiers":[
        {
            "category":"Personal",
            "subcategory":"Beauty Salon",
            "type":"Services"
        }
    ],
    "sg:phone":"+1 810 621 4880",
    "sg:postcode":"48463",
    "sg:province":"MI",
    "wof:name":"A Head A Time",
    "wof:placetype":"venue"
},
  "geometry": {"coordinates":[-83.48100599999999,43.165878],"type":"Point"}
}