{
  "type": "Feature",
  "properties": {
    "iso:country":"US",
    "sg:address":"1629 E Huron Rd",
    "sg:city":"Omer",
    "sg:classifiers":[
        {
            "category":"Building & Trades",
            "subcategory":"Construction",
            "type":"Services"
        }
    ],
    "sg:phone":"+1 989 876 8381",
    "sg:postcode":"48749",
    "sg:province":"MI",
    "sg:tags":[
        "excavating",
        "contractor"
    ],
    "wof:name":"C Woods Trucking & Excavating",
    "wof:placetype":"venue"
},
  "geometry": {"coordinates":[-83.742774,44.048227],"type":"Point"}
}