{
  "type": "Feature",
  "properties": {
    "iso:country":"US",
    "sg:address":"321 Ottawa Dr",
    "sg:city":"Oscoda",
    "sg:classifiers":[
        {
            "category":"Real Estate",
            "subcategory":"Real Estate Agent",
            "type":"Services"
        }
    ],
    "sg:phone":"+1 989 739 2396",
    "sg:postcode":"48750",
    "sg:province":"MI",
    "wof:name":"Mg Properties Inc",
    "wof:placetype":"venue"
},
  "geometry": {"coordinates":[-83.335246,44.423677],"type":"Point"}
}