{
  "type": "Feature",
  "properties": {
    "iso:country":"US",
    "sg:address":"22175 Coolidge Hwy",
    "sg:city":"Oak Park",
    "sg:classifiers":[
        {
            "category":"Shopping",
            "subcategory":"Bridal",
            "type":"Retail Goods"
        }
    ],
    "sg:phone":"+1 248 399 8887",
    "sg:postcode":"48237",
    "sg:province":"MI",
    "sg:website":"www.elegantlady.com/",
    "wof:name":"Elegant Lady",
    "wof:placetype":"venue"
},
  "geometry": {"coordinates":[-83.181904,42.457763],"type":"Point"}
}