{
  "type": "Feature",
  "properties": {
    "iso:country":"US",
    "sg:address":"32053 E Red Arrow Hwy",
    "sg:city":"Paw Paw",
    "sg:classifiers":[
        {
            "category":"Wholesale",
            "subcategory":"Office Equipment",
            "type":"Manufacturing & Wholesale Goods"
        }
    ],
    "sg:phone":"+1 269 655 1566",
    "sg:postcode":"49079",
    "sg:province":"MI",
    "sg:tags":[
        "credit",
        "system",
        "card"
    ],
    "wof:name":"New Concept Marketing",
    "wof:placetype":"venue"
},
  "geometry": {"coordinates":[-85.86274,42.221811],"type":"Point"}
}