{
  "type": "Feature",
  "properties": {
    "iso:country":"US",
    "sg:address":"2750 Lauria Rd",
    "sg:city":"Midland",
    "sg:classifiers":[
        {
            "category":"Sports & Exercise",
            "subcategory":"Golf",
            "type":"Entertainment"
        }
    ],
    "sg:phone":"+1 989 631 6010",
    "sg:postcode":"48642",
    "sg:province":"MI",
    "sg:tags":[
        "course"
    ],
    "sg:website":"www.golfsandyridge.com",
    "wof:name":"Sandy Ridge Golf Course",
    "wof:placetype":"venue"
},
  "geometry": {"coordinates":[-84.158007,43.6616],"type":"Point"}
}