{
  "type": "Feature",
  "properties": {
    "iso:country":"US",
    "sg:address":"13380 Capital St",
    "sg:city":"Oak Park",
    "sg:classifiers":[
        {
            "category":"Wholesale",
            "subcategory":"Durable Goods & Equipment",
            "type":"Manufacturing & Wholesale Goods"
        }
    ],
    "sg:phone":"+1 248 543 0095",
    "sg:postcode":"48237",
    "sg:province":"MI",
    "sg:tags":[
        "representative",
        "manufacturer"
    ],
    "sg:website":"www.fontanesi-kann.com",
    "wof:name":"Fontanesi & KANN Co",
    "wof:placetype":"venue"
},
  "geometry": {"coordinates":[-83.179254,42.455058],"type":"Point"}
}