{
  "type": "Feature",
  "properties": {
    "iso:country":"US",
    "sg:address":"8818 Lake Bluff Dr",
    "sg:city":"Brighton",
    "sg:classifiers":[
        {
            "category":"Professional",
            "type":"Services"
        }
    ],
    "sg:phone":"+1 810 220 4943",
    "sg:postcode":"48114",
    "sg:province":"MI",
    "wof:name":"Fresh Sports & Svcs LLC",
    "wof:placetype":"venue"
},
  "geometry": {"coordinates":[-83.772679,42.558789],"type":"Point"}
}