{
  "type": "Feature",
  "properties": {
    "iso:country":"US",
    "sg:address":"43422 W Oaks Dr",
    "sg:city":"Novi",
    "sg:classifiers":[
        {
            "category":"Organizations",
            "subcategory":"Professional Association",
            "type":"Services"
        }
    ],
    "sg:phone":"+1 810 231 2502",
    "sg:postcode":"48377",
    "sg:province":"MI",
    "sg:tags":[
        "trade"
    ],
    "wof:name":"American Welding Soc Detroit",
    "wof:placetype":"venue"
},
  "geometry": {"coordinates":[-83.47649199999999,42.491184],"type":"Point"}
}