{
  "type": "Feature",
  "properties": {
    "iso:country":"US",
    "sg:address":"5044 John R Rd",
    "sg:city":"Troy",
    "sg:classifiers":[
        {
            "category":"Retail",
            "subcategory":"Animal Services",
            "type":"Services"
        }
    ],
    "sg:phone":"+1 248 689 7660",
    "sg:postcode":"48085",
    "sg:province":"MI",
    "sg:tags":[
        "boarding",
        "pet",
        "boarding/pet",
        "sitting"
    ],
    "wof:name":"R & R Kennels",
    "wof:placetype":"venue"
},
  "geometry": {"coordinates":[-83.10929899999999,42.593201],"type":"Point"}
}