{
  "type": "Feature",
  "properties": {
    "iso:country":"US",
    "sg:address":"10460 Peninsula Dr",
    "sg:city":"Traverse City",
    "sg:classifiers":[
        {
            "category":"Organizations",
            "subcategory":"Non-profit Organization",
            "type":"Services"
        }
    ],
    "sg:phone":"+1 231 922 0518",
    "sg:postcode":"49686",
    "sg:province":"MI",
    "sg:tags":[
        "social"
    ],
    "wof:name":"Peninsula Coupons",
    "wof:placetype":"venue"
},
  "geometry": {"coordinates":[-85.560676,44.838862],"type":"Point"}
}