{
  "type": "Feature",
  "properties": {
    "iso:country":"US",
    "sg:address":"3754 Lacey Rd",
    "sg:city":"Bellevue",
    "sg:classifiers":[
        {
            "category":"Education",
            "subcategory":"School",
            "type":"Public Place"
        }
    ],
    "sg:phone":"+1 269 758 3361",
    "sg:postcode":"49050",
    "sg:province":"MI",
    "wof:name":"Pleasantview Elementary School",
    "wof:placetype":"venue"
},
  "geometry": {"coordinates":[-85.209762,42.493238],"type":"Point"}
}