{
  "type": "Feature",
  "properties": {
    "iso:country":"US",
    "sg:address":"1115 W John Beers Rd",
    "sg:city":"Stevensville",
    "sg:classifiers":[
        {
            "category":"Shopping",
            "subcategory":"Gifts & Souvenirs",
            "type":"Retail Goods"
        }
    ],
    "sg:phone":"+1 269 428 2391",
    "sg:postcode":"49127",
    "sg:province":"MI",
    "wof:name":"Natures Natural Gifts",
    "wof:placetype":"venue"
},
  "geometry": {"coordinates":[-86.484816,42.014542],"type":"Point"}
}