{
  "type": "Feature",
  "properties": {
    "iso:country":"US",
    "sg:address":"35625 Johnstown Rd",
    "sg:city":"Farmington Hills",
    "sg:classifiers":[
        {
            "category":"Professional",
            "type":"Services"
        },
        {
            "category":"Organizations",
            "subcategory":"Community Association",
            "type":"Services"
        }
    ],
    "sg:phone":"+1 248 477 1360",
    "sg:postcode":"48335",
    "sg:province":"MI",
    "sg:tags":[
        "establishment"
    ],
    "wof:name":"Rare Bird Alert of Detroit",
    "wof:placetype":"venue"
},
  "geometry": {"coordinates":[-83.401439,42.476892],"type":"Point"}
}