{
  "type": "Feature",
  "properties": {
    "iso:country":"US",
    "sg:address":"4328 Livernois Rd",
    "sg:city":"Troy",
    "sg:classifiers":[
        {
            "category":"Organizations",
            "subcategory":"Religious Organization",
            "type":"Services"
        }
    ],
    "sg:phone":"+1 248 689 0112",
    "sg:postcode":"48098",
    "sg:province":"MI",
    "sg:tags":[
        "church"
    ],
    "wof:name":"First Presbyterian Church Troy",
    "wof:placetype":"venue"
},
  "geometry": {"coordinates":[-83.14851,42.581742],"type":"Point"}
}