{
  "type": "Feature",
  "properties": {
    "iso:country":"US",
    "sg:address":"964 N Adams Rd",
    "sg:city":"Birmingham",
    "sg:classifiers":[
        {
            "category":"Education",
            "subcategory":"Library",
            "type":"Public Place"
        }
    ],
    "sg:phone":"+1 248 258 6721",
    "sg:postcode":"48009",
    "sg:province":"MI",
    "wof:name":"Library Dust Consulting LLC",
    "wof:placetype":"venue"
},
  "geometry": {"coordinates":[-83.206104,42.554558],"type":"Point"}
}