{
  "type": "Feature",
  "properties": {
    "iso:country":"US",
    "sg:address":"2327 Beechwood Dr",
    "sg:city":"Royal Oak",
    "sg:classifiers":[
        {
            "category":"Building & Trades",
            "subcategory":"Construction",
            "type":"Services"
        }
    ],
    "sg:phone":"+1 248 585 8250",
    "sg:postcode":"48073",
    "sg:province":"MI",
    "sg:tags":[
        "contractor"
    ],
    "wof:name":"Camelot Building & Dev",
    "wof:placetype":"venue"
},
  "geometry": {"coordinates":[-83.152626,42.509447],"type":"Point"}
}