{
  "type": "Feature",
  "properties": {
    "iso:country":"US",
    "sg:address":"18505 92nd Ave",
    "sg:city":"Coopersville",
    "sg:classifiers":[
        {
            "category":"Real Estate",
            "subcategory":"Real Estate Operator",
            "type":"Services"
        }
    ],
    "sg:phone":"+1 616 837 8277",
    "sg:postcode":"49404",
    "sg:province":"MI",
    "sg:tags":[
        "building",
        "apartment"
    ],
    "wof:name":"University Apartments",
    "wof:placetype":"venue"
},
  "geometry": {"coordinates":[-86.01721499999999,43.106293],"type":"Point"}
}