{
  "type": "Feature",
  "properties": {
    "iso:country":"US",
    "sg:address":"5227 Auburn Rd",
    "sg:city":"Shelby Twp",
    "sg:classifiers":[
        {
            "category":"Wholesale",
            "subcategory":"Hardware",
            "type":"Manufacturing & Wholesale Goods"
        }
    ],
    "sg:phone":"+1 586 731 4000",
    "sg:postcode":"48317",
    "sg:province":"MI",
    "sg:tags":[
        "plumbing",
        "fixture",
        "supply"
    ],
    "sg:website":"www.nuwaysupply.com",
    "wof:name":"Nu-Way Supply Kitchen & Bath",
    "wof:placetype":"venue"
},
  "geometry": {"coordinates":[-83.05861899999999,42.638518],"type":"Point"}
}