{
  "type": "Feature",
  "properties": {
    "iso:country":"US",
    "sg:address":"3301 E 8 Mile Rd",
    "sg:city":"Warren",
    "sg:classifiers":[
        {
            "category":"Wholesale",
            "subcategory":"Machinery & Supplies",
            "type":"Manufacturing & Wholesale Goods"
        }
    ],
    "sg:phone":"+1 586 771 1662",
    "sg:postcode":"48234",
    "sg:province":"MI",
    "wof:name":"GCH Machinery",
    "wof:placetype":"venue"
},
  "geometry": {"coordinates":[-83.07082699999999,42.447103],"type":"Point"}
}