{
  "type": "Feature",
  "properties": {
    "iso:country":"US",
    "sg:address":"15400 W 10 Mile Rd",
    "sg:city":"Oak Park",
    "sg:classifiers":[
        {
            "category":"Place Of Worship",
            "subcategory":"Synagogue",
            "type":"Public Place"
        }
    ],
    "sg:phone":"+1 248 967 3969",
    "sg:postcode":"48237",
    "sg:province":"MI",
    "wof:name":"Congregation B'nai Israel Beth'yehudah",
    "wof:placetype":"venue"
},
  "geometry": {"coordinates":[-83.20059999999999,42.473999],"type":"Point"}
}