{
  "type": "Feature",
  "properties": {
    "iso:country":"US",
    "sg:address":"5070 E N Ave",
    "sg:city":"Kalamazoo",
    "sg:classifiers":[
        {
            "category":"Wholesale",
            "subcategory":"Machinery & Supplies",
            "type":"Manufacturing & Wholesale Goods"
        }
    ],
    "sg:phone":"+1 269 388 8762",
    "sg:postcode":"49048",
    "sg:province":"MI",
    "sg:tags":[
        "valve"
    ],
    "wof:name":"Koganei LTD",
    "wof:placetype":"venue"
},
  "geometry": {"coordinates":[-85.530018,42.244857],"type":"Point"}
}