{
  "type": "Feature",
  "properties": {
    "iso:country":"US",
    "sg:address":"6800 S Westnedge Ave",
    "sg:city":"Portage",
    "sg:classifiers":[
        {
            "category":"Shopping",
            "subcategory":"Computers & Home Electronics",
            "type":"Retail Goods"
        }
    ],
    "sg:phone":"+1 269 324 0665",
    "sg:postcode":"49002",
    "sg:province":"MI",
    "sg:tags":[
        "high",
        "fidelity",
        "stereophonic"
    ],
    "sg:website":"www.classicstereo.com",
    "wof:name":"Classic Stereo & Video",
    "wof:placetype":"venue"
},
  "geometry": {"coordinates":[-85.58942999999999,42.219443],"type":"Point"}
}