{
  "type": "Feature",
  "properties": {
    "iso:country":"US",
    "sg:address":"7135 Whiteford Center Rd",
    "sg:city":"Lambertville",
    "sg:classifiers":[
        {
            "category":"Autos & Motor Vehicles",
            "subcategory":"Automobile Sales",
            "type":"Retail Goods"
        },
        {
            "category":"Autos & Motor Vehicles",
            "subcategory":"Auto Supplies",
            "type":"Retail Goods"
        }
    ],
    "sg:phone":"+1 734 856 7223",
    "sg:postcode":"48144",
    "sg:province":"MI",
    "sg:tags":[
        "car",
        "dealer"
    ],
    "wof:name":"Ron Miller Race Cars Inc",
    "wof:placetype":"venue"
},
  "geometry": {"coordinates":[-83.64931799999999,41.744163],"type":"Point"}
}