{
  "type": "Feature",
  "properties": {
    "iso:country":"US",
    "sg:address":"108 Church St",
    "sg:city":"Tustin",
    "sg:classifiers":[
        {
            "category":"Organizations",
            "subcategory":"Religious Organization",
            "type":"Services"
        }
    ],
    "sg:phone":"+1 231 829 3833",
    "sg:postcode":"49688",
    "sg:province":"MI",
    "sg:tags":[
        "church"
    ],
    "wof:name":"Covenant Presbyterian Church",
    "wof:placetype":"venue"
},
  "geometry": {"coordinates":[-85.45956099999999,44.102862],"type":"Point"}
}