{
  "type": "Feature",
  "properties": {
    "iso:country":"US",
    "sg:address":"306 Johnson St",
    "sg:city":"Jackson",
    "sg:classifiers":[
        {
            "category":"Arts & Performance",
            "subcategory":"Theater",
            "type":"Entertainment"
        }
    ],
    "sg:phone":"+1 517 787 2034",
    "sg:postcode":"49203",
    "sg:province":"MI",
    "sg:tags":[
        "live",
        "music"
    ],
    "sg:website":"www.espromobiledj.com",
    "wof:name":"E's Professional Mobile DJ Co",
    "wof:placetype":"venue"
},
  "geometry": {"coordinates":[-84.391616,42.245601],"type":"Point"}
}