{
  "type": "Feature",
  "properties": {
    "iso:country":"US",
    "sg:address":"3342 E Pierson Rd",
    "sg:city":"Flint",
    "sg:classifiers":[
        {
            "category":"Building & Trades",
            "subcategory":"Construction",
            "type":"Services"
        }
    ],
    "sg:phone":"+1 810 736 4128",
    "sg:postcode":"48506",
    "sg:province":"MI",
    "sg:tags":[
        "heavy"
    ],
    "wof:name":"Bieber Construction",
    "wof:placetype":"venue"
},
  "geometry": {"coordinates":[-83.65009499999999,43.061631],"type":"Point"}
}