{
  "type": "Feature",
  "properties": {
    "iso:country":"US",
    "sg:address":"749 Hombach St",
    "sg:city":"St Ignace",
    "sg:classifiers":[
        {
            "category":"Government",
            "subcategory":"Office",
            "type":"Public Place"
        }
    ],
    "sg:phone":"+1 906 643 1103",
    "sg:postcode":"49781",
    "sg:province":"MI",
    "wof:name":"Mackinac County Addictions Svc",
    "wof:placetype":"venue"
},
  "geometry": {"coordinates":[-84.712988,45.858917],"type":"Point"}
}