{
  "type": "Feature",
  "properties": {
    "iso:country":"US",
    "sg:address":"4024 Park Forest Dr",
    "sg:city":"Flint",
    "sg:classifiers":[
        {
            "category":"Professional",
            "type":"Services"
        }
    ],
    "sg:phone":"+1 810 232 2389",
    "sg:postcode":"48507",
    "sg:province":"MI",
    "wof:name":"Marys Errand Service",
    "wof:placetype":"venue"
},
  "geometry": {"coordinates":[-83.712346,42.98624],"type":"Point"}
}