{
  "type": "Feature",
  "properties": {
    "iso:country":"US",
    "sg:address":"617 Fulton St W",
    "sg:city":"Grand Rapids",
    "sg:classifiers":[
        {
            "category":"Restaurant",
            "type":"Food & Drink"
        }
    ],
    "sg:menulink":"http://www.allmenus.com/mi/grand-rapids/59195-adobe-in--out/menu/",
    "sg:phone":"+1 616 454 0279",
    "sg:postcode":"49504",
    "sg:province":"MI",
    "sg:tags":[
        "mexican"
    ],
    "wof:name":"Adobe In & Out",
    "wof:placetype":"venue"
},
  "geometry": {"coordinates":[-85.68362399999999,42.963426],"type":"Point"}
}