{
  "type": "Feature",
  "properties": {
    "iso:country":"US",
    "sg:address":"17601 Mound Rd",
    "sg:city":"Detroit",
    "sg:classifiers":[
        {
            "category":"Government",
            "subcategory":"Jail",
            "type":"Public Place"
        }
    ],
    "sg:phone":"+1 313 368 8300",
    "sg:postcode":"48212",
    "sg:province":"MI",
    "sg:tags":[
        "correctional",
        "institution"
    ],
    "wof:name":"Mound Correctional Facility",
    "wof:placetype":"venue"
},
  "geometry": {"coordinates":[-83.043404,42.423309],"type":"Point"}
}