{
  "type": "Feature",
  "properties": {
    "iso:country":"US",
    "sg:address":"2884 Brooklyn Rd",
    "sg:city":"Jackson",
    "sg:classifiers":[
        {
            "category":"Building & Trades",
            "subcategory":"Plumbing",
            "type":"Services"
        }
    ],
    "sg:phone":"+1 517 783 5100",
    "sg:postcode":"49203",
    "sg:province":"MI",
    "sg:tags":[
        "conditioning",
        "air",
        "system",
        "contractor"
    ],
    "wof:name":"Guardian Heating & AC",
    "wof:placetype":"venue"
},
  "geometry": {"coordinates":[-84.364943,42.197049],"type":"Point"}
}