{
  "type": "Feature",
  "properties": {
    "iso:country":"US",
    "sg:address":"33656 Woodward Ave",
    "sg:city":"Birmingham",
    "sg:classifiers":[
        {
            "category":"Building & Trades",
            "subcategory":"Construction",
            "type":"Services"
        }
    ],
    "sg:phone":"+1 248 644 0444",
    "sg:postcode":"48009",
    "sg:province":"MI",
    "sg:tags":[
        "woodworker"
    ],
    "wof:name":"Glenn Wing Power Tools",
    "wof:placetype":"venue"
},
  "geometry": {"coordinates":[-83.20421,42.536221],"type":"Point"}
}