{
  "type": "Feature",
  "properties": {
    "iso:country":"US",
    "sg:address":"97 S 4th St",
    "sg:city":"Ishpeming",
    "sg:classifiers":[
        {
            "category":"Health Services",
            "subcategory":"Doctor",
            "type":"Services"
        }
    ],
    "sg:phone":"+1 906 485 5571",
    "sg:postcode":"49849",
    "sg:province":"MI",
    "sg:tags":[
        "physician",
        "surgeon"
    ],
    "wof:name":"Superior Women's Care",
    "wof:placetype":"venue"
},
  "geometry": {"coordinates":[-87.663799,46.489624],"type":"Point"}
}