{
  "type": "Feature",
  "properties": {
    "iso:country":"US",
    "sg:address":"23800 Piper Ave",
    "sg:city":"Eastpointe",
    "sg:classifiers":[
        {
            "category":"Professional",
            "subcategory":"Business Services",
            "type":"Services"
        }
    ],
    "sg:phone":"+1 586 775 0846",
    "sg:postcode":"48021",
    "sg:province":"MI",
    "wof:name":"Unlimited Ventures",
    "wof:placetype":"venue"
},
  "geometry": {"coordinates":[-82.948932,42.471707],"type":"Point"}
}