{
  "type": "Feature",
  "properties": {
    "iso:country":"US",
    "sg:address":"22130 Gratiot Ave",
    "sg:city":"Eastpointe",
    "sg:classifiers":[
        {
            "category":"Retail",
            "subcategory":"Auto Repair",
            "type":"Services"
        }
    ],
    "sg:phone":"+1 586 776 7700",
    "sg:postcode":"48021",
    "sg:province":"MI",
    "wof:name":"Eastpointe Auto Clinic",
    "wof:placetype":"venue"
},
  "geometry": {"coordinates":[-82.960503,42.460201],"type":"Point"}
}