{
  "type": "Feature",
  "properties": {
    "iso:country":"US",
    "sg:address":"275 N Old Woodward Ave",
    "sg:city":"Birmingham",
    "sg:classifiers":[
        {
            "category":"Building & Trades",
            "subcategory":"Construction",
            "type":"Services"
        },
        {
            "category":"Home & Garden",
            "subcategory":"Furniture",
            "type":"Retail Goods"
        }
    ],
    "sg:phone":"+1 248 540 8558",
    "sg:postcode":"48009",
    "sg:province":"MI",
    "sg:tags":[
        "interior",
        "design",
        "store"
    ],
    "sg:website":"www.ethanallen.com",
    "wof:name":"Ethan Allen Home Interiors",
    "wof:placetype":"venue"
},
  "geometry": {"coordinates":[-83.215599,42.547901],"type":"Point"}
}