{
  "type": "Feature",
  "properties": {
    "iso:country":"US",
    "sg:address":"2780 Judah Rd",
    "sg:city":"Orion",
    "sg:classifiers":[
        {
            "category":"Building & Trades",
            "subcategory":"Construction",
            "type":"Services"
        }
    ],
    "sg:phone":"+1 248 393 0704",
    "sg:postcode":"48359",
    "sg:province":"MI",
    "sg:tags":[
        "roofing",
        "contractor"
    ],
    "wof:name":"Feliccia Construction",
    "wof:placetype":"venue"
},
  "geometry": {"coordinates":[-83.295564,42.714983],"type":"Point"}
}