{
  "type": "Feature",
  "properties": {
    "iso:country":"US",
    "sg:address":"107 S 3rd St",
    "sg:city":"Rogers City",
    "sg:classifiers":[
        {
            "category":"Autos & Motor Vehicles",
            "subcategory":"Fuel & Gas Station",
            "type":"Retail Goods"
        }
    ],
    "sg:phone":"+1 989 734 3052",
    "sg:postcode":"49779",
    "sg:province":"MI",
    "sg:tags":[
        "oil"
    ],
    "wof:name":"B & G Standard Svc",
    "wof:placetype":"venue"
},
  "geometry": {"coordinates":[-83.81558200000001,45.419315],"type":"Point"}
}