{
  "type": "Feature",
  "properties": {
    "iso:country":"US",
    "sg:address":"8045 2nd Ave",
    "sg:city":"Detroit",
    "sg:classifiers":[
        {
            "category":"Government",
            "subcategory":"Office",
            "type":"Public Place"
        }
    ],
    "sg:phone":"+1 313 876 0500",
    "sg:postcode":"48202",
    "sg:province":"MI",
    "sg:tags":[
        "general"
    ],
    "wof:name":"Nch-Northend",
    "wof:placetype":"venue"
},
  "geometry": {"coordinates":[-83.079525,42.373747],"type":"Point"}
}