{
  "type": "Feature",
  "properties": {
    "iso:country":"US",
    "sg:address":"231 N Main St",
    "sg:city":"Davison",
    "sg:classifiers":[
        {
            "category":"Professional",
            "subcategory":"Business Services",
            "type":"Services"
        }
    ],
    "sg:phone":"+1 810 658 8080",
    "sg:postcode":"48423",
    "sg:province":"MI",
    "sg:tags":[
        "interior",
        "consultant",
        "design",
        "decorator"
    ],
    "wof:name":"Farmers Daughter Inc the",
    "wof:placetype":"venue"
},
  "geometry": {"coordinates":[-83.516899,43.031601],"type":"Point"}
}