{
  "type": "Feature",
  "properties": {
    "iso:country":"US",
    "sg:address":"4800 W Saginaw Hwy",
    "sg:city":"Lansing",
    "sg:classifiers":[
        {
            "category":"Wholesale",
            "subcategory":"Office Equipment",
            "type":"Manufacturing & Wholesale Goods"
        }
    ],
    "sg:phone":"+1 517 321 1867",
    "sg:postcode":"48917",
    "sg:province":"MI",
    "sg:tags":[
        "dictating",
        "machine",
        "supply"
    ],
    "wof:name":"O'Neil & Co",
    "wof:placetype":"venue"
},
  "geometry": {"coordinates":[-84.61698699999999,42.741077],"type":"Point"}
}