{
  "type": "Feature",
  "properties": {
    "iso:country":"US",
    "sg:address":"1324 Ivywood Dr",
    "sg:city":"Okemos",
    "sg:classifiers":[
        {
            "category":"Professional",
            "subcategory":"Computer Services",
            "type":"Services"
        }
    ],
    "sg:phone":"+1 517 749 5985",
    "sg:postcode":"48864",
    "sg:province":"MI",
    "sg:tags":[
        "related"
    ],
    "wof:name":"M/M Consulting Svcs",
    "wof:placetype":"venue"
},
  "geometry": {"coordinates":[-84.396039,42.711428],"type":"Point"}
}