{
  "type": "Feature",
  "properties": {
    "iso:country":"US",
    "sg:address":"6103 W Colony Rd",
    "sg:city":"St Johns",
    "sg:classifiers":[
        {
            "category":"Personal",
            "subcategory":"Beauty Salon",
            "type":"Services"
        }
    ],
    "sg:phone":"+1 989 227 8126",
    "sg:postcode":"48879",
    "sg:province":"MI",
    "wof:name":"Kim Ferdern",
    "wof:placetype":"venue"
},
  "geometry": {"coordinates":[-84.649505,43.046201],"type":"Point"}
}