{
  "type": "Feature",
  "properties": {
    "iso:country":"US",
    "sg:address":"6815 Saint Joseph Hwy",
    "sg:city":"Grand Ledge",
    "sg:classifiers":[
        {
            "category":"Retail",
            "subcategory":"Repair Shop",
            "type":"Services"
        }
    ],
    "sg:phone":"+1 517 627 5476",
    "sg:postcode":"48890",
    "sg:province":"MI",
    "sg:tags":[
        "upholsterer"
    ],
    "wof:name":"Diversified Upholstery",
    "wof:placetype":"venue"
},
  "geometry": {"coordinates":[-84.96880899999999,42.726572],"type":"Point"}
}