{
  "type": "Feature",
  "properties": {
    "iso:country":"US",
    "sg:address":"4611 Van Dyke Rd",
    "sg:city":"Almont",
    "sg:classifiers":[
        {
            "category":"Retail",
            "subcategory":"Auto Repair",
            "type":"Services"
        },
        {
            "category":"Autos & Motor Vehicles",
            "subcategory":"Auto Supplies",
            "type":"Retail Goods"
        }
    ],
    "sg:phone":"+1 810 798 7750",
    "sg:postcode":"48003",
    "sg:province":"MI",
    "sg:tags":[
        "engine",
        "exchanging",
        "general"
    ],
    "wof:name":"Preferred Tire & Auto Inc",
    "wof:placetype":"venue"
},
  "geometry": {"coordinates":[-83.05287800000001,42.931028],"type":"Point"}
}