{
  "type": "Feature",
  "properties": {
    "iso:country":"US",
    "sg:address":"4440 Bowen Blvd SE",
    "sg:city":"Grand Rapids",
    "sg:classifiers":[
        {
            "category":"Insurance",
            "subcategory":"Hazard Insurance",
            "type":"Services"
        }
    ],
    "sg:phone":"+1 616 455 3320",
    "sg:postcode":"49508",
    "sg:province":"MI",
    "sg:tags":[
        "agency"
    ],
    "wof:name":"Charter Lakes Insurance Agency",
    "wof:placetype":"venue"
},
  "geometry": {"coordinates":[-85.62190699999999,42.881546],"type":"Point"}
}