{
  "type": "Feature",
  "properties": {
    "iso:country":"US",
    "sg:address":"50695 Chesterfield Rd",
    "sg:city":"Chesterfield",
    "sg:classifiers":[
        {
            "category":"Building & Trades",
            "subcategory":"Construction",
            "type":"Services"
        }
    ],
    "sg:phone":"+1 586 949 6370",
    "sg:postcode":"48051",
    "sg:province":"MI",
    "sg:tags":[
        "masonry",
        "contractor"
    ],
    "wof:name":"T I Group Automotive Systems",
    "wof:placetype":"venue"
},
  "geometry": {"coordinates":[-82.837945,42.66909],"type":"Point"}
}