{
  "type": "Feature",
  "properties": {
    "iso:country":"US",
    "sg:address":"193 State St",
    "sg:city":"Gwinn",
    "sg:classifiers":[
        {
            "category":"Building & Trades",
            "subcategory":"Construction",
            "type":"Services"
        }
    ],
    "sg:phone":"+1 906 346 7941",
    "sg:postcode":"49802",
    "sg:province":"MI",
    "sg:tags":[
        "contractor"
    ],
    "wof:name":"Jack Of All Trades",
    "wof:placetype":"venue"
},
  "geometry": {"coordinates":[-88.06365599999999,45.79168],"type":"Point"}
}