{
  "type": "Feature",
  "properties": {
    "iso:country":"US",
    "sg:address":"2136 Robinson Rd",
    "sg:city":"Jackson",
    "sg:classifiers":[
        {
            "category":"Health Services",
            "subcategory":"Health Practitioner",
            "type":"Services"
        }
    ],
    "sg:phone":"+1 517 750 4777",
    "sg:postcode":"49203",
    "sg:province":"MI",
    "sg:tags":[
        "pathologist",
        "speech"
    ],
    "wof:name":"Comprehensive Speech & Lanuage",
    "wof:placetype":"venue"
},
  "geometry": {"coordinates":[-84.462537,42.230784],"type":"Point"}
}