{
  "type": "Feature",
  "properties": {
    "iso:country":"US",
    "sg:address":"108 W Allegan St",
    "sg:city":"Otsego",
    "sg:classifiers":[
        {
            "category":"Personal",
            "subcategory":"Beauty Salon",
            "type":"Services"
        }
    ],
    "sg:phone":"+1 269 694 4747",
    "sg:postcode":"49078",
    "sg:province":"MI",
    "wof:name":"Conversion Point",
    "wof:placetype":"venue"
},
  "geometry": {"coordinates":[-85.698212,42.460864],"type":"Point"}
}