{
  "type": "Feature",
  "properties": {
    "iso:country":"US",
    "sg:address":"101 E M-134",
    "sg:city":"Cedarville",
    "sg:classifiers":[
        {
            "category":"Real Estate",
            "subcategory":"Real Estate Agent",
            "type":"Services"
        }
    ],
    "sg:phone":"+1 906 484 3945",
    "sg:postcode":"49719",
    "sg:province":"MI",
    "wof:name":"Schmidt Realtors",
    "wof:placetype":"venue"
},
  "geometry": {"coordinates":[-84.358565,45.999509],"type":"Point"}
}