{
  "type": "Feature",
  "properties": {
    "iso:country":"US",
    "sg:address":"106 S Old Woodward Ave Ste A",
    "sg:city":"Birmingham",
    "sg:classifiers":[
        {
            "category":"Professional",
            "subcategory":"Accounting & Tax Preparation",
            "type":"Services"
        }
    ],
    "sg:phone":"+1 248 645 5200",
    "sg:postcode":"48009",
    "sg:province":"MI",
    "sg:tags":[
        "accountant"
    ],
    "sg:website":"www.mjevco.com",
    "wof:name":"M Jevahirian & Co",
    "wof:placetype":"venue"
},
  "geometry": {"coordinates":[-83.214449,42.546486],"type":"Point"}
}