{
  "type": "Feature",
  "properties": {
    "iso:country":"US",
    "sg:address":"3180 Racquet Club Dr",
    "sg:city":"Traverse City",
    "sg:classifiers":[
        {
            "category":"Banks & Credit Unions",
            "subcategory":"Investment Brokerage",
            "type":"Services"
        }
    ],
    "sg:phone":"+1 231 929 9600",
    "sg:postcode":"49684",
    "sg:province":"MI",
    "sg:tags":[
        "consultant",
        "planning",
        "financial"
    ],
    "wof:name":"Kevin Paul Kelly & Assoc",
    "wof:placetype":"venue"
},
  "geometry": {"coordinates":[-85.61739900000001,44.732341],"type":"Point"}
}