{
  "type": "Feature",
  "properties": {
    "iso:country":"US",
    "sg:address":"3838 Livernois Rd",
    "sg:city":"Troy",
    "sg:classifiers":[
        {
            "category":"Education",
            "subcategory":"College",
            "type":"Public Place"
        }
    ],
    "sg:phone":"+1 248 689 8282",
    "sg:postcode":"48083",
    "sg:province":"MI",
    "sg:tags":[
        "academic",
        "university",
        "school"
    ],
    "sg:website":"www.walshcollege.edu",
    "wof:name":"Walsh College",
    "wof:placetype":"venue"
},
  "geometry": {"coordinates":[-83.148003,42.574001],"type":"Point"}
}