{
  "type": "Feature",
  "properties": {
    "iso:country":"US",
    "sg:address":"12891 Flynn Rd",
    "sg:city":"Sawyer",
    "sg:classifiers":[
        {
            "category":"Freight",
            "type":"Transportation"
        }
    ],
    "sg:phone":"+1 269 426 8193",
    "sg:postcode":"49125",
    "sg:province":"MI",
    "sg:tags":[
        "operator",
        "local",
        "trucking"
    ],
    "wof:name":"J M Cole Trkng",
    "wof:placetype":"venue"
},
  "geometry": {"coordinates":[-86.58976699999999,41.885617],"type":"Point"}
}