{
  "type": "Feature",
  "properties": {
    "iso:country":"US",
    "sg:address":"42420 Mound Rd",
    "sg:city":"Sterling Heights",
    "sg:classifiers":[
        {
            "category":"Wholesale",
            "subcategory":"Hardware",
            "type":"Manufacturing & Wholesale Goods"
        }
    ],
    "sg:phone":"+1 586 323 5193",
    "sg:postcode":"48314",
    "sg:province":"MI",
    "sg:tags":[
        "equipment",
        "heating",
        "system"
    ],
    "wof:name":"Van's Heating & Cooling Inc",
    "wof:placetype":"venue"
},
  "geometry": {"coordinates":[-83.051351,42.604303],"type":"Point"}
}