{
  "type": "Feature",
  "properties": {
    "iso:country":"US",
    "sg:address":"6152 Telegraph Rd",
    "sg:city":"Dearborn Heights",
    "sg:classifiers":[
        {
            "category":"Retail",
            "subcategory":"Auto Repair",
            "type":"Services"
        }
    ],
    "sg:phone":"+1 313 565 4941",
    "sg:postcode":"48127",
    "sg:province":"MI",
    "sg:tags":[
        "automotive"
    ],
    "wof:name":"Multi-State Transmission",
    "wof:placetype":"venue"
},
  "geometry": {"coordinates":[-83.272598,42.332219],"type":"Point"}
}