{
  "type": "Feature",
  "properties": {
    "iso:country":"US",
    "sg:address":"22757 S Woodward Ave",
    "sg:city":"Ferndale",
    "sg:classifiers":[
        {
            "category":"Real Estate",
            "subcategory":"Real Estate Operator",
            "type":"Services"
        }
    ],
    "sg:phone":"+1 248 591 0071",
    "sg:postcode":"48220",
    "sg:province":"MI",
    "sg:tags":[
        "apartment"
    ],
    "wof:name":"Apartment Agents",
    "wof:placetype":"venue"
},
  "geometry": {"coordinates":[-83.134739,42.460261],"type":"Point"}
}