{
  "type": "Feature",
  "properties": {
    "iso:country":"US",
    "sg:address":"16222 Pine Lake Forest Ct",
    "sg:city":"Linden",
    "sg:classifiers":[
        {
            "category":"Banks & Credit Unions",
            "subcategory":"Bank",
            "type":"Services"
        }
    ],
    "sg:phone":"+1 810 714 9333",
    "sg:postcode":"48451",
    "sg:province":"MI",
    "sg:tags":[
        "mortgage"
    ],
    "wof:name":"Hunter Mortgage",
    "wof:placetype":"venue"
},
  "geometry": {"coordinates":[-83.77322700000001,42.791102],"type":"Point"}
}