{
  "type": "Feature",
  "properties": {
    "iso:country":"US",
    "sg:address":"146 Wamplers Lake Rd",
    "sg:city":"Brooklyn",
    "sg:classifiers":[
        {
            "category":"Retail",
            "subcategory":"Self-service Laundry",
            "type":"Services"
        }
    ],
    "sg:phone":"+1 517 529 4337",
    "sg:postcode":"49230",
    "sg:province":"MI",
    "sg:tags":[
        "coin"
    ],
    "wof:name":"Brooklyn Coin Laundry",
    "wof:placetype":"venue"
},
  "geometry": {"coordinates":[-84.24555599999999,42.099249],"type":"Point"}
}