{
  "type": "Feature",
  "properties": {
    "iso:country":"US",
    "sg:address":"7200 Old Pipestone Rd",
    "sg:city":"Eau Claire",
    "sg:classifiers":[
        {
            "category":"Farming",
            "subcategory":"Farm",
            "type":"Manufacturing & Wholesale Goods"
        }
    ],
    "sg:phone":"+1 269 461 3100",
    "sg:postcode":"49111",
    "sg:province":"MI",
    "wof:name":"Lennard Ag Co",
    "wof:placetype":"venue"
},
  "geometry": {"coordinates":[-86.300336,41.98713],"type":"Point"}
}