{
  "type": "Feature",
  "properties": {
    "iso:country":"US",
    "sg:address":"10179 N US Hwy 31",
    "sg:city":"Ellsworth",
    "sg:classifiers":[
        {
            "category":"Home & Garden",
            "subcategory":"Hardware",
            "type":"Retail Goods"
        }
    ],
    "sg:phone":"+1 231 599 2551",
    "sg:postcode":"49729",
    "sg:province":"MI",
    "wof:name":"Penfold Ace Hardware",
    "wof:placetype":"venue"
},
  "geometry": {"coordinates":[-85.34496300000001,45.184825],"type":"Point"}
}