{
  "type": "Feature",
  "properties": {
    "iso:country":"US",
    "sg:address":"24916 Harper Ave",
    "sg:city":"St Clair Shores",
    "sg:classifiers":[
        {
            "category":"Social Services",
            "type":"Services"
        }
    ],
    "sg:phone":"+1 586 498 8813",
    "sg:postcode":"48080",
    "sg:province":"MI",
    "sg:tags":[
        "counseling"
    ],
    "wof:name":"Rainbow Treatment Svc",
    "wof:placetype":"venue"
},
  "geometry": {"coordinates":[-82.90150199999999,42.480335],"type":"Point"}
}