{
  "type": "Feature",
  "properties": {
    "iso:country":"US",
    "sg:address":"4280 W Bay City Forestville Rd",
    "sg:city":"Unionville",
    "sg:classifiers":[
        {
            "category":"Restaurant",
            "type":"Food & Drink"
        }
    ],
    "sg:phone":"+1 989 674 1000",
    "sg:postcode":"48767",
    "sg:province":"MI",
    "wof:name":"Light House Cafe & Lounge",
    "wof:placetype":"venue"
},
  "geometry": {"coordinates":[-83.516824,43.652753],"type":"Point"}
}