{
  "type": "Feature",
  "properties": {
    "iso:country":"US",
    "sg:address":"201 E Chapel Ln",
    "sg:city":"Midland",
    "sg:classifiers":[
        {
            "category":"Retail",
            "subcategory":"Animal Services",
            "type":"Services"
        }
    ],
    "sg:phone":"+1 989 633 9932",
    "sg:postcode":"48642",
    "sg:province":"MI",
    "wof:name":"Canine Care",
    "wof:placetype":"venue"
},
  "geometry": {"coordinates":[-84.22199000000001,43.648574],"type":"Point"}
}