{
  "type": "Feature",
  "properties": {
    "iso:country":"US",
    "sg:address":"7255 Pontiac Trl",
    "sg:city":"West Bloomfield",
    "sg:classifiers":[
        {
            "category":"Building & Trades",
            "subcategory":"Construction",
            "type":"Services"
        }
    ],
    "sg:phone":"+1 248 624 9310",
    "sg:postcode":"48323",
    "sg:province":"MI",
    "sg:tags":[
        "waterproofing",
        "contractor"
    ],
    "wof:name":"Trowbridge Restoration Inc",
    "wof:placetype":"venue"
},
  "geometry": {"coordinates":[-83.433632,42.563409],"type":"Point"}
}