{
  "type": "Feature",
  "properties": {
    "iso:country":"US",
    "sg:address":"1340 Locust St",
    "sg:city":"Fremont",
    "sg:classifiers":[
        {
            "category":"Professional",
            "type":"Services"
        }
    ],
    "sg:phone":"+1 231 924 7208",
    "sg:postcode":"49412",
    "sg:province":"MI",
    "sg:tags":[
        "establishment"
    ],
    "wof:name":"CNC National Enterprises",
    "wof:placetype":"venue"
},
  "geometry": {"coordinates":[-85.96778500000001,43.463094],"type":"Point"}
}