{
  "type": "Feature",
  "properties": {
    "iso:country":"US",
    "sg:address":"3758 Auburn Rd",
    "sg:city":"Auburn Hills",
    "sg:classifiers":[
        {
            "category":"Airport",
            "type":"Transportation"
        }
    ],
    "sg:phone":"+1 248 853 7229",
    "sg:postcode":"48326",
    "sg:province":"MI",
    "wof:name":"A A Advantage Airport Svc",
    "wof:placetype":"venue"
},
  "geometry": {"coordinates":[-83.210868,42.633897],"type":"Point"}
}