{
  "type": "Feature",
  "properties": {
    "iso:country":"US",
    "sg:address":"20101 Carlier St",
    "sg:city":"Clinton Township",
    "sg:classifiers":[
        {
            "category":"Shopping",
            "subcategory":"Party Supplies",
            "type":"Retail Goods"
        },
        {
            "category":"Personal",
            "type":"Services"
        }
    ],
    "sg:phone":"+1 586 790 7154",
    "sg:postcode":"48035",
    "sg:province":"MI",
    "sg:tags":[
        "planning",
        "event"
    ],
    "wof:name":"D Brothers",
    "wof:placetype":"venue"
},
  "geometry": {"coordinates":[-82.9104,42.5574],"type":"Point"}
}