{
  "type": "Feature",
  "properties": {
    "iso:country":"US",
    "sg:address":"2088 Kinney Rd",
    "sg:city":"Riley",
    "sg:classifiers":[
        {
            "category":"Farming",
            "subcategory":"Nursery",
            "type":"Manufacturing & Wholesale Goods"
        }
    ],
    "sg:phone":"+1 810 384 6700",
    "sg:postcode":"48041",
    "sg:province":"MI",
    "sg:tags":[
        "greenhouse"
    ],
    "wof:name":"Little Portion Greenhouse",
    "wof:placetype":"venue"
},
  "geometry": {"coordinates":[-82.763285,42.957815],"type":"Point"}
}