{
  "type": "Feature",
  "properties": {
    "iso:country":"US",
    "sg:address":"19606 Joy Rd",
    "sg:city":"Detroit",
    "sg:classifiers":[
        {
            "category":"Real Estate",
            "subcategory":"Architect",
            "type":"Services"
        }
    ],
    "sg:phone":"+1 313 836 1466",
    "sg:postcode":"48228",
    "sg:province":"MI",
    "wof:name":"Hair Architects",
    "wof:placetype":"venue"
},
  "geometry": {"coordinates":[-83.233902,42.3577],"type":"Point"}
}