{
  "type": "Feature",
  "properties": {
    "iso:country":"US",
    "sg:address":"9905 Union Pier Rd",
    "sg:city":"Union Pier",
    "sg:classifiers":[
        {
            "category":"Food & Beverages",
            "subcategory":"Groceries & Convenience Stores",
            "type":"Retail Goods"
        }
    ],
    "sg:phone":"+1 269 469 5651",
    "sg:postcode":"49116",
    "sg:province":"MI",
    "wof:name":"G & K Party Store",
    "wof:placetype":"venue"
},
  "geometry": {"coordinates":[-86.69215699999999,41.828195],"type":"Point"}
}