{
  "type": "Feature",
  "properties": {
    "iso:country":"US",
    "sg:address":"40925 Garfield Rd",
    "sg:city":"Clinton Twp",
    "sg:classifiers":[
        {
            "category":"Shopping",
            "subcategory":"Pharmacy",
            "type":"Retail Goods"
        }
    ],
    "sg:phone":"+1 248 652 2227",
    "sg:postcode":"48038",
    "sg:province":"MI",
    "sg:tags":[
        "drugstore"
    ],
    "sg:website":"www.cvs.com",
    "wof:name":"Cvs Pharmacy",
    "wof:placetype":"venue"
},
  "geometry": {"coordinates":[-82.952499,42.5979],"type":"Point"}
}