{
  "type": "Feature",
  "properties": {
    "iso:country":"US",
    "sg:address":"901 Spruce St",
    "sg:city":"Dowagiac",
    "sg:classifiers":[
        {
            "category":"Government",
            "subcategory":"Office",
            "type":"Public Place"
        }
    ],
    "sg:phone":"+1 269 782 0887",
    "sg:postcode":"49047",
    "sg:province":"MI",
    "sg:website":"www.pokagon.com",
    "wof:name":"Pokagon Band Employment & Trng",
    "wof:placetype":"venue"
},
  "geometry": {"coordinates":[-86.121759,41.984378],"type":"Point"}
}