{
  "type": "Feature",
  "properties": {
    "iso:country":"US",
    "sg:address":"36784 Gregory Dr",
    "sg:city":"Sterling Heights",
    "sg:classifiers":[
        {
            "category":"Health Services",
            "subcategory":"Clinic",
            "type":"Services"
        }
    ],
    "sg:phone":"+1 586 446 9414",
    "sg:postcode":"48312",
    "sg:province":"MI",
    "sg:tags":[
        "home",
        "care"
    ],
    "wof:name":"Devine Health Care Inc",
    "wof:placetype":"venue"
},
  "geometry": {"coordinates":[-83.019074,42.563611],"type":"Point"}
}