{
  "type": "Feature",
  "properties": {
    "iso:country":"US",
    "sg:address":"8947 US Hwy 31",
    "sg:city":"Alanson",
    "sg:classifiers":[
        {
            "category":"Food & Beverages",
            "subcategory":"Groceries & Convenience Stores",
            "type":"Retail Goods"
        }
    ],
    "sg:phone":"+1 231 347 1494",
    "sg:postcode":"49706",
    "sg:province":"MI",
    "wof:name":"Ponshewaing General Store",
    "wof:placetype":"venue"
},
  "geometry": {"coordinates":[-84.804714,45.421508],"type":"Point"}
}