{
  "type": "Feature",
  "properties": {
    "iso:country":"US",
    "sg:address":"11899 State Hwy 32",
    "sg:city":"Atlanta",
    "sg:classifiers":[
        {
            "category":"Health Services",
            "subcategory":"Clinic",
            "type":"Services"
        }
    ],
    "sg:phone":"+1 989 785 2571",
    "sg:postcode":"49709",
    "sg:province":"MI",
    "sg:tags":[
        "specialty",
        "outpatient"
    ],
    "wof:name":"A G H Rehabilitation Services",
    "wof:placetype":"venue"
},
  "geometry": {"coordinates":[-84.155934,45.007148],"type":"Point"}
}