{
  "type": "Feature",
  "properties": {
    "iso:country":"US",
    "sg:address":"1028 Dreon Dr",
    "sg:city":"Clawson",
    "sg:classifiers":[
        {
            "category":"Shopping",
            "subcategory":"Bicycles & Sporting Goods",
            "type":"Retail Goods"
        }
    ],
    "sg:phone":"+1 248 435 6463",
    "sg:postcode":"48017",
    "sg:province":"MI",
    "sg:tags":[
        "repair"
    ],
    "wof:name":"Rf Enterprises",
    "wof:placetype":"venue"
},
  "geometry": {"coordinates":[-83.159948,42.546609],"type":"Point"}
}