{
  "type": "Feature",
  "properties": {
    "iso:country":"US",
    "sg:address":"7905 Reed Rd",
    "sg:city":"Howard City",
    "sg:classifiers":[
        {
            "category":"Building & Trades",
            "subcategory":"Construction",
            "type":"Services"
        }
    ],
    "sg:phone":"+1 231 937 4519",
    "sg:postcode":"49329",
    "sg:province":"MI",
    "sg:tags":[
        "floor",
        "laying",
        "contractor"
    ],
    "wof:name":"K & S Floor Covering",
    "wof:placetype":"venue"
},
  "geometry": {"coordinates":[-85.46250499999999,43.407353],"type":"Point"}
}