{
  "type": "Feature",
  "properties": {
    "iso:country":"US",
    "sg:address":"1213 Hampton Dr",
    "sg:city":"Jackson",
    "sg:classifiers":[
        {
            "category":"Professional",
            "subcategory":"Management & Consulting",
            "type":"Services"
        }
    ],
    "sg:phone":"+1 517 782 2255",
    "sg:postcode":"49203",
    "sg:province":"MI",
    "sg:tags":[
        "consultant",
        "business"
    ],
    "wof:name":"Ggw & Assoc",
    "wof:placetype":"venue"
},
  "geometry": {"coordinates":[-84.431996,42.213818],"type":"Point"}
}