{
  "type": "Feature",
  "properties": {
    "iso:country":"US",
    "sg:address":"4901 N Clare Ave",
    "sg:city":"Harrison",
    "sg:classifiers":[
        {
            "category":"Freight",
            "type":"Transportation"
        }
    ],
    "sg:phone":"+1 989 539 1341",
    "sg:postcode":"48625",
    "sg:province":"MI",
    "sg:tags":[
        "commercial",
        "storage"
    ],
    "wof:name":"Al's Mini-Storage",
    "wof:placetype":"venue"
},
  "geometry": {"coordinates":[-84.80712800000001,44.058935],"type":"Point"}
}