{
  "type": "Feature",
  "properties": {
    "iso:country":"US",
    "sg:address":"1870 Country Ln",
    "sg:city":"Weidman",
    "sg:classifiers":[
        {
            "category":"Freight",
            "type":"Transportation"
        }
    ],
    "sg:phone":"+1 989 644 3765",
    "sg:postcode":"48893",
    "sg:province":"MI",
    "sg:tags":[
        "operator",
        "trucking"
    ],
    "wof:name":"McCormick Trucking",
    "wof:placetype":"venue"
},
  "geometry": {"coordinates":[-84.95150599999999,43.66729],"type":"Point"}
}