{
  "type": "Feature",
  "properties": {
    "iso:country":"US",
    "sg:address":"3838 Jarvis Ave",
    "sg:city":"Warren",
    "sg:classifiers":[
        {
            "category":"Real Estate",
            "subcategory":"Real Estate Agent",
            "type":"Services"
        }
    ],
    "sg:phone":"+1 586 427 3925",
    "sg:postcode":"48091",
    "sg:province":"MI",
    "wof:name":"Adz Appraisals",
    "wof:placetype":"venue"
},
  "geometry": {"coordinates":[-83.06441100000001,42.457248],"type":"Point"}
}