{
  "type": "Feature",
  "properties": {
    "iso:country":"US",
    "sg:address":"2597 Marble Ct",
    "sg:city":"Zeeland",
    "sg:classifiers":[
        {
            "category":"Real Estate",
            "subcategory":"Real Estate Agent",
            "type":"Services"
        }
    ],
    "sg:phone":"+1 616 748 8000",
    "sg:postcode":"49464",
    "sg:province":"MI",
    "wof:name":"Woodside Green Condominiums",
    "wof:placetype":"venue"
},
  "geometry": {"coordinates":[-86.04130499999999,42.814156],"type":"Point"}
}