{
  "type": "Feature",
  "properties": {
    "iso:country":"US",
    "sg:address":"7821 Lakeview Dr",
    "sg:city":"Lexington",
    "sg:classifiers":[
        {
            "category":"Building & Trades",
            "subcategory":"Construction",
            "type":"Services"
        }
    ],
    "sg:phone":"+1 810 359 2032",
    "sg:postcode":"48450",
    "sg:province":"MI",
    "sg:tags":[
        "home",
        "builder"
    ],
    "wof:name":"Nardone Homes Inc",
    "wof:placetype":"venue"
},
  "geometry": {"coordinates":[-82.512874,43.203016],"type":"Point"}
}