{
  "type": "Feature",
  "properties": {
    "iso:country":"US",
    "sg:address":"4250 Lucinda Dr",
    "sg:city":"Prescott",
    "sg:classifiers":[
        {
            "category":"Organizations",
            "subcategory":"Religious Organization",
            "type":"Services"
        }
    ],
    "sg:phone":"+1 989 873 5979",
    "sg:postcode":"48756",
    "sg:province":"MI",
    "sg:tags":[
        "church"
    ],
    "wof:name":"Skidway Lake Baptist Church",
    "wof:placetype":"venue"
},
  "geometry": {"coordinates":[-84.025138,44.212867],"type":"Point"}
}