{
  "type": "Feature",
  "properties": {
    "iso:country":"US",
    "sg:address":"42229 Columbia Ct",
    "sg:city":"Sterling Heights",
    "sg:classifiers":[
        {
            "category":"Real Estate",
            "subcategory":"Real Estate Agent",
            "type":"Services"
        }
    ],
    "sg:phone":"+1 586 566 0578",
    "sg:postcode":"48313",
    "sg:province":"MI",
    "sg:tags":[
        "agency",
        "rental"
    ],
    "wof:name":"Norton Rentals Inc",
    "wof:placetype":"venue"
},
  "geometry": {"coordinates":[-82.978966,42.607154],"type":"Point"}
}