{
  "type": "Feature",
  "properties": {
    "iso:country":"US",
    "sg:address":"14420 Labelle St",
    "sg:city":"Oak Park",
    "sg:classifiers":[
        {
            "category":"Building & Trades",
            "subcategory":"Landscaping Services",
            "type":"Services"
        }
    ],
    "sg:phone":"+1 248 548 9136",
    "sg:postcode":"48237",
    "sg:province":"MI",
    "sg:tags":[
        "lawn",
        "maintenance",
        "grounds"
    ],
    "wof:name":"Two Mowers & A Man",
    "wof:placetype":"venue"
},
  "geometry": {"coordinates":[-83.192348,42.4871],"type":"Point"}
}