{
  "type": "Feature",
  "properties": {
    "iso:country":"US",
    "sg:address":"4870 W River Dr NE",
    "sg:city":"Comstock Park",
    "sg:classifiers":[
        {
            "category":"Wholesale",
            "subcategory":"Hardware",
            "type":"Manufacturing & Wholesale Goods"
        }
    ],
    "sg:phone":"+1 616 785 0306",
    "sg:postcode":"49321",
    "sg:province":"MI",
    "sg:tags":[
        "furnace"
    ],
    "wof:name":"Behler Young-Co",
    "wof:placetype":"venue"
},
  "geometry": {"coordinates":[-85.652767,43.050606],"type":"Point"}
}