{
  "type": "Feature",
  "properties": {
    "iso:country":"US",
    "sg:address":"1529 Co Rd Fa",
    "sg:city":"Champion",
    "sg:classifiers":[
        {
            "category":"Shopping",
            "subcategory":"Used Merchandise",
            "type":"Retail Goods"
        }
    ],
    "sg:phone":"+1 906 485 6449",
    "sg:postcode":"49814",
    "sg:province":"MI",
    "sg:tags":[
        "antique"
    ],
    "wof:name":"Just Browsing",
    "wof:placetype":"venue"
},
  "geometry": {"coordinates":[-87.91115000000001,46.495684],"type":"Point"}
}