{
  "type": "Feature",
  "properties": {
    "iso:country":"US",
    "sg:address":"15900 Woodward Ave",
    "sg:city":"Highland Park",
    "sg:classifiers":[
        {
            "category":"Education",
            "subcategory":"School",
            "type":"Public Place"
        }
    ],
    "sg:phone":"+1 313 957 3001",
    "sg:postcode":"48203",
    "sg:province":"MI",
    "wof:name":"Highland Park Public Schools",
    "wof:placetype":"venue"
},
  "geometry": {"coordinates":[-83.101709,42.41279],"type":"Point"}
}