{
  "type": "Feature",
  "properties": {
    "iso:country":"US",
    "sg:address":"39318 Owendale Dr",
    "sg:city":"Sterling Heights",
    "sg:classifiers":[
        {
            "category":"Professional",
            "subcategory":"Computer Services",
            "type":"Services"
        }
    ],
    "sg:phone":"+1 586 978 8772",
    "sg:postcode":"48310",
    "sg:province":"MI",
    "sg:tags":[
        "related"
    ],
    "wof:name":"Raj Consulting",
    "wof:placetype":"venue"
},
  "geometry": {"coordinates":[-83.073986,42.581201],"type":"Point"}
}