{
  "type": "Feature",
  "properties": {
    "iso:country":"US",
    "sg:address":"1530 E Hamilton Ave",
    "sg:city":"Flint",
    "sg:classifiers":[
        {
            "category":"Professional",
            "subcategory":"Computer Services",
            "type":"Services"
        }
    ],
    "sg:phone":"+1 810 232 9349",
    "sg:postcode":"48506",
    "sg:province":"MI",
    "wof:name":"ISPA One",
    "wof:placetype":"venue"
},
  "geometry": {"coordinates":[-83.670811,43.034921],"type":"Point"}
}