{
  "type": "Feature",
  "properties": {
    "iso:country":"US",
    "sg:address":"855 Michigan Ave",
    "sg:city":"Marysville",
    "sg:classifiers":[
        {
            "category":"Professional",
            "subcategory":"Employment Agencies",
            "type":"Services"
        }
    ],
    "sg:phone":"+1 810 388 0800",
    "sg:postcode":"48040",
    "sg:province":"MI",
    "sg:tags":[
        "opportunity"
    ],
    "wof:name":"Labor Ready Inc",
    "wof:placetype":"venue"
},
  "geometry": {"coordinates":[-82.48029200000001,42.91762],"type":"Point"}
}