{
  "type": "Feature",
  "properties": {
    "iso:country":"US",
    "sg:address":"22077 Gudith Rd",
    "sg:city":"Trenton",
    "sg:classifiers":[
        {
            "category":"Retail",
            "subcategory":"Repair Shop",
            "type":"Services"
        }
    ],
    "sg:phone":"+1 734 675 8933",
    "sg:postcode":"48183",
    "sg:province":"MI",
    "sg:tags":[
        "welding"
    ],
    "wof:name":"Journeyman Welding",
    "wof:placetype":"venue"
},
  "geometry": {"coordinates":[-83.251397,42.145428],"type":"Point"}
}