{
  "type": "Feature",
  "properties": {
    "iso:country":"US",
    "sg:address":"120 S Clark St",
    "sg:city":"Albion",
    "sg:classifiers":[
        {
            "category":"Shopping",
            "subcategory":"Pharmacy",
            "type":"Retail Goods"
        }
    ],
    "sg:phone":"+1 517 629 2900",
    "sg:postcode":"49224",
    "sg:province":"MI",
    "wof:name":"Young's Pharmacy",
    "wof:placetype":"venue"
},
  "geometry": {"coordinates":[-84.7364,42.245292],"type":"Point"}
}