{
  "type": "Feature",
  "properties": {
    "iso:country":"US",
    "sg:address":"12160 Neff Rd",
    "sg:city":"Clio",
    "sg:classifiers":[
        {
            "category":"Retail",
            "subcategory":"Auto Repair",
            "type":"Services"
        }
    ],
    "sg:phone":"+1 810 252 3860",
    "sg:postcode":"48420",
    "sg:province":"MI",
    "sg:tags":[
        "body"
    ],
    "wof:name":"Jfr Inc",
    "wof:placetype":"venue"
},
  "geometry": {"coordinates":[-83.71475,43.181874],"type":"Point"}
}