{
  "type": "Feature",
  "properties": {
    "iso:country":"US",
    "sg:address":"9894 Coleman Rd",
    "sg:city":"Haslett",
    "sg:classifiers":[
        {
            "category":"Wholesale",
            "subcategory":"Hardware",
            "type":"Manufacturing & Wholesale Goods"
        }
    ],
    "sg:phone":"+1 517 485 6295",
    "sg:postcode":"48840",
    "sg:province":"MI",
    "sg:tags":[
        "refrigerating"
    ],
    "wof:name":"S & S Refrigeration Inc",
    "wof:placetype":"venue"
},
  "geometry": {"coordinates":[-84.364774,42.769971],"type":"Point"}
}