{
  "type": "Feature",
  "properties": {
    "iso:country":"US",
    "sg:address":"4165 24th Ave",
    "sg:city":"Fort Gratiot",
    "sg:classifiers":[
        {
            "category":"Restaurant",
            "type":"Food & Drink"
        }
    ],
    "sg:menulink":"http://www.allmenus.com/mi/fort-gratiot/121994-quiznos-sub/menu/",
    "sg:phone":"+1 810 385 9490",
    "sg:postcode":"48059",
    "sg:province":"MI",
    "sg:tags":[
        "wrap",
        "american",
        "sandwich"
    ],
    "wof:name":"Quiznos Sub",
    "wof:placetype":"venue"
},
  "geometry": {"coordinates":[-82.456192,43.029815],"type":"Point"}
}