{
  "type": "Feature",
  "properties": {
    "iso:country":"US",
    "sg:address":"3057 Sandy Beach Rd",
    "sg:city":"Wayland",
    "sg:classifiers":[
        {
            "category":"Building & Trades",
            "subcategory":"Construction",
            "type":"Services"
        }
    ],
    "sg:phone":"+1 269 792 2380",
    "sg:postcode":"49348",
    "sg:province":"MI",
    "sg:tags":[
        "house"
    ],
    "wof:name":"John Rough Builder",
    "wof:placetype":"venue"
},
  "geometry": {"coordinates":[-85.542304,42.607959],"type":"Point"}
}