{
  "type": "Feature",
  "properties": {
    "iso:country":"US",
    "sg:address":"11343 Coyle St",
    "sg:city":"Detroit",
    "sg:classifiers":[
        {
            "category":"Social Services",
            "subcategory":"Child Care",
            "type":"Services"
        }
    ],
    "sg:phone":"+1 313 835 1785",
    "sg:postcode":"48227",
    "sg:province":"MI",
    "sg:tags":[
        "day"
    ],
    "wof:name":"Sandra Hardaway",
    "wof:placetype":"venue"
},
  "geometry": {"coordinates":[-83.193251,42.372345],"type":"Point"}
}