{
  "type": "Feature",
  "properties": {
    "iso:country":"US",
    "sg:address":"1732 Monroe Ave NW",
    "sg:city":"Grand Rapids",
    "sg:classifiers":[
        {
            "category":"Home & Garden",
            "subcategory":"Household Appliances",
            "type":"Retail Goods"
        }
    ],
    "sg:phone":"+1 616 364 5677",
    "sg:postcode":"49505",
    "sg:province":"MI",
    "wof:name":"Zeeff Appliance Market",
    "wof:placetype":"venue"
},
  "geometry": {"coordinates":[-85.67045,42.995517],"type":"Point"}
}