{
  "type": "Feature",
  "properties": {
    "iso:country":"US",
    "sg:address":"33654 Oak Point Cir",
    "sg:city":"Farmington",
    "sg:classifiers":[
        {
            "category":"Organizations",
            "subcategory":"Membership Organization",
            "type":"Services"
        }
    ],
    "sg:phone":"+1 248 553 5035",
    "sg:postcode":"48331",
    "sg:province":"MI",
    "wof:name":"Rbkkk Foundation",
    "wof:placetype":"venue"
},
  "geometry": {"coordinates":[-83.379822,42.51264],"type":"Point"}
}