{
  "type": "Feature",
  "properties": {
    "iso:country":"US",
    "sg:address":"7816 Elk Tip Dr",
    "sg:city":"Rapid City",
    "sg:classifiers":[
        {
            "category":"Professional",
            "subcategory":"Management & Consulting",
            "type":"Services"
        }
    ],
    "sg:phone":"+1 231 264 5590",
    "sg:postcode":"49648",
    "sg:province":"MI",
    "sg:tags":[
        "consultant",
        "educational"
    ],
    "wof:name":"Michael Mc Intyre Michgan",
    "wof:placetype":"venue"
},
  "geometry": {"coordinates":[-85.36456200000001,44.917887],"type":"Point"}
}