{
  "type": "Feature",
  "properties": {
    "iso:country":"US",
    "sg:address":"1110 S University Ave",
    "sg:city":"Ann Arbor",
    "sg:classifiers":[
        {
            "category":"Deli",
            "type":"Food & Drink"
        },
        {
            "category":"Cafe",
            "type":"Food & Drink"
        }
    ],
    "sg:menulink":"http://www.allmenus.com/mi/ann-arbor/248065-rendez-vous-cafe/menu/",
    "sg:phone":"+1 734 761 8600",
    "sg:postcode":"48104",
    "sg:province":"MI",
    "sg:tags":[
        "wrap",
        "american",
        "sandwich"
    ],
    "wof:name":"Rendez-vous Cafe",
    "wof:placetype":"venue"
},
  "geometry": {"coordinates":[-83.73564,42.27498],"type":"Point"}
}