{
  "type": "Feature",
  "properties": {
    "iso:country":"US",
    "sg:address":"5303 Kuzmik Rd",
    "sg:city":"Elmira",
    "sg:classifiers":[
        {
            "category":"Building & Trades",
            "subcategory":"Construction",
            "type":"Services"
        }
    ],
    "sg:phone":"+1 231 549 2826",
    "sg:postcode":"49730",
    "sg:province":"MI",
    "sg:tags":[
        "excavation",
        "work"
    ],
    "wof:name":"R & K Excavating",
    "wof:placetype":"venue"
},
  "geometry": {"coordinates":[-84.83676199999999,45.126894],"type":"Point"}
}