{
  "type": "Feature",
  "properties": {
    "iso:country":"US",
    "sg:address":"1640 N Cochran Ave",
    "sg:city":"Charlotte",
    "sg:classifiers":[
        {
            "category":"Manufacturing",
            "subcategory":"Tools & Machinery",
            "type":"Manufacturing & Wholesale Goods"
        }
    ],
    "sg:phone":"+1 517 541 0414",
    "sg:postcode":"48813",
    "sg:province":"MI",
    "sg:tags":[
        "mfg"
    ],
    "wof:name":"Eaton Electrical Inc",
    "wof:placetype":"venue"
},
  "geometry": {"coordinates":[-84.836026,42.590262],"type":"Point"}
}