{
  "type": "Feature",
  "properties": {
    "iso:country":"US",
    "sg:address":"1045 W Bemis Rd",
    "sg:city":"Saline",
    "sg:classifiers":[
        {
            "category":"Organizations",
            "subcategory":"Religious Organization",
            "type":"Services"
        }
    ],
    "sg:phone":"+1 734 429 7196",
    "sg:postcode":"48176",
    "sg:province":"MI",
    "wof:name":"Fellowship Baptist Church Inc",
    "wof:placetype":"venue"
},
  "geometry": {"coordinates":[-83.746138,42.17049],"type":"Point"}
}