{
  "type": "Feature",
  "properties": {
    "iso:country":"US",
    "sg:address":"3950 S Rochester Rd",
    "sg:city":"Rochester Hills",
    "sg:classifiers":[
        {
            "category":"Professional",
            "type":"Services"
        }
    ],
    "sg:phone":"+1 248 852 8051",
    "sg:postcode":"48307",
    "sg:province":"MI",
    "sg:tags":[
        "establishment"
    ],
    "wof:name":"Bolyard Lumber Gateway",
    "wof:placetype":"venue"
},
  "geometry": {"coordinates":[-83.130859,42.624029],"type":"Point"}
}