{
  "type": "Feature",
  "properties": {
    "iso:country":"US",
    "sg:address":"2331 Rothbury Ct NE",
    "sg:city":"Grand Rapids",
    "sg:classifiers":[
        {
            "category":"Professional",
            "subcategory":"Business Services",
            "type":"Services"
        }
    ],
    "sg:phone":"+1 616 235 0450",
    "sg:postcode":"49505",
    "sg:province":"MI",
    "wof:name":"Dbr Simple Solutions",
    "wof:placetype":"venue"
},
  "geometry": {"coordinates":[-85.611994,42.98909],"type":"Point"}
}