{
  "type": "Feature",
  "properties": {
    "iso:country":"US",
    "sg:address":"33341 Kelly Rd",
    "sg:city":"Fraser",
    "sg:classifiers":[
        {
            "category":"Retail",
            "subcategory":"Auto Repair",
            "type":"Services"
        }
    ],
    "sg:phone":"+1 586 415 9381",
    "sg:postcode":"48026",
    "sg:province":"MI",
    "sg:tags":[
        "trailer"
    ],
    "wof:name":"Raven Resteel Inc",
    "wof:placetype":"venue"
},
  "geometry": {"coordinates":[-82.929951,42.543529],"type":"Point"}
}