{
  "type": "Feature",
  "properties": {
    "iso:country":"US",
    "sg:address":"12615 Stark Rd.",
    "sg:city":"Livonia",
    "sg:classifiers":[
        {
            "category":"Retail",
            "subcategory":"Pet Boarding",
            "type":"Services"
        }
    ],
    "sg:phone":"+1 734 522 7297",
    "sg:postcode":"48150",
    "sg:province":"MI",
    "sg:tags":[
        "boarding/pet",
        "sitting"
    ],
    "sg:website":"www.4-leggedfriendsdaycare.com/",
    "wof:name":"4-Legged Friends Daycare & Boarding",
    "wof:placetype":"venue"
},
  "geometry": {"coordinates":[-83.380878,42.375693],"type":"Point"}
}