{
  "type": "Feature",
  "properties": {
    "iso:country":"US",
    "sg:address":"39300 W 10 Mile Rd",
    "sg:city":"Farmington",
    "sg:classifiers":[
        {
            "category":"Autos & Motor Vehicles",
            "subcategory":"Automobile Sales",
            "type":"Retail Goods"
        },
        {
            "category":"Retail",
            "subcategory":"Auto Repair",
            "type":"Services"
        }
    ],
    "sg:phone":"+1 248 474 1234",
    "sg:postcode":"48335",
    "sg:province":"MI",
    "sg:tags":[
        "body",
        "shop",
        "car"
    ],
    "wof:name":"Holzer Tom Ford Inc",
    "wof:placetype":"venue"
},
  "geometry": {"coordinates":[-83.43440200000001,42.468102],"type":"Point"}
}