{
  "type": "Feature",
  "properties": {
    "iso:country":"US",
    "sg:address":"4228 Main St",
    "sg:city":"Brown City",
    "sg:classifiers":[
        {
            "category":"Retail",
            "subcategory":"Portrait Studio",
            "type":"Services"
        }
    ],
    "sg:phone":"+1 810 346 3245",
    "sg:postcode":"48416",
    "sg:province":"MI",
    "sg:tags":[
        "photographer"
    ],
    "wof:name":"Marion's Studios",
    "wof:placetype":"venue"
},
  "geometry": {"coordinates":[-82.988545,43.212263],"type":"Point"}
}