{
  "type": "Feature",
  "properties": {
    "iso:country":"US",
    "sg:address":"8300 Hudson Rd",
    "sg:city":"Pittsford",
    "sg:classifiers":[
        {
            "category":"Freight",
            "type":"Transportation"
        }
    ],
    "sg:phone":"+1 517 523 2444",
    "sg:postcode":"49271",
    "sg:province":"MI",
    "sg:tags":[
        "storage"
    ],
    "wof:name":"Wildcat Mini-Storage",
    "wof:placetype":"venue"
},
  "geometry": {"coordinates":[-84.492244,41.86573],"type":"Point"}
}