{
  "type": "Feature",
  "properties": {
    "iso:country":"US",
    "sg:address":"300 Monroe Ave NW",
    "sg:city":"Grand Rapids",
    "sg:classifiers":[
        {
            "category":"Government",
            "subcategory":"Office",
            "type":"Public Place"
        }
    ],
    "sg:phone":"+1 616 336 3550",
    "sg:postcode":"49503",
    "sg:province":"MI",
    "sg:tags":[
        "county",
        "information",
        "dept"
    ],
    "wof:name":"Vital Statistics Dept",
    "wof:placetype":"venue"
},
  "geometry": {"coordinates":[-85.672175,42.969175],"type":"Point"}
}