{
  "type": "Feature",
  "properties": {
    "iso:country":"US",
    "sg:address":"125 N Military St",
    "sg:city":"Dearborn",
    "sg:classifiers":[
        {
            "category":"Health Services",
            "subcategory":"Dentist",
            "type":"Services"
        }
    ],
    "sg:phone":"+1 313 274 1195",
    "sg:postcode":"48124",
    "sg:province":"MI",
    "wof:name":"Ken Rahmut Dr",
    "wof:placetype":"venue"
},
  "geometry": {"coordinates":[-83.25403300000001,42.312255],"type":"Point"}
}