{
  "type": "Feature",
  "properties": {
    "iso:country":"US",
    "sg:address":"7279 Hillside Dr",
    "sg:city":"Dearborn Heights",
    "sg:classifiers":[
        {
            "category":"Personal",
            "subcategory":"Tattoo Parlor",
            "type":"Services"
        }
    ],
    "sg:phone":"+1 313 278 1647",
    "sg:postcode":"48127",
    "sg:province":"MI",
    "wof:name":"Permanent Makeup by Joan",
    "wof:placetype":"venue"
},
  "geometry": {"coordinates":[-83.309898,42.341801],"type":"Point"}
}