{
  "type": "Feature",
  "properties": {
    "iso:country":"US",
    "sg:address":"57245 Travis Rd",
    "sg:city":"New Hudson",
    "sg:classifiers":[
        {
            "category":"Home & Garden",
            "subcategory":"Building Materials",
            "type":"Retail Goods"
        }
    ],
    "sg:phone":"+1 248 437 5861",
    "sg:postcode":"48165",
    "sg:province":"MI",
    "sg:tags":[
        "windows"
    ],
    "sg:website":"www.classicwindow.com",
    "wof:name":"Classic Window Builders Supply",
    "wof:placetype":"venue"
},
  "geometry": {"coordinates":[-83.618624,42.499618],"type":"Point"}
}