{
  "type": "Feature",
  "properties": {
    "iso:country":"US",
    "sg:address":"4932 W Tyler Rd",
    "sg:city":"Hart",
    "sg:classifiers":[
        {
            "category":"Farming",
            "subcategory":"Orchard",
            "type":"Manufacturing & Wholesale Goods"
        }
    ],
    "sg:phone":"+1 231 873 4174",
    "sg:postcode":"49420",
    "sg:province":"MI",
    "sg:tags":[
        "fruit",
        "tree"
    ],
    "wof:name":"Tim Tubbs",
    "wof:placetype":"venue"
},
  "geometry": {"coordinates":[-86.40612299999999,43.704031],"type":"Point"}
}