{
  "type": "Feature",
  "properties": {
    "iso:country":"US",
    "sg:address":"1020 Washington St",
    "sg:city":"Temperance",
    "sg:classifiers":[
        {
            "category":"Freight",
            "type":"Transportation"
        }
    ],
    "sg:phone":"+1 734 847 1700",
    "sg:postcode":"48182",
    "sg:province":"MI",
    "sg:tags":[
        "commercial",
        "storage"
    ],
    "wof:name":"Erie Shores Self Storage",
    "wof:placetype":"venue"
},
  "geometry": {"coordinates":[-83.57038799999999,41.778304],"type":"Point"}
}