{
  "type": "Feature",
  "properties": {
    "iso:country":"US",
    "sg:address":"579 W Isabella Rd",
    "sg:city":"Midland",
    "sg:classifiers":[
        {
            "category":"Cinema",
            "subcategory":"Movie Rental",
            "type":"Entertainment"
        }
    ],
    "sg:phone":"+1 989 835 4361",
    "sg:postcode":"48640",
    "sg:province":"MI",
    "sg:tags":[
        "leasing",
        "video",
        "disc",
        "tape"
    ],
    "wof:name":"Don's Video",
    "wof:placetype":"venue"
},
  "geometry": {"coordinates":[-84.390895,43.610776],"type":"Point"}
}