{
  "type": "Feature",
  "properties": {
    "iso:country":"US",
    "sg:address":"5178 136th Ave",
    "sg:city":"Hamilton",
    "sg:classifiers":[
        {
            "category":"Manufacturing",
            "subcategory":"Tools & Machinery",
            "type":"Manufacturing & Wholesale Goods"
        }
    ],
    "sg:phone":"+1 269 751 5578",
    "sg:postcode":"49419",
    "sg:province":"MI",
    "sg:tags":[
        "machine",
        "shop"
    ],
    "wof:name":"DMS Inc",
    "wof:placetype":"venue"
},
  "geometry": {"coordinates":[-86.052964,42.68211],"type":"Point"}
}