{
  "type": "Feature",
  "properties": {
    "iso:country":"US",
    "sg:address":"32758 Grand River Ave",
    "sg:city":"Farmington",
    "sg:classifiers":[
        {
            "category":"Restaurant",
            "type":"Food & Drink"
        }
    ],
    "sg:phone":"+1 248 478 2889",
    "sg:postcode":"48336",
    "sg:province":"MI",
    "sg:tags":[
        "korean"
    ],
    "wof:name":"Korea House",
    "wof:placetype":"venue"
},
  "geometry": {"coordinates":[-83.37145200000001,42.462795],"type":"Point"}
}