{
  "type": "Feature",
  "properties": {
    "iso:country":"US",
    "sg:address":"18440 Greenlawn St",
    "sg:city":"Detroit",
    "sg:classifiers":[
        {
            "category":"Organizations",
            "subcategory":"Religious Organization",
            "type":"Services"
        }
    ],
    "sg:phone":"+1 313 342 8587",
    "sg:postcode":"48221",
    "sg:province":"MI",
    "wof:name":"Transfrmng Love Community",
    "wof:placetype":"venue"
},
  "geometry": {"coordinates":[-83.151672,42.427491],"type":"Point"}
}