{
  "type": "Feature",
  "properties": {
    "iso:country":"US",
    "sg:address":"111 E Buffalo St",
    "sg:city":"New Buffalo",
    "sg:classifiers":[
        {
            "category":"Autos & Motor Vehicles",
            "subcategory":"Auto Supplies",
            "type":"Retail Goods"
        }
    ],
    "sg:phone":"+1 269 469 4470",
    "sg:postcode":"49117",
    "sg:province":"MI",
    "sg:tags":[
        "automobile",
        "parts"
    ],
    "wof:name":"Ridge Napa",
    "wof:placetype":"venue"
},
  "geometry": {"coordinates":[-86.741505,41.79489],"type":"Point"}
}