{
  "type": "Feature",
  "properties": {
    "iso:country":"US",
    "sg:address":"3425 W Jefferson Ave",
    "sg:city":"Ecorse",
    "sg:classifiers":[
        {
            "category":"Shopping",
            "subcategory":"Beauty & Cosmetics",
            "type":"Retail Goods"
        }
    ],
    "sg:phone":"+1 313 842 2226",
    "sg:postcode":"48229",
    "sg:province":"MI",
    "sg:tags":[
        "supply"
    ],
    "wof:name":"Pk Beauty",
    "wof:placetype":"venue"
},
  "geometry": {"coordinates":[-83.137384,42.261518],"type":"Point"}
}