{
  "type": "Feature",
  "properties": {
    "iso:country":"US",
    "sg:address":"320 Martin St",
    "sg:city":"Birmingham",
    "sg:classifiers":[
        {
            "category":"Government",
            "subcategory":"Post Office",
            "type":"Public Place"
        }
    ],
    "sg:phone":"+1 313 226 8362",
    "sg:postcode":"48009",
    "sg:province":"MI",
    "sg:tags":[
        "postal",
        "us"
    ],
    "wof:name":"United States Postal Service",
    "wof:placetype":"venue"
},
  "geometry": {"coordinates":[-83.21813299999999,42.545937],"type":"Point"}
}