{
  "type": "Feature",
  "properties": {
    "iso:country":"US",
    "sg:address":"22604 Stephens St",
    "sg:city":"Saint Clair Shores",
    "sg:classifiers":[
        {
            "category":"Building & Trades",
            "subcategory":"Cleaning & Sanitation",
            "type":"Services"
        }
    ],
    "sg:phone":"+1 586 777 0023",
    "sg:postcode":"48080",
    "sg:province":"MI",
    "sg:tags":[
        "maintenance"
    ],
    "wof:name":"Moffitt Facility Maintenance",
    "wof:placetype":"venue"
},
  "geometry": {"coordinates":[-82.890907,42.470062],"type":"Point"}
}