{
  "type": "Feature",
  "properties": {
    "iso:country":"US",
    "sg:address":"3315 Lorraine Ave",
    "sg:city":"Kalamazoo",
    "sg:classifiers":[
        {
            "category":"Professional",
            "subcategory":"Research",
            "type":"Services"
        }
    ],
    "sg:phone":"+1 269 217 2001",
    "sg:postcode":"49008",
    "sg:province":"MI",
    "sg:tags":[
        "nonphysical",
        "commercial"
    ],
    "wof:name":"Wordengroup Enterprises Inc",
    "wof:placetype":"venue"
},
  "geometry": {"coordinates":[-85.632209,42.263057],"type":"Point"}
}