{
  "type": "Feature",
  "properties": {
    "iso:country":"US",
    "sg:address":"28 W Adams St",
    "sg:city":"Detroit",
    "sg:classifiers":[
        {
            "category":"Banks & Credit Unions",
            "subcategory":"Bank",
            "type":"Services"
        }
    ],
    "sg:phone":"+1 313 961 3940",
    "sg:postcode":"48226",
    "sg:province":"MI",
    "sg:tags":[
        "national",
        "commercial"
    ],
    "wof:name":"Standard Federal Bank N A",
    "wof:placetype":"venue"
},
  "geometry": {"coordinates":[-83.052148,42.336573],"type":"Point"}
}