{
  "type": "Feature",
  "properties": {
    "iso:country":"US",
    "sg:address":"51071 Mound Rd",
    "sg:city":"Shelby Twp",
    "sg:classifiers":[
        {
            "category":"Food & Beverages",
            "subcategory":"Liquor & Beverages",
            "type":"Retail Goods"
        }
    ],
    "sg:phone":"+1 586 739 5940",
    "sg:postcode":"48316",
    "sg:province":"MI",
    "wof:name":"Max Liquor",
    "wof:placetype":"venue"
},
  "geometry": {"coordinates":[-83.053785,42.671607],"type":"Point"}
}