{
  "type": "Feature",
  "properties": {
    "iso:country":"US",
    "sg:address":"3960 S Ortonville Rd",
    "sg:city":"Clarkston",
    "sg:classifiers":[
        {
            "category":"Building & Trades",
            "subcategory":"Construction",
            "type":"Services"
        }
    ],
    "sg:phone":"+1 248 625 6700",
    "sg:postcode":"48348",
    "sg:province":"MI",
    "sg:tags":[
        "excavating",
        "contractor"
    ],
    "wof:name":"MVA Contracting",
    "wof:placetype":"venue"
},
  "geometry": {"coordinates":[-83.422191,42.793582],"type":"Point"}
}