{
  "type": "Feature",
  "properties": {
    "iso:country":"US",
    "sg:address":"246 W Genesee Ave",
    "sg:city":"Saginaw",
    "sg:classifiers":[
        {
            "category":"Professional",
            "subcategory":"Accounting & Tax Preparation",
            "type":"Services"
        }
    ],
    "sg:phone":"+1 989 752 2008",
    "sg:postcode":"48602",
    "sg:province":"MI",
    "sg:tags":[
        "return",
        "filing"
    ],
    "wof:name":"H & R Block Tax Svc",
    "wof:placetype":"venue"
},
  "geometry": {"coordinates":[-83.944019,43.434188],"type":"Point"}
}