{
  "type": "Feature",
  "properties": {
    "iso:country":"US",
    "sg:address":"2430 E Crown Dr",
    "sg:city":"Traverse City",
    "sg:classifiers":[
        {
            "category":"Sports & Exercise",
            "subcategory":"Golf",
            "type":"Entertainment"
        }
    ],
    "sg:phone":"+1 231 946 2975",
    "sg:postcode":"49684",
    "sg:province":"MI",
    "sg:tags":[
        "course"
    ],
    "wof:name":"Crown Golf Club",
    "wof:placetype":"venue"
},
  "geometry": {"coordinates":[-85.68166600000001,44.725759],"type":"Point"}
}