{
  "type": "Feature",
  "properties": {
    "iso:country":"US",
    "sg:address":"32788 5 Mile Rd",
    "sg:city":"Livonia",
    "sg:classifiers":[
        {
            "category":"Health Services",
            "subcategory":"Dentist",
            "type":"Services"
        }
    ],
    "sg:phone":"+1 734 425 1610",
    "sg:postcode":"48154",
    "sg:province":"MI",
    "wof:name":"Skelly & Zager DDS PC",
    "wof:placetype":"venue"
},
  "geometry": {"coordinates":[-83.367369,42.397555],"type":"Point"}
}