{
  "type": "Feature",
  "properties": {
    "iso:country":"US",
    "sg:address":"2950 Ziegler Rd",
    "sg:city":"Bay City",
    "sg:classifiers":[
        {
            "category":"Professional",
            "subcategory":"Advertising",
            "type":"Services"
        }
    ],
    "sg:phone":"+1 989 671 0732",
    "sg:postcode":"48706",
    "sg:province":"MI",
    "sg:tags":[
        "counselor",
        "agency"
    ],
    "wof:name":"Sam Britton Organization Inc",
    "wof:placetype":"venue"
},
  "geometry": {"coordinates":[-83.94066599999999,43.562072],"type":"Point"}
}