{
  "type": "Feature",
  "properties": {
    "iso:country":"US",
    "sg:address":"1989 Tobsal Ct",
    "sg:city":"Warren",
    "sg:classifiers":[
        {
            "category":"Professional",
            "type":"Services"
        },
        {
            "category":"Personal",
            "type":"Services"
        },
        {
            "category":"Home & Garden",
            "subcategory":"Hardware",
            "type":"Retail Goods"
        },
        {
            "category":"Food & Beverages",
            "subcategory":"Groceries & Convenience Stores",
            "type":"Retail Goods"
        }
    ],
    "sg:phone":"+1 586 755 6311",
    "sg:postcode":"48091",
    "sg:province":"MI",
    "sg:tags":[
        "closet",
        "cabinet",
        "garage",
        "designing",
        "organizer",
        "accessory",
        "remodeling"
    ],
    "sg:website":"www.greatlakesclosets.com",
    "wof:name":"Great Lakes Closet Company",
    "wof:placetype":"venue"
},
  "geometry": {"coordinates":[-83.083614,42.481954],"type":"Point"}
}