{
  "type": "Feature",
  "properties": {
    "iso:country":"US",
    "sg:address":"347 S Main St",
    "sg:city":"Ann Arbor",
    "sg:classifiers":[
        {
            "category":"Restaurant",
            "type":"Food & Drink"
        }
    ],
    "sg:menulink":"http://www.allmenus.com/mi/ann-arbor/16429-palio/menu/",
    "sg:phone":"+1 734 930 6156",
    "sg:postcode":"48104",
    "sg:province":"MI",
    "sg:tags":[
        "italian"
    ],
    "wof:name":"Palio",
    "wof:placetype":"venue"
},
  "geometry": {"coordinates":[-83.748653,42.278812],"type":"Point"}
}