{
  "type": "Feature",
  "properties": {
    "iso:country":"US",
    "sg:address":"700 McMillan Rd",
    "sg:city":"Owosso",
    "sg:classifiers":[
        {
            "category":"Manufacturing",
            "subcategory":"Metals",
            "type":"Manufacturing & Wholesale Goods"
        }
    ],
    "sg:phone":"+1 989 723 7930",
    "sg:postcode":"48867",
    "sg:province":"MI",
    "wof:name":"Clark Engineering",
    "wof:placetype":"venue"
},
  "geometry": {"coordinates":[-84.15495799999999,42.98538],"type":"Point"}
}