{
  "type": "Feature",
  "properties": {
    "iso:country":"US",
    "sg:address":"5530 Supply Rd",
    "sg:city":"Traverse City",
    "sg:classifiers":[
        {
            "category":"Retail",
            "subcategory":"Repair Shop",
            "type":"Services"
        }
    ],
    "sg:phone":"+1 231 947 5636",
    "sg:postcode":"49686",
    "sg:province":"MI",
    "wof:name":"Black Rock Forge",
    "wof:placetype":"venue"
},
  "geometry": {"coordinates":[-85.465648,44.695504],"type":"Point"}
}