{
  "type": "Feature",
  "properties": {
    "iso:country":"US",
    "sg:address":"2228 Alpine Ave NW",
    "sg:city":"Grand Rapids",
    "sg:classifiers":[
        {
            "category":"Banks & Credit Unions",
            "subcategory":"Bank",
            "type":"Services"
        }
    ],
    "sg:phone":"+1 616 364 7567",
    "sg:postcode":"49544",
    "sg:province":"MI",
    "sg:tags":[
        "federal"
    ],
    "wof:name":"Stampers Federal Credit Union",
    "wof:placetype":"venue"
},
  "geometry": {"coordinates":[-85.68848300000001,43.004625],"type":"Point"}
}