{
  "type": "Feature",
  "properties": {
    "iso:country":"US",
    "sg:address":"7734 Paw Paw Ave",
    "sg:city":"Watervliet",
    "sg:classifiers":[
        {
            "category":"Organizations",
            "subcategory":"Religious Organization",
            "type":"Services"
        }
    ],
    "sg:phone":"+1 269 463 8280",
    "sg:postcode":"49098",
    "sg:province":"MI",
    "sg:tags":[
        "church"
    ],
    "sg:website":"www.watervlietfmc.org",
    "wof:name":"Watervliet Free Methodist Chr",
    "wof:placetype":"venue"
},
  "geometry": {"coordinates":[-86.27076599999999,42.193127],"type":"Point"}
}