{
  "type": "Feature",
  "properties": {
    "iso:country":"US",
    "sg:address":"51158 Garret Rd",
    "sg:city":"Dowagiac",
    "sg:classifiers":[
        {
            "category":"Professional",
            "subcategory":"Management & Consulting",
            "type":"Services"
        },
        {
            "category":"Professional",
            "subcategory":"Computer Services",
            "type":"Services"
        }
    ],
    "sg:phone":"+1 269 424 6520",
    "sg:postcode":"49047",
    "sg:province":"MI",
    "sg:tags":[
        "consultant",
        "educational",
        "programing",
        "related",
        "custom"
    ],
    "sg:website":"www.lynjan.com",
    "wof:name":"Lynian Solutions",
    "wof:placetype":"venue"
},
  "geometry": {"coordinates":[-86.192674,42.0548],"type":"Point"}
}