{
  "type": "Feature",
  "properties": {
    "iso:country":"US",
    "sg:address":"509 Court St",
    "sg:city":"St Joseph",
    "sg:classifiers":[
        {
            "category":"Retail",
            "subcategory":"Laundry & Dry Cleaning",
            "type":"Services"
        }
    ],
    "sg:phone":"+1 269 982 2942",
    "sg:postcode":"49085",
    "sg:province":"MI",
    "sg:tags":[
        "cleaners",
        "rug",
        "carpet"
    ],
    "wof:name":"Rainbow International Carpet",
    "wof:placetype":"venue"
},
  "geometry": {"coordinates":[-86.481369,42.106088],"type":"Point"}
}