{
  "type": "Feature",
  "properties": {
    "iso:country":"US",
    "sg:address":"1651 S Bamber Rd",
    "sg:city":"Mount Pleasant",
    "sg:classifiers":[
        {
            "category":"Social Services",
            "subcategory":"Child Care",
            "type":"Services"
        }
    ],
    "sg:phone":"+1 989 775 2370",
    "sg:postcode":"48858",
    "sg:province":"MI",
    "sg:tags":[
        "day"
    ],
    "wof:name":"Mt Pleasant Cmty & Adult Ed",
    "wof:placetype":"venue"
},
  "geometry": {"coordinates":[-84.797827,43.616741],"type":"Point"}
}