{
  "type": "Feature",
  "properties": {
    "iso:country":"US",
    "sg:address":"224 S Huron Ave",
    "sg:city":"Harbor Beach",
    "sg:classifiers":[
        {
            "category":"Retail",
            "subcategory":"Laundry & Dry Cleaning",
            "type":"Services"
        }
    ],
    "sg:phone":"+1 989 479 3663",
    "sg:postcode":"48441",
    "sg:province":"MI",
    "sg:tags":[
        "cleaners"
    ],
    "wof:name":"Huron Laundry Cleaners",
    "wof:placetype":"venue"
},
  "geometry": {"coordinates":[-82.651156,43.84162],"type":"Point"}
}