{
  "type": "Feature",
  "properties": {
    "iso:country":"US",
    "sg:address":"45 Lexington Ave NW",
    "sg:city":"Grand Rapids",
    "sg:classifiers":[
        {
            "category":"Education",
            "subcategory":"School",
            "type":"Public Place"
        }
    ],
    "sg:phone":"+1 616 819 2792",
    "sg:postcode":"49504",
    "sg:province":"MI",
    "wof:name":"Bimaadiziwin Alternative High",
    "wof:placetype":"venue"
},
  "geometry": {"coordinates":[-85.683905,42.965134],"type":"Point"}
}