{
  "type": "Feature",
  "properties": {
    "iso:country":"US",
    "sg:address":"5661 Clintonville Rd",
    "sg:city":"Clarkston",
    "sg:classifiers":[
        {
            "category":"Recreation",
            "type":"Entertainment"
        }
    ],
    "sg:phone":"+1 248 391 8995",
    "sg:postcode":"48348",
    "sg:province":"MI",
    "sg:tags":[
        "club",
        "membership"
    ],
    "wof:name":"Alano Center-Oakland County",
    "wof:placetype":"venue"
},
  "geometry": {"coordinates":[-83.349639,42.725188],"type":"Point"}
}