{
  "type": "Feature",
  "properties": {
    "iso:country":"US",
    "sg:address":"3912 Peacock Rd",
    "sg:city":"Wellston",
    "sg:classifiers":[
        {
            "category":"Arts & Performance",
            "subcategory":"Theater",
            "type":"Entertainment"
        }
    ],
    "sg:phone":"+1 231 859 4858",
    "sg:postcode":"49689",
    "sg:province":"MI",
    "sg:tags":[
        "group"
    ],
    "wof:name":"Music Matters D J Service",
    "wof:placetype":"venue"
},
  "geometry": {"coordinates":[-85.911383,44.180408],"type":"Point"}
}