{
  "type": "Feature",
  "properties": {
    "iso:country":"US",
    "sg:address":"20500 W 13 Mile Rd",
    "sg:city":"Beverly Hills",
    "sg:classifiers":[
        {
            "category":"Education",
            "subcategory":"School",
            "type":"Public Place"
        }
    ],
    "sg:phone":"+1 248 203 3500",
    "sg:postcode":"48025",
    "sg:province":"MI",
    "sg:tags":[
        "high",
        "middle",
        "elementary"
    ],
    "wof:name":"Birmingham School District",
    "wof:placetype":"venue"
},
  "geometry": {"coordinates":[-83.246171,42.51664],"type":"Point"}
}