{
  "type": "Feature",
  "properties": {
    "iso:country":"US",
    "sg:address":"921 Emmet St",
    "sg:city":"Petoskey",
    "sg:classifiers":[
        {
            "category":"Food & Beverages",
            "subcategory":"Liquor & Beverages",
            "type":"Retail Goods"
        }
    ],
    "sg:phone":"+1 231 347 9909",
    "sg:postcode":"49770",
    "sg:province":"MI",
    "wof:name":"Tom & Dick's Grocery",
    "wof:placetype":"venue"
},
  "geometry": {"coordinates":[-84.958759,45.369221],"type":"Point"}
}