{
  "type": "Feature",
  "properties": {
    "iso:country":"US",
    "sg:address":"5490 Marsh View Ct",
    "sg:city":"Utica",
    "sg:classifiers":[
        {
            "category":"Building & Trades",
            "subcategory":"Construction",
            "type":"Services"
        }
    ],
    "sg:phone":"+1 586 786 5459",
    "sg:postcode":"48316",
    "sg:province":"MI",
    "sg:tags":[
        "home",
        "contractor"
    ],
    "wof:name":"Emh Building Co",
    "wof:placetype":"venue"
},
  "geometry": {"coordinates":[-83.06142699999999,42.708848],"type":"Point"}
}