{
  "type": "Feature",
  "properties": {
    "iso:country":"US",
    "sg:address":"820 Monroe Ave NW",
    "sg:city":"Grand Rapids",
    "sg:classifiers":[
        {
            "category":"Professional",
            "subcategory":"Computer Services",
            "type":"Services"
        }
    ],
    "sg:phone":"+1 616 454 2357",
    "sg:postcode":"49503",
    "sg:province":"MI",
    "sg:tags":[
        "website",
        "development",
        "medium",
        "design",
        "interactive"
    ],
    "sg:website":"www.fusionary.com",
    "wof:name":"Fusionary Media Inc",
    "wof:placetype":"venue"
},
  "geometry": {"coordinates":[-85.672439,42.977886],"type":"Point"}
}