{
  "type": "Feature",
  "properties": {
    "iso:country":"US",
    "sg:address":"1090 Cherry Creek Rd",
    "sg:city":"Marquette",
    "sg:classifiers":[
        {
            "category":"Professional",
            "subcategory":"Management & Consulting",
            "type":"Services"
        }
    ],
    "sg:phone":"+1 906 249 9565",
    "sg:postcode":"49855",
    "sg:province":"MI",
    "sg:tags":[
        "retail",
        "direct",
        "sales"
    ],
    "wof:name":"Mary Vandemark 7",
    "wof:placetype":"venue"
},
  "geometry": {"coordinates":[-87.355391,46.424712],"type":"Point"}
}