{
  "type": "Feature",
  "properties": {
    "iso:country":"US",
    "sg:address":"2688 Barkwood Ln",
    "sg:city":"Kalamazoo",
    "sg:classifiers":[
        {
            "category":"Shopping",
            "type":"Retail Goods"
        }
    ],
    "sg:phone":"+1 269 345 8035",
    "sg:postcode":"49004",
    "sg:province":"MI",
    "sg:tags":[
        "cosmetic",
        "perfume"
    ],
    "wof:name":"Merle Norman Cosmetics",
    "wof:placetype":"venue"
},
  "geometry": {"coordinates":[-85.62040399999999,42.331922],"type":"Point"}
}