{
  "type": "Feature",
  "properties": {
    "iso:country":"US",
    "sg:address":"2221 Livernois Rd",
    "sg:city":"Troy",
    "sg:classifiers":[
        {
            "category":"Community Center",
            "type":"Public Place"
        }
    ],
    "sg:phone":"+1 248 250 9472",
    "sg:postcode":"48083",
    "sg:province":"MI",
    "sg:tags":[
        "medical"
    ],
    "wof:name":"Mathews Medical Center",
    "wof:placetype":"venue"
},
  "geometry": {"coordinates":[-83.147312,42.554854],"type":"Point"}
}