{
  "type": "Feature",
  "properties": {
    "iso:country":"US",
    "sg:address":"2598 S Duffield Rd",
    "sg:city":"Sumner",
    "sg:classifiers":[
        {
            "category":"Building & Trades",
            "subcategory":"Landscaping Services",
            "type":"Services"
        }
    ],
    "sg:phone":"+1 989 875 7025",
    "sg:postcode":"48889",
    "sg:province":"MI",
    "wof:name":"Leps Lawn Care",
    "wof:placetype":"venue"
},
  "geometry": {"coordinates":[-84.782472,43.254789],"type":"Point"}
}