{
  "type": "Feature",
  "properties": {
    "iso:country":"US",
    "sg:address":"1264 US Hwy 31",
    "sg:city":"Petoskey",
    "sg:classifiers":[
        {
            "category":"Restaurant",
            "type":"Food & Drink"
        }
    ],
    "sg:phone":"+1 231 347 0550",
    "sg:postcode":"49770",
    "sg:province":"MI",
    "wof:name":"Burger King",
    "wof:placetype":"venue"
},
  "geometry": {"coordinates":[-84.982719,45.370029],"type":"Point"}
}