{
  "type": "Feature",
  "properties": {
    "iso:country":"US",
    "sg:address":"202 US Hwy 41",
    "sg:city":"Stephenson",
    "sg:classifiers":[
        {
            "category":"Education",
            "subcategory":"School",
            "type":"Public Place"
        },
        {
            "category":"Social Services",
            "type":"Services"
        }
    ],
    "sg:phone":"+1 906 753 4393",
    "sg:postcode":"49887",
    "sg:province":"MI",
    "wof:name":"Neighborhood Family Center",
    "wof:placetype":"venue"
},
  "geometry": {"coordinates":[-87.605707,45.417028],"type":"Point"}
}