{
  "type": "Feature",
  "properties": {
    "iso:country":"US",
    "sg:address":"333 W Nepessing St",
    "sg:city":"Lapeer",
    "sg:classifiers":[
        {
            "category":"Shopping",
            "type":"Retail Goods"
        }
    ],
    "sg:phone":"+1 810 245 1880",
    "sg:postcode":"48446",
    "sg:province":"MI",
    "sg:tags":[
        "album",
        "photo",
        "frame"
    ],
    "wof:name":"Crystal Scrapworks",
    "wof:placetype":"venue"
},
  "geometry": {"coordinates":[-83.31185600000001,43.05402],"type":"Point"}
}