{
  "type": "Feature",
  "properties": {
    "iso:country":"US",
    "sg:address":"6765 Pine Way Dr",
    "sg:city":"Troy",
    "sg:classifiers":[
        {
            "category":"Manufacturing",
            "subcategory":"Printing",
            "type":"Manufacturing & Wholesale Goods"
        }
    ],
    "sg:phone":"+1 248 585 5530",
    "sg:postcode":"48098",
    "sg:province":"MI",
    "sg:tags":[
        "printer"
    ],
    "wof:name":"Atlantic Press",
    "wof:placetype":"venue"
},
  "geometry": {"coordinates":[-83.1768,42.616217],"type":"Point"}
}