{
  "type": "Feature",
  "properties": {
    "iso:country":"US",
    "sg:address":"521 Court St",
    "sg:city":"Saint Joseph",
    "sg:classifiers":[
        {
            "category":"Banks & Credit Unions",
            "subcategory":"Financial Services",
            "type":"Services"
        }
    ],
    "sg:phone":"+1 269 985 9225",
    "sg:postcode":"49085",
    "sg:province":"MI",
    "sg:tags":[
        "investor"
    ],
    "wof:name":"James Ashmead Jr Investments",
    "wof:placetype":"venue"
},
  "geometry": {"coordinates":[-86.48131100000001,42.106184],"type":"Point"}
}