{
  "type": "Feature",
  "properties": {
    "iso:country":"US",
    "sg:address":"21700 Northwestern Hwy Ste 750",
    "sg:city":"Southfield",
    "sg:classifiers":[
        {
            "category":"Health Services",
            "subcategory":"Clinic",
            "type":"Services"
        }
    ],
    "sg:phone":"+1 248 559 5558",
    "sg:postcode":"48075",
    "sg:province":"MI",
    "sg:tags":[
        "counseling",
        "mental"
    ],
    "sg:website":"www.oakpsych.com",
    "wof:name":"Oakland Psychological Clinic PC",
    "wof:placetype":"venue"
},
  "geometry": {"coordinates":[-83.210503,42.4515],"type":"Point"}
}