{
  "type": "Feature",
  "properties": {
    "iso:country":"US",
    "sg:address":"414 Maple St",
    "sg:city":"Wyandotte",
    "sg:classifiers":[
        {
            "category":"Shopping",
            "subcategory":"Gifts & Souvenirs",
            "type":"Retail Goods"
        }
    ],
    "sg:phone":"+1 734 347 1622",
    "sg:postcode":"48192",
    "sg:province":"MI",
    "wof:name":"Bearden Soap Co",
    "wof:placetype":"venue"
},
  "geometry": {"coordinates":[-83.156164,42.202082],"type":"Point"}
}