{
  "type": "Feature",
  "properties": {
    "iso:country":"US",
    "sg:address":"5956 State St",
    "sg:city":"Kingston",
    "sg:classifiers":[
        {
            "category":"Restaurant",
            "type":"Food & Drink"
        }
    ],
    "sg:phone":"+1 989 683 9304",
    "sg:postcode":"48741",
    "sg:province":"MI",
    "wof:name":"K T Tavern",
    "wof:placetype":"venue"
},
  "geometry": {"coordinates":[-83.187669,43.41285],"type":"Point"}
}