{
  "type": "Feature",
  "properties": {
    "iso:country":"US",
    "sg:address":"3581 Swan Creek Dr",
    "sg:city":"Portage",
    "sg:classifiers":[
        {
            "category":"Real Estate",
            "subcategory":"Developer",
            "type":"Services"
        }
    ],
    "sg:phone":"+1 269 385 5819",
    "sg:postcode":"49024",
    "sg:province":"MI",
    "wof:name":"Process & Product Development",
    "wof:placetype":"venue"
},
  "geometry": {"coordinates":[-85.631287,42.242942],"type":"Point"}
}