{
  "type": "Feature",
  "properties": {
    "iso:country":"US",
    "sg:address":"1317 Mason St",
    "sg:city":"Dansville",
    "sg:classifiers":[
        {
            "category":"Social Services",
            "subcategory":"Child Care",
            "type":"Services"
        }
    ],
    "sg:phone":"+1 517 623 6904",
    "sg:postcode":"48819",
    "sg:province":"MI",
    "sg:tags":[
        "kindergarten",
        "academic",
        "school"
    ],
    "wof:name":"Dansville Co-Op Preschool",
    "wof:placetype":"venue"
},
  "geometry": {"coordinates":[-84.30314799999999,42.555931],"type":"Point"}
}