{
  "type": "Feature",
  "properties": {
    "iso:country":"US",
    "sg:address":"29355 Northwestern Hwy",
    "sg:city":"Southfield",
    "sg:classifiers":[
        {
            "category":"Professional",
            "subcategory":"Lawyer & Legal Services",
            "type":"Services"
        },
        {
            "category":"Personal",
            "type":"Services"
        }
    ],
    "sg:phone":"+1 248 353 1595",
    "sg:postcode":"48034",
    "sg:province":"MI",
    "sg:tags":[
        "attorney",
        "referral"
    ],
    "wof:name":"Metro Detroit Lawyers",
    "wof:placetype":"venue"
},
  "geometry": {"coordinates":[-83.31451,42.504421],"type":"Point"}
}