{
  "type": "Feature",
  "properties": {
    "iso:country":"US",
    "sg:address":"23667 Greening Ct",
    "sg:city":"Novi",
    "sg:classifiers":[
        {
            "category":"Professional",
            "type":"Services"
        }
    ],
    "sg:phone":"+1 248 349 7391",
    "sg:postcode":"48375",
    "sg:province":"MI",
    "sg:tags":[
        "writer"
    ],
    "wof:name":"Michael Thomas Writing-Editing",
    "wof:placetype":"venue"
},
  "geometry": {"coordinates":[-83.481233,42.462645],"type":"Point"}
}