{
  "type": "Feature",
  "properties": {
    "iso:country":"US",
    "sg:address":"3121 Hedgewood Ln",
    "sg:city":"Rochester",
    "sg:classifiers":[
        {
            "category":"Insurance",
            "subcategory":"Insurance Agent",
            "type":"Services"
        }
    ],
    "sg:phone":"+1 248 475 1803",
    "sg:postcode":"48309",
    "sg:province":"MI",
    "wof:name":"Statewide Insurance Agency",
    "wof:placetype":"venue"
},
  "geometry": {"coordinates":[-83.196056,42.648323],"type":"Point"}
}