{
  "type": "Feature",
  "properties": {
    "iso:country":"US",
    "sg:address":"775 S Maple Rd",
    "sg:city":"Ann Arbor",
    "sg:classifiers":[
        {
            "category":"Social Services",
            "subcategory":"Child Care",
            "type":"Services"
        }
    ],
    "sg:phone":"+1 734 663 7496",
    "sg:postcode":"48103",
    "sg:province":"MI",
    "sg:tags":[
        "day"
    ],
    "wof:name":"Discovery Center Inc",
    "wof:placetype":"venue"
},
  "geometry": {"coordinates":[-83.779937,42.272694],"type":"Point"}
}