{
  "type": "Feature",
  "properties": {
    "iso:country":"US",
    "sg:address":"4599 Borland St",
    "sg:city":"West Bloomfield",
    "sg:classifiers":[
        {
            "category":"Personal",
            "subcategory":"Beauty Salon",
            "type":"Services"
        }
    ],
    "sg:phone":"+1 248 366 9519",
    "sg:postcode":"48323",
    "sg:province":"MI",
    "sg:tags":[
        "shop"
    ],
    "wof:name":"Facials By Natasha",
    "wof:placetype":"venue"
},
  "geometry": {"coordinates":[-83.416478,42.568595],"type":"Point"}
}