{
  "type": "Feature",
  "properties": {
    "iso:country":"US",
    "sg:address":"1420 Merle Ave",
    "sg:city":"Burton",
    "sg:classifiers":[
        {
            "category":"Retail",
            "subcategory":"Repair Shop",
            "type":"Services"
        }
    ],
    "sg:phone":"+1 810 742 5383",
    "sg:postcode":"48509",
    "sg:province":"MI",
    "wof:name":"Skips Towing & Lock Out",
    "wof:placetype":"venue"
},
  "geometry": {"coordinates":[-83.602812,43.007898],"type":"Point"}
}