{
  "type": "Feature",
  "properties": {
    "iso:country":"US",
    "sg:address":"5516 Torrey Rd",
    "sg:city":"Flint",
    "sg:classifiers":[
        {
            "category":"Health Services",
            "subcategory":"Doctor",
            "type":"Services"
        }
    ],
    "sg:phone":"+1 810 232 2515",
    "sg:postcode":"48507",
    "sg:province":"MI",
    "sg:tags":[
        "dentist"
    ],
    "wof:name":"David L Ewing DDS",
    "wof:placetype":"venue"
},
  "geometry": {"coordinates":[-83.73182300000001,42.944004],"type":"Point"}
}