{
  "type": "Feature",
  "properties": {
    "iso:country":"US",
    "sg:address":"305 South Dr",
    "sg:city":"Grayling",
    "sg:classifiers":[
        {
            "category":"Ice Cream",
            "type":"Food & Drink"
        }
    ],
    "sg:menulink":"http://www.allmenus.com/mi/grayling/168559-dairy-queen/menu/",
    "sg:phone":"+1 989 348 9511",
    "sg:postcode":"49738",
    "sg:province":"MI",
    "sg:tags":[
        "burger",
        "american"
    ],
    "wof:name":"Dairy Queen",
    "wof:placetype":"venue"
},
  "geometry": {"coordinates":[-84.71062999999999,44.67508],"type":"Point"}
}