{
  "type": "Feature",
  "properties": {
    "iso:country":"US",
    "sg:address":"1515 Langley St SE",
    "sg:city":"Grand Rapids",
    "sg:classifiers":[
        {
            "category":"Organizations",
            "subcategory":"Religious Organization",
            "type":"Services"
        }
    ],
    "sg:phone":"+1 616 281 1285",
    "sg:postcode":"49508",
    "sg:province":"MI",
    "wof:name":"Joy Ministries",
    "wof:placetype":"venue"
},
  "geometry": {"coordinates":[-85.62900399999999,42.886655],"type":"Point"}
}