{
  "type": "Feature",
  "properties": {
    "iso:country":"US",
    "sg:address":"20505 Martin Rd",
    "sg:city":"St Clair Shores",
    "sg:classifiers":[
        {
            "category":"Organizations",
            "subcategory":"Religious Organization",
            "type":"Services"
        }
    ],
    "sg:phone":"+1 586 771 7630",
    "sg:postcode":"48081",
    "sg:province":"MI",
    "sg:tags":[
        "church"
    ],
    "wof:name":"Martin Road Gospel Chapel",
    "wof:placetype":"venue"
},
  "geometry": {"coordinates":[-82.910388,42.502849],"type":"Point"}
}