{
  "type": "Feature",
  "properties": {
    "iso:country":"US",
    "sg:address":"10964 Bird Rd",
    "sg:city":"Dowling",
    "sg:classifiers":[
        {
            "category":"Organizations",
            "subcategory":"Labor Organization",
            "type":"Services"
        }
    ],
    "sg:phone":"+1 269 758 3432",
    "sg:postcode":"49050",
    "sg:province":"MI",
    "wof:name":"Bctgm Local 66 G",
    "wof:placetype":"venue"
},
  "geometry": {"coordinates":[-85.21817900000001,42.499413],"type":"Point"}
}