{
  "type": "Feature",
  "properties": {
    "iso:country":"US",
    "sg:address":"8701 48th Ave",
    "sg:city":"Hudsonville",
    "sg:classifiers":[
        {
            "category":"Building & Trades",
            "subcategory":"Landscaping Services",
            "type":"Services"
        }
    ],
    "sg:phone":"+1 616 481 3058",
    "sg:postcode":"49426",
    "sg:province":"MI",
    "sg:tags":[
        "landscape",
        "contractor"
    ],
    "wof:name":"Frye Custom Lawn Care",
    "wof:placetype":"venue"
},
  "geometry": {"coordinates":[-85.902795,42.922216],"type":"Point"}
}