{
  "type": "Feature",
  "properties": {
    "iso:country":"US",
    "sg:address":"705 N Main St",
    "sg:city":"Clawson",
    "sg:classifiers":[
        {
            "category":"Retail",
            "subcategory":"Funeral Services",
            "type":"Services"
        }
    ],
    "sg:phone":"+1 248 435 9010",
    "sg:postcode":"48017",
    "sg:province":"MI",
    "sg:tags":[
        "director",
        "cemetery"
    ],
    "sg:website":"www.gramerfuneralhome.com",
    "wof:name":"Gramer Funeral Home",
    "wof:placetype":"venue"
},
  "geometry": {"coordinates":[-83.14679700000001,42.539799],"type":"Point"}
}