{
  "type": "Feature",
  "properties": {
    "iso:country":"US",
    "sg:address":"17039 Mackinaw Trl",
    "sg:city":"Le Roy",
    "sg:classifiers":[
        {
            "category":"Retail",
            "subcategory":"Auto Repair",
            "type":"Services"
        }
    ],
    "sg:phone":"+1 231 768 5199",
    "sg:postcode":"49655",
    "sg:province":"MI",
    "sg:tags":[
        "general"
    ],
    "wof:name":"Ricks Automotive Center",
    "wof:placetype":"venue"
},
  "geometry": {"coordinates":[-85.44391899999999,44.073374],"type":"Point"}
}