{
  "type": "Feature",
  "properties": {
    "iso:country":"US",
    "sg:address":"515 S Parker St",
    "sg:city":"Marine City",
    "sg:classifiers":[
        {
            "category":"Shopping",
            "subcategory":"Tobacco",
            "type":"Retail Goods"
        }
    ],
    "sg:phone":"+1 810 765 5758",
    "sg:postcode":"48039",
    "sg:province":"MI",
    "sg:tags":[
        "cigarette",
        "cigar",
        "dealer"
    ],
    "wof:name":"Dar Dees Smoke Shop",
    "wof:placetype":"venue"
},
  "geometry": {"coordinates":[-82.500362,42.714535],"type":"Point"}
}