{
  "type": "Feature",
  "properties": {
    "iso:country":"US",
    "sg:address":"800 N Connecticut Ave",
    "sg:city":"Royal Oak",
    "sg:classifiers":[
        {
            "category":"Building & Trades",
            "subcategory":"Landscaping Services",
            "type":"Services"
        }
    ],
    "sg:phone":"+1 248 288 3826",
    "sg:postcode":"48067",
    "sg:province":"MI",
    "sg:tags":[
        "tree"
    ],
    "wof:name":"S & J Tree Care",
    "wof:placetype":"venue"
},
  "geometry": {"coordinates":[-83.12730500000001,42.498084],"type":"Point"}
}