{
  "type": "Feature",
  "properties": {
    "iso:country":"US",
    "sg:address":"8855 Gratiot Rd",
    "sg:city":"Saginaw",
    "sg:classifiers":[
        {
            "category":"Personal",
            "subcategory":"Barber",
            "type":"Services"
        }
    ],
    "sg:phone":"+1 989 781 0555",
    "sg:postcode":"48609",
    "sg:province":"MI",
    "sg:tags":[
        "shop"
    ],
    "wof:name":"Golden Knight",
    "wof:placetype":"venue"
},
  "geometry": {"coordinates":[-84.08851900000001,43.416004],"type":"Point"}
}