{
  "type": "Feature",
  "properties": {
    "iso:country":"US",
    "sg:address":"664 Ajax Dr",
    "sg:city":"Madison Heights",
    "sg:classifiers":[
        {
            "category":"Manufacturing",
            "subcategory":"Tools & Machinery",
            "type":"Manufacturing & Wholesale Goods"
        }
    ],
    "sg:phone":"+1 248 585 2344",
    "sg:postcode":"48071",
    "sg:province":"MI",
    "sg:tags":[
        "mold"
    ],
    "wof:name":"Delta Precision Inc",
    "wof:placetype":"venue"
},
  "geometry": {"coordinates":[-83.11062099999999,42.511456],"type":"Point"}
}