{
  "type": "Feature",
  "properties": {
    "iso:country":"US",
    "sg:address":"1182 W Boston Blvd",
    "sg:city":"Detroit",
    "sg:classifiers":[
        {
            "category":"Real Estate",
            "subcategory":"Real Estate Agent",
            "type":"Services"
        }
    ],
    "sg:phone":"+1 313 869 9179",
    "sg:postcode":"48202",
    "sg:province":"MI",
    "wof:name":"Rlw Realty Limited Partnership",
    "wof:placetype":"venue"
},
  "geometry": {"coordinates":[-83.095865,42.383813],"type":"Point"}
}