{
  "type": "Feature",
  "properties": {
    "iso:country":"US",
    "sg:address":"1117 Pipestone Rd",
    "sg:city":"Benton Harbor",
    "sg:classifiers":[
        {
            "category":"Autos & Motor Vehicles",
            "subcategory":"Fuel & Gas Station",
            "type":"Retail Goods"
        }
    ],
    "sg:phone":"+1 269 925 5009",
    "sg:postcode":"49022",
    "sg:province":"MI",
    "sg:tags":[
        "oil"
    ],
    "wof:name":"Total Gas Station",
    "wof:placetype":"venue"
},
  "geometry": {"coordinates":[-86.43523500000001,42.098023],"type":"Point"}
}