{
  "type": "Feature",
  "properties": {
    "iso:country":"US",
    "sg:address":"137 Hillsborough St",
    "sg:city":"Hartford",
    "sg:classifiers":[
        {
            "category":"Retail",
            "subcategory":"Auto Rental",
            "type":"Services"
        }
    ],
    "sg:phone":"+1 269 621 6216",
    "sg:postcode":"49057",
    "sg:province":"MI",
    "sg:tags":[
        "equipment",
        "construction",
        "truck",
        "trailer"
    ],
    "wof:name":"Southwest Transport Co",
    "wof:placetype":"venue"
},
  "geometry": {"coordinates":[-86.169335,42.209203],"type":"Point"}
}