{
  "type": "Feature",
  "properties": {
    "iso:country":"US",
    "sg:address":"16246 Ilene St",
    "sg:city":"Detroit",
    "sg:classifiers":[
        {
            "category":"Shopping",
            "subcategory":"Gifts & Souvenirs",
            "type":"Retail Goods"
        }
    ],
    "sg:phone":"+1 313 863 0018",
    "sg:postcode":"48221",
    "sg:province":"MI",
    "wof:name":"Gifts Ave",
    "wof:placetype":"venue"
},
  "geometry": {"coordinates":[-83.162167,42.411212],"type":"Point"}
}