{
  "type": "Feature",
  "properties": {
    "iso:country":"US",
    "sg:address":"2330 Mellowood Dr",
    "sg:city":"Sterling Heights",
    "sg:classifiers":[
        {
            "category":"Professional",
            "type":"Services"
        }
    ],
    "sg:phone":"+1 586 264 2888",
    "sg:postcode":"48310",
    "sg:province":"MI",
    "wof:name":"Paul Swanlund",
    "wof:placetype":"venue"
},
  "geometry": {"coordinates":[-83.085504,42.581071],"type":"Point"}
}