{
  "type": "Feature",
  "properties": {
    "iso:country":"US",
    "sg:address":"6273 Miramonte Dr NE",
    "sg:city":"Rockford",
    "sg:classifiers":[
        {
            "category":"Professional",
            "subcategory":"Management & Consulting",
            "type":"Services"
        }
    ],
    "sg:phone":"+1 616 874 6341",
    "sg:postcode":"49341",
    "sg:province":"MI",
    "sg:tags":[
        "business"
    ],
    "wof:name":"Telephony Consulting Services",
    "wof:placetype":"venue"
},
  "geometry": {"coordinates":[-85.51175499999999,43.097217],"type":"Point"}
}