{
  "type": "Feature",
  "properties": {
    "iso:country":"US",
    "sg:address":"11287 Braden Rd",
    "sg:city":"Byron",
    "sg:classifiers":[
        {
            "category":"Social Services",
            "subcategory":"Child Care",
            "type":"Services"
        }
    ],
    "sg:phone":"+1 810 266 5123",
    "sg:postcode":"48418",
    "sg:province":"MI",
    "sg:tags":[
        "day"
    ],
    "wof:name":"Joyce Fearson",
    "wof:placetype":"venue"
},
  "geometry": {"coordinates":[-83.941368,42.794983],"type":"Point"}
}