{
  "type": "Feature",
  "properties": {
    "iso:country":"US",
    "sg:address":"21477 Bridge St",
    "sg:city":"Southfield",
    "sg:classifiers":[
        {
            "category":"Shopping",
            "subcategory":"Stationery & Office Supplies",
            "type":"Retail Goods"
        }
    ],
    "sg:phone":"+1 248 355 3006",
    "sg:postcode":"48033",
    "sg:province":"MI",
    "sg:tags":[
        "labels-plastic",
        "foil",
        "metal"
    ],
    "sg:website":"http://www.schreiner-protech-na.com",
    "wof:name":"Schreiner Protech",
    "wof:placetype":"venue"
},
  "geometry": {"coordinates":[-83.284254,42.448968],"type":"Point"}
}