{
  "type": "Feature",
  "properties": {
    "iso:country":"US",
    "sg:address":"114 W Main St",
    "sg:city":"Pinckney",
    "sg:classifiers":[
        {
            "category":"Home & Garden",
            "subcategory":"Hardware",
            "type":"Retail Goods"
        }
    ],
    "sg:phone":"+1 734 878 2000",
    "sg:postcode":"48169",
    "sg:province":"MI",
    "wof:name":"Pinckney Hardware",
    "wof:placetype":"venue"
},
  "geometry": {"coordinates":[-83.947445,42.45691],"type":"Point"}
}