{
  "type": "Feature",
  "properties": {
    "iso:country":"US",
    "sg:address":"10874 Valley View Dr",
    "sg:city":"Brighton",
    "sg:classifiers":[
        {
            "category":"Building & Trades",
            "subcategory":"Construction",
            "type":"Services"
        }
    ],
    "sg:phone":"+1 810 844 0722",
    "sg:postcode":"48116",
    "sg:province":"MI",
    "sg:tags":[
        "general",
        "contractor"
    ],
    "wof:name":"Biondi Building",
    "wof:placetype":"venue"
},
  "geometry": {"coordinates":[-83.736909,42.514212],"type":"Point"}
}