{
  "type": "Feature",
  "properties": {
    "iso:country":"US",
    "sg:address":"721 Mount Pleasant Ave",
    "sg:city":"Ann Arbor",
    "sg:classifiers":[
        {
            "category":"Social Services",
            "subcategory":"Child Care",
            "type":"Services"
        }
    ],
    "sg:phone":"+1 734 662 2739",
    "sg:postcode":"48103",
    "sg:province":"MI",
    "sg:tags":[
        "day"
    ],
    "wof:name":"Gretchens House 2",
    "wof:placetype":"venue"
},
  "geometry": {"coordinates":[-83.76085399999999,42.271692],"type":"Point"}
}