{
  "type": "Feature",
  "properties": {
    "iso:country":"US",
    "sg:address":"4001 N Saginaw St",
    "sg:city":"Flint",
    "sg:classifiers":[
        {
            "category":"Health Services",
            "subcategory":"Clinic",
            "type":"Services"
        }
    ],
    "sg:phone":"+1 810 789 9141",
    "sg:postcode":"48505",
    "sg:province":"MI",
    "sg:tags":[
        "center",
        "care"
    ],
    "wof:name":"Hamilton Family Health Center",
    "wof:placetype":"venue"
},
  "geometry": {"coordinates":[-83.69376,43.051558],"type":"Point"}
}