{
  "type": "Feature",
  "properties": {
    "iso:country":"US",
    "sg:address":"50 Louis St NW",
    "sg:city":"Grand Rapids",
    "sg:classifiers":[
        {
            "category":"Professional",
            "subcategory":"Management & Consulting",
            "type":"Services"
        }
    ],
    "sg:phone":"+1 616 233 8193",
    "sg:postcode":"49503",
    "sg:province":"MI",
    "wof:name":"M-Com Inc",
    "wof:placetype":"venue"
},
  "geometry": {"coordinates":[-85.67073600000001,42.964244],"type":"Point"}
}