{
  "type": "Feature",
  "properties": {
    "iso:country":"US",
    "sg:address":"1010 26th Ave",
    "sg:city":"Menominee",
    "sg:classifiers":[
        {
            "category":"Retail",
            "subcategory":"Auto Repair",
            "type":"Services"
        }
    ],
    "sg:phone":"+1 906 863 9901",
    "sg:postcode":"49858",
    "sg:province":"MI",
    "sg:tags":[
        "body",
        "automobile",
        "painting"
    ],
    "sg:website":"www.lindnersorenson.com",
    "wof:name":"Linder & Sorenson Inc",
    "wof:placetype":"venue"
},
  "geometry": {"coordinates":[-87.61709,45.122517],"type":"Point"}
}