{
  "type": "Feature",
  "properties": {
    "iso:country":"US",
    "sg:address":"11570 la Salle Blvd",
    "sg:city":"Detroit",
    "sg:classifiers":[
        {
            "category":"Professional",
            "type":"Services"
        }
    ],
    "sg:phone":"+1 313 883 4940",
    "sg:postcode":"48206",
    "sg:province":"MI",
    "wof:name":"Amolod",
    "wof:placetype":"venue"
},
  "geometry": {"coordinates":[-83.08327199999999,42.348451],"type":"Point"}
}