{
  "type": "Feature",
  "properties": {
    "iso:country":"US",
    "sg:address":"612 N Trumbull St",
    "sg:city":"Bay City",
    "sg:classifiers":[
        {
            "category":"Retail",
            "subcategory":"Repair Shop",
            "type":"Services"
        }
    ],
    "sg:phone":"+1 989 893 7213",
    "sg:postcode":"48708",
    "sg:province":"MI",
    "sg:tags":[
        "plumbing",
        "drain",
        "cleaning",
        "sewer"
    ],
    "wof:name":"Reliable Sewer Svc",
    "wof:placetype":"venue"
},
  "geometry": {"coordinates":[-83.86717899999999,43.595262],"type":"Point"}
}