{
  "type": "Feature",
  "properties": {
    "iso:country":"US",
    "sg:address":"2820 Haynor Rd",
    "sg:city":"Ionia",
    "sg:classifiers":[
        {
            "category":"Professional",
            "subcategory":"Business Services",
            "type":"Services"
        }
    ],
    "sg:phone":"+1 616 761 4444",
    "sg:postcode":"48846",
    "sg:province":"MI",
    "sg:tags":[
        "durable",
        "good"
    ],
    "wof:name":"R&M Fire Extinguishers & Svcs",
    "wof:placetype":"venue"
},
  "geometry": {"coordinates":[-85.11456200000001,43.03239],"type":"Point"}
}