{
  "type": "Feature",
  "properties": {
    "iso:country":"US",
    "sg:address":"42000 Carousel St",
    "sg:city":"Novi",
    "sg:classifiers":[
        {
            "category":"Professional",
            "type":"Services"
        }
    ],
    "sg:phone":"+1 248 624 2200",
    "sg:postcode":"48377",
    "sg:province":"MI",
    "sg:tags":[
        "establishment"
    ],
    "wof:name":"Community Sales Inc",
    "wof:placetype":"venue"
},
  "geometry": {"coordinates":[-83.460887,42.51118],"type":"Point"}
}