{
  "type": "Feature",
  "properties": {
    "iso:country":"US",
    "sg:address":"231 N Shiawassee St",
    "sg:city":"Corunna",
    "sg:classifiers":[
        {
            "category":"Shopping",
            "subcategory":"Used Merchandise",
            "type":"Retail Goods"
        }
    ],
    "sg:phone":"+1 989 743 5744",
    "sg:postcode":"48817",
    "sg:province":"MI",
    "sg:tags":[
        "shop",
        "consignment"
    ],
    "wof:name":"Ken's Consignment Resale Shop",
    "wof:placetype":"venue"
},
  "geometry": {"coordinates":[-84.117997,42.981583],"type":"Point"}
}