{
  "type": "Feature",
  "properties": {
    "iso:country":"US",
    "sg:address":"14925 Livernois Ave",
    "sg:city":"Detroit",
    "sg:classifiers":[
        {
            "category":"Bars & Pubs",
            "subcategory":"Nightclub",
            "type":"Food & Drink"
        }
    ],
    "sg:phone":"+1 313 861 5340",
    "sg:postcode":"48238",
    "sg:province":"MI",
    "sg:tags":[
        "nightlife"
    ],
    "wof:name":"Tropical Hut Lounge",
    "wof:placetype":"venue"
},
  "geometry": {"coordinates":[-83.140297,42.399899],"type":"Point"}
}