{
  "type": "Feature",
  "properties": {
    "iso:country":"US",
    "sg:address":"8311 Wilson St",
    "sg:city":"Utica",
    "sg:classifiers":[
        {
            "category":"Organizations",
            "subcategory":"Community Association",
            "type":"Services"
        }
    ],
    "sg:phone":"+1 586 781 9109",
    "sg:postcode":"48316",
    "sg:province":"MI",
    "sg:tags":[
        "building",
        "nonresidential"
    ],
    "wof:name":"V F W Post 4659",
    "wof:placetype":"venue"
},
  "geometry": {"coordinates":[-83.030168,42.687321],"type":"Point"}
}