{
  "type": "Feature",
  "properties": {
    "iso:country":"US",
    "sg:address":"951 Whitmore Rd",
    "sg:city":"Detroit",
    "sg:classifiers":[
        {
            "category":"Personal",
            "type":"Services"
        }
    ],
    "sg:phone":"+1 313 345 4591",
    "sg:postcode":"48203",
    "sg:province":"MI",
    "sg:tags":[
        "mover"
    ],
    "wof:name":"Eight Mile Moving Co",
    "wof:placetype":"venue"
},
  "geometry": {"coordinates":[-83.116168,42.420238],"type":"Point"}
}