{
  "type": "Feature",
  "properties": {
    "iso:country":"US",
    "sg:address":"1414 W Fair Ave",
    "sg:city":"Marquette",
    "sg:classifiers":[
        {
            "category":"Banks & Credit Unions",
            "subcategory":"Bank",
            "type":"Services"
        }
    ],
    "sg:phone":"+1 906 228 1290",
    "sg:postcode":"49855",
    "sg:province":"MI",
    "sg:tags":[
        "federal",
        "savings",
        "institution"
    ],
    "wof:name":"Wells Fargo Bank N A",
    "wof:placetype":"venue"
},
  "geometry": {"coordinates":[-87.41648000000001,46.556861],"type":"Point"}
}