{
  "type": "Feature",
  "properties": {
    "iso:country":"US",
    "sg:address":"2821 E Highland Rd",
    "sg:city":"Highland",
    "sg:classifiers":[
        {
            "category":"Cinema",
            "subcategory":"Movie Rental",
            "type":"Entertainment"
        }
    ],
    "sg:phone":"+1 248 889 3733",
    "sg:postcode":"48356",
    "sg:province":"MI",
    "sg:tags":[
        "leasing",
        "video",
        "disc",
        "tape"
    ],
    "wof:name":"Video Palace",
    "wof:placetype":"venue"
},
  "geometry": {"coordinates":[-83.571832,42.654044],"type":"Point"}
}