{
  "type": "Feature",
  "properties": {
    "iso:country":"US",
    "sg:address":"388 W Predmore Rd",
    "sg:city":"Oakland",
    "sg:classifiers":[
        {
            "category":"Recreation",
            "type":"Entertainment"
        }
    ],
    "sg:phone":"+1 248 693 1404",
    "sg:postcode":"48363",
    "sg:province":"MI",
    "sg:tags":[
        "parks"
    ],
    "wof:name":"Oakland Township Cranberry",
    "wof:placetype":"venue"
},
  "geometry": {"coordinates":[-83.14417400000001,42.784782],"type":"Point"}
}