{
  "type": "Feature",
  "properties": {
    "iso:country":"US",
    "sg:address":"8924 Nevada St",
    "sg:city":"Livonia",
    "sg:classifiers":[
        {
            "category":"Professional",
            "subcategory":"Business Services",
            "type":"Services"
        }
    ],
    "sg:phone":"+1 734 261 1703",
    "sg:postcode":"48150",
    "sg:province":"MI",
    "wof:name":"Preferred Equipment Sales Inc",
    "wof:placetype":"venue"
},
  "geometry": {"coordinates":[-83.357918,42.355645],"type":"Point"}
}