{
  "type": "Feature",
  "properties": {
    "iso:country":"US",
    "sg:address":"417 N State St",
    "sg:city":"St Ignace",
    "sg:classifiers":[
        {
            "category":"Shopping",
            "subcategory":"Gifts & Souvenirs",
            "type":"Retail Goods"
        }
    ],
    "sg:phone":"+1 906 643 9947",
    "sg:postcode":"49781",
    "sg:province":"MI",
    "sg:tags":[
        "shop"
    ],
    "wof:name":"Vandusen Clothing",
    "wof:placetype":"venue"
},
  "geometry": {"coordinates":[-84.731078,45.870733],"type":"Point"}
}