{
  "type": "Feature",
  "properties": {
    "iso:country":"US",
    "sg:address":"190 Monroe Ave NW",
    "sg:city":"Grand Rapids",
    "sg:classifiers":[
        {
            "category":"Restaurant",
            "type":"Food & Drink"
        }
    ],
    "sg:menulink":"http://www.allmenus.com/mi/grand-rapids/58305-the-chop-house/menu/",
    "sg:phone":"+1 616 451 6184",
    "sg:postcode":"49503",
    "sg:province":"MI",
    "sg:tags":[
        "new",
        "american"
    ],
    "wof:name":"The Chop House",
    "wof:placetype":"venue"
},
  "geometry": {"coordinates":[-85.67218699999999,42.966878],"type":"Point"}
}