{
  "type": "Feature",
  "properties": {
    "iso:country":"US",
    "sg:address":"28 W Chicago St",
    "sg:city":"Coldwater",
    "sg:classifiers":[
        {
            "category":"Building & Trades",
            "subcategory":"Construction",
            "type":"Services"
        }
    ],
    "sg:phone":"+1 517 278 7700",
    "sg:postcode":"49036",
    "sg:province":"MI",
    "sg:tags":[
        "contractor"
    ],
    "wof:name":"Payseno Builders & Mechanical",
    "wof:placetype":"venue"
},
  "geometry": {"coordinates":[-85.002008,41.940894],"type":"Point"}
}