{
  "type": "Feature",
  "properties": {
    "iso:country":"US",
    "sg:address":"1638 E Lincoln Ave",
    "sg:city":"Royal Oak",
    "sg:classifiers":[
        {
            "category":"Restaurant",
            "type":"Food & Drink"
        }
    ],
    "sg:phone":"+1 248 546 7783",
    "sg:postcode":"48067",
    "sg:province":"MI",
    "wof:name":"Primo Pizza",
    "wof:placetype":"venue"
},
  "geometry": {"coordinates":[-83.12425500000001,42.482924],"type":"Point"}
}