{
  "type": "Feature",
  "properties": {
    "iso:country":"US",
    "sg:address":"4545 Pittsburg Rd",
    "sg:city":"Owosso",
    "sg:classifiers":[
        {
            "category":"Farming",
            "subcategory":"Farm",
            "type":"Manufacturing & Wholesale Goods"
        }
    ],
    "sg:phone":"+1 517 651 2090",
    "sg:postcode":"48867",
    "sg:province":"MI",
    "sg:tags":[
        "crop",
        "general"
    ],
    "wof:name":"Doug Ash",
    "wof:placetype":"venue"
},
  "geometry": {"coordinates":[-84.261321,42.891794],"type":"Point"}
}