{
  "type": "Feature",
  "properties": {
    "iso:country":"US",
    "sg:address":"5056 N Belsay Rd",
    "sg:city":"Flint",
    "sg:classifiers":[
        {
            "category":"Building & Trades",
            "subcategory":"Construction",
            "type":"Services"
        }
    ],
    "sg:phone":"+1 810 736 4271",
    "sg:postcode":"48506",
    "sg:province":"MI",
    "sg:tags":[
        "house"
    ],
    "wof:name":"North Hemisphere Construction",
    "wof:placetype":"venue"
},
  "geometry": {"coordinates":[-83.597184,43.083797],"type":"Point"}
}