{
  "type": "Feature",
  "properties": {
    "iso:country":"US",
    "sg:address":"17631 Schoolcraft St",
    "sg:city":"Detroit",
    "sg:classifiers":[
        {
            "category":"Retail",
            "subcategory":"Laundry & Dry Cleaning",
            "type":"Services"
        }
    ],
    "sg:phone":"+1 313 835 2402",
    "sg:postcode":"48227",
    "sg:province":"MI",
    "wof:name":"Morgan Cleaners",
    "wof:placetype":"venue"
},
  "geometry": {"coordinates":[-83.215609,42.386426],"type":"Point"}
}