{
  "type": "Feature",
  "properties": {
    "iso:country":"US",
    "sg:address":"3965 School Rd",
    "sg:city":"Temperance",
    "sg:classifiers":[
        {
            "category":"Professional",
            "subcategory":"Management & Consulting",
            "type":"Services"
        }
    ],
    "sg:phone":"+1 734 854 8173",
    "sg:postcode":"48182",
    "sg:province":"MI",
    "wof:name":"United States Fidelty Guaranty",
    "wof:placetype":"venue"
},
  "geometry": {"coordinates":[-83.642664,41.814107],"type":"Point"}
}