{
  "type": "Feature",
  "properties": {
    "iso:country":"US",
    "sg:address":"312 E Lawrence Ave",
    "sg:city":"Charlotte",
    "sg:classifiers":[
        {
            "category":"Retail",
            "subcategory":"Portrait Studio",
            "type":"Services"
        }
    ],
    "sg:phone":"+1 517 543 3000",
    "sg:postcode":"48813",
    "sg:province":"MI",
    "sg:tags":[
        "photographer"
    ],
    "wof:name":"Reed Studio",
    "wof:placetype":"venue"
},
  "geometry": {"coordinates":[-84.83174200000001,42.56393],"type":"Point"}
}