{
  "type": "Feature",
  "properties": {
    "iso:country":"US",
    "sg:address":"211 Spencer St NE",
    "sg:city":"Grand Rapids",
    "sg:classifiers":[
        {
            "category":"Professional",
            "subcategory":"Engineering",
            "type":"Services"
        }
    ],
    "sg:phone":"+1 616 454 1181",
    "sg:postcode":"49505",
    "sg:province":"MI",
    "sg:tags":[
        "engineer"
    ],
    "wof:name":"Mechanical Electrical Design",
    "wof:placetype":"venue"
},
  "geometry": {"coordinates":[-85.664568,42.988289],"type":"Point"}
}