{
  "type": "Feature",
  "properties": {
    "iso:country":"US",
    "sg:address":"605 Ridge St",
    "sg:city":"Sault Sainte Marie",
    "sg:classifiers":[
        {
            "category":"Home & Garden",
            "subcategory":"Furniture",
            "type":"Retail Goods"
        }
    ],
    "sg:phone":"+1 906 632 8858",
    "sg:postcode":"49783",
    "sg:province":"MI",
    "sg:tags":[
        "household"
    ],
    "wof:name":"Weir Package & Freight Service",
    "wof:placetype":"venue"
},
  "geometry": {"coordinates":[-84.362481,46.500311],"type":"Point"}
}