{
  "type": "Feature",
  "properties": {
    "iso:country":"US",
    "sg:address":"Palmer and Sheldon Roads",
    "sg:city":"Canton",
    "sg:classifiers":[
        {
            "category":"Sports & Exercise",
            "subcategory":"Tennis Court",
            "type":"Entertainment"
        }
    ],
    "sg:postcode":"48188",
    "sg:province":"MI",
    "wof:name":"Freedom Park",
    "wof:placetype":"venue"
},
  "geometry": {"coordinates":[-83.476748,42.29308],"type":"Point"}
}