{
  "type": "Feature",
  "properties": {
    "iso:country":"US",
    "sg:address":"7481 Meisner Rd",
    "sg:city":"East China",
    "sg:classifiers":[
        {
            "category":"Farming",
            "subcategory":"Dairy Farm",
            "type":"Manufacturing & Wholesale Goods"
        }
    ],
    "sg:phone":"+1 810 765 4948",
    "sg:postcode":"48054",
    "sg:province":"MI",
    "wof:name":"Dale Guldenstein",
    "wof:placetype":"venue"
},
  "geometry": {"coordinates":[-82.608724,42.754265],"type":"Point"}
}