{
  "type": "Feature",
  "properties": {
    "iso:country":"US",
    "sg:address":"101 W Maumee St",
    "sg:city":"Angola",
    "sg:classifiers":[
        {
            "category":"Restaurant",
            "type":"Food & Drink"
        }
    ],
    "sg:phone":"+1 260 665 5282",
    "sg:postcode":"46703",
    "sg:province":"MI",
    "sg:tags":[
        "shop",
        "coffee"
    ],
    "wof:name":"Coachlight Coffee House",
    "wof:placetype":"venue"
},
  "geometry": {"coordinates":[-85.00041400000001,41.634837],"type":"Point"}
}