{
  "type": "Feature",
  "properties": {
    "iso:country":"US",
    "sg:address":"3235 Soft Water Lake Dr NE",
    "sg:city":"Grand Rapids",
    "sg:classifiers":[
        {
            "category":"Real Estate",
            "subcategory":"Real Estate Operator",
            "type":"Services"
        }
    ],
    "sg:phone":"+1 616 363 7016",
    "sg:postcode":"49525",
    "sg:province":"MI",
    "sg:tags":[
        "apartment"
    ],
    "wof:name":"Lake Forest Apartments",
    "wof:placetype":"venue"
},
  "geometry": {"coordinates":[-85.63609599999999,43.022932],"type":"Point"}
}