{
  "type": "Feature",
  "properties": {
    "iso:country":"US",
    "sg:address":"699 Balfour St",
    "sg:city":"Grosse Pointe",
    "sg:classifiers":[
        {
            "category":"Professional",
            "subcategory":"Advertising",
            "type":"Services"
        }
    ],
    "sg:phone":"+1 313 331 6131",
    "sg:postcode":"48230",
    "sg:province":"MI",
    "sg:tags":[
        "agency"
    ],
    "wof:name":"Ad Hoc Productions Inc",
    "wof:placetype":"venue"
},
  "geometry": {"coordinates":[-82.92489399999999,42.36828],"type":"Point"}
}