{
  "type": "Feature",
  "properties": {
    "iso:country":"US",
    "sg:address":"25860 Lahser Rd",
    "sg:city":"Southfield",
    "sg:classifiers":[
        {
            "category":"Retail",
            "subcategory":"Repair Shop",
            "type":"Services"
        }
    ],
    "sg:phone":"+1 248 350 2020",
    "sg:postcode":"48033",
    "sg:province":"MI",
    "sg:tags":[
        "maintenance",
        "installation",
        "sales",
        "business"
    ],
    "sg:website":"www.ultracom.bz",
    "wof:name":"Ultracom Inc",
    "wof:placetype":"venue"
},
  "geometry": {"coordinates":[-83.26079900000001,42.475904],"type":"Point"}
}