{
  "type": "Feature",
  "properties": {
    "iso:country":"US",
    "sg:address":"1810 Maplelawn Dr 909",
    "sg:city":"Troy",
    "sg:classifiers":[
        {
            "category":"Autos & Motor Vehicles",
            "subcategory":"Automobile Sales",
            "type":"Retail Goods"
        }
    ],
    "sg:phone":"+1 248 816 0772",
    "sg:postcode":"48084",
    "sg:province":"MI",
    "sg:tags":[
        "dealers-used",
        "car",
        "used",
        "cars-wholesale"
    ],
    "wof:name":"Leftlane.Com Inc",
    "wof:placetype":"venue"
},
  "geometry": {"coordinates":[-83.175078,42.551875],"type":"Point"}
}