{
  "type": "Feature",
  "properties": {
    "iso:country":"US",
    "sg:address":"5076 Scofield Rd",
    "sg:city":"Maybee",
    "sg:classifiers":[
        {
            "category":"Government",
            "subcategory":"Office",
            "type":"Public Place"
        }
    ],
    "sg:phone":"+1 734 587 7205",
    "sg:postcode":"48159",
    "sg:province":"MI",
    "sg:tags":[
        "federal"
    ],
    "wof:name":"Us Faa",
    "wof:placetype":"venue"
},
  "geometry": {"coordinates":[-83.458991,42.02194],"type":"Point"}
}