{
  "type": "Feature",
  "properties": {
    "iso:country":"US",
    "sg:address":"11630 14th Ave NW",
    "sg:city":"Grand Rapids",
    "sg:classifiers":[
        {
            "category":"Real Estate",
            "subcategory":"Real Estate Operator",
            "type":"Services"
        }
    ],
    "sg:phone":"+1 616 677 5418",
    "sg:postcode":"49544",
    "sg:province":"MI",
    "sg:tags":[
        "mobile",
        "home",
        "site"
    ],
    "wof:name":"Whites Mobile Home Plaza Inc",
    "wof:placetype":"venue"
},
  "geometry": {"coordinates":[-85.820407,42.982609],"type":"Point"}
}