{
  "type": "Feature",
  "properties": {
    "iso:country":"US",
    "sg:address":"822 Ashmun St",
    "sg:city":"Sault Ste Marie",
    "sg:classifiers":[
        {
            "category":"Manufacturing",
            "subcategory":"Printing",
            "type":"Manufacturing & Wholesale Goods"
        }
    ],
    "sg:phone":"+1 906 635 1218",
    "sg:postcode":"49783",
    "sg:province":"MI",
    "sg:tags":[
        "screen"
    ],
    "wof:name":"All Star Graphics",
    "wof:placetype":"venue"
},
  "geometry": {"coordinates":[-84.350666,46.493734],"type":"Point"}
}