{
  "type": "Feature",
  "properties": {
    "iso:country":"US",
    "sg:address":"4230 Salling Ave",
    "sg:city":"Lewiston",
    "sg:classifiers":[
        {
            "category":"Recreation",
            "type":"Entertainment"
        }
    ],
    "sg:phone":"+1 989 786 3888",
    "sg:postcode":"49756",
    "sg:province":"MI",
    "sg:tags":[
        "club",
        "membership"
    ],
    "wof:name":"Lewiston Curling Club",
    "wof:placetype":"venue"
},
  "geometry": {"coordinates":[-84.308649,44.884027],"type":"Point"}
}