{
  "type": "Feature",
  "properties": {
    "iso:country":"US",
    "sg:address":"16715 Lincoln St",
    "sg:city":"Grand Haven",
    "sg:classifiers":[
        {
            "category":"Personal",
            "subcategory":"Tanning Parlor",
            "type":"Services"
        }
    ],
    "sg:phone":"+1 616 846 4100",
    "sg:postcode":"49417",
    "sg:province":"MI",
    "sg:tags":[
        "salon"
    ],
    "wof:name":"Midnite Sun & Cruise",
    "wof:placetype":"venue"
},
  "geometry": {"coordinates":[-86.20219400000001,43.001256],"type":"Point"}
}