{
  "type": "Feature",
  "properties": {
    "iso:country":"US",
    "sg:address":"2523 Tower Hill Ln",
    "sg:city":"Rochester",
    "sg:classifiers":[
        {
            "category":"Shopping",
            "subcategory":"Clothing, Apparel, & Fashions",
            "type":"Retail Goods"
        }
    ],
    "sg:phone":"+1 248 601 1934",
    "sg:postcode":"48306",
    "sg:province":"MI",
    "sg:tags":[
        "veil",
        "bridal",
        "communion",
        "gown"
    ],
    "wof:name":"Laurel Street Design",
    "wof:placetype":"venue"
},
  "geometry": {"coordinates":[-83.18543699999999,42.708096],"type":"Point"}
}