{
  "type": "Feature",
  "properties": {
    "iso:country":"US",
    "sg:address":"340 E Big Beaver Rd",
    "sg:city":"Troy",
    "sg:classifiers":[
        {
            "category":"Professional",
            "type":"Services"
        }
    ],
    "sg:phone":"+1 248 816 0500",
    "sg:postcode":"48083",
    "sg:province":"MI",
    "sg:tags":[
        "establishment"
    ],
    "wof:name":"ICONMA",
    "wof:placetype":"venue"
},
  "geometry": {"coordinates":[-83.139933,42.562592],"type":"Point"}
}