{
  "type": "Feature",
  "properties": {
    "iso:country":"US",
    "sg:address":"17521 Westland Ave",
    "sg:city":"Southfield",
    "sg:classifiers":[
        {
            "category":"Professional",
            "subcategory":"Management & Consulting",
            "type":"Services"
        }
    ],
    "sg:phone":"+1 248 552 6205",
    "sg:postcode":"48075",
    "sg:province":"MI",
    "wof:name":"D & B Management Company",
    "wof:placetype":"venue"
},
  "geometry": {"coordinates":[-83.21530199999999,42.448089],"type":"Point"}
}