{
  "type": "Feature",
  "properties": {
    "iso:country":"US",
    "sg:address":"28466 Groesbeck Hwy",
    "sg:city":"Roseville",
    "sg:classifiers":[
        {
            "category":"Retail",
            "subcategory":"Auto Repair",
            "type":"Services"
        }
    ],
    "sg:phone":"+1 586 772 2620",
    "sg:postcode":"48066",
    "sg:province":"MI",
    "wof:name":"Charlie's Auto Service",
    "wof:placetype":"venue"
},
  "geometry": {"coordinates":[-82.959278,42.507086],"type":"Point"}
}