{
  "type": "Feature",
  "properties": {
    "iso:country":"US",
    "sg:address":"6155 Markel Rd",
    "sg:city":"Cottrellville",
    "sg:classifiers":[
        {
            "category":"Building & Trades",
            "subcategory":"Construction",
            "type":"Services"
        }
    ],
    "sg:phone":"+1 810 765 9823",
    "sg:postcode":"48039",
    "sg:province":"MI",
    "sg:tags":[
        "painter"
    ],
    "wof:name":"D Brown Painting Svc",
    "wof:placetype":"venue"
},
  "geometry": {"coordinates":[-82.553692,42.704104],"type":"Point"}
}