{
  "type": "Feature",
  "properties": {
    "iso:country":"US",
    "sg:address":"218 Water St",
    "sg:city":"Benton Harbor",
    "sg:classifiers":[
        {
            "category":"Manufacturing",
            "subcategory":"Tools & Machinery",
            "type":"Manufacturing & Wholesale Goods"
        }
    ],
    "sg:phone":"+1 269 926 6244",
    "sg:postcode":"49022",
    "sg:province":"MI",
    "sg:tags":[
        "machine",
        "shop"
    ],
    "wof:name":"Firehouse Machine",
    "wof:placetype":"venue"
},
  "geometry": {"coordinates":[-86.453819,42.118798],"type":"Point"}
}