{
  "type": "Feature",
  "properties": {
    "iso:country":"US",
    "sg:address":"2442 152nd Ave",
    "sg:city":"Holland",
    "sg:classifiers":[
        {
            "category":"Professional",
            "type":"Services"
        }
    ],
    "sg:phone":"+1 616 786 0676",
    "sg:postcode":"49424",
    "sg:province":"MI",
    "sg:tags":[
        "establishment"
    ],
    "wof:name":"Novus International",
    "wof:placetype":"venue"
},
  "geometry": {"coordinates":[-86.15751,42.814655],"type":"Point"}
}