{
  "type": "Feature",
  "properties": {
    "iso:country":"US",
    "sg:address":"5142 Straits Hwy",
    "sg:city":"Indian River",
    "sg:classifiers":[
        {
            "category":"Travel",
            "subcategory":"Hotels & Motels",
            "type":"Entertainment"
        }
    ],
    "sg:phone":"+1 231 238 4749",
    "sg:postcode":"49749",
    "sg:province":"MI",
    "wof:name":"Indian Trail Motel",
    "wof:placetype":"venue"
},
  "geometry": {"coordinates":[-84.629165,45.386414],"type":"Point"}
}