{
  "type": "Feature",
  "properties": {
    "iso:country":"US",
    "sg:address":"1150 E Lantz St",
    "sg:city":"Detroit",
    "sg:classifiers":[
        {
            "category":"Education",
            "subcategory":"School",
            "type":"Public Place"
        }
    ],
    "sg:phone":"+1 313 866 7730",
    "sg:postcode":"48203",
    "sg:province":"MI",
    "wof:name":"Detroit Public Schools",
    "wof:placetype":"venue"
},
  "geometry": {"coordinates":[-83.092236,42.437323],"type":"Point"}
}