{
  "type": "Feature",
  "properties": {
    "iso:country":"US",
    "sg:address":"801 W Grand Blvd",
    "sg:city":"Detroit",
    "sg:classifiers":[
        {
            "category":"Social Services",
            "subcategory":"Adult Care",
            "type":"Services"
        }
    ],
    "sg:phone":"+1 313 894 6378",
    "sg:postcode":"48216",
    "sg:province":"MI",
    "sg:tags":[
        "residential"
    ],
    "wof:name":"Forrest Haven West",
    "wof:placetype":"venue"
},
  "geometry": {"coordinates":[-83.093808,42.329269],"type":"Point"}
}