{
  "type": "Feature",
  "properties": {
    "iso:country":"US",
    "sg:address":"7519 Moyer Rd",
    "sg:city":"Charlotte",
    "sg:classifiers":[
        {
            "category":"Wholesale",
            "subcategory":"Plants",
            "type":"Manufacturing & Wholesale Goods"
        }
    ],
    "sg:phone":"+1 517 543 7291",
    "sg:postcode":"48813",
    "sg:province":"MI",
    "sg:tags":[
        "nursery",
        "tree"
    ],
    "wof:name":"A Daylily Maze",
    "wof:placetype":"venue"
},
  "geometry": {"coordinates":[-84.88622100000001,42.681513],"type":"Point"}
}