{
  "type": "Feature",
  "properties": {
    "iso:country":"US",
    "sg:address":"4165 Lippincott Blvd Ste 2",
    "sg:city":"Burton",
    "sg:classifiers":[
        {
            "category":"Health Services",
            "subcategory":"Doctor",
            "type":"Services"
        }
    ],
    "sg:phone":"+1 810 744 1883",
    "sg:postcode":"48519",
    "sg:province":"MI",
    "wof:name":"Johnson Ellen DO",
    "wof:placetype":"venue"
},
  "geometry": {"coordinates":[-83.62815000000001,43.006028],"type":"Point"}
}