{
  "type": "Feature",
  "properties": {
    "iso:country":"US",
    "sg:address":"735 W Warren Ave",
    "sg:city":"Detroit",
    "sg:classifiers":[
        {
            "category":"Professional",
            "subcategory":"Secretarial Services",
            "type":"Services"
        }
    ],
    "sg:phone":"+1 313 897 9140",
    "sg:postcode":"48201",
    "sg:province":"MI",
    "wof:name":"Vjt Secretarial Services Inc",
    "wof:placetype":"venue"
},
  "geometry": {"coordinates":[-83.06994299999999,42.354895],"type":"Point"}
}