{
  "type": "Feature",
  "properties": {
    "iso:country":"US",
    "sg:address":"10757 US Hwy 12",
    "sg:city":"New Buffalo",
    "sg:classifiers":[
        {
            "category":"Education",
            "subcategory":"College",
            "type":"Public Place"
        }
    ],
    "sg:phone":"+1 269 469 0041",
    "sg:postcode":"49117",
    "sg:province":"MI",
    "sg:tags":[
        "academic",
        "school"
    ],
    "wof:name":"Professional Drivers Institute",
    "wof:placetype":"venue"
},
  "geometry": {"coordinates":[-86.72012100000001,41.800305],"type":"Point"}
}