{
  "type": "Feature",
  "properties": {
    "iso:country":"US",
    "sg:address":"8888 Lansing Rd",
    "sg:city":"Durand",
    "sg:classifiers":[
        {
            "category":"Building & Trades",
            "subcategory":"Construction",
            "type":"Services"
        }
    ],
    "sg:phone":"+1 989 288 6046",
    "sg:postcode":"48429",
    "sg:province":"MI",
    "sg:tags":[
        "general",
        "contractor"
    ],
    "wof:name":"Perrin Construction Inc",
    "wof:placetype":"venue"
},
  "geometry": {"coordinates":[-83.98967,42.92521],"type":"Point"}
}