{
  "type": "Feature",
  "properties": {
    "iso:country":"US",
    "sg:address":"13832 Van Dyke St",
    "sg:city":"Detroit",
    "sg:classifiers":[
        {
            "category":"Autos & Motor Vehicles",
            "subcategory":"Auto Supplies",
            "type":"Retail Goods"
        },
        {
            "category":"Retail",
            "subcategory":"Auto Repair",
            "type":"Services"
        }
    ],
    "sg:phone":"+1 313 365 6000",
    "sg:postcode":"48234",
    "sg:province":"MI",
    "sg:tags":[
        "tire"
    ],
    "wof:name":"Metro 25 Tire",
    "wof:placetype":"venue"
},
  "geometry": {"coordinates":[-83.023499,42.4193],"type":"Point"}
}