{
  "type": "Feature",
  "properties": {
    "iso:country":"US",
    "sg:address":"542 Tecumseh St",
    "sg:city":"Dundee",
    "sg:classifiers":[
        {
            "category":"Restaurant",
            "type":"Food & Drink"
        }
    ],
    "sg:phone":"+1 734 529 2423",
    "sg:postcode":"48131",
    "sg:province":"MI",
    "sg:tags":[
        "eating"
    ],
    "wof:name":"McDonalds",
    "wof:placetype":"venue"
},
  "geometry": {"coordinates":[-83.66773999999999,41.958629],"type":"Point"}
}