{
  "type": "Feature",
  "properties": {
    "iso:country":"US",
    "sg:address":"5479 Ray Rd",
    "sg:city":"Linden",
    "sg:classifiers":[
        {
            "category":"Shopping",
            "type":"Retail Goods"
        }
    ],
    "sg:phone":"+1 810 735 4057",
    "sg:postcode":"48451",
    "sg:province":"MI",
    "sg:tags":[
        "cosmetic",
        "perfume"
    ],
    "wof:name":"Pat J Stone",
    "wof:placetype":"venue"
},
  "geometry": {"coordinates":[-83.779459,42.869915],"type":"Point"}
}