{
  "type": "Feature",
  "properties": {
    "iso:country":"US",
    "sg:address":"6100 Belding Rd",
    "sg:city":"Belding",
    "sg:classifiers":[
        {
            "category":"Freight",
            "type":"Transportation"
        }
    ],
    "sg:phone":"+1 616 794 2582",
    "sg:postcode":"48809",
    "sg:province":"MI",
    "sg:tags":[
        "operator",
        "automotive",
        "trucking",
        "repair"
    ],
    "wof:name":"Premium Truck & Auto",
    "wof:placetype":"venue"
},
  "geometry": {"coordinates":[-85.199499,43.085938],"type":"Point"}
}