{
  "type": "Feature",
  "properties": {
    "iso:country":"US",
    "sg:address":"5027 W Michigan Ave",
    "sg:city":"Lansing",
    "sg:classifiers":[
        {
            "category":"Education",
            "subcategory":"School",
            "type":"Public Place"
        }
    ],
    "sg:phone":"+1 517 323 3831",
    "sg:postcode":"48917",
    "sg:province":"MI",
    "wof:name":"Waverly High School",
    "wof:placetype":"venue"
},
  "geometry": {"coordinates":[-84.618871,42.733741],"type":"Point"}
}