{
  "type": "Feature",
  "properties": {
    "iso:country":"US",
    "sg:address":"23935 Denton St",
    "sg:city":"Clinton Township",
    "sg:classifiers":[
        {
            "category":"Health Services",
            "subcategory":"Dentist",
            "type":"Services"
        }
    ],
    "sg:phone":"+1 586 465 4505",
    "sg:postcode":"48036",
    "sg:province":"MI",
    "wof:name":"Ardelean Family & Cosmetic Dentistry",
    "wof:placetype":"venue"
},
  "geometry": {"coordinates":[-82.872491,42.571471],"type":"Point"}
}