{
  "type": "Feature",
  "properties": {
    "iso:country":"US",
    "sg:address":"15635 172nd Ave",
    "sg:city":"Big Rapids",
    "sg:classifiers":[
        {
            "category":"Professional",
            "subcategory":"Research",
            "type":"Services"
        }
    ],
    "sg:phone":"+1 231 796 3204",
    "sg:postcode":"49307",
    "sg:province":"MI",
    "sg:tags":[
        "nonphysical",
        "commercial",
        "health",
        "o"
    ],
    "wof:name":"Donald L Hecker",
    "wof:placetype":"venue"
},
  "geometry": {"coordinates":[-85.430595,43.700374],"type":"Point"}
}