{
  "type": "Feature",
  "properties": {
    "iso:country":"US",
    "sg:address":"20945 Link Rd",
    "sg:city":"Southfield",
    "sg:classifiers":[
        {
            "category":"Freight",
            "type":"Transportation"
        }
    ],
    "sg:phone":"+1 248 352 9610",
    "sg:postcode":"48033",
    "sg:province":"MI",
    "sg:tags":[
        "commercial",
        "storage"
    ],
    "wof:name":"E-Z Mini Storage",
    "wof:placetype":"venue"
},
  "geometry": {"coordinates":[-83.28001500000001,42.44412],"type":"Point"}
}