{
  "type": "Feature",
  "properties": {
    "iso:country":"US",
    "sg:address":"5600 W Maple Rd",
    "sg:city":"West Bloomfield",
    "sg:classifiers":[
        {
            "category":"Health Services",
            "subcategory":"Health Practitioner",
            "type":"Services"
        }
    ],
    "sg:phone":"+1 248 865 0938",
    "sg:postcode":"48322",
    "sg:province":"MI",
    "sg:tags":[
        "psychologist"
    ],
    "wof:name":"Bette Glickfield PHD",
    "wof:placetype":"venue"
},
  "geometry": {"coordinates":[-83.35641800000001,42.543138],"type":"Point"}
}