{
  "type": "Feature",
  "properties": {
    "iso:country":"US",
    "sg:address":"1385 E 12 Mile Rd Ste 215",
    "sg:city":"Madison Heights",
    "sg:classifiers":[
        {
            "category":"Health Services",
            "subcategory":"Chiropractor",
            "type":"Services"
        }
    ],
    "sg:phone":"+1 248 414 5555",
    "sg:postcode":"48071",
    "sg:province":"MI",
    "wof:name":"Wellness Chiropractic Center",
    "wof:placetype":"venue"
},
  "geometry": {"coordinates":[-83.091904,42.5051],"type":"Point"}
}