{
  "type": "Feature",
  "properties": {
    "iso:country":"US",
    "sg:address":"7074 Hadley Rd",
    "sg:city":"Cass City",
    "sg:classifiers":[
        {
            "category":"Professional",
            "subcategory":"Business Services",
            "type":"Services"
        }
    ],
    "sg:phone":"+1 231 882 5270",
    "sg:postcode":"48726",
    "sg:province":"MI",
    "sg:tags":[
        "auctioneer"
    ],
    "wof:name":"Cole & Co Auction & Appraisal",
    "wof:placetype":"venue"
},
  "geometry": {"coordinates":[-83.077009,43.619974],"type":"Point"}
}