{
  "type": "Feature",
  "properties": {
    "iso:country":"US",
    "sg:address":"4808 Isabella St",
    "sg:city":"Midland",
    "sg:classifiers":[
        {
            "category":"Retail",
            "subcategory":"Veterinary Services",
            "type":"Services"
        }
    ],
    "sg:phone":"+1 989 631 7170",
    "sg:postcode":"48640",
    "sg:province":"MI",
    "sg:tags":[
        "veterinarian"
    ],
    "wof:name":"M-20 Animal Hospital",
    "wof:placetype":"venue"
},
  "geometry": {"coordinates":[-84.29789100000001,43.612108],"type":"Point"}
}