{
  "type": "Feature",
  "properties": {
    "iso:country":"US",
    "sg:address":"1406 N Henry St",
    "sg:city":"Bay City",
    "sg:classifiers":[
        {
            "category":"Restaurant",
            "type":"Food & Drink"
        }
    ],
    "sg:phone":"+1 989 686 1641",
    "sg:postcode":"48706",
    "sg:province":"MI",
    "sg:tags":[
        "pizza"
    ],
    "wof:name":"Josephines Pizzeria & Family",
    "wof:placetype":"venue"
},
  "geometry": {"coordinates":[-83.899462,43.617447],"type":"Point"}
}