{
  "type": "Feature",
  "properties": {
    "iso:country":"US",
    "sg:address":"34520 Ford Rd",
    "sg:city":"Westland",
    "sg:classifiers":[
        {
            "category":"Sports & Exercise",
            "subcategory":"Gym",
            "type":"Entertainment"
        }
    ],
    "sg:phone":"+1 734 722 4040",
    "sg:postcode":"48185",
    "sg:province":"MI",
    "wof:name":"Power House Gym of Westland",
    "wof:placetype":"venue"
},
  "geometry": {"coordinates":[-83.38099699999999,42.324699],"type":"Point"}
}