{
  "type": "Feature",
  "properties": {
    "iso:country":"US",
    "sg:address":"43762 Merrill Rd",
    "sg:city":"Sterling Heights",
    "sg:classifiers":[
        {
            "category":"Manufacturing",
            "subcategory":"Motor Vehicles & Parts",
            "type":"Manufacturing & Wholesale Goods"
        }
    ],
    "sg:phone":"+1 586 323 6033",
    "sg:postcode":"48314",
    "sg:province":"MI",
    "sg:tags":[
        "automobile",
        "supply"
    ],
    "wof:name":"Cousins Manufacturing",
    "wof:placetype":"venue"
},
  "geometry": {"coordinates":[-83.04654499999999,42.61545],"type":"Point"}
}