{
  "type": "Feature",
  "properties": {
    "iso:country":"US",
    "sg:address":"4081 W Polk Rd",
    "sg:city":"Hart",
    "sg:classifiers":[
        {
            "category":"Government",
            "subcategory":"Office",
            "type":"Public Place"
        }
    ],
    "sg:phone":"+1 231 873 7251",
    "sg:postcode":"49420",
    "sg:province":"MI",
    "wof:name":"Family Independence Agency",
    "wof:placetype":"venue"
},
  "geometry": {"coordinates":[-86.383566,43.688931],"type":"Point"}
}