{
  "type": "Feature",
  "properties": {
    "iso:country":"US",
    "sg:address":"2500 W Maple Ridge 37 Rd",
    "sg:city":"Rock",
    "sg:classifiers":[
        {
            "category":"Government",
            "subcategory":"Office",
            "type":"Public Place"
        }
    ],
    "sg:phone":"+1 906 356 6135",
    "sg:postcode":"49880",
    "sg:province":"MI",
    "sg:tags":[
        "village"
    ],
    "wof:name":"Ewing Township Hall",
    "wof:placetype":"venue"
},
  "geometry": {"coordinates":[-87.250237,46.071954],"type":"Point"}
}