{
  "type": "Feature",
  "properties": {
    "iso:country":"US",
    "sg:address":"5135 E Hill Rd",
    "sg:city":"Grand Blanc",
    "sg:classifiers":[
        {
            "category":"Education",
            "subcategory":"School",
            "type":"Public Place"
        }
    ],
    "sg:phone":"+1 810 953 3140",
    "sg:postcode":"48439",
    "sg:province":"MI",
    "sg:tags":[
        "high",
        "middle",
        "elementary"
    ],
    "wof:name":"Grand Blanc Academy",
    "wof:placetype":"venue"
},
  "geometry": {"coordinates":[-83.60880299999999,42.945301],"type":"Point"}
}