{
  "type": "Feature",
  "properties": {
    "iso:country":"US",
    "sg:address":"3798 W Centre Ave",
    "sg:city":"Portage",
    "sg:classifiers":[
        {
            "category":"Sports & Exercise",
            "subcategory":"Gym",
            "type":"Entertainment"
        }
    ],
    "sg:phone":"+1 269 329 0070",
    "sg:postcode":"49024",
    "sg:province":"MI",
    "sg:tags":[
        "club",
        "health",
        "studio",
        "gymnasium"
    ],
    "wof:name":"Ladies Workout Express",
    "wof:placetype":"venue"
},
  "geometry": {"coordinates":[-85.642528,42.198379],"type":"Point"}
}