{
  "type": "Feature",
  "properties": {
    "iso:country":"US",
    "sg:address":"839 Mineral St",
    "sg:city":"Benton Harbor",
    "sg:classifiers":[
        {
            "category":"Organizations",
            "subcategory":"Religious Organization",
            "type":"Services"
        }
    ],
    "sg:phone":"+1 269 925 7693",
    "sg:postcode":"49022",
    "sg:province":"MI",
    "wof:name":"Leonard Robinson Rev",
    "wof:placetype":"venue"
},
  "geometry": {"coordinates":[-86.43746400000001,42.109958],"type":"Point"}
}