{
  "type": "Feature",
  "properties": {
    "iso:country":"US",
    "sg:address":"3850 State Rd",
    "sg:city":"Fort Gratiot",
    "sg:classifiers":[
        {
            "category":"Building & Trades",
            "subcategory":"Landscaping Services",
            "type":"Services"
        }
    ],
    "sg:phone":"+1 810 985 7593",
    "sg:postcode":"48059",
    "sg:province":"MI",
    "wof:name":"Ed Lewis Lawncare Service",
    "wof:placetype":"venue"
},
  "geometry": {"coordinates":[-82.495036,43.020262],"type":"Point"}
}