{
  "type": "Feature",
  "properties": {
    "iso:country":"US",
    "sg:address":"24147 Grange St",
    "sg:city":"Clinton Twp",
    "sg:classifiers":[
        {
            "category":"Health Services",
            "subcategory":"Health Practitioner",
            "type":"Services"
        }
    ],
    "sg:phone":"+1 586 463 2171",
    "sg:postcode":"48036",
    "sg:province":"MI",
    "sg:tags":[
        "nurse",
        "registry"
    ],
    "wof:name":"Do Nursing Registry",
    "wof:placetype":"venue"
},
  "geometry": {"coordinates":[-82.867412,42.570902],"type":"Point"}
}