{
  "type": "Feature",
  "properties": {
    "iso:country":"US",
    "sg:address":"6251 Losee Ln",
    "sg:city":"Davisburg",
    "sg:classifiers":[
        {
            "category":"Building & Trades",
            "subcategory":"Construction",
            "type":"Services"
        }
    ],
    "sg:phone":"+1 248 620 5080",
    "sg:postcode":"48350",
    "sg:province":"MI",
    "sg:tags":[
        "house"
    ],
    "wof:name":"Ald Construction Inc",
    "wof:placetype":"venue"
},
  "geometry": {"coordinates":[-83.519758,42.725578],"type":"Point"}
}