{
  "type": "Feature",
  "properties": {
    "iso:country":"US",
    "sg:address":"125 W Shiawassee Ave",
    "sg:city":"Fenton",
    "sg:classifiers":[
        {
            "category":"Restaurant",
            "type":"Food & Drink"
        }
    ],
    "sg:phone":"+1 810 629 8852",
    "sg:postcode":"48430",
    "sg:province":"MI",
    "wof:name":"French Laundry",
    "wof:placetype":"venue"
},
  "geometry": {"coordinates":[-83.705465,42.792878],"type":"Point"}
}