{
  "type": "Feature",
  "properties": {
    "iso:country":"US",
    "sg:address":"902 Razorback Dr",
    "sg:city":"Houghton",
    "sg:classifiers":[
        {
            "category":"Ice Cream",
            "type":"Food & Drink"
        }
    ],
    "sg:menulink":"http://www.allmenus.com/mi/houghton/168570-dairy-queen/menu/",
    "sg:phone":"+1 906 483 0707",
    "sg:postcode":"49931",
    "sg:province":"MI",
    "sg:tags":[
        "burger",
        "american"
    ],
    "wof:name":"Dairy Queen",
    "wof:placetype":"venue"
},
  "geometry": {"coordinates":[-88.586673,47.112924],"type":"Point"}
}