{
  "type": "Feature",
  "properties": {
    "iso:country":"US",
    "sg:address":"349 Eagle Landings Ct",
    "sg:city":"Waterford",
    "sg:classifiers":[
        {
            "category":"Professional",
            "subcategory":"Computer Services",
            "type":"Services"
        }
    ],
    "sg:phone":"+1 248 706 1984",
    "sg:postcode":"48327",
    "sg:province":"MI",
    "sg:tags":[
        "datum"
    ],
    "wof:name":"Technique Consulting",
    "wof:placetype":"venue"
},
  "geometry": {"coordinates":[-83.426796,42.636958],"type":"Point"}
}