{
  "type": "Feature",
  "properties": {
    "iso:country":"US",
    "sg:address":"118 E Hines St",
    "sg:city":"Midland",
    "sg:classifiers":[
        {
            "category":"Home & Garden",
            "subcategory":"Carpets & Floor Coverings",
            "type":"Retail Goods"
        }
    ],
    "sg:phone":"+1 989 832 2221",
    "sg:postcode":"48640",
    "sg:province":"MI",
    "sg:tags":[
        "dealer",
        "rug"
    ],
    "wof:name":"Stanley's Furniture & Crptng",
    "wof:placetype":"venue"
},
  "geometry": {"coordinates":[-84.238806,43.617775],"type":"Point"}
}