{
  "type": "Feature",
  "properties": {
    "iso:country":"US",
    "sg:address":"4465 E 9 Mile Rd",
    "sg:city":"Sault Sainte Marie",
    "sg:classifiers":[
        {
            "category":"Farming",
            "subcategory":"Dairy Farm",
            "type":"Manufacturing & Wholesale Goods"
        }
    ],
    "sg:phone":"+1 906 635 0696",
    "sg:postcode":"49783",
    "sg:province":"MI",
    "wof:name":"Van Luven Farm",
    "wof:placetype":"venue"
},
  "geometry": {"coordinates":[-84.277727,46.376443],"type":"Point"}
}