{
  "type": "Feature",
  "properties": {
    "iso:country":"US",
    "sg:address":"206 S 4th Ave",
    "sg:city":"Ann Arbor",
    "sg:classifiers":[
        {
            "category":"Banks & Credit Unions",
            "subcategory":"Investment Brokerage",
            "type":"Services"
        }
    ],
    "sg:phone":"+1 734 662 1746",
    "sg:postcode":"48104",
    "sg:province":"MI",
    "sg:tags":[
        "advisory"
    ],
    "wof:name":"Pinnacle Investment Advisors",
    "wof:placetype":"venue"
},
  "geometry": {"coordinates":[-83.74742500000001,42.279608],"type":"Point"}
}