{
  "type": "Feature",
  "properties": {
    "iso:country":"US",
    "sg:address":"2888 Phelps Rd",
    "sg:city":"Traverse City",
    "sg:classifiers":[
        {
            "category":"Farming",
            "subcategory":"Vineyard",
            "type":"Manufacturing & Wholesale Goods"
        }
    ],
    "sg:phone":"+1 313 278 7351",
    "sg:postcode":"49686",
    "sg:province":"MI",
    "wof:name":"Porchside Vineyard",
    "wof:placetype":"venue"
},
  "geometry": {"coordinates":[-85.51947699999999,44.928105],"type":"Point"}
}