{
  "type": "Feature",
  "properties": {
    "iso:country":"US",
    "sg:address":"2916 W Townline Rd",
    "sg:city":"Midland",
    "sg:classifiers":[
        {
            "category":"Organizations",
            "subcategory":"Professional Association",
            "type":"Services"
        }
    ],
    "sg:phone":"+1 989 835 8309",
    "sg:postcode":"48642",
    "sg:province":"MI",
    "sg:tags":[
        "business"
    ],
    "wof:name":"Pleasantview Creamery Inc",
    "wof:placetype":"venue"
},
  "geometry": {"coordinates":[-84.159283,43.65446],"type":"Point"}
}