{
  "type": "Feature",
  "properties": {
    "iso:country":"US",
    "sg:address":"28830 W 8 Mile Rd",
    "sg:city":"Farmington Hills",
    "sg:classifiers":[
        {
            "category":"Building & Trades",
            "subcategory":"Plumbing",
            "type":"Services"
        }
    ],
    "sg:phone":"+1 248 477 0146",
    "sg:postcode":"48336",
    "sg:province":"MI",
    "wof:name":"McCaul Patrick",
    "wof:placetype":"venue"
},
  "geometry": {"coordinates":[-83.331703,42.441799],"type":"Point"}
}