{
  "type": "Feature",
  "properties": {
    "iso:country":"US",
    "sg:address":"8708 92nd St SE",
    "sg:city":"Alto",
    "sg:classifiers":[
        {
            "category":"Building & Trades",
            "subcategory":"Landscaping Services",
            "type":"Services"
        }
    ],
    "sg:phone":"+1 616 891 9850",
    "sg:postcode":"49302",
    "sg:province":"MI",
    "sg:tags":[
        "landscape",
        "contractor"
    ],
    "wof:name":"Sunset Landscape Contractors",
    "wof:placetype":"venue"
},
  "geometry": {"coordinates":[-85.451185,42.797803],"type":"Point"}
}