{
  "type": "Feature",
  "properties": {
    "iso:country":"US",
    "sg:address":"3701 S Creyts Rd",
    "sg:city":"Lansing",
    "sg:classifiers":[
        {
            "category":"Real Estate",
            "subcategory":"Real Estate Agent",
            "type":"Services"
        }
    ],
    "sg:phone":"+1 517 322 2005",
    "sg:postcode":"48917",
    "sg:province":"MI",
    "sg:tags":[
        "management"
    ],
    "wof:name":"Complete Crane Svc Inc",
    "wof:placetype":"venue"
},
  "geometry": {"coordinates":[-84.642267,42.692922],"type":"Point"}
}