{
  "type": "Feature",
  "properties": {
    "iso:country":"US",
    "sg:address":"3486 Pointe Tremble Rd",
    "sg:city":"Algonac",
    "sg:classifiers":[
        {
            "category":"Freight",
            "type":"Transportation"
        }
    ],
    "sg:phone":"+1 810 794 3660",
    "sg:postcode":"48001",
    "sg:province":"MI",
    "sg:tags":[
        "commercial",
        "storage"
    ],
    "wof:name":"Algonac Mini-Storage",
    "wof:placetype":"venue"
},
  "geometry": {"coordinates":[-82.56013400000001,42.618595],"type":"Point"}
}