{
  "type": "Feature",
  "properties": {
    "iso:country":"US",
    "sg:address":"1159 Pleasure St",
    "sg:city":"Milford",
    "sg:classifiers":[
        {
            "category":"Sports & Exercise",
            "subcategory":"Golf",
            "type":"Entertainment"
        },
        {
            "category":"Building & Trades",
            "subcategory":"Landscaping Services",
            "type":"Services"
        }
    ],
    "sg:phone":"+1 248 684 4868",
    "sg:postcode":"48381",
    "sg:province":"MI",
    "sg:tags":[
        "heavy",
        "construction",
        "putting",
        "greens"
    ],
    "wof:name":"Great Lakes Putting Greens Inc",
    "wof:placetype":"venue"
},
  "geometry": {"coordinates":[-83.58778,42.593308],"type":"Point"}
}