{
  "type": "Feature",
  "properties": {
    "iso:country":"US",
    "sg:address":"7312 Park Ave",
    "sg:city":"Allen Park",
    "sg:classifiers":[
        {
            "category":"Health Services",
            "subcategory":"Doctor",
            "type":"Services"
        }
    ],
    "sg:phone":"+1 313 381 5930",
    "sg:postcode":"48101",
    "sg:province":"MI",
    "sg:tags":[
        "medical"
    ],
    "wof:name":"Doraikannu Sukumarin MD PC",
    "wof:placetype":"venue"
},
  "geometry": {"coordinates":[-83.20984,42.253446],"type":"Point"}
}