{
  "type": "Feature",
  "properties": {
    "iso:country":"US",
    "sg:address":"3319 Remembrance Rd NW",
    "sg:city":"Grand Rapids",
    "sg:classifiers":[
        {
            "category":"Wholesale",
            "subcategory":"Vending Machines",
            "type":"Manufacturing & Wholesale Goods"
        }
    ],
    "sg:phone":"+1 616 453 2974",
    "sg:postcode":"49534",
    "sg:province":"MI",
    "wof:name":"BOS Vending Svc Inc",
    "wof:placetype":"venue"
},
  "geometry": {"coordinates":[-85.74996299999999,42.988038],"type":"Point"}
}