{
  "type": "Feature",
  "properties": {
    "iso:country":"US",
    "sg:address":"26076 Woodward Ave",
    "sg:city":"Royal Oak",
    "sg:classifiers":[
        {
            "category":"Real Estate",
            "subcategory":"Real Estate Agent",
            "type":"Services"
        }
    ],
    "sg:phone":"+1 248 591 9525",
    "sg:postcode":"48067",
    "sg:province":"MI",
    "sg:tags":[
        "appraiser"
    ],
    "wof:name":"Eisenbraun Appraisal Group Inc",
    "wof:placetype":"venue"
},
  "geometry": {"coordinates":[-83.153126,42.483707],"type":"Point"}
}