{
  "type": "Feature",
  "properties": {
    "iso:country":"US",
    "sg:address":"137 W Liberty St",
    "sg:city":"Plymouth",
    "sg:classifiers":[
        {
            "category":"Personal",
            "subcategory":"Beauty Salon",
            "type":"Services"
        }
    ],
    "sg:phone":"+1 734 453 5020",
    "sg:postcode":"48170",
    "sg:province":"MI",
    "sg:tags":[
        "shop",
        "barber"
    ],
    "wof:name":"Your Grampa's Moustache",
    "wof:placetype":"venue"
},
  "geometry": {"coordinates":[-83.460899,42.3792],"type":"Point"}
}