{
  "type": "Feature",
  "properties": {
    "iso:country":"US",
    "sg:address":"9450 100th St SE",
    "sg:city":"Alto",
    "sg:classifiers":[
        {
            "category":"Farming",
            "subcategory":"Farm",
            "type":"Manufacturing & Wholesale Goods"
        }
    ],
    "sg:phone":"+1 616 891 1521",
    "sg:postcode":"49302",
    "sg:province":"MI",
    "wof:name":"Vantage Point Farm",
    "wof:placetype":"venue"
},
  "geometry": {"coordinates":[-85.432706,42.783453],"type":"Point"}
}