{
  "type": "Feature",
  "properties": {
    "iso:country":"US",
    "sg:address":"7678 Cottonwood Dr Ste 3",
    "sg:city":"Jenison",
    "sg:classifiers":[
        {
            "category":"Health Services",
            "subcategory":"Dentist",
            "type":"Services"
        }
    ],
    "sg:phone":"+1 616 457 4600",
    "sg:postcode":"49428",
    "sg:province":"MI",
    "wof:name":"Wolf Tyler A DDS",
    "wof:placetype":"venue"
},
  "geometry": {"coordinates":[-85.79359100000001,42.908537],"type":"Point"}
}