{
  "type": "Feature",
  "properties": {
    "iso:country":"US",
    "sg:address":"9616 Rouget Rd",
    "sg:city":"Blissfield",
    "sg:phone":"+1 517 486 2871",
    "sg:postcode":"49228",
    "sg:province":"MI",
    "sg:tags":[
        "farm",
        "corn",
        "soybean"
    ],
    "wof:name":"J C Hamann",
    "wof:placetype":"venue"
},
  "geometry": {"coordinates":[-83.86756200000001,41.863063],"type":"Point"}
}