{
  "type": "Feature",
  "properties": {
    "iso:country":"US",
    "sg:address":"27934 Vandy St",
    "sg:city":"Harrison Twp",
    "sg:classifiers":[
        {
            "category":"Retail",
            "subcategory":"Auto Repair",
            "type":"Services"
        }
    ],
    "sg:phone":"+1 586 463 1188",
    "sg:postcode":"48045",
    "sg:province":"MI",
    "sg:tags":[
        "body",
        "automobile",
        "painting"
    ],
    "wof:name":"Paint Free Dent Removal Inc",
    "wof:placetype":"venue"
},
  "geometry": {"coordinates":[-82.83006399999999,42.570605],"type":"Point"}
}