{
  "type": "Feature",
  "properties": {
    "iso:country":"US",
    "sg:address":"156 N Ridge Rd",
    "sg:city":"Port Sanilac",
    "sg:classifiers":[
        {
            "category":"Restaurant",
            "type":"Food & Drink"
        }
    ],
    "sg:phone":"+1 810 622 6200",
    "sg:postcode":"48469",
    "sg:province":"MI",
    "wof:name":"Stone Lodge",
    "wof:placetype":"venue"
},
  "geometry": {"coordinates":[-82.54326,43.436051],"type":"Point"}
}