{
  "type": "Feature",
  "properties": {
    "iso:country":"US",
    "sg:address":"580 N Nicolet St",
    "sg:city":"Mackinaw City",
    "sg:classifiers":[
        {
            "category":"Professional",
            "subcategory":"Accounting & Tax Preparation",
            "type":"Services"
        }
    ],
    "sg:phone":"+1 231 436 5223",
    "sg:postcode":"49701",
    "sg:province":"MI",
    "sg:tags":[
        "accountant"
    ],
    "wof:name":"Richard E Mahlmeister CPA",
    "wof:placetype":"venue"
},
  "geometry": {"coordinates":[-84.732006,45.78593],"type":"Point"}
}