{
  "type": "Feature",
  "properties": {
    "iso:country":"US",
    "sg:address":"233 Euclid St",
    "sg:city":"Mount Clemens",
    "sg:classifiers":[
        {
            "category":"Building & Trades",
            "subcategory":"Construction",
            "type":"Services"
        }
    ],
    "sg:phone":"+1 586 954 2674",
    "sg:postcode":"48043",
    "sg:province":"MI",
    "sg:tags":[
        "hanging",
        "contractor"
    ],
    "wof:name":"Hot Boxes",
    "wof:placetype":"venue"
},
  "geometry": {"coordinates":[-82.87546,42.607185],"type":"Point"}
}