{
  "type": "Feature",
  "properties": {
    "iso:country":"US",
    "sg:address":"7095 Newark Rd",
    "sg:city":"Imlay City",
    "sg:classifiers":[
        {
            "category":"Home & Garden",
            "subcategory":"Garden Supply",
            "type":"Retail Goods"
        }
    ],
    "sg:phone":"+1 810 724 0050",
    "sg:postcode":"48444",
    "sg:province":"MI",
    "sg:tags":[
        "nurseryman"
    ],
    "wof:name":"Super & Son Nursery & Landscpg",
    "wof:placetype":"venue"
},
  "geometry": {"coordinates":[-83.06639699999999,43.007264],"type":"Point"}
}