{
  "type": "Feature",
  "properties": {
    "iso:country":"US",
    "sg:address":"27927 23 Mile Rd",
    "sg:city":"Chesterfield",
    "sg:classifiers":[
        {
            "category":"Restaurant",
            "type":"Food & Drink"
        }
    ],
    "sg:phone":"+1 586 598 5800",
    "sg:postcode":"48051",
    "sg:province":"MI",
    "sg:tags":[
        "pizza"
    ],
    "wof:name":"Papa Romano's",
    "wof:placetype":"venue"
},
  "geometry": {"coordinates":[-82.82815600000001,42.674558],"type":"Point"}
}