{
  "type": "Feature",
  "properties": {
    "iso:country":"US",
    "sg:address":"19 Hawley St",
    "sg:city":"Quincy",
    "sg:classifiers":[
        {
            "category":"Building & Trades",
            "subcategory":"Construction",
            "type":"Services"
        }
    ],
    "sg:phone":"+1 517 639 8405",
    "sg:postcode":"49082",
    "sg:province":"MI",
    "sg:tags":[
        "contractor"
    ],
    "wof:name":"Emerson Legg",
    "wof:placetype":"venue"
},
  "geometry": {"coordinates":[-84.875737,41.947953],"type":"Point"}
}