{
  "type": "Feature",
  "properties": {
    "iso:country":"US",
    "sg:address":"4297 Teal Rd",
    "sg:city":"Petersburg",
    "sg:classifiers":[
        {
            "category":"Freight",
            "type":"Transportation"
        }
    ],
    "sg:phone":"+1 734 279 2026",
    "sg:postcode":"49270",
    "sg:province":"MI",
    "wof:name":"Wadsworth Milk Transport Inc",
    "wof:placetype":"venue"
},
  "geometry": {"coordinates":[-83.706287,41.889269],"type":"Point"}
}