{
  "type": "Feature",
  "properties": {
    "iso:country":"US",
    "sg:address":"2010 Woodrun Dr SE",
    "sg:city":"Lowell",
    "sg:classifiers":[
        {
            "category":"Manufacturing",
            "subcategory":"Printing",
            "type":"Manufacturing & Wholesale Goods"
        }
    ],
    "sg:phone":"+1 616 987 9575",
    "sg:postcode":"49331",
    "sg:province":"MI",
    "sg:tags":[
        "commercial"
    ],
    "wof:name":"Everlasting Impressions",
    "wof:placetype":"venue"
},
  "geometry": {"coordinates":[-85.39914400000001,42.929637],"type":"Point"}
}