{
  "type": "Feature",
  "properties": {
    "iso:country":"US",
    "sg:address":"119 E Center St",
    "sg:city":"Ithaca",
    "sg:classifiers":[
        {
            "category":"Home & Garden",
            "subcategory":"Hardware",
            "type":"Retail Goods"
        }
    ],
    "sg:phone":"+1 989 875 3456",
    "sg:postcode":"48847",
    "sg:province":"MI",
    "wof:name":"Larry's True Value Hardware",
    "wof:placetype":"venue"
},
  "geometry": {"coordinates":[-84.607333,43.291726],"type":"Point"}
}