{
  "type": "Feature",
  "properties": {
    "iso:country":"US",
    "sg:address":"1821 Peters St",
    "sg:city":"Monroe",
    "sg:classifiers":[
        {
            "category":"Education",
            "subcategory":"Special Training",
            "type":"Public Place"
        }
    ],
    "sg:phone":"+1 734 241 0467",
    "sg:postcode":"48161",
    "sg:province":"MI",
    "wof:name":"Orchard Center",
    "wof:placetype":"venue"
},
  "geometry": {"coordinates":[-83.379361,41.901297],"type":"Point"}
}