{
  "type": "Feature",
  "properties": {
    "iso:country":"US",
    "sg:address":"2303 Ashmun St",
    "sg:city":"Sault Sainte Marie",
    "sg:classifiers":[
        {
            "category":"Autos & Motor Vehicles",
            "subcategory":"Automobile Sales",
            "type":"Retail Goods"
        }
    ],
    "sg:phone":"+1 906 632 0339",
    "sg:postcode":"49783",
    "sg:province":"MI",
    "sg:tags":[
        "used"
    ],
    "wof:name":"Autobaun Sales Inc",
    "wof:placetype":"venue"
},
  "geometry": {"coordinates":[-84.353692,46.479063],"type":"Point"}
}