{
  "type": "Feature",
  "properties": {
    "iso:country":"US",
    "sg:address":"3711 Lapeer Rd",
    "sg:city":"Flint",
    "sg:classifiers":[
        {
            "category":"Food & Beverages",
            "subcategory":"Groceries & Convenience Stores",
            "type":"Retail Goods"
        }
    ],
    "sg:phone":"+1 810 715 1143",
    "sg:postcode":"48506",
    "sg:province":"MI",
    "sg:tags":[
        "grocer"
    ],
    "wof:name":"Farmer Jack Market",
    "wof:placetype":"venue"
},
  "geometry": {"coordinates":[-83.637489,43.010093],"type":"Point"}
}