{
  "type": "Feature",
  "properties": {
    "iso:country":"US",
    "sg:address":"106 E 8th St",
    "sg:city":"Holland",
    "sg:classifiers":[
        {
            "category":"Shopping",
            "type":"Retail Goods"
        }
    ],
    "sg:phone":"+1 616 538 3030",
    "sg:postcode":"49423",
    "sg:province":"MI",
    "sg:tags":[
        "miscellaneous",
        "store"
    ],
    "wof:name":"Light Metals Corp",
    "wof:placetype":"venue"
},
  "geometry": {"coordinates":[-86.103021,42.790269],"type":"Point"}
}