{
  "type": "Feature",
  "properties": {
    "iso:country":"US",
    "sg:address":"950 N Mill St",
    "sg:city":"Northport",
    "sg:classifiers":[
        {
            "category":"Building & Trades",
            "subcategory":"Landscaping Services",
            "type":"Services"
        }
    ],
    "sg:phone":"+1 231 932 8361",
    "sg:postcode":"49670",
    "sg:province":"MI",
    "sg:tags":[
        "landscape",
        "contractor"
    ],
    "wof:name":"Northport Nursery Inc",
    "wof:placetype":"venue"
},
  "geometry": {"coordinates":[-85.61009900000001,45.151054],"type":"Point"}
}