{
  "type": "Feature",
  "properties": {
    "iso:country":"US",
    "sg:address":"1716 Montana Ave",
    "sg:city":"Gladstone",
    "sg:classifiers":[
        {
            "category":"Building & Trades",
            "subcategory":"Construction",
            "type":"Services"
        }
    ],
    "sg:phone":"+1 906 428 9072",
    "sg:postcode":"49837",
    "sg:province":"MI",
    "sg:tags":[
        "house"
    ],
    "wof:name":"Bay Building Consultants Inc",
    "wof:placetype":"venue"
},
  "geometry": {"coordinates":[-87.032349,45.840006],"type":"Point"}
}