{
  "type": "Feature",
  "properties": {
    "iso:country":"US",
    "sg:address":"664 S Rochester Rd",
    "sg:city":"Clawson",
    "sg:classifiers":[
        {
            "category":"Retail",
            "subcategory":"Auto Rental",
            "type":"Services"
        }
    ],
    "sg:phone":"+1 248 583 9382",
    "sg:postcode":"48073",
    "sg:province":"MI",
    "sg:tags":[
        "renting",
        "automobile"
    ],
    "wof:name":"Hertz Rent A Car",
    "wof:placetype":"venue"
},
  "geometry": {"coordinates":[-83.137365,42.52745],"type":"Point"}
}