{
  "type": "Feature",
  "properties": {
    "iso:country":"US",
    "sg:address":"5443 S Custer Rd",
    "sg:city":"Custer",
    "sg:classifiers":[
        {
            "category":"Professional",
            "subcategory":"Engineering",
            "type":"Services"
        }
    ],
    "sg:phone":"+1 231 757 9236",
    "sg:postcode":"49405",
    "sg:province":"MI",
    "wof:name":"Western Michigan Old Eng Corp",
    "wof:placetype":"venue"
},
  "geometry": {"coordinates":[-86.218169,43.855599],"type":"Point"}
}