{
  "type": "Feature",
  "properties": {
    "iso:country":"US",
    "sg:address":"8080 Monroe Rd",
    "sg:city":"Elwell",
    "sg:classifiers":[
        {
            "category":"Home & Garden",
            "subcategory":"Carpets & Floor Coverings",
            "type":"Retail Goods"
        }
    ],
    "sg:phone":"+1 989 463 4883",
    "sg:postcode":"48832",
    "sg:province":"MI",
    "wof:name":"Larrys Carpet & Home Center",
    "wof:placetype":"venue"
},
  "geometry": {"coordinates":[-84.775424,43.408312],"type":"Point"}
}