{
  "type": "Feature",
  "properties": {
    "iso:country":"US",
    "sg:address":"501 E Hobson Ave",
    "sg:city":"Flint",
    "sg:classifiers":[
        {
            "category":"Personal",
            "subcategory":"Beauty Salon",
            "type":"Services"
        }
    ],
    "sg:phone":"+1 810 787 3299",
    "sg:postcode":"48505",
    "sg:province":"MI",
    "wof:name":"Michelle's Beauty",
    "wof:placetype":"venue"
},
  "geometry": {"coordinates":[-83.697361,43.066597],"type":"Point"}
}