{
  "type": "Feature",
  "properties": {
    "iso:country":"US",
    "sg:address":"1750 E Lansing Dr",
    "sg:city":"East Lansing",
    "sg:classifiers":[
        {
            "category":"Insurance",
            "subcategory":"Insurance Agent",
            "type":"Services"
        }
    ],
    "sg:phone":"+1 517 333 7200",
    "sg:postcode":"48823",
    "sg:province":"MI",
    "wof:name":"AAA Insurance",
    "wof:placetype":"venue"
},
  "geometry": {"coordinates":[-84.452209,42.747943],"type":"Point"}
}