{
  "type": "Feature",
  "properties": {
    "iso:country":"US",
    "sg:address":"240 Emmons St SE",
    "sg:city":"Caledonia",
    "sg:classifiers":[
        {
            "category":"Education",
            "subcategory":"Library",
            "type":"Public Place"
        }
    ],
    "sg:phone":"+1 616 647 3840",
    "sg:postcode":"49316",
    "sg:province":"MI",
    "wof:name":"Caledonia Township Hall & Offices",
    "wof:placetype":"venue"
},
  "geometry": {"coordinates":[-85.514397,42.790298],"type":"Point"}
}