{
  "type": "Feature",
  "properties": {
    "iso:country":"US",
    "sg:address":"685 W Columbia Ave",
    "sg:city":"Battle Creek",
    "sg:classifiers":[
        {
            "category":"Manufacturing",
            "subcategory":"Printing",
            "type":"Manufacturing & Wholesale Goods"
        }
    ],
    "sg:phone":"+1 269 965 0525",
    "sg:postcode":"49015",
    "sg:province":"MI",
    "sg:tags":[
        "commercial"
    ],
    "wof:name":"Lawson Printers Inc",
    "wof:placetype":"venue"
},
  "geometry": {"coordinates":[-85.21311,42.298321],"type":"Point"}
}