{
  "type": "Feature",
  "properties": {
    "iso:country":"US",
    "sg:address":"4930 W Haslett Rd",
    "sg:city":"Perry",
    "sg:classifiers":[
        {
            "category":"Wholesale",
            "subcategory":"Farm Supplies",
            "type":"Manufacturing & Wholesale Goods"
        }
    ],
    "sg:phone":"+1 517 468 2480",
    "sg:postcode":"48872",
    "sg:province":"MI",
    "sg:tags":[
        "horse",
        "dealer"
    ],
    "wof:name":"Spruce Run Thoroughbred Trng",
    "wof:placetype":"venue"
},
  "geometry": {"coordinates":[-84.175146,42.742926],"type":"Point"}
}