{
  "type": "Feature",
  "properties": {
    "iso:country":"US",
    "sg:address":"7181 Whaley Rd",
    "sg:city":"Cadillac",
    "sg:classifiers":[
        {
            "category":"Freight",
            "type":"Transportation"
        }
    ],
    "sg:phone":"+1 231 779 2400",
    "sg:postcode":"49601",
    "sg:province":"MI",
    "sg:tags":[
        "commercial",
        "storage"
    ],
    "wof:name":"Security Storage Of Cadillac",
    "wof:placetype":"venue"
},
  "geometry": {"coordinates":[-85.381325,44.235552],"type":"Point"}
}