{
  "type": "Feature",
  "properties": {
    "iso:country":"US",
    "sg:address":"6676 Bloomfield Ln",
    "sg:city":"West Bloomfield",
    "sg:classifiers":[
        {
            "category":"Restaurant",
            "type":"Food & Drink"
        }
    ],
    "sg:phone":"+1 248 851 8782",
    "sg:postcode":"48322",
    "sg:province":"MI",
    "wof:name":"Fiddler",
    "wof:placetype":"venue"
},
  "geometry": {"coordinates":[-83.332736,42.542104],"type":"Point"}
}