{
  "type": "Feature",
  "properties": {
    "iso:country":"US",
    "sg:address":"14610 W 8 Mile Rd",
    "sg:city":"Oak Park",
    "sg:classifiers":[
        {
            "category":"Wholesale",
            "subcategory":"Electrical",
            "type":"Manufacturing & Wholesale Goods"
        }
    ],
    "sg:phone":"+1 248 967 5555",
    "sg:postcode":"48237",
    "sg:province":"MI",
    "sg:tags":[
        "alarm",
        "burglar",
        "system"
    ],
    "wof:name":"First Alert Inc",
    "wof:placetype":"venue"
},
  "geometry": {"coordinates":[-83.188355,42.445416],"type":"Point"}
}