{
  "type": "Feature",
  "properties": {
    "iso:country":"US",
    "sg:address":"254 W Maple Rd",
    "sg:city":"Birmingham",
    "sg:classifiers":[
        {
            "category":"Home & Garden",
            "subcategory":"Furniture",
            "type":"Retail Goods"
        }
    ],
    "sg:phone":"+1 248 644 4705",
    "sg:postcode":"48009",
    "sg:province":"MI",
    "sg:tags":[
        "store"
    ],
    "sg:website":"www.quatrine.com",
    "wof:name":"Quatrine Washable Furniture",
    "wof:placetype":"venue"
},
  "geometry": {"coordinates":[-83.21639999999999,42.546799],"type":"Point"}
}