{
  "type": "Feature",
  "properties": {
    "iso:country":"US",
    "sg:address":"9902 Wexford Dr",
    "sg:city":"Portage",
    "sg:classifiers":[
        {
            "category":"Building & Trades",
            "subcategory":"Construction",
            "type":"Services"
        }
    ],
    "sg:phone":"+1 269 324 9800",
    "sg:postcode":"49024",
    "sg:province":"MI",
    "sg:tags":[
        "home",
        "builder"
    ],
    "wof:name":"Advantage Home Inspections",
    "wof:placetype":"venue"
},
  "geometry": {"coordinates":[-85.59477200000001,42.172524],"type":"Point"}
}