{
  "type": "Feature",
  "properties": {
    "iso:country":"US",
    "sg:address":"836 2nd St",
    "sg:city":"Bay Port",
    "sg:classifiers":[
        {
            "category":"Organizations",
            "subcategory":"Religious Organization",
            "type":"Services"
        }
    ],
    "sg:phone":"+1 989 656 2151",
    "sg:postcode":"48720",
    "sg:province":"MI",
    "wof:name":"Bay Port United Methodist",
    "wof:placetype":"venue"
},
  "geometry": {"coordinates":[-83.371257,43.849315],"type":"Point"}
}