{
  "type": "Feature",
  "properties": {
    "iso:country":"US",
    "sg:address":"26400 W 12 Mile Rd",
    "sg:city":"Southfield",
    "sg:classifiers":[
        {
            "category":"Health Services",
            "subcategory":"Doctor",
            "type":"Services"
        }
    ],
    "sg:phone":"+1 248 355 3875",
    "sg:postcode":"48034",
    "sg:province":"MI",
    "wof:name":"Taylor Danette DO",
    "wof:placetype":"venue"
},
  "geometry": {"coordinates":[-83.30680099999999,42.500599],"type":"Point"}
}