{
  "type": "Feature",
  "properties": {
    "iso:country":"US",
    "sg:address":"2476 Slocum Rd",
    "sg:city":"Kingsley",
    "sg:classifiers":[
        {
            "category":"Shopping",
            "subcategory":"Hobbies, Toys, & Games",
            "type":"Retail Goods"
        }
    ],
    "sg:phone":"+1 231 263 3333",
    "sg:postcode":"49649",
    "sg:province":"MI",
    "sg:tags":[
        "craft"
    ],
    "wof:name":"Sandart Custom Creations",
    "wof:placetype":"venue"
},
  "geometry": {"coordinates":[-85.52614699999999,44.598856],"type":"Point"}
}