{
  "type": "Feature",
  "properties": {
    "iso:country":"US",
    "sg:address":"14225 Polk St",
    "sg:city":"Taylor",
    "sg:classifiers":[
        {
            "category":"Building & Trades",
            "subcategory":"Construction",
            "type":"Services"
        }
    ],
    "sg:phone":"+1 734 287 3799",
    "sg:postcode":"48180",
    "sg:province":"MI",
    "sg:tags":[
        "contractor"
    ],
    "wof:name":"L&L Siding",
    "wof:placetype":"venue"
},
  "geometry": {"coordinates":[-83.237297,42.203161],"type":"Point"}
}