{
  "type": "Feature",
  "properties": {
    "iso:country":"US",
    "sg:address":"10145 Portage Rd",
    "sg:city":"Portage",
    "sg:classifiers":[
        {
            "category":"Social Services",
            "subcategory":"Adult Care",
            "type":"Services"
        }
    ],
    "sg:phone":"+1 269 327 3640",
    "sg:postcode":"49002",
    "sg:province":"MI",
    "sg:tags":[
        "residential"
    ],
    "wof:name":"Portgage Road",
    "wof:placetype":"venue"
},
  "geometry": {"coordinates":[-85.569149,42.169787],"type":"Point"}
}