{
  "type": "Feature",
  "properties": {
    "iso:country":"US",
    "sg:address":"2411 W Camden Rd",
    "sg:city":"Camden",
    "sg:classifiers":[
        {
            "category":"Retail",
            "subcategory":"Repair Shop",
            "type":"Services"
        }
    ],
    "sg:phone":"+1 517 254 4484",
    "sg:postcode":"49232",
    "sg:province":"MI",
    "wof:name":"Turkeyfoot Taxidermy",
    "wof:placetype":"venue"
},
  "geometry": {"coordinates":[-84.65992799999999,41.752772],"type":"Point"}
}