{
  "type": "Feature",
  "properties": {
    "iso:country":"US",
    "sg:address":"4435 W Saginaw Hwy",
    "sg:city":"Lansing",
    "sg:classifiers":[
        {
            "category":"Professional",
            "subcategory":"Computer Services",
            "type":"Services"
        }
    ],
    "sg:phone":"+1 517 853 1942",
    "sg:postcode":"48917",
    "sg:province":"MI",
    "wof:name":"Computer Troubleshooters",
    "wof:placetype":"venue"
},
  "geometry": {"coordinates":[-84.61134300000001,42.741035],"type":"Point"}
}