{
  "type": "Feature",
  "properties": {
    "iso:country":"US",
    "sg:address":"14441 Eureka Road",
    "sg:city":"Southgate",
    "sg:classifiers":[
        {
            "category":"Home & Garden",
            "subcategory":"Garden Supply",
            "type":"Retail Goods"
        },
        {
            "category":"Home & Garden",
            "subcategory":"Hardware",
            "type":"Retail Goods"
        }
    ],
    "sg:phone":"+1 734 284 7440",
    "sg:postcode":"48195",
    "sg:province":"MI",
    "sg:tags":[
        "nursery",
        "gardening",
        "store"
    ],
    "sg:website":"www.acohardware.com",
    "wof:name":"Aco Hardware",
    "wof:placetype":"venue"
},
  "geometry": {"coordinates":[-83.199202,42.198924],"type":"Point"}
}