{
  "type": "Feature",
  "properties": {
    "iso:country":"US",
    "sg:address":"6806 S Shore Dr",
    "sg:city":"Whitehall",
    "sg:classifiers":[
        {
            "category":"Recreation",
            "subcategory":"Marina",
            "type":"Entertainment"
        }
    ],
    "sg:phone":"+1 231 893 3935",
    "sg:postcode":"49461",
    "sg:province":"MI",
    "sg:tags":[
        "rental",
        "boat"
    ],
    "wof:name":"South Shore Marina Inc",
    "wof:placetype":"venue"
},
  "geometry": {"coordinates":[-86.40828,43.362511],"type":"Point"}
}