{
  "type": "Feature",
  "properties": {
    "iso:country":"US",
    "sg:address":"2243 Ashmun St",
    "sg:city":"Sault Sainte Marie",
    "sg:classifiers":[
        {
            "category":"Organizations",
            "subcategory":"Professional Association",
            "type":"Services"
        }
    ],
    "sg:phone":"+1 906 635 1544",
    "sg:postcode":"49783",
    "sg:province":"MI",
    "sg:tags":[
        "business"
    ],
    "wof:name":"M E A",
    "wof:placetype":"venue"
},
  "geometry": {"coordinates":[-84.353678,46.479596],"type":"Point"}
}