{
  "type": "Feature",
  "properties": {
    "iso:country":"US",
    "sg:address":"4554 W 48th St",
    "sg:city":"Fremont",
    "sg:classifiers":[
        {
            "category":"Social Services",
            "subcategory":"Job Training",
            "type":"Services"
        }
    ],
    "sg:phone":"+1 231 924 9295",
    "sg:postcode":"49412",
    "sg:province":"MI",
    "sg:tags":[
        "rehabilitation"
    ],
    "wof:name":"THS Of Fremont Rehab",
    "wof:placetype":"venue"
},
  "geometry": {"coordinates":[-85.919234,43.466964],"type":"Point"}
}