{
  "type": "Feature",
  "properties": {
    "iso:country":"US",
    "sg:address":"25260 Stanford St",
    "sg:city":"Dearborn Heights",
    "sg:classifiers":[
        {
            "category":"Social Services",
            "subcategory":"Child Care",
            "type":"Services"
        }
    ],
    "sg:phone":"+1 313 730 8707",
    "sg:postcode":"48125",
    "sg:province":"MI",
    "sg:tags":[
        "day"
    ],
    "wof:name":"Laurels Little Day Care",
    "wof:placetype":"venue"
},
  "geometry": {"coordinates":[-83.284539,42.278813],"type":"Point"}
}