{
  "type": "Feature",
  "properties": {
    "iso:country":"US",
    "sg:address":"15050 Dexter Ave",
    "sg:city":"Detroit",
    "sg:classifiers":[
        {
            "category":"Retail",
            "subcategory":"Funeral Services",
            "type":"Services"
        }
    ],
    "sg:phone":"+1 313 863 6366",
    "sg:postcode":"48238",
    "sg:province":"MI",
    "wof:name":"Ramsey Memorial Chapel",
    "wof:placetype":"venue"
},
  "geometry": {"coordinates":[-83.135502,42.402417],"type":"Point"}
}