{
  "type": "Feature",
  "properties": {
    "iso:country":"US",
    "sg:address":"24865 5 Mile Rd Ste 3",
    "sg:city":"Redford",
    "sg:classifiers":[
        {
            "category":"Health Services",
            "subcategory":"Chiropractor",
            "type":"Services"
        }
    ],
    "sg:phone":"+1 313 592 4556",
    "sg:postcode":"48239",
    "sg:province":"MI",
    "wof:name":"Whalen Chiropractic Clinic",
    "wof:placetype":"venue"
},
  "geometry": {"coordinates":[-83.28510300000001,42.399799],"type":"Point"}
}