{
  "type": "Feature",
  "properties": {
    "iso:country":"US",
    "sg:address":"14055 Simone Dr",
    "sg:city":"Shelby Twp",
    "sg:classifiers":[
        {
            "category":"Manufacturing",
            "subcategory":"Furniture",
            "type":"Manufacturing & Wholesale Goods"
        },
        {
            "category":"Retail",
            "subcategory":"Auto Repair",
            "type":"Services"
        }
    ],
    "sg:phone":"+1 586 532 8715",
    "sg:postcode":"48315",
    "sg:province":"MI",
    "sg:tags":[
        "trim",
        "for",
        "mfg",
        "automotive",
        "consultant",
        "interior"
    ],
    "sg:website":"www.rivasinc.com",
    "wof:name":"Rivas Inc",
    "wof:placetype":"venue"
},
  "geometry": {"coordinates":[-82.987627,42.669882],"type":"Point"}
}