{
  "type": "Feature",
  "properties": {
    "iso:country":"US",
    "sg:address":"3463 Forest Meadow Ct",
    "sg:city":"Saginaw",
    "sg:classifiers":[
        {
            "category":"Communications",
            "subcategory":"Film & Video Production",
            "type":"Services"
        }
    ],
    "sg:phone":"+1 989 792 6532",
    "sg:postcode":"48603",
    "sg:province":"MI",
    "sg:tags":[
        "motion",
        "audio"
    ],
    "wof:name":"Creative Communications Video",
    "wof:placetype":"venue"
},
  "geometry": {"coordinates":[-84.026839,43.457675],"type":"Point"}
}