{
  "type": "Feature",
  "properties": {
    "iso:country":"US",
    "sg:address":"206 E Huron St",
    "sg:city":"Ann Arbor",
    "sg:classifiers":[
        {
            "category":"Insurance",
            "subcategory":"Insurance Agent",
            "type":"Services"
        }
    ],
    "sg:phone":"+1 734 995 9797",
    "sg:postcode":"48104",
    "sg:province":"MI",
    "wof:name":"Massmutual",
    "wof:placetype":"venue"
},
  "geometry": {"coordinates":[-83.73969200000001,42.28115],"type":"Point"}
}