{
  "type": "Feature",
  "properties": {
    "iso:country":"US",
    "sg:address":"609 S Forest Ave",
    "sg:city":"Ann Arbor",
    "sg:classifiers":[
        {
            "category":"Retail",
            "subcategory":"Self-service Laundry",
            "type":"Services"
        }
    ],
    "sg:phone":"+1 734 747 8007",
    "sg:postcode":"48104",
    "sg:province":"MI",
    "sg:tags":[
        "coin"
    ],
    "wof:name":"Champions Laundromat",
    "wof:placetype":"venue"
},
  "geometry": {"coordinates":[-83.73297599999999,42.273945],"type":"Point"}
}