{
  "type": "Feature",
  "properties": {
    "iso:country":"US",
    "sg:address":"150 Maincentre",
    "sg:city":"Northville",
    "sg:classifiers":[
        {
            "category":"Real Estate",
            "subcategory":"Real Estate Operator",
            "type":"Services"
        }
    ],
    "sg:phone":"+1 248 347 6811",
    "sg:postcode":"48167",
    "sg:province":"MI",
    "sg:tags":[
        "building",
        "apartment"
    ],
    "wof:name":"Main Center",
    "wof:placetype":"venue"
},
  "geometry": {"coordinates":[-83.483519,42.43083],"type":"Point"}
}