{
  "type": "Feature",
  "properties": {
    "iso:country":"US",
    "sg:address":"9841 Kier Rd",
    "sg:city":"Holly",
    "sg:classifiers":[
        {
            "category":"Utilities",
            "subcategory":"Telephone",
            "type":"Services"
        }
    ],
    "sg:phone":"+1 248 531 0132",
    "sg:postcode":"48442",
    "sg:province":"MI",
    "sg:tags":[
        "communications"
    ],
    "wof:name":"PQI Communications",
    "wof:placetype":"venue"
},
  "geometry": {"coordinates":[-83.485989,42.78846],"type":"Point"}
}