{
  "type": "Feature",
  "properties": {
    "iso:country":"US",
    "sg:address":"2613 Collendale",
    "sg:city":"Commerce Twp",
    "sg:classifiers":[
        {
            "category":"Professional",
            "subcategory":"Business Services",
            "type":"Services"
        }
    ],
    "sg:phone":"+1 248 685 9281",
    "sg:postcode":"48382",
    "sg:province":"MI",
    "sg:tags":[
        "decorating",
        "contractor"
    ],
    "wof:name":"One Enchanted Evening",
    "wof:placetype":"venue"
},
  "geometry": {"coordinates":[-83.557468,42.564631],"type":"Point"}
}