{
  "type": "Feature",
  "properties": {
    "iso:country":"US",
    "sg:address":"21055 E 12 Mile Rd",
    "sg:city":"Roseville",
    "sg:classifiers":[
        {
            "category":"Health Services",
            "subcategory":"Doctor",
            "type":"Services"
        }
    ],
    "sg:phone":"+1 586 772 0322",
    "sg:postcode":"48066",
    "sg:province":"MI",
    "sg:tags":[
        "surgeon",
        "oral"
    ],
    "sg:website":"www.drerichaskins.com",
    "wof:name":"Haskins Eric C DDS",
    "wof:placetype":"venue"
},
  "geometry": {"coordinates":[-82.903603,42.510399],"type":"Point"}
}