{
  "type": "Feature",
  "properties": {
    "iso:country":"US",
    "sg:address":"294 84th St SW",
    "sg:city":"Byron Center",
    "sg:classifiers":[
        {
            "category":"Autos & Motor Vehicles",
            "subcategory":"Auto Supplies",
            "type":"Retail Goods"
        },
        {
            "category":"Retail",
            "subcategory":"Auto Repair",
            "type":"Services"
        }
    ],
    "sg:phone":"+1 616 878 1581",
    "sg:postcode":"49315",
    "sg:province":"MI",
    "sg:tags":[
        "new",
        "retread",
        "tire"
    ],
    "sg:website":"www.wonderlandtire.com",
    "wof:name":"Wonderland Tire Co Inc",
    "wof:placetype":"venue"
},
  "geometry": {"coordinates":[-85.669411,42.811649],"type":"Point"}
}