{
  "type": "Feature",
  "properties": {
    "iso:country":"US",
    "sg:address":"655 Brockmoor Ln",
    "sg:city":"Bloomfield Hills",
    "sg:classifiers":[
        {
            "category":"Communications",
            "subcategory":"Film & Video Production",
            "type":"Services"
        }
    ],
    "sg:phone":"+1 248 335 2511",
    "sg:postcode":"48304",
    "sg:province":"MI",
    "sg:tags":[
        "motion"
    ],
    "wof:name":"Broken Twig Productions Inc",
    "wof:placetype":"venue"
},
  "geometry": {"coordinates":[-83.233244,42.607395],"type":"Point"}
}