{
  "type": "Feature",
  "properties": {
    "iso:country":"US",
    "sg:address":"1223 Ludington St",
    "sg:city":"Escanaba",
    "sg:classifiers":[
        {
            "category":"Bars & Pubs",
            "type":"Food & Drink"
        }
    ],
    "sg:phone":"+1 906 786 9757",
    "sg:postcode":"49829",
    "sg:province":"MI",
    "sg:tags":[
        "lounge",
        "cocktail"
    ],
    "wof:name":"Catmando's",
    "wof:placetype":"venue"
},
  "geometry": {"coordinates":[-87.06532,45.745685],"type":"Point"}
}