{
  "type": "Feature",
  "properties": {
    "iso:country":"US",
    "sg:address":"141 N Telegraph Rd",
    "sg:city":"Waterford",
    "sg:classifiers":[
        {
            "category":"Restaurant",
            "type":"Food & Drink"
        }
    ],
    "sg:menulink":"http://www.allmenus.com/mi/waterford/185769-mcdonalds/menu/",
    "sg:postcode":"48328",
    "sg:province":"MI",
    "sg:tags":[
        "burger",
        "american"
    ],
    "wof:name":"McDonald's",
    "wof:placetype":"venue"
},
  "geometry": {"coordinates":[-83.326611,42.639153],"type":"Point"}
}