{
  "type": "Feature",
  "properties": {
    "iso:country":"US",
    "sg:address":"1901 Horton Rd",
    "sg:city":"Jackson",
    "sg:classifiers":[
        {
            "category":"Utilities",
            "subcategory":"Cable",
            "type":"Services"
        }
    ],
    "sg:phone":"+1 517 789 8121",
    "sg:postcode":"49203",
    "sg:province":"MI",
    "sg:tags":[
        "tv"
    ],
    "wof:name":"AT&T",
    "wof:placetype":"venue"
},
  "geometry": {"coordinates":[-84.43776699999999,42.201057],"type":"Point"}
}