{
  "type": "Feature",
  "properties": {
    "iso:country":"US",
    "sg:address":"7085 Henderson Dr",
    "sg:city":"Traverse City",
    "sg:classifiers":[
        {
            "category":"Professional",
            "subcategory":"Business Services",
            "type":"Services"
        }
    ],
    "sg:phone":"+1 231 947 2242",
    "sg:postcode":"49686",
    "sg:province":"MI",
    "wof:name":"Doug Rigan Inspection Service",
    "wof:placetype":"venue"
},
  "geometry": {"coordinates":[-85.562394,44.792561],"type":"Point"}
}