{
  "type": "Feature",
  "properties": {
    "iso:country":"US",
    "sg:address":"1623 Grand Ave",
    "sg:city":"Kalamazoo",
    "sg:classifiers":[
        {
            "category":"Professional",
            "subcategory":"Business Services",
            "type":"Services"
        }
    ],
    "sg:phone":"+1 269 385 3146",
    "sg:postcode":"49006",
    "sg:province":"MI",
    "wof:name":"Partner Building",
    "wof:placetype":"venue"
},
  "geometry": {"coordinates":[-85.60805499999999,42.291685],"type":"Point"}
}