{
  "type": "Feature",
  "properties": {
    "iso:country":"US",
    "sg:address":"150 N Michigan Ave",
    "sg:city":"Shelby",
    "sg:classifiers":[
        {
            "category":"Personal",
            "subcategory":"Beauty Salon",
            "type":"Services"
        }
    ],
    "sg:phone":"+1 231 861 5237",
    "sg:postcode":"49455",
    "sg:province":"MI",
    "sg:tags":[
        "shop"
    ],
    "wof:name":"Touch of Beauty",
    "wof:placetype":"venue"
},
  "geometry": {"coordinates":[-86.363883,43.610334],"type":"Point"}
}