{
  "type": "Feature",
  "properties": {
    "iso:country":"US",
    "sg:address":"1549 S Wayne Rd",
    "sg:city":"Westland",
    "sg:classifiers":[
        {
            "category":"Personal",
            "subcategory":"Beauty Salon",
            "type":"Services"
        }
    ],
    "sg:phone":"+1 734 721 1957",
    "sg:postcode":"48186",
    "sg:province":"MI",
    "sg:tags":[
        "shop"
    ],
    "wof:name":"Distinct Design In Hair & Nail",
    "wof:placetype":"venue"
},
  "geometry": {"coordinates":[-83.388133,42.297438],"type":"Point"}
}