{
  "type": "Feature",
  "properties": {
    "iso:country":"US",
    "sg:address":"5135 Windyridge Dr",
    "sg:city":"Portage",
    "sg:classifiers":[
        {
            "category":"Professional",
            "subcategory":"Accounting & Tax Preparation",
            "type":"Services"
        }
    ],
    "sg:phone":"+1 269 382 5923",
    "sg:postcode":"49002",
    "sg:province":"MI",
    "wof:name":"John A Lilly CPA",
    "wof:placetype":"venue"
},
  "geometry": {"coordinates":[-85.581872,42.241578],"type":"Point"}
}