{
  "type": "Feature",
  "properties": {
    "iso:country":"US",
    "sg:address":"900 Tower Dr Ste 100",
    "sg:city":"Troy",
    "sg:classifiers":[
        {
            "category":"Banks & Credit Unions",
            "subcategory":"Bank",
            "type":"Services"
        }
    ],
    "sg:phone":"+1 248 293 3051",
    "sg:postcode":"48098",
    "sg:province":"MI",
    "sg:website":"www.citizensbank.com",
    "wof:name":"Citizens Bank",
    "wof:placetype":"venue"
},
  "geometry": {"coordinates":[-83.166281,42.596252],"type":"Point"}
}