{
  "type": "Feature",
  "properties": {
    "iso:country":"US",
    "sg:address":"219 N Main St",
    "sg:city":"Davison",
    "sg:classifiers":[
        {
            "category":"Retail",
            "subcategory":"Portrait Studio",
            "type":"Services"
        }
    ],
    "sg:phone":"+1 810 658 7089",
    "sg:postcode":"48423",
    "sg:province":"MI",
    "sg:tags":[
        "identification",
        "card"
    ],
    "sg:website":"www.safetykid.com",
    "wof:name":"Safe & Sound",
    "wof:placetype":"venue"
},
  "geometry": {"coordinates":[-83.516842,43.031632],"type":"Point"}
}