{
  "type": "Feature",
  "properties": {
    "iso:country":"US",
    "sg:address":"10837 E M 48",
    "sg:city":"Stalwart",
    "sg:classifiers":[
        {
            "category":"Personal",
            "type":"Services"
        }
    ],
    "sg:phone":"+1 906 647 2007",
    "sg:postcode":"49736",
    "sg:province":"MI",
    "sg:tags":[
        "therapist",
        "massage"
    ],
    "wof:name":"Follow Your Heart",
    "wof:placetype":"venue"
},
  "geometry": {"coordinates":[-84.221445,46.071695],"type":"Point"}
}