{
  "type": "Feature",
  "properties": {
    "iso:country":"US",
    "sg:address":"3516 S Westnedge Ave",
    "sg:city":"Kalamazoo",
    "sg:classifiers":[
        {
            "category":"Personal",
            "subcategory":"Beauty Salon",
            "type":"Services"
        }
    ],
    "sg:phone":"+1 269 381 8311",
    "sg:postcode":"49008",
    "sg:province":"MI",
    "sg:tags":[
        "shop"
    ],
    "wof:name":"Roger's Hair A Scope",
    "wof:placetype":"venue"
},
  "geometry": {"coordinates":[-85.58969399999999,42.255694],"type":"Point"}
}