{
  "type": "Feature",
  "properties": {
    "iso:country":"US",
    "sg:address":"409 N Jeffery St",
    "sg:city":"Ithaca",
    "sg:classifiers":[
        {
            "category":"Social Services",
            "subcategory":"Child Care",
            "type":"Services"
        }
    ],
    "sg:phone":"+1 989 875 3173",
    "sg:postcode":"48847",
    "sg:province":"MI",
    "sg:tags":[
        "day"
    ],
    "wof:name":"Red Wagon Day Care",
    "wof:placetype":"venue"
},
  "geometry": {"coordinates":[-84.603774,43.296891],"type":"Point"}
}