{
  "type": "Feature",
  "properties": {
    "iso:country":"US",
    "sg:address":"15437 N Red Bud Trl",
    "sg:city":"Buchanan",
    "sg:classifiers":[
        {
            "category":"Wholesale",
            "subcategory":"Books, Periodicals, & Newspapers",
            "type":"Manufacturing & Wholesale Goods"
        }
    ],
    "sg:phone":"+1 269 695 1800",
    "sg:postcode":"49107",
    "sg:province":"MI",
    "sg:tags":[
        "dealer"
    ],
    "wof:name":"Library & Educational Svc",
    "wof:placetype":"venue"
},
  "geometry": {"coordinates":[-86.365408,41.846782],"type":"Point"}
}