{
  "type": "Feature",
  "properties": {
    "iso:country":"US",
    "sg:address":"200 South St",
    "sg:city":"Rochester",
    "sg:classifiers":[
        {
            "category":"Professional",
            "subcategory":"Advertising",
            "type":"Services"
        }
    ],
    "sg:phone":"+1 248 650 4401",
    "sg:postcode":"48307",
    "sg:province":"MI",
    "sg:tags":[
        "distribution"
    ],
    "wof:name":"G & B Distribution",
    "wof:placetype":"venue"
},
  "geometry": {"coordinates":[-83.122535,42.676682],"type":"Point"}
}