{
  "type": "Feature",
  "properties": {
    "iso:country":"US",
    "sg:address":"1191 E Mosherville Rd",
    "sg:city":"Jonesville",
    "sg:classifiers":[
        {
            "category":"Retail",
            "subcategory":"Auto Repair",
            "type":"Services"
        }
    ],
    "sg:phone":"+1 517 549 8520",
    "sg:postcode":"49250",
    "sg:province":"MI",
    "sg:tags":[
        "general"
    ],
    "wof:name":"Arts Garage",
    "wof:placetype":"venue"
},
  "geometry": {"coordinates":[-84.643658,42.058144],"type":"Point"}
}