{
  "type": "Feature",
  "properties": {
    "iso:country":"US",
    "sg:address":"37855 Lyndon St",
    "sg:city":"Livonia",
    "sg:classifiers":[
        {
            "category":"Education",
            "subcategory":"School",
            "type":"Public Place"
        }
    ],
    "sg:phone":"+1 734 744 2795",
    "sg:postcode":"48154",
    "sg:province":"MI",
    "sg:tags":[
        "high",
        "middle",
        "elementary"
    ],
    "wof:name":"Livonia Public Schools",
    "wof:placetype":"venue"
},
  "geometry": {"coordinates":[-83.41870299999999,42.389046],"type":"Point"}
}