{
  "type": "Feature",
  "properties": {
    "iso:country":"US",
    "sg:address":"1038 E Michigan Ave",
    "sg:city":"Paw Paw",
    "sg:classifiers":[
        {
            "category":"Home & Garden",
            "subcategory":"Hardware",
            "type":"Retail Goods"
        }
    ],
    "sg:phone":"+1 269 657 2515",
    "sg:postcode":"49079",
    "sg:province":"MI",
    "wof:name":"Ace Hardware",
    "wof:placetype":"venue"
},
  "geometry": {"coordinates":[-85.876181,42.219241],"type":"Point"}
}