{
  "type": "Feature",
  "properties": {
    "iso:country":"US",
    "sg:address":"3044 W Grand Blvd",
    "sg:city":"Detroit",
    "sg:classifiers":[
        {
            "category":"Landmark",
            "subcategory":"Historic",
            "type":"Public Place"
        }
    ],
    "sg:postcode":"48218",
    "sg:province":"MI",
    "sg:tags":[
        "building",
        "historical"
    ],
    "wof:name":"General Motors Building",
    "wof:placetype":"venue"
},
  "geometry": {"coordinates":[-83.075413,42.368793],"type":"Point"}
}