{
  "type": "Feature",
  "properties": {
    "iso:country":"US",
    "sg:address":"10497 Lake Shore Dr",
    "sg:city":"Fenton",
    "sg:classifiers":[
        {
            "category":"Building & Trades",
            "subcategory":"Cleaning & Sanitation",
            "type":"Services"
        }
    ],
    "sg:phone":"+1 810 714 1296",
    "sg:postcode":"48430",
    "sg:province":"MI",
    "sg:tags":[
        "maintenance"
    ],
    "wof:name":"Garrard Cleaning",
    "wof:placetype":"venue"
},
  "geometry": {"coordinates":[-83.746816,42.753863],"type":"Point"}
}