{
  "type": "Feature",
  "properties": {
    "iso:country":"US",
    "sg:address":"43560 Utica Rd",
    "sg:city":"Sterling Heights",
    "sg:classifiers":[
        {
            "category":"Retail",
            "subcategory":"Auto Repair",
            "type":"Services"
        }
    ],
    "sg:phone":"+1 586 726 9400",
    "sg:postcode":"48314",
    "sg:province":"MI",
    "sg:website":"www.fairwayenglne.com",
    "wof:name":"Fairway Engine Exchange",
    "wof:placetype":"venue"
},
  "geometry": {"coordinates":[-83.03469800000001,42.614399],"type":"Point"}
}