{
  "type": "Feature",
  "properties": {
    "iso:country":"US",
    "sg:address":"6292 American Ave",
    "sg:city":"Portage",
    "sg:classifiers":[
        {
            "category":"Wholesale",
            "subcategory":"Construction Materials",
            "type":"Manufacturing & Wholesale Goods"
        }
    ],
    "sg:phone":"+1 269 324 6926",
    "sg:postcode":"49002",
    "sg:province":"MI",
    "sg:tags":[
        "insulation"
    ],
    "wof:name":"N L Fabricating",
    "wof:placetype":"venue"
},
  "geometry": {"coordinates":[-85.534828,42.225801],"type":"Point"}
}