{
  "type": "Feature",
  "properties": {
    "iso:country":"US",
    "sg:address":"34029 Roycroft St",
    "sg:city":"Livonia",
    "sg:classifiers":[
        {
            "category":"Real Estate",
            "subcategory":"Architect",
            "type":"Services"
        }
    ],
    "sg:phone":"+1 734 945 6837",
    "sg:postcode":"48154",
    "sg:province":"MI",
    "sg:tags":[
        "management",
        "general",
        "project",
        "engineering",
        "design",
        "supplier"
    ],
    "wof:name":"Lorenz Consulting LLC",
    "wof:placetype":"venue"
},
  "geometry": {"coordinates":[-83.379132,42.399208],"type":"Point"}
}