{
  "type": "Feature",
  "properties": {
    "iso:country":"US",
    "sg:address":"679 Butternut Dr",
    "sg:city":"Holland",
    "sg:classifiers":[
        {
            "category":"Organizations",
            "subcategory":"Membership Organization",
            "type":"Services"
        }
    ],
    "sg:phone":"+1 616 399 3759",
    "sg:postcode":"49424",
    "sg:province":"MI",
    "wof:name":"Sjr Enterprise",
    "wof:placetype":"venue"
},
  "geometry": {"coordinates":[-86.12643300000001,42.817857],"type":"Point"}
}