{
  "type": "Feature",
  "properties": {
    "iso:country":"US",
    "sg:address":"53635 Grand River Ave",
    "sg:city":"New Hudson",
    "sg:classifiers":[
        {
            "category":"Home & Garden",
            "subcategory":"Garden Supply",
            "type":"Retail Goods"
        }
    ],
    "sg:phone":"+1 248 437 1444",
    "sg:postcode":"48165",
    "sg:province":"MI",
    "sg:tags":[
        "outdoor",
        "power",
        "equipment",
        "pump",
        "industrial",
        "gen"
    ],
    "wof:name":"New Hudson Power Inc",
    "wof:placetype":"venue"
},
  "geometry": {"coordinates":[-83.581457,42.504142],"type":"Point"}
}