{
  "type": "Feature",
  "properties": {
    "iso:country":"US",
    "sg:address":"8566 S West-Bay Shore Dr",
    "sg:city":"Traverse City",
    "sg:classifiers":[
        {
            "category":"Building & Trades",
            "subcategory":"Construction",
            "type":"Services"
        }
    ],
    "sg:phone":"+1 231 929 8007",
    "sg:postcode":"49684",
    "sg:province":"MI",
    "sg:tags":[
        "fire",
        "restoration",
        "damage"
    ],
    "wof:name":"Northern Reflections Constr",
    "wof:placetype":"venue"
},
  "geometry": {"coordinates":[-85.651516,44.854205],"type":"Point"}
}