{
  "type": "Feature",
  "properties": {
    "iso:country":"US",
    "sg:address":"107 E Main St",
    "sg:city":"Northville",
    "sg:classifiers":[
        {
            "category":"Insurance",
            "subcategory":"Life Insurance",
            "type":"Services"
        }
    ],
    "sg:phone":"+1 248 349 4639",
    "sg:postcode":"48167",
    "sg:province":"MI",
    "sg:tags":[
        "fun",
        "annuity",
        "mutual",
        "accident",
        "health"
    ],
    "wof:name":"Teubert & Associates",
    "wof:placetype":"venue"
},
  "geometry": {"coordinates":[-83.482232,42.431211],"type":"Point"}
}