{
  "type": "Feature",
  "properties": {
    "iso:country":"US",
    "sg:address":"15638 W 10 Mile Rd",
    "sg:city":"Southfield",
    "sg:classifiers":[
        {
            "category":"Personal",
            "subcategory":"Nail Salon",
            "type":"Services"
        }
    ],
    "sg:phone":"+1 248 968 5216",
    "sg:postcode":"48075",
    "sg:province":"MI",
    "wof:name":"Pink and White Salon",
    "wof:placetype":"venue"
},
  "geometry": {"coordinates":[-83.20241799999999,42.473955],"type":"Point"}
}