{
  "type": "Feature",
  "properties": {
    "iso:country":"US",
    "sg:address":"195 W 9 Mile Rd Ste 207",
    "sg:city":"Ferndale",
    "sg:classifiers":[
        {
            "category":"Banks & Credit Unions",
            "subcategory":"Financial Services",
            "type":"Services"
        }
    ],
    "sg:phone":"+1 248 336 2003",
    "sg:postcode":"48220",
    "sg:province":"MI",
    "sg:tags":[
        "broker",
        "mortgage"
    ],
    "wof:name":"P R Processing & Closing",
    "wof:placetype":"venue"
},
  "geometry": {"coordinates":[-83.1362,42.460499],"type":"Point"}
}