{
  "type": "Feature",
  "properties": {
    "iso:country":"US",
    "sg:address":"6520 Stadium Dr",
    "sg:city":"Kalamazoo",
    "sg:classifiers":[
        {
            "category":"Food & Beverages",
            "subcategory":"Groceries & Convenience Stores",
            "type":"Retail Goods"
        }
    ],
    "sg:phone":"+1 269 375 6527",
    "sg:postcode":"49009",
    "sg:province":"MI",
    "wof:name":"Oshtemo Quick Mart",
    "wof:placetype":"venue"
},
  "geometry": {"coordinates":[-85.67889700000001,42.25894],"type":"Point"}
}