{
  "type": "Feature",
  "properties": {
    "iso:country":"US",
    "sg:address":"211 S Michigan Ave",
    "sg:city":"Howell",
    "sg:classifiers":[
        {
            "category":"Building & Trades",
            "subcategory":"Pest Control",
            "type":"Services"
        }
    ],
    "sg:phone":"+1 517 548 5200",
    "sg:postcode":"48843",
    "sg:province":"MI",
    "wof:name":"Absolute Pest Control",
    "wof:placetype":"venue"
},
  "geometry": {"coordinates":[-83.93012400000001,42.606186],"type":"Point"}
}