{
  "type": "Feature",
  "properties": {
    "iso:country":"US",
    "sg:address":"1635 Huntington Park",
    "sg:city":"Rochester Hills",
    "sg:classifiers":[
        {
            "category":"Organizations",
            "subcategory":"Religious Organization",
            "type":"Services"
        }
    ],
    "sg:phone":"+1 248 650 8785",
    "sg:postcode":"48309",
    "sg:province":"MI",
    "wof:name":"Oakland County Chaplain",
    "wof:placetype":"venue"
},
  "geometry": {"coordinates":[-83.164923,42.681336],"type":"Point"}
}