{
  "type": "Feature",
  "properties": {
    "iso:country":"US",
    "sg:address":"300 Haskins Ct SE",
    "sg:city":"Ada",
    "sg:classifiers":[
        {
            "category":"Professional",
            "subcategory":"Detective & Security Services",
            "type":"Services"
        }
    ],
    "sg:phone":"+1 616 957 9730",
    "sg:postcode":"49301",
    "sg:province":"MI",
    "sg:tags":[
        "car"
    ],
    "wof:name":"Asset Management & Investigati",
    "wof:placetype":"venue"
},
  "geometry": {"coordinates":[-85.53032399999999,42.956065],"type":"Point"}
}