{
  "type": "Feature",
  "properties": {
    "iso:country":"US",
    "sg:address":"510 E 40th St",
    "sg:city":"Holland",
    "sg:classifiers":[
        {
            "category":"Manufacturing",
            "subcategory":"Metals",
            "type":"Manufacturing & Wholesale Goods"
        }
    ],
    "sg:phone":"+1 616 355 2800",
    "sg:postcode":"49423",
    "sg:province":"MI",
    "sg:tags":[
        "fabricator",
        "sheet"
    ],
    "sg:website":"www.imcs-fab.com",
    "wof:name":"IMCS Fabricators Inc",
    "wof:placetype":"venue"
},
  "geometry": {"coordinates":[-86.085671,42.761945],"type":"Point"}
}