{
  "type": "Feature",
  "properties": {
    "iso:country":"US",
    "sg:address":"13627 Helen St",
    "sg:city":"Southgate",
    "sg:classifiers":[
        {
            "category":"Real Estate",
            "subcategory":"Developer",
            "type":"Services"
        }
    ],
    "sg:phone":"+1 734 283 3594",
    "sg:postcode":"48195",
    "sg:province":"MI",
    "wof:name":"Richmond Land Development",
    "wof:placetype":"venue"
},
  "geometry": {"coordinates":[-83.19878799999999,42.206422],"type":"Point"}
}