{
  "type": "Feature",
  "properties": {
    "iso:country":"US",
    "sg:address":"8516 Homestead Dr",
    "sg:city":"Zeeland",
    "sg:classifiers":[
        {
            "category":"Shopping",
            "subcategory":"Department Store",
            "type":"Retail Goods"
        }
    ],
    "sg:phone":"+1 616 748 1611",
    "sg:postcode":"49464",
    "sg:province":"MI",
    "sg:tags":[
        "shop"
    ],
    "wof:name":"Dollar General",
    "wof:placetype":"venue"
},
  "geometry": {"coordinates":[-85.99067100000001,42.809351],"type":"Point"}
}