{
  "type": "Feature",
  "properties": {
    "iso:country":"US",
    "sg:address":"2212 S 11th St",
    "sg:city":"Niles",
    "sg:classifiers":[
        {
            "category":"Building & Trades",
            "subcategory":"Construction",
            "type":"Services"
        }
    ],
    "sg:phone":"+1 269 683 3577",
    "sg:postcode":"49120",
    "sg:province":"MI",
    "sg:tags":[
        "home",
        "improvement"
    ],
    "wof:name":"Ham's Home Improvements",
    "wof:placetype":"venue"
},
  "geometry": {"coordinates":[-86.250496,41.785492],"type":"Point"}
}