{
  "type": "Feature",
  "properties": {
    "iso:country":"US",
    "sg:address":"5257 S Coldwater Rd",
    "sg:city":"Remus",
    "sg:classifiers":[
        {
            "category":"Social Services",
            "subcategory":"Adult Care",
            "type":"Services"
        }
    ],
    "sg:phone":"+1 989 561 5009",
    "sg:postcode":"49340",
    "sg:province":"MI",
    "sg:tags":[
        "home",
        "residential"
    ],
    "wof:name":"Margaret's Meadows",
    "wof:placetype":"venue"
},
  "geometry": {"coordinates":[-84.985857,43.563688],"type":"Point"}
}