{
  "type": "Feature",
  "properties": {
    "iso:country":"US",
    "sg:address":"1010 E Elm Ave",
    "sg:city":"Monroe",
    "sg:classifiers":[
        {
            "category":"Retail",
            "subcategory":"Car Wash",
            "type":"Services"
        }
    ],
    "sg:phone":"+1 734 241 5465",
    "sg:postcode":"48162",
    "sg:province":"MI",
    "sg:tags":[
        "polishing",
        "washing"
    ],
    "wof:name":"Massingo's Car Wash",
    "wof:placetype":"venue"
},
  "geometry": {"coordinates":[-83.384658,41.914605],"type":"Point"}
}