{
  "type": "Feature",
  "properties": {
    "iso:country":"US",
    "sg:address":"5322 15 Mile Rd",
    "sg:city":"Sterling Heights",
    "sg:classifiers":[
        {
            "category":"Professional",
            "subcategory":"Accounting & Tax Preparation",
            "type":"Services"
        }
    ],
    "sg:phone":"+1 586 978 7340",
    "sg:postcode":"48310",
    "sg:province":"MI",
    "sg:tags":[
        "accountant"
    ],
    "wof:name":"Kaszubksi & Al-Hassan & Associates",
    "wof:placetype":"venue"
},
  "geometry": {"coordinates":[-83.054497,42.550499],"type":"Point"}
}