{
  "type": "Feature",
  "properties": {
    "iso:country":"US",
    "sg:address":"306 Norfolk St",
    "sg:city":"Midland",
    "sg:classifiers":[
        {
            "category":"Building & Trades",
            "subcategory":"Construction",
            "type":"Services"
        }
    ],
    "sg:phone":"+1 989 837 1780",
    "sg:postcode":"48640",
    "sg:province":"MI",
    "sg:tags":[
        "contractor"
    ],
    "wof:name":"Trilogy Builders",
    "wof:placetype":"venue"
},
  "geometry": {"coordinates":[-84.22922800000001,43.638732],"type":"Point"}
}