{
  "type": "Feature",
  "properties": {
    "iso:country":"US",
    "sg:address":"1215 E Apple Ave",
    "sg:city":"Muskegon",
    "sg:classifiers":[
        {
            "category":"Organizations",
            "subcategory":"Religious Organization",
            "type":"Services"
        }
    ],
    "sg:phone":"+1 231 773 2667",
    "sg:postcode":"49442",
    "sg:province":"MI",
    "sg:tags":[
        "elementary",
        "school",
        "secondary"
    ],
    "wof:name":"Our Redeemer Lutheran Church",
    "wof:placetype":"venue"
},
  "geometry": {"coordinates":[-86.213151,43.234065],"type":"Point"}
}