{
  "type": "Feature",
  "properties": {
    "iso:country":"US",
    "sg:address":"6045 Johnson Rd",
    "sg:city":"Flushing",
    "sg:classifiers":[
        {
            "category":"Local Transit",
            "type":"Transportation"
        }
    ],
    "sg:phone":"+1 810 659 6714",
    "sg:postcode":"48433",
    "sg:province":"MI",
    "sg:tags":[
        "passenger"
    ],
    "wof:name":"Animal Ambulance",
    "wof:placetype":"venue"
},
  "geometry": {"coordinates":[-83.828473,43.090606],"type":"Point"}
}