{
  "type": "Feature",
  "properties": {
    "iso:country":"US",
    "sg:address":"12601 Grand River Rd",
    "sg:city":"Brighton",
    "sg:classifiers":[
        {
            "category":"Autos & Motor Vehicles",
            "subcategory":"Fuel & Gas Station",
            "type":"Retail Goods"
        }
    ],
    "sg:phone":"+1 810 225 0313",
    "sg:postcode":"48116",
    "sg:province":"MI",
    "sg:tags":[
        "oil"
    ],
    "wof:name":"Quality Testing Svc",
    "wof:placetype":"venue"
},
  "geometry": {"coordinates":[-83.706695,42.517047],"type":"Point"}
}