{
  "type": "Feature",
  "properties": {
    "iso:country":"US",
    "sg:address":"18458 Biltmore St",
    "sg:city":"Detroit",
    "sg:classifiers":[
        {
            "category":"Social Services",
            "subcategory":"Child Care",
            "type":"Services"
        }
    ],
    "sg:phone":"+1 313 835 8806",
    "sg:postcode":"48235",
    "sg:province":"MI",
    "sg:tags":[
        "day"
    ],
    "wof:name":"Twinz Child Development Center Llc",
    "wof:placetype":"venue"
},
  "geometry": {"coordinates":[-83.211207,42.425566],"type":"Point"}
}