{
  "type": "Feature",
  "properties": {
    "iso:country":"US",
    "sg:address":"4072 Middlebury Dr",
    "sg:city":"Troy",
    "sg:classifiers":[
        {
            "category":"Recreation",
            "type":"Entertainment"
        }
    ],
    "sg:phone":"+1 248 689 6692",
    "sg:postcode":"48085",
    "sg:province":"MI",
    "sg:tags":[
        "club",
        "membership"
    ],
    "wof:name":"Oak Lane Gun & Reel Club",
    "wof:placetype":"venue"
},
  "geometry": {"coordinates":[-83.10136799999999,42.580351],"type":"Point"}
}