{
  "type": "Feature",
  "properties": {
    "iso:country":"US",
    "sg:address":"120 Greenfield Blvd",
    "sg:city":"Marshall",
    "sg:classifiers":[
        {
            "category":"Professional",
            "subcategory":"Business Services",
            "type":"Services"
        }
    ],
    "sg:phone":"+1 269 789 0905",
    "sg:postcode":"49068",
    "sg:province":"MI",
    "wof:name":"Michelle Holmes",
    "wof:placetype":"venue"
},
  "geometry": {"coordinates":[-84.975774,42.271989],"type":"Point"}
}