{
  "type": "Feature",
  "properties": {
    "iso:country":"US",
    "sg:address":"725 Demille Rd",
    "sg:city":"Lapeer",
    "sg:classifiers":[
        {
            "category":"Real Estate",
            "subcategory":"Real Estate Operator",
            "type":"Services"
        }
    ],
    "sg:phone":"+1 810 667 3098",
    "sg:postcode":"48446",
    "sg:province":"MI",
    "sg:tags":[
        "mobile",
        "home",
        "community"
    ],
    "wof:name":"Hunters Creek Mobile Home",
    "wof:placetype":"venue"
},
  "geometry": {"coordinates":[-83.316643,43.042872],"type":"Point"}
}