{
  "type": "Feature",
  "properties": {
    "iso:country":"US",
    "sg:address":"5051 144th Ave",
    "sg:city":"Holland",
    "sg:classifiers":[
        {
            "category":"Building & Trades",
            "subcategory":"Plumbing",
            "type":"Services"
        }
    ],
    "sg:phone":"+1 269 751 8698",
    "sg:postcode":"49423",
    "sg:province":"MI",
    "sg:tags":[
        "contractor"
    ],
    "wof:name":"Lighthouse Plumbing",
    "wof:placetype":"venue"
},
  "geometry": {"coordinates":[-86.037192,42.740276],"type":"Point"}
}