{
  "type": "Feature",
  "properties": {
    "iso:country":"US",
    "sg:address":"32800 Stephenson Hwy",
    "sg:city":"Madison Heights",
    "sg:classifiers":[
        {
            "category":"Travel",
            "subcategory":"Hotels & Motels",
            "type":"Entertainment"
        }
    ],
    "sg:phone":"+1 248 588 3388",
    "sg:postcode":"48071",
    "sg:province":"MI",
    "wof:name":"Fairfield Inn by Marriott",
    "wof:placetype":"venue"
},
  "geometry": {"coordinates":[-83.11990400000001,42.5326],"type":"Point"}
}