{
  "type": "Feature",
  "properties": {
    "iso:country":"US",
    "sg:address":"44 Birwoode Dr",
    "sg:city":"Pontiac",
    "sg:classifiers":[
        {
            "category":"Real Estate",
            "subcategory":"Real Estate Operator",
            "type":"Services"
        }
    ],
    "sg:phone":"+1 248 373 0420",
    "sg:postcode":"48340",
    "sg:province":"MI",
    "sg:tags":[
        "apartment"
    ],
    "wof:name":"Auburn Heights Apartments",
    "wof:placetype":"venue"
},
  "geometry": {"coordinates":[-83.259421,42.677293],"type":"Point"}
}