{
  "type": "Feature",
  "properties": {
    "iso:country":"US",
    "sg:address":"8253 Lewis Ave",
    "sg:city":"Temperance",
    "sg:classifiers":[
        {
            "category":"Personal",
            "subcategory":"Barber",
            "type":"Services"
        }
    ],
    "sg:phone":"+1 734 847 8190",
    "sg:postcode":"48182",
    "sg:province":"MI",
    "sg:tags":[
        "shop"
    ],
    "wof:name":"Town & Country Barber Shop",
    "wof:placetype":"venue"
},
  "geometry": {"coordinates":[-83.56833,41.765837],"type":"Point"}
}