{
  "type": "Feature",
  "properties": {
    "iso:country":"US",
    "sg:address":"2112 20th Ave S",
    "sg:city":"Escanaba",
    "sg:classifiers":[
        {
            "category":"Retail",
            "subcategory":"Repair Shop",
            "type":"Services"
        }
    ],
    "sg:phone":"+1 906 786 4447",
    "sg:postcode":"49829",
    "sg:province":"MI",
    "wof:name":"Krans Piano Service",
    "wof:placetype":"venue"
},
  "geometry": {"coordinates":[-87.07567,45.722541],"type":"Point"}
}