{
  "type": "Feature",
  "properties": {
    "iso:country":"US",
    "sg:address":"7391 Hogan Rd",
    "sg:city":"Fenton",
    "sg:classifiers":[
        {
            "category":"Building & Trades",
            "subcategory":"Landscaping Services",
            "type":"Services"
        }
    ],
    "sg:phone":"+1 810 735 7972",
    "sg:postcode":"48430",
    "sg:province":"MI",
    "wof:name":"Shepps Tree Service",
    "wof:placetype":"venue"
},
  "geometry": {"coordinates":[-83.819035,42.749686],"type":"Point"}
}