{
  "type": "Feature",
  "properties": {
    "iso:country":"US",
    "sg:address":"11525 E 10 Mile Rd",
    "sg:city":"Warren",
    "sg:classifiers":[
        {
            "category":"Health Services",
            "subcategory":"Nursing And Care Facility",
            "type":"Services"
        }
    ],
    "sg:phone":"+1 586 759 0700",
    "sg:postcode":"48089",
    "sg:province":"MI",
    "sg:tags":[
        "home",
        "convalescent"
    ],
    "wof:name":"Nightingale Health Care",
    "wof:placetype":"venue"
},
  "geometry": {"coordinates":[-83.008219,42.477894],"type":"Point"}
}