{
  "type": "Feature",
  "properties": {
    "iso:country":"US",
    "sg:address":"8726 Portage Rd",
    "sg:city":"Portage",
    "sg:classifiers":[
        {
            "category":"Manufacturing",
            "subcategory":"Glass & Minerals",
            "type":"Manufacturing & Wholesale Goods"
        },
        {
            "category":"Retail",
            "subcategory":"Auto Repair",
            "type":"Services"
        }
    ],
    "sg:phone":"+1 800 800 2727",
    "sg:postcode":"49002",
    "sg:province":"MI",
    "sg:tags":[
        "plate",
        "window",
        "windshield",
        "glass-auto"
    ],
    "wof:name":"Safelite Autoglass",
    "wof:placetype":"venue"
},
  "geometry": {"coordinates":[-85.56209,42.190258],"type":"Point"}
}