{
  "type": "Feature",
  "properties": {
    "iso:country":"US",
    "sg:address":"1667 Hamilton Rd",
    "sg:city":"Okemos",
    "sg:classifiers":[
        {
            "category":"Social Services",
            "type":"Services"
        }
    ],
    "sg:phone":"+1 517 332 7124",
    "sg:postcode":"48864",
    "sg:province":"MI",
    "wof:name":"Walkington Barbara Acsw Csw",
    "wof:placetype":"venue"
},
  "geometry": {"coordinates":[-84.40866800000001,42.717026],"type":"Point"}
}