{
  "type": "Feature",
  "properties": {
    "iso:country":"US",
    "sg:address":"2901 Sunshine Ter",
    "sg:city":"Waterford",
    "sg:classifiers":[
        {
            "category":"Education",
            "subcategory":"School",
            "type":"Public Place"
        }
    ],
    "sg:phone":"+1 248 666 2879",
    "sg:postcode":"48329",
    "sg:province":"MI",
    "wof:name":"Alfa Preschool",
    "wof:placetype":"venue"
},
  "geometry": {"coordinates":[-83.42609299999999,42.681241],"type":"Point"}
}