{
  "type": "Feature",
  "properties": {
    "iso:country":"US",
    "sg:address":"2445 W Neuman Rd",
    "sg:city":"Pinconning",
    "sg:classifiers":[
        {
            "category":"Social Services",
            "subcategory":"Adult Care",
            "type":"Services"
        }
    ],
    "sg:phone":"+1 989 879 7404",
    "sg:postcode":"48650",
    "sg:province":"MI",
    "sg:tags":[
        "broker"
    ],
    "wof:name":"Sunshine Reality",
    "wof:placetype":"venue"
},
  "geometry": {"coordinates":[-84.13872499999999,43.840306],"type":"Point"}
}