{
  "type": "Feature",
  "properties": {
    "iso:country":"US",
    "sg:address":"21315 Hilltop St",
    "sg:city":"Southfield",
    "sg:classifiers":[
        {
            "category":"Wholesale",
            "subcategory":"Machinery & Supplies",
            "type":"Manufacturing & Wholesale Goods"
        }
    ],
    "sg:phone":"+1 616 897 9810",
    "sg:postcode":"48033",
    "sg:province":"MI",
    "sg:tags":[
        "operated",
        "laundry"
    ],
    "wof:name":"Curtis Equipment Co",
    "wof:placetype":"venue"
},
  "geometry": {"coordinates":[-83.286564,42.447561],"type":"Point"}
}