{
  "type": "Feature",
  "properties": {
    "iso:country":"US",
    "sg:address":"4284 E Court St",
    "sg:city":"Burton",
    "sg:classifiers":[
        {
            "category":"Real Estate",
            "subcategory":"Real Estate Agent",
            "type":"Services"
        }
    ],
    "sg:phone":"+1 810 743 7681",
    "sg:postcode":"48509",
    "sg:province":"MI",
    "sg:tags":[
        "appraiser"
    ],
    "wof:name":"Paris & Assoc Appraisers",
    "wof:placetype":"venue"
},
  "geometry": {"coordinates":[-83.624605,43.018621],"type":"Point"}
}