{
  "type": "Feature",
  "properties": {
    "iso:country":"US",
    "sg:address":"1003 N Leroy St",
    "sg:city":"Fenton",
    "sg:classifiers":[
        {
            "category":"Restaurant",
            "type":"Food & Drink"
        }
    ],
    "sg:phone":"+1 810 629 3100",
    "sg:postcode":"48430",
    "sg:province":"MI",
    "sg:tags":[
        "pizza"
    ],
    "sg:website":"http://www.hungryhowies.com",
    "wof:name":"Hungry Howie's Pizza",
    "wof:placetype":"venue"
},
  "geometry": {"coordinates":[-83.70732099999999,42.807586],"type":"Point"}
}