{
  "type": "Feature",
  "properties": {
    "iso:country":"US",
    "sg:address":"34900 W Michigan Ave",
    "sg:city":"Wayne",
    "sg:classifiers":[
        {
            "category":"Shopping",
            "subcategory":"Jewelry",
            "type":"Retail Goods"
        }
    ],
    "sg:phone":"+1 734 721 4311",
    "sg:postcode":"48184",
    "sg:province":"MI",
    "sg:tags":[
        "watch"
    ],
    "sg:website":"www.leosjeweler.com",
    "wof:name":"Leo's Jewelry & Gifts Inc",
    "wof:placetype":"venue"
},
  "geometry": {"coordinates":[-83.383003,42.282299],"type":"Point"}
}