{
  "type": "Feature",
  "properties": {
    "iso:country":"US",
    "sg:address":"8503 Sparta Ave NW",
    "sg:city":"Sparta",
    "sg:classifiers":[
        {
            "category":"Autos & Motor Vehicles",
            "subcategory":"Boat Sales",
            "type":"Retail Goods"
        }
    ],
    "sg:phone":"+1 616 887 1119",
    "sg:postcode":"49345",
    "sg:province":"MI",
    "sg:tags":[
        "dealer",
        "sales"
    ],
    "wof:name":"Roark's Garden Ctr",
    "wof:placetype":"venue"
},
  "geometry": {"coordinates":[-85.710137,43.118876],"type":"Point"}
}