{
  "type": "Feature",
  "properties": {
    "iso:country":"US",
    "sg:address":"1822 Arrowhead Trl",
    "sg:city":"Oxford",
    "sg:classifiers":[
        {
            "category":"Insurance",
            "subcategory":"Health Insurance",
            "type":"Services"
        }
    ],
    "sg:phone":"+1 248 212 9200",
    "sg:postcode":"48371",
    "sg:province":"MI",
    "sg:tags":[
        "carrier"
    ],
    "wof:name":"Moore Financial",
    "wof:placetype":"venue"
},
  "geometry": {"coordinates":[-83.270912,42.798137],"type":"Point"}
}