{
  "type": "Feature",
  "properties": {
    "iso:country":"US",
    "sg:address":"11445 Van Dyke St",
    "sg:city":"Detroit",
    "sg:classifiers":[
        {
            "category":"Retail",
            "subcategory":"Auto Repair",
            "type":"Services"
        }
    ],
    "sg:phone":"+1 313 571 5135",
    "sg:postcode":"48234",
    "sg:province":"MI",
    "sg:tags":[
        "body",
        "shop"
    ],
    "wof:name":"Knocker's Collision",
    "wof:placetype":"venue"
},
  "geometry": {"coordinates":[-83.023399,42.407101],"type":"Point"}
}