{
  "type": "Feature",
  "properties": {
    "iso:country":"US",
    "sg:address":"30300 Northwestern Hwy",
    "sg:city":"Farmington Hills",
    "sg:classifiers":[
        {
            "category":"Professional",
            "subcategory":"Lawyer & Legal Services",
            "type":"Services"
        }
    ],
    "sg:phone":"+1 248 808 0011",
    "sg:postcode":"48334",
    "sg:province":"MI",
    "wof:name":"Rose Law Ofc",
    "wof:placetype":"venue"
},
  "geometry": {"coordinates":[-83.322958,42.509103],"type":"Point"}
}