{
  "type": "Feature",
  "properties": {
    "iso:country":"US",
    "sg:address":"1419 John R Rd",
    "sg:city":"Troy",
    "sg:classifiers":[
        {
            "category":"Manufacturing",
            "subcategory":"Metals",
            "type":"Manufacturing & Wholesale Goods"
        }
    ],
    "sg:phone":"+1 248 585 3220",
    "sg:postcode":"48083",
    "sg:province":"MI",
    "sg:tags":[
        "fitting",
        "fluid",
        "power"
    ],
    "sg:website":"www.med-kas.com",
    "wof:name":"Med-Kas Hydraulic Inc",
    "wof:placetype":"venue"
},
  "geometry": {"coordinates":[-83.107601,42.546172],"type":"Point"}
}