{
  "type": "Feature",
  "properties": {
    "iso:country":"US",
    "sg:address":"24800 Hayes St",
    "sg:city":"Taylor",
    "sg:classifiers":[
        {
            "category":"Education",
            "subcategory":"School",
            "type":"Public Place"
        }
    ],
    "sg:phone":"+1 313 295 5816",
    "sg:postcode":"48180",
    "sg:province":"MI",
    "wof:name":"Margaret E Wareing Elem School",
    "wof:placetype":"venue"
},
  "geometry": {"coordinates":[-83.28120800000001,42.250232],"type":"Point"}
}