{
  "type": "Feature",
  "properties": {
    "iso:country":"US",
    "sg:address":"204 University St",
    "sg:city":"Ferndale",
    "sg:classifiers":[
        {
            "category":"Social Services",
            "subcategory":"Child Care",
            "type":"Services"
        }
    ],
    "sg:phone":"+1 248 546 7379",
    "sg:postcode":"48220",
    "sg:province":"MI",
    "sg:tags":[
        "homes-children"
    ],
    "wof:name":"Designer Cmpt Art & Graphics",
    "wof:placetype":"venue"
},
  "geometry": {"coordinates":[-83.13058700000001,42.456089],"type":"Point"}
}