{
  "type": "Feature",
  "properties": {
    "iso:country":"US",
    "sg:address":"5426 S 64th Ave",
    "sg:city":"New Era",
    "sg:classifiers":[
        {
            "category":"Social Services",
            "subcategory":"Child Care",
            "type":"Services"
        }
    ],
    "sg:phone":"+1 231 861 4695",
    "sg:postcode":"49446",
    "sg:province":"MI",
    "sg:tags":[
        "day"
    ],
    "wof:name":"Orchard View Farm",
    "wof:placetype":"venue"
},
  "geometry": {"coordinates":[-86.39765,43.555386],"type":"Point"}
}