{
  "type": "Feature",
  "properties": {
    "iso:country":"US",
    "sg:address":"5333 Centerline Rd",
    "sg:city":"Newaygo",
    "sg:classifiers":[
        {
            "category":"Travel",
            "subcategory":"Campground",
            "type":"Entertainment"
        }
    ],
    "sg:phone":"+1 231 652 1184",
    "sg:postcode":"49337",
    "sg:province":"MI",
    "sg:tags":[
        "camp"
    ],
    "wof:name":"NCCS Camp Newaygo",
    "wof:placetype":"venue"
},
  "geometry": {"coordinates":[-85.797943,43.458101],"type":"Point"}
}