{
  "type": "Feature",
  "properties": {
    "iso:country":"US",
    "sg:address":"634 E York Ave",
    "sg:city":"Flint",
    "sg:classifiers":[
        {
            "category":"Professional",
            "type":"Services"
        }
    ],
    "sg:phone":"+1 810 787 4511",
    "sg:postcode":"48505",
    "sg:province":"MI",
    "sg:tags":[
        "caterer"
    ],
    "wof:name":"James Lewis' Bar-B-Que & Catering",
    "wof:placetype":"venue"
},
  "geometry": {"coordinates":[-83.695667,43.073681],"type":"Point"}
}