{
  "type": "Feature",
  "properties": {
    "iso:country":"US",
    "sg:address":"47887 Michigan Ave",
    "sg:city":"Canton",
    "sg:classifiers":[
        {
            "category":"Retail",
            "subcategory":"Storage",
            "type":"Services"
        }
    ],
    "sg:phone":"+1 734 217 4033",
    "sg:postcode":"48188",
    "sg:province":"MI",
    "sg:tags":[
        "self"
    ],
    "sg:website":"www.devonselfstorage.com",
    "wof:name":"Devon Self Storage",
    "wof:placetype":"venue"
},
  "geometry": {"coordinates":[-83.509923,42.265469],"type":"Point"}
}