{
  "type": "Feature",
  "properties": {
    "iso:country":"US",
    "sg:address":"2561 Sandalwood Cir",
    "sg:city":"Ann Arbor",
    "sg:classifiers":[
        {
            "category":"Professional",
            "subcategory":"Computer Services",
            "type":"Services"
        }
    ],
    "sg:phone":"+1 734 662 2481",
    "sg:postcode":"48105",
    "sg:province":"MI",
    "sg:tags":[
        "datum"
    ],
    "wof:name":"Ramsey & Assoc Data Entry",
    "wof:placetype":"venue"
},
  "geometry": {"coordinates":[-83.70783400000001,42.307936],"type":"Point"}
}