{
  "type": "Feature",
  "properties": {
    "iso:country":"US",
    "sg:address":"30880 Park St",
    "sg:city":"Roseville",
    "sg:classifiers":[
        {
            "category":"Real Estate",
            "subcategory":"Real Estate Agent",
            "type":"Services"
        }
    ],
    "sg:phone":"+1 586 778 8300",
    "sg:postcode":"48066",
    "sg:province":"MI",
    "wof:name":"Midwest Realty",
    "wof:placetype":"venue"
},
  "geometry": {"coordinates":[-82.931335,42.522961],"type":"Point"}
}