{
  "type": "Feature",
  "properties": {
    "iso:country":"US",
    "sg:address":"34164 Plymouth Rd",
    "sg:city":"Livonia",
    "sg:classifiers":[
        {
            "category":"Juice Bar",
            "subcategory":"None",
            "type":"Food & Drink"
        },
        {
            "category":"Insurance",
            "subcategory":"Health Insurance",
            "type":"Services"
        },
        {
            "category":"Food & Beverages",
            "subcategory":"Groceries & Convenience Stores",
            "type":"Retail Goods"
        }
    ],
    "sg:phone":"+1 734 427 3144",
    "sg:postcode":"48150",
    "sg:province":"MI",
    "sg:tags":[
        "smoothy",
        "market"
    ],
    "sg:website":"www.zerbos.com",
    "wof:name":"Zerbo's Health Foods Supermarket",
    "wof:placetype":"venue"
},
  "geometry": {"coordinates":[-83.381897,42.368301],"type":"Point"}
}