{
  "type": "Feature",
  "properties": {
    "iso:country":"US",
    "sg:address":"100 Cedar Ln",
    "sg:city":"Negaunee",
    "sg:classifiers":[
        {
            "category":"Shopping",
            "subcategory":"Optical Goods",
            "type":"Retail Goods"
        }
    ],
    "sg:phone":"+1 906 475 5022",
    "sg:postcode":"49866",
    "sg:province":"MI",
    "wof:name":"U P Eye Specialists Optical",
    "wof:placetype":"venue"
},
  "geometry": {"coordinates":[-87.57311199999999,46.538111],"type":"Point"}
}