{
  "type": "Feature",
  "properties": {
    "iso:country":"US",
    "sg:address":"568 S Main St",
    "sg:city":"Frankenmuth",
    "sg:classifiers":[
        {
            "category":"Shopping",
            "type":"Retail Goods"
        }
    ],
    "sg:phone":"+1 989 652 6878",
    "sg:postcode":"48734",
    "sg:province":"MI",
    "sg:tags":[
        "art",
        "gallery",
        "dealer"
    ],
    "sg:website":"www.frankenmuthgallery.com",
    "wof:name":"Frankenmuth Gallery",
    "wof:placetype":"venue"
},
  "geometry": {"coordinates":[-83.739186,43.328993],"type":"Point"}
}