{
  "type": "Feature",
  "properties": {
    "iso:country":"US",
    "sg:address":"5181 Milroy Ln",
    "sg:city":"Brighton",
    "sg:classifiers":[
        {
            "category":"Professional",
            "subcategory":"Management & Consulting",
            "type":"Services"
        }
    ],
    "sg:phone":"+1 810 229 9905",
    "sg:postcode":"48116",
    "sg:province":"MI",
    "sg:tags":[
        "logistics"
    ],
    "wof:name":"Trans-Man Logistics",
    "wof:placetype":"venue"
},
  "geometry": {"coordinates":[-83.844465,42.525186],"type":"Point"}
}