{
  "type": "Feature",
  "properties": {
    "iso:country":"US",
    "sg:address":"3436 Franette Rd",
    "sg:city":"Lansing",
    "sg:classifiers":[
        {
            "category":"Utilities",
            "subcategory":"Water",
            "type":"Services"
        },
        {
            "category":"Building & Trades",
            "subcategory":"Cleaning & Sanitation",
            "type":"Services"
        },
        {
            "category":"Retail",
            "subcategory":"Laundry & Dry Cleaning",
            "type":"Services"
        },
        {
            "category":"Building & Trades",
            "subcategory":"Construction",
            "type":"Services"
        }
    ],
    "sg:phone":"+1 517 886 5367",
    "sg:postcode":"48906",
    "sg:province":"MI",
    "sg:tags":[
        "cleaner",
        "tile-cleaning",
        "emergency",
        "fire",
        "damage",
        "rug",
        "restoration",
        "refinishing",
        "sealing",
        "carpet"
    ],
    "sg:website":"http://www.lenscarpetcare.com",
    "wof:name":"Len's Carpet Care & Consultants",
    "wof:placetype":"venue"
},
  "geometry": {"coordinates":[-84.602782,42.769411],"type":"Point"}
}