{
  "type": "Feature",
  "properties": {
    "iso:country":"US",
    "sg:address":"66787 Gratiot Ave",
    "sg:city":"Richmond",
    "sg:classifiers":[
        {
            "category":"Health Services",
            "subcategory":"Doctor",
            "type":"Services"
        }
    ],
    "sg:phone":"+1 586 727 3488",
    "sg:postcode":"48062",
    "sg:province":"MI",
    "sg:tags":[
        "medical"
    ],
    "wof:name":"Owczarzak Michael MD",
    "wof:placetype":"venue"
},
  "geometry": {"coordinates":[-82.738421,42.79226],"type":"Point"}
}