{
  "type": "Feature",
  "properties": {
    "iso:country":"US",
    "sg:address":"13710 Fulton Rd",
    "sg:city":"Yale",
    "sg:phone":"+1 810 387 2965",
    "sg:postcode":"48097",
    "sg:province":"MI",
    "sg:tags":[
        "farm",
        "corn"
    ],
    "wof:name":"Gary Rapley",
    "wof:placetype":"venue"
},
  "geometry": {"coordinates":[-82.874758,43.105686],"type":"Point"}
}