{
  "type": "Feature",
  "properties": {
    "iso:country":"US",
    "sg:address":"10475 Junet Rd",
    "sg:city":"Ironwood",
    "sg:classifiers":[
        {
            "category":"Home & Garden",
            "subcategory":"Hardware",
            "type":"Retail Goods"
        }
    ],
    "sg:phone":"+1 906 932 0046",
    "sg:postcode":"49938",
    "sg:province":"MI",
    "sg:tags":[
        "tool",
        "used"
    ],
    "sg:website":"www.extremetool.com",
    "wof:name":"Extreme Tool & Engineering",
    "wof:placetype":"venue"
},
  "geometry": {"coordinates":[-90.192644,46.48127],"type":"Point"}
}