{
  "type": "Feature",
  "properties": {
    "iso:country":"US",
    "sg:address":"4471 Sheffield Pl",
    "sg:city":"Bay City",
    "sg:classifiers":[
        {
            "category":"Real Estate",
            "subcategory":"Real Estate Operator",
            "type":"Services"
        }
    ],
    "sg:phone":"+1 989 684 6800",
    "sg:postcode":"48706",
    "sg:province":"MI",
    "sg:tags":[
        "building",
        "intermediate",
        "apartment",
        "care",
        "facility"
    ],
    "wof:name":"Sheffield Bay",
    "wof:placetype":"venue"
},
  "geometry": {"coordinates":[-83.917666,43.610583],"type":"Point"}
}