{
  "type": "Feature",
  "properties": {
    "iso:country":"US",
    "sg:address":"256 S Waverly Rd",
    "sg:city":"Holland",
    "sg:classifiers":[
        {
            "category":"Building & Trades",
            "subcategory":"Cleaning & Sanitation",
            "type":"Services"
        },
        {
            "category":"Retail",
            "subcategory":"Laundry & Dry Cleaning",
            "type":"Services"
        }
    ],
    "sg:phone":"+1 616 394 9178",
    "sg:postcode":"49423",
    "sg:province":"MI",
    "sg:tags":[
        "cleaners",
        "rug",
        "maintenance",
        "carpet"
    ],
    "wof:name":"Three Royal Treatment",
    "wof:placetype":"venue"
},
  "geometry": {"coordinates":[-86.077709,42.78804],"type":"Point"}
}