{
  "type": "Feature",
  "properties": {
    "iso:country":"US",
    "sg:address":"56762 Copperfield Dr",
    "sg:city":"Shelby Twp",
    "sg:classifiers":[
        {
            "category":"Social Services",
            "subcategory":"Adult Care",
            "type":"Services"
        }
    ],
    "sg:phone":"+1 586 786 0978",
    "sg:postcode":"48316",
    "sg:province":"MI",
    "sg:tags":[
        "home",
        "group"
    ],
    "wof:name":"Tikvah Corp",
    "wof:placetype":"venue"
},
  "geometry": {"coordinates":[-83.083296,42.710792],"type":"Point"}
}