{
  "type": "Feature",
  "properties": {
    "iso:country":"US",
    "sg:address":"910 N 3rd St",
    "sg:city":"Marquette",
    "sg:classifiers":[
        {
            "category":"Professional",
            "subcategory":"Management & Consulting",
            "type":"Services"
        }
    ],
    "sg:phone":"+1 906 226 7309",
    "sg:postcode":"49855",
    "sg:province":"MI",
    "wof:name":"Diane L Tonella",
    "wof:placetype":"venue"
},
  "geometry": {"coordinates":[-87.39466,46.552097],"type":"Point"}
}