{
  "type": "Feature",
  "properties": {
    "iso:country":"US",
    "sg:address":"203 Athlone Beach Rd",
    "sg:city":"Bay City",
    "sg:classifiers":[
        {
            "category":"Organizations",
            "subcategory":"Membership Organization",
            "type":"Services"
        }
    ],
    "sg:phone":"+1 989 684 6982",
    "sg:postcode":"48706",
    "sg:province":"MI",
    "wof:name":"Experimental Aircraft Assn",
    "wof:placetype":"venue"
},
  "geometry": {"coordinates":[-83.92214199999999,43.68951],"type":"Point"}
}