{
  "type": "Feature",
  "properties": {
    "iso:country":"US",
    "sg:address":"42950 Dequindre Rd",
    "sg:city":"Sterling Heights",
    "sg:classifiers":[
        {
            "category":"Shopping",
            "subcategory":"Party Supplies",
            "type":"Retail Goods"
        },
        {
            "category":"Personal",
            "type":"Services"
        },
        {
            "category":"Food & Beverages",
            "subcategory":"Groceries & Convenience Stores",
            "type":"Retail Goods"
        }
    ],
    "sg:phone":"+1 586 254 0417",
    "sg:postcode":"48314",
    "sg:province":"MI",
    "sg:tags":[
        "planning",
        "event"
    ],
    "sg:website":"www.7-eleven.com",
    "wof:name":"7-Eleven",
    "wof:placetype":"venue"
},
  "geometry": {"coordinates":[-83.090414,42.607226],"type":"Point"}
}