{
  "type": "Feature",
  "properties": {
    "iso:country":"US",
    "sg:address":"3310 Ramada Dr",
    "sg:city":"Highland",
    "sg:classifiers":[
        {
            "category":"Manufacturing",
            "subcategory":"Toys & Sporting Goods",
            "type":"Manufacturing & Wholesale Goods"
        }
    ],
    "sg:phone":"+1 248 887 6567",
    "sg:postcode":"48356",
    "sg:province":"MI",
    "sg:tags":[
        "mfg"
    ],
    "wof:name":"Clamp Engineering Inc",
    "wof:placetype":"venue"
},
  "geometry": {"coordinates":[-83.594407,42.66873],"type":"Point"}
}