{
  "type": "Feature",
  "properties": {
    "iso:country":"US",
    "sg:address":"25625 Southfield Rd",
    "sg:city":"Southfield",
    "sg:classifiers":[
        {
            "category":"Building & Trades",
            "subcategory":"Construction",
            "type":"Services"
        }
    ],
    "sg:phone":"+1 248 559 1044",
    "sg:postcode":"48075",
    "sg:province":"MI",
    "sg:tags":[
        "painter"
    ],
    "wof:name":"Reiter Sam Decrtr",
    "wof:placetype":"venue"
},
  "geometry": {"coordinates":[-83.221397,42.4781],"type":"Point"}
}