{
  "type": "Feature",
  "properties": {
    "iso:country":"US",
    "sg:address":"6163 Dixie Hwy",
    "sg:city":"Bridgeport",
    "sg:classifiers":[
        {
            "category":"Real Estate",
            "subcategory":"Real Estate Agent",
            "type":"Services"
        }
    ],
    "sg:phone":"+1 989 777 3590",
    "sg:postcode":"48722",
    "sg:province":"MI",
    "sg:website":"www.normanglightinc.com",
    "wof:name":"Norman G Light Inc Realtors",
    "wof:placetype":"venue"
},
  "geometry": {"coordinates":[-83.880658,43.358487],"type":"Point"}
}