{
  "type": "Feature",
  "properties": {
    "iso:country":"US",
    "sg:address":"99 Crescent Ave",
    "sg:city":"Lake Orion",
    "sg:classifiers":[
        {
            "category":"Building & Trades",
            "subcategory":"Construction",
            "type":"Services"
        }
    ],
    "sg:phone":"+1 248 391 2082",
    "sg:postcode":"48362",
    "sg:province":"MI",
    "sg:tags":[
        "home",
        "improvement"
    ],
    "wof:name":"Bellevue Home Improvement",
    "wof:placetype":"venue"
},
  "geometry": {"coordinates":[-83.25279500000001,42.78319],"type":"Point"}
}