{
  "type": "Feature",
  "properties": {
    "iso:country":"US",
    "sg:address":"2317 E Lansing Dr",
    "sg:city":"East Lansing",
    "sg:classifiers":[
        {
            "category":"Banks & Credit Unions",
            "subcategory":"Financial Services",
            "type":"Services"
        }
    ],
    "sg:phone":"+1 517 351 9290",
    "sg:postcode":"48823",
    "sg:province":"MI",
    "sg:tags":[
        "investment"
    ],
    "wof:name":"Jwh Enterprises LLC",
    "wof:placetype":"venue"
},
  "geometry": {"coordinates":[-84.451306,42.7496],"type":"Point"}
}