{
  "type": "Feature",
  "properties": {
    "iso:country":"US",
    "sg:address":"1115 S Saginaw Rd",
    "sg:city":"Midland",
    "sg:classifiers":[
        {
            "category":"Retail",
            "subcategory":"Auto Repair",
            "type":"Services"
        }
    ],
    "sg:phone":"+1 989 832 8785",
    "sg:postcode":"48640",
    "sg:province":"MI",
    "sg:tags":[
        "automobile",
        "lubrication"
    ],
    "sg:website":"http://www.valvoline.com",
    "wof:name":"Valvoline Instant Oil Change",
    "wof:placetype":"venue"
},
  "geometry": {"coordinates":[-84.218232,43.618412],"type":"Point"}
}