{
  "type": "Feature",
  "properties": {
    "iso:country":"US",
    "sg:address":"12210 Big Lake Rd",
    "sg:city":"Davisburg",
    "sg:classifiers":[
        {
            "category":"Farming",
            "subcategory":"Farm",
            "type":"Manufacturing & Wholesale Goods"
        }
    ],
    "sg:phone":"+1 248 625 7418",
    "sg:postcode":"48350",
    "sg:province":"MI",
    "wof:name":"Big Lake Farm",
    "wof:placetype":"venue"
},
  "geometry": {"coordinates":[-83.538871,42.721754],"type":"Point"}
}