{
  "type": "Feature",
  "properties": {
    "iso:country":"US",
    "sg:address":"1831 Jefferson Ave SE",
    "sg:city":"Grand Rapids",
    "sg:classifiers":[
        {
            "category":"Social Services",
            "subcategory":"Child Care",
            "type":"Services"
        }
    ],
    "sg:phone":"+1 616 243 9610",
    "sg:postcode":"49507",
    "sg:province":"MI",
    "sg:tags":[
        "day"
    ],
    "wof:name":"Sharon Haner",
    "wof:placetype":"venue"
},
  "geometry": {"coordinates":[-85.662865,42.927448],"type":"Point"}
}