{
  "type": "Feature",
  "properties": {
    "iso:country":"US",
    "sg:address":"364 Highview Rd",
    "sg:city":"Traverse City",
    "sg:classifiers":[
        {
            "category":"Building & Trades",
            "subcategory":"Cleaning & Sanitation",
            "type":"Services"
        }
    ],
    "sg:phone":"+1 231 933 9577",
    "sg:postcode":"49686",
    "sg:province":"MI",
    "sg:tags":[
        "maintenance"
    ],
    "wof:name":"Maloneys Janitorial Svc",
    "wof:placetype":"venue"
},
  "geometry": {"coordinates":[-85.51876799999999,44.690917],"type":"Point"}
}