{
  "type": "Feature",
  "properties": {
    "iso:country":"US",
    "sg:address":"31100 Telegraph Rd",
    "sg:city":"Bingham Farms",
    "sg:classifiers":[
        {
            "category":"Wholesale",
            "subcategory":"Durable Goods & Equipment",
            "type":"Manufacturing & Wholesale Goods"
        }
    ],
    "sg:phone":"+1 248 433 2090",
    "sg:postcode":"48025",
    "sg:province":"MI",
    "sg:tags":[
        "representative",
        "manufacturer"
    ],
    "sg:website":"www.timken.com",
    "wof:name":"Timken Co",
    "wof:placetype":"venue"
},
  "geometry": {"coordinates":[-83.285527,42.516727],"type":"Point"}
}