{
  "type": "Feature",
  "properties": {
    "iso:country":"US",
    "sg:address":"4700 Rochester Road",
    "sg:city":"Troy",
    "sg:classifiers":[
        {
            "category":"Real Estate",
            "subcategory":"Real Estate Services",
            "type":"Services"
        }
    ],
    "sg:phone":"+1 248 879 3400",
    "sg:postcode":"48085",
    "sg:province":"MI",
    "sg:website":"www.cbweirmanuel.com",
    "wof:name":"Coldwell Banker Weir Manuel",
    "wof:placetype":"venue"
},
  "geometry": {"coordinates":[-83.128845,42.587544],"type":"Point"}
}