{
  "type": "Feature",
  "properties": {
    "iso:country":"US",
    "sg:address":"3549 S Lapeer Rd",
    "sg:city":"Metamora",
    "sg:classifiers":[
        {
            "category":"Restaurant",
            "type":"Food & Drink"
        }
    ],
    "sg:phone":"+1 810 678 8350",
    "sg:postcode":"48455",
    "sg:province":"MI",
    "sg:tags":[
        "banquet",
        "rooms"
    ],
    "wof:name":"Timber Ridge Woods",
    "wof:placetype":"venue"
},
  "geometry": {"coordinates":[-83.31367899999999,42.952058],"type":"Point"}
}