{
  "type": "Feature",
  "properties": {
    "iso:country":"US",
    "sg:address":"1220 Butler Blvd",
    "sg:city":"Howell",
    "sg:classifiers":[
        {
            "category":"Wholesale",
            "subcategory":"Construction Materials",
            "type":"Manufacturing & Wholesale Goods"
        }
    ],
    "sg:phone":"+1 517 548 1883",
    "sg:postcode":"48843",
    "sg:province":"MI",
    "sg:tags":[
        "building"
    ],
    "wof:name":"METT",
    "wof:placetype":"venue"
},
  "geometry": {"coordinates":[-83.914177,42.621082],"type":"Point"}
}