{
  "type": "Feature",
  "properties": {
    "iso:country":"US",
    "sg:address":"616 E Savidge St",
    "sg:city":"Spring Lake",
    "sg:classifiers":[
        {
            "category":"Shopping",
            "subcategory":"Optical Goods",
            "type":"Retail Goods"
        },
        {
            "category":"Health Services",
            "subcategory":"Optometrist",
            "type":"Services"
        }
    ],
    "sg:phone":"+1 616 846 5220",
    "sg:postcode":"49456",
    "sg:province":"MI",
    "sg:website":"www.eyevision.org",
    "wof:name":"Eye Vision",
    "wof:placetype":"venue"
},
  "geometry": {"coordinates":[-86.184313,43.076598],"type":"Point"}
}