{
  "type": "Feature",
  "properties": {
    "iso:country":"US",
    "sg:address":"6048 Tamarack Dr",
    "sg:city":"Kingston",
    "sg:classifiers":[
        {
            "category":"Building & Trades",
            "subcategory":"Construction",
            "type":"Services"
        }
    ],
    "sg:phone":"+1 989 683 2138",
    "sg:postcode":"48741",
    "sg:province":"MI",
    "sg:tags":[
        "contractor"
    ],
    "wof:name":"Dns Custom Tile",
    "wof:placetype":"venue"
},
  "geometry": {"coordinates":[-83.18362399999999,43.384516],"type":"Point"}
}