{
  "type": "Feature",
  "properties": {
    "iso:country":"US",
    "sg:address":"227 2nd St",
    "sg:city":"Spring Lake",
    "sg:classifiers":[
        {
            "category":"Manufacturing",
            "subcategory":"Pottery",
            "type":"Manufacturing & Wholesale Goods"
        }
    ],
    "sg:phone":"+1 616 846 3660",
    "sg:postcode":"49456",
    "sg:province":"MI",
    "sg:tags":[
        "product"
    ],
    "wof:name":"Northern Clay",
    "wof:placetype":"venue"
},
  "geometry": {"coordinates":[-86.22012100000001,43.079854],"type":"Point"}
}