{
  "type": "Feature",
  "properties": {
    "iso:country":"US",
    "sg:address":"150 Landrow Dr",
    "sg:city":"Wixom",
    "sg:classifiers":[
        {
            "category":"Manufacturing",
            "subcategory":"Glass & Minerals",
            "type":"Manufacturing & Wholesale Goods"
        }
    ],
    "sg:phone":"+1 248 669 9886",
    "sg:postcode":"48393",
    "sg:province":"MI",
    "sg:tags":[
        "refractory"
    ],
    "wof:name":"Chase Nedrow Mfg Inc",
    "wof:placetype":"venue"
},
  "geometry": {"coordinates":[-83.55081199999999,42.524659],"type":"Point"}
}