{
  "type": "Feature",
  "properties": {
    "iso:country":"US",
    "sg:address":"12874 Rouget Rd",
    "sg:city":"Deerfield",
    "sg:classifiers":[
        {
            "category":"Retail",
            "subcategory":"Auto Repair",
            "type":"Services"
        }
    ],
    "sg:phone":"+1 517 447 3506",
    "sg:postcode":"49238",
    "sg:province":"MI",
    "sg:tags":[
        "automotive"
    ],
    "wof:name":"Dans Repair Shop",
    "wof:placetype":"venue"
},
  "geometry": {"coordinates":[-83.820931,41.870828],"type":"Point"}
}