{
  "type": "Feature",
  "properties": {
    "iso:country":"US",
    "sg:address":"5415 E 8 Mile Rd",
    "sg:city":"Warren",
    "sg:classifiers":[
        {
            "category":"Manufacturing",
            "subcategory":"Aerospace",
            "type":"Manufacturing & Wholesale Goods"
        }
    ],
    "sg:phone":"+1 586 756 2000",
    "sg:postcode":"48234",
    "sg:province":"MI",
    "sg:tags":[
        "aircraft",
        "component"
    ],
    "wof:name":"Maidstone Industries",
    "wof:placetype":"venue"
},
  "geometry": {"coordinates":[-83.04879099999999,42.447561],"type":"Point"}
}