{
  "type": "Feature",
  "properties": {
    "iso:country":"US",
    "sg:address":"3562 Hickory St",
    "sg:city":"Inkster",
    "sg:classifiers":[
        {
            "category":"Professional",
            "subcategory":"Business Services",
            "type":"Services"
        }
    ],
    "sg:phone":"+1 313 565 6312",
    "sg:postcode":"48141",
    "sg:province":"MI",
    "wof:name":"Trells Landscape Garden Design",
    "wof:placetype":"venue"
},
  "geometry": {"coordinates":[-83.316159,42.283407],"type":"Point"}
}