{
  "type": "Feature",
  "properties": {
    "iso:country":"US",
    "sg:address":"5315 US Hwy 12",
    "sg:city":"Buchanan",
    "sg:classifiers":[
        {
            "category":"Wholesale",
            "subcategory":"Durable Goods & Equipment",
            "type":"Manufacturing & Wholesale Goods"
        }
    ],
    "sg:phone":"+1 269 695 5884",
    "sg:postcode":"49107",
    "sg:province":"MI",
    "sg:tags":[
        "representative",
        "manufacturer"
    ],
    "wof:name":"Frame Products Inc",
    "wof:placetype":"venue"
},
  "geometry": {"coordinates":[-86.41956399999999,41.794385],"type":"Point"}
}