{
  "type": "Feature",
  "properties": {
    "iso:country":"US",
    "sg:address":"214 E Reasoner St",
    "sg:city":"Lansing",
    "sg:classifiers":[
        {
            "category":"Wholesale",
            "subcategory":"Fruits & Vegetables",
            "type":"Manufacturing & Wholesale Goods"
        }
    ],
    "sg:phone":"+1 517 482 6880",
    "sg:postcode":"48906",
    "sg:province":"MI",
    "wof:name":"Stan Setas Produce Co LLC",
    "wof:placetype":"venue"
},
  "geometry": {"coordinates":[-84.550077,42.75349],"type":"Point"}
}