{
  "type": "Feature",
  "properties": {
    "iso:country":"US",
    "sg:address":"104 W Walton Blvd",
    "sg:city":"Pontiac",
    "sg:classifiers":[
        {
            "category":"Communications",
            "subcategory":"Film & Video Production",
            "type":"Services"
        }
    ],
    "sg:phone":"+1 248 682 9626",
    "sg:postcode":"48340",
    "sg:province":"MI",
    "sg:tags":[
        "motion"
    ],
    "wof:name":"Twelfth House Productions",
    "wof:placetype":"venue"
},
  "geometry": {"coordinates":[-83.305882,42.676984],"type":"Point"}
}