{
  "type": "Feature",
  "properties": {
    "iso:country":"US",
    "sg:address":"7301 S State Rd",
    "sg:city":"Goodrich",
    "sg:classifiers":[
        {
            "category":"Banks & Credit Unions",
            "subcategory":"Bank",
            "type":"Services"
        }
    ],
    "sg:phone":"+1 810 636 2483",
    "sg:postcode":"48438",
    "sg:province":"MI",
    "sg:tags":[
        "state",
        "commercial"
    ],
    "wof:name":"Bank One",
    "wof:placetype":"venue"
},
  "geometry": {"coordinates":[-83.501897,42.925288],"type":"Point"}
}