{
  "type": "Feature",
  "properties": {
    "iso:country":"US",
    "sg:address":"430 Fuller Ave NE",
    "sg:city":"Grand Rapids",
    "sg:classifiers":[
        {
            "category":"Retail",
            "subcategory":"Repair Shop",
            "type":"Services"
        }
    ],
    "sg:phone":"+1 616 454 8282",
    "sg:postcode":"49503",
    "sg:province":"MI",
    "sg:tags":[
        "television",
        "radio"
    ],
    "wof:name":"North Rapids Television Svc",
    "wof:placetype":"venue"
},
  "geometry": {"coordinates":[-85.639758,42.971227],"type":"Point"}
}