{
  "type": "Feature",
  "properties": {
    "iso:country":"US",
    "sg:address":"24934 Orchid St",
    "sg:city":"Harrison Twp",
    "sg:classifiers":[
        {
            "category":"Professional",
            "subcategory":"Credit Reporting & Collection",
            "type":"Services"
        }
    ],
    "sg:phone":"+1 586 790 5530",
    "sg:postcode":"48045",
    "sg:province":"MI",
    "sg:tags":[
        "agency"
    ],
    "wof:name":"Great Lakes Judgement Recovery",
    "wof:placetype":"venue"
},
  "geometry": {"coordinates":[-82.85906300000001,42.550269],"type":"Point"}
}