{
  "type": "Feature",
  "properties": {
    "iso:country":"US",
    "sg:address":"3470 Centenniel",
    "sg:city":"Holly",
    "sg:classifiers":[
        {
            "category":"Personal",
            "type":"Services"
        }
    ],
    "sg:phone":"+1 248 634 7974",
    "sg:postcode":"48442",
    "sg:province":"MI",
    "wof:name":"Creative Party Planners",
    "wof:placetype":"venue"
},
  "geometry": {"coordinates":[-83.630365,42.843408],"type":"Point"}
}