{
  "type": "Feature",
  "properties": {
    "iso:country":"US",
    "sg:address":"111 College Ave NE",
    "sg:city":"Grand Rapids",
    "sg:classifiers":[
        {
            "category":"Education",
            "subcategory":"School",
            "type":"Public Place"
        }
    ],
    "sg:phone":"+1 616 771 2380",
    "sg:postcode":"49503",
    "sg:province":"MI",
    "wof:name":"City Middle School",
    "wof:placetype":"venue"
},
  "geometry": {"coordinates":[-85.657011,42.967171],"type":"Point"}
}