{
  "type": "Feature",
  "properties": {
    "iso:country":"US",
    "sg:address":"11120 Berry St",
    "sg:city":"Berrien Springs",
    "sg:classifiers":[
        {
            "category":"Building & Trades",
            "subcategory":"Landscaping Services",
            "type":"Services"
        }
    ],
    "sg:phone":"+1 269 473 1516",
    "sg:postcode":"49103",
    "sg:province":"MI",
    "wof:name":"Whiteheads Mowing",
    "wof:placetype":"venue"
},
  "geometry": {"coordinates":[-86.31505199999999,41.918583],"type":"Point"}
}