{
  "type": "Feature",
  "properties": {
    "iso:country":"US",
    "sg:address":"1400 Battle Creek Rd",
    "sg:city":"Charlotte",
    "sg:classifiers":[
        {
            "category":"Arts & Performance",
            "subcategory":"Theater",
            "type":"Entertainment"
        }
    ],
    "sg:phone":"+1 517 541 1200",
    "sg:postcode":"48813",
    "sg:province":"MI",
    "sg:tags":[
        "live",
        "music"
    ],
    "wof:name":"A J Radio",
    "wof:placetype":"venue"
},
  "geometry": {"coordinates":[-84.86139900000001,42.548497],"type":"Point"}
}