{
  "type": "Feature",
  "properties": {
    "iso:country":"US",
    "sg:address":"506 N Bradley Hwy",
    "sg:city":"Rogers City",
    "sg:classifiers":[
        {
            "category":"Health Services",
            "subcategory":"Health Practitioner",
            "type":"Services"
        }
    ],
    "sg:phone":"+1 989 734 7607",
    "sg:postcode":"49779",
    "sg:province":"MI",
    "sg:tags":[
        "therapist",
        "physical"
    ],
    "wof:name":"Rogers City Physical Therapy",
    "wof:placetype":"venue"
},
  "geometry": {"coordinates":[-83.83514700000001,45.425008],"type":"Point"}
}