{
  "type": "Feature",
  "properties": {
    "iso:country":"US",
    "sg:address":"3307 Kiesel Rd",
    "sg:city":"Bay City",
    "sg:classifiers":[
        {
            "category":"Organizations",
            "subcategory":"Religious Organization",
            "type":"Services"
        }
    ],
    "sg:phone":"+1 989 684 7960",
    "sg:postcode":"48706",
    "sg:province":"MI",
    "sg:tags":[
        "church"
    ],
    "wof:name":"Bangor Baptist Church",
    "wof:placetype":"venue"
},
  "geometry": {"coordinates":[-83.91943000000001,43.616686],"type":"Point"}
}