{
  "type": "Feature",
  "properties": {
    "iso:country":"US",
    "sg:address":"132 E Bridge St",
    "sg:city":"Portland",
    "sg:classifiers":[
        {
            "category":"Organizations",
            "subcategory":"Religious Organization",
            "type":"Services"
        }
    ],
    "sg:phone":"+1 517 647 4102",
    "sg:postcode":"48875",
    "sg:province":"MI",
    "sg:tags":[
        "synagogue"
    ],
    "wof:name":"Portland Masonic Temple",
    "wof:placetype":"venue"
},
  "geometry": {"coordinates":[-84.903254,42.869258],"type":"Point"}
}