{
  "type": "Feature",
  "properties": {
    "iso:country":"US",
    "sg:address":"1935 W Genesee St",
    "sg:city":"Lapeer",
    "sg:classifiers":[
        {
            "category":"Shopping",
            "subcategory":"Bicycles & Sporting Goods",
            "type":"Retail Goods"
        }
    ],
    "sg:phone":"+1 810 664 7200",
    "sg:postcode":"48446",
    "sg:province":"MI",
    "wof:name":"Dunham's Sports",
    "wof:placetype":"venue"
},
  "geometry": {"coordinates":[-83.328163,43.050605],"type":"Point"}
}