{
  "type": "Feature",
  "properties": {
    "iso:country":"US",
    "sg:address":"30514 Fox Club Dr",
    "sg:city":"Farmington Hills",
    "sg:classifiers":[
        {
            "category":"Professional",
            "subcategory":"Management & Consulting",
            "type":"Services"
        }
    ],
    "sg:phone":"+1 248 788 9294",
    "sg:postcode":"48331",
    "sg:province":"MI",
    "sg:tags":[
        "consultant",
        "training"
    ],
    "wof:name":"Learning Prism",
    "wof:placetype":"venue"
},
  "geometry": {"coordinates":[-83.40688299999999,42.51681],"type":"Point"}
}