{
  "type": "Feature",
  "properties": {
    "iso:country":"US",
    "sg:address":"215 S 12th St",
    "sg:city":"Escanaba",
    "sg:classifiers":[
        {
            "category":"Social Services",
            "subcategory":"Adult Care",
            "type":"Services"
        }
    ],
    "sg:phone":"+1 906 786 3336",
    "sg:postcode":"49829",
    "sg:province":"MI",
    "sg:tags":[
        "foster"
    ],
    "wof:name":"Boomer Adult Foster Care",
    "wof:placetype":"venue"
},
  "geometry": {"coordinates":[-87.064082,45.744488],"type":"Point"}
}