{
  "type": "Feature",
  "properties": {
    "iso:country":"US",
    "sg:address":"3435 Tuscany Dr SE",
    "sg:city":"Grand Rapids",
    "sg:classifiers":[
        {
            "category":"Professional",
            "subcategory":"Testing Lab",
            "type":"Services"
        }
    ],
    "sg:phone":"+1 616 285 9929",
    "sg:postcode":"49546",
    "sg:province":"MI",
    "sg:tags":[
        "asbestos"
    ],
    "wof:name":"Environmental Advisory Group",
    "wof:placetype":"venue"
},
  "geometry": {"coordinates":[-85.498079,42.901526],"type":"Point"}
}