{
  "type": "Feature",
  "properties": {
    "iso:country":"US",
    "sg:address":"940 Capital Ave NE",
    "sg:city":"Battle Creek",
    "sg:classifiers":[
        {
            "category":"Personal",
            "subcategory":"Barber",
            "type":"Services"
        }
    ],
    "sg:phone":"+1 269 274 3248",
    "sg:postcode":"49017",
    "sg:province":"MI",
    "wof:name":"Josiah's Barber Shop",
    "wof:placetype":"venue"
},
  "geometry": {"coordinates":[-85.15519399999999,42.335341],"type":"Point"}
}