{
  "type": "Feature",
  "properties": {
    "iso:country":"US",
    "sg:address":"11500 15 Mile Rd",
    "sg:city":"Sterling Heights",
    "sg:classifiers":[
        {
            "category":"Restaurant",
            "type":"Food & Drink"
        }
    ],
    "sg:phone":"+1 586 939 4690",
    "sg:postcode":"48312",
    "sg:province":"MI",
    "sg:tags":[
        "chinese"
    ],
    "wof:name":"Chinese Gourmet",
    "wof:placetype":"venue"
},
  "geometry": {"coordinates":[-83.010597,42.551601],"type":"Point"}
}