{
  "type": "Feature",
  "properties": {
    "iso:country":"US",
    "sg:address":"1349 S Otsego Ave",
    "sg:city":"Gaylord",
    "sg:classifiers":[
        {
            "category":"Retail",
            "subcategory":"Repair Shop",
            "type":"Services"
        }
    ],
    "sg:phone":"+1 989 732 5004",
    "sg:postcode":"49735",
    "sg:province":"MI",
    "wof:name":"Alpine Electronics Service",
    "wof:placetype":"venue"
},
  "geometry": {"coordinates":[-84.677654,45.013247],"type":"Point"}
}