{
  "type": "Feature",
  "properties": {
    "iso:country":"US",
    "sg:address":"1926 Washtenaw Rd",
    "sg:city":"Ypsilanti",
    "sg:classifiers":[
        {
            "category":"Real Estate",
            "subcategory":"Real Estate Operator",
            "type":"Services"
        }
    ],
    "sg:phone":"+1 734 487 5109",
    "sg:postcode":"48197",
    "sg:province":"MI",
    "sg:tags":[
        "building",
        "apartment"
    ],
    "wof:name":"Triangle West Apartments",
    "wof:placetype":"venue"
},
  "geometry": {"coordinates":[-83.644445,42.248272],"type":"Point"}
}