{
  "type": "Feature",
  "properties": {
    "iso:country":"US",
    "sg:address":"13910 Stout Ave NE",
    "sg:city":"Cedar Springs",
    "sg:classifiers":[
        {
            "category":"Personal",
            "type":"Services"
        }
    ],
    "sg:phone":"+1 616 696 3663",
    "sg:postcode":"49319",
    "sg:province":"MI",
    "wof:name":"D&B Shops 4u",
    "wof:placetype":"venue"
},
  "geometry": {"coordinates":[-85.50085,43.214701],"type":"Point"}
}