{
  "type": "Feature",
  "properties": {
    "iso:country":"US",
    "sg:address":"2750 W Monroe Rd",
    "sg:city":"Tecumseh",
    "sg:classifiers":[
        {
            "category":"Organizations",
            "subcategory":"Religious Organization",
            "type":"Services"
        }
    ],
    "sg:phone":"+1 517 423 5152",
    "sg:postcode":"49287",
    "sg:province":"MI",
    "sg:tags":[
        "church"
    ],
    "wof:name":"Jehovah's Witnesses",
    "wof:placetype":"venue"
},
  "geometry": {"coordinates":[-84.024976,42.01198],"type":"Point"}
}