{
  "type": "Feature",
  "properties": {
    "iso:country":"US",
    "sg:address":"10658 W Olive Rd",
    "sg:city":"West Olive",
    "sg:classifiers":[
        {
            "category":"Home & Garden",
            "subcategory":"Garden Supply",
            "type":"Retail Goods"
        }
    ],
    "sg:phone":"+1 616 842 8936",
    "sg:postcode":"49460",
    "sg:province":"MI",
    "sg:tags":[
        "tree",
        "christmas"
    ],
    "wof:name":"Pine Ridge Nursery & Wreath",
    "wof:placetype":"venue"
},
  "geometry": {"coordinates":[-86.17450700000001,42.962265],"type":"Point"}
}