{
  "type": "Feature",
  "properties": {
    "iso:country":"US",
    "sg:address":"230 S Pleasant St",
    "sg:city":"Pickford",
    "sg:classifiers":[
        {
            "category":"Building & Trades",
            "subcategory":"Construction",
            "type":"Services"
        }
    ],
    "sg:phone":"+1 906 647 3802",
    "sg:postcode":"49774",
    "sg:province":"MI",
    "sg:tags":[
        "general",
        "contractor"
    ],
    "wof:name":"Mark Schwab Construction",
    "wof:placetype":"venue"
},
  "geometry": {"coordinates":[-84.36066099999999,46.156715],"type":"Point"}
}