{
  "type": "Feature",
  "properties": {
    "iso:country":"US",
    "sg:address":"4315 Dixie Hwy",
    "sg:city":"Waterford",
    "sg:classifiers":[
        {
            "category":"Home & Garden",
            "subcategory":"Building Materials",
            "type":"Retail Goods"
        }
    ],
    "sg:phone":"+1 248 673 1211",
    "sg:postcode":"48329",
    "sg:province":"MI",
    "sg:tags":[
        "lumber"
    ],
    "wof:name":"Burke Building Ctr",
    "wof:placetype":"venue"
},
  "geometry": {"coordinates":[-83.37372499999999,42.681223],"type":"Point"}
}