{
  "type": "Feature",
  "properties": {
    "iso:country":"US",
    "sg:address":"304 S Clippert St",
    "sg:city":"Lansing",
    "sg:classifiers":[
        {
            "category":"Retail",
            "subcategory":"Auto Repair",
            "type":"Services"
        }
    ],
    "sg:phone":"+1 517 337 0444",
    "sg:postcode":"48912",
    "sg:province":"MI",
    "sg:tags":[
        "repairing",
        "automobile",
        "automotive",
        "general"
    ],
    "wof:name":"Badgley's Garage",
    "wof:placetype":"venue"
},
  "geometry": {"coordinates":[-84.50849100000001,42.730018],"type":"Point"}
}