{
  "type": "Feature",
  "properties": {
    "iso:country":"US",
    "sg:address":"17564 Dix Rd",
    "sg:city":"Melvindale",
    "sg:classifiers":[
        {
            "category":"Autos & Motor Vehicles",
            "subcategory":"Automobile Sales",
            "type":"Retail Goods"
        }
    ],
    "sg:phone":"+1 313 381 3555",
    "sg:postcode":"48122",
    "sg:province":"MI",
    "sg:tags":[
        "car"
    ],
    "wof:name":"Bell Auto Sales",
    "wof:placetype":"venue"
},
  "geometry": {"coordinates":[-83.170601,42.282398],"type":"Point"}
}