{
  "type": "Feature",
  "properties": {
    "iso:country":"US",
    "sg:address":"2831 N Lincoln Rd",
    "sg:city":"Escanaba",
    "sg:classifiers":[
        {
            "category":"Social Services",
            "subcategory":"Job Training",
            "type":"Services"
        }
    ],
    "sg:phone":"+1 906 789 9732",
    "sg:postcode":"49829",
    "sg:province":"MI",
    "wof:name":"Six County Employement Aliance",
    "wof:placetype":"venue"
},
  "geometry": {"coordinates":[-87.083446,45.780746],"type":"Point"}
}