{
  "type": "Feature",
  "properties": {
    "iso:country":"US",
    "sg:address":"2111 Walker Ct NW",
    "sg:city":"Grand Rapids",
    "sg:classifiers":[
        {
            "category":"Wholesale",
            "subcategory":"Hardware",
            "type":"Manufacturing & Wholesale Goods"
        }
    ],
    "sg:phone":"+1 616 453 6004",
    "sg:postcode":"49544",
    "sg:province":"MI",
    "sg:tags":[
        "ice",
        "freezer",
        "cream"
    ],
    "sg:website":"www.taylor-michigan.com",
    "wof:name":"Taylor Freezer Of Michigan Inc",
    "wof:placetype":"venue"
},
  "geometry": {"coordinates":[-85.720675,43.010757],"type":"Point"}
}