{
  "type": "Feature",
  "properties": {
    "iso:country":"US",
    "sg:address":"1900 Cindy St",
    "sg:city":"Ishpeming",
    "sg:classifiers":[
        {
            "category":"Shopping",
            "subcategory":"Discount & Variety Stores",
            "type":"Retail Goods"
        }
    ],
    "sg:phone":"+1 906 485 5756",
    "sg:postcode":"49849",
    "sg:province":"MI",
    "wof:name":"Baldwin Sales & Service",
    "wof:placetype":"venue"
},
  "geometry": {"coordinates":[-87.717861,46.489324],"type":"Point"}
}