{
  "type": "Feature",
  "properties": {
    "iso:country":"US",
    "sg:address":"1500 E Kilgore Rd",
    "sg:city":"Kalamazoo",
    "sg:classifiers":[
        {
            "category":"Travel",
            "subcategory":"Hotels & Motels",
            "type":"Entertainment"
        }
    ],
    "sg:phone":"+1 269 349 0855",
    "sg:postcode":"49001",
    "sg:province":"MI",
    "sg:website":"http://www.marriott.com",
    "wof:name":"Residence Inn by Marriott Kalamazoo East",
    "wof:placetype":"venue"
},
  "geometry": {"coordinates":[-85.563751,42.245361],"type":"Point"}
}