{
  "type": "Feature",
  "properties": {
    "iso:country":"US",
    "sg:address":"2055 Oak Industrial Dr NE",
    "sg:city":"Grand Rapids",
    "sg:classifiers":[
        {
            "category":"Wholesale",
            "subcategory":"Machinery & Supplies",
            "type":"Manufacturing & Wholesale Goods"
        }
    ],
    "sg:phone":"+1 616 459 5004",
    "sg:postcode":"49505",
    "sg:province":"MI",
    "sg:tags":[
        "equipment",
        "labeling"
    ],
    "sg:website":"www.grlabel.com",
    "wof:name":"Grand Rapids Label Systems",
    "wof:placetype":"venue"
},
  "geometry": {"coordinates":[-85.61357,42.975152],"type":"Point"}
}