{
  "type": "Feature",
  "properties": {
    "iso:country":"US",
    "sg:address":"5252 N Dort Hwy",
    "sg:city":"Flint",
    "sg:classifiers":[
        {
            "category":"Shopping",
            "subcategory":"Department Store",
            "type":"Retail Goods"
        }
    ],
    "sg:phone":"+1 810 785 0565",
    "sg:postcode":"48505",
    "sg:province":"MI",
    "sg:tags":[
        "shop"
    ],
    "wof:name":"Rock Bottom Closeout Inc",
    "wof:placetype":"venue"
},
  "geometry": {"coordinates":[-83.673796,43.061429],"type":"Point"}
}