{
  "type": "Feature",
  "properties": {
    "iso:country":"US",
    "sg:address":"232 E Hurd Rd",
    "sg:city":"Monroe",
    "sg:classifiers":[
        {
            "category":"Personal",
            "subcategory":"Beauty Salon",
            "type":"Services"
        }
    ],
    "sg:phone":"+1 734 242 1577",
    "sg:postcode":"48162",
    "sg:province":"MI",
    "sg:tags":[
        "shop"
    ],
    "wof:name":"Body & Mind Essentials",
    "wof:placetype":"venue"
},
  "geometry": {"coordinates":[-83.373161,41.958167],"type":"Point"}
}