{
  "type": "Feature",
  "properties": {
    "iso:country":"US",
    "sg:address":"2720 E Oakley Park Rd",
    "sg:city":"Commerce Township",
    "sg:classifiers":[
        {
            "category":"Social Services",
            "subcategory":"Child Care",
            "type":"Services"
        },
        {
            "category":"Education",
            "subcategory":"Preschool",
            "type":"Public Place"
        },
        {
            "category":"Education",
            "subcategory":"School",
            "type":"Public Place"
        }
    ],
    "sg:phone":"+1 248 669 7448",
    "sg:postcode":"48390",
    "sg:province":"MI",
    "sg:tags":[
        "elementary",
        "day"
    ],
    "sg:website":"www.childtime.com",
    "wof:name":"Childtime Learning Centers",
    "wof:placetype":"venue"
},
  "geometry": {"coordinates":[-83.449501,42.5704],"type":"Point"}
}