{
  "type": "Feature",
  "properties": {
    "iso:country":"US",
    "sg:address":"1921 Warwick Ave",
    "sg:city":"Lincoln Park",
    "sg:classifiers":[
        {
            "category":"Building & Trades",
            "subcategory":"Construction",
            "type":"Services"
        }
    ],
    "sg:phone":"+1 313 381 9899",
    "sg:postcode":"48146",
    "sg:province":"MI",
    "sg:tags":[
        "house"
    ],
    "wof:name":"All Decked Out Construction",
    "wof:placetype":"venue"
},
  "geometry": {"coordinates":[-83.188751,42.257915],"type":"Point"}
}