{
  "type": "Feature",
  "properties": {
    "iso:country":"US",
    "sg:address":"12884 Trist Rd",
    "sg:city":"Grass Lake",
    "sg:classifiers":[
        {
            "category":"Organizations",
            "subcategory":"Religious Organization",
            "type":"Services"
        }
    ],
    "sg:phone":"+1 517 522 8182",
    "sg:postcode":"49240",
    "sg:province":"MI",
    "sg:tags":[
        "church"
    ],
    "wof:name":"Mount Hope Bible Church",
    "wof:placetype":"venue"
},
  "geometry": {"coordinates":[-84.176507,42.33625],"type":"Point"}
}