{
  "type": "Feature",
  "properties": {
    "iso:country":"US",
    "sg:address":"10 N State St",
    "sg:city":"Niles",
    "sg:classifiers":[
        {
            "category":"Health Services",
            "subcategory":"Doctor",
            "type":"Services"
        }
    ],
    "sg:phone":"+1 269 684 6003",
    "sg:postcode":"49120",
    "sg:province":"MI",
    "wof:name":"Gerald A Bienman DDS PC",
    "wof:placetype":"venue"
},
  "geometry": {"coordinates":[-86.26257699999999,41.827317],"type":"Point"}
}