{
  "type": "Feature",
  "properties": {
    "iso:country":"US",
    "sg:address":"1230 Sheridan St",
    "sg:city":"Plymouth",
    "sg:classifiers":[
        {
            "category":"Professional",
            "subcategory":"Management & Consulting",
            "type":"Services"
        }
    ],
    "sg:phone":"+1 734 394 1276",
    "sg:postcode":"48170",
    "sg:province":"MI",
    "wof:name":"Integrated Process Developers",
    "wof:placetype":"venue"
},
  "geometry": {"coordinates":[-83.47452199999999,42.371418],"type":"Point"}
}