{
  "type": "Feature",
  "properties": {
    "iso:country":"US",
    "sg:address":"4229 Cass Ave",
    "sg:city":"Detroit",
    "sg:classifiers":[
        {
            "category":"Health Services",
            "subcategory":"Doctor",
            "type":"Services"
        }
    ],
    "sg:phone":"+1 313 831 7776",
    "sg:postcode":"48201",
    "sg:province":"MI",
    "sg:tags":[
        "obstetrician",
        "gynecologist"
    ],
    "sg:website":"www.plannedparenthood.org/midsou...",
    "wof:name":"Planned Parenthood",
    "wof:placetype":"venue"
},
  "geometry": {"coordinates":[-83.064072,42.35069],"type":"Point"}
}