{
  "type": "Feature",
  "properties": {
    "iso:country":"US",
    "sg:address":"47725 Michigan Ave",
    "sg:city":"Canton",
    "sg:classifiers":[
        {
            "category":"Shopping",
            "subcategory":"Party Supplies",
            "type":"Retail Goods"
        }
    ],
    "sg:phone":"+1 800 562 3412",
    "sg:postcode":"48188",
    "sg:province":"MI",
    "wof:name":"Party Max",
    "wof:placetype":"venue"
},
  "geometry": {"coordinates":[-83.509804,42.2654],"type":"Point"}
}