{
  "type": "Feature",
  "properties": {
    "iso:country":"US",
    "sg:address":"31108 Beverly Rd",
    "sg:city":"Romulus",
    "sg:classifiers":[
        {
            "category":"Retail",
            "subcategory":"Photofinishing",
            "type":"Services"
        }
    ],
    "sg:phone":"+1 734 595 3814",
    "sg:postcode":"48174",
    "sg:province":"MI",
    "sg:tags":[
        "laboratory"
    ],
    "wof:name":"M N M Photographix",
    "wof:placetype":"venue"
},
  "geometry": {"coordinates":[-83.34795,42.260118],"type":"Point"}
}