{
  "type": "Feature",
  "properties": {
    "iso:country":"US",
    "sg:address":"28067 John R Rd",
    "sg:city":"Madison Heights",
    "sg:classifiers":[
        {
            "category":"Personal",
            "subcategory":"Beauty Salon",
            "type":"Services"
        }
    ],
    "sg:phone":"+1 248 545 8170",
    "sg:postcode":"48071",
    "sg:province":"MI",
    "wof:name":"Jodeen's Hair Salon",
    "wof:placetype":"venue"
},
  "geometry": {"coordinates":[-83.10565,42.500219],"type":"Point"}
}