{
  "type": "Feature",
  "properties": {
    "iso:country":"US",
    "sg:address":"729 Durkee",
    "sg:city":"Nashville",
    "sg:classifiers":[
        {
            "category":"Wholesale",
            "subcategory":"Meat",
            "type":"Manufacturing & Wholesale Goods"
        }
    ],
    "sg:phone":"+1 517 852 9332",
    "sg:postcode":"49073",
    "sg:province":"MI",
    "sg:tags":[
        "packer"
    ],
    "wof:name":"Nashville Locker Svc",
    "wof:placetype":"venue"
},
  "geometry": {"coordinates":[-85.09468,42.597772],"type":"Point"}
}