{
  "type": "Feature",
  "properties": {
    "iso:country":"US",
    "sg:address":"5660 State St",
    "sg:city":"Saginaw",
    "sg:classifiers":[
        {
            "category":"Shopping",
            "subcategory":"Department Store",
            "type":"Retail Goods"
        }
    ],
    "sg:phone":"+1 989 790 3852",
    "sg:postcode":"48603",
    "sg:province":"MI",
    "sg:tags":[
        "shop"
    ],
    "wof:name":"Dollar General",
    "wof:placetype":"venue"
},
  "geometry": {"coordinates":[-84.02780300000001,43.437005],"type":"Point"}
}