{
  "type": "Feature",
  "properties": {
    "iso:country":"US",
    "sg:address":"1018 Lafayette Ave NE",
    "sg:city":"Grand Rapids",
    "sg:classifiers":[
        {
            "category":"Organizations",
            "subcategory":"Religious Organization",
            "type":"Services"
        }
    ],
    "sg:phone":"+1 616 454 1812",
    "sg:postcode":"49503",
    "sg:province":"MI",
    "wof:name":"His Place Ministry",
    "wof:placetype":"venue"
},
  "geometry": {"coordinates":[-85.661976,42.981737],"type":"Point"}
}