{
  "type": "Feature",
  "properties": {
    "iso:country":"US",
    "sg:address":"576 N Union City Rd",
    "sg:city":"Coldwater",
    "sg:classifiers":[
        {
            "category":"Professional",
            "subcategory":"Business Services",
            "type":"Services"
        }
    ],
    "sg:phone":"+1 517 278 5590",
    "sg:postcode":"49036",
    "sg:province":"MI",
    "wof:name":"R&D Enterprises",
    "wof:placetype":"venue"
},
  "geometry": {"coordinates":[-85.02050800000001,42.008858],"type":"Point"}
}