{
  "type": "Feature",
  "properties": {
    "iso:country":"US",
    "sg:address":"1787 Van Courtland Dr",
    "sg:city":"Troy",
    "sg:classifiers":[
        {
            "category":"Wholesale",
            "subcategory":"Vending Machines",
            "type":"Manufacturing & Wholesale Goods"
        }
    ],
    "sg:phone":"+1 248 689 6156",
    "sg:postcode":"48083",
    "sg:province":"MI",
    "sg:tags":[
        "operator"
    ],
    "wof:name":"Vending Liquidators",
    "wof:placetype":"venue"
},
  "geometry": {"coordinates":[-83.13461700000001,42.552784],"type":"Point"}
}