{
  "type": "Feature",
  "properties": {
    "iso:country":"US",
    "sg:address":"6667 W River Rd NE",
    "sg:city":"Belmont",
    "sg:classifiers":[
        {
            "category":"Professional",
            "subcategory":"Lawyer & Legal Services",
            "type":"Services"
        }
    ],
    "sg:phone":"+1 616 364 4297",
    "sg:postcode":"49306",
    "sg:province":"MI",
    "sg:tags":[
        "attorney"
    ],
    "wof:name":"Edward J Kehoe Jr",
    "wof:placetype":"venue"
},
  "geometry": {"coordinates":[-85.58378399999999,43.064242],"type":"Point"}
}