{
  "type": "Feature",
  "properties": {
    "iso:country":"US",
    "sg:address":"2972 Center Ave",
    "sg:city":"Essexville",
    "sg:classifiers":[
        {
            "category":"Shopping",
            "subcategory":"Clothing, Apparel, & Fashions",
            "type":"Retail Goods"
        }
    ],
    "sg:phone":"+1 989 892 3992",
    "sg:postcode":"48732",
    "sg:province":"MI",
    "wof:name":"Fashion Bug Plus",
    "wof:placetype":"venue"
},
  "geometry": {"coordinates":[-83.844263,43.594539],"type":"Point"}
}