{
  "type": "Feature",
  "properties": {
    "iso:country":"US",
    "sg:address":"400 Bates Dr",
    "sg:city":"Lapeer",
    "sg:classifiers":[
        {
            "category":"Building & Trades",
            "subcategory":"Construction",
            "type":"Services"
        }
    ],
    "sg:phone":"+1 810 667 3147",
    "sg:postcode":"48446",
    "sg:province":"MI",
    "sg:tags":[
        "concrete",
        "contractor"
    ],
    "wof:name":"Elite Concrete",
    "wof:placetype":"venue"
},
  "geometry": {"coordinates":[-83.32137899999999,43.075976],"type":"Point"}
}