{
  "type": "Feature",
  "properties": {
    "iso:country":"US",
    "sg:address":"PO Box 588",
    "sg:city":"Flint",
    "sg:classifiers":[
        {
            "category":"Building & Trades",
            "subcategory":"Plumbing",
            "type":"Services"
        }
    ],
    "sg:phone":"+1 810 232 5232",
    "sg:postcode":"48501",
    "sg:province":"MI",
    "wof:name":"Shank-Coupland-Long Co Plbrs",
    "wof:placetype":"venue"
},
  "geometry": {"coordinates":[-83.68789700000001,43.021],"type":"Point"}
}