{
  "type": "Feature",
  "properties": {
    "iso:country":"US",
    "sg:address":"31313 Kendall Ave",
    "sg:city":"Fraser",
    "sg:classifiers":[
        {
            "category":"Manufacturing",
            "subcategory":"Tools & Machinery",
            "type":"Manufacturing & Wholesale Goods"
        }
    ],
    "sg:phone":"+1 586 293 0200",
    "sg:postcode":"48026",
    "sg:province":"MI",
    "sg:tags":[
        "machine"
    ],
    "sg:website":"www.newmethod.com",
    "wof:name":"New Method Steel Stamps",
    "wof:placetype":"venue"
},
  "geometry": {"coordinates":[-82.950548,42.52609],"type":"Point"}
}