{
  "type": "Feature",
  "properties": {
    "iso:country":"US",
    "sg:address":"506 S Centerville Rd",
    "sg:city":"Sturgis",
    "sg:classifiers":[
        {
            "category":"Retail",
            "subcategory":"Car Wash",
            "type":"Services"
        }
    ],
    "sg:phone":"+1 269 651 6380",
    "sg:postcode":"49091",
    "sg:province":"MI",
    "sg:tags":[
        "carwash"
    ],
    "wof:name":"Aquablast Car Wash",
    "wof:placetype":"venue"
},
  "geometry": {"coordinates":[-85.42833,41.793128],"type":"Point"}
}