{
  "type": "Feature",
  "properties": {
    "iso:country":"US",
    "sg:address":"716 Grant St",
    "sg:city":"Big Rapids",
    "sg:classifiers":[
        {
            "category":"Professional",
            "subcategory":"Business Services",
            "type":"Services"
        }
    ],
    "sg:phone":"+1 231 796 3981",
    "sg:postcode":"49307",
    "sg:province":"MI",
    "wof:name":"Interior Illusions",
    "wof:placetype":"venue"
},
  "geometry": {"coordinates":[-85.490404,43.707201],"type":"Point"}
}