{
  "type": "Feature",
  "properties": {
    "iso:country":"US",
    "sg:address":"445 W 17th St",
    "sg:city":"Holland",
    "sg:classifiers":[
        {
            "category":"Building & Trades",
            "subcategory":"Construction",
            "type":"Services"
        }
    ],
    "sg:phone":"+1 616 494 0530",
    "sg:postcode":"49423",
    "sg:province":"MI",
    "sg:tags":[
        "designer",
        "marine",
        "contractor"
    ],
    "wof:name":"Drummond Marine Boat Sale",
    "wof:placetype":"venue"
},
  "geometry": {"coordinates":[-86.127788,42.782085],"type":"Point"}
}