{
  "type": "Feature",
  "properties": {
    "iso:country":"US",
    "sg:address":"2030 S Center Rd",
    "sg:city":"Midland",
    "sg:classifiers":[
        {
            "category":"Professional",
            "subcategory":"Engineering",
            "type":"Services"
        },
        {
            "category":"Professional",
            "subcategory":"Testing Lab",
            "type":"Services"
        }
    ],
    "sg:phone":"+1 989 636 0289",
    "sg:postcode":"48609",
    "sg:province":"MI",
    "sg:tags":[
        "laboratory",
        "physical",
        "commercial",
        "research"
    ],
    "wof:name":"Dow Chemical",
    "wof:placetype":"venue"
},
  "geometry": {"coordinates":[-84.014942,43.39078],"type":"Point"}
}