{
  "type": "Feature",
  "properties": {
    "iso:country":"US",
    "sg:address":"1194 Roods Lake Rd",
    "sg:city":"Lapeer",
    "sg:classifiers":[
        {
            "category":"Manufacturing",
            "subcategory":"Metals",
            "type":"Manufacturing & Wholesale Goods"
        }
    ],
    "sg:phone":"+1 810 664 7741",
    "sg:postcode":"48446",
    "sg:province":"MI",
    "sg:tags":[
        "fastener"
    ],
    "wof:name":"Kamax",
    "wof:placetype":"venue"
},
  "geometry": {"coordinates":[-83.276246,43.064681],"type":"Point"}
}