{
  "type": "Feature",
  "properties": {
    "iso:country":"US",
    "sg:address":"18489 Davidson Rd",
    "sg:city":"Fraser",
    "sg:classifiers":[
        {
            "category":"Wholesale",
            "subcategory":"Hardware",
            "type":"Manufacturing & Wholesale Goods"
        }
    ],
    "sg:phone":"+1 586 294 5959",
    "sg:postcode":"48026",
    "sg:province":"MI",
    "sg:tags":[
        "refrigerating"
    ],
    "wof:name":"Rapid Service Refrigeration",
    "wof:placetype":"venue"
},
  "geometry": {"coordinates":[-82.93200299999999,42.532788],"type":"Point"}
}