{
  "type": "Feature",
  "properties": {
    "iso:country":"US",
    "sg:address":"2655 Eastern Ave SE",
    "sg:city":"Grand Rapids",
    "sg:classifiers":[
        {
            "category":"Organizations",
            "subcategory":"Religious Organization",
            "type":"Services"
        }
    ],
    "sg:phone":"+1 616 452 9686",
    "sg:postcode":"49507",
    "sg:province":"MI",
    "sg:tags":[
        "church"
    ],
    "sg:website":"www.algerparkcrc.com",
    "wof:name":"Alger Park Christian Reformed",
    "wof:placetype":"venue"
},
  "geometry": {"coordinates":[-85.647296,42.915099],"type":"Point"}
}