{
  "type": "Feature",
  "properties": {
    "iso:country":"US",
    "sg:address":"712 Provincial Dr",
    "sg:city":"Chelsea",
    "sg:classifiers":[
        {
            "category":"Real Estate",
            "subcategory":"Real Estate Operator",
            "type":"Services"
        }
    ],
    "sg:phone":"+1 734 433 0912",
    "sg:postcode":"48118",
    "sg:province":"MI",
    "sg:tags":[
        "building",
        "nonresidential"
    ],
    "wof:name":"Silverspoons Properties LLC",
    "wof:placetype":"venue"
},
  "geometry": {"coordinates":[-84.00606000000001,42.318801],"type":"Point"}
}