{
  "type": "Feature",
  "properties": {
    "iso:country":"US",
    "sg:address":"1580 S Old US Highway 23",
    "sg:city":"Brighton",
    "sg:classifiers":[
        {
            "category":"Government",
            "subcategory":"Fire Station",
            "type":"Public Place"
        }
    ],
    "sg:phone":"+1 810 229 0565",
    "sg:postcode":"48114",
    "sg:province":"MI",
    "sg:tags":[
        "department"
    ],
    "wof:name":"Brighton Twp Fire Dept",
    "wof:placetype":"venue"
},
  "geometry": {"coordinates":[-83.75345799999999,42.580226],"type":"Point"}
}