{
  "type": "Feature",
  "properties": {
    "iso:country":"US",
    "sg:address":"117 W Main St",
    "sg:city":"Hudson",
    "sg:classifiers":[
        {
            "category":"Retail",
            "subcategory":"Auto Repair",
            "type":"Services"
        }
    ],
    "sg:phone":"+1 517 448 4848",
    "sg:postcode":"49247",
    "sg:province":"MI",
    "sg:tags":[
        "general"
    ],
    "wof:name":"Tiger Carwash",
    "wof:placetype":"venue"
},
  "geometry": {"coordinates":[-84.35185300000001,41.85487],"type":"Point"}
}