{
  "type": "Feature",
  "properties": {
    "iso:country":"US",
    "sg:address":"1451 Lake St",
    "sg:city":"Niles",
    "sg:classifiers":[
        {
            "category":"Professional",
            "subcategory":"Engineering",
            "type":"Services"
        }
    ],
    "sg:phone":"+1 269 684 9960",
    "sg:postcode":"49120",
    "sg:province":"MI",
    "sg:tags":[
        "engineer"
    ],
    "sg:website":"www.rti-products.com",
    "wof:name":"RTI Products",
    "wof:placetype":"venue"
},
  "geometry": {"coordinates":[-86.239439,41.841408],"type":"Point"}
}