{
  "type": "Feature",
  "properties": {
    "iso:country":"US",
    "sg:address":"303 W Buffalo St",
    "sg:city":"New Buffalo",
    "sg:classifiers":[
        {
            "category":"Restaurant",
            "type":"Food & Drink"
        }
    ],
    "sg:phone":"+1 269 469 9010",
    "sg:postcode":"49117",
    "sg:province":"MI",
    "wof:name":"Baguette De France",
    "wof:placetype":"venue"
},
  "geometry": {"coordinates":[-86.74682900000001,41.7926],"type":"Point"}
}