{
  "type": "Feature",
  "properties": {
    "iso:country":"US",
    "sg:address":"2902 Connon St",
    "sg:city":"Alpena",
    "sg:classifiers":[
        {
            "category":"Social Services",
            "subcategory":"Adult Care",
            "type":"Services"
        }
    ],
    "sg:phone":"+1 989 354 5837",
    "sg:postcode":"49707",
    "sg:province":"MI",
    "sg:tags":[
        "residential"
    ],
    "wof:name":"Sunrise Adult Foster Care Home",
    "wof:placetype":"venue"
},
  "geometry": {"coordinates":[-83.462177,45.042178],"type":"Point"}
}