{
  "type": "Feature",
  "properties": {
    "iso:country":"US",
    "sg:address":"127 Main St",
    "sg:city":"Hanover",
    "sg:classifiers":[
        {
            "category":"Food & Beverages",
            "subcategory":"Groceries & Convenience Stores",
            "type":"Retail Goods"
        }
    ],
    "sg:phone":"+1 517 563 8291",
    "sg:postcode":"49241",
    "sg:province":"MI",
    "sg:tags":[
        "grocer"
    ],
    "wof:name":"Hanover Market",
    "wof:placetype":"venue"
},
  "geometry": {"coordinates":[-84.55448800000001,42.101829],"type":"Point"}
}