{
  "type": "Feature",
  "properties": {
    "iso:country":"US",
    "sg:address":"925 S Canal Rd",
    "sg:city":"Lansing",
    "sg:classifiers":[
        {
            "category":"Sports & Exercise",
            "subcategory":"Golf",
            "type":"Entertainment"
        }
    ],
    "sg:phone":"+1 517 627 8687",
    "sg:postcode":"48917",
    "sg:province":"MI",
    "sg:tags":[
        "course",
        "public"
    ],
    "wof:name":"Players Club Golf Course",
    "wof:placetype":"venue"
},
  "geometry": {"coordinates":[-84.661945,42.722431],"type":"Point"}
}