{
  "type": "Feature",
  "properties": {
    "iso:country":"US",
    "sg:address":"216 Dartmouth Ave",
    "sg:city":"Holland",
    "sg:classifiers":[
        {
            "category":"Professional",
            "subcategory":"Business Services",
            "type":"Services"
        }
    ],
    "sg:phone":"+1 616 396 6876",
    "sg:postcode":"49423",
    "sg:province":"MI",
    "wof:name":"Yonkman Interior",
    "wof:placetype":"venue"
},
  "geometry": {"coordinates":[-86.069658,42.789569],"type":"Point"}
}