{
  "type": "Feature",
  "properties": {
    "iso:country":"US",
    "sg:address":"19150 Meginnity St",
    "sg:city":"Melvindale",
    "sg:classifiers":[
        {
            "category":"Shopping",
            "subcategory":"Hobbies, Toys, & Games",
            "type":"Retail Goods"
        }
    ],
    "sg:phone":"+1 313 389 2866",
    "sg:postcode":"48122",
    "sg:province":"MI",
    "sg:tags":[
        "shop",
        "hobby"
    ],
    "wof:name":"Spin-O",
    "wof:placetype":"venue"
},
  "geometry": {"coordinates":[-83.177803,42.2705],"type":"Point"}
}