{
  "type": "Feature",
  "properties": {
    "iso:country":"US",
    "sg:address":"21825 Superior Rd",
    "sg:city":"Taylor",
    "sg:classifiers":[
        {
            "category":"Professional",
            "subcategory":"Accounting & Tax Preparation",
            "type":"Services"
        }
    ],
    "sg:phone":"+1 734 287 8420",
    "sg:postcode":"48180",
    "sg:province":"MI",
    "wof:name":"Buck-N-Ham Machine Inc",
    "wof:placetype":"venue"
},
  "geometry": {"coordinates":[-83.247855,42.205457],"type":"Point"}
}