{
  "type": "Feature",
  "properties": {
    "iso:country":"US",
    "sg:address":"19782 Whitcomb St",
    "sg:city":"Detroit",
    "sg:classifiers":[
        {
            "category":"Personal",
            "type":"Services"
        }
    ],
    "sg:phone":"+1 313 864 4212",
    "sg:postcode":"48235",
    "sg:province":"MI",
    "sg:tags":[
        "towing"
    ],
    "wof:name":"C & C Towing Service",
    "wof:placetype":"venue"
},
  "geometry": {"coordinates":[-83.19760100000001,42.437599],"type":"Point"}
}