{
  "type": "Feature",
  "properties": {
    "iso:country":"US",
    "sg:address":"850 N Crooks Rd",
    "sg:city":"Clawson",
    "sg:classifiers":[
        {
            "category":"Real Estate",
            "subcategory":"Real Estate Services",
            "type":"Services"
        },
        {
            "category":"Professional",
            "subcategory":"Management & Consulting",
            "type":"Services"
        }
    ],
    "sg:phone":"+1 248 655 1500",
    "sg:postcode":"48017",
    "sg:province":"MI",
    "sg:tags":[
        "property"
    ],
    "sg:website":"http://www.casabellamanagement.com",
    "wof:name":"Casa Bella Property Management",
    "wof:placetype":"venue"
},
  "geometry": {"coordinates":[-83.166011,42.539815],"type":"Point"}
}