{
  "type": "Feature",
  "properties": {
    "iso:country":"US",
    "sg:address":"2255 E Hill Rd",
    "sg:city":"Grand Blanc",
    "sg:classifiers":[
        {
            "category":"Restaurant",
            "type":"Food & Drink"
        }
    ],
    "sg:phone":"+1 810 695 9494",
    "sg:postcode":"48439",
    "sg:province":"MI",
    "sg:tags":[
        "pizza"
    ],
    "wof:name":"Champs Pizza",
    "wof:placetype":"venue"
},
  "geometry": {"coordinates":[-83.66130099999999,42.9445],"type":"Point"}
}