{
  "type": "Feature",
  "properties": {
    "iso:country":"US",
    "sg:address":"3660 Rochester Rd",
    "sg:city":"Troy",
    "sg:classifiers":[
        {
            "category":"Shopping",
            "subcategory":"Jewelry",
            "type":"Retail Goods"
        }
    ],
    "sg:phone":"+1 248 689 9145",
    "sg:postcode":"48083",
    "sg:province":"MI",
    "sg:tags":[
        "jeweler"
    ],
    "wof:name":"Gammo Jewelry",
    "wof:placetype":"venue"
},
  "geometry": {"coordinates":[-83.128057,42.572482],"type":"Point"}
}