{
  "type": "Feature",
  "properties": {
    "iso:country":"US",
    "sg:address":"2555 Burlingame Ave SW",
    "sg:city":"Wyoming",
    "sg:classifiers":[
        {
            "category":"Food & Beverages",
            "subcategory":"Candy",
            "type":"Retail Goods"
        }
    ],
    "sg:phone":"+1 616 724 2620",
    "sg:postcode":"49509",
    "sg:province":"MI",
    "sg:tags":[
        "confectionery"
    ],
    "sg:website":"www.koeze.com",
    "wof:name":"Koeze's",
    "wof:placetype":"venue"
},
  "geometry": {"coordinates":[-85.70538000000001,42.914671],"type":"Point"}
}