{
  "type": "Feature",
  "properties": {
    "iso:country":"US",
    "sg:address":"8306 Crescent Beach Rd",
    "sg:city":"Pigeon",
    "sg:classifiers":[
        {
            "category":"Professional",
            "subcategory":"Engineering",
            "type":"Services"
        }
    ],
    "sg:phone":"+1 989 856 3541",
    "sg:postcode":"48755",
    "sg:province":"MI",
    "wof:name":"Tuckey Engineering",
    "wof:placetype":"venue"
},
  "geometry": {"coordinates":[-83.33256299999999,43.914447],"type":"Point"}
}