{
  "type": "Feature",
  "properties": {
    "iso:country":"US",
    "sg:address":"1028 Hannah Ave",
    "sg:city":"Traverse City",
    "sg:classifiers":[
        {
            "category":"Real Estate",
            "subcategory":"Real Estate Agent",
            "type":"Services"
        }
    ],
    "sg:phone":"+1 231 922 9089",
    "sg:postcode":"49686",
    "sg:province":"MI",
    "wof:name":"Gary Vidor Realtor",
    "wof:placetype":"venue"
},
  "geometry": {"coordinates":[-85.597319,44.755043],"type":"Point"}
}