{
  "type": "Feature",
  "properties": {
    "iso:country":"US",
    "sg:address":"3384 Sussex Ct",
    "sg:city":"Rochester",
    "sg:classifiers":[
        {
            "category":"Organizations",
            "subcategory":"Labor Organization",
            "type":"Services"
        }
    ],
    "sg:phone":"+1 248 377 9477",
    "sg:postcode":"48306",
    "sg:province":"MI",
    "wof:name":"Klevermen Lc",
    "wof:placetype":"venue"
},
  "geometry": {"coordinates":[-83.203979,42.726052],"type":"Point"}
}