{
  "type": "Feature",
  "properties": {
    "iso:country":"US",
    "sg:address":"2725 Grovenburg Rd",
    "sg:city":"Lansing",
    "sg:classifiers":[
        {
            "category":"Retail",
            "subcategory":"Auto Repair",
            "type":"Services"
        }
    ],
    "sg:phone":"+1 517 394 3393",
    "sg:postcode":"48911",
    "sg:province":"MI",
    "sg:tags":[
        "general"
    ],
    "wof:name":"RR Repair",
    "wof:placetype":"venue"
},
  "geometry": {"coordinates":[-84.582627,42.661663],"type":"Point"}
}