{
  "type": "Feature",
  "properties": {
    "iso:country":"US",
    "sg:address":"46023 Heydenreich Rd",
    "sg:city":"Macomb",
    "sg:classifiers":[
        {
            "category":"Wholesale",
            "subcategory":"Stationery",
            "type":"Manufacturing & Wholesale Goods"
        }
    ],
    "sg:phone":"+1 586 412 9400",
    "sg:postcode":"48044",
    "sg:province":"MI",
    "sg:tags":[
        "business",
        "specialty",
        "form",
        "advertising"
    ],
    "wof:name":"Bee Line Bus Systems Advg Spc",
    "wof:placetype":"venue"
},
  "geometry": {"coordinates":[-82.916303,42.63512],"type":"Point"}
}