{
  "type": "Feature",
  "properties": {
    "iso:country":"US",
    "sg:address":"1917 N Vermont Ave",
    "sg:city":"Royal Oak",
    "sg:classifiers":[
        {
            "category":"Organizations",
            "subcategory":"Community Association",
            "type":"Services"
        }
    ],
    "sg:phone":"+1 248 545 1113",
    "sg:postcode":"48073",
    "sg:province":"MI",
    "wof:name":"Interntnal Assn of Lions Clubs",
    "wof:placetype":"venue"
},
  "geometry": {"coordinates":[-83.12931500000001,42.507075],"type":"Point"}
}