{
  "type": "Feature",
  "properties": {
    "iso:country":"US",
    "sg:address":"195 North Ave",
    "sg:city":"Battle Creek",
    "sg:classifiers":[
        {
            "category":"Health Services",
            "subcategory":"Doctor",
            "type":"Services"
        }
    ],
    "sg:phone":"+1 269 962 3297",
    "sg:postcode":"49017",
    "sg:province":"MI",
    "sg:tags":[
        "medical"
    ],
    "wof:name":"Acres & Woods Product Inc",
    "wof:placetype":"venue"
},
  "geometry": {"coordinates":[-85.180351,42.325918],"type":"Point"}
}