{
  "type": "Feature",
  "properties": {
    "iso:country":"US",
    "sg:address":"113 W Michigan Ave",
    "sg:city":"Augusta",
    "sg:classifiers":[
        {
            "category":"Food & Beverages",
            "subcategory":"Bakery",
            "type":"Retail Goods"
        }
    ],
    "sg:phone":"+1 269 731 3688",
    "sg:postcode":"49012",
    "sg:province":"MI",
    "sg:tags":[
        "doughnut"
    ],
    "wof:name":"Treats Donut & Deli",
    "wof:placetype":"venue"
},
  "geometry": {"coordinates":[-85.351918,42.335313],"type":"Point"}
}