{
  "type": "Feature",
  "properties": {
    "iso:country":"US",
    "sg:address":"19391 Connecticut St",
    "sg:city":"Roseville",
    "sg:classifiers":[
        {
            "category":"Building & Trades",
            "subcategory":"Plumbing",
            "type":"Services"
        }
    ],
    "sg:phone":"+1 586 774 0000",
    "sg:postcode":"48066",
    "sg:province":"MI",
    "sg:tags":[
        "air",
        "heating",
        "conditioning",
        "contractor"
    ],
    "wof:name":"Bullets Heating & Cooling",
    "wof:placetype":"venue"
},
  "geometry": {"coordinates":[-82.923767,42.511409],"type":"Point"}
}