{
  "type": "Feature",
  "properties": {
    "iso:country":"US",
    "sg:address":"6218 Ormada Dr",
    "sg:city":"Kalamazoo",
    "sg:classifiers":[
        {
            "category":"Recreation",
            "subcategory":"Arcade",
            "type":"Entertainment"
        }
    ],
    "sg:phone":"+1 269 344 8330",
    "sg:postcode":"49048",
    "sg:province":"MI",
    "sg:tags":[
        "device",
        "operator",
        "amusement"
    ],
    "wof:name":"Dino Bouncers Inc",
    "wof:placetype":"venue"
},
  "geometry": {"coordinates":[-85.510288,42.319343],"type":"Point"}
}