{
  "type": "Feature",
  "properties": {
    "iso:country":"US",
    "sg:address":"4309 Division Ave",
    "sg:city":"Wayland",
    "sg:classifiers":[
        {
            "category":"Building & Trades",
            "subcategory":"Construction",
            "type":"Services"
        }
    ],
    "sg:phone":"+1 616 877 4133",
    "sg:postcode":"49348",
    "sg:province":"MI",
    "sg:tags":[
        "house"
    ],
    "wof:name":"Rookus Builders Inc",
    "wof:placetype":"venue"
},
  "geometry": {"coordinates":[-85.653858,42.736806],"type":"Point"}
}