{
  "type": "Feature",
  "properties": {
    "iso:country":"US",
    "sg:address":"4408 W Pierson Rd",
    "sg:city":"Flint",
    "sg:classifiers":[
        {
            "category":"Restaurant",
            "type":"Food & Drink"
        }
    ],
    "sg:menulink":"http://www.allmenus.com/mi/mount-morris/196809-burger-king/menu/",
    "sg:phone":"+1 810 732 4470",
    "sg:postcode":"48504",
    "sg:province":"MI",
    "sg:tags":[
        "burger",
        "american"
    ],
    "wof:name":"Burger King",
    "wof:placetype":"venue"
},
  "geometry": {"coordinates":[-83.768417,43.060732],"type":"Point"}
}