{
  "type": "Feature",
  "properties": {
    "iso:country":"US",
    "sg:address":"37566 Agar Dr",
    "sg:city":"Sterling Heights",
    "sg:classifiers":[
        {
            "category":"Professional",
            "subcategory":"Computer Services",
            "type":"Services"
        }
    ],
    "sg:phone":"+1 586 264 3106",
    "sg:postcode":"48310",
    "sg:province":"MI",
    "sg:tags":[
        "development",
        "software"
    ],
    "wof:name":"Clinecta LLC",
    "wof:placetype":"venue"
},
  "geometry": {"coordinates":[-83.076205,42.56893],"type":"Point"}
}