{
  "type": "Feature",
  "properties": {
    "iso:country":"US",
    "sg:address":"24615 Halsted Rd",
    "sg:city":"Farmington Hills",
    "sg:classifiers":[
        {
            "category":"Shopping",
            "subcategory":"Computers & Home Electronics",
            "type":"Retail Goods"
        }
    ],
    "sg:phone":"+1 248 615 9124",
    "sg:postcode":"48335",
    "sg:province":"MI",
    "sg:tags":[
        "equipment",
        "dealer"
    ],
    "wof:name":"Sun Data Corp",
    "wof:placetype":"venue"
},
  "geometry": {"coordinates":[-83.41585000000001,42.47002],"type":"Point"}
}