{
  "type": "Feature",
  "properties": {
    "iso:country":"US",
    "sg:address":"1565 Pyle Dr",
    "sg:city":"Kingsford",
    "sg:classifiers":[
        {
            "category":"Building & Trades",
            "subcategory":"Plumbing",
            "type":"Services"
        }
    ],
    "sg:phone":"+1 906 774 1631",
    "sg:postcode":"49802",
    "sg:province":"MI",
    "sg:tags":[
        "heating",
        "contractor"
    ],
    "wof:name":"Universal Plumbing-Heating AC",
    "wof:placetype":"venue"
},
  "geometry": {"coordinates":[-88.088381,45.80401],"type":"Point"}
}