{
  "type": "Feature",
  "properties": {
    "iso:country":"US",
    "sg:address":"2004 Hogback Rd",
    "sg:city":"Ann Arbor",
    "sg:classifiers":[
        {
            "category":"Health Services",
            "subcategory":"Doctor",
            "type":"Services"
        }
    ],
    "sg:phone":"+1 734 677 0809",
    "sg:postcode":"48105",
    "sg:province":"MI",
    "wof:name":"Center For Behavior & Medicine",
    "wof:placetype":"venue"
},
  "geometry": {"coordinates":[-83.68086700000001,42.25636],"type":"Point"}
}