{
  "type": "Feature",
  "properties": {
    "iso:country":"US",
    "sg:address":"1162 E 9 Mile Rd",
    "sg:city":"Hazel Park",
    "sg:classifiers":[
        {
            "category":"Personal",
            "subcategory":"Beauty Salon",
            "type":"Services"
        }
    ],
    "sg:phone":"+1 248 546 7670",
    "sg:postcode":"48030",
    "sg:province":"MI",
    "wof:name":"Great Clips",
    "wof:placetype":"venue"
},
  "geometry": {"coordinates":[-83.09378599999999,42.46154],"type":"Point"}
}