{
  "type": "Feature",
  "properties": {
    "iso:country":"US",
    "sg:address":"8560 Centre Industrial Dr SW",
    "sg:city":"Byron Center",
    "sg:classifiers":[
        {
            "category":"Wholesale",
            "subcategory":"Electrical",
            "type":"Manufacturing & Wholesale Goods"
        }
    ],
    "sg:phone":"+1 616 583 1681",
    "sg:postcode":"49315",
    "sg:province":"MI",
    "sg:tags":[
        "equipment",
        "electric",
        "supply"
    ],
    "wof:name":"Matic Electro",
    "wof:placetype":"venue"
},
  "geometry": {"coordinates":[-85.68907,42.81014],"type":"Point"}
}