{
  "type": "Feature",
  "properties": {
    "iso:country":"US",
    "sg:address":"144 Avon Dr",
    "sg:city":"Battle Creek",
    "sg:classifiers":[
        {
            "category":"Professional",
            "subcategory":"Computer Services",
            "type":"Services"
        }
    ],
    "sg:phone":"+1 269 965 1805",
    "sg:postcode":"49037",
    "sg:province":"MI",
    "sg:tags":[
        "datum"
    ],
    "wof:name":"Battle Creek Web Design",
    "wof:placetype":"venue"
},
  "geometry": {"coordinates":[-85.70918899999999,42.723023],"type":"Point"}
}