{
  "type": "Feature",
  "properties": {
    "iso:country":"US",
    "sg:address":"509 W Washington St",
    "sg:city":"Marquette",
    "sg:classifiers":[
        {
            "category":"Manufacturing",
            "subcategory":"Apparel",
            "type":"Manufacturing & Wholesale Goods"
        }
    ],
    "sg:phone":"+1 906 225 5532",
    "sg:postcode":"49855",
    "sg:province":"MI",
    "sg:tags":[
        "sewing",
        "contractor"
    ],
    "wof:name":"Superior Sewing",
    "wof:placetype":"venue"
},
  "geometry": {"coordinates":[-87.403921,46.544756],"type":"Point"}
}