{
  "type": "Feature",
  "properties": {
    "iso:country":"US",
    "sg:address":"2225 Argentina Dr SE",
    "sg:city":"Grand Rapids",
    "sg:classifiers":[
        {
            "category":"Professional",
            "subcategory":"Art Services",
            "type":"Services"
        }
    ],
    "sg:phone":"+1 616 452 0905",
    "sg:postcode":"49506",
    "sg:province":"MI",
    "sg:tags":[
        "photography",
        "commercial"
    ],
    "wof:name":"Tippett Jeff Photog",
    "wof:placetype":"venue"
},
  "geometry": {"coordinates":[-85.613697,42.944713],"type":"Point"}
}