{
  "type": "Feature",
  "properties": {
    "iso:country":"US",
    "sg:address":"12991 US Hwy 31",
    "sg:city":"Bear Lake",
    "sg:classifiers":[
        {
            "category":"Food & Beverages",
            "subcategory":"Groceries & Convenience Stores",
            "type":"Retail Goods"
        }
    ],
    "sg:phone":"+1 231 864 3060",
    "sg:postcode":"49614",
    "sg:province":"MI",
    "wof:name":"Saddle Up Gas & Grocery",
    "wof:placetype":"venue"
},
  "geometry": {"coordinates":[-86.126451,44.436843],"type":"Point"}
}