{
  "type": "Feature",
  "properties": {
    "iso:country":"US",
    "sg:address":"6785 Keigley Rd",
    "sg:city":"Eau Claire",
    "sg:phone":"+1 269 461 6210",
    "sg:postcode":"49111",
    "sg:province":"MI",
    "sg:tags":[
        "farm",
        "soybean"
    ],
    "wof:name":"Nelson Layman",
    "wof:placetype":"venue"
},
  "geometry": {"coordinates":[-86.29278499999999,41.999814],"type":"Point"}
}