{
  "type": "Feature",
  "properties": {
    "iso:country":"US",
    "sg:address":"28475 Walnut Crk",
    "sg:city":"Flat Rock",
    "sg:classifiers":[
        {
            "category":"Real Estate",
            "subcategory":"Real Estate Operator",
            "type":"Services"
        }
    ],
    "sg:phone":"+1 734 782 3070",
    "sg:postcode":"48134",
    "sg:province":"MI",
    "sg:tags":[
        "apartment"
    ],
    "wof:name":"Walnut Creek Apts",
    "wof:placetype":"venue"
},
  "geometry": {"coordinates":[-83.264397,42.0839],"type":"Point"}
}