{
  "type": "Feature",
  "properties": {
    "iso:country":"US",
    "sg:address":"20151 Telegraph Rd",
    "sg:city":"Romulus",
    "sg:classifiers":[
        {
            "category":"Personal",
            "subcategory":"Tattoo Parlor",
            "type":"Services"
        }
    ],
    "sg:phone":"+1 734 479 2420",
    "sg:postcode":"48174",
    "sg:province":"MI",
    "wof:name":"Liquid Chaos",
    "wof:placetype":"venue"
},
  "geometry": {"coordinates":[-83.266293,42.158455],"type":"Point"}
}