{
  "type": "Feature",
  "properties": {
    "iso:country":"US",
    "sg:address":"20793 Farmington Rd",
    "sg:city":"Farmington",
    "sg:classifiers":[
        {
            "category":"Health Services",
            "subcategory":"Doctor",
            "type":"Services"
        }
    ],
    "sg:phone":"+1 248 426 0079",
    "sg:postcode":"48336",
    "sg:province":"MI",
    "sg:tags":[
        "clinic"
    ],
    "wof:name":"Bridgewood Clinic",
    "wof:placetype":"venue"
},
  "geometry": {"coordinates":[-83.37551499999999,42.440666],"type":"Point"}
}