{
  "type": "Feature",
  "properties": {
    "iso:country":"US",
    "sg:address":"3700 Patterson Ave SE",
    "sg:city":"Grand Rapids",
    "sg:classifiers":[
        {
            "category":"Building & Trades",
            "subcategory":"Plumbing",
            "type":"Services"
        }
    ],
    "sg:phone":"+1 616 949 0500",
    "sg:postcode":"49512",
    "sg:province":"MI",
    "sg:tags":[
        "boiler",
        "cleaning"
    ],
    "sg:website":"www.viersonboiler.com",
    "wof:name":"Vierson Boiler & Repair Co",
    "wof:placetype":"venue"
},
  "geometry": {"coordinates":[-85.54773400000001,42.895165],"type":"Point"}
}