{
  "type": "Feature",
  "properties": {
    "iso:country":"US",
    "sg:address":"607 S Putnam St",
    "sg:city":"Williamston",
    "sg:classifiers":[
        {
            "category":"Building & Trades",
            "subcategory":"Landscaping Services",
            "type":"Services"
        }
    ],
    "sg:phone":"+1 517 655 5554",
    "sg:postcode":"48895",
    "sg:province":"MI",
    "sg:tags":[
        "lawn"
    ],
    "wof:name":"Bacons Lawn Care",
    "wof:placetype":"venue"
},
  "geometry": {"coordinates":[-84.282865,42.685009],"type":"Point"}
}