{
  "type": "Feature",
  "properties": {
    "iso:country":"US",
    "sg:address":"3519 2nd Ave",
    "sg:city":"Spring Arbor",
    "sg:classifiers":[
        {
            "category":"Wholesale",
            "subcategory":"Construction Materials",
            "type":"Manufacturing & Wholesale Goods"
        }
    ],
    "sg:phone":"+1 517 750 7501",
    "sg:postcode":"49283",
    "sg:province":"MI",
    "sg:tags":[
        "pallet",
        "skid"
    ],
    "wof:name":"H & S Svc Co",
    "wof:placetype":"venue"
},
  "geometry": {"coordinates":[-84.548419,42.208975],"type":"Point"}
}