{
  "type": "Feature",
  "properties": {
    "iso:country":"US",
    "sg:address":"11306 S Saginaw St",
    "sg:city":"Grand Blanc",
    "sg:classifiers":[
        {
            "category":"Building & Trades",
            "subcategory":"Construction",
            "type":"Services"
        }
    ],
    "sg:phone":"+1 810 695 6680",
    "sg:postcode":"48439",
    "sg:province":"MI",
    "sg:tags":[
        "pond",
        "supply"
    ],
    "wof:name":"Aqua Creations Pond Supplies",
    "wof:placetype":"venue"
},
  "geometry": {"coordinates":[-83.63241600000001,42.929206],"type":"Point"}
}