{
  "type": "Feature",
  "properties": {
    "iso:country":"US",
    "sg:address":"15113 E Erie Rd",
    "sg:city":"Albion",
    "sg:classifiers":[
        {
            "category":"Farming",
            "subcategory":"Farm",
            "type":"Manufacturing & Wholesale Goods"
        }
    ],
    "sg:phone":"+1 517 629 6080",
    "sg:postcode":"49224",
    "sg:province":"MI",
    "sg:tags":[
        "crop",
        "general"
    ],
    "wof:name":"Boehlke Farm",
    "wof:placetype":"venue"
},
  "geometry": {"coordinates":[-84.682453,42.246879],"type":"Point"}
}