{
  "type": "Feature",
  "properties": {
    "iso:country":"US",
    "sg:address":"2616 Niles Ave",
    "sg:city":"St Joseph",
    "sg:classifiers":[
        {
            "category":"Shopping",
            "subcategory":"Clothing, Apparel, & Fashions",
            "type":"Retail Goods"
        }
    ],
    "sg:phone":"+1 269 983 5235",
    "sg:postcode":"49085",
    "sg:province":"MI",
    "wof:name":"Dotty's Chapeaux Boutique",
    "wof:placetype":"venue"
},
  "geometry": {"coordinates":[-86.485384,42.087171],"type":"Point"}
}