{
  "type": "Feature",
  "properties": {
    "iso:country":"US",
    "sg:address":"19693 Washtenaw St",
    "sg:city":"Harper Woods",
    "sg:classifiers":[
        {
            "category":"Building & Trades",
            "subcategory":"Construction",
            "type":"Services"
        }
    ],
    "sg:phone":"+1 313 372 9349",
    "sg:postcode":"48225",
    "sg:province":"MI",
    "sg:tags":[
        "contractor"
    ],
    "wof:name":"B&C Custom Ceramic Tile",
    "wof:placetype":"venue"
},
  "geometry": {"coordinates":[-82.937518,42.431227],"type":"Point"}
}