{
  "type": "Feature",
  "properties": {
    "iso:country":"US",
    "sg:address":"1425 Pine Grove Ave",
    "sg:city":"Port Huron",
    "sg:classifiers":[
        {
            "category":"Personal",
            "subcategory":"Beauty Salon",
            "type":"Services"
        }
    ],
    "sg:phone":"+1 810 982 5485",
    "sg:postcode":"48060",
    "sg:province":"MI",
    "wof:name":"Blondie's Hair Salon",
    "wof:placetype":"venue"
},
  "geometry": {"coordinates":[-82.42993300000001,42.989338],"type":"Point"}
}