{
  "type": "Feature",
  "properties": {
    "iso:country":"US",
    "sg:address":"14300 Lakeside Cir",
    "sg:city":"Sterling Heights",
    "sg:classifiers":[
        {
            "category":"Shopping",
            "subcategory":"Optician",
            "type":"Retail Goods"
        }
    ],
    "sg:phone":"+1 586 247 9220",
    "sg:postcode":"48313",
    "sg:province":"MI",
    "sg:tags":[
        "eyewear"
    ],
    "wof:name":"Jc Penney Optical Center",
    "wof:placetype":"venue"
},
  "geometry": {"coordinates":[-82.983498,42.620098],"type":"Point"}
}