{
  "type": "Feature",
  "properties": {
    "iso:country":"US",
    "sg:address":"28901 Groesbeck Hwy",
    "sg:city":"Roseville",
    "sg:classifiers":[
        {
            "category":"Restaurant",
            "type":"Food & Drink"
        }
    ],
    "sg:menulink":"http://www.allmenus.com/mi/roseville/23988-national-coney-island/menu/",
    "sg:phone":"+1 586 772 1324",
    "sg:postcode":"48066",
    "sg:province":"MI",
    "sg:tags":[
        "american"
    ],
    "wof:name":"National Coney Island",
    "wof:placetype":"venue"
},
  "geometry": {"coordinates":[-82.958437,42.508208],"type":"Point"}
}