{
  "type": "Feature",
  "properties": {
    "iso:country":"US",
    "sg:address":"145 W Genesee St",
    "sg:city":"Frankenmuth",
    "sg:classifiers":[
        {
            "category":"Professional",
            "subcategory":"Lawyer & Legal Services",
            "type":"Services"
        }
    ],
    "sg:phone":"+1 989 652 9240",
    "sg:postcode":"48734",
    "sg:province":"MI",
    "sg:tags":[
        "attorney"
    ],
    "wof:name":"Julie A Gafkay Law Office",
    "wof:placetype":"venue"
},
  "geometry": {"coordinates":[-83.73936399999999,43.335752],"type":"Point"}
}