{
  "type": "Feature",
  "properties": {
    "iso:country":"US",
    "sg:address":"1927 Rosa Parks Blvd",
    "sg:city":"Detroit",
    "sg:classifiers":[
        {
            "category":"Professional",
            "subcategory":"Employment Agencies",
            "type":"Services"
        }
    ],
    "sg:phone":"+1 313 965 4756",
    "sg:postcode":"48216",
    "sg:province":"MI",
    "sg:tags":[
        "temporary",
        "for",
        "general"
    ],
    "wof:name":"Staffing Connection",
    "wof:placetype":"venue"
},
  "geometry": {"coordinates":[-83.07064800000001,42.329218],"type":"Point"}
}