{
  "type": "Feature",
  "properties": {
    "iso:country":"US",
    "sg:address":"1720 W Sterns Rd",
    "sg:city":"Temperance",
    "sg:classifiers":[
        {
            "category":"Personal",
            "subcategory":"Beauty Salon",
            "type":"Services"
        }
    ],
    "sg:phone":"+1 734 856 6312",
    "sg:postcode":"48182",
    "sg:province":"MI",
    "sg:website":"www.terrariumhairspa.com",
    "wof:name":"Terrarium Hair Salon",
    "wof:placetype":"venue"
},
  "geometry": {"coordinates":[-83.58691399999999,41.750112],"type":"Point"}
}