{
  "type": "Feature",
  "properties": {
    "iso:country":"US",
    "sg:address":"228 W Railway St",
    "sg:city":"Coleman",
    "sg:classifiers":[
        {
            "category":"Restaurant",
            "type":"Food & Drink"
        }
    ],
    "sg:phone":"+1 989 465 6021",
    "sg:postcode":"48618",
    "sg:province":"MI",
    "sg:tags":[
        "parlor",
        "ice",
        "cream"
    ],
    "wof:name":"Kay's",
    "wof:placetype":"venue"
},
  "geometry": {"coordinates":[-84.591489,43.758828],"type":"Point"}
}