{
  "type": "Feature",
  "properties": {
    "iso:country":"US",
    "sg:address":"708 Liberty St",
    "sg:city":"Spring Lake",
    "sg:classifiers":[
        {
            "category":"Building & Trades",
            "subcategory":"Construction",
            "type":"Services"
        }
    ],
    "sg:phone":"+1 616 847 6415",
    "sg:postcode":"49456",
    "sg:province":"MI",
    "sg:tags":[
        "general",
        "contractor"
    ],
    "wof:name":"Koster Steigenga Construction",
    "wof:placetype":"venue"
},
  "geometry": {"coordinates":[-86.20601000000001,43.077747],"type":"Point"}
}