{
  "type": "Feature",
  "properties": {
    "iso:country":"US",
    "sg:address":"15170 Telegraph Rd",
    "sg:city":"Redford",
    "sg:classifiers":[
        {
            "category":"Restaurant",
            "type":"Food & Drink"
        }
    ],
    "sg:menulink":"http://www.allmenus.com/mi/redford/182184-wendys/menu/",
    "sg:phone":"+1 313 592 1142",
    "sg:postcode":"48239",
    "sg:province":"MI",
    "sg:tags":[
        "burger",
        "american",
        "soup"
    ],
    "wof:name":"Wendy's",
    "wof:placetype":"venue"
},
  "geometry": {"coordinates":[-83.276427,42.399108],"type":"Point"}
}