{
  "type": "Feature",
  "properties": {
    "iso:country":"US",
    "sg:address":"4410 S Westnedge Ave",
    "sg:city":"Kalamazoo",
    "sg:classifiers":[
        {
            "category":"Professional",
            "subcategory":"Accounting & Tax Preparation",
            "type":"Services"
        }
    ],
    "sg:phone":"+1 269 343 8005",
    "sg:postcode":"49008",
    "sg:province":"MI",
    "sg:tags":[
        "return",
        "filing"
    ],
    "wof:name":"Jackson Hewitt Tax Svc",
    "wof:placetype":"venue"
},
  "geometry": {"coordinates":[-85.589704,42.245686],"type":"Point"}
}