{
  "type": "Feature",
  "properties": {
    "iso:country":"US",
    "sg:address":"16837 Kercheval St",
    "sg:city":"Grosse Pointe",
    "sg:classifiers":[
        {
            "category":"Shopping",
            "subcategory":"Stationery & Office Supplies",
            "type":"Retail Goods"
        }
    ],
    "sg:phone":"+1 313 884 6880",
    "sg:postcode":"48230",
    "sg:province":"MI",
    "sg:tags":[
        "equipment"
    ],
    "wof:name":"Cavanaugh's Office Supply and Gifts",
    "wof:placetype":"venue"
},
  "geometry": {"coordinates":[-82.917801,42.389702],"type":"Point"}
}