{
  "type": "Feature",
  "properties": {
    "iso:country":"US",
    "sg:address":"7250 S 40th St",
    "sg:city":"Climax",
    "sg:classifiers":[
        {
            "category":"Travel",
            "subcategory":"Campground",
            "type":"Entertainment"
        }
    ],
    "sg:phone":"+1 269 746 4101",
    "sg:postcode":"49034",
    "sg:province":"MI",
    "sg:tags":[
        "consulting",
        "management",
        "trailer"
    ],
    "wof:name":"Timberlake Campground",
    "wof:placetype":"venue"
},
  "geometry": {"coordinates":[-85.374038,42.201719],"type":"Point"}
}