{
  "type": "Feature",
  "properties": {
    "iso:country":"US",
    "sg:address":"592 University Dr",
    "sg:city":"Pontiac",
    "sg:classifiers":[
        {
            "category":"Personal",
            "type":"Services"
        }
    ],
    "sg:phone":"+1 248 333 7009",
    "sg:postcode":"48342",
    "sg:province":"MI",
    "sg:tags":[
        "consultant",
        "program",
        "health",
        "fitness"
    ],
    "wof:name":"Twril A Cize",
    "wof:placetype":"venue"
},
  "geometry": {"coordinates":[-83.2735,42.647167],"type":"Point"}
}