{
  "type": "Feature",
  "properties": {
    "iso:country":"US",
    "sg:address":"110 Sanborn Ave",
    "sg:city":"Big Rapids",
    "sg:classifiers":[
        {
            "category":"Insurance",
            "subcategory":"Insurance Agent",
            "type":"Services"
        }
    ],
    "sg:phone":"+1 231 592 8050",
    "sg:postcode":"49307",
    "sg:province":"MI",
    "wof:name":"AFLAC",
    "wof:placetype":"venue"
},
  "geometry": {"coordinates":[-85.486633,43.695707],"type":"Point"}
}