{
  "type": "Feature",
  "properties": {
    "iso:country":"US",
    "sg:address":"10182 Munro Lake Dr",
    "sg:city":"Levering",
    "sg:classifiers":[
        {
            "category":"Building & Trades",
            "subcategory":"Construction",
            "type":"Services"
        }
    ],
    "sg:phone":"+1 231 537 2421",
    "sg:postcode":"49755",
    "sg:province":"MI",
    "sg:tags":[
        "tile",
        "dealer"
    ],
    "wof:name":"Buehler Ceramic Tile Inc",
    "wof:placetype":"venue"
},
  "geometry": {"coordinates":[-84.677938,45.602605],"type":"Point"}
}