{
  "type": "Feature",
  "properties": {
    "iso:country":"US",
    "sg:address":"78 Beechwoode Ln",
    "sg:city":"Pontiac",
    "sg:classifiers":[
        {
            "category":"Retail",
            "subcategory":"Repair Shop",
            "type":"Services"
        }
    ],
    "sg:phone":"+1 248 373 6359",
    "sg:postcode":"48340",
    "sg:province":"MI",
    "wof:name":"Harris Cleaning",
    "wof:placetype":"venue"
},
  "geometry": {"coordinates":[-83.25659,42.676898],"type":"Point"}
}