{
  "type": "Feature",
  "properties": {
    "iso:country":"US",
    "sg:address":"317 E 11 Mile Rd",
    "sg:city":"Royal Oak",
    "sg:classifiers":[
        {
            "category":"Health Services",
            "subcategory":"Clinic",
            "type":"Services"
        },
        {
            "category":"Health Services",
            "subcategory":"Health Practitioner",
            "type":"Services"
        }
    ],
    "sg:phone":"+1 248 414 4050",
    "sg:postcode":"48067",
    "sg:province":"MI",
    "sg:tags":[
        "psychologist",
        "specialty",
        "outpatient"
    ],
    "wof:name":"Center For Creative Living Inc",
    "wof:placetype":"venue"
},
  "geometry": {"coordinates":[-83.13991799999999,42.490007],"type":"Point"}
}