{
  "type": "Feature",
  "properties": {
    "iso:country":"US",
    "sg:address":"4500 Arline Dr",
    "sg:city":"West Bloomfield",
    "sg:classifiers":[
        {
            "category":"Social Services",
            "subcategory":"Child Care",
            "type":"Services"
        },
        {
            "category":"Education",
            "subcategory":"Preschool",
            "type":"Public Place"
        },
        {
            "category":"Education",
            "subcategory":"School",
            "type":"Public Place"
        }
    ],
    "sg:phone":"+1 248 682 0110",
    "sg:postcode":"48323",
    "sg:province":"MI",
    "sg:tags":[
        "elementary",
        "day"
    ],
    "wof:name":"Whitney Bloomfield Nursery & Kindergarten",
    "wof:placetype":"venue"
},
  "geometry": {"coordinates":[-83.37550400000001,42.5714],"type":"Point"}
}