{
  "type": "Feature",
  "properties": {
    "iso:country":"US",
    "sg:address":"15228 Wyoming St",
    "sg:city":"Detroit",
    "sg:classifiers":[
        {
            "category":"Restaurant",
            "type":"Food & Drink"
        }
    ],
    "sg:menulink":"http://www.allmenus.com/mi/detroit/247297-china-garden/menu/",
    "sg:phone":"+1 313 933 3686",
    "sg:postcode":"48238",
    "sg:province":"MI",
    "sg:tags":[
        "asian",
        "chinese"
    ],
    "wof:name":"China Garden",
    "wof:placetype":"venue"
},
  "geometry": {"coordinates":[-83.159656,42.402217],"type":"Point"}
}