{
  "type": "Feature",
  "properties": {
    "iso:country":"US",
    "sg:address":"756 W Michigan Ave",
    "sg:city":"Jackson",
    "sg:classifiers":[
        {
            "category":"Organizations",
            "subcategory":"Religious Organization",
            "type":"Services"
        }
    ],
    "sg:phone":"+1 517 796 5670",
    "sg:postcode":"49201",
    "sg:province":"MI",
    "sg:tags":[
        "house",
        "retreat"
    ],
    "wof:name":"Cottage Retreat Ctr",
    "wof:placetype":"venue"
},
  "geometry": {"coordinates":[-84.42031299999999,42.247493],"type":"Point"}
}