{
  "type": "Feature",
  "properties": {
    "iso:country":"US",
    "sg:address":"10555 Stoney Point Dr",
    "sg:city":"Delton",
    "sg:classifiers":[
        {
            "category":"Health Services",
            "subcategory":"Doctor",
            "type":"Services"
        }
    ],
    "sg:phone":"+1 269 623 3355",
    "sg:postcode":"49046",
    "sg:province":"MI",
    "sg:tags":[
        "dentist"
    ],
    "wof:name":"Mike Merda DDS",
    "wof:placetype":"venue"
},
  "geometry": {"coordinates":[-85.42265,42.498835],"type":"Point"}
}