{
  "type": "Feature",
  "properties": {
    "iso:country":"US",
    "sg:address":"2503 Jackson Ave",
    "sg:city":"Ann Arbor",
    "sg:classifiers":[
        {
            "category":"Education",
            "subcategory":"Library",
            "type":"Public Place"
        }
    ],
    "sg:phone":"+1 734 994 1674",
    "sg:postcode":"48103",
    "sg:province":"MI",
    "wof:name":"West Branch Library",
    "wof:placetype":"venue"
},
  "geometry": {"coordinates":[-83.782121,42.280778],"type":"Point"}
}