{
  "type": "Feature",
  "properties": {
    "iso:country":"US",
    "sg:address":"1550 Cramton Ave NE",
    "sg:city":"Ada",
    "sg:classifiers":[
        {
            "category":"Professional",
            "subcategory":"Management & Consulting",
            "type":"Services"
        }
    ],
    "sg:phone":"+1 616 676 5000",
    "sg:postcode":"49301",
    "sg:province":"MI",
    "sg:tags":[
        "business"
    ],
    "wof:name":"Powell International Inc",
    "wof:placetype":"venue"
},
  "geometry": {"coordinates":[-85.49086699999999,42.989891],"type":"Point"}
}