{
  "type": "Feature",
  "properties": {
    "iso:country":"US",
    "sg:address":"111 N Lincoln Rd",
    "sg:city":"Escanaba",
    "sg:classifiers":[
        {
            "category":"Travel",
            "subcategory":"Travel Agent",
            "type":"Entertainment"
        }
    ],
    "sg:phone":"+1 906 789 0800",
    "sg:postcode":"49829",
    "sg:province":"MI",
    "sg:tags":[
        "agency",
        "bureau"
    ],
    "wof:name":"Holiday Travel & Cruise",
    "wof:placetype":"venue"
},
  "geometry": {"coordinates":[-87.079784,45.746728],"type":"Point"}
}