{
  "type": "Feature",
  "properties": {
    "iso:country":"US",
    "sg:address":"40400 Production Dr",
    "sg:city":"Harrison Twp",
    "sg:classifiers":[
        {
            "category":"Building & Trades",
            "subcategory":"Construction",
            "type":"Services"
        }
    ],
    "sg:phone":"+1 586 307 8560",
    "sg:postcode":"48045",
    "sg:province":"MI",
    "sg:tags":[
        "home",
        "improvement"
    ],
    "wof:name":"Northview Cabinets & Tops Inc",
    "wof:placetype":"venue"
},
  "geometry": {"coordinates":[-82.853697,42.595317],"type":"Point"}
}