{
  "type": "Feature",
  "properties": {
    "iso:country":"US",
    "sg:address":"1168 Capac Rd",
    "sg:city":"Berlin",
    "sg:classifiers":[
        {
            "category":"Farming",
            "subcategory":"Farm",
            "type":"Manufacturing & Wholesale Goods"
        }
    ],
    "sg:phone":"+1 810 395 8152",
    "sg:postcode":"48002",
    "sg:province":"MI",
    "wof:name":"Jake's Place",
    "wof:placetype":"venue"
},
  "geometry": {"coordinates":[-82.945644,42.929513],"type":"Point"}
}