{
  "type": "Feature",
  "properties": {
    "iso:country":"US",
    "sg:address":"810 Highland Ave",
    "sg:city":"St Joseph",
    "sg:classifiers":[
        {
            "category":"Shopping",
            "type":"Retail Goods"
        }
    ],
    "sg:phone":"+1 269 983 1500",
    "sg:postcode":"49085",
    "sg:province":"MI",
    "sg:tags":[
        "pet",
        "food",
        "supply"
    ],
    "wof:name":"Biscuits Pet Ctr",
    "wof:placetype":"venue"
},
  "geometry": {"coordinates":[-86.48277299999999,42.085276],"type":"Point"}
}