{
  "type": "Feature",
  "properties": {
    "iso:country":"US",
    "sg:address":"1355 N Leroy St",
    "sg:city":"Fenton",
    "sg:classifiers":[
        {
            "category":"Restaurant",
            "type":"Food & Drink"
        }
    ],
    "sg:menulink":"http://www.allmenus.com/mi/fenton/196800-burger-king/menu/",
    "sg:phone":"+1 810 629 0930",
    "sg:postcode":"48430",
    "sg:province":"MI",
    "sg:tags":[
        "burger",
        "american"
    ],
    "wof:name":"Burger King",
    "wof:placetype":"venue"
},
  "geometry": {"coordinates":[-83.707498,42.814151],"type":"Point"}
}