{
  "type": "Feature",
  "properties": {
    "iso:country":"US",
    "sg:address":"8888 Whittaker Rd",
    "sg:city":"Ypsilanti",
    "sg:classifiers":[
        {
            "category":"Education",
            "subcategory":"School",
            "type":"Public Place"
        }
    ],
    "sg:phone":"+1 734 484 7061",
    "sg:postcode":"48197",
    "sg:province":"MI",
    "sg:website":"www.lincoln.k12.mi.us",
    "wof:name":"Redner Elementary School",
    "wof:placetype":"venue"
},
  "geometry": {"coordinates":[-83.60140699999999,42.171446],"type":"Point"}
}