{
  "type": "Feature",
  "properties": {
    "iso:country":"US",
    "sg:address":"900 Jackson St",
    "sg:city":"Grand Haven",
    "sg:classifiers":[
        {
            "category":"Home & Garden",
            "subcategory":"Building Materials",
            "type":"Retail Goods"
        }
    ],
    "sg:phone":"+1 616 850 8401",
    "sg:postcode":"49417",
    "sg:province":"MI",
    "sg:tags":[
        "center"
    ],
    "wof:name":"Home Depot",
    "wof:placetype":"venue"
},
  "geometry": {"coordinates":[-86.22035,43.066697],"type":"Point"}
}