{
  "type": "Feature",
  "properties": {
    "iso:country":"US",
    "sg:address":"1100 Rosewood St",
    "sg:city":"Ann Arbor",
    "sg:classifiers":[
        {
            "category":"Retail",
            "subcategory":"Auto Repair",
            "type":"Services"
        }
    ],
    "sg:phone":"+1 734 994 0447",
    "sg:postcode":"48104",
    "sg:province":"MI",
    "sg:tags":[
        "body",
        "shop"
    ],
    "wof:name":"Westside Body Repair Inc",
    "wof:placetype":"venue"
},
  "geometry": {"coordinates":[-83.732387,42.254929],"type":"Point"}
}