{
  "type": "Feature",
  "properties": {
    "iso:country":"US",
    "sg:address":"36261 Saint Clair Dr",
    "sg:city":"New Baltimore",
    "sg:classifiers":[
        {
            "category":"Building & Trades",
            "subcategory":"Construction",
            "type":"Services"
        }
    ],
    "sg:phone":"+1 586 725 9380",
    "sg:postcode":"48047",
    "sg:province":"MI",
    "sg:tags":[
        "painter"
    ],
    "wof:name":"Sunny Mountain Painting",
    "wof:placetype":"venue"
},
  "geometry": {"coordinates":[-82.739785,42.698052],"type":"Point"}
}