{
  "type": "Feature",
  "properties": {
    "iso:country":"US",
    "sg:address":"629 Ionia Ave SW",
    "sg:city":"Grand Rapids",
    "sg:classifiers":[
        {
            "category":"Manufacturing",
            "subcategory":"Motor Vehicles & Parts",
            "type":"Manufacturing & Wholesale Goods"
        }
    ],
    "sg:phone":"+1 616 456 9928",
    "sg:postcode":"49503",
    "sg:province":"MI",
    "sg:tags":[
        "automobile",
        "supply"
    ],
    "sg:website":"www.excellenceusa.com",
    "wof:name":"Excellence Manufacturing Co",
    "wof:placetype":"venue"
},
  "geometry": {"coordinates":[-85.670096,42.950647],"type":"Point"}
}