{
  "type": "Feature",
  "properties": {
    "iso:country":"US",
    "sg:address":"3084 Vineland Ave",
    "sg:city":"Burton",
    "sg:classifiers":[
        {
            "category":"Social Services",
            "subcategory":"Child Care",
            "type":"Services"
        }
    ],
    "sg:phone":"+1 810 743 7555",
    "sg:postcode":"48519",
    "sg:province":"MI",
    "sg:tags":[
        "day"
    ],
    "wof:name":"Kathryns Kuddle N Care",
    "wof:placetype":"venue"
},
  "geometry": {"coordinates":[-83.57726599999999,42.98929],"type":"Point"}
}