{
  "type": "Feature",
  "properties": {
    "iso:country":"US",
    "sg:address":"3416 S Westnedge Ave",
    "sg:city":"Kalamazoo",
    "sg:classifiers":[
        {
            "category":"Shopping",
            "subcategory":"Clothing, Apparel, & Fashions",
            "type":"Retail Goods"
        }
    ],
    "sg:phone":"+1 269 382 1900",
    "sg:postcode":"49008",
    "sg:province":"MI",
    "sg:tags":[
        "navy",
        "army"
    ],
    "wof:name":"Young's Army-Navy Surplus",
    "wof:placetype":"venue"
},
  "geometry": {"coordinates":[-85.589691,42.257475],"type":"Point"}
}