{
  "type": "Feature",
  "properties": {
    "iso:country":"US",
    "sg:address":"600 E Ayer St",
    "sg:city":"Ironwood",
    "sg:classifiers":[
        {
            "category":"Shopping",
            "subcategory":"Used Merchandise",
            "type":"Retail Goods"
        }
    ],
    "sg:phone":"+1 906 932 2773",
    "sg:postcode":"49938",
    "sg:province":"MI",
    "sg:tags":[
        "second",
        "store",
        "hand"
    ],
    "wof:name":"Treasure House",
    "wof:placetype":"venue"
},
  "geometry": {"coordinates":[-90.159054,46.457394],"type":"Point"}
}