{
  "type": "Feature",
  "properties": {
    "iso:country":"US",
    "sg:address":"26710 Carol Dr",
    "sg:city":"Franklin",
    "sg:classifiers":[
        {
            "category":"Professional",
            "subcategory":"Computer Services",
            "type":"Services"
        }
    ],
    "sg:phone":"+1 248 851 4053",
    "sg:postcode":"48025",
    "sg:province":"MI",
    "sg:tags":[
        "programming",
        "software"
    ],
    "wof:name":"Hurlbert Associates Inc",
    "wof:placetype":"venue"
},
  "geometry": {"coordinates":[-83.31191800000001,42.525897],"type":"Point"}
}