{
  "type": "Feature",
  "properties": {
    "iso:country":"US",
    "sg:address":"4358 Division Ave S",
    "sg:city":"Grand Rapids",
    "sg:classifiers":[
        {
            "category":"Personal",
            "subcategory":"Beauty Salon",
            "type":"Services"
        }
    ],
    "sg:phone":"+1 616 254 8117",
    "sg:postcode":"49548",
    "sg:province":"MI",
    "sg:tags":[
        "manicuring"
    ],
    "wof:name":"JVS Nails",
    "wof:placetype":"venue"
},
  "geometry": {"coordinates":[-85.664663,42.884346],"type":"Point"}
}