{
  "type": "Feature",
  "properties": {
    "iso:country":"US",
    "sg:address":"15303 S Commerce Dr",
    "sg:city":"Dearborn",
    "sg:classifiers":[
        {
            "category":"Professional",
            "subcategory":"Business Services",
            "type":"Services"
        }
    ],
    "sg:phone":"+1 313 845 1479",
    "sg:postcode":"48120",
    "sg:province":"MI",
    "wof:name":"Ford",
    "wof:placetype":"venue"
},
  "geometry": {"coordinates":[-83.183075,42.304547],"type":"Point"}
}