{
  "type": "Feature",
  "properties": {
    "iso:country":"US",
    "sg:address":"2800 W Townsend Rd",
    "sg:city":"Saint Johns",
    "sg:classifiers":[
        {
            "category":"Social Services",
            "subcategory":"Child Care",
            "type":"Services"
        }
    ],
    "sg:phone":"+1 989 224 9461",
    "sg:postcode":"48879",
    "sg:province":"MI",
    "sg:tags":[
        "day"
    ],
    "wof:name":"Lullaby Lodge Daycare",
    "wof:placetype":"venue"
},
  "geometry": {"coordinates":[-84.576956,42.987012],"type":"Point"}
}