{
  "type": "Feature",
  "properties": {
    "iso:country":"US",
    "sg:address":"6528 N Telegraph Rd",
    "sg:city":"Dearborn Heights",
    "sg:classifiers":[
        {
            "category":"Retail",
            "subcategory":"Auto Repair",
            "type":"Services"
        }
    ],
    "sg:phone":"+1 313 278 0613",
    "sg:postcode":"48127",
    "sg:province":"MI",
    "sg:tags":[
        "body",
        "shop"
    ],
    "wof:name":"J & J Collision Service Inc",
    "wof:placetype":"venue"
},
  "geometry": {"coordinates":[-83.27269699999999,42.3354],"type":"Point"}
}