{
  "type": "Feature",
  "properties": {
    "iso:country":"US",
    "sg:address":"3551 Keswick Dr NE",
    "sg:city":"Belmont",
    "sg:classifiers":[
        {
            "category":"Professional",
            "subcategory":"Business Services",
            "type":"Services"
        }
    ],
    "sg:phone":"+1 616 866 0693",
    "sg:postcode":"49306",
    "sg:province":"MI",
    "sg:tags":[
        "notary",
        "public"
    ],
    "wof:name":"Ruth A Smith",
    "wof:placetype":"venue"
},
  "geometry": {"coordinates":[-85.58185,43.080571],"type":"Point"}
}