{
  "type": "Feature",
  "properties": {
    "iso:country":"US",
    "sg:address":"298 S Hancock St",
    "sg:city":"Pentwater",
    "sg:classifiers":[
        {
            "category":"Shopping",
            "subcategory":"Clothing, Apparel, & Fashions",
            "type":"Retail Goods"
        }
    ],
    "sg:phone":"+1 231 869 4320",
    "sg:postcode":"49449",
    "sg:province":"MI",
    "sg:tags":[
        "t"
    ],
    "wof:name":"Sassafras Tees",
    "wof:placetype":"venue"
},
  "geometry": {"coordinates":[-86.43298900000001,43.779063],"type":"Point"}
}