{
  "type": "Feature",
  "properties": {
    "iso:country":"US",
    "sg:address":"1000 Church St",
    "sg:city":"Mt Morris",
    "sg:classifiers":[
        {
            "category":"Building & Trades",
            "subcategory":"Electrical",
            "type":"Services"
        }
    ],
    "sg:phone":"+1 810 687 2568",
    "sg:postcode":"48458",
    "sg:province":"MI",
    "sg:tags":[
        "electric",
        "contractor"
    ],
    "wof:name":"Arrow Flint Electric Co",
    "wof:placetype":"venue"
},
  "geometry": {"coordinates":[-83.692385,43.117954],"type":"Point"}
}