{
  "type": "Feature",
  "properties": {
    "iso:country":"US",
    "sg:address":"1173 Barrington",
    "sg:city":"Grand Rapids",
    "sg:classifiers":[
        {
            "category":"Recreation",
            "type":"Entertainment"
        }
    ],
    "sg:phone":"+1 616 735 3610",
    "sg:postcode":"49534",
    "sg:province":"MI",
    "wof:name":"Nothing But Fairways & Greens",
    "wof:placetype":"venue"
},
  "geometry": {"coordinates":[-85.770813,42.984157],"type":"Point"}
}