{
  "type": "Feature",
  "properties": {
    "iso:country":"US",
    "sg:address":"2911 S Washington Ave",
    "sg:city":"Lansing",
    "sg:classifiers":[
        {
            "category":"Retail",
            "subcategory":"Laundry & Dry Cleaning",
            "type":"Services"
        }
    ],
    "sg:phone":"+1 517 393 1730",
    "sg:postcode":"48910",
    "sg:province":"MI",
    "sg:tags":[
        "cleaners"
    ],
    "wof:name":"Kent Deluxe Cleaners",
    "wof:placetype":"venue"
},
  "geometry": {"coordinates":[-84.559764,42.703096],"type":"Point"}
}