{
  "type": "Feature",
  "properties": {
    "iso:country":"US",
    "sg:address":"18401 W McNichols Rd",
    "sg:city":"Detroit",
    "sg:classifiers":[
        {
            "category":"Education",
            "subcategory":"School",
            "type":"Public Place"
        }
    ],
    "sg:phone":"+1 313 537 9400",
    "sg:postcode":"48219",
    "sg:province":"MI",
    "wof:name":"Ctr For Literacy & Creativity",
    "wof:placetype":"venue"
},
  "geometry": {"coordinates":[-83.224344,42.415444],"type":"Point"}
}