{
  "type": "Feature",
  "properties": {
    "iso:country":"US",
    "sg:address":"957 E Auburn Rd",
    "sg:city":"Rochester Hills",
    "sg:classifiers":[
        {
            "category":"Autos & Motor Vehicles",
            "subcategory":"Auto Supplies",
            "type":"Retail Goods"
        }
    ],
    "sg:phone":"+1 248 853 7770",
    "sg:postcode":"48307",
    "sg:province":"MI",
    "sg:tags":[
        "automobile",
        "parts"
    ],
    "wof:name":"Murray's Discount Auto Store",
    "wof:placetype":"venue"
},
  "geometry": {"coordinates":[-83.114057,42.636713],"type":"Point"}
}