{
  "type": "Feature",
  "properties": {
    "iso:country":"US",
    "sg:address":"3118 Shawnee Ave",
    "sg:city":"Flint",
    "sg:phone":"+1 810 785 6686",
    "sg:postcode":"48507",
    "sg:province":"MI",
    "sg:tags":[
        "oil"
    ],
    "wof:name":"Royal Fuel",
    "wof:placetype":"venue"
},
  "geometry": {"coordinates":[-83.657132,42.994719],"type":"Point"}
}