{
  "type": "Feature",
  "properties": {
    "iso:country":"US",
    "sg:address":"1220 W Parnall Rd",
    "sg:city":"Jackson",
    "sg:classifiers":[
        {
            "category":"Restaurant",
            "type":"Food & Drink"
        }
    ],
    "sg:phone":"+1 517 782 1737",
    "sg:postcode":"49201",
    "sg:province":"MI",
    "wof:name":"Subway Sandwiches & Salads",
    "wof:placetype":"venue"
},
  "geometry": {"coordinates":[-84.421896,42.291183],"type":"Point"}
}