{
  "type": "Feature",
  "properties": {
    "iso:country":"US",
    "sg:address":"990 W Kilgore Rd",
    "sg:city":"Kalamazoo",
    "sg:classifiers":[
        {
            "category":"Social Services",
            "type":"Services"
        }
    ],
    "sg:phone":"+1 269 343 8765",
    "sg:postcode":"49008",
    "sg:province":"MI",
    "sg:tags":[
        "organization",
        "welfare"
    ],
    "wof:name":"ARK-For Youth",
    "wof:placetype":"venue"
},
  "geometry": {"coordinates":[-85.595208,42.245249],"type":"Point"}
}