{
  "type": "Feature",
  "properties": {
    "iso:country":"US",
    "sg:address":"1425 Jolly Rd",
    "sg:city":"Okemos",
    "sg:classifiers":[
        {
            "category":"Professional",
            "type":"Services"
        }
    ],
    "sg:phone":"+1 517 347 5507",
    "sg:postcode":"48864",
    "sg:province":"MI",
    "sg:tags":[
        "control",
        "vibration"
    ],
    "wof:name":"Lord Corp",
    "wof:placetype":"venue"
},
  "geometry": {"coordinates":[-84.40537999999999,42.682958],"type":"Point"}
}