{
  "type": "Feature",
  "properties": {
    "iso:country":"US",
    "sg:address":"4633 Dexter Ann Arbor Rd",
    "sg:city":"Ann Arbor",
    "sg:classifiers":[
        {
            "category":"Professional",
            "subcategory":"Business Services",
            "type":"Services"
        }
    ],
    "sg:phone":"+1 734 665 1168",
    "sg:postcode":"48103",
    "sg:province":"MI",
    "wof:name":"Tenacious Creations LLC",
    "wof:placetype":"venue"
},
  "geometry": {"coordinates":[-83.824687,42.29758],"type":"Point"}
}