{
  "type": "Feature",
  "properties": {
    "iso:country":"US",
    "sg:address":"28993 Ford Rd",
    "sg:city":"Garden City",
    "sg:classifiers":[
        {
            "category":"Restaurant",
            "type":"Food & Drink"
        }
    ],
    "sg:phone":"+1 734 522 2960",
    "sg:postcode":"48135",
    "sg:province":"MI",
    "sg:website":"www.tacobell.com",
    "wof:name":"Taco Bell",
    "wof:placetype":"venue"
},
  "geometry": {"coordinates":[-83.32060199999999,42.325802],"type":"Point"}
}