{
  "type": "Feature",
  "properties": {
    "iso:country":"US",
    "sg:address":"1134 East Big Beaver",
    "sg:city":"Troy",
    "sg:classifiers":[
        {
            "category":"Shopping",
            "subcategory":"Tobacco",
            "type":"Retail Goods"
        }
    ],
    "sg:phone":"+1 248 616 2000",
    "sg:postcode":"48083",
    "sg:province":"MI",
    "sg:tags":[
        "shop"
    ],
    "sg:website":"www.detroitcigaroutlet.com/",
    "wof:name":"The Cigar Factory Outlet",
    "wof:placetype":"venue"
},
  "geometry": {"coordinates":[-83.114372,42.561146],"type":"Point"}
}