{
  "type": "Feature",
  "properties": {
    "iso:country":"US",
    "sg:address":"6807 E Knollwood Cir",
    "sg:city":"West Bloomfield",
    "sg:classifiers":[
        {
            "category":"Building & Trades",
            "subcategory":"Electrical",
            "type":"Services"
        }
    ],
    "sg:phone":"+1 248 855 8909",
    "sg:postcode":"48322",
    "sg:province":"MI",
    "sg:tags":[
        "electrician"
    ],
    "wof:name":"Imperial Electric",
    "wof:placetype":"venue"
},
  "geometry": {"coordinates":[-83.3274,42.539398],"type":"Point"}
}