{
  "type": "Feature",
  "properties": {
    "iso:country":"US",
    "sg:address":"301 Washington Ave",
    "sg:city":"Bay City",
    "sg:classifiers":[
        {
            "category":"Government",
            "subcategory":"Office",
            "type":"Public Place"
        },
        {
            "category":"Professional",
            "subcategory":"Accounting & Tax Preparation",
            "type":"Services"
        }
    ],
    "sg:phone":"+1 989 894 8132",
    "sg:postcode":"48708",
    "sg:province":"MI",
    "sg:tags":[
        "village"
    ],
    "wof:name":"Bay City Accounting Department",
    "wof:placetype":"venue"
},
  "geometry": {"coordinates":[-83.8884,43.594051],"type":"Point"}
}