{
  "type": "Feature",
  "properties": {
    "iso:country":"US",
    "sg:address":"18500 John R St",
    "sg:city":"Highland Park",
    "sg:classifiers":[
        {
            "category":"Retail",
            "subcategory":"Auto Repair",
            "type":"Services"
        }
    ],
    "sg:phone":"+1 313 891 6177",
    "sg:postcode":"48203",
    "sg:province":"MI",
    "sg:tags":[
        "body",
        "shop"
    ],
    "wof:name":"John R Auto Body",
    "wof:placetype":"venue"
},
  "geometry": {"coordinates":[-83.102203,42.427601],"type":"Point"}
}