{
  "type": "Feature",
  "properties": {
    "iso:country":"US",
    "sg:address":"521 Baldwin St",
    "sg:city":"Jenison",
    "sg:classifiers":[
        {
            "category":"Real Estate",
            "subcategory":"Real Estate Agent",
            "type":"Services"
        }
    ],
    "sg:phone":"+1 616 249 0815",
    "sg:postcode":"49428",
    "sg:province":"MI",
    "wof:name":"Quality Home Realty",
    "wof:placetype":"venue"
},
  "geometry": {"coordinates":[-85.793682,42.907218],"type":"Point"}
}