{
  "type": "Feature",
  "properties": {
    "iso:country":"US",
    "sg:address":"7200 Parkhurst Dr",
    "sg:city":"Bloomfield Hills",
    "sg:classifiers":[
        {
            "category":"Retail",
            "subcategory":"Repair Shop",
            "type":"Services"
        }
    ],
    "sg:phone":"+1 248 644 6315",
    "sg:postcode":"48301",
    "sg:province":"MI",
    "sg:tags":[
        "equipment",
        "printing"
    ],
    "wof:name":"Jack & Co",
    "wof:placetype":"venue"
},
  "geometry": {"coordinates":[-83.269228,42.53469],"type":"Point"}
}