{
  "type": "Feature",
  "properties": {
    "iso:country":"US",
    "sg:address":"1515 Lake Lansing Rd",
    "sg:city":"Lansing",
    "sg:classifiers":[
        {
            "category":"Health Services",
            "subcategory":"Doctor",
            "type":"Services"
        }
    ],
    "sg:phone":"+1 517 374 1055",
    "sg:postcode":"48912",
    "sg:province":"MI",
    "sg:tags":[
        "medical"
    ],
    "wof:name":"Frederick M Vincent MD Faan",
    "wof:placetype":"venue"
},
  "geometry": {"coordinates":[-84.53014,42.760755],"type":"Point"}
}