{
  "type": "Feature",
  "properties": {
    "iso:country":"US",
    "sg:address":"29 Oak Hill Dr",
    "sg:city":"Marquette",
    "sg:classifiers":[
        {
            "category":"Travel",
            "subcategory":"Travel Agent",
            "type":"Entertainment"
        }
    ],
    "sg:phone":"+1 906 225 9777",
    "sg:postcode":"49855",
    "sg:province":"MI",
    "sg:tags":[
        "agency"
    ],
    "wof:name":"O Lets Go Travel LLC",
    "wof:placetype":"venue"
},
  "geometry": {"coordinates":[-87.449219,46.527867],"type":"Point"}
}