{
  "type": "Feature",
  "properties": {
    "iso:country":"US",
    "sg:address":"8957 N Loomis Rd",
    "sg:city":"Coleman",
    "sg:phone":"+1 989 465 1415",
    "sg:postcode":"48618",
    "sg:province":"MI",
    "sg:tags":[
        "farm",
        "grain",
        "cash"
    ],
    "wof:name":"Joe Babosh",
    "wof:placetype":"venue"
},
  "geometry": {"coordinates":[-84.667198,43.758131],"type":"Point"}
}