{
  "type": "Feature",
  "properties": {
    "iso:country":"US",
    "sg:address":"204 W Aurora St",
    "sg:city":"Ironwood",
    "sg:classifiers":[
        {
            "category":"Bars & Pubs",
            "type":"Food & Drink"
        }
    ],
    "sg:phone":"+1 906 932 4130",
    "sg:postcode":"49938",
    "sg:province":"MI",
    "wof:name":"Midway Bar",
    "wof:placetype":"venue"
},
  "geometry": {"coordinates":[-90.172614,46.45207],"type":"Point"}
}