{
  "type": "Feature",
  "properties": {
    "iso:country":"US",
    "sg:address":"155 S Saginaw St",
    "sg:city":"Lapeer",
    "sg:classifiers":[
        {
            "category":"Wholesale",
            "subcategory":"Farm Supplies",
            "type":"Manufacturing & Wholesale Goods"
        }
    ],
    "sg:phone":"+1 810 664 2987",
    "sg:postcode":"48446",
    "sg:province":"MI",
    "sg:tags":[
        "feed"
    ],
    "wof:name":"Lapeer Grain Co",
    "wof:placetype":"venue"
},
  "geometry": {"coordinates":[-83.30432399999999,43.04936],"type":"Point"}
}