{
  "type": "Feature",
  "properties": {
    "iso:country":"US",
    "sg:address":"2127 Brighton Rd",
    "sg:city":"Howell",
    "sg:classifiers":[
        {
            "category":"Education",
            "subcategory":"School",
            "type":"Public Place"
        },
        {
            "category":"Education",
            "subcategory":"Special Training",
            "type":"Public Place"
        }
    ],
    "sg:phone":"+1 517 545 8612",
    "sg:postcode":"48843",
    "sg:province":"MI",
    "sg:tags":[
        "educational"
    ],
    "wof:name":"Special Education Service",
    "wof:placetype":"venue"
},
  "geometry": {"coordinates":[-83.90940999999999,42.525647],"type":"Point"}
}