{
  "type": "Feature",
  "properties": {
    "iso:country":"US",
    "sg:address":"706 W Centre Ave",
    "sg:city":"Portage",
    "sg:classifiers":[
        {
            "category":"Health Services",
            "subcategory":"Doctor",
            "type":"Services"
        }
    ],
    "sg:phone":"+1 269 323 1679",
    "sg:postcode":"49024",
    "sg:province":"MI",
    "sg:tags":[
        "dentist"
    ],
    "wof:name":"Richard A Shockley DDS",
    "wof:placetype":"venue"
},
  "geometry": {"coordinates":[-85.597286,42.201046],"type":"Point"}
}