{
  "type": "Feature",
  "properties": {
    "iso:country":"US",
    "sg:address":"1340 S Clark Rd",
    "sg:city":"Dansville",
    "sg:classifiers":[
        {
            "category":"Professional",
            "type":"Services"
        }
    ],
    "sg:phone":"+1 517 623 6590",
    "sg:postcode":"48819",
    "sg:province":"MI",
    "wof:name":"Labor Tech",
    "wof:placetype":"venue"
},
  "geometry": {"coordinates":[-84.324793,42.541421],"type":"Point"}
}