{
  "type": "Feature",
  "properties": {
    "iso:country":"US",
    "sg:address":"963 Oak St",
    "sg:city":"Wyandotte",
    "sg:classifiers":[
        {
            "category":"Organizations",
            "subcategory":"Community Association",
            "type":"Services"
        }
    ],
    "sg:phone":"+1 734 283 5525",
    "sg:postcode":"48192",
    "sg:province":"MI",
    "wof:name":"Polish Lgn Amer Vets Post 74",
    "wof:placetype":"venue"
},
  "geometry": {"coordinates":[-83.164737,42.203867],"type":"Point"}
}