{
  "type": "Feature",
  "properties": {
    "iso:country":"US",
    "sg:address":"58590 Travis Rd",
    "sg:city":"New Hudson",
    "sg:classifiers":[
        {
            "category":"Professional",
            "type":"Services"
        }
    ],
    "sg:phone":"+1 248 437 8544",
    "sg:postcode":"48165",
    "sg:province":"MI",
    "sg:tags":[
        "establishment"
    ],
    "wof:name":"Di Ponio Inc",
    "wof:placetype":"venue"
},
  "geometry": {"coordinates":[-83.62868,42.497951],"type":"Point"}
}