{
  "type": "Feature",
  "properties": {
    "iso:country":"US",
    "sg:address":"10941 Michigan Ave",
    "sg:city":"Posen",
    "sg:phone":"+1 989 356 6279",
    "sg:postcode":"49776",
    "sg:province":"MI",
    "sg:tags":[
        "oil"
    ],
    "wof:name":"Huron Oil",
    "wof:placetype":"venue"
},
  "geometry": {"coordinates":[-83.69879400000001,45.263197],"type":"Point"}
}