{
  "type": "Feature",
  "properties": {
    "iso:country":"US",
    "sg:address":"811 Topinabee Rd",
    "sg:city":"Niles",
    "sg:classifiers":[
        {
            "category":"Retail",
            "subcategory":"Auto Repair",
            "type":"Services"
        }
    ],
    "sg:phone":"+1 269 684 3235",
    "sg:postcode":"49120",
    "sg:province":"MI",
    "sg:tags":[
        "body"
    ],
    "wof:name":"Classic Auto Restoration",
    "wof:placetype":"venue"
},
  "geometry": {"coordinates":[-86.26669699999999,41.819582],"type":"Point"}
}