{
  "type": "Feature",
  "properties": {
    "iso:country":"US",
    "sg:address":"195 W Pine St",
    "sg:city":"Harrison",
    "sg:classifiers":[
        {
            "category":"Social Services",
            "type":"Services"
        }
    ],
    "sg:phone":"+1 989 539 0499",
    "sg:postcode":"48625",
    "sg:province":"MI",
    "sg:tags":[
        "counselor",
        "marriage",
        "family"
    ],
    "wof:name":"Counseling Services Clare Cnty",
    "wof:placetype":"venue"
},
  "geometry": {"coordinates":[-84.801827,44.017761],"type":"Point"}
}