{
  "type": "Feature",
  "properties": {
    "iso:country":"US",
    "sg:address":"26111 Northline Rd",
    "sg:city":"Taylor",
    "sg:classifiers":[
        {
            "category":"Professional",
            "subcategory":"Management & Consulting",
            "type":"Services"
        }
    ],
    "sg:phone":"+1 734 946 0673",
    "sg:postcode":"48180",
    "sg:province":"MI",
    "sg:tags":[
        "marketing",
        "event"
    ],
    "wof:name":"Whitecap Events",
    "wof:placetype":"venue"
},
  "geometry": {"coordinates":[-83.29752000000001,42.211],"type":"Point"}
}