{
  "type": "Feature",
  "properties": {
    "iso:country":"US",
    "sg:address":"8713 S 38th St",
    "sg:city":"Scotts",
    "sg:classifiers":[
        {
            "category":"Wholesale",
            "subcategory":"Meat",
            "type":"Manufacturing & Wholesale Goods"
        }
    ],
    "sg:phone":"+1 269 626 8891",
    "sg:postcode":"49088",
    "sg:province":"MI",
    "sg:tags":[
        "packer"
    ],
    "wof:name":"Pease Packing Corp",
    "wof:placetype":"venue"
},
  "geometry": {"coordinates":[-85.39343700000001,42.195894],"type":"Point"}
}