{
  "type": "Feature",
  "properties": {
    "iso:country":"US",
    "sg:address":"45317 Utica Grn W",
    "sg:city":"Utica",
    "sg:classifiers":[
        {
            "category":"Building & Trades",
            "subcategory":"Construction",
            "type":"Services"
        }
    ],
    "sg:phone":"+1 586 739 0676",
    "sg:postcode":"48317",
    "sg:province":"MI",
    "sg:tags":[
        "hanging",
        "contractor"
    ],
    "wof:name":"Classic Coat",
    "wof:placetype":"venue"
},
  "geometry": {"coordinates":[-83.055274,42.628162],"type":"Point"}
}