{
  "type": "Feature",
  "properties": {
    "iso:country":"US",
    "sg:address":"43435 Joy Rd",
    "sg:city":"Canton",
    "sg:classifiers":[
        {
            "category":"Real Estate",
            "subcategory":"Real Estate Agent",
            "type":"Services"
        }
    ],
    "sg:phone":"+1 734 459 1010",
    "sg:postcode":"48187",
    "sg:province":"MI",
    "wof:name":"Bittinger Lee & Noel",
    "wof:placetype":"venue"
},
  "geometry": {"coordinates":[-83.470269,42.351404],"type":"Point"}
}