{
  "type": "Feature",
  "properties": {
    "iso:country":"US",
    "sg:address":"5127 Highland Rd",
    "sg:city":"Waterford",
    "sg:classifiers":[
        {
            "category":"Restaurant",
            "type":"Food & Drink"
        }
    ],
    "sg:phone":"+1 248 673 3333",
    "sg:postcode":"48327",
    "sg:province":"MI",
    "wof:name":"Quiznos Sub",
    "wof:placetype":"venue"
},
  "geometry": {"coordinates":[-83.387783,42.660196],"type":"Point"}
}