{
  "type": "Feature",
  "properties": {
    "iso:country":"US",
    "sg:address":"3620 N Country Ln",
    "sg:city":"Traverse City",
    "sg:classifiers":[
        {
            "category":"Bars & Pubs",
            "type":"Food & Drink"
        }
    ],
    "sg:menulink":"http://www.allmenus.com/mi/long-lake/34380-cracker-barrel-old-country-store/menu/",
    "sg:phone":"+1 231 933 9244",
    "sg:postcode":"49684",
    "sg:province":"MI",
    "sg:tags":[
        "american",
        "southern"
    ],
    "wof:name":"Cracker Barrel Old Country Store",
    "wof:placetype":"venue"
},
  "geometry": {"coordinates":[-85.69974000000001,44.732786],"type":"Point"}
}