{
  "type": "Feature",
  "properties": {
    "iso:country":"US",
    "sg:address":"21223 Mack Ave",
    "sg:city":"Grosse Pointe Woods",
    "sg:classifiers":[
        {
            "category":"Health Services",
            "subcategory":"Dentist",
            "type":"Services"
        }
    ],
    "sg:phone":"+1 313 884 1320",
    "sg:postcode":"48236",
    "sg:province":"MI",
    "wof:name":"Aesthetic & Family Dentistry by Drs Hurst and Cash",
    "wof:placetype":"venue"
},
  "geometry": {"coordinates":[-82.90533000000001,42.450007],"type":"Point"}
}