{
  "type": "Feature",
  "properties": {
    "iso:country":"US",
    "sg:address":"4175 Sherry Ct",
    "sg:city":"Bay City",
    "sg:classifiers":[
        {
            "category":"Retail",
            "subcategory":"Repair Shop",
            "type":"Services"
        }
    ],
    "sg:phone":"+1 989 684 8173",
    "sg:postcode":"48706",
    "sg:province":"MI",
    "wof:name":"Worry Free Repair",
    "wof:placetype":"venue"
},
  "geometry": {"coordinates":[-83.887398,43.626811],"type":"Point"}
}