{
  "type": "Feature",
  "properties": {
    "iso:country":"US",
    "sg:address":"6977 James St",
    "sg:city":"Brown City",
    "sg:classifiers":[
        {
            "category":"Retail",
            "subcategory":"Auto Repair",
            "type":"Services"
        }
    ],
    "sg:phone":"+1 810 346 2600",
    "sg:postcode":"48416",
    "sg:province":"MI",
    "sg:tags":[
        "body",
        "automobile",
        "painting"
    ],
    "wof:name":"Bill's Body Shop",
    "wof:placetype":"venue"
},
  "geometry": {"coordinates":[-82.987493,43.212647],"type":"Point"}
}