{
  "type": "Feature",
  "properties": {
    "iso:country":"US",
    "sg:address":"2333 Biddle Ave",
    "sg:city":"Wyandotte",
    "sg:classifiers":[
        {
            "category":"Health Services",
            "subcategory":"Doctor",
            "type":"Services"
        }
    ],
    "sg:phone":"+1 734 246 6966",
    "sg:postcode":"48192",
    "sg:province":"MI",
    "wof:name":"Matthews Burton V MD",
    "wof:placetype":"venue"
},
  "geometry": {"coordinates":[-83.146874,42.210619],"type":"Point"}
}