{
  "type": "Feature",
  "properties": {
    "iso:country":"US",
    "sg:address":"1081 Eagle Nest Dr",
    "sg:city":"Milford",
    "sg:classifiers":[
        {
            "category":"Professional",
            "subcategory":"Management & Consulting",
            "type":"Services"
        }
    ],
    "sg:phone":"+1 248 685 2424",
    "sg:postcode":"48381",
    "sg:province":"MI",
    "sg:tags":[
        "consultant",
        "business"
    ],
    "wof:name":"E Project-Management.Com Inc",
    "wof:placetype":"venue"
},
  "geometry": {"coordinates":[-83.606245,42.574741],"type":"Point"}
}