{
  "type": "Feature",
  "properties": {
    "iso:country":"US",
    "sg:address":"1205 W Michigan Ave",
    "sg:city":"Marshall",
    "sg:classifiers":[
        {
            "category":"Restaurant",
            "type":"Food & Drink"
        }
    ],
    "sg:menulink":"http://www.allmenus.com/mi/marshall/58141-applebees/menu/",
    "sg:phone":"+1 269 781 9699",
    "sg:postcode":"49068",
    "sg:province":"MI",
    "sg:tags":[
        "burger",
        "american",
        "sandwich",
        "soup"
    ],
    "wof:name":"Applebee's",
    "wof:placetype":"venue"
},
  "geometry": {"coordinates":[-84.98205799999999,42.271656],"type":"Point"}
}