{
  "type": "Feature",
  "properties": {
    "iso:country":"US",
    "sg:address":"2945 S Canfield Rd",
    "sg:city":"Eaton Rapids",
    "sg:classifiers":[
        {
            "category":"Professional",
            "subcategory":"Business Services",
            "type":"Services"
        }
    ],
    "sg:phone":"+1 517 663 7944",
    "sg:postcode":"48827",
    "sg:province":"MI",
    "wof:name":"Ra Harmon Enterprises",
    "wof:placetype":"venue"
},
  "geometry": {"coordinates":[-84.69958699999999,42.525083],"type":"Point"}
}