{
  "type": "Feature",
  "properties": {
    "iso:country":"US",
    "sg:address":"211 N Bridge St",
    "sg:city":"Linden",
    "sg:classifiers":[
        {
            "category":"Personal",
            "subcategory":"Beauty Salon",
            "type":"Services"
        }
    ],
    "sg:phone":"+1 810 735 7600",
    "sg:postcode":"48451",
    "sg:province":"MI",
    "wof:name":"Marshall's Family Hair Care",
    "wof:placetype":"venue"
},
  "geometry": {"coordinates":[-83.7824,42.815559],"type":"Point"}
}