{
  "type": "Feature",
  "properties": {
    "iso:country":"US",
    "sg:address":"185 S Main St",
    "sg:city":"Custer",
    "sg:classifiers":[
        {
            "category":"Education",
            "subcategory":"School",
            "type":"Public Place"
        }
    ],
    "sg:phone":"+1 231 757 3733",
    "sg:postcode":"49405",
    "sg:province":"MI",
    "sg:tags":[
        "a",
        "as",
        "district",
        "operates"
    ],
    "wof:name":"Pre School",
    "wof:placetype":"venue"
},
  "geometry": {"coordinates":[-86.218721,43.950813],"type":"Point"}
}