{
  "type": "Feature",
  "properties": {
    "iso:country":"US",
    "sg:address":"39194 Grand River Ave",
    "sg:city":"Farmington",
    "sg:classifiers":[
        {
            "category":"Retail",
            "subcategory":"Auto Repair",
            "type":"Services"
        }
    ],
    "sg:phone":"+1 248 471 3600",
    "sg:postcode":"48335",
    "sg:province":"MI",
    "wof:name":"Ethan's Auto Service",
    "wof:placetype":"venue"
},
  "geometry": {"coordinates":[-83.432999,42.471401],"type":"Point"}
}