{
  "type": "Feature",
  "properties": {
    "iso:country":"US",
    "sg:address":"622 Howard St",
    "sg:city":"Petoskey",
    "sg:classifiers":[
        {
            "category":"Social Services",
            "type":"Services"
        }
    ],
    "sg:phone":"+1 231 348 8393",
    "sg:postcode":"49770",
    "sg:province":"MI",
    "sg:tags":[
        "youth",
        "organization",
        "center"
    ],
    "wof:name":"Ymca Of Northern Michigan",
    "wof:placetype":"venue"
},
  "geometry": {"coordinates":[-84.95563199999999,45.37164],"type":"Point"}
}