{
  "type": "Feature",
  "properties": {
    "iso:country":"US",
    "sg:address":"8362 Richardson Rd",
    "sg:city":"Commerce Township",
    "sg:classifiers":[
        {
            "category":"Health Services",
            "subcategory":"Doctor",
            "type":"Services"
        }
    ],
    "sg:phone":"+1 248 363 7177",
    "sg:postcode":"48382",
    "sg:province":"MI",
    "sg:tags":[
        "surgeon",
        "oral"
    ],
    "wof:name":"Shuster Allen J DDS",
    "wof:placetype":"venue"
},
  "geometry": {"coordinates":[-83.448654,42.5779],"type":"Point"}
}