{
  "type": "Feature",
  "properties": {
    "iso:country":"US",
    "sg:address":"21176 Midway Ave",
    "sg:city":"Southfield",
    "sg:classifiers":[
        {
            "category":"Banks & Credit Unions",
            "subcategory":"Bank",
            "type":"Services"
        }
    ],
    "sg:phone":"+1 248 353 8330",
    "sg:postcode":"48075",
    "sg:province":"MI",
    "sg:tags":[
        "mortgage"
    ],
    "wof:name":"Midway Mortgage",
    "wof:placetype":"venue"
},
  "geometry": {"coordinates":[-83.25422500000001,42.451307],"type":"Point"}
}