{
  "type": "Feature",
  "properties": {
    "iso:country":"US",
    "sg:address":"10170 Shaver Rd",
    "sg:city":"Portage",
    "sg:classifiers":[
        {
            "category":"Autos & Motor Vehicles",
            "subcategory":"Recreational Vehicle Sales",
            "type":"Retail Goods"
        }
    ],
    "sg:phone":"+1 269 323 2166",
    "sg:postcode":"49024",
    "sg:province":"MI",
    "sg:tags":[
        "repair",
        "cap",
        "trailer"
    ],
    "wof:name":"Mad-Cap",
    "wof:placetype":"venue"
},
  "geometry": {"coordinates":[-85.616412,42.168645],"type":"Point"}
}