{
  "type": "Feature",
  "properties": {
    "iso:country":"US",
    "sg:address":"138 Maple Valley St",
    "sg:city":"Sandusky",
    "sg:classifiers":[
        {
            "category":"Social Services",
            "subcategory":"Child Care",
            "type":"Services"
        }
    ],
    "sg:phone":"+1 810 648 2775",
    "sg:postcode":"48471",
    "sg:province":"MI",
    "sg:tags":[
        "kindergarten",
        "academic",
        "school"
    ],
    "wof:name":"Sandusky Head Start Program",
    "wof:placetype":"venue"
},
  "geometry": {"coordinates":[-82.839968,43.41764],"type":"Point"}
}