{
  "type": "Feature",
  "properties": {
    "iso:country":"US",
    "sg:address":"1217 Fort St",
    "sg:city":"Wyandotte",
    "sg:classifiers":[
        {
            "category":"Personal",
            "subcategory":"Nail Salon",
            "type":"Services"
        }
    ],
    "sg:phone":"+1 734 284 6599",
    "sg:postcode":"48192",
    "sg:province":"MI",
    "wof:name":"Helen's Magic Mirror",
    "wof:placetype":"venue"
},
  "geometry": {"coordinates":[-83.180801,42.220798],"type":"Point"}
}