{
  "type": "Feature",
  "properties": {
    "iso:country":"US",
    "sg:address":"3713 Riggsville Rd",
    "sg:city":"Cheboygan",
    "sg:classifiers":[
        {
            "category":"Social Services",
            "subcategory":"Adult Care",
            "type":"Services"
        }
    ],
    "sg:phone":"+1 231 627 5878",
    "sg:postcode":"49721",
    "sg:province":"MI",
    "sg:tags":[
        "day",
        "provider"
    ],
    "wof:name":"Marilyn Frederick",
    "wof:placetype":"venue"
},
  "geometry": {"coordinates":[-84.564651,45.591822],"type":"Point"}
}