{
  "type": "Feature",
  "properties": {
    "iso:country":"US",
    "sg:address":"3682 Plainfield Ave NE",
    "sg:city":"Grand Rapids",
    "sg:classifiers":[
        {
            "category":"Retail",
            "subcategory":"Auto Repair",
            "type":"Services"
        }
    ],
    "sg:phone":"+1 616 361 7776",
    "sg:postcode":"49525",
    "sg:province":"MI",
    "sg:tags":[
        "glass",
        "replacement"
    ],
    "wof:name":"Henderson Glass Inc",
    "wof:placetype":"venue"
},
  "geometry": {"coordinates":[-85.629301,43.030615],"type":"Point"}
}