{
  "type": "Feature",
  "properties": {
    "iso:country":"US",
    "sg:address":"5375 Fisher Rd",
    "sg:city":"Howell",
    "sg:classifiers":[
        {
            "category":"Building & Trades",
            "subcategory":"Construction",
            "type":"Services"
        }
    ],
    "sg:phone":"+1 517 548 0946",
    "sg:postcode":"48855",
    "sg:province":"MI",
    "sg:tags":[
        "contractor"
    ],
    "wof:name":"Tobias Tile & Marble",
    "wof:placetype":"venue"
},
  "geometry": {"coordinates":[-83.91701500000001,42.679108],"type":"Point"}
}