{
  "type": "Feature",
  "properties": {
    "iso:country":"US",
    "sg:address":"1100 Cherry Rd",
    "sg:city":"Manistee",
    "sg:classifiers":[
        {
            "category":"Real Estate",
            "subcategory":"Real Estate Operator",
            "type":"Services"
        }
    ],
    "sg:phone":"+1 231 398 9626",
    "sg:postcode":"49660",
    "sg:province":"MI",
    "sg:tags":[
        "building",
        "apartment"
    ],
    "wof:name":"Lakeview Apts",
    "wof:placetype":"venue"
},
  "geometry": {"coordinates":[-86.33951500000001,44.235391],"type":"Point"}
}