{
  "type": "Feature",
  "properties": {
    "iso:country":"US",
    "sg:address":"4331 Keller Rd",
    "sg:city":"Holt",
    "sg:classifiers":[
        {
            "category":"Freight",
            "type":"Transportation"
        }
    ],
    "sg:phone":"+1 517 699 2279",
    "sg:postcode":"48842",
    "sg:province":"MI",
    "sg:tags":[
        "operator",
        "local",
        "trucking"
    ],
    "wof:name":"Ellis Trucking Corp",
    "wof:placetype":"venue"
},
  "geometry": {"coordinates":[-84.51705699999999,42.647439],"type":"Point"}
}