{
  "type": "Feature",
  "properties": {
    "iso:country":"US",
    "sg:address":"4631 Highland Rd",
    "sg:city":"Waterford",
    "sg:classifiers":[
        {
            "category":"Restaurant",
            "type":"Food & Drink"
        }
    ],
    "sg:phone":"+1 248 674 3155",
    "sg:postcode":"48328",
    "sg:province":"MI",
    "wof:name":"Copperstone Of Waterford",
    "wof:placetype":"venue"
},
  "geometry": {"coordinates":[-83.377782,42.65698],"type":"Point"}
}