{
  "type": "Feature",
  "properties": {
    "iso:country":"US",
    "sg:address":"2215 Opdyke Rd",
    "sg:city":"Bloomfield Hills",
    "sg:classifiers":[
        {
            "category":"Organizations",
            "subcategory":"Religious Organization",
            "type":"Services"
        }
    ],
    "sg:phone":"+1 248 644 5460",
    "sg:postcode":"48304",
    "sg:province":"MI",
    "sg:tags":[
        "church"
    ],
    "sg:website":"www.sthugo.org",
    "wof:name":"St Hugo Of The Hills Church",
    "wof:placetype":"venue"
},
  "geometry": {"coordinates":[-83.24727799999999,42.588057],"type":"Point"}
}