{
  "type": "Feature",
  "properties": {
    "iso:country":"US",
    "sg:address":"545 Cheshire Dr NE",
    "sg:city":"Grand Rapids",
    "sg:classifiers":[
        {
            "category":"Health Services",
            "subcategory":"Doctor",
            "type":"Services"
        }
    ],
    "sg:phone":"+1 616 361 7666",
    "sg:postcode":"49505",
    "sg:province":"MI",
    "sg:tags":[
        "osteopathic"
    ],
    "wof:name":"Keith Sisson Do",
    "wof:placetype":"venue"
},
  "geometry": {"coordinates":[-85.655128,43.002875],"type":"Point"}
}