{
  "type": "Feature",
  "properties": {
    "iso:country":"US",
    "sg:address":"3850 Dearborn Ave",
    "sg:city":"Rochester",
    "sg:classifiers":[
        {
            "category":"Building & Trades",
            "subcategory":"Cleaning & Sanitation",
            "type":"Services"
        }
    ],
    "sg:phone":"+1 248 299 5850",
    "sg:postcode":"48309",
    "sg:province":"MI",
    "sg:tags":[
        "maintenance"
    ],
    "wof:name":"N Oakland Office Cleaning LLC",
    "wof:placetype":"venue"
},
  "geometry": {"coordinates":[-83.159103,42.622915],"type":"Point"}
}