{
  "type": "Feature",
  "properties": {
    "iso:country":"US",
    "sg:address":"3937 Wilson Ave SW",
    "sg:city":"Grandville",
    "sg:classifiers":[
        {
            "category":"Organizations",
            "subcategory":"Religious Organization",
            "type":"Services"
        }
    ],
    "sg:phone":"+1 616 531 2337",
    "sg:postcode":"49418",
    "sg:province":"MI",
    "sg:tags":[
        "church"
    ],
    "sg:website":"www.stpiusxchurch3937.org",
    "wof:name":"St Pius X Church",
    "wof:placetype":"venue"
},
  "geometry": {"coordinates":[-85.762541,42.892121],"type":"Point"}
}