{
  "type": "Feature",
  "properties": {
    "iso:country":"US",
    "sg:address":"4045 Dix Hwy",
    "sg:city":"Lincoln Park",
    "sg:classifiers":[
        {
            "category":"Shopping",
            "subcategory":"Mobile Phones",
            "type":"Retail Goods"
        }
    ],
    "sg:phone":"+1 313 382 2200",
    "sg:postcode":"48146",
    "sg:province":"MI",
    "sg:website":"www.sprint.com",
    "wof:name":"Sprint Store of Lincoln Park",
    "wof:placetype":"venue"
},
  "geometry": {"coordinates":[-83.19401499999999,42.223221],"type":"Point"}
}