{
  "type": "Feature",
  "properties": {
    "iso:country":"US",
    "sg:address":"4851 E 10 Rd",
    "sg:city":"Manton",
    "sg:classifiers":[
        {
            "category":"Organizations",
            "subcategory":"Religious Organization",
            "type":"Services"
        }
    ],
    "sg:phone":"+1 231 824 9580",
    "sg:postcode":"49663",
    "sg:province":"MI",
    "sg:tags":[
        "church"
    ],
    "wof:name":"Greenwood Bible Church",
    "wof:placetype":"venue"
},
  "geometry": {"coordinates":[-85.48699000000001,44.453699],"type":"Point"}
}