{
  "type": "Feature",
  "properties": {
    "iso:country":"US",
    "sg:address":"318 Massoit St",
    "sg:city":"Clawson",
    "sg:classifiers":[
        {
            "category":"Personal",
            "type":"Services"
        }
    ],
    "sg:phone":"+1 248 435 5628",
    "sg:postcode":"48017",
    "sg:province":"MI",
    "sg:tags":[
        "repair"
    ],
    "wof:name":"Chard Repair",
    "wof:placetype":"venue"
},
  "geometry": {"coordinates":[-83.151134,42.528021],"type":"Point"}
}