{
  "type": "Feature",
  "properties": {
    "iso:country":"US",
    "sg:address":"974 Dewsenberry Rd",
    "sg:city":"Bronson",
    "sg:classifiers":[
        {
            "category":"Organizations",
            "subcategory":"Non-profit Organization",
            "type":"Services"
        }
    ],
    "sg:phone":"+1 517 369 2131",
    "sg:postcode":"49028",
    "sg:province":"MI",
    "sg:tags":[
        "alternative",
        "abortion"
    ],
    "wof:name":"Branch County Right To Life",
    "wof:placetype":"venue"
},
  "geometry": {"coordinates":[-85.22838299999999,41.847262],"type":"Point"}
}