{
  "type": "Feature",
  "properties": {
    "iso:country":"US",
    "sg:address":"1701 N Dort Hwy",
    "sg:city":"Flint",
    "sg:classifiers":[
        {
            "category":"Food & Beverages",
            "subcategory":"Bakery",
            "type":"Retail Goods"
        }
    ],
    "sg:phone":"+1 810 234 2255",
    "sg:postcode":"48506",
    "sg:province":"MI",
    "sg:tags":[
        "sandwich"
    ],
    "wof:name":"Worldwide Pager & Phone Co",
    "wof:placetype":"venue"
},
  "geometry": {"coordinates":[-83.655502,43.032101],"type":"Point"}
}