{
  "type": "Feature",
  "properties": {
    "iso:country":"US",
    "sg:address":"175 W Tami Cir",
    "sg:city":"Westland",
    "sg:classifiers":[
        {
            "category":"Wholesale",
            "subcategory":"Vending Machines",
            "type":"Manufacturing & Wholesale Goods"
        }
    ],
    "sg:phone":"+1 734 467 6261",
    "sg:postcode":"48186",
    "sg:province":"MI",
    "sg:tags":[
        "operator"
    ],
    "wof:name":"Steves Vending Services",
    "wof:placetype":"venue"
},
  "geometry": {"coordinates":[-83.342686,42.309674],"type":"Point"}
}