{
  "type": "Feature",
  "properties": {
    "iso:country":"US",
    "sg:address":"130 Mills St",
    "sg:city":"Croswell",
    "sg:classifiers":[
        {
            "category":"Building & Trades",
            "subcategory":"Equipment Rental",
            "type":"Services"
        }
    ],
    "sg:phone":"+1 810 679 3325",
    "sg:postcode":"48422",
    "sg:province":"MI",
    "wof:name":"Power Snake Rental Co Inc",
    "wof:placetype":"venue"
},
  "geometry": {"coordinates":[-82.61758500000001,43.278114],"type":"Point"}
}