{
  "type": "Feature",
  "properties": {
    "iso:country":"US",
    "sg:address":"2301 Tipperary Rd",
    "sg:city":"Kalamazoo",
    "sg:classifiers":[
        {
            "category":"Professional",
            "subcategory":"Management & Consulting",
            "type":"Services"
        }
    ],
    "sg:phone":"+1 269 388 5286",
    "sg:postcode":"49008",
    "sg:province":"MI",
    "sg:tags":[
        "consultant",
        "training"
    ],
    "wof:name":"Productivity Solutions",
    "wof:placetype":"venue"
},
  "geometry": {"coordinates":[-85.61248999999999,42.267012],"type":"Point"}
}