{
  "type": "Feature",
  "properties": {
    "iso:country":"US",
    "sg:address":"4743 Don Ct",
    "sg:city":"Warren",
    "sg:classifiers":[
        {
            "category":"Building & Trades",
            "subcategory":"Construction",
            "type":"Services"
        }
    ],
    "sg:phone":"+1 586 751 3909",
    "sg:postcode":"48092",
    "sg:province":"MI",
    "sg:tags":[
        "home",
        "improvement"
    ],
    "wof:name":"CBJ Enterprises Inc",
    "wof:placetype":"venue"
},
  "geometry": {"coordinates":[-83.06039199999999,42.519456],"type":"Point"}
}