{
  "type": "Feature",
  "properties": {
    "iso:country":"US",
    "sg:address":"5454 Split Rail Ln",
    "sg:city":"Brighton",
    "sg:classifiers":[
        {
            "category":"Building & Trades",
            "subcategory":"Construction",
            "type":"Services"
        }
    ],
    "sg:phone":"+1 810 220 4565",
    "sg:postcode":"48114",
    "sg:province":"MI",
    "sg:tags":[
        "house"
    ],
    "wof:name":"Woodworth Builders",
    "wof:placetype":"venue"
},
  "geometry": {"coordinates":[-83.746379,42.526845],"type":"Point"}
}