{
  "type": "Feature",
  "properties": {
    "iso:country":"US",
    "sg:address":"4560 National Ave",
    "sg:city":"Bay City",
    "sg:classifiers":[
        {
            "category":"Communications",
            "subcategory":"Film & Video Production",
            "type":"Services"
        }
    ],
    "sg:phone":"+1 989 684 9949",
    "sg:postcode":"48706",
    "sg:province":"MI",
    "sg:tags":[
        "motion"
    ],
    "wof:name":"Jet Plane Productions",
    "wof:placetype":"venue"
},
  "geometry": {"coordinates":[-83.87149100000001,43.652726],"type":"Point"}
}