{
  "type": "Feature",
  "properties": {
    "iso:country":"US",
    "sg:address":"25224 Dallas Dr",
    "sg:city":"Grosse Ile",
    "sg:classifiers":[
        {
            "category":"Professional",
            "type":"Services"
        }
    ],
    "sg:phone":"+1 734 675 3393",
    "sg:postcode":"48138",
    "sg:province":"MI",
    "wof:name":"Outback Products",
    "wof:placetype":"venue"
},
  "geometry": {"coordinates":[-83.157825,42.125072],"type":"Point"}
}