{
  "type": "Feature",
  "properties": {
    "iso:country":"US",
    "sg:address":"44201 Cherbourg St",
    "sg:city":"Canton",
    "sg:classifiers":[
        {
            "category":"Professional",
            "subcategory":"Business Services",
            "type":"Services"
        }
    ],
    "sg:phone":"+1 734 398 6900",
    "sg:postcode":"48188",
    "sg:province":"MI",
    "wof:name":"Varsity Inspection Professiona",
    "wof:placetype":"venue"
},
  "geometry": {"coordinates":[-83.476928,42.297165],"type":"Point"}
}