{
  "type": "Feature",
  "properties": {
    "iso:country":"US",
    "sg:address":"3550 Airline Rd",
    "sg:city":"Muskegon",
    "sg:classifiers":[
        {
            "category":"Retail",
            "subcategory":"Car Wash",
            "type":"Services"
        }
    ],
    "sg:phone":"+1 231 733 0733",
    "sg:postcode":"49444",
    "sg:province":"MI",
    "sg:tags":[
        "automobile",
        "detail",
        "clean"
    ],
    "wof:name":"Sun Coast Auto Ctr",
    "wof:placetype":"venue"
},
  "geometry": {"coordinates":[-86.23760900000001,43.192456],"type":"Point"}
}