{
  "type": "Feature",
  "properties": {
    "iso:country":"US",
    "sg:address":"1205 N West Ave",
    "sg:city":"Jackson",
    "sg:classifiers":[
        {
            "category":"Restaurant",
            "type":"Food & Drink"
        }
    ],
    "sg:menulink":"http://www.allmenus.com/mi/jackson/200501-long-john-silvers/menu/",
    "sg:phone":"+1 517 783 4405",
    "sg:postcode":"49202",
    "sg:province":"MI",
    "sg:tags":[
        "seafood",
        "american"
    ],
    "wof:name":"Long John Silver's",
    "wof:placetype":"venue"
},
  "geometry": {"coordinates":[-84.423181,42.263552],"type":"Point"}
}