{
  "type": "Feature",
  "properties": {
    "iso:country":"US",
    "sg:address":"29050 Wellington Rd W",
    "sg:city":"Southfield",
    "sg:classifiers":[
        {
            "category":"Building & Trades",
            "subcategory":"Cleaning & Sanitation",
            "type":"Services"
        }
    ],
    "sg:phone":"+1 248 357 0225",
    "sg:postcode":"48034",
    "sg:province":"MI",
    "sg:tags":[
        "maintenance"
    ],
    "wof:name":"Wellington Place Manor",
    "wof:placetype":"venue"
},
  "geometry": {"coordinates":[-83.29357899999999,42.504022],"type":"Point"}
}