{
  "type": "Feature",
  "properties": {
    "iso:country":"US",
    "sg:address":"3801 Alpine Ave NW",
    "sg:city":"Comstock Park",
    "sg:classifiers":[
        {
            "category":"Home & Garden",
            "subcategory":"Garden Supply",
            "type":"Retail Goods"
        }
    ],
    "sg:phone":"+1 616 784 0542",
    "sg:postcode":"49321",
    "sg:province":"MI",
    "sg:tags":[
        "center"
    ],
    "wof:name":"Flowerland",
    "wof:placetype":"venue"
},
  "geometry": {"coordinates":[-85.689651,43.033226],"type":"Point"}
}