{
  "type": "Feature",
  "properties": {
    "iso:country":"US",
    "sg:address":"724 Columbia St",
    "sg:city":"Caro",
    "sg:classifiers":[
        {
            "category":"Government",
            "subcategory":"Office",
            "type":"Public Place"
        }
    ],
    "sg:phone":"+1 989 673 2840",
    "sg:postcode":"48723",
    "sg:province":"MI",
    "sg:tags":[
        "govt",
        "city"
    ],
    "wof:name":"Caro Waste Water Treatment Plt",
    "wof:placetype":"venue"
},
  "geometry": {"coordinates":[-83.391502,43.48339],"type":"Point"}
}