{
  "type": "Feature",
  "properties": {
    "iso:country":"US",
    "sg:address":"343 Elm St",
    "sg:city":"Dimondale",
    "sg:classifiers":[
        {
            "category":"Building & Trades",
            "subcategory":"Construction",
            "type":"Services"
        }
    ],
    "sg:phone":"+1 517 646 7567",
    "sg:postcode":"48821",
    "sg:province":"MI",
    "sg:tags":[
        "house"
    ],
    "wof:name":"Kogut Construction",
    "wof:placetype":"venue"
},
  "geometry": {"coordinates":[-84.649856,42.642042],"type":"Point"}
}