{
  "type": "Feature",
  "properties": {
    "iso:country":"US",
    "sg:address":"834 E Grand River Ave",
    "sg:city":"Brighton",
    "sg:classifiers":[
        {
            "category":"Building & Trades",
            "subcategory":"Construction",
            "type":"Services"
        }
    ],
    "sg:phone":"+1 810 227 4525",
    "sg:postcode":"48116",
    "sg:province":"MI",
    "sg:tags":[
        "house",
        "real estate"
    ],
    "wof:name":"Asher Homes Inc",
    "wof:placetype":"venue"
},
  "geometry": {"coordinates":[-83.771624,42.523612],"type":"Point"}
}