{
  "type": "Feature",
  "properties": {
    "iso:country":"US",
    "sg:address":"5500 S Harvey St",
    "sg:city":"Muskegon",
    "sg:classifiers":[
        {
            "category":"Shopping",
            "type":"Retail Goods"
        }
    ],
    "sg:phone":"+1 231 798 7706",
    "sg:postcode":"49444",
    "sg:province":"MI",
    "sg:tags":[
        "hearing",
        "equipment",
        "supply",
        "impaired"
    ],
    "wof:name":"Miracle-Ear",
    "wof:placetype":"venue"
},
  "geometry": {"coordinates":[-86.20576199999999,43.150869],"type":"Point"}
}