{
  "type": "Feature",
  "properties": {
    "iso:country":"US",
    "sg:address":"2420 Mershon Dr",
    "sg:city":"Ann Arbor",
    "sg:classifiers":[
        {
            "category":"Retail",
            "subcategory":"Portrait Studio",
            "type":"Services"
        }
    ],
    "sg:phone":"+1 734 665 8830",
    "sg:postcode":"48103",
    "sg:province":"MI",
    "sg:tags":[
        "photo"
    ],
    "wof:name":"Thurman Marti Photography",
    "wof:placetype":"venue"
},
  "geometry": {"coordinates":[-83.767652,42.252125],"type":"Point"}
}