{
  "type": "Feature",
  "properties": {
    "iso:country":"US",
    "sg:address":"2881 Monroe St",
    "sg:city":"Dearborn",
    "sg:classifiers":[
        {
            "category":"Government",
            "subcategory":"Office",
            "type":"Public Place"
        }
    ],
    "sg:phone":"+1 313 277 1428",
    "sg:postcode":"48124",
    "sg:province":"MI",
    "sg:tags":[
        "vet",
        "center"
    ],
    "wof:name":"Dearborn Vet Center",
    "wof:placetype":"venue"
},
  "geometry": {"coordinates":[-83.250817,42.291663],"type":"Point"}
}