{
  "type": "Feature",
  "properties": {
    "iso:country":"US",
    "sg:address":"1860 E Hile Rd",
    "sg:city":"Muskegon",
    "sg:classifiers":[
        {
            "category":"Organizations",
            "subcategory":"Religious Organization",
            "type":"Services"
        }
    ],
    "sg:phone":"+1 231 733 0603",
    "sg:postcode":"49444",
    "sg:province":"MI",
    "sg:tags":[
        "church"
    ],
    "wof:name":"Dr Martin Luther Lutheran Chr",
    "wof:placetype":"venue"
},
  "geometry": {"coordinates":[-86.200839,43.168877],"type":"Point"}
}