{
  "type": "Feature",
  "properties": {
    "iso:country":"US",
    "sg:address":"226 N Main St",
    "sg:city":"Evart",
    "sg:classifiers":[
        {
            "category":"Shopping",
            "subcategory":"Jewelry",
            "type":"Retail Goods"
        }
    ],
    "sg:phone":"+1 231 734 5068",
    "sg:postcode":"49631",
    "sg:province":"MI",
    "sg:tags":[
        "jeweler"
    ],
    "wof:name":"Evart Jewelers",
    "wof:placetype":"venue"
},
  "geometry": {"coordinates":[-85.259325,43.90284],"type":"Point"}
}