{
  "type": "Feature",
  "properties": {
    "iso:country":"US",
    "sg:address":"11928 Upton Rd",
    "sg:city":"Grand Ledge",
    "sg:classifiers":[
        {
            "category":"Building & Trades",
            "subcategory":"Construction",
            "type":"Services"
        }
    ],
    "sg:phone":"+1 517 627 2056",
    "sg:postcode":"48837",
    "sg:province":"MI",
    "sg:tags":[
        "hanging",
        "contractor"
    ],
    "wof:name":"L B Parking Lots Painting",
    "wof:placetype":"venue"
},
  "geometry": {"coordinates":[-84.691322,42.734654],"type":"Point"}
}