{
  "type": "Feature",
  "properties": {
    "iso:country":"US",
    "sg:address":"1651 Kingsway Ct",
    "sg:city":"Trenton",
    "sg:classifiers":[
        {
            "category":"Professional",
            "subcategory":"Engineering",
            "type":"Services"
        }
    ],
    "sg:phone":"+1 734 692 0123",
    "sg:postcode":"48183",
    "sg:province":"MI",
    "sg:tags":[
        "energy",
        "conservation",
        "engineer"
    ],
    "wof:name":"Onsite Energy Corporation",
    "wof:placetype":"venue"
},
  "geometry": {"coordinates":[-83.191271,42.15528],"type":"Point"}
}