{
  "type": "Feature",
  "properties": {
    "iso:country":"US",
    "sg:address":"1362 N Whitehall Rd",
    "sg:city":"North Muskegon",
    "sg:classifiers":[
        {
            "category":"Restaurant",
            "type":"Food & Drink"
        }
    ],
    "sg:phone":"+1 231 744 1450",
    "sg:postcode":"49445",
    "sg:province":"MI",
    "wof:name":"Dah Hu Restaurant",
    "wof:placetype":"venue"
},
  "geometry": {"coordinates":[-86.261426,43.276576],"type":"Point"}
}