{
  "type": "Feature",
  "properties": {
    "iso:country":"US",
    "sg:address":"42249 Lochmoor St",
    "sg:city":"Clinton Township",
    "sg:classifiers":[
        {
            "category":"Professional",
            "subcategory":"Accounting & Tax Preparation",
            "type":"Services"
        }
    ],
    "sg:phone":"+1 586 263 9813",
    "sg:postcode":"48038",
    "sg:province":"MI",
    "sg:tags":[
        "return"
    ],
    "wof:name":"David Johnstone Taxes & Insura",
    "wof:placetype":"venue"
},
  "geometry": {"coordinates":[-82.94591,42.606637],"type":"Point"}
}