{
  "type": "Feature",
  "properties": {
    "iso:country":"US",
    "sg:address":"23604 36th Ave",
    "sg:city":"Ravenna",
    "sg:classifiers":[
        {
            "category":"Organizations",
            "subcategory":"Labor Organization",
            "type":"Services"
        }
    ],
    "sg:phone":"+1 231 853 5530",
    "sg:postcode":"49451",
    "sg:province":"MI",
    "wof:name":"First Place Cable Lc",
    "wof:placetype":"venue"
},
  "geometry": {"coordinates":[-85.87927000000001,43.202396],"type":"Point"}
}