{
  "type": "Feature",
  "properties": {
    "iso:country":"US",
    "sg:address":"1115 Holland St",
    "sg:city":"Birmingham",
    "sg:classifiers":[
        {
            "category":"Building & Trades",
            "subcategory":"Construction",
            "type":"Services"
        }
    ],
    "sg:phone":"+1 248 594 5790",
    "sg:postcode":"48009",
    "sg:province":"MI",
    "sg:tags":[
        "contractor"
    ],
    "wof:name":"Hunter Robert Homes",
    "wof:placetype":"venue"
},
  "geometry": {"coordinates":[-83.205308,42.541496],"type":"Point"}
}