{
  "type": "Feature",
  "properties": {
    "iso:country":"US",
    "sg:address":"29550 Grand River Ave",
    "sg:city":"Farmington Hills",
    "sg:classifiers":[
        {
            "category":"Restaurant",
            "type":"Food & Drink"
        }
    ],
    "sg:phone":"+1 248 477 9000",
    "sg:postcode":"48336",
    "sg:province":"MI",
    "wof:name":"Sitar India Restaurant",
    "wof:placetype":"venue"
},
  "geometry": {"coordinates":[-83.33820299999999,42.4492],"type":"Point"}
}