{
  "type": "Feature",
  "properties": {
    "iso:country":"US",
    "sg:address":"7458 Beaverland St",
    "sg:city":"Redford",
    "sg:classifiers":[
        {
            "category":"Arts & Performance",
            "subcategory":"Theater",
            "type":"Entertainment"
        }
    ],
    "sg:phone":"+1 313 563 7920",
    "sg:postcode":"48239",
    "sg:province":"MI",
    "sg:tags":[
        "group"
    ],
    "wof:name":"Fantasy Entertainment",
    "wof:placetype":"venue"
},
  "geometry": {"coordinates":[-83.262548,42.345692],"type":"Point"}
}