{
  "type": "Feature",
  "properties": {
    "iso:country":"US",
    "sg:address":"522 W 2nd St",
    "sg:city":"Pinconning",
    "sg:classifiers":[
        {
            "category":"Travel",
            "subcategory":"Hotels & Motels",
            "type":"Entertainment"
        }
    ],
    "sg:phone":"+1 989 879 5422",
    "sg:postcode":"48650",
    "sg:province":"MI",
    "sg:tags":[
        "operation"
    ],
    "wof:name":"Gibson Motel",
    "wof:placetype":"venue"
},
  "geometry": {"coordinates":[-83.96773899999999,43.856545],"type":"Point"}
}