{
  "type": "Feature",
  "properties": {
    "iso:country":"US",
    "sg:address":"5845 Lincoln Ave",
    "sg:city":"Hudsonville",
    "sg:classifiers":[
        {
            "category":"Insurance",
            "subcategory":"Insurance Agent",
            "type":"Services"
        }
    ],
    "sg:phone":"+1 616 669 7995",
    "sg:postcode":"49426",
    "sg:province":"MI",
    "wof:name":"Simmons & Simmons Agency",
    "wof:placetype":"venue"
},
  "geometry": {"coordinates":[-85.87025,42.874661],"type":"Point"}
}