{
  "type": "Feature",
  "properties": {
    "iso:country":"US",
    "sg:address":"394 W Beaver Rd",
    "sg:city":"Kawkawlin",
    "sg:classifiers":[
        {
            "category":"Building & Trades",
            "subcategory":"Construction",
            "type":"Services"
        }
    ],
    "sg:phone":"+1 989 662 4841",
    "sg:postcode":"48631",
    "sg:province":"MI",
    "sg:tags":[
        "general",
        "contractor"
    ],
    "wof:name":"D Louis Builders",
    "wof:placetype":"venue"
},
  "geometry": {"coordinates":[-84.06749000000001,43.668082],"type":"Point"}
}