{
  "type": "Feature",
  "properties": {
    "iso:country":"US",
    "sg:address":"24142 W Warren St Ste A",
    "sg:city":"Dearborn Heights",
    "sg:classifiers":[
        {
            "category":"Shopping",
            "subcategory":"Pharmacy",
            "type":"Retail Goods"
        }
    ],
    "sg:phone":"+1 313 730 0677",
    "sg:postcode":"48127",
    "sg:province":"MI",
    "sg:tags":[
        "drugstore"
    ],
    "wof:name":"123 Pharmacy",
    "wof:placetype":"venue"
},
  "geometry": {"coordinates":[-83.27482000000001,42.341529],"type":"Point"}
}