{
  "type": "Feature",
  "properties": {
    "iso:country":"US",
    "sg:address":"2138 Fox Rd",
    "sg:city":"Jackson",
    "sg:classifiers":[
        {
            "category":"Farming",
            "subcategory":"Dairy Farm",
            "type":"Manufacturing & Wholesale Goods"
        }
    ],
    "sg:phone":"+1 517 522 4318",
    "sg:postcode":"49201",
    "sg:province":"MI",
    "wof:name":"A Sova",
    "wof:placetype":"venue"
},
  "geometry": {"coordinates":[-84.289705,42.26671],"type":"Point"}
}