{
  "type": "Feature",
  "properties": {
    "iso:country":"US",
    "sg:address":"1220 W Auburn Rd",
    "sg:city":"Rochester Hills",
    "sg:classifiers":[
        {
            "category":"Professional",
            "type":"Services"
        }
    ],
    "sg:phone":"+1 248 689 6481",
    "sg:postcode":"48309",
    "sg:province":"MI",
    "sg:tags":[
        "establishment"
    ],
    "wof:name":"KOR Enterprises",
    "wof:placetype":"venue"
},
  "geometry": {"coordinates":[-83.155873,42.635542],"type":"Point"}
}