{
  "type": "Feature",
  "properties": {
    "iso:country":"US",
    "sg:address":"24600 F V Pankow Blvd",
    "sg:city":"Clinton Township",
    "sg:classifiers":[
        {
            "category":"Education",
            "subcategory":"School",
            "type":"Public Place"
        }
    ],
    "sg:phone":"+1 586 783 6570",
    "sg:postcode":"48035",
    "sg:province":"MI",
    "sg:tags":[
        "high",
        "middle",
        "elementary"
    ],
    "wof:name":"L'anse Creuse School District",
    "wof:placetype":"venue"
},
  "geometry": {"coordinates":[-82.861589,42.621336],"type":"Point"}
}