{
  "type": "Feature",
  "properties": {
    "iso:country":"US",
    "sg:address":"228 Hesse St",
    "sg:city":"Howell",
    "sg:classifiers":[
        {
            "category":"Real Estate",
            "subcategory":"Real Estate Agent",
            "type":"Services"
        }
    ],
    "sg:phone":"+1 517 548 3717",
    "sg:postcode":"48843",
    "sg:province":"MI",
    "wof:name":"Estate of Roy Harold Oesterle",
    "wof:placetype":"venue"
},
  "geometry": {"coordinates":[-83.923517,42.606762],"type":"Point"}
}