{
  "type": "Feature",
  "properties": {
    "iso:country":"US",
    "sg:address":"110 N State St",
    "sg:city":"St Ignace",
    "sg:classifiers":[
        {
            "category":"Shopping",
            "subcategory":"Used Merchandise",
            "type":"Retail Goods"
        }
    ],
    "sg:phone":"+1 906 643 6565",
    "sg:postcode":"49781",
    "sg:province":"MI",
    "sg:tags":[
        "antique"
    ],
    "wof:name":"Emporium",
    "wof:placetype":"venue"
},
  "geometry": {"coordinates":[-84.725255,45.868106],"type":"Point"}
}