{
  "type": "Feature",
  "properties": {
    "iso:country":"US",
    "sg:address":"2750 Ridgeway Ct",
    "sg:city":"Commerce Twp",
    "sg:classifiers":[
        {
            "category":"Professional",
            "subcategory":"Management & Consulting",
            "type":"Services"
        }
    ],
    "sg:phone":"+1 248 669 8100",
    "sg:postcode":"48390",
    "sg:province":"MI",
    "sg:tags":[
        "export"
    ],
    "sg:website":"www.rria.com",
    "wof:name":"R Robb Intl Assoc Inc",
    "wof:placetype":"venue"
},
  "geometry": {"coordinates":[-83.44640699999999,42.568058],"type":"Point"}
}