{
  "type": "Feature",
  "properties": {
    "iso:country":"US",
    "sg:address":"40 E Davison Lake Rd",
    "sg:city":"Metamora",
    "sg:classifiers":[
        {
            "category":"Building & Trades",
            "subcategory":"Landscaping Services",
            "type":"Services"
        }
    ],
    "sg:phone":"+1 248 969 4300",
    "sg:postcode":"48455",
    "sg:province":"MI",
    "sg:tags":[
        "tree"
    ],
    "wof:name":"T & L Tree Transplanting",
    "wof:placetype":"venue"
},
  "geometry": {"coordinates":[-83.287524,42.883906],"type":"Point"}
}