{
  "type": "Feature",
  "properties": {
    "iso:country":"US",
    "sg:address":"517 Main St",
    "sg:city":"Morrice",
    "sg:classifiers":[
        {
            "category":"Organizations",
            "subcategory":"Religious Organization",
            "type":"Services"
        }
    ],
    "sg:phone":"+1 517 625 6140",
    "sg:postcode":"48857",
    "sg:province":"MI",
    "sg:tags":[
        "church"
    ],
    "wof:name":"St Mary's Church & Rectory",
    "wof:placetype":"venue"
},
  "geometry": {"coordinates":[-84.177953,42.840965],"type":"Point"}
}