{
  "type": "Feature",
  "properties": {
    "iso:country":"US",
    "sg:address":"150 Van Buren St",
    "sg:city":"Manistee",
    "sg:classifiers":[
        {
            "category":"Wholesale",
            "subcategory":"Machinery & Supplies",
            "type":"Manufacturing & Wholesale Goods"
        }
    ],
    "sg:phone":"+1 231 723 1136",
    "sg:postcode":"49660",
    "sg:province":"MI",
    "sg:tags":[
        "equipment",
        "welding"
    ],
    "wof:name":"Lake Welding Supply Co",
    "wof:placetype":"venue"
},
  "geometry": {"coordinates":[-86.321679,44.253505],"type":"Point"}
}