{
  "type": "Feature",
  "properties": {
    "iso:country":"US",
    "sg:address":"4301 Orchard Lake Rd",
    "sg:city":"West Bloomfield Township",
    "sg:classifiers":[
        {
            "category":"Restaurant",
            "type":"Food & Drink"
        }
    ],
    "sg:phone":"+1 248 737 6888",
    "sg:postcode":"48323",
    "sg:province":"MI",
    "sg:tags":[
        "italian"
    ],
    "wof:name":"Cheesy Luigi's",
    "wof:placetype":"venue"
},
  "geometry": {"coordinates":[-83.36214099999999,42.574212],"type":"Point"}
}