{
  "type": "Feature",
  "properties": {
    "iso:country":"US",
    "sg:address":"511 N Gulley Rd",
    "sg:city":"Dearborn Heights",
    "sg:classifiers":[
        {
            "category":"Personal",
            "type":"Services"
        }
    ],
    "sg:phone":"+1 313 562 5228",
    "sg:postcode":"48127",
    "sg:province":"MI",
    "wof:name":"Happy Pets At Home",
    "wof:placetype":"venue"
},
  "geometry": {"coordinates":[-83.28679099999999,42.318364],"type":"Point"}
}