{
  "type": "Feature",
  "properties": {
    "iso:country":"US",
    "sg:address":"1203 Division St",
    "sg:city":"Adrian",
    "sg:classifiers":[
        {
            "category":"Professional",
            "type":"Services"
        }
    ],
    "sg:phone":"+1 517 263 4373",
    "sg:postcode":"49221",
    "sg:province":"MI",
    "sg:tags":[
        "establishment"
    ],
    "wof:name":"Hometown USA",
    "wof:placetype":"venue"
},
  "geometry": {"coordinates":[-84.033354,41.880051],"type":"Point"}
}