{
  "type": "Feature",
  "properties": {
    "iso:country":"US",
    "sg:address":"4626 N Owens Ln",
    "sg:city":"Midland",
    "sg:classifiers":[
        {
            "category":"Building & Trades",
            "subcategory":"Construction",
            "type":"Services"
        }
    ],
    "sg:phone":"+1 989 689 3319",
    "sg:postcode":"48642",
    "sg:province":"MI",
    "sg:tags":[
        "house"
    ],
    "wof:name":"George Owens Builders",
    "wof:placetype":"venue"
},
  "geometry": {"coordinates":[-84.29385499999999,43.742458],"type":"Point"}
}