{
  "type": "Feature",
  "properties": {
    "iso:country":"US",
    "sg:address":"1041 King Hwy",
    "sg:city":"Kalamazoo",
    "sg:classifiers":[
        {
            "category":"Sports & Exercise",
            "subcategory":"Golf",
            "type":"Entertainment"
        }
    ],
    "sg:phone":"+1 269 345 8329",
    "sg:postcode":"49001",
    "sg:province":"MI",
    "sg:tags":[
        "course",
        "executive",
        "public"
    ],
    "wof:name":"Red Arrow Golf Course",
    "wof:placetype":"venue"
},
  "geometry": {"coordinates":[-85.56712899999999,42.290172],"type":"Point"}
}