{
  "type": "Feature",
  "properties": {
    "iso:country":"US",
    "sg:address":"8060 Main St",
    "sg:city":"Dexter",
    "sg:classifiers":[
        {
            "category":"Shopping",
            "subcategory":"Photographic Equipment",
            "type":"Retail Goods"
        }
    ],
    "sg:phone":"+1 734 426 4584",
    "sg:postcode":"48130",
    "sg:province":"MI",
    "sg:tags":[
        "repair",
        "camera"
    ],
    "wof:name":"Huron Camera & Video",
    "wof:placetype":"venue"
},
  "geometry": {"coordinates":[-83.889387,42.33854],"type":"Point"}
}