{
  "type": "Feature",
  "properties": {
    "iso:country":"US",
    "sg:address":"31095 Floralview Dr S",
    "sg:city":"Farmington Hills",
    "sg:classifiers":[
        {
            "category":"Banks & Credit Unions",
            "subcategory":"Bank",
            "type":"Services"
        }
    ],
    "sg:phone":"+1 248 661 8344",
    "sg:postcode":"48331",
    "sg:province":"MI",
    "sg:tags":[
        "loan"
    ],
    "wof:name":"Equity Corporate Housing",
    "wof:placetype":"venue"
},
  "geometry": {"coordinates":[-83.435962,42.521831],"type":"Point"}
}