{
  "type": "Feature",
  "properties": {
    "iso:country":"US",
    "sg:address":"24360 Novi Rd Ste A",
    "sg:city":"Novi",
    "sg:classifiers":[
        {
            "category":"Retail",
            "subcategory":"Veterinary Services",
            "type":"Services"
        },
        {
            "category":"Retail",
            "subcategory":"Animal Services",
            "type":"Services"
        }
    ],
    "sg:phone":"+1 248 348 1788",
    "sg:postcode":"48375",
    "sg:province":"MI",
    "sg:tags":[
        "emergency",
        "pet",
        "hospital",
        "specialty",
        "clinic",
        "veterinarian"
    ],
    "sg:website":"http://www.theanimalemergencycenter.com",
    "wof:name":"Animal Emergency Center",
    "wof:placetype":"venue"
},
  "geometry": {"coordinates":[-83.47483200000001,42.468166],"type":"Point"}
}