{
  "type": "Feature",
  "properties": {
    "iso:country":"US",
    "sg:address":"413 E Pere Marquette St",
    "sg:city":"Ludington",
    "sg:classifiers":[
        {
            "category":"Organizations",
            "subcategory":"Religious Organization",
            "type":"Services"
        }
    ],
    "sg:phone":"+1 231 845 1920",
    "sg:postcode":"49431",
    "sg:province":"MI",
    "sg:tags":[
        "church"
    ],
    "wof:name":"Ludington Seventh Day Adventst",
    "wof:placetype":"venue"
},
  "geometry": {"coordinates":[-86.443518,43.957771],"type":"Point"}
}