{
  "type": "Feature",
  "properties": {
    "iso:country":"US",
    "sg:address":"5365 Maple Lane Rd",
    "sg:city":"Rives Junction",
    "sg:classifiers":[
        {
            "category":"Social Services",
            "subcategory":"Child Care",
            "type":"Services"
        }
    ],
    "sg:phone":"+1 517 569 2015",
    "sg:postcode":"49277",
    "sg:province":"MI",
    "wof:name":"Busy Bee Playground",
    "wof:placetype":"venue"
},
  "geometry": {"coordinates":[-84.487679,42.37059],"type":"Point"}
}