{
  "type": "Feature",
  "properties": {
    "iso:country":"US",
    "sg:address":"16777 Lincoln St",
    "sg:city":"Grand Haven",
    "sg:classifiers":[
        {
            "category":"Retail",
            "subcategory":"Funeral Services",
            "type":"Services"
        }
    ],
    "sg:phone":"+1 616 844 4200",
    "sg:postcode":"49417",
    "sg:province":"MI",
    "sg:tags":[
        "director"
    ],
    "wof:name":"Clock Funeral Home",
    "wof:placetype":"venue"
},
  "geometry": {"coordinates":[-86.20340299999999,43.00125],"type":"Point"}
}