{
  "type": "Feature",
  "properties": {
    "iso:country":"US",
    "sg:address":"3060 Breton Rd SE",
    "sg:city":"Kentwood",
    "sg:classifiers":[
        {
            "category":"Building & Trades",
            "subcategory":"Construction",
            "type":"Services"
        }
    ],
    "sg:phone":"+1 616 949 6660",
    "sg:postcode":"49512",
    "sg:province":"MI",
    "sg:tags":[
        "excavating",
        "contractor"
    ],
    "sg:website":"www.velting.com",
    "wof:name":"Velting Contractors Inc",
    "wof:placetype":"venue"
},
  "geometry": {"coordinates":[-85.607692,42.907334],"type":"Point"}
}