{
  "type": "Feature",
  "properties": {
    "iso:country":"US",
    "sg:address":"2428 Anderson Rd",
    "sg:city":"Saginaw",
    "sg:classifiers":[
        {
            "category":"Professional",
            "subcategory":"Computer Services",
            "type":"Services"
        }
    ],
    "sg:phone":"+1 989 799 8710",
    "sg:postcode":"48603",
    "sg:province":"MI",
    "sg:tags":[
        "consulting"
    ],
    "wof:name":"Accessible Computer Solutions",
    "wof:placetype":"venue"
},
  "geometry": {"coordinates":[-84.010462,43.441793],"type":"Point"}
}