{
  "type": "Feature",
  "properties": {
    "iso:country":"US",
    "sg:address":"8504 Secor Rd",
    "sg:city":"Lambertville",
    "sg:classifiers":[
        {
            "category":"Restaurant",
            "type":"Food & Drink"
        }
    ],
    "sg:phone":"+1 734 856 5111",
    "sg:postcode":"48144",
    "sg:province":"MI",
    "sg:website":"www.jeffreys.com",
    "wof:name":"Jeffrey's Restaurant",
    "wof:placetype":"venue"
},
  "geometry": {"coordinates":[-83.62640500000001,41.769762],"type":"Point"}
}