{
  "type": "Feature",
  "properties": {
    "iso:country":"US",
    "sg:address":"11020 W Kipling Dr",
    "sg:city":"Rudyard",
    "sg:classifiers":[
        {
            "category":"Home & Garden",
            "subcategory":"Building Materials",
            "type":"Retail Goods"
        }
    ],
    "sg:phone":"+1 906 478 6221",
    "sg:postcode":"49780",
    "sg:province":"MI",
    "sg:tags":[
        "lumber"
    ],
    "sg:website":"www.unitedbuildingcenters.com",
    "wof:name":"United Building Ctr",
    "wof:placetype":"venue"
},
  "geometry": {"coordinates":[-84.592709,46.234011],"type":"Point"}
}