{
  "type": "Feature",
  "properties": {
    "iso:country":"US",
    "sg:address":"5969 Kalamazoo Ave SE",
    "sg:city":"Grand Rapids",
    "sg:classifiers":[
        {
            "category":"Retail",
            "subcategory":"Auto Repair",
            "type":"Services"
        }
    ],
    "sg:phone":"+1 616 455 6677",
    "sg:postcode":"49508",
    "sg:province":"MI",
    "sg:tags":[
        "automobile",
        "lubrication",
        "general"
    ],
    "wof:name":"Fast Trak Quick Oil & Lube",
    "wof:placetype":"venue"
},
  "geometry": {"coordinates":[-85.624966,42.855733],"type":"Point"}
}