{
  "type": "Feature",
  "properties": {
    "iso:country":"US",
    "sg:address":"11332 Riverside Dr",
    "sg:city":"Stanwood",
    "sg:classifiers":[
        {
            "category":"Organizations",
            "subcategory":"Religious Organization",
            "type":"Services"
        }
    ],
    "sg:phone":"+1 231 527 1560",
    "sg:postcode":"49346",
    "sg:province":"MI",
    "sg:tags":[
        "church"
    ],
    "wof:name":"Healing Word Ministries",
    "wof:placetype":"venue"
},
  "geometry": {"coordinates":[-85.461787,43.632589],"type":"Point"}
}