{
  "type": "Feature",
  "properties": {
    "iso:country":"US",
    "sg:address":"2160 W Hill Rd",
    "sg:city":"Flint",
    "sg:classifiers":[
        {
            "category":"Restaurant",
            "type":"Food & Drink"
        }
    ],
    "sg:phone":"+1 810 234 5444",
    "sg:postcode":"48507",
    "sg:province":"MI",
    "sg:tags":[
        "breakfast",
        "brunch",
        "buffet"
    ],
    "sg:website":"www.thompsoncreekturkeyfarm.com/",
    "wof:name":"Thompson Creek Turkey Farm",
    "wof:placetype":"venue"
},
  "geometry": {"coordinates":[-83.718447,42.944657],"type":"Point"}
}