{
  "type": "Feature",
  "properties": {
    "iso:country":"US",
    "sg:address":"19990 Arcadia Dr",
    "sg:city":"Clinton Twp",
    "sg:classifiers":[
        {
            "category":"Insurance",
            "subcategory":"Insurance Agent",
            "type":"Services"
        }
    ],
    "sg:phone":"+1 586 468 2767",
    "sg:postcode":"48036",
    "sg:province":"MI",
    "sg:tags":[
        "accident"
    ],
    "wof:name":"Healthplans",
    "wof:placetype":"venue"
},
  "geometry": {"coordinates":[-82.919,42.575763],"type":"Point"}
}