{
  "type": "Feature",
  "properties": {
    "iso:country":"US",
    "sg:address":"1010 Lincoln Ave",
    "sg:city":"Port Huron",
    "sg:classifiers":[
        {
            "category":"Health Services",
            "subcategory":"Hospital",
            "type":"Services"
        }
    ],
    "sg:phone":"+1 810 989 3347",
    "sg:postcode":"48060",
    "sg:province":"MI",
    "wof:name":"Port Huron Hospital Parkview",
    "wof:placetype":"venue"
},
  "geometry": {"coordinates":[-82.430632,42.98513],"type":"Point"}
}