{
  "type": "Feature",
  "properties": {
    "iso:country":"US",
    "sg:address":"135 S Saginaw St",
    "sg:city":"Chesaning",
    "sg:classifiers":[
        {
            "category":"Personal",
            "subcategory":"Beauty Salon",
            "type":"Services"
        }
    ],
    "sg:phone":"+1 989 845 6923",
    "sg:postcode":"48616",
    "sg:province":"MI",
    "sg:tags":[
        "shop"
    ],
    "wof:name":"Look Hair Nails & Tanning",
    "wof:placetype":"venue"
},
  "geometry": {"coordinates":[-84.116562,43.184734],"type":"Point"}
}