{
  "type": "Feature",
  "properties": {
    "iso:country":"US",
    "sg:address":"3550 US Hwy 23 N",
    "sg:city":"Alpena",
    "sg:classifiers":[
        {
            "category":"Wholesale",
            "subcategory":"Machinery & Supplies",
            "type":"Manufacturing & Wholesale Goods"
        }
    ],
    "sg:phone":"+1 989 356 3464",
    "sg:postcode":"49707",
    "sg:province":"MI",
    "sg:tags":[
        "contractor"
    ],
    "sg:website":"www.thompsonjeepalpena.com",
    "wof:name":"Thompson Sales & Svc Inc",
    "wof:placetype":"venue"
},
  "geometry": {"coordinates":[-83.45433800000001,45.101245],"type":"Point"}
}