{
  "type": "Feature",
  "properties": {
    "iso:country":"US",
    "sg:address":"230 S State St",
    "sg:city":"Zeeland",
    "sg:classifiers":[
        {
            "category":"Building & Trades",
            "subcategory":"Construction",
            "type":"Services"
        }
    ],
    "sg:phone":"+1 616 772 7201",
    "sg:postcode":"49464",
    "sg:province":"MI",
    "sg:tags":[
        "roofing",
        "contractor"
    ],
    "wof:name":"Gates Roofing & Construction",
    "wof:placetype":"venue"
},
  "geometry": {"coordinates":[-86.018873,42.80709],"type":"Point"}
}