{
  "type": "Feature",
  "properties": {
    "iso:country":"US",
    "sg:address":"22933 N Nunneley Rd Apt 102",
    "sg:city":"Clinton Township",
    "sg:classifiers":[
        {
            "category":"Real Estate",
            "subcategory":"Real Estate Operator",
            "type":"Services"
        }
    ],
    "sg:phone":"+1 586 463 7511",
    "sg:postcode":"48036",
    "sg:province":"MI",
    "sg:tags":[
        "apartment"
    ],
    "wof:name":"Harper Square",
    "wof:placetype":"venue"
},
  "geometry": {"coordinates":[-82.88629899999999,42.570301],"type":"Point"}
}