{
  "type": "Feature",
  "properties": {
    "iso:country":"US",
    "sg:address":"20700 Civic Center Dr",
    "sg:city":"Southfield",
    "sg:classifiers":[
        {
            "category":"Building & Trades",
            "subcategory":"Cleaning & Sanitation",
            "type":"Services"
        },
        {
            "category":"Real Estate",
            "subcategory":"Real Estate Agent",
            "type":"Services"
        }
    ],
    "sg:phone":"+1 248 233 1078",
    "sg:postcode":"48076",
    "sg:province":"MI",
    "sg:tags":[
        "janitor",
        "leasing",
        "rental"
    ],
    "wof:name":"Allied Maintenence RE Corp",
    "wof:placetype":"venue"
},
  "geometry": {"coordinates":[-83.248869,42.479744],"type":"Point"}
}