{
  "type": "Feature",
  "properties": {
    "iso:country":"US",
    "sg:address":"4165 Lake St",
    "sg:city":"Bridgman",
    "sg:classifiers":[
        {
            "category":"Building & Trades",
            "subcategory":"Plumbing",
            "type":"Services"
        }
    ],
    "sg:phone":"+1 269 465 5656",
    "sg:postcode":"49106",
    "sg:province":"MI",
    "sg:tags":[
        "conditioning",
        "air",
        "system",
        "contractor"
    ],
    "sg:website":"www.ptjassoc.com",
    "wof:name":"PTJ & Assoc Inc",
    "wof:placetype":"venue"
},
  "geometry": {"coordinates":[-86.553336,41.942976],"type":"Point"}
}