{
  "type": "Feature",
  "properties": {
    "iso:country":"US",
    "sg:address":"113 E Liberty St",
    "sg:city":"Ann Arbor",
    "sg:classifiers":[
        {
            "category":"Cafe",
            "type":"Food & Drink"
        }
    ],
    "sg:menulink":"http://www.allmenus.com/mi/ann-arbor/248005-cafe-japon/menu/",
    "sg:phone":"+1 734 332 6200",
    "sg:postcode":"48104",
    "sg:province":"MI",
    "sg:tags":[
        "wrap",
        "american",
        "sandwich"
    ],
    "wof:name":"Cafe Japon",
    "wof:placetype":"venue"
},
  "geometry": {"coordinates":[-83.74841600000001,42.279556],"type":"Point"}
}