{
  "type": "Feature",
  "properties": {
    "iso:country":"US",
    "sg:address":"8654 S Maple City Rd",
    "sg:city":"Maple City",
    "sg:classifiers":[
        {
            "category":"Restaurant",
            "type":"Food & Drink"
        }
    ],
    "sg:phone":"+1 231 228 6692",
    "sg:postcode":"49664",
    "sg:province":"MI",
    "sg:website":"www.pegtownstation.net",
    "wof:name":"Peg Town Station",
    "wof:placetype":"venue"
},
  "geometry": {"coordinates":[-85.856003,44.8442],"type":"Point"}
}