{
  "type": "Feature",
  "properties": {
    "iso:country":"US",
    "sg:address":"260 N Church St",
    "sg:city":"Zeeland",
    "sg:classifiers":[
        {
            "category":"Manufacturing",
            "subcategory":"Tools & Machinery",
            "type":"Manufacturing & Wholesale Goods"
        }
    ],
    "sg:phone":"+1 616 772 9511",
    "sg:postcode":"49464",
    "sg:province":"MI",
    "sg:tags":[
        "mold"
    ],
    "wof:name":"Proto-Tec Inc",
    "wof:placetype":"venue"
},
  "geometry": {"coordinates":[-86.014107,42.81568],"type":"Point"}
}