{
  "type": "Feature",
  "properties": {
    "iso:country":"US",
    "sg:address":"516 N Main St",
    "sg:city":"Wayland",
    "sg:classifiers":[
        {
            "category":"Professional",
            "type":"Services"
        }
    ],
    "sg:phone":"+1 269 792 4458",
    "sg:postcode":"49348",
    "sg:province":"MI",
    "sg:tags":[
        "establishment"
    ],
    "wof:name":"Premier Designs",
    "wof:placetype":"venue"
},
  "geometry": {"coordinates":[-85.643305,42.679979],"type":"Point"}
}