{
  "type": "Feature",
  "properties": {
    "iso:country":"US",
    "sg:address":"2801 W Big Beaver Rd",
    "sg:city":"Troy",
    "sg:classifiers":[
        {
            "category":"Coffee & Tea",
            "type":"Food & Drink"
        }
    ],
    "sg:menulink":"http://www.allmenus.com/mi/troy/125687-starbucks-coffee/menu/",
    "sg:phone":"+1 248 614 1770",
    "sg:postcode":"48084",
    "sg:province":"MI",
    "sg:tags":[
        "american"
    ],
    "wof:name":"Starbucks Coffee",
    "wof:placetype":"venue"
},
  "geometry": {"coordinates":[-83.18300499999999,42.561154],"type":"Point"}
}