{
  "type": "Feature",
  "properties": {
    "iso:country":"US",
    "sg:address":"780 Washington Blvd",
    "sg:city":"Lake Odessa",
    "sg:classifiers":[
        {
            "category":"Social Services",
            "subcategory":"Child Care",
            "type":"Services"
        }
    ],
    "sg:phone":"+1 616 374 8359",
    "sg:postcode":"48849",
    "sg:province":"MI",
    "sg:tags":[
        "day"
    ],
    "wof:name":"Room To Grow",
    "wof:placetype":"venue"
},
  "geometry": {"coordinates":[-85.14376,42.77799],"type":"Point"}
}