{
  "type": "Feature",
  "properties": {
    "iso:country":"US",
    "sg:address":"2885 Seabolt Ave",
    "sg:city":"Muskegon",
    "sg:classifiers":[
        {
            "category":"Building & Trades",
            "subcategory":"Construction",
            "type":"Services"
        }
    ],
    "sg:phone":"+1 231 719 8065",
    "sg:postcode":"49445",
    "sg:province":"MI",
    "sg:tags":[
        "residential",
        "general",
        "contractor"
    ],
    "wof:name":"Eling Construction Company",
    "wof:placetype":"venue"
},
  "geometry": {"coordinates":[-86.31836300000001,43.252723],"type":"Point"}
}