{
  "type": "Feature",
  "properties": {
    "iso:country":"US",
    "sg:address":"1120 W Michigan Ave",
    "sg:city":"Marshall",
    "sg:classifiers":[
        {
            "category":"Retail",
            "subcategory":"Car Wash",
            "type":"Services"
        }
    ],
    "sg:phone":"+1 269 781 9620",
    "sg:postcode":"49068",
    "sg:province":"MI",
    "sg:tags":[
        "carwash"
    ],
    "wof:name":"Mission Car Wash",
    "wof:placetype":"venue"
},
  "geometry": {"coordinates":[-84.977186,42.272043],"type":"Point"}
}