{
  "type": "Feature",
  "properties": {
    "iso:country":"US",
    "sg:address":"3766 Division Ave S",
    "sg:city":"Grand Rapids",
    "sg:classifiers":[
        {
            "category":"Bars & Pubs",
            "type":"Food & Drink"
        }
    ],
    "sg:phone":"+1 616 241 5166",
    "sg:postcode":"49548",
    "sg:province":"MI",
    "wof:name":"Southland Tavern",
    "wof:placetype":"venue"
},
  "geometry": {"coordinates":[-85.665117,42.89575],"type":"Point"}
}