{
  "type": "Feature",
  "properties": {
    "iso:country":"US",
    "sg:address":"7475 Grand River Rd",
    "sg:city":"Brighton",
    "sg:classifiers":[
        {
            "category":"Professional",
            "subcategory":"Printing & Photocopies",
            "type":"Services"
        }
    ],
    "sg:phone":"+1 810 229 2989",
    "sg:postcode":"48114",
    "sg:province":"MI",
    "sg:tags":[
        "lithographic",
        "commercial",
        "copying"
    ],
    "wof:name":"Big PDQ Ink Inc",
    "wof:placetype":"venue"
},
  "geometry": {"coordinates":[-83.80295099999999,42.565906],"type":"Point"}
}