{
  "type": "Feature",
  "properties": {
    "iso:country":"US",
    "sg:address":"3606 W Blair Townhall Rd",
    "sg:city":"Traverse City",
    "sg:classifiers":[
        {
            "category":"Recreation",
            "type":"Entertainment"
        }
    ],
    "sg:phone":"+1 231 943 4150",
    "sg:postcode":"49684",
    "sg:province":"MI",
    "sg:tags":[
        "county",
        "fair"
    ],
    "wof:name":"Northwestern Mich Fair Assn",
    "wof:placetype":"venue"
},
  "geometry": {"coordinates":[-85.647533,44.643031],"type":"Point"}
}