{
  "type": "Feature",
  "properties": {
    "iso:country":"US",
    "sg:address":"2536 Birchcrest Dr SE",
    "sg:city":"Grand Rapids",
    "sg:classifiers":[
        {
            "category":"Professional",
            "subcategory":"Management & Consulting",
            "type":"Services"
        }
    ],
    "sg:phone":"+1 616 942 0211",
    "sg:postcode":"49506",
    "sg:province":"MI",
    "wof:name":"Cascade Consulting",
    "wof:placetype":"venue"
},
  "geometry": {"coordinates":[-85.613901,42.917086],"type":"Point"}
}