{
  "type": "Feature",
  "properties": {
    "iso:country":"US",
    "sg:address":"1722 Fisher Rd",
    "sg:city":"Traverse City",
    "sg:classifiers":[
        {
            "category":"Building & Trades",
            "subcategory":"Construction",
            "type":"Services"
        }
    ],
    "sg:phone":"+1 231 933 0844",
    "sg:postcode":"49684",
    "sg:province":"MI",
    "sg:tags":[
        "dry wall",
        "contractor"
    ],
    "wof:name":"A 1 Drywall",
    "wof:placetype":"venue"
},
  "geometry": {"coordinates":[-85.776923,44.71437],"type":"Point"}
}