{
  "type": "Feature",
  "properties": {
    "iso:country":"US",
    "sg:address":"4335 Lake Michigan Dr NW",
    "sg:city":"Grand Rapids",
    "sg:classifiers":[
        {
            "category":"Professional",
            "subcategory":"Business Services",
            "type":"Services"
        }
    ],
    "sg:phone":"+1 616 791 8760",
    "sg:postcode":"49544",
    "sg:province":"MI",
    "sg:tags":[
        "notary",
        "public"
    ],
    "wof:name":"Joyce M Cnossen",
    "wof:placetype":"venue"
},
  "geometry": {"coordinates":[-85.774491,42.972265],"type":"Point"}
}