{
  "type": "Feature",
  "properties": {
    "iso:country":"US",
    "sg:address":"5085 Kendrick Ct SE",
    "sg:city":"Grand Rapids",
    "sg:classifiers":[
        {
            "category":"Wholesale",
            "subcategory":"Machinery & Supplies",
            "type":"Manufacturing & Wholesale Goods"
        }
    ],
    "sg:phone":"+1 616 956 6060",
    "sg:postcode":"49512",
    "sg:province":"MI",
    "sg:tags":[
        "equipment",
        "safety",
        "clothing"
    ],
    "wof:name":"Safety Services Inc",
    "wof:placetype":"venue"
},
  "geometry": {"coordinates":[-85.543621,42.872103],"type":"Point"}
}