{
  "type": "Feature",
  "properties": {
    "iso:country":"US",
    "sg:address":"2075 W Big Beaver Rd",
    "sg:city":"Troy",
    "sg:classifiers":[
        {
            "category":"Wholesale",
            "subcategory":"Hardware",
            "type":"Manufacturing & Wholesale Goods"
        }
    ],
    "sg:phone":"+1 248 649 9742",
    "sg:postcode":"48084",
    "sg:province":"MI",
    "sg:tags":[
        "lock",
        "locksmith"
    ],
    "sg:website":"www.strattec.com",
    "wof:name":"Strattec Security Corp",
    "wof:placetype":"venue"
},
  "geometry": {"coordinates":[-83.174983,42.56152],"type":"Point"}
}