{
  "type": "Feature",
  "properties": {
    "iso:country":"US",
    "sg:address":"8727 Taylor St",
    "sg:city":"Zeeland",
    "sg:classifiers":[
        {
            "category":"Building & Trades",
            "subcategory":"Construction",
            "type":"Services"
        }
    ],
    "sg:phone":"+1 616 875 4100",
    "sg:postcode":"49464",
    "sg:province":"MI",
    "sg:tags":[
        "concrete",
        "contractor"
    ],
    "wof:name":"Van Loo Poured Walls",
    "wof:placetype":"venue"
},
  "geometry": {"coordinates":[-85.99925399999999,42.928917],"type":"Point"}
}