{
  "type": "Feature",
  "properties": {
    "iso:country":"US",
    "sg:address":"38284 Mallast St",
    "sg:city":"Harrison Township",
    "sg:classifiers":[
        {
            "category":"Building & Trades",
            "subcategory":"Cleaning & Sanitation",
            "type":"Services"
        }
    ],
    "sg:phone":"+1 586 469 9293",
    "sg:postcode":"48045",
    "sg:province":"MI",
    "sg:tags":[
        "maintenance"
    ],
    "wof:name":"Lindas Quality Cleaning",
    "wof:placetype":"venue"
},
  "geometry": {"coordinates":[-82.811606,42.576609],"type":"Point"}
}