{
  "type": "Feature",
  "properties": {
    "iso:country":"US",
    "sg:address":"14617 W 8 Mile Rd",
    "sg:city":"Detroit",
    "sg:classifiers":[
        {
            "category":"Personal",
            "subcategory":"Nail Salon",
            "type":"Services"
        }
    ],
    "sg:phone":"+1 313 863 4870",
    "sg:postcode":"48235",
    "sg:province":"MI",
    "wof:name":"Bao Saoi Van",
    "wof:placetype":"venue"
},
  "geometry": {"coordinates":[-83.19093599999999,42.444853],"type":"Point"}
}