{
  "type": "Feature",
  "properties": {
    "iso:country":"US",
    "sg:address":"400 W John St",
    "sg:city":"Bay City",
    "sg:classifiers":[
        {
            "category":"Professional",
            "type":"Services"
        }
    ],
    "sg:phone":"+1 989 892 3778",
    "sg:postcode":"48706",
    "sg:province":"MI",
    "wof:name":"Highlands",
    "wof:placetype":"venue"
},
  "geometry": {"coordinates":[-83.907873,43.601339],"type":"Point"}
}