{
  "type": "Feature",
  "properties": {
    "iso:country":"US",
    "sg:address":"13404 W State Rd",
    "sg:city":"Grand Ledge",
    "sg:classifiers":[
        {
            "category":"Organizations",
            "subcategory":"Religious Organization",
            "type":"Services"
        }
    ],
    "sg:phone":"+1 517 622 1577",
    "sg:postcode":"48822",
    "sg:province":"MI",
    "wof:name":"Church of Christ Grand Ledge",
    "wof:placetype":"venue"
},
  "geometry": {"coordinates":[-84.795188,42.785014],"type":"Point"}
}