{
  "type": "Feature",
  "properties": {
    "iso:country":"US",
    "sg:address":"20235 Middlebelt Rd",
    "sg:city":"Livonia",
    "sg:classifiers":[
        {
            "category":"Deli",
            "type":"Food & Drink"
        },
        {
            "category":"Food & Beverages",
            "subcategory":"Bakery",
            "type":"Retail Goods"
        }
    ],
    "sg:phone":"+1 248 442 7827",
    "sg:postcode":"48152",
    "sg:province":"MI",
    "sg:tags":[
        "sandwich"
    ],
    "wof:name":"Deli the",
    "wof:placetype":"venue"
},
  "geometry": {"coordinates":[-83.336607,42.437438],"type":"Point"}
}