{
  "type": "Feature",
  "properties": {
    "iso:country":"US",
    "sg:address":"913 Boulevard Dr",
    "sg:city":"Saint Ignace",
    "sg:classifiers":[
        {
            "category":"Travel",
            "subcategory":"Hotels & Motels",
            "type":"Entertainment"
        }
    ],
    "sg:phone":"+1 906 643 9700",
    "sg:postcode":"49781",
    "sg:province":"MI",
    "wof:name":"Howard Johnson",
    "wof:placetype":"venue"
},
  "geometry": {"coordinates":[-84.744896,45.847583],"type":"Point"}
}