{
  "type": "Feature",
  "properties": {
    "iso:country":"US",
    "sg:address":"3332 E Bristol Rd",
    "sg:city":"Burton",
    "sg:classifiers":[
        {
            "category":"Freight",
            "type":"Transportation"
        }
    ],
    "sg:phone":"+1 810 715 1424",
    "sg:postcode":"48529",
    "sg:province":"MI",
    "sg:tags":[
        "warehouse"
    ],
    "wof:name":"Great Lakes Mudflaps Co",
    "wof:placetype":"venue"
},
  "geometry": {"coordinates":[-83.641184,42.974838],"type":"Point"}
}