{
  "type": "Feature",
  "properties": {
    "iso:country":"US",
    "sg:address":"31545 Harper Ave",
    "sg:city":"Saint Clair Shores",
    "sg:classifiers":[
        {
            "category":"Building & Trades",
            "subcategory":"Pest Control",
            "type":"Services"
        }
    ],
    "sg:phone":"+1 586 296 7590",
    "sg:postcode":"48082",
    "sg:province":"MI",
    "sg:website":"www.tricountypestcontrol.com",
    "wof:name":"Tri County Pest Control",
    "wof:placetype":"venue"
},
  "geometry": {"coordinates":[-82.892799,42.527699],"type":"Point"}
}