{
  "type": "Feature",
  "properties": {
    "iso:country":"US",
    "sg:address":"3904 Buckingham Ave",
    "sg:city":"Detroit",
    "sg:classifiers":[
        {
            "category":"Building & Trades",
            "subcategory":"Pest Control",
            "type":"Services"
        }
    ],
    "sg:phone":"+1 313 882 4198",
    "sg:postcode":"48224",
    "sg:province":"MI",
    "wof:name":"Orbit Exterminating Co",
    "wof:placetype":"venue"
},
  "geometry": {"coordinates":[-82.93814999999999,42.392961],"type":"Point"}
}