{
  "type": "Feature",
  "properties": {
    "iso:country":"US",
    "sg:address":"2640 Winslow Rd",
    "sg:city":"Imlay City",
    "sg:classifiers":[
        {
            "category":"Social Services",
            "subcategory":"Adult Care",
            "type":"Services"
        }
    ],
    "sg:phone":"+1 810 724 0780",
    "sg:postcode":"48444",
    "sg:province":"MI",
    "sg:tags":[
        "residential"
    ],
    "wof:name":"Pineview Acres Inc",
    "wof:placetype":"venue"
},
  "geometry": {"coordinates":[-83.124273,42.985244],"type":"Point"}
}