{
  "type": "Feature",
  "properties": {
    "iso:country":"US",
    "sg:address":"937 W State St",
    "sg:city":"Cheboygan",
    "sg:classifiers":[
        {
            "category":"Social Services",
            "subcategory":"Child Care",
            "type":"Services"
        }
    ],
    "sg:phone":"+1 231 627 9513",
    "sg:postcode":"49721",
    "sg:province":"MI",
    "sg:tags":[
        "day"
    ],
    "wof:name":"Susan Winters",
    "wof:placetype":"venue"
},
  "geometry": {"coordinates":[-84.48703,45.648443],"type":"Point"}
}