{
  "type": "Feature",
  "properties": {
    "iso:country":"US",
    "sg:address":"7137 Wedworth St",
    "sg:city":"Waterford",
    "sg:classifiers":[
        {
            "category":"Building & Trades",
            "subcategory":"Cleaning & Sanitation",
            "type":"Services"
        }
    ],
    "sg:phone":"+1 248 683 3836",
    "sg:postcode":"48327",
    "sg:province":"MI",
    "sg:tags":[
        "janitor"
    ],
    "wof:name":"Kinkade Cleaning",
    "wof:placetype":"venue"
},
  "geometry": {"coordinates":[-83.426768,42.639112],"type":"Point"}
}