{
  "type": "Feature",
  "properties": {
    "iso:country":"US",
    "sg:address":"12423 N 20th Ave",
    "sg:city":"Marion",
    "sg:classifiers":[
        {
            "category":"Farming",
            "subcategory":"Livestock Farm",
            "type":"Manufacturing & Wholesale Goods"
        }
    ],
    "sg:phone":"+1 231 743 6393",
    "sg:postcode":"49665",
    "sg:province":"MI",
    "sg:tags":[
        "ranch"
    ],
    "wof:name":"L B Ranch",
    "wof:placetype":"venue"
},
  "geometry": {"coordinates":[-85.12782799999999,43.996197],"type":"Point"}
}