{
  "type": "Feature",
  "properties": {
    "iso:country":"US",
    "sg:address":"5806 Monticello Ave",
    "sg:city":"Portage",
    "sg:classifiers":[
        {
            "category":"Building & Trades",
            "subcategory":"Electrical",
            "type":"Services"
        }
    ],
    "sg:phone":"+1 269 806 3331",
    "sg:postcode":"49024",
    "sg:province":"MI",
    "sg:tags":[
        "industrial",
        "electrician",
        "contractors-commercial",
        "electric"
    ],
    "wof:name":"Synder's Electrical",
    "wof:placetype":"venue"
},
  "geometry": {"coordinates":[-85.60447499999999,42.232712],"type":"Point"}
}