{
  "type": "Feature",
  "properties": {
    "iso:country":"US",
    "sg:address":"631 Minnesota Dr",
    "sg:city":"Troy",
    "sg:classifiers":[
        {
            "category":"Building & Trades",
            "subcategory":"Landscaping Services",
            "type":"Services"
        }
    ],
    "sg:phone":"+1 248 588 1888",
    "sg:postcode":"48083",
    "sg:province":"MI",
    "sg:tags":[
        "lawn",
        "maintenance",
        "grounds"
    ],
    "wof:name":"Diamond Lawn Svc",
    "wof:placetype":"venue"
},
  "geometry": {"coordinates":[-83.096344,42.54127],"type":"Point"}
}