{
  "type": "Feature",
  "properties": {
    "iso:country":"US",
    "sg:address":"1407 S Lakeview St",
    "sg:city":"Sturgis",
    "sg:classifiers":[
        {
            "category":"Social Services",
            "subcategory":"Child Care",
            "type":"Services"
        }
    ],
    "sg:phone":"+1 269 651 2314",
    "sg:postcode":"49091",
    "sg:province":"MI",
    "sg:tags":[
        "day"
    ],
    "wof:name":"Vickys Day Care",
    "wof:placetype":"venue"
},
  "geometry": {"coordinates":[-85.40895500000001,41.785864],"type":"Point"}
}