{
  "type": "Feature",
  "properties": {
    "iso:country":"US",
    "sg:address":"12764 Greenly St",
    "sg:city":"Holland",
    "sg:classifiers":[
        {
            "category":"Manufacturing",
            "subcategory":"Tools & Machinery",
            "type":"Manufacturing & Wholesale Goods"
        }
    ],
    "sg:phone":"+1 616 399 8893",
    "sg:postcode":"49424",
    "sg:province":"MI",
    "sg:tags":[
        "lubricating",
        "system",
        "devices"
    ],
    "sg:website":"www.gpreeves.com",
    "wof:name":"G P Reeves Inc",
    "wof:placetype":"venue"
},
  "geometry": {"coordinates":[-86.09468099999999,42.833666],"type":"Point"}
}