{
  "type": "Feature",
  "properties": {
    "iso:country":"US",
    "sg:address":"8876 Brookshire",
    "sg:city":"Saginaw",
    "sg:classifiers":[
        {
            "category":"Banks & Credit Unions",
            "subcategory":"Financial Services",
            "type":"Services"
        }
    ],
    "sg:phone":"+1 989 781 2716",
    "sg:postcode":"48609",
    "sg:province":"MI",
    "sg:tags":[
        "investor"
    ],
    "wof:name":"Perceptive Investment Assoc",
    "wof:placetype":"venue"
},
  "geometry": {"coordinates":[-84.089311,43.421155],"type":"Point"}
}