{
  "type": "Feature",
  "properties": {
    "iso:country":"US",
    "sg:address":"2801 S Schaefer Hwy",
    "sg:city":"Detroit",
    "sg:classifiers":[
        {
            "category":"Autos & Motor Vehicles",
            "subcategory":"Fuel & Gas Station",
            "type":"Retail Goods"
        }
    ],
    "sg:phone":"+1 313 843 1615",
    "sg:postcode":"48217",
    "sg:province":"MI",
    "wof:name":"Amine Fuel & Truck Mart Inc",
    "wof:placetype":"venue"
},
  "geometry": {"coordinates":[-83.144302,42.275902],"type":"Point"}
}