{
  "type": "Feature",
  "properties": {
    "iso:country":"US",
    "sg:address":"6490 W Walton Rd",
    "sg:city":"Blanchard",
    "sg:classifiers":[
        {
            "category":"Building & Trades",
            "subcategory":"Construction",
            "type":"Services"
        }
    ],
    "sg:phone":"+1 989 561 2119",
    "sg:postcode":"49310",
    "sg:province":"MI",
    "sg:tags":[
        "painter"
    ],
    "wof:name":"Schafer Painting",
    "wof:placetype":"venue"
},
  "geometry": {"coordinates":[-84.982702,43.538595],"type":"Point"}
}