{
  "type": "Feature",
  "properties": {
    "iso:country":"US",
    "sg:address":"33610 7 Mile Rd",
    "sg:city":"Livonia",
    "sg:classifiers":[
        {
            "category":"Professional",
            "type":"Services"
        }
    ],
    "sg:phone":"+1 248 476 3080",
    "sg:postcode":"48152",
    "sg:province":"MI",
    "sg:tags":[
        "caterer"
    ],
    "sg:website":"www.elitecateringcompany.com",
    "wof:name":"Elite Catering Company",
    "wof:placetype":"venue"
},
  "geometry": {"coordinates":[-83.378799,42.426102],"type":"Point"}
}