{
  "type": "Feature",
  "properties": {
    "iso:country":"US",
    "sg:address":"30018 Orchard Lake Rd",
    "sg:city":"Farmington Hills",
    "sg:classifiers":[
        {
            "category":"Banks & Credit Unions",
            "subcategory":"Financial Services",
            "type":"Services"
        }
    ],
    "sg:phone":"+1 248 538 7237",
    "sg:postcode":"48334",
    "sg:province":"MI",
    "sg:tags":[
        "broker",
        "mortgage"
    ],
    "wof:name":"First Choice Finance",
    "wof:placetype":"venue"
},
  "geometry": {"coordinates":[-83.359393,42.517975],"type":"Point"}
}