{
  "type": "Feature",
  "properties": {
    "iso:country":"US",
    "sg:address":"4905 Long Lake Rd",
    "sg:city":"Hale",
    "sg:classifiers":[
        {
            "category":"Freight",
            "type":"Transportation"
        }
    ],
    "sg:phone":"+1 989 257 0006",
    "sg:postcode":"48739",
    "sg:province":"MI",
    "sg:tags":[
        "commercial",
        "storage"
    ],
    "wof:name":"Long Lake Storage",
    "wof:placetype":"venue"
},
  "geometry": {"coordinates":[-83.87222800000001,44.419716],"type":"Point"}
}