{
  "type": "Feature",
  "properties": {
    "iso:country":"US",
    "sg:address":"2325 N Ely Hwy",
    "sg:city":"Alma",
    "sg:classifiers":[
        {
            "category":"Building & Trades",
            "subcategory":"Construction",
            "type":"Services"
        }
    ],
    "sg:phone":"+1 989 463 2975",
    "sg:postcode":"48801",
    "sg:province":"MI",
    "sg:tags":[
        "excavating",
        "contractor"
    ],
    "wof:name":"Camp Excavating",
    "wof:placetype":"venue"
},
  "geometry": {"coordinates":[-84.701691,43.325011],"type":"Point"}
}