{
  "type": "Feature",
  "properties": {
    "iso:country":"US",
    "sg:address":"411 Ottawa St",
    "sg:city":"Muskegon",
    "sg:classifiers":[
        {
            "category":"Wholesale",
            "subcategory":"Electrical",
            "type":"Manufacturing & Wholesale Goods"
        }
    ],
    "sg:phone":"+1 231 726 2396",
    "sg:postcode":"49442",
    "sg:province":"MI",
    "sg:tags":[
        "fire",
        "equipment",
        "protection"
    ],
    "sg:website":"www.cofessco.com",
    "wof:name":"Cofessco Fire Protection Inc",
    "wof:placetype":"venue"
},
  "geometry": {"coordinates":[-86.239682,43.244529],"type":"Point"}
}