{
  "type": "Feature",
  "properties": {
    "iso:country":"US",
    "sg:address":"34324 Colfax St",
    "sg:city":"Farmington Hills",
    "sg:classifiers":[
        {
            "category":"Building & Trades",
            "subcategory":"Construction",
            "type":"Services"
        }
    ],
    "sg:phone":"+1 248 471 7240",
    "sg:postcode":"48335",
    "sg:province":"MI",
    "sg:tags":[
        "house",
        "improvement",
        "home"
    ],
    "wof:name":"Bliss Home Improvement",
    "wof:placetype":"venue"
},
  "geometry": {"coordinates":[-83.384417,42.447627],"type":"Point"}
}