{
  "type": "Feature",
  "properties": {
    "iso:country":"US",
    "sg:address":"6100 W County Line Rd",
    "sg:city":"Richland",
    "sg:classifiers":[
        {
            "category":"Professional",
            "subcategory":"Business Services",
            "type":"Services"
        }
    ],
    "sg:phone":"+1 231 825 3786",
    "sg:postcode":"49051",
    "sg:province":"MI",
    "wof:name":"C & C Custom Engraving",
    "wof:placetype":"venue"
},
  "geometry": {"coordinates":[-85.295287,42.159707],"type":"Point"}
}