{
  "type": "Feature",
  "properties": {
    "iso:country":"US",
    "sg:address":"8400 Ohern Rd",
    "sg:city":"Saginaw",
    "sg:classifiers":[
        {
            "category":"Education",
            "subcategory":"School",
            "type":"Public Place"
        }
    ],
    "sg:phone":"+1 989 921 2401",
    "sg:postcode":"48609",
    "sg:province":"MI",
    "sg:website":"www.swanvalley.k12.mi.us",
    "wof:name":"Swan Valley High School",
    "wof:placetype":"venue"
},
  "geometry": {"coordinates":[-84.085819,43.408923],"type":"Point"}
}