{
  "type": "Feature",
  "properties": {
    "iso:country":"US",
    "sg:address":"18600 Van Horn Rd",
    "sg:city":"Trenton",
    "sg:classifiers":[
        {
            "category":"Health Services",
            "subcategory":"Doctor",
            "type":"Services"
        }
    ],
    "sg:phone":"+1 734 671 1303",
    "sg:postcode":"48183",
    "sg:province":"MI",
    "sg:tags":[
        "medical"
    ],
    "wof:name":"Cardo Thoracic & Vasular",
    "wof:placetype":"venue"
},
  "geometry": {"coordinates":[-83.21835,42.126363],"type":"Point"}
}