{
  "type": "Feature",
  "properties": {
    "iso:country":"US",
    "sg:address":"22837 Heslip Dr",
    "sg:city":"Novi",
    "sg:classifiers":[
        {
            "category":"Professional",
            "type":"Services"
        }
    ],
    "sg:phone":"+1 248 348 2885",
    "sg:postcode":"48375",
    "sg:province":"MI",
    "sg:tags":[
        "establishment"
    ],
    "wof:name":"Beauty's Mystery",
    "wof:placetype":"venue"
},
  "geometry": {"coordinates":[-83.467833,42.457831],"type":"Point"}
}