{
  "type": "Feature",
  "properties": {
    "iso:country":"US",
    "sg:address":"1100 Central Avenue",
    "sg:city":"Detroit",
    "sg:classifiers":[
        {
            "category":"Restaurant",
            "type":"Food & Drink"
        }
    ],
    "sg:phone":"+1 313 297 8804",
    "sg:postcode":"48209",
    "sg:province":"MI",
    "sg:tags":[
        "mexican"
    ],
    "sg:website":"www.restaurantcaminoreal.com/",
    "wof:name":"Taqueria Camino Real",
    "wof:placetype":"venue"
},
  "geometry": {"coordinates":[-83.11813600000001,42.304133],"type":"Point"}
}