{
  "type": "Feature",
  "properties": {
    "iso:country":"US",
    "sg:address":"5080 Corunna Rd",
    "sg:city":"Flint",
    "sg:classifiers":[
        {
            "category":"Banks & Credit Unions",
            "subcategory":"Bank",
            "type":"Services"
        }
    ],
    "sg:phone":"+1 810 720 4630",
    "sg:postcode":"48532",
    "sg:province":"MI",
    "sg:tags":[
        "state"
    ],
    "wof:name":"Fifth Third Bank",
    "wof:placetype":"venue"
},
  "geometry": {"coordinates":[-83.77728,43.002052],"type":"Point"}
}