{
  "type": "Feature",
  "properties": {
    "iso:country":"US",
    "sg:address":"8307 Old US Hwy 223",
    "sg:city":"Ottawa Lake",
    "sg:classifiers":[
        {
            "category":"Organizations",
            "subcategory":"Religious Organization",
            "type":"Services"
        }
    ],
    "sg:phone":"+1 734 856 2921",
    "sg:postcode":"49267",
    "sg:province":"MI",
    "sg:tags":[
        "church"
    ],
    "wof:name":"Zion Lutheran Church",
    "wof:placetype":"venue"
},
  "geometry": {"coordinates":[-83.747523,41.76384],"type":"Point"}
}