{
  "type": "Feature",
  "properties": {
    "iso:country":"US",
    "sg:address":"5778 S Oceana Dr",
    "sg:city":"New Era",
    "sg:classifiers":[
        {
            "category":"Retail",
            "subcategory":"Veterinary Services",
            "type":"Services"
        }
    ],
    "sg:phone":"+1 231 861 8196",
    "sg:postcode":"49452",
    "sg:province":"MI",
    "sg:tags":[
        "veterinarian"
    ],
    "wof:name":"Oceana Veterinary Svc",
    "wof:placetype":"venue"
},
  "geometry": {"coordinates":[-86.34759099999999,43.540341],"type":"Point"}
}