{
  "type": "Feature",
  "properties": {
    "iso:country":"US",
    "sg:address":"5038 Miller Rd",
    "sg:city":"Flint",
    "sg:classifiers":[
        {
            "category":"Social Services",
            "type":"Services"
        }
    ],
    "sg:phone":"+1 810 720 5435",
    "sg:postcode":"48503",
    "sg:province":"MI",
    "sg:tags":[
        "professional",
        "counselor"
    ],
    "wof:name":"Christian Counseling",
    "wof:placetype":"venue"
},
  "geometry": {"coordinates":[-83.77331700000001,42.975734],"type":"Point"}
}