{
  "type": "Feature",
  "properties": {
    "iso:country":"US",
    "sg:address":"6900 E 10 Mile Rd",
    "sg:city":"Center Line",
    "sg:classifiers":[
        {
            "category":"Insurance",
            "subcategory":"Insurance Agent",
            "type":"Services"
        }
    ],
    "sg:phone":"+1 586 758 4800",
    "sg:postcode":"48015",
    "sg:province":"MI",
    "sg:tags":[
        "employee",
        "benefit",
        "agency"
    ],
    "sg:website":"www.timberlandgroup.com",
    "wof:name":"Timberland Group",
    "wof:placetype":"venue"
},
  "geometry": {"coordinates":[-83.036387,42.477095],"type":"Point"}
}