{
  "type": "Feature",
  "properties": {
    "iso:country":"US",
    "sg:address":"14440 Houston Whittier St",
    "sg:city":"Detroit",
    "sg:classifiers":[
        {
            "category":"Shopping",
            "subcategory":"Clothing, Apparel, & Fashions",
            "type":"Retail Goods"
        }
    ],
    "sg:phone":"+1 313 526 3914",
    "sg:postcode":"48205",
    "sg:province":"MI",
    "sg:tags":[
        "wear"
    ],
    "wof:name":"Cleopatras",
    "wof:placetype":"venue"
},
  "geometry": {"coordinates":[-82.972881,42.420608],"type":"Point"}
}