{
  "type": "Feature",
  "properties": {
    "iso:country":"US",
    "sg:address":"45630 Sheri Dr",
    "sg:city":"Macomb",
    "sg:classifiers":[
        {
            "category":"Building & Trades",
            "subcategory":"Construction",
            "type":"Services"
        }
    ],
    "sg:phone":"+1 586 949 8865",
    "sg:postcode":"48044",
    "sg:province":"MI",
    "sg:tags":[
        "contractor"
    ],
    "wof:name":"Berge Construction Co Inc",
    "wof:placetype":"venue"
},
  "geometry": {"coordinates":[-82.90303,42.631799],"type":"Point"}
}