{
  "type": "Feature",
  "properties": {
    "iso:country":"US",
    "sg:address":"3160 Lansing Ave",
    "sg:city":"Jackson",
    "sg:classifiers":[
        {
            "category":"Freight",
            "type":"Transportation"
        }
    ],
    "sg:phone":"+1 517 782 9898",
    "sg:postcode":"49202",
    "sg:province":"MI",
    "sg:tags":[
        "commercial",
        "storage"
    ],
    "wof:name":"Northside Self Storage",
    "wof:placetype":"venue"
},
  "geometry": {"coordinates":[-84.413695,42.287863],"type":"Point"}
}