{
  "type": "Feature",
  "properties": {
    "iso:country":"US",
    "sg:address":"9600 Nook Rd",
    "sg:city":"Algonac",
    "sg:classifiers":[
        {
            "category":"Real Estate",
            "subcategory":"Real Estate Operator",
            "type":"Services"
        }
    ],
    "sg:phone":"+1 810 794 2348",
    "sg:postcode":"48001",
    "sg:province":"MI",
    "sg:tags":[
        "home",
        "park",
        "mobil"
    ],
    "wof:name":"Thorn Hollow Mobile Home Park",
    "wof:placetype":"venue"
},
  "geometry": {"coordinates":[-82.55112800000001,42.619434],"type":"Point"}
}