{
  "type": "Feature",
  "properties": {
    "iso:country":"US",
    "sg:address":"2622 W Michigan Ave",
    "sg:city":"Kalamazoo",
    "sg:classifiers":[
        {
            "category":"Food & Beverages",
            "subcategory":"Liquor & Beverages",
            "type":"Retail Goods"
        }
    ],
    "sg:phone":"+1 269 381 5857",
    "sg:postcode":"49006",
    "sg:province":"MI",
    "sg:tags":[
        "beer",
        "ale"
    ],
    "wof:name":"Den",
    "wof:placetype":"venue"
},
  "geometry": {"coordinates":[-85.62248,42.281377],"type":"Point"}
}