{
  "type": "Feature",
  "properties": {
    "iso:country":"US",
    "sg:address":"1978 Chicago Dr",
    "sg:city":"Jenison",
    "sg:classifiers":[
        {
            "category":"Retail",
            "subcategory":"Auto Rental",
            "type":"Services"
        }
    ],
    "sg:phone":"+1 616 662 8158",
    "sg:postcode":"49428",
    "sg:province":"MI",
    "wof:name":"U-Haul",
    "wof:placetype":"venue"
},
  "geometry": {"coordinates":[-85.82975399999999,42.888119],"type":"Point"}
}