{
  "type": "Feature",
  "properties": {
    "iso:country":"US",
    "sg:address":"4525 Stauffer Ave SE",
    "sg:city":"Grand Rapids",
    "sg:classifiers":[
        {
            "category":"Recreation",
            "type":"Entertainment"
        }
    ],
    "sg:phone":"+1 616 301 0404",
    "sg:postcode":"49508",
    "sg:province":"MI",
    "sg:tags":[
        "instruction",
        "gymnastic"
    ],
    "wof:name":"Bounceland",
    "wof:placetype":"venue"
},
  "geometry": {"coordinates":[-85.616923,42.883223],"type":"Point"}
}