{
  "type": "Feature",
  "properties": {
    "iso:country":"US",
    "sg:address":"1777 Highland Dr",
    "sg:city":"Ann Arbor",
    "sg:classifiers":[
        {
            "category":"Professional",
            "subcategory":"Engineering",
            "type":"Services"
        }
    ],
    "sg:phone":"+1 734 975 8777",
    "sg:postcode":"48108",
    "sg:province":"MI",
    "wof:name":"Michigan Aerospace",
    "wof:placetype":"venue"
},
  "geometry": {"coordinates":[-83.724667,42.226626],"type":"Point"}
}