{
  "type": "Feature",
  "properties": {
    "iso:country":"US",
    "sg:address":"6357 US Hwy 31 N",
    "sg:city":"Charlevoix",
    "sg:classifiers":[
        {
            "category":"Real Estate",
            "subcategory":"Real Estate Agent",
            "type":"Services"
        }
    ],
    "sg:phone":"+1 231 547 0234",
    "sg:postcode":"49720",
    "sg:province":"MI",
    "wof:name":"Sbd Real Estate LLC",
    "wof:placetype":"venue"
},
  "geometry": {"coordinates":[-85.104733,45.35966],"type":"Point"}
}