{
  "type": "Feature",
  "properties": {
    "iso:country":"US",
    "sg:address":"333 Linwood Ave",
    "sg:city":"Rochester",
    "sg:classifiers":[
        {
            "category":"Personal",
            "type":"Services"
        }
    ],
    "sg:phone":"+1 248 656 2063",
    "sg:postcode":"48307",
    "sg:province":"MI",
    "sg:tags":[
        "therapist",
        "massage"
    ],
    "wof:name":"Harmony In Motion",
    "wof:placetype":"venue"
},
  "geometry": {"coordinates":[-83.12958399999999,42.690566],"type":"Point"}
}