{
  "type": "Feature",
  "properties": {
    "iso:country":"US",
    "sg:address":"11469 White Lake Rd",
    "sg:city":"Fenton",
    "sg:classifiers":[
        {
            "category":"Building & Trades",
            "subcategory":"Construction",
            "type":"Services"
        }
    ],
    "sg:phone":"+1 810 750 7113",
    "sg:postcode":"48430",
    "sg:province":"MI",
    "sg:tags":[
        "general",
        "contractor"
    ],
    "wof:name":"TRK Building Co",
    "wof:placetype":"venue"
},
  "geometry": {"coordinates":[-83.73044,42.762619],"type":"Point"}
}