{
  "type": "Feature",
  "properties": {
    "iso:country":"US",
    "sg:address":"25120 Rose St",
    "sg:city":"Roseville",
    "sg:classifiers":[
        {
            "category":"Shopping",
            "subcategory":"Crafts & Fabrics",
            "type":"Retail Goods"
        }
    ],
    "sg:phone":"+1 586 771 5729",
    "sg:postcode":"48066",
    "sg:province":"MI",
    "sg:tags":[
        "sewing"
    ],
    "wof:name":"Wild Child Fibres & Fabrics",
    "wof:placetype":"venue"
},
  "geometry": {"coordinates":[-82.958446,42.483139],"type":"Point"}
}