{
  "type": "Feature",
  "properties": {
    "iso:country":"US",
    "sg:address":"3253 Owen Rd",
    "sg:city":"Fenton",
    "sg:classifiers":[
        {
            "category":"Real Estate",
            "subcategory":"Real Estate Operator",
            "type":"Services"
        }
    ],
    "sg:phone":"+1 810 750 3423",
    "sg:postcode":"48430",
    "sg:province":"MI",
    "sg:tags":[
        "property",
        "commercial"
    ],
    "wof:name":"Lake Fenton Management",
    "wof:placetype":"venue"
},
  "geometry": {"coordinates":[-83.732523,42.78974],"type":"Point"}
}