{
  "type": "Feature",
  "properties": {
    "iso:country":"US",
    "sg:address":"6367 Stephen",
    "sg:city":"Brighton",
    "sg:classifiers":[
        {
            "category":"Building & Trades",
            "subcategory":"Construction",
            "type":"Services"
        }
    ],
    "sg:phone":"+1 810 220 1013",
    "sg:postcode":"48116",
    "sg:province":"MI",
    "sg:tags":[
        "carpentry",
        "contractor"
    ],
    "wof:name":"F I P Enterprises Inc",
    "wof:placetype":"venue"
},
  "geometry": {"coordinates":[-83.7612,42.511981],"type":"Point"}
}