{
  "type": "Feature",
  "properties": {
    "iso:country":"US",
    "sg:address":"1419 Water St",
    "sg:city":"Port Huron",
    "sg:classifiers":[
        {
            "category":"Manufacturing",
            "subcategory":"Printing",
            "type":"Manufacturing & Wholesale Goods"
        }
    ],
    "sg:phone":"+1 810 984 3813",
    "sg:postcode":"48060",
    "sg:province":"MI",
    "sg:tags":[
        "commercial"
    ],
    "wof:name":"Acorn Press",
    "wof:placetype":"venue"
},
  "geometry": {"coordinates":[-82.44182000000001,42.983803],"type":"Point"}
}