{
  "type": "Feature",
  "properties": {
    "iso:country":"US",
    "sg:address":"12301 Farmington Rd",
    "sg:city":"Livonia",
    "sg:classifiers":[
        {
            "category":"Bakery",
            "type":"Food & Drink"
        },
        {
            "category":"Donuts",
            "subcategory":"None",
            "type":"Food & Drink"
        }
    ],
    "sg:phone":"+1 734 522 1100",
    "sg:postcode":"48150",
    "sg:province":"MI",
    "wof:name":"Awrey's Bakeries",
    "wof:placetype":"venue"
},
  "geometry": {"coordinates":[-83.372704,42.374699],"type":"Point"}
}