{
  "type": "Feature",
  "properties": {
    "iso:country":"US",
    "sg:address":"500 E Huron Blvd",
    "sg:city":"Marysville",
    "sg:classifiers":[
        {
            "category":"Retail",
            "subcategory":"Auto Repair",
            "type":"Services"
        }
    ],
    "sg:phone":"+1 810 364 2318",
    "sg:postcode":"48040",
    "sg:province":"MI",
    "sg:tags":[
        "automotive",
        "used",
        "parts"
    ],
    "wof:name":"Parts 4 Less",
    "wof:placetype":"venue"
},
  "geometry": {"coordinates":[-82.475139,42.909218],"type":"Point"}
}