{
  "type": "Feature",
  "properties": {
    "iso:country":"US",
    "sg:address":"113 N Robinson St",
    "sg:city":"Perrinton",
    "sg:classifiers":[
        {
            "category":"Shopping",
            "subcategory":"Gifts & Souvenirs",
            "type":"Retail Goods"
        }
    ],
    "sg:phone":"+1 989 236 5740",
    "sg:postcode":"48871",
    "sg:province":"MI",
    "sg:tags":[
        "shop"
    ],
    "wof:name":"Karla's Country Rose",
    "wof:placetype":"venue"
},
  "geometry": {"coordinates":[-84.6793,43.182998],"type":"Point"}
}