{
  "type": "Feature",
  "properties": {
    "iso:country":"US",
    "sg:address":"4365 Curran Rd",
    "sg:city":"Buchanan",
    "sg:classifiers":[
        {
            "category":"Shopping",
            "subcategory":"Clothing, Apparel, & Fashions",
            "type":"Retail Goods"
        }
    ],
    "sg:phone":"+1 269 695 9260",
    "sg:postcode":"49107",
    "sg:province":"MI",
    "sg:tags":[
        "salvage",
        "surplus",
        "merchandise"
    ],
    "wof:name":"Baber's Salvage",
    "wof:placetype":"venue"
},
  "geometry": {"coordinates":[-86.378788,41.776443],"type":"Point"}
}