{
  "type": "Feature",
  "properties": {
    "iso:country":"US",
    "sg:address":"20351 Ramblewood Dr",
    "sg:city":"Macomb",
    "sg:classifiers":[
        {
            "category":"Personal",
            "type":"Services"
        }
    ],
    "sg:phone":"+1 586 247 7667",
    "sg:postcode":"48044",
    "sg:province":"MI",
    "wof:name":"Carol Vasscotta",
    "wof:placetype":"venue"
},
  "geometry": {"coordinates":[-82.922944,42.647974],"type":"Point"}
}