{
  "type": "Feature",
  "properties": {
    "iso:country":"US",
    "sg:address":"17940 Farmington Rd Ste 130",
    "sg:city":"Livonia",
    "sg:classifiers":[
        {
            "category":"Health Services",
            "subcategory":"Doctor",
            "type":"Services"
        }
    ],
    "sg:phone":"+1 734 266 2488",
    "sg:postcode":"48152",
    "sg:province":"MI",
    "sg:website":"www.newhorizonpediatriccare.com",
    "wof:name":"Gupta Madan MD",
    "wof:placetype":"venue"
},
  "geometry": {"coordinates":[-83.37440100000001,42.418455],"type":"Point"}
}