{
  "type": "Feature",
  "properties": {
    "iso:country":"US",
    "sg:address":"13271 Crane Ridge Ct",
    "sg:city":"Fenton",
    "sg:classifiers":[
        {
            "category":"Social Services",
            "subcategory":"Child Care",
            "type":"Services"
        }
    ],
    "sg:phone":"+1 810 629 9439",
    "sg:postcode":"48430",
    "sg:province":"MI",
    "sg:tags":[
        "day"
    ],
    "wof:name":"Kims Learning Castle Day",
    "wof:placetype":"venue"
},
  "geometry": {"coordinates":[-83.71968200000001,42.833634],"type":"Point"}
}