{
  "type": "Feature",
  "properties": {
    "iso:country":"US",
    "sg:address":"3670 Auburn Ave NE",
    "sg:city":"Grand Rapids",
    "sg:classifiers":[
        {
            "category":"Professional",
            "subcategory":"Accounting & Tax Preparation",
            "type":"Services"
        }
    ],
    "sg:phone":"+1 616 363 6094",
    "sg:postcode":"49525",
    "sg:province":"MI",
    "sg:tags":[
        "accountant"
    ],
    "wof:name":"First Affordable Accounting",
    "wof:placetype":"venue"
},
  "geometry": {"coordinates":[-85.63771300000001,43.029362],"type":"Point"}
}