{
  "type": "Feature",
  "properties": {
    "iso:country":"US",
    "sg:address":"2031 International Way",
    "sg:city":"Port Huron",
    "sg:classifiers":[
        {
            "category":"Wholesale",
            "subcategory":"Construction Materials",
            "type":"Manufacturing & Wholesale Goods"
        }
    ],
    "sg:phone":"+1 810 982 0552",
    "sg:postcode":"48060",
    "sg:province":"MI",
    "sg:tags":[
        "fence"
    ],
    "wof:name":"Snug Cottage Imports",
    "wof:placetype":"venue"
},
  "geometry": {"coordinates":[-82.46602300000001,42.9678],"type":"Point"}
}