{
  "type": "Feature",
  "properties": {
    "iso:country":"US",
    "sg:address":"1367 N Leroy St",
    "sg:city":"Fenton",
    "sg:classifiers":[
        {
            "category":"Autos & Motor Vehicles",
            "subcategory":"Auto Supplies",
            "type":"Retail Goods"
        }
    ],
    "sg:phone":"+1 810 629 4422",
    "sg:postcode":"48430",
    "sg:province":"MI",
    "sg:tags":[
        "automobile",
        "parts"
    ],
    "wof:name":"Fenton Automotive",
    "wof:placetype":"venue"
},
  "geometry": {"coordinates":[-83.707505,42.813776],"type":"Point"}
}