{
  "type": "Feature",
  "properties": {
    "iso:country":"US",
    "sg:address":"183 Standish St",
    "sg:city":"Holland",
    "sg:classifiers":[
        {
            "category":"Building & Trades",
            "subcategory":"Construction",
            "type":"Services"
        }
    ],
    "sg:phone":"+1 616 392 5551",
    "sg:postcode":"49423",
    "sg:province":"MI",
    "sg:tags":[
        "house"
    ],
    "wof:name":"Moxie Builders",
    "wof:placetype":"venue"
},
  "geometry": {"coordinates":[-86.114439,42.758515],"type":"Point"}
}