{
  "type": "Feature",
  "properties": {
    "iso:country":"US",
    "sg:address":"35613 Warren Rd",
    "sg:city":"Westland",
    "sg:classifiers":[
        {
            "category":"Restaurant",
            "type":"Food & Drink"
        }
    ],
    "sg:menulink":"http://www.allmenus.com/mi/westland/105036-carinos-italian-grill/menu/",
    "sg:phone":"+1 734 641 4500",
    "sg:postcode":"48185",
    "sg:province":"MI",
    "sg:tags":[
        "american",
        "italian"
    ],
    "wof:name":"Carino's Italian Grill",
    "wof:placetype":"venue"
},
  "geometry": {"coordinates":[-83.394457,42.338735],"type":"Point"}
}