{
  "type": "Feature",
  "properties": {
    "iso:country":"US",
    "sg:address":"14500 W 8 Mile Rd",
    "sg:city":"Oak Park",
    "sg:classifiers":[
        {
            "category":"Professional",
            "subcategory":"Accounting & Tax Preparation",
            "type":"Services"
        }
    ],
    "sg:phone":"+1 248 968 3327",
    "sg:postcode":"48237",
    "sg:province":"MI",
    "sg:tags":[
        "return",
        "filing"
    ],
    "wof:name":"W J Ivery Accounting & Tax Svc",
    "wof:placetype":"venue"
},
  "geometry": {"coordinates":[-83.187952,42.445427],"type":"Point"}
}