{
  "type": "Feature",
  "properties": {
    "iso:country":"US",
    "sg:address":"7264 N Sheldon Rd",
    "sg:city":"Canton",
    "sg:classifiers":[
        {
            "category":"Professional",
            "subcategory":"Lawyer & Legal Services",
            "type":"Services"
        }
    ],
    "sg:phone":"+1 734 455 9100",
    "sg:postcode":"48187",
    "sg:province":"MI",
    "wof:name":"Bundarin Peter",
    "wof:placetype":"venue"
},
  "geometry": {"coordinates":[-83.478798,42.337399],"type":"Point"}
}