{
  "type": "Feature",
  "properties": {
    "iso:country":"US",
    "sg:address":"24600 Gratiot Ave",
    "sg:city":"Eastpointe",
    "sg:classifiers":[
        {
            "category":"Retail",
            "subcategory":"Auto Repair",
            "type":"Services"
        }
    ],
    "sg:phone":"+1 586 774 0200",
    "sg:postcode":"48021",
    "sg:province":"MI",
    "sg:website":"www.pepboys.com",
    "wof:name":"Pep Boys Automotive Supercenters",
    "wof:placetype":"venue"
},
  "geometry": {"coordinates":[-82.948898,42.478001],"type":"Point"}
}