{
  "type": "Feature",
  "properties": {
    "iso:country":"US",
    "sg:address":"3337 S Telegraph Rd",
    "sg:city":"Dearborn",
    "sg:classifiers":[
        {
            "category":"Restaurant",
            "type":"Food & Drink"
        }
    ],
    "sg:phone":"+1 313 562 8100",
    "sg:postcode":"48124",
    "sg:province":"MI",
    "wof:name":"Dearborn Cafe & Coffee Shop",
    "wof:placetype":"venue"
},
  "geometry": {"coordinates":[-83.27069899999999,42.286598],"type":"Point"}
}