{
  "type": "Feature",
  "properties": {
    "iso:country":"US",
    "sg:address":"2646 Le Boeuf St",
    "sg:city":"Muskegon",
    "sg:classifiers":[
        {
            "category":"Social Services",
            "subcategory":"Adult Care",
            "type":"Services"
        }
    ],
    "sg:phone":"+1 231 755 4998",
    "sg:postcode":"49441",
    "sg:province":"MI",
    "sg:tags":[
        "foster"
    ],
    "wof:name":"Winicki Adult Foster Care",
    "wof:placetype":"venue"
},
  "geometry": {"coordinates":[-86.30066100000001,43.203638],"type":"Point"}
}