{
  "type": "Feature",
  "properties": {
    "iso:country":"US",
    "sg:address":"205 S Range Rd",
    "sg:city":"St Clair",
    "sg:classifiers":[
        {
            "category":"Food & Beverages",
            "subcategory":"Groceries & Convenience Stores",
            "type":"Retail Goods"
        }
    ],
    "sg:phone":"+1 810 388 1477",
    "sg:postcode":"48079",
    "sg:province":"MI",
    "sg:tags":[
        "grocer"
    ],
    "wof:name":"Meijer Inc",
    "wof:placetype":"venue"
},
  "geometry": {"coordinates":[-82.499304,42.89997],"type":"Point"}
}