{
  "type": "Feature",
  "properties": {
    "iso:country":"US",
    "sg:address":"21778 Donald Ave",
    "sg:city":"Eastpointe",
    "sg:classifiers":[
        {
            "category":"Restaurant",
            "type":"Food & Drink"
        }
    ],
    "sg:phone":"+1 586 778 7829",
    "sg:postcode":"48021",
    "sg:province":"MI",
    "sg:tags":[
        "eating"
    ],
    "wof:name":"Two Guys With Tools",
    "wof:placetype":"venue"
},
  "geometry": {"coordinates":[-82.94553500000001,42.459251],"type":"Point"}
}