{
  "type": "Feature",
  "properties": {
    "iso:country":"US",
    "sg:address":"11786 Bowens Mill Rd",
    "sg:city":"Middleville",
    "sg:classifiers":[
        {
            "category":"Social Services",
            "subcategory":"Job Training",
            "type":"Services"
        }
    ],
    "sg:phone":"+1 269 795 8693",
    "sg:postcode":"49333",
    "sg:province":"MI",
    "wof:name":"Nelson Training Development",
    "wof:placetype":"venue"
},
  "geometry": {"coordinates":[-85.51877,42.65757],"type":"Point"}
}