{
  "type": "Feature",
  "properties": {
    "iso:country":"US",
    "sg:address":"1424 US Hwy 23",
    "sg:city":"Tawas City",
    "sg:classifiers":[
        {
            "category":"Wholesale",
            "subcategory":"Machinery & Supplies",
            "type":"Manufacturing & Wholesale Goods"
        }
    ],
    "sg:phone":"+1 989 362 2916",
    "sg:postcode":"48763",
    "sg:province":"MI",
    "sg:tags":[
        "truck"
    ],
    "wof:name":"Gold Bond BG Product",
    "wof:placetype":"venue"
},
  "geometry": {"coordinates":[-83.569996,44.121714],"type":"Point"}
}