{
  "type": "Feature",
  "properties": {
    "iso:country":"US",
    "sg:address":"1018 E 11 Mile Rd",
    "sg:city":"Royal Oak",
    "sg:classifiers":[
        {
            "category":"Restaurant",
            "type":"Food & Drink"
        }
    ],
    "sg:phone":"+1 248 398 7066",
    "sg:postcode":"48067",
    "sg:province":"MI",
    "sg:tags":[
        "greek"
    ],
    "wof:name":"Grecian House Inc",
    "wof:placetype":"venue"
},
  "geometry": {"coordinates":[-83.132288,42.490018],"type":"Point"}
}