{
  "type": "Feature",
  "properties": {
    "iso:country":"US",
    "sg:address":"5235 Carroll Lake Rd",
    "sg:city":"Commerce Twp",
    "sg:classifiers":[
        {
            "category":"Shopping",
            "type":"Retail Goods"
        }
    ],
    "sg:phone":"+1 248 363 5302",
    "sg:postcode":"48382",
    "sg:province":"MI",
    "sg:tags":[
        "coin",
        "dealer",
        "supply"
    ],
    "wof:name":"Just Coins",
    "wof:placetype":"venue"
},
  "geometry": {"coordinates":[-83.481595,42.59888],"type":"Point"}
}