{
  "type": "Feature",
  "properties": {
    "iso:country":"US",
    "sg:address":"532 Mill St",
    "sg:city":"Wayland",
    "sg:classifiers":[
        {
            "category":"Professional",
            "subcategory":"Management & Consulting",
            "type":"Services"
        }
    ],
    "sg:phone":"+1 616 262 3704",
    "sg:postcode":"49348",
    "sg:province":"MI",
    "wof:name":"Capital Wise Engineer",
    "wof:placetype":"venue"
},
  "geometry": {"coordinates":[-85.65468,42.677712],"type":"Point"}
}