{
  "type": "Feature",
  "properties": {
    "iso:country":"US",
    "sg:address":"550 US Hwy 41",
    "sg:city":"Michigamme",
    "sg:classifiers":[
        {
            "category":"Travel",
            "subcategory":"Hotels & Motels",
            "type":"Entertainment"
        }
    ],
    "sg:phone":"+1 906 323 6101",
    "sg:postcode":"49866",
    "sg:province":"MI",
    "wof:name":"Three Lakes Motel",
    "wof:placetype":"venue"
},
  "geometry": {"coordinates":[-87.60187500000001,46.512585],"type":"Point"}
}