{
  "type": "Feature",
  "properties": {
    "iso:country":"US",
    "sg:address":"28188 Golf Pointe Blvd",
    "sg:city":"Farmington Hills",
    "sg:classifiers":[
        {
            "category":"Professional",
            "type":"Services"
        }
    ],
    "sg:phone":"+1 248 553 9086",
    "sg:postcode":"48331",
    "sg:province":"MI",
    "sg:tags":[
        "establishment"
    ],
    "wof:name":"Bergin-Millian Group LTD",
    "wof:placetype":"venue"
},
  "geometry": {"coordinates":[-83.42236200000001,42.500034],"type":"Point"}
}