{
  "type": "Feature",
  "properties": {
    "iso:country":"US",
    "sg:address":"2151 Crystal Lake Dr",
    "sg:city":"Utica",
    "sg:classifiers":[
        {
            "category":"Building & Trades",
            "subcategory":"Construction",
            "type":"Services"
        }
    ],
    "sg:phone":"+1 586 254 3646",
    "sg:postcode":"48316",
    "sg:province":"MI",
    "sg:tags":[
        "contractor"
    ],
    "wof:name":"Galaxy Tile Co",
    "wof:placetype":"venue"
},
  "geometry": {"coordinates":[-83.091621,42.673743],"type":"Point"}
}