{
  "type": "Feature",
  "properties": {
    "iso:country":"US",
    "sg:address":"2140 Fairway Dr",
    "sg:city":"Davison",
    "sg:classifiers":[
        {
            "category":"Bars & Pubs",
            "subcategory":"Nightclub",
            "type":"Food & Drink"
        }
    ],
    "sg:phone":"+1 810 658 2355",
    "sg:postcode":"48423",
    "sg:province":"MI",
    "sg:tags":[
        "nightlife"
    ],
    "wof:name":"Tiebreaker Lounge",
    "wof:placetype":"venue"
},
  "geometry": {"coordinates":[-83.517799,43.004398],"type":"Point"}
}