{
  "type": "Feature",
  "properties": {
    "iso:country":"US",
    "sg:address":"1323 Sheridan Rd",
    "sg:city":"Escanaba",
    "sg:classifiers":[
        {
            "category":"Retail",
            "subcategory":"Animal Services",
            "type":"Services"
        }
    ],
    "sg:phone":"+1 906 789 0123",
    "sg:postcode":"49829",
    "sg:province":"MI",
    "sg:tags":[
        "pet",
        "grooming",
        "washing"
    ],
    "wof:name":"Pooch Parlor",
    "wof:placetype":"venue"
},
  "geometry": {"coordinates":[-87.069214,45.763172],"type":"Point"}
}