{
  "type": "Feature",
  "properties": {
    "iso:country":"US",
    "sg:address":"3051 W Grand Blanc Rd",
    "sg:city":"Swartz Creek",
    "sg:classifiers":[
        {
            "category":"Building & Trades",
            "subcategory":"Landscaping Services",
            "type":"Services"
        }
    ],
    "sg:phone":"+1 810 655 4482",
    "sg:postcode":"48473",
    "sg:province":"MI",
    "sg:tags":[
        "landscape",
        "contractor"
    ],
    "wof:name":"Lowe's Nursery",
    "wof:placetype":"venue"
},
  "geometry": {"coordinates":[-83.732939,42.914544],"type":"Point"}
}