{
  "type": "Feature",
  "properties": {
    "iso:country":"US",
    "sg:address":"1360 Judy Dr",
    "sg:city":"Troy",
    "sg:classifiers":[
        {
            "category":"Professional",
            "subcategory":"Computer Services",
            "type":"Services"
        }
    ],
    "sg:phone":"+1 248 884 3306",
    "sg:postcode":"48083",
    "sg:province":"MI",
    "sg:tags":[
        "development",
        "consulting",
        "software"
    ],
    "wof:name":"Flash Point Inc",
    "wof:placetype":"venue"
},
  "geometry": {"coordinates":[-83.12611200000001,42.575154],"type":"Point"}
}