{
  "type": "Feature",
  "properties": {
    "iso:country":"US",
    "sg:address":"25530 Schoenherr Rd",
    "sg:city":"Warren",
    "sg:classifiers":[
        {
            "category":"Building & Trades",
            "subcategory":"Cleaning & Sanitation",
            "type":"Services"
        }
    ],
    "sg:phone":"+1 586 772 1660",
    "sg:postcode":"48089",
    "sg:province":"MI",
    "sg:tags":[
        "ventilating",
        "system"
    ],
    "wof:name":"American Construction Inc",
    "wof:placetype":"venue"
},
  "geometry": {"coordinates":[-82.986704,42.478496],"type":"Point"}
}