{
  "type": "Feature",
  "properties": {
    "iso:country":"US",
    "sg:address":"9807 Oak Grove Rd",
    "sg:city":"Howell",
    "sg:classifiers":[
        {
            "category":"Building & Trades",
            "subcategory":"Construction",
            "type":"Services"
        }
    ],
    "sg:phone":"+1 517 545 7374",
    "sg:postcode":"48855",
    "sg:province":"MI",
    "sg:tags":[
        "general",
        "contractor"
    ],
    "wof:name":"Northstar Co Inc",
    "wof:placetype":"venue"
},
  "geometry": {"coordinates":[-83.949935,42.742746],"type":"Point"}
}