{
  "type": "Feature",
  "properties": {
    "iso:country":"US",
    "sg:address":"5001 Kendrick St SE",
    "sg:city":"Grand Rapids",
    "sg:classifiers":[
        {
            "category":"Manufacturing",
            "subcategory":"Rubber & Plastics",
            "type":"Manufacturing & Wholesale Goods"
        }
    ],
    "sg:phone":"+1 616 975 7639",
    "sg:postcode":"49512",
    "sg:province":"MI",
    "wof:name":"Plastech Engineered Prods Inc",
    "wof:placetype":"venue"
},
  "geometry": {"coordinates":[-85.54205899999999,42.872709],"type":"Point"}
}