{
  "type": "Feature",
  "properties": {
    "iso:country":"US",
    "sg:address":"7576 Ridge Valley Dr",
    "sg:city":"Clarkston",
    "sg:classifiers":[
        {
            "category":"Wholesale",
            "subcategory":"Non-durable Goods",
            "type":"Manufacturing & Wholesale Goods"
        }
    ],
    "sg:phone":"+1 248 922 0767",
    "sg:postcode":"48348",
    "sg:province":"MI",
    "wof:name":"From Bottom of My Heart",
    "wof:placetype":"venue"
},
  "geometry": {"coordinates":[-83.48177200000001,42.746469],"type":"Point"}
}