{
  "type": "Feature",
  "properties": {
    "iso:country":"US",
    "sg:address":"1640 Fort St",
    "sg:city":"Trenton",
    "sg:classifiers":[
        {
            "category":"Health Services",
            "subcategory":"Dentist",
            "type":"Services"
        }
    ],
    "sg:phone":"+1 734 675 8400",
    "sg:postcode":"48183",
    "sg:province":"MI",
    "wof:name":"Glavin Tressa DDS",
    "wof:placetype":"venue"
},
  "geometry": {"coordinates":[-83.188985,42.154577],"type":"Point"}
}