{
  "type": "Feature",
  "properties": {
    "iso:country":"US",
    "sg:address":"731 S Evergreen Dr",
    "sg:city":"White Cloud",
    "sg:classifiers":[
        {
            "category":"Real Estate",
            "subcategory":"Real Estate Agent",
            "type":"Services"
        }
    ],
    "sg:phone":"+1 231 689 9920",
    "sg:postcode":"49349",
    "sg:province":"MI",
    "wof:name":"Greenridge Realty & Country",
    "wof:placetype":"venue"
},
  "geometry": {"coordinates":[-85.771494,43.54086],"type":"Point"}
}