{
  "type": "Feature",
  "properties": {
    "iso:country":"US",
    "sg:address":"26250 Main St",
    "sg:city":"Beaver Island",
    "sg:classifiers":[
        {
            "category":"Recreation",
            "type":"Entertainment"
        }
    ],
    "sg:phone":"+1 231 448 2166",
    "sg:postcode":"49782",
    "sg:province":"MI",
    "wof:name":"Lakesports",
    "wof:placetype":"venue"
},
  "geometry": {"coordinates":[-85.514262,45.750107],"type":"Point"}
}