{
  "type": "Feature",
  "properties": {
    "iso:country":"US",
    "sg:address":"215 W Portage Ave",
    "sg:city":"Sault Ste Marie",
    "sg:classifiers":[
        {
            "category":"Freight",
            "type":"Transportation"
        }
    ],
    "sg:phone":"+1 906 635 5353",
    "sg:postcode":"49783",
    "sg:province":"MI",
    "sg:tags":[
        "commercial",
        "storage"
    ],
    "wof:name":"J & E Storage",
    "wof:placetype":"venue"
},
  "geometry": {"coordinates":[-84.347427,46.500666],"type":"Point"}
}