{
  "type": "Feature",
  "properties": {
    "iso:country":"US",
    "sg:address":"120 N Main St",
    "sg:city":"L Anse",
    "sg:classifiers":[
        {
            "category":"Government",
            "subcategory":"Post Office",
            "type":"Public Place"
        }
    ],
    "sg:phone":"+1 906 524 7977",
    "sg:postcode":"49946",
    "sg:province":"MI",
    "wof:name":"US Post Office",
    "wof:placetype":"venue"
},
  "geometry": {"coordinates":[-88.452949,46.758905],"type":"Point"}
}