{
  "type": "Feature",
  "properties": {
    "iso:country":"US",
    "sg:address":"301 N Suffolk St",
    "sg:city":"Ironwood",
    "sg:classifiers":[
        {
            "category":"Professional",
            "subcategory":"Accounting & Tax Preparation",
            "type":"Services"
        }
    ],
    "sg:phone":"+1 906 932 4430",
    "sg:postcode":"49938",
    "sg:province":"MI",
    "sg:tags":[
        "accountant"
    ],
    "wof:name":"Joki Makela & Pollack",
    "wof:placetype":"venue"
},
  "geometry": {"coordinates":[-90.17108399999999,46.457471],"type":"Point"}
}