{
  "type": "Feature",
  "properties": {
    "iso:country":"US",
    "sg:address":"10007 Northend Ave",
    "sg:city":"Ferndale",
    "sg:classifiers":[
        {
            "category":"Retail",
            "subcategory":"Auto Repair",
            "type":"Services"
        }
    ],
    "sg:phone":"+1 248 547 0500",
    "sg:postcode":"48220",
    "sg:province":"MI",
    "wof:name":"Charlie's Auto Repair",
    "wof:placetype":"venue"
},
  "geometry": {"coordinates":[-83.161866,42.45275],"type":"Point"}
}