{
  "type": "Feature",
  "properties": {
    "iso:country":"US",
    "sg:address":"4809 Jefferson Ave",
    "sg:city":"Midland",
    "sg:classifiers":[
        {
            "category":"Real Estate",
            "subcategory":"Real Estate Agent",
            "type":"Services"
        }
    ],
    "sg:phone":"+1 989 633 9598",
    "sg:postcode":"48640",
    "sg:province":"MI",
    "wof:name":"Henry Flandysz",
    "wof:placetype":"venue"
},
  "geometry": {"coordinates":[-84.22687500000001,43.643199],"type":"Point"}
}