{
  "type": "Feature",
  "properties": {
    "iso:country":"US",
    "sg:address":"1107 Michigan Ave",
    "sg:city":"Alma",
    "sg:classifiers":[
        {
            "category":"Organizations",
            "subcategory":"Religious Organization",
            "type":"Services"
        }
    ],
    "sg:phone":"+1 989 463 8201",
    "sg:postcode":"48801",
    "sg:province":"MI",
    "sg:tags":[
        "church"
    ],
    "wof:name":"Alma Foursquare Church",
    "wof:placetype":"venue"
},
  "geometry": {"coordinates":[-84.644727,43.38256],"type":"Point"}
}