{
  "type": "Feature",
  "properties": {
    "iso:country":"US",
    "sg:address":"316 Davis St",
    "sg:city":"Paw Paw",
    "sg:classifiers":[
        {
            "category":"Organizations",
            "subcategory":"Community Association",
            "type":"Services"
        }
    ],
    "sg:phone":"+1 269 657 5087",
    "sg:postcode":"49079",
    "sg:province":"MI",
    "wof:name":"Optimist International",
    "wof:placetype":"venue"
},
  "geometry": {"coordinates":[-85.88622700000001,42.226703],"type":"Point"}
}