{
  "type": "Feature",
  "properties": {
    "iso:country":"US",
    "sg:address":"5 E Sanilac Rd",
    "sg:city":"Sandusky",
    "sg:classifiers":[
        {
            "category":"Recreation",
            "type":"Entertainment"
        }
    ],
    "sg:phone":"+1 810 648 5945",
    "sg:postcode":"48471",
    "sg:province":"MI",
    "sg:tags":[
        "martial",
        "arts",
        "instruction"
    ],
    "wof:name":"Washido Kan Martial Arts",
    "wof:placetype":"venue"
},
  "geometry": {"coordinates":[-82.829009,43.421397],"type":"Point"}
}