{
  "type": "Feature",
  "properties": {
    "iso:country":"US",
    "sg:address":"18763 Farmington Rd",
    "sg:city":"Livonia",
    "sg:classifiers":[
        {
            "category":"Health Services",
            "subcategory":"Doctor",
            "type":"Services"
        }
    ],
    "sg:phone":"+1 248 478 0884",
    "sg:postcode":"48152",
    "sg:province":"MI",
    "sg:tags":[
        "surgeon",
        "oral"
    ],
    "wof:name":"Lassaline William J DDS",
    "wof:placetype":"venue"
},
  "geometry": {"coordinates":[-83.375,42.4235],"type":"Point"}
}