{
  "type": "Feature",
  "properties": {
    "iso:country":"US",
    "sg:address":"12805 Telegraph Rd",
    "sg:city":"Redford",
    "sg:classifiers":[
        {
            "category":"Autos & Motor Vehicles",
            "subcategory":"Fuel & Gas Station",
            "type":"Retail Goods"
        }
    ],
    "sg:phone":"+1 313 541 5512",
    "sg:postcode":"48239",
    "sg:province":"MI",
    "wof:name":"Three Beydoun Brothers",
    "wof:placetype":"venue"
},
  "geometry": {"coordinates":[-83.276016,42.379892],"type":"Point"}
}