{
  "type": "Feature",
  "properties": {
    "iso:country":"US",
    "sg:address":"12035 Mendota St",
    "sg:city":"Detroit",
    "sg:classifiers":[
        {
            "category":"Building & Trades",
            "subcategory":"Landscaping Services",
            "type":"Services"
        }
    ],
    "sg:phone":"+1 313 999 5404",
    "sg:postcode":"48204",
    "sg:province":"MI",
    "wof:name":"Horticulture Consultants Inc",
    "wof:placetype":"venue"
},
  "geometry": {"coordinates":[-83.164755,42.376805],"type":"Point"}
}