{
  "type": "Feature",
  "properties": {
    "iso:country":"US",
    "sg:address":"20524 Rutherford St",
    "sg:city":"Detroit",
    "sg:classifiers":[
        {
            "category":"Wholesale",
            "subcategory":"Drugs",
            "type":"Manufacturing & Wholesale Goods"
        }
    ],
    "sg:phone":"+1 313 837 9712",
    "sg:postcode":"48235",
    "sg:province":"MI",
    "sg:tags":[
        "shop",
        "beauty"
    ],
    "wof:name":"Beauty From On High",
    "wof:placetype":"venue"
},
  "geometry": {"coordinates":[-83.205791,42.443997],"type":"Point"}
}