{
  "type": "Feature",
  "properties": {
    "iso:country":"US",
    "sg:address":"4315 Clio Rd",
    "sg:city":"Flint",
    "sg:classifiers":[
        {
            "category":"Home & Garden",
            "subcategory":"Furniture",
            "type":"Retail Goods"
        }
    ],
    "sg:phone":"+1 810 785 3332",
    "sg:postcode":"48504",
    "sg:province":"MI",
    "wof:name":"Classic Furniture Design",
    "wof:placetype":"venue"
},
  "geometry": {"coordinates":[-83.732876,43.054731],"type":"Point"}
}