{
  "type": "Feature",
  "properties": {
    "iso:country":"US",
    "sg:address":"24911 Misery Bay Rd",
    "sg:city":"Land O Lakes",
    "sg:classifiers":[
        {
            "category":"Travel",
            "subcategory":"Hotels & Motels",
            "type":"Entertainment"
        }
    ],
    "sg:phone":"+1 906 544 2262",
    "sg:postcode":"49969",
    "sg:province":"WI",
    "sg:tags":[
        "resort"
    ],
    "sg:website":"www.winddriftresort.com",
    "wof:name":"Wind Drift Resort",
    "wof:placetype":"venue"
},
  "geometry": {"coordinates":[-89.122437,46.159779],"type":"Point"}
}