{
  "type": "Feature",
  "properties": {
    "iso:country":"US",
    "sg:address":"16840 E 9 Mile Rd",
    "sg:city":"Eastpointe",
    "sg:classifiers":[
        {
            "category":"Professional",
            "subcategory":"Management & Consulting",
            "type":"Services"
        }
    ],
    "sg:phone":"+1 586 772 0222",
    "sg:postcode":"48021",
    "sg:province":"MI",
    "sg:tags":[
        "consultant",
        "business"
    ],
    "wof:name":"Buckingham Associates Inc",
    "wof:placetype":"venue"
},
  "geometry": {"coordinates":[-82.94806800000001,42.464732],"type":"Point"}
}