{
  "type": "Feature",
  "properties": {
    "iso:country":"US",
    "sg:address":"4393 Koepfgen Rd",
    "sg:city":"Cass City",
    "sg:classifiers":[
        {
            "category":"Organizations",
            "subcategory":"Religious Organization",
            "type":"Services"
        }
    ],
    "sg:phone":"+1 989 872 2729",
    "sg:postcode":"48726",
    "sg:province":"MI",
    "sg:tags":[
        "church"
    ],
    "wof:name":"Cass City Missionary Church",
    "wof:placetype":"venue"
},
  "geometry": {"coordinates":[-83.194292,43.59594],"type":"Point"}
}