{
  "type": "Feature",
  "properties": {
    "iso:country":"US",
    "sg:address":"1209 Military St",
    "sg:city":"Port Huron",
    "sg:classifiers":[
        {
            "category":"Restaurant",
            "type":"Food & Drink"
        }
    ],
    "sg:phone":"+1 810 985 5130",
    "sg:postcode":"48060",
    "sg:province":"MI",
    "wof:name":"Powers Classic Hamburgers",
    "wof:placetype":"venue"
},
  "geometry": {"coordinates":[-82.42468,42.971686],"type":"Point"}
}