{
  "type": "Feature",
  "properties": {
    "iso:country":"US",
    "sg:address":"4965 E 1st St",
    "sg:city":"Custer",
    "sg:classifiers":[
        {
            "category":"Farming",
            "subcategory":"Farm",
            "type":"Manufacturing & Wholesale Goods"
        }
    ],
    "sg:phone":"+1 231 757 2687",
    "sg:postcode":"49405",
    "sg:province":"MI",
    "sg:tags":[
        "crop",
        "general"
    ],
    "wof:name":"William Shoup",
    "wof:placetype":"venue"
},
  "geometry": {"coordinates":[-86.15367500000001,43.945871],"type":"Point"}
}