{
  "type": "Feature",
  "properties": {
    "iso:country":"US",
    "sg:address":"8190 Boardwalk",
    "sg:city":"Brighton",
    "sg:classifiers":[
        {
            "category":"Professional",
            "subcategory":"Business Services",
            "type":"Services"
        }
    ],
    "sg:phone":"+1 248 437 6616",
    "sg:postcode":"48116",
    "sg:province":"MI",
    "wof:name":"Mc Williams Sales & Svc",
    "wof:placetype":"venue"
},
  "geometry": {"coordinates":[-83.688317,42.489583],"type":"Point"}
}