{
  "type": "Feature",
  "properties": {
    "iso:country":"US",
    "sg:address":"153 E Front St",
    "sg:city":"Traverse City",
    "sg:classifiers":[
        {
            "category":"Shopping",
            "type":"Retail Goods"
        }
    ],
    "sg:phone":"+1 231 929 7426",
    "sg:postcode":"49684",
    "sg:province":"MI",
    "sg:tags":[
        "art",
        "gallery",
        "dealer"
    ],
    "sg:website":"www.watermelonsugar.com",
    "wof:name":"Watermelon Sugar Gallery",
    "wof:placetype":"venue"
},
  "geometry": {"coordinates":[-85.622068,44.764127],"type":"Point"}
}