{
  "type": "Feature",
  "properties": {
    "iso:country":"US",
    "sg:address":"700 W Sebewaing St",
    "sg:city":"Sebewaing",
    "sg:classifiers":[
        {
            "category":"Recreation",
            "subcategory":"Marina",
            "type":"Entertainment"
        }
    ],
    "sg:phone":"+1 989 883 9558",
    "sg:postcode":"48759",
    "sg:province":"MI",
    "wof:name":"Sebewaing Harbor Marina",
    "wof:placetype":"venue"
},
  "geometry": {"coordinates":[-83.459593,43.73312],"type":"Point"}
}