{
  "type": "Feature",
  "properties": {
    "iso:country":"US",
    "sg:address":"226 Burtch Rd",
    "sg:city":"Grass Lake",
    "sg:classifiers":[
        {
            "category":"Retail",
            "subcategory":"Repair Shop",
            "type":"Services"
        },
        {
            "category":"Home & Garden",
            "subcategory":"Garden Supply",
            "type":"Retail Goods"
        }
    ],
    "sg:phone":"+1 517 522 8227",
    "sg:postcode":"49240",
    "sg:province":"MI",
    "sg:tags":[
        "sell",
        "repairing",
        "lawn",
        "chain",
        "mower",
        "saw"
    ],
    "wof:name":"S & S Mower Sales & Services",
    "wof:placetype":"venue"
},
  "geometry": {"coordinates":[-84.211877,42.249124],"type":"Point"}
}