{
  "type": "Feature",
  "properties": {
    "iso:country":"US",
    "sg:address":"5130 Coolidge Hwy.",
    "sg:city":"Royal Oak",
    "sg:classifiers":[
        {
            "category":"Health Services",
            "subcategory":"Doctor",
            "type":"Services"
        }
    ],
    "sg:phone":"+1 248 280 0502",
    "sg:postcode":"48073",
    "sg:province":"MI",
    "sg:tags":[
        "surgeon",
        "cosmetic"
    ],
    "sg:website":"www.ArtisanCosmeticSurgery.com",
    "wof:name":"Artisan Cosmetic Surgery",
    "wof:placetype":"venue"
},
  "geometry": {"coordinates":[-83.184288,42.538182],"type":"Point"}
}