{
  "type": "Feature",
  "properties": {
    "iso:country":"US",
    "sg:address":"281 Main St",
    "sg:city":"Coopersville",
    "sg:classifiers":[
        {
            "category":"Shopping",
            "subcategory":"Pharmacy",
            "type":"Retail Goods"
        }
    ],
    "sg:phone":"+1 616 837 6394",
    "sg:postcode":"49404",
    "sg:province":"MI",
    "wof:name":"Tasker Drug Store",
    "wof:placetype":"venue"
},
  "geometry": {"coordinates":[-85.934381,43.063758],"type":"Point"}
}