{
  "type": "Feature",
  "properties": {
    "iso:country":"US",
    "sg:address":"1313 Imlay City Rd",
    "sg:city":"Lapeer",
    "sg:classifiers":[
        {
            "category":"Building & Trades",
            "subcategory":"Landscaping Services",
            "type":"Services"
        }
    ],
    "sg:phone":"+1 810 245 2616",
    "sg:postcode":"48446",
    "sg:province":"MI",
    "sg:tags":[
        "tree"
    ],
    "wof:name":"Palm Tree Auto",
    "wof:placetype":"venue"
},
  "geometry": {"coordinates":[-83.286886,43.047186],"type":"Point"}
}