{
  "type": "Feature",
  "properties": {
    "iso:country":"US",
    "sg:address":"11 E 32nd St",
    "sg:city":"Holland",
    "sg:classifiers":[
        {
            "category":"Organizations",
            "subcategory":"Religious Organization",
            "type":"Services"
        }
    ],
    "sg:phone":"+1 616 392 2635",
    "sg:postcode":"49423",
    "sg:province":"MI",
    "wof:name":"Bethany Chrstn Rform Chrch Inc",
    "wof:placetype":"venue"
},
  "geometry": {"coordinates":[-86.10441,42.768617],"type":"Point"}
}