{
  "type": "Feature",
  "properties": {
    "iso:country":"US",
    "sg:address":"25901 W 10 Mile Rd",
    "sg:city":"Southfield",
    "sg:classifiers":[
        {
            "category":"Professional",
            "subcategory":"Management & Consulting",
            "type":"Services"
        }
    ],
    "sg:phone":"+1 248 353 6044",
    "sg:postcode":"48033",
    "sg:province":"MI",
    "wof:name":"Financial Network Ltd",
    "wof:placetype":"venue"
},
  "geometry": {"coordinates":[-83.303438,42.471365],"type":"Point"}
}