{
  "type": "Feature",
  "properties": {
    "iso:country":"US",
    "sg:address":"515 Bryant Ave",
    "sg:city":"Manistee",
    "sg:classifiers":[
        {
            "category":"Education",
            "subcategory":"School",
            "type":"Public Place"
        }
    ],
    "sg:phone":"+1 231 723 9285",
    "sg:postcode":"49660",
    "sg:province":"MI",
    "wof:name":"Jefferson Thmas Elmentary Schl",
    "wof:placetype":"venue"
},
  "geometry": {"coordinates":[-86.33217399999999,44.241807],"type":"Point"}
}