{
  "type": "Feature",
  "properties": {
    "iso:country":"US",
    "sg:address":"10807 Lakeside Dr",
    "sg:city":"Perrinton",
    "sg:classifiers":[
        {
            "category":"Restaurant",
            "type":"Food & Drink"
        }
    ],
    "sg:phone":"+1 989 682 4547",
    "sg:postcode":"48871",
    "sg:province":"MI",
    "sg:tags":[
        "caterer"
    ],
    "wof:name":"Diana's Catering",
    "wof:placetype":"venue"
},
  "geometry": {"coordinates":[-84.689729,43.144489],"type":"Point"}
}