{
  "type": "Feature",
  "properties": {
    "iso:country":"US",
    "sg:address":"2001 Flushing Rd",
    "sg:city":"Flint",
    "sg:classifiers":[
        {
            "category":"Professional",
            "subcategory":"Credit Reporting & Collection",
            "type":"Services"
        }
    ],
    "sg:phone":"+1 810 424 1060",
    "sg:postcode":"48504",
    "sg:province":"MI",
    "wof:name":"Precise Document Collection",
    "wof:placetype":"venue"
},
  "geometry": {"coordinates":[-83.7158,43.019779],"type":"Point"}
}