{
  "type": "Feature",
  "properties": {
    "iso:country":"US",
    "sg:address":"13622 Merriman Rd",
    "sg:city":"Livonia",
    "sg:classifiers":[
        {
            "category":"Autos & Motor Vehicles",
            "subcategory":"Auto Supplies",
            "type":"Retail Goods"
        }
    ],
    "sg:phone":"+1 586 713 3871",
    "sg:postcode":"48150",
    "sg:province":"MI",
    "sg:tags":[
        "glass"
    ],
    "wof:name":"Notorious Tintz",
    "wof:placetype":"venue"
},
  "geometry": {"coordinates":[-83.353104,42.381699],"type":"Point"}
}