{
  "type": "Feature",
  "properties": {
    "iso:country":"US",
    "sg:address":"11491 E 13 Mile Rd",
    "sg:city":"Warren",
    "sg:classifiers":[
        {
            "category":"Shopping",
            "subcategory":"Tobacco",
            "type":"Retail Goods"
        }
    ],
    "sg:phone":"+1 586 795 0117",
    "sg:postcode":"48093",
    "sg:province":"MI",
    "sg:tags":[
        "shop"
    ],
    "wof:name":"Smokers Outlet",
    "wof:placetype":"venue"
},
  "geometry": {"coordinates":[-83.006401,42.5215],"type":"Point"}
}