{
  "type": "Feature",
  "properties": {
    "iso:country":"US",
    "sg:address":"6425 Shappie Rd",
    "sg:city":"Clarkston",
    "sg:classifiers":[
        {
            "category":"Real Estate",
            "subcategory":"Real Estate Agent",
            "type":"Services"
        }
    ],
    "sg:phone":"+1 248 421 3393",
    "sg:postcode":"48348",
    "sg:province":"MI",
    "wof:name":"Pearl Revoldt",
    "wof:placetype":"venue"
},
  "geometry": {"coordinates":[-83.409012,42.783749],"type":"Point"}
}