{
  "type": "Feature",
  "properties": {
    "iso:country":"US",
    "sg:address":"45241 Van Dyke Ave",
    "sg:city":"Utica",
    "sg:classifiers":[
        {
            "category":"Restaurant",
            "type":"Food & Drink"
        }
    ],
    "sg:phone":"+1 586 737 2494",
    "sg:postcode":"48317",
    "sg:province":"MI",
    "sg:tags":[
        "shop",
        "coffee"
    ],
    "wof:name":"Second Cup Coffee",
    "wof:placetype":"venue"
},
  "geometry": {"coordinates":[-83.03254099999999,42.626813],"type":"Point"}
}