{
  "type": "Feature",
  "properties": {
    "iso:country":"US",
    "sg:address":"21890 Colony Park Cir",
    "sg:city":"Southfield",
    "sg:classifiers":[
        {
            "category":"Professional",
            "type":"Services"
        }
    ],
    "sg:phone":"+1 248 355 2024",
    "sg:postcode":"48076",
    "sg:province":"MI",
    "sg:tags":[
        "establishment"
    ],
    "wof:name":"Colony Park",
    "wof:placetype":"venue"
},
  "geometry": {"coordinates":[-83.259995,42.502],"type":"Point"}
}