{
  "type": "Feature",
  "properties": {
    "iso:country":"US",
    "sg:address":"4087 S Center Rd",
    "sg:city":"Burton",
    "sg:classifiers":[
        {
            "category":"Social Services",
            "subcategory":"Child Care",
            "type":"Services"
        }
    ],
    "sg:phone":"+1 810 715 1577",
    "sg:postcode":"48519",
    "sg:province":"MI",
    "sg:tags":[
        "day"
    ],
    "wof:name":"Active Learning Childcare Center",
    "wof:placetype":"venue"
},
  "geometry": {"coordinates":[-83.632937,42.971341],"type":"Point"}
}