{
  "type": "Feature",
  "properties": {
    "iso:country":"US",
    "sg:address":"8474 Krause Rd",
    "sg:city":"Engadine",
    "sg:classifiers":[
        {
            "category":"Shopping",
            "subcategory":"Discount & Variety Stores",
            "type":"Retail Goods"
        }
    ],
    "sg:phone":"+1 906 477 6273",
    "sg:postcode":"49827",
    "sg:province":"MI",
    "wof:name":"Hiawatha Associates",
    "wof:placetype":"venue"
},
  "geometry": {"coordinates":[-85.55027200000001,46.169993],"type":"Point"}
}