{
  "type": "Feature",
  "properties": {
    "iso:country":"US",
    "sg:address":"6622 Robinson Ave",
    "sg:city":"Allen Park",
    "sg:classifiers":[
        {
            "category":"Building & Trades",
            "subcategory":"Construction",
            "type":"Services"
        }
    ],
    "sg:phone":"+1 313 386 4152",
    "sg:postcode":"48101",
    "sg:province":"MI",
    "sg:tags":[
        "carpentry",
        "contractor"
    ],
    "wof:name":"Atwood Home Svcs",
    "wof:placetype":"venue"
},
  "geometry": {"coordinates":[-83.23026400000001,42.260339],"type":"Point"}
}