{
  "type": "Feature",
  "properties": {
    "iso:country":"US",
    "sg:address":"719 W 4th St",
    "sg:city":"Monroe",
    "sg:classifiers":[
        {
            "category":"Professional",
            "subcategory":"Management & Consulting",
            "type":"Services"
        }
    ],
    "sg:phone":"+1 734 457 0566",
    "sg:postcode":"48161",
    "sg:province":"MI",
    "sg:tags":[
        "fuel"
    ],
    "wof:name":"JCO Inc",
    "wof:placetype":"venue"
},
  "geometry": {"coordinates":[-83.40793600000001,41.916504],"type":"Point"}
}