{
  "type": "Feature",
  "properties": {
    "iso:country":"US",
    "sg:address":"380 N Old Woodward Ave",
    "sg:city":"Birmingham",
    "sg:classifiers":[
        {
            "category":"Professional",
            "type":"Services"
        }
    ],
    "sg:phone":"+1 248 594 2022",
    "sg:postcode":"48009",
    "sg:province":"MI",
    "sg:tags":[
        "establishment"
    ],
    "wof:name":"Dod Enterprises LTD",
    "wof:placetype":"venue"
},
  "geometry": {"coordinates":[-83.216759,42.549693],"type":"Point"}
}