{
  "type": "Feature",
  "properties": {
    "iso:country":"US",
    "sg:address":"1564 Club Rd",
    "sg:city":"Saint Helen",
    "sg:classifiers":[
        {
            "category":"Professional",
            "subcategory":"Accounting & Tax Preparation",
            "type":"Services"
        }
    ],
    "sg:phone":"+1 989 389 4617",
    "sg:postcode":"48656",
    "sg:province":"MI",
    "wof:name":"Leutz Ray F C P A P C",
    "wof:placetype":"venue"
},
  "geometry": {"coordinates":[-84.445008,44.355412],"type":"Point"}
}