{
  "type": "Feature",
  "properties": {
    "iso:country":"US",
    "sg:address":"14132 Woodward Ave",
    "sg:city":"Highland Park",
    "sg:classifiers":[
        {
            "category":"Shopping",
            "subcategory":"Shoes",
            "type":"Retail Goods"
        }
    ],
    "sg:phone":"+1 313 869 4767",
    "sg:postcode":"48203",
    "sg:province":"MI",
    "sg:tags":[
        "store"
    ],
    "sg:website":"www.payless.com",
    "wof:name":"Payless Shoes",
    "wof:placetype":"venue"
},
  "geometry": {"coordinates":[-83.098297,42.4076],"type":"Point"}
}