{
  "type": "Feature",
  "properties": {
    "iso:country":"US",
    "sg:address":"9323 Main St",
    "sg:city":"Ellsworth",
    "sg:classifiers":[
        {
            "category":"Organizations",
            "subcategory":"Religious Organization",
            "type":"Services"
        }
    ],
    "sg:phone":"+1 231 588 7805",
    "sg:postcode":"49729",
    "sg:province":"MI",
    "sg:tags":[
        "church"
    ],
    "wof:name":"Ellsworth Christian Church",
    "wof:placetype":"venue"
},
  "geometry": {"coordinates":[-85.24617499999999,45.166617],"type":"Point"}
}