{
  "type": "Feature",
  "properties": {
    "iso:country":"US",
    "sg:address":"2299 State Hwy 113",
    "sg:city":"Kingsley",
    "sg:classifiers":[
        {
            "category":"Cinema",
            "subcategory":"Movie Rental",
            "type":"Entertainment"
        }
    ],
    "sg:phone":"+1 231 263 4075",
    "sg:postcode":"49649",
    "sg:province":"MI",
    "sg:tags":[
        "leasing",
        "video",
        "disc",
        "tape"
    ],
    "wof:name":"Primetyme Video",
    "wof:placetype":"venue"
},
  "geometry": {"coordinates":[-85.521545,44.584653],"type":"Point"}
}