{
  "type": "Feature",
  "properties": {
    "iso:country":"US",
    "sg:address":"48670 Geddes Rd",
    "sg:city":"Canton",
    "sg:classifiers":[
        {
            "category":"Social Services",
            "subcategory":"Child Care",
            "type":"Services"
        },
        {
            "category":"Education",
            "subcategory":"Preschool",
            "type":"Public Place"
        },
        {
            "category":"Education",
            "subcategory":"School",
            "type":"Public Place"
        }
    ],
    "sg:phone":"+1 734 495 0833",
    "sg:postcode":"48188",
    "sg:province":"MI",
    "sg:tags":[
        "elementary",
        "day"
    ],
    "sg:website":"www.reallifenurseryschool.com",
    "wof:name":"Real Life Nursery School",
    "wof:placetype":"venue"
},
  "geometry": {"coordinates":[-83.5215,42.277599],"type":"Point"}
}