{
  "type": "Feature",
  "properties": {
    "iso:country":"US",
    "sg:address":"651 Northrup Ave NW",
    "sg:city":"Grand Rapids",
    "sg:classifiers":[
        {
            "category":"Professional",
            "subcategory":"Art Services",
            "type":"Services"
        }
    ],
    "sg:phone":"+1 616 453 2967",
    "sg:postcode":"49504",
    "sg:province":"MI",
    "sg:tags":[
        "commercial",
        "design"
    ],
    "wof:name":"Naimo Jones Jan Illustrations",
    "wof:placetype":"venue"
},
  "geometry": {"coordinates":[-85.725359,42.977963],"type":"Point"}
}