{
  "type": "Feature",
  "properties": {
    "iso:country":"US",
    "sg:address":"530 W Ionia St",
    "sg:city":"Lansing",
    "sg:classifiers":[
        {
            "category":"Organizations",
            "subcategory":"Professional Association",
            "type":"Services"
        }
    ],
    "sg:phone":"+1 517 346 5088",
    "sg:postcode":"48933",
    "sg:province":"MI",
    "wof:name":"Michigan Soc-Anesthesiologists",
    "wof:placetype":"venue"
},
  "geometry": {"coordinates":[-84.559648,42.736092],"type":"Point"}
}