{
  "type": "Feature",
  "properties": {
    "iso:country":"US",
    "sg:address":"6915 Rochester Rd",
    "sg:city":"Troy",
    "sg:classifiers":[
        {
            "category":"Banks & Credit Unions",
            "subcategory":"Investment Brokerage",
            "type":"Services"
        }
    ],
    "sg:phone":"+1 248 879 1448",
    "sg:postcode":"48085",
    "sg:province":"MI",
    "sg:tags":[
        "security"
    ],
    "sg:website":"www.edwardjones.com",
    "wof:name":"Edward Jones Co",
    "wof:placetype":"venue"
},
  "geometry": {"coordinates":[-83.130608,42.621335],"type":"Point"}
}