{
  "type": "Feature",
  "properties": {
    "iso:country":"US",
    "sg:address":"11200 State Hwy 32",
    "sg:city":"Lachine",
    "sg:classifiers":[
        {
            "category":"Real Estate",
            "subcategory":"Real Estate Agent",
            "type":"Services"
        }
    ],
    "sg:phone":"+1 989 379 4012",
    "sg:postcode":"49753",
    "sg:province":"MI",
    "wof:name":"Mc Girr Realty",
    "wof:placetype":"venue"
},
  "geometry": {"coordinates":[-83.67905,45.06755],"type":"Point"}
}