{
  "type": "Feature",
  "properties": {
    "iso:country":"US",
    "sg:address":"26510 Harper Ave",
    "sg:city":"Saint Clair Shores",
    "sg:classifiers":[
        {
            "category":"Banks & Credit Unions",
            "subcategory":"Financial Services",
            "type":"Services"
        }
    ],
    "sg:phone":"+1 586 552 5513",
    "sg:postcode":"48081",
    "sg:province":"MI",
    "sg:tags":[
        "broker",
        "mortgage"
    ],
    "wof:name":"Ebg Management",
    "wof:placetype":"venue"
},
  "geometry": {"coordinates":[-82.897824,42.488441],"type":"Point"}
}