{
  "type": "Feature",
  "properties": {
    "iso:country":"US",
    "sg:address":"414 Cheshire Dr NE",
    "sg:city":"Grand Rapids",
    "sg:classifiers":[
        {
            "category":"Professional",
            "subcategory":"Management & Consulting",
            "type":"Services"
        }
    ],
    "sg:phone":"+1 616 363 5684",
    "sg:postcode":"49505",
    "sg:province":"MI",
    "sg:tags":[
        "representative",
        "manufacturer"
    ],
    "wof:name":"James Casey Associates",
    "wof:placetype":"venue"
},
  "geometry": {"coordinates":[-85.659015,43.004065],"type":"Point"}
}