{
  "type": "Feature",
  "properties": {
    "iso:country":"US",
    "sg:address":"30231 Jefferson Ave",
    "sg:city":"Saint Clair Shores",
    "sg:classifiers":[
        {
            "category":"Health Services",
            "subcategory":"Doctor",
            "type":"Services"
        }
    ],
    "sg:phone":"+1 586 294 0350",
    "sg:postcode":"48082",
    "sg:province":"MI",
    "sg:tags":[
        "surgeon",
        "oral"
    ],
    "wof:name":"Sorbo David M DDS",
    "wof:placetype":"venue"
},
  "geometry": {"coordinates":[-82.878502,42.5172],"type":"Point"}
}