{
  "type": "Feature",
  "properties": {
    "iso:country":"US",
    "sg:address":"1081 S State Rd",
    "sg:city":"Davison",
    "sg:classifiers":[
        {
            "category":"Restaurant",
            "type":"Food & Drink"
        }
    ],
    "sg:phone":"+1 810 653 3400",
    "sg:postcode":"48423",
    "sg:province":"MI",
    "sg:tags":[
        "pizza"
    ],
    "wof:name":"Little Caesars Pizza",
    "wof:placetype":"venue"
},
  "geometry": {"coordinates":[-83.517403,43.018501],"type":"Point"}
}