{
  "type": "Feature",
  "properties": {
    "iso:country":"US",
    "sg:address":"700 Cheshire Dr",
    "sg:city":"Sturgis",
    "sg:classifiers":[
        {
            "category":"Banks & Credit Unions",
            "subcategory":"Bank",
            "type":"Services"
        }
    ],
    "sg:phone":"+1 269 651 1268",
    "sg:postcode":"49091",
    "sg:province":"MI",
    "sg:tags":[
        "state"
    ],
    "wof:name":"Sturgis Building Trades",
    "wof:placetype":"venue"
},
  "geometry": {"coordinates":[-85.41122799999999,41.817138],"type":"Point"}
}