{
  "type": "Feature",
  "properties": {
    "iso:country":"US",
    "sg:address":"3100 Henry St",
    "sg:city":"Muskegon",
    "sg:classifiers":[
        {
            "category":"Shopping",
            "subcategory":"Musical Instruments",
            "type":"Retail Goods"
        }
    ],
    "sg:phone":"+1 231 737 7625",
    "sg:postcode":"49441",
    "sg:province":"MI",
    "sg:tags":[
        "music",
        "dealer"
    ],
    "wof:name":"Moore Music",
    "wof:placetype":"venue"
},
  "geometry": {"coordinates":[-86.263231,43.195777],"type":"Point"}
}