{
  "type": "Feature",
  "properties": {
    "iso:country":"US",
    "sg:address":"28510 Halecreek St",
    "sg:city":"Romulus",
    "sg:classifiers":[
        {
            "category":"Professional",
            "type":"Services"
        }
    ],
    "sg:phone":"+1 734 941 2334",
    "sg:postcode":"48174",
    "sg:province":"MI",
    "wof:name":"Reptiles Unlimited",
    "wof:placetype":"venue"
},
  "geometry": {"coordinates":[-83.31717999999999,42.18884],"type":"Point"}
}