{
  "type": "Feature",
  "properties": {
    "iso:country":"US",
    "sg:address":"5587 N Adams Way",
    "sg:city":"Bloomfield Hills",
    "sg:classifiers":[
        {
            "category":"Health Services",
            "subcategory":"Doctor",
            "type":"Services"
        }
    ],
    "sg:phone":"+1 248 433 3398",
    "sg:postcode":"48302",
    "sg:province":"MI",
    "sg:tags":[
        "physician",
        "surgeon"
    ],
    "wof:name":"Robin Stone MD",
    "wof:placetype":"venue"
},
  "geometry": {"coordinates":[-83.284723,42.557069],"type":"Point"}
}