{
  "type": "Feature",
  "properties": {
    "iso:country":"US",
    "sg:address":"54833 Woodcreek Blvd",
    "sg:city":"Shelby Twp",
    "sg:classifiers":[
        {
            "category":"Building & Trades",
            "subcategory":"Construction",
            "type":"Services"
        }
    ],
    "sg:phone":"+1 586 786 1050",
    "sg:postcode":"48315",
    "sg:province":"MI",
    "sg:tags":[
        "home",
        "builder"
    ],
    "wof:name":"Sal-Mar Homes Inc",
    "wof:placetype":"venue"
},
  "geometry": {"coordinates":[-82.990071,42.699603],"type":"Point"}
}