{
  "type": "Feature",
  "properties": {
    "iso:country":"US",
    "sg:address":"5701 Woodbridge Ln",
    "sg:city":"Midland",
    "sg:classifiers":[
        {
            "category":"Wholesale",
            "subcategory":"Machinery & Supplies",
            "type":"Manufacturing & Wholesale Goods"
        }
    ],
    "sg:phone":"+1 989 835 5752",
    "sg:postcode":"48640",
    "sg:province":"MI",
    "sg:tags":[
        "equipment",
        "industrial"
    ],
    "wof:name":"Bernkay Industrial Tooling",
    "wof:placetype":"venue"
},
  "geometry": {"coordinates":[-84.27842200000001,43.649946],"type":"Point"}
}