{
  "type": "Feature",
  "properties": {
    "iso:country":"US",
    "sg:address":"2020 E Lansing Dr",
    "sg:city":"East Lansing",
    "sg:classifiers":[
        {
            "category":"Professional",
            "subcategory":"Management & Consulting",
            "type":"Services"
        }
    ],
    "sg:phone":"+1 517 333 4500",
    "sg:postcode":"48823",
    "sg:province":"MI",
    "sg:tags":[
        "consultant"
    ],
    "sg:website":"www.cityanimation.com",
    "wof:name":"City Animation",
    "wof:placetype":"venue"
},
  "geometry": {"coordinates":[-84.452006,42.749263],"type":"Point"}
}