{
  "type": "Feature",
  "properties": {
    "iso:country":"US",
    "sg:address":"1212 S Washington Ave",
    "sg:city":"Royal Oak",
    "sg:classifiers":[
        {
            "category":"Professional",
            "type":"Services"
        }
    ],
    "sg:phone":"+1 248 544 9586",
    "sg:postcode":"48067",
    "sg:province":"MI",
    "sg:tags":[
        "consulting",
        "management"
    ],
    "wof:name":"Big Productions",
    "wof:placetype":"venue"
},
  "geometry": {"coordinates":[-83.1463,42.478697],"type":"Point"}
}