{
  "type": "Feature",
  "properties": {
    "iso:country":"US",
    "sg:address":"5 S Glaspie St",
    "sg:city":"Oxford",
    "sg:classifiers":[
        {
            "category":"Building & Trades",
            "subcategory":"Electrical",
            "type":"Services"
        }
    ],
    "sg:phone":"+1 248 628 2575",
    "sg:postcode":"48371",
    "sg:province":"MI",
    "sg:tags":[
        "electric",
        "contractor"
    ],
    "wof:name":"Oxford Electric Co Inc",
    "wof:placetype":"venue"
},
  "geometry": {"coordinates":[-83.258875,42.823662],"type":"Point"}
}