{
  "type": "Feature",
  "properties": {
    "iso:country":"US",
    "sg:address":"511 N Mc Ewan St",
    "sg:city":"Clare",
    "sg:classifiers":[
        {
            "category":"Manufacturing",
            "subcategory":"Metals",
            "type":"Manufacturing & Wholesale Goods"
        }
    ],
    "sg:phone":"+1 989 386 9881",
    "sg:postcode":"48617",
    "sg:province":"MI",
    "sg:tags":[
        "engraver"
    ],
    "wof:name":"Artistic Engraving & Marketing",
    "wof:placetype":"venue"
},
  "geometry": {"coordinates":[-84.768254,43.822201],"type":"Point"}
}