{
  "type": "Feature",
  "properties": {
    "iso:country":"US",
    "sg:address":"5205 Eastman Ave",
    "sg:city":"Midland",
    "sg:classifiers":[
        {
            "category":"Food & Beverages",
            "subcategory":"Specialty",
            "type":"Retail Goods"
        }
    ],
    "sg:phone":"+1 989 835 7991",
    "sg:postcode":"48640",
    "sg:province":"MI",
    "sg:tags":[
        "gourmet",
        "shop"
    ],
    "sg:website":"www.eastmanpartystore.com",
    "wof:name":"Eastman Party Store",
    "wof:placetype":"venue"
},
  "geometry": {"coordinates":[-84.246853,43.644866],"type":"Point"}
}