{
  "type": "Feature",
  "properties": {
    "iso:country":"US",
    "sg:address":"417 Seymour Ave",
    "sg:city":"Lansing",
    "sg:classifiers":[
        {
            "category":"Insurance",
            "subcategory":"Insurance Agent",
            "type":"Services"
        }
    ],
    "sg:phone":"+1 517 482 9166",
    "sg:postcode":"48933",
    "sg:province":"MI",
    "wof:name":"Michigan County Insurance Pool",
    "wof:placetype":"venue"
},
  "geometry": {"coordinates":[-84.55544399999999,42.738399],"type":"Point"}
}