{
  "type": "Feature",
  "properties": {
    "iso:country":"US",
    "sg:address":"15464 Livernois Ave",
    "sg:city":"Detroit",
    "sg:classifiers":[
        {
            "category":"Autos & Motor Vehicles",
            "subcategory":"Fuel & Gas Station",
            "type":"Retail Goods"
        }
    ],
    "sg:phone":"+1 313 861 0224",
    "sg:postcode":"48238",
    "sg:province":"MI",
    "sg:website":"www.sunocoinc.com",
    "wof:name":"Sunoco Gas Station",
    "wof:placetype":"venue"
},
  "geometry": {"coordinates":[-83.140146,42.405132],"type":"Point"}
}