{
  "type": "Feature",
  "properties": {
    "iso:country":"US",
    "sg:address":"270 N Cedar St",
    "sg:city":"Imlay City",
    "sg:classifiers":[
        {
            "category":"Real Estate",
            "subcategory":"Real Estate Agent",
            "type":"Services"
        }
    ],
    "sg:phone":"+1 810 724 5300",
    "sg:postcode":"48444",
    "sg:province":"MI",
    "sg:tags":[
        "broker"
    ],
    "wof:name":"Market Value Real Estate Inc",
    "wof:placetype":"venue"
},
  "geometry": {"coordinates":[-83.07123799999999,43.027061],"type":"Point"}
}