{
  "type": "Feature",
  "properties": {
    "iso:country":"US",
    "sg:address":"692 Kinneville Rd",
    "sg:city":"Leslie",
    "sg:classifiers":[
        {
            "category":"Retail",
            "subcategory":"Repair Shop",
            "type":"Services"
        }
    ],
    "sg:phone":"+1 517 589 9673",
    "sg:postcode":"49251",
    "sg:province":"MI",
    "sg:tags":[
        "re"
    ],
    "wof:name":"Antiquity Restoration LLC",
    "wof:placetype":"venue"
},
  "geometry": {"coordinates":[-84.37175499999999,42.465727],"type":"Point"}
}