{
  "type": "Feature",
  "properties": {
    "iso:country":"US",
    "sg:address":"8075 Creekside Dr",
    "sg:city":"Portage",
    "sg:classifiers":[
        {
            "category":"Professional",
            "subcategory":"Employment Agencies",
            "type":"Services"
        }
    ],
    "sg:phone":"+1 269 321 5022",
    "sg:postcode":"49024",
    "sg:province":"MI",
    "sg:tags":[
        "opportunity",
        "contractor"
    ],
    "sg:website":"http://www.technisource.com",
    "wof:name":"Technisource",
    "wof:placetype":"venue"
},
  "geometry": {"coordinates":[-85.601508,42.199616],"type":"Point"}
}