{
  "type": "Feature",
  "properties": {
    "iso:country":"US",
    "sg:address":"2328 Livernois Rd",
    "sg:city":"Troy",
    "sg:classifiers":[
        {
            "category":"Banks & Credit Unions",
            "subcategory":"Bank",
            "type":"Services"
        }
    ],
    "sg:phone":"+1 248 619 0193",
    "sg:postcode":"48083",
    "sg:province":"MI",
    "sg:tags":[
        "mortgage"
    ],
    "wof:name":"Ufg Mortgage",
    "wof:placetype":"venue"
},
  "geometry": {"coordinates":[-83.14729699999999,42.55589],"type":"Point"}
}