{
  "type": "Feature",
  "properties": {
    "iso:country":"US",
    "sg:address":"190 N Powell Rd",
    "sg:city":"Essexville",
    "sg:classifiers":[
        {
            "category":"Banks & Credit Unions",
            "subcategory":"Bank",
            "type":"Services"
        }
    ],
    "sg:phone":"+1 989 892 2971",
    "sg:postcode":"48732",
    "sg:province":"MI",
    "sg:tags":[
        "loan",
        "real estate"
    ],
    "wof:name":"Irwin Mortgage",
    "wof:placetype":"venue"
},
  "geometry": {"coordinates":[-83.8403,43.595609],"type":"Point"}
}