{
  "type": "Feature",
  "properties": {
    "iso:country":"US",
    "sg:address":"8157 Lakecrest Dr",
    "sg:city":"Ypsilanti",
    "sg:classifiers":[
        {
            "category":"Manufacturing",
            "subcategory":"Jewelry",
            "type":"Manufacturing & Wholesale Goods"
        }
    ],
    "sg:phone":"+1 734 484 4751",
    "sg:postcode":"48197",
    "sg:province":"MI",
    "sg:tags":[
        "costume",
        "mfg"
    ],
    "wof:name":"Quiet Water Creations",
    "wof:placetype":"venue"
},
  "geometry": {"coordinates":[-83.599069,42.214118],"type":"Point"}
}