{
  "type": "Feature",
  "properties": {
    "iso:country":"US",
    "sg:address":"233 Beaupre Ave",
    "sg:city":"Grosse Pointe",
    "sg:classifiers":[
        {
            "category":"Real Estate",
            "subcategory":"Real Estate Agent",
            "type":"Services"
        }
    ],
    "sg:phone":"+1 313 885 3044",
    "sg:postcode":"48236",
    "sg:province":"MI",
    "wof:name":"Atlantic Ventures Inc",
    "wof:placetype":"venue"
},
  "geometry": {"coordinates":[-82.905396,42.405758],"type":"Point"}
}