{
  "type": "Feature",
  "properties": {
    "iso:country":"US",
    "sg:address":"44908 Trails Ct",
    "sg:city":"Canton",
    "sg:classifiers":[
        {
            "category":"Real Estate",
            "subcategory":"Real Estate Operator",
            "type":"Services"
        }
    ],
    "sg:phone":"+1 734 453 6500",
    "sg:postcode":"48187",
    "sg:province":"MI",
    "sg:tags":[
        "apartment"
    ],
    "sg:website":"www.smartapartmentliving.com",
    "wof:name":"Lincolnshire Apartments & Townhomes",
    "wof:placetype":"venue"
},
  "geometry": {"coordinates":[-83.482603,42.35029],"type":"Point"}
}