{
  "type": "Feature",
  "properties": {
    "iso:country":"US",
    "sg:address":"723 E Grand River Ave",
    "sg:city":"Portland",
    "sg:classifiers":[
        {
            "category":"Government",
            "subcategory":"Office",
            "type":"Public Place"
        }
    ],
    "sg:phone":"+1 517 647 6912",
    "sg:postcode":"48875",
    "sg:province":"MI",
    "sg:tags":[
        "village"
    ],
    "wof:name":"Portland Electric Distribution",
    "wof:placetype":"venue"
},
  "geometry": {"coordinates":[-84.896095,42.868493],"type":"Point"}
}