{
  "type": "Feature",
  "properties": {
    "iso:country":"US",
    "sg:address":"9837 Manning Rd",
    "sg:city":"Honor",
    "sg:classifiers":[
        {
            "category":"Home & Garden",
            "subcategory":"Garden Supply",
            "type":"Retail Goods"
        }
    ],
    "sg:phone":"+1 231 326 5855",
    "sg:postcode":"49640",
    "sg:province":"MI",
    "sg:tags":[
        "nurseryman"
    ],
    "wof:name":"Greystone Gardens",
    "wof:placetype":"venue"
},
  "geometry": {"coordinates":[-86.04443499999999,44.778518],"type":"Point"}
}