{
  "type": "Feature",
  "properties": {
    "iso:country":"US",
    "sg:address":"27475 Dover St",
    "sg:city":"Southfield",
    "sg:classifiers":[
        {
            "category":"Professional",
            "subcategory":"Management & Consulting",
            "type":"Services"
        }
    ],
    "sg:phone":"+1 248 353 1726",
    "sg:postcode":"48076",
    "sg:province":"MI",
    "sg:tags":[
        "business"
    ],
    "wof:name":"Galperin Enterprises Inc",
    "wof:placetype":"venue"
},
  "geometry": {"coordinates":[-83.258301,42.491141],"type":"Point"}
}