{
  "type": "Feature",
  "properties": {
    "iso:country":"US",
    "sg:address":"26900 Michigan Ave",
    "sg:city":"Inkster",
    "sg:classifiers":[
        {
            "category":"Retail",
            "subcategory":"Car Wash",
            "type":"Services"
        }
    ],
    "sg:phone":"+1 313 563 2247",
    "sg:postcode":"48141",
    "sg:province":"MI",
    "wof:name":"Mr Car Wash",
    "wof:placetype":"venue"
},
  "geometry": {"coordinates":[-83.31012800000001,42.294444],"type":"Point"}
}