{
  "type": "Feature",
  "properties": {
    "iso:country":"US",
    "sg:address":"200 E Big Beaver Rd",
    "sg:city":"Troy",
    "sg:classifiers":[
        {
            "category":"Insurance",
            "subcategory":"Insurance Agent",
            "type":"Services"
        }
    ],
    "sg:phone":"+1 248 362 8108",
    "sg:postcode":"48083",
    "sg:province":"MI",
    "sg:tags":[
        "consultant"
    ],
    "wof:name":"Employee Benefit Network",
    "wof:placetype":"venue"
},
  "geometry": {"coordinates":[-83.141516,42.562635],"type":"Point"}
}