{
  "type": "Feature",
  "properties": {
    "iso:country":"US",
    "sg:address":"17322 Cambridge Ave",
    "sg:city":"Southfield",
    "sg:classifiers":[
        {
            "category":"Building & Trades",
            "subcategory":"Construction",
            "type":"Services"
        }
    ],
    "sg:phone":"+1 248 569 3970",
    "sg:postcode":"48076",
    "sg:province":"MI",
    "sg:tags":[
        "home",
        "improvement"
    ],
    "wof:name":"Electric Eagle Co",
    "wof:placetype":"venue"
},
  "geometry": {"coordinates":[-83.21666999999999,42.490159],"type":"Point"}
}