{
  "type": "Feature",
  "properties": {
    "iso:country":"US",
    "sg:address":"37816 Ford Rd",
    "sg:city":"Westland",
    "sg:classifiers":[
        {
            "category":"Shopping",
            "subcategory":"Clothing, Apparel, & Fashions",
            "type":"Retail Goods"
        }
    ],
    "sg:phone":"+1 630 637 1300",
    "sg:postcode":"48185",
    "sg:province":"MI",
    "sg:tags":[
        "lingerie"
    ],
    "wof:name":"Lovers Lane & Co-Illinois",
    "wof:placetype":"venue"
},
  "geometry": {"coordinates":[-83.4132,42.323799],"type":"Point"}
}