{
  "type": "Feature",
  "properties": {
    "iso:country":"US",
    "sg:address":"2012 Hillgrove Pkwy",
    "sg:city":"Midland",
    "sg:classifiers":[
        {
            "category":"Building & Trades",
            "subcategory":"Construction",
            "type":"Services"
        }
    ],
    "sg:phone":"+1 989 839 0514",
    "sg:postcode":"48642",
    "sg:province":"MI",
    "sg:tags":[
        "general",
        "contractor"
    ],
    "wof:name":"Wertz Contracting Co",
    "wof:placetype":"venue"
},
  "geometry": {"coordinates":[-84.202973,43.63306],"type":"Point"}
}