{
  "type": "Feature",
  "properties": {
    "iso:country":"US",
    "sg:address":"1848 Ponderosa",
    "sg:city":"Columbus",
    "sg:classifiers":[
        {
            "category":"Building & Trades",
            "subcategory":"Construction",
            "type":"Services"
        }
    ],
    "sg:phone":"+1 586 727 3521",
    "sg:postcode":"48063",
    "sg:province":"MI",
    "sg:tags":[
        "excavating",
        "contractor"
    ],
    "wof:name":"Mike's Excavating & Dev",
    "wof:placetype":"venue"
},
  "geometry": {"coordinates":[-82.66550700000001,42.837089],"type":"Point"}
}