{
  "type": "Feature",
  "properties": {
    "iso:country":"US",
    "sg:address":"555 Michigan Ave",
    "sg:city":"Holland",
    "sg:classifiers":[
        {
            "category":"Organizations",
            "subcategory":"Non-profit Organization",
            "type":"Services"
        }
    ],
    "sg:phone":"+1 616 395 5902",
    "sg:postcode":"49423",
    "sg:province":"MI",
    "sg:tags":[
        "info",
        "addiction",
        "abuse",
        "treatment",
        "drug"
    ],
    "wof:name":"Narcotics Anonymous",
    "wof:placetype":"venue"
},
  "geometry": {"coordinates":[-86.111423,42.776443],"type":"Point"}
}