{
  "type": "Feature",
  "properties": {
    "iso:country":"US",
    "sg:address":"1513 Fulton St E",
    "sg:city":"Grand Rapids",
    "sg:classifiers":[
        {
            "category":"Organizations",
            "subcategory":"Religious Organization",
            "type":"Services"
        }
    ],
    "sg:phone":"+1 616 233 4023",
    "sg:postcode":"49503",
    "sg:province":"MI",
    "sg:website":"www.calvarychapel.com",
    "wof:name":"Calvary Chapel",
    "wof:placetype":"venue"
},
  "geometry": {"coordinates":[-85.63287800000001,42.962789],"type":"Point"}
}