{
  "type": "Feature",
  "properties": {
    "iso:country":"US",
    "sg:address":"4591 Fruin Rd",
    "sg:city":"Bellevue",
    "sg:classifiers":[
        {
            "category":"Social Services",
            "subcategory":"Child Care",
            "type":"Services"
        }
    ],
    "sg:phone":"+1 269 758 4334",
    "sg:postcode":"49021",
    "sg:province":"MI",
    "wof:name":"Titia's Tot's Day Care",
    "wof:placetype":"venue"
},
  "geometry": {"coordinates":[-85.199783,42.471524],"type":"Point"}
}