{
  "type": "Feature",
  "properties": {
    "iso:country":"US",
    "sg:address":"35438 Mound Rd",
    "sg:city":"Sterling Heights",
    "sg:classifiers":[
        {
            "category":"Manufacturing",
            "subcategory":"Rubber & Plastics",
            "type":"Manufacturing & Wholesale Goods"
        }
    ],
    "sg:phone":"+1 586 795 0065",
    "sg:postcode":"48310",
    "sg:province":"MI",
    "wof:name":"Urethane Engineering Corp",
    "wof:placetype":"venue"
},
  "geometry": {"coordinates":[-83.048428,42.555509],"type":"Point"}
}