{
  "type": "Feature",
  "properties": {
    "iso:country":"US",
    "sg:address":"21815 Greater Mack Ave",
    "sg:city":"St Clair Shores",
    "sg:classifiers":[
        {
            "category":"Shopping",
            "subcategory":"Computers & Home Electronics",
            "type":"Retail Goods"
        }
    ],
    "sg:phone":"+1 586 772 9333",
    "sg:postcode":"48080",
    "sg:province":"MI",
    "sg:tags":[
        "television",
        "radio"
    ],
    "wof:name":"Nbs TV & Video-Audio Sales",
    "wof:placetype":"venue"
},
  "geometry": {"coordinates":[-82.902923,42.455007],"type":"Point"}
}