{
  "type": "Feature",
  "properties": {
    "iso:country":"US",
    "sg:address":"1262 Van Dyke Rd",
    "sg:city":"Beaverton",
    "sg:classifiers":[
        {
            "category":"Professional",
            "subcategory":"Advertising",
            "type":"Services"
        }
    ],
    "sg:phone":"+1 989 435 2599",
    "sg:postcode":"48612",
    "sg:province":"MI",
    "sg:tags":[
        "agency"
    ],
    "wof:name":"Creative Exchange Inc",
    "wof:placetype":"venue"
},
  "geometry": {"coordinates":[-84.41207,43.871967],"type":"Point"}
}