{
  "type": "Feature",
  "properties": {
    "iso:country":"US",
    "sg:address":"900 E Paris Ave SE",
    "sg:city":"Grand Rapids",
    "sg:classifiers":[
        {
            "category":"Real Estate",
            "subcategory":"Real Estate Services",
            "type":"Services"
        }
    ],
    "sg:phone":"+1 616 975 7756",
    "sg:postcode":"49546",
    "sg:province":"MI",
    "sg:tags":[
        "company",
        "title"
    ],
    "wof:name":"Michigan Bankers Title LLC",
    "wof:placetype":"venue"
},
  "geometry": {"coordinates":[-85.570605,42.947262],"type":"Point"}
}