{
  "type": "Feature",
  "properties": {
    "iso:country":"US",
    "sg:address":"29548 Northwestern Hwy",
    "sg:city":"Southfield",
    "sg:classifiers":[
        {
            "category":"Shopping",
            "subcategory":"Used Merchandise",
            "type":"Retail Goods"
        }
    ],
    "sg:phone":"+1 248 356 0212",
    "sg:postcode":"48034",
    "sg:province":"MI",
    "sg:tags":[
        "shop",
        "consignment"
    ],
    "wof:name":"North West Resale",
    "wof:placetype":"venue"
},
  "geometry": {"coordinates":[-83.312647,42.503401],"type":"Point"}
}