{
  "type": "Feature",
  "properties": {
    "iso:country":"US",
    "sg:address":"6129 N Dort Hwy",
    "sg:city":"Flint",
    "sg:classifiers":[
        {
            "category":"Professional",
            "subcategory":"Detective & Security Services",
            "type":"Services"
        }
    ],
    "sg:phone":"+1 810 785 2200",
    "sg:postcode":"48505",
    "sg:province":"MI",
    "sg:tags":[
        "guard",
        "patrol"
    ],
    "wof:name":"Guardian Armored",
    "wof:placetype":"venue"
},
  "geometry": {"coordinates":[-83.67406200000001,43.065021],"type":"Point"}
}