{
  "type": "Feature",
  "properties": {
    "iso:country":"US",
    "sg:address":"2810 W Blanchard Rd",
    "sg:city":"Winn",
    "sg:classifiers":[
        {
            "category":"Food & Beverages",
            "subcategory":"Groceries & Convenience Stores",
            "type":"Retail Goods"
        }
    ],
    "sg:phone":"+1 989 866 2480",
    "sg:postcode":"48896",
    "sg:province":"MI",
    "sg:tags":[
        "grocer"
    ],
    "wof:name":"Winn Shopping Ctr",
    "wof:placetype":"venue"
},
  "geometry": {"coordinates":[-84.90337599999999,43.525189],"type":"Point"}
}