{
  "type": "Feature",
  "properties": {
    "iso:country":"US",
    "sg:address":"22022 Parkwood Ln",
    "sg:city":"Northville",
    "sg:classifiers":[
        {
            "category":"Professional",
            "subcategory":"Computer Services",
            "type":"Services"
        }
    ],
    "sg:phone":"+1 248 478 3221",
    "sg:postcode":"48167",
    "sg:province":"MI",
    "sg:tags":[
        "datum"
    ],
    "wof:name":"Agitated Net Irc Network",
    "wof:placetype":"venue"
},
  "geometry": {"coordinates":[-83.42843999999999,42.45144],"type":"Point"}
}