{
  "type": "Feature",
  "properties": {
    "iso:country":"US",
    "sg:address":"24792 Hathaway St",
    "sg:city":"Farmington Hills",
    "sg:classifiers":[
        {
            "category":"Building & Trades",
            "subcategory":"Construction",
            "type":"Services"
        }
    ],
    "sg:phone":"+1 248 471 1616",
    "sg:postcode":"48335",
    "sg:province":"MI",
    "sg:tags":[
        "restoration",
        "cleaning",
        "patio",
        "deck"
    ],
    "wof:name":"Hydroblast",
    "wof:placetype":"venue"
},
  "geometry": {"coordinates":[-83.42294800000001,42.470185],"type":"Point"}
}