{
  "type": "Feature",
  "properties": {
    "iso:country":"US",
    "sg:address":"1601 E Stockbridge Ave",
    "sg:city":"Kalamazoo",
    "sg:classifiers":[
        {
            "category":"Food & Beverages",
            "subcategory":"Specialty",
            "type":"Retail Goods"
        },
        {
            "category":"Food & Beverages",
            "subcategory":"Groceries & Convenience Stores",
            "type":"Retail Goods"
        }
    ],
    "sg:phone":"+1 269 381 6464",
    "sg:postcode":"49001",
    "sg:province":"MI",
    "sg:tags":[
        "grocers-specialty"
    ],
    "wof:name":"Jack's Party Store",
    "wof:placetype":"venue"
},
  "geometry": {"coordinates":[-85.56047100000001,42.277451],"type":"Point"}
}