{
  "type": "Feature",
  "properties": {
    "iso:country":"US",
    "sg:address":"31440 Northwestern Hwy Ste 120",
    "sg:city":"Farmington Hills",
    "sg:classifiers":[
        {
            "category":"Professional",
            "subcategory":"Lawyer & Legal Services",
            "type":"Services"
        }
    ],
    "sg:phone":"+1 248 851 5316",
    "sg:postcode":"48334",
    "sg:province":"MI",
    "sg:website":"www.wetzeltrott.com",
    "wof:name":"Wetzel Trott",
    "wof:placetype":"venue"
},
  "geometry": {"coordinates":[-83.338252,42.518253],"type":"Point"}
}