{
  "type": "Feature",
  "properties": {
    "iso:country":"US",
    "sg:address":"3160 Biddle Ave",
    "sg:city":"Wyandotte",
    "sg:classifiers":[
        {
            "category":"Shopping",
            "subcategory":"Jewelry",
            "type":"Retail Goods"
        }
    ],
    "sg:phone":"+1 734 284 9044",
    "sg:postcode":"48192",
    "sg:province":"MI",
    "sg:website":"milkinsjewelers.com",
    "wof:name":"Milkins Jewelers",
    "wof:placetype":"venue"
},
  "geometry": {"coordinates":[-83.150516,42.201419],"type":"Point"}
}