{
  "type": "Feature",
  "properties": {
    "iso:country":"US",
    "sg:address":"200 S Stewart Ave",
    "sg:city":"Big Rapids",
    "sg:classifiers":[
        {
            "category":"Organizations",
            "subcategory":"Membership Organization",
            "type":"Services"
        }
    ],
    "sg:phone":"+1 231 592 0933",
    "sg:postcode":"49307",
    "sg:province":"MI",
    "wof:name":"Hope House Ministries",
    "wof:placetype":"venue"
},
  "geometry": {"coordinates":[-85.47891799999999,43.697053],"type":"Point"}
}