{
  "type": "Feature",
  "properties": {
    "iso:country":"US",
    "sg:address":"12301 N Division Ave",
    "sg:city":"Sparta",
    "sg:classifiers":[
        {
            "category":"Retail",
            "subcategory":"Repair Shop",
            "type":"Services"
        },
        {
            "category":"Autos & Motor Vehicles",
            "subcategory":"Auto Supplies",
            "type":"Retail Goods"
        }
    ],
    "sg:phone":"+1 616 887 0912",
    "sg:postcode":"49345",
    "sg:province":"MI",
    "sg:tags":[
        "industrial",
        "automobile",
        "equipment",
        "balancing",
        "car",
        "racing"
    ],
    "wof:name":"G R Electronics Balancing",
    "wof:placetype":"venue"
},
  "geometry": {"coordinates":[-85.67129799999999,43.189491],"type":"Point"}
}