{
  "type": "Feature",
  "properties": {
    "iso:country":"US",
    "sg:address":"980 Regents Park Dr",
    "sg:city":"Monroe",
    "sg:classifiers":[
        {
            "category":"Manufacturing",
            "subcategory":"Rubber & Plastics",
            "type":"Manufacturing & Wholesale Goods"
        }
    ],
    "sg:phone":"+1 734 457 2960",
    "sg:postcode":"48161",
    "sg:province":"MI",
    "sg:tags":[
        "sealing",
        "devices",
        "gasket"
    ],
    "wof:name":"Gasket Guy Of Detroit",
    "wof:placetype":"venue"
},
  "geometry": {"coordinates":[-83.457159,41.920423],"type":"Point"}
}