{
  "type": "Feature",
  "properties": {
    "iso:country":"US",
    "sg:address":"1388 Baldwin St",
    "sg:city":"Jenison",
    "sg:classifiers":[
        {
            "category":"Organizations",
            "subcategory":"Professional Association",
            "type":"Services"
        }
    ],
    "sg:phone":"+1 616 457 8555",
    "sg:postcode":"49428",
    "sg:province":"MI",
    "sg:tags":[
        "chambers",
        "commerce"
    ],
    "wof:name":"Jenison Area Chamber-Commerce",
    "wof:placetype":"venue"
},
  "geometry": {"coordinates":[-85.81338599999999,42.907122],"type":"Point"}
}