{
  "type": "Feature",
  "properties": {
    "iso:country":"US",
    "sg:address":"60 Parkhurst St",
    "sg:city":"Pontiac",
    "sg:classifiers":[
        {
            "category":"Education",
            "subcategory":"School",
            "type":"Public Place"
        }
    ],
    "sg:phone":"+1 248 857 8222",
    "sg:postcode":"48342",
    "sg:province":"MI",
    "wof:name":"Whrc",
    "wof:placetype":"venue"
},
  "geometry": {"coordinates":[-83.284992,42.634892],"type":"Point"}
}