{
  "type": "Feature",
  "properties": {
    "iso:country":"US",
    "sg:address":"23700 Philip Dr",
    "sg:city":"Southfield",
    "sg:classifiers":[
        {
            "category":"Arts & Performance",
            "subcategory":"Theater",
            "type":"Entertainment"
        }
    ],
    "sg:phone":"+1 248 353 6177",
    "sg:postcode":"48075",
    "sg:province":"MI",
    "sg:tags":[
        "group",
        "vocal"
    ],
    "wof:name":"Miracles",
    "wof:placetype":"venue"
},
  "geometry": {"coordinates":[-83.229857,42.461998],"type":"Point"}
}