{
  "type": "Feature",
  "properties": {
    "iso:country":"US",
    "sg:address":"48644 Roma Valley Dr",
    "sg:city":"Shelby Twp",
    "sg:classifiers":[
        {
            "category":"Building & Trades",
            "subcategory":"Landscaping Services",
            "type":"Services"
        }
    ],
    "sg:phone":"+1 586 323 0520",
    "sg:postcode":"48317",
    "sg:province":"MI",
    "sg:tags":[
        "lawn",
        "maintenance",
        "grounds"
    ],
    "wof:name":"ANR",
    "wof:placetype":"venue"
},
  "geometry": {"coordinates":[-83.04824000000001,42.651808],"type":"Point"}
}