{
  "type": "Feature",
  "properties": {
    "iso:country":"US",
    "sg:address":"74 Battle Creek Ave",
    "sg:city":"Battle Creek",
    "sg:classifiers":[
        {
            "category":"Retail",
            "subcategory":"Repair Shop",
            "type":"Services"
        }
    ],
    "sg:phone":"+1 269 660 8324",
    "sg:postcode":"49037",
    "sg:province":"MI",
    "sg:tags":[
        "upholsterer"
    ],
    "wof:name":"Ny Custom Upholstering-Window",
    "wof:placetype":"venue"
},
  "geometry": {"coordinates":[-85.85833599999999,43.74704],"type":"Point"}
}