{
  "type": "Feature",
  "properties": {
    "iso:country":"US",
    "sg:address":"15128 Seagull Dr",
    "sg:city":"Sterling Heights",
    "sg:classifiers":[
        {
            "category":"Building & Trades",
            "subcategory":"Construction",
            "type":"Services"
        }
    ],
    "sg:phone":"+1 586 566 7060",
    "sg:postcode":"48313",
    "sg:province":"MI",
    "sg:tags":[
        "dry wall",
        "contractor"
    ],
    "wof:name":"Absolute Dry Wall",
    "wof:placetype":"venue"
},
  "geometry": {"coordinates":[-82.973958,42.615301],"type":"Point"}
}