{
  "type": "Feature",
  "properties": {
    "iso:country":"US",
    "sg:address":"305 Remus Dr",
    "sg:city":"Buchanan",
    "sg:classifiers":[
        {
            "category":"Professional",
            "subcategory":"Computer Services",
            "type":"Services"
        }
    ],
    "sg:phone":"+1 269 695 1547",
    "sg:postcode":"49107",
    "sg:province":"MI",
    "sg:tags":[
        "design",
        "system"
    ],
    "wof:name":"Fuller Web Designs",
    "wof:placetype":"venue"
},
  "geometry": {"coordinates":[-86.364599,41.836138],"type":"Point"}
}