{
  "type": "Feature",
  "properties": {
    "iso:country":"US",
    "sg:address":"7220 Gratiot Ave",
    "sg:city":"Detroit",
    "sg:classifiers":[
        {
            "category":"Health Services",
            "subcategory":"Doctor",
            "type":"Services"
        },
        {
            "category":"Health Services",
            "subcategory":"Chiropractor",
            "type":"Services"
        }
    ],
    "sg:phone":"+1 248 388 4941",
    "sg:postcode":"48213",
    "sg:province":"MI",
    "sg:tags":[
        "medicine",
        "sport"
    ],
    "wof:name":"Chiropractic Works PC",
    "wof:placetype":"venue"
},
  "geometry": {"coordinates":[-83.017799,42.373798],"type":"Point"}
}