{
  "type": "Feature",
  "properties": {
    "iso:country":"US",
    "sg:address":"1032 N Crooks Rd Ste F",
    "sg:city":"Clawson",
    "sg:classifiers":[
        {
            "category":"Building & Trades",
            "subcategory":"Pest Control",
            "type":"Services"
        }
    ],
    "sg:phone":"+1 248 280 8530",
    "sg:postcode":"48017",
    "sg:province":"MI",
    "wof:name":"Abell Pest Control Inc",
    "wof:placetype":"venue"
},
  "geometry": {"coordinates":[-83.166236,42.541065],"type":"Point"}
}