{
  "type": "Feature",
  "properties": {
    "iso:country":"US",
    "sg:address":"14626 Houston Whittier St",
    "sg:city":"Detroit",
    "sg:classifiers":[
        {
            "category":"Manufacturing",
            "subcategory":"Tools & Machinery",
            "type":"Manufacturing & Wholesale Goods"
        }
    ],
    "sg:phone":"+1 313 839 6480",
    "sg:postcode":"48205",
    "sg:province":"MI",
    "sg:tags":[
        "industrial",
        "mfg"
    ],
    "wof:name":"Royal Centerless Grinding",
    "wof:placetype":"venue"
},
  "geometry": {"coordinates":[-82.97193300000001,42.420621],"type":"Point"}
}