{
  "type": "Feature",
  "properties": {
    "iso:country":"US",
    "sg:address":"4839 Steffas Rd",
    "sg:city":"Monroe",
    "sg:classifiers":[
        {
            "category":"Recreation",
            "type":"Entertainment"
        }
    ],
    "sg:phone":"+1 734 384 1718",
    "sg:postcode":"48162",
    "sg:province":"MI",
    "sg:tags":[
        "riding",
        "academy"
    ],
    "wof:name":"Raisinville Farm",
    "wof:placetype":"venue"
},
  "geometry": {"coordinates":[-83.454426,41.999992],"type":"Point"}
}