{
  "type": "Feature",
  "properties": {
    "iso:country":"US",
    "sg:address":"1132 Division Ave S",
    "sg:city":"Grand Rapids",
    "sg:classifiers":[
        {
            "category":"Organizations",
            "subcategory":"Religious Organization",
            "type":"Services"
        }
    ],
    "sg:phone":"+1 616 452 3904",
    "sg:postcode":"49507",
    "sg:province":"MI",
    "sg:tags":[
        "church"
    ],
    "wof:name":"Church Of God Of Sion",
    "wof:placetype":"venue"
},
  "geometry": {"coordinates":[-85.667269,42.941521],"type":"Point"}
}