{
  "type": "Feature",
  "properties": {
    "iso:country":"US",
    "sg:address":"34122 Woodward Ave",
    "sg:city":"Birmingham",
    "sg:classifiers":[
        {
            "category":"Real Estate",
            "subcategory":"Real Estate Services",
            "type":"Services"
        }
    ],
    "sg:phone":"+1 248 357 3270",
    "sg:postcode":"48009",
    "sg:province":"MI",
    "sg:tags":[
        "company",
        "title"
    ],
    "wof:name":"Land Owners Title Agency",
    "wof:placetype":"venue"
},
  "geometry": {"coordinates":[-83.207064,42.540108],"type":"Point"}
}