{
  "type": "Feature",
  "properties": {
    "iso:country":"US",
    "sg:address":"19319 Archdale St",
    "sg:city":"Detroit",
    "sg:classifiers":[
        {
            "category":"Professional",
            "subcategory":"Business Services",
            "type":"Services"
        }
    ],
    "sg:phone":"+1 313 534 2574",
    "sg:postcode":"48235",
    "sg:province":"MI",
    "wof:name":"Lyqk Enterprises",
    "wof:placetype":"venue"
},
  "geometry": {"coordinates":[-83.21742999999999,42.433358],"type":"Point"}
}