{
  "type": "Feature",
  "properties": {
    "iso:country":"US",
    "sg:address":"601 Calumet St",
    "sg:city":"Lake Linden",
    "sg:classifiers":[
        {
            "category":"Education",
            "subcategory":"School",
            "type":"Public Place"
        }
    ],
    "sg:phone":"+1 906 296 6211",
    "sg:postcode":"49945",
    "sg:province":"MI",
    "sg:tags":[
        "district"
    ],
    "wof:name":"School District 31-130",
    "wof:placetype":"venue"
},
  "geometry": {"coordinates":[-88.40770500000001,47.194433],"type":"Point"}
}