{
  "type": "Feature",
  "properties": {
    "iso:country":"US",
    "sg:address":"5026 Straits Hwy",
    "sg:city":"Indian River",
    "sg:classifiers":[
        {
            "category":"Retail",
            "subcategory":"Repair Shop",
            "type":"Services"
        }
    ],
    "sg:phone":"+1 231 238 0900",
    "sg:postcode":"49749",
    "sg:province":"MI",
    "sg:tags":[
        "equipment",
        "outdoor",
        "power"
    ],
    "wof:name":"Triple-M Power Equipment Inc",
    "wof:placetype":"venue"
},
  "geometry": {"coordinates":[-84.629154,45.386812],"type":"Point"}
}