{
  "type": "Feature",
  "properties": {
    "iso:country":"US",
    "sg:address":"6617 Western Ave",
    "sg:city":"Glen Arbor",
    "sg:classifiers":[
        {
            "category":"Museum",
            "type":"Entertainment"
        }
    ],
    "sg:phone":"+1 231 334 4732",
    "sg:postcode":"49636",
    "sg:province":"MI",
    "sg:tags":[
        "gallery"
    ],
    "wof:name":"Synchronicity Gallery",
    "wof:placetype":"venue"
},
  "geometry": {"coordinates":[-85.992169,44.89767],"type":"Point"}
}