{
  "type": "Feature",
  "properties": {
    "iso:country":"US",
    "sg:address":"73619 Dequindre Rd",
    "sg:city":"Leonard",
    "sg:classifiers":[
        {
            "category":"Wholesale",
            "subcategory":"Hardware",
            "type":"Manufacturing & Wholesale Goods"
        }
    ],
    "sg:phone":"+1 586 752 6068",
    "sg:postcode":"48367",
    "sg:province":"MI",
    "wof:name":"Snap-On Tools",
    "wof:placetype":"venue"
},
  "geometry": {"coordinates":[-83.100442,42.826886],"type":"Point"}
}