{
  "type": "Feature",
  "properties": {
    "iso:country":"US",
    "sg:address":"875 Airport Blvd",
    "sg:city":"Ann Arbor",
    "sg:classifiers":[
        {
            "category":"Government",
            "subcategory":"Office",
            "type":"Public Place"
        }
    ],
    "sg:phone":"+1 734 769 1830",
    "sg:postcode":"48108",
    "sg:province":"MI",
    "sg:tags":[
        "federal",
        "aviation"
    ],
    "wof:name":"Airport Traffic Control Tower",
    "wof:placetype":"venue"
},
  "geometry": {"coordinates":[-83.748734,42.225986],"type":"Point"}
}