{
  "type": "Feature",
  "properties": {
    "iso:country":"US",
    "sg:address":"9361 Rayna Dr",
    "sg:city":"Davison",
    "sg:classifiers":[
        {
            "category":"Building & Trades",
            "subcategory":"Construction",
            "type":"Services"
        }
    ],
    "sg:phone":"+1 810 658 3535",
    "sg:postcode":"48423",
    "sg:province":"MI",
    "sg:tags":[
        "painter"
    ],
    "wof:name":"J G Michael's Painting",
    "wof:placetype":"venue"
},
  "geometry": {"coordinates":[-83.520893,43.017781],"type":"Point"}
}