{
  "type": "Feature",
  "properties": {
    "iso:country":"US",
    "sg:address":"47 Clarence St",
    "sg:city":"Pontiac",
    "sg:classifiers":[
        {
            "category":"Professional",
            "subcategory":"Business Services",
            "type":"Services"
        }
    ],
    "sg:phone":"+1 248 253 0874",
    "sg:postcode":"48342",
    "sg:province":"MI",
    "wof:name":"Building Solutions",
    "wof:placetype":"venue"
},
  "geometry": {"coordinates":[-83.287592,42.649762],"type":"Point"}
}