{
  "type": "Feature",
  "properties": {
    "iso:country":"US",
    "sg:address":"519 E Dowland St",
    "sg:city":"Ludington",
    "sg:classifiers":[
        {
            "category":"Bars & Pubs",
            "type":"Food & Drink"
        }
    ],
    "sg:phone":"+1 231 845 5895",
    "sg:postcode":"49431",
    "sg:province":"MI",
    "wof:name":"Bud's Tap Room",
    "wof:placetype":"venue"
},
  "geometry": {"coordinates":[-86.440546,43.949582],"type":"Point"}
}