{
  "type": "Feature",
  "properties": {
    "iso:country":"US",
    "sg:address":"4057 Commerce Dr",
    "sg:city":"Flushing",
    "sg:classifiers":[
        {
            "category":"Wholesale",
            "subcategory":"Durable Goods & Equipment",
            "type":"Manufacturing & Wholesale Goods"
        }
    ],
    "sg:phone":"+1 810 487 1096",
    "sg:postcode":"48433",
    "sg:province":"MI",
    "sg:tags":[
        "representative",
        "manufacturer"
    ],
    "wof:name":"Elite Products Inc",
    "wof:placetype":"venue"
},
  "geometry": {"coordinates":[-83.80919299999999,43.062],"type":"Point"}
}