{
  "type": "Feature",
  "properties": {
    "iso:country":"US",
    "sg:address":"12870 Lahser Rd",
    "sg:city":"Detroit",
    "sg:classifiers":[
        {
            "category":"Real Estate",
            "subcategory":"Real Estate Services",
            "type":"Services"
        }
    ],
    "sg:phone":"+1 313 362 9997",
    "sg:postcode":"48223",
    "sg:province":"MI",
    "sg:tags":[
        "management",
        "property"
    ],
    "wof:name":"First Choice Properyt Management",
    "wof:placetype":"venue"
},
  "geometry": {"coordinates":[-83.256038,42.382479],"type":"Point"}
}