{
  "type": "Feature",
  "properties": {
    "iso:country":"US",
    "sg:address":"2550 Bluewater Ct SW",
    "sg:city":"Grandville",
    "sg:classifiers":[
        {
            "category":"Education",
            "subcategory":"Special Training",
            "type":"Public Place"
        }
    ],
    "sg:phone":"+1 616 531 7744",
    "sg:postcode":"49418",
    "sg:province":"MI",
    "wof:name":"Meier Reading Svc",
    "wof:placetype":"venue"
},
  "geometry": {"coordinates":[-85.73870599999999,42.918087],"type":"Point"}
}