{
  "type": "Feature",
  "properties": {
    "iso:country":"US",
    "sg:address":"37602 96th Ave",
    "sg:city":"Decatur",
    "sg:classifiers":[
        {
            "category":"Real Estate",
            "subcategory":"Real Estate Operator",
            "type":"Services"
        }
    ],
    "sg:phone":"+1 269 423 7706",
    "sg:postcode":"49045",
    "sg:province":"MI",
    "sg:tags":[
        "property",
        "conservation",
        "lessor"
    ],
    "wof:name":"Donald Mackellar",
    "wof:placetype":"venue"
},
  "geometry": {"coordinates":[-85.89874,42.069561],"type":"Point"}
}