{
  "type": "Feature",
  "properties": {
    "iso:country":"US",
    "sg:address":"1315 Greenridge Dr",
    "sg:city":"Flint",
    "sg:classifiers":[
        {
            "category":"Building & Trades",
            "subcategory":"Construction",
            "type":"Services"
        }
    ],
    "sg:phone":"+1 810 732 6179",
    "sg:postcode":"48532",
    "sg:province":"MI",
    "sg:tags":[
        "carpentry",
        "contractor"
    ],
    "wof:name":"H&K Finish Carpentry",
    "wof:placetype":"venue"
},
  "geometry": {"coordinates":[-83.75488900000001,43.00764],"type":"Point"}
}