{
  "type": "Feature",
  "properties": {
    "iso:country":"US",
    "sg:address":"27560 Ponchartrain St",
    "sg:city":"Harrison Twp",
    "sg:classifiers":[
        {
            "category":"Building & Trades",
            "subcategory":"Construction",
            "type":"Services"
        }
    ],
    "sg:phone":"+1 586 465 5950",
    "sg:postcode":"48045",
    "sg:province":"MI",
    "sg:tags":[
        "painter"
    ],
    "wof:name":"New Finish Painting Co",
    "wof:placetype":"venue"
},
  "geometry": {"coordinates":[-82.834688,42.568318],"type":"Point"}
}