{
  "type": "Feature",
  "properties": {
    "iso:country":"US",
    "sg:address":"124 E Chicago Blvd",
    "sg:city":"Britton",
    "sg:classifiers":[
        {
            "category":"Professional",
            "subcategory":"Business Services",
            "type":"Services"
        }
    ],
    "sg:phone":"+1 517 451 4021",
    "sg:postcode":"49229",
    "sg:province":"MI",
    "sg:tags":[
        "interior",
        "designer",
        "decorator",
        "workroom"
    ],
    "wof:name":"Karyn Forbes-Thomas",
    "wof:placetype":"venue"
},
  "geometry": {"coordinates":[-83.83053200000001,41.986571],"type":"Point"}
}