{
  "type": "Feature",
  "properties": {
    "iso:country":"US",
    "sg:address":"2529 S Pine View Rd",
    "sg:city":"Suttons Bay",
    "sg:classifiers":[
        {
            "category":"Professional",
            "type":"Services"
        }
    ],
    "sg:phone":"+1 231 271 6683",
    "sg:postcode":"49682",
    "sg:province":"MI",
    "wof:name":"Quikeys Transcription Svcs LLC",
    "wof:placetype":"venue"
},
  "geometry": {"coordinates":[-85.655235,44.947659],"type":"Point"}
}