{
  "type": "Feature",
  "properties": {
    "iso:country":"US",
    "sg:address":"7341 Triangle Dr",
    "sg:city":"Sterling Heights",
    "sg:classifiers":[
        {
            "category":"Real Estate",
            "subcategory":"Architect",
            "type":"Services"
        }
    ],
    "sg:phone":"+1 586 803 1410",
    "sg:postcode":"48314",
    "sg:province":"MI",
    "wof:name":"Das Architechs",
    "wof:placetype":"venue"
},
  "geometry": {"coordinates":[-83.036339,42.616197],"type":"Point"}
}