{
  "type": "Feature",
  "properties": {
    "iso:country":"US",
    "sg:address":"221 Ann St",
    "sg:city":"East Lansing",
    "sg:classifiers":[
        {
            "category":"Food & Beverages",
            "subcategory":"Liquor & Beverages",
            "type":"Retail Goods"
        }
    ],
    "sg:phone":"+1 517 337 3950",
    "sg:postcode":"48823",
    "sg:province":"MI",
    "wof:name":"Spartan Spirits",
    "wof:placetype":"venue"
},
  "geometry": {"coordinates":[-84.48092,42.7359],"type":"Point"}
}