{
  "type": "Feature",
  "properties": {
    "iso:country":"US",
    "sg:address":"2136 Edington Dr SE",
    "sg:city":"Grand Rapids",
    "sg:classifiers":[
        {
            "category":"Professional",
            "subcategory":"Art Services",
            "type":"Services"
        }
    ],
    "sg:phone":"+1 616 243 9293",
    "sg:postcode":"49508",
    "sg:province":"MI",
    "sg:tags":[
        "graphic",
        "designer"
    ],
    "wof:name":"Blimpie Bv & Blimpie Bk",
    "wof:placetype":"venue"
},
  "geometry": {"coordinates":[-85.611808,42.897213],"type":"Point"}
}