{
  "type": "Feature",
  "properties": {
    "iso:country":"US",
    "sg:address":"247 W Lovell St",
    "sg:city":"Kalamazoo",
    "sg:classifiers":[
        {
            "category":"Organizations",
            "subcategory":"Religious Organization",
            "type":"Services"
        }
    ],
    "sg:phone":"+1 269 345 8553",
    "sg:postcode":"49007",
    "sg:province":"MI",
    "sg:tags":[
        "church"
    ],
    "wof:name":"St Luke's Episcopal Church",
    "wof:placetype":"venue"
},
  "geometry": {"coordinates":[-85.585517,42.288653],"type":"Point"}
}