{
  "type": "Feature",
  "properties": {
    "iso:country":"US",
    "sg:address":"105 E Chicago St",
    "sg:city":"Bronson",
    "sg:classifiers":[
        {
            "category":"Shopping",
            "subcategory":"Shoes",
            "type":"Retail Goods"
        }
    ],
    "sg:phone":"+1 517 369 6715",
    "sg:postcode":"49028",
    "sg:province":"MI",
    "sg:tags":[
        "apparel",
        "sport",
        "shoe",
        "store"
    ],
    "wof:name":"Jane-Dee Shoes",
    "wof:placetype":"venue"
},
  "geometry": {"coordinates":[-85.194001,41.872554],"type":"Point"}
}