{
  "type": "Feature",
  "properties": {
    "iso:country":"US",
    "sg:address":"35323 State Hwy 140",
    "sg:city":"Covert",
    "sg:classifiers":[
        {
            "category":"Education",
            "subcategory":"School",
            "type":"Public Place"
        }
    ],
    "sg:phone":"+1 269 764 3715",
    "sg:postcode":"49043",
    "sg:province":"MI",
    "wof:name":"Covert Child Care Ctr",
    "wof:placetype":"venue"
},
  "geometry": {"coordinates":[-86.262434,42.289222],"type":"Point"}
}