{
  "type": "Feature",
  "properties": {
    "iso:country":"US",
    "sg:address":"40 W Chicago St",
    "sg:city":"Coldwater",
    "sg:classifiers":[
        {
            "category":"Shopping",
            "subcategory":"Shoes",
            "type":"Retail Goods"
        }
    ],
    "sg:phone":"+1 517 278 8252",
    "sg:postcode":"49036",
    "sg:province":"MI",
    "sg:tags":[
        "shoe",
        "store"
    ],
    "wof:name":"Jim's Shoes & Boots",
    "wof:placetype":"venue"
},
  "geometry": {"coordinates":[-85.00366200000001,41.94118],"type":"Point"}
}