{
  "type": "Feature",
  "properties": {
    "iso:country":"US",
    "sg:address":"660 Woodward Ave",
    "sg:city":"Detroit",
    "sg:classifiers":[
        {
            "category":"Professional",
            "subcategory":"Lawyer & Legal Services",
            "type":"Services"
        }
    ],
    "sg:phone":"+1 313 256 8900",
    "sg:postcode":"48226",
    "sg:province":"MI",
    "sg:tags":[
        "firm",
        "law"
    ],
    "wof:name":"Dawson & Clark PC",
    "wof:placetype":"venue"
},
  "geometry": {"coordinates":[-83.045984,42.330677],"type":"Point"}
}