{
  "type": "Feature",
  "properties": {
    "iso:country":"US",
    "sg:address":"3801 Listerman Rd",
    "sg:city":"Howell",
    "sg:classifiers":[
        {
            "category":"Building & Trades",
            "subcategory":"Construction",
            "type":"Services"
        }
    ],
    "sg:phone":"+1 517 552 0101",
    "sg:postcode":"48855",
    "sg:province":"MI",
    "sg:tags":[
        "masonry",
        "contractor"
    ],
    "wof:name":"Filice Masonry Inc",
    "wof:placetype":"venue"
},
  "geometry": {"coordinates":[-83.86662099999999,42.652262],"type":"Point"}
}