{
  "type": "Feature",
  "properties": {
    "iso:country":"US",
    "sg:address":"5776 Schwegler Rd",
    "sg:city":"Cass City",
    "sg:phone":"+1 989 872 2334",
    "sg:postcode":"48726",
    "sg:province":"MI",
    "sg:tags":[
        "farm",
        "field",
        "crop"
    ],
    "wof:name":"Mark Stoeckle",
    "wof:placetype":"venue"
},
  "geometry": {"coordinates":[-83.155956,43.640412],"type":"Point"}
}