{
  "type": "Feature",
  "properties": {
    "iso:country":"US",
    "sg:address":"21711 W 10 Mile Rd",
    "sg:city":"Southfield",
    "sg:classifiers":[
        {
            "category":"Professional",
            "subcategory":"Lawyer & Legal Services",
            "type":"Services"
        }
    ],
    "sg:phone":"+1 248 223 9830",
    "sg:postcode":"48075",
    "sg:province":"MI",
    "wof:name":"Shallal Jane Atty",
    "wof:placetype":"venue"
},
  "geometry": {"coordinates":[-83.257797,42.4725],"type":"Point"}
}