{
  "type": "Feature",
  "properties": {
    "iso:country":"US",
    "sg:address":"22264 Novi Rd",
    "sg:city":"Novi",
    "sg:classifiers":[
        {
            "category":"Cinema",
            "subcategory":"Movie Rental",
            "type":"Entertainment"
        }
    ],
    "sg:phone":"+1 248 380 9880",
    "sg:postcode":"48375",
    "sg:province":"MI",
    "sg:tags":[
        "leasing",
        "video",
        "disc",
        "tape"
    ],
    "sg:website":"www.blockbuster.com",
    "wof:name":"Blockbuster Video",
    "wof:placetype":"venue"
},
  "geometry": {"coordinates":[-83.47380200000001,42.44809],"type":"Point"}
}