{
  "type": "Feature",
  "properties": {
    "iso:country":"US",
    "sg:address":"1819 Village Green Blvd",
    "sg:city":"Rochester",
    "sg:classifiers":[
        {
            "category":"Building & Trades",
            "subcategory":"Landscaping Services",
            "type":"Services"
        }
    ],
    "sg:phone":"+1 248 299 1936",
    "sg:postcode":"48307",
    "sg:province":"MI",
    "wof:name":"Pyra Development",
    "wof:placetype":"venue"
},
  "geometry": {"coordinates":[-83.09354,42.630211],"type":"Point"}
}