{
  "type": "Feature",
  "properties": {
    "iso:country":"US",
    "sg:address":"28467 Anchor Dr",
    "sg:city":"Chesterfield",
    "sg:classifiers":[
        {
            "category":"Retail",
            "subcategory":"Auto Repair",
            "type":"Services"
        }
    ],
    "sg:phone":"+1 586 949 9444",
    "sg:postcode":"48047",
    "sg:province":"MI",
    "sg:tags":[
        "body",
        "automobile",
        "painting"
    ],
    "wof:name":"Rick's Bump & Paint",
    "wof:placetype":"venue"
},
  "geometry": {"coordinates":[-82.823114,42.640649],"type":"Point"}
}