{
  "type": "Feature",
  "properties": {
    "iso:country":"US",
    "sg:address":"1401 E Saginaw St",
    "sg:city":"Lansing",
    "sg:classifiers":[
        {
            "category":"Professional",
            "subcategory":"Computer Services",
            "type":"Services"
        }
    ],
    "sg:phone":"+1 517 324 1143",
    "sg:postcode":"48906",
    "sg:province":"MI",
    "sg:tags":[
        "programing",
        "custom"
    ],
    "wof:name":"Flobase Inc",
    "wof:placetype":"venue"
},
  "geometry": {"coordinates":[-84.53077399999999,42.740885],"type":"Point"}
}