{
  "type": "Feature",
  "properties": {
    "iso:country":"US",
    "sg:address":"665 100th St SW",
    "sg:city":"Byron Center",
    "sg:classifiers":[
        {
            "category":"Wholesale",
            "subcategory":"Machinery & Supplies",
            "type":"Manufacturing & Wholesale Goods"
        }
    ],
    "sg:phone":"+1 616 878 5111",
    "sg:postcode":"49315",
    "sg:province":"MI",
    "sg:tags":[
        "dock",
        "loading",
        "equipment"
    ],
    "wof:name":"Truck Dock Svc Inc",
    "wof:placetype":"venue"
},
  "geometry": {"coordinates":[-85.679664,42.782763],"type":"Point"}
}