{
  "type": "Feature",
  "properties": {
    "iso:country":"US",
    "sg:address":"10200 Ford Rd",
    "sg:city":"Dearborn",
    "sg:classifiers":[
        {
            "category":"Shopping",
            "subcategory":"Stationery & Office Supplies",
            "type":"Retail Goods"
        }
    ],
    "sg:phone":"+1 313 624 9680",
    "sg:postcode":"48126",
    "sg:province":"MI",
    "sg:tags":[
        "equipment"
    ],
    "wof:name":"Working Environment",
    "wof:placetype":"venue"
},
  "geometry": {"coordinates":[-83.159103,42.330002],"type":"Point"}
}