{
  "type": "Feature",
  "properties": {
    "iso:country":"US",
    "sg:address":"132 W Wright Ave",
    "sg:city":"Shepherd",
    "sg:classifiers":[
        {
            "category":"Insurance",
            "subcategory":"Insurance Agent",
            "type":"Services"
        }
    ],
    "sg:phone":"+1 989 828 4441",
    "sg:postcode":"48883",
    "sg:province":"MI",
    "wof:name":"Zimmerman Insurance Inc",
    "wof:placetype":"venue"
},
  "geometry": {"coordinates":[-84.692262,43.524343],"type":"Point"}
}