{
  "type": "Feature",
  "properties": {
    "iso:country":"US",
    "sg:address":"18244 W McNichols Rd",
    "sg:city":"Detroit",
    "sg:classifiers":[
        {
            "category":"Real Estate",
            "subcategory":"Real Estate Agent",
            "type":"Services"
        }
    ],
    "sg:phone":"+1 313 541 9877",
    "sg:postcode":"48219",
    "sg:province":"MI",
    "wof:name":"Burley Real Estate Inc",
    "wof:placetype":"venue"
},
  "geometry": {"coordinates":[-83.22127399999999,42.41558],"type":"Point"}
}