{
  "type": "Feature",
  "properties": {
    "iso:country":"US",
    "sg:address":"1915 S Fenner Rd",
    "sg:city":"Caro",
    "sg:classifiers":[
        {
            "category":"Real Estate",
            "subcategory":"Real Estate Operator",
            "type":"Services"
        }
    ],
    "sg:phone":"+1 989 673 3503",
    "sg:postcode":"48723",
    "sg:province":"MI",
    "sg:tags":[
        "property",
        "lessor"
    ],
    "wof:name":"Kim Manke",
    "wof:placetype":"venue"
},
  "geometry": {"coordinates":[-83.50304300000001,43.454638],"type":"Point"}
}