{
  "type": "Feature",
  "properties": {
    "iso:country":"US",
    "sg:address":"318 N Lake St",
    "sg:city":"Ironwood",
    "sg:classifiers":[
        {
            "category":"Food & Beverages",
            "subcategory":"Groceries & Convenience Stores",
            "type":"Retail Goods"
        }
    ],
    "sg:phone":"+1 906 932 0900",
    "sg:postcode":"49938",
    "sg:province":"MI",
    "sg:tags":[
        "grocer"
    ],
    "wof:name":"Depot Antique Shop",
    "wof:placetype":"venue"
},
  "geometry": {"coordinates":[-90.156481,46.459664],"type":"Point"}
}