{
  "type": "Feature",
  "properties": {
    "iso:country":"US",
    "sg:address":"16143 Wyoming St",
    "sg:city":"Detroit",
    "sg:classifiers":[
        {
            "category":"Wholesale",
            "subcategory":"Stationery",
            "type":"Manufacturing & Wholesale Goods"
        }
    ],
    "sg:phone":"+1 313 345 8200",
    "sg:postcode":"48221",
    "sg:province":"MI",
    "sg:tags":[
        "card"
    ],
    "wof:name":"Odyssey Enterprises Inc",
    "wof:placetype":"venue"
},
  "geometry": {"coordinates":[-83.16019,42.410193],"type":"Point"}
}