{
  "type": "Feature",
  "properties": {
    "iso:country":"US",
    "sg:address":"1151 Bowes Rd",
    "sg:city":"Lowell",
    "sg:classifiers":[
        {
            "category":"Retail",
            "subcategory":"Veterinary Services",
            "type":"Services"
        }
    ],
    "sg:phone":"+1 616 897 4900",
    "sg:postcode":"49331",
    "sg:province":"MI",
    "sg:tags":[
        "veterinarian"
    ],
    "wof:name":"Grand River Veterinary Hosp",
    "wof:placetype":"venue"
},
  "geometry": {"coordinates":[-85.357406,42.929269],"type":"Point"}
}