{
  "type": "Feature",
  "properties": {
    "iso:country":"US",
    "sg:address":"1114 Baldwin St SE",
    "sg:city":"Grand Rapids",
    "sg:classifiers":[
        {
            "category":"Retail",
            "subcategory":"Portrait Studio",
            "type":"Services"
        }
    ],
    "sg:phone":"+1 616 262 1519",
    "sg:postcode":"49506",
    "sg:province":"MI",
    "sg:tags":[
        "photo"
    ],
    "wof:name":"In Focus Photography",
    "wof:placetype":"venue"
},
  "geometry": {"coordinates":[-85.641525,42.961795],"type":"Point"}
}