{
  "type": "Feature",
  "properties": {
    "iso:country":"US",
    "sg:address":"2385 Delhi Commerce Dr",
    "sg:city":"Holt",
    "sg:classifiers":[
        {
            "category":"Professional",
            "type":"Services"
        }
    ],
    "sg:phone":"+1 517 694 6074",
    "sg:postcode":"48842",
    "sg:province":"MI",
    "sg:tags":[
        "establishment"
    ],
    "wof:name":"Gaffey & Assoc",
    "wof:placetype":"venue"
},
  "geometry": {"coordinates":[-84.527754,42.652384],"type":"Point"}
}