{
  "type": "Feature",
  "properties": {
    "iso:country":"US",
    "sg:address":"5103 N Meadow Ln",
    "sg:city":"Mt Morris",
    "sg:classifiers":[
        {
            "category":"Organizations",
            "subcategory":"Religious Organization",
            "type":"Services"
        }
    ],
    "sg:phone":"+1 810 732 0282",
    "sg:postcode":"48458",
    "sg:province":"MI",
    "sg:tags":[
        "church"
    ],
    "sg:website":"www.flushingcommunity.org",
    "wof:name":"Flushing Community Church",
    "wof:placetype":"venue"
},
  "geometry": {"coordinates":[-83.76021799999999,43.107318],"type":"Point"}
}