{
  "type": "Feature",
  "properties": {
    "iso:country":"US",
    "sg:address":"5600 Crooks Rd Ste Ll7",
    "sg:city":"Troy",
    "sg:classifiers":[
        {
            "category":"Professional",
            "type":"Services"
        }
    ],
    "sg:phone":"+1 248 813 7800",
    "sg:postcode":"48098",
    "sg:province":"MI",
    "sg:tags":[
        "caterer"
    ],
    "wof:name":"Annabel's & Co",
    "wof:placetype":"venue"
},
  "geometry": {"coordinates":[-83.16871399999999,42.601155],"type":"Point"}
}