{
  "type": "Feature",
  "properties": {
    "iso:country":"US",
    "sg:address":"6532 Schaefer Rd",
    "sg:city":"Dearborn",
    "sg:classifiers":[
        {
            "category":"Bakery",
            "type":"Food & Drink"
        }
    ],
    "sg:phone":"+1 313 581 0022",
    "sg:postcode":"48126",
    "sg:province":"MI",
    "wof:name":"Ghandour Pastry",
    "wof:placetype":"venue"
},
  "geometry": {"coordinates":[-83.176498,42.338902],"type":"Point"}
}