{
  "type": "Feature",
  "properties": {
    "iso:country":"US",
    "sg:address":"3115 Orchard Vista Dr SE",
    "sg:city":"Grand Rapids",
    "sg:classifiers":[
        {
            "category":"Real Estate",
            "subcategory":"Real Estate Agent",
            "type":"Services"
        }
    ],
    "sg:phone":"+1 616 974 6536",
    "sg:postcode":"49546",
    "sg:province":"MI",
    "wof:name":"Barbara Rich Real Estate",
    "wof:placetype":"venue"
},
  "geometry": {"coordinates":[-85.52330000000001,42.907486],"type":"Point"}
}