{
  "type": "Feature",
  "properties": {
    "iso:country":"US",
    "sg:address":"1018 N State St",
    "sg:city":"Gladwin",
    "sg:classifiers":[
        {
            "category":"Manufacturing",
            "subcategory":"Tools & Machinery",
            "type":"Manufacturing & Wholesale Goods"
        }
    ],
    "sg:phone":"+1 989 426 4733",
    "sg:postcode":"48624",
    "sg:province":"MI",
    "sg:tags":[
        "furnace"
    ],
    "wof:name":"AAA Plumbing Heating & Air",
    "wof:placetype":"venue"
},
  "geometry": {"coordinates":[-84.485749,43.989157],"type":"Point"}
}