{
  "type": "Feature",
  "properties": {
    "iso:country":"US",
    "sg:address":"1354 W Princeton Ave",
    "sg:city":"Flint",
    "sg:classifiers":[
        {
            "category":"Building & Trades",
            "subcategory":"Equipment Rental",
            "type":"Services"
        }
    ],
    "sg:phone":"+1 810 789 7570",
    "sg:postcode":"48505",
    "sg:province":"MI",
    "wof:name":"Princeton Rentals",
    "wof:placetype":"venue"
},
  "geometry": {"coordinates":[-83.70823300000001,43.08582],"type":"Point"}
}