{
  "type": "Feature",
  "properties": {
    "iso:country":"US",
    "sg:address":"29937 Eastfield St",
    "sg:city":"Farmington Hills",
    "sg:classifiers":[
        {
            "category":"Building & Trades",
            "subcategory":"Plumbing",
            "type":"Services"
        }
    ],
    "sg:phone":"+1 248 719 3265",
    "sg:postcode":"48334",
    "sg:province":"MI",
    "sg:tags":[
        "mechanical",
        "contractor"
    ],
    "wof:name":"Medallion Heating & Cooling Co",
    "wof:placetype":"venue"
},
  "geometry": {"coordinates":[-83.35841600000001,42.518218],"type":"Point"}
}