{
  "type": "Feature",
  "properties": {
    "iso:country":"US",
    "sg:address":"7777 Timber Canyon Dr SE",
    "sg:city":"Ada",
    "sg:classifiers":[
        {
            "category":"Professional",
            "subcategory":"Art Services",
            "type":"Services"
        }
    ],
    "sg:phone":"+1 616 682 7777",
    "sg:postcode":"49301",
    "sg:province":"MI",
    "sg:tags":[
        "commercial",
        "design"
    ],
    "wof:name":"George Gaskey Design",
    "wof:placetype":"venue"
},
  "geometry": {"coordinates":[-85.480468,42.931745],"type":"Point"}
}