{
  "type": "Feature",
  "properties": {
    "iso:country":"US",
    "sg:address":"21521 Telegraph Rd",
    "sg:city":"Trenton",
    "sg:classifiers":[
        {
            "category":"Retail",
            "subcategory":"Repair Shop",
            "type":"Services"
        }
    ],
    "sg:phone":"+1 734 675 5733",
    "sg:postcode":"48174",
    "sg:province":"MI",
    "sg:tags":[
        "furniture"
    ],
    "wof:name":"Rob Hckeys Furn Strpping Refin",
    "wof:placetype":"venue"
},
  "geometry": {"coordinates":[-83.266147,42.148275],"type":"Point"}
}