{
  "type": "Feature",
  "properties": {
    "iso:country":"US",
    "sg:address":"6814 W Michigan Ave",
    "sg:city":"Jackson",
    "sg:classifiers":[
        {
            "category":"Retail",
            "subcategory":"Auto Repair",
            "type":"Services"
        }
    ],
    "sg:phone":"+1 517 750 2282",
    "sg:postcode":"49201",
    "sg:province":"MI",
    "sg:tags":[
        "repairing",
        "automobile",
        "general"
    ],
    "wof:name":"Sun Set Automotive",
    "wof:placetype":"venue"
},
  "geometry": {"coordinates":[-84.517122,42.252851],"type":"Point"}
}