{
  "type": "Feature",
  "properties": {
    "iso:country":"US",
    "sg:address":"907 Fowler St",
    "sg:city":"Howell",
    "sg:classifiers":[
        {
            "category":"Professional",
            "subcategory":"Engineering",
            "type":"Services"
        }
    ],
    "sg:phone":"+1 517 545 2712",
    "sg:postcode":"48843",
    "sg:province":"MI",
    "sg:tags":[
        "engineer"
    ],
    "wof:name":"May & Scofield",
    "wof:placetype":"venue"
},
  "geometry": {"coordinates":[-83.92643099999999,42.599508],"type":"Point"}
}