{
  "type": "Feature",
  "properties": {
    "iso:country":"US",
    "sg:address":"2690 Auburn Rd",
    "sg:city":"Shelby Twp",
    "sg:classifiers":[
        {
            "category":"Organizations",
            "subcategory":"Religious Organization",
            "type":"Services"
        }
    ],
    "sg:phone":"+1 586 731 5690",
    "sg:postcode":"48317",
    "sg:province":"MI",
    "sg:tags":[
        "church"
    ],
    "wof:name":"Mammoth Baptist Church",
    "wof:placetype":"venue"
},
  "geometry": {"coordinates":[-83.085431,42.638849],"type":"Point"}
}