{
  "type": "Feature",
  "properties": {
    "iso:country":"US",
    "sg:address":"21150 Mack Ave",
    "sg:city":"Grosse Pointe",
    "sg:classifiers":[
        {
            "category":"Bakery",
            "type":"Food & Drink"
        }
    ],
    "sg:phone":"+1 313 881 5710",
    "sg:postcode":"48236",
    "sg:province":"MI",
    "sg:website":"www.josefspastryshop.com/",
    "wof:name":"Josef's French Pastry Shop",
    "wof:placetype":"venue"
},
  "geometry": {"coordinates":[-82.905098,42.4491],"type":"Point"}
}