{
  "type": "Feature",
  "properties": {
    "iso:country":"US",
    "sg:address":"622 N College Rd",
    "sg:city":"Mason",
    "sg:classifiers":[
        {
            "category":"Real Estate",
            "subcategory":"Real Estate Agent",
            "type":"Services"
        }
    ],
    "sg:phone":"+1 517 676 4378",
    "sg:postcode":"48854",
    "sg:province":"MI",
    "sg:tags":[
        "inspection"
    ],
    "wof:name":"Quality Home Inspection",
    "wof:placetype":"venue"
},
  "geometry": {"coordinates":[-84.48344899999999,42.597446],"type":"Point"}
}