{
  "type": "Feature",
  "properties": {
    "iso:country":"US",
    "sg:address":"21 E Long Lake Rd",
    "sg:city":"Bloomfield Hills",
    "sg:classifiers":[
        {
            "category":"Professional",
            "subcategory":"Lawyer & Legal Services",
            "type":"Services"
        }
    ],
    "sg:phone":"+1 248 220 2209",
    "sg:postcode":"48304",
    "sg:province":"MI",
    "wof:name":"George Derrick ESQ",
    "wof:placetype":"venue"
},
  "geometry": {"coordinates":[-83.244615,42.584052],"type":"Point"}
}