{
  "type": "Feature",
  "properties": {
    "iso:country":"US",
    "sg:address":"753 Line St",
    "sg:city":"Boyne City",
    "sg:classifiers":[
        {
            "category":"Building & Trades",
            "subcategory":"Cleaning & Sanitation",
            "type":"Services"
        }
    ],
    "sg:phone":"+1 231 582 5640",
    "sg:postcode":"49712",
    "sg:province":"MI",
    "sg:tags":[
        "maintenance"
    ],
    "wof:name":"Harbor View Cleaning",
    "wof:placetype":"venue"
},
  "geometry": {"coordinates":[-85.01873399999999,45.224242],"type":"Point"}
}