{
  "type": "Feature",
  "properties": {
    "iso:country":"US",
    "sg:address":"9160 Eagle Rd",
    "sg:city":"Davisburg",
    "sg:classifiers":[
        {
            "category":"Professional",
            "subcategory":"Computer Services",
            "type":"Services"
        }
    ],
    "sg:phone":"+1 248 634 7574",
    "sg:postcode":"48350",
    "sg:province":"MI",
    "sg:tags":[
        "development",
        "training",
        "material"
    ],
    "sg:website":"www.tlcreations.com",
    "wof:name":"T L Creations",
    "wof:placetype":"venue"
},
  "geometry": {"coordinates":[-83.57660199999999,42.725821],"type":"Point"}
}