{
  "type": "Feature",
  "properties": {
    "iso:country":"US",
    "sg:address":"24610 Michigan Ave",
    "sg:city":"Dearborn",
    "sg:classifiers":[
        {
            "category":"Real Estate",
            "subcategory":"Real Estate Services",
            "type":"Services"
        },
        {
            "category":"Building & Trades",
            "subcategory":"Construction",
            "type":"Services"
        }
    ],
    "sg:phone":"+1 313 565 9850",
    "sg:postcode":"48124",
    "sg:province":"MI",
    "sg:tags":[
        "management",
        "property",
        "contractor"
    ],
    "wof:name":"Uznis John F Builder",
    "wof:placetype":"venue"
},
  "geometry": {"coordinates":[-83.277199,42.298901],"type":"Point"}
}