{
  "type": "Feature",
  "properties": {
    "iso:country":"US",
    "sg:address":"1522 Janes Ave",
    "sg:city":"Saginaw",
    "sg:classifiers":[
        {
            "category":"Social Services",
            "type":"Services"
        }
    ],
    "sg:phone":"+1 989 754 6111",
    "sg:postcode":"48601",
    "sg:province":"MI",
    "sg:tags":[
        "organization",
        "welfare"
    ],
    "wof:name":"WIC Program",
    "wof:placetype":"venue"
},
  "geometry": {"coordinates":[-83.923034,43.429103],"type":"Point"}
}