{
  "type": "Feature",
  "properties": {
    "iso:country":"US",
    "sg:address":"3166 Midvale Dr",
    "sg:city":"Rochester",
    "sg:classifiers":[
        {
            "category":"Building & Trades",
            "subcategory":"Construction",
            "type":"Services"
        }
    ],
    "sg:phone":"+1 248 852 1614",
    "sg:postcode":"48309",
    "sg:province":"MI",
    "sg:tags":[
        "concrete",
        "contractor"
    ],
    "wof:name":"Biundo Building Co",
    "wof:placetype":"venue"
},
  "geometry": {"coordinates":[-83.17695500000001,42.633374],"type":"Point"}
}