{
  "type": "Feature",
  "properties": {
    "iso:country":"US",
    "sg:address":"5651 Plymouth Rd",
    "sg:city":"Ann Arbor",
    "sg:classifiers":[
        {
            "category":"Professional",
            "subcategory":"Computer Services",
            "type":"Services"
        }
    ],
    "sg:phone":"+1 734 741 8700",
    "sg:postcode":"48105",
    "sg:province":"MI",
    "sg:tags":[
        "software",
        "developer"
    ],
    "wof:name":"Arbor Image",
    "wof:placetype":"venue"
},
  "geometry": {"coordinates":[-83.650262,42.313947],"type":"Point"}
}