{
  "type": "Feature",
  "properties": {
    "iso:country":"US",
    "sg:address":"651 Commerce Ln",
    "sg:city":"Kalamazoo",
    "sg:classifiers":[
        {
            "category":"Retail",
            "subcategory":"Auto Repair",
            "type":"Services"
        }
    ],
    "sg:phone":"+1 269 388 8396",
    "sg:postcode":"49004",
    "sg:province":"MI",
    "sg:tags":[
        "body",
        "automobile",
        "painting"
    ],
    "wof:name":"Parchment Collision Center",
    "wof:placetype":"venue"
},
  "geometry": {"coordinates":[-85.57231299999999,42.321374],"type":"Point"}
}