{
  "type": "Feature",
  "properties": {
    "iso:country":"US",
    "sg:address":"13750 Sycamore St",
    "sg:city":"Southgate",
    "sg:classifiers":[
        {
            "category":"Wholesale",
            "subcategory":"Machinery & Supplies",
            "type":"Manufacturing & Wholesale Goods"
        }
    ],
    "sg:phone":"+1 734 281 1460",
    "sg:postcode":"48195",
    "sg:province":"MI",
    "sg:tags":[
        "industrial"
    ],
    "wof:name":"Dave Buchanan Distribution",
    "wof:placetype":"venue"
},
  "geometry": {"coordinates":[-83.191991,42.200177],"type":"Point"}
}