{
  "type": "Feature",
  "properties": {
    "iso:country":"US",
    "sg:address":"32838 Warren Rd",
    "sg:city":"Westland",
    "sg:classifiers":[
        {
            "category":"Restaurant",
            "type":"Food & Drink"
        }
    ],
    "sg:menulink":"http://www.allmenus.com/mi/westland/235908-mancinos-pizzas-and-grinders/menu/",
    "sg:phone":"+1 734 421 1930",
    "sg:postcode":"48185",
    "sg:province":"MI",
    "sg:tags":[
        "wrap",
        "american",
        "sandwich",
        "pizza"
    ],
    "wof:name":"Mancinos Pizzas and Grinders",
    "wof:placetype":"venue"
},
  "geometry": {"coordinates":[-83.36575999999999,42.339331],"type":"Point"}
}