{
  "type": "Feature",
  "properties": {
    "iso:country":"US",
    "sg:address":"29550 5 Mile Rd",
    "sg:city":"Livonia",
    "sg:classifiers":[
        {
            "category":"Banks & Credit Unions",
            "subcategory":"Bank",
            "type":"Services"
        }
    ],
    "sg:phone":"+1 734 524 0786",
    "sg:postcode":"48154",
    "sg:province":"MI",
    "wof:name":"Co-Op Services",
    "wof:placetype":"venue"
},
  "geometry": {"coordinates":[-83.335999,42.398201],"type":"Point"}
}