{
  "type": "Feature",
  "properties": {
    "iso:country":"US",
    "sg:address":"6754 Tomer Rd",
    "sg:city":"Clayton",
    "sg:classifiers":[
        {
            "category":"Building & Trades",
            "subcategory":"Construction",
            "type":"Services"
        }
    ],
    "sg:phone":"+1 517 436 9232",
    "sg:postcode":"49235",
    "sg:province":"MI",
    "sg:tags":[
        "general",
        "contractor"
    ],
    "wof:name":"D P Roofing & Sheet Metal",
    "wof:placetype":"venue"
},
  "geometry": {"coordinates":[-84.144648,41.843859],"type":"Point"}
}