{
  "type": "Feature",
  "properties": {
    "iso:country":"US",
    "sg:address":"284 River St",
    "sg:city":"Manistee",
    "sg:classifiers":[
        {
            "category":"Restaurant",
            "type":"Food & Drink"
        }
    ],
    "sg:menulink":"http://www.allmenus.com/mi/manistee/141200-house-of-flavors/menu/",
    "sg:phone":"+1 231 398 9510",
    "sg:postcode":"49660",
    "sg:province":"MI",
    "sg:tags":[
        "american"
    ],
    "wof:name":"House Of Flavors",
    "wof:placetype":"venue"
},
  "geometry": {"coordinates":[-86.318091,44.249344],"type":"Point"}
}