{
  "type": "Feature",
  "properties": {
    "iso:country":"US",
    "sg:address":"6100 Oakman Blvd",
    "sg:city":"Dearborn",
    "sg:classifiers":[
        {
            "category":"Building & Trades",
            "subcategory":"Construction",
            "type":"Services"
        }
    ],
    "sg:phone":"+1 313 582 3631",
    "sg:postcode":"48126",
    "sg:province":"MI",
    "sg:tags":[
        "floor",
        "laying",
        "contractor"
    ],
    "wof:name":"Deluxe Carpet Installation",
    "wof:placetype":"venue"
},
  "geometry": {"coordinates":[-83.168954,42.334169],"type":"Point"}
}