{
  "type": "Feature",
  "properties": {
    "iso:country":"US",
    "sg:address":"1516 S Getty St",
    "sg:city":"Muskegon",
    "sg:classifiers":[
        {
            "category":"Retail",
            "subcategory":"Auto Repair",
            "type":"Services"
        }
    ],
    "sg:phone":"+1 231 767 1878",
    "sg:postcode":"49442",
    "sg:province":"MI",
    "sg:tags":[
        "repairing",
        "tire"
    ],
    "wof:name":"Jalisco Tires & Auto Repair",
    "wof:placetype":"venue"
},
  "geometry": {"coordinates":[-86.224294,43.224118],"type":"Point"}
}