{
  "type": "Feature",
  "properties": {
    "iso:country":"US",
    "sg:address":"4633 John R St",
    "sg:city":"Detroit",
    "sg:classifiers":[
        {
            "category":"Personal",
            "subcategory":"Barber",
            "type":"Services"
        }
    ],
    "sg:phone":"+1 313 832 8112",
    "sg:postcode":"48201",
    "sg:province":"MI",
    "sg:tags":[
        "shop"
    ],
    "wof:name":"Palmers Barber Shop",
    "wof:placetype":"venue"
},
  "geometry": {"coordinates":[-83.06067,42.355307],"type":"Point"}
}