{
  "type": "Feature",
  "properties": {
    "iso:country":"US",
    "sg:address":"1111 Fenway Cir",
    "sg:city":"Fenton",
    "sg:classifiers":[
        {
            "category":"Manufacturing",
            "subcategory":"Tools & Machinery",
            "type":"Manufacturing & Wholesale Goods"
        }
    ],
    "sg:phone":"+1 810 629 9885",
    "sg:postcode":"48430",
    "sg:province":"MI",
    "sg:tags":[
        "machine"
    ],
    "sg:website":"www.harroun.com",
    "wof:name":"Harroun Enterprises",
    "wof:placetype":"venue"
},
  "geometry": {"coordinates":[-83.727886,42.797898],"type":"Point"}
}