{
  "type": "Feature",
  "properties": {
    "iso:country":"US",
    "sg:address":"20665 Telegraph Rd",
    "sg:city":"Trenton",
    "sg:classifiers":[
        {
            "category":"Real Estate",
            "subcategory":"Real Estate Operator",
            "type":"Services"
        }
    ],
    "sg:phone":"+1 734 479 2479",
    "sg:postcode":"48183",
    "sg:province":"MI",
    "sg:tags":[
        "mobile",
        "home",
        "site"
    ],
    "wof:name":"Lloyds Mobile Home Park",
    "wof:placetype":"venue"
},
  "geometry": {"coordinates":[-83.266362,42.15256],"type":"Point"}
}