{
  "type": "Feature",
  "properties": {
    "iso:country":"US",
    "sg:address":"386 Ringle St",
    "sg:city":"Hurley",
    "sg:classifiers":[
        {
            "category":"Shopping",
            "subcategory":"Used Merchandise",
            "type":"Retail Goods"
        }
    ],
    "sg:phone":"+1 715 561 3670",
    "sg:postcode":"54534",
    "sg:province":"WI",
    "sg:tags":[
        "antique"
    ],
    "wof:name":"Two Tinkers",
    "wof:placetype":"venue"
},
  "geometry": {"coordinates":[-90.20532300000001,46.440235],"type":"Point"}
}