{
  "type": "Feature",
  "properties": {
    "iso:country":"US",
    "sg:address":"3520 Keewahdin Rd",
    "sg:city":"Fort Gratiot",
    "sg:classifiers":[
        {
            "category":"Building & Trades",
            "subcategory":"Construction",
            "type":"Services"
        }
    ],
    "sg:phone":"+1 810 385 8721",
    "sg:postcode":"48059",
    "sg:province":"MI",
    "sg:tags":[
        "roofing",
        "contractor"
    ],
    "wof:name":"Abco Roofing",
    "wof:placetype":"venue"
},
  "geometry": {"coordinates":[-82.477075,43.039023],"type":"Point"}
}