{
  "type": "Feature",
  "properties": {
    "iso:country":"US",
    "sg:address":"1070 Jackson Xing",
    "sg:city":"Jackson",
    "sg:classifiers":[
        {
            "category":"Personal",
            "type":"Services"
        }
    ],
    "sg:phone":"+1 517 780 0045",
    "sg:postcode":"49202",
    "sg:province":"MI",
    "sg:tags":[
        "wear",
        "formal"
    ],
    "wof:name":"After Hours Formalwear",
    "wof:placetype":"venue"
},
  "geometry": {"coordinates":[-84.43343,42.26932],"type":"Point"}
}