{
  "type": "Feature",
  "properties": {
    "iso:country":"US",
    "sg:address":"328 W Main St",
    "sg:city":"Brighton",
    "sg:classifiers":[
        {
            "category":"Shopping",
            "subcategory":"Clothing, Apparel, & Fashions",
            "type":"Retail Goods"
        }
    ],
    "sg:phone":"+1 810 227 7107",
    "sg:postcode":"48116",
    "sg:province":"MI",
    "sg:website":"www.margrethunters.com",
    "wof:name":"Margret Hunters Clothing",
    "wof:placetype":"venue"
},
  "geometry": {"coordinates":[-83.78340799999999,42.529569],"type":"Point"}
}