{
  "type": "Feature",
  "properties": {
    "iso:country":"US",
    "sg:address":"15885 Goddard Rd",
    "sg:city":"Southgate",
    "sg:classifiers":[
        {
            "category":"Wholesale",
            "subcategory":"Electrical",
            "type":"Manufacturing & Wholesale Goods"
        }
    ],
    "sg:phone":"+1 734 287 4526",
    "sg:postcode":"48195",
    "sg:province":"MI",
    "sg:tags":[
        "equipment"
    ],
    "wof:name":"Low Voltage Building Tech",
    "wof:placetype":"venue"
},
  "geometry": {"coordinates":[-83.219548,42.227773],"type":"Point"}
}