{
  "type": "Feature",
  "properties": {
    "iso:country":"US",
    "sg:address":"20480 Beaconsfield St",
    "sg:city":"Harper Woods",
    "sg:classifiers":[
        {
            "category":"Organizations",
            "subcategory":"Religious Organization",
            "type":"Services"
        }
    ],
    "sg:phone":"+1 313 417 3916",
    "sg:postcode":"48225",
    "sg:province":"MI",
    "wof:name":"Blessed Hope Ministries Cogic",
    "wof:placetype":"venue"
},
  "geometry": {"coordinates":[-82.93002300000001,42.447144],"type":"Point"}
}