{
  "type": "Feature",
  "properties": {
    "iso:country":"US",
    "sg:address":"12131 Pine Row Ln",
    "sg:city":"Grand Blanc",
    "sg:classifiers":[
        {
            "category":"Museum",
            "type":"Entertainment"
        }
    ],
    "sg:phone":"+1 810 694 3084",
    "sg:postcode":"48439",
    "sg:province":"MI",
    "sg:tags":[
        "gallery"
    ],
    "wof:name":"Village Art",
    "wof:placetype":"venue"
},
  "geometry": {"coordinates":[-83.598752,42.921256],"type":"Point"}
}