{
  "type": "Feature",
  "properties": {
    "iso:country":"US",
    "sg:address":"26417 Plymouth Rd",
    "sg:city":"Redford",
    "sg:classifiers":[
        {
            "category":"Food & Beverages",
            "subcategory":"Bakery",
            "type":"Retail Goods"
        }
    ],
    "sg:phone":"+1 313 937 2288",
    "sg:postcode":"48239",
    "sg:province":"MI",
    "wof:name":"Italian American Artistic",
    "wof:placetype":"venue"
},
  "geometry": {"coordinates":[-83.303162,42.370394],"type":"Point"}
}