{
  "type": "Feature",
  "properties": {
    "iso:country":"US",
    "sg:address":"650 Burton St SE",
    "sg:city":"Grand Rapids",
    "sg:classifiers":[
        {
            "category":"Sports & Exercise",
            "subcategory":"Gym",
            "type":"Entertainment"
        }
    ],
    "sg:phone":"+1 616 245 8510",
    "sg:postcode":"49507",
    "sg:province":"MI",
    "sg:tags":[
        "gymnasium"
    ],
    "wof:name":"St Joseph Seminary Gymnsm",
    "wof:placetype":"venue"
},
  "geometry": {"coordinates":[-85.650859,42.927276],"type":"Point"}
}