{
  "type": "Feature",
  "properties": {
    "iso:country":"US",
    "sg:address":"976 Barney Ave",
    "sg:city":"Flint",
    "sg:classifiers":[
        {
            "category":"Building & Trades",
            "subcategory":"Landscaping Services",
            "type":"Services"
        }
    ],
    "sg:phone":"+1 810 629 8252",
    "sg:postcode":"48503",
    "sg:province":"MI",
    "sg:tags":[
        "tree"
    ],
    "wof:name":"Fenton Tree Svc",
    "wof:placetype":"venue"
},
  "geometry": {"coordinates":[-83.73133900000001,43.00464],"type":"Point"}
}