{
  "type": "Feature",
  "properties": {
    "iso:country":"US",
    "sg:address":"101 Court St",
    "sg:city":"Munising",
    "sg:classifiers":[
        {
            "category":"Government",
            "subcategory":"Court House",
            "type":"Public Place"
        }
    ],
    "sg:phone":"+1 906 387 4636",
    "sg:postcode":"49862",
    "sg:province":"MI",
    "sg:tags":[
        "county"
    ],
    "wof:name":"Alger Friend Of The Court",
    "wof:placetype":"venue"
},
  "geometry": {"coordinates":[-86.65837999999999,46.408311],"type":"Point"}
}