{
  "type": "Feature",
  "properties": {
    "iso:country":"US",
    "sg:address":"43550 N Groesbeck Hwy",
    "sg:city":"Clinton Township",
    "sg:classifiers":[
        {
            "category":"Retail",
            "subcategory":"Auto Repair",
            "type":"Services"
        }
    ],
    "sg:phone":"+1 586 468 1618",
    "sg:postcode":"48036",
    "sg:province":"MI",
    "wof:name":"Buck's Garage",
    "wof:placetype":"venue"
},
  "geometry": {"coordinates":[-82.88629899999999,42.615898],"type":"Point"}
}