{
  "type": "Feature",
  "properties": {
    "iso:country":"US",
    "sg:address":"9200 Dwight St",
    "sg:city":"Detroit",
    "sg:classifiers":[
        {
            "category":"Education",
            "subcategory":"Library",
            "type":"Public Place"
        }
    ],
    "sg:phone":"+1 313 822 4412",
    "sg:postcode":"48214",
    "sg:province":"MI",
    "wof:name":"Antique Enterprises Inc",
    "wof:placetype":"venue"
},
  "geometry": {"coordinates":[-82.98180499999999,42.354205],"type":"Point"}
}