{
  "type": "Feature",
  "properties": {
    "iso:country":"US",
    "sg:address":"2187 Orchard Lake Rd",
    "sg:city":"Keego Harbor",
    "sg:classifiers":[
        {
            "category":"Insurance",
            "subcategory":"Insurance Agent",
            "type":"Services"
        }
    ],
    "sg:phone":"+1 248 253 1140",
    "sg:postcode":"48320",
    "sg:province":"MI",
    "sg:tags":[
        "security"
    ],
    "wof:name":"Robert H Lyons & Associates",
    "wof:placetype":"venue"
},
  "geometry": {"coordinates":[-83.327935,42.611712],"type":"Point"}
}