{
  "type": "Feature",
  "properties": {
    "iso:country":"US",
    "sg:address":"2441 Townline Rd",
    "sg:city":"Tawas City",
    "sg:classifiers":[
        {
            "category":"Building & Trades",
            "subcategory":"Construction",
            "type":"Services"
        }
    ],
    "sg:phone":"+1 989 362 2565",
    "sg:postcode":"48763",
    "sg:province":"MI",
    "sg:tags":[
        "house"
    ],
    "wof:name":"David Kendall Builder",
    "wof:placetype":"venue"
},
  "geometry": {"coordinates":[-83.621049,44.249815],"type":"Point"}
}