{
  "type": "Feature",
  "properties": {
    "iso:country":"US",
    "sg:address":"200 S Main St",
    "sg:city":"Northville",
    "sg:classifiers":[
        {
            "category":"Manufacturing",
            "subcategory":"Apparel",
            "type":"Manufacturing & Wholesale Goods"
        }
    ],
    "sg:phone":"+1 248 347 8822",
    "sg:postcode":"48167",
    "sg:province":"MI",
    "sg:tags":[
        "tax",
        "embroidery",
        "income"
    ],
    "wof:name":"Mach II Tax Service",
    "wof:placetype":"venue"
},
  "geometry": {"coordinates":[-83.475583,42.429658],"type":"Point"}
}