{
  "type": "Feature",
  "properties": {
    "iso:country":"US",
    "sg:address":"1122 W Michigan Ave",
    "sg:city":"Marshall",
    "sg:classifiers":[
        {
            "category":"Retail",
            "subcategory":"Auto Repair",
            "type":"Services"
        }
    ],
    "sg:phone":"+1 269 789 0454",
    "sg:postcode":"49068",
    "sg:province":"MI",
    "wof:name":"Spencers Fast Lane Inc",
    "wof:placetype":"venue"
},
  "geometry": {"coordinates":[-84.977205,42.272043],"type":"Point"}
}