{
  "type": "Feature",
  "properties": {
    "iso:country":"US",
    "sg:address":"1105 N. Vernon",
    "sg:city":"Dearborn",
    "sg:classifiers":[
        {
            "category":"Personal",
            "subcategory":"Beauty Salon",
            "type":"Services"
        }
    ],
    "sg:phone":"+1 313 444 0096",
    "sg:postcode":"48128",
    "sg:province":"MI",
    "sg:tags":[
        "spa"
    ],
    "sg:website":"myliquidsunsalon.com",
    "wof:name":"My Liquid Sun Salon",
    "wof:placetype":"venue"
},
  "geometry": {"coordinates":[-83.27576500000001,42.319733],"type":"Point"}
}