{
  "type": "Feature",
  "properties": {
    "iso:country":"US",
    "sg:address":"15354 Chapel St",
    "sg:city":"Detroit",
    "sg:classifiers":[
        {
            "category":"Social Services",
            "subcategory":"Child Care",
            "type":"Services"
        }
    ],
    "sg:phone":"+1 313 255 8839",
    "sg:postcode":"48223",
    "sg:province":"MI",
    "sg:tags":[
        "day"
    ],
    "wof:name":"Full of Joy Childcare",
    "wof:placetype":"venue"
},
  "geometry": {"coordinates":[-83.253033,42.401453],"type":"Point"}
}