{
  "type": "Feature",
  "properties": {
    "iso:country":"US",
    "sg:address":"348 S Cedar St",
    "sg:city":"Kalkaska",
    "sg:classifiers":[
        {
            "category":"Banks & Credit Unions",
            "subcategory":"Bank",
            "type":"Services"
        }
    ],
    "sg:phone":"+1 231 258 0300",
    "sg:postcode":"49646",
    "sg:province":"MI",
    "sg:tags":[
        "cashing",
        "check"
    ],
    "wof:name":"Instant Cash Advance",
    "wof:placetype":"venue"
},
  "geometry": {"coordinates":[-85.177846,44.731278],"type":"Point"}
}