{
  "type": "Feature",
  "properties": {
    "iso:country":"US",
    "sg:address":"950 S Clinton St",
    "sg:city":"Stockbridge",
    "sg:classifiers":[
        {
            "category":"Organizations",
            "subcategory":"Religious Organization",
            "type":"Services"
        }
    ],
    "sg:phone":"+1 517 851 7075",
    "sg:postcode":"49285",
    "sg:province":"MI",
    "sg:tags":[
        "church"
    ],
    "sg:website":"www.1stbcs.org",
    "wof:name":"First Baptist Church",
    "wof:placetype":"venue"
},
  "geometry": {"coordinates":[-84.18013500000001,42.441321],"type":"Point"}
}