{
  "type": "Feature",
  "properties": {
    "iso:country":"US",
    "sg:address":"2950 Rochester Rd",
    "sg:city":"Troy",
    "sg:classifiers":[
        {
            "category":"Restaurant",
            "type":"Food & Drink"
        }
    ],
    "sg:phone":"+1 248 689 8194",
    "sg:postcode":"48083",
    "sg:province":"MI",
    "wof:name":"Wagon Wheel Saloon",
    "wof:placetype":"venue"
},
  "geometry": {"coordinates":[-83.128699,42.562861],"type":"Point"}
}