{
  "type": "Feature",
  "properties": {
    "iso:country":"US",
    "sg:address":"3751 Varsity Dr",
    "sg:city":"Ann Arbor",
    "sg:classifiers":[
        {
            "category":"Health Services",
            "subcategory":"Health Practitioner",
            "type":"Services"
        }
    ],
    "sg:phone":"+1 734 677 4345",
    "sg:postcode":"48108",
    "sg:province":"MI",
    "sg:tags":[
        "occupational",
        "therapist",
        "speech",
        "physical"
    ],
    "wof:name":"Ann Arbor Physical Therapy Ser",
    "wof:placetype":"venue"
},
  "geometry": {"coordinates":[-83.72583400000001,42.231221],"type":"Point"}
}