{
  "type": "Feature",
  "properties": {
    "iso:country":"US",
    "sg:address":"221 S Broadway St",
    "sg:city":"Hastings",
    "sg:classifiers":[
        {
            "category":"Professional",
            "subcategory":"Lawyer & Legal Services",
            "type":"Services"
        }
    ],
    "sg:phone":"+1 269 945 9596",
    "sg:postcode":"49058",
    "sg:province":"MI",
    "wof:name":"William M Doherty",
    "wof:placetype":"venue"
},
  "geometry": {"coordinates":[-85.290559,42.647596],"type":"Point"}
}