{
  "type": "Feature",
  "properties": {
    "iso:country":"US",
    "sg:address":"49 Monroe Center St NW",
    "sg:city":"Grand Rapids",
    "sg:classifiers":[
        {
            "category":"Real Estate",
            "subcategory":"Developer",
            "type":"Services"
        }
    ],
    "sg:phone":"+1 616 458 0597",
    "sg:postcode":"49503",
    "sg:province":"MI",
    "wof:name":"Wesley & Assoc",
    "wof:placetype":"venue"
},
  "geometry": {"coordinates":[-85.668627,42.963838],"type":"Point"}
}