{
  "type": "Feature",
  "properties": {
    "iso:country":"US",
    "sg:address":"570 Chandler St",
    "sg:city":"Detroit",
    "sg:classifiers":[
        {
            "category":"Arts & Performance",
            "subcategory":"Theater",
            "type":"Entertainment"
        }
    ],
    "sg:phone":"+1 313 872 3437",
    "sg:postcode":"48202",
    "sg:province":"MI",
    "sg:tags":[
        "group"
    ],
    "wof:name":"Hugh Burrell Prods",
    "wof:placetype":"venue"
},
  "geometry": {"coordinates":[-83.067757,42.376865],"type":"Point"}
}