{
  "type": "Feature",
  "properties": {
    "iso:country":"US",
    "sg:address":"1553 Brookview Dr",
    "sg:city":"Canton",
    "sg:classifiers":[
        {
            "category":"Building & Trades",
            "subcategory":"Locksmith",
            "type":"Services"
        }
    ],
    "sg:phone":"+1 734 629 1060",
    "sg:postcode":"48188",
    "sg:province":"MI",
    "sg:tags":[
        "key"
    ],
    "wof:name":"24 7",
    "wof:placetype":"venue"
},
  "geometry": {"coordinates":[-83.455568,42.296033],"type":"Point"}
}