{
  "type": "Feature",
  "properties": {
    "iso:country":"US",
    "sg:address":"3417 Elizabeth Lake Rd",
    "sg:city":"Waterford",
    "sg:classifiers":[
        {
            "category":"Restaurant",
            "type":"Food & Drink"
        }
    ],
    "sg:menulink":"http://www.allmenus.com/mi/waterford/24564-tubbys-grilled-submarines/menu/",
    "sg:phone":"+1 248 682 0413",
    "sg:postcode":"48328",
    "sg:province":"MI",
    "sg:tags":[
        "wrap",
        "american",
        "sandwich"
    ],
    "wof:name":"Tubby's Grilled Submarines",
    "wof:placetype":"venue"
},
  "geometry": {"coordinates":[-83.352339,42.639375],"type":"Point"}
}