{
  "type": "Feature",
  "properties": {
    "iso:country":"US",
    "sg:address":"374 N Gratiot Ave",
    "sg:city":"Clinton Township",
    "sg:classifiers":[
        {
            "category":"Retail",
            "subcategory":"Auto Repair",
            "type":"Services"
        }
    ],
    "sg:phone":"+1 586 463 7733",
    "sg:postcode":"48036",
    "sg:province":"MI",
    "sg:website":"www.northgratiotautoelectric.com",
    "wof:name":"North Gratiot Auto Electric",
    "wof:placetype":"venue"
},
  "geometry": {"coordinates":[-82.87069700000001,42.6106],"type":"Point"}
}