{
  "type": "Feature",
  "properties": {
    "iso:country":"US",
    "sg:address":"5898 Sylvan Ln",
    "sg:city":"Interlochen",
    "sg:classifiers":[
        {
            "category":"Organizations",
            "subcategory":"Membership Organization",
            "type":"Services"
        }
    ],
    "sg:phone":"+1 231 276 9631",
    "sg:postcode":"49643",
    "sg:province":"MI",
    "wof:name":"Hardwick Family Foundation",
    "wof:placetype":"venue"
},
  "geometry": {"coordinates":[-85.772445,44.603639],"type":"Point"}
}