{
  "type": "Feature",
  "properties": {
    "iso:country":"US",
    "sg:address":"9207 Andersonville Rd",
    "sg:city":"Clarkston",
    "sg:classifiers":[
        {
            "category":"Professional",
            "subcategory":"Computer Services",
            "type":"Services"
        }
    ],
    "sg:phone":"+1 248 620 2201",
    "sg:postcode":"48346",
    "sg:province":"MI",
    "sg:tags":[
        "consultant",
        "repair"
    ],
    "sg:website":"www.maureenfinch.com",
    "wof:name":"P C Miracles Inc",
    "wof:placetype":"venue"
},
  "geometry": {"coordinates":[-83.471242,42.709956],"type":"Point"}
}