{
  "type": "Feature",
  "properties": {
    "iso:country":"US",
    "sg:address":"115 N Cottage St",
    "sg:city":"Potterville",
    "sg:classifiers":[
        {
            "category":"Professional",
            "type":"Services"
        }
    ],
    "sg:phone":"+1 517 645 2015",
    "sg:postcode":"48876",
    "sg:province":"MI",
    "wof:name":"BBC Services Inc",
    "wof:placetype":"venue"
},
  "geometry": {"coordinates":[-84.74016399999999,42.625662],"type":"Point"}
}