{
  "type": "Feature",
  "properties": {
    "iso:country":"US",
    "sg:address":"1002 W Main St SE",
    "sg:city":"Lowell",
    "sg:classifiers":[
        {
            "category":"Personal",
            "subcategory":"Beauty Salon",
            "type":"Services"
        }
    ],
    "sg:phone":"+1 616 897 7131",
    "sg:postcode":"49331",
    "sg:province":"MI",
    "sg:tags":[
        "shop"
    ],
    "wof:name":"Brenda's Hair Design",
    "wof:placetype":"venue"
},
  "geometry": {"coordinates":[-85.35061,42.931683],"type":"Point"}
}