{
  "type": "Feature",
  "properties": {
    "iso:country":"US",
    "sg:address":"530 Edwin Ave",
    "sg:city":"Kalamazoo",
    "sg:classifiers":[
        {
            "category":"Arts & Performance",
            "subcategory":"Theater",
            "type":"Entertainment"
        }
    ],
    "sg:phone":"+1 269 388 2084",
    "sg:postcode":"49048",
    "sg:province":"MI",
    "sg:tags":[
        "group"
    ],
    "wof:name":"Murder For Hire",
    "wof:placetype":"venue"
},
  "geometry": {"coordinates":[-85.55852899999999,42.29825],"type":"Point"}
}