{
  "type": "Feature",
  "properties": {
    "iso:country":"US",
    "sg:address":"4747 W River Dr NE",
    "sg:city":"Comstock Park",
    "sg:classifiers":[
        {
            "category":"Real Estate",
            "subcategory":"Real Estate Operator",
            "type":"Services"
        }
    ],
    "sg:phone":"+1 616 784 6749",
    "sg:postcode":"49321",
    "sg:province":"MI",
    "sg:tags":[
        "mobile",
        "home",
        "site",
        "community"
    ],
    "wof:name":"Brook Haven Mobile Home Park",
    "wof:placetype":"venue"
},
  "geometry": {"coordinates":[-85.653564,43.050315],"type":"Point"}
}