{
  "type": "Feature",
  "properties": {
    "iso:country":"US",
    "sg:address":"275 Central Ave",
    "sg:city":"Pontiac",
    "sg:classifiers":[
        {
            "category":"Building & Trades",
            "subcategory":"Landscaping Services",
            "type":"Services"
        }
    ],
    "sg:phone":"+1 248 481 2160",
    "sg:postcode":"48341",
    "sg:province":"MI",
    "wof:name":"Maywa Green Thumb Landscaping",
    "wof:placetype":"venue"
},
  "geometry": {"coordinates":[-83.27544899999999,42.62161],"type":"Point"}
}