{
  "type": "Feature",
  "properties": {
    "iso:country":"US",
    "sg:address":"1445 Sheldon Rd",
    "sg:city":"Grand Haven",
    "sg:classifiers":[
        {
            "category":"Health Services",
            "subcategory":"Hospital",
            "type":"Services"
        }
    ],
    "sg:phone":"+1 616 847 5145",
    "sg:postcode":"49417",
    "sg:province":"MI",
    "sg:tags":[
        "mental"
    ],
    "wof:name":"Pine Rest Christian Mental",
    "wof:placetype":"venue"
},
  "geometry": {"coordinates":[-86.227966,43.050323],"type":"Point"}
}