{
  "type": "Feature",
  "properties": {
    "iso:country":"US",
    "sg:address":"6265 Artesian St",
    "sg:city":"Detroit",
    "sg:classifiers":[
        {
            "category":"Personal",
            "type":"Services"
        }
    ],
    "sg:phone":"+1 313 492 8177",
    "sg:postcode":"48228",
    "sg:province":"MI",
    "sg:tags":[
        "consultation",
        "wedding"
    ],
    "wof:name":"Ads Wedding Elegance",
    "wof:placetype":"venue"
},
  "geometry": {"coordinates":[-83.22548500000001,42.335935],"type":"Point"}
}