{
  "type": "Feature",
  "properties": {
    "iso:country":"US",
    "sg:address":"11890 45th St",
    "sg:city":"Bloomingdale",
    "sg:classifiers":[
        {
            "category":"Building & Trades",
            "subcategory":"Construction",
            "type":"Services"
        }
    ],
    "sg:phone":"+1 269 344 3049",
    "sg:postcode":"49026",
    "sg:province":"MI",
    "sg:tags":[
        "house"
    ],
    "wof:name":"Versluis John",
    "wof:placetype":"venue"
},
  "geometry": {"coordinates":[-85.986513,42.375926],"type":"Point"}
}