{
  "type": "Feature",
  "properties": {
    "iso:country":"US",
    "sg:address":"11250 Buckhorn Lake Rd",
    "sg:city":"Holly",
    "sg:classifiers":[
        {
            "category":"Building & Trades",
            "subcategory":"Construction",
            "type":"Services"
        }
    ],
    "sg:phone":"+1 248 417 0025",
    "sg:postcode":"48442",
    "sg:province":"MI",
    "sg:tags":[
        "concrete",
        "contractor"
    ],
    "wof:name":"Holly Poured Walls Inc",
    "wof:placetype":"venue"
},
  "geometry": {"coordinates":[-83.631747,42.75646],"type":"Point"}
}