{
  "type": "Feature",
  "properties": {
    "iso:country":"US",
    "sg:address":"49354 Carles Dr",
    "sg:city":"Macomb",
    "sg:classifiers":[
        {
            "category":"Shopping",
            "type":"Retail Goods"
        }
    ],
    "sg:phone":"+1 586 226 2005",
    "sg:postcode":"48044",
    "sg:province":"MI",
    "sg:tags":[
        "merchandise",
        "contract"
    ],
    "wof:name":"Reminder Co",
    "wof:placetype":"venue"
},
  "geometry": {"coordinates":[-82.940422,42.659085],"type":"Point"}
}