{
  "type": "Feature",
  "properties": {
    "iso:country":"US",
    "sg:address":"648 Monroe Ave NW",
    "sg:city":"Grand Rapids",
    "sg:classifiers":[
        {
            "category":"Building & Trades",
            "subcategory":"Construction",
            "type":"Services"
        }
    ],
    "sg:phone":"+1 616 235 9471",
    "sg:postcode":"49503",
    "sg:province":"MI",
    "sg:tags":[
        "contractor"
    ],
    "wof:name":"Brass Works Building",
    "wof:placetype":"venue"
},
  "geometry": {"coordinates":[-85.672347,42.974335],"type":"Point"}
}