{
  "type": "Feature",
  "properties": {
    "iso:country":"US",
    "sg:address":"1954 College Ave",
    "sg:city":"Lincoln Park",
    "sg:classifiers":[
        {
            "category":"Building & Trades",
            "subcategory":"Locksmith",
            "type":"Services"
        }
    ],
    "sg:phone":"+1 313 388 5522",
    "sg:postcode":"48146",
    "sg:province":"MI",
    "sg:tags":[
        "key"
    ],
    "wof:name":"Able 24 Hour Locksmith",
    "wof:placetype":"venue"
},
  "geometry": {"coordinates":[-83.184555,42.264563],"type":"Point"}
}