{
  "type": "Feature",
  "properties": {
    "iso:country":"US",
    "sg:address":"118 N Saginaw St",
    "sg:city":"Durand",
    "sg:classifiers":[
        {
            "category":"Shopping",
            "subcategory":"Discount & Variety Stores",
            "type":"Retail Goods"
        }
    ],
    "sg:phone":"+1 989 288 6919",
    "sg:postcode":"48429",
    "sg:province":"MI",
    "wof:name":"Fairway Discount",
    "wof:placetype":"venue"
},
  "geometry": {"coordinates":[-83.98451900000001,42.911033],"type":"Point"}
}