{
  "type": "Feature",
  "properties": {
    "iso:country":"US",
    "sg:address":"1838 Ruddiman Dr",
    "sg:city":"Muskegon",
    "sg:classifiers":[
        {
            "category":"Real Estate",
            "subcategory":"Developer",
            "type":"Services"
        }
    ],
    "sg:phone":"+1 231 744 2399",
    "sg:postcode":"49445",
    "sg:province":"MI",
    "wof:name":"Tridonn Development Co",
    "wof:placetype":"venue"
},
  "geometry": {"coordinates":[-86.26138400000001,43.261042],"type":"Point"}
}