{
  "type": "Feature",
  "properties": {
    "iso:country":"US",
    "sg:address":"1409 Springville Hwy",
    "sg:city":"Adrian",
    "sg:classifiers":[
        {
            "category":"Building & Trades",
            "subcategory":"Construction",
            "type":"Services"
        }
    ],
    "sg:phone":"+1 517 263 6610",
    "sg:postcode":"49221",
    "sg:province":"MI",
    "sg:tags":[
        "house"
    ],
    "wof:name":"D Robertson Construct Inc",
    "wof:placetype":"venue"
},
  "geometry": {"coordinates":[-84.16398700000001,41.914715],"type":"Point"}
}