{
  "type": "Feature",
  "properties": {
    "iso:country":"US",
    "sg:address":"2632 Howden St",
    "sg:city":"Muskegon",
    "sg:classifiers":[
        {
            "category":"Professional",
            "type":"Services"
        }
    ],
    "sg:phone":"+1 231 739 7481",
    "sg:postcode":"49444",
    "sg:province":"MI",
    "wof:name":"What About US Now Inc",
    "wof:placetype":"venue"
},
  "geometry": {"coordinates":[-86.237101,43.203626],"type":"Point"}
}