{
  "type": "Feature",
  "properties": {
    "iso:country":"US",
    "sg:address":"744 W Tyler Rd",
    "sg:city":"Hart",
    "sg:classifiers":[
        {
            "category":"Farming",
            "subcategory":"Livestock Farm",
            "type":"Manufacturing & Wholesale Goods"
        }
    ],
    "sg:phone":"+1 231 873 2246",
    "sg:postcode":"49420",
    "sg:province":"MI",
    "sg:tags":[
        "beef",
        "feedlot",
        "cattle"
    ],
    "wof:name":"Gordon Hill",
    "wof:placetype":"venue"
},
  "geometry": {"coordinates":[-86.297044,43.701763],"type":"Point"}
}