{
  "type": "Feature",
  "properties": {
    "iso:country":"US",
    "sg:address":"1300 Burton St SE",
    "sg:city":"Grand Rapids",
    "sg:classifiers":[
        {
            "category":"Wholesale",
            "subcategory":"Machinery & Supplies",
            "type":"Manufacturing & Wholesale Goods"
        }
    ],
    "sg:phone":"+1 616 243 2531",
    "sg:postcode":"49507",
    "sg:province":"MI",
    "sg:tags":[
        "equipment",
        "welding"
    ],
    "wof:name":"Aladdin Welding Products Inc",
    "wof:placetype":"venue"
},
  "geometry": {"coordinates":[-85.63602299999999,42.927172],"type":"Point"}
}