{
  "type": "Feature",
  "properties": {
    "iso:country":"US",
    "sg:address":"122 Silver St",
    "sg:city":"Hurley",
    "sg:classifiers":[
        {
            "category":"Restaurant",
            "type":"Food & Drink"
        },
        {
            "category":"Shopping",
            "subcategory":"Gifts & Souvenirs",
            "type":"Retail Goods"
        }
    ],
    "sg:phone":"+1 715 561 5500",
    "sg:postcode":"54534",
    "sg:province":"WI",
    "sg:tags":[
        "shop",
        "house",
        "coffee"
    ],
    "wof:name":"Hurley Coffee Co",
    "wof:placetype":"venue"
},
  "geometry": {"coordinates":[-90.18182,46.44986],"type":"Point"}
}