{
  "type": "Feature",
  "properties": {
    "iso:country":"US",
    "sg:address":"15800 Fenkell St",
    "sg:city":"Detroit",
    "sg:classifiers":[
        {
            "category":"Organizations",
            "subcategory":"Religious Organization",
            "type":"Services"
        }
    ],
    "sg:phone":"+1 313 837 5861",
    "sg:postcode":"48227",
    "sg:province":"MI",
    "wof:name":"Faith Principles Missnry Bapti",
    "wof:placetype":"venue"
},
  "geometry": {"coordinates":[-83.20293599999999,42.40141],"type":"Point"}
}