{
  "type": "Feature",
  "properties": {
    "iso:country":"US",
    "sg:address":"5611 Cedar Ridge Dr",
    "sg:city":"Ann Arbor",
    "sg:classifiers":[
        {
            "category":"Professional",
            "subcategory":"Business Services",
            "type":"Services"
        }
    ],
    "sg:phone":"+1 734 998 3722",
    "sg:postcode":"48103",
    "sg:province":"MI",
    "wof:name":"Career Path By Design",
    "wof:placetype":"venue"
},
  "geometry": {"coordinates":[-83.840631,42.280518],"type":"Point"}
}