{
  "type": "Feature",
  "properties": {
    "iso:country":"US",
    "sg:address":"1200 Elmwood St",
    "sg:city":"Detroit",
    "sg:classifiers":[
        {
            "category":"Retail",
            "subcategory":"Funeral Services",
            "type":"Services"
        }
    ],
    "sg:phone":"+1 313 567 3453",
    "sg:postcode":"48207",
    "sg:province":"MI",
    "sg:tags":[
        "cemetery"
    ],
    "wof:name":"Elmwood Cemetery",
    "wof:placetype":"venue"
},
  "geometry": {"coordinates":[-83.02570299999999,42.345501],"type":"Point"}
}