{
  "type": "Feature",
  "properties": {
    "iso:country":"US",
    "sg:address":"4801 Chrysler Dr",
    "sg:city":"Detroit",
    "sg:classifiers":[
        {
            "category":"Social Services",
            "subcategory":"Adult Care",
            "type":"Services"
        }
    ],
    "sg:phone":"+1 313 831 0600",
    "sg:postcode":"48201",
    "sg:province":"MI",
    "sg:tags":[
        "home"
    ],
    "wof:name":"Cyprian Adult Respic Care",
    "wof:placetype":"venue"
},
  "geometry": {"coordinates":[-83.053821,42.36098],"type":"Point"}
}