{
  "type": "Feature",
  "properties": {
    "iso:country":"US",
    "sg:address":"1476 Rosewood St",
    "sg:city":"Ann Arbor",
    "sg:classifiers":[
        {
            "category":"Professional",
            "subcategory":"Art Services",
            "type":"Services"
        }
    ],
    "sg:phone":"+1 734 761 4404",
    "sg:postcode":"48104",
    "sg:province":"MI",
    "sg:tags":[
        "commercial",
        "design"
    ],
    "wof:name":"Hite Graphics",
    "wof:placetype":"venue"
},
  "geometry": {"coordinates":[-83.72905900000001,42.255478],"type":"Point"}
}