{
  "type": "Feature",
  "properties": {
    "iso:country":"US",
    "sg:address":"6095 Baldwin Rd",
    "sg:city":"Swartz Creek",
    "sg:classifiers":[
        {
            "category":"Real Estate",
            "subcategory":"Real Estate Agent",
            "type":"Services"
        }
    ],
    "sg:phone":"+1 810 655 4076",
    "sg:postcode":"48473",
    "sg:province":"MI",
    "wof:name":"Pinkston Properties",
    "wof:placetype":"venue"
},
  "geometry": {"coordinates":[-83.791462,42.884381],"type":"Point"}
}