{
  "type": "Feature",
  "properties": {
    "iso:country":"US",
    "sg:address":"11815 Patton St",
    "sg:city":"Detroit",
    "sg:classifiers":[
        {
            "category":"Arts & Performance",
            "subcategory":"Theater",
            "type":"Entertainment"
        }
    ],
    "sg:phone":"+1 313 835 2279",
    "sg:postcode":"48228",
    "sg:province":"MI",
    "sg:tags":[
        "group"
    ],
    "wof:name":"Bulkhead Entertainment",
    "wof:placetype":"venue"
},
  "geometry": {"coordinates":[-83.24263500000001,42.3758],"type":"Point"}
}