{
  "type": "Feature",
  "properties": {
    "iso:country":"US",
    "sg:address":"5851 S Lake St",
    "sg:city":"Glen Arbor",
    "sg:classifiers":[
        {
            "category":"Health Services",
            "subcategory":"Doctor",
            "type":"Services"
        }
    ],
    "sg:phone":"+1 231 334 8300",
    "sg:postcode":"49636",
    "sg:province":"MI",
    "sg:tags":[
        "physician",
        "surgeon"
    ],
    "wof:name":"Matthew A Houghton Jr DO",
    "wof:placetype":"venue"
},
  "geometry": {"coordinates":[-85.98881,44.899299],"type":"Point"}
}