{
  "type": "Feature",
  "properties": {
    "iso:country":"US",
    "sg:address":"3131 Third Street",
    "sg:city":"Wyandotte",
    "sg:classifiers":[
        {
            "category":"Transit Center",
            "subcategory":"Passenger",
            "type":"Transportation"
        }
    ],
    "sg:postcode":"48192",
    "sg:province":"MI",
    "sg:website":"www.wyandotte.net/FrontDesk/Form...",
    "wof:name":"City of Wyandotte Trolley",
    "wof:placetype":"venue"
},
  "geometry": {"coordinates":[-83.153099,42.201741],"type":"Point"}
}