{
  "type": "Feature",
  "properties": {
    "iso:country":"US",
    "sg:address":"2151 Bray Rd",
    "sg:city":"Vulcan",
    "sg:classifiers":[
        {
            "category":"Building & Trades",
            "subcategory":"Construction",
            "type":"Services"
        }
    ],
    "sg:phone":"+1 906 563 5506",
    "sg:postcode":"49892",
    "sg:province":"MI",
    "sg:tags":[
        "resurfacing",
        "laying",
        "refinishing",
        "floor"
    ],
    "wof:name":"Sam's Hardwood Floor Instltn",
    "wof:placetype":"venue"
},
  "geometry": {"coordinates":[-87.728298,45.773213],"type":"Point"}
}