{
  "type": "Feature",
  "properties": {
    "iso:country":"US",
    "sg:address":"3924 E Johns Ln",
    "sg:city":"Midland",
    "sg:classifiers":[
        {
            "category":"Social Services",
            "subcategory":"Child Care",
            "type":"Services"
        }
    ],
    "sg:phone":"+1 989 832 0492",
    "sg:postcode":"48642",
    "sg:province":"MI",
    "sg:tags":[
        "day"
    ],
    "wof:name":"Kids House Chrstn Day Care",
    "wof:placetype":"venue"
},
  "geometry": {"coordinates":[-84.21073699999999,43.68662],"type":"Point"}
}