{
  "type": "Feature",
  "properties": {
    "iso:country":"US",
    "sg:address":"3979 N Lincoln Rd",
    "sg:city":"Ludington",
    "sg:classifiers":[
        {
            "category":"Professional",
            "subcategory":"Business Services",
            "type":"Services"
        }
    ],
    "sg:phone":"+1 231 843 4313",
    "sg:postcode":"49431",
    "sg:province":"MI",
    "wof:name":"Wash-On-Wheels",
    "wof:placetype":"venue"
},
  "geometry": {"coordinates":[-86.440066,44.027734],"type":"Point"}
}