{
  "type": "Feature",
  "properties": {
    "iso:country":"US",
    "sg:address":"2686 N School Rd",
    "sg:city":"Weidman",
    "sg:classifiers":[
        {
            "category":"Building & Trades",
            "subcategory":"Construction",
            "type":"Services"
        }
    ],
    "sg:phone":"+1 989 644 3007",
    "sg:postcode":"48893",
    "sg:province":"MI",
    "sg:tags":[
        "insulation",
        "heat",
        "contractor"
    ],
    "wof:name":"CDI Insulation Specialist",
    "wof:placetype":"venue"
},
  "geometry": {"coordinates":[-84.977789,43.676657],"type":"Point"}
}