{
  "type": "Feature",
  "properties": {
    "iso:country":"US",
    "sg:address":"407 Perry St",
    "sg:city":"Albion",
    "sg:classifiers":[
        {
            "category":"Shopping",
            "subcategory":"Florist",
            "type":"Retail Goods"
        }
    ],
    "sg:phone":"+1 517 629 2131",
    "sg:postcode":"49224",
    "sg:province":"MI",
    "wof:name":"Clark's Flowers",
    "wof:placetype":"venue"
},
  "geometry": {"coordinates":[-84.747129,42.246092],"type":"Point"}
}