{
  "type": "Feature",
  "properties": {
    "iso:country":"US",
    "sg:address":"3686 N River Rd",
    "sg:city":"Fort Gratiot",
    "sg:classifiers":[
        {
            "category":"Organizations",
            "subcategory":"Religious Organization",
            "type":"Services"
        }
    ],
    "sg:phone":"+1 810 987 8580",
    "sg:postcode":"48059",
    "sg:province":"MI",
    "wof:name":"Fellowship Bible Church",
    "wof:placetype":"venue"
},
  "geometry": {"coordinates":[-82.48174299999999,43.012181],"type":"Point"}
}