{
  "type": "Feature",
  "properties": {
    "iso:country":"US",
    "sg:address":"1202 College Ave",
    "sg:city":"Houghton",
    "sg:classifiers":[
        {
            "category":"Organizations",
            "subcategory":"Community Association",
            "type":"Services"
        }
    ],
    "sg:phone":"+1 906 482 6012",
    "sg:postcode":"49931",
    "sg:province":"MI",
    "sg:tags":[
        "fraternal"
    ],
    "wof:name":"Lambda Chi Alpha",
    "wof:placetype":"venue"
},
  "geometry": {"coordinates":[-88.556358,47.120862],"type":"Point"}
}