{
  "type": "Feature",
  "properties": {
    "iso:country":"US",
    "sg:address":"1504 Cutler St",
    "sg:city":"Burton",
    "sg:classifiers":[
        {
            "category":"Personal",
            "subcategory":"Beauty Salon",
            "type":"Services"
        }
    ],
    "sg:phone":"+1 810 742 7101",
    "sg:postcode":"48509",
    "sg:province":"MI",
    "sg:tags":[
        "shop"
    ],
    "wof:name":"Nancy Shanks",
    "wof:placetype":"venue"
},
  "geometry": {"coordinates":[-83.598404,43.005899],"type":"Point"}
}