{
  "type": "Feature",
  "properties": {
    "iso:country":"US",
    "sg:address":"578 N Cedar St",
    "sg:city":"Imlay City",
    "sg:classifiers":[
        {
            "category":"Food & Beverages",
            "subcategory":"Groceries & Convenience Stores",
            "type":"Retail Goods"
        }
    ],
    "sg:phone":"+1 810 724 8653",
    "sg:postcode":"48444",
    "sg:province":"MI",
    "sg:tags":[
        "grocer"
    ],
    "wof:name":"Pronto Marts",
    "wof:placetype":"venue"
},
  "geometry": {"coordinates":[-83.071468,43.030818],"type":"Point"}
}