{
  "type": "Feature",
  "properties": {
    "iso:country":"US",
    "sg:address":"2900 Crystal Ln",
    "sg:city":"Kalamazoo",
    "sg:classifiers":[
        {
            "category":"Real Estate",
            "subcategory":"Real Estate Operator",
            "type":"Services"
        }
    ],
    "sg:phone":"+1 269 375 6667",
    "sg:postcode":"49009",
    "sg:province":"MI",
    "sg:tags":[
        "building",
        "apartment"
    ],
    "wof:name":"Evergreen South",
    "wof:placetype":"venue"
},
  "geometry": {"coordinates":[-85.65966400000001,42.262051],"type":"Point"}
}