{
  "type": "Feature",
  "properties": {
    "iso:country":"US",
    "sg:address":"34005 Autry St",
    "sg:city":"Livonia",
    "sg:classifiers":[
        {
            "category":"Real Estate",
            "subcategory":"Real Estate Operator",
            "type":"Services"
        }
    ],
    "sg:phone":"+1 734 261 0060",
    "sg:postcode":"48150",
    "sg:province":"MI",
    "sg:tags":[
        "building",
        "owns",
        "commercial",
        "operates"
    ],
    "wof:name":"Robian USA LLC",
    "wof:placetype":"venue"
},
  "geometry": {"coordinates":[-83.380518,42.380172],"type":"Point"}
}