{
  "type": "Feature",
  "properties": {
    "iso:country":"US",
    "sg:address":"1101 S Beacon Blvd",
    "sg:city":"Grand Haven",
    "sg:classifiers":[
        {
            "category":"Food & Beverages",
            "subcategory":"Groceries & Convenience Stores",
            "type":"Retail Goods"
        }
    ],
    "sg:phone":"+1 616 296 0340",
    "sg:postcode":"49417",
    "sg:province":"MI",
    "sg:tags":[
        "grocer"
    ],
    "sg:website":"www.savealot.com",
    "wof:name":"Grand Haven Save-A-Lot",
    "wof:placetype":"venue"
},
  "geometry": {"coordinates":[-86.220466,43.046322],"type":"Point"}
}