{
  "type": "Feature",
  "properties": {
    "iso:country":"US",
    "sg:address":"1041 E M 21",
    "sg:city":"Owosso",
    "sg:classifiers":[
        {
            "category":"Building & Trades",
            "subcategory":"Landscaping Services",
            "type":"Services"
        }
    ],
    "sg:phone":"+1 989 725 7120",
    "sg:postcode":"48867",
    "sg:province":"MI",
    "sg:tags":[
        "landscape",
        "contractor"
    ],
    "wof:name":"Turf Chemicals Inc",
    "wof:placetype":"venue"
},
  "geometry": {"coordinates":[-84.154297,42.997756],"type":"Point"}
}