{
  "type": "Feature",
  "properties": {
    "iso:country":"US",
    "sg:address":"12375 S Tallman Rd",
    "sg:city":"Eagle",
    "sg:classifiers":[
        {
            "category":"Professional",
            "subcategory":"Lawyer & Legal Services",
            "type":"Services"
        }
    ],
    "sg:phone":"+1 517 647 4348",
    "sg:postcode":"48822",
    "sg:province":"MI",
    "wof:name":"Legal Invest Svcs",
    "wof:placetype":"venue"
},
  "geometry": {"coordinates":[-84.75928,42.835071],"type":"Point"}
}