{
  "type": "Feature",
  "properties": {
    "iso:country":"US",
    "sg:address":"103 S Clay St",
    "sg:city":"Homer",
    "sg:classifiers":[
        {
            "category":"Manufacturing",
            "subcategory":"Tools & Machinery",
            "type":"Manufacturing & Wholesale Goods"
        }
    ],
    "sg:phone":"+1 517 568 4787",
    "sg:postcode":"49245",
    "sg:province":"MI",
    "sg:tags":[
        "mfg"
    ],
    "wof:name":"CPM",
    "wof:placetype":"venue"
},
  "geometry": {"coordinates":[-84.80381,42.145371],"type":"Point"}
}