{
  "type": "Feature",
  "properties": {
    "iso:country":"US",
    "sg:address":"16 E Judson St",
    "sg:city":"Pontiac",
    "sg:classifiers":[
        {
            "category":"Health Services",
            "subcategory":"Doctor",
            "type":"Services"
        }
    ],
    "sg:phone":"+1 248 456 5963",
    "sg:postcode":"48342",
    "sg:province":"MI",
    "sg:tags":[
        "physician",
        "surgeon"
    ],
    "wof:name":"Joseph Grayson MD",
    "wof:placetype":"venue"
},
  "geometry": {"coordinates":[-83.289056,42.633466],"type":"Point"}
}