{
  "type": "Feature",
  "properties": {
    "iso:country":"US",
    "sg:address":"14595 Livernois Ave",
    "sg:city":"Detroit",
    "sg:classifiers":[
        {
            "category":"Autos & Motor Vehicles",
            "subcategory":"Auto Supplies",
            "type":"Retail Goods"
        }
    ],
    "sg:phone":"+1 313 861 5500",
    "sg:postcode":"48238",
    "sg:province":"MI",
    "sg:tags":[
        "tire"
    ],
    "wof:name":"Detroit Tire & Auto",
    "wof:placetype":"venue"
},
  "geometry": {"coordinates":[-83.140198,42.397598],"type":"Point"}
}