{
  "type": "Feature",
  "properties": {
    "iso:country":"US",
    "sg:address":"8933 S 25th St",
    "sg:city":"Scotts",
    "sg:classifiers":[
        {
            "category":"Building & Trades",
            "subcategory":"Landscaping Services",
            "type":"Services"
        }
    ],
    "sg:phone":"+1 269 327 7343",
    "sg:postcode":"49088",
    "sg:province":"MI",
    "wof:name":"Neubauer Maintenance",
    "wof:placetype":"venue"
},
  "geometry": {"coordinates":[-85.51560499999999,42.189363],"type":"Point"}
}