{
  "type": "Feature",
  "properties": {
    "iso:country":"US",
    "sg:address":"6480 Norton Center Dr",
    "sg:city":"Muskegon",
    "sg:classifiers":[
        {
            "category":"Manufacturing",
            "subcategory":"Tools & Machinery",
            "type":"Manufacturing & Wholesale Goods"
        }
    ],
    "sg:phone":"+1 231 798 1111",
    "sg:postcode":"49441",
    "sg:province":"MI",
    "sg:tags":[
        "equipment",
        "laboratory",
        "supply"
    ],
    "sg:website":"www.airmastersystems.com",
    "wof:name":"Air Master Systems",
    "wof:placetype":"venue"
},
  "geometry": {"coordinates":[-86.217848,43.135229],"type":"Point"}
}