{
  "type": "Feature",
  "properties": {
    "iso:country":"US",
    "sg:address":"6230 Hellner Rd",
    "sg:city":"Ann Arbor",
    "sg:classifiers":[
        {
            "category":"Professional",
            "subcategory":"Computer Services",
            "type":"Services"
        }
    ],
    "sg:phone":"+1 734 994 5322",
    "sg:postcode":"48105",
    "sg:province":"MI",
    "sg:tags":[
        "related"
    ],
    "wof:name":"Kr Consulting",
    "wof:placetype":"venue"
},
  "geometry": {"coordinates":[-83.771092,42.359681],"type":"Point"}
}