{
  "type": "Feature",
  "properties": {
    "iso:country":"US",
    "sg:address":"1429 Oakwood St",
    "sg:city":"Sylvan Lake",
    "sg:classifiers":[
        {
            "category":"Personal",
            "subcategory":"Beauty Salon",
            "type":"Services"
        }
    ],
    "sg:phone":"+1 248 706 2242",
    "sg:postcode":"48320",
    "sg:province":"MI",
    "wof:name":"Utopia Salon",
    "wof:placetype":"venue"
},
  "geometry": {"coordinates":[-83.32901200000001,42.617844],"type":"Point"}
}