{
  "type": "Feature",
  "properties": {
    "iso:country":"US",
    "sg:address":"11426 Yates Rd",
    "sg:city":"Copemish",
    "sg:classifiers":[
        {
            "category":"Farming",
            "subcategory":"Fish & Marine Products",
            "type":"Manufacturing & Wholesale Goods"
        }
    ],
    "sg:phone":"+1 231 362 2828",
    "sg:postcode":"49625",
    "sg:province":"MI",
    "sg:tags":[
        "preserves",
        "fishing",
        "hunting"
    ],
    "wof:name":"Cudney's Big Bucks",
    "wof:placetype":"venue"
},
  "geometry": {"coordinates":[-85.91947,44.404916],"type":"Point"}
}