{
  "type": "Feature",
  "properties": {
    "iso:country":"US",
    "sg:address":"6243 Dixie Hwy",
    "sg:city":"Bridgeport",
    "sg:classifiers":[
        {
            "category":"Manufacturing",
            "subcategory":"Tools & Machinery",
            "type":"Manufacturing & Wholesale Goods"
        }
    ],
    "sg:phone":"+1 989 777 7190",
    "sg:postcode":"48722",
    "sg:province":"MI",
    "sg:tags":[
        "cutting"
    ],
    "sg:website":"www.stoneycrest.com",
    "wof:name":"Stoney Crest Regrind Svc",
    "wof:placetype":"venue"
},
  "geometry": {"coordinates":[-83.87617899999999,43.356209],"type":"Point"}
}