{
  "type": "Feature",
  "properties": {
    "iso:country":"US",
    "sg:address":"5915 S Cedar St",
    "sg:city":"Lansing",
    "sg:classifiers":[
        {
            "category":"Wholesale",
            "subcategory":"Electrical",
            "type":"Manufacturing & Wholesale Goods"
        }
    ],
    "sg:phone":"+1 517 887 9907",
    "sg:postcode":"48911",
    "sg:province":"MI",
    "sg:tags":[
        "control",
        "security",
        "system"
    ],
    "wof:name":"Watson Alarm Inc",
    "wof:placetype":"venue"
},
  "geometry": {"coordinates":[-84.54533600000001,42.671902],"type":"Point"}
}