{
  "type": "Feature",
  "properties": {
    "iso:country":"US",
    "sg:address":"230 E Buffalo St",
    "sg:city":"New Buffalo",
    "sg:classifiers":[
        {
            "category":"Real Estate",
            "subcategory":"Real Estate Agent",
            "type":"Services"
        }
    ],
    "sg:phone":"+1 269 469 3300",
    "sg:postcode":"49117",
    "sg:province":"MI",
    "wof:name":"Degroff Properties",
    "wof:placetype":"venue"
},
  "geometry": {"coordinates":[-86.74096,41.795278],"type":"Point"}
}