{
  "type": "Feature",
  "properties": {
    "iso:country":"US",
    "sg:address":"20398 Waubascon Rd",
    "sg:city":"Battle Creek",
    "sg:classifiers":[
        {
            "category":"Organizations",
            "subcategory":"Religious Organization",
            "type":"Services"
        }
    ],
    "sg:phone":"+1 269 964 6090",
    "sg:postcode":"49017",
    "sg:province":"MI",
    "wof:name":"First Presbyterian Retreat Ctr",
    "wof:placetype":"venue"
},
  "geometry": {"coordinates":[-85.21038900000001,42.365482],"type":"Point"}
}