{
  "type": "Feature",
  "properties": {
    "iso:country":"US",
    "sg:address":"205 Riviera Dr",
    "sg:city":"Brooklyn",
    "sg:classifiers":[
        {
            "category":"Building & Trades",
            "subcategory":"Construction",
            "type":"Services"
        }
    ],
    "sg:phone":"+1 517 592 4616",
    "sg:postcode":"49230",
    "sg:province":"MI",
    "sg:tags":[
        "house"
    ],
    "wof:name":"Sun Technologies",
    "wof:placetype":"venue"
},
  "geometry": {"coordinates":[-84.289118,42.085319],"type":"Point"}
}