{
  "type": "Feature",
  "properties": {
    "iso:country":"US",
    "sg:address":"9000 Conner St",
    "sg:city":"Detroit",
    "sg:classifiers":[
        {
            "category":"Food & Beverages",
            "subcategory":"Groceries & Convenience Stores",
            "type":"Retail Goods"
        }
    ],
    "sg:phone":"+1 313 372 1564",
    "sg:postcode":"48213",
    "sg:province":"MI",
    "wof:name":"N & J Mini Mart",
    "wof:placetype":"venue"
},
  "geometry": {"coordinates":[-82.9897,42.397598],"type":"Point"}
}