{
  "type": "Feature",
  "properties": {
    "iso:country":"US",
    "sg:address":"800 Monroe Ave NW",
    "sg:city":"Grand Rapids",
    "sg:classifiers":[
        {
            "category":"Government",
            "subcategory":"Office",
            "type":"Public Place"
        }
    ],
    "sg:phone":"+1 616 456 2335",
    "sg:postcode":"49503",
    "sg:province":"MI",
    "sg:tags":[
        "labor",
        "management",
        "standard"
    ],
    "wof:name":"Office Labor MGT Standards",
    "wof:placetype":"venue"
},
  "geometry": {"coordinates":[-85.67249700000001,42.978204],"type":"Point"}
}