{
  "type": "Feature",
  "properties": {
    "iso:country":"US",
    "sg:address":"7363 Pleasantview Rd",
    "sg:city":"Harbor Springs",
    "sg:classifiers":[
        {
            "category":"Wholesale",
            "subcategory":"Scrap",
            "type":"Manufacturing & Wholesale Goods"
        }
    ],
    "sg:phone":"+1 231 526 2031",
    "sg:postcode":"49740",
    "sg:province":"MI",
    "sg:tags":[
        "recycling",
        "center"
    ],
    "wof:name":"Emmet County Recycling Ctr",
    "wof:placetype":"venue"
},
  "geometry": {"coordinates":[-84.914755,45.444252],"type":"Point"}
}