{
  "type": "Feature",
  "properties": {
    "iso:country":"US",
    "sg:address":"524 McCormick Dr",
    "sg:city":"Lapeer",
    "sg:classifiers":[
        {
            "category":"Manufacturing",
            "subcategory":"Tools & Machinery",
            "type":"Manufacturing & Wholesale Goods"
        }
    ],
    "sg:phone":"+1 810 245 6840",
    "sg:postcode":"48446",
    "sg:province":"MI",
    "sg:tags":[
        "designed",
        "built"
    ],
    "wof:name":"MTS Systems Corp",
    "wof:placetype":"venue"
},
  "geometry": {"coordinates":[-83.314514,43.043624],"type":"Point"}
}