{
  "type": "Feature",
  "properties": {
    "iso:country":"US",
    "sg:address":"5169 W Kl Ave",
    "sg:city":"Kalamazoo",
    "sg:classifiers":[
        {
            "category":"Freight",
            "type":"Transportation"
        }
    ],
    "sg:phone":"+1 269 372 6464",
    "sg:postcode":"49009",
    "sg:province":"MI",
    "sg:tags":[
        "commercial",
        "storage"
    ],
    "wof:name":"National Mini Storage",
    "wof:placetype":"venue"
},
  "geometry": {"coordinates":[-85.653459,42.277991],"type":"Point"}
}