{
  "type": "Feature",
  "properties": {
    "iso:country":"US",
    "sg:address":"2051 Niles Rd",
    "sg:city":"Saint Joseph",
    "sg:classifiers":[
        {
            "category":"Restaurant",
            "type":"Food & Drink"
        }
    ],
    "sg:menulink":"http://www.allmenus.com/mi/st-joseph/207785-taco-bell/menu/",
    "sg:phone":"+1 269 983 4118",
    "sg:postcode":"49085",
    "sg:province":"MI",
    "sg:tags":[
        "mexican"
    ],
    "wof:name":"Taco Bell",
    "wof:placetype":"venue"
},
  "geometry": {"coordinates":[-86.484763,42.081031],"type":"Point"}
}