{
  "type": "Feature",
  "properties": {
    "iso:country":"US",
    "sg:address":"22201 Ardmore Park Dr",
    "sg:city":"Saint Clair Shores",
    "sg:classifiers":[
        {
            "category":"Personal",
            "type":"Services"
        }
    ],
    "sg:phone":"+1 586 779 5761",
    "sg:postcode":"48081",
    "sg:province":"MI",
    "sg:tags":[
        "towing"
    ],
    "wof:name":"Shores Towing",
    "wof:placetype":"venue"
},
  "geometry": {"coordinates":[-82.89119700000001,42.490799],"type":"Point"}
}