{
  "type": "Feature",
  "properties": {
    "iso:country":"US",
    "sg:address":"4880 S Good Harbor Trl",
    "sg:city":"Cedar",
    "sg:classifiers":[
        {
            "category":"Freight",
            "type":"Transportation"
        }
    ],
    "sg:phone":"+1 231 228 6902",
    "sg:postcode":"49621",
    "sg:province":"MI",
    "sg:tags":[
        "commercial",
        "storage"
    ],
    "wof:name":"Costal Marine Storage",
    "wof:placetype":"venue"
},
  "geometry": {"coordinates":[-85.796449,44.908373],"type":"Point"}
}