{
  "type": "Feature",
  "properties": {
    "iso:country":"US",
    "sg:address":"8101 Centerline Rd",
    "sg:city":"Saranac",
    "sg:classifiers":[
        {
            "category":"Food & Beverages",
            "subcategory":"Bakery",
            "type":"Retail Goods"
        }
    ],
    "sg:phone":"+1 616 642 6931",
    "sg:postcode":"48881",
    "sg:province":"MI",
    "wof:name":"Cakes By Tami",
    "wof:placetype":"venue"
},
  "geometry": {"coordinates":[-85.238754,42.943947],"type":"Point"}
}