{
  "type": "Feature",
  "properties": {
    "iso:country":"US",
    "sg:address":"504 Grand River Ave",
    "sg:city":"Port Huron",
    "sg:classifiers":[
        {
            "category":"Professional",
            "subcategory":"Art Services",
            "type":"Services"
        }
    ],
    "sg:phone":"+1 810 985 6005",
    "sg:postcode":"48060",
    "sg:province":"MI",
    "sg:tags":[
        "artist"
    ],
    "wof:name":"Duchene Backdrops Inc",
    "wof:placetype":"venue"
},
  "geometry": {"coordinates":[-82.42527699999999,42.977324],"type":"Point"}
}