{
  "type": "Feature",
  "properties": {
    "iso:country":"US",
    "sg:address":"38215 W 10 Mile Rd",
    "sg:city":"Farmington",
    "sg:classifiers":[
        {
            "category":"Professional",
            "subcategory":"Employment Agencies",
            "type":"Services"
        }
    ],
    "sg:phone":"+1 248 474 5000",
    "sg:postcode":"48335",
    "sg:province":"MI",
    "sg:tags":[
        "employee",
        "temporary",
        "leasing",
        "help"
    ],
    "wof:name":"Express Personnel Services",
    "wof:placetype":"venue"
},
  "geometry": {"coordinates":[-83.427222,42.468171],"type":"Point"}
}