{
  "type": "Feature",
  "properties": {
    "iso:country":"US",
    "sg:address":"4900 Rayner Park Dr",
    "sg:city":"Lake Orion",
    "sg:classifiers":[
        {
            "category":"Building & Trades",
            "subcategory":"Construction",
            "type":"Services"
        }
    ],
    "sg:phone":"+1 248 393 3242",
    "sg:postcode":"48359",
    "sg:province":"MI",
    "sg:tags":[
        "dry wall",
        "contractor"
    ],
    "wof:name":"Doctor Drywall",
    "wof:placetype":"venue"
},
  "geometry": {"coordinates":[-83.320475,42.709445],"type":"Point"}
}