{
  "type": "Feature",
  "properties": {
    "iso:country":"US",
    "sg:address":"3342 Hack Rd",
    "sg:city":"Saginaw",
    "sg:classifiers":[
        {
            "category":"Real Estate",
            "subcategory":"Developer",
            "type":"Services"
        }
    ],
    "sg:phone":"+1 989 771 9393",
    "sg:postcode":"48601",
    "sg:province":"MI",
    "wof:name":"Leasco Properties",
    "wof:placetype":"venue"
},
  "geometry": {"coordinates":[-83.887536,43.464849],"type":"Point"}
}