{
  "type": "Feature",
  "properties": {
    "iso:country":"US",
    "sg:address":"3849 Loch Dr",
    "sg:city":"Highland",
    "sg:classifiers":[
        {
            "category":"Building & Trades",
            "subcategory":"Construction",
            "type":"Services"
        }
    ],
    "sg:phone":"+1 248 887 1326",
    "sg:postcode":"48357",
    "sg:province":"MI",
    "sg:tags":[
        "house"
    ],
    "wof:name":"Wiza Const",
    "wof:placetype":"venue"
},
  "geometry": {"coordinates":[-83.634694,42.669568],"type":"Point"}
}