{
  "type": "Feature",
  "properties": {
    "iso:country":"US",
    "sg:address":"5030 W Progress Dr",
    "sg:city":"Ludington",
    "sg:classifiers":[
        {
            "category":"Building & Trades",
            "subcategory":"Construction",
            "type":"Services"
        }
    ],
    "sg:phone":"+1 231 843 1833",
    "sg:postcode":"49431",
    "sg:province":"MI",
    "sg:tags":[
        "contractor"
    ],
    "wof:name":"Wagner & Sons Construction Inc",
    "wof:placetype":"venue"
},
  "geometry": {"coordinates":[-86.402754,43.940768],"type":"Point"}
}