{
  "type": "Feature",
  "properties": {
    "iso:country":"US",
    "sg:address":"9187 Sunset Dr",
    "sg:city":"Berrien Springs",
    "sg:classifiers":[
        {
            "category":"Building & Trades",
            "subcategory":"Construction",
            "type":"Services"
        }
    ],
    "sg:phone":"+1 269 471 9271",
    "sg:postcode":"49103",
    "sg:province":"MI",
    "sg:tags":[
        "house"
    ],
    "wof:name":"Scott Collard Constructio",
    "wof:placetype":"venue"
},
  "geometry": {"coordinates":[-86.362742,41.953094],"type":"Point"}
}