{
  "type": "Feature",
  "properties": {
    "iso:country":"US",
    "sg:address":"52238 Birch Ct",
    "sg:city":"New Baltimore",
    "sg:classifiers":[
        {
            "category":"Freight",
            "type":"Transportation"
        }
    ],
    "sg:phone":"+1 586 634 6863",
    "sg:postcode":"48047",
    "sg:province":"MI",
    "sg:tags":[
        "operator",
        "local",
        "trucking"
    ],
    "wof:name":"Load & Go Inc",
    "wof:placetype":"venue"
},
  "geometry": {"coordinates":[-82.78371300000001,42.689371],"type":"Point"}
}