{
  "type": "Feature",
  "properties": {
    "iso:country":"US",
    "sg:address":"802 W Front St",
    "sg:city":"Traverse City",
    "sg:classifiers":[
        {
            "category":"Shopping",
            "type":"Retail Goods"
        }
    ],
    "sg:phone":"+1 231 941 4452",
    "sg:postcode":"49684",
    "sg:province":"MI",
    "sg:tags":[
        "trophy",
        "medal",
        "award"
    ],
    "wof:name":"Lessard's Trophies & Awards",
    "wof:placetype":"venue"
},
  "geometry": {"coordinates":[-85.637987,44.764091],"type":"Point"}
}