{
  "type": "Feature",
  "properties": {
    "iso:country":"US",
    "sg:address":"4994 Lakeshore Blvd",
    "sg:city":"Newaygo",
    "sg:classifiers":[
        {
            "category":"Farming",
            "subcategory":"Farm",
            "type":"Manufacturing & Wholesale Goods"
        }
    ],
    "sg:phone":"+1 231 652 5346",
    "sg:postcode":"49337",
    "sg:province":"MI",
    "sg:tags":[
        "crop",
        "general"
    ],
    "wof:name":"JC Farms",
    "wof:placetype":"venue"
},
  "geometry": {"coordinates":[-85.781826,43.46395],"type":"Point"}
}