{
  "type": "Feature",
  "properties": {
    "iso:country":"US",
    "sg:address":"13677 White Creek Ave NE",
    "sg:city":"Cedar Springs",
    "sg:classifiers":[
        {
            "category":"Travel",
            "subcategory":"Campground",
            "type":"Entertainment"
        }
    ],
    "sg:phone":"+1 616 696 1735",
    "sg:postcode":"49319",
    "sg:province":"MI",
    "sg:tags":[
        "trailer"
    ],
    "sg:website":"www.lakesidecamppark.com",
    "wof:name":"Lake Side Camp Park",
    "wof:placetype":"venue"
},
  "geometry": {"coordinates":[-85.571192,43.213081],"type":"Point"}
}