{
  "type": "Feature",
  "properties": {
    "iso:country":"US",
    "sg:address":"51056 Atwood St",
    "sg:city":"New Baltimore",
    "sg:classifiers":[
        {
            "category":"Shopping",
            "type":"Retail Goods"
        }
    ],
    "sg:phone":"+1 586 725 0067",
    "sg:postcode":"48047",
    "sg:province":"MI",
    "sg:tags":[
        "picture",
        "frame"
    ],
    "wof:name":"Jeanine's Art",
    "wof:placetype":"venue"
},
  "geometry": {"coordinates":[-82.732438,42.682104],"type":"Point"}
}