{
  "type": "Feature",
  "properties": {
    "iso:country":"US",
    "sg:address":"24668 Regal Pl",
    "sg:city":"Harrison Twp",
    "sg:classifiers":[
        {
            "category":"Health Services",
            "subcategory":"Doctor",
            "type":"Services"
        }
    ],
    "sg:phone":"+1 586 465 0433",
    "sg:postcode":"48045",
    "sg:province":"MI",
    "sg:tags":[
        "dentist"
    ],
    "wof:name":"Robert P Baker DDS",
    "wof:placetype":"venue"
},
  "geometry": {"coordinates":[-82.86092600000001,42.57702],"type":"Point"}
}