{
  "type": "Feature",
  "properties": {
    "iso:country":"US",
    "sg:address":"207 Transit St",
    "sg:city":"Bay City",
    "sg:classifiers":[
        {
            "category":"Professional",
            "subcategory":"Computer Services",
            "type":"Services"
        }
    ],
    "sg:phone":"+1 989 667 8750",
    "sg:postcode":"48706",
    "sg:province":"MI",
    "sg:tags":[
        "datum"
    ],
    "wof:name":"Keith Bell",
    "wof:placetype":"venue"
},
  "geometry": {"coordinates":[-83.877815,43.616422],"type":"Point"}
}