{
  "type": "Feature",
  "properties": {
    "iso:country":"US",
    "sg:address":"11 Cambridge Blvd",
    "sg:city":"Pleasant Ridge",
    "sg:classifiers":[
        {
            "category":"Building & Trades",
            "subcategory":"Construction",
            "type":"Services"
        }
    ],
    "sg:phone":"+1 248 543 1231",
    "sg:postcode":"48069",
    "sg:province":"MI",
    "sg:tags":[
        "maker",
        "cabinet"
    ],
    "sg:website":"www.caninet.com",
    "wof:name":"Caninet.Com Inc",
    "wof:placetype":"venue"
},
  "geometry": {"coordinates":[-83.146761,42.468112],"type":"Point"}
}