{
  "type": "Feature",
  "properties": {
    "iso:country":"US",
    "sg:address":"38916 Dequindre Rd",
    "sg:city":"Sterling Heights",
    "sg:classifiers":[
        {
            "category":"Insurance",
            "subcategory":"Insurance Agent",
            "type":"Services"
        }
    ],
    "sg:phone":"+1 586 977 9250",
    "sg:postcode":"48310",
    "sg:province":"MI",
    "wof:name":"Casebolt Terry",
    "wof:placetype":"venue"
},
  "geometry": {"coordinates":[-83.089252,42.577125],"type":"Point"}
}