{
  "type": "Feature",
  "properties": {
    "iso:country":"US",
    "sg:address":"15526 Leonard Rd",
    "sg:city":"Spring Lake",
    "sg:classifiers":[
        {
            "category":"Building & Trades",
            "subcategory":"Pest Control",
            "type":"Services"
        }
    ],
    "sg:phone":"+1 616 847 0957",
    "sg:postcode":"49456",
    "sg:province":"MI",
    "wof:name":"AAA Termite & Pest Control",
    "wof:placetype":"venue"
},
  "geometry": {"coordinates":[-86.18164,43.062699],"type":"Point"}
}