{
  "type": "Feature",
  "properties": {
    "iso:country":"US",
    "sg:address":"201 Perry St",
    "sg:city":"Albion",
    "sg:classifiers":[
        {
            "category":"Food & Beverages",
            "subcategory":"Liquor & Beverages",
            "type":"Retail Goods"
        }
    ],
    "sg:phone":"+1 517 629 4225",
    "sg:postcode":"49224",
    "sg:province":"MI",
    "wof:name":"Snack Shop",
    "wof:placetype":"venue"
},
  "geometry": {"coordinates":[-84.75146599999999,42.24606],"type":"Point"}
}