{
  "type": "Feature",
  "properties": {
    "iso:country":"US",
    "sg:address":"35493 Harper Ave",
    "sg:city":"Clinton Township",
    "sg:classifiers":[
        {
            "category":"Restaurant",
            "type":"Food & Drink"
        }
    ],
    "sg:phone":"+1 586 791 7960",
    "sg:postcode":"48035",
    "sg:province":"MI",
    "sg:tags":[
        "pizza"
    ],
    "wof:name":"Carmen's Pizza & Party Shop",
    "wof:placetype":"venue"
},
  "geometry": {"coordinates":[-82.87039900000001,42.559601],"type":"Point"}
}