{
  "type": "Feature",
  "properties": {
    "iso:country":"US",
    "sg:address":"7200 E 10 Mile Rd",
    "sg:city":"Center Line",
    "sg:classifiers":[
        {
            "category":"Health Services",
            "subcategory":"Doctor",
            "type":"Services"
        }
    ],
    "sg:phone":"+1 586 758 3210",
    "sg:postcode":"48015",
    "sg:province":"MI",
    "wof:name":"Kanta Chander M D",
    "wof:placetype":"venue"
},
  "geometry": {"coordinates":[-83.03210300000001,42.477143],"type":"Point"}
}