{
  "type": "Feature",
  "properties": {
    "iso:country":"US",
    "sg:address":"604 N Lake St",
    "sg:city":"Ironwood",
    "sg:classifiers":[
        {
            "category":"Social Services",
            "subcategory":"Child Care",
            "type":"Services"
        }
    ],
    "sg:phone":"+1 906 932 2761",
    "sg:postcode":"49938",
    "sg:province":"MI",
    "sg:tags":[
        "home",
        "day"
    ],
    "wof:name":"Linda Beckman",
    "wof:placetype":"venue"
},
  "geometry": {"coordinates":[-90.156498,46.464715],"type":"Point"}
}