{
  "type": "Feature",
  "properties": {
    "iso:country":"US",
    "sg:address":"121 Franklin St SE",
    "sg:city":"Grand Rapids",
    "sg:classifiers":[
        {
            "category":"Social Services",
            "subcategory":"Job Training",
            "type":"Services"
        }
    ],
    "sg:phone":"+1 616 336 4040",
    "sg:postcode":"49507",
    "sg:province":"MI",
    "sg:tags":[
        "employment"
    ],
    "sg:website":"www.michworks.org",
    "wof:name":"Michigan Works Employment",
    "wof:placetype":"venue"
},
  "geometry": {"coordinates":[-85.664868,42.948673],"type":"Point"}
}