{
  "type": "Feature",
  "properties": {
    "iso:country":"US",
    "sg:address":"40580 Van Dyke Ave Ste A",
    "sg:city":"Sterling Heights",
    "sg:classifiers":[
        {
            "category":"Health Services",
            "subcategory":"Chiropractor",
            "type":"Services"
        }
    ],
    "sg:phone":"+1 586 978 1100",
    "sg:postcode":"48313",
    "sg:province":"MI",
    "wof:name":"AAA Swan Chiropractic Clinic",
    "wof:placetype":"venue"
},
  "geometry": {"coordinates":[-83.03040300000001,42.589802],"type":"Point"}
}