{
  "type": "Feature",
  "properties": {
    "iso:country":"US",
    "sg:address":"325 S Waverly Rd",
    "sg:city":"Holland",
    "sg:classifiers":[
        {
            "category":"Professional",
            "subcategory":"Business Services",
            "type":"Services"
        }
    ],
    "sg:phone":"+1 616 355 6569",
    "sg:postcode":"49423",
    "sg:province":"MI",
    "wof:name":"Spiewak Intl Enterprises Inc",
    "wof:placetype":"venue"
},
  "geometry": {"coordinates":[-86.07752000000001,42.785443],"type":"Point"}
}