{
  "type": "Feature",
  "properties": {
    "iso:country":"US",
    "sg:address":"10011 W McNichols Rd",
    "sg:city":"Detroit",
    "sg:classifiers":[
        {
            "category":"Shopping",
            "subcategory":"Pharmacy",
            "type":"Retail Goods"
        }
    ],
    "sg:phone":"+1 313 340 2892",
    "sg:postcode":"48221",
    "sg:province":"MI",
    "sg:tags":[
        "drugstore"
    ],
    "sg:website":"www.cvs.com",
    "wof:name":"Cvs Pharmacy",
    "wof:placetype":"venue"
},
  "geometry": {"coordinates":[-83.160301,42.416901],"type":"Point"}
}