{
  "type": "Feature",
  "properties": {
    "iso:country":"US",
    "sg:address":"5102 Foster Rd",
    "sg:city":"Midland",
    "sg:classifiers":[
        {
            "category":"Education",
            "subcategory":"Special Training",
            "type":"Public Place"
        }
    ],
    "sg:phone":"+1 989 835 4699",
    "sg:postcode":"48642",
    "sg:province":"MI",
    "sg:tags":[
        "instruction",
        "music"
    ],
    "wof:name":"Earl Norris Music Studio & Ins",
    "wof:placetype":"venue"
},
  "geometry": {"coordinates":[-84.196918,43.642705],"type":"Point"}
}