{
  "type": "Feature",
  "properties": {
    "iso:country":"US",
    "sg:address":"1429 Hill St",
    "sg:city":"Ann Arbor",
    "sg:classifiers":[
        {
            "category":"Organizations",
            "subcategory":"Religious Organization",
            "type":"Services"
        }
    ],
    "sg:phone":"+1 734 769 0500",
    "sg:postcode":"48104",
    "sg:province":"MI",
    "wof:name":"Hillel Foundation",
    "wof:placetype":"venue"
},
  "geometry": {"coordinates":[-83.730205,42.272384],"type":"Point"}
}