{
  "type": "Feature",
  "properties": {
    "iso:country":"US",
    "sg:address":"3531 60th St",
    "sg:city":"Hamilton",
    "sg:classifiers":[
        {
            "category":"Banks & Credit Unions",
            "subcategory":"Financial Services",
            "type":"Services"
        }
    ],
    "sg:phone":"+1 269 751 8563",
    "sg:postcode":"49419",
    "sg:province":"MI",
    "sg:tags":[
        "trust",
        "management"
    ],
    "wof:name":"American Assn Univ Women",
    "wof:placetype":"venue"
},
  "geometry": {"coordinates":[-86.13480300000001,42.675775],"type":"Point"}
}