{
  "type": "Feature",
  "properties": {
    "iso:country":"US",
    "sg:address":"2740 Challen Ln",
    "sg:city":"Ortonville",
    "sg:classifiers":[
        {
            "category":"Building & Trades",
            "subcategory":"Construction",
            "type":"Services"
        }
    ],
    "sg:phone":"+1 248 627 4849",
    "sg:postcode":"48462",
    "sg:province":"MI",
    "sg:tags":[
        "carpentry",
        "contractor"
    ],
    "wof:name":"Custom Mill Work",
    "wof:placetype":"venue"
},
  "geometry": {"coordinates":[-83.415907,42.812239],"type":"Point"}
}