{
  "type": "Feature",
  "properties": {
    "iso:country":"US",
    "sg:address":"25430 Portage Entry Rd",
    "sg:city":"Chassell",
    "sg:classifiers":[
        {
            "category":"Retail",
            "subcategory":"Veterinary Services",
            "type":"Services"
        }
    ],
    "sg:phone":"+1 906 523 4293",
    "sg:postcode":"49916",
    "sg:province":"MI",
    "wof:name":"Sprague Animal Clinic",
    "wof:placetype":"venue"
},
  "geometry": {"coordinates":[-88.46940499999999,46.982248],"type":"Point"}
}