{
  "type": "Feature",
  "properties": {
    "iso:country":"US",
    "sg:address":"45245 W 10 Mile Rd",
    "sg:city":"Novi",
    "sg:classifiers":[
        {
            "category":"Education",
            "subcategory":"Library",
            "type":"Public Place"
        }
    ],
    "sg:phone":"+1 248 349 0720",
    "sg:postcode":"48375",
    "sg:province":"MI",
    "wof:name":"Novi Public Library",
    "wof:placetype":"venue"
},
  "geometry": {"coordinates":[-83.49305200000001,42.465993],"type":"Point"}
}