{
  "type": "Feature",
  "properties": {
    "iso:country":"US",
    "sg:address":"749 Grand River Dr NE",
    "sg:city":"Ada",
    "sg:classifiers":[
        {
            "category":"Building & Trades",
            "subcategory":"Construction",
            "type":"Services"
        }
    ],
    "sg:phone":"+1 616 575 7522",
    "sg:postcode":"49301",
    "sg:province":"MI",
    "sg:tags":[
        "designer"
    ],
    "sg:website":"www.designren.com",
    "wof:name":"Design Renaissance",
    "wof:placetype":"venue"
},
  "geometry": {"coordinates":[-85.533801,42.977838],"type":"Point"}
}