{
  "type": "Feature",
  "properties": {
    "iso:country":"US",
    "sg:address":"4017 Pebble Ridge Ct",
    "sg:city":"Fenton",
    "sg:classifiers":[
        {
            "category":"Professional",
            "type":"Services"
        }
    ],
    "sg:phone":"+1 810 714 9443",
    "sg:postcode":"48430",
    "sg:province":"MI",
    "sg:tags":[
        "establishment"
    ],
    "wof:name":"Above A Cut",
    "wof:placetype":"venue"
},
  "geometry": {"coordinates":[-83.746664,42.791592],"type":"Point"}
}