{
  "type": "Feature",
  "properties": {
    "iso:country":"US",
    "sg:address":"10421 Douglas Ave",
    "sg:city":"Plainwell",
    "sg:classifiers":[
        {
            "category":"Wholesale",
            "subcategory":"Groceries",
            "type":"Manufacturing & Wholesale Goods"
        }
    ],
    "sg:phone":"+1 269 685 8889",
    "sg:postcode":"49080",
    "sg:province":"MI",
    "sg:tags":[
        "food",
        "product"
    ],
    "wof:name":"Troyer Foods",
    "wof:placetype":"venue"
},
  "geometry": {"coordinates":[-85.620757,42.41224],"type":"Point"}
}