{
  "type": "Feature",
  "properties": {
    "iso:country":"US",
    "sg:address":"2475 Cedar Lake Rd SE",
    "sg:city":"Stanton",
    "sg:classifiers":[
        {
            "category":"Health Services",
            "subcategory":"Doctor",
            "type":"Services"
        }
    ],
    "sg:phone":"+1 989 261 4230",
    "sg:postcode":"48888",
    "sg:province":"MI",
    "sg:tags":[
        "clinic"
    ],
    "wof:name":"Michigan Medical Laser Sltns",
    "wof:placetype":"venue"
},
  "geometry": {"coordinates":[-84.984151,43.257497],"type":"Point"}
}