{
  "type": "Feature",
  "properties": {
    "iso:country":"US",
    "sg:address":"4206 Metcalf Rd",
    "sg:city":"Burtchville",
    "sg:classifiers":[
        {
            "category":"Banks & Credit Unions",
            "subcategory":"Investment Brokerage",
            "type":"Services"
        }
    ],
    "sg:phone":"+1 810 385 4318",
    "sg:postcode":"48059",
    "sg:province":"MI",
    "wof:name":"Blue Water Investments & Mgt",
    "wof:placetype":"venue"
},
  "geometry": {"coordinates":[-82.509685,43.082199],"type":"Point"}
}