{
  "type": "Feature",
  "properties": {
    "iso:country":"US",
    "sg:address":"230 Huron Ave",
    "sg:city":"Port Huron",
    "sg:classifiers":[
        {
            "category":"Government",
            "subcategory":"Office",
            "type":"Public Place"
        }
    ],
    "sg:phone":"+1 810 985 9440",
    "sg:postcode":"48060",
    "sg:province":"MI",
    "sg:tags":[
        "county",
        "program",
        "health"
    ],
    "wof:name":"St Clair Cty Mental Health",
    "wof:placetype":"venue"
},
  "geometry": {"coordinates":[-82.424133,42.977046],"type":"Point"}
}