{
  "type": "Feature",
  "properties": {
    "iso:country":"US",
    "sg:address":"5400 N Eastman Rd",
    "sg:city":"Midland",
    "sg:classifiers":[
        {
            "category":"Professional",
            "subcategory":"Business Services",
            "type":"Services"
        }
    ],
    "sg:phone":"+1 989 839 4445",
    "sg:postcode":"48642",
    "sg:province":"MI",
    "wof:name":"Midmichigan Transciption Svcs",
    "wof:placetype":"venue"
},
  "geometry": {"coordinates":[-84.246775,43.761589],"type":"Point"}
}