{
  "type": "Feature",
  "properties": {
    "iso:country":"US",
    "sg:address":"2270 Traversefield Dr",
    "sg:city":"Traverse City",
    "sg:classifiers":[
        {
            "category":"Manufacturing",
            "subcategory":"Metals",
            "type":"Manufacturing & Wholesale Goods"
        }
    ],
    "sg:phone":"+1 231 922 9500",
    "sg:postcode":"49686",
    "sg:province":"MI",
    "sg:tags":[
        "machine",
        "screw",
        "product"
    ],
    "wof:name":"Federal Screw Works",
    "wof:placetype":"venue"
},
  "geometry": {"coordinates":[-85.587444,44.716255],"type":"Point"}
}