{
  "type": "Feature",
  "properties": {
    "iso:country":"US",
    "sg:address":"1400 E Maple Rd",
    "sg:city":"Birmingham",
    "sg:classifiers":[
        {
            "category":"Building & Trades",
            "subcategory":"Construction",
            "type":"Services"
        }
    ],
    "sg:phone":"+1 248 647 3640",
    "sg:postcode":"48009",
    "sg:province":"MI",
    "sg:tags":[
        "interior",
        "design"
    ],
    "wof:name":"Woodbury Design Group",
    "wof:placetype":"venue"
},
  "geometry": {"coordinates":[-83.202202,42.546902],"type":"Point"}
}