{
  "type": "Feature",
  "properties": {
    "iso:country":"US",
    "sg:address":"98 Ottawa Ave NW",
    "sg:city":"Grand Rapids",
    "sg:classifiers":[
        {
            "category":"Real Estate",
            "subcategory":"Real Estate Agent",
            "type":"Services"
        }
    ],
    "sg:phone":"+1 616 456 7114",
    "sg:postcode":"49503",
    "sg:province":"MI",
    "wof:name":"Ben M Muller Realty Co",
    "wof:placetype":"venue"
},
  "geometry": {"coordinates":[-85.67008199999999,42.965237],"type":"Point"}
}