{
  "type": "Feature",
  "properties": {
    "iso:country":"US",
    "sg:address":"137 N Park St",
    "sg:city":"Kalamazoo",
    "sg:classifiers":[
        {
            "category":"Professional",
            "subcategory":"Lawyer & Legal Services",
            "type":"Services"
        }
    ],
    "sg:phone":"+1 269 349 6808",
    "sg:postcode":"49007",
    "sg:province":"MI",
    "sg:tags":[
        "attorney",
        "law",
        "adoption"
    ],
    "sg:website":"http://www.rathertlaw.com",
    "wof:name":"Rathert Law Offices",
    "wof:placetype":"venue"
},
  "geometry": {"coordinates":[-85.58729599999999,42.291945],"type":"Point"}
}