{
  "type": "Feature",
  "properties": {
    "iso:country":"US",
    "sg:address":"17529 US Hwy 223",
    "sg:city":"Addison",
    "sg:classifiers":[
        {
            "category":"Organizations",
            "subcategory":"Religious Organization",
            "type":"Services"
        }
    ],
    "sg:phone":"+1 517 547 5155",
    "sg:postcode":"49220",
    "sg:province":"MI",
    "sg:tags":[
        "church"
    ],
    "wof:name":"New Life Baptist Church",
    "wof:placetype":"venue"
},
  "geometry": {"coordinates":[-84.334785,42.029029],"type":"Point"}
}