{
  "type": "Feature",
  "properties": {
    "iso:country":"US",
    "sg:address":"245 State St SE",
    "sg:city":"Grand Rapids",
    "sg:classifiers":[
        {
            "category":"Organizations",
            "subcategory":"Non-profit Organization",
            "type":"Services"
        }
    ],
    "sg:phone":"+1 616 233 7510",
    "sg:postcode":"49503",
    "sg:province":"MI",
    "sg:tags":[
        "human"
    ],
    "wof:name":"Moka Corp",
    "wof:placetype":"venue"
},
  "geometry": {"coordinates":[-85.661753,42.960539],"type":"Point"}
}