{
  "type": "Feature",
  "properties": {
    "iso:country":"US",
    "sg:address":"24714 5 Mile Rd",
    "sg:city":"Redford",
    "sg:classifiers":[
        {
            "category":"Food & Beverages",
            "subcategory":"Liquor & Beverages",
            "type":"Retail Goods"
        }
    ],
    "sg:phone":"+1 313 538 6533",
    "sg:postcode":"48239",
    "sg:province":"MI",
    "sg:tags":[
        "beer",
        "spirit",
        "wine"
    ],
    "wof:name":"Heather's Liquor Land",
    "wof:placetype":"venue"
},
  "geometry": {"coordinates":[-83.283609,42.400013],"type":"Point"}
}