{
  "type": "Feature",
  "properties": {
    "iso:country":"US",
    "sg:address":"112 S Lowell St",
    "sg:city":"Ironwood",
    "sg:classifiers":[
        {
            "category":"Bars & Pubs",
            "type":"Food & Drink"
        }
    ],
    "sg:phone":"+1 906 932 3667",
    "sg:postcode":"49938",
    "sg:province":"MI",
    "wof:name":"Brewster's Northwoods Bar",
    "wof:placetype":"venue"
},
  "geometry": {"coordinates":[-90.170585,46.454435],"type":"Point"}
}