{
  "type": "Feature",
  "properties": {
    "iso:country":"US",
    "sg:address":"15725 Black River Rd",
    "sg:city":"Ironwood",
    "sg:classifiers":[
        {
            "category":"Travel",
            "subcategory":"Campground",
            "type":"Entertainment"
        }
    ],
    "sg:phone":"+1 906 932 7250",
    "sg:postcode":"49938",
    "sg:province":"MI",
    "sg:tags":[
        "trailer"
    ],
    "wof:name":"Black River Harbour Campground",
    "wof:placetype":"venue"
},
  "geometry": {"coordinates":[-90.04931500000001,46.654374],"type":"Point"}
}