{
  "type": "Feature",
  "properties": {
    "iso:country":"US",
    "sg:address":"868 N Carney Dr",
    "sg:city":"St Clair",
    "sg:classifiers":[
        {
            "category":"Health Services",
            "subcategory":"Nursing And Care Facility",
            "type":"Services"
        }
    ],
    "sg:phone":"+1 810 326 1688",
    "sg:postcode":"48079",
    "sg:province":"MI",
    "sg:tags":[
        "home",
        "rest"
    ],
    "wof:name":"Visions AFC",
    "wof:placetype":"venue"
},
  "geometry": {"coordinates":[-82.50259,42.830731],"type":"Point"}
}