{
  "type": "Feature",
  "properties": {
    "iso:country":"US",
    "sg:address":"32932 Warren Rd",
    "sg:city":"Westland",
    "sg:classifiers":[
        {
            "category":"Health Services",
            "subcategory":"Health Practitioner",
            "type":"Services"
        }
    ],
    "sg:phone":"+1 313 562 2800",
    "sg:postcode":"48185",
    "sg:province":"MI",
    "sg:tags":[
        "psychological",
        "therapy"
    ],
    "wof:name":"Insight",
    "wof:placetype":"venue"
},
  "geometry": {"coordinates":[-83.36441000000001,42.33944],"type":"Point"}
}