{
  "type": "Feature",
  "properties": {
    "iso:country":"US",
    "sg:address":"7494 Division Ave S",
    "sg:city":"Grand Rapids",
    "sg:classifiers":[
        {
            "category":"Wholesale",
            "subcategory":"Electrical",
            "type":"Manufacturing & Wholesale Goods"
        }
    ],
    "sg:phone":"+1 616 942 6290",
    "sg:postcode":"49548",
    "sg:province":"MI",
    "sg:tags":[
        "sound",
        "equipment",
        "system"
    ],
    "sg:website":"www.icommusa.com",
    "wof:name":"I.COM",
    "wof:placetype":"venue"
},
  "geometry": {"coordinates":[-85.663522,42.828347],"type":"Point"}
}