{
  "type": "Feature",
  "properties": {
    "iso:country":"US",
    "sg:address":"7687 N 6th St",
    "sg:city":"Kalamazoo",
    "sg:classifiers":[
        {
            "category":"Manufacturing",
            "subcategory":"Tools & Machinery",
            "type":"Manufacturing & Wholesale Goods"
        }
    ],
    "sg:phone":"+1 269 385 0006",
    "sg:postcode":"49009",
    "sg:province":"MI",
    "sg:tags":[
        "equipment",
        "conveyor",
        "conveying"
    ],
    "wof:name":"Dynamet Inc",
    "wof:placetype":"venue"
},
  "geometry": {"coordinates":[-85.707694,42.37004],"type":"Point"}
}