{
  "type": "Feature",
  "properties": {
    "iso:country":"US",
    "sg:address":"142 E 2nd St",
    "sg:city":"Flint",
    "sg:classifiers":[
        {
            "category":"Professional",
            "subcategory":"Lawyer & Legal Services",
            "type":"Services"
        }
    ],
    "sg:phone":"+1 810 234 3666",
    "sg:postcode":"48502",
    "sg:province":"MI",
    "wof:name":"Hamo George R & Associates",
    "wof:placetype":"venue"
},
  "geometry": {"coordinates":[-83.688698,43.0154],"type":"Point"}
}