{
  "type": "Feature",
  "properties": {
    "iso:country":"US",
    "sg:address":"3914 N Mission Rd",
    "sg:city":"Rosebush",
    "sg:classifiers":[
        {
            "category":"Organizations",
            "subcategory":"Religious Organization",
            "type":"Services"
        }
    ],
    "sg:phone":"+1 989 433 5492",
    "sg:postcode":"48878",
    "sg:province":"MI",
    "sg:tags":[
        "church"
    ],
    "wof:name":"Rosebush Presbyterian Church",
    "wof:placetype":"venue"
},
  "geometry": {"coordinates":[-84.76781800000001,43.696281],"type":"Point"}
}