{
  "type": "Feature",
  "properties": {
    "iso:country":"US",
    "sg:address":"700 Mall Dr",
    "sg:city":"Portage",
    "sg:classifiers":[
        {
            "category":"Health Services",
            "subcategory":"Doctor",
            "type":"Services"
        }
    ],
    "sg:phone":"+1 269 329 3034",
    "sg:postcode":"49024",
    "sg:province":"MI",
    "sg:tags":[
        "dentist"
    ],
    "wof:name":"Linda Hubbard Dds",
    "wof:placetype":"venue"
},
  "geometry": {"coordinates":[-85.59652199999999,42.224615],"type":"Point"}
}