{
  "type": "Feature",
  "properties": {
    "iso:country":"US",
    "sg:address":"47138 52nd St",
    "sg:city":"Lawrence",
    "sg:classifiers":[
        {
            "category":"Retail",
            "subcategory":"Animal Services",
            "type":"Services"
        }
    ],
    "sg:phone":"+1 269 674 8072",
    "sg:postcode":"49064",
    "sg:province":"MI",
    "sg:tags":[
        "horse",
        "training"
    ],
    "wof:name":"Cedar Lodge Stables",
    "wof:placetype":"venue"
},
  "geometry": {"coordinates":[-86.052026,42.246896],"type":"Point"}
}