{
  "type": "Feature",
  "properties": {
    "iso:country":"US",
    "sg:address":"5388 Lauren Ct",
    "sg:city":"Bloomfield Hills",
    "sg:classifiers":[
        {
            "category":"Building & Trades",
            "subcategory":"Construction",
            "type":"Services"
        }
    ],
    "sg:phone":"+1 248 593 6949",
    "sg:postcode":"48302",
    "sg:province":"MI",
    "sg:tags":[
        "contractor"
    ],
    "wof:name":"Alshab Construction Group Llc",
    "wof:placetype":"venue"
},
  "geometry": {"coordinates":[-83.267066,42.560328],"type":"Point"}
}