{
  "type": "Feature",
  "properties": {
    "iso:country":"US",
    "sg:address":"2910 Harrington Rd",
    "sg:city":"Rochester",
    "sg:classifiers":[
        {
            "category":"Wholesale",
            "subcategory":"Non-durable Goods",
            "type":"Manufacturing & Wholesale Goods"
        }
    ],
    "sg:phone":"+1 248 852 5587",
    "sg:postcode":"48307",
    "sg:province":"MI",
    "sg:tags":[
        "advertising",
        "specialty"
    ],
    "wof:name":"PR Marketing",
    "wof:placetype":"venue"
},
  "geometry": {"coordinates":[-83.144386,42.6412],"type":"Point"}
}