{
  "type": "Feature",
  "properties": {
    "iso:country":"US",
    "sg:address":"5748 Clarkston Rd",
    "sg:city":"Clarkston",
    "sg:classifiers":[
        {
            "category":"Shopping",
            "subcategory":"Gifts & Souvenirs",
            "type":"Retail Goods"
        }
    ],
    "sg:phone":"+1 248 922 3196",
    "sg:postcode":"48348",
    "sg:province":"MI",
    "sg:tags":[
        "party",
        "supply"
    ],
    "wof:name":"Sashabaw Market Square",
    "wof:placetype":"venue"
},
  "geometry": {"coordinates":[-83.370469,42.752126],"type":"Point"}
}