{
  "type": "Feature",
  "properties": {
    "iso:country":"US",
    "sg:address":"23616 Farmington Rd",
    "sg:city":"Farmington",
    "sg:classifiers":[
        {
            "category":"Shopping",
            "subcategory":"Gifts & Souvenirs",
            "type":"Retail Goods"
        }
    ],
    "sg:phone":"+1 248 474 4690",
    "sg:postcode":"48336",
    "sg:province":"MI",
    "sg:tags":[
        "shop"
    ],
    "wof:name":"Victorian Lace Elegance Crmcs",
    "wof:placetype":"venue"
},
  "geometry": {"coordinates":[-83.376379,42.464666],"type":"Point"}
}