{
  "type": "Feature",
  "properties": {
    "iso:country":"US",
    "sg:address":"31702 Mound Rd",
    "sg:city":"Warren",
    "sg:classifiers":[
        {
            "category":"Sports & Exercise",
            "subcategory":"Bicycle Rental",
            "type":"Entertainment"
        },
        {
            "category":"Sports & Exercise",
            "subcategory":"Gym",
            "type":"Entertainment"
        }
    ],
    "sg:phone":"+1 586 795 3488",
    "sg:postcode":"48092",
    "sg:province":"MI",
    "sg:tags":[
        "trainer",
        "wear"
    ],
    "sg:website":"www.tgmfitness.com",
    "wof:name":"Tgm Fitness",
    "wof:placetype":"venue"
},
  "geometry": {"coordinates":[-83.047147,42.526358],"type":"Point"}
}