{
  "type": "Feature",
  "properties": {
    "iso:country":"US",
    "sg:address":"905 E King St",
    "sg:city":"Owosso",
    "sg:classifiers":[
        {
            "category":"Retail",
            "subcategory":"Repair Shop",
            "type":"Services"
        }
    ],
    "sg:phone":"+1 989 725 2991",
    "sg:postcode":"48867",
    "sg:province":"MI",
    "sg:tags":[
        "sporting"
    ],
    "wof:name":"Jims Sharpening Service Inc",
    "wof:placetype":"venue"
},
  "geometry": {"coordinates":[-84.158849,43.004957],"type":"Point"}
}