{
  "type": "Feature",
  "properties": {
    "iso:country":"US",
    "sg:address":"1221 W Washington St",
    "sg:city":"Marquette",
    "sg:classifiers":[
        {
            "category":"Home & Garden",
            "subcategory":"Building Materials",
            "type":"Retail Goods"
        }
    ],
    "sg:phone":"+1 906 226 1491",
    "sg:postcode":"49855",
    "sg:province":"MI",
    "sg:tags":[
        "windows"
    ],
    "sg:website":"www.vinyl-windows.com",
    "wof:name":"Superiorland Vinyl Windows",
    "wof:placetype":"venue"
},
  "geometry": {"coordinates":[-87.42103400000001,46.545915],"type":"Point"}
}