{
  "type": "Feature",
  "properties": {
    "iso:country":"US",
    "sg:address":"50651 Garret Rd",
    "sg:city":"Dowagiac",
    "sg:classifiers":[
        {
            "category":"Manufacturing",
            "subcategory":"Retail Goods",
            "type":"Manufacturing & Wholesale Goods"
        }
    ],
    "sg:phone":"+1 269 424 5732",
    "sg:postcode":"49047",
    "sg:province":"MI",
    "sg:tags":[
        "product",
        "mfg"
    ],
    "wof:name":"Peninsula Mfg LLC",
    "wof:placetype":"venue"
},
  "geometry": {"coordinates":[-86.191744,42.05844],"type":"Point"}
}