{
  "type": "Feature",
  "properties": {
    "iso:country":"US",
    "sg:address":"9335 Telegraph Rd",
    "sg:city":"Redford",
    "sg:classifiers":[
        {
            "category":"Personal",
            "subcategory":"Nail Salon",
            "type":"Services"
        }
    ],
    "sg:phone":"+1 313 541 9218",
    "sg:postcode":"48239",
    "sg:province":"MI",
    "wof:name":"Central Nails",
    "wof:placetype":"venue"
},
  "geometry": {"coordinates":[-83.275803,42.3634],"type":"Point"}
}