{
  "type": "Feature",
  "properties": {
    "iso:country":"US",
    "sg:address":"902 2nd St",
    "sg:city":"Menominee",
    "sg:classifiers":[
        {
            "category":"Shopping",
            "subcategory":"Used Merchandise",
            "type":"Retail Goods"
        }
    ],
    "sg:phone":"+1 906 864 2412",
    "sg:postcode":"49858",
    "sg:province":"MI",
    "sg:tags":[
        "antique"
    ],
    "wof:name":"Timeless Treasures",
    "wof:placetype":"venue"
},
  "geometry": {"coordinates":[-87.606129,45.107619],"type":"Point"}
}