{
  "type": "Feature",
  "properties": {
    "iso:country":"US",
    "sg:address":"2667 Oxford Dr",
    "sg:city":"Troy",
    "sg:classifiers":[
        {
            "category":"Education",
            "subcategory":"School",
            "type":"Public Place"
        }
    ],
    "sg:phone":"+1 248 647 5754",
    "sg:postcode":"48084",
    "sg:province":"MI",
    "wof:name":"Independent Christian Educ",
    "wof:placetype":"venue"
},
  "geometry": {"coordinates":[-83.19798400000001,42.573916],"type":"Point"}
}