{
  "type": "Feature",
  "properties": {
    "iso:country":"US",
    "sg:address":"7560 Leyton Dr SE",
    "sg:city":"Ada",
    "sg:classifiers":[
        {
            "category":"Building & Trades",
            "subcategory":"Construction",
            "type":"Services"
        }
    ],
    "sg:phone":"+1 616 940 0804",
    "sg:postcode":"49301",
    "sg:province":"MI",
    "sg:tags":[
        "hanging",
        "contractor"
    ],
    "wof:name":"Maple Leaf Painting Inc",
    "wof:placetype":"venue"
},
  "geometry": {"coordinates":[-85.481195,42.90675],"type":"Point"}
}