{
  "type": "Feature",
  "properties": {
    "iso:country":"US",
    "sg:address":"2868 Fox Hill Dr",
    "sg:city":"Sterling Heights",
    "sg:classifiers":[
        {
            "category":"Wholesale",
            "subcategory":"Scrap",
            "type":"Manufacturing & Wholesale Goods"
        }
    ],
    "sg:phone":"+1 586 826 8547",
    "sg:postcode":"48310",
    "sg:province":"MI",
    "sg:tags":[
        "metal",
        "iron"
    ],
    "wof:name":"G & M Metal",
    "wof:placetype":"venue"
},
  "geometry": {"coordinates":[-83.08094,42.570939],"type":"Point"}
}