{
  "type": "Feature",
  "properties": {
    "iso:country":"US",
    "sg:address":"110 N Verlinden Ave",
    "sg:city":"Lansing",
    "sg:classifiers":[
        {
            "category":"Building & Trades",
            "subcategory":"Plumbing",
            "type":"Services"
        }
    ],
    "sg:phone":"+1 517 485 4329",
    "sg:postcode":"48915",
    "sg:province":"MI",
    "sg:tags":[
        "conditioning",
        "air",
        "system",
        "contractor"
    ],
    "wof:name":"A A Plus Heating & Cooling",
    "wof:placetype":"venue"
},
  "geometry": {"coordinates":[-84.577056,42.734607],"type":"Point"}
}