{
  "type": "Feature",
  "properties": {
    "iso:country":"US",
    "sg:address":"1627 Hunters Ridge Dr",
    "sg:city":"Bloomfield Hills",
    "sg:classifiers":[
        {
            "category":"Building & Trades",
            "subcategory":"Construction",
            "type":"Services"
        }
    ],
    "sg:phone":"+1 248 334 1427",
    "sg:postcode":"48304",
    "sg:province":"MI",
    "sg:tags":[
        "house"
    ],
    "wof:name":"Pett Projects",
    "wof:placetype":"venue"
},
  "geometry": {"coordinates":[-83.239566,42.618083],"type":"Point"}
}