{
  "type": "Feature",
  "properties": {
    "iso:country":"US",
    "sg:address":"4677 S Harvey St",
    "sg:city":"Muskegon",
    "sg:classifiers":[
        {
            "category":"Travel",
            "subcategory":"Hotels & Motels",
            "type":"Entertainment"
        }
    ],
    "sg:phone":"+1 231 798 0220",
    "sg:postcode":"49444",
    "sg:province":"MI",
    "sg:tags":[
        "operations"
    ],
    "wof:name":"Amerihost Inn Muskegon",
    "wof:placetype":"venue"
},
  "geometry": {"coordinates":[-86.20568799999999,43.162873],"type":"Point"}
}