{
  "type": "Feature",
  "properties": {
    "iso:country":"US",
    "sg:address":"3722 56th St",
    "sg:city":"Hamilton",
    "sg:classifiers":[
        {
            "category":"Retail",
            "subcategory":"Auto Repair",
            "type":"Services"
        }
    ],
    "sg:phone":"+1 269 751 5644",
    "sg:postcode":"49419",
    "sg:province":"MI",
    "sg:tags":[
        "body"
    ],
    "wof:name":"Zoerhofs Body Shop",
    "wof:placetype":"venue"
},
  "geometry": {"coordinates":[-86.093332,42.683185],"type":"Point"}
}