{
  "type": "Feature",
  "properties": {
    "iso:country":"US",
    "sg:address":"119 S Main St",
    "sg:city":"Eaton Rapids",
    "sg:classifiers":[
        {
            "category":"Shopping",
            "subcategory":"Bicycles & Sporting Goods",
            "type":"Retail Goods"
        }
    ],
    "sg:phone":"+1 517 663 5170",
    "sg:postcode":"48827",
    "sg:province":"MI",
    "sg:tags":[
        "bait",
        "fishing"
    ],
    "wof:name":"Hunt & Hook",
    "wof:placetype":"venue"
},
  "geometry": {"coordinates":[-84.655627,42.512599],"type":"Point"}
}