{
  "type": "Feature",
  "properties": {
    "iso:country":"US",
    "sg:address":"37586 Fiore Trl",
    "sg:city":"Clinton Township",
    "sg:classifiers":[
        {
            "category":"Professional",
            "subcategory":"Business Services",
            "type":"Services"
        }
    ],
    "sg:phone":"+1 586 263 8198",
    "sg:postcode":"48036",
    "sg:province":"MI",
    "wof:name":"Extreme Interiors Inc",
    "wof:placetype":"venue"
},
  "geometry": {"coordinates":[-82.941266,42.573192],"type":"Point"}
}