{
  "type": "Feature",
  "properties": {
    "iso:country":"US",
    "sg:address":"10738 88th Ave",
    "sg:city":"Zeeland",
    "sg:classifiers":[
        {
            "category":"Farming",
            "subcategory":"Nursery",
            "type":"Manufacturing & Wholesale Goods"
        }
    ],
    "sg:phone":"+1 616 895 4898",
    "sg:postcode":"49464",
    "sg:province":"MI",
    "sg:tags":[
        "greenhouse"
    ],
    "wof:name":"Zysk's Farm & Greenhouse",
    "wof:placetype":"venue"
},
  "geometry": {"coordinates":[-86.003271,42.964449],"type":"Point"}
}