{
  "type": "Feature",
  "properties": {
    "iso:country":"US",
    "sg:address":"10603 Grand River Rd",
    "sg:city":"Brighton",
    "sg:classifiers":[
        {
            "category":"Building & Trades",
            "subcategory":"Construction",
            "type":"Services"
        }
    ],
    "sg:phone":"+1 810 227 1824",
    "sg:postcode":"48116",
    "sg:province":"MI",
    "sg:tags":[
        "planning",
        "remodeling",
        "kitchen"
    ],
    "wof:name":"J & J Laminate Connection",
    "wof:placetype":"venue"
},
  "geometry": {"coordinates":[-83.741355,42.517053],"type":"Point"}
}