{
  "type": "Feature",
  "properties": {
    "iso:country":"US",
    "sg:address":"300 Galleria Officentre",
    "sg:city":"Southfield",
    "sg:classifiers":[
        {
            "category":"Wholesale",
            "subcategory":"Auto Parts",
            "type":"Manufacturing & Wholesale Goods"
        }
    ],
    "sg:phone":"+1 248 356 0800",
    "sg:postcode":"48034",
    "sg:province":"MI",
    "sg:tags":[
        "automotive",
        "lighting"
    ],
    "wof:name":"Vehicle Lighting Corp",
    "wof:placetype":"venue"
},
  "geometry": {"coordinates":[-83.29182,42.499434],"type":"Point"}
}