{
  "type": "Feature",
  "properties": {
    "iso:country":"US",
    "sg:address":"25922 Van Dyke Ave",
    "sg:city":"Center Line",
    "sg:classifiers":[
        {
            "category":"Wholesale",
            "subcategory":"Electrical",
            "type":"Manufacturing & Wholesale Goods"
        }
    ],
    "sg:phone":"+1 586 758 3520",
    "sg:postcode":"48015",
    "sg:province":"MI",
    "sg:tags":[
        "light",
        "tube",
        "fixture",
        "equipment",
        "lighting",
        "bulb"
    ],
    "wof:name":"General Distributors",
    "wof:placetype":"venue"
},
  "geometry": {"coordinates":[-83.02739699999999,42.4846],"type":"Point"}
}