{
  "type": "Feature",
  "properties": {
    "iso:country":"US",
    "sg:address":"32180 Linderman Ave",
    "sg:city":"Warren",
    "sg:classifiers":[
        {
            "category":"Building & Trades",
            "subcategory":"Construction",
            "type":"Services"
        }
    ],
    "sg:phone":"+1 586 939 2044",
    "sg:postcode":"48093",
    "sg:province":"MI",
    "sg:tags":[
        "hanging",
        "contractor"
    ],
    "wof:name":"B&Z Professional Painting Co",
    "wof:placetype":"venue"
},
  "geometry": {"coordinates":[-83.026768,42.529367],"type":"Point"}
}