{
  "type": "Feature",
  "properties": {
    "iso:country":"US",
    "sg:address":"736 W Park St",
    "sg:city":"Lapeer",
    "sg:classifiers":[
        {
            "category":"Professional",
            "subcategory":"Art Services",
            "type":"Services"
        }
    ],
    "sg:phone":"+1 810 338 1814",
    "sg:postcode":"48446",
    "sg:province":"MI",
    "sg:tags":[
        "commercial",
        "design"
    ],
    "wof:name":"Metrographics Inc",
    "wof:placetype":"venue"
},
  "geometry": {"coordinates":[-83.316175,43.054091],"type":"Point"}
}