{
  "type": "Feature",
  "properties": {
    "iso:country":"US",
    "sg:address":"8033 E 10 Mile Rd Apt 716",
    "sg:city":"Center Line",
    "sg:classifiers":[
        {
            "category":"Real Estate",
            "subcategory":"Real Estate Operator",
            "type":"Services"
        }
    ],
    "sg:phone":"+1 586 755 2270",
    "sg:postcode":"48015",
    "sg:province":"MI",
    "sg:tags":[
        "apartment"
    ],
    "wof:name":"Center Line Park Tower",
    "wof:placetype":"venue"
},
  "geometry": {"coordinates":[-83.023804,42.478901],"type":"Point"}
}