{
  "type": "Feature",
  "properties": {
    "iso:country":"US",
    "sg:address":"42830 Mound Rd",
    "sg:city":"Sterling Heights",
    "sg:classifiers":[
        {
            "category":"Shopping",
            "type":"Retail Goods"
        }
    ],
    "sg:phone":"+1 586 739 4999",
    "sg:postcode":"48314",
    "sg:province":"MI",
    "sg:tags":[
        "trophy",
        "medal",
        "award"
    ],
    "wof:name":"Creative Awards",
    "wof:placetype":"venue"
},
  "geometry": {"coordinates":[-83.051039,42.608409],"type":"Point"}
}