{
  "type": "Feature",
  "properties": {
    "iso:country":"US",
    "sg:address":"700 Washington Ave",
    "sg:city":"Grand Haven",
    "sg:classifiers":[
        {
            "category":"Food & Beverages",
            "subcategory":"Specialty",
            "type":"Retail Goods"
        }
    ],
    "sg:phone":"+1 616 846 3026",
    "sg:postcode":"49417",
    "sg:province":"MI",
    "sg:tags":[
        "health",
        "diet"
    ],
    "wof:name":"Health Hutt",
    "wof:placetype":"venue"
},
  "geometry": {"coordinates":[-86.221418,43.061091],"type":"Point"}
}