{
  "type": "Feature",
  "properties": {
    "iso:country":"US",
    "sg:address":"20849 Capital Ave NE",
    "sg:city":"Battle Creek",
    "sg:classifiers":[
        {
            "category":"Retail",
            "subcategory":"Veterinary Services",
            "type":"Services"
        }
    ],
    "sg:phone":"+1 269 964 0966",
    "sg:postcode":"49017",
    "sg:province":"MI",
    "sg:tags":[
        "veterinarian"
    ],
    "sg:website":"www.pennfieldanimalhospital.com",
    "wof:name":"Pennfield Animal Hospital",
    "wof:placetype":"venue"
},
  "geometry": {"coordinates":[-85.14210799999999,42.375555],"type":"Point"}
}