{
  "type": "Feature",
  "properties": {
    "iso:country":"US",
    "sg:address":"14245 Northland Dr",
    "sg:city":"Big Rapids",
    "sg:classifiers":[
        {
            "category":"Health Services",
            "subcategory":"Clinic",
            "type":"Services"
        }
    ],
    "sg:phone":"+1 231 592 0922",
    "sg:postcode":"49307",
    "sg:province":"MI",
    "sg:tags":[
        "home"
    ],
    "wof:name":"Metron/Home Health Care",
    "wof:placetype":"venue"
},
  "geometry": {"coordinates":[-85.48344400000001,43.672247],"type":"Point"}
}