{
  "type": "Feature",
  "properties": {
    "iso:country":"US",
    "sg:address":"100 W Michigan Ave",
    "sg:city":"Kalamazoo",
    "sg:classifiers":[
        {
            "category":"Sports & Exercise",
            "subcategory":"Gym",
            "type":"Entertainment"
        }
    ],
    "sg:phone":"+1 269 226 3184",
    "sg:postcode":"49007",
    "sg:province":"MI",
    "sg:tags":[
        "club",
        "health",
        "studio",
        "gymnasium"
    ],
    "wof:name":"Fitness Works",
    "wof:placetype":"venue"
},
  "geometry": {"coordinates":[-85.58474699999999,42.291619],"type":"Point"}
}