{
  "type": "Feature",
  "properties": {
    "iso:country":"US",
    "sg:address":"2760 Patrick Henry St",
    "sg:city":"Auburn Hills",
    "sg:classifiers":[
        {
            "category":"Professional",
            "subcategory":"Management & Consulting",
            "type":"Services"
        }
    ],
    "sg:phone":"+1 248 373 8810",
    "sg:postcode":"48326",
    "sg:province":"MI",
    "wof:name":"David Leader Management",
    "wof:placetype":"venue"
},
  "geometry": {"coordinates":[-83.228168,42.684629],"type":"Point"}
}