{
  "type": "Feature",
  "properties": {
    "iso:country":"US",
    "sg:address":"300 Race St",
    "sg:city":"Coldwater",
    "sg:classifiers":[
        {
            "category":"Manufacturing",
            "subcategory":"Tools & Machinery",
            "type":"Manufacturing & Wholesale Goods"
        }
    ],
    "sg:phone":"+1 517 279 7538",
    "sg:postcode":"49036",
    "sg:province":"MI",
    "sg:tags":[
        "machine",
        "shop"
    ],
    "wof:name":"Coldwater Products",
    "wof:placetype":"venue"
},
  "geometry": {"coordinates":[-85.014994,41.935618],"type":"Point"}
}