{
  "type": "Feature",
  "properties": {
    "iso:country":"US",
    "sg:address":"700 Barclay Ct",
    "sg:city":"Ann Arbor",
    "sg:classifiers":[
        {
            "category":"Professional",
            "subcategory":"Management & Consulting",
            "type":"Services"
        }
    ],
    "sg:phone":"+1 734 769 1447",
    "sg:postcode":"48105",
    "sg:province":"MI",
    "wof:name":"Cap International",
    "wof:placetype":"venue"
},
  "geometry": {"coordinates":[-83.69143,42.285067],"type":"Point"}
}