{
  "type": "Feature",
  "properties": {
    "iso:country":"US",
    "sg:address":"4293 Partridge Ln",
    "sg:city":"Newport",
    "sg:classifiers":[
        {
            "category":"Professional",
            "type":"Services"
        }
    ],
    "sg:phone":"+1 734 586 4007",
    "sg:postcode":"48166",
    "sg:province":"MI",
    "wof:name":"J D Grading",
    "wof:placetype":"venue"
},
  "geometry": {"coordinates":[-83.290871,41.989766],"type":"Point"}
}