{
  "type": "Feature",
  "properties": {
    "iso:country":"US",
    "sg:address":"309 E Lake St",
    "sg:city":"Tawas City",
    "sg:classifiers":[
        {
            "category":"Autos & Motor Vehicles",
            "subcategory":"Fuel & Gas Station",
            "type":"Retail Goods"
        }
    ],
    "sg:phone":"+1 989 362 3433",
    "sg:postcode":"48763",
    "sg:province":"MI",
    "sg:tags":[
        "oil"
    ],
    "wof:name":"Forward Corp",
    "wof:placetype":"venue"
},
  "geometry": {"coordinates":[-83.508144,44.274207],"type":"Point"}
}