{
  "type": "Feature",
  "properties": {
    "iso:country":"US",
    "sg:address":"101 S Saginaw St",
    "sg:city":"Holly",
    "sg:classifiers":[
        {
            "category":"Shopping",
            "subcategory":"Gifts & Souvenirs",
            "type":"Retail Goods"
        }
    ],
    "sg:phone":"+1 248 634 9380",
    "sg:postcode":"48442",
    "sg:province":"MI",
    "wof:name":"Abundance",
    "wof:placetype":"venue"
},
  "geometry": {"coordinates":[-83.627675,42.791906],"type":"Point"}
}