{
  "type": "Feature",
  "properties": {
    "iso:country":"US",
    "sg:address":"441 Cherry St SE",
    "sg:city":"Grand Rapids",
    "sg:classifiers":[
        {
            "category":"Personal",
            "subcategory":"Beauty Salon",
            "type":"Services"
        }
    ],
    "sg:phone":"+1 616 458 9622",
    "sg:postcode":"49503",
    "sg:province":"MI",
    "sg:tags":[
        "shop"
    ],
    "wof:name":"Stan and Company",
    "wof:placetype":"venue"
},
  "geometry": {"coordinates":[-85.656921,42.959417],"type":"Point"}
}