{
  "type": "Feature",
  "properties": {
    "iso:country":"US",
    "sg:address":"1562 E Pratt Rd",
    "sg:city":"Dewitt",
    "sg:phone":"+1 517 669 5787",
    "sg:postcode":"48820",
    "sg:province":"MI",
    "sg:tags":[
        "farm",
        "soybean"
    ],
    "wof:name":"Myron Grubaugh",
    "wof:placetype":"venue"
},
  "geometry": {"coordinates":[-84.558138,42.90015],"type":"Point"}
}