{
  "type": "Feature",
  "properties": {
    "iso:country":"US",
    "sg:address":"1118 W Lake St",
    "sg:city":"Tawas City",
    "sg:classifiers":[
        {
            "category":"Insurance",
            "subcategory":"Insurance Agent",
            "type":"Services"
        }
    ],
    "sg:phone":"+1 989 362 3261",
    "sg:postcode":"48763",
    "sg:province":"MI",
    "wof:name":"Tri County Agency",
    "wof:placetype":"venue"
},
  "geometry": {"coordinates":[-83.53595900000001,44.253846],"type":"Point"}
}