{
  "type": "Feature",
  "properties": {
    "iso:country":"US",
    "sg:address":"2900 Mackinac Trl",
    "sg:city":"St Ignace",
    "sg:classifiers":[
        {
            "category":"Professional",
            "type":"Services"
        }
    ],
    "sg:phone":"+1 906 643 7985",
    "sg:postcode":"49781",
    "sg:province":"MI",
    "sg:tags":[
        "establishment"
    ],
    "wof:name":"Fort Alogonquin",
    "wof:placetype":"venue"
},
  "geometry": {"coordinates":[-84.737737,45.904983],"type":"Point"}
}