{
  "type": "Feature",
  "properties": {
    "iso:country":"US",
    "sg:address":"1469 Fort St",
    "sg:city":"Wyandotte",
    "sg:classifiers":[
        {
            "category":"Professional",
            "subcategory":"Management & Consulting",
            "type":"Services"
        }
    ],
    "sg:phone":"+1 734 284 3700",
    "sg:postcode":"48183",
    "sg:province":"MI",
    "wof:name":"American Express",
    "wof:placetype":"venue"
},
  "geometry": {"coordinates":[-83.188428,42.165562],"type":"Point"}
}