{
  "type": "Feature",
  "properties": {
    "iso:country":"US",
    "sg:address":"4329 Duke St",
    "sg:city":"Kalamazoo",
    "sg:classifiers":[
        {
            "category":"Building & Trades",
            "subcategory":"Landscaping Services",
            "type":"Services"
        }
    ],
    "sg:phone":"+1 269 341 9099",
    "sg:postcode":"49008",
    "sg:province":"MI",
    "wof:name":"S & H Lawn Care",
    "wof:placetype":"venue"
},
  "geometry": {"coordinates":[-85.595054,42.245792],"type":"Point"}
}