{
  "type": "Feature",
  "properties": {
    "iso:country":"US",
    "sg:address":"50 Filer St",
    "sg:city":"Manistee",
    "sg:classifiers":[
        {
            "category":"Shopping",
            "type":"Retail Goods"
        }
    ],
    "sg:phone":"+1 231 723 0699",
    "sg:postcode":"49660",
    "sg:province":"MI",
    "sg:tags":[
        "hearing",
        "equipment",
        "supply",
        "impaired"
    ],
    "wof:name":"Beltone Hearing Aid Ctr",
    "wof:placetype":"venue"
},
  "geometry": {"coordinates":[-86.318927,44.247611],"type":"Point"}
}