{
  "type": "Feature",
  "properties": {
    "iso:country":"US",
    "sg:address":"203 E Main St",
    "sg:city":"Dewitt",
    "sg:classifiers":[
        {
            "category":"Health Services",
            "subcategory":"Doctor",
            "type":"Services"
        }
    ],
    "sg:phone":"+1 517 669 5833",
    "sg:postcode":"48820",
    "sg:province":"MI",
    "wof:name":"John B Faust DDS PC",
    "wof:placetype":"venue"
},
  "geometry": {"coordinates":[-84.566608,42.842277],"type":"Point"}
}