{
  "type": "Feature",
  "properties": {
    "iso:country":"US",
    "sg:address":"27222 Gloede Dr",
    "sg:city":"Warren",
    "sg:classifiers":[
        {
            "category":"Professional",
            "type":"Services"
        }
    ],
    "sg:phone":"+1 586 443 5513",
    "sg:postcode":"48088",
    "sg:province":"MI",
    "sg:tags":[
        "establishment"
    ],
    "wof:name":"JCI",
    "wof:placetype":"venue"
},
  "geometry": {"coordinates":[-82.972308,42.497277],"type":"Point"}
}