{
  "type": "Feature",
  "properties": {
    "iso:country":"US",
    "sg:address":"22483 Ennishore Dr",
    "sg:city":"Novi",
    "sg:classifiers":[
        {
            "category":"Professional",
            "subcategory":"Management & Consulting",
            "type":"Services"
        }
    ],
    "sg:phone":"+1 248 305 9339",
    "sg:postcode":"48375",
    "sg:province":"MI",
    "sg:tags":[
        "business"
    ],
    "wof:name":"Eddie Fossbakk Tor",
    "wof:placetype":"venue"
},
  "geometry": {"coordinates":[-83.46132799999999,42.454957],"type":"Point"}
}