{
  "type": "Feature",
  "properties": {
    "iso:country":"US",
    "sg:address":"200 Colrain St SW",
    "sg:city":"Grand Rapids",
    "sg:classifiers":[
        {
            "category":"Education",
            "subcategory":"Vocational School",
            "type":"Public Place"
        }
    ],
    "sg:phone":"+1 616 243 4898",
    "sg:postcode":"49548",
    "sg:province":"MI",
    "sg:tags":[
        "training",
        "computer"
    ],
    "wof:name":"Usereasy Technical Training",
    "wof:placetype":"venue"
},
  "geometry": {"coordinates":[-85.67294699999999,42.910664],"type":"Point"}
}