{
  "type": "Feature",
  "properties": {
    "iso:country":"US",
    "sg:address":"20780 Hugo St",
    "sg:city":"Farmington Hills",
    "sg:classifiers":[
        {
            "category":"Retail",
            "subcategory":"Animal Services",
            "type":"Services"
        }
    ],
    "sg:phone":"+1 248 474 4100",
    "sg:postcode":"48336",
    "sg:province":"MI",
    "sg:tags":[
        "pet",
        "training"
    ],
    "sg:website":"www.4-leggedfriendsdaycare.com",
    "wof:name":"Four-Legged Friends Daycare",
    "wof:placetype":"venue"
},
  "geometry": {"coordinates":[-83.364282,42.441208],"type":"Point"}
}