{
  "type": "Feature",
  "properties": {
    "iso:country":"US",
    "sg:address":"7180 County Farm Rd",
    "sg:city":"Parma",
    "sg:classifiers":[
        {
            "category":"Personal",
            "subcategory":"Beauty Salon",
            "type":"Services"
        }
    ],
    "sg:phone":"+1 517 784 9257",
    "sg:postcode":"49269",
    "sg:province":"MI",
    "sg:tags":[
        "shop"
    ],
    "wof:name":"Eileen's Country Coiffures",
    "wof:placetype":"venue"
},
  "geometry": {"coordinates":[-84.52237599999999,42.27665],"type":"Point"}
}