{
  "type": "Feature",
  "properties": {
    "iso:country":"US",
    "sg:address":"2601 W US Hwy 10",
    "sg:city":"Ludington",
    "sg:classifiers":[
        {
            "category":"Manufacturing",
            "subcategory":"Metals",
            "type":"Manufacturing & Wholesale Goods"
        }
    ],
    "sg:phone":"+1 231 843 4455",
    "sg:postcode":"49431",
    "sg:province":"MI",
    "sg:tags":[
        "scrap",
        "product"
    ],
    "wof:name":"Padnos Pere Marquette Div",
    "wof:placetype":"venue"
},
  "geometry": {"coordinates":[-86.347694,43.955576],"type":"Point"}
}