{
  "type": "Feature",
  "properties": {
    "iso:country":"US",
    "sg:address":"13677 Eureka Rd",
    "sg:city":"Southgate",
    "sg:classifiers":[
        {
            "category":"Shopping",
            "subcategory":"Hobbies, Toys, & Games",
            "type":"Retail Goods"
        },
        {
            "category":"Shopping",
            "subcategory":"Shoes",
            "type":"Retail Goods"
        }
    ],
    "sg:phone":"+1 734 246 5877",
    "sg:postcode":"48195",
    "sg:province":"MI",
    "sg:tags":[
        "toy",
        "store"
    ],
    "wof:name":"Anime To Skateboards",
    "wof:placetype":"venue"
},
  "geometry": {"coordinates":[-83.190648,42.199306],"type":"Point"}
}