{
  "type": "Feature",
  "properties": {
    "iso:country":"US",
    "sg:address":"6300 Kelly Dr",
    "sg:city":"Jackson",
    "sg:classifiers":[
        {
            "category":"Manufacturing",
            "subcategory":"Tools & Machinery",
            "type":"Manufacturing & Wholesale Goods"
        }
    ],
    "sg:phone":"+1 517 536 0325",
    "sg:postcode":"49201",
    "sg:province":"MI",
    "sg:tags":[
        "equipment",
        "screening",
        "sifting"
    ],
    "sg:website":"www.dandlequipment.com",
    "wof:name":"D & L Power Screen",
    "wof:placetype":"venue"
},
  "geometry": {"coordinates":[-84.304671,42.19263],"type":"Point"}
}