{
  "type": "Feature",
  "properties": {
    "iso:country":"US",
    "sg:address":"6225 Prairie St",
    "sg:city":"Muskegon",
    "sg:classifiers":[
        {
            "category":"Health Services",
            "subcategory":"Doctor",
            "type":"Services"
        },
        {
            "category":"Personal",
            "subcategory":"Massage",
            "type":"Services"
        },
        {
            "category":"Personal",
            "subcategory":"Day Spa",
            "type":"Services"
        },
        {
            "category":"Personal",
            "subcategory":"Skin Care",
            "type":"Services"
        },
        {
            "category":"Personal",
            "subcategory":"Nail Salon",
            "type":"Services"
        }
    ],
    "sg:phone":"+1 231 798 9500",
    "sg:postcode":"49444",
    "sg:province":"MI",
    "sg:tags":[
        "physician",
        "reconstructive",
        "surgeons",
        "plastic",
        "therapist",
        "dermatology"
    ],
    "sg:website":"http://www.lsderm.com/_Home.aspx",
    "wof:name":"Lakeshore Dermatology Laser & Medical Spa",
    "wof:placetype":"venue"
},
  "geometry": {"coordinates":[-86.209243,43.138561],"type":"Point"}
}