{
  "type": "Feature",
  "properties": {
    "iso:country":"US",
    "sg:address":"6775 Carlyle Xing",
    "sg:city":"West Bloomfield",
    "sg:classifiers":[
        {
            "category":"Professional",
            "type":"Services"
        }
    ],
    "sg:phone":"+1 248 661 8170",
    "sg:postcode":"48322",
    "sg:province":"MI",
    "wof:name":"T & T Special T Svc Inc",
    "wof:placetype":"venue"
},
  "geometry": {"coordinates":[-83.416302,42.53545],"type":"Point"}
}