{
  "type": "Feature",
  "properties": {
    "iso:country":"US",
    "sg:address":"25785 Catalina Dr",
    "sg:city":"Southfield",
    "sg:classifiers":[
        {
            "category":"Manufacturing",
            "subcategory":"Printing",
            "type":"Manufacturing & Wholesale Goods"
        }
    ],
    "sg:phone":"+1 248 552 0582",
    "sg:postcode":"48075",
    "sg:province":"MI",
    "sg:tags":[
        "publisher",
        "music"
    ],
    "wof:name":"Cane River Media",
    "wof:placetype":"venue"
},
  "geometry": {"coordinates":[-83.22971800000001,42.479712],"type":"Point"}
}