{
  "type": "Feature",
  "properties": {
    "iso:country":"US",
    "sg:address":"120 S Saginaw St",
    "sg:city":"Montrose",
    "sg:classifiers":[
        {
            "category":"Health Services",
            "subcategory":"Doctor",
            "type":"Services"
        }
    ],
    "sg:phone":"+1 810 639 6121",
    "sg:postcode":"48457",
    "sg:province":"MI",
    "sg:tags":[
        "physician",
        "surgeon"
    ],
    "wof:name":"Carlton K Dettman MD",
    "wof:placetype":"venue"
},
  "geometry": {"coordinates":[-83.893117,43.175633],"type":"Point"}
}