{
  "type": "Feature",
  "properties": {
    "iso:country":"US",
    "sg:address":"4752 S Ruess Rd",
    "sg:city":"Owosso",
    "sg:classifiers":[
        {
            "category":"Building & Trades",
            "subcategory":"Landscaping Services",
            "type":"Services"
        }
    ],
    "sg:phone":"+1 989 723 5546",
    "sg:postcode":"48867",
    "sg:province":"MI",
    "wof:name":"Bradley Lab Tree Work",
    "wof:placetype":"venue"
},
  "geometry": {"coordinates":[-84.242118,42.924474],"type":"Point"}
}