{
  "type": "Feature",
  "properties": {
    "iso:country":"US",
    "sg:address":"20658 Harper Ave",
    "sg:city":"Harper Woods",
    "sg:classifiers":[
        {
            "category":"Insurance",
            "subcategory":"Hazard Insurance",
            "type":"Services"
        }
    ],
    "sg:phone":"+1 313 881 4623",
    "sg:postcode":"48225",
    "sg:province":"MI",
    "sg:website":"www.progressiveagent.com/the-pep...",
    "wof:name":"The Peppler Agency",
    "wof:placetype":"venue"
},
  "geometry": {"coordinates":[-82.916729,42.445014],"type":"Point"}
}