{
  "type": "Feature",
  "properties": {
    "iso:country":"US",
    "sg:address":"940 28th St SE",
    "sg:city":"Grand Rapids",
    "sg:classifiers":[
        {
            "category":"Shopping",
            "type":"Retail Goods"
        }
    ],
    "sg:phone":"+1 616 243 3200",
    "sg:postcode":"49508",
    "sg:province":"MI",
    "sg:tags":[
        "cards",
        "sport",
        "baseball",
        "memorabilia"
    ],
    "wof:name":"Collectors Emporium",
    "wof:placetype":"venue"
},
  "geometry": {"coordinates":[-85.64439,42.91271],"type":"Point"}
}