{
  "type": "Feature",
  "properties": {
    "iso:country":"US",
    "sg:address":"441 W Morrell St",
    "sg:city":"Otsego",
    "sg:classifiers":[
        {
            "category":"Building & Trades",
            "subcategory":"Plumbing",
            "type":"Services"
        }
    ],
    "sg:phone":"+1 269 694 5742",
    "sg:postcode":"49078",
    "sg:province":"MI",
    "sg:tags":[
        "contractor"
    ],
    "wof:name":"Darnell Plumbing",
    "wof:placetype":"venue"
},
  "geometry": {"coordinates":[-85.706503,42.457726],"type":"Point"}
}