{
  "type": "Feature",
  "properties": {
    "iso:country":"US",
    "sg:address":"1557 W Maumee St",
    "sg:city":"Adrian",
    "sg:classifiers":[
        {
            "category":"Restaurant",
            "type":"Food & Drink"
        }
    ],
    "sg:phone":"+1 517 263 4828",
    "sg:postcode":"49221",
    "sg:province":"MI",
    "wof:name":"China Garden Restaurant",
    "wof:placetype":"venue"
},
  "geometry": {"coordinates":[-84.069777,41.905474],"type":"Point"}
}