{
  "type": "Feature",
  "properties": {
    "iso:country":"US",
    "sg:address":"137 Tarzon",
    "sg:city":"Gwinn",
    "sg:classifiers":[
        {
            "category":"Building & Trades",
            "subcategory":"Construction",
            "type":"Services"
        }
    ],
    "sg:phone":"+1 906 346 6984",
    "sg:postcode":"49841",
    "sg:province":"MI",
    "sg:tags":[
        "general",
        "contractor"
    ],
    "wof:name":"K I Construction",
    "wof:placetype":"venue"
},
  "geometry": {"coordinates":[-87.377984,46.325347],"type":"Point"}
}