{
  "type": "Feature",
  "properties": {
    "iso:country":"US",
    "sg:address":"8261 Foster Rd",
    "sg:city":"Clarkston",
    "sg:classifiers":[
        {
            "category":"Retail",
            "subcategory":"Repair Shop",
            "type":"Services"
        }
    ],
    "sg:phone":"+1 248 625 8680",
    "sg:postcode":"48346",
    "sg:province":"MI",
    "wof:name":"B & B Sewer & Septic",
    "wof:placetype":"venue"
},
  "geometry": {"coordinates":[-83.447267,42.723657],"type":"Point"}
}