{
  "type": "Feature",
  "properties": {
    "iso:country":"US",
    "sg:address":"309 E Huron Ave",
    "sg:city":"Bad Axe",
    "sg:classifiers":[
        {
            "category":"Cinema",
            "subcategory":"Movie Theater",
            "type":"Entertainment"
        }
    ],
    "sg:phone":"+1 989 269 7911",
    "sg:postcode":"48413",
    "sg:province":"MI",
    "sg:tags":[
        "motion",
        "picture"
    ],
    "wof:name":"Bad Axe Theatre",
    "wof:placetype":"venue"
},
  "geometry": {"coordinates":[-82.99612399999999,43.802242],"type":"Point"}
}