{
  "type": "Feature",
  "properties": {
    "iso:country":"US",
    "sg:address":"24850 Gratiot Ave",
    "sg:city":"Eastpointe",
    "sg:classifiers":[
        {
            "category":"Food & Beverages",
            "subcategory":"Liquor & Beverages",
            "type":"Retail Goods"
        }
    ],
    "sg:phone":"+1 586 774 2977",
    "sg:postcode":"48021",
    "sg:province":"MI",
    "sg:tags":[
        "beer",
        "spirit",
        "wine"
    ],
    "wof:name":"Eastpointe Liquor",
    "wof:placetype":"venue"
},
  "geometry": {"coordinates":[-82.948097,42.479198],"type":"Point"}
}