{
  "type": "Feature",
  "properties": {
    "iso:country":"US",
    "sg:address":"4016 Kendrick St",
    "sg:city":"Saginaw",
    "sg:classifiers":[
        {
            "category":"Building & Trades",
            "subcategory":"Construction",
            "type":"Services"
        }
    ],
    "sg:phone":"+1 989 399 1300",
    "sg:postcode":"48638",
    "sg:province":"MI",
    "sg:tags":[
        "tile",
        "dealer"
    ],
    "wof:name":"Espinoza Enterprises Inc",
    "wof:placetype":"venue"
},
  "geometry": {"coordinates":[-83.99727799999999,43.405277],"type":"Point"}
}