{
  "type": "Feature",
  "properties": {
    "iso:country":"US",
    "sg:address":"1416 North Ave NE",
    "sg:city":"Grand Rapids",
    "sg:classifiers":[
        {
            "category":"Food & Beverages",
            "subcategory":"Meat & Fish",
            "type":"Retail Goods"
        }
    ],
    "sg:phone":"+1 616 361 6328",
    "sg:postcode":"49505",
    "sg:province":"MI",
    "wof:name":"Denver Beef Co",
    "wof:placetype":"venue"
},
  "geometry": {"coordinates":[-85.659547,42.988772],"type":"Point"}
}