{
  "type": "Feature",
  "properties": {
    "iso:country":"US",
    "sg:address":"14444 168th Ave",
    "sg:city":"Grand Haven",
    "sg:classifiers":[
        {
            "category":"Manufacturing",
            "subcategory":"Metals",
            "type":"Manufacturing & Wholesale Goods"
        }
    ],
    "sg:phone":"+1 616 846 8510",
    "sg:postcode":"49417",
    "sg:province":"MI",
    "sg:tags":[
        "stamping"
    ],
    "sg:website":"www.transfertool.com",
    "wof:name":"Transfer Tool Systems Inc",
    "wof:placetype":"venue"
},
  "geometry": {"coordinates":[-86.204908,43.031296],"type":"Point"}
}