{
  "type": "Feature",
  "properties": {
    "iso:country":"US",
    "sg:address":"4248 E Lake Rd",
    "sg:city":"Clio",
    "sg:classifiers":[
        {
            "category":"Building & Trades",
            "subcategory":"Landscaping Services",
            "type":"Services"
        }
    ],
    "sg:phone":"+1 810 687 3867",
    "sg:postcode":"48420",
    "sg:province":"MI",
    "wof:name":"Hobsons Lawn Care",
    "wof:placetype":"venue"
},
  "geometry": {"coordinates":[-83.626305,43.208391],"type":"Point"}
}