{
  "type": "Feature",
  "properties": {
    "iso:country":"US",
    "sg:address":"2425 Bond St",
    "sg:city":"Niles",
    "sg:classifiers":[
        {
            "category":"Professional",
            "subcategory":"Management & Consulting",
            "type":"Services"
        }
    ],
    "sg:phone":"+1 269 684 2438",
    "sg:postcode":"49120",
    "sg:province":"MI",
    "sg:tags":[
        "promotion",
        "sales"
    ],
    "wof:name":"Applied Plastics",
    "wof:placetype":"venue"
},
  "geometry": {"coordinates":[-86.26220600000001,41.778278],"type":"Point"}
}