{
  "type": "Feature",
  "properties": {
    "iso:country":"US",
    "sg:address":"56230 Grand River Ave",
    "sg:city":"New Hudson",
    "sg:classifiers":[
        {
            "category":"Restaurant",
            "type":"Food & Drink"
        }
    ],
    "sg:phone":"+1 248 437 9212",
    "sg:postcode":"48165",
    "sg:province":"MI",
    "wof:name":"Bob's Carry Out",
    "wof:placetype":"venue"
},
  "geometry": {"coordinates":[-83.61188,42.510857],"type":"Point"}
}