{
  "type": "Feature",
  "properties": {
    "iso:country":"US",
    "sg:address":"112 W Washington St",
    "sg:city":"Ann Arbor",
    "sg:classifiers":[
        {
            "category":"Cafe",
            "type":"Food & Drink"
        }
    ],
    "sg:menulink":"http://www.allmenus.com/mi/ann-arbor/248042-cafe-zola/menu/",
    "sg:phone":"+1 734 769 2020",
    "sg:postcode":"48104",
    "sg:province":"MI",
    "sg:tags":[
        "american",
        "mediterranean",
        "french",
        "italian"
    ],
    "wof:name":"Cafe Zola",
    "wof:placetype":"venue"
},
  "geometry": {"coordinates":[-83.748676,42.280479],"type":"Point"}
}