{
  "type": "Feature",
  "properties": {
    "iso:country":"US",
    "sg:address":"7495 Cottonwood Dr",
    "sg:city":"Jenison",
    "sg:classifiers":[
        {
            "category":"Shopping",
            "subcategory":"Photographic Equipment",
            "type":"Retail Goods"
        }
    ],
    "sg:phone":"+1 616 457 1460",
    "sg:postcode":"49428",
    "sg:province":"MI",
    "sg:tags":[
        "supply"
    ],
    "wof:name":"Lakewood Photo & Video",
    "wof:placetype":"venue"
},
  "geometry": {"coordinates":[-85.79206499999999,42.904369],"type":"Point"}
}