{
  "type": "Feature",
  "properties": {
    "iso:country":"US",
    "sg:address":"7247 Warner Rd",
    "sg:city":"Elwell",
    "sg:classifiers":[
        {
            "category":"Building & Trades",
            "subcategory":"Landscaping Services",
            "type":"Services"
        }
    ],
    "sg:phone":"+1 989 463 1712",
    "sg:postcode":"48832",
    "sg:province":"MI",
    "sg:tags":[
        "tree"
    ],
    "wof:name":"Freed's Tree Svc",
    "wof:placetype":"venue"
},
  "geometry": {"coordinates":[-84.786597,43.404681],"type":"Point"}
}