{
  "type": "Feature",
  "properties": {
    "iso:country":"US",
    "sg:address":"1 Lafayette Blvd",
    "sg:city":"Detroit",
    "sg:classifiers":[
        {
            "category":"Shopping",
            "subcategory":"Clothing, Apparel, & Fashions",
            "type":"Retail Goods"
        }
    ],
    "sg:phone":"+1 313 638 2644",
    "sg:postcode":"48209",
    "sg:province":"MI",
    "sg:tags":[
        "designer"
    ],
    "wof:name":"TM Glam Squad",
    "wof:placetype":"venue"
},
  "geometry": {"coordinates":[-83.08783699999999,42.314322],"type":"Point"}
}