{
  "type": "Feature",
  "properties": {
    "iso:country":"US",
    "sg:address":"974 W Norton Ave",
    "sg:city":"Muskegon",
    "sg:classifiers":[
        {
            "category":"Real Estate",
            "subcategory":"Real Estate Operator",
            "type":"Services"
        }
    ],
    "sg:phone":"+1 231 737 7863",
    "sg:postcode":"49441",
    "sg:province":"MI",
    "sg:tags":[
        "building",
        "apartment"
    ],
    "wof:name":"Mona Shores Apartments",
    "wof:placetype":"venue"
},
  "geometry": {"coordinates":[-86.266966,43.190866],"type":"Point"}
}