{
  "type": "Feature",
  "properties": {
    "iso:country":"US",
    "sg:address":"4930 N Burkhart Rd",
    "sg:city":"Howell",
    "sg:classifiers":[
        {
            "category":"Social Services",
            "subcategory":"Child Care",
            "type":"Services"
        }
    ],
    "sg:phone":"+1 517 548 0969",
    "sg:postcode":"48855",
    "sg:province":"MI",
    "wof:name":"Happy Acres Day Care",
    "wof:placetype":"venue"
},
  "geometry": {"coordinates":[-83.994996,42.671643],"type":"Point"}
}