{
  "type": "Feature",
  "properties": {
    "iso:country":"US",
    "sg:address":"18964 174th Ave",
    "sg:city":"Spring Lake",
    "sg:classifiers":[
        {
            "category":"Building & Trades",
            "subcategory":"Construction",
            "type":"Services"
        }
    ],
    "sg:phone":"+1 616 846 9060",
    "sg:postcode":"49456",
    "sg:province":"MI",
    "sg:tags":[
        "dock"
    ],
    "wof:name":"V & T Construction Inc",
    "wof:placetype":"venue"
},
  "geometry": {"coordinates":[-86.219753,43.117587],"type":"Point"}
}