{
  "type": "Feature",
  "properties": {
    "iso:country":"US",
    "sg:address":"3330 Claystone St SE",
    "sg:city":"Grand Rapids",
    "sg:classifiers":[
        {
            "category":"Health Services",
            "subcategory":"Doctor",
            "type":"Services"
        }
    ],
    "sg:phone":"+1 616 949 7460",
    "sg:postcode":"49546",
    "sg:province":"MI",
    "sg:tags":[
        "medical"
    ],
    "wof:name":"Stauffer Susan Msw Acsw",
    "wof:placetype":"venue"
},
  "geometry": {"coordinates":[-85.585539,42.923128],"type":"Point"}
}