{
  "type": "Feature",
  "properties": {
    "iso:country":"US",
    "sg:address":"27600 7 Mile Rd",
    "sg:city":"Livonia",
    "sg:classifiers":[
        {
            "category":"Personal",
            "subcategory":"Barber",
            "type":"Services"
        }
    ],
    "sg:phone":"+1 248 777 4247",
    "sg:postcode":"48152",
    "sg:province":"MI",
    "wof:name":"Orlando's J Barber Shop",
    "wof:placetype":"venue"
},
  "geometry": {"coordinates":[-83.31880200000001,42.4277],"type":"Point"}
}