{
  "type": "Feature",
  "properties": {
    "iso:country":"US",
    "sg:address":"15422 Harrison Ave",
    "sg:city":"Allen Park",
    "sg:classifiers":[
        {
            "category":"Freight",
            "type":"Transportation"
        }
    ],
    "sg:phone":"+1 313 388 6376",
    "sg:postcode":"48101",
    "sg:province":"MI",
    "sg:tags":[
        "operator",
        "trucking"
    ],
    "wof:name":"T C Transport Inc",
    "wof:placetype":"venue"
},
  "geometry": {"coordinates":[-83.207187,42.254141],"type":"Point"}
}