{
  "type": "Feature",
  "properties": {
    "iso:country":"US",
    "sg:address":"25545 Pattow St",
    "sg:city":"Roseville",
    "sg:classifiers":[
        {
            "category":"Retail",
            "subcategory":"Repair Shop",
            "type":"Services"
        }
    ],
    "sg:phone":"+1 586 498 9282",
    "sg:postcode":"48066",
    "sg:province":"MI",
    "sg:tags":[
        "lock",
        "locksmith"
    ],
    "wof:name":"A Autosmart Lock & Key",
    "wof:placetype":"venue"
},
  "geometry": {"coordinates":[-82.92313799999999,42.487402],"type":"Point"}
}