{
  "type": "Feature",
  "properties": {
    "iso:country":"US",
    "sg:address":"734 W Huron St",
    "sg:city":"Pontiac",
    "sg:classifiers":[
        {
            "category":"Bars & Pubs",
            "type":"Food & Drink"
        }
    ],
    "sg:phone":"+1 248 332 6980",
    "sg:postcode":"48341",
    "sg:province":"MI",
    "wof:name":"Prues Bar",
    "wof:placetype":"venue"
},
  "geometry": {"coordinates":[-83.321186,42.635426],"type":"Point"}
}