{
  "type": "Feature",
  "properties": {
    "iso:country":"US",
    "sg:address":"838 Helston Ct",
    "sg:city":"Bloomfield Hills",
    "sg:classifiers":[
        {
            "category":"Banks & Credit Unions",
            "subcategory":"Financial Services",
            "type":"Services"
        }
    ],
    "sg:phone":"+1 248 645 6534",
    "sg:postcode":"48304",
    "sg:province":"MI",
    "sg:tags":[
        "investor"
    ],
    "wof:name":"Spare Change Investment Club",
    "wof:placetype":"venue"
},
  "geometry": {"coordinates":[-83.220838,42.594992],"type":"Point"}
}