{
  "type": "Feature",
  "properties": {
    "iso:country":"US",
    "sg:address":"3640 Rue Foret",
    "sg:city":"Flint",
    "sg:classifiers":[
        {
            "category":"Organizations",
            "subcategory":"Religious Organization",
            "type":"Services"
        }
    ],
    "sg:phone":"+1 810 732 8751",
    "sg:postcode":"48532",
    "sg:province":"MI",
    "wof:name":"Gospel Health Inc",
    "wof:placetype":"venue"
},
  "geometry": {"coordinates":[-83.749512,43.01996],"type":"Point"}
}