{
  "type": "Feature",
  "properties": {
    "iso:country":"US",
    "sg:address":"309 Buena Vista St W",
    "sg:city":"Detroit",
    "sg:classifiers":[
        {
            "category":"Building & Trades",
            "subcategory":"Cleaning & Sanitation",
            "type":"Services"
        }
    ],
    "sg:phone":"+1 313 867 3104",
    "sg:postcode":"48203",
    "sg:province":"MI",
    "sg:tags":[
        "maintenance"
    ],
    "wof:name":"Rks Janitorial Service",
    "wof:placetype":"venue"
},
  "geometry": {"coordinates":[-83.104658,42.397322],"type":"Point"}
}