{
  "type": "Feature",
  "properties": {
    "iso:country":"US",
    "sg:address":"4321 Airwest Dr SE",
    "sg:city":"Kentwood",
    "sg:classifiers":[
        {
            "category":"Shopping",
            "subcategory":"Gifts & Souvenirs",
            "type":"Retail Goods"
        }
    ],
    "sg:phone":"+1 616 698 9621",
    "sg:postcode":"49512",
    "sg:province":"MI",
    "sg:tags":[
        "shop"
    ],
    "wof:name":"Furry Critterz Fashionz N Gift",
    "wof:placetype":"venue"
},
  "geometry": {"coordinates":[-85.571489,42.885135],"type":"Point"}
}