{
  "type": "Feature",
  "properties": {
    "iso:country":"US",
    "sg:address":"33523 8 Mile Rd",
    "sg:city":"Livonia",
    "sg:classifiers":[
        {
            "category":"Restaurant",
            "type":"Food & Drink"
        }
    ],
    "sg:menulink":"http://www.allmenus.com/mi/livonia/26276-rio-wraps/menu/",
    "sg:phone":"+1 248 888 9727",
    "sg:postcode":"48152",
    "sg:province":"MI",
    "sg:tags":[
        "wrap",
        "american",
        "sandwich"
    ],
    "wof:name":"Rio Wraps",
    "wof:placetype":"venue"
},
  "geometry": {"coordinates":[-83.376818,42.440517],"type":"Point"}
}