{
  "type": "Feature",
  "properties": {
    "iso:country":"US",
    "sg:address":"2340 Canyon Ridge Dr",
    "sg:city":"White Lake",
    "sg:classifiers":[
        {
            "category":"Building & Trades",
            "subcategory":"Construction",
            "type":"Services"
        }
    ],
    "sg:phone":"+1 248 887 9529",
    "sg:postcode":"48383",
    "sg:province":"MI",
    "sg:tags":[
        "hanging",
        "contractor"
    ],
    "wof:name":"Jeff Schimp Painting LLC",
    "wof:placetype":"venue"
},
  "geometry": {"coordinates":[-83.545462,42.660237],"type":"Point"}
}