{
  "type": "Feature",
  "properties": {
    "iso:country":"US",
    "sg:address":"1119 N Fairway Dr",
    "sg:city":"Pontiac",
    "sg:classifiers":[
        {
            "category":"Real Estate",
            "subcategory":"Developer",
            "type":"Services"
        }
    ],
    "sg:phone":"+1 248 377 2424",
    "sg:postcode":"48340",
    "sg:province":"MI",
    "wof:name":"Fieldstone Village Development",
    "wof:placetype":"venue"
},
  "geometry": {"coordinates":[-83.260803,42.679855],"type":"Point"}
}