{
  "type": "Feature",
  "properties": {
    "iso:country":"US",
    "sg:address":"7701 Grand River Rd",
    "sg:city":"Brighton",
    "sg:classifiers":[
        {
            "category":"Wholesale",
            "subcategory":"Groceries",
            "type":"Manufacturing & Wholesale Goods"
        }
    ],
    "sg:phone":"+1 810 225 3200",
    "sg:postcode":"48114",
    "sg:province":"MI",
    "sg:tags":[
        "juice",
        "fruit"
    ],
    "wof:name":"Bug Juice Brands Inc",
    "wof:placetype":"venue"
},
  "geometry": {"coordinates":[-83.79703000000001,42.562767],"type":"Point"}
}