{
  "type": "Feature",
  "properties": {
    "iso:country":"US",
    "sg:address":"33786 Morse St",
    "sg:city":"Clinton Township",
    "sg:classifiers":[
        {
            "category":"Building & Trades",
            "subcategory":"Construction",
            "type":"Services"
        }
    ],
    "sg:phone":"+1 586 791 4006",
    "sg:postcode":"48035",
    "sg:province":"MI",
    "sg:tags":[
        "house"
    ],
    "wof:name":"Cochranes Construction Svcs",
    "wof:placetype":"venue"
},
  "geometry": {"coordinates":[-82.88764399999999,42.547457],"type":"Point"}
}