{
  "type": "Feature",
  "properties": {
    "iso:country":"US",
    "sg:address":"11200 Beechwood Dr",
    "sg:city":"Kewadin",
    "sg:classifiers":[
        {
            "category":"Building & Trades",
            "subcategory":"Construction",
            "type":"Services"
        }
    ],
    "sg:phone":"+1 231 599 2517",
    "sg:postcode":"49648",
    "sg:province":"MI",
    "sg:tags":[
        "house"
    ],
    "wof:name":"Beechwood Builders",
    "wof:placetype":"venue"
},
  "geometry": {"coordinates":[-85.334481,45.036363],"type":"Point"}
}