{
  "type": "Feature",
  "properties": {
    "iso:country":"US",
    "sg:address":"5996 128th Ave",
    "sg:city":"Fennville",
    "sg:classifiers":[
        {
            "category":"Health Services",
            "subcategory":"Nursing And Care Facility",
            "type":"Services"
        }
    ],
    "sg:phone":"+1 269 561 5784",
    "sg:postcode":"49408",
    "sg:province":"MI",
    "sg:tags":[
        "adult"
    ],
    "wof:name":"Country Corners Assisted Lvng",
    "wof:placetype":"venue"
},
  "geometry": {"coordinates":[-86.132543,42.623026],"type":"Point"}
}