{
  "type": "Feature",
  "properties": {
    "iso:country":"US",
    "sg:address":"110 W Michigan Ave",
    "sg:city":"Lansing",
    "sg:classifiers":[
        {
            "category":"Professional",
            "subcategory":"Lawyer & Legal Services",
            "type":"Services"
        }
    ],
    "sg:phone":"+1 517 372 6622",
    "sg:postcode":"48933",
    "sg:province":"MI",
    "wof:name":"Urban James J Atty",
    "wof:placetype":"venue"
},
  "geometry": {"coordinates":[-84.55376699999999,42.733751],"type":"Point"}
}