{
  "type": "Feature",
  "properties": {
    "iso:country":"US",
    "sg:address":"25801 Harper Ave",
    "sg:city":"St Clair Shores",
    "sg:classifiers":[
        {
            "category":"Professional",
            "subcategory":"Accounting & Tax Preparation",
            "type":"Services"
        }
    ],
    "sg:phone":"+1 586 777 5929",
    "sg:postcode":"48081",
    "sg:province":"MI",
    "sg:tags":[
        "bookkeeping",
        "general"
    ],
    "wof:name":"Custom Accounting",
    "wof:placetype":"venue"
},
  "geometry": {"coordinates":[-82.900155,42.483697],"type":"Point"}
}