{
  "type": "Feature",
  "properties": {
    "iso:country":"US",
    "sg:address":"22200 Gratiot Ave",
    "sg:city":"Eastpointe",
    "sg:classifiers":[
        {
            "category":"Retail",
            "subcategory":"Auto Repair",
            "type":"Services"
        }
    ],
    "sg:phone":"+1 586 775 2560",
    "sg:postcode":"48021",
    "sg:province":"MI",
    "sg:website":"www.squaredealautoservice.com",
    "wof:name":"Square Deal Auto Service",
    "wof:placetype":"venue"
},
  "geometry": {"coordinates":[-82.96019699999999,42.460701],"type":"Point"}
}