{
  "type": "Feature",
  "properties": {
    "iso:country":"US",
    "sg:address":"215 S Cedar St",
    "sg:city":"Mason",
    "sg:classifiers":[
        {
            "category":"Retail",
            "subcategory":"Auto Repair",
            "type":"Services"
        }
    ],
    "sg:phone":"+1 517 676 5888",
    "sg:postcode":"48854",
    "sg:province":"MI",
    "sg:tags":[
        "body",
        "automobile",
        "painting"
    ],
    "wof:name":"Tom's Auto Body",
    "wof:placetype":"venue"
},
  "geometry": {"coordinates":[-84.45278399999999,42.580335],"type":"Point"}
}