{
  "type": "Feature",
  "properties": {
    "iso:country":"US",
    "sg:address":"208 Seminole Ct",
    "sg:city":"Midland",
    "sg:classifiers":[
        {
            "category":"Social Services",
            "subcategory":"Child Care",
            "type":"Services"
        }
    ],
    "sg:phone":"+1 989 839 9103",
    "sg:postcode":"48642",
    "sg:province":"MI",
    "sg:tags":[
        "day",
        "provider"
    ],
    "wof:name":"Barbara S Foster",
    "wof:placetype":"venue"
},
  "geometry": {"coordinates":[-84.225184,43.636755],"type":"Point"}
}