{
  "type": "Feature",
  "properties": {
    "iso:country":"US",
    "sg:address":"10576 Erskine Dr",
    "sg:city":"Battle Creek",
    "sg:classifiers":[
        {
            "category":"Professional",
            "subcategory":"Business Services",
            "type":"Services"
        }
    ],
    "sg:phone":"+1 269 979 3908",
    "sg:postcode":"49014",
    "sg:province":"MI",
    "wof:name":"Gs Enterprises",
    "wof:placetype":"venue"
},
  "geometry": {"coordinates":[-85.19829900000001,42.225601],"type":"Point"}
}