{
  "type": "Feature",
  "properties": {
    "iso:country":"US",
    "sg:address":"4991 Williams Lake Rd",
    "sg:city":"Waterford",
    "sg:classifiers":[
        {
            "category":"Organizations",
            "subcategory":"Religious Organization",
            "type":"Services"
        }
    ],
    "sg:phone":"+1 248 674 1553",
    "sg:postcode":"48329",
    "sg:province":"MI",
    "sg:website":"www.waterfordchurch.com",
    "wof:name":"Waterford Church Of Christ",
    "wof:placetype":"venue"
},
  "geometry": {"coordinates":[-83.38521,42.689634],"type":"Point"}
}