{
  "type": "Feature",
  "properties": {
    "iso:country":"US",
    "sg:address":"2171 E Michigan Ave",
    "sg:city":"Ypsilanti",
    "sg:classifiers":[
        {
            "category":"Education",
            "subcategory":"School",
            "type":"Public Place"
        }
    ],
    "sg:phone":"+1 734 481 8200",
    "sg:postcode":"48198",
    "sg:province":"MI",
    "sg:tags":[
        "elementary",
        "district"
    ],
    "wof:name":"Willow Run Community Schools",
    "wof:placetype":"venue"
},
  "geometry": {"coordinates":[-83.567924,42.249353],"type":"Point"}
}