{
  "type": "Feature",
  "properties": {
    "iso:country":"US",
    "sg:address":"1676 Lincolnshire Dr",
    "sg:city":"Detroit",
    "sg:classifiers":[
        {
            "category":"Communications",
            "type":"Services"
        }
    ],
    "sg:phone":"+1 313 366 5813",
    "sg:postcode":"48203",
    "sg:province":"MI",
    "wof:name":"Kick The Can Media Productions",
    "wof:placetype":"venue"
},
  "geometry": {"coordinates":[-83.123862,42.43311],"type":"Point"}
}