{
  "type": "Feature",
  "properties": {
    "iso:country":"US",
    "sg:address":"23385 Glenwood St",
    "sg:city":"Clinton Township",
    "sg:classifiers":[
        {
            "category":"Retail",
            "subcategory":"Portrait Studio",
            "type":"Services"
        }
    ],
    "sg:phone":"+1 586 791 2085",
    "sg:postcode":"48035",
    "sg:province":"MI",
    "sg:tags":[
        "photo"
    ],
    "wof:name":"M J M Photography",
    "wof:placetype":"venue"
},
  "geometry": {"coordinates":[-82.877653,42.560708],"type":"Point"}
}