{
  "type": "Feature",
  "properties": {
    "iso:country":"US",
    "sg:address":"1577 Capital Ave NE",
    "sg:city":"Battle Creek",
    "sg:classifiers":[
        {
            "category":"Professional",
            "subcategory":"Accounting & Tax Preparation",
            "type":"Services"
        }
    ],
    "sg:phone":"+1 269 964 9001",
    "sg:postcode":"49017",
    "sg:province":"MI",
    "sg:tags":[
        "return",
        "filing"
    ],
    "wof:name":"H & R Block Tax Svc",
    "wof:placetype":"venue"
},
  "geometry": {"coordinates":[-85.15412999999999,42.34511],"type":"Point"}
}