{
  "type": "Feature",
  "properties": {
    "iso:country":"US",
    "sg:address":"29578 E Channel Rd",
    "sg:city":"Drummond Island",
    "sg:classifiers":[
        {
            "category":"Shopping",
            "subcategory":"Bicycles & Sporting Goods",
            "type":"Retail Goods"
        }
    ],
    "sg:phone":"+1 906 493 6300",
    "sg:postcode":"49726",
    "sg:province":"MI",
    "wof:name":"Johnson's Sport Shop",
    "wof:placetype":"venue"
},
  "geometry": {"coordinates":[-83.764475,45.999269],"type":"Point"}
}