{
  "type": "Feature",
  "properties": {
    "iso:country":"US",
    "sg:address":"1173 Pleasure St",
    "sg:city":"Milford",
    "sg:classifiers":[
        {
            "category":"Professional",
            "subcategory":"Business Services",
            "type":"Services"
        }
    ],
    "sg:phone":"+1 248 207 3302",
    "sg:postcode":"48381",
    "sg:province":"MI",
    "sg:tags":[
        "home",
        "company",
        "inspection"
    ],
    "wof:name":"Landmark Home Inspections LLC",
    "wof:placetype":"venue"
},
  "geometry": {"coordinates":[-83.588184,42.593298],"type":"Point"}
}