{
  "type": "Feature",
  "properties": {
    "iso:country":"US",
    "sg:address":"224 Leo Dr",
    "sg:city":"Burlington",
    "sg:classifiers":[
        {
            "category":"Building & Trades",
            "subcategory":"Construction",
            "type":"Services"
        }
    ],
    "sg:phone":"+1 517 765 0303",
    "sg:postcode":"49029",
    "sg:province":"MI",
    "sg:tags":[
        "house"
    ],
    "wof:name":"Womack Builders",
    "wof:placetype":"venue"
},
  "geometry": {"coordinates":[-85.070364,42.107396],"type":"Point"}
}