{
  "type": "Feature",
  "properties": {
    "iso:country":"US",
    "sg:address":"414 Union St",
    "sg:city":"Milford",
    "sg:classifiers":[
        {
            "category":"Health Services",
            "subcategory":"Medical Lab",
            "type":"Services"
        }
    ],
    "sg:phone":"+1 248 685 9520",
    "sg:postcode":"48381",
    "sg:province":"MI",
    "sg:tags":[
        "laboratory"
    ],
    "wof:name":"Dmc University Laboratory",
    "wof:placetype":"venue"
},
  "geometry": {"coordinates":[-83.59907699999999,42.591567],"type":"Point"}
}