{
  "type": "Feature",
  "properties": {
    "iso:country":"US",
    "sg:address":"8080 Moorsbridge Rd",
    "sg:city":"Portage",
    "sg:classifiers":[
        {
            "category":"Health Services",
            "subcategory":"Health Practitioner",
            "type":"Services"
        }
    ],
    "sg:phone":"+1 269 324 5100",
    "sg:postcode":"49024",
    "sg:province":"MI",
    "wof:name":"Wiliam G Dodds",
    "wof:placetype":"venue"
},
  "geometry": {"coordinates":[-85.63455399999999,42.204695],"type":"Point"}
}