{
  "type": "Feature",
  "properties": {
    "iso:country":"US",
    "sg:address":"5309 Main St",
    "sg:city":"Lexington",
    "sg:classifiers":[
        {
            "category":"Restaurant",
            "type":"Food & Drink"
        }
    ],
    "sg:phone":"+1 810 359 8522",
    "sg:postcode":"48450",
    "sg:province":"MI",
    "sg:tags":[
        "eating"
    ],
    "wof:name":"A&W Restaurant",
    "wof:placetype":"venue"
},
  "geometry": {"coordinates":[-82.53126399999999,43.27349],"type":"Point"}
}