{
  "type": "Feature",
  "properties": {
    "iso:country":"US",
    "sg:address":"3435 Orchard Lake Rd",
    "sg:city":"Keego Harbor",
    "sg:classifiers":[
        {
            "category":"Health Services",
            "subcategory":"Dentist",
            "type":"Services"
        }
    ],
    "sg:phone":"+1 248 681 4660",
    "sg:postcode":"48320",
    "sg:province":"MI",
    "wof:name":"West Bloomfield Dental Center",
    "wof:placetype":"venue"
},
  "geometry": {"coordinates":[-83.34929700000001,42.597301],"type":"Point"}
}