{
  "type": "Feature",
  "properties": {
    "iso:country":"US",
    "sg:address":"310 N Walnut St",
    "sg:city":"Bay City",
    "sg:classifiers":[
        {
            "category":"Wholesale",
            "subcategory":"Non-durable Goods",
            "type":"Manufacturing & Wholesale Goods"
        }
    ],
    "sg:phone":"+1 989 894 2782",
    "sg:postcode":"48706",
    "sg:province":"MI",
    "wof:name":"Pueblo Creations",
    "wof:placetype":"venue"
},
  "geometry": {"coordinates":[-83.89807500000001,43.604615],"type":"Point"}
}