{
  "type": "Feature",
  "properties": {
    "iso:country":"US",
    "sg:address":"565 N State St",
    "sg:city":"Sparta",
    "sg:classifiers":[
        {
            "category":"Food & Beverages",
            "subcategory":"Groceries & Convenience Stores",
            "type":"Retail Goods"
        }
    ],
    "sg:phone":"+1 616 887 0737",
    "sg:postcode":"49345",
    "sg:province":"MI",
    "sg:tags":[
        "grocer"
    ],
    "wof:name":"Family Fare",
    "wof:placetype":"venue"
},
  "geometry": {"coordinates":[-85.710201,43.168108],"type":"Point"}
}