{
  "type": "Feature",
  "properties": {
    "iso:country":"US",
    "sg:address":"1830 Greenwood Rd",
    "sg:city":"Prescott",
    "sg:classifiers":[
        {
            "category":"Food & Beverages",
            "subcategory":"Groceries & Convenience Stores",
            "type":"Retail Goods"
        }
    ],
    "sg:phone":"+1 989 873 4425",
    "sg:postcode":"48756",
    "sg:province":"MI",
    "sg:tags":[
        "grocer"
    ],
    "wof:name":"Chipp's & Nichol's Iga",
    "wof:placetype":"venue"
},
  "geometry": {"coordinates":[-84.05059900000001,44.183355],"type":"Point"}
}