{
  "type": "Feature",
  "properties": {
    "iso:country":"US",
    "sg:address":"450 Orchard St",
    "sg:city":"Belding",
    "sg:classifiers":[
        {
            "category":"Education",
            "subcategory":"School",
            "type":"Public Place"
        }
    ],
    "sg:phone":"+1 616 794 4750",
    "sg:postcode":"48809",
    "sg:province":"MI",
    "wof:name":"Woodview Elementary School",
    "wof:placetype":"venue"
},
  "geometry": {"coordinates":[-85.250833,43.094599],"type":"Point"}
}