{
  "type": "Feature",
  "properties": {
    "iso:country":"US",
    "sg:address":"6215 S Harvey St",
    "sg:city":"Muskegon",
    "sg:classifiers":[
        {
            "category":"Health Services",
            "subcategory":"Doctor",
            "type":"Services"
        }
    ],
    "sg:phone":"+1 231 799 8777",
    "sg:postcode":"49444",
    "sg:province":"MI",
    "sg:tags":[
        "physician",
        "surgeon"
    ],
    "wof:name":"Shoreline Allergy PC",
    "wof:placetype":"venue"
},
  "geometry": {"coordinates":[-86.20608900000001,43.132577],"type":"Point"}
}