{
  "type": "Feature",
  "properties": {
    "iso:country":"US",
    "sg:address":"1721 Madison Ave SE",
    "sg:city":"Grand Rapids",
    "sg:classifiers":[
        {
            "category":"Organizations",
            "subcategory":"Membership Organization",
            "type":"Services"
        }
    ],
    "sg:phone":"+1 616 452 5512",
    "sg:postcode":"49507",
    "sg:province":"MI",
    "wof:name":"Urban Produce",
    "wof:placetype":"venue"
},
  "geometry": {"coordinates":[-85.658399,42.932609],"type":"Point"}
}