{
  "type": "Feature",
  "properties": {
    "iso:country":"US",
    "sg:address":"835 Golden Ave",
    "sg:city":"Battle Creek",
    "sg:classifiers":[
        {
            "category":"Professional",
            "subcategory":"Lawyer & Legal Services",
            "type":"Services"
        }
    ],
    "sg:phone":"+1 269 963 0378",
    "sg:postcode":"49014",
    "sg:province":"MI",
    "wof:name":"James L Juhnke",
    "wof:placetype":"venue"
},
  "geometry": {"coordinates":[-85.162778,42.293814],"type":"Point"}
}