{
  "type": "Feature",
  "properties": {
    "iso:country":"US",
    "sg:address":"32287 Gratiot Ave",
    "sg:city":"Roseville",
    "sg:classifiers":[
        {
            "category":"Shopping",
            "subcategory":"Music",
            "type":"Retail Goods"
        }
    ],
    "sg:phone":"+1 586 294 2345",
    "sg:postcode":"48066",
    "sg:province":"MI",
    "sg:tags":[
        "dvd's"
    ],
    "wof:name":"Fye",
    "wof:placetype":"venue"
},
  "geometry": {"coordinates":[-82.91297900000001,42.534324],"type":"Point"}
}