{
  "type": "Feature",
  "properties": {
    "iso:country":"US",
    "sg:address":"3655 Alida Ave",
    "sg:city":"Rochester",
    "sg:classifiers":[
        {
            "category":"Retail",
            "subcategory":"Repair Shop",
            "type":"Services"
        }
    ],
    "sg:phone":"+1 248 852 6838",
    "sg:postcode":"48309",
    "sg:province":"MI",
    "wof:name":"Pams Upholstering",
    "wof:placetype":"venue"
},
  "geometry": {"coordinates":[-83.163928,42.625309],"type":"Point"}
}