{
  "type": "Feature",
  "properties": {
    "iso:country":"US",
    "sg:address":"4438 N Henderson Rd",
    "sg:city":"Davison",
    "sg:classifiers":[
        {
            "category":"Building & Trades",
            "subcategory":"Cleaning & Sanitation",
            "type":"Services"
        }
    ],
    "sg:phone":"+1 810 653 8887",
    "sg:postcode":"48423",
    "sg:province":"MI",
    "sg:tags":[
        "house"
    ],
    "wof:name":"Maid To Order",
    "wof:placetype":"venue"
},
  "geometry": {"coordinates":[-83.47906,43.076819],"type":"Point"}
}