{
  "type": "Feature",
  "properties": {
    "iso:country":"US",
    "sg:address":"37 Branson Bay Dr",
    "sg:city":"Mason",
    "sg:classifiers":[
        {
            "category":"Professional",
            "subcategory":"Business Services",
            "type":"Services"
        }
    ],
    "sg:phone":"+1 517 663 3437",
    "sg:postcode":"48854",
    "sg:province":"MI",
    "wof:name":"Eye On Design",
    "wof:placetype":"venue"
},
  "geometry": {"coordinates":[-84.58999799999999,42.576114],"type":"Point"}
}