{
  "type": "Feature",
  "properties": {
    "iso:country":"US",
    "sg:address":"447 N Clinton St",
    "sg:city":"Charlotte",
    "sg:classifiers":[
        {
            "category":"Building & Trades",
            "subcategory":"Construction",
            "type":"Services"
        }
    ],
    "sg:phone":"+1 517 543 9143",
    "sg:postcode":"48813",
    "sg:province":"MI",
    "sg:tags":[
        "house"
    ],
    "wof:name":"Mark Grimwood Builders",
    "wof:placetype":"venue"
},
  "geometry": {"coordinates":[-84.839783,42.569226],"type":"Point"}
}