{
  "type": "Feature",
  "properties": {
    "iso:country":"US",
    "sg:address":"301 Water St",
    "sg:city":"Boyne City",
    "sg:classifiers":[
        {
            "category":"Government",
            "subcategory":"Post Office",
            "type":"Public Place"
        }
    ],
    "sg:phone":"+1 231 582 9941",
    "sg:postcode":"49712",
    "sg:province":"MI",
    "wof:name":"US Post Office",
    "wof:placetype":"venue"
},
  "geometry": {"coordinates":[-85.012852,45.213684],"type":"Point"}
}