{
  "type": "Feature",
  "properties": {
    "iso:country":"US",
    "sg:address":"1019 E 2nd St",
    "sg:city":"Royal Oak",
    "sg:classifiers":[
        {
            "category":"Professional",
            "subcategory":"Management & Consulting",
            "type":"Services"
        }
    ],
    "sg:phone":"+1 248 399 3804",
    "sg:postcode":"48067",
    "sg:province":"MI",
    "sg:tags":[
        "business"
    ],
    "wof:name":"Earth Village",
    "wof:placetype":"venue"
},
  "geometry": {"coordinates":[-83.133083,42.489348],"type":"Point"}
}