{
  "type": "Feature",
  "properties": {
    "iso:country":"US",
    "sg:address":"18330 W Chicago St",
    "sg:city":"Detroit",
    "sg:classifiers":[
        {
            "category":"Food & Beverages",
            "subcategory":"Groceries & Convenience Stores",
            "type":"Retail Goods"
        }
    ],
    "sg:phone":"+1 313 659 2999",
    "sg:postcode":"48228",
    "sg:province":"MI",
    "wof:name":"Seaway Market Place",
    "wof:placetype":"venue"
},
  "geometry": {"coordinates":[-83.219437,42.365145],"type":"Point"}
}