{
  "type": "Feature",
  "properties": {
    "iso:country":"US",
    "sg:address":"23419 Gratiot Ave",
    "sg:city":"Eastpointe",
    "sg:classifiers":[
        {
            "category":"Retail",
            "subcategory":"Repair Shop",
            "type":"Services"
        }
    ],
    "sg:phone":"+1 586 774 1230",
    "sg:postcode":"48021",
    "sg:province":"MI",
    "wof:name":"Transistor Clinic",
    "wof:placetype":"venue"
},
  "geometry": {"coordinates":[-82.954536,42.470432],"type":"Point"}
}