{
  "type": "Feature",
  "properties": {
    "iso:country":"US",
    "sg:address":"7810 S Grant Ave",
    "sg:city":"Clare",
    "sg:classifiers":[
        {
            "category":"Farming",
            "subcategory":"Livestock Farm",
            "type":"Manufacturing & Wholesale Goods"
        }
    ],
    "sg:phone":"+1 989 386 2034",
    "sg:postcode":"48617",
    "sg:province":"MI",
    "sg:tags":[
        "animal",
        "general"
    ],
    "wof:name":"Circle Jt Ranch",
    "wof:placetype":"venue"
},
  "geometry": {"coordinates":[-84.78803600000001,43.879719],"type":"Point"}
}