{
  "type": "Feature",
  "properties": {
    "iso:country":"US",
    "sg:address":"8971 Lewis Ave",
    "sg:city":"Temperance",
    "sg:classifiers":[
        {
            "category":"Organizations",
            "subcategory":"Religious Organization",
            "type":"Services"
        }
    ],
    "sg:phone":"+1 734 847 7800",
    "sg:postcode":"48182",
    "sg:province":"MI",
    "sg:tags":[
        "church"
    ],
    "wof:name":"Abundant Life Ministry",
    "wof:placetype":"venue"
},
  "geometry": {"coordinates":[-83.568883,41.77881],"type":"Point"}
}