{
  "type": "Feature",
  "properties": {
    "iso:country":"US",
    "sg:address":"1675 Wright Ave",
    "sg:city":"Alma",
    "sg:classifiers":[
        {
            "category":"Restaurant",
            "type":"Food & Drink"
        }
    ],
    "sg:menulink":"http://www.allmenus.com/mi/alma/196839-burger-king/menu/",
    "sg:phone":"+1 989 463 1076",
    "sg:postcode":"48801",
    "sg:province":"MI",
    "sg:tags":[
        "burger",
        "american"
    ],
    "wof:name":"Burger King",
    "wof:placetype":"venue"
},
  "geometry": {"coordinates":[-84.66674500000001,43.395205],"type":"Point"}
}