{
  "type": "Feature",
  "properties": {
    "iso:country":"US",
    "sg:address":"1337 Airport Rd",
    "sg:city":"Niles",
    "sg:classifiers":[
        {
            "category":"Retail",
            "subcategory":"Repair Shop",
            "type":"Services"
        }
    ],
    "sg:phone":"+1 269 684 6024",
    "sg:postcode":"49120",
    "sg:province":"MI",
    "wof:name":"Swartz Excavation & Septic",
    "wof:placetype":"venue"
},
  "geometry": {"coordinates":[-86.22429700000001,41.851244],"type":"Point"}
}