{
  "type": "Feature",
  "properties": {
    "iso:country":"US",
    "sg:address":"38520 Ford Rd",
    "sg:city":"Westland",
    "sg:classifiers":[
        {
            "category":"Recreation",
            "subcategory":"Amusement Park",
            "type":"Entertainment"
        },
        {
            "category":"Sports & Exercise",
            "subcategory":"Golf",
            "type":"Entertainment"
        }
    ],
    "sg:phone":"+1 734 728 7222",
    "sg:postcode":"48185",
    "sg:province":"MI",
    "sg:tags":[
        "mini"
    ],
    "sg:website":"www.sportwayinc.com/",
    "wof:name":"SportWay of Westland",
    "wof:placetype":"venue"
},
  "geometry": {"coordinates":[-83.4188,42.323799],"type":"Point"}
}