{
  "type": "Feature",
  "properties": {
    "iso:country":"US",
    "sg:address":"200 W Main St",
    "sg:city":"Potterville",
    "sg:classifiers":[
        {
            "category":"Shopping",
            "subcategory":"Discount & Variety Stores",
            "type":"Retail Goods"
        }
    ],
    "sg:phone":"+1 517 645 4155",
    "sg:postcode":"48876",
    "sg:province":"MI",
    "sg:tags":[
        "merchandise",
        "general"
    ],
    "wof:name":"Lantrip's Mainstreet Estate",
    "wof:placetype":"venue"
},
  "geometry": {"coordinates":[-84.74385100000001,42.629379],"type":"Point"}
}