{
  "type": "Feature",
  "properties": {
    "iso:country":"US",
    "sg:address":"4318 Rochester Rd",
    "sg:city":"Royal Oak",
    "sg:classifiers":[
        {
            "category":"Insurance",
            "subcategory":"Hazard Insurance",
            "type":"Services"
        }
    ],
    "sg:phone":"+1 248 298 3046",
    "sg:postcode":"48073",
    "sg:province":"MI",
    "wof:name":"Deriveau Insurance Agency Llc",
    "wof:placetype":"venue"
},
  "geometry": {"coordinates":[-83.137123,42.527924],"type":"Point"}
}