{
  "type": "Feature",
  "properties": {
    "iso:country":"US",
    "sg:address":"220 Washington Sq S",
    "sg:city":"Lansing",
    "sg:classifiers":[
        {
            "category":"Food & Beverages",
            "subcategory":"Groceries & Convenience Stores",
            "type":"Retail Goods"
        }
    ],
    "sg:phone":"+1 517 853 0749",
    "sg:postcode":"48933",
    "sg:province":"MI",
    "wof:name":"Saini Spirits",
    "wof:placetype":"venue"
},
  "geometry": {"coordinates":[-84.55233200000001,42.731594],"type":"Point"}
}