{
  "type": "Feature",
  "properties": {
    "iso:country":"US",
    "sg:address":"616 State St",
    "sg:city":"Midland",
    "sg:classifiers":[
        {
            "category":"Manufacturing",
            "subcategory":"Jewelry",
            "type":"Manufacturing & Wholesale Goods"
        }
    ],
    "sg:phone":"+1 989 837 6547",
    "sg:postcode":"48640",
    "sg:province":"MI",
    "sg:tags":[
        "precious",
        "metal",
        "mfg"
    ],
    "wof:name":"Jajtinis",
    "wof:placetype":"venue"
},
  "geometry": {"coordinates":[-84.23506500000001,43.612558],"type":"Point"}
}