{
  "type": "Feature",
  "properties": {
    "iso:country":"US",
    "sg:address":"8772 E Lakeview Hills Rd",
    "sg:city":"Traverse City",
    "sg:classifiers":[
        {
            "category":"Farming",
            "subcategory":"Nursery",
            "type":"Manufacturing & Wholesale Goods"
        }
    ],
    "sg:phone":"+1 231 946 6529",
    "sg:postcode":"49684",
    "sg:province":"MI",
    "sg:tags":[
        "ornamental"
    ],
    "wof:name":"John Stanek Sr",
    "wof:placetype":"venue"
},
  "geometry": {"coordinates":[-85.678894,44.851647],"type":"Point"}
}