{
  "type": "Feature",
  "properties": {
    "iso:country":"US",
    "sg:address":"537 E Shevlin Ave",
    "sg:city":"Hazel Park",
    "sg:classifiers":[
        {
            "category":"Building & Trades",
            "subcategory":"Cleaning & Sanitation",
            "type":"Services"
        }
    ],
    "sg:phone":"+1 248 546 6480",
    "sg:postcode":"48030",
    "sg:province":"MI",
    "sg:tags":[
        "window",
        "maintenance"
    ],
    "wof:name":"Quality Window Cleaning Inc",
    "wof:placetype":"venue"
},
  "geometry": {"coordinates":[-83.097532,42.473307],"type":"Point"}
}