{
  "type": "Feature",
  "properties": {
    "iso:country":"US",
    "sg:address":"310 Miller Ave",
    "sg:city":"Ann Arbor",
    "sg:classifiers":[
        {
            "category":"Professional",
            "subcategory":"Management & Consulting",
            "type":"Services"
        }
    ],
    "sg:phone":"+1 734 213 7704",
    "sg:postcode":"48103",
    "sg:province":"MI",
    "sg:tags":[
        "business"
    ],
    "wof:name":"Richner & Richner L L C",
    "wof:placetype":"venue"
},
  "geometry": {"coordinates":[-83.751864,42.283623],"type":"Point"}
}