{
  "type": "Feature",
  "properties": {
    "iso:country":"US",
    "sg:address":"19466 Denby",
    "sg:city":"Redford",
    "sg:classifiers":[
        {
            "category":"Building & Trades",
            "subcategory":"Cleaning & Sanitation",
            "type":"Services"
        }
    ],
    "sg:phone":"+1 313 794 9000",
    "sg:postcode":"48240",
    "sg:province":"MI",
    "sg:tags":[
        "carpet"
    ],
    "wof:name":"Brian's 1st Class Carpet Care",
    "wof:placetype":"venue"
},
  "geometry": {"coordinates":[-83.310303,42.431801],"type":"Point"}
}