{
  "type": "Feature",
  "properties": {
    "iso:country":"US",
    "sg:address":"34 W Sheffield Ave",
    "sg:city":"Pontiac",
    "sg:classifiers":[
        {
            "category":"Manufacturing",
            "subcategory":"Metals",
            "type":"Manufacturing & Wholesale Goods"
        }
    ],
    "sg:phone":"+1 248 332 9151",
    "sg:postcode":"48340",
    "sg:province":"MI",
    "sg:tags":[
        "tube",
        "fabricating"
    ],
    "wof:name":"Trans Tube Inc",
    "wof:placetype":"venue"
},
  "geometry": {"coordinates":[-83.30243,42.675306],"type":"Point"}
}