{
  "type": "Feature",
  "properties": {
    "iso:country":"US",
    "sg:address":"3135 Howard City Edmore Rd",
    "sg:city":"Edmore",
    "sg:classifiers":[
        {
            "category":"Restaurant",
            "type":"Food & Drink"
        }
    ],
    "sg:phone":"+1 989 427 3431",
    "sg:postcode":"48829",
    "sg:province":"MI",
    "wof:name":"Beardslee's Restaurant",
    "wof:placetype":"venue"
},
  "geometry": {"coordinates":[-85.02219599999999,43.408139],"type":"Point"}
}