{
  "type": "Feature",
  "properties": {
    "iso:country":"US",
    "sg:address":"28 W Adams Ave",
    "sg:city":"Detroit",
    "sg:classifiers":[
        {
            "category":"Restaurant",
            "type":"Food & Drink"
        }
    ],
    "sg:menulink":"http://www.allmenus.com/mi/detroit/56890-subway/menu/",
    "sg:phone":"+1 313 963 9166",
    "sg:postcode":"48226",
    "sg:province":"MI",
    "sg:tags":[
        "american",
        "sandwich"
    ],
    "wof:name":"Subway",
    "wof:placetype":"venue"
},
  "geometry": {"coordinates":[-83.051328,42.336784],"type":"Point"}
}