{
  "type": "Feature",
  "properties": {
    "iso:country":"US",
    "sg:address":"39893 Duluth St",
    "sg:city":"Harrison Township",
    "sg:classifiers":[
        {
            "category":"Building & Trades",
            "subcategory":"Construction",
            "type":"Services"
        }
    ],
    "sg:phone":"+1 586 954 1845",
    "sg:postcode":"48045",
    "sg:province":"MI",
    "sg:tags":[
        "residential"
    ],
    "wof:name":"A J Bldrs",
    "wof:placetype":"venue"
},
  "geometry": {"coordinates":[-82.83515199999999,42.591128],"type":"Point"}
}