{
  "type": "Feature",
  "properties": {
    "iso:country":"US",
    "sg:address":"2534 N Genesee Rd",
    "sg:city":"Burton",
    "sg:classifiers":[
        {
            "category":"Retail",
            "subcategory":"Repair Shop",
            "type":"Services"
        }
    ],
    "sg:phone":"+1 810 744 4155",
    "sg:postcode":"48509",
    "sg:province":"MI",
    "sg:tags":[
        "related"
    ],
    "wof:name":"Appliance Technician Repair",
    "wof:placetype":"venue"
},
  "geometry": {"coordinates":[-83.61578299999999,43.043248],"type":"Point"}
}