{
  "type": "Feature",
  "properties": {
    "iso:country":"US",
    "sg:address":"587 E 8th St",
    "sg:city":"Holland",
    "sg:classifiers":[
        {
            "category":"Restaurant",
            "type":"Food & Drink"
        }
    ],
    "sg:menulink":"http://www.allmenus.com/mi/holland/142318-subway/menu/",
    "sg:phone":"+1 616 393 0123",
    "sg:postcode":"49423",
    "sg:province":"MI",
    "sg:tags":[
        "american",
        "sandwich"
    ],
    "wof:name":"Subway",
    "wof:placetype":"venue"
},
  "geometry": {"coordinates":[-86.08211799999999,42.79042],"type":"Point"}
}