{
  "type": "Feature",
  "properties": {
    "iso:country":"US",
    "sg:address":"3585 Clyde Park Ave SW",
    "sg:city":"Wyoming",
    "sg:classifiers":[
        {
            "category":"Wholesale",
            "subcategory":"Groceries",
            "type":"Manufacturing & Wholesale Goods"
        }
    ],
    "sg:phone":"+1 616 249 9395",
    "sg:postcode":"49509",
    "sg:province":"MI",
    "sg:tags":[
        "food"
    ],
    "wof:name":"Bosna Express",
    "wof:placetype":"venue"
},
  "geometry": {"coordinates":[-85.685108,42.899533],"type":"Point"}
}