{
  "type": "Feature",
  "properties": {
    "iso:country":"US",
    "sg:address":"1775 W Hamlin Rd",
    "sg:city":"Rochester",
    "sg:classifiers":[
        {
            "category":"Personal",
            "type":"Services"
        }
    ],
    "sg:phone":"+1 248 853 9898",
    "sg:postcode":"48309",
    "sg:province":"MI",
    "sg:tags":[
        "club"
    ],
    "wof:name":"U CC Total Home",
    "wof:placetype":"venue"
},
  "geometry": {"coordinates":[-83.17034099999999,42.651266],"type":"Point"}
}