{
  "type": "Feature",
  "properties": {
    "iso:country":"US",
    "sg:address":"15401 Grand River Ave",
    "sg:city":"Detroit",
    "sg:classifiers":[
        {
            "category":"Wholesale",
            "subcategory":"Drugs",
            "type":"Manufacturing & Wholesale Goods"
        }
    ],
    "sg:phone":"+1 313 835 2295",
    "sg:postcode":"48227",
    "sg:province":"MI",
    "wof:name":"Mecca Aroma",
    "wof:placetype":"venue"
},
  "geometry": {"coordinates":[-83.197643,42.392178],"type":"Point"}
}