{
  "type": "Feature",
  "properties": {
    "iso:country":"US",
    "sg:address":"28640 Gratiot Ave",
    "sg:city":"Roseville",
    "sg:classifiers":[
        {
            "category":"Real Estate",
            "subcategory":"Real Estate Services",
            "type":"Services"
        }
    ],
    "sg:phone":"+1 586 771 3814",
    "sg:postcode":"48066",
    "sg:province":"MI",
    "sg:tags":[
        "management",
        "property"
    ],
    "wof:name":"Eastern Management Co Inc",
    "wof:placetype":"venue"
},
  "geometry": {"coordinates":[-82.929703,42.507198],"type":"Point"}
}