{
  "type": "Feature",
  "properties": {
    "iso:country":"US",
    "sg:address":"11275 Harrison Ave",
    "sg:city":"Farwell",
    "sg:classifiers":[
        {
            "category":"Professional",
            "subcategory":"Art Services",
            "type":"Services"
        }
    ],
    "sg:phone":"+1 989 633 9097",
    "sg:postcode":"48622",
    "sg:province":"MI",
    "sg:tags":[
        "graphic",
        "designer"
    ],
    "wof:name":"Cornerstone Graphics",
    "wof:placetype":"venue"
},
  "geometry": {"coordinates":[-84.828311,43.825234],"type":"Point"}
}