{
  "type": "Feature",
  "properties": {
    "iso:country":"US",
    "sg:address":"3800 Munson Hwy",
    "sg:city":"Hudson",
    "sg:classifiers":[
        {
            "category":"Farming",
            "subcategory":"Farm",
            "type":"Manufacturing & Wholesale Goods"
        }
    ],
    "sg:phone":"+1 517 448 2914",
    "sg:postcode":"49247",
    "sg:province":"MI",
    "wof:name":"Rima Farmhouse",
    "wof:placetype":"venue"
},
  "geometry": {"coordinates":[-84.334197,41.858457],"type":"Point"}
}