{
  "type": "Feature",
  "properties": {
    "iso:country":"US",
    "sg:address":"1405 Michigan Ave",
    "sg:city":"Benzonia",
    "sg:classifiers":[
        {
            "category":"Freight",
            "type":"Transportation"
        }
    ],
    "sg:phone":"+1 231 882 4039",
    "sg:postcode":"49616",
    "sg:province":"MI",
    "sg:tags":[
        "commercial",
        "storage"
    ],
    "wof:name":"Crystal Falls Self Storage",
    "wof:placetype":"venue"
},
  "geometry": {"coordinates":[-86.09924599999999,44.61175],"type":"Point"}
}