{
  "type": "Feature",
  "properties": {
    "iso:country":"US",
    "sg:address":"20221 Joy Rd",
    "sg:city":"Detroit",
    "sg:classifiers":[
        {
            "category":"Food & Beverages",
            "subcategory":"Groceries & Convenience Stores",
            "type":"Retail Goods"
        }
    ],
    "sg:phone":"+1 313 846 7555",
    "sg:postcode":"48228",
    "sg:province":"MI",
    "wof:name":"Saturn Super Foods",
    "wof:placetype":"venue"
},
  "geometry": {"coordinates":[-83.238602,42.357399],"type":"Point"}
}