{
  "type": "Feature",
  "properties": {
    "iso:country":"US",
    "sg:address":"21578 Hidden Rivers Dr S",
    "sg:city":"Southfield",
    "sg:classifiers":[
        {
            "category":"Building & Trades",
            "subcategory":"Construction",
            "type":"Services"
        }
    ],
    "sg:phone":"+1 248 355 3669",
    "sg:postcode":"48075",
    "sg:province":"MI",
    "sg:tags":[
        "general",
        "contractor"
    ],
    "wof:name":"Nu Metro Construction Svc",
    "wof:placetype":"venue"
},
  "geometry": {"coordinates":[-83.25747699999999,42.464712],"type":"Point"}
}