{
  "type": "Feature",
  "properties": {
    "iso:country":"US",
    "sg:address":"1050 Stewart Rd",
    "sg:city":"Monroe",
    "sg:classifiers":[
        {
            "category":"Retail",
            "subcategory":"Auto Rental",
            "type":"Services"
        }
    ],
    "sg:phone":"+1 734 243 9414",
    "sg:postcode":"48162",
    "sg:province":"MI",
    "sg:tags":[
        "renting",
        "truck",
        "leasing"
    ],
    "wof:name":"Budget Truck Rental",
    "wof:placetype":"venue"
},
  "geometry": {"coordinates":[-83.401568,41.941683],"type":"Point"}
}