{
  "type": "Feature",
  "properties": {
    "iso:country":"US",
    "sg:address":"103 S Capital Ave",
    "sg:city":"Athens",
    "sg:classifiers":[
        {
            "category":"Real Estate",
            "subcategory":"Real Estate Agent",
            "type":"Services"
        }
    ],
    "sg:phone":"+1 269 729 5355",
    "sg:postcode":"49011",
    "sg:province":"MI",
    "sg:tags":[
        "inspection"
    ],
    "wof:name":"South Central Mi Construction",
    "wof:placetype":"venue"
},
  "geometry": {"coordinates":[-85.235491,42.087931],"type":"Point"}
}