{
  "type": "Feature",
  "properties": {
    "iso:country":"US",
    "sg:address":"6720 Ainsworth Rd",
    "sg:city":"Ionia",
    "sg:classifiers":[
        {
            "category":"Farming",
            "subcategory":"Farm",
            "type":"Manufacturing & Wholesale Goods"
        }
    ],
    "sg:phone":"+1 616 527 5910",
    "sg:postcode":"48846",
    "sg:province":"MI",
    "sg:tags":[
        "petting",
        "zoo"
    ],
    "sg:website":"www.homesteadacres.com",
    "wof:name":"Homestead Acres",
    "wof:placetype":"venue"
},
  "geometry": {"coordinates":[-85.11456099999999,42.889971],"type":"Point"}
}