{
  "type": "Feature",
  "properties": {
    "iso:country":"US",
    "sg:address":"5380 Holiday Ter",
    "sg:city":"Kalamazoo",
    "sg:classifiers":[
        {
            "category":"Health Services",
            "subcategory":"Health Practitioner",
            "type":"Services"
        }
    ],
    "sg:phone":"+1 269 375 0778",
    "sg:postcode":"49009",
    "sg:province":"MI",
    "sg:tags":[
        "psychologist"
    ],
    "wof:name":"Merry Carson",
    "wof:placetype":"venue"
},
  "geometry": {"coordinates":[-85.656597,42.265106],"type":"Point"}
}