{
  "type": "Feature",
  "properties": {
    "iso:country":"US",
    "sg:address":"7869 Belleau Rd",
    "sg:city":"Fair Haven",
    "sg:classifiers":[
        {
            "category":"Building & Trades",
            "subcategory":"Cleaning & Sanitation",
            "type":"Services"
        }
    ],
    "sg:phone":"+1 586 725 2595",
    "sg:postcode":"48023",
    "sg:province":"MI",
    "sg:tags":[
        "maintenance"
    ],
    "wof:name":"Long Island Cleaning",
    "wof:placetype":"venue"
},
  "geometry": {"coordinates":[-82.62658999999999,42.671476],"type":"Point"}
}