{
  "type": "Feature",
  "properties": {
    "iso:country":"US",
    "sg:address":"19449 Livernois Ave",
    "sg:city":"Detroit",
    "sg:classifiers":[
        {
            "category":"Shopping",
            "subcategory":"Clothing, Apparel, & Fashions",
            "type":"Retail Goods"
        }
    ],
    "sg:phone":"+1 313 862 0003",
    "sg:postcode":"48221",
    "sg:province":"MI",
    "sg:tags":[
        "children's",
        "clothing"
    ],
    "wof:name":"Miller's Children's Apparel",
    "wof:placetype":"venue"
},
  "geometry": {"coordinates":[-83.1418,42.436298],"type":"Point"}
}