{
  "type": "Feature",
  "properties": {
    "iso:country":"US",
    "sg:address":"4261 W U Ave",
    "sg:city":"Schoolcraft",
    "sg:classifiers":[
        {
            "category":"Restaurant",
            "type":"Food & Drink"
        }
    ],
    "sg:phone":"+1 269 679 3656",
    "sg:postcode":"49087",
    "sg:province":"MI",
    "sg:tags":[
        "caterer"
    ],
    "wof:name":"Schnauzers Banquet Hall",
    "wof:placetype":"venue"
},
  "geometry": {"coordinates":[-85.639126,42.143272],"type":"Point"}
}