{
  "type": "Feature",
  "properties": {
    "iso:country":"US",
    "sg:address":"2262 Glenlord Rd",
    "sg:city":"Stevensville",
    "sg:classifiers":[
        {
            "category":"Restaurant",
            "type":"Food & Drink"
        }
    ],
    "sg:phone":"+1 269 429 3966",
    "sg:postcode":"49127",
    "sg:province":"MI",
    "sg:tags":[
        "pizza"
    ],
    "wof:name":"Santaniello's Glenlord Rstrnt",
    "wof:placetype":"venue"
},
  "geometry": {"coordinates":[-86.508679,42.043317],"type":"Point"}
}