{
  "type": "Feature",
  "properties": {
    "iso:country":"US",
    "sg:address":"200 N Occidental Hwy",
    "sg:city":"Tecumseh",
    "sg:classifiers":[
        {
            "category":"Real Estate",
            "subcategory":"Real Estate Operator",
            "type":"Services"
        }
    ],
    "sg:phone":"+1 517 423 6309",
    "sg:postcode":"49286",
    "sg:province":"MI",
    "sg:tags":[
        "apartment"
    ],
    "wof:name":"Stonehenge Tecumseh",
    "wof:placetype":"venue"
},
  "geometry": {"coordinates":[-83.965012,42.009958],"type":"Point"}
}