{
  "type": "Feature",
  "properties": {
    "iso:country":"US",
    "sg:address":"24882 5 Mile Rd",
    "sg:city":"Redford",
    "sg:classifiers":[
        {
            "category":"Building & Trades",
            "subcategory":"Plumbing",
            "type":"Services"
        }
    ],
    "sg:phone":"+1 313 533 1046",
    "sg:postcode":"48239",
    "sg:province":"MI",
    "wof:name":"Plumbing Zeb",
    "wof:placetype":"venue"
},
  "geometry": {"coordinates":[-83.285439,42.399962],"type":"Point"}
}