{
  "type": "Feature",
  "properties": {
    "iso:country":"US",
    "sg:address":"222 S Monroe St",
    "sg:city":"Monroe",
    "sg:classifiers":[
        {
            "category":"Home & Garden",
            "subcategory":"Furniture",
            "type":"Retail Goods"
        }
    ],
    "sg:phone":"+1 734 241 7626",
    "sg:postcode":"48161",
    "sg:province":"MI",
    "wof:name":"Durochers La-Z-Boy",
    "wof:placetype":"venue"
},
  "geometry": {"coordinates":[-83.399097,41.914773],"type":"Point"}
}