{
  "type": "Feature",
  "properties": {
    "iso:country":"US",
    "sg:address":"18580 Mack Ave",
    "sg:city":"Grosse Pointe",
    "sg:classifiers":[
        {
            "category":"Professional",
            "subcategory":"Lawyer & Legal Services",
            "type":"Services"
        }
    ],
    "sg:phone":"+1 313 885 6800",
    "sg:postcode":"48236",
    "sg:province":"MI",
    "wof:name":"Draper David Atty",
    "wof:placetype":"venue"
},
  "geometry": {"coordinates":[-82.9123,42.412498],"type":"Point"}
}