{
  "type": "Feature",
  "properties": {
    "iso:country":"US",
    "sg:address":"1450 W Main St SE",
    "sg:city":"Lowell",
    "sg:classifiers":[
        {
            "category":"Retail",
            "subcategory":"Auto Repair",
            "type":"Services"
        }
    ],
    "sg:phone":"+1 616 897 5166",
    "sg:postcode":"49331",
    "sg:province":"MI",
    "sg:tags":[
        "automotive"
    ],
    "wof:name":"River City Auto Service",
    "wof:placetype":"venue"
},
  "geometry": {"coordinates":[-85.35576500000001,42.93131],"type":"Point"}
}