{
  "type": "Feature",
  "properties": {
    "iso:country":"US",
    "sg:address":"55221 Shelby Rd",
    "sg:city":"Shelby Twp",
    "sg:classifiers":[
        {
            "category":"Education",
            "subcategory":"Dance Studio",
            "type":"Public Place"
        }
    ],
    "sg:phone":"+1 248 656 3087",
    "sg:postcode":"48316",
    "sg:province":"MI",
    "sg:tags":[
        "instruction",
        "dancing"
    ],
    "wof:name":"K & T's Dance Ctr & Dancewear",
    "wof:placetype":"venue"
},
  "geometry": {"coordinates":[-83.069777,42.699096],"type":"Point"}
}