{
  "type": "Feature",
  "properties": {
    "iso:country":"US",
    "sg:address":"8881 Beech Daly Rd",
    "sg:city":"Redford",
    "sg:classifiers":[
        {
            "category":"Health Services",
            "subcategory":"Doctor",
            "type":"Services"
        }
    ],
    "sg:phone":"+1 313 937 1520",
    "sg:postcode":"48239",
    "sg:province":"MI",
    "sg:tags":[
        "surgeon",
        "oral"
    ],
    "wof:name":"Mulka Laurie DDS",
    "wof:placetype":"venue"
},
  "geometry": {"coordinates":[-83.294403,42.357399],"type":"Point"}
}