{
  "type": "Feature",
  "properties": {
    "iso:country":"US",
    "sg:address":"570 Kirts Blvd",
    "sg:city":"Troy",
    "sg:classifiers":[
        {
            "category":"Professional",
            "subcategory":"Printing & Photocopies",
            "type":"Services"
        }
    ],
    "sg:phone":"+1 248 269 8350",
    "sg:postcode":"48084",
    "sg:province":"MI",
    "wof:name":"Docusource",
    "wof:placetype":"venue"
},
  "geometry": {"coordinates":[-83.15619700000001,42.556702],"type":"Point"}
}