{
  "type": "Feature",
  "properties": {
    "iso:country":"US",
    "sg:address":"616 W Shiawassee St",
    "sg:city":"Lansing",
    "sg:classifiers":[
        {
            "category":"Organizations",
            "subcategory":"Non-profit Organization",
            "type":"Services"
        },
        {
            "category":"Health Services",
            "subcategory":"Clinic",
            "type":"Services"
        }
    ],
    "sg:phone":"+1 517 485 7170",
    "sg:postcode":"48933",
    "sg:province":"MI",
    "sg:tags":[
        "specialty",
        "outpatient"
    ],
    "wof:name":"Richard's Place",
    "wof:placetype":"venue"
},
  "geometry": {"coordinates":[-84.561334,42.737411],"type":"Point"}
}