{
  "type": "Feature",
  "properties": {
    "iso:country":"US",
    "sg:address":"6835 E Apple Ave",
    "sg:city":"Muskegon",
    "sg:classifiers":[
        {
            "category":"Retail",
            "subcategory":"Auto Repair",
            "type":"Services"
        }
    ],
    "sg:phone":"+1 231 788 3261",
    "sg:postcode":"49442",
    "sg:province":"MI",
    "sg:tags":[
        "body",
        "re",
        "general",
        "supply"
    ],
    "wof:name":"APS & Performance Collision",
    "wof:placetype":"venue"
},
  "geometry": {"coordinates":[-86.069379,43.234904],"type":"Point"}
}