{
  "type": "Feature",
  "properties": {
    "iso:country":"US",
    "sg:address":"3310 W Big Beaver Rd",
    "sg:city":"Troy",
    "sg:classifiers":[
        {
            "category":"Banks & Credit Unions",
            "subcategory":"Investment Brokerage",
            "type":"Services"
        }
    ],
    "sg:phone":"+1 248 649 4759",
    "sg:postcode":"48084",
    "sg:province":"MI",
    "sg:tags":[
        "consultant",
        "planning",
        "financial"
    ],
    "wof:name":"Asset Advisors",
    "wof:placetype":"venue"
},
  "geometry": {"coordinates":[-83.193592,42.561127],"type":"Point"}
}