{
  "type": "Feature",
  "properties": {
    "iso:country":"US",
    "sg:address":"4477 Cascade Rd SE",
    "sg:city":"Grand Rapids",
    "sg:classifiers":[
        {
            "category":"Social Services",
            "type":"Services"
        }
    ],
    "sg:phone":"+1 616 957 4140",
    "sg:postcode":"49546",
    "sg:province":"MI",
    "wof:name":"Shawn Hordyk Msw Acsw",
    "wof:placetype":"venue"
},
  "geometry": {"coordinates":[-85.558324,42.946299],"type":"Point"}
}