{
  "type": "Feature",
  "properties": {
    "iso:country":"US",
    "sg:address":"4970 Railroad St",
    "sg:city":"Elkton",
    "sg:classifiers":[
        {
            "category":"Health Services",
            "subcategory":"Doctor",
            "type":"Services"
        }
    ],
    "sg:phone":"+1 989 375 2214",
    "sg:postcode":"48731",
    "sg:province":"MI",
    "sg:tags":[
        "clinic"
    ],
    "wof:name":"Elkton Family Medicine",
    "wof:placetype":"venue"
},
  "geometry": {"coordinates":[-83.179856,43.81918],"type":"Point"}
}