{
  "type": "Feature",
  "properties": {
    "iso:country":"US",
    "sg:address":"1690 W Sterns Rd",
    "sg:city":"Temperance",
    "sg:classifiers":[
        {
            "category":"Social Services",
            "subcategory":"Child Care",
            "type":"Services"
        }
    ],
    "sg:phone":"+1 734 847 0531",
    "sg:postcode":"48182",
    "sg:province":"MI",
    "sg:tags":[
        "kindergarten",
        "academic",
        "school",
        "day"
    ],
    "wof:name":"Play & Learn Preschool Inc",
    "wof:placetype":"venue"
},
  "geometry": {"coordinates":[-83.58549499999999,41.750126],"type":"Point"}
}