{
  "type": "Feature",
  "properties": {
    "iso:country":"US",
    "sg:address":"1145 Ironwood Ct",
    "sg:city":"Rochester",
    "sg:classifiers":[
        {
            "category":"Professional",
            "subcategory":"Advertising",
            "type":"Services"
        }
    ],
    "sg:phone":"+1 248 390 5649",
    "sg:postcode":"48307",
    "sg:province":"MI",
    "sg:tags":[
        "gathering",
        "promoting",
        "social"
    ],
    "wof:name":"Infinity Entertainment",
    "wof:placetype":"venue"
},
  "geometry": {"coordinates":[-83.14417299999999,42.687494],"type":"Point"}
}