{
  "type": "Feature",
  "properties": {
    "iso:country":"US",
    "sg:address":"1221 Royce Ave",
    "sg:city":"Kalamazoo",
    "sg:classifiers":[
        {
            "category":"Retail",
            "subcategory":"Repair Shop",
            "type":"Services"
        }
    ],
    "sg:phone":"+1 269 349 3040",
    "sg:postcode":"49001",
    "sg:province":"MI",
    "sg:tags":[
        "ironwork"
    ],
    "wof:name":"Rwr Timber & Iron Products",
    "wof:placetype":"venue"
},
  "geometry": {"coordinates":[-85.566745,42.255445],"type":"Point"}
}