{
  "type": "Feature",
  "properties": {
    "iso:country":"US",
    "sg:address":"9400 Courville St",
    "sg:city":"Detroit",
    "sg:classifiers":[
        {
            "category":"Education",
            "subcategory":"Special Training",
            "type":"Public Place"
        }
    ],
    "sg:phone":"+1 313 882 4853",
    "sg:postcode":"48224",
    "sg:province":"MI",
    "wof:name":"Dominican Literacy Center",
    "wof:placetype":"venue"
},
  "geometry": {"coordinates":[-82.94813499999999,42.412891],"type":"Point"}
}