{
  "type": "Feature",
  "properties": {
    "iso:country":"US",
    "sg:address":"909 W Maple Rd Ste 106",
    "sg:city":"Clawson",
    "sg:classifiers":[
        {
            "category":"Health Services",
            "subcategory":"Chiropractor",
            "type":"Services"
        }
    ],
    "sg:phone":"+1 248 288 3280",
    "sg:postcode":"48017",
    "sg:province":"MI",
    "wof:name":"Signature Chiropractic",
    "wof:placetype":"venue"
},
  "geometry": {"coordinates":[-83.160202,42.5481],"type":"Point"}
}