{
  "type": "Feature",
  "properties": {
    "iso:country":"US",
    "sg:address":"3480 125th Ave",
    "sg:city":"Allegan",
    "sg:classifiers":[
        {
            "category":"Manufacturing",
            "subcategory":"Wood Products",
            "type":"Manufacturing & Wholesale Goods"
        }
    ],
    "sg:phone":"+1 269 673 6802",
    "sg:postcode":"49010",
    "sg:province":"MI",
    "sg:tags":[
        "pallet",
        "skid"
    ],
    "wof:name":"Gleason Crating Mill",
    "wof:placetype":"venue"
},
  "geometry": {"coordinates":[-85.882589,42.601261],"type":"Point"}
}