{
  "type": "Feature",
  "properties": {
    "iso:country":"US",
    "sg:address":"6684 Dixie Hwy",
    "sg:city":"Clarkston",
    "sg:classifiers":[
        {
            "category":"Professional",
            "subcategory":"Secretarial Services",
            "type":"Services"
        }
    ],
    "sg:phone":"+1 248 620 8900",
    "sg:postcode":"48346",
    "sg:province":"MI",
    "wof:name":"Your Personal Secretary",
    "wof:placetype":"venue"
},
  "geometry": {"coordinates":[-83.416417,42.718498],"type":"Point"}
}