{
  "type": "Feature",
  "properties": {
    "iso:country":"US",
    "sg:address":"910 W Commerce Dr",
    "sg:city":"Traverse City",
    "sg:classifiers":[
        {
            "category":"Mining & Drilling",
            "type":"Manufacturing & Wholesale Goods"
        }
    ],
    "sg:phone":"+1 231 943 9900",
    "sg:postcode":"49684",
    "sg:province":"MI",
    "sg:tags":[
        "field",
        "oil"
    ],
    "wof:name":"Oilfield Tools Inc",
    "wof:placetype":"venue"
},
  "geometry": {"coordinates":[-85.665817,44.673819],"type":"Point"}
}