{
  "type": "Feature",
  "properties": {
    "iso:country":"US",
    "sg:address":"48200 Perkins Blvd",
    "sg:city":"New Buffalo",
    "sg:classifiers":[
        {
            "category":"Sports & Exercise",
            "subcategory":"Golf",
            "type":"Entertainment"
        }
    ],
    "sg:phone":"+1 269 469 4888",
    "sg:postcode":"49117",
    "sg:province":"MI",
    "sg:tags":[
        "course"
    ],
    "wof:name":"Grand Beach Golf Course",
    "wof:placetype":"venue"
},
  "geometry": {"coordinates":[-86.794842,41.772359],"type":"Point"}
}