{
  "type": "Feature",
  "properties": {
    "iso:country":"US",
    "sg:address":"505 Sunday Lake St",
    "sg:city":"Wakefield",
    "sg:classifiers":[
        {
            "category":"Food & Beverages",
            "subcategory":"Bakery",
            "type":"Retail Goods"
        }
    ],
    "sg:phone":"+1 906 224 5401",
    "sg:postcode":"49968",
    "sg:province":"MI",
    "sg:tags":[
        "baker"
    ],
    "wof:name":"Roger Randall Bakery",
    "wof:placetype":"venue"
},
  "geometry": {"coordinates":[-89.941187,46.473639],"type":"Point"}
}