{
  "type": "Feature",
  "properties": {
    "iso:country":"US",
    "sg:address":"104 E Grand River Ave",
    "sg:city":"Howell",
    "sg:classifiers":[
        {
            "category":"Personal",
            "subcategory":"Beauty Salon",
            "type":"Services"
        }
    ],
    "sg:phone":"+1 517 546 7797",
    "sg:postcode":"48843",
    "sg:province":"MI",
    "wof:name":"Carolyn Cunnings",
    "wof:placetype":"venue"
},
  "geometry": {"coordinates":[-83.92957,42.607241],"type":"Point"}
}