{
  "type": "Feature",
  "properties": {
    "iso:country":"US",
    "sg:address":"899 Enterprise Way",
    "sg:city":"Benton Harbor",
    "sg:classifiers":[
        {
            "category":"Manufacturing",
            "subcategory":"Tools & Machinery",
            "type":"Manufacturing & Wholesale Goods"
        }
    ],
    "sg:phone":"+1 269 923 6666",
    "sg:postcode":"49022",
    "sg:province":"MI",
    "sg:tags":[
        "appliance"
    ],
    "sg:website":"www.whirlpool.com",
    "wof:name":"Whirlpool Corp",
    "wof:placetype":"venue"
},
  "geometry": {"coordinates":[-86.442847,42.138735],"type":"Point"}
}