{
  "type": "Feature",
  "properties": {
    "iso:country":"US",
    "sg:address":"67695 Hidden Oak Ln",
    "sg:city":"Washington",
    "sg:classifiers":[
        {
            "category":"Shopping",
            "type":"Retail Goods"
        }
    ],
    "sg:phone":"+1 586 752 7388",
    "sg:postcode":"48095",
    "sg:province":"MI",
    "sg:tags":[
        "art",
        "gallery",
        "dealer"
    ],
    "wof:name":"Fell Art",
    "wof:placetype":"venue"
},
  "geometry": {"coordinates":[-83.044724,42.788801],"type":"Point"}
}