{
  "type": "Feature",
  "properties": {
    "iso:country":"US",
    "sg:address":"21369 Hall Rd",
    "sg:city":"Trenton",
    "sg:classifiers":[
        {
            "category":"Professional",
            "subcategory":"Management & Consulting",
            "type":"Services"
        }
    ],
    "sg:phone":"+1 734 675 7511",
    "sg:postcode":"48183",
    "sg:province":"MI",
    "wof:name":"Delta Quality Group Inc",
    "wof:placetype":"venue"
},
  "geometry": {"coordinates":[-83.24606300000001,42.151371],"type":"Point"}
}