{
  "type": "Feature",
  "properties": {
    "iso:country":"US",
    "sg:address":"1901 S Euclid Ave",
    "sg:city":"Bay City",
    "sg:classifiers":[
        {
            "category":"Banks & Credit Unions",
            "subcategory":"Bank",
            "type":"Services"
        }
    ],
    "sg:phone":"+1 989 686 4777",
    "sg:postcode":"48706",
    "sg:province":"MI",
    "sg:tags":[
        "cashing",
        "check"
    ],
    "wof:name":"Instant Cash Advance",
    "wof:placetype":"venue"
},
  "geometry": {"coordinates":[-83.91575899999999,43.580344],"type":"Point"}
}