{
  "type": "Feature",
  "properties": {
    "iso:country":"US",
    "sg:address":"923 S Main St",
    "sg:city":"Adrian",
    "sg:classifiers":[
        {
            "category":"Restaurant",
            "type":"Food & Drink"
        }
    ],
    "sg:menulink":"http://www.allmenus.com/mi/adrian/68849-marcos-pizza/menu/",
    "sg:phone":"+1 517 265 3333",
    "sg:postcode":"49221",
    "sg:province":"MI",
    "sg:tags":[
        "american",
        "pizza"
    ],
    "wof:name":"Marco's Pizza",
    "wof:placetype":"venue"
},
  "geometry": {"coordinates":[-84.043406,41.88575],"type":"Point"}
}