{
  "type": "Feature",
  "properties": {
    "iso:country":"US",
    "sg:address":"9114 Pierson St",
    "sg:city":"Detroit",
    "sg:classifiers":[
        {
            "category":"Communications",
            "type":"Services"
        }
    ],
    "sg:phone":"+1 313 272 1623",
    "sg:postcode":"48228",
    "sg:province":"MI",
    "sg:tags":[
        "communication"
    ],
    "wof:name":"L West Communications",
    "wof:placetype":"venue"
},
  "geometry": {"coordinates":[-83.244478,42.359925],"type":"Point"}
}