{
  "type": "Feature",
  "properties": {
    "iso:country":"US",
    "sg:address":"3603 Sandhurst Dr",
    "sg:city":"Lansing",
    "sg:classifiers":[
        {
            "category":"Shopping",
            "subcategory":"Department Store",
            "type":"Retail Goods"
        }
    ],
    "sg:phone":"+1 517 882 2533",
    "sg:postcode":"48911",
    "sg:province":"MI",
    "wof:name":"Just More",
    "wof:placetype":"venue"
},
  "geometry": {"coordinates":[-84.601691,42.703321],"type":"Point"}
}