{
  "type": "Feature",
  "properties": {
    "iso:country":"US",
    "sg:address":"4674 Buzzell Rd",
    "sg:city":"Gladwin",
    "sg:classifiers":[
        {
            "category":"Farming",
            "subcategory":"Livestock Farm",
            "type":"Manufacturing & Wholesale Goods"
        }
    ],
    "sg:phone":"+1 989 426 7202",
    "sg:postcode":"48624",
    "sg:province":"MI",
    "sg:tags":[
        "beef",
        "feedlot",
        "cattle"
    ],
    "wof:name":"Robert Buzzell",
    "wof:placetype":"venue"
},
  "geometry": {"coordinates":[-84.56021699999999,43.974015],"type":"Point"}
}