{
  "type": "Feature",
  "properties": {
    "iso:country":"US",
    "sg:address":"2376 S Charlton Park Rd",
    "sg:city":"Hastings",
    "sg:classifiers":[
        {
            "category":"Building & Trades",
            "subcategory":"Construction",
            "type":"Services"
        }
    ],
    "sg:phone":"+1 269 945 4272",
    "sg:postcode":"49058",
    "sg:province":"MI",
    "sg:tags":[
        "water",
        "well",
        "drilling"
    ],
    "wof:name":"Lewis Well Drilling",
    "wof:placetype":"venue"
},
  "geometry": {"coordinates":[-85.211744,42.619538],"type":"Point"}
}