{
  "type": "Feature",
  "properties": {
    "iso:country":"US",
    "sg:address":"901 W Huron River Dr",
    "sg:city":"Belleville",
    "sg:classifiers":[
        {
            "category":"Social Services",
            "subcategory":"Adult Care",
            "type":"Services"
        }
    ],
    "sg:phone":"+1 734 697 8461",
    "sg:postcode":"48111",
    "sg:province":"MI",
    "sg:tags":[
        "residential"
    ],
    "wof:name":"Huron House",
    "wof:placetype":"venue"
},
  "geometry": {"coordinates":[-83.49951299999999,42.202277],"type":"Point"}
}