{
  "type": "Feature",
  "properties": {
    "iso:country":"US",
    "sg:address":"25157 Appleton Dr",
    "sg:city":"Farmington Hills",
    "sg:classifiers":[
        {
            "category":"Professional",
            "subcategory":"Business Services",
            "type":"Services"
        }
    ],
    "sg:phone":"+1 248 477 4635",
    "sg:postcode":"48336",
    "sg:province":"MI",
    "sg:tags":[
        "interior",
        "consultant",
        "design",
        "decorator"
    ],
    "wof:name":"HAG Interiors",
    "wof:placetype":"venue"
},
  "geometry": {"coordinates":[-83.322715,42.478919],"type":"Point"}
}