{
  "type": "Feature",
  "properties": {
    "iso:country":"US",
    "sg:address":"116 Tawas St",
    "sg:city":"East Tawas",
    "sg:classifiers":[
        {
            "category":"Home & Garden",
            "subcategory":"Furniture",
            "type":"Retail Goods"
        }
    ],
    "sg:phone":"+1 989 362 3437",
    "sg:postcode":"48730",
    "sg:province":"MI",
    "wof:name":"O'Connor's",
    "wof:placetype":"venue"
},
  "geometry": {"coordinates":[-83.488181,44.280991],"type":"Point"}
}