{
  "type": "Feature",
  "properties": {
    "iso:country":"US",
    "sg:address":"1967 W Midland Rd",
    "sg:city":"Auburn",
    "sg:classifiers":[
        {
            "category":"Building & Trades",
            "subcategory":"Construction",
            "type":"Services"
        }
    ],
    "sg:phone":"+1 989 859 5287",
    "sg:postcode":"48611",
    "sg:province":"MI",
    "sg:tags":[
        "painter"
    ],
    "wof:name":"A-1 Affordable Paint",
    "wof:placetype":"venue"
},
  "geometry": {"coordinates":[-84.127859,43.604237],"type":"Point"}
}