{
  "type": "Feature",
  "properties": {
    "iso:country":"US",
    "sg:address":"250 S Haven St",
    "sg:city":"South Haven",
    "sg:classifiers":[
        {
            "category":"Home & Garden",
            "subcategory":"Carpets & Floor Coverings",
            "type":"Retail Goods"
        }
    ],
    "sg:phone":"+1 269 637 5808",
    "sg:postcode":"49090",
    "sg:province":"MI",
    "sg:tags":[
        "dealer",
        "rug"
    ],
    "wof:name":"Carpet Shop LTD",
    "wof:placetype":"venue"
},
  "geometry": {"coordinates":[-86.278836,42.396359],"type":"Point"}
}