{
  "type": "Feature",
  "properties": {
    "iso:country":"US",
    "sg:address":"5047 Cardinal Ct",
    "sg:city":"Troy",
    "sg:classifiers":[
        {
            "category":"Manufacturing",
            "subcategory":"Printing",
            "type":"Manufacturing & Wholesale Goods"
        }
    ],
    "sg:phone":"+1 248 673 4700",
    "sg:postcode":"48098",
    "sg:province":"MI",
    "sg:tags":[
        "printer"
    ],
    "wof:name":"Proforma Michigan Business",
    "wof:placetype":"venue"
},
  "geometry": {"coordinates":[-83.192241,42.591432],"type":"Point"}
}