{
  "type": "Feature",
  "properties": {
    "iso:country":"US",
    "sg:address":"124 N Saginaw St",
    "sg:city":"Holly",
    "sg:classifiers":[
        {
            "category":"Health Services",
            "subcategory":"Doctor",
            "type":"Services"
        }
    ],
    "sg:phone":"+1 248 634 1976",
    "sg:postcode":"48442",
    "sg:province":"MI",
    "sg:tags":[
        "dentist"
    ],
    "sg:website":"www.creativesmiles.com",
    "wof:name":"Creative Smiles Dental Group",
    "wof:placetype":"venue"
},
  "geometry": {"coordinates":[-83.62760400000001,42.792095],"type":"Point"}
}