{
  "type": "Feature",
  "properties": {
    "iso:country":"US",
    "sg:address":"19660 Hilton Dr",
    "sg:city":"Southfield",
    "sg:classifiers":[
        {
            "category":"Building & Trades",
            "subcategory":"Construction",
            "type":"Services"
        }
    ],
    "sg:phone":"+1 248 827 1547",
    "sg:postcode":"48075",
    "sg:province":"MI",
    "sg:tags":[
        "dry wall",
        "contractor"
    ],
    "wof:name":"B & D Drywall",
    "wof:placetype":"venue"
},
  "geometry": {"coordinates":[-83.239514,42.473953],"type":"Point"}
}