{
  "type": "Feature",
  "properties": {
    "iso:country":"US",
    "sg:address":"8350 Winding Creek Dr SE",
    "sg:city":"Caledonia",
    "sg:classifiers":[
        {
            "category":"Professional",
            "subcategory":"Art Services",
            "type":"Services"
        }
    ],
    "sg:phone":"+1 616 891 1284",
    "sg:postcode":"49316",
    "sg:province":"MI",
    "sg:tags":[
        "graphic",
        "designer"
    ],
    "wof:name":"Design Works",
    "wof:placetype":"venue"
},
  "geometry": {"coordinates":[-85.528801,42.812804],"type":"Point"}
}