{
  "type": "Feature",
  "properties": {
    "iso:country":"US",
    "sg:address":"475 E Lansing Rd",
    "sg:city":"East Lansing",
    "sg:classifiers":[
        {
            "category":"Education",
            "subcategory":"College",
            "type":"Public Place"
        }
    ],
    "sg:phone":"+1 517 355 1878",
    "sg:postcode":"48857",
    "sg:province":"MI",
    "wof:name":"Business College",
    "wof:placetype":"venue"
},
  "geometry": {"coordinates":[-84.154483,42.854055],"type":"Point"}
}