{
  "type": "Feature",
  "properties": {
    "iso:country":"US",
    "sg:address":"8254 Livernois Ave",
    "sg:city":"Detroit",
    "sg:classifiers":[
        {
            "category":"Retail",
            "subcategory":"Car Wash",
            "type":"Services"
        }
    ],
    "sg:phone":"+1 313 895 4657",
    "sg:postcode":"48204",
    "sg:province":"MI",
    "sg:tags":[
        "carwash"
    ],
    "wof:name":"New Way Car Wash",
    "wof:placetype":"venue"
},
  "geometry": {"coordinates":[-83.13767900000001,42.354732],"type":"Point"}
}