{
  "type": "Feature",
  "properties": {
    "iso:country":"US",
    "sg:address":"50 Hudson Ave",
    "sg:city":"Pontiac",
    "sg:classifiers":[
        {
            "category":"Real Estate",
            "subcategory":"Real Estate Agent",
            "type":"Services"
        },
        {
            "category":"Professional",
            "subcategory":"Business Services",
            "type":"Services"
        }
    ],
    "sg:phone":"+1 248 334 5214",
    "sg:postcode":"48342",
    "sg:province":"MI",
    "sg:tags":[
        "consultant"
    ],
    "wof:name":"C & W Enterprises",
    "wof:placetype":"venue"
},
  "geometry": {"coordinates":[-83.301115,42.653697],"type":"Point"}
}