{
  "type": "Feature",
  "properties": {
    "iso:country":"US",
    "sg:address":"123 Maple St",
    "sg:city":"Sault Ste Marie",
    "sg:classifiers":[
        {
            "category":"Retail",
            "subcategory":"Auto Repair",
            "type":"Services"
        }
    ],
    "sg:phone":"+1 906 635 1052",
    "sg:postcode":"49783",
    "sg:province":"MI",
    "sg:tags":[
        "repairing",
        "automobile",
        "general"
    ],
    "wof:name":"Precision Automotive Towing",
    "wof:placetype":"venue"
},
  "geometry": {"coordinates":[-84.34604,46.499096],"type":"Point"}
}