{
  "type": "Feature",
  "properties": {
    "iso:country":"US",
    "sg:address":"4325 Breton Rd SE",
    "sg:city":"Grand Rapids",
    "sg:classifiers":[
        {
            "category":"Personal",
            "subcategory":"Beauty Salon",
            "type":"Services"
        }
    ],
    "sg:phone":"+1 616 827 1045",
    "sg:postcode":"49512",
    "sg:province":"MI",
    "sg:tags":[
        "shop"
    ],
    "wof:name":"Supercuts",
    "wof:placetype":"venue"
},
  "geometry": {"coordinates":[-85.60663700000001,42.887643],"type":"Point"}
}