{
  "type": "Feature",
  "properties": {
    "iso:country":"US",
    "sg:address":"11940 Middlebelt Rd",
    "sg:city":"Livonia",
    "sg:classifiers":[
        {
            "category":"Wholesale",
            "subcategory":"Medical Equipment & Supplies",
            "type":"Manufacturing & Wholesale Goods"
        },
        {
            "category":"Shopping",
            "subcategory":"Pharmacy",
            "type":"Retail Goods"
        }
    ],
    "sg:phone":"+1 734 422 4234",
    "sg:postcode":"48150",
    "sg:province":"MI",
    "sg:tags":[
        "home",
        "health",
        "care"
    ],
    "sg:website":"http://www.a1mobilitycenter.com",
    "wof:name":"A-1 Mobility Center, Inc.",
    "wof:placetype":"venue"
},
  "geometry": {"coordinates":[-83.33321100000001,42.372289],"type":"Point"}
}