{
  "type": "Feature",
  "properties": {
    "iso:country":"US",
    "sg:address":"989 Fuller",
    "sg:city":"White Lake",
    "sg:classifiers":[
        {
            "category":"Health Services",
            "subcategory":"Health Practitioner",
            "type":"Services"
        }
    ],
    "sg:phone":"+1 248 363 8556",
    "sg:postcode":"48386",
    "sg:province":"MI",
    "wof:name":"Essence Of Self",
    "wof:placetype":"venue"
},
  "geometry": {"coordinates":[-83.49064,42.623516],"type":"Point"}
}