{
  "type": "Feature",
  "properties": {
    "iso:country":"US",
    "sg:address":"3423 E Mount Morris Rd",
    "sg:city":"Mt Morris",
    "sg:classifiers":[
        {
            "category":"Retail",
            "subcategory":"Animal Services",
            "type":"Services"
        }
    ],
    "sg:phone":"+1 810 686 2002",
    "sg:postcode":"48458",
    "sg:province":"MI",
    "sg:tags":[
        "pet",
        "boarding",
        "sitting"
    ],
    "wof:name":"Stonehill Kennels",
    "wof:placetype":"venue"
},
  "geometry": {"coordinates":[-83.63797599999999,43.120101],"type":"Point"}
}