{
  "type": "Feature",
  "properties": {
    "iso:country":"US",
    "sg:address":"5056 Mansfield Ave",
    "sg:city":"Royal Oak",
    "sg:classifiers":[
        {
            "category":"Professional",
            "subcategory":"Computer Services",
            "type":"Services"
        }
    ],
    "sg:phone":"+1 765 532 8280",
    "sg:postcode":"48073",
    "sg:province":"MI",
    "sg:tags":[
        "related"
    ],
    "wof:name":"Adam Reger Consulting",
    "wof:placetype":"venue"
},
  "geometry": {"coordinates":[-83.173716,42.536856],"type":"Point"}
}