{
  "type": "Feature",
  "properties": {
    "iso:country":"US",
    "sg:address":"1140 S Averill Ave",
    "sg:city":"Flint",
    "sg:classifiers":[
        {
            "category":"Autos & Motor Vehicles",
            "subcategory":"Automobile Sales",
            "type":"Retail Goods"
        }
    ],
    "sg:phone":"+1 810 715 2506",
    "sg:postcode":"48503",
    "sg:province":"MI",
    "sg:tags":[
        "car",
        "dealer"
    ],
    "wof:name":"G W Motors",
    "wof:placetype":"venue"
},
  "geometry": {"coordinates":[-83.643044,43.013256],"type":"Point"}
}