{
  "type": "Feature",
  "properties": {
    "iso:country":"US",
    "sg:address":"3663 South Blvd",
    "sg:city":"Auburn Hills",
    "sg:classifiers":[
        {
            "category":"Organizations",
            "subcategory":"Community Association",
            "type":"Services"
        }
    ],
    "sg:phone":"+1 248 852 3034",
    "sg:postcode":"48326",
    "sg:province":"MI",
    "wof:name":"Over Hill Gang",
    "wof:placetype":"venue"
},
  "geometry": {"coordinates":[-83.216791,42.620885],"type":"Point"}
}