{
  "type": "Feature",
  "properties": {
    "iso:country":"US",
    "sg:address":"68 W Chicago St",
    "sg:city":"Coldwater",
    "sg:classifiers":[
        {
            "category":"Restaurant",
            "type":"Food & Drink"
        }
    ],
    "sg:menulink":"http://www.allmenus.com/mi/coldwater/57473-gw-allen/menu/",
    "sg:phone":"+1 517 278 5955",
    "sg:postcode":"49036",
    "sg:province":"MI",
    "sg:tags":[
        "wrap",
        "american",
        "sandwich"
    ],
    "wof:name":"G.w. Allen",
    "wof:placetype":"venue"
},
  "geometry": {"coordinates":[-85.00357,41.941069],"type":"Point"}
}