{
  "type": "Feature",
  "properties": {
    "iso:country":"US",
    "sg:address":"120 Garland St",
    "sg:city":"Davison",
    "sg:classifiers":[
        {
            "category":"Building & Trades",
            "subcategory":"Construction",
            "type":"Services"
        }
    ],
    "sg:phone":"+1 810 653 7630",
    "sg:postcode":"48423",
    "sg:province":"MI",
    "sg:tags":[
        "floor",
        "laying",
        "contractor"
    ],
    "wof:name":"Boros Carpet Installation",
    "wof:placetype":"venue"
},
  "geometry": {"coordinates":[-83.522898,43.031575],"type":"Point"}
}