{
  "type": "Feature",
  "properties": {
    "iso:country":"US",
    "sg:address":"24045 Meadowbrook Rd",
    "sg:city":"Novi",
    "sg:classifiers":[
        {
            "category":"Restaurant",
            "type":"Food & Drink"
        }
    ],
    "sg:menulink":"http://www.allmenus.com/mi/novi/70022-cottage-inn-pizza/menu/",
    "sg:phone":"+1 248 380 4900",
    "sg:postcode":"48375",
    "sg:province":"MI",
    "sg:tags":[
        "wrap",
        "american",
        "sandwich",
        "pizza"
    ],
    "wof:name":"Cottage Inn Pizza",
    "wof:placetype":"venue"
},
  "geometry": {"coordinates":[-83.455089,42.466033],"type":"Point"}
}