{
  "type": "Feature",
  "properties": {
    "iso:country":"US",
    "sg:address":"721 Terminal Ave",
    "sg:city":"Iron Mountain",
    "sg:classifiers":[
        {
            "category":"Building & Trades",
            "subcategory":"Construction",
            "type":"Services"
        }
    ],
    "sg:phone":"+1 906 774 3717",
    "sg:postcode":"49801",
    "sg:province":"MI",
    "sg:tags":[
        "excavating",
        "contractor"
    ],
    "wof:name":"Edward Gauthier & Sons Inc",
    "wof:placetype":"venue"
},
  "geometry": {"coordinates":[-88.057587,45.807858],"type":"Point"}
}