{
  "type": "Feature",
  "properties": {
    "iso:country":"US",
    "sg:address":"4239 W Jefferson Ave",
    "sg:city":"Ecorse",
    "sg:classifiers":[
        {
            "category":"Autos & Motor Vehicles",
            "subcategory":"Automobile Sales",
            "type":"Retail Goods"
        }
    ],
    "sg:phone":"+1 313 386 2923",
    "sg:postcode":"48229",
    "sg:province":"MI",
    "sg:tags":[
        "car"
    ],
    "wof:name":"Ecorse Motor Sales",
    "wof:placetype":"venue"
},
  "geometry": {"coordinates":[-83.1427,42.246899],"type":"Point"}
}