{
  "type": "Feature",
  "properties": {
    "iso:country":"US",
    "sg:address":"3458 S Linden Rd",
    "sg:city":"Flint",
    "sg:classifiers":[
        {
            "category":"Restaurant",
            "type":"Food & Drink"
        }
    ],
    "sg:menulink":"http://www.allmenus.com/mi/flint/142461-subway/menu/",
    "sg:phone":"+1 810 733 7827",
    "sg:postcode":"48507",
    "sg:province":"MI",
    "sg:tags":[
        "american",
        "sandwich"
    ],
    "wof:name":"Subway",
    "wof:placetype":"venue"
},
  "geometry": {"coordinates":[-83.77213399999999,42.975415],"type":"Point"}
}