{
  "type": "Feature",
  "properties": {
    "iso:country":"US",
    "sg:address":"1229 S Washington Ave",
    "sg:city":"Royal Oak",
    "sg:classifiers":[
        {
            "category":"Professional",
            "subcategory":"Art Services",
            "type":"Services"
        }
    ],
    "sg:phone":"+1 248 546 4390",
    "sg:postcode":"48067",
    "sg:province":"MI",
    "sg:tags":[
        "commercial",
        "design"
    ],
    "sg:website":"www.design-group.net",
    "wof:name":"Design Group",
    "wof:placetype":"venue"
},
  "geometry": {"coordinates":[-83.146157,42.478867],"type":"Point"}
}