{
  "type": "Feature",
  "properties": {
    "iso:country":"US",
    "sg:address":"22618 Candace Dr",
    "sg:city":"Rockwood",
    "sg:classifiers":[
        {
            "category":"Retail",
            "subcategory":"Portrait Studio",
            "type":"Services"
        }
    ],
    "sg:phone":"+1 734 379 4136",
    "sg:postcode":"48173",
    "sg:province":"MI",
    "sg:tags":[
        "photo"
    ],
    "wof:name":"Amy Roberts Photography",
    "wof:placetype":"venue"
},
  "geometry": {"coordinates":[-83.255645,42.076961],"type":"Point"}
}