{
  "type": "Feature",
  "properties": {
    "iso:country":"US",
    "sg:address":"723 W Shiawassee St",
    "sg:city":"Lansing",
    "sg:classifiers":[
        {
            "category":"Social Services",
            "type":"Services"
        }
    ],
    "sg:phone":"+1 517 487 8814",
    "sg:postcode":"48915",
    "sg:province":"MI",
    "wof:name":"Successful Futures Inc",
    "wof:placetype":"venue"
},
  "geometry": {"coordinates":[-84.564331,42.737299],"type":"Point"}
}