{
  "type": "Feature",
  "properties": {
    "iso:country":"US",
    "sg:address":"415 S McEwan St",
    "sg:city":"Clare",
    "sg:classifiers":[
        {
            "category":"Building & Trades",
            "subcategory":"Construction",
            "type":"Services"
        }
    ],
    "sg:phone":"+1 989 386 7364",
    "sg:postcode":"48617",
    "sg:province":"MI",
    "sg:tags":[
        "concrete",
        "contractor"
    ],
    "wof:name":"Crawford Concrete",
    "wof:placetype":"venue"
},
  "geometry": {"coordinates":[-84.768407,43.811462],"type":"Point"}
}