{
  "type": "Feature",
  "properties": {
    "iso:country":"US",
    "sg:address":"398 Brooklyn Rd",
    "sg:city":"Napoleon",
    "sg:classifiers":[
        {
            "category":"Retail",
            "subcategory":"Auto Repair",
            "type":"Services"
        }
    ],
    "sg:phone":"+1 517 536 8635",
    "sg:postcode":"49201",
    "sg:province":"MI",
    "sg:tags":[
        "repairing",
        "automobile"
    ],
    "wof:name":"T C's Garage",
    "wof:placetype":"venue"
},
  "geometry": {"coordinates":[-84.252315,42.163719],"type":"Point"}
}