{
  "type": "Feature",
  "properties": {
    "iso:country":"US",
    "sg:address":"9058 Cedar Lake Rd",
    "sg:city":"Pinckney",
    "sg:classifiers":[
        {
            "category":"Building & Trades",
            "subcategory":"Landscaping Services",
            "type":"Services"
        }
    ],
    "sg:phone":"+1 734 878 0456",
    "sg:postcode":"48169",
    "sg:province":"MI",
    "sg:tags":[
        "landscape",
        "contractor"
    ],
    "wof:name":"DWC Dirt Works",
    "wof:placetype":"venue"
},
  "geometry": {"coordinates":[-83.967186,42.472738],"type":"Point"}
}