{
  "type": "Feature",
  "properties": {
    "iso:country":"US",
    "sg:address":"1003 N State St",
    "sg:city":"Big Rapids",
    "sg:classifiers":[
        {
            "category":"Freight",
            "type":"Transportation"
        }
    ],
    "sg:phone":"+1 231 796 5800",
    "sg:postcode":"49307",
    "sg:province":"MI",
    "sg:tags":[
        "commercial",
        "storage"
    ],
    "wof:name":"M-20 Self Storage",
    "wof:placetype":"venue"
},
  "geometry": {"coordinates":[-85.485688,43.711151],"type":"Point"}
}