{
  "type": "Feature",
  "properties": {
    "iso:country":"US",
    "sg:address":"8084 Burning Bush",
    "sg:city":"Grosse Ile",
    "sg:classifiers":[
        {
            "category":"Retail",
            "subcategory":"Auto Repair",
            "type":"Services"
        }
    ],
    "sg:phone":"+1 734 692 1674",
    "sg:postcode":"48138",
    "sg:province":"MI",
    "sg:tags":[
        "general"
    ],
    "wof:name":"Harmony Automotive LLC",
    "wof:placetype":"venue"
},
  "geometry": {"coordinates":[-83.14467500000001,42.146587],"type":"Point"}
}