{
  "type": "Feature",
  "properties": {
    "iso:country":"US",
    "sg:address":"274 E Chicago St",
    "sg:city":"Coldwater",
    "sg:classifiers":[
        {
            "category":"Health Services",
            "subcategory":"Doctor",
            "type":"Services"
        }
    ],
    "sg:phone":"+1 517 279 5363",
    "sg:postcode":"49036",
    "sg:province":"MI",
    "sg:tags":[
        "physician",
        "surgeon"
    ],
    "wof:name":"Maria Alvarez Krizan MD",
    "wof:placetype":"venue"
},
  "geometry": {"coordinates":[-84.990233,41.938819],"type":"Point"}
}