{
  "type": "Feature",
  "properties": {
    "iso:country":"US",
    "sg:address":"214 N Huron Rd",
    "sg:city":"Au Gres",
    "sg:classifiers":[
        {
            "category":"Professional",
            "type":"Services"
        }
    ],
    "sg:phone":"+1 989 876 8576",
    "sg:postcode":"48703",
    "sg:province":"MI",
    "sg:tags":[
        "establishment"
    ],
    "wof:name":"Ameri Claim",
    "wof:placetype":"venue"
},
  "geometry": {"coordinates":[-83.58348700000001,44.091423],"type":"Point"}
}