{
  "type": "Feature",
  "properties": {
    "iso:country":"US",
    "sg:address":"11839 Chattman Dr",
    "sg:city":"Sterling Heights",
    "sg:classifiers":[
        {
            "category":"Professional",
            "subcategory":"Computer Services",
            "type":"Services"
        }
    ],
    "sg:phone":"+1 248 637 3664",
    "sg:postcode":"48313",
    "sg:province":"MI",
    "sg:tags":[
        "datum"
    ],
    "wof:name":"Mediasoft",
    "wof:placetype":"venue"
},
  "geometry": {"coordinates":[-83.008612,42.610983],"type":"Point"}
}