{
  "type": "Feature",
  "properties": {
    "iso:country":"US",
    "sg:address":"301 W Main St",
    "sg:city":"Owosso",
    "sg:classifiers":[
        {
            "category":"Government",
            "subcategory":"Office",
            "type":"Public Place"
        }
    ],
    "sg:phone":"+1 989 725 0540",
    "sg:postcode":"48867",
    "sg:province":"MI",
    "sg:tags":[
        "city",
        "program"
    ],
    "wof:name":"Owosso Planning & Development",
    "wof:placetype":"venue"
},
  "geometry": {"coordinates":[-84.17384699999999,42.997558],"type":"Point"}
}