{
  "type": "Feature",
  "properties": {
    "iso:country":"US",
    "sg:address":"20271 Damman St",
    "sg:city":"Harper Woods",
    "sg:classifiers":[
        {
            "category":"Communications",
            "subcategory":"Film & Video Production",
            "type":"Services"
        }
    ],
    "sg:phone":"+1 313 647 0207",
    "sg:postcode":"48225",
    "sg:province":"MI",
    "sg:tags":[
        "motion"
    ],
    "wof:name":"Date Productions",
    "wof:placetype":"venue"
},
  "geometry": {"coordinates":[-82.92187300000001,42.43762],"type":"Point"}
}