{
  "type": "Feature",
  "properties": {
    "iso:country":"US",
    "sg:address":"24369 Halsted Rd",
    "sg:city":"Farmington Hills",
    "sg:classifiers":[
        {
            "category":"Restaurant",
            "type":"Food & Drink"
        }
    ],
    "sg:phone":"+1 248 888 4888",
    "sg:postcode":"48332",
    "sg:province":"MI",
    "sg:tags":[
        "pizza"
    ],
    "sg:website":"tomatoesapizza.com",
    "wof:name":"Tomatoes Apizza",
    "wof:placetype":"venue"
},
  "geometry": {"coordinates":[-83.415784,42.470225],"type":"Point"}
}