{
  "type": "Feature",
  "properties": {
    "iso:country":"US",
    "sg:address":"905 W Summit Ave",
    "sg:city":"Muskegon",
    "sg:classifiers":[
        {
            "category":"Health Services",
            "subcategory":"Clinic",
            "type":"Services"
        },
        {
            "category":"Professional",
            "subcategory":"Employment Agencies",
            "type":"Services"
        }
    ],
    "sg:phone":"+1 231 755 7115",
    "sg:postcode":"49441",
    "sg:province":"MI",
    "sg:tags":[
        "home",
        "medical",
        "help"
    ],
    "wof:name":"Professional Nursing Assoc Inc",
    "wof:placetype":"venue"
},
  "geometry": {"coordinates":[-86.266289,43.198035],"type":"Point"}
}