{
  "type": "Feature",
  "properties": {
    "iso:country":"US",
    "sg:address":"1073 US Hwy 27 Bus",
    "sg:city":"St Johns",
    "sg:classifiers":[
        {
            "category":"Food & Beverages",
            "subcategory":"Groceries & Convenience Stores",
            "type":"Retail Goods"
        }
    ],
    "sg:phone":"+1 989 227 1553",
    "sg:postcode":"48879",
    "sg:province":"MI",
    "sg:tags":[
        "product"
    ],
    "wof:name":"Fast Mamma's Italian Food",
    "wof:placetype":"venue"
},
  "geometry": {"coordinates":[-84.55195399999999,43.009081],"type":"Point"}
}