{
  "type": "Feature",
  "properties": {
    "iso:country":"US",
    "sg:address":"272 N Maple Rd",
    "sg:city":"Saline",
    "sg:classifiers":[
        {
            "category":"Retail",
            "subcategory":"Repair Shop",
            "type":"Services"
        }
    ],
    "sg:phone":"+1 734 944 8180",
    "sg:postcode":"48176",
    "sg:province":"MI",
    "wof:name":"Kimberley P Sexton",
    "wof:placetype":"venue"
},
  "geometry": {"coordinates":[-83.774244,42.172334],"type":"Point"}
}