{
  "type": "Feature",
  "properties": {
    "iso:country":"US",
    "sg:address":"266 North Ave",
    "sg:city":"Battle Creek",
    "sg:classifiers":[
        {
            "category":"Professional",
            "subcategory":"Secretarial Services",
            "type":"Services"
        }
    ],
    "sg:phone":"+1 269 963 4706",
    "sg:postcode":"49017",
    "sg:province":"MI",
    "sg:tags":[
        "reporting"
    ],
    "wof:name":"Quines Medical Transcription",
    "wof:placetype":"venue"
},
  "geometry": {"coordinates":[-85.1803,42.330037],"type":"Point"}
}