{
  "type": "Feature",
  "properties": {
    "iso:country":"US",
    "sg:address":"9129 Tecumseh Clinton Hwy",
    "sg:city":"Tecumseh",
    "sg:classifiers":[
        {
            "category":"Real Estate",
            "subcategory":"Real Estate Agent",
            "type":"Services"
        }
    ],
    "sg:phone":"+1 517 423 1209",
    "sg:postcode":"49286",
    "sg:province":"MI",
    "wof:name":"Tecumseh Properties Inc",
    "wof:placetype":"venue"
},
  "geometry": {"coordinates":[-83.941897,42.022688],"type":"Point"}
}