{
  "type": "Feature",
  "properties": {
    "iso:country":"US",
    "sg:address":"19111 W 10 Mile Rd",
    "sg:city":"Southfield",
    "sg:classifiers":[
        {
            "category":"Professional",
            "type":"Services"
        }
    ],
    "sg:phone":"+1 248 354 4006",
    "sg:postcode":"48075",
    "sg:province":"MI",
    "sg:tags":[
        "establishment"
    ],
    "wof:name":"Josefina S Baltao LLC",
    "wof:placetype":"venue"
},
  "geometry": {"coordinates":[-83.233189,42.473025],"type":"Point"}
}