{
  "type": "Feature",
  "properties": {
    "iso:country":"US",
    "sg:address":"1295 N Linden Rd",
    "sg:city":"Flint",
    "sg:classifiers":[
        {
            "category":"Health Services",
            "subcategory":"Doctor",
            "type":"Services"
        }
    ],
    "sg:phone":"+1 810 733 7096",
    "sg:postcode":"48532",
    "sg:province":"MI",
    "sg:tags":[
        "physician",
        "surgeon"
    ],
    "wof:name":"Flint Gastroenterology Assoc",
    "wof:placetype":"venue"
},
  "geometry": {"coordinates":[-83.773346,43.024198],"type":"Point"}
}