{
  "type": "Feature",
  "properties": {
    "iso:country":"US",
    "sg:address":"826 Edgemont Run",
    "sg:city":"Bloomfield Hills",
    "sg:classifiers":[
        {
            "category":"Education",
            "subcategory":"Special Training",
            "type":"Public Place"
        }
    ],
    "sg:phone":"+1 248 338 3296",
    "sg:postcode":"48304",
    "sg:province":"MI",
    "wof:name":"RLM Engineering Co",
    "wof:placetype":"venue"
},
  "geometry": {"coordinates":[-83.232896,42.606602],"type":"Point"}
}