{
  "type": "Feature",
  "properties": {
    "iso:country":"US",
    "sg:address":"3930 Stahl Dr SE",
    "sg:city":"Grand Rapids",
    "sg:classifiers":[
        {
            "category":"Travel",
            "subcategory":"Hotels & Motels",
            "type":"Entertainment"
        }
    ],
    "sg:phone":"+1 616 940 2700",
    "sg:postcode":"49546",
    "sg:province":"MI",
    "sg:tags":[
        "operation"
    ],
    "wof:name":"Midwest Heritage Inn of Grand",
    "wof:placetype":"venue"
},
  "geometry": {"coordinates":[-85.570916,42.914544],"type":"Point"}
}