{
  "type": "Feature",
  "properties": {
    "iso:country":"US",
    "sg:address":"5415 Lincoln Ave",
    "sg:city":"Saint Joseph",
    "sg:classifiers":[
        {
            "category":"Shopping",
            "subcategory":"Bicycles & Sporting Goods",
            "type":"Retail Goods"
        }
    ],
    "sg:phone":"+1 269 429 0671",
    "sg:postcode":"49085",
    "sg:province":"MI",
    "wof:name":"Zicks Tack & Equipment",
    "wof:placetype":"venue"
},
  "geometry": {"coordinates":[-86.4752,42.016625],"type":"Point"}
}