{
  "type": "Feature",
  "properties": {
    "iso:country":"US",
    "sg:address":"3995 E 14 Mile Rd",
    "sg:city":"Sterling Heights",
    "sg:classifiers":[
        {
            "category":"Food & Beverages",
            "subcategory":"Groceries & Convenience Stores",
            "type":"Retail Goods"
        }
    ],
    "sg:phone":"+1 586 268 2662",
    "sg:postcode":"48310",
    "sg:province":"MI",
    "sg:tags":[
        "grocer"
    ],
    "wof:name":"Farmer Jack Market",
    "wof:placetype":"venue"
},
  "geometry": {"coordinates":[-83.07005700000001,42.535427],"type":"Point"}
}