{
  "type": "Feature",
  "properties": {
    "iso:country":"US",
    "sg:address":"739 Dryer Farm Rd",
    "sg:city":"Lansing",
    "sg:classifiers":[
        {
            "category":"Recreation",
            "type":"Entertainment"
        }
    ],
    "sg:phone":"+1 517 339 7454",
    "sg:postcode":"48917",
    "sg:province":"MI",
    "sg:tags":[
        "club",
        "volleyball"
    ],
    "wof:name":"Michigan Amateur & Rec Vllybll",
    "wof:placetype":"venue"
},
  "geometry": {"coordinates":[-84.593298,42.744539],"type":"Point"}
}