{
  "type": "Feature",
  "properties": {
    "iso:country":"US",
    "sg:address":"31122 W 8 Mile Rd",
    "sg:city":"Farmington Hills",
    "sg:classifiers":[
        {
            "category":"Retail",
            "subcategory":"Auto Repair",
            "type":"Services"
        }
    ],
    "sg:phone":"+1 248 888 1001",
    "sg:postcode":"48336",
    "sg:province":"MI",
    "sg:tags":[
        "repairing",
        "automobile"
    ],
    "wof:name":"Kim's Auto Care Inc",
    "wof:placetype":"venue"
},
  "geometry": {"coordinates":[-83.354401,42.4412],"type":"Point"}
}