{
  "type": "Feature",
  "properties": {
    "iso:country":"US",
    "sg:address":"301 Harrison St",
    "sg:city":"Kingsford",
    "sg:classifiers":[
        {
            "category":"Manufacturing",
            "subcategory":"Apparel",
            "type":"Manufacturing & Wholesale Goods"
        }
    ],
    "sg:phone":"+1 906 774 5523",
    "sg:postcode":"49802",
    "sg:province":"MI",
    "sg:tags":[
        "flag",
        "banner"
    ],
    "wof:name":"Quality Flags Poles & Banners",
    "wof:placetype":"venue"
},
  "geometry": {"coordinates":[-88.090673,45.811648],"type":"Point"}
}