{
  "type": "Feature",
  "properties": {
    "iso:country":"US",
    "sg:address":"20601 W 8 Mile Rd",
    "sg:city":"Detroit",
    "sg:classifiers":[
        {
            "category":"Restaurant",
            "type":"Food & Drink"
        }
    ],
    "sg:phone":"+1 313 533 0353",
    "sg:postcode":"48219",
    "sg:province":"MI",
    "sg:tags":[
        "traditional",
        "american"
    ],
    "wof:name":"T & J Coney Island",
    "wof:placetype":"venue"
},
  "geometry": {"coordinates":[-83.245903,42.443501],"type":"Point"}
}