{
  "type": "Feature",
  "properties": {
    "iso:country":"US",
    "sg:address":"112 E Michigan Ave",
    "sg:city":"Marshall",
    "sg:classifiers":[
        {
            "category":"Personal",
            "subcategory":"Beauty Salon",
            "type":"Services"
        }
    ],
    "sg:phone":"+1 269 781 6269",
    "sg:postcode":"49068",
    "sg:province":"MI",
    "sg:tags":[
        "shop"
    ],
    "wof:name":"Hair Co",
    "wof:placetype":"venue"
},
  "geometry": {"coordinates":[-84.958624,42.271969],"type":"Point"}
}