{
  "type": "Feature",
  "properties": {
    "iso:country":"US",
    "sg:address":"35210 Nankin Blvd",
    "sg:city":"Westland",
    "sg:classifiers":[
        {
            "category":"Health Services",
            "subcategory":"Doctor",
            "type":"Services"
        }
    ],
    "sg:phone":"+1 734 525 2555",
    "sg:postcode":"48185",
    "sg:province":"MI",
    "sg:tags":[
        "podiatrist"
    ],
    "sg:website":"www.westlandpodiatry.com",
    "wof:name":"Kane Howard D DPM",
    "wof:placetype":"venue"
},
  "geometry": {"coordinates":[-83.389297,42.345299],"type":"Point"}
}