{
  "type": "Feature",
  "properties": {
    "iso:country":"US",
    "sg:address":"1817 Sunny Dale",
    "sg:city":"Lansing",
    "sg:classifiers":[
        {
            "category":"Professional",
            "subcategory":"Business Services",
            "type":"Services"
        }
    ],
    "sg:phone":"+1 517 323 6525",
    "sg:postcode":"48917",
    "sg:province":"MI",
    "wof:name":"Ron Smith",
    "wof:placetype":"venue"
},
  "geometry": {"coordinates":[-84.62666400000001,42.753233],"type":"Point"}
}