{
  "type": "Feature",
  "properties": {
    "iso:country":"US",
    "sg:address":"3812 McKinley St",
    "sg:city":"Dearborn",
    "sg:classifiers":[
        {
            "category":"Building & Trades",
            "subcategory":"Landscaping Services",
            "type":"Services"
        }
    ],
    "sg:phone":"+1 313 274 7517",
    "sg:postcode":"48124",
    "sg:province":"MI",
    "wof:name":"Lawn Creations",
    "wof:placetype":"venue"
},
  "geometry": {"coordinates":[-83.253659,42.283137],"type":"Point"}
}