{
  "type": "Feature",
  "properties": {
    "iso:country":"US",
    "sg:address":"243 S Huron Rd",
    "sg:city":"Linwood",
    "sg:classifiers":[
        {
            "category":"Retail",
            "subcategory":"Auto Repair",
            "type":"Services"
        }
    ],
    "sg:phone":"+1 989 697 4206",
    "sg:postcode":"48634",
    "sg:province":"MI",
    "sg:tags":[
        "body",
        "automobile",
        "painting"
    ],
    "wof:name":"Pro Tec Collision",
    "wof:placetype":"venue"
},
  "geometry": {"coordinates":[-83.974872,43.73307],"type":"Point"}
}