{
  "type": "Feature",
  "properties": {
    "iso:country":"US",
    "sg:address":"45203 Fryer Dr",
    "sg:city":"Macomb",
    "sg:classifiers":[
        {
            "category":"Travel",
            "subcategory":"Travel Agent",
            "type":"Entertainment"
        }
    ],
    "sg:phone":"+1 586 566 0636",
    "sg:postcode":"48044",
    "sg:province":"MI",
    "sg:tags":[
        "agency",
        "bureau"
    ],
    "wof:name":"Stargate Travel",
    "wof:placetype":"venue"
},
  "geometry": {"coordinates":[-82.96796399999999,42.629168],"type":"Point"}
}