{
  "type": "Feature",
  "properties": {
    "iso:country":"US",
    "sg:address":"3926 Windemere Dr",
    "sg:city":"Lansing",
    "sg:classifiers":[
        {
            "category":"Social Services",
            "subcategory":"Adult Care",
            "type":"Services"
        }
    ],
    "sg:phone":"+1 517 393 9085",
    "sg:postcode":"48911",
    "sg:province":"MI",
    "sg:tags":[
        "foster",
        "provider"
    ],
    "wof:name":"Frank and Barbara Beverly",
    "wof:placetype":"venue"
},
  "geometry": {"coordinates":[-84.60483600000001,42.691758],"type":"Point"}
}