{
  "type": "Feature",
  "properties": {
    "iso:country":"US",
    "sg:address":"2192 Valley Vista Dr",
    "sg:city":"Davison",
    "sg:classifiers":[
        {
            "category":"Insurance",
            "subcategory":"Health Insurance",
            "type":"Services"
        }
    ],
    "sg:phone":"+1 810 658 7394",
    "sg:postcode":"48423",
    "sg:province":"MI",
    "sg:tags":[
        "carrier"
    ],
    "wof:name":"Elkins Agency",
    "wof:placetype":"venue"
},
  "geometry": {"coordinates":[-83.538251,43.004966],"type":"Point"}
}