{
  "type": "Feature",
  "properties": {
    "iso:country":"US",
    "sg:address":"19150 Briarwood Ln",
    "sg:city":"Clinton Township",
    "sg:classifiers":[
        {
            "category":"Education",
            "subcategory":"School",
            "type":"Public Place"
        }
    ],
    "sg:phone":"+1 586 723 3500",
    "sg:postcode":"48036",
    "sg:province":"MI",
    "sg:tags":[
        "high",
        "middle",
        "elementary"
    ],
    "wof:name":"Chippewa Valley School District",
    "wof:placetype":"venue"
},
  "geometry": {"coordinates":[-82.924367,42.570811],"type":"Point"}
}