{
  "type": "Feature",
  "properties": {
    "iso:country":"US",
    "sg:address":"28755 Alycekay St",
    "sg:city":"Farmington Hills",
    "sg:classifiers":[
        {
            "category":"Building & Trades",
            "subcategory":"Construction",
            "type":"Services"
        }
    ],
    "sg:phone":"+1 248 427 8262",
    "sg:postcode":"48334",
    "sg:province":"MI",
    "sg:tags":[
        "blacktopping"
    ],
    "wof:name":"Blondie's Blacktop",
    "wof:placetype":"venue"
},
  "geometry": {"coordinates":[-83.351837,42.507498],"type":"Point"}
}