{
  "type": "Feature",
  "properties": {
    "iso:country":"US",
    "sg:address":"3210 State St",
    "sg:city":"Saginaw",
    "sg:classifiers":[
        {
            "category":"Health Services",
            "subcategory":"Optometrist",
            "type":"Services"
        }
    ],
    "sg:phone":"+1 989 799 2860",
    "sg:postcode":"48602",
    "sg:province":"MI",
    "wof:name":"Andersen Eye Assoc",
    "wof:placetype":"venue"
},
  "geometry": {"coordinates":[-83.986791,43.436719],"type":"Point"}
}