{
  "type": "Feature",
  "properties": {
    "iso:country":"US",
    "sg:address":"1707 Stanley Blvd",
    "sg:city":"Birmingham",
    "sg:classifiers":[
        {
            "category":"Real Estate",
            "subcategory":"Real Estate Agent",
            "type":"Services"
        }
    ],
    "sg:phone":"+1 248 642 6464",
    "sg:postcode":"48009",
    "sg:province":"MI",
    "sg:tags":[
        "consultant"
    ],
    "wof:name":"Retail Real Estate Consulting",
    "wof:placetype":"venue"
},
  "geometry": {"coordinates":[-83.219008,42.531524],"type":"Point"}
}