{
  "type": "Feature",
  "properties": {
    "iso:country":"US",
    "sg:address":"3240 44th St",
    "sg:city":"Hamilton",
    "sg:phone":"+1 269 751 5907",
    "sg:postcode":"49419",
    "sg:province":"MI",
    "sg:tags":[
        "farm"
    ],
    "wof:name":"Nyboer Greenhouse",
    "wof:placetype":"venue"
},
  "geometry": {"coordinates":[-85.97654300000001,42.651739],"type":"Point"}
}