{
  "type": "Feature",
  "properties": {
    "iso:country":"US",
    "sg:address":"17876 Kenowa Ave",
    "sg:city":"Grant",
    "sg:classifiers":[
        {
            "category":"Personal",
            "type":"Services"
        }
    ],
    "sg:phone":"+1 231 834 5381",
    "sg:postcode":"49327",
    "sg:province":"MI",
    "wof:name":"Party Creations Prof Planner",
    "wof:placetype":"venue"
},
  "geometry": {"coordinates":[-85.79038199999999,43.289963],"type":"Point"}
}