{
  "type": "Feature",
  "properties": {
    "iso:country":"US",
    "sg:address":"6478 W Emery Rd",
    "sg:city":"Houghton Lake",
    "sg:classifiers":[
        {
            "category":"Building & Trades",
            "subcategory":"Construction",
            "type":"Services"
        }
    ],
    "sg:phone":"+1 989 422 3446",
    "sg:postcode":"48629",
    "sg:province":"MI",
    "sg:tags":[
        "hanging",
        "contractor"
    ],
    "wof:name":"Jafo Unlimited",
    "wof:placetype":"venue"
},
  "geometry": {"coordinates":[-84.732585,44.276502],"type":"Point"}
}