{
  "type": "Feature",
  "properties": {
    "iso:country":"US",
    "sg:address":"7680 Gratiot Rd",
    "sg:city":"Saginaw",
    "sg:classifiers":[
        {
            "category":"Utilities",
            "subcategory":"Mobile Phone",
            "type":"Services"
        }
    ],
    "sg:phone":"+1 989 781 0347",
    "sg:postcode":"48609",
    "sg:province":"MI",
    "sg:tags":[
        "telephone",
        "cellular"
    ],
    "wof:name":"Redmond Communications",
    "wof:placetype":"venue"
},
  "geometry": {"coordinates":[-84.06532,43.415945],"type":"Point"}
}