{
  "type": "Feature",
  "properties": {
    "iso:country":"US",
    "sg:address":"9357 River Rd",
    "sg:city":"Evart",
    "sg:classifiers":[
        {
            "category":"Social Services",
            "subcategory":"Child Care",
            "type":"Services"
        }
    ],
    "sg:phone":"+1 231 734 2293",
    "sg:postcode":"49631",
    "sg:province":"MI",
    "sg:tags":[
        "personal",
        "day"
    ],
    "wof:name":"Charlenes Daycare",
    "wof:placetype":"venue"
},
  "geometry": {"coordinates":[-85.323789,43.872394],"type":"Point"}
}