{
  "type": "Feature",
  "properties": {
    "iso:country":"US",
    "sg:address":"23101 Edsel Ford Ct",
    "sg:city":"Saint Clair Shores",
    "sg:classifiers":[
        {
            "category":"Professional",
            "type":"Services"
        }
    ],
    "sg:phone":"+1 586 778 5976",
    "sg:postcode":"48080",
    "sg:province":"MI",
    "wof:name":"Doubleknowledge Inc",
    "wof:placetype":"venue"
},
  "geometry": {"coordinates":[-82.88556699999999,42.457454],"type":"Point"}
}