{
  "type": "Feature",
  "properties": {
    "iso:country":"US",
    "sg:address":"17401 E 10 Mile Rd",
    "sg:city":"Eastpointe",
    "sg:classifiers":[
        {
            "category":"Wholesale",
            "subcategory":"Metals & Minerals",
            "type":"Manufacturing & Wholesale Goods"
        }
    ],
    "sg:phone":"+1 586 552 8061",
    "sg:postcode":"48021",
    "sg:province":"MI",
    "sg:tags":[
        "steel",
        "warehouse"
    ],
    "sg:website":"www.tkxlogistics.com",
    "wof:name":"Thyssen Krupp Steel NA Inc",
    "wof:placetype":"venue"
},
  "geometry": {"coordinates":[-82.942583,42.479861],"type":"Point"}
}