{
  "type": "Feature",
  "properties": {
    "iso:country":"US",
    "sg:address":"6454 Mayfair St",
    "sg:city":"Taylor",
    "sg:classifiers":[
        {
            "category":"Building & Trades",
            "subcategory":"Construction",
            "type":"Services"
        }
    ],
    "sg:phone":"+1 313 382 3758",
    "sg:postcode":"48180",
    "sg:province":"MI",
    "sg:tags":[
        "house"
    ],
    "wof:name":"Brisky Construction Co",
    "wof:placetype":"venue"
},
  "geometry": {"coordinates":[-83.23620200000001,42.261133],"type":"Point"}
}