{
  "type": "Feature",
  "properties": {
    "iso:country":"US",
    "sg:address":"5645 Ramsdell Dr NE",
    "sg:city":"Rockford",
    "sg:classifiers":[
        {
            "category":"Education",
            "subcategory":"School",
            "type":"Public Place"
        }
    ],
    "sg:phone":"+1 616 874 5739",
    "sg:postcode":"49341",
    "sg:province":"MI",
    "wof:name":"Servants of Immaculata Inc",
    "wof:placetype":"venue"
},
  "geometry": {"coordinates":[-85.46548,43.0624],"type":"Point"}
}