{
  "type": "Feature",
  "properties": {
    "iso:country":"US",
    "sg:address":"6224 60th Ave",
    "sg:city":"Hudsonville",
    "sg:classifiers":[
        {
            "category":"Building & Trades",
            "subcategory":"Construction",
            "type":"Services"
        }
    ],
    "sg:phone":"+1 616 875 8659",
    "sg:postcode":"49426",
    "sg:province":"MI",
    "sg:tags":[
        "masonry",
        "contractor"
    ],
    "wof:name":"Moelker Masonry Inc",
    "wof:placetype":"venue"
},
  "geometry": {"coordinates":[-85.931006,42.882096],"type":"Point"}
}