{
  "type": "Feature",
  "properties": {
    "iso:country":"US",
    "sg:address":"45918 Morceau Dr",
    "sg:city":"Macomb",
    "sg:classifiers":[
        {
            "category":"Retail",
            "subcategory":"Repair Shop",
            "type":"Services"
        }
    ],
    "sg:phone":"+1 586 447 8022",
    "sg:postcode":"48044",
    "sg:province":"MI",
    "sg:tags":[
        "lock",
        "locksmith"
    ],
    "wof:name":"Access Safe & Lock",
    "wof:placetype":"venue"
},
  "geometry": {"coordinates":[-82.902078,42.63494],"type":"Point"}
}