{
  "type": "Feature",
  "properties": {
    "iso:country":"US",
    "sg:address":"829 Mullen St",
    "sg:city":"Quinnesec",
    "sg:classifiers":[
        {
            "category":"Organizations",
            "subcategory":"Religious Organization",
            "type":"Services"
        }
    ],
    "sg:phone":"+1 906 774 7335",
    "sg:postcode":"49876",
    "sg:province":"MI",
    "wof:name":"Child Evangelism Fellowship",
    "wof:placetype":"venue"
},
  "geometry": {"coordinates":[-87.99964900000001,45.801992],"type":"Point"}
}