{
  "type": "Feature",
  "properties": {
    "iso:country":"US",
    "sg:address":"23533 Northport",
    "sg:city":"Clinton Township",
    "sg:classifiers":[
        {
            "category":"Shopping",
            "subcategory":"Used Merchandise",
            "type":"Retail Goods"
        }
    ],
    "sg:phone":"+1 586 783 5537",
    "sg:postcode":"48036",
    "sg:province":"MI",
    "sg:tags":[
        "business"
    ],
    "wof:name":"Diane Reh Antiques",
    "wof:placetype":"venue"
},
  "geometry": {"coordinates":[-82.86814,42.621239],"type":"Point"}
}