{
  "type": "Feature",
  "properties": {
    "iso:country":"US",
    "sg:address":"3705 Medbury St",
    "sg:city":"Detroit",
    "sg:classifiers":[
        {
            "category":"Professional",
            "type":"Services"
        }
    ],
    "sg:phone":"+1 313 399 4847",
    "sg:postcode":"48211",
    "sg:province":"MI",
    "wof:name":"Dallas Deandrea",
    "wof:placetype":"venue"
},
  "geometry": {"coordinates":[-83.032484,42.377857],"type":"Point"}
}