{
  "type": "Feature",
  "properties": {
    "iso:country":"US",
    "sg:address":"31 E Long Lake Rd",
    "sg:city":"Troy",
    "sg:classifiers":[
        {
            "category":"Deli",
            "type":"Food & Drink"
        },
        {
            "category":"Food & Beverages",
            "subcategory":"Groceries & Convenience Stores",
            "type":"Retail Goods"
        }
    ],
    "sg:phone":"+1 248 879 1040",
    "sg:postcode":"48085",
    "sg:province":"MI",
    "wof:name":"Kroger Food & Pharmacy",
    "wof:placetype":"venue"
},
  "geometry": {"coordinates":[-83.14755,42.593195],"type":"Point"}
}