{
  "type": "Feature",
  "properties": {
    "iso:country":"US",
    "sg:address":"2578 Bender Ave",
    "sg:city":"Waterford",
    "sg:classifiers":[
        {
            "category":"Building & Trades",
            "subcategory":"Landscaping Services",
            "type":"Services"
        }
    ],
    "sg:phone":"+1 248 618 9803",
    "sg:postcode":"48329",
    "sg:province":"MI",
    "sg:tags":[
        "landscape",
        "contractor"
    ],
    "wof:name":"Crestwood Lawn & Landscpg LLC",
    "wof:placetype":"venue"
},
  "geometry": {"coordinates":[-83.39122500000001,42.675863],"type":"Point"}
}