{
  "type": "Feature",
  "properties": {
    "iso:country":"US",
    "sg:address":"6895 Marshall Rd",
    "sg:city":"Nashville",
    "sg:classifiers":[
        {
            "category":"Manufacturing",
            "subcategory":"Jewelry",
            "type":"Manufacturing & Wholesale Goods"
        }
    ],
    "sg:phone":"+1 517 852 0688",
    "sg:postcode":"49073",
    "sg:province":"MI",
    "sg:tags":[
        "costume"
    ],
    "wof:name":"Trinkets Deluxe Inc",
    "wof:placetype":"venue"
},
  "geometry": {"coordinates":[-85.15335399999999,42.554034],"type":"Point"}
}