{
  "type": "Feature",
  "properties": {
    "iso:country":"US",
    "sg:address":"1857 N 9 Mile Rd",
    "sg:city":"Sanford",
    "sg:classifiers":[
        {
            "category":"Organizations",
            "subcategory":"Labor Organization",
            "type":"Services"
        }
    ],
    "sg:phone":"+1 989 687 2243",
    "sg:postcode":"48657",
    "sg:province":"MI",
    "wof:name":"N E A",
    "wof:placetype":"venue"
},
  "geometry": {"coordinates":[-84.428647,43.65488],"type":"Point"}
}