{
  "type": "Feature",
  "properties": {
    "iso:country":"US",
    "sg:address":"29665 Colony Circle Dr",
    "sg:city":"Farmington Hills",
    "sg:classifiers":[
        {
            "category":"Insurance",
            "subcategory":"Insurance Agent",
            "type":"Services"
        }
    ],
    "sg:phone":"+1 248 865 9399",
    "sg:postcode":"48334",
    "sg:province":"MI",
    "wof:name":"Met Life",
    "wof:placetype":"venue"
},
  "geometry": {"coordinates":[-83.37357299999999,42.514808],"type":"Point"}
}