{
  "type": "Feature",
  "properties": {
    "iso:country":"US",
    "sg:address":"8900 W State Hwy 21",
    "sg:city":"St Johns",
    "sg:classifiers":[
        {
            "category":"Building & Trades",
            "subcategory":"Construction",
            "type":"Services"
        }
    ],
    "sg:phone":"+1 989 593 3399",
    "sg:postcode":"48879",
    "sg:province":"MI",
    "sg:tags":[
        "excavating",
        "contractor"
    ],
    "wof:name":"T H Miller Excavating Inc",
    "wof:placetype":"venue"
},
  "geometry": {"coordinates":[-84.690117,43.001798],"type":"Point"}
}