{
  "type": "Feature",
  "properties": {
    "iso:country":"US",
    "sg:address":"4755 Rochester Rd",
    "sg:city":"Troy",
    "sg:classifiers":[
        {
            "category":"Wholesale",
            "subcategory":"Auto Parts",
            "type":"Manufacturing & Wholesale Goods"
        }
    ],
    "sg:phone":"+1 248 689 7725",
    "sg:postcode":"48085",
    "sg:province":"MI",
    "sg:tags":[
        "equipment",
        "truck"
    ],
    "sg:website":"www.flexatube.com",
    "wof:name":"Flexatube Industries Inc",
    "wof:placetype":"venue"
},
  "geometry": {"coordinates":[-83.128911,42.59003],"type":"Point"}
}