{
  "type": "Feature",
  "properties": {
    "iso:country":"US",
    "sg:address":"4046 Moulton Dr",
    "sg:city":"Flint",
    "sg:classifiers":[
        {
            "category":"Professional",
            "subcategory":"Accounting & Tax Preparation",
            "type":"Services"
        }
    ],
    "sg:phone":"+1 810 767 4046",
    "sg:postcode":"48507",
    "sg:province":"MI",
    "sg:tags":[
        "return",
        "filing"
    ],
    "wof:name":"Accounting Plus",
    "wof:placetype":"venue"
},
  "geometry": {"coordinates":[-83.707741,42.967864],"type":"Point"}
}