{
  "type": "Feature",
  "properties": {
    "iso:country":"US",
    "sg:address":"1022 Weiss St",
    "sg:city":"Frankenmuth",
    "sg:classifiers":[
        {
            "category":"Health Services",
            "subcategory":"Chiropractor",
            "type":"Services"
        }
    ],
    "sg:phone":"+1 989 652 3244",
    "sg:postcode":"48734",
    "sg:province":"MI",
    "wof:name":"Mark R Limberg DC",
    "wof:placetype":"venue"
},
  "geometry": {"coordinates":[-83.73486,43.32129],"type":"Point"}
}