{
  "type": "Feature",
  "properties": {
    "iso:country":"US",
    "sg:address":"210 W Lincoln St",
    "sg:city":"Caro",
    "sg:classifiers":[
        {
            "category":"Government",
            "subcategory":"Post Office",
            "type":"Public Place"
        }
    ],
    "sg:phone":"+1 989 673 2322",
    "sg:postcode":"48723",
    "sg:province":"MI",
    "wof:name":"US Post Office",
    "wof:placetype":"venue"
},
  "geometry": {"coordinates":[-83.397026,43.491017],"type":"Point"}
}