{
  "type": "Feature",
  "properties": {
    "iso:country":"US",
    "sg:address":"4061 N Euclid Ave",
    "sg:city":"Bay City",
    "sg:classifiers":[
        {
            "category":"Government",
            "subcategory":"Office",
            "type":"Public Place"
        }
    ],
    "sg:phone":"+1 989 671 2470",
    "sg:postcode":"48706",
    "sg:province":"MI",
    "sg:tags":[
        "armed",
        "force",
        "recruiting"
    ],
    "wof:name":"US Naval Recruiting",
    "wof:placetype":"venue"
},
  "geometry": {"coordinates":[-83.914231,43.62215],"type":"Point"}
}