{
  "type": "Feature",
  "properties": {
    "iso:country":"US",
    "sg:address":"160 S Elba Rd",
    "sg:city":"Lapeer",
    "sg:classifiers":[
        {
            "category":"Personal",
            "subcategory":"Beauty Salon",
            "type":"Services"
        }
    ],
    "sg:phone":"+1 810 664 3651",
    "sg:postcode":"48446",
    "sg:province":"MI",
    "wof:name":"Stylistics Inc",
    "wof:placetype":"venue"
},
  "geometry": {"coordinates":[-83.440174,43.038145],"type":"Point"}
}