{
  "type": "Feature",
  "properties": {
    "iso:country":"US",
    "sg:address":"14460 Lakeside Cir",
    "sg:city":"Sterling Heights",
    "sg:classifiers":[
        {
            "category":"Banks & Credit Unions",
            "subcategory":"Financial Services",
            "type":"Services"
        }
    ],
    "sg:phone":"+1 586 532 0600",
    "sg:postcode":"48313",
    "sg:province":"MI",
    "sg:tags":[
        "broker",
        "mortgage"
    ],
    "wof:name":"Great Lakes Mortgage Funding",
    "wof:placetype":"venue"
},
  "geometry": {"coordinates":[-82.982201,42.620998],"type":"Point"}
}