{
  "type": "Feature",
  "properties": {
    "iso:country":"US",
    "sg:address":"1566 10th St",
    "sg:city":"Martin",
    "sg:classifiers":[
        {
            "category":"Restaurant",
            "type":"Food & Drink"
        }
    ],
    "sg:phone":"+1 269 672 9944",
    "sg:postcode":"49070",
    "sg:province":"MI",
    "wof:name":"Red Barn",
    "wof:placetype":"venue"
},
  "geometry": {"coordinates":[-85.641772,42.533672],"type":"Point"}
}