{
  "type": "Feature",
  "properties": {
    "iso:country":"US",
    "sg:address":"10645 East Rd",
    "sg:city":"Burt",
    "sg:classifiers":[
        {
            "category":"Government",
            "subcategory":"Office",
            "type":"Public Place"
        }
    ],
    "sg:phone":"+1 989 770 4844",
    "sg:postcode":"48417",
    "sg:province":"MI",
    "sg:tags":[
        "village"
    ],
    "wof:name":"Albee Township Offices",
    "wof:placetype":"venue"
},
  "geometry": {"coordinates":[-83.952654,43.268792],"type":"Point"}
}