{
  "type": "Feature",
  "properties": {
    "iso:country":"US",
    "sg:address":"4653 Butternut St",
    "sg:city":"Clarkston",
    "sg:classifiers":[
        {
            "category":"Home & Garden",
            "subcategory":"Building Materials",
            "type":"Retail Goods"
        }
    ],
    "sg:phone":"+1 248 941 1402",
    "sg:postcode":"48348",
    "sg:province":"MI",
    "wof:name":"Jim Beasley Custom Copper",
    "wof:placetype":"venue"
},
  "geometry": {"coordinates":[-83.358751,42.800399],"type":"Point"}
}