{
  "type": "Feature",
  "properties": {
    "iso:country":"US",
    "sg:address":"45348 15th Ave",
    "sg:city":"Bloomingdale",
    "sg:classifiers":[
        {
            "category":"Professional",
            "subcategory":"Business Services",
            "type":"Services"
        }
    ],
    "sg:phone":"+1 269 521 4332",
    "sg:postcode":"49026",
    "sg:province":"MI",
    "sg:tags":[
        "painter",
        "sign"
    ],
    "wof:name":"Advanced Signs & Graphics",
    "wof:placetype":"venue"
},
  "geometry": {"coordinates":[-85.986289,42.36474],"type":"Point"}
}