{
  "type": "Feature",
  "properties": {
    "iso:country":"US",
    "sg:address":"13341 Bird Rd",
    "sg:city":"Gaines",
    "sg:phone":"+1 989 271 0138",
    "sg:postcode":"48436",
    "sg:province":"MI",
    "sg:tags":[
        "farm",
        "corn",
        "soybean"
    ],
    "wof:name":"Robert Malone",
    "wof:placetype":"venue"
},
  "geometry": {"coordinates":[-83.876278,42.834895],"type":"Point"}
}