{
  "type": "Feature",
  "properties": {
    "iso:country":"US",
    "sg:address":"3599 Annchester Dr",
    "sg:city":"Saginaw",
    "sg:classifiers":[
        {
            "category":"Building & Trades",
            "subcategory":"Construction",
            "type":"Services"
        }
    ],
    "sg:phone":"+1 989 752 4857",
    "sg:postcode":"48603",
    "sg:province":"MI",
    "sg:tags":[
        "new",
        "some",
        "commercial",
        "contractor"
    ],
    "wof:name":"G Ruhlig Builders",
    "wof:placetype":"venue"
},
  "geometry": {"coordinates":[-83.96275799999999,43.45917],"type":"Point"}
}