{
  "type": "Feature",
  "properties": {
    "iso:country":"US",
    "sg:address":"322 S Lafayette St",
    "sg:city":"Greenville",
    "sg:classifiers":[
        {
            "category":"Shopping",
            "subcategory":"Optical Goods",
            "type":"Retail Goods"
        }
    ],
    "sg:phone":"+1 616 754 4696",
    "sg:postcode":"48838",
    "sg:province":"MI",
    "wof:name":"Pearle Vision",
    "wof:placetype":"venue"
},
  "geometry": {"coordinates":[-85.25306399999999,43.17834],"type":"Point"}
}