{
  "type": "Feature",
  "properties": {
    "iso:country":"US",
    "sg:address":"3975 N Oak St",
    "sg:city":"Metamora",
    "sg:classifiers":[
        {
            "category":"Insurance",
            "subcategory":"Insurance Agent",
            "type":"Services"
        }
    ],
    "sg:phone":"+1 810 678 2233",
    "sg:postcode":"48455",
    "sg:province":"MI",
    "wof:name":"Community Insurance Ctr II",
    "wof:placetype":"venue"
},
  "geometry": {"coordinates":[-83.288658,42.942261],"type":"Point"}
}