{
  "type": "Feature",
  "properties": {
    "iso:country":"US",
    "sg:address":"1327 24th St",
    "sg:city":"Port Huron",
    "sg:classifiers":[
        {
            "category":"Banks & Credit Unions",
            "subcategory":"Bank",
            "type":"Services"
        }
    ],
    "sg:phone":"+1 810 984 9900",
    "sg:postcode":"48060",
    "sg:province":"MI",
    "sg:tags":[
        "depository",
        "banking",
        "check",
        "cashing"
    ],
    "wof:name":"Check 'n Go",
    "wof:placetype":"venue"
},
  "geometry": {"coordinates":[-82.452631,42.969542],"type":"Point"}
}