{
  "type": "Feature",
  "properties": {
    "iso:country":"US",
    "sg:address":"4260 Van Dyke Rd",
    "sg:city":"Almont",
    "sg:classifiers":[
        {
            "category":"Social Services",
            "subcategory":"Child Care",
            "type":"Services"
        }
    ],
    "sg:phone":"+1 810 798 8000",
    "sg:postcode":"48003",
    "sg:province":"MI",
    "sg:tags":[
        "kindergarten",
        "academic",
        "school"
    ],
    "wof:name":"Smarty Pants Preschool",
    "wof:placetype":"venue"
},
  "geometry": {"coordinates":[-83.056056,42.9379],"type":"Point"}
}