{
  "type": "Feature",
  "properties": {
    "iso:country":"US",
    "sg:address":"1979 S Maple Island Rd",
    "sg:city":"Muskegon",
    "sg:classifiers":[
        {
            "category":"Building & Trades",
            "subcategory":"Construction",
            "type":"Services"
        }
    ],
    "sg:phone":"+1 231 788 5352",
    "sg:postcode":"49442",
    "sg:province":"MI",
    "sg:tags":[
        "contractor"
    ],
    "wof:name":"Builder Boys",
    "wof:placetype":"venue"
},
  "geometry": {"coordinates":[-86.067663,43.217186],"type":"Point"}
}