{
  "type": "Feature",
  "properties": {
    "iso:country":"US",
    "sg:address":"244 Parkway St",
    "sg:city":"Kingsford",
    "sg:classifiers":[
        {
            "category":"Social Services",
            "subcategory":"Adult Care",
            "type":"Services"
        }
    ],
    "sg:phone":"+1 906 774 5110",
    "sg:postcode":"49802",
    "sg:province":"MI",
    "sg:tags":[
        "organization",
        "senior",
        "citizen"
    ],
    "wof:name":"Breen Avenue Senior Citizens",
    "wof:placetype":"venue"
},
  "geometry": {"coordinates":[-88.07293,45.79437],"type":"Point"}
}