{
  "type": "Feature",
  "properties": {
    "iso:country":"US",
    "sg:address":"517 Leonard St NW",
    "sg:city":"Grand Rapids",
    "sg:classifiers":[
        {
            "category":"Professional",
            "subcategory":"Accounting & Tax Preparation",
            "type":"Services"
        }
    ],
    "sg:phone":"+1 616 451 8605",
    "sg:postcode":"49504",
    "sg:province":"MI",
    "sg:tags":[
        "return",
        "filing"
    ],
    "wof:name":"Liberty Tax Svc",
    "wof:placetype":"venue"
},
  "geometry": {"coordinates":[-85.680277,42.985041],"type":"Point"}
}