{
  "type": "Feature",
  "properties": {
    "iso:country":"US",
    "sg:address":"12348 Morrish Rd",
    "sg:city":"Clio",
    "sg:classifiers":[
        {
            "category":"Recreation",
            "type":"Entertainment"
        }
    ],
    "sg:phone":"+1 810 233 9464",
    "sg:postcode":"48420",
    "sg:province":"MI",
    "sg:tags":[
        "martial",
        "arts",
        "instruction"
    ],
    "wof:name":"Garner K Train's Law Office",
    "wof:placetype":"venue"
},
  "geometry": {"coordinates":[-83.833647,43.182056],"type":"Point"}
}