{
  "type": "Feature",
  "properties": {
    "iso:country":"US",
    "sg:address":"116 Macomb Pl",
    "sg:city":"Mount Clemens",
    "sg:classifiers":[
        {
            "category":"Professional",
            "subcategory":"Lawyer & Legal Services",
            "type":"Services"
        }
    ],
    "sg:phone":"+1 586 463 4817",
    "sg:postcode":"48043",
    "sg:province":"MI",
    "sg:tags":[
        "attorney"
    ],
    "wof:name":"Grande Law Offices",
    "wof:placetype":"venue"
},
  "geometry": {"coordinates":[-82.879898,42.5998],"type":"Point"}
}