{
  "type": "Feature",
  "properties": {
    "iso:country":"US",
    "sg:address":"3232 Michigamme Woods Dr",
    "sg:city":"Kalamazoo",
    "sg:classifiers":[
        {
            "category":"Health Services",
            "subcategory":"Medical Lab",
            "type":"Services"
        }
    ],
    "sg:phone":"+1 269 372 9327",
    "sg:postcode":"49006",
    "sg:province":"MI",
    "sg:tags":[
        "detection",
        "equipment",
        "drug"
    ],
    "wof:name":"SAMO",
    "wof:placetype":"venue"
},
  "geometry": {"coordinates":[-85.629614,42.277343],"type":"Point"}
}