{
  "type": "Feature",
  "properties": {
    "iso:country":"US",
    "sg:address":"21711 W 10 Mile Rd",
    "sg:city":"Southfield",
    "sg:classifiers":[
        {
            "category":"Banks & Credit Unions",
            "subcategory":"Investment Brokerage",
            "type":"Services"
        }
    ],
    "sg:phone":"+1 248 351 4378",
    "sg:postcode":"48075",
    "sg:province":"MI",
    "wof:name":"Chicago Investment Group",
    "wof:placetype":"venue"
},
  "geometry": {"coordinates":[-83.260381,42.472359],"type":"Point"}
}