{
  "type": "Feature",
  "properties": {
    "iso:country":"US",
    "sg:address":"6112 Filion Rd",
    "sg:city":"Pigeon",
    "sg:classifiers":[
        {
            "category":"Shopping",
            "type":"Retail Goods"
        }
    ],
    "sg:phone":"+1 989 453 3530",
    "sg:postcode":"48755",
    "sg:province":"MI",
    "sg:tags":[
        "spa",
        "hot",
        "tub"
    ],
    "wof:name":"Blue Water Spas",
    "wof:placetype":"venue"
},
  "geometry": {"coordinates":[-83.225353,43.88907],"type":"Point"}
}