{
  "type": "Feature",
  "properties": {
    "iso:country":"US",
    "sg:address":"8585 Saratoga St",
    "sg:city":"Oak Park",
    "sg:classifiers":[
        {
            "category":"Education",
            "subcategory":"School",
            "type":"Public Place"
        }
    ],
    "sg:phone":"+1 248 548 0070",
    "sg:postcode":"48237",
    "sg:province":"MI",
    "sg:tags":[
        "high",
        "middle",
        "elementary"
    ],
    "wof:name":"Ferndale Public Schools",
    "wof:placetype":"venue"
},
  "geometry": {"coordinates":[-83.16191600000001,42.458244],"type":"Point"}
}