{
  "type": "Feature",
  "properties": {
    "iso:country":"US",
    "sg:address":"8400 Ohern Rd",
    "sg:city":"Saginaw",
    "sg:classifiers":[
        {
            "category":"Social Services",
            "subcategory":"Child Care",
            "type":"Services"
        }
    ],
    "sg:phone":"+1 989 921 2461",
    "sg:postcode":"48609",
    "sg:province":"MI",
    "sg:tags":[
        "day"
    ],
    "wof:name":"Latch Key",
    "wof:placetype":"venue"
},
  "geometry": {"coordinates":[-84.085819,43.408923],"type":"Point"}
}