{
  "type": "Feature",
  "properties": {
    "iso:country":"US",
    "sg:address":"2955 Lorraine St",
    "sg:city":"Marlette",
    "sg:classifiers":[
        {
            "category":"Personal",
            "type":"Services"
        }
    ],
    "sg:phone":"+1 989 635 2837",
    "sg:postcode":"48453",
    "sg:province":"MI",
    "wof:name":"Loras Herbs & Massage",
    "wof:placetype":"venue"
},
  "geometry": {"coordinates":[-83.09202500000001,43.331137],"type":"Point"}
}