{
  "type": "Feature",
  "properties": {
    "iso:country":"US",
    "sg:address":"519 Melody Ct",
    "sg:city":"Royal Oak",
    "sg:classifiers":[
        {
            "category":"Retail",
            "subcategory":"Repair Shop",
            "type":"Services"
        }
    ],
    "sg:phone":"+1 248 398 3876",
    "sg:postcode":"48073",
    "sg:province":"MI",
    "wof:name":"Richard Bittner Piano Tuning",
    "wof:placetype":"venue"
},
  "geometry": {"coordinates":[-83.13798199999999,42.512349],"type":"Point"}
}