{
  "type": "Feature",
  "properties": {
    "iso:country":"US",
    "sg:address":"27101 Groesbeck Hwy",
    "sg:city":"Warren",
    "sg:classifiers":[
        {
            "category":"Manufacturing",
            "subcategory":"Metals",
            "type":"Manufacturing & Wholesale Goods"
        }
    ],
    "sg:phone":"+1 586 779 0300",
    "sg:postcode":"48089",
    "sg:province":"MI",
    "sg:tags":[
        "automotive",
        "stampings"
    ],
    "sg:website":"www.radarindustries.com",
    "wof:name":"Radar Industries Inc",
    "wof:placetype":"venue"
},
  "geometry": {"coordinates":[-82.968433,42.494801],"type":"Point"}
}