{
  "type": "Feature",
  "properties": {
    "iso:country":"US",
    "sg:address":"4274 E Court St",
    "sg:city":"Burton",
    "sg:classifiers":[
        {
            "category":"Home & Garden",
            "subcategory":"Building Materials",
            "type":"Retail Goods"
        }
    ],
    "sg:phone":"+1 810 744 2830",
    "sg:postcode":"48509",
    "sg:province":"MI",
    "sg:tags":[
        "center"
    ],
    "wof:name":"Lowe's",
    "wof:placetype":"venue"
},
  "geometry": {"coordinates":[-83.624256,43.018615],"type":"Point"}
}