{
  "type": "Feature",
  "properties": {
    "iso:country":"US",
    "sg:address":"5475 Livernois Rd",
    "sg:city":"Troy",
    "sg:classifiers":[
        {
            "category":"Social Services",
            "subcategory":"Child Care",
            "type":"Services"
        }
    ],
    "sg:phone":"+1 248 879 2893",
    "sg:postcode":"48098",
    "sg:province":"MI",
    "sg:tags":[
        "elementary",
        "kindergarten",
        "school",
        "academic"
    ],
    "wof:name":"St Augustine Lutheran Pre School",
    "wof:placetype":"venue"
},
  "geometry": {"coordinates":[-83.14949799999999,42.5984],"type":"Point"}
}