{
  "type": "Feature",
  "properties": {
    "iso:country":"US",
    "sg:address":"807 E State St",
    "sg:city":"Cheboygan",
    "sg:classifiers":[
        {
            "category":"Retail",
            "subcategory":"Auto Repair",
            "type":"Services"
        }
    ],
    "sg:phone":"+1 231 627 7431",
    "sg:postcode":"49721",
    "sg:province":"MI",
    "sg:tags":[
        "repairing",
        "automobile"
    ],
    "wof:name":"Wheelock's Muffler Ctr",
    "wof:placetype":"venue"
},
  "geometry": {"coordinates":[-84.46468,45.642421],"type":"Point"}
}