{
  "type": "Feature",
  "properties": {
    "iso:country":"US",
    "sg:address":"202 S Oak St",
    "sg:city":"Buchanan",
    "sg:classifiers":[
        {
            "category":"Manufacturing",
            "subcategory":"Toys & Sporting Goods",
            "type":"Manufacturing & Wholesale Goods"
        }
    ],
    "sg:phone":"+1 269 695 2868",
    "sg:postcode":"49107",
    "sg:province":"MI",
    "sg:tags":[
        "stuffed",
        "doll"
    ],
    "wof:name":"Tender Loving Creations",
    "wof:placetype":"venue"
},
  "geometry": {"coordinates":[-86.361186,41.824955],"type":"Point"}
}