{
  "type": "Feature",
  "properties": {
    "iso:country":"US",
    "sg:address":"7701 Vreeland Rd",
    "sg:city":"Ypsilanti",
    "sg:classifiers":[
        {
            "category":"Sports & Exercise",
            "subcategory":"Race Track",
            "type":"Entertainment"
        }
    ],
    "sg:phone":"+1 734 485 7606",
    "sg:postcode":"48198",
    "sg:province":"MI",
    "sg:tags":[
        "operation",
        "racing",
        "or"
    ],
    "wof:name":"M Lowe",
    "wof:placetype":"venue"
},
  "geometry": {"coordinates":[-83.605345,42.290154],"type":"Point"}
}