{
  "type": "Feature",
  "properties": {
    "iso:country":"US",
    "sg:address":"9207 Timberline Dr",
    "sg:city":"Grand Blanc",
    "sg:classifiers":[
        {
            "category":"Banks & Credit Unions",
            "subcategory":"Investment Brokerage",
            "type":"Services"
        }
    ],
    "sg:phone":"+1 810 579 7526",
    "sg:postcode":"48439",
    "sg:province":"MI",
    "sg:tags":[
        "advisory"
    ],
    "wof:name":"GA Rapple Investmants",
    "wof:placetype":"venue"
},
  "geometry": {"coordinates":[-83.65146799999999,42.893884],"type":"Point"}
}