{
  "type": "Feature",
  "properties": {
    "iso:country":"US",
    "sg:address":"14525 Sibley Rd",
    "sg:city":"Wyandotte",
    "sg:classifiers":[
        {
            "category":"Education",
            "subcategory":"Preschool",
            "type":"Public Place"
        },
        {
            "category":"Education",
            "subcategory":"School",
            "type":"Public Place"
        }
    ],
    "sg:phone":"+1 734 479 4191",
    "sg:postcode":"48193",
    "sg:province":"MI",
    "sg:tags":[
        "elementary"
    ],
    "sg:website":"www.islandkiddiekampus.com",
    "wof:name":"Island Kiddie Kampus",
    "wof:placetype":"venue"
},
  "geometry": {"coordinates":[-83.197688,42.170037],"type":"Point"}
}