{
  "type": "Feature",
  "properties": {
    "iso:country":"US",
    "sg:address":"916 S Main St",
    "sg:city":"Eaton Rapids",
    "sg:classifiers":[
        {
            "category":"Restaurant",
            "type":"Food & Drink"
        }
    ],
    "sg:phone":"+1 517 663 6200",
    "sg:postcode":"48827",
    "sg:province":"MI",
    "wof:name":"Hungry Howie's Pizza & Subs",
    "wof:placetype":"venue"
},
  "geometry": {"coordinates":[-84.656464,42.503466],"type":"Point"}
}