{
  "type": "Feature",
  "properties": {
    "iso:country":"US",
    "sg:address":"3359 Yellowstone Dr",
    "sg:city":"Ann Arbor",
    "sg:classifiers":[
        {
            "category":"Professional",
            "subcategory":"Management & Consulting",
            "type":"Services"
        }
    ],
    "sg:phone":"+1 734 761 1782",
    "sg:postcode":"48105",
    "sg:province":"MI",
    "sg:tags":[
        "consultant",
        "engineering"
    ],
    "wof:name":"J J A Associates",
    "wof:placetype":"venue"
},
  "geometry": {"coordinates":[-83.693889,42.311274],"type":"Point"}
}