{
  "type": "Feature",
  "properties": {
    "iso:country":"US",
    "sg:address":"2437 Division Ave S",
    "sg:city":"Grand Rapids",
    "sg:classifiers":[
        {
            "category":"Wholesale",
            "subcategory":"Machinery & Supplies",
            "type":"Manufacturing & Wholesale Goods"
        }
    ],
    "sg:phone":"+1 616 243 5007",
    "sg:postcode":"49507",
    "sg:province":"MI",
    "sg:tags":[
        "equipment",
        "industrial"
    ],
    "sg:website":"www.linksystems.com",
    "wof:name":"Link Systems",
    "wof:placetype":"venue"
},
  "geometry": {"coordinates":[-85.666282,42.919159],"type":"Point"}
}