{
  "type": "Feature",
  "properties": {
    "iso:country":"US",
    "sg:address":"3232 Kraft Ave SE",
    "sg:city":"Grand Rapids",
    "sg:classifiers":[
        {
            "category":"Manufacturing",
            "subcategory":"Textiles",
            "type":"Manufacturing & Wholesale Goods"
        }
    ],
    "sg:phone":"+1 616 954 3200",
    "sg:postcode":"49512",
    "sg:province":"MI",
    "sg:tags":[
        "rug",
        "carpet"
    ],
    "sg:website":"www.scottgroupcustomcarpet.com",
    "wof:name":"Scott Group Custom Carpets",
    "wof:placetype":"venue"
},
  "geometry": {"coordinates":[-85.52919,42.903721],"type":"Point"}
}