{
  "type": "Feature",
  "properties": {
    "iso:country":"US",
    "sg:address":"4301 Kalamazoo Ave SE",
    "sg:city":"Grand Rapids",
    "sg:classifiers":[
        {
            "category":"Retail",
            "subcategory":"Laundry & Dry Cleaning",
            "type":"Services"
        },
        {
            "category":"Shopping",
            "subcategory":"Clothing, Apparel, & Fashions",
            "type":"Retail Goods"
        }
    ],
    "sg:phone":"+1 616 455 0050",
    "sg:postcode":"49508",
    "sg:province":"MI",
    "sg:tags":[
        "alteration"
    ],
    "wof:name":"Kim & Kim Alterations",
    "wof:placetype":"venue"
},
  "geometry": {"coordinates":[-85.626036,42.884781],"type":"Point"}
}