{
  "type": "Feature",
  "properties": {
    "iso:country":"US",
    "sg:address":"3120 W Johnson Rd",
    "sg:city":"Ithaca",
    "sg:classifiers":[
        {
            "category":"Organizations",
            "subcategory":"Religious Organization",
            "type":"Services"
        }
    ],
    "sg:phone":"+1 989 875 3317",
    "sg:postcode":"48847",
    "sg:province":"MI",
    "sg:tags":[
        "church"
    ],
    "wof:name":"Newark-Mennonite Church",
    "wof:placetype":"venue"
},
  "geometry": {"coordinates":[-84.661017,43.233815],"type":"Point"}
}