{
  "type": "Feature",
  "properties": {
    "iso:country":"US",
    "sg:address":"820 E 3rd St",
    "sg:city":"Royal Oak",
    "sg:classifiers":[
        {
            "category":"Shopping",
            "subcategory":"Florist",
            "type":"Retail Goods"
        }
    ],
    "sg:phone":"+1 248 399 7948",
    "sg:postcode":"48067",
    "sg:province":"MI",
    "wof:name":"Floral Dsigns By Carol Valente",
    "wof:placetype":"venue"
},
  "geometry": {"coordinates":[-83.135386,42.488311],"type":"Point"}
}