{
  "type": "Feature",
  "properties": {
    "iso:country":"US",
    "sg:address":"610 N Mission St",
    "sg:city":"Mount Pleasant",
    "sg:classifiers":[
        {
            "category":"Retail",
            "subcategory":"Car Wash",
            "type":"Services"
        }
    ],
    "sg:phone":"+1 989 773 3477",
    "sg:postcode":"48858",
    "sg:province":"MI",
    "sg:tags":[
        "polishing",
        "automobile",
        "washing"
    ],
    "wof:name":"Valet Auto Care Inc",
    "wof:placetype":"venue"
},
  "geometry": {"coordinates":[-84.76767,43.609897],"type":"Point"}
}