{
  "type": "Feature",
  "properties": {
    "iso:country":"US",
    "sg:address":"1919 Birchwood Dr",
    "sg:city":"Troy",
    "sg:classifiers":[
        {
            "category":"Wholesale",
            "subcategory":"Furniture",
            "type":"Manufacturing & Wholesale Goods"
        }
    ],
    "sg:phone":"+1 248 524 1000",
    "sg:postcode":"48083",
    "sg:province":"MI",
    "wof:name":"Techline Studio",
    "wof:placetype":"venue"
},
  "geometry": {"coordinates":[-83.10806700000001,42.550874],"type":"Point"}
}