{
  "type": "Feature",
  "properties": {
    "iso:country":"US",
    "sg:address":"5423 W Vernor Hwy",
    "sg:city":"Detroit",
    "sg:classifiers":[
        {
            "category":"Shopping",
            "subcategory":"Florist",
            "type":"Retail Goods"
        }
    ],
    "sg:phone":"+1 313 554 1420",
    "sg:postcode":"48209",
    "sg:province":"MI",
    "wof:name":"George's Flowers",
    "wof:placetype":"venue"
},
  "geometry": {"coordinates":[-83.101303,42.317902],"type":"Point"}
}