{
  "type": "Feature",
  "properties": {
    "iso:country":"US",
    "sg:address":"7478 Sheffield Dr SE",
    "sg:city":"Ada",
    "sg:classifiers":[
        {
            "category":"Utilities",
            "subcategory":"Telephone",
            "type":"Services"
        }
    ],
    "sg:phone":"+1 616 949 1422",
    "sg:postcode":"49301",
    "sg:province":"MI",
    "sg:tags":[
        "communications"
    ],
    "wof:name":"1 800 Corp",
    "wof:placetype":"venue"
},
  "geometry": {"coordinates":[-85.485055,42.908956],"type":"Point"}
}