{
  "type": "Feature",
  "properties": {
    "iso:country":"US",
    "sg:address":"8225 Caribou",
    "sg:city":"Clarkston",
    "sg:classifiers":[
        {
            "category":"Real Estate",
            "subcategory":"Real Estate Operator",
            "type":"Services"
        }
    ],
    "sg:phone":"+1 248 620 6995",
    "sg:postcode":"48348",
    "sg:province":"MI",
    "sg:tags":[
        "building",
        "nonresidential"
    ],
    "wof:name":"MCG Properties",
    "wof:placetype":"venue"
},
  "geometry": {"coordinates":[-83.41525300000001,42.758631],"type":"Point"}
}