{
  "type": "Feature",
  "properties": {
    "iso:country":"US",
    "sg:address":"9495 Westwood St",
    "sg:city":"Detroit",
    "sg:classifiers":[
        {
            "category":"Professional",
            "subcategory":"Business Services",
            "type":"Services"
        }
    ],
    "sg:phone":"+1 313 477 1896",
    "sg:postcode":"48228",
    "sg:province":"MI",
    "sg:tags":[
        "interior",
        "design"
    ],
    "wof:name":"Professional Development Inc",
    "wof:placetype":"venue"
},
  "geometry": {"coordinates":[-83.23125899999999,42.363003],"type":"Point"}
}