{
  "type": "Feature",
  "properties": {
    "iso:country":"US",
    "sg:address":"3878 Sherman St",
    "sg:city":"Bridgeport",
    "sg:classifiers":[
        {
            "category":"Education",
            "subcategory":"School",
            "type":"Public Place"
        }
    ],
    "sg:phone":"+1 989 777 1770",
    "sg:postcode":"48722",
    "sg:province":"MI",
    "wof:name":"Bridgeport-Spaulding Schl Supt",
    "wof:placetype":"venue"
},
  "geometry": {"coordinates":[-83.87795800000001,43.359645],"type":"Point"}
}