{
  "type": "Feature",
  "properties": {
    "iso:country":"US",
    "sg:address":"4431 E Allen Rd",
    "sg:city":"Howell",
    "sg:classifiers":[
        {
            "category":"Building & Trades",
            "subcategory":"Construction",
            "type":"Services"
        }
    ],
    "sg:phone":"+1 517 548 4300",
    "sg:postcode":"48855",
    "sg:province":"MI",
    "sg:tags":[
        "concrete",
        "restoration",
        "cleaning",
        "repair"
    ],
    "wof:name":"Ultimate Concrete Solutions",
    "wof:placetype":"venue"
},
  "geometry": {"coordinates":[-83.863112,42.689832],"type":"Point"}
}