{
  "type": "Feature",
  "properties": {
    "iso:country":"US",
    "sg:address":"2635 Cascade Rd SE",
    "sg:city":"Grand Rapids",
    "sg:classifiers":[
        {
            "category":"Social Services",
            "subcategory":"Child Care",
            "type":"Services"
        }
    ],
    "sg:phone":"+1 616 292 9208",
    "sg:postcode":"49506",
    "sg:province":"MI",
    "wof:name":"Cascada Point Child Care",
    "wof:placetype":"venue"
},
  "geometry": {"coordinates":[-85.604823,42.960723],"type":"Point"}
}