{
  "type": "Feature",
  "properties": {
    "iso:country":"US",
    "sg:address":"22621 64th Ave",
    "sg:city":"Mattawan",
    "sg:classifiers":[
        {
            "category":"Manufacturing",
            "subcategory":"Lumber",
            "type":"Manufacturing & Wholesale Goods"
        }
    ],
    "sg:phone":"+1 269 668 2479",
    "sg:postcode":"49071",
    "sg:province":"MI",
    "sg:tags":[
        "hardwood",
        "mill",
        "sawmill"
    ],
    "wof:name":"Van Niman Saw Mill",
    "wof:placetype":"venue"
},
  "geometry": {"coordinates":[-85.78174,42.186083],"type":"Point"}
}