{
  "type": "Feature",
  "properties": {
    "iso:country":"US",
    "sg:address":"1001 W Fort St",
    "sg:city":"Detroit",
    "sg:classifiers":[
        {
            "category":"Restaurant",
            "type":"Food & Drink"
        }
    ],
    "sg:menulink":"http://www.allmenus.com/mi/detroit/56910-subway/menu/",
    "sg:phone":"+1 313 962 1307",
    "sg:postcode":"48226",
    "sg:province":"MI",
    "sg:tags":[
        "american",
        "sandwich"
    ],
    "wof:name":"Subway",
    "wof:placetype":"venue"
},
  "geometry": {"coordinates":[-83.056684,42.326702],"type":"Point"}
}