{
  "type": "Feature",
  "properties": {
    "iso:country":"US",
    "sg:address":"3030 Kersten Ct",
    "sg:city":"Kalamazoo",
    "sg:classifiers":[
        {
            "category":"Real Estate",
            "subcategory":"Real Estate Operator",
            "type":"Services"
        }
    ],
    "sg:phone":"+1 269 385 2400",
    "sg:postcode":"49048",
    "sg:province":"MI",
    "sg:tags":[
        "property",
        "commercial"
    ],
    "wof:name":"Filtec Industries Inc",
    "wof:placetype":"venue"
},
  "geometry": {"coordinates":[-85.51476,42.259369],"type":"Point"}
}