{
  "type": "Feature",
  "properties": {
    "iso:country":"US",
    "sg:address":"477 Michigan Ave",
    "sg:city":"Detroit",
    "sg:classifiers":[
        {
            "category":"Professional",
            "subcategory":"Management & Consulting",
            "type":"Services"
        }
    ],
    "sg:phone":"+1 313 226 3534",
    "sg:postcode":"48226",
    "sg:province":"MI",
    "sg:tags":[
        "public",
        "relations"
    ],
    "wof:name":"Detroit Federal Executive Bd",
    "wof:placetype":"venue"
},
  "geometry": {"coordinates":[-83.052663,42.331672],"type":"Point"}
}