{
  "type": "Feature",
  "properties": {
    "iso:country":"US",
    "sg:address":"2057 Winding Oak Dr",
    "sg:city":"Dorr",
    "sg:classifiers":[
        {
            "category":"Social Services",
            "subcategory":"Child Care",
            "type":"Services"
        }
    ],
    "sg:phone":"+1 616 681 8855",
    "sg:postcode":"49323",
    "sg:province":"MI",
    "sg:tags":[
        "day"
    ],
    "wof:name":"Molly S Duiven",
    "wof:placetype":"venue"
},
  "geometry": {"coordinates":[-85.748271,42.716078],"type":"Point"}
}