{
  "type": "Feature",
  "properties": {
    "iso:country":"US",
    "sg:address":"241 Burr Oak Rd",
    "sg:city":"Burr Oak",
    "sg:classifiers":[
        {
            "category":"Building & Trades",
            "subcategory":"Construction",
            "type":"Services"
        }
    ],
    "sg:phone":"+1 269 489 2927",
    "sg:postcode":"49030",
    "sg:province":"MI",
    "sg:tags":[
        "house"
    ],
    "wof:name":"Silver Creek Construction",
    "wof:placetype":"venue"
},
  "geometry": {"coordinates":[-85.31156799999999,41.858411],"type":"Point"}
}