{
  "type": "Feature",
  "properties": {
    "iso:country":"US",
    "sg:address":"1327 Reo Rd",
    "sg:city":"Lansing",
    "sg:classifiers":[
        {
            "category":"Professional",
            "subcategory":"Management & Consulting",
            "type":"Services"
        }
    ],
    "sg:phone":"+1 517 394 7078",
    "sg:postcode":"48910",
    "sg:province":"MI",
    "sg:tags":[
        "business"
    ],
    "wof:name":"Delgade Consulting Inc",
    "wof:placetype":"venue"
},
  "geometry": {"coordinates":[-84.57367600000001,42.687816],"type":"Point"}
}