{
  "type": "Feature",
  "properties": {
    "iso:country":"US",
    "sg:address":"1456 Goffe St",
    "sg:city":"St Clair",
    "sg:classifiers":[
        {
            "category":"Arts & Performance",
            "subcategory":"Theater",
            "type":"Entertainment"
        }
    ],
    "sg:phone":"+1 810 326 3977",
    "sg:postcode":"48079",
    "sg:province":"MI",
    "wof:name":"St Clair Theatre Guild",
    "wof:placetype":"venue"
},
  "geometry": {"coordinates":[-82.489048,42.812333],"type":"Point"}
}