{
  "type": "Feature",
  "properties": {
    "iso:country":"US",
    "sg:address":"17250 W 12 Mile Rd",
    "sg:city":"Southfield",
    "sg:classifiers":[
        {
            "category":"Wholesale",
            "subcategory":"Computers",
            "type":"Manufacturing & Wholesale Goods"
        }
    ],
    "sg:phone":"+1 248 559 5700",
    "sg:postcode":"48076",
    "sg:province":"MI",
    "wof:name":"Inacomp Computer Centers",
    "wof:placetype":"venue"
},
  "geometry": {"coordinates":[-83.217212,42.502776],"type":"Point"}
}