{
  "type": "Feature",
  "properties": {
    "iso:country":"US",
    "sg:address":"203 E Cedar Ave",
    "sg:city":"Gladwin",
    "sg:classifiers":[
        {
            "category":"Manufacturing",
            "subcategory":"Printing",
            "type":"Manufacturing & Wholesale Goods"
        }
    ],
    "sg:phone":"+1 989 846 4531",
    "sg:postcode":"48624",
    "sg:province":"MI",
    "sg:tags":[
        "printer"
    ],
    "wof:name":"Sunrise Printing & Pub Inc",
    "wof:placetype":"venue"
},
  "geometry": {"coordinates":[-84.48433900000001,43.980558],"type":"Point"}
}