{
  "type": "Feature",
  "properties": {
    "iso:country":"US",
    "sg:address":"2282 Plumgrove Ln",
    "sg:city":"West Bloomfield",
    "sg:classifiers":[
        {
            "category":"Shopping",
            "subcategory":"Computers & Home Electronics",
            "type":"Retail Goods"
        }
    ],
    "sg:phone":"+1 248 682 6746",
    "sg:postcode":"48324",
    "sg:province":"MI",
    "sg:tags":[
        "software"
    ],
    "wof:name":"Sreepad Inc",
    "wof:placetype":"venue"
},
  "geometry": {"coordinates":[-83.39654299999999,42.604686],"type":"Point"}
}