{
  "type": "Feature",
  "properties": {
    "iso:country":"US",
    "sg:address":"223 N Clinton Ave",
    "sg:city":"Saint Johns",
    "sg:classifiers":[
        {
            "category":"Shopping",
            "subcategory":"Used Merchandise",
            "type":"Retail Goods"
        }
    ],
    "sg:phone":"+1 989 224 8852",
    "sg:postcode":"48879",
    "sg:province":"MI",
    "wof:name":"Saint Vincent De Paul Store",
    "wof:placetype":"venue"
},
  "geometry": {"coordinates":[-84.558515,43.003222],"type":"Point"}
}