{
  "type": "Feature",
  "properties": {
    "iso:country":"US",
    "sg:address":"901 W Main St",
    "sg:city":"Owosso",
    "sg:classifiers":[
        {
            "category":"Shopping",
            "subcategory":"Discount & Variety Stores",
            "type":"Retail Goods"
        }
    ],
    "sg:phone":"+1 989 729 2904",
    "sg:postcode":"48867",
    "sg:province":"MI",
    "wof:name":"Dontae Holidays",
    "wof:placetype":"venue"
},
  "geometry": {"coordinates":[-84.182158,42.99758],"type":"Point"}
}