{
  "type": "Feature",
  "properties": {
    "iso:country":"US",
    "sg:address":"1224 Calvin Ave SE",
    "sg:city":"Grand Rapids",
    "sg:classifiers":[
        {
            "category":"Retail",
            "subcategory":"Repair Shop",
            "type":"Services"
        }
    ],
    "sg:phone":"+1 616 452 5662",
    "sg:postcode":"49506",
    "sg:province":"MI",
    "sg:tags":[
        "sharpening"
    ],
    "wof:name":"Ron's Sharpening Svc",
    "wof:placetype":"venue"
},
  "geometry": {"coordinates":[-85.63582,42.939986],"type":"Point"}
}