{
  "type": "Feature",
  "properties": {
    "iso:country":"US",
    "sg:address":"453 Moran Rd",
    "sg:city":"Grosse Pointe",
    "sg:classifiers":[
        {
            "category":"Building & Trades",
            "subcategory":"Construction",
            "type":"Services"
        }
    ],
    "sg:phone":"+1 313 882 1168",
    "sg:postcode":"48236",
    "sg:province":"MI",
    "sg:tags":[
        "floor",
        "laying",
        "contractor"
    ],
    "wof:name":"Harrisberg Co",
    "wof:placetype":"venue"
},
  "geometry": {"coordinates":[-82.913415,42.408514],"type":"Point"}
}