{
  "type": "Feature",
  "properties": {
    "iso:country":"US",
    "sg:address":"6818 Niagra St",
    "sg:city":"Romulus",
    "sg:classifiers":[
        {
            "category":"Banks & Credit Unions",
            "subcategory":"Financial Services",
            "type":"Services"
        }
    ],
    "sg:phone":"+1 734 776 4669",
    "sg:postcode":"48174",
    "sg:province":"MI",
    "sg:tags":[
        "investor",
        "real estate"
    ],
    "wof:name":"Keystone Financial Inv Group",
    "wof:placetype":"venue"
},
  "geometry": {"coordinates":[-83.35415999999999,42.254401],"type":"Point"}
}