{
  "type": "Feature",
  "properties": {
    "iso:country":"US",
    "sg:address":"404 Rounds Dr",
    "sg:city":"Fenton",
    "sg:classifiers":[
        {
            "category":"Organizations",
            "subcategory":"Membership Organization",
            "type":"Services"
        }
    ],
    "sg:phone":"+1 810 750 0351",
    "sg:postcode":"48430",
    "sg:province":"MI",
    "sg:tags":[
        "athletic"
    ],
    "wof:name":"Fenton Fitness & Athletic Ctr",
    "wof:placetype":"venue"
},
  "geometry": {"coordinates":[-83.720935,42.79183],"type":"Point"}
}