{
  "type": "Feature",
  "properties": {
    "iso:country":"US",
    "sg:address":"1214 Kalamazoo Ave SE",
    "sg:city":"Grand Rapids",
    "sg:classifiers":[
        {
            "category":"Retail",
            "subcategory":"Auto Repair",
            "type":"Services"
        }
    ],
    "sg:phone":"+1 616 813 8832",
    "sg:postcode":"49507",
    "sg:province":"MI",
    "sg:tags":[
        "wrecker"
    ],
    "wof:name":"Howell's Towing",
    "wof:placetype":"venue"
},
  "geometry": {"coordinates":[-85.64380800000001,42.940415],"type":"Point"}
}