{
  "type": "Feature",
  "properties": {
    "iso:country":"US",
    "sg:address":"927 S Carmel St",
    "sg:city":"Cadillac",
    "sg:classifiers":[
        {
            "category":"Health Services",
            "subcategory":"Doctor",
            "type":"Services"
        }
    ],
    "sg:phone":"+1 231 876 3876",
    "sg:postcode":"49601",
    "sg:province":"MI",
    "sg:tags":[
        "physician",
        "surgeon"
    ],
    "wof:name":"Verbrugge Glenn P",
    "wof:placetype":"venue"
},
  "geometry": {"coordinates":[-85.38638,44.244223],"type":"Point"}
}