{
  "type": "Feature",
  "properties": {
    "iso:country":"US",
    "sg:address":"1404 Coventry Square Dr",
    "sg:city":"Ann Arbor",
    "sg:classifiers":[
        {
            "category":"Professional",
            "subcategory":"Management & Consulting",
            "type":"Services"
        }
    ],
    "sg:phone":"+1 734 994 8500",
    "sg:postcode":"48103",
    "sg:province":"MI",
    "wof:name":"Eagle Professional Dev LLC",
    "wof:placetype":"venue"
},
  "geometry": {"coordinates":[-83.806376,42.304706],"type":"Point"}
}