{
  "type": "Feature",
  "properties": {
    "iso:country":"US",
    "sg:address":"2795 W US Hwy 20",
    "sg:city":"Angola",
    "sg:classifiers":[
        {
            "category":"Autos & Motor Vehicles",
            "subcategory":"Fuel & Gas Station",
            "type":"Retail Goods"
        }
    ],
    "sg:phone":"+1 260 665 5580",
    "sg:postcode":"46703",
    "sg:province":"MI",
    "sg:tags":[
        "oil"
    ],
    "wof:name":"Angola Amoco",
    "wof:placetype":"venue"
},
  "geometry": {"coordinates":[-85.03931300000001,41.634903],"type":"Point"}
}