{
  "type": "Feature",
  "properties": {
    "iso:country":"US",
    "sg:address":"558 Poplar St",
    "sg:city":"Clio",
    "sg:classifiers":[
        {
            "category":"Building & Trades",
            "subcategory":"Cleaning & Sanitation",
            "type":"Services"
        }
    ],
    "sg:phone":"+1 810 686 7963",
    "sg:postcode":"48420",
    "sg:province":"MI",
    "sg:tags":[
        "maintenance"
    ],
    "wof:name":"Nieces",
    "wof:placetype":"venue"
},
  "geometry": {"coordinates":[-83.725182,43.183775],"type":"Point"}
}