{
  "type": "Feature",
  "properties": {
    "iso:country":"US",
    "sg:address":"29625 Northwestern Hwy",
    "sg:city":"Southfield",
    "sg:classifiers":[
        {
            "category":"Retail",
            "subcategory":"Veterinary Services",
            "type":"Services"
        },
        {
            "category":"Retail",
            "subcategory":"Pet Boarding",
            "type":"Services"
        }
    ],
    "sg:phone":"+1 248 356 7360",
    "sg:postcode":"48034",
    "sg:province":"MI",
    "sg:tags":[
        "veterinarian",
        "boarding/pet",
        "sitting"
    ],
    "wof:name":"Atler Cindy",
    "wof:placetype":"venue"
},
  "geometry": {"coordinates":[-83.318298,42.505901],"type":"Point"}
}