{
  "type": "Feature",
  "properties": {
    "iso:country":"US",
    "sg:address":"8243 Hall Rd",
    "sg:city":"Utica",
    "sg:classifiers":[
        {
            "category":"Professional",
            "subcategory":"Employment Agencies",
            "type":"Services"
        }
    ],
    "sg:phone":"+1 586 323 3555",
    "sg:postcode":"48317",
    "sg:province":"MI",
    "sg:tags":[
        "organization"
    ],
    "wof:name":"EMC",
    "wof:placetype":"venue"
},
  "geometry": {"coordinates":[-83.030384,42.625953],"type":"Point"}
}