{
  "type": "Feature",
  "properties": {
    "iso:country":"US",
    "sg:address":"3000 Packard St",
    "sg:city":"Ann Arbor",
    "sg:classifiers":[
        {
            "category":"Restaurant",
            "type":"Food & Drink"
        }
    ],
    "sg:menulink":"http://www.allmenus.com/mi/ann-arbor/87536-little-caesars-pizza/menu/",
    "sg:phone":"+1 734 971 0933",
    "sg:postcode":"48108",
    "sg:province":"MI",
    "sg:tags":[
        "american",
        "pizza"
    ],
    "wof:name":"Little Caesar's Pizza",
    "wof:placetype":"venue"
},
  "geometry": {"coordinates":[-83.700084,42.245057],"type":"Point"}
}