{
  "type": "Feature",
  "properties": {
    "iso:country":"US",
    "sg:address":"215 N Old Woodward",
    "sg:city":"Birmingham",
    "sg:classifiers":[
        {
            "category":"Restaurant",
            "type":"Food & Drink"
        }
    ],
    "sg:phone":"+1 248 594 6316",
    "sg:postcode":"48009",
    "sg:province":"MI",
    "sg:tags":[
        "new",
        "american"
    ],
    "wof:name":"Tropical Squeeze",
    "wof:placetype":"venue"
},
  "geometry": {"coordinates":[-83.214935,42.547401],"type":"Point"}
}