{
  "type": "Feature",
  "properties": {
    "iso:country":"US",
    "sg:address":"3590 Lincoln Ave",
    "sg:city":"St Joseph",
    "sg:classifiers":[
        {
            "category":"Organizations",
            "subcategory":"Religious Organization",
            "type":"Services"
        }
    ],
    "sg:phone":"+1 269 556 7000",
    "sg:postcode":"49085",
    "sg:province":"MI",
    "sg:tags":[
        "church"
    ],
    "wof:name":"Peace Lutheran Church",
    "wof:placetype":"venue"
},
  "geometry": {"coordinates":[-86.475357,42.051047],"type":"Point"}
}