{
  "type": "Feature",
  "properties": {
    "iso:country":"US",
    "sg:address":"405 Riverside Rd",
    "sg:city":"Marquette",
    "sg:classifiers":[
        {
            "category":"Shopping",
            "subcategory":"Computers & Home Electronics",
            "type":"Retail Goods"
        }
    ],
    "sg:phone":"+1 906 226 7955",
    "sg:postcode":"49855",
    "sg:province":"MI",
    "sg:tags":[
        "software"
    ],
    "wof:name":"Maki Consulting",
    "wof:placetype":"venue"
},
  "geometry": {"coordinates":[-87.329798,46.491179],"type":"Point"}
}