{
  "type": "Feature",
  "properties": {
    "iso:country":"US",
    "sg:address":"153 Cherokee Rd",
    "sg:city":"Pontiac",
    "sg:classifiers":[
        {
            "category":"Social Services",
            "type":"Services"
        }
    ],
    "sg:phone":"+1 248 332 3591",
    "sg:postcode":"48341",
    "sg:province":"MI",
    "sg:tags":[
        "for",
        "deficiency",
        "support",
        "primary",
        "immune",
        "provides"
    ],
    "wof:name":"Immune Deficiency Foundation",
    "wof:placetype":"venue"
},
  "geometry": {"coordinates":[-83.31502399999999,42.630623],"type":"Point"}
}