{
  "type": "Feature",
  "properties": {
    "iso:country":"US",
    "sg:address":"54474 Sassafras Dr",
    "sg:city":"Shelby Twp",
    "sg:classifiers":[
        {
            "category":"Professional",
            "subcategory":"Business Services",
            "type":"Services"
        },
        {
            "category":"Building & Trades",
            "subcategory":"Construction",
            "type":"Services"
        }
    ],
    "sg:phone":"+1 586 786 1630",
    "sg:postcode":"48315",
    "sg:province":"MI",
    "sg:tags":[
        "wallpaper"
    ],
    "wof:name":"Kaleidoscope LTD",
    "wof:placetype":"venue"
},
  "geometry": {"coordinates":[-83.000952,42.695929],"type":"Point"}
}