{
  "type": "Feature",
  "properties": {
    "iso:country":"US",
    "sg:address":"112 Washington St",
    "sg:city":"Middleville",
    "sg:classifiers":[
        {
            "category":"Organizations",
            "subcategory":"Religious Organization",
            "type":"Services"
        }
    ],
    "sg:phone":"+1 269 795 6012",
    "sg:postcode":"49333",
    "sg:province":"MI",
    "wof:name":"Calvary Temple Ch of God",
    "wof:placetype":"venue"
},
  "geometry": {"coordinates":[-85.464243,42.716385],"type":"Point"}
}