{
  "type": "Feature",
  "properties": {
    "iso:country":"US",
    "sg:address":"4331 Budziak Rd",
    "sg:city":"Oscoda",
    "sg:classifiers":[
        {
            "category":"Social Services",
            "subcategory":"Child Care",
            "type":"Services"
        }
    ],
    "sg:phone":"+1 989 739 3346",
    "sg:postcode":"48730",
    "sg:province":"MI",
    "wof:name":"J V Daycare",
    "wof:placetype":"venue"
},
  "geometry": {"coordinates":[-83.345196,44.450374],"type":"Point"}
}