{
  "type": "Feature",
  "properties": {
    "iso:country":"US",
    "sg:address":"17168 Main St",
    "sg:city":"Curtis",
    "sg:classifiers":[
        {
            "category":"Real Estate",
            "subcategory":"Real Estate Agent",
            "type":"Services"
        }
    ],
    "sg:phone":"+1 906 586 9445",
    "sg:postcode":"49820",
    "sg:province":"MI",
    "wof:name":"Woods N Water Real Estate",
    "wof:placetype":"venue"
},
  "geometry": {"coordinates":[-85.736071,46.203485],"type":"Point"}
}