{
  "type": "Feature",
  "properties": {
    "iso:country":"US",
    "sg:address":"2018 Murray Rd",
    "sg:city":"Dansville",
    "sg:classifiers":[
        {
            "category":"Organizations",
            "subcategory":"Religious Organization",
            "type":"Services"
        }
    ],
    "sg:phone":"+1 517 623 0003",
    "sg:postcode":"48819",
    "sg:province":"MI",
    "sg:tags":[
        "church"
    ],
    "wof:name":"Holy Bible Church Of God",
    "wof:placetype":"venue"
},
  "geometry": {"coordinates":[-84.26830099999999,42.501585],"type":"Point"}
}