{
  "type": "Feature",
  "properties": {
    "iso:country":"US",
    "sg:address":"436 Browning Dr",
    "sg:city":"Howell",
    "sg:classifiers":[
        {
            "category":"Professional",
            "subcategory":"Accounting & Tax Preparation",
            "type":"Services"
        }
    ],
    "sg:phone":"+1 517 552 9166",
    "sg:postcode":"48843",
    "sg:province":"MI",
    "sg:tags":[
        "return"
    ],
    "wof:name":"Ray Tax Man",
    "wof:placetype":"venue"
},
  "geometry": {"coordinates":[-83.946836,42.609198],"type":"Point"}
}