{
  "type": "Feature",
  "properties": {
    "iso:country":"US",
    "sg:address":"420 N Dexter St",
    "sg:city":"Ionia",
    "sg:classifiers":[
        {
            "category":"Sports & Exercise",
            "subcategory":"Bowling",
            "type":"Entertainment"
        }
    ],
    "sg:phone":"+1 616 527 2830",
    "sg:postcode":"48846",
    "sg:province":"MI",
    "sg:tags":[
        "tavern",
        "alley"
    ],
    "wof:name":"Cat Lanes",
    "wof:placetype":"venue"
},
  "geometry": {"coordinates":[-85.07095099999999,42.986936],"type":"Point"}
}