{
  "type": "Feature",
  "properties": {
    "iso:country":"US",
    "sg:address":"42253 Parkside Cir",
    "sg:city":"Sterling Heights",
    "sg:classifiers":[
        {
            "category":"Professional",
            "subcategory":"Management & Consulting",
            "type":"Services"
        }
    ],
    "sg:phone":"+1 586 739 8506",
    "sg:postcode":"48314",
    "sg:province":"MI",
    "sg:tags":[
        "coaching",
        "for",
        "business"
    ],
    "wof:name":"Relating To Success",
    "wof:placetype":"venue"
},
  "geometry": {"coordinates":[-83.02697000000001,42.603872],"type":"Point"}
}