{
  "type": "Feature",
  "properties": {
    "iso:country":"US",
    "sg:address":"2956 Mackin Rd",
    "sg:city":"Flint",
    "sg:classifiers":[
        {
            "category":"Freight",
            "type":"Transportation"
        }
    ],
    "sg:phone":"+1 810 785 7073",
    "sg:postcode":"48504",
    "sg:province":"MI",
    "sg:tags":[
        "operator",
        "local",
        "trucking"
    ],
    "wof:name":"Peoples Trucking Inc",
    "wof:placetype":"venue"
},
  "geometry": {"coordinates":[-83.73132200000001,43.030291],"type":"Point"}
}