{
  "type": "Feature",
  "properties": {
    "iso:country":"US",
    "sg:address":"7691 S 12th St",
    "sg:city":"Portage",
    "sg:classifiers":[
        {
            "category":"Building & Trades",
            "subcategory":"Construction",
            "type":"Services"
        }
    ],
    "sg:phone":"+1 269 375 4044",
    "sg:postcode":"49024",
    "sg:province":"MI",
    "sg:tags":[
        "painter"
    ],
    "wof:name":"Kalamazoo Decorating Co",
    "wof:placetype":"venue"
},
  "geometry": {"coordinates":[-85.64818099999999,42.207896],"type":"Point"}
}