{
  "type": "Feature",
  "properties": {
    "iso:country":"US",
    "sg:address":"540 S Parker St",
    "sg:city":"Marine City",
    "sg:classifiers":[
        {
            "category":"Health Services",
            "subcategory":"Doctor",
            "type":"Services"
        }
    ],
    "sg:phone":"+1 810 765 1440",
    "sg:postcode":"48039",
    "sg:province":"MI",
    "sg:tags":[
        "dentist"
    ],
    "wof:name":"Kenneth J Mc Cormick DDS",
    "wof:placetype":"venue"
},
  "geometry": {"coordinates":[-82.500505,42.71431],"type":"Point"}
}