{
  "type": "Feature",
  "properties": {
    "iso:country":"US",
    "sg:address":"4071 W Jefferson Ave",
    "sg:city":"Ecorse",
    "sg:classifiers":[
        {
            "category":"Personal",
            "subcategory":"Beauty Salon",
            "type":"Services"
        }
    ],
    "sg:phone":"+1 313 928 0882",
    "sg:postcode":"48229",
    "sg:province":"MI",
    "sg:tags":[
        "hair"
    ],
    "wof:name":"Russ Barber Shop",
    "wof:placetype":"venue"
},
  "geometry": {"coordinates":[-83.141098,42.250801],"type":"Point"}
}