{
  "type": "Feature",
  "properties": {
    "iso:country":"US",
    "sg:address":"8320 Conant St",
    "sg:city":"Detroit",
    "sg:classifiers":[
        {
            "category":"Retail",
            "subcategory":"Auto Repair",
            "type":"Services"
        }
    ],
    "sg:phone":"+1 313 921 0767",
    "sg:postcode":"48211",
    "sg:province":"MI",
    "sg:tags":[
        "body",
        "shop"
    ],
    "wof:name":"Ample Car Market",
    "wof:placetype":"venue"
},
  "geometry": {"coordinates":[-83.04360200000001,42.389801],"type":"Point"}
}