{
  "type": "Feature",
  "properties": {
    "iso:country":"US",
    "sg:address":"1550 Rulane Dr",
    "sg:city":"Lapeer",
    "sg:classifiers":[
        {
            "category":"Professional",
            "type":"Services"
        }
    ],
    "sg:phone":"+1 810 667 4869",
    "sg:postcode":"48446",
    "sg:province":"MI",
    "sg:tags":[
        "establishment"
    ],
    "wof:name":"Sandy's Enterprises Inc",
    "wof:placetype":"venue"
},
  "geometry": {"coordinates":[-83.323183,43.065294],"type":"Point"}
}