{
  "type": "Feature",
  "properties": {
    "iso:country":"US",
    "sg:address":"1423 7th St",
    "sg:city":"Menominee",
    "sg:classifiers":[
        {
            "category":"Social Services",
            "type":"Services"
        }
    ],
    "sg:phone":"+1 906 863 9512",
    "sg:postcode":"49858",
    "sg:province":"MI",
    "sg:tags":[
        "youth",
        "organization",
        "center"
    ],
    "wof:name":"DAR Boys & Girls Club",
    "wof:placetype":"venue"
},
  "geometry": {"coordinates":[-87.611026,45.111907],"type":"Point"}
}