{
  "type": "Feature",
  "properties": {
    "iso:country":"US",
    "sg:address":"171 W Pike St",
    "sg:city":"Pontiac",
    "sg:classifiers":[
        {
            "category":"Organizations",
            "subcategory":"Religious Organization",
            "type":"Services"
        }
    ],
    "sg:phone":"+1 248 334 4571",
    "sg:postcode":"48341",
    "sg:province":"MI",
    "sg:tags":[
        "church"
    ],
    "sg:website":"www.allsaintspontiac.org",
    "wof:name":"All Saints Episcopal Church",
    "wof:placetype":"venue"
},
  "geometry": {"coordinates":[-83.298401,42.6353],"type":"Point"}
}