{
  "type": "Feature",
  "properties": {
    "iso:country":"US",
    "sg:address":"204 W 7th St",
    "sg:city":"Clare",
    "sg:classifiers":[
        {
            "category":"Social Services",
            "subcategory":"Adult Care",
            "type":"Services"
        }
    ],
    "sg:phone":"+1 989 386 2672",
    "sg:postcode":"48617",
    "sg:province":"MI",
    "sg:tags":[
        "day",
        "provider"
    ],
    "wof:name":"Barbara Blystone",
    "wof:placetype":"venue"
},
  "geometry": {"coordinates":[-84.77188599999999,43.821551],"type":"Point"}
}