{
  "type": "Feature",
  "properties": {
    "iso:country":"US",
    "sg:address":"11359 James St",
    "sg:city":"Holland",
    "sg:classifiers":[
        {
            "category":"Manufacturing",
            "subcategory":"Retail Goods",
            "type":"Manufacturing & Wholesale Goods"
        }
    ],
    "sg:phone":"+1 616 395 2075",
    "sg:postcode":"49424",
    "sg:province":"MI",
    "sg:tags":[
        "assembly",
        "fabricating"
    ],
    "sg:website":"www.dentalert.net",
    "wof:name":"Subassembly Plus Inc",
    "wof:placetype":"venue"
},
  "geometry": {"coordinates":[-86.060603,42.812409],"type":"Point"}
}