{
  "type": "Feature",
  "properties": {
    "iso:country":"US",
    "sg:address":"4101 John R Rd Ste 300",
    "sg:city":"Troy",
    "sg:classifiers":[
        {
            "category":"Health Services",
            "subcategory":"Chiropractor",
            "type":"Services"
        }
    ],
    "sg:phone":"+1 248 680 7200",
    "sg:postcode":"48085",
    "sg:province":"MI",
    "sg:website":"www.nuccainfo.com",
    "wof:name":"Precise Chiropractic",
    "wof:placetype":"venue"
},
  "geometry": {"coordinates":[-83.109126,42.579943],"type":"Point"}
}