{
  "type": "Feature",
  "properties": {
    "iso:country":"US",
    "sg:address":"21200 Schoenherr Rd",
    "sg:city":"Warren",
    "sg:classifiers":[
        {
            "category":"Organizations",
            "subcategory":"Labor Organization",
            "type":"Services"
        }
    ],
    "sg:phone":"+1 248 543 3847",
    "sg:postcode":"48089",
    "sg:province":"MI",
    "wof:name":"Roofers Apprentice School",
    "wof:placetype":"venue"
},
  "geometry": {"coordinates":[-82.985601,42.449384],"type":"Point"}
}