{
  "type": "Feature",
  "properties": {
    "iso:country":"US",
    "sg:address":"106 E Mills St",
    "sg:city":"Sandusky",
    "sg:classifiers":[
        {
            "category":"Professional",
            "subcategory":"Business Services",
            "type":"Services"
        }
    ],
    "sg:phone":"+1 810 648 9793",
    "sg:postcode":"48471",
    "sg:province":"MI",
    "wof:name":"Gemini Investigation",
    "wof:placetype":"venue"
},
  "geometry": {"coordinates":[-82.8253,43.415894],"type":"Point"}
}