{
  "type": "Feature",
  "properties": {
    "iso:country":"US",
    "sg:address":"27497 Eureka Rd",
    "sg:city":"Romulus",
    "sg:classifiers":[
        {
            "category":"Insurance",
            "subcategory":"Insurance Agent",
            "type":"Services"
        }
    ],
    "sg:phone":"+1 734 955 8000",
    "sg:postcode":"48174",
    "sg:province":"MI",
    "wof:name":"L A Insurance Agencies",
    "wof:placetype":"venue"
},
  "geometry": {"coordinates":[-83.307076,42.195861],"type":"Point"}
}