{
  "type": "Feature",
  "properties": {
    "iso:country":"US",
    "sg:address":"945 Freeman Ave SW",
    "sg:city":"Grand Rapids",
    "sg:classifiers":[
        {
            "category":"Freight",
            "type":"Transportation"
        }
    ],
    "sg:phone":"+1 616 247 7900",
    "sg:postcode":"49503",
    "sg:province":"MI",
    "sg:tags":[
        "heavy",
        "warehouse",
        "machinery"
    ],
    "wof:name":"Grand Rapids Steel Distrbtn",
    "wof:placetype":"venue"
},
  "geometry": {"coordinates":[-85.694768,42.949597],"type":"Point"}
}