{
  "type": "Feature",
  "properties": {
    "iso:country":"US",
    "sg:address":"602 Brown St",
    "sg:city":"Norway",
    "sg:classifiers":[
        {
            "category":"Food & Beverages",
            "subcategory":"Candy",
            "type":"Retail Goods"
        }
    ],
    "sg:phone":"+1 906 563 7330",
    "sg:postcode":"49870",
    "sg:province":"MI",
    "sg:tags":[
        "making",
        "supply"
    ],
    "wof:name":"Mary Beth's Cake Shoppe",
    "wof:placetype":"venue"
},
  "geometry": {"coordinates":[-87.909813,45.787279],"type":"Point"}
}