{
  "type": "Feature",
  "properties": {
    "iso:country":"US",
    "sg:address":"2135 N Center Rd",
    "sg:city":"Saginaw",
    "sg:classifiers":[
        {
            "category":"Professional",
            "subcategory":"Accounting & Tax Preparation",
            "type":"Services"
        }
    ],
    "sg:phone":"+1 989 497 0185",
    "sg:postcode":"48603",
    "sg:province":"MI",
    "sg:tags":[
        "return",
        "filing"
    ],
    "wof:name":"Da-Mar Tax & Accounting",
    "wof:placetype":"venue"
},
  "geometry": {"coordinates":[-84.014771,43.437076],"type":"Point"}
}