{
  "type": "Feature",
  "properties": {
    "iso:country":"US",
    "sg:address":"5080 Swan Creek Rd",
    "sg:city":"Saginaw",
    "sg:classifiers":[
        {
            "category":"Farming",
            "subcategory":"Nursery",
            "type":"Manufacturing & Wholesale Goods"
        }
    ],
    "sg:phone":"+1 989 792 2039",
    "sg:postcode":"48609",
    "sg:province":"MI",
    "sg:tags":[
        "greenhouse"
    ],
    "wof:name":"Boehler's Greenhouse",
    "wof:placetype":"venue"
},
  "geometry": {"coordinates":[-84.01759199999999,43.37961],"type":"Point"}
}