{
  "type": "Feature",
  "properties": {
    "iso:country":"US",
    "sg:address":"604 W Bridge St",
    "sg:city":"Big Rapids",
    "sg:classifiers":[
        {
            "category":"Organizations",
            "subcategory":"Religious Organization",
            "type":"Services"
        }
    ],
    "sg:phone":"+1 231 796 6505",
    "sg:postcode":"49307",
    "sg:province":"MI",
    "sg:tags":[
        "church"
    ],
    "wof:name":"Big Rapids Free Methodist Chr",
    "wof:placetype":"venue"
},
  "geometry": {"coordinates":[-85.49368200000001,43.705911],"type":"Point"}
}