{
  "type": "Feature",
  "properties": {
    "iso:country":"US",
    "sg:address":"2186 N Telegraph Rd",
    "sg:city":"Monroe",
    "sg:classifiers":[
        {
            "category":"Freight",
            "type":"Transportation"
        }
    ],
    "sg:phone":"+1 734 243 2725",
    "sg:postcode":"48162",
    "sg:province":"MI",
    "sg:tags":[
        "hauling",
        "trucking"
    ],
    "wof:name":"Foster Trucking",
    "wof:placetype":"venue"
},
  "geometry": {"coordinates":[-83.397243,41.953732],"type":"Point"}
}