{
  "type": "Feature",
  "properties": {
    "iso:country":"US",
    "sg:address":"510 S Euclid Ave",
    "sg:city":"Bay City",
    "sg:classifiers":[
        {
            "category":"Health Services",
            "subcategory":"Doctor",
            "type":"Services"
        }
    ],
    "sg:phone":"+1 989 684 3505",
    "sg:postcode":"48706",
    "sg:province":"MI",
    "sg:tags":[
        "physician",
        "surgeon",
        "medical"
    ],
    "wof:name":"East Central Oncology Assoc PC",
    "wof:placetype":"venue"
},
  "geometry": {"coordinates":[-83.91547199999999,43.596305],"type":"Point"}
}