{
  "type": "Feature",
  "properties": {
    "iso:country":"US",
    "sg:address":"18275 Quarry St",
    "sg:city":"Riverview",
    "sg:classifiers":[
        {
            "category":"Retail",
            "subcategory":"Event Space",
            "type":"Services"
        }
    ],
    "sg:phone":"+1 734 282 2198",
    "sg:postcode":"48193",
    "sg:province":"MI",
    "sg:tags":[
        "venue"
    ],
    "sg:website":"www.arnaldosbanquetcenter.com",
    "wof:name":"Arnaldo's Banquet & Catering",
    "wof:placetype":"venue"
},
  "geometry": {"coordinates":[-83.179182,42.176059],"type":"Point"}
}