{
  "type": "Feature",
  "properties": {
    "iso:country":"US",
    "sg:address":"7250 Venoy Rd",
    "sg:city":"Romulus",
    "sg:classifiers":[
        {
            "category":"Shopping",
            "subcategory":"Pharmacy",
            "type":"Retail Goods"
        }
    ],
    "sg:phone":"+1 734 422 5150",
    "sg:postcode":"48174",
    "sg:province":"MI",
    "sg:tags":[
        "drugstore"
    ],
    "sg:website":"www.cvs.com",
    "wof:name":"Cvs Pharmacy",
    "wof:placetype":"venue"
},
  "geometry": {"coordinates":[-83.362185,42.252057],"type":"Point"}
}