{
  "type": "Feature",
  "properties": {
    "iso:country":"US",
    "sg:address":"2045 E South St",
    "sg:city":"Jackson",
    "sg:classifiers":[
        {
            "category":"Food & Beverages",
            "subcategory":"Groceries & Convenience Stores",
            "type":"Retail Goods"
        }
    ],
    "sg:phone":"+1 517 796 8320",
    "sg:postcode":"49203",
    "sg:province":"MI",
    "wof:name":"Save Time Convenience Stores",
    "wof:placetype":"venue"
},
  "geometry": {"coordinates":[-84.366394,42.222425],"type":"Point"}
}