{
  "type": "Feature",
  "properties": {
    "iso:country":"US",
    "sg:address":"36150 Dequindre Rd Ste 730",
    "sg:city":"Sterling Heights",
    "sg:classifiers":[
        {
            "category":"Health Services",
            "subcategory":"Chiropractor",
            "type":"Services"
        }
    ],
    "sg:phone":"+1 586 979 4950",
    "sg:postcode":"48310",
    "sg:province":"MI",
    "wof:name":"Brown Chiropractic",
    "wof:placetype":"venue"
},
  "geometry": {"coordinates":[-83.08842,42.556709],"type":"Point"}
}