{
  "type": "Feature",
  "properties": {
    "iso:country":"US",
    "sg:address":"924 W. Ann Arbor Trail",
    "sg:city":"Plymouth",
    "sg:classifiers":[
        {
            "category":"Community Center",
            "subcategory":"Senior",
            "type":"Public Place"
        }
    ],
    "sg:phone":"+1 734 453 8797",
    "sg:postcode":"48170",
    "sg:province":"MI",
    "sg:tags":[
        "leisure"
    ],
    "sg:website":"www.creatopiapottery.com/creatopia/",
    "wof:name":"Creatopia",
    "wof:placetype":"venue"
},
  "geometry": {"coordinates":[-83.47085,42.370015],"type":"Point"}
}