{
  "type": "Feature",
  "properties": {
    "iso:country":"US",
    "sg:address":"507 S Cedar St",
    "sg:city":"Owosso",
    "sg:classifiers":[
        {
            "category":"Autos & Motor Vehicles",
            "subcategory":"Boat Sales",
            "type":"Retail Goods"
        }
    ],
    "sg:phone":"+1 989 725 5611",
    "sg:postcode":"48867",
    "sg:province":"MI",
    "sg:tags":[
        "top",
        "upholstery",
        "cover"
    ],
    "wof:name":"R-Dee's Covers",
    "wof:placetype":"venue"
},
  "geometry": {"coordinates":[-84.181675,42.99334],"type":"Point"}
}