{
  "type": "Feature",
  "properties": {
    "iso:country":"US",
    "sg:address":"6950 Halstead Rd",
    "sg:city":"West Bloomfield",
    "sg:classifiers":[
        {
            "category":"Building & Trades",
            "subcategory":"Landscaping Services",
            "type":"Services"
        }
    ],
    "sg:phone":"+1 248 661 0110",
    "sg:postcode":"48322",
    "sg:province":"MI",
    "sg:tags":[
        "landscape",
        "contractor"
    ],
    "wof:name":"Johonnot Landscape & Tree",
    "wof:placetype":"venue"
},
  "geometry": {"coordinates":[-83.419397,42.53607],"type":"Point"}
}