{
  "type": "Feature",
  "properties": {
    "iso:country":"US",
    "sg:address":"7022 E Michigan Ave",
    "sg:city":"Kalamazoo",
    "sg:classifiers":[
        {
            "category":"Organizations",
            "subcategory":"Religious Organization",
            "type":"Services"
        }
    ],
    "sg:phone":"+1 269 349 3758",
    "sg:postcode":"49048",
    "sg:province":"MI",
    "wof:name":"Word For Life Church Of God",
    "wof:placetype":"venue"
},
  "geometry": {"coordinates":[-85.49096,42.28831],"type":"Point"}
}