{
  "type": "Feature",
  "properties": {
    "iso:country":"US",
    "sg:address":"4806 Holly Way",
    "sg:city":"Ann Arbor",
    "sg:classifiers":[
        {
            "category":"Shopping",
            "subcategory":"Used Merchandise",
            "type":"Retail Goods"
        }
    ],
    "sg:phone":"+1 734 426 5736",
    "sg:postcode":"48103",
    "sg:province":"MI",
    "wof:name":"Cr Antiques",
    "wof:placetype":"venue"
},
  "geometry": {"coordinates":[-83.816391,42.34702],"type":"Point"}
}