{
  "type": "Feature",
  "properties": {
    "iso:country":"US",
    "sg:address":"38316 Golfview Dr",
    "sg:city":"Farmington",
    "sg:classifiers":[
        {
            "category":"Professional",
            "subcategory":"Engineering",
            "type":"Services"
        }
    ],
    "sg:phone":"+1 248 489 1239",
    "sg:postcode":"48331",
    "sg:province":"MI",
    "wof:name":"Rvp & S Inc",
    "wof:placetype":"venue"
},
  "geometry": {"coordinates":[-83.426804,42.501795],"type":"Point"}
}