{
  "type": "Feature",
  "properties": {
    "iso:country":"US",
    "sg:address":"2744 W Marr Rd",
    "sg:city":"Howell",
    "sg:classifiers":[
        {
            "category":"Building & Trades",
            "subcategory":"Landscaping Services",
            "type":"Services"
        }
    ],
    "sg:phone":"+1 517 552 0542",
    "sg:postcode":"48855",
    "sg:province":"MI",
    "sg:tags":[
        "tree"
    ],
    "wof:name":"Treemaster Inc",
    "wof:placetype":"venue"
},
  "geometry": {"coordinates":[-83.96652899999999,42.666303],"type":"Point"}
}