{
  "type": "Feature",
  "properties": {
    "iso:country":"US",
    "sg:address":"6800 Cleveland Ave",
    "sg:city":"Stevensville",
    "sg:classifiers":[
        {
            "category":"Real Estate",
            "subcategory":"Real Estate Services",
            "type":"Services"
        }
    ],
    "sg:phone":"+1 269 422 1555",
    "sg:postcode":"49127",
    "sg:province":"MI",
    "sg:tags":[
        "abstract",
        "title"
    ],
    "wof:name":"Berrier Title Search Serv",
    "wof:placetype":"venue"
},
  "geometry": {"coordinates":[-86.49491399999999,41.99516],"type":"Point"}
}