{
  "type": "Feature",
  "properties": {
    "iso:country":"US",
    "sg:address":"3455 Jefferson Hwy",
    "sg:city":"Grand Ledge",
    "sg:classifiers":[
        {
            "category":"Wholesale",
            "subcategory":"Auto Parts",
            "type":"Manufacturing & Wholesale Goods"
        }
    ],
    "sg:phone":"+1 517 627 8855",
    "sg:postcode":"48837",
    "sg:province":"MI",
    "sg:tags":[
        "automobile",
        "rebuilt"
    ],
    "wof:name":"Quinn's Auto Parts",
    "wof:placetype":"venue"
},
  "geometry": {"coordinates":[-84.775125,42.755519],"type":"Point"}
}