{
  "type": "Feature",
  "properties": {
    "iso:country":"US",
    "sg:address":"801 Ruskin Ave",
    "sg:city":"Algonac",
    "sg:classifiers":[
        {
            "category":"Building & Trades",
            "subcategory":"Construction",
            "type":"Services"
        }
    ],
    "sg:phone":"+1 810 794 7545",
    "sg:postcode":"48001",
    "sg:province":"MI",
    "sg:tags":[
        "house"
    ],
    "wof:name":"Rjm Home Improvements",
    "wof:placetype":"venue"
},
  "geometry": {"coordinates":[-82.54301100000001,42.611577],"type":"Point"}
}