{
  "type": "Feature",
  "properties": {
    "iso:country":"US",
    "sg:address":"4701 Towne Centre Rd",
    "sg:city":"Saginaw",
    "sg:classifiers":[
        {
            "category":"Health Services",
            "subcategory":"Doctor",
            "type":"Services"
        }
    ],
    "sg:phone":"+1 989 790 1437",
    "sg:postcode":"48604",
    "sg:province":"MI",
    "sg:tags":[
        "physician",
        "surgeon"
    ],
    "wof:name":"Laser Treatment Ctr",
    "wof:placetype":"venue"
},
  "geometry": {"coordinates":[-83.963596,43.475586],"type":"Point"}
}