{
  "type": "Feature",
  "properties": {
    "iso:country":"US",
    "sg:address":"2460 Lakeshore Dr",
    "sg:city":"Saint Joseph",
    "sg:classifiers":[
        {
            "category":"Health Services",
            "subcategory":"Doctor",
            "type":"Services"
        }
    ],
    "sg:phone":"+1 269 983 5583",
    "sg:postcode":"49085",
    "sg:province":"MI",
    "sg:tags":[
        "medical"
    ],
    "wof:name":"Klug Rick E DDS",
    "wof:placetype":"venue"
},
  "geometry": {"coordinates":[-86.49531399999999,42.091284],"type":"Point"}
}