{
  "type": "Feature",
  "properties": {
    "iso:country":"US",
    "sg:address":"16800 E 9 Mile Rd",
    "sg:city":"Eastpointe",
    "sg:classifiers":[
        {
            "category":"Retail",
            "subcategory":"Auto Repair",
            "type":"Services"
        }
    ],
    "sg:phone":"+1 586 776 5552",
    "sg:postcode":"48021",
    "sg:province":"MI",
    "sg:website":"www.mobil.com",
    "wof:name":"Nine Mile-I 94 Mobil Service",
    "wof:placetype":"venue"
},
  "geometry": {"coordinates":[-82.948601,42.464699],"type":"Point"}
}