{
  "type": "Feature",
  "properties": {
    "iso:country":"US",
    "sg:address":"5848 N Stiles Rd",
    "sg:city":"Ludington",
    "sg:classifiers":[
        {
            "category":"Utilities",
            "subcategory":"Refuse",
            "type":"Services"
        }
    ],
    "sg:phone":"+1 231 843 9129",
    "sg:postcode":"49431",
    "sg:province":"MI",
    "sg:tags":[
        "garbage",
        "collection"
    ],
    "wof:name":"Waste Reduction Systems",
    "wof:placetype":"venue"
},
  "geometry": {"coordinates":[-86.340603,44.056193],"type":"Point"}
}