{
  "type": "Feature",
  "properties": {
    "iso:country":"US",
    "sg:address":"37700 Harper Ave",
    "sg:city":"Clinton Twp",
    "sg:classifiers":[
        {
            "category":"Health Services",
            "subcategory":"Nursing And Care Facility",
            "type":"Services"
        }
    ],
    "sg:phone":"+1 586 468 7174",
    "sg:postcode":"48036",
    "sg:province":"MI",
    "sg:tags":[
        "home",
        "convalescent"
    ],
    "wof:name":"Lakepointe Villa Nursing Ctr",
    "wof:placetype":"venue"
},
  "geometry": {"coordinates":[-82.871391,42.573103],"type":"Point"}
}