{
  "type": "Feature",
  "properties": {
    "iso:country":"US",
    "sg:address":"1481 Ronnie St",
    "sg:city":"Flint",
    "sg:classifiers":[
        {
            "category":"Shopping",
            "subcategory":"Jewelry",
            "type":"Retail Goods"
        }
    ],
    "sg:phone":"+1 810 239 0881",
    "sg:postcode":"48507",
    "sg:province":"MI",
    "wof:name":"Llandlyon Unlimited",
    "wof:placetype":"venue"
},
  "geometry": {"coordinates":[-83.7115,42.967096],"type":"Point"}
}