{
  "type": "Feature",
  "properties": {
    "iso:country":"US",
    "sg:address":"2800 Ludington St",
    "sg:city":"Escanaba",
    "sg:classifiers":[
        {
            "category":"Banks & Credit Unions",
            "subcategory":"Bank",
            "type":"Services"
        }
    ],
    "sg:phone":"+1 906 786 3355",
    "sg:postcode":"49829",
    "sg:province":"MI",
    "sg:website":"www.first-bank.com",
    "wof:name":"First Bank Upper Michigan",
    "wof:placetype":"venue"
},
  "geometry": {"coordinates":[-87.086969,45.745821],"type":"Point"}
}