{
  "type": "Feature",
  "properties": {
    "iso:country":"US",
    "sg:address":"1659 S Dow Rd",
    "sg:city":"West Branch",
    "sg:classifiers":[
        {
            "category":"Building & Trades",
            "subcategory":"Construction",
            "type":"Services"
        }
    ],
    "sg:phone":"+1 989 345 0326",
    "sg:postcode":"48661",
    "sg:province":"MI",
    "sg:tags":[
        "paving",
        "contractor"
    ],
    "wof:name":"Hodgins Asphalt Paving Co",
    "wof:placetype":"venue"
},
  "geometry": {"coordinates":[-84.246358,44.284489],"type":"Point"}
}