{
  "type": "Feature",
  "properties": {
    "iso:country":"US",
    "sg:address":"18406 Parkside St",
    "sg:city":"Detroit",
    "sg:classifiers":[
        {
            "category":"Real Estate",
            "subcategory":"Real Estate Agent",
            "type":"Services"
        }
    ],
    "sg:phone":"+1 313 345 3000",
    "sg:postcode":"48221",
    "sg:province":"MI",
    "sg:tags":[
        "housing",
        "income",
        "low",
        "family",
        "for"
    ],
    "wof:name":"Managed Estates",
    "wof:placetype":"venue"
},
  "geometry": {"coordinates":[-83.132068,42.428071],"type":"Point"}
}