{
  "type": "Feature",
  "properties": {
    "iso:country":"US",
    "sg:address":"29006 Forest Hill Dr",
    "sg:city":"Farmington Hills",
    "sg:classifiers":[
        {
            "category":"Health Services",
            "subcategory":"Doctor",
            "type":"Services"
        }
    ],
    "sg:phone":"+1 248 553 3087",
    "sg:postcode":"48331",
    "sg:province":"MI",
    "wof:name":"Ayeni Kehinde MD PC",
    "wof:placetype":"venue"
},
  "geometry": {"coordinates":[-83.409897,42.5065],"type":"Point"}
}