{
  "type": "Feature",
  "properties": {
    "iso:country":"US",
    "sg:address":"5074 Daly Blvd",
    "sg:city":"Flint",
    "sg:classifiers":[
        {
            "category":"Home & Garden",
            "subcategory":"Building Materials",
            "type":"Retail Goods"
        }
    ],
    "sg:phone":"+1 810 736 3925",
    "sg:postcode":"48506",
    "sg:province":"MI",
    "sg:tags":[
        "windows"
    ],
    "wof:name":"Diamond Window & Glass Co",
    "wof:placetype":"venue"
},
  "geometry": {"coordinates":[-83.612448,43.070562],"type":"Point"}
}