{
  "type": "Feature",
  "properties": {
    "iso:country":"US",
    "sg:address":"16531 Hi Land Trl",
    "sg:city":"Fenton",
    "sg:classifiers":[
        {
            "category":"Professional",
            "type":"Services"
        }
    ],
    "sg:phone":"+1 810 629 5902",
    "sg:postcode":"48451",
    "sg:province":"MI",
    "sg:tags":[
        "establishment"
    ],
    "wof:name":"Strongrich & Reschly Inc",
    "wof:placetype":"venue"
},
  "geometry": {"coordinates":[-83.767959,42.783666],"type":"Point"}
}