{
  "type": "Feature",
  "properties": {
    "iso:country":"US",
    "sg:address":"5378 E Gallivan Rd",
    "sg:city":"Cedar",
    "sg:classifiers":[
        {
            "category":"Organizations",
            "subcategory":"Religious Organization",
            "type":"Services"
        }
    ],
    "sg:phone":"+1 231 946 5641",
    "sg:postcode":"49621",
    "sg:province":"MI",
    "sg:tags":[
        "church"
    ],
    "wof:name":"Zion Baptist Church",
    "wof:placetype":"venue"
},
  "geometry": {"coordinates":[-85.746706,44.818632],"type":"Point"}
}