{
  "type": "Feature",
  "properties": {
    "iso:country":"US",
    "sg:address":"310 S Minerva Ave",
    "sg:city":"Royal Oak",
    "sg:classifiers":[
        {
            "category":"Building & Trades",
            "subcategory":"Landscaping Services",
            "type":"Services"
        }
    ],
    "sg:phone":"+1 248 543 0548",
    "sg:postcode":"48067",
    "sg:province":"MI",
    "wof:name":"Master Gardener Lawncare",
    "wof:placetype":"venue"
},
  "geometry": {"coordinates":[-83.11898600000001,42.490015],"type":"Point"}
}