{
  "type": "Feature",
  "properties": {
    "iso:country":"US",
    "sg:address":"8900 W 8 Mile Rd",
    "sg:city":"Ferndale",
    "sg:classifiers":[
        {
            "category":"Building & Trades",
            "subcategory":"Construction",
            "type":"Services"
        }
    ],
    "sg:phone":"+1 248 546 6565",
    "sg:postcode":"48220",
    "sg:province":"MI",
    "sg:tags":[
        "front",
        "store"
    ],
    "wof:name":"Simply Fashions LTD",
    "wof:placetype":"venue"
},
  "geometry": {"coordinates":[-83.15481,42.446171],"type":"Point"}
}