{
  "type": "Feature",
  "properties": {
    "iso:country":"US",
    "sg:address":"417 W 14 Mile Rd",
    "sg:city":"Clawson",
    "sg:classifiers":[
        {
            "category":"Retail",
            "subcategory":"Pet Boarding",
            "type":"Services"
        }
    ],
    "sg:phone":"+1 248 288 4638",
    "sg:postcode":"48017",
    "sg:province":"MI",
    "sg:tags":[
        "boarding/pet",
        "sitting"
    ],
    "wof:name":"Robin's Wash N Wag",
    "wof:placetype":"venue"
},
  "geometry": {"coordinates":[-83.15266800000001,42.533258],"type":"Point"}
}