{
  "type": "Feature",
  "properties": {
    "iso:country":"US",
    "sg:address":"27098 Taft Rd",
    "sg:city":"Novi",
    "sg:classifiers":[
        {
            "category":"Professional",
            "subcategory":"Management & Consulting",
            "type":"Services"
        }
    ],
    "sg:phone":"+1 248 615 9300",
    "sg:postcode":"48377",
    "sg:province":"MI",
    "sg:tags":[
        "business"
    ],
    "wof:name":"Elan Engineering Inc",
    "wof:placetype":"venue"
},
  "geometry": {"coordinates":[-83.49584,42.492254],"type":"Point"}
}