{
  "type": "Feature",
  "properties": {
    "iso:country":"US",
    "sg:address":"9164 Baldwin Rd",
    "sg:city":"Gaines",
    "sg:classifiers":[
        {
            "category":"Building & Trades",
            "subcategory":"Construction",
            "type":"Services"
        }
    ],
    "sg:phone":"+1 989 271 2024",
    "sg:postcode":"48436",
    "sg:province":"MI",
    "sg:tags":[
        "contractor"
    ],
    "wof:name":"Kelsey Brothers",
    "wof:placetype":"venue"
},
  "geometry": {"coordinates":[-83.855298,42.88392],"type":"Point"}
}