{
  "type": "Feature",
  "properties": {
    "iso:country":"US",
    "sg:address":"1417 S Burdick St",
    "sg:city":"Kalamazoo",
    "sg:classifiers":[
        {
            "category":"Wholesale",
            "subcategory":"Electrical",
            "type":"Manufacturing & Wholesale Goods"
        }
    ],
    "sg:phone":"+1 269 343 2567",
    "sg:postcode":"49001",
    "sg:province":"MI",
    "sg:tags":[
        "control"
    ],
    "sg:website":"www.wilsonbrinker.com",
    "wof:name":"Wilson-Brinker Assoc Inc",
    "wof:placetype":"venue"
},
  "geometry": {"coordinates":[-85.582883,42.276779],"type":"Point"}
}