{
  "type": "Feature",
  "properties": {
    "iso:country":"US",
    "sg:address":"5601 Woodview Pass",
    "sg:city":"Midland",
    "sg:classifiers":[
        {
            "category":"Wholesale",
            "subcategory":"Jewelry",
            "type":"Manufacturing & Wholesale Goods"
        }
    ],
    "sg:phone":"+1 989 832 4918",
    "sg:postcode":"48642",
    "sg:province":"MI",
    "sg:tags":[
        "stone"
    ],
    "wof:name":"Teedy Beadies",
    "wof:placetype":"venue"
},
  "geometry": {"coordinates":[-84.214356,43.647941],"type":"Point"}
}