{
  "type": "Feature",
  "properties": {
    "iso:country":"US",
    "sg:address":"224 Sisu Knoll Dr",
    "sg:city":"Brighton",
    "sg:classifiers":[
        {
            "category":"Retail",
            "subcategory":"Repair Shop",
            "type":"Services"
        }
    ],
    "sg:phone":"+1 810 220 4853",
    "sg:postcode":"48116",
    "sg:province":"MI",
    "sg:tags":[
        "antique",
        "restoring"
    ],
    "wof:name":"Timbur Finishing",
    "wof:placetype":"venue"
},
  "geometry": {"coordinates":[-83.777942,42.51938],"type":"Point"}
}