{
  "type": "Feature",
  "properties": {
    "iso:country":"US",
    "sg:address":"4955 Granger Rd",
    "sg:city":"Oxford",
    "sg:classifiers":[
        {
            "category":"Building & Trades",
            "subcategory":"Construction",
            "type":"Services"
        }
    ],
    "sg:phone":"+1 248 236 9844",
    "sg:postcode":"48371",
    "sg:province":"MI",
    "sg:tags":[
        "contractor"
    ],
    "wof:name":"Clasman Tile",
    "wof:placetype":"venue"
},
  "geometry": {"coordinates":[-83.364524,42.838173],"type":"Point"}
}