{
  "type": "Feature",
  "properties": {
    "iso:country":"US",
    "sg:address":"5520 School Rd",
    "sg:city":"Petersburg",
    "sg:classifiers":[
        {
            "category":"Retail",
            "subcategory":"Repair Shop",
            "type":"Services"
        }
    ],
    "sg:phone":"+1 734 854 8542",
    "sg:postcode":"49270",
    "sg:province":"MI",
    "sg:tags":[
        "plumbing",
        "drain",
        "cleaning",
        "sewer"
    ],
    "wof:name":"Great Lakes Svc & Supplies",
    "wof:placetype":"venue"
},
  "geometry": {"coordinates":[-83.684496,41.812813],"type":"Point"}
}