{
  "type": "Feature",
  "properties": {
    "iso:country":"US",
    "sg:address":"426 Minneapolis Ave",
    "sg:city":"Gladstone",
    "sg:classifiers":[
        {
            "category":"Shopping",
            "subcategory":"Crafts & Fabrics",
            "type":"Retail Goods"
        }
    ],
    "sg:phone":"+1 906 428 2985",
    "sg:postcode":"49837",
    "sg:province":"MI",
    "sg:tags":[
        "sewing"
    ],
    "wof:name":"Sew Unique",
    "wof:placetype":"venue"
},
  "geometry": {"coordinates":[-87.010642,45.843364],"type":"Point"}
}