{
  "type": "Feature",
  "properties": {
    "iso:country":"US",
    "sg:address":"63656 Walnut Rd",
    "sg:city":"Vandalia",
    "sg:classifiers":[
        {
            "category":"Building & Trades",
            "subcategory":"Construction",
            "type":"Services"
        }
    ],
    "sg:phone":"+1 269 476 9806",
    "sg:postcode":"49095",
    "sg:province":"MI",
    "sg:tags":[
        "concrete",
        "contractor"
    ],
    "wof:name":"Richards' & Sons Concrete",
    "wof:placetype":"venue"
},
  "geometry": {"coordinates":[-85.86445399999999,41.870794],"type":"Point"}
}