{
  "type": "Feature",
  "properties": {
    "iso:country":"US",
    "sg:address":"41969 Ford Rd",
    "sg:city":"Canton",
    "sg:classifiers":[
        {
            "category":"Recreation",
            "subcategory":"Amusement Park",
            "type":"Entertainment"
        }
    ],
    "sg:phone":"+1 734 844 2244",
    "sg:postcode":"48187",
    "sg:province":"MI",
    "wof:name":"Glo Golf",
    "wof:placetype":"venue"
},
  "geometry": {"coordinates":[-83.454449,42.322624],"type":"Point"}
}