{
  "type": "Feature",
  "properties": {
    "iso:country":"US",
    "sg:address":"11535 Hamburg Rd",
    "sg:city":"Whitmore Lake",
    "sg:classifiers":[
        {
            "category":"Professional",
            "subcategory":"Accounting & Tax Preparation",
            "type":"Services"
        }
    ],
    "sg:phone":"+1 810 231 6837",
    "sg:postcode":"48189",
    "sg:province":"MI",
    "wof:name":"Office Pro",
    "wof:placetype":"venue"
},
  "geometry": {"coordinates":[-83.802407,42.435736],"type":"Point"}
}