{
  "type": "Feature",
  "properties": {
    "iso:country":"US",
    "sg:address":"25800 Northwestern Hwy",
    "sg:city":"Southfield",
    "sg:classifiers":[
        {
            "category":"Professional",
            "type":"Services"
        }
    ],
    "sg:phone":"+1 248 351 7777",
    "sg:postcode":"48075",
    "sg:province":"MI",
    "wof:name":"Harris Investor Svc",
    "wof:placetype":"venue"
},
  "geometry": {"coordinates":[-83.248943,42.478238],"type":"Point"}
}