{
  "type": "Feature",
  "properties": {
    "iso:country":"US",
    "sg:address":"45430 Schoenherr Rd",
    "sg:city":"Utica",
    "sg:classifiers":[
        {
            "category":"Shopping",
            "subcategory":"Mobile Phones",
            "type":"Retail Goods"
        }
    ],
    "sg:phone":"+1 586 247 9070",
    "sg:postcode":"48315",
    "sg:province":"MI",
    "sg:website":"www.autooneinc.com",
    "wof:name":"Auto One",
    "wof:placetype":"venue"
},
  "geometry": {"coordinates":[-82.99299600000001,42.630299],"type":"Point"}
}