{
  "type": "Feature",
  "properties": {
    "iso:country":"US",
    "sg:address":"2640 E French Rd",
    "sg:city":"Saint Johns",
    "sg:phone":"+1 989 224 7716",
    "sg:postcode":"48879",
    "sg:province":"MI",
    "sg:tags":[
        "farm",
        "soybean",
        "crop",
        "general"
    ],
    "wof:name":"Reginald Stevens",
    "wof:placetype":"venue"
},
  "geometry": {"coordinates":[-84.49605699999999,43.059739],"type":"Point"}
}