{
  "type": "Feature",
  "properties": {
    "iso:country":"US",
    "sg:address":"1 Hovey St",
    "sg:city":"Oxford",
    "sg:classifiers":[
        {
            "category":"Organizations",
            "subcategory":"Religious Organization",
            "type":"Services"
        }
    ],
    "sg:phone":"+1 248 628 1610",
    "sg:postcode":"48371",
    "sg:province":"MI",
    "sg:tags":[
        "church"
    ],
    "wof:name":"Immanuel Congregational Church",
    "wof:placetype":"venue"
},
  "geometry": {"coordinates":[-83.26509799999999,42.821466],"type":"Point"}
}