{
  "type": "Feature",
  "properties": {
    "iso:country":"US",
    "sg:address":"1400 Fulton St",
    "sg:city":"Grand Haven",
    "sg:classifiers":[
        {
            "category":"Restaurant",
            "type":"Food & Drink"
        }
    ],
    "sg:phone":"+1 616 842 8640",
    "sg:postcode":"49417",
    "sg:province":"MI",
    "sg:tags":[
        "pizza"
    ],
    "wof:name":"Fricano's Pizza Tavern",
    "wof:placetype":"venue"
},
  "geometry": {"coordinates":[-86.208348,43.062985],"type":"Point"}
}