{
  "type": "Feature",
  "properties": {
    "iso:country":"US",
    "sg:address":"2612 N 5th St",
    "sg:city":"Niles",
    "sg:classifiers":[
        {
            "category":"Professional",
            "type":"Services"
        }
    ],
    "sg:phone":"+1 269 684 8255",
    "sg:postcode":"49120",
    "sg:province":"MI",
    "sg:tags":[
        "establishment"
    ],
    "wof:name":"Massee Products",
    "wof:placetype":"venue"
},
  "geometry": {"coordinates":[-86.243641,41.85826],"type":"Point"}
}