{
  "type": "Feature",
  "properties": {
    "iso:country":"US",
    "sg:address":"62 Jeff St",
    "sg:city":"Waterford",
    "sg:classifiers":[
        {
            "category":"Building & Trades",
            "subcategory":"Construction",
            "type":"Services"
        }
    ],
    "sg:phone":"+1 248 683 1563",
    "sg:postcode":"48328",
    "sg:province":"MI",
    "sg:tags":[
        "hanging",
        "contractor"
    ],
    "wof:name":"Proficient Painting Servi",
    "wof:placetype":"venue"
},
  "geometry": {"coordinates":[-83.350937,42.640584],"type":"Point"}
}