{
  "type": "Feature",
  "properties": {
    "iso:country":"US",
    "sg:address":"8472 Ronda Dr",
    "sg:city":"Canton",
    "sg:classifiers":[
        {
            "category":"Manufacturing",
            "subcategory":"Printing",
            "type":"Manufacturing & Wholesale Goods"
        }
    ],
    "sg:phone":"+1 734 737 0406",
    "sg:postcode":"48187",
    "sg:province":"MI",
    "sg:tags":[
        "work"
    ],
    "wof:name":"Reliable Bindery of Michigan",
    "wof:placetype":"venue"
},
  "geometry": {"coordinates":[-83.45277,42.349226],"type":"Point"}
}