{
  "type": "Feature",
  "properties": {
    "iso:country":"US",
    "sg:address":"10689 Red Bud Trl",
    "sg:city":"Berrien Springs",
    "sg:classifiers":[
        {
            "category":"Building & Trades",
            "subcategory":"Construction",
            "type":"Services"
        }
    ],
    "sg:phone":"+1 269 473 5333",
    "sg:postcode":"49103",
    "sg:province":"MI",
    "sg:tags":[
        "dry wall",
        "contractor"
    ],
    "wof:name":"Advanced Drywall",
    "wof:placetype":"venue"
},
  "geometry": {"coordinates":[-86.378344,41.925489],"type":"Point"}
}