{
  "type": "Feature",
  "properties": {
    "iso:country":"US",
    "sg:address":"20300 Faust Ave",
    "sg:city":"Detroit",
    "sg:classifiers":[
        {
            "category":"Real Estate",
            "subcategory":"Real Estate Operator",
            "type":"Services"
        }
    ],
    "sg:phone":"+1 313 535 5177",
    "sg:postcode":"48219",
    "sg:province":"MI",
    "sg:tags":[
        "building",
        "nonresidential"
    ],
    "wof:name":"Eagle Mountain Property",
    "wof:placetype":"venue"
},
  "geometry": {"coordinates":[-83.22471400000001,42.441871],"type":"Point"}
}