{
  "type": "Feature",
  "properties": {
    "iso:country":"US",
    "sg:address":"363 W Big Beaver Rd",
    "sg:city":"Troy",
    "sg:classifiers":[
        {
            "category":"Banks & Credit Unions",
            "subcategory":"Financial Services",
            "type":"Services"
        }
    ],
    "sg:phone":"+1 248 932 4060",
    "sg:postcode":"48084",
    "sg:province":"MI",
    "sg:tags":[
        "broker",
        "mortgage"
    ],
    "wof:name":"Fidelity Mortgage Co",
    "wof:placetype":"venue"
},
  "geometry": {"coordinates":[-83.153108,42.562171],"type":"Point"}
}