{
  "type": "Feature",
  "properties": {
    "iso:country":"US",
    "sg:address":"6491 Whaley Hwy",
    "sg:city":"Clayton",
    "sg:classifiers":[
        {
            "category":"Building & Trades",
            "subcategory":"Construction",
            "type":"Services"
        }
    ],
    "sg:phone":"+1 517 445 2724",
    "sg:postcode":"49235",
    "sg:province":"MI",
    "sg:tags":[
        "house"
    ],
    "wof:name":"Dominique Builders",
    "wof:placetype":"venue"
},
  "geometry": {"coordinates":[-84.197588,41.826688],"type":"Point"}
}