{
  "type": "Feature",
  "properties": {
    "iso:country":"US",
    "sg:address":"2931 Muirwood Ct",
    "sg:city":"Waterford",
    "sg:classifiers":[
        {
            "category":"Professional",
            "subcategory":"Business Services",
            "type":"Services"
        }
    ],
    "sg:phone":"+1 248 673 4481",
    "sg:postcode":"48329",
    "sg:province":"MI",
    "wof:name":"Okw Group LLC",
    "wof:placetype":"venue"
},
  "geometry": {"coordinates":[-83.347256,42.699975],"type":"Point"}
}