{
  "type": "Feature",
  "properties": {
    "iso:country":"US",
    "sg:address":"7788 E de Ave",
    "sg:city":"Richland",
    "sg:classifiers":[
        {
            "category":"Social Services",
            "subcategory":"Adult Care",
            "type":"Services"
        }
    ],
    "sg:phone":"+1 269 629 3178",
    "sg:postcode":"49083",
    "sg:province":"MI",
    "sg:tags":[
        "home",
        "residential"
    ],
    "wof:name":"Gull Arbor Senior Living",
    "wof:placetype":"venue"
},
  "geometry": {"coordinates":[-85.494106,42.368933],"type":"Point"}
}