{
  "type": "Feature",
  "properties": {
    "iso:country":"US",
    "sg:address":"19597 Colman St",
    "sg:city":"Clinton Twp",
    "sg:classifiers":[
        {
            "category":"Social Services",
            "subcategory":"Child Care",
            "type":"Services"
        }
    ],
    "sg:phone":"+1 586 792 3060",
    "sg:postcode":"48035",
    "sg:province":"MI",
    "wof:name":"Ms Micki's Playhouse",
    "wof:placetype":"venue"
},
  "geometry": {"coordinates":[-82.92341999999999,42.544144],"type":"Point"}
}