{
  "type": "Feature",
  "properties": {
    "iso:country":"US",
    "sg:address":"1000 S Woodward Ave",
    "sg:city":"Birmingham",
    "sg:classifiers":[
        {
            "category":"Real Estate",
            "subcategory":"Real Estate Agent",
            "type":"Services"
        }
    ],
    "sg:phone":"+1 248 647 3250",
    "sg:postcode":"48009",
    "sg:province":"MI",
    "sg:tags":[
        "management"
    ],
    "wof:name":"Sanbreen Co",
    "wof:placetype":"venue"
},
  "geometry": {"coordinates":[-83.207458,42.539624],"type":"Point"}
}