{
  "type": "Feature",
  "properties": {
    "iso:country":"US",
    "sg:address":"532 N Bossett Rd",
    "sg:city":"Ravenna",
    "sg:classifiers":[
        {
            "category":"Home & Garden",
            "subcategory":"Furniture",
            "type":"Retail Goods"
        }
    ],
    "sg:phone":"+1 231 853 6163",
    "sg:postcode":"49451",
    "sg:province":"MI",
    "wof:name":"Wiles Refurbishing",
    "wof:placetype":"venue"
},
  "geometry": {"coordinates":[-85.968222,43.262276],"type":"Point"}
}