{
  "type": "Feature",
  "properties": {
    "iso:country":"US",
    "sg:address":"48 Airport Dr",
    "sg:city":"Kimball",
    "sg:classifiers":[
        {
            "category":"Manufacturing",
            "subcategory":"Chemicals & Compounds",
            "type":"Manufacturing & Wholesale Goods"
        }
    ],
    "sg:phone":"+1 810 364 6910",
    "sg:postcode":"48079",
    "sg:province":"MI",
    "sg:tags":[
        "printing",
        "ink"
    ],
    "sg:website":"www.alliedphotochemical.com",
    "wof:name":"Allied Photochemical Inc",
    "wof:placetype":"venue"
},
  "geometry": {"coordinates":[-82.523251,42.904206],"type":"Point"}
}