{
  "type": "Feature",
  "properties": {
    "iso:country":"US",
    "sg:address":"4123 Martin Rd Ste 201",
    "sg:city":"Commerce Township",
    "sg:classifiers":[
        {
            "category":"Health Services",
            "subcategory":"Health Practitioner",
            "type":"Services"
        }
    ],
    "sg:phone":"+1 248 366 9170",
    "sg:postcode":"48390",
    "sg:province":"MI",
    "sg:tags":[
        "therapy",
        "physical"
    ],
    "sg:website":"www.s-i-p-t.com",
    "wof:name":"Shaul's Individualized Physical Therapy PC",
    "wof:placetype":"venue"
},
  "geometry": {"coordinates":[-83.449984,42.577353],"type":"Point"}
}