{
  "type": "Feature",
  "properties": {
    "iso:country":"US",
    "sg:address":"634 E Lincoln Ave",
    "sg:city":"Ionia",
    "sg:classifiers":[
        {
            "category":"Building & Trades",
            "subcategory":"Construction",
            "type":"Services"
        }
    ],
    "sg:phone":"+1 616 527 6611",
    "sg:postcode":"48846",
    "sg:province":"MI",
    "sg:tags":[
        "contractor"
    ],
    "wof:name":"B & H Drywall",
    "wof:placetype":"venue"
},
  "geometry": {"coordinates":[-85.049057,42.987462],"type":"Point"}
}