{
  "type": "Feature",
  "properties": {
    "iso:country":"US",
    "sg:address":"700 State Hwy 139",
    "sg:city":"Benton Harbor",
    "sg:classifiers":[
        {
            "category":"Retail",
            "subcategory":"Auto Repair",
            "type":"Services"
        }
    ],
    "sg:phone":"+1 269 925 4958",
    "sg:postcode":"49022",
    "sg:province":"MI",
    "sg:tags":[
        "repairing",
        "automobile"
    ],
    "wof:name":"Rapid Wrench",
    "wof:placetype":"venue"
},
  "geometry": {"coordinates":[-86.43527899999999,42.103248],"type":"Point"}
}