{
  "type": "Feature",
  "properties": {
    "iso:country":"US",
    "sg:address":"3070 State Hwy 113",
    "sg:city":"Kingsley",
    "sg:phone":"+1 231 263 5953",
    "sg:postcode":"49649",
    "sg:province":"MI",
    "sg:tags":[
        "farm",
        "grain",
        "cash"
    ],
    "wof:name":"Mehs Farm",
    "wof:placetype":"venue"
},
  "geometry": {"coordinates":[-85.514948,44.584479],"type":"Point"}
}