{
  "type": "Feature",
  "properties": {
    "iso:country":"US",
    "sg:address":"5967 Clark Rd",
    "sg:city":"Unionville",
    "sg:classifiers":[
        {
            "category":"Personal",
            "subcategory":"Beauty Salon",
            "type":"Services"
        }
    ],
    "sg:phone":"+1 989 674 2130",
    "sg:postcode":"48767",
    "sg:province":"MI",
    "sg:tags":[
        "shop"
    ],
    "wof:name":"Southgate Style Studio",
    "wof:placetype":"venue"
},
  "geometry": {"coordinates":[-83.505725,43.625202],"type":"Point"}
}