{
  "type": "Feature",
  "properties": {
    "iso:country":"US",
    "sg:address":"4996 Steadman Rd",
    "sg:city":"Ionia",
    "sg:classifiers":[
        {
            "category":"Building & Trades",
            "subcategory":"Construction",
            "type":"Services"
        }
    ],
    "sg:phone":"+1 616 527 3744",
    "sg:postcode":"48846",
    "sg:province":"MI",
    "sg:tags":[
        "house"
    ],
    "wof:name":"Helpful Hands",
    "wof:placetype":"venue"
},
  "geometry": {"coordinates":[-85.035257,43.047037],"type":"Point"}
}