{
  "type": "Feature",
  "properties": {
    "iso:country":"US",
    "sg:address":"12897 Woodward Ave",
    "sg:city":"Highland Park",
    "sg:classifiers":[
        {
            "category":"Insurance",
            "subcategory":"Health Insurance",
            "type":"Services"
        }
    ],
    "sg:phone":"+1 313 883 3593",
    "sg:postcode":"48203",
    "sg:province":"MI",
    "sg:tags":[
        "market"
    ],
    "wof:name":"Honeycomb Health Foods",
    "wof:placetype":"venue"
},
  "geometry": {"coordinates":[-83.0933,42.399941],"type":"Point"}
}