{
  "type": "Feature",
  "properties": {
    "iso:country":"US",
    "sg:address":"1638 Adams Rd",
    "sg:city":"Fennville",
    "sg:classifiers":[
        {
            "category":"Wholesale",
            "subcategory":"Machinery & Supplies",
            "type":"Manufacturing & Wholesale Goods"
        }
    ],
    "sg:phone":"+1 269 227 1222",
    "sg:postcode":"49408",
    "sg:province":"MI",
    "sg:tags":[
        "bookbinder",
        "equipment"
    ],
    "wof:name":"Stitch Rite Products",
    "wof:placetype":"venue"
},
  "geometry": {"coordinates":[-86.227801,42.530142],"type":"Point"}
}