{
  "type": "Feature",
  "properties": {
    "iso:country":"US",
    "sg:address":"4711 W Wackerly St",
    "sg:city":"Midland",
    "sg:classifiers":[
        {
            "category":"Building & Trades",
            "subcategory":"Electrical",
            "type":"Services"
        }
    ],
    "sg:phone":"+1 989 839 2123",
    "sg:postcode":"48640",
    "sg:province":"MI",
    "sg:tags":[
        "electric",
        "contractor"
    ],
    "wof:name":"Advance Electric",
    "wof:placetype":"venue"
},
  "geometry": {"coordinates":[-84.285928,43.654988],"type":"Point"}
}