{
  "type": "Feature",
  "properties": {
    "iso:country":"US",
    "sg:address":"675 Coleman St SE",
    "sg:city":"Grand Rapids",
    "sg:classifiers":[
        {
            "category":"Social Services",
            "subcategory":"Child Care",
            "type":"Services"
        }
    ],
    "sg:phone":"+1 616 554 9138",
    "sg:postcode":"49508",
    "sg:province":"MI",
    "sg:tags":[
        "day"
    ],
    "wof:name":"Cynthia Lynn Stolt",
    "wof:placetype":"venue"
},
  "geometry": {"coordinates":[-85.649373,42.830307],"type":"Point"}
}