{
  "type": "Feature",
  "properties": {
    "iso:country":"US",
    "sg:address":"8899 Peck Rd",
    "sg:city":"Greenville",
    "sg:classifiers":[
        {
            "category":"Building & Trades",
            "subcategory":"Construction",
            "type":"Services"
        }
    ],
    "sg:phone":"+1 616 225 0777",
    "sg:postcode":"48838",
    "sg:province":"MI",
    "sg:tags":[
        "concrete",
        "contractor"
    ],
    "wof:name":"Integrity Concrete Constr",
    "wof:placetype":"venue"
},
  "geometry": {"coordinates":[-85.24492600000001,43.213584],"type":"Point"}
}