{
  "type": "Feature",
  "properties": {
    "iso:country":"US",
    "sg:address":"47677 Galleon Dr",
    "sg:city":"Plymouth",
    "sg:classifiers":[
        {
            "category":"Manufacturing",
            "subcategory":"Tools & Machinery",
            "type":"Manufacturing & Wholesale Goods"
        },
        {
            "category":"Autos & Motor Vehicles",
            "subcategory":"Auto Supplies",
            "type":"Retail Goods"
        }
    ],
    "sg:phone":"+1 734 446 2200",
    "sg:postcode":"48170",
    "sg:province":"MI",
    "sg:tags":[
        "automobile",
        "machine",
        "parts",
        "accessories-wholesale",
        "part",
        "manufacturer"
    ],
    "wof:name":"American Furukawa Inc",
    "wof:placetype":"venue"
},
  "geometry": {"coordinates":[-83.513369,42.387432],"type":"Point"}
}