{
  "type": "Feature",
  "properties": {
    "iso:country":"US",
    "sg:address":"7841 Munsell Rd",
    "sg:city":"Howell",
    "sg:classifiers":[
        {
            "category":"Building & Trades",
            "subcategory":"Cleaning & Sanitation",
            "type":"Services"
        }
    ],
    "sg:phone":"+1 517 223 2421",
    "sg:postcode":"48843",
    "sg:province":"MI",
    "sg:tags":[
        "janitor"
    ],
    "wof:name":"Cardinal Clean Care",
    "wof:placetype":"venue"
},
  "geometry": {"coordinates":[-84.06227800000001,42.560825],"type":"Point"}
}