{
  "type": "Feature",
  "properties": {
    "iso:country":"US",
    "sg:address":"3940 Acorn Cir",
    "sg:city":"Holt",
    "sg:classifiers":[
        {
            "category":"Personal",
            "subcategory":"Beauty Salon",
            "type":"Services"
        },
        {
            "category":"Personal",
            "subcategory":"Barber",
            "type":"Services"
        },
        {
            "category":"Personal",
            "subcategory":"Day Spa",
            "type":"Services"
        }
    ],
    "sg:phone":"+1 517 694 8303",
    "sg:postcode":"48842",
    "sg:province":"MI",
    "sg:website":"http://www.aveda.com",
    "wof:name":"Joni's Hair Salon",
    "wof:placetype":"venue"
},
  "geometry": {"coordinates":[-84.49981200000001,42.649332],"type":"Point"}
}