{
  "type": "Feature",
  "properties": {
    "iso:country":"US",
    "sg:address":"202 E Lansing Rd",
    "sg:city":"East Lansing",
    "sg:classifiers":[
        {
            "category":"Communications",
            "subcategory":"Radio Station",
            "type":"Services"
        }
    ],
    "sg:phone":"+1 517 353 5925",
    "sg:postcode":"48857",
    "sg:province":"MI",
    "sg:tags":[
        "broadcast"
    ],
    "wof:name":"MSU Dept of Casid",
    "wof:placetype":"venue"
},
  "geometry": {"coordinates":[-84.159323,42.851031],"type":"Point"}
}