{
  "type": "Feature",
  "properties": {
    "iso:country":"US",
    "sg:address":"16606 Strathmoor St",
    "sg:city":"Detroit",
    "sg:classifiers":[
        {
            "category":"Social Services",
            "subcategory":"Child Care",
            "type":"Services"
        }
    ],
    "sg:phone":"+1 313 835 6397",
    "sg:postcode":"48235",
    "sg:province":"MI",
    "sg:tags":[
        "day"
    ],
    "wof:name":"Spraggins Funhouse",
    "wof:placetype":"venue"
},
  "geometry": {"coordinates":[-83.188216,42.413313],"type":"Point"}
}