{
  "type": "Feature",
  "properties": {
    "iso:country":"US",
    "sg:address":"411 N Griffin St",
    "sg:city":"Grand Haven",
    "sg:classifiers":[
        {
            "category":"Wholesale",
            "subcategory":"Scrap",
            "type":"Manufacturing & Wholesale Goods"
        }
    ],
    "sg:phone":"+1 231 798 8000",
    "sg:postcode":"49417",
    "sg:province":"MI",
    "sg:tags":[
        "cloth",
        "wiping"
    ],
    "wof:name":"ASAP Ind Supply",
    "wof:placetype":"venue"
},
  "geometry": {"coordinates":[-86.210926,43.066444],"type":"Point"}
}