{
  "type": "Feature",
  "properties": {
    "iso:country":"US",
    "sg:address":"26801 Groesbeck Hwy",
    "sg:city":"Warren",
    "sg:classifiers":[
        {
            "category":"Building & Trades",
            "subcategory":"Construction",
            "type":"Services"
        },
        {
            "category":"Wholesale",
            "subcategory":"Electrical",
            "type":"Manufacturing & Wholesale Goods"
        }
    ],
    "sg:phone":"+1 586 771 8080",
    "sg:postcode":"48089",
    "sg:province":"MI",
    "sg:tags":[
        "repair",
        "balancing",
        "electric",
        "motor"
    ],
    "sg:website":"www.spinaelectric.com",
    "wof:name":"Spina Electric Company",
    "wof:placetype":"venue"
},
  "geometry": {"coordinates":[-82.969832,42.493095],"type":"Point"}
}