{
  "type": "Feature",
  "properties": {
    "iso:country":"US",
    "sg:address":"2121 Ferguson Rd",
    "sg:city":"Jackson",
    "sg:classifiers":[
        {
            "category":"Government",
            "subcategory":"Office",
            "type":"Public Place"
        },
        {
            "category":"Government",
            "subcategory":"Fire Station",
            "type":"Public Place"
        }
    ],
    "sg:phone":"+1 517 788 4115",
    "sg:postcode":"49203",
    "sg:province":"MI",
    "sg:tags":[
        "department",
        "executive"
    ],
    "sg:website":"www.summittownship.com",
    "wof:name":"Summit Township Fire Dept",
    "wof:placetype":"venue"
},
  "geometry": {"coordinates":[-84.438045,42.19926],"type":"Point"}
}