{
  "type": "Feature",
  "properties": {
    "iso:country":"US",
    "sg:address":"4445 W Sanilac Rd",
    "sg:city":"Vassar",
    "sg:classifiers":[
        {
            "category":"Building & Trades",
            "subcategory":"Cleaning & Sanitation",
            "type":"Services"
        }
    ],
    "sg:phone":"+1 989 823 8848",
    "sg:postcode":"48768",
    "sg:province":"MI",
    "sg:tags":[
        "janitor"
    ],
    "wof:name":"Dust Till Dawn",
    "wof:placetype":"venue"
},
  "geometry": {"coordinates":[-83.517717,43.40851],"type":"Point"}
}