{
  "type": "Feature",
  "properties": {
    "iso:country":"US",
    "sg:address":"4620 US Hwy 31",
    "sg:city":"Traverse City",
    "sg:classifiers":[
        {
            "category":"Health Services",
            "subcategory":"Doctor",
            "type":"Services"
        }
    ],
    "sg:phone":"+1 231 938 2010",
    "sg:postcode":"49686",
    "sg:province":"MI",
    "sg:tags":[
        "physician",
        "surgeon"
    ],
    "wof:name":"Engel Mind-Body Psychiatry",
    "wof:placetype":"venue"
},
  "geometry": {"coordinates":[-85.51778299999999,44.757128],"type":"Point"}
}