{
  "type": "Feature",
  "properties": {
    "iso:country":"US",
    "sg:address":"888 Forest Hill Ave SE",
    "sg:city":"Grand Rapids",
    "sg:classifiers":[
        {
            "category":"Food & Beverages",
            "subcategory":"Groceries & Convenience Stores",
            "type":"Retail Goods"
        }
    ],
    "sg:phone":"+1 616 942 9310",
    "sg:postcode":"49546",
    "sg:province":"MI",
    "wof:name":"7-Eleven",
    "wof:placetype":"venue"
},
  "geometry": {"coordinates":[-85.55573699999999,42.948048],"type":"Point"}
}