{
  "type": "Feature",
  "properties": {
    "iso:country":"US",
    "sg:address":"44 E Sharlear Dr",
    "sg:city":"Essexville",
    "sg:classifiers":[
        {
            "category":"Social Services",
            "type":"Services"
        }
    ],
    "sg:phone":"+1 989 892 4997",
    "sg:postcode":"48732",
    "sg:province":"MI",
    "sg:tags":[
        "organization",
        "religious"
    ],
    "wof:name":"Nu Vey",
    "wof:placetype":"venue"
},
  "geometry": {"coordinates":[-83.848777,43.610883],"type":"Point"}
}