{
  "type": "Feature",
  "properties": {
    "iso:country":"US",
    "sg:address":"3963 17 Mile Road",
    "sg:city":"Sterling Heights",
    "sg:classifiers":[
        {
            "category":"Restaurant",
            "type":"Food & Drink"
        },
        {
            "category":"Food & Beverages",
            "subcategory":"Groceries & Convenience Stores",
            "type":"Retail Goods"
        }
    ],
    "sg:phone":"+1 586 838 4434",
    "sg:postcode":"48310",
    "sg:province":"MI",
    "sg:tags":[
        "middle",
        "halal",
        "eastern"
    ],
    "wof:name":"La Rosa Meats",
    "wof:placetype":"venue"
},
  "geometry": {"coordinates":[-83.068755,42.579257],"type":"Point"}
}