{
  "type": "Feature",
  "properties": {
    "iso:country":"US",
    "sg:address":"37611 W 12 Mile Rd",
    "sg:city":"Farmington Hills",
    "sg:classifiers":[
        {
            "category":"Bakery",
            "type":"Food & Drink"
        }
    ],
    "sg:menulink":"http://www.allmenus.com/mi/farmington-hills/103121-panera-bread/menu/",
    "sg:phone":"+1 248 324 4402",
    "sg:postcode":"48331",
    "sg:province":"MI",
    "sg:tags":[
        "american",
        "sandwich",
        "pastry"
    ],
    "wof:name":"Panera Bread",
    "wof:placetype":"venue"
},
  "geometry": {"coordinates":[-83.418493,42.497417],"type":"Point"}
}