{
  "type": "Feature",
  "properties": {
    "iso:country":"US",
    "sg:address":"19730 Harper Ave",
    "sg:city":"Harper Woods",
    "sg:classifiers":[
        {
            "category":"Retail",
            "subcategory":"Event Space",
            "type":"Services"
        }
    ],
    "sg:phone":"+1 313 885 9659",
    "sg:postcode":"48225",
    "sg:province":"MI",
    "sg:tags":[
        "venue"
    ],
    "wof:name":"Amvets Richard S Hayes-Post 57",
    "wof:placetype":"venue"
},
  "geometry": {"coordinates":[-82.92179899999999,42.433601],"type":"Point"}
}