{
  "type": "Feature",
  "properties": {
    "iso:country":"US",
    "sg:address":"39011 Harper Ave",
    "sg:city":"Clinton Twp",
    "sg:classifiers":[
        {
            "category":"Shopping",
            "subcategory":"Pharmacy",
            "type":"Retail Goods"
        }
    ],
    "sg:phone":"+1 586 468 1207",
    "sg:postcode":"48036",
    "sg:province":"MI",
    "wof:name":"Frank's Pharmacy & Medical",
    "wof:placetype":"venue"
},
  "geometry": {"coordinates":[-82.86703300000001,42.585347],"type":"Point"}
}