{
  "type": "Feature",
  "properties": {
    "iso:country":"US",
    "sg:address":"13455 Jack St",
    "sg:city":"Holland",
    "sg:classifiers":[
        {
            "category":"Shopping",
            "type":"Retail Goods"
        }
    ],
    "sg:phone":"+1 616 994 9704",
    "sg:postcode":"49424",
    "sg:province":"MI",
    "sg:tags":[
        "pet",
        "shop"
    ],
    "wof:name":"Paradise Birds & Saltwater Fsh",
    "wof:placetype":"venue"
},
  "geometry": {"coordinates":[-86.114351,42.837022],"type":"Point"}
}