{
  "type": "Feature",
  "properties": {
    "iso:country":"US",
    "sg:address":"900 Carpenter Ave",
    "sg:city":"Iron Mountain",
    "sg:classifiers":[
        {
            "category":"Professional",
            "subcategory":"Lawyer & Legal Services",
            "type":"Services"
        }
    ],
    "sg:phone":"+1 906 779 1280",
    "sg:postcode":"49801",
    "sg:province":"MI",
    "sg:tags":[
        "attorney"
    ],
    "wof:name":"Wisti & Wisti",
    "wof:placetype":"venue"
},
  "geometry": {"coordinates":[-88.068462,45.814668],"type":"Point"}
}