{
  "type": "Feature",
  "properties": {
    "iso:country":"US",
    "sg:address":"11755 E Michigan Ave",
    "sg:city":"Grass Lake",
    "sg:classifiers":[
        {
            "category":"Health Services",
            "subcategory":"Doctor",
            "type":"Services"
        }
    ],
    "sg:phone":"+1 517 522 6100",
    "sg:postcode":"49240",
    "sg:province":"MI",
    "sg:tags":[
        "physician",
        "surgeon"
    ],
    "wof:name":"Sacred Heart Pediatrics",
    "wof:placetype":"venue"
},
  "geometry": {"coordinates":[-84.196138,42.253474],"type":"Point"}
}