{
  "type": "Feature",
  "properties": {
    "iso:country":"US",
    "sg:address":"3864 Island Park Dr",
    "sg:city":"Waterford",
    "sg:classifiers":[
        {
            "category":"Manufacturing",
            "subcategory":"Tools & Machinery",
            "type":"Manufacturing & Wholesale Goods"
        }
    ],
    "sg:phone":"+1 248 705 9835",
    "sg:postcode":"48329",
    "sg:province":"MI",
    "sg:tags":[
        "prosthetics"
    ],
    "wof:name":"Bacon Robert CP",
    "wof:placetype":"venue"
},
  "geometry": {"coordinates":[-83.366135,42.700549],"type":"Point"}
}