{
  "type": "Feature",
  "properties": {
    "iso:country":"US",
    "sg:address":"9810 Lee St",
    "sg:city":"Algonac",
    "sg:classifiers":[
        {
            "category":"Arts & Performance",
            "subcategory":"Theater",
            "type":"Entertainment"
        }
    ],
    "sg:phone":"+1 810 794 9717",
    "sg:postcode":"48001",
    "sg:province":"MI",
    "sg:tags":[
        "group"
    ],
    "wof:name":"Great Lkes Alnce Lving Hstrans",
    "wof:placetype":"venue"
},
  "geometry": {"coordinates":[-82.532357,42.632836],"type":"Point"}
}