{
  "type": "Feature",
  "properties": {
    "iso:country":"US",
    "sg:address":"30061 Schoenherr Rd",
    "sg:city":"Warren",
    "sg:classifiers":[
        {
            "category":"Social Services",
            "subcategory":"Job Training",
            "type":"Services"
        }
    ],
    "sg:phone":"+1 586 573 0200",
    "sg:postcode":"48088",
    "sg:province":"MI",
    "sg:tags":[
        "placement",
        "rehabilitation"
    ],
    "wof:name":"Jewish Vctonal Svc Cmnty Wkshp",
    "wof:placetype":"venue"
},
  "geometry": {"coordinates":[-82.988107,42.515297],"type":"Point"}
}