{
  "type": "Feature",
  "properties": {
    "iso:country":"US",
    "sg:address":"7594 W Hazel Rd",
    "sg:city":"Mears",
    "sg:classifiers":[
        {
            "category":"Travel",
            "subcategory":"Campground",
            "type":"Entertainment"
        }
    ],
    "sg:phone":"+1 231 873 3976",
    "sg:postcode":"49436",
    "sg:province":"MI",
    "sg:tags":[
        "trailer"
    ],
    "wof:name":"Silver Hills Camp Resort",
    "wof:placetype":"venue"
},
  "geometry": {"coordinates":[-86.47206799999999,43.667788],"type":"Point"}
}