{
  "type": "Feature",
  "properties": {
    "iso:country":"US",
    "sg:address":"3558 Washington St",
    "sg:city":"Snover",
    "sg:classifiers":[
        {
            "category":"Retail",
            "subcategory":"Auto Repair",
            "type":"Services"
        }
    ],
    "sg:phone":"+1 810 672 9404",
    "sg:postcode":"48472",
    "sg:province":"MI",
    "sg:tags":[
        "body",
        "automobile",
        "painting"
    ],
    "wof:name":"Snover Auto Body",
    "wof:placetype":"venue"
},
  "geometry": {"coordinates":[-82.97262499999999,43.461186],"type":"Point"}
}