{
  "type": "Feature",
  "properties": {
    "iso:country":"US",
    "sg:address":"8976 US Hwy 31",
    "sg:city":"Berrien Springs",
    "sg:classifiers":[
        {
            "category":"Professional",
            "subcategory":"Lawyer & Legal Services",
            "type":"Services"
        }
    ],
    "sg:phone":"+1 269 471 2848",
    "sg:postcode":"49103",
    "sg:province":"MI",
    "sg:tags":[
        "attorney"
    ],
    "wof:name":"Norm R Perry",
    "wof:placetype":"venue"
},
  "geometry": {"coordinates":[-86.364807,41.959029],"type":"Point"}
}