{
  "type": "Feature",
  "properties": {
    "iso:country":"US",
    "sg:address":"7743 Sashabaw Rd",
    "sg:city":"Clarkston",
    "sg:classifiers":[
        {
            "category":"Restaurant",
            "type":"Food & Drink"
        }
    ],
    "sg:menulink":"http://www.allmenus.com/mi/independence/142387-subway/menu/",
    "sg:phone":"+1 248 625 5739",
    "sg:postcode":"48348",
    "sg:province":"MI",
    "sg:tags":[
        "american",
        "sandwich"
    ],
    "wof:name":"Subway",
    "wof:placetype":"venue"
},
  "geometry": {"coordinates":[-83.38027599999999,42.751042],"type":"Point"}
}