{
  "type": "Feature",
  "properties": {
    "iso:country":"US",
    "sg:address":"3794 Tressla Rd",
    "sg:city":"Vassar",
    "sg:classifiers":[
        {
            "category":"Real Estate",
            "subcategory":"Real Estate Operator",
            "type":"Services"
        }
    ],
    "sg:phone":"+1 989 823 3369",
    "sg:postcode":"48768",
    "sg:province":"MI",
    "sg:tags":[
        "property",
        "lessor"
    ],
    "wof:name":"Gordon Bierlein",
    "wof:placetype":"venue"
},
  "geometry": {"coordinates":[-83.66963800000001,43.398754],"type":"Point"}
}