{
  "type": "Feature",
  "properties": {
    "iso:country":"US",
    "sg:address":"50 Monroe Ave NW",
    "sg:city":"Grand Rapids",
    "sg:classifiers":[
        {
            "category":"Professional",
            "subcategory":"Management & Consulting",
            "type":"Services"
        }
    ],
    "sg:phone":"+1 616 454 6670",
    "sg:postcode":"49503",
    "sg:province":"MI",
    "sg:tags":[
        "consultant",
        "business"
    ],
    "wof:name":"Anderson Keegin & Assoc Inc",
    "wof:placetype":"venue"
},
  "geometry": {"coordinates":[-85.673439,42.963249],"type":"Point"}
}