{
  "type": "Feature",
  "properties": {
    "iso:country":"US",
    "sg:address":"1526 Osborn St",
    "sg:city":"Saginaw",
    "sg:classifiers":[
        {
            "category":"Retail",
            "subcategory":"Auto Repair",
            "type":"Services"
        }
    ],
    "sg:phone":"+1 989 797 2279",
    "sg:postcode":"48602",
    "sg:province":"MI",
    "wof:name":"Monkey Wrench",
    "wof:placetype":"venue"
},
  "geometry": {"coordinates":[-83.984438,43.419543],"type":"Point"}
}