{
  "type": "Feature",
  "properties": {
    "iso:country":"US",
    "sg:address":"5763 Eastman Blvd",
    "sg:city":"West Bloomfield",
    "sg:classifiers":[
        {
            "category":"Professional",
            "subcategory":"Management & Consulting",
            "type":"Services"
        }
    ],
    "sg:phone":"+1 248 626 5286",
    "sg:postcode":"48323",
    "sg:province":"MI",
    "sg:tags":[
        "consultant",
        "business"
    ],
    "wof:name":"Egan Enterprises Inc",
    "wof:placetype":"venue"
},
  "geometry": {"coordinates":[-83.32374,42.554054],"type":"Point"}
}