{
  "type": "Feature",
  "properties": {
    "iso:country":"US",
    "sg:address":"206 S 5th Ave",
    "sg:city":"Ann Arbor",
    "sg:classifiers":[
        {
            "category":"Education",
            "subcategory":"Vocational School",
            "type":"Public Place"
        }
    ],
    "sg:phone":"+1 734 761 4689",
    "sg:postcode":"48104",
    "sg:province":"MI",
    "sg:tags":[
        "development",
        "consulting",
        "integration",
        "source",
        "open",
        "software"
    ],
    "wof:name":"Linux Box Corporation",
    "wof:placetype":"venue"
},
  "geometry": {"coordinates":[-83.746172,42.27957],"type":"Point"}
}