{
  "type": "Feature",
  "properties": {
    "iso:country":"US",
    "sg:address":"2119 8th St",
    "sg:city":"Port Huron",
    "sg:classifiers":[
        {
            "category":"Social Services",
            "subcategory":"Child Care",
            "type":"Services"
        }
    ],
    "sg:phone":"+1 810 985 6984",
    "sg:postcode":"48060",
    "sg:province":"MI",
    "sg:tags":[
        "day"
    ],
    "wof:name":"Lindas Daycare",
    "wof:placetype":"venue"
},
  "geometry": {"coordinates":[-82.428837,42.962202],"type":"Point"}
}