{
  "type": "Feature",
  "properties": {
    "iso:country":"US",
    "sg:address":"3908 Hall Rd",
    "sg:city":"Muskegon",
    "sg:classifiers":[
        {
            "category":"Social Services",
            "subcategory":"Child Care",
            "type":"Services"
        }
    ],
    "sg:phone":"+1 231 773 0897",
    "sg:postcode":"49442",
    "sg:province":"MI",
    "sg:tags":[
        "day",
        "provider"
    ],
    "wof:name":"Aunt Wandas Daycare",
    "wof:placetype":"venue"
},
  "geometry": {"coordinates":[-86.147507,43.248918],"type":"Point"}
}