{
  "type": "Feature",
  "properties": {
    "iso:country":"US",
    "sg:address":"1787 Wagner St",
    "sg:city":"Muskegon",
    "sg:classifiers":[
        {
            "category":"Health Services",
            "subcategory":"Doctor",
            "type":"Services"
        }
    ],
    "sg:phone":"+1 231 767 1775",
    "sg:postcode":"49442",
    "sg:province":"MI",
    "sg:tags":[
        "obstetrician",
        "gynecologist"
    ],
    "wof:name":"West Shore Obgyn PC",
    "wof:placetype":"venue"
},
  "geometry": {"coordinates":[-86.20796799999999,43.286224],"type":"Point"}
}