{
  "type": "Feature",
  "properties": {
    "iso:country":"US",
    "sg:address":"7419 Noffke Dr",
    "sg:city":"Caledonia",
    "sg:classifiers":[
        {
            "category":"Building & Trades",
            "subcategory":"Landscaping Services",
            "type":"Services"
        }
    ],
    "sg:phone":"+1 616 891 5930",
    "sg:postcode":"49316",
    "sg:province":"MI",
    "wof:name":"Greenscape Lawn Care Inc",
    "wof:placetype":"venue"
},
  "geometry": {"coordinates":[-85.523111,42.767729],"type":"Point"}
}