{
  "type": "Feature",
  "properties": {
    "iso:country":"US",
    "sg:address":"1010 Robinson St",
    "sg:city":"Manistee",
    "sg:classifiers":[
        {
            "category":"Organizations",
            "subcategory":"Community Association",
            "type":"Services"
        }
    ],
    "sg:phone":"+1 231 723 2432",
    "sg:postcode":"49660",
    "sg:province":"MI",
    "sg:tags":[
        "fraternal"
    ],
    "wof:name":"Loyal Order Of Moose",
    "wof:placetype":"venue"
},
  "geometry": {"coordinates":[-86.32686200000001,44.236822],"type":"Point"}
}