{
  "type": "Feature",
  "properties": {
    "iso:country":"US",
    "sg:address":"422 Oliver Dr",
    "sg:city":"Troy",
    "sg:classifiers":[
        {
            "category":"Professional",
            "subcategory":"Advertising",
            "type":"Services"
        }
    ],
    "sg:phone":"+1 248 362 2750",
    "sg:postcode":"48084",
    "sg:province":"MI",
    "sg:tags":[
        "counselor",
        "agency"
    ],
    "wof:name":"G & D Communications Corp",
    "wof:placetype":"venue"
},
  "geometry": {"coordinates":[-83.153445,42.554126],"type":"Point"}
}