{
  "type": "Feature",
  "properties": {
    "iso:country":"US",
    "sg:address":"2000 Winner St",
    "sg:city":"Commerce Twp",
    "sg:classifiers":[
        {
            "category":"Manufacturing",
            "subcategory":"Furniture",
            "type":"Manufacturing & Wholesale Goods"
        }
    ],
    "sg:phone":"+1 248 669 0000",
    "sg:postcode":"48390",
    "sg:province":"MI",
    "sg:tags":[
        "household"
    ],
    "wof:name":"Options Furniture",
    "wof:placetype":"venue"
},
  "geometry": {"coordinates":[-83.45974699999999,42.544816],"type":"Point"}
}