{
  "type": "Feature",
  "properties": {
    "iso:country":"US",
    "sg:address":"885 Hagadorn Rd",
    "sg:city":"Mason",
    "sg:classifiers":[
        {
            "category":"Real Estate",
            "subcategory":"Real Estate Agent",
            "type":"Services"
        }
    ],
    "sg:phone":"+1 517 676 7000",
    "sg:postcode":"48854",
    "sg:province":"MI",
    "wof:name":"Realty 44 Mattox Real Estate",
    "wof:placetype":"venue"
},
  "geometry": {"coordinates":[-84.457143,42.611108],"type":"Point"}
}