{
  "type": "Feature",
  "properties": {
    "iso:country":"US",
    "sg:address":"4390 King Rd",
    "sg:city":"China",
    "sg:classifiers":[
        {
            "category":"Building & Trades",
            "subcategory":"Construction",
            "type":"Services"
        }
    ],
    "sg:phone":"+1 810 326 0339",
    "sg:postcode":"48054",
    "sg:province":"MI",
    "sg:tags":[
        "dry wall",
        "contractor"
    ],
    "wof:name":"Independent Interiors Drywall",
    "wof:placetype":"venue"
},
  "geometry": {"coordinates":[-82.512547,42.775956],"type":"Point"}
}