{
  "type": "Feature",
  "properties": {
    "iso:country":"US",
    "sg:address":"6003 Fulton St",
    "sg:city":"Mayville",
    "sg:classifiers":[
        {
            "category":"Organizations",
            "subcategory":"Community Association",
            "type":"Services"
        }
    ],
    "sg:phone":"+1 989 843 6937",
    "sg:postcode":"48744",
    "sg:province":"MI",
    "sg:tags":[
        "military"
    ],
    "wof:name":"Veterans Of Foreign Wars",
    "wof:placetype":"venue"
},
  "geometry": {"coordinates":[-83.352478,43.33676],"type":"Point"}
}