{
  "type": "Feature",
  "properties": {
    "iso:country":"US",
    "sg:address":"8313 Indian Trl",
    "sg:city":"Watervliet",
    "sg:classifiers":[
        {
            "category":"Manufacturing",
            "subcategory":"Printing",
            "type":"Manufacturing & Wholesale Goods"
        }
    ],
    "sg:phone":"+1 269 463 8545",
    "sg:postcode":"49098",
    "sg:province":"MI",
    "sg:tags":[
        "commercial"
    ],
    "wof:name":"Lighthouse Media",
    "wof:placetype":"venue"
},
  "geometry": {"coordinates":[-86.257527,42.202223],"type":"Point"}
}