{
  "type": "Feature",
  "properties": {
    "iso:country":"US",
    "sg:address":"7492 Majestic Wood Dr",
    "sg:city":"Linden",
    "sg:classifiers":[
        {
            "category":"Building & Trades",
            "subcategory":"Construction",
            "type":"Services"
        }
    ],
    "sg:phone":"+1 810 735 2997",
    "sg:postcode":"48451",
    "sg:province":"MI",
    "sg:tags":[
        "house"
    ],
    "wof:name":"C&J Custom Homes",
    "wof:placetype":"venue"
},
  "geometry": {"coordinates":[-83.826672,42.790569],"type":"Point"}
}