{
  "type": "Feature",
  "properties": {
    "iso:country":"US",
    "sg:address":"6805 Bluegrass Dr",
    "sg:city":"Clarkston",
    "sg:classifiers":[
        {
            "category":"Social Services",
            "type":"Services"
        }
    ],
    "sg:phone":"+1 248 922 3004",
    "sg:postcode":"48346",
    "sg:province":"MI",
    "sg:tags":[
        "youth",
        "organization",
        "center"
    ],
    "wof:name":"Clarkston Coalition For Youth",
    "wof:placetype":"venue"
},
  "geometry": {"coordinates":[-83.419427,42.743299],"type":"Point"}
}