{
  "type": "Feature",
  "properties": {
    "iso:country":"US",
    "sg:address":"1160 Penniman Ave",
    "sg:city":"Plymouth",
    "sg:classifiers":[
        {
            "category":"Professional",
            "subcategory":"Lawyer & Legal Services",
            "type":"Services"
        }
    ],
    "sg:phone":"+1 734 453 0326",
    "sg:postcode":"48170",
    "sg:province":"MI",
    "wof:name":"Our Lady of Good Counsel",
    "wof:placetype":"venue"
},
  "geometry": {"coordinates":[-83.47368299999999,42.373666],"type":"Point"}
}