{
  "type": "Feature",
  "properties": {
    "iso:country":"US",
    "sg:address":"2277 S Grove St",
    "sg:city":"Ypsilanti",
    "sg:classifiers":[
        {
            "category":"Real Estate",
            "subcategory":"Real Estate Operator",
            "type":"Services"
        }
    ],
    "sg:phone":"+1 734 483 2332",
    "sg:postcode":"48198",
    "sg:province":"MI",
    "sg:tags":[
        "building",
        "apartment"
    ],
    "wof:name":"Bryn Mawr Apartments",
    "wof:placetype":"venue"
},
  "geometry": {"coordinates":[-83.562612,42.214867],"type":"Point"}
}