{
  "type": "Feature",
  "properties": {
    "iso:country":"US",
    "sg:address":"507 W Michigan Ave",
    "sg:city":"Jackson",
    "sg:classifiers":[
        {
            "category":"Insurance",
            "subcategory":"Hazard Insurance",
            "type":"Services"
        }
    ],
    "sg:phone":"+1 517 787 1054",
    "sg:postcode":"49201",
    "sg:province":"MI",
    "sg:tags":[
        "profit",
        "sharing",
        "pension",
        "plan"
    ],
    "wof:name":"Massachusetts Mutual Life Ins",
    "wof:placetype":"venue"
},
  "geometry": {"coordinates":[-84.417115,42.247423],"type":"Point"}
}