{
  "type": "Feature",
  "properties": {
    "iso:country":"US",
    "sg:address":"15464 Dixie",
    "sg:city":"Redford",
    "sg:classifiers":[
        {
            "category":"Professional",
            "subcategory":"Business Services",
            "type":"Services"
        }
    ],
    "sg:phone":"+1 313 387 9019",
    "sg:postcode":"48239",
    "sg:province":"MI",
    "wof:name":"Pearl Enterprises",
    "wof:placetype":"venue"
},
  "geometry": {"coordinates":[-83.28420199999999,42.403377],"type":"Point"}
}