{
  "type": "Feature",
  "properties": {
    "iso:country":"US",
    "sg:address":"850 N Center Ave",
    "sg:city":"Gaylord",
    "sg:classifiers":[
        {
            "category":"Health Services",
            "subcategory":"Clinic",
            "type":"Services"
        }
    ],
    "sg:phone":"+1 989 705 8844",
    "sg:postcode":"49735",
    "sg:province":"MI",
    "sg:tags":[
        "home",
        "care"
    ],
    "wof:name":"Compassonate Care HM Hlth Svcs",
    "wof:placetype":"venue"
},
  "geometry": {"coordinates":[-84.673817,45.034181],"type":"Point"}
}