{
  "type": "Feature",
  "properties": {
    "iso:country":"US",
    "sg:address":"32680 Van Dyke Ave",
    "sg:city":"Warren",
    "sg:classifiers":[
        {
            "category":"Shopping",
            "subcategory":"Mobile Phones",
            "type":"Retail Goods"
        }
    ],
    "sg:phone":"+1 586 268 5708",
    "sg:postcode":"48093",
    "sg:province":"MI",
    "wof:name":"My Mobile Store",
    "wof:placetype":"venue"
},
  "geometry": {"coordinates":[-83.029084,42.534333],"type":"Point"}
}