{
  "type": "Feature",
  "properties": {
    "iso:country":"US",
    "sg:address":"309 Kayser Ave",
    "sg:city":"Royal Oak",
    "sg:classifiers":[
        {
            "category":"Wholesale",
            "subcategory":"Medical Equipment & Supplies",
            "type":"Manufacturing & Wholesale Goods"
        }
    ],
    "sg:phone":"+1 248 582 8610",
    "sg:postcode":"48067",
    "sg:province":"MI",
    "sg:tags":[
        "physician",
        "surgeon"
    ],
    "wof:name":"Murphy Orthopedic",
    "wof:placetype":"venue"
},
  "geometry": {"coordinates":[-83.13694,42.487575],"type":"Point"}
}