{
  "type": "Feature",
  "properties": {
    "iso:country":"US",
    "sg:address":"46462 Dequindre Rd",
    "sg:city":"Utica",
    "sg:classifiers":[
        {
            "category":"Retail",
            "subcategory":"Car Wash",
            "type":"Services"
        }
    ],
    "sg:phone":"+1 586 731 0880",
    "sg:postcode":"48317",
    "sg:province":"MI",
    "sg:tags":[
        "carwash"
    ],
    "wof:name":"A & G Detailing",
    "wof:placetype":"venue"
},
  "geometry": {"coordinates":[-83.09174400000001,42.631729],"type":"Point"}
}