{
  "type": "Feature",
  "properties": {
    "iso:country":"US",
    "sg:address":"417 S Haven St",
    "sg:city":"South Haven",
    "sg:classifiers":[
        {
            "category":"Real Estate",
            "subcategory":"Real Estate Agent",
            "type":"Services"
        }
    ],
    "sg:phone":"+1 269 639 1683",
    "sg:postcode":"49090",
    "sg:province":"MI",
    "sg:tags":[
        "authorities",
        "housing"
    ],
    "wof:name":"Housing Development Corp",
    "wof:placetype":"venue"
},
  "geometry": {"coordinates":[-86.275558,42.396521],"type":"Point"}
}