{
  "type": "Feature",
  "properties": {
    "iso:country":"US",
    "sg:address":"10329 S Verona",
    "sg:city":"Ramsay",
    "sg:classifiers":[
        {
            "category":"Social Services",
            "subcategory":"Child Care",
            "type":"Services"
        }
    ],
    "sg:phone":"+1 906 667 0121",
    "sg:postcode":"49959",
    "sg:province":"MI",
    "wof:name":"Kids Connection Licensed Day",
    "wof:placetype":"venue"
},
  "geometry": {"coordinates":[-89.997517,46.471675],"type":"Point"}
}