{
  "type": "Feature",
  "properties": {
    "iso:country":"US",
    "sg:address":"700 S Main St",
    "sg:city":"Lapeer",
    "sg:classifiers":[
        {
            "category":"Social Services",
            "type":"Services"
        }
    ],
    "sg:phone":"+1 810 664 4363",
    "sg:postcode":"48446",
    "sg:province":"MI",
    "sg:tags":[
        "counselor",
        "marriage",
        "family"
    ],
    "wof:name":"Lapeer Counseling Ctr",
    "wof:placetype":"venue"
},
  "geometry": {"coordinates":[-83.32077200000001,43.041232],"type":"Point"}
}