{
  "type": "Feature",
  "properties": {
    "iso:country":"US",
    "sg:address":"8505 Quincy St",
    "sg:city":"Detroit",
    "sg:classifiers":[
        {
            "category":"Autos & Motor Vehicles",
            "subcategory":"Auto Supplies",
            "type":"Retail Goods"
        }
    ],
    "sg:phone":"+1 313 898 3750",
    "sg:postcode":"48204",
    "sg:province":"MI",
    "sg:tags":[
        "tire"
    ],
    "wof:name":"Lee's Tire Repair",
    "wof:placetype":"venue"
},
  "geometry": {"coordinates":[-83.121201,42.362],"type":"Point"}
}