{
  "type": "Feature",
  "properties": {
    "iso:country":"US",
    "sg:address":"1830 Pipestone Rd",
    "sg:city":"Benton Harbor",
    "sg:classifiers":[
        {
            "category":"Restaurant",
            "type":"Food & Drink"
        }
    ],
    "sg:phone":"+1 269 934 7445",
    "sg:postcode":"49022",
    "sg:province":"MI",
    "wof:name":"Texas Corral Restaurant",
    "wof:placetype":"venue"
},
  "geometry": {"coordinates":[-86.42008800000001,42.086976],"type":"Point"}
}