{
  "type": "Feature",
  "properties": {
    "iso:country":"US",
    "sg:address":"15886 Briar Ln",
    "sg:city":"Presque Isle",
    "sg:classifiers":[
        {
            "category":"Building & Trades",
            "subcategory":"Construction",
            "type":"Services"
        }
    ],
    "sg:phone":"+1 989 595 2846",
    "sg:postcode":"49777",
    "sg:province":"MI",
    "sg:tags":[
        "contractor"
    ],
    "wof:name":"Frank M Herman",
    "wof:placetype":"venue"
},
  "geometry": {"coordinates":[-83.522583,45.346655],"type":"Point"}
}