{
  "type": "Feature",
  "properties": {
    "iso:country":"US",
    "sg:address":"34346 Michigan Ave",
    "sg:city":"Wayne",
    "sg:classifiers":[
        {
            "category":"Restaurant",
            "type":"Food & Drink"
        }
    ],
    "sg:menulink":"http://www.allmenus.com/mi/wayne/40604-papa-romanos/menu/",
    "sg:phone":"+1 734 721 7272",
    "sg:postcode":"48184",
    "sg:province":"MI",
    "sg:tags":[
        "wrap",
        "american",
        "sandwich",
        "pizza"
    ],
    "wof:name":"Papa Romano's",
    "wof:placetype":"venue"
},
  "geometry": {"coordinates":[-83.376766,42.281488],"type":"Point"}
}