{
  "type": "Feature",
  "properties": {
    "iso:country":"US",
    "sg:address":"5651 Hasco Rd",
    "sg:city":"Millington",
    "sg:classifiers":[
        {
            "category":"Real Estate",
            "subcategory":"Real Estate Operator",
            "type":"Services"
        }
    ],
    "sg:phone":"+1 989 823 8753",
    "sg:postcode":"48746",
    "sg:province":"MI",
    "sg:tags":[
        "mobile",
        "home",
        "community"
    ],
    "wof:name":"Woodvalley Mobile Home Park",
    "wof:placetype":"venue"
},
  "geometry": {"coordinates":[-83.563221,43.329452],"type":"Point"}
}