{
  "type": "Feature",
  "properties": {
    "iso:country":"US",
    "sg:address":"9930 Burlingame Ave SW",
    "sg:city":"Byron Center",
    "sg:classifiers":[
        {
            "category":"Education",
            "subcategory":"School",
            "type":"Public Place"
        }
    ],
    "sg:phone":"+1 616 878 4852",
    "sg:postcode":"49315",
    "sg:province":"MI",
    "sg:website":"www.tlcacademy.org",
    "wof:name":"Learning Ctr Academy",
    "wof:placetype":"venue"
},
  "geometry": {"coordinates":[-85.702821,42.787781],"type":"Point"}
}