{
  "type": "Feature",
  "properties": {
    "iso:country":"US",
    "sg:address":"4250 Spartan Industrial Dr SW",
    "sg:city":"Grandville",
    "sg:classifiers":[
        {
            "category":"Sports & Exercise",
            "subcategory":"Gym",
            "type":"Entertainment"
        }
    ],
    "sg:phone":"+1 616 538 4600",
    "sg:postcode":"49418",
    "sg:province":"MI",
    "sg:tags":[
        "club",
        "health"
    ],
    "wof:name":"Ramblewood Tennis and Hlth CLB",
    "wof:placetype":"venue"
},
  "geometry": {"coordinates":[-85.73592600000001,42.887682],"type":"Point"}
}