{
  "type": "Feature",
  "properties": {
    "iso:country":"US",
    "sg:address":"6926 Lehring Rd",
    "sg:city":"Bancroft",
    "sg:classifiers":[
        {
            "category":"Communications",
            "subcategory":"Film & Video Production",
            "type":"Services"
        }
    ],
    "sg:phone":"+1 989 634 9179",
    "sg:postcode":"48414",
    "sg:province":"MI",
    "sg:tags":[
        "taping"
    ],
    "wof:name":"Take One Television Production",
    "wof:placetype":"venue"
},
  "geometry": {"coordinates":[-84.03380900000001,42.843582],"type":"Point"}
}