{
  "type": "Feature",
  "properties": {
    "iso:country":"US",
    "sg:address":"5989 Tahoe Dr SE",
    "sg:city":"Grand Rapids",
    "sg:classifiers":[
        {
            "category":"Professional",
            "subcategory":"Computer Services",
            "type":"Services"
        }
    ],
    "sg:phone":"+1 616 949 9128",
    "sg:postcode":"49546",
    "sg:province":"MI",
    "sg:tags":[
        "consultant",
        "designer",
        "design",
        "system",
        "integrated"
    ],
    "wof:name":"Keane Inc",
    "wof:placetype":"venue"
},
  "geometry": {"coordinates":[-85.52002400000001,42.910302],"type":"Point"}
}