{
  "type": "Feature",
  "properties": {
    "iso:country":"US",
    "sg:address":"369 Walper Ave",
    "sg:city":"Clawson",
    "sg:classifiers":[
        {
            "category":"Building & Trades",
            "subcategory":"Construction",
            "type":"Services"
        }
    ],
    "sg:phone":"+1 248 588 7934",
    "sg:postcode":"48017",
    "sg:province":"MI",
    "sg:tags":[
        "contractor",
        "mason"
    ],
    "wof:name":"Duff Restoration",
    "wof:placetype":"venue"
},
  "geometry": {"coordinates":[-83.141361,42.530279],"type":"Point"}
}