{
  "type": "Feature",
  "properties": {
    "iso:country":"US",
    "sg:address":"6575 Belding Rd NE",
    "sg:city":"Rockford",
    "sg:classifiers":[
        {
            "category":"Personal",
            "subcategory":"Beauty Salon",
            "type":"Services"
        }
    ],
    "sg:phone":"+1 616 874 9215",
    "sg:postcode":"49341",
    "sg:province":"MI",
    "sg:tags":[
        "shop"
    ],
    "wof:name":"Accents Hair Design Studio",
    "wof:placetype":"venue"
},
  "geometry": {"coordinates":[-85.502759,43.086327],"type":"Point"}
}