{
  "type": "Feature",
  "properties": {
    "iso:country":"US",
    "sg:address":"2449 US Hwy 23 N",
    "sg:city":"Alpena",
    "sg:classifiers":[
        {
            "category":"Retail",
            "subcategory":"Auto Repair",
            "type":"Services"
        }
    ],
    "sg:phone":"+1 989 356 0006",
    "sg:postcode":"49707",
    "sg:province":"MI",
    "sg:tags":[
        "repairing",
        "automobile"
    ],
    "wof:name":"Beaver Automotive",
    "wof:placetype":"venue"
},
  "geometry": {"coordinates":[-83.45649299999999,45.094937],"type":"Point"}
}