{
  "type": "Feature",
  "properties": {
    "iso:country":"US",
    "sg:address":"4726 Wheeler Rd",
    "sg:city":"Standish",
    "sg:classifiers":[
        {
            "category":"Retail",
            "subcategory":"Animal Services",
            "type":"Services"
        }
    ],
    "sg:phone":"+1 989 846 8331",
    "sg:postcode":"48658",
    "sg:province":"MI",
    "sg:tags":[
        "pet",
        "boarding",
        "sitting"
    ],
    "wof:name":"Autumn Kennels",
    "wof:placetype":"venue"
},
  "geometry": {"coordinates":[-83.987403,43.990177],"type":"Point"}
}