{
  "type": "Feature",
  "properties": {
    "iso:country":"US",
    "sg:address":"2550 S Telegraph Rd",
    "sg:city":"Bloomfield Hills",
    "sg:classifiers":[
        {
            "category":"Banks & Credit Unions",
            "subcategory":"Investment Brokerage",
            "type":"Services"
        }
    ],
    "sg:phone":"+1 248 338 7800",
    "sg:postcode":"48302",
    "sg:province":"MI",
    "sg:tags":[
        "advisory",
        "financial"
    ],
    "wof:name":"H & R Block",
    "wof:placetype":"venue"
},
  "geometry": {"coordinates":[-83.288978,42.602425],"type":"Point"}
}