{
  "type": "Feature",
  "properties": {
    "iso:country":"US",
    "sg:address":"12065 Grass Rd",
    "sg:city":"Sebewaing",
    "sg:classifiers":[
        {
            "category":"Retail",
            "subcategory":"Laundry & Dry Cleaning",
            "type":"Services"
        }
    ],
    "sg:phone":"+1 989 674 2961",
    "sg:postcode":"48759",
    "sg:province":"MI",
    "wof:name":"Gainforth Carpet Care",
    "wof:placetype":"venue"
},
  "geometry": {"coordinates":[-83.463258,43.716439],"type":"Point"}
}