{
  "type": "Feature",
  "properties": {
    "iso:country":"US",
    "sg:address":"1083 E Main St",
    "sg:city":"Owosso",
    "sg:classifiers":[
        {
            "category":"Health Services",
            "subcategory":"Doctor",
            "type":"Services"
        }
    ],
    "sg:phone":"+1 989 723 6124",
    "sg:postcode":"48867",
    "sg:province":"MI",
    "sg:tags":[
        "dentist"
    ],
    "wof:name":"Owosso Dental Ctr PC",
    "wof:placetype":"venue"
},
  "geometry": {"coordinates":[-84.155867,42.997737],"type":"Point"}
}