{
  "type": "Feature",
  "properties": {
    "iso:country":"US",
    "sg:address":"16042 E 8 Mile Rd",
    "sg:city":"Detroit",
    "sg:classifiers":[
        {
            "category":"Personal",
            "subcategory":"Beauty Salon",
            "type":"Services"
        }
    ],
    "sg:phone":"+1 313 526 6034",
    "sg:postcode":"48021",
    "sg:province":"MI",
    "sg:tags":[
        "shop"
    ],
    "wof:name":"Faith Hair & Nails",
    "wof:placetype":"venue"
},
  "geometry": {"coordinates":[-82.953923,42.450166],"type":"Point"}
}