{
  "type": "Feature",
  "properties": {
    "iso:country":"US",
    "sg:address":"13721 Northline Rd",
    "sg:city":"Southgate",
    "sg:classifiers":[
        {
            "category":"Recreation",
            "subcategory":"Amusement Park",
            "type":"Entertainment"
        },
        {
            "category":"Bars & Pubs",
            "subcategory":"Sports Bar",
            "type":"Food & Drink"
        }
    ],
    "sg:phone":"+1 734 282 3350",
    "sg:postcode":"48195",
    "sg:province":"MI",
    "sg:tags":[
        "hall",
        "pool"
    ],
    "wof:name":"Hall's Billiards",
    "wof:placetype":"venue"
},
  "geometry": {"coordinates":[-83.19270299999999,42.2136],"type":"Point"}
}