{
  "type": "Feature",
  "properties": {
    "iso:country":"US",
    "sg:address":"1947 Jiroch St",
    "sg:city":"Muskegon",
    "sg:classifiers":[
        {
            "category":"Shopping",
            "subcategory":"Catalog Store",
            "type":"Retail Goods"
        }
    ],
    "sg:phone":"+1 231 722 0809",
    "sg:postcode":"49442",
    "sg:province":"MI",
    "sg:tags":[
        "mail",
        "house"
    ],
    "wof:name":"Travis Specialty Co",
    "wof:placetype":"venue"
},
  "geometry": {"coordinates":[-86.242006,43.216986],"type":"Point"}
}