{
  "type": "Feature",
  "properties": {
    "iso:country":"US",
    "sg:address":"14478 Parklane St",
    "sg:city":"Livonia",
    "sg:classifiers":[
        {
            "category":"Professional",
            "subcategory":"Engineering",
            "type":"Services"
        }
    ],
    "sg:phone":"+1 734 462 9227",
    "sg:postcode":"48154",
    "sg:province":"MI",
    "wof:name":"Continental Midland Inc",
    "wof:placetype":"venue"
},
  "geometry": {"coordinates":[-83.39935800000001,42.388544],"type":"Point"}
}