{
  "type": "Feature",
  "properties": {
    "iso:country":"US",
    "sg:address":"12855 S 1st St",
    "sg:city":"Schoolcraft",
    "sg:classifiers":[
        {
            "category":"Social Services",
            "subcategory":"Adult Care",
            "type":"Services"
        }
    ],
    "sg:phone":"+1 269 679 5815",
    "sg:postcode":"49087",
    "sg:province":"MI",
    "sg:tags":[
        "foster",
        "provider"
    ],
    "wof:name":"Robin & Sharon Chaney",
    "wof:placetype":"venue"
},
  "geometry": {"coordinates":[-85.749894,42.133694],"type":"Point"}
}