{
  "type": "Feature",
  "properties": {
    "iso:country":"US",
    "sg:address":"20078 W Kramer Rd",
    "sg:city":"Elsie",
    "sg:classifiers":[
        {
            "category":"Farming",
            "subcategory":"Farm",
            "type":"Manufacturing & Wholesale Goods"
        }
    ],
    "sg:phone":"+1 989 661 7975",
    "sg:postcode":"48831",
    "sg:province":"MI",
    "sg:tags":[
        "crop",
        "general"
    ],
    "wof:name":"Mark Guziak",
    "wof:placetype":"venue"
},
  "geometry": {"coordinates":[-84.306478,43.143399],"type":"Point"}
}