{
  "type": "Feature",
  "properties": {
    "iso:country":"US",
    "sg:address":"7244 Greenfield Rd",
    "sg:city":"Dearborn",
    "sg:classifiers":[
        {
            "category":"Cinema",
            "subcategory":"Movie Rental",
            "type":"Entertainment"
        }
    ],
    "sg:phone":"+1 313 582 9199",
    "sg:postcode":"48126",
    "sg:province":"MI",
    "sg:tags":[
        "game",
        "video"
    ],
    "wof:name":"Video House",
    "wof:placetype":"venue"
},
  "geometry": {"coordinates":[-83.196198,42.344601],"type":"Point"}
}