{
  "type": "Feature",
  "properties": {
    "iso:country":"US",
    "sg:address":"17514 Kentucky St",
    "sg:city":"Detroit",
    "sg:classifiers":[
        {
            "category":"Professional",
            "subcategory":"Accounting & Tax Preparation",
            "type":"Services"
        }
    ],
    "sg:phone":"+1 313 341 2133",
    "sg:postcode":"48221",
    "sg:province":"MI",
    "sg:tags":[
        "return"
    ],
    "wof:name":"Ifas Tax Services",
    "wof:placetype":"venue"
},
  "geometry": {"coordinates":[-83.159476,42.422334],"type":"Point"}
}