{
  "type": "Feature",
  "properties": {
    "iso:country":"US",
    "sg:address":"15 Mill Rd",
    "sg:city":"Marshall",
    "sg:classifiers":[
        {
            "category":"Food & Beverages",
            "subcategory":"Meat & Fish",
            "type":"Retail Goods"
        },
        {
            "category":"Personal",
            "type":"Services"
        }
    ],
    "sg:phone":"+1 269 781 7123",
    "sg:postcode":"49014",
    "sg:province":"MI",
    "sg:tags":[
        "processing"
    ],
    "wof:name":"Riggs Quality Meats Inc",
    "wof:placetype":"venue"
},
  "geometry": {"coordinates":[-85.149592,42.332456],"type":"Point"}
}