{
  "type": "Feature",
  "properties": {
    "iso:country":"US",
    "sg:address":"8449 Linden Rd",
    "sg:city":"Swartz Creek",
    "sg:classifiers":[
        {
            "category":"Home & Garden",
            "subcategory":"Home Furnishings",
            "type":"Retail Goods"
        }
    ],
    "sg:phone":"+1 810 691 1553",
    "sg:postcode":"48473",
    "sg:province":"MI",
    "sg:tags":[
        "venetian",
        "blind"
    ],
    "wof:name":"Decorating Windows",
    "wof:placetype":"venue"
},
  "geometry": {"coordinates":[-83.769769,42.908143],"type":"Point"}
}