{
  "type": "Feature",
  "properties": {
    "iso:country":"US",
    "sg:address":"6095 W Pierson Rd",
    "sg:city":"Flushing",
    "sg:classifiers":[
        {
            "category":"Retail",
            "subcategory":"Auto Repair",
            "type":"Services"
        }
    ],
    "sg:phone":"+1 810 249 5886",
    "sg:postcode":"48433",
    "sg:province":"MI",
    "sg:tags":[
        "repairing",
        "automobile",
        "general"
    ],
    "wof:name":"Flushing Service Center",
    "wof:placetype":"venue"
},
  "geometry": {"coordinates":[-83.797591,43.060262],"type":"Point"}
}