{
  "type": "Feature",
  "properties": {
    "iso:country":"US",
    "sg:address":"3130 Old Farm Ln",
    "sg:city":"Commerce Twp",
    "sg:classifiers":[
        {
            "category":"Professional",
            "subcategory":"Business Services",
            "type":"Services"
        }
    ],
    "sg:phone":"+1 248 360 8119",
    "sg:postcode":"48390",
    "sg:province":"MI",
    "sg:tags":[
        "embroidery"
    ],
    "sg:website":"www.pro-stitch.net",
    "wof:name":"Prostitch Embroidery",
    "wof:placetype":"venue"
},
  "geometry": {"coordinates":[-83.442831,42.567975],"type":"Point"}
}