{
  "type": "Feature",
  "properties": {
    "iso:country":"US",
    "sg:address":"225 W 8th St",
    "sg:city":"Holland",
    "sg:classifiers":[
        {
            "category":"Manufacturing",
            "subcategory":"Glass & Minerals",
            "type":"Manufacturing & Wholesale Goods"
        }
    ],
    "sg:phone":"+1 616 392 7994",
    "sg:postcode":"49423",
    "sg:province":"MI",
    "sg:tags":[
        "cement"
    ],
    "wof:name":"Holnam Inc",
    "wof:placetype":"venue"
},
  "geometry": {"coordinates":[-86.11744899999999,42.790312],"type":"Point"}
}