{
  "type": "Feature",
  "properties": {
    "iso:country":"US",
    "sg:address":"10885 Hartel Rd",
    "sg:city":"Grand Ledge",
    "sg:classifiers":[
        {
            "category":"Professional",
            "subcategory":"Business Services",
            "type":"Services"
        }
    ],
    "sg:phone":"+1 517 627 2455",
    "sg:postcode":"48837",
    "sg:province":"MI",
    "wof:name":"Helfrich Management Inc",
    "wof:placetype":"venue"
},
  "geometry": {"coordinates":[-84.73969,42.724675],"type":"Point"}
}