{
  "type": "Feature",
  "properties": {
    "iso:country":"US",
    "sg:address":"4754 Majestic Vue",
    "sg:city":"Zeeland",
    "sg:classifiers":[
        {
            "category":"Building & Trades",
            "subcategory":"Construction",
            "type":"Services"
        }
    ],
    "sg:phone":"+1 616 875 6091",
    "sg:postcode":"49464",
    "sg:province":"MI",
    "sg:tags":[
        "contractor"
    ],
    "wof:name":"Done Rite Builders",
    "wof:placetype":"venue"
},
  "geometry": {"coordinates":[-85.945407,42.854197],"type":"Point"}
}