{
  "type": "Feature",
  "properties": {
    "iso:country":"US",
    "sg:address":"31739 Mound Rd",
    "sg:city":"Warren",
    "sg:classifiers":[
        {
            "category":"Personal",
            "type":"Services"
        }
    ],
    "sg:phone":"+1 248 230 4674",
    "sg:postcode":"48083",
    "sg:province":"MI",
    "sg:tags":[
        "local"
    ],
    "sg:website":"www.EngraveOMatic.com",
    "wof:name":"Engrave O Matic",
    "wof:placetype":"venue"
},
  "geometry": {"coordinates":[-83.047855,42.52666],"type":"Point"}
}