{
  "type": "Feature",
  "properties": {
    "iso:country":"US",
    "sg:address":"2021 Penncraft Ct",
    "sg:city":"Ann Arbor",
    "sg:classifiers":[
        {
            "category":"Arts & Performance",
            "subcategory":"Theater",
            "type":"Entertainment"
        }
    ],
    "sg:phone":"+1 734 665 0165",
    "sg:postcode":"48103",
    "sg:province":"MI",
    "sg:tags":[
        "group"
    ],
    "wof:name":"Gemini",
    "wof:placetype":"venue"
},
  "geometry": {"coordinates":[-83.772853,42.284875],"type":"Point"}
}