{
  "type": "Feature",
  "properties": {
    "iso:country":"US",
    "sg:address":"738 32nd St SE",
    "sg:city":"Grand Rapids",
    "sg:classifiers":[
        {
            "category":"Manufacturing",
            "subcategory":"Printing",
            "type":"Manufacturing & Wholesale Goods"
        }
    ],
    "sg:phone":"+1 616 245 1560",
    "sg:postcode":"49548",
    "sg:province":"MI",
    "sg:tags":[
        "book"
    ],
    "wof:name":"Roberts Publishing Company",
    "wof:placetype":"venue"
},
  "geometry": {"coordinates":[-85.64725300000001,42.905513],"type":"Point"}
}