{
  "type": "Feature",
  "properties": {
    "iso:country":"US",
    "sg:address":"155 Clemens St",
    "sg:city":"Mt Clemens",
    "sg:classifiers":[
        {
            "category":"Manufacturing",
            "subcategory":"Tools & Machinery",
            "type":"Manufacturing & Wholesale Goods"
        }
    ],
    "sg:phone":"+1 586 466 5700",
    "sg:postcode":"48043",
    "sg:province":"MI",
    "sg:tags":[
        "industry",
        "special"
    ],
    "wof:name":"DMJ Tech Inc",
    "wof:placetype":"venue"
},
  "geometry": {"coordinates":[-82.87230700000001,42.604886],"type":"Point"}
}