{
  "type": "Feature",
  "properties": {
    "iso:country":"US",
    "sg:address":"1965 Pine Creek Rd",
    "sg:city":"Manistee",
    "sg:classifiers":[
        {
            "category":"Manufacturing",
            "subcategory":"Tools & Machinery",
            "type":"Manufacturing & Wholesale Goods"
        }
    ],
    "sg:phone":"+1 231 723 7041",
    "sg:postcode":"49660",
    "sg:province":"MI",
    "sg:tags":[
        "machine",
        "shop"
    ],
    "wof:name":"Metal Line Inc",
    "wof:placetype":"venue"
},
  "geometry": {"coordinates":[-86.272429,44.247556],"type":"Point"}
}