{
  "type": "Feature",
  "properties": {
    "iso:country":"US",
    "sg:address":"5924 Yawger Rd",
    "sg:city":"Battle Creek",
    "sg:classifiers":[
        {
            "category":"Professional",
            "subcategory":"Business Services",
            "type":"Services"
        }
    ],
    "sg:phone":"+1 269 660 9266",
    "sg:postcode":"49017",
    "sg:province":"MI",
    "wof:name":"Embroidery Creations LLC",
    "wof:placetype":"venue"
},
  "geometry": {"coordinates":[-85.18295500000001,42.362654],"type":"Point"}
}