{
  "type": "Feature",
  "properties": {
    "iso:country":"US",
    "sg:address":"28437 San Marino Dr",
    "sg:city":"Southfield",
    "sg:classifiers":[
        {
            "category":"Professional",
            "subcategory":"Engineering",
            "type":"Services"
        }
    ],
    "sg:phone":"+1 248 350 1048",
    "sg:postcode":"48034",
    "sg:province":"MI",
    "wof:name":"United Rhythm Entertainment",
    "wof:placetype":"venue"
},
  "geometry": {"coordinates":[-83.31652200000001,42.494084],"type":"Point"}
}