{
  "type": "Feature",
  "properties": {
    "iso:country":"US",
    "sg:address":"17016 Mack Ave",
    "sg:city":"Grosse Pointe",
    "sg:classifiers":[
        {
            "category":"Building & Trades",
            "subcategory":"Construction",
            "type":"Services"
        }
    ],
    "sg:phone":"+1 313 881 5956",
    "sg:postcode":"48230",
    "sg:province":"MI",
    "sg:tags":[
        "contractor"
    ],
    "wof:name":"Vesprini Bros General Contractors",
    "wof:placetype":"venue"
},
  "geometry": {"coordinates":[-82.9226,42.3946],"type":"Point"}
}