{
  "type": "Feature",
  "properties": {
    "iso:country":"US",
    "sg:address":"18625 Centennial Rd",
    "sg:city":"Marshall",
    "sg:classifiers":[
        {
            "category":"Banks & Credit Unions",
            "subcategory":"Investment Brokerage",
            "type":"Services"
        }
    ],
    "sg:phone":"+1 269 789 9760",
    "sg:postcode":"49068",
    "sg:province":"MI",
    "sg:tags":[
        "consultant",
        "planning",
        "financial"
    ],
    "wof:name":"David L Cushard CMFC",
    "wof:placetype":"venue"
},
  "geometry": {"coordinates":[-84.933925,42.278688],"type":"Point"}
}