{
  "type": "Feature",
  "properties": {
    "iso:country":"US",
    "sg:address":"3535 Jackson Rd",
    "sg:city":"Ann Arbor",
    "sg:classifiers":[
        {
            "category":"Autos & Motor Vehicles",
            "subcategory":"Fuel & Gas Station",
            "type":"Retail Goods"
        }
    ],
    "sg:phone":"+1 734 662 2252",
    "sg:postcode":"48103",
    "sg:province":"MI",
    "sg:tags":[
        "station",
        "gasoline"
    ],
    "wof:name":"Clark Service Station",
    "wof:placetype":"venue"
},
  "geometry": {"coordinates":[-83.80013099999999,42.28488],"type":"Point"}
}