{
  "type": "Feature",
  "properties": {
    "iso:country":"US",
    "sg:address":"1316 Jennings Ct",
    "sg:city":"Allegan",
    "sg:classifiers":[
        {
            "category":"Health Services",
            "subcategory":"Nursing And Care Facility",
            "type":"Services"
        }
    ],
    "sg:phone":"+1 269 673 0193",
    "sg:postcode":"49010",
    "sg:province":"MI",
    "sg:tags":[
        "adult"
    ],
    "wof:name":"Sharon's Adult Foster Care",
    "wof:placetype":"venue"
},
  "geometry": {"coordinates":[-85.828222,42.516704],"type":"Point"}
}