{
  "type": "Feature",
  "properties": {
    "iso:country":"US",
    "sg:address":"5860 Briarcliff Ln",
    "sg:city":"Kalamazoo",
    "sg:classifiers":[
        {
            "category":"Real Estate",
            "subcategory":"Real Estate Operator",
            "type":"Services"
        }
    ],
    "sg:phone":"+1 269 323 7774",
    "sg:postcode":"49009",
    "sg:province":"MI",
    "sg:tags":[
        "apartment"
    ],
    "sg:website":"www.gardnergroupofmichigan.com",
    "wof:name":"Lotus Townhomes",
    "wof:placetype":"venue"
},
  "geometry": {"coordinates":[-85.680795,42.231386],"type":"Point"}
}