{
  "type": "Feature",
  "properties": {
    "iso:country":"US",
    "sg:address":"3340 Lake St",
    "sg:city":"Arcadia",
    "sg:classifiers":[
        {
            "category":"Recreation",
            "type":"Entertainment"
        }
    ],
    "sg:phone":"+1 231 889 4360",
    "sg:postcode":"49613",
    "sg:province":"MI",
    "sg:tags":[
        "historical"
    ],
    "wof:name":"Arcadia Area Historical Scty",
    "wof:placetype":"venue"
},
  "geometry": {"coordinates":[-86.235236,44.493314],"type":"Point"}
}