{
  "type": "Feature",
  "properties": {
    "iso:country":"US",
    "sg:address":"209 N Walnut St",
    "sg:city":"Lansing",
    "sg:classifiers":[
        {
            "category":"Professional",
            "subcategory":"Lawyer & Legal Services",
            "type":"Services"
        }
    ],
    "sg:phone":"+1 517 372 4204",
    "sg:postcode":"48933",
    "sg:province":"MI",
    "wof:name":"Lett Steven T Atty",
    "wof:placetype":"venue"
},
  "geometry": {"coordinates":[-84.557058,42.735887],"type":"Point"}
}