{
  "type": "Feature",
  "properties": {
    "iso:country":"US",
    "sg:address":"57007 Pontiac Trl",
    "sg:city":"New Hudson",
    "sg:classifiers":[
        {
            "category":"Manufacturing",
            "subcategory":"Tools & Machinery",
            "type":"Manufacturing & Wholesale Goods"
        }
    ],
    "sg:phone":"+1 248 437 1510",
    "sg:postcode":"48165",
    "sg:province":"MI",
    "sg:tags":[
        "machine"
    ],
    "wof:name":"Ideal Heated Knives Inc",
    "wof:placetype":"venue"
},
  "geometry": {"coordinates":[-83.617981,42.510427],"type":"Point"}
}