{
  "type": "Feature",
  "properties": {
    "iso:country":"US",
    "sg:address":"2249 W Moore Rd",
    "sg:city":"Hillsdale",
    "sg:classifiers":[
        {
            "category":"Manufacturing",
            "subcategory":"Retail Goods",
            "type":"Manufacturing & Wholesale Goods"
        }
    ],
    "sg:phone":"+1 517 849 9647",
    "sg:postcode":"49242",
    "sg:province":"MI",
    "sg:tags":[
        "manufacturer"
    ],
    "wof:name":"Gateway Manufacturing Inc",
    "wof:placetype":"venue"
},
  "geometry": {"coordinates":[-84.65364700000001,41.95637],"type":"Point"}
}