{
  "type": "Feature",
  "properties": {
    "iso:country":"US",
    "sg:address":"5635 Sheffer Rd",
    "sg:city":"Prescott",
    "sg:classifiers":[
        {
            "category":"Building & Trades",
            "subcategory":"Construction",
            "type":"Services"
        }
    ],
    "sg:phone":"+1 989 873 5029",
    "sg:postcode":"48756",
    "sg:province":"MI",
    "sg:tags":[
        "contractor"
    ],
    "wof:name":"Barriger Builders",
    "wof:placetype":"venue"
},
  "geometry": {"coordinates":[-83.89614899999999,44.17654],"type":"Point"}
}