{
  "type": "Feature",
  "properties": {
    "iso:country":"US",
    "sg:address":"39600 W 14 Mile Rd",
    "sg:city":"Commerce Township",
    "sg:classifiers":[
        {
            "category":"Shopping",
            "subcategory":"Party Supplies",
            "type":"Retail Goods"
        }
    ],
    "sg:phone":"+1 248 960 5555",
    "sg:postcode":"48390",
    "sg:province":"MI",
    "wof:name":"Party & Gifts",
    "wof:placetype":"venue"
},
  "geometry": {"coordinates":[-83.438816,42.527227],"type":"Point"}
}