{
  "type": "Feature",
  "properties": {
    "iso:country":"US",
    "sg:address":"15335 Stout St",
    "sg:city":"Detroit",
    "sg:classifiers":[
        {
            "category":"Shopping",
            "subcategory":"Computers & Home Electronics",
            "type":"Retail Goods"
        }
    ],
    "sg:phone":"+1 313 534 3036",
    "sg:postcode":"48223",
    "sg:province":"MI",
    "wof:name":"See More Pay Less Computi",
    "wof:placetype":"venue"
},
  "geometry": {"coordinates":[-83.241737,42.401784],"type":"Point"}
}