{
  "type": "Feature",
  "properties": {
    "iso:country":"US",
    "sg:address":"14000 Telegraph Rd",
    "sg:city":"Redford",
    "sg:classifiers":[
        {
            "category":"Shopping",
            "subcategory":"Department Store",
            "type":"Retail Goods"
        }
    ],
    "sg:phone":"+1 313 255 1420",
    "sg:postcode":"48239",
    "sg:province":"MI",
    "sg:website":"www.familydollar.com",
    "wof:name":"Family Dollar Stores",
    "wof:placetype":"venue"
},
  "geometry": {"coordinates":[-83.275803,42.3876],"type":"Point"}
}