{
  "type": "Feature",
  "properties": {
    "iso:country":"US",
    "sg:address":"10774 Borgman Ave",
    "sg:city":"Huntington Woods",
    "sg:classifiers":[
        {
            "category":"Professional",
            "subcategory":"Computer Services",
            "type":"Services"
        }
    ],
    "sg:phone":"+1 248 543 6437",
    "sg:postcode":"48070",
    "sg:province":"MI",
    "sg:tags":[
        "datum"
    ],
    "wof:name":"Michael Edelman",
    "wof:placetype":"venue"
},
  "geometry": {"coordinates":[-83.17335300000001,42.486539],"type":"Point"}
}