{
  "type": "Feature",
  "properties": {
    "iso:country":"US",
    "sg:address":"601 W 4th St",
    "sg:city":"Buchanan",
    "sg:classifiers":[
        {
            "category":"Real Estate",
            "subcategory":"Real Estate Operator",
            "type":"Services"
        }
    ],
    "sg:phone":"+1 269 695 7047",
    "sg:postcode":"49107",
    "sg:province":"MI",
    "sg:tags":[
        "building",
        "apartment"
    ],
    "wof:name":"Buchanan Place APT",
    "wof:placetype":"venue"
},
  "geometry": {"coordinates":[-86.37420899999999,41.832582],"type":"Point"}
}