{
  "type": "Feature",
  "properties": {
    "iso:country":"US",
    "sg:address":"5391 Coldwater Rd",
    "sg:city":"Flint",
    "sg:classifiers":[
        {
            "category":"Professional",
            "subcategory":"Business Services",
            "type":"Services"
        }
    ],
    "sg:phone":"+1 810 732 2689",
    "sg:postcode":"48504",
    "sg:province":"MI",
    "sg:tags":[
        "interior",
        "consultant",
        "design",
        "decorator"
    ],
    "wof:name":"Steve Davidek Painting",
    "wof:placetype":"venue"
},
  "geometry": {"coordinates":[-83.79313500000001,43.089459],"type":"Point"}
}