{
  "type": "Feature",
  "properties": {
    "iso:country":"US",
    "sg:address":"95 Chimney Oaks Dr",
    "sg:city":"Okemos",
    "sg:classifiers":[
        {
            "category":"Professional",
            "type":"Services"
        }
    ],
    "sg:phone":"+1 517 347 8640",
    "sg:postcode":"48864",
    "sg:province":"MI",
    "sg:tags":[
        "establishment"
    ],
    "wof:name":"Boegner A",
    "wof:placetype":"venue"
},
  "geometry": {"coordinates":[-84.36690299999999,42.698515],"type":"Point"}
}