{
  "type": "Feature",
  "properties": {
    "iso:country":"US",
    "sg:address":"2305 E Coe Rd",
    "sg:city":"Shepherd",
    "sg:classifiers":[
        {
            "category":"Manufacturing",
            "subcategory":"Rubber & Plastics",
            "type":"Manufacturing & Wholesale Goods"
        }
    ],
    "sg:phone":"+1 989 828 6526",
    "sg:postcode":"48883",
    "sg:province":"MI",
    "sg:tags":[
        "forming"
    ],
    "wof:name":"Contour Engineering",
    "wof:placetype":"venue"
},
  "geometry": {"coordinates":[-84.801185,43.480737],"type":"Point"}
}