{
  "type": "Feature",
  "properties": {
    "iso:country":"US",
    "sg:address":"33151 23 Mile Rd",
    "sg:city":"New Baltimore",
    "sg:classifiers":[
        {
            "category":"Restaurant",
            "type":"Food & Drink"
        }
    ],
    "sg:menulink":"http://www.allmenus.com/mi/chesterfield/43894-guilianos/menu/",
    "sg:phone":"+1 586 725 3914",
    "sg:postcode":"48047",
    "sg:province":"MI",
    "sg:tags":[
        "italian"
    ],
    "wof:name":"Guiliano's",
    "wof:placetype":"venue"
},
  "geometry": {"coordinates":[-82.775682,42.675511],"type":"Point"}
}