{
  "type": "Feature",
  "properties": {
    "iso:country":"US",
    "sg:address":"42711 Ford Rd",
    "sg:city":"Plymouth",
    "sg:classifiers":[
        {
            "category":"Real Estate",
            "subcategory":"Real Estate Operator",
            "type":"Services"
        }
    ],
    "sg:phone":"+1 734 981 7200",
    "sg:postcode":"48170",
    "sg:province":"MI",
    "sg:tags":[
        "apartment"
    ],
    "wof:name":"Spectrum Apartment Search",
    "wof:placetype":"venue"
},
  "geometry": {"coordinates":[-83.488899,42.3675],"type":"Point"}
}