{
  "type": "Feature",
  "properties": {
    "iso:country":"US",
    "sg:address":"6176 US Hwy 31",
    "sg:city":"Grawn",
    "sg:classifiers":[
        {
            "category":"Real Estate",
            "subcategory":"Real Estate Agent",
            "type":"Services"
        }
    ],
    "sg:phone":"+1 231 943 5729",
    "sg:postcode":"49637",
    "sg:province":"MI",
    "sg:tags":[
        "rental",
        "vacation"
    ],
    "wof:name":"Kay Ray Properties",
    "wof:placetype":"venue"
},
  "geometry": {"coordinates":[-85.707746,44.665228],"type":"Point"}
}