{
  "type": "Feature",
  "properties": {
    "iso:country":"US",
    "sg:address":"3013 Clements St",
    "sg:city":"Detroit",
    "sg:classifiers":[
        {
            "category":"Manufacturing",
            "subcategory":"Textiles",
            "type":"Manufacturing & Wholesale Goods"
        }
    ],
    "sg:phone":"+1 313 515 1730",
    "sg:postcode":"48238",
    "sg:province":"MI",
    "sg:tags":[
        "mill",
        "knit",
        "outerwear"
    ],
    "wof:name":"Lmn Enterprises",
    "wof:placetype":"venue"
},
  "geometry": {"coordinates":[-83.12722100000001,42.392148],"type":"Point"}
}