{
  "type": "Feature",
  "properties": {
    "iso:country":"US",
    "sg:address":"3851 Dobson Rd",
    "sg:city":"Filion",
    "sg:classifiers":[
        {
            "category":"Real Estate",
            "subcategory":"Real Estate Operator",
            "type":"Services"
        }
    ],
    "sg:phone":"+1 989 428 4420",
    "sg:postcode":"48432",
    "sg:province":"MI",
    "sg:tags":[
        "property",
        "lessor"
    ],
    "wof:name":"Frank Kanaski",
    "wof:placetype":"venue"
},
  "geometry": {"coordinates":[-82.871809,43.913775],"type":"Point"}
}