{
  "type": "Feature",
  "properties": {
    "iso:country":"US",
    "sg:address":"2524 Baltusrol Dr",
    "sg:city":"Commerce Township",
    "sg:classifiers":[
        {
            "category":"Recreation",
            "type":"Entertainment"
        }
    ],
    "sg:phone":"+1 248 330 1111",
    "sg:postcode":"48382",
    "sg:province":"MI",
    "sg:tags":[
        "guide",
        "hunting"
    ],
    "wof:name":"Hunting Legacy LLC",
    "wof:placetype":"venue"
},
  "geometry": {"coordinates":[-83.524441,42.600015],"type":"Point"}
}