{
  "type": "Feature",
  "properties": {
    "iso:country":"US",
    "sg:address":"26671 Gratiot Ave",
    "sg:city":"Roseville",
    "sg:classifiers":[
        {
            "category":"Taxi",
            "type":"Transportation"
        },
        {
            "category":"Airline",
            "type":"Transportation"
        },
        {
            "category":"Professional",
            "subcategory":"Business Services",
            "type":"Services"
        }
    ],
    "sg:phone":"+1 586 777 1111",
    "sg:postcode":"48066",
    "sg:province":"MI",
    "sg:tags":[
        "delivery",
        "shuttle",
        "airport",
        "courier"
    ],
    "wof:name":"Shamrock Cab Co",
    "wof:placetype":"venue"
},
  "geometry": {"coordinates":[-82.940102,42.4925],"type":"Point"}
}