{
  "type": "Feature",
  "properties": {
    "iso:country":"US",
    "sg:address":"6757 Cascade Rd SE",
    "sg:city":"Grand Rapids",
    "sg:classifiers":[
        {
            "category":"Professional",
            "subcategory":"Management & Consulting",
            "type":"Services"
        }
    ],
    "sg:phone":"+1 616 897 4325",
    "sg:postcode":"49546",
    "sg:province":"MI",
    "wof:name":"Conrin Inc",
    "wof:placetype":"venue"
},
  "geometry": {"coordinates":[-85.499253,42.91347],"type":"Point"}
}