{
  "type": "Feature",
  "properties": {
    "iso:country":"US",
    "sg:address":"23 Mill Rd",
    "sg:city":"Utica",
    "sg:classifiers":[
        {
            "category":"Home & Garden",
            "subcategory":"Hardware",
            "type":"Retail Goods"
        }
    ],
    "sg:phone":"+1 586 739 5082",
    "sg:postcode":"48386",
    "sg:province":"MI",
    "sg:tags":[
        "pressure",
        "washer"
    ],
    "wof:name":"Mikes Pump Service Inc",
    "wof:placetype":"venue"
},
  "geometry": {"coordinates":[-83.48759800000001,42.638901],"type":"Point"}
}