{
  "type": "Feature",
  "properties": {
    "iso:country":"US",
    "sg:address":"2918 Territorial Rd",
    "sg:city":"Benton Harbor",
    "sg:classifiers":[
        {
            "category":"Retail",
            "subcategory":"Repair Shop",
            "type":"Services"
        }
    ],
    "sg:phone":"+1 269 934 8021",
    "sg:postcode":"49022",
    "sg:province":"MI",
    "sg:tags":[
        "water",
        "well",
        "drilling"
    ],
    "wof:name":"Collins Well Drilling",
    "wof:placetype":"venue"
},
  "geometry": {"coordinates":[-86.390505,42.124512],"type":"Point"}
}