{
  "type": "Feature",
  "properties": {
    "iso:country":"US",
    "sg:address":"1439 N Van Rd",
    "sg:city":"Holly",
    "sg:classifiers":[
        {
            "category":"Professional",
            "subcategory":"Management & Consulting",
            "type":"Services"
        }
    ],
    "sg:phone":"+1 248 634 9708",
    "sg:postcode":"48442",
    "sg:province":"MI",
    "wof:name":"C M Enterprises",
    "wof:placetype":"venue"
},
  "geometry": {"coordinates":[-83.532004,42.871925],"type":"Point"}
}