{
  "type": "Feature",
  "properties": {
    "iso:country":"US",
    "sg:address":"38936 Dequindre Rd",
    "sg:city":"Sterling Heights",
    "sg:classifiers":[
        {
            "category":"Shopping",
            "subcategory":"Clothing, Apparel, & Fashions",
            "type":"Retail Goods"
        }
    ],
    "sg:phone":"+1 586 977 8845",
    "sg:postcode":"48310",
    "sg:province":"MI",
    "wof:name":"Bolly Wood Fashion",
    "wof:placetype":"venue"
},
  "geometry": {"coordinates":[-83.089247,42.576968],"type":"Point"}
}