{
  "type": "Feature",
  "properties": {
    "iso:country":"US",
    "sg:address":"2480 Chicago Dr",
    "sg:city":"Hudsonville",
    "sg:classifiers":[
        {
            "category":"Wholesale",
            "subcategory":"Farm Supplies",
            "type":"Manufacturing & Wholesale Goods"
        }
    ],
    "sg:phone":"+1 616 662 6450",
    "sg:postcode":"49426",
    "sg:province":"MI",
    "sg:website":"www.mytscstore.com",
    "wof:name":"Tractor Supply Co",
    "wof:placetype":"venue"
},
  "geometry": {"coordinates":[-85.85010800000001,42.876624],"type":"Point"}
}