{
  "type": "Feature",
  "properties": {
    "iso:country":"US",
    "sg:address":"4008 Bart Ave",
    "sg:city":"Warren",
    "sg:classifiers":[
        {
            "category":"Professional",
            "subcategory":"Business Services",
            "type":"Services"
        }
    ],
    "sg:phone":"+1 586 755 5754",
    "sg:postcode":"48091",
    "sg:province":"MI",
    "wof:name":"Creative Living Design",
    "wof:placetype":"venue"
},
  "geometry": {"coordinates":[-83.071687,42.465663],"type":"Point"}
}