{
  "type": "Feature",
  "properties": {
    "iso:country":"US",
    "sg:address":"36800 Woodward Ave",
    "sg:city":"Bloomfield Hills",
    "sg:classifiers":[
        {
            "category":"Banks & Credit Unions",
            "subcategory":"Investment Brokerage",
            "type":"Services"
        }
    ],
    "sg:phone":"+1 248 647 1781",
    "sg:postcode":"48304",
    "sg:province":"MI",
    "sg:tags":[
        "investing"
    ],
    "wof:name":"Thinkorswim Advisors",
    "wof:placetype":"venue"
},
  "geometry": {"coordinates":[-83.2229,42.558601],"type":"Point"}
}