{
  "type": "Feature",
  "properties": {
    "iso:country":"US",
    "sg:address":"156 S Main St",
    "sg:city":"Fowler",
    "sg:classifiers":[
        {
            "category":"Restaurant",
            "type":"Food & Drink"
        }
    ],
    "sg:phone":"+1 989 593 3546",
    "sg:postcode":"48835",
    "sg:province":"MI",
    "wof:name":"Main Street Pizza",
    "wof:placetype":"venue"
},
  "geometry": {"coordinates":[-84.739727,43.002281],"type":"Point"}
}