{
  "type": "Feature",
  "properties": {
    "iso:country":"US",
    "sg:address":"6999 Clymer Rd",
    "sg:city":"Coloma",
    "sg:classifiers":[
        {
            "category":"Wholesale",
            "subcategory":"Plants",
            "type":"Manufacturing & Wholesale Goods"
        }
    ],
    "sg:phone":"+1 269 468 6150",
    "sg:postcode":"49038",
    "sg:province":"MI",
    "sg:tags":[
        "nursery",
        "tree"
    ],
    "wof:name":"Grapevine Nursery",
    "wof:placetype":"venue"
},
  "geometry": {"coordinates":[-86.340245,42.239926],"type":"Point"}
}