{
  "type": "Feature",
  "properties": {
    "iso:country":"US",
    "sg:address":"5049 Northland Dr NE",
    "sg:city":"Grand Rapids",
    "sg:classifiers":[
        {
            "category":"Restaurant",
            "type":"Food & Drink"
        }
    ],
    "sg:menulink":"http://www.allmenus.com/mi/plainfield/208700-taco-bell/menu/",
    "sg:phone":"+1 616 364 8946",
    "sg:postcode":"49525",
    "sg:province":"MI",
    "sg:tags":[
        "mexican"
    ],
    "wof:name":"Taco Bell",
    "wof:placetype":"venue"
},
  "geometry": {"coordinates":[-85.57992900000001,43.053986],"type":"Point"}
}