{
  "type": "Feature",
  "properties": {
    "iso:country":"US",
    "sg:address":"3401 Vivian Rd",
    "sg:city":"Monroe",
    "sg:classifiers":[
        {
            "category":"Banks & Credit Unions",
            "subcategory":"Financial Services",
            "type":"Services"
        }
    ],
    "sg:phone":"+1 734 241 7032",
    "sg:postcode":"48162",
    "sg:province":"MI",
    "sg:tags":[
        "company",
        "holding"
    ],
    "wof:name":"Merritt Holdings LLC",
    "wof:placetype":"venue"
},
  "geometry": {"coordinates":[-83.362346,41.956252],"type":"Point"}
}