{
  "type": "Feature",
  "properties": {
    "iso:country":"US",
    "sg:address":"349 N Water St",
    "sg:city":"Portland",
    "sg:classifiers":[
        {
            "category":"Home & Garden",
            "subcategory":"Building Materials",
            "type":"Retail Goods"
        }
    ],
    "sg:phone":"+1 517 647 4131",
    "sg:postcode":"48875",
    "sg:province":"MI",
    "sg:tags":[
        "lumber"
    ],
    "wof:name":"Builders Lumber Co",
    "wof:placetype":"venue"
},
  "geometry": {"coordinates":[-84.904213,42.874844],"type":"Point"}
}