{
  "type": "Feature",
  "properties": {
    "iso:country":"US",
    "sg:address":"6339 Atlantic Ave",
    "sg:city":"Kalamazoo",
    "sg:classifiers":[
        {
            "category":"Organizations",
            "subcategory":"Religious Organization",
            "type":"Services"
        }
    ],
    "sg:phone":"+1 269 375 5265",
    "sg:postcode":"49009",
    "sg:province":"MI",
    "sg:website":"www.fourthrca.org",
    "wof:name":"Fourth Reformed Church",
    "wof:placetype":"venue"
},
  "geometry": {"coordinates":[-85.67596500000001,42.257453],"type":"Point"}
}