{
  "type": "Feature",
  "properties": {
    "iso:country":"US",
    "sg:address":"430 E Congress St",
    "sg:city":"Sturgis",
    "sg:classifiers":[
        {
            "category":"Retail",
            "subcategory":"Portrait Studio",
            "type":"Services"
        }
    ],
    "sg:phone":"+1 269 268 9744",
    "sg:postcode":"49091",
    "sg:province":"MI",
    "sg:tags":[
        "photo"
    ],
    "wof:name":"Kinsey Photography",
    "wof:placetype":"venue"
},
  "geometry": {"coordinates":[-85.41229199999999,41.796802],"type":"Point"}
}