{
  "type": "Feature",
  "properties": {
    "iso:country":"US",
    "sg:address":"43063 Mound Rd",
    "sg:city":"Sterling Heights",
    "sg:classifiers":[
        {
            "category":"Personal",
            "subcategory":"Beauty Salon",
            "type":"Services"
        }
    ],
    "sg:phone":"+1 586 991 0092",
    "sg:postcode":"48314",
    "sg:province":"MI",
    "wof:name":"Fantastic Sam's",
    "wof:placetype":"venue"
},
  "geometry": {"coordinates":[-83.05159999999999,42.609231],"type":"Point"}
}