{
  "type": "Feature",
  "properties": {
    "iso:country":"US",
    "sg:address":"1724 Inner Dr",
    "sg:city":"Ortonville",
    "sg:classifiers":[
        {
            "category":"Building & Trades",
            "subcategory":"Construction",
            "type":"Services"
        }
    ],
    "sg:phone":"+1 248 627 9418",
    "sg:postcode":"48462",
    "sg:province":"MI",
    "sg:tags":[
        "woodworker"
    ],
    "wof:name":"North Oakland Woodworks",
    "wof:placetype":"venue"
},
  "geometry": {"coordinates":[-83.398996,42.826575],"type":"Point"}
}