{
  "type": "Feature",
  "properties": {
    "iso:country":"US",
    "sg:address":"414 Perry Rd",
    "sg:city":"Grand Blanc",
    "sg:classifiers":[
        {
            "category":"Health Services",
            "subcategory":"Doctor",
            "type":"Services"
        }
    ],
    "sg:phone":"+1 810 694 8423",
    "sg:postcode":"48439",
    "sg:province":"MI",
    "sg:tags":[
        "medicine",
        "internal"
    ],
    "wof:name":"Reddy Kunadi S MD Internal Medcn",
    "wof:placetype":"venue"
},
  "geometry": {"coordinates":[-83.623001,42.924801],"type":"Point"}
}