{
  "type": "Feature",
  "properties": {
    "iso:country":"US",
    "sg:address":"222 S Kendall Ave",
    "sg:city":"Kalamazoo",
    "sg:classifiers":[
        {
            "category":"Real Estate",
            "subcategory":"Real Estate Operator",
            "type":"Services"
        }
    ],
    "sg:phone":"+1 269 344 6558",
    "sg:postcode":"49006",
    "sg:province":"MI",
    "sg:tags":[
        "apartment"
    ],
    "wof:name":"Mansard House",
    "wof:placetype":"venue"
},
  "geometry": {"coordinates":[-85.626473,42.289191],"type":"Point"}
}