{
  "type": "Feature",
  "properties": {
    "iso:country":"US",
    "sg:address":"13229 E 14 Mile Rd",
    "sg:city":"Sterling Heights",
    "sg:classifiers":[
        {
            "category":"Restaurant",
            "type":"Food & Drink"
        }
    ],
    "sg:menulink":"http://www.allmenus.com/mi/sterling-heights/26978-hungry-howies-pizza/menu/",
    "sg:phone":"+1 586 264 0215",
    "sg:postcode":"48312",
    "sg:province":"MI",
    "sg:tags":[
        "wrap",
        "american",
        "sandwich",
        "pizza"
    ],
    "wof:name":"Hungry Howie's Pizza",
    "wof:placetype":"venue"
},
  "geometry": {"coordinates":[-83.04817199999999,42.536155],"type":"Point"}
}