{
  "type": "Feature",
  "properties": {
    "iso:country":"US",
    "sg:address":"512 Harper St",
    "sg:city":"Pontiac",
    "sg:classifiers":[
        {
            "category":"Wholesale",
            "subcategory":"Machinery & Supplies",
            "type":"Manufacturing & Wholesale Goods"
        }
    ],
    "sg:phone":"+1 248 335 0098",
    "sg:postcode":"48342",
    "sg:province":"MI",
    "sg:tags":[
        "equipment",
        "irrigation",
        "system"
    ],
    "wof:name":"Top Of The Hill",
    "wof:placetype":"venue"
},
  "geometry": {"coordinates":[-83.280711,42.653008],"type":"Point"}
}