{
  "type": "Feature",
  "properties": {
    "iso:country":"US",
    "sg:address":"10600 Victory Rd",
    "sg:city":"Erie",
    "sg:classifiers":[
        {
            "category":"Retail",
            "subcategory":"Auto Repair",
            "type":"Services"
        }
    ],
    "sg:phone":"+1 734 241 3601",
    "sg:postcode":"48133",
    "sg:province":"MI",
    "sg:tags":[
        "wrecker"
    ],
    "wof:name":"Star Towing",
    "wof:placetype":"venue"
},
  "geometry": {"coordinates":[-83.45446699999999,41.809065],"type":"Point"}
}