{
  "type": "Feature",
  "properties": {
    "iso:country":"US",
    "sg:address":"614 N Gibbs Rd",
    "sg:city":"Albion",
    "sg:classifiers":[
        {
            "category":"Education",
            "subcategory":"Vocational School",
            "type":"Public Place"
        }
    ],
    "sg:phone":"+1 517 629 3253",
    "sg:postcode":"49224",
    "sg:province":"MI",
    "wof:name":"Educational Concepts Inc",
    "wof:placetype":"venue"
},
  "geometry": {"coordinates":[-84.678506,42.2566],"type":"Point"}
}