{
  "type": "Feature",
  "properties": {
    "iso:country":"US",
    "sg:address":"7450 Pokagon Rd",
    "sg:city":"Berrien Center",
    "sg:classifiers":[
        {
            "category":"Farming",
            "subcategory":"Farm",
            "type":"Manufacturing & Wholesale Goods"
        }
    ],
    "sg:phone":"+1 269 461 6665",
    "sg:postcode":"49102",
    "sg:province":"MI",
    "wof:name":"O'Dell Farms",
    "wof:placetype":"venue"
},
  "geometry": {"coordinates":[-86.279742,41.932316],"type":"Point"}
}