{
  "type": "Feature",
  "properties": {
    "iso:country":"US",
    "sg:address":"1500 E Beltline Ave SE",
    "sg:city":"Grand Rapids",
    "sg:classifiers":[
        {
            "category":"Professional",
            "subcategory":"Lawyer & Legal Services",
            "type":"Services"
        }
    ],
    "sg:phone":"+1 616 285 0143",
    "sg:postcode":"49506",
    "sg:province":"MI",
    "wof:name":"Secrest Wardle Lynch Hampton",
    "wof:placetype":"venue"
},
  "geometry": {"coordinates":[-85.584739,42.935149],"type":"Point"}
}