{
  "type": "Feature",
  "properties": {
    "iso:country":"US",
    "sg:address":"3237 Monument Dr",
    "sg:city":"Ann Arbor",
    "sg:classifiers":[
        {
            "category":"Manufacturing",
            "subcategory":"Metals",
            "type":"Manufacturing & Wholesale Goods"
        }
    ],
    "sg:phone":"+1 734 975 2491",
    "sg:postcode":"48108",
    "sg:province":"MI",
    "sg:tags":[
        "nonferrous"
    ],
    "wof:name":"Syran Systems",
    "wof:placetype":"venue"
},
  "geometry": {"coordinates":[-83.687759,42.236659],"type":"Point"}
}