{
  "type": "Feature",
  "properties": {
    "iso:country":"US",
    "sg:address":"20343 Fenkell St",
    "sg:city":"Detroit",
    "sg:classifiers":[
        {
            "category":"Retail",
            "subcategory":"Auto Repair",
            "type":"Services"
        }
    ],
    "sg:phone":"+1 313 533 9700",
    "sg:postcode":"48223",
    "sg:province":"MI",
    "sg:tags":[
        "exhaust"
    ],
    "wof:name":"M & J Mufflers Brakes Shocks",
    "wof:placetype":"venue"
},
  "geometry": {"coordinates":[-83.241272,42.400536],"type":"Point"}
}