{
  "type": "Feature",
  "properties": {
    "iso:country":"US",
    "sg:address":"7622 S Westnedge Ave",
    "sg:city":"Portage",
    "sg:classifiers":[
        {
            "category":"Personal",
            "subcategory":"Beauty Salon",
            "type":"Services"
        }
    ],
    "sg:phone":"+1 269 323 9350",
    "sg:postcode":"49002",
    "sg:province":"MI",
    "sg:tags":[
        "manicuring"
    ],
    "wof:name":"Vicki Nails",
    "wof:placetype":"venue"
},
  "geometry": {"coordinates":[-85.589466,42.205254],"type":"Point"}
}