{
  "type": "Feature",
  "properties": {
    "iso:country":"US",
    "sg:address":"2900 W Maple Rd Ste 201",
    "sg:city":"Troy",
    "sg:classifiers":[
        {
            "category":"Banks & Credit Unions",
            "subcategory":"Bank",
            "type":"Services"
        },
        {
            "category":"Banks & Credit Unions",
            "subcategory":"Financial Services",
            "type":"Services"
        }
    ],
    "sg:phone":"+1 248 643 0021",
    "sg:postcode":"48084",
    "sg:province":"MI",
    "sg:tags":[
        "broker",
        "mortgage"
    ],
    "sg:website":"www.lasallebank.com",
    "wof:name":"Bank of America",
    "wof:placetype":"venue"
},
  "geometry": {"coordinates":[-83.18407500000001,42.547643],"type":"Point"}
}