{
  "type": "Feature",
  "properties": {
    "iso:country":"US",
    "sg:address":"37339 Calka Dr",
    "sg:city":"Sterling Heights",
    "sg:classifiers":[
        {
            "category":"Organizations",
            "subcategory":"Community Association",
            "type":"Services"
        }
    ],
    "sg:phone":"+1 586 979 8167",
    "sg:postcode":"48310",
    "sg:province":"MI",
    "wof:name":"Awana Clubs International",
    "wof:placetype":"venue"
},
  "geometry": {"coordinates":[-83.08151700000001,42.568963],"type":"Point"}
}