{
  "type": "Feature",
  "properties": {
    "iso:country":"US",
    "sg:address":"8948 Trezwood Ter",
    "sg:city":"Traverse City",
    "sg:classifiers":[
        {
            "category":"Retail",
            "subcategory":"Repair Shop",
            "type":"Services"
        }
    ],
    "sg:phone":"+1 231 943 3455",
    "sg:postcode":"49684",
    "sg:province":"MI",
    "sg:tags":[
        "upholstery",
        "work"
    ],
    "wof:name":"Neuco Seating Inc",
    "wof:placetype":"venue"
},
  "geometry": {"coordinates":[-85.75573199999999,44.682296],"type":"Point"}
}