{
  "type": "Feature",
  "properties": {
    "iso:country":"US",
    "sg:address":"11942 Scott Rd",
    "sg:city":"Davisburg",
    "sg:classifiers":[
        {
            "category":"Professional",
            "subcategory":"Art Services",
            "type":"Services"
        }
    ],
    "sg:phone":"+1 248 634 3699",
    "sg:postcode":"48350",
    "sg:province":"MI",
    "sg:tags":[
        "commercial",
        "design"
    ],
    "wof:name":"Tobias Design",
    "wof:placetype":"venue"
},
  "geometry": {"coordinates":[-83.526493,42.732695],"type":"Point"}
}