{
  "type": "Feature",
  "properties": {
    "iso:country":"US",
    "sg:address":"23262 John R Rd",
    "sg:city":"Hazel Park",
    "sg:classifiers":[
        {
            "category":"Organizations",
            "subcategory":"Community Association",
            "type":"Services"
        }
    ],
    "sg:phone":"+1 248 988 1336",
    "sg:postcode":"48030",
    "sg:province":"MI",
    "sg:tags":[
        "club"
    ],
    "wof:name":"Wolverine Sports Club",
    "wof:placetype":"venue"
},
  "geometry": {"coordinates":[-83.10396,42.461694],"type":"Point"}
}