{
  "type": "Feature",
  "properties": {
    "iso:country":"US",
    "sg:address":"1819 E Big Beaver Rd",
    "sg:city":"Troy",
    "sg:classifiers":[
        {
            "category":"Shopping",
            "subcategory":"Bicycles & Sporting Goods",
            "type":"Retail Goods"
        }
    ],
    "sg:phone":"+1 248 526 7941",
    "sg:postcode":"48083",
    "sg:province":"MI",
    "wof:name":"B & R Sporting Goods II",
    "wof:placetype":"venue"
},
  "geometry": {"coordinates":[-83.111198,42.563702],"type":"Point"}
}