{
  "type": "Feature",
  "properties": {
    "iso:country":"US",
    "sg:address":"35531 Cherry Hill Rd",
    "sg:city":"Westland",
    "sg:classifiers":[
        {
            "category":"Personal",
            "subcategory":"Barber",
            "type":"Services"
        }
    ],
    "sg:phone":"+1 734 722 0150",
    "sg:postcode":"48186",
    "sg:province":"MI",
    "sg:tags":[
        "shop"
    ],
    "wof:name":"Cher Way Barber Shop",
    "wof:placetype":"venue"
},
  "geometry": {"coordinates":[-83.390811,42.309846],"type":"Point"}
}