{
  "type": "Feature",
  "properties": {
    "iso:country":"US",
    "sg:address":"4050 W Maple Rd Ste 201",
    "sg:city":"Bloomfield Hills",
    "sg:classifiers":[
        {
            "category":"Health Services",
            "subcategory":"Dentist",
            "type":"Services"
        }
    ],
    "sg:phone":"+1 248 646 4002",
    "sg:postcode":"48301",
    "sg:province":"MI",
    "sg:tags":[
        "orthodontist"
    ],
    "sg:website":"www.mapleorthodontics.com",
    "wof:name":"Maple Orthodontics Pllc",
    "wof:placetype":"venue"
},
  "geometry": {"coordinates":[-83.281063,42.545027],"type":"Point"}
}