{
  "type": "Feature",
  "properties": {
    "iso:country":"US",
    "sg:address":"134 Petrie Rd",
    "sg:city":"Cadillac",
    "sg:classifiers":[
        {
            "category":"Organizations",
            "subcategory":"Membership Organization",
            "type":"Services"
        }
    ],
    "sg:phone":"+1 231 775 8896",
    "sg:postcode":"49601",
    "sg:province":"MI",
    "wof:name":"South Shore Improvement Corp",
    "wof:placetype":"venue"
},
  "geometry": {"coordinates":[-85.418256,44.234926],"type":"Point"}
}