{
  "type": "Feature",
  "properties": {
    "iso:country":"US",
    "sg:address":"1441 Saint Antoine St",
    "sg:city":"Detroit",
    "sg:classifiers":[
        {
            "category":"Government",
            "subcategory":"Office",
            "type":"Public Place"
        }
    ],
    "sg:phone":"+1 313 224 2525",
    "sg:postcode":"48226",
    "sg:province":"MI",
    "sg:tags":[
        "recorder",
        "tax"
    ],
    "wof:name":"Tax Recorders Office",
    "wof:placetype":"venue"
},
  "geometry": {"coordinates":[-83.04227,42.337323],"type":"Point"}
}