{
  "type": "Feature",
  "properties": {
    "iso:country":"US",
    "sg:address":"2373 Marsh St",
    "sg:city":"Bitely",
    "sg:classifiers":[
        {
            "category":"Health Services",
            "subcategory":"Hospital",
            "type":"Services"
        },
        {
            "category":"Health Services",
            "subcategory":"Clinic",
            "type":"Services"
        }
    ],
    "sg:phone":"+1 231 745 9119",
    "sg:postcode":"49309",
    "sg:province":"MI",
    "sg:tags":[
        "medical",
        "squad",
        "rescue",
        "emergency",
        "surgical"
    ],
    "wof:name":"Lilley-Merrill Rescue Inc",
    "wof:placetype":"venue"
},
  "geometry": {"coordinates":[-85.85932,43.749073],"type":"Point"}
}