{
  "type": "Feature",
  "properties": {
    "iso:country":"US",
    "sg:address":"6672 E Weston Rd",
    "sg:city":"Blissfield",
    "sg:phone":"+1 517 443 5814",
    "sg:postcode":"49228",
    "sg:province":"MI",
    "sg:tags":[
        "farm",
        "grain",
        "cash"
    ],
    "wof:name":"Mark Vandenbusche",
    "wof:placetype":"venue"
},
  "geometry": {"coordinates":[-83.93700800000001,41.772315],"type":"Point"}
}