{
  "type": "Feature",
  "properties": {
    "iso:country":"US",
    "sg:address":"242 John R St",
    "sg:city":"Detroit",
    "sg:classifiers":[
        {
            "category":"Restaurant",
            "type":"Food & Drink"
        }
    ],
    "sg:phone":"+1 313 964 0934",
    "sg:postcode":"48226",
    "sg:province":"MI",
    "wof:name":"Harmonie Cafe",
    "wof:placetype":"venue"
},
  "geometry": {"coordinates":[-83.04769899999999,42.336399],"type":"Point"}
}