{
  "type": "Feature",
  "properties": {
    "iso:country":"US",
    "sg:address":"3501 Lake Eastbrook Blvd SE",
    "sg:city":"Grand Rapids",
    "sg:classifiers":[
        {
            "category":"Banks & Credit Unions",
            "subcategory":"Bank",
            "type":"Services"
        }
    ],
    "sg:phone":"+1 616 975 7550",
    "sg:postcode":"49546",
    "sg:province":"MI",
    "sg:tags":[
        "loan",
        "real estate"
    ],
    "wof:name":"Premier Mortgage Funding",
    "wof:placetype":"venue"
},
  "geometry": {"coordinates":[-85.58004,42.917736],"type":"Point"}
}