{
  "type": "Feature",
  "properties": {
    "iso:country":"US",
    "sg:address":"11055 Allen Rd",
    "sg:city":"Southgate",
    "sg:classifiers":[
        {
            "category":"Food & Beverages",
            "subcategory":"Farmers Market",
            "type":"Retail Goods"
        }
    ],
    "sg:phone":"+1 734 287 8807",
    "sg:postcode":"48195",
    "sg:province":"MI",
    "wof:name":"Trentwood Farms",
    "wof:placetype":"venue"
},
  "geometry": {"coordinates":[-83.228802,42.227009],"type":"Point"}
}