{
  "type": "Feature",
  "properties": {
    "iso:country":"US",
    "sg:address":"32303 Howard Ave",
    "sg:city":"Madison Heights",
    "sg:classifiers":[
        {
            "category":"Manufacturing",
            "subcategory":"Tools & Machinery",
            "type":"Manufacturing & Wholesale Goods"
        }
    ],
    "sg:phone":"+1 248 588 2669",
    "sg:postcode":"48071",
    "sg:province":"MI",
    "sg:tags":[
        "pattern",
        "maker"
    ],
    "wof:name":"Cobra Patterns & Models Inc",
    "wof:placetype":"venue"
},
  "geometry": {"coordinates":[-83.09952800000001,42.530642],"type":"Point"}
}