{
  "type": "Feature",
  "properties": {
    "iso:country":"US",
    "sg:address":"5022 Pine Knob Ln",
    "sg:city":"Clarkston",
    "sg:classifiers":[
        {
            "category":"Home & Garden",
            "subcategory":"Building Materials",
            "type":"Retail Goods"
        },
        {
            "category":"Manufacturing",
            "subcategory":"Building Materials",
            "type":"Manufacturing & Wholesale Goods"
        }
    ],
    "sg:phone":"+1 248 674 2061",
    "sg:postcode":"48346",
    "sg:province":"MI",
    "sg:tags":[
        "wood",
        "cabinet",
        "door",
        "kitchen",
        "mfg"
    ],
    "wof:name":"Pontiac Overhead Door Company",
    "wof:placetype":"venue"
},
  "geometry": {"coordinates":[-83.35875799999999,42.710521],"type":"Point"}
}