{
  "type": "Feature",
  "properties": {
    "iso:country":"US",
    "sg:address":"2927 Millcork St",
    "sg:city":"Kalamazoo",
    "sg:classifiers":[
        {
            "category":"Wholesale",
            "subcategory":"Construction Materials",
            "type":"Manufacturing & Wholesale Goods"
        }
    ],
    "sg:phone":"+1 269 349 6978",
    "sg:postcode":"49001",
    "sg:province":"MI",
    "sg:tags":[
        "equipment",
        "roofing",
        "supply"
    ],
    "sg:website":"www.abcsupply.com",
    "wof:name":"ABC Supply Co",
    "wof:placetype":"venue"
},
  "geometry": {"coordinates":[-85.53815400000001,42.2618],"type":"Point"}
}