{
  "type": "Feature",
  "properties": {
    "iso:country":"US",
    "sg:address":"307 Arthur St",
    "sg:city":"Albion",
    "sg:classifiers":[
        {
            "category":"Shopping",
            "subcategory":"Gifts & Souvenirs",
            "type":"Retail Goods"
        }
    ],
    "sg:phone":"+1 517 629 4526",
    "sg:postcode":"49224",
    "sg:province":"MI",
    "wof:name":"Gifts & More",
    "wof:placetype":"venue"
},
  "geometry": {"coordinates":[-84.75765,42.252607],"type":"Point"}
}