{
  "type": "Feature",
  "properties": {
    "iso:country":"US",
    "sg:address":"9339 Gera Rd",
    "sg:city":"Birch Run",
    "sg:classifiers":[
        {
            "category":"Retail",
            "subcategory":"Veterinary Services",
            "type":"Services"
        }
    ],
    "sg:phone":"+1 989 652 6689",
    "sg:postcode":"48415",
    "sg:province":"MI",
    "sg:tags":[
        "veterinarian"
    ],
    "wof:name":"Frankenmuth-Birch Run Vet Hosp",
    "wof:placetype":"venue"
},
  "geometry": {"coordinates":[-83.73534100000001,43.28781],"type":"Point"}
}