{
  "type": "Feature",
  "properties": {
    "iso:country":"US",
    "sg:address":"3920 Lake Taho Trl",
    "sg:city":"Lake",
    "sg:classifiers":[
        {
            "category":"Shopping",
            "subcategory":"Computers & Home Electronics",
            "type":"Retail Goods"
        }
    ],
    "sg:phone":"+1 989 588 4681",
    "sg:postcode":"48632",
    "sg:province":"MI",
    "wof:name":"Mid-State Computers",
    "wof:placetype":"venue"
},
  "geometry": {"coordinates":[-85.040164,43.937748],"type":"Point"}
}