{
  "type": "Feature",
  "properties": {
    "iso:country":"US",
    "sg:address":"4762 Old Mill Rd",
    "sg:city":"Traverse City",
    "sg:classifiers":[
        {
            "category":"Building & Trades",
            "subcategory":"Construction",
            "type":"Services"
        }
    ],
    "sg:phone":"+1 231 929 3660",
    "sg:postcode":"49684",
    "sg:province":"MI",
    "sg:tags":[
        "marking",
        "maintenance",
        "parking"
    ],
    "wof:name":"Black Magic Asphalt Sealing",
    "wof:placetype":"venue"
},
  "geometry": {"coordinates":[-85.76017899999999,44.758679],"type":"Point"}
}