{
  "type": "Feature",
  "properties": {
    "iso:country":"US",
    "sg:address":"971 Baldwin Rd",
    "sg:city":"Lapeer",
    "sg:classifiers":[
        {
            "category":"Health Services",
            "subcategory":"Doctor",
            "type":"Services"
        }
    ],
    "sg:phone":"+1 810 667 3811",
    "sg:postcode":"48446",
    "sg:province":"MI",
    "sg:tags":[
        "physician",
        "surgeon"
    ],
    "wof:name":"Selimul Haque MD",
    "wof:placetype":"venue"
},
  "geometry": {"coordinates":[-83.325332,43.035455],"type":"Point"}
}