{
  "type": "Feature",
  "properties": {
    "iso:country":"US",
    "sg:address":"751 N Morrison Rd",
    "sg:city":"West Branch",
    "sg:classifiers":[
        {
            "category":"Professional",
            "type":"Services"
        }
    ],
    "sg:phone":"+1 989 685 2894",
    "sg:postcode":"48661",
    "sg:province":"MI",
    "sg:tags":[
        "establishment"
    ],
    "wof:name":"Cummings Twp",
    "wof:placetype":"venue"
},
  "geometry": {"coordinates":[-84.10597,44.361438],"type":"Point"}
}