{
  "type": "Feature",
  "properties": {
    "iso:country":"US",
    "sg:address":"6466 Van Dyke Rd",
    "sg:city":"Cass City",
    "sg:classifiers":[
        {
            "category":"Retail",
            "subcategory":"Repair Shop",
            "type":"Services"
        }
    ],
    "sg:phone":"+1 989 872 4077",
    "sg:postcode":"48726",
    "sg:province":"MI",
    "sg:tags":[
        "scooter",
        "motorcycle",
        "motor"
    ],
    "sg:website":"www.thumbmotorsports.com",
    "wof:name":"Thumb Motorsports",
    "wof:placetype":"venue"
},
  "geometry": {"coordinates":[-83.096542,43.593273],"type":"Point"}
}