{
  "type": "Feature",
  "properties": {
    "iso:country":"US",
    "sg:address":"2234 N Moore Rd",
    "sg:city":"Elkton",
    "sg:classifiers":[
        {
            "category":"Professional",
            "subcategory":"Business Services",
            "type":"Services"
        }
    ],
    "sg:phone":"+1 989 375 2724",
    "sg:postcode":"48731",
    "sg:province":"MI",
    "wof:name":"Thumb Home Inspections",
    "wof:placetype":"venue"
},
  "geometry": {"coordinates":[-83.141401,43.850411],"type":"Point"}
}