{
  "type": "Feature",
  "properties": {
    "iso:country":"US",
    "sg:address":"42030 Koppernick Rd",
    "sg:city":"Canton",
    "sg:classifiers":[
        {
            "category":"Manufacturing",
            "subcategory":"Textiles",
            "type":"Manufacturing & Wholesale Goods"
        }
    ],
    "sg:phone":"+1 734 207 0759",
    "sg:postcode":"48187",
    "sg:province":"MI",
    "sg:tags":[
        "finishing",
        "plant",
        "cotton"
    ],
    "wof:name":"Screened Images Inc",
    "wof:placetype":"venue"
},
  "geometry": {"coordinates":[-83.45626,42.340989],"type":"Point"}
}