{
  "type": "Feature",
  "properties": {
    "iso:country":"US",
    "sg:address":"292 S Fremont Rd",
    "sg:city":"Coldwater",
    "sg:classifiers":[
        {
            "category":"Autos & Motor Vehicles",
            "subcategory":"Boat Sales",
            "type":"Retail Goods"
        }
    ],
    "sg:phone":"+1 517 238 5955",
    "sg:postcode":"49036",
    "sg:province":"MI",
    "sg:tags":[
        "dealer",
        "sales"
    ],
    "wof:name":"Hildebrands Sea Doo Repair",
    "wof:placetype":"venue"
},
  "geometry": {"coordinates":[-84.93192999999999,41.869775],"type":"Point"}
}