{
  "type": "Feature",
  "properties": {
    "iso:country":"US",
    "sg:address":"11019 Morang Dr",
    "sg:city":"Detroit",
    "sg:classifiers":[
        {
            "category":"Autos & Motor Vehicles",
            "subcategory":"Automobile Sales",
            "type":"Retail Goods"
        },
        {
            "category":"Personal",
            "type":"Services"
        },
        {
            "category":"Building & Trades",
            "subcategory":"Locksmith",
            "type":"Services"
        }
    ],
    "sg:phone":"+1 313 640 9342",
    "sg:postcode":"48224",
    "sg:province":"MI",
    "sg:tags":[
        "lock",
        "towing",
        "salvage"
    ],
    "wof:name":"End Time Towing",
    "wof:placetype":"venue"
},
  "geometry": {"coordinates":[-82.941903,42.422819],"type":"Point"}
}