{
  "type": "Feature",
  "properties": {
    "iso:country":"US",
    "sg:address":"930 E M-134",
    "sg:city":"Cedarville",
    "sg:classifiers":[
        {
            "category":"Travel",
            "subcategory":"Hotels & Motels",
            "type":"Entertainment"
        }
    ],
    "sg:phone":"+1 906 484 2252",
    "sg:postcode":"49719",
    "sg:province":"MI",
    "sg:tags":[
        "resort"
    ],
    "wof:name":"Island View Resort Inc",
    "wof:placetype":"venue"
},
  "geometry": {"coordinates":[-84.343493,45.999627],"type":"Point"}
}