{
  "type": "Feature",
  "properties": {
    "iso:country":"US",
    "sg:address":"15490 Haggerty Rd",
    "sg:city":"Belleville",
    "sg:classifiers":[
        {
            "category":"Building & Trades",
            "subcategory":"Landscaping Services",
            "type":"Services"
        }
    ],
    "sg:phone":"+1 734 699 4399",
    "sg:postcode":"48111",
    "sg:province":"MI",
    "wof:name":"Wieses Lawn Care",
    "wof:placetype":"venue"
},
  "geometry": {"coordinates":[-83.438958,42.18835],"type":"Point"}
}