{
  "type": "Feature",
  "properties": {
    "iso:country":"US",
    "sg:address":"2789 Mac Duff Ct",
    "sg:city":"Highland",
    "sg:classifiers":[
        {
            "category":"Building & Trades",
            "subcategory":"Construction",
            "type":"Services"
        }
    ],
    "sg:phone":"+1 248 361 3554",
    "sg:postcode":"48357",
    "sg:province":"MI",
    "sg:tags":[
        "contractor"
    ],
    "wof:name":"Evolved Foundation",
    "wof:placetype":"venue"
},
  "geometry": {"coordinates":[-83.622417,42.665678],"type":"Point"}
}