{
  "type": "Feature",
  "properties": {
    "iso:country":"US",
    "sg:address":"6133 Leroux Rd",
    "sg:city":"Newport",
    "sg:classifiers":[
        {
            "category":"Manufacturing",
            "subcategory":"Tools & Machinery",
            "type":"Manufacturing & Wholesale Goods"
        }
    ],
    "sg:phone":"+1 734 586 2183",
    "sg:postcode":"48166",
    "sg:province":"MI",
    "sg:tags":[
        "machine",
        "shop"
    ],
    "wof:name":"Ellison Machine & Fabricating",
    "wof:placetype":"venue"
},
  "geometry": {"coordinates":[-83.287441,41.962951],"type":"Point"}
}