{
  "type": "Feature",
  "properties": {
    "iso:country":"US",
    "sg:address":"17100 Silver Pkwy",
    "sg:city":"Fenton",
    "sg:classifiers":[
        {
            "category":"Professional",
            "subcategory":"Lawyer & Legal Services",
            "type":"Services"
        }
    ],
    "sg:phone":"+1 810 750 0440",
    "sg:postcode":"48430",
    "sg:province":"MI",
    "sg:tags":[
        "attorney"
    ],
    "wof:name":"Joseph J Abraham PC",
    "wof:placetype":"venue"
},
  "geometry": {"coordinates":[-83.736073,42.796909],"type":"Point"}
}