{
  "type": "Feature",
  "properties": {
    "iso:country":"US",
    "sg:address":"3617 Division Ave S",
    "sg:city":"Grand Rapids",
    "sg:classifiers":[
        {
            "category":"Shopping",
            "subcategory":"Jewelry",
            "type":"Retail Goods"
        }
    ],
    "sg:phone":"+1 616 243 4941",
    "sg:postcode":"49548",
    "sg:province":"MI",
    "wof:name":"KB Jewelers",
    "wof:placetype":"venue"
},
  "geometry": {"coordinates":[-85.665378,42.898186],"type":"Point"}
}