{
  "type": "Feature",
  "properties": {
    "iso:country":"US",
    "sg:address":"3154 Quinnesec Lake Antoine Rd",
    "sg:city":"Iron Mountain",
    "sg:classifiers":[
        {
            "category":"Building & Trades",
            "subcategory":"Plumbing",
            "type":"Services"
        }
    ],
    "sg:phone":"+1 906 776 1195",
    "sg:postcode":"49801",
    "sg:province":"MI",
    "sg:tags":[
        "conditioning",
        "air",
        "system",
        "contractor"
    ],
    "wof:name":"BMS Heating & Cooling",
    "wof:placetype":"venue"
},
  "geometry": {"coordinates":[-88.00191599999999,45.831405],"type":"Point"}
}