{
  "type": "Feature",
  "properties": {
    "iso:country":"US",
    "sg:address":"26637 W Carnegie Park Dr",
    "sg:city":"Southfield",
    "sg:classifiers":[
        {
            "category":"Food & Beverages",
            "subcategory":"Ethnic Foods",
            "type":"Retail Goods"
        }
    ],
    "sg:phone":"+1 248 996 8616",
    "sg:postcode":"48034",
    "sg:province":"MI",
    "sg:tags":[
        "soul"
    ],
    "wof:name":"Annette's Soul Food",
    "wof:placetype":"venue"
},
  "geometry": {"coordinates":[-83.307419,42.486887],"type":"Point"}
}