{
  "type": "Feature",
  "properties": {
    "iso:country":"US",
    "sg:address":"921 E State St",
    "sg:city":"Hastings",
    "sg:classifiers":[
        {
            "category":"Freight",
            "type":"Transportation"
        }
    ],
    "sg:phone":"+1 269 948 2930",
    "sg:postcode":"49058",
    "sg:province":"MI",
    "sg:tags":[
        "warehouse"
    ],
    "wof:name":"Flexfab Warehouse",
    "wof:placetype":"venue"
},
  "geometry": {"coordinates":[-85.27367700000001,42.642116],"type":"Point"}
}