{
  "type": "Feature",
  "properties": {
    "iso:country":"US",
    "sg:address":"5890 Winans View Ct",
    "sg:city":"Pinckney",
    "sg:classifiers":[
        {
            "category":"Professional",
            "subcategory":"Business Services",
            "type":"Services"
        }
    ],
    "sg:phone":"+1 810 231 6561",
    "sg:postcode":"48169",
    "sg:province":"MI",
    "wof:name":"Denby Enterprises",
    "wof:placetype":"venue"
},
  "geometry": {"coordinates":[-83.832908,42.480737],"type":"Point"}
}