{
  "type": "Feature",
  "properties": {
    "iso:country":"US",
    "sg:address":"3500 S Wacousta Rd",
    "sg:city":"Saint Johns",
    "sg:phone":"+1 989 593 3364",
    "sg:postcode":"48879",
    "sg:province":"MI",
    "sg:tags":[
        "farm",
        "soybean"
    ],
    "wof:name":"Kenneth Miller",
    "wof:placetype":"venue"
},
  "geometry": {"coordinates":[-84.700244,42.964743],"type":"Point"}
}