{
  "type": "Feature",
  "properties": {
    "iso:country":"US",
    "sg:address":"25920 Greenfield Rd",
    "sg:city":"Oak Park",
    "sg:classifiers":[
        {
            "category":"Restaurant",
            "type":"Food & Drink"
        }
    ],
    "sg:phone":"+1 248 968 4060",
    "sg:postcode":"48237",
    "sg:province":"MI",
    "sg:tags":[
        "new",
        "american",
        "diner"
    ],
    "wof:name":"Eddie's Gourmet",
    "wof:placetype":"venue"
},
  "geometry": {"coordinates":[-83.201797,42.480801],"type":"Point"}
}