{
  "type": "Feature",
  "properties": {
    "iso:country":"US",
    "sg:address":"4225 Michelle Ct",
    "sg:city":"Walled Lake",
    "sg:classifiers":[
        {
            "category":"Professional",
            "subcategory":"Management & Consulting",
            "type":"Services"
        }
    ],
    "sg:phone":"+1 248 624 1833",
    "sg:postcode":"48390",
    "sg:province":"MI",
    "sg:tags":[
        "public",
        "relations"
    ],
    "wof:name":"Paramount Public Relations",
    "wof:placetype":"venue"
},
  "geometry": {"coordinates":[-83.45731499999999,42.57178],"type":"Point"}
}