{
  "type": "Feature",
  "properties": {
    "iso:country":"US",
    "sg:address":"3379 Main St",
    "sg:city":"Marlette",
    "sg:classifiers":[
        {
            "category":"Personal",
            "subcategory":"Beauty Salon",
            "type":"Services"
        }
    ],
    "sg:phone":"+1 989 635 2200",
    "sg:postcode":"48453",
    "sg:province":"MI",
    "sg:tags":[
        "shop"
    ],
    "wof:name":"Hair Center The",
    "wof:placetype":"venue"
},
  "geometry": {"coordinates":[-83.079769,43.321503],"type":"Point"}
}