{
  "type": "Feature",
  "properties": {
    "iso:country":"US",
    "sg:address":"111 N Davenport St",
    "sg:city":"Saline",
    "sg:classifiers":[
        {
            "category":"Social Services",
            "subcategory":"Child Care",
            "type":"Services"
        }
    ],
    "sg:phone":"+1 734 429 4428",
    "sg:postcode":"48176",
    "sg:province":"MI",
    "sg:tags":[
        "day"
    ],
    "wof:name":"Riveroaks Day Care Center",
    "wof:placetype":"venue"
},
  "geometry": {"coordinates":[-83.778029,42.170377],"type":"Point"}
}