{
  "type": "Feature",
  "properties": {
    "iso:country":"US",
    "sg:address":"1509 Nickleplate Rd",
    "sg:city":"Ionia",
    "sg:classifiers":[
        {
            "category":"Farming",
            "subcategory":"Farm",
            "type":"Manufacturing & Wholesale Goods"
        }
    ],
    "sg:phone":"+1 616 527 1192",
    "sg:postcode":"48846",
    "sg:province":"MI",
    "wof:name":"Nickle Plate Farm",
    "wof:placetype":"venue"
},
  "geometry": {"coordinates":[-85.043648,43.032518],"type":"Point"}
}