{
  "type": "Feature",
  "properties": {
    "iso:country":"US",
    "sg:address":"121 E Elizabeth St",
    "sg:city":"Stockbridge",
    "sg:classifiers":[
        {
            "category":"Retail",
            "subcategory":"Auto Repair",
            "type":"Services"
        }
    ],
    "sg:phone":"+1 517 851 7047",
    "sg:postcode":"49285",
    "sg:province":"MI",
    "sg:tags":[
        "automotive",
        "general"
    ],
    "wof:name":"Stockbridge Auto Care Inc",
    "wof:placetype":"venue"
},
  "geometry": {"coordinates":[-84.179104,42.450107],"type":"Point"}
}