{
  "type": "Feature",
  "properties": {
    "iso:country":"US",
    "sg:address":"2937 Leslie St",
    "sg:city":"Detroit",
    "sg:classifiers":[
        {
            "category":"Professional",
            "subcategory":"Business Services",
            "type":"Services"
        }
    ],
    "sg:phone":"+1 313 868 0615",
    "sg:postcode":"48238",
    "sg:province":"MI",
    "wof:name":"Stevens Management Inc",
    "wof:placetype":"venue"
},
  "geometry": {"coordinates":[-83.124703,42.387395],"type":"Point"}
}