{
  "type": "Feature",
  "properties": {
    "iso:country":"US",
    "sg:address":"7250 Gale Rd",
    "sg:city":"Grand Blanc",
    "sg:classifiers":[
        {
            "category":"Building & Trades",
            "subcategory":"Construction",
            "type":"Services"
        }
    ],
    "sg:phone":"+1 810 636 6111",
    "sg:postcode":"48439",
    "sg:province":"MI",
    "sg:tags":[
        "contractor"
    ],
    "wof:name":"Rooney Construction",
    "wof:placetype":"venue"
},
  "geometry": {"coordinates":[-83.534103,42.934799],"type":"Point"}
}