{
  "type": "Feature",
  "properties": {
    "iso:country":"US",
    "sg:address":"5470 Sheridan Rd",
    "sg:city":"Flushing",
    "sg:classifiers":[
        {
            "category":"Retail",
            "subcategory":"Repair Shop",
            "type":"Services"
        }
    ],
    "sg:phone":"+1 810 659 5946",
    "sg:postcode":"48433",
    "sg:province":"MI",
    "sg:tags":[
        "welding"
    ],
    "wof:name":"Ben S Heavy Equiptment",
    "wof:placetype":"venue"
},
  "geometry": {"coordinates":[-83.928647,43.080776],"type":"Point"}
}