{
  "type": "Feature",
  "properties": {
    "iso:country":"US",
    "sg:address":"3816 Milan Ave SW",
    "sg:city":"Grand Rapids",
    "sg:classifiers":[
        {
            "category":"Social Services",
            "subcategory":"Child Care",
            "type":"Services"
        }
    ],
    "sg:phone":"+1 616 532 5325",
    "sg:postcode":"49509",
    "sg:province":"MI",
    "sg:tags":[
        "day"
    ],
    "wof:name":"Jackies Day Care",
    "wof:placetype":"venue"
},
  "geometry": {"coordinates":[-85.694074,42.891768],"type":"Point"}
}