{
  "type": "Feature",
  "properties": {
    "iso:country":"US",
    "sg:address":"1300 W Washington Ave",
    "sg:city":"Alpena",
    "sg:classifiers":[
        {
            "category":"Real Estate",
            "subcategory":"Developer",
            "type":"Services"
        }
    ],
    "sg:phone":"+1 989 354 3831",
    "sg:postcode":"49707",
    "sg:province":"MI",
    "sg:tags":[
        "cemetery"
    ],
    "wof:name":"Holy Cross Cemetery",
    "wof:placetype":"venue"
},
  "geometry": {"coordinates":[-83.463212,45.06125],"type":"Point"}
}