{
  "type": "Feature",
  "properties": {
    "iso:country":"US",
    "sg:address":"17 Burt Ave SE",
    "sg:city":"Grand Rapids",
    "sg:classifiers":[
        {
            "category":"Retail",
            "subcategory":"Car Wash",
            "type":"Services"
        }
    ],
    "sg:phone":"+1 616 261 0006",
    "sg:postcode":"49548",
    "sg:province":"MI",
    "sg:tags":[
        "automobile",
        "detail",
        "clean"
    ],
    "wof:name":"Appearance Auto Detailing",
    "wof:placetype":"venue"
},
  "geometry": {"coordinates":[-85.661068,42.890866],"type":"Point"}
}