{
  "type": "Feature",
  "properties": {
    "iso:country":"US",
    "sg:address":"6161 Orchard Lake Rd",
    "sg:city":"West Bloomfield",
    "sg:classifiers":[
        {
            "category":"Health Services",
            "subcategory":"Doctor",
            "type":"Services"
        }
    ],
    "sg:phone":"+1 248 737 3370",
    "sg:postcode":"48322",
    "sg:province":"MI",
    "wof:name":"Boodin Stephen E MD",
    "wof:placetype":"venue"
},
  "geometry": {"coordinates":[-83.360901,42.547401],"type":"Point"}
}