{
  "type": "Feature",
  "properties": {
    "iso:country":"US",
    "sg:address":"2021 Shepherds Dr",
    "sg:city":"Troy",
    "sg:classifiers":[
        {
            "category":"Professional",
            "subcategory":"Management & Consulting",
            "type":"Services"
        }
    ],
    "sg:phone":"+1 248 396 7302",
    "sg:postcode":"48084",
    "sg:province":"MI",
    "sg:tags":[
        "training",
        "microsoft"
    ],
    "wof:name":"Krell Labs",
    "wof:placetype":"venue"
},
  "geometry": {"coordinates":[-83.151456,42.551765],"type":"Point"}
}