{
  "type": "Feature",
  "properties": {
    "iso:country":"US",
    "sg:address":"29832 Palomino Dr",
    "sg:city":"Warren",
    "sg:classifiers":[
        {
            "category":"Personal",
            "subcategory":"Beauty Salon",
            "type":"Services"
        }
    ],
    "sg:phone":"+1 586 582 9457",
    "sg:postcode":"48093",
    "sg:province":"MI",
    "sg:tags":[
        "shop"
    ],
    "wof:name":"All About Nails",
    "wof:placetype":"venue"
},
  "geometry": {"coordinates":[-82.99813899999999,42.512001],"type":"Point"}
}