{
  "type": "Feature",
  "properties": {
    "iso:country":"US",
    "sg:address":"2640 Peck St",
    "sg:city":"Muskegon",
    "sg:classifiers":[
        {
            "category":"Organizations",
            "subcategory":"Religious Organization",
            "type":"Services"
        }
    ],
    "sg:phone":"+1 231 739 5371",
    "sg:postcode":"49444",
    "sg:province":"MI",
    "sg:tags":[
        "church"
    ],
    "wof:name":"House Of Judah Fgbc",
    "wof:placetype":"venue"
},
  "geometry": {"coordinates":[-86.24458300000001,43.203893],"type":"Point"}
}