{
  "type": "Feature",
  "properties": {
    "iso:country":"US",
    "sg:address":"16357 Carol St",
    "sg:city":"Spring Lake",
    "sg:classifiers":[
        {
            "category":"Professional",
            "subcategory":"Computer Services",
            "type":"Services"
        }
    ],
    "sg:phone":"+1 616 402 0025",
    "sg:postcode":"49456",
    "sg:province":"MI",
    "sg:tags":[
        "website",
        "development"
    ],
    "wof:name":"Jeoworks LLC",
    "wof:placetype":"venue"
},
  "geometry": {"coordinates":[-86.16763,43.065433],"type":"Point"}
}