{
  "type": "Feature",
  "properties": {
    "iso:country":"US",
    "sg:address":"17660 Westbrook Dr",
    "sg:city":"Casnovia",
    "sg:classifiers":[
        {
            "category":"Farming",
            "subcategory":"Farm",
            "type":"Manufacturing & Wholesale Goods"
        }
    ],
    "sg:phone":"+1 616 675 4115",
    "sg:postcode":"49318",
    "sg:province":"MI",
    "sg:tags":[
        "crop",
        "general"
    ],
    "wof:name":"Humprey Hap",
    "wof:placetype":"venue"
},
  "geometry": {"coordinates":[-85.809607,43.253336],"type":"Point"}
}