{
  "type": "Feature",
  "properties": {
    "iso:country":"US",
    "sg:address":"334 S Shepherd Rd",
    "sg:city":"Mount Pleasant",
    "sg:classifiers":[
        {
            "category":"Social Services",
            "subcategory":"Child Care",
            "type":"Services"
        }
    ],
    "sg:phone":"+1 989 772 2298",
    "sg:postcode":"48858",
    "sg:province":"MI",
    "sg:tags":[
        "day"
    ],
    "wof:name":"Tammys Daycare",
    "wof:placetype":"venue"
},
  "geometry": {"coordinates":[-84.688181,43.637065],"type":"Point"}
}