{
  "type": "Feature",
  "properties": {
    "iso:country":"US",
    "sg:address":"12020 M 216",
    "sg:city":"Marcellus",
    "sg:classifiers":[
        {
            "category":"Government",
            "subcategory":"Office",
            "type":"Public Place"
        }
    ],
    "sg:phone":"+1 269 646 9121",
    "sg:postcode":"49067",
    "sg:province":"MI",
    "sg:tags":[
        "village"
    ],
    "wof:name":"Flowerfield Township Hall",
    "wof:placetype":"venue"
},
  "geometry": {"coordinates":[-85.71859000000001,42.025099],"type":"Point"}
}