{
  "type": "Feature",
  "properties": {
    "iso:country":"US",
    "sg:address":"165 Division St",
    "sg:city":"Freeport",
    "sg:classifiers":[
        {
            "category":"Banks & Credit Unions",
            "subcategory":"Bank",
            "type":"Services"
        }
    ],
    "sg:phone":"+1 616 765 3100",
    "sg:postcode":"49325",
    "sg:province":"MI",
    "wof:name":"Union Bank",
    "wof:placetype":"venue"
},
  "geometry": {"coordinates":[-85.31509800000001,42.766074],"type":"Point"}
}