{
  "type": "Feature",
  "properties": {
    "iso:country":"US",
    "sg:address":"9191 Coleman Rd",
    "sg:city":"Haslett",
    "sg:classifiers":[
        {
            "category":"Social Services",
            "subcategory":"Child Care",
            "type":"Services"
        }
    ],
    "sg:phone":"+1 517 339 9478",
    "sg:postcode":"48840",
    "sg:province":"MI",
    "sg:tags":[
        "day",
        "provider"
    ],
    "wof:name":"Sue Dalman",
    "wof:placetype":"venue"
},
  "geometry": {"coordinates":[-84.375366,42.771171],"type":"Point"}
}