{
  "type": "Feature",
  "properties": {
    "iso:country":"US",
    "sg:address":"16566 Manitou Beach Rd",
    "sg:city":"Addison",
    "sg:classifiers":[
        {
            "category":"Professional",
            "subcategory":"Engineering",
            "type":"Services"
        }
    ],
    "sg:phone":"+1 517 547 8071",
    "sg:postcode":"49220",
    "sg:province":"MI",
    "sg:tags":[
        "engineer"
    ],
    "wof:name":"Creative Solutions Specialty",
    "wof:placetype":"venue"
},
  "geometry": {"coordinates":[-84.31640299999999,41.972192],"type":"Point"}
}