{
  "type": "Feature",
  "properties": {
    "iso:country":"US",
    "sg:address":"915 Red Oak Rd",
    "sg:city":"Bronson",
    "sg:classifiers":[
        {
            "category":"Building & Trades",
            "subcategory":"Construction",
            "type":"Services"
        }
    ],
    "sg:phone":"+1 517 238 2884",
    "sg:postcode":"49028",
    "sg:province":"MI",
    "sg:tags":[
        "dry wall",
        "contractor"
    ],
    "wof:name":"Robert Speigle",
    "wof:placetype":"venue"
},
  "geometry": {"coordinates":[-85.048925,41.780468],"type":"Point"}
}