{
  "type": "Feature",
  "properties": {
    "iso:country":"US",
    "sg:address":"70 S Squirrel Rd",
    "sg:city":"Auburn Hills",
    "sg:classifiers":[
        {
            "category":"Manufacturing",
            "subcategory":"Tools & Machinery",
            "type":"Manufacturing & Wholesale Goods"
        }
    ],
    "sg:phone":"+1 248 852 2353",
    "sg:postcode":"48326",
    "sg:province":"MI",
    "sg:tags":[
        "machine",
        "shop"
    ],
    "wof:name":"Apollo Machining",
    "wof:placetype":"venue"
},
  "geometry": {"coordinates":[-83.222953,42.632226],"type":"Point"}
}