{
  "type": "Feature",
  "properties": {
    "iso:country":"US",
    "sg:address":"25254 Greenfield Rd",
    "sg:city":"Oak Park",
    "sg:classifiers":[
        {
            "category":"Shopping",
            "type":"Retail Goods"
        }
    ],
    "sg:phone":"+1 248 968 2090",
    "sg:postcode":"48237",
    "sg:province":"MI",
    "sg:tags":[
        "supply",
        "cosmetic",
        "beauty",
        "perfume"
    ],
    "wof:name":"May Queen and Beauty Supply",
    "wof:placetype":"venue"
},
  "geometry": {"coordinates":[-83.2015,42.4753],"type":"Point"}
}