{
  "type": "Feature",
  "properties": {
    "iso:country":"US",
    "sg:address":"1720 Harris Rd",
    "sg:city":"Beulah",
    "sg:classifiers":[
        {
            "category":"Building & Trades",
            "subcategory":"Landscaping Services",
            "type":"Services"
        }
    ],
    "sg:phone":"+1 231 882 5071",
    "sg:postcode":"49617",
    "sg:province":"MI",
    "sg:tags":[
        "landscape"
    ],
    "wof:name":"JS Earthworks",
    "wof:placetype":"venue"
},
  "geometry": {"coordinates":[-86.095349,44.65486],"type":"Point"}
}