{
  "type": "Feature",
  "properties": {
    "iso:country":"US",
    "sg:address":"6200 W Old Channel Trl",
    "sg:city":"Montague",
    "sg:classifiers":[
        {
            "category":"Manufacturing",
            "subcategory":"Metals",
            "type":"Manufacturing & Wholesale Goods"
        }
    ],
    "sg:phone":"+1 231 894 4282",
    "sg:postcode":"49437",
    "sg:province":"MI",
    "sg:tags":[
        "machine",
        "screw",
        "product"
    ],
    "wof:name":"Pin Key Mfg Co",
    "wof:placetype":"venue"
},
  "geometry": {"coordinates":[-86.39935,43.382128],"type":"Point"}
}