{
  "type": "Feature",
  "properties": {
    "iso:country":"US",
    "sg:address":"43675 Ford Rd",
    "sg:city":"Canton",
    "sg:classifiers":[
        {
            "category":"Shopping",
            "subcategory":"Gifts & Souvenirs",
            "type":"Retail Goods"
        }
    ],
    "sg:phone":"+1 734 981 5758",
    "sg:postcode":"48187",
    "sg:province":"MI",
    "sg:tags":[
        "party",
        "supply"
    ],
    "sg:website":"www.gagsandgiftsparty.com",
    "wof:name":"Gags & Gifts",
    "wof:placetype":"venue"
},
  "geometry": {"coordinates":[-83.476776,42.322128],"type":"Point"}
}