{
  "type": "Feature",
  "properties": {
    "iso:country":"US",
    "sg:address":"229 E Home Ave",
    "sg:city":"Flint",
    "sg:classifiers":[
        {
            "category":"Professional",
            "subcategory":"Business Services",
            "type":"Services"
        }
    ],
    "sg:phone":"+1 810 789 2265",
    "sg:postcode":"48505",
    "sg:province":"MI",
    "wof:name":"Genesee Council of Blind",
    "wof:placetype":"venue"
},
  "geometry": {"coordinates":[-83.701826,43.067279],"type":"Point"}
}