{
  "type": "Feature",
  "properties": {
    "iso:country":"US",
    "sg:address":"5836 W Weidman Rd",
    "sg:city":"Weidman",
    "sg:classifiers":[
        {
            "category":"Organizations",
            "subcategory":"Community Association",
            "type":"Services"
        }
    ],
    "sg:phone":"+1 989 644 2555",
    "sg:postcode":"48893",
    "sg:province":"MI",
    "wof:name":"Jatec Corp",
    "wof:placetype":"venue"
},
  "geometry": {"coordinates":[-84.96542100000001,43.683376],"type":"Point"}
}