{
  "type": "Feature",
  "properties": {
    "iso:country":"US",
    "sg:address":"6485 Belding Rd NE",
    "sg:city":"Rockford",
    "sg:classifiers":[
        {
            "category":"Professional",
            "type":"Services"
        }
    ],
    "sg:phone":"+1 616 874 7368",
    "sg:postcode":"49341",
    "sg:province":"MI",
    "sg:tags":[
        "establishment"
    ],
    "wof:name":"P Mcr",
    "wof:placetype":"venue"
},
  "geometry": {"coordinates":[-85.50112300000001,43.086333],"type":"Point"}
}