{
  "type": "Feature",
  "properties": {
    "iso:country":"US",
    "sg:address":"602 14th St",
    "sg:city":"Port Huron",
    "sg:classifiers":[
        {
            "category":"Building & Trades",
            "subcategory":"Construction",
            "type":"Services"
        }
    ],
    "sg:phone":"+1 810 966 7991",
    "sg:postcode":"48060",
    "sg:province":"MI",
    "sg:tags":[
        "painter"
    ],
    "wof:name":"Sterling Painting",
    "wof:placetype":"venue"
},
  "geometry": {"coordinates":[-82.439976,42.977803],"type":"Point"}
}