{
  "type": "Feature",
  "properties": {
    "iso:country":"US",
    "sg:address":"584 S Main St",
    "sg:city":"Plymouth",
    "sg:classifiers":[
        {
            "category":"Health Services",
            "subcategory":"Dentist",
            "type":"Services"
        }
    ],
    "sg:phone":"+1 734 453 5588",
    "sg:postcode":"48170",
    "sg:province":"MI",
    "wof:name":"Flury Penny S DDS PC",
    "wof:placetype":"venue"
},
  "geometry": {"coordinates":[-83.470029,42.367888],"type":"Point"}
}