{
  "type": "Feature",
  "properties": {
    "iso:country":"US",
    "sg:address":"470 100th St SW",
    "sg:city":"Byron Center",
    "sg:classifiers":[
        {
            "category":"Shopping",
            "subcategory":"Discount & Variety Stores",
            "type":"Retail Goods"
        }
    ],
    "sg:phone":"+1 616 878 0111",
    "sg:postcode":"49315",
    "sg:province":"MI",
    "sg:tags":[
        "merchandise",
        "general"
    ],
    "wof:name":"Schwan's Sales Enterprises",
    "wof:placetype":"venue"
},
  "geometry": {"coordinates":[-85.673051,42.782599],"type":"Point"}
}