{
  "type": "Feature",
  "properties": {
    "iso:country":"US",
    "sg:address":"1058 Carlisle Hwy",
    "sg:city":"Charlotte",
    "sg:classifiers":[
        {
            "category":"Social Services",
            "subcategory":"Child Care",
            "type":"Services"
        }
    ],
    "sg:phone":"+1 517 543 8559",
    "sg:postcode":"48813",
    "sg:province":"MI",
    "sg:tags":[
        "day"
    ],
    "wof:name":"South Ridge Latchkey",
    "wof:placetype":"venue"
},
  "geometry": {"coordinates":[-84.857659,42.553539],"type":"Point"}
}