{
  "type": "Feature",
  "properties": {
    "iso:country":"US",
    "sg:address":"5801 Woodward Ave",
    "sg:city":"Detroit",
    "sg:classifiers":[
        {
            "category":"Government",
            "subcategory":"Jail",
            "type":"Public Place"
        }
    ],
    "sg:phone":"+1 313 833 5044",
    "sg:postcode":"48202",
    "sg:province":"MI",
    "sg:tags":[
        "correctional",
        "institution"
    ],
    "wof:name":"Woodward Correction Ctr",
    "wof:placetype":"venue"
},
  "geometry": {"coordinates":[-83.068704,42.363445],"type":"Point"}
}