{
  "type": "Feature",
  "properties": {
    "iso:country":"US",
    "sg:address":"2744 Dixon Rd",
    "sg:city":"Caro",
    "sg:classifiers":[
        {
            "category":"Freight",
            "type":"Transportation"
        }
    ],
    "sg:phone":"+1 989 673 6453",
    "sg:postcode":"48723",
    "sg:province":"MI",
    "sg:tags":[
        "operator",
        "local",
        "trucking"
    ],
    "wof:name":"Ozbat Trucking",
    "wof:placetype":"venue"
},
  "geometry": {"coordinates":[-83.453802,43.46616],"type":"Point"}
}