{
  "type": "Feature",
  "properties": {
    "iso:country":"US",
    "sg:address":"13436 Grove St",
    "sg:city":"Detroit",
    "sg:classifiers":[
        {
            "category":"Education",
            "subcategory":"School",
            "type":"Public Place"
        }
    ],
    "sg:phone":"+1 313 862 2352",
    "sg:postcode":"48235",
    "sg:province":"MI",
    "sg:tags":[
        "high",
        "middle",
        "elementary"
    ],
    "sg:website":"www.cornerstoneschools.org",
    "wof:name":"Cornerstone Schools",
    "wof:placetype":"venue"
},
  "geometry": {"coordinates":[-83.17791,42.414114],"type":"Point"}
}