{
  "type": "Feature",
  "properties": {
    "iso:country":"US",
    "sg:address":"4026 S Huron Rd",
    "sg:city":"Standish",
    "sg:classifiers":[
        {
            "category":"Autos & Motor Vehicles",
            "subcategory":"Automobile Sales",
            "type":"Retail Goods"
        }
    ],
    "sg:phone":"+1 989 846 9933",
    "sg:postcode":"48658",
    "sg:province":"MI",
    "sg:tags":[
        "car",
        "dealer"
    ],
    "wof:name":"Sylvester Auto Sales",
    "wof:placetype":"venue"
},
  "geometry": {"coordinates":[-83.959896,43.969143],"type":"Point"}
}