{
  "type": "Feature",
  "properties": {
    "iso:country":"US",
    "sg:address":"51990 Van Dyke Ave",
    "sg:city":"Shelby Twp",
    "sg:classifiers":[
        {
            "category":"Restaurant",
            "type":"Food & Drink"
        }
    ],
    "sg:phone":"+1 586 731 0464",
    "sg:postcode":"48316",
    "sg:province":"MI",
    "wof:name":"Olympia Coney Island",
    "wof:placetype":"venue"
},
  "geometry": {"coordinates":[-83.033979,42.67328],"type":"Point"}
}