{
  "type": "Feature",
  "properties": {
    "iso:country":"US",
    "sg:address":"318 Harrow Ln",
    "sg:city":"Saginaw",
    "sg:classifiers":[
        {
            "category":"Social Services",
            "subcategory":"Child Care",
            "type":"Services"
        }
    ],
    "sg:phone":"+1 989 792 8299",
    "sg:postcode":"48638",
    "sg:province":"MI",
    "sg:tags":[
        "day"
    ],
    "wof:name":"Ruth Singer",
    "wof:placetype":"venue"
},
  "geometry": {"coordinates":[-84.025954,43.41177],"type":"Point"}
}