{
  "type": "Feature",
  "properties": {
    "iso:country":"US",
    "sg:address":"5217 Brush St",
    "sg:city":"Detroit",
    "sg:classifiers":[
        {
            "category":"Parking",
            "type":"Transportation"
        }
    ],
    "sg:phone":"+1 313 833 9463",
    "sg:postcode":"48202",
    "sg:province":"MI",
    "wof:name":"Park Rite Inc",
    "wof:placetype":"venue"
},
  "geometry": {"coordinates":[-83.060997,42.360298],"type":"Point"}
}