{
  "type": "Feature",
  "properties": {
    "iso:country":"US",
    "sg:address":"200 S State St",
    "sg:city":"Oscoda",
    "sg:classifiers":[
        {
            "category":"Autos & Motor Vehicles",
            "subcategory":"Fuel & Gas Station",
            "type":"Retail Goods"
        }
    ],
    "sg:phone":"+1 989 739 1051",
    "sg:postcode":"48740",
    "sg:province":"MI",
    "sg:tags":[
        "oil"
    ],
    "wof:name":"UDS-Total Petroleum",
    "wof:placetype":"venue"
},
  "geometry": {"coordinates":[-83.29706899999999,44.654778],"type":"Point"}
}