{
  "type": "Feature",
  "properties": {
    "iso:country":"US",
    "sg:address":"3315 McKeith Ct",
    "sg:city":"Midland",
    "sg:classifiers":[
        {
            "category":"Wholesale",
            "subcategory":"Vending Machines",
            "type":"Manufacturing & Wholesale Goods"
        }
    ],
    "sg:phone":"+1 989 839 7620",
    "sg:postcode":"48642",
    "sg:province":"MI",
    "sg:tags":[
        "operator"
    ],
    "wof:name":"Van Tastic Vending",
    "wof:placetype":"venue"
},
  "geometry": {"coordinates":[-84.205718,43.629185],"type":"Point"}
}