{
  "type": "Feature",
  "properties": {
    "iso:country":"US",
    "sg:address":"120 N 6th St",
    "sg:city":"Escanaba",
    "sg:classifiers":[
        {
            "category":"Organizations",
            "subcategory":"Labor Organization",
            "type":"Services"
        }
    ],
    "sg:phone":"+1 906 786 2743",
    "sg:postcode":"49829",
    "sg:province":"MI",
    "wof:name":"Teamsters Local Union",
    "wof:placetype":"venue"
},
  "geometry": {"coordinates":[-87.055167,45.746615],"type":"Point"}
}