{
  "type": "Feature",
  "properties": {
    "iso:country":"US",
    "sg:address":"2634 Division Ave S",
    "sg:city":"Grand Rapids",
    "sg:classifiers":[
        {
            "category":"Retail",
            "subcategory":"Auto Repair",
            "type":"Services"
        }
    ],
    "sg:phone":"+1 616 970 0023",
    "sg:postcode":"49507",
    "sg:province":"MI",
    "sg:tags":[
        "repairing",
        "automobile",
        "radiator"
    ],
    "wof:name":"KOOL Radiator Svc",
    "wof:placetype":"venue"
},
  "geometry": {"coordinates":[-85.66607399999999,42.916621],"type":"Point"}
}