{
  "type": "Feature",
  "properties": {
    "iso:country":"US",
    "sg:address":"5017 Hayes St",
    "sg:city":"Wayne",
    "sg:classifiers":[
        {
            "category":"Personal",
            "subcategory":"Beauty Salon",
            "type":"Services"
        }
    ],
    "sg:phone":"+1 734 729 5790",
    "sg:postcode":"48184",
    "sg:province":"MI",
    "sg:tags":[
        "shop"
    ],
    "wof:name":"Helens Unisex Hair Design",
    "wof:placetype":"venue"
},
  "geometry": {"coordinates":[-83.349751,42.271652],"type":"Point"}
}