{
  "type": "Feature",
  "properties": {
    "iso:country":"US",
    "sg:address":"974 7th St",
    "sg:city":"Plainwell",
    "sg:classifiers":[
        {
            "category":"Retail",
            "subcategory":"Portrait Studio",
            "type":"Services"
        }
    ],
    "sg:phone":"+1 269 685 7615",
    "sg:postcode":"49080",
    "sg:province":"MI",
    "sg:tags":[
        "photo"
    ],
    "wof:name":"Michelles Portraits",
    "wof:placetype":"venue"
},
  "geometry": {"coordinates":[-85.612413,42.491156],"type":"Point"}
}