{
  "type": "Feature",
  "properties": {
    "iso:country":"US",
    "sg:address":"11925 Marsh Rd",
    "sg:city":"Shelbyville",
    "sg:classifiers":[
        {
            "category":"Restaurant",
            "type":"Food & Drink"
        }
    ],
    "sg:phone":"+1 269 672 5577",
    "sg:postcode":"49344",
    "sg:province":"MI",
    "wof:name":"Southside Pizza & Grill",
    "wof:placetype":"venue"
},
  "geometry": {"coordinates":[-85.523107,42.587874],"type":"Point"}
}