{
  "type": "Feature",
  "properties": {
    "iso:country":"US",
    "sg:address":"13301 E 8 Mile Rd",
    "sg:city":"Warren",
    "sg:classifiers":[
        {
            "category":"Retail",
            "subcategory":"Animal Services",
            "type":"Services"
        }
    ],
    "sg:phone":"+1 586 771 9009",
    "sg:postcode":"48089",
    "sg:province":"MI",
    "sg:tags":[
        "beef",
        "feedlot",
        "cattle"
    ],
    "wof:name":"G C H Land & Cattle Co",
    "wof:placetype":"venue"
},
  "geometry": {"coordinates":[-82.98809199999999,42.449223],"type":"Point"}
}