{
  "type": "Feature",
  "properties": {
    "iso:country":"US",
    "sg:address":"604 W John Beers Rd",
    "sg:city":"Stevensville",
    "sg:classifiers":[
        {
            "category":"Retail",
            "subcategory":"Repair Shop",
            "type":"Services"
        }
    ],
    "sg:phone":"+1 269 422 1533",
    "sg:postcode":"49127",
    "sg:province":"MI",
    "sg:tags":[
        "bathtub",
        "sink",
        "refinishing"
    ],
    "wof:name":"American Tub & Tile",
    "wof:placetype":"venue"
},
  "geometry": {"coordinates":[-86.46526799999999,42.014533],"type":"Point"}
}