{
  "type": "Feature",
  "properties": {
    "iso:country":"US",
    "sg:address":"25875 Groesbeck Hwy",
    "sg:city":"Warren",
    "sg:classifiers":[
        {
            "category":"Retail",
            "subcategory":"Auto Repair",
            "type":"Services"
        }
    ],
    "sg:phone":"+1 586 773 3939",
    "sg:postcode":"48089",
    "sg:province":"MI",
    "sg:tags":[
        "automobile",
        "co",
        "drive",
        "transporter"
    ],
    "wof:name":"G & L Auto Sales",
    "wof:placetype":"venue"
},
  "geometry": {"coordinates":[-82.975551,42.485264],"type":"Point"}
}