{
  "type": "Feature",
  "properties": {
    "iso:country":"US",
    "sg:address":"5132 N Hubbard Lake Rd",
    "sg:city":"Spruce",
    "sg:classifiers":[
        {
            "category":"Government",
            "subcategory":"Fire Station",
            "type":"Public Place"
        }
    ],
    "sg:phone":"+1 989 727 2539",
    "sg:postcode":"48762",
    "sg:province":"MI",
    "sg:tags":[
        "protection"
    ],
    "wof:name":"Alcona Township Fire Station",
    "wof:placetype":"venue"
},
  "geometry": {"coordinates":[-83.52617600000001,44.785425],"type":"Point"}
}