{
  "type": "Feature",
  "properties": {
    "iso:country":"US",
    "sg:address":"3600 Enterprise Dr",
    "sg:city":"Allen Park",
    "sg:classifiers":[
        {
            "category":"Travel",
            "subcategory":"Hotels & Motels",
            "type":"Entertainment"
        },
        {
            "category":"Retail",
            "subcategory":"Event Space",
            "type":"Services"
        }
    ],
    "sg:phone":"+1 313 323 3500",
    "sg:postcode":"48101",
    "sg:province":"MI",
    "sg:tags":[
        "venue"
    ],
    "sg:website":"www.holidayinnexpress.com",
    "wof:name":"Holiday Inn Express Hotel & Suites Allen Park-Dearborn",
    "wof:placetype":"venue"
},
  "geometry": {"coordinates":[-83.198252,42.280788],"type":"Point"}
}