{
  "type": "Feature",
  "properties": {
    "iso:country":"US",
    "sg:address":"30619 Lebanon Dr",
    "sg:city":"Warren",
    "sg:classifiers":[
        {
            "category":"Professional",
            "subcategory":"Management & Consulting",
            "type":"Services"
        }
    ],
    "sg:phone":"+1 586 945 0506",
    "sg:postcode":"48093",
    "sg:province":"MI",
    "sg:tags":[
        "energy",
        "devices",
        "commercialization"
    ],
    "wof:name":"Involute Solutions",
    "wof:placetype":"venue"
},
  "geometry": {"coordinates":[-83.01225100000001,42.518644],"type":"Point"}
}