{
  "type": "Feature",
  "properties": {
    "iso:country":"US",
    "sg:address":"4152 Fillmore Rd",
    "sg:city":"Holland",
    "sg:classifiers":[
        {
            "category":"Retail",
            "subcategory":"Auto Repair",
            "type":"Services"
        }
    ],
    "sg:phone":"+1 269 751 8750",
    "sg:postcode":"49423",
    "sg:province":"MI",
    "sg:tags":[
        "general"
    ],
    "wof:name":"Jims Engine Repair",
    "wof:placetype":"venue"
},
  "geometry": {"coordinates":[-86.03963400000001,42.721997],"type":"Point"}
}