{
  "type": "Feature",
  "properties": {
    "iso:country":"US",
    "sg:address":"200 E Wattles Rd",
    "sg:city":"Troy",
    "sg:classifiers":[
        {
            "category":"Organizations",
            "subcategory":"Religious Organization",
            "type":"Services"
        }
    ],
    "sg:phone":"+1 248 619 9910",
    "sg:postcode":"48085",
    "sg:province":"MI",
    "sg:tags":[
        "church"
    ],
    "wof:name":"St Lucy Croatian Catholic Chr",
    "wof:placetype":"venue"
},
  "geometry": {"coordinates":[-83.14833299999999,42.577301],"type":"Point"}
}