{
  "type": "Feature",
  "properties": {
    "iso:country":"US",
    "sg:address":"17999 Washburne Rd",
    "sg:city":"Grass Lake",
    "sg:classifiers":[
        {
            "category":"Organizations",
            "subcategory":"Religious Organization",
            "type":"Services"
        }
    ],
    "sg:phone":"+1 734 428 7222",
    "sg:postcode":"49240",
    "sg:province":"MI",
    "sg:tags":[
        "school"
    ],
    "wof:name":"North Sharn Bapt Ch Christ Sch",
    "wof:placetype":"venue"
},
  "geometry": {"coordinates":[-84.07834699999999,42.219938],"type":"Point"}
}