{
  "type": "Feature",
  "properties": {
    "iso:country":"US",
    "sg:address":"3284 Chicago Dr",
    "sg:city":"Hudsonville",
    "sg:classifiers":[
        {
            "category":"Autos & Motor Vehicles",
            "subcategory":"Automobile Sales",
            "type":"Retail Goods"
        }
    ],
    "sg:phone":"+1 616 669 6612",
    "sg:postcode":"49426",
    "sg:province":"MI",
    "sg:tags":[
        "car",
        "dealer"
    ],
    "sg:website":"www.haroldzeigler.com",
    "wof:name":"Herold Zeigler Chrysler Dodge",
    "wof:placetype":"venue"
},
  "geometry": {"coordinates":[-85.86428100000001,42.868974],"type":"Point"}
}