{
  "type": "Feature",
  "properties": {
    "iso:country":"US",
    "sg:address":"4300 24th Ave",
    "sg:city":"Fort Gratiot",
    "sg:classifiers":[
        {
            "category":"Food & Beverages",
            "subcategory":"Specialty",
            "type":"Retail Goods"
        }
    ],
    "sg:phone":"+1 810 385 8279",
    "sg:postcode":"48059",
    "sg:province":"MI",
    "sg:tags":[
        "gourmet",
        "shop"
    ],
    "wof:name":"Hickory Farms",
    "wof:placetype":"venue"
},
  "geometry": {"coordinates":[-82.456142,43.02893],"type":"Point"}
}