{
  "type": "Feature",
  "properties": {
    "iso:country":"US",
    "sg:address":"21850 O'Hara Rd",
    "sg:city":"Merrill",
    "sg:classifiers":[
        {
            "category":"Real Estate",
            "subcategory":"Real Estate Operator",
            "type":"Services"
        }
    ],
    "sg:phone":"+1 989 643 5614",
    "sg:postcode":"48637",
    "sg:province":"MI",
    "sg:tags":[
        "property",
        "lessor"
    ],
    "wof:name":"Lloyd Zeitler",
    "wof:placetype":"venue"
},
  "geometry": {"coordinates":[-84.180345,43.378989],"type":"Point"}
}