{
  "type": "Feature",
  "properties": {
    "iso:country":"US",
    "sg:address":"812 Washington Blvd",
    "sg:city":"Lake Odessa",
    "sg:classifiers":[
        {
            "category":"Education",
            "subcategory":"School",
            "type":"Public Place"
        }
    ],
    "sg:phone":"+1 616 374 8842",
    "sg:postcode":"48849",
    "sg:province":"MI",
    "sg:website":"www.lakewood.k12.mi.us",
    "wof:name":"West Elementary School",
    "wof:placetype":"venue"
},
  "geometry": {"coordinates":[-85.14376,42.782163],"type":"Point"}
}