{
  "type": "Feature",
  "properties": {
    "iso:country":"US",
    "sg:address":"19980 30th Ave",
    "sg:city":"Barryton",
    "sg:classifiers":[
        {
            "category":"Communications",
            "type":"Services"
        }
    ],
    "sg:phone":"+1 989 382 7630",
    "sg:postcode":"49305",
    "sg:province":"MI",
    "wof:name":"Nationwide Communications",
    "wof:placetype":"venue"
},
  "geometry": {"coordinates":[-85.147581,43.75417],"type":"Point"}
}