{
  "type": "Feature",
  "properties": {
    "iso:country":"US",
    "sg:address":"1428 W Norton Ave",
    "sg:city":"Muskegon",
    "sg:classifiers":[
        {
            "category":"Restaurant",
            "type":"Food & Drink"
        }
    ],
    "sg:phone":"+1 231 773 7317",
    "sg:postcode":"49441",
    "sg:province":"MI",
    "wof:name":"China Star",
    "wof:placetype":"venue"
},
  "geometry": {"coordinates":[-86.277781,43.190928],"type":"Point"}
}