{
  "type": "Feature",
  "properties": {
    "iso:country":"US",
    "sg:address":"12074 N Genesee Rd",
    "sg:city":"Clio",
    "sg:classifiers":[
        {
            "category":"Professional",
            "subcategory":"Business Services",
            "type":"Services"
        }
    ],
    "sg:phone":"+1 586 871 4214",
    "sg:postcode":"48420",
    "sg:province":"MI",
    "wof:name":"Loper Corp",
    "wof:placetype":"venue"
},
  "geometry": {"coordinates":[-83.62036999999999,43.185096],"type":"Point"}
}