{
  "type": "Feature",
  "properties": {
    "iso:country":"US",
    "sg:address":"887 N Union City Rd",
    "sg:city":"Coldwater",
    "sg:classifiers":[
        {
            "category":"Building & Trades",
            "subcategory":"Electrical",
            "type":"Services"
        }
    ],
    "sg:phone":"+1 517 278 8500",
    "sg:postcode":"49036",
    "sg:province":"MI",
    "sg:tags":[
        "electrical",
        "contractor"
    ],
    "wof:name":"Patriot Electric Inc",
    "wof:placetype":"venue"
},
  "geometry": {"coordinates":[-85.020336,42.006063],"type":"Point"}
}