{
  "type": "Feature",
  "properties": {
    "iso:country":"US",
    "sg:address":"3075 W 13th St",
    "sg:city":"Cadillac",
    "sg:classifiers":[
        {
            "category":"Restaurant",
            "type":"Food & Drink"
        }
    ],
    "sg:phone":"+1 231 779 3000",
    "sg:postcode":"49601",
    "sg:province":"MI",
    "sg:tags":[
        "caterer"
    ],
    "wof:name":"Jean's Kitchen",
    "wof:placetype":"venue"
},
  "geometry": {"coordinates":[-85.447171,44.266773],"type":"Point"}
}