{
  "type": "Feature",
  "properties": {
    "iso:country":"US",
    "sg:address":"200 N Groesbeck Hwy",
    "sg:city":"Mount Clemens",
    "sg:classifiers":[
        {
            "category":"Sports & Exercise",
            "subcategory":"Ice Rink",
            "type":"Entertainment"
        }
    ],
    "sg:phone":"+1 586 307 8202",
    "sg:postcode":"48043",
    "sg:province":"MI",
    "sg:tags":[
        "skating"
    ],
    "wof:name":"Mt Clemens Ice Arena & Fitness Center",
    "wof:placetype":"venue"
},
  "geometry": {"coordinates":[-82.8937,42.609798],"type":"Point"}
}