{
  "type": "Feature",
  "properties": {
    "iso:country":"US",
    "sg:address":"5119 W U Ave",
    "sg:city":"Schoolcraft",
    "sg:classifiers":[
        {
            "category":"Home & Garden",
            "subcategory":"Furniture",
            "type":"Retail Goods"
        }
    ],
    "sg:phone":"+1 269 679 4151",
    "sg:postcode":"49087",
    "sg:province":"MI",
    "wof:name":"Ballinger Yard Furniture",
    "wof:placetype":"venue"
},
  "geometry": {"coordinates":[-85.649063,42.143169],"type":"Point"}
}