{
  "type": "Feature",
  "properties": {
    "iso:country":"US",
    "sg:address":"650 Livernois St",
    "sg:city":"Ferndale",
    "sg:classifiers":[
        {
            "category":"Real Estate",
            "subcategory":"Architect",
            "type":"Services"
        }
    ],
    "sg:phone":"+1 248 591 0360",
    "sg:postcode":"48220",
    "sg:province":"MI",
    "sg:website":"www.silveri.com",
    "wof:name":"Silveri Architects",
    "wof:placetype":"venue"
},
  "geometry": {"coordinates":[-83.142403,42.451],"type":"Point"}
}