{
  "type": "Feature",
  "properties": {
    "iso:country":"US",
    "sg:address":"3501 Sehler St",
    "sg:city":"Conklin",
    "sg:classifiers":[
        {
            "category":"Social Services",
            "subcategory":"Child Care",
            "type":"Services"
        }
    ],
    "sg:phone":"+1 616 899 5583",
    "sg:postcode":"49403",
    "sg:province":"MI",
    "sg:website":"www.telmon.org",
    "wof:name":"Conklin Migrant Head Start",
    "wof:placetype":"venue"
},
  "geometry": {"coordinates":[-85.879321,43.126073],"type":"Point"}
}