{
  "type": "Feature",
  "properties": {
    "iso:country":"US",
    "sg:address":"871 E Walton Blvd",
    "sg:city":"Pontiac",
    "sg:classifiers":[
        {
            "category":"Retail",
            "subcategory":"Auto Repair",
            "type":"Services"
        }
    ],
    "sg:phone":"+1 248 373 6073",
    "sg:postcode":"48340",
    "sg:province":"MI",
    "sg:tags":[
        "general"
    ],
    "wof:name":"J&S Automotives",
    "wof:placetype":"venue"
},
  "geometry": {"coordinates":[-83.26754699999999,42.677864],"type":"Point"}
}