{
  "type": "Feature",
  "properties": {
    "iso:country":"US",
    "sg:address":"228 Bridge St",
    "sg:city":"Charlevoix",
    "sg:classifiers":[
        {
            "category":"Shopping",
            "subcategory":"Used Merchandise",
            "type":"Retail Goods"
        }
    ],
    "sg:phone":"+1 231 547 0550",
    "sg:postcode":"49720",
    "sg:province":"MI",
    "sg:tags":[
        "antique"
    ],
    "wof:name":"Maison & Jardin",
    "wof:placetype":"venue"
},
  "geometry": {"coordinates":[-85.258605,45.317762],"type":"Point"}
}