{
  "type": "Feature",
  "properties": {
    "iso:country":"US",
    "sg:address":"40139 Michigan Ave",
    "sg:city":"Canton",
    "sg:classifiers":[
        {
            "category":"Travel",
            "subcategory":"Hotels & Motels",
            "type":"Entertainment"
        }
    ],
    "sg:phone":"+1 734 721 1220",
    "sg:postcode":"48188",
    "sg:province":"MI",
    "wof:name":"Willow Acres Motel",
    "wof:placetype":"venue"
},
  "geometry": {"coordinates":[-83.429298,42.278999],"type":"Point"}
}