{
  "type": "Feature",
  "properties": {
    "iso:country":"US",
    "sg:address":"2380 Holmes St",
    "sg:city":"Hamtramck",
    "sg:classifiers":[
        {
            "category":"Building & Trades",
            "subcategory":"Locksmith",
            "type":"Services"
        }
    ],
    "sg:phone":"+1 313 989 0290",
    "sg:postcode":"48212",
    "sg:province":"MI",
    "sg:tags":[
        "key"
    ],
    "wof:name":"Emergency Any Locksmith",
    "wof:placetype":"venue"
},
  "geometry": {"coordinates":[-83.06424,42.398945],"type":"Point"}
}