{
  "type": "Feature",
  "properties": {
    "iso:country":"US",
    "sg:address":"2611 16th St",
    "sg:city":"Port Huron",
    "sg:classifiers":[
        {
            "category":"Manufacturing",
            "subcategory":"Rubber & Plastics",
            "type":"Manufacturing & Wholesale Goods"
        }
    ],
    "sg:phone":"+1 810 985 9730",
    "sg:postcode":"48060",
    "sg:province":"MI",
    "sg:website":"www.blackriverplastics.com",
    "wof:name":"Black River Plastics",
    "wof:placetype":"venue"
},
  "geometry": {"coordinates":[-82.442021,42.955355],"type":"Point"}
}