{
  "type": "Feature",
  "properties": {
    "iso:country":"US",
    "sg:address":"2111 Orchard Lake Rd",
    "sg:city":"Keego Harbor",
    "sg:classifiers":[
        {
            "category":"Personal",
            "subcategory":"Beauty Salon",
            "type":"Services"
        }
    ],
    "sg:phone":"+1 248 335 8270",
    "sg:postcode":"48320",
    "sg:province":"MI",
    "sg:tags":[
        "shop"
    ],
    "wof:name":"Sylvan Cut N Curl",
    "wof:placetype":"venue"
},
  "geometry": {"coordinates":[-83.325496,42.614151],"type":"Point"}
}