{
  "type": "Feature",
  "properties": {
    "iso:country":"US",
    "sg:address":"1122 Industrial Ave",
    "sg:city":"Holland",
    "sg:classifiers":[
        {
            "category":"Wholesale",
            "subcategory":"Auto Parts",
            "type":"Manufacturing & Wholesale Goods"
        }
    ],
    "sg:phone":"+1 616 392 1481",
    "sg:postcode":"49423",
    "sg:province":"MI",
    "sg:tags":[
        "equipment",
        "truck"
    ],
    "wof:name":"Holland Hitch Co",
    "wof:placetype":"venue"
},
  "geometry": {"coordinates":[-86.089232,42.757772],"type":"Point"}
}