{
  "type": "Feature",
  "properties": {
    "iso:country":"US",
    "sg:address":"616 W Monroe St",
    "sg:city":"Durand",
    "sg:classifiers":[
        {
            "category":"Building & Trades",
            "subcategory":"Construction",
            "type":"Services"
        }
    ],
    "sg:phone":"+1 989 288 5412",
    "sg:postcode":"48429",
    "sg:province":"MI",
    "sg:tags":[
        "contractor"
    ],
    "wof:name":"Jerry Hart Roofing & Siding",
    "wof:placetype":"venue"
},
  "geometry": {"coordinates":[-83.99382,42.91807],"type":"Point"}
}