{
  "type": "Feature",
  "properties": {
    "iso:country":"US",
    "sg:address":"738 N Harris St",
    "sg:city":"Saline",
    "sg:classifiers":[
        {
            "category":"Retail",
            "subcategory":"Portrait Studio",
            "type":"Services"
        }
    ],
    "sg:phone":"+1 734 429 4715",
    "sg:postcode":"48176",
    "sg:province":"MI",
    "sg:tags":[
        "photo"
    ],
    "wof:name":"Bates Tech",
    "wof:placetype":"venue"
},
  "geometry": {"coordinates":[-83.780817,42.175568],"type":"Point"}
}