{
  "type": "Feature",
  "properties": {
    "iso:country":"US",
    "sg:address":"321 E Ohio St",
    "sg:city":"Marquette",
    "sg:classifiers":[
        {
            "category":"Education",
            "subcategory":"School",
            "type":"Public Place"
        }
    ],
    "sg:phone":"+1 906 226 5100",
    "sg:postcode":"49855",
    "sg:province":"MI",
    "sg:tags":[
        "district"
    ],
    "wof:name":"Marquette-Alger Interm",
    "wof:placetype":"venue"
},
  "geometry": {"coordinates":[-87.388803,46.548286],"type":"Point"}
}