{
  "type": "Feature",
  "properties": {
    "iso:country":"US",
    "sg:address":"308 W Tobias St",
    "sg:city":"Flint",
    "sg:classifiers":[
        {
            "category":"Retail",
            "subcategory":"Auto Repair",
            "type":"Services"
        }
    ],
    "sg:phone":"+1 810 232 1111",
    "sg:postcode":"48503",
    "sg:province":"MI",
    "sg:tags":[
        "towing"
    ],
    "wof:name":"City Towing",
    "wof:placetype":"venue"
},
  "geometry": {"coordinates":[-83.68357,42.998887],"type":"Point"}
}