{
  "type": "Feature",
  "properties": {
    "iso:country":"US",
    "sg:address":"2768 Foster Ave",
    "sg:city":"Ann Arbor",
    "sg:classifiers":[
        {
            "category":"Professional",
            "subcategory":"Computer Services",
            "type":"Services"
        }
    ],
    "sg:phone":"+1 734 434 4681",
    "sg:postcode":"48108",
    "sg:province":"MI",
    "sg:tags":[
        "related"
    ],
    "wof:name":"Broadbase Technologies",
    "wof:placetype":"venue"
},
  "geometry": {"coordinates":[-83.666507,42.246485],"type":"Point"}
}