{
  "type": "Feature",
  "properties": {
    "iso:country":"US",
    "sg:address":"27492 5 Mile Rd",
    "sg:city":"Livonia",
    "sg:classifiers":[
        {
            "category":"Real Estate",
            "subcategory":"Real Estate Services",
            "type":"Services"
        }
    ],
    "sg:phone":"+1 734 425 7300",
    "sg:postcode":"48154",
    "sg:province":"MI",
    "wof:name":"Clark Weldon Realtor",
    "wof:placetype":"venue"
},
  "geometry": {"coordinates":[-83.31819900000001,42.398602],"type":"Point"}
}