{
  "type": "Feature",
  "properties": {
    "iso:country":"US",
    "sg:address":"42051 Mound Rd",
    "sg:city":"Sterling Heights",
    "sg:classifiers":[
        {
            "category":"Health Services",
            "subcategory":"Dentist",
            "type":"Services"
        }
    ],
    "sg:phone":"+1 586 323 7700",
    "sg:postcode":"48314",
    "sg:province":"MI",
    "wof:name":"Oakland Oral Surgery Associates",
    "wof:placetype":"venue"
},
  "geometry": {"coordinates":[-83.0513,42.602001],"type":"Point"}
}