{
  "type": "Feature",
  "properties": {
    "iso:country":"US",
    "sg:address":"15600 W 12 Mile Rd",
    "sg:city":"Southfield",
    "sg:classifiers":[
        {
            "category":"Communications",
            "subcategory":"Radio Station",
            "type":"Services"
        }
    ],
    "sg:phone":"+1 248 233 3401",
    "sg:postcode":"48076",
    "sg:province":"MI",
    "wof:name":"Infinity Promotions Group of Detroit",
    "wof:placetype":"venue"
},
  "geometry": {"coordinates":[-83.204498,42.502998],"type":"Point"}
}