{
  "type": "Feature",
  "properties": {
    "iso:country":"US",
    "sg:address":"2390 N Telegraph Rd",
    "sg:city":"Monroe",
    "sg:classifiers":[
        {
            "category":"Building & Trades",
            "subcategory":"Equipment Rental",
            "type":"Services"
        }
    ],
    "sg:phone":"+1 734 241 5290",
    "sg:postcode":"48162",
    "sg:province":"MI",
    "sg:tags":[
        "yard"
    ],
    "wof:name":"Black Swamp Equipment",
    "wof:placetype":"venue"
},
  "geometry": {"coordinates":[-83.394822,41.958041],"type":"Point"}
}