{
  "type": "Feature",
  "properties": {
    "iso:country":"US",
    "sg:address":"865 S Main St",
    "sg:city":"Lapeer",
    "sg:classifiers":[
        {
            "category":"Shopping",
            "subcategory":"Department Store",
            "type":"Retail Goods"
        }
    ],
    "sg:phone":"+1 810 667 1684",
    "sg:postcode":"48446",
    "sg:province":"MI",
    "wof:name":"Glik's",
    "wof:placetype":"venue"
},
  "geometry": {"coordinates":[-83.321568,43.038662],"type":"Point"}
}