{
  "type": "Feature",
  "properties": {
    "iso:country":"US",
    "sg:address":"23459 Springbrook Dr",
    "sg:city":"Farmington",
    "sg:classifiers":[
        {
            "category":"Professional",
            "type":"Services"
        }
    ],
    "sg:phone":"+1 248 474 9755",
    "sg:postcode":"48336",
    "sg:province":"MI",
    "wof:name":"Dnd Services",
    "wof:placetype":"venue"
},
  "geometry": {"coordinates":[-83.34853699999999,42.464272],"type":"Point"}
}