{
  "type": "Feature",
  "properties": {
    "iso:country":"US",
    "sg:address":"104 S Main St",
    "sg:city":"Cheboygan",
    "sg:classifiers":[
        {
            "category":"Personal",
            "subcategory":"Beauty Salon",
            "type":"Services"
        }
    ],
    "sg:phone":"+1 231 627 4699",
    "sg:postcode":"49721",
    "sg:province":"MI",
    "sg:tags":[
        "shop"
    ],
    "wof:name":"Attitudes Hair Salon",
    "wof:placetype":"venue"
},
  "geometry": {"coordinates":[-84.474768,45.646736],"type":"Point"}
}