{
  "type": "Feature",
  "properties": {
    "iso:country":"US",
    "sg:address":"6494 Milano St",
    "sg:city":"Burton",
    "sg:classifiers":[
        {
            "category":"Building & Trades",
            "subcategory":"Construction",
            "type":"Services"
        }
    ],
    "sg:phone":"+1 810 744 2321",
    "sg:postcode":"48519",
    "sg:province":"MI",
    "sg:tags":[
        "concrete",
        "contractor"
    ],
    "wof:name":"Diamond Asphalt & Paving",
    "wof:placetype":"venue"
},
  "geometry": {"coordinates":[-83.57649000000001,42.997436],"type":"Point"}
}