{
  "type": "Feature",
  "properties": {
    "iso:country":"US",
    "sg:address":"364 Pipestone St",
    "sg:city":"Benton Harbor",
    "sg:classifiers":[
        {
            "category":"Organizations",
            "subcategory":"Religious Organization",
            "type":"Services"
        }
    ],
    "sg:phone":"+1 269 927 1734",
    "sg:postcode":"49022",
    "sg:province":"MI",
    "sg:tags":[
        "church"
    ],
    "wof:name":"Faith Center COGIC",
    "wof:placetype":"venue"
},
  "geometry": {"coordinates":[-86.449578,42.110904],"type":"Point"}
}