{
  "type": "Feature",
  "properties": {
    "iso:country":"US",
    "sg:address":"77 E Jefferson St",
    "sg:city":"Quincy",
    "sg:classifiers":[
        {
            "category":"Freight",
            "type":"Transportation"
        }
    ],
    "sg:phone":"+1 517 414 6374",
    "sg:postcode":"49082",
    "sg:province":"MI",
    "sg:tags":[
        "operator",
        "trucking"
    ],
    "wof:name":"Reliable Transport",
    "wof:placetype":"venue"
},
  "geometry": {"coordinates":[-84.876733,41.944882],"type":"Point"}
}