{
  "type": "Feature",
  "properties": {
    "iso:country":"US",
    "sg:address":"7525 Michigan Ave",
    "sg:city":"Thompsonville",
    "sg:classifiers":[
        {
            "category":"Building & Trades",
            "subcategory":"Construction",
            "type":"Services"
        }
    ],
    "sg:phone":"+1 231 378 2600",
    "sg:postcode":"49683",
    "sg:province":"MI",
    "sg:tags":[
        "well",
        "drilling"
    ],
    "wof:name":"Benjamin Sowers Well Drilling",
    "wof:placetype":"venue"
},
  "geometry": {"coordinates":[-85.938772,44.520117],"type":"Point"}
}