{
  "type": "Feature",
  "properties": {
    "iso:country":"US",
    "sg:address":"210 Clark St",
    "sg:city":"Wyandotte",
    "sg:classifiers":[
        {
            "category":"Building & Trades",
            "subcategory":"Landscaping Services",
            "type":"Services"
        }
    ],
    "sg:phone":"+1 734 283 4188",
    "sg:postcode":"48192",
    "sg:province":"MI",
    "wof:name":"J&R Landscape Maintenance",
    "wof:placetype":"venue"
},
  "geometry": {"coordinates":[-83.153492,42.218099],"type":"Point"}
}