{
  "type": "Feature",
  "properties": {
    "iso:country":"US",
    "sg:address":"390 E Pearl Rd",
    "sg:city":"Coldwater",
    "sg:classifiers":[
        {
            "category":"Freight",
            "type":"Transportation"
        }
    ],
    "sg:phone":"+1 517 238 8165",
    "sg:postcode":"49036",
    "sg:province":"MI",
    "sg:tags":[
        "dock"
    ],
    "wof:name":"Superior Products",
    "wof:placetype":"venue"
},
  "geometry": {"coordinates":[-85.02276000000001,41.825644],"type":"Point"}
}