{
  "type": "Feature",
  "properties": {
    "iso:country":"US",
    "sg:address":"1853 S Shore Dr",
    "sg:city":"Holland",
    "sg:classifiers":[
        {
            "category":"Professional",
            "subcategory":"Business Services",
            "type":"Services"
        }
    ],
    "sg:phone":"+1 616 786 4424",
    "sg:postcode":"49423",
    "sg:province":"MI",
    "sg:tags":[
        "appraiser"
    ],
    "wof:name":"Tulip City Appraisers",
    "wof:placetype":"venue"
},
  "geometry": {"coordinates":[-86.186221,42.771899],"type":"Point"}
}