{
  "type": "Feature",
  "properties": {
    "iso:country":"US",
    "sg:address":"1424 Congress St",
    "sg:city":"Lansing",
    "sg:classifiers":[
        {
            "category":"Building & Trades",
            "subcategory":"Construction",
            "type":"Services"
        }
    ],
    "sg:phone":"+1 517 487 8777",
    "sg:postcode":"48906",
    "sg:province":"MI",
    "sg:tags":[
        "house"
    ],
    "wof:name":"Eaton & Sons Construction",
    "wof:placetype":"venue"
},
  "geometry": {"coordinates":[-84.52933,42.746016],"type":"Point"}
}