{
  "type": "Feature",
  "properties": {
    "iso:country":"US",
    "sg:address":"31664 John R Rd",
    "sg:city":"Madison Heights",
    "sg:classifiers":[
        {
            "category":"Personal",
            "type":"Services"
        }
    ],
    "sg:phone":"+1 248 585 2569",
    "sg:postcode":"48071",
    "sg:province":"MI",
    "sg:tags":[
        "sewing",
        "alteration"
    ],
    "wof:name":"European Custom Tailors",
    "wof:placetype":"venue"
},
  "geometry": {"coordinates":[-83.106499,42.525002],"type":"Point"}
}