{
  "type": "Feature",
  "properties": {
    "iso:country":"US",
    "sg:address":"17900 Allen Rd",
    "sg:city":"Melvindale",
    "sg:classifiers":[
        {
            "category":"Restaurant",
            "type":"Food & Drink"
        }
    ],
    "sg:phone":"+1 313 383 6279",
    "sg:postcode":"48122",
    "sg:province":"MI",
    "sg:tags":[
        "italian"
    ],
    "wof:name":"Fredi's",
    "wof:placetype":"venue"
},
  "geometry": {"coordinates":[-83.18436800000001,42.285244],"type":"Point"}
}