{
  "type": "Feature",
  "properties": {
    "iso:country":"US",
    "sg:address":"1788 State Hwy 37 S",
    "sg:city":"Traverse City",
    "sg:classifiers":[
        {
            "category":"Shopping",
            "subcategory":"Bicycles & Sporting Goods",
            "type":"Retail Goods"
        }
    ],
    "sg:phone":"+1 231 943 4432",
    "sg:postcode":"49637",
    "sg:province":"MI",
    "sg:tags":[
        "equipment",
        "archery",
        "supply"
    ],
    "wof:name":"Gauthier's Archery",
    "wof:placetype":"venue"
},
  "geometry": {"coordinates":[-85.656261,44.660496],"type":"Point"}
}