{
  "type": "Feature",
  "properties": {
    "iso:country":"US",
    "sg:address":"4530 36th St SE",
    "sg:city":"Kentwood",
    "sg:classifiers":[
        {
            "category":"Freight",
            "type":"Transportation"
        }
    ],
    "sg:phone":"+1 616 954 2400",
    "sg:postcode":"49512",
    "sg:province":"MI",
    "sg:tags":[
        "trucking"
    ],
    "sg:website":"www.mywatkins.com",
    "wof:name":"Watkins Motor Lines",
    "wof:placetype":"venue"
},
  "geometry": {"coordinates":[-85.554906,42.89796],"type":"Point"}
}