{
  "type": "Feature",
  "properties": {
    "iso:country":"US",
    "sg:address":"1150 Rosewood St",
    "sg:city":"Ann Arbor",
    "sg:classifiers":[
        {
            "category":"Retail",
            "subcategory":"Auto Repair",
            "type":"Services"
        }
    ],
    "sg:phone":"+1 734 761 3517",
    "sg:postcode":"48104",
    "sg:province":"MI",
    "sg:tags":[
        "shop",
        "automotive",
        "general",
        "mechanic",
        "specializing"
    ],
    "wof:name":"Haner Motors Inc",
    "wof:placetype":"venue"
},
  "geometry": {"coordinates":[-83.733024,42.254912],"type":"Point"}
}