{
  "type": "Feature",
  "properties": {
    "iso:country":"US",
    "sg:address":"3521 State St",
    "sg:city":"Saginaw",
    "sg:classifiers":[
        {
            "category":"Social Services",
            "type":"Services"
        }
    ],
    "sg:phone":"+1 989 791 4066",
    "sg:postcode":"48602",
    "sg:province":"MI",
    "sg:tags":[
        "counselor",
        "marriage",
        "family"
    ],
    "wof:name":"Academy Of Counseling",
    "wof:placetype":"venue"
},
  "geometry": {"coordinates":[-83.990526,43.43658],"type":"Point"}
}