{
  "type": "Feature",
  "properties": {
    "iso:country":"US",
    "sg:address":"2490 Dixie Hwy",
    "sg:city":"Waterford",
    "sg:classifiers":[
        {
            "category":"Restaurant",
            "type":"Food & Drink"
        }
    ],
    "sg:menulink":"http://www.allmenus.com/mi/waterford/26939-big-boy-restaurants/menu/",
    "sg:phone":"+1 248 858 2265",
    "sg:postcode":"48328",
    "sg:province":"MI",
    "sg:tags":[
        "sandwich",
        "salad",
        "burger",
        "dog",
        "soup",
        "hot",
        "wrap",
        "american"
    ],
    "wof:name":"Big Boy Restaurants",
    "wof:placetype":"venue"
},
  "geometry": {"coordinates":[-83.336725,42.671128],"type":"Point"}
}