{
  "type": "Feature",
  "properties": {
    "iso:country":"US",
    "sg:address":"250 S Washington Ave",
    "sg:city":"Battle Creek",
    "sg:classifiers":[
        {
            "category":"Food & Beverages",
            "subcategory":"Groceries & Convenience Stores",
            "type":"Retail Goods"
        }
    ],
    "sg:phone":"+1 269 962 2098",
    "sg:postcode":"49015",
    "sg:province":"MI",
    "wof:name":"Drive Thru Party Factory",
    "wof:placetype":"venue"
},
  "geometry": {"coordinates":[-85.19470699999999,42.318318],"type":"Point"}
}