{
  "type": "Feature",
  "properties": {
    "iso:country":"US",
    "sg:address":"13300 W 7 Mile Rd",
    "sg:city":"Detroit",
    "sg:classifiers":[
        {
            "category":"Banks & Credit Unions",
            "subcategory":"Bank",
            "type":"Services"
        }
    ],
    "sg:phone":"+1 313 345 6080",
    "sg:postcode":"48235",
    "sg:province":"MI",
    "wof:name":"Home Federal Savings Bank",
    "wof:placetype":"venue"
},
  "geometry": {"coordinates":[-83.17739899999999,42.431301],"type":"Point"}
}