{
  "type": "Feature",
  "properties": {
    "iso:country":"US",
    "sg:address":"800 Cole Rd",
    "sg:city":"Monroe",
    "sg:classifiers":[
        {
            "category":"Shopping",
            "subcategory":"Gifts & Souvenirs",
            "type":"Retail Goods"
        }
    ],
    "sg:phone":"+1 734 241 8360",
    "sg:postcode":"48162",
    "sg:province":"MI",
    "sg:tags":[
        "party",
        "supply"
    ],
    "wof:name":"J T's Party Store",
    "wof:placetype":"venue"
},
  "geometry": {"coordinates":[-83.371893,41.939492],"type":"Point"}
}