{
  "type": "Feature",
  "properties": {
    "iso:country":"US",
    "sg:address":"1028 Ethel Ave",
    "sg:city":"Hancock",
    "sg:classifiers":[
        {
            "category":"Mining & Drilling",
            "type":"Manufacturing & Wholesale Goods"
        }
    ],
    "sg:phone":"+1 906 482 3130",
    "sg:postcode":"49930",
    "sg:province":"MI",
    "sg:tags":[
        "construction",
        "gravel"
    ],
    "wof:name":"Superior Sand & Gravel Inc",
    "wof:placetype":"venue"
},
  "geometry": {"coordinates":[-88.59979800000001,47.133823],"type":"Point"}
}