{
  "type": "Feature",
  "properties": {
    "iso:country":"US",
    "sg:address":"905 Putnam St",
    "sg:city":"Wakefield",
    "sg:classifiers":[
        {
            "category":"Bars & Pubs",
            "type":"Food & Drink"
        }
    ],
    "sg:phone":"+1 906 224 7051",
    "sg:postcode":"49968",
    "sg:province":"MI",
    "wof:name":"Crossing Inn",
    "wof:placetype":"venue"
},
  "geometry": {"coordinates":[-89.93592,46.47682],"type":"Point"}
}