{
  "type": "Feature",
  "properties": {
    "iso:country":"US",
    "sg:address":"630 E Lovell Dr",
    "sg:city":"Troy",
    "sg:phone":"+1 248 879 1150",
    "sg:postcode":"48085",
    "sg:province":"MI",
    "sg:tags":[
        "shelving"
    ],
    "wof:name":"Lista International Corp",
    "wof:placetype":"venue"
},
  "geometry": {"coordinates":[-83.13961399999999,42.617716],"type":"Point"}
}