{
  "type": "Feature",
  "properties": {
    "iso:country":"US",
    "sg:address":"7301 W Victoria Dr",
    "sg:city":"Laingsburg",
    "sg:classifiers":[
        {
            "category":"Professional",
            "subcategory":"Art Services",
            "type":"Services"
        }
    ],
    "sg:phone":"+1 517 651 2526",
    "sg:postcode":"48848",
    "sg:province":"MI",
    "sg:tags":[
        "commercial",
        "design"
    ],
    "wof:name":"Rk Graphics",
    "wof:placetype":"venue"
},
  "geometry": {"coordinates":[-84.374206,42.910069],"type":"Point"}
}