{
  "type": "Feature",
  "properties": {
    "iso:country":"US",
    "sg:address":"9032 Big Hand Rd",
    "sg:city":"Columbus",
    "sg:classifiers":[
        {
            "category":"Home & Garden",
            "subcategory":"Building Materials",
            "type":"Retail Goods"
        }
    ],
    "sg:phone":"+1 586 727 4717",
    "sg:postcode":"48063",
    "sg:province":"MI",
    "sg:tags":[
        "repair"
    ],
    "wof:name":"Richmond Motor Company",
    "wof:placetype":"venue"
},
  "geometry": {"coordinates":[-82.679778,42.84104],"type":"Point"}
}