{
  "type": "Feature",
  "properties": {
    "iso:country":"US",
    "sg:address":"45 Oregon St",
    "sg:city":"Ypsilanti",
    "sg:classifiers":[
        {
            "category":"Organizations",
            "subcategory":"Religious Organization",
            "type":"Services"
        }
    ],
    "sg:phone":"+1 734 485 0808",
    "sg:postcode":"48198",
    "sg:province":"MI",
    "wof:name":"Pentecostal Church of God",
    "wof:placetype":"venue"
},
  "geometry": {"coordinates":[-83.575829,42.241703],"type":"Point"}
}