{
  "type": "Feature",
  "properties": {
    "iso:country":"US",
    "sg:address":"22785 Macomb Industrial Dr",
    "sg:city":"Clinton Twp",
    "sg:classifiers":[
        {
            "category":"Manufacturing",
            "subcategory":"Tools & Machinery",
            "type":"Manufacturing & Wholesale Goods"
        }
    ],
    "sg:phone":"+1 586 465 7610",
    "sg:postcode":"48036",
    "sg:province":"MI",
    "sg:tags":[
        "die",
        "maker"
    ],
    "wof:name":"Anbo Tool & Mfg",
    "wof:placetype":"venue"
},
  "geometry": {"coordinates":[-82.882142,42.622606],"type":"Point"}
}