{
  "type": "Feature",
  "properties": {
    "iso:country":"US",
    "sg:address":"11276 E Lakewood Blvd",
    "sg:city":"Holland",
    "sg:classifiers":[
        {
            "category":"Social Services",
            "type":"Services"
        }
    ],
    "sg:phone":"+1 616 396 3949",
    "sg:postcode":"49424",
    "sg:province":"MI",
    "sg:tags":[
        "youth",
        "organization",
        "center"
    ],
    "wof:name":"Youth For Christ Donation Ctr",
    "wof:placetype":"venue"
},
  "geometry": {"coordinates":[-86.060024,42.804934],"type":"Point"}
}