{
  "type": "Feature",
  "properties": {
    "iso:country":"US",
    "sg:address":"1447 Orban",
    "sg:city":"Milford",
    "sg:classifiers":[
        {
            "category":"Sports & Exercise",
            "subcategory":"Race Track",
            "type":"Entertainment"
        }
    ],
    "sg:phone":"+1 248 889 3645",
    "sg:postcode":"48380",
    "sg:province":"MI",
    "sg:tags":[
        "operation",
        "racing",
        "or"
    ],
    "wof:name":"Parker Tech LLC",
    "wof:placetype":"venue"
},
  "geometry": {"coordinates":[-83.629705,42.626298],"type":"Point"}
}