{
  "type": "Feature",
  "properties": {
    "iso:country":"US",
    "sg:address":"3303 Canterbury Ave",
    "sg:city":"Kalamazoo",
    "sg:classifiers":[
        {
            "category":"Building & Trades",
            "subcategory":"Construction",
            "type":"Services"
        }
    ],
    "sg:phone":"+1 269 385 4413",
    "sg:postcode":"49006",
    "sg:province":"MI",
    "sg:tags":[
        "general",
        "contractor"
    ],
    "wof:name":"Custom Design Group",
    "wof:placetype":"venue"
},
  "geometry": {"coordinates":[-85.630281,42.300163],"type":"Point"}
}