{
  "type": "Feature",
  "properties": {
    "iso:country":"US",
    "sg:address":"7033 E Jefferson Ave",
    "sg:city":"Detroit",
    "sg:classifiers":[
        {
            "category":"Restaurant",
            "type":"Food & Drink"
        }
    ],
    "sg:phone":"+1 313 259 1360",
    "sg:postcode":"48207",
    "sg:province":"MI",
    "wof:name":"Big Boy Restaurants",
    "wof:placetype":"venue"
},
  "geometry": {"coordinates":[-83.002701,42.346901],"type":"Point"}
}