{
  "type": "Feature",
  "properties": {
    "iso:country":"US",
    "sg:address":"149 Crestwood Dr",
    "sg:city":"Holland",
    "sg:classifiers":[
        {
            "category":"Ferry",
            "type":"Transportation"
        }
    ],
    "sg:phone":"+1 616 399 8203",
    "sg:postcode":"49424",
    "sg:province":"MI",
    "sg:tags":[
        "boat"
    ],
    "wof:name":"Yacht Boat Charters",
    "wof:placetype":"venue"
},
  "geometry": {"coordinates":[-86.147976,42.79157],"type":"Point"}
}