{
  "type": "Feature",
  "properties": {
    "iso:country":"US",
    "sg:address":"3676 Dobie Rd",
    "sg:city":"Okemos",
    "sg:classifiers":[
        {
            "category":"Professional",
            "subcategory":"Management & Consulting",
            "type":"Services"
        }
    ],
    "sg:phone":"+1 517 204 2102",
    "sg:postcode":"48864",
    "sg:province":"MI",
    "sg:tags":[
        "business"
    ],
    "wof:name":"Nmx Consulting",
    "wof:placetype":"venue"
},
  "geometry": {"coordinates":[-84.410296,42.690238],"type":"Point"}
}