{
  "type": "Feature",
  "properties": {
    "iso:country":"US",
    "sg:address":"8540 S Clare Ave",
    "sg:city":"Clare",
    "sg:classifiers":[
        {
            "category":"Government",
            "subcategory":"Office",
            "type":"Public Place"
        }
    ],
    "sg:phone":"+1 989 386 4067",
    "sg:postcode":"48617",
    "sg:province":"MI",
    "sg:tags":[
        "state"
    ],
    "sg:website":"www.michigan.gov",
    "wof:name":"Dept Of Natural Resources",
    "wof:placetype":"venue"
},
  "geometry": {"coordinates":[-84.768128,43.86269],"type":"Point"}
}