{
  "type": "Feature",
  "properties": {
    "iso:country":"US",
    "sg:address":"20784 Curie Ave",
    "sg:city":"Warren",
    "sg:classifiers":[
        {
            "category":"Retail",
            "subcategory":"Repair Shop",
            "type":"Services"
        }
    ],
    "sg:phone":"+1 586 757 3227",
    "sg:postcode":"48091",
    "sg:province":"MI",
    "wof:name":"Sweep Away Personal Services",
    "wof:placetype":"venue"
},
  "geometry": {"coordinates":[-83.05107599999999,42.449479],"type":"Point"}
}