{
  "type": "Feature",
  "properties": {
    "iso:country":"US",
    "sg:address":"1627 Progress Ave",
    "sg:city":"Lincoln Park",
    "sg:classifiers":[
        {
            "category":"Shopping",
            "subcategory":"Gifts & Souvenirs",
            "type":"Retail Goods"
        }
    ],
    "sg:phone":"+1 313 386 4474",
    "sg:postcode":"48146",
    "sg:province":"MI",
    "wof:name":"Mary Jane Gifts",
    "wof:placetype":"venue"
},
  "geometry": {"coordinates":[-83.18751399999999,42.243114],"type":"Point"}
}