{
  "type": "Feature",
  "properties": {
    "iso:country":"US",
    "sg:address":"883 Capital Ave SW",
    "sg:city":"Battle Creek",
    "sg:classifiers":[
        {
            "category":"Real Estate",
            "subcategory":"Real Estate Agent",
            "type":"Services"
        }
    ],
    "sg:phone":"+1 269 660 0033",
    "sg:postcode":"49015",
    "sg:province":"MI",
    "sg:website":"www.homestylerealty.com",
    "wof:name":"Homestyle Realty",
    "wof:placetype":"venue"
},
  "geometry": {"coordinates":[-85.19929399999999,42.29767],"type":"Point"}
}