{
  "type": "Feature",
  "properties": {
    "iso:country":"US",
    "sg:address":"17200 E 10 Mile Rd",
    "sg:city":"Eastpointe",
    "sg:classifiers":[
        {
            "category":"Professional",
            "subcategory":"Lawyer & Legal Services",
            "type":"Services"
        }
    ],
    "sg:phone":"+1 586 775 5578",
    "sg:postcode":"48021",
    "sg:province":"MI",
    "sg:tags":[
        "attorney"
    ],
    "wof:name":"Darke & Wilson",
    "wof:placetype":"venue"
},
  "geometry": {"coordinates":[-82.942802,42.479801],"type":"Point"}
}