{
  "type": "Feature",
  "properties": {
    "iso:country":"US",
    "sg:address":"624 S Cedar St",
    "sg:city":"Mason",
    "sg:classifiers":[
        {
            "category":"Social Services",
            "subcategory":"Child Care",
            "type":"Services"
        }
    ],
    "sg:phone":"+1 517 676 2221",
    "sg:postcode":"48854",
    "sg:province":"MI",
    "sg:tags":[
        "day"
    ],
    "wof:name":"Colts Fillys Child Child Care",
    "wof:placetype":"venue"
},
  "geometry": {"coordinates":[-84.452915,42.575127],"type":"Point"}
}