{
  "type": "Feature",
  "properties": {
    "iso:country":"US",
    "sg:address":"326 Tawas St",
    "sg:city":"East Tawas",
    "sg:classifiers":[
        {
            "category":"Government",
            "subcategory":"Post Office",
            "type":"Public Place"
        }
    ],
    "sg:phone":"+1 989 000 1111",
    "sg:postcode":"48730",
    "sg:province":"MI",
    "wof:name":"US Post Office",
    "wof:placetype":"venue"
},
  "geometry": {"coordinates":[-83.488816,44.283196],"type":"Point"}
}