{
  "type": "Feature",
  "properties": {
    "iso:country":"US",
    "sg:address":"23514 Groesbeck Hwy",
    "sg:city":"Warren",
    "sg:classifiers":[
        {
            "category":"Manufacturing",
            "subcategory":"Tools & Machinery",
            "type":"Manufacturing & Wholesale Goods"
        }
    ],
    "sg:phone":"+1 586 778 6777",
    "sg:postcode":"48089",
    "sg:province":"MI",
    "sg:tags":[
        "industry",
        "aerospace"
    ],
    "wof:name":"Ppi Aerospace Inc",
    "wof:placetype":"venue"
},
  "geometry": {"coordinates":[-82.989428,42.46572],"type":"Point"}
}