{
  "type": "Feature",
  "properties": {
    "iso:country":"US",
    "sg:address":"3949 Oak Dr",
    "sg:city":"Ypsilanti",
    "sg:classifiers":[
        {
            "category":"Retail",
            "subcategory":"Car Wash",
            "type":"Services"
        }
    ],
    "sg:phone":"+1 734 971 7487",
    "sg:postcode":"48197",
    "sg:province":"MI",
    "sg:tags":[
        "carwash"
    ],
    "wof:name":"Hub A Scrub",
    "wof:placetype":"venue"
},
  "geometry": {"coordinates":[-83.661851,42.232908],"type":"Point"}
}