{
  "type": "Feature",
  "properties": {
    "iso:country":"US",
    "sg:address":"3611 Bent Trail Dr",
    "sg:city":"Ann Arbor",
    "sg:classifiers":[
        {
            "category":"Professional",
            "subcategory":"Business Services",
            "type":"Services"
        }
    ],
    "sg:phone":"+1 734 214 9706",
    "sg:postcode":"48108",
    "sg:province":"MI",
    "wof:name":"Rebecca Lezenson",
    "wof:placetype":"venue"
},
  "geometry": {"coordinates":[-83.770877,42.235903],"type":"Point"}
}