{
  "type": "Feature",
  "properties": {
    "iso:country":"US",
    "sg:address":"17890 Brucker St",
    "sg:city":"Grand Haven",
    "sg:classifiers":[
        {
            "category":"Building & Trades",
            "subcategory":"Construction",
            "type":"Services"
        }
    ],
    "sg:phone":"+1 616 846 5206",
    "sg:postcode":"49417",
    "sg:province":"MI",
    "sg:tags":[
        "house"
    ],
    "wof:name":"Laughead Construction Inc",
    "wof:placetype":"venue"
},
  "geometry": {"coordinates":[-86.232201,43.03346],"type":"Point"}
}