{
  "type": "Feature",
  "properties": {
    "iso:country":"US",
    "sg:address":"1530 McLaughlin Ave",
    "sg:city":"Muskegon",
    "sg:classifiers":[
        {
            "category":"Social Services",
            "subcategory":"Adult Care",
            "type":"Services"
        }
    ],
    "sg:phone":"+1 231 777 3494",
    "sg:postcode":"49442",
    "sg:province":"MI",
    "sg:tags":[
        "home",
        "aged",
        "for"
    ],
    "wof:name":"Christian Care",
    "wof:placetype":"venue"
},
  "geometry": {"coordinates":[-86.207289,43.230648],"type":"Point"}
}