{
  "type": "Feature",
  "properties": {
    "iso:country":"US",
    "sg:address":"1747 Eppenbrock Rd",
    "sg:city":"Harbor Beach",
    "sg:classifiers":[
        {
            "category":"Personal",
            "subcategory":"Beauty Salon",
            "type":"Services"
        }
    ],
    "sg:phone":"+1 989 479 6880",
    "sg:postcode":"48441",
    "sg:province":"MI",
    "sg:tags":[
        "shop"
    ],
    "wof:name":"A Cut Above",
    "wof:placetype":"venue"
},
  "geometry": {"coordinates":[-82.721988,43.795631],"type":"Point"}
}