{
  "type": "Feature",
  "properties": {
    "iso:country":"US",
    "sg:address":"378 Old 51",
    "sg:city":"Carsonville",
    "sg:classifiers":[
        {
            "category":"Autos & Motor Vehicles",
            "subcategory":"Auto Supplies",
            "type":"Retail Goods"
        }
    ],
    "sg:phone":"+1 810 657 9105",
    "sg:postcode":"48419",
    "sg:province":"MI",
    "sg:tags":[
        "automobile",
        "stereo",
        "radio"
    ],
    "wof:name":"Jones Sound Shop",
    "wof:placetype":"venue"
},
  "geometry": {"coordinates":[-82.671352,43.416549],"type":"Point"}
}