{
  "type": "Feature",
  "properties": {
    "iso:country":"US",
    "sg:address":"816 N 3rd St",
    "sg:city":"Marquette",
    "sg:classifiers":[
        {
            "category":"Personal",
            "subcategory":"Beauty Salon",
            "type":"Services"
        }
    ],
    "sg:phone":"+1 906 226 3602",
    "sg:postcode":"49855",
    "sg:province":"MI",
    "sg:tags":[
        "shop"
    ],
    "wof:name":"Profiles In Hair Design",
    "wof:placetype":"venue"
},
  "geometry": {"coordinates":[-87.39467999999999,46.551016],"type":"Point"}
}