{
  "type": "Feature",
  "properties": {
    "iso:country":"US",
    "sg:address":"38456 S Seajay Row",
    "sg:city":"Drummond Island",
    "sg:classifiers":[
        {
            "category":"Professional",
            "subcategory":"Management & Consulting",
            "type":"Services"
        }
    ],
    "sg:phone":"+1 906 493 6517",
    "sg:postcode":"49726",
    "sg:province":"MI",
    "sg:tags":[
        "consultant",
        "business"
    ],
    "wof:name":"Pathfinders Consulting Svc",
    "wof:placetype":"venue"
},
  "geometry": {"coordinates":[-83.808483,45.947986],"type":"Point"}
}