{
  "type": "Feature",
  "properties": {
    "iso:country":"US",
    "sg:address":"620 E Colby St",
    "sg:city":"Whitehall",
    "sg:classifiers":[
        {
            "category":"Restaurant",
            "type":"Food & Drink"
        }
    ],
    "sg:phone":"+1 231 893 3663",
    "sg:postcode":"49461",
    "sg:province":"MI",
    "wof:name":"Morning Glory Cafe",
    "wof:placetype":"venue"
},
  "geometry": {"coordinates":[-86.339237,43.40959],"type":"Point"}
}