{
  "type": "Feature",
  "properties": {
    "iso:country":"US",
    "sg:address":"257 Lakeshore Dr N",
    "sg:city":"Manistee",
    "sg:classifiers":[
        {
            "category":"Personal",
            "type":"Services"
        }
    ],
    "sg:phone":"+1 231 398 9426",
    "sg:postcode":"49660",
    "sg:province":"MI",
    "wof:name":"Preferd Theraptc Messg Thrpy",
    "wof:placetype":"venue"
},
  "geometry": {"coordinates":[-86.33736500000001,44.252363],"type":"Point"}
}