{
  "type": "Feature",
  "properties": {
    "iso:country":"US",
    "sg:address":"224 Barrington Cir",
    "sg:city":"Lake Orion",
    "sg:classifiers":[
        {
            "category":"Personal",
            "subcategory":"Beauty Salon",
            "type":"Services"
        }
    ],
    "sg:phone":"+1 248 693 0398",
    "sg:postcode":"48360",
    "sg:province":"MI",
    "sg:tags":[
        "shop"
    ],
    "wof:name":"Pompnonis Hair Shop",
    "wof:placetype":"venue"
},
  "geometry": {"coordinates":[-83.248138,42.756663],"type":"Point"}
}