{
  "type": "Feature",
  "properties": {
    "iso:country":"US",
    "sg:address":"600 E Cloverland Dr",
    "sg:city":"Ironwood",
    "sg:classifiers":[
        {
            "category":"Shopping",
            "subcategory":"Hobbies, Toys, & Games",
            "type":"Retail Goods"
        }
    ],
    "sg:phone":"+1 906 932 7340",
    "sg:postcode":"49938",
    "sg:province":"MI",
    "sg:tags":[
        "shop",
        "rock"
    ],
    "wof:name":"Nature's Picks",
    "wof:placetype":"venue"
},
  "geometry": {"coordinates":[-90.161817,46.463286],"type":"Point"}
}