{
  "type": "Feature",
  "properties": {
    "iso:country":"US",
    "sg:address":"2901 Niles Ave",
    "sg:city":"Saint Joseph",
    "sg:classifiers":[
        {
            "category":"Ice Cream",
            "type":"Food & Drink"
        }
    ],
    "sg:menulink":"http://www.allmenus.com/mi/st-joseph/168168-dairy-queen/menu/",
    "sg:phone":"+1 269 983 1319",
    "sg:postcode":"49085",
    "sg:province":"MI",
    "sg:tags":[
        "burger",
        "american"
    ],
    "wof:name":"Dairy Queen",
    "wof:placetype":"venue"
},
  "geometry": {"coordinates":[-86.48544699999999,42.083506],"type":"Point"}
}