{
  "type": "Feature",
  "properties": {
    "iso:country":"US",
    "sg:address":"40 Sylvan Ave",
    "sg:city":"Pleasant Ridge",
    "sg:classifiers":[
        {
            "category":"Professional",
            "subcategory":"Management & Consulting",
            "type":"Services"
        }
    ],
    "sg:phone":"+1 248 544 2073",
    "sg:postcode":"48069",
    "sg:province":"MI",
    "sg:tags":[
        "consultant"
    ],
    "wof:name":"Zendler Environmental Inc",
    "wof:placetype":"venue"
},
  "geometry": {"coordinates":[-83.137421,42.470304],"type":"Point"}
}