{
  "type": "Feature",
  "properties": {
    "iso:country":"US",
    "sg:address":"2215 John B Ave",
    "sg:city":"Warren",
    "sg:classifiers":[
        {
            "category":"Wholesale",
            "subcategory":"Non-durable Goods",
            "type":"Manufacturing & Wholesale Goods"
        },
        {
            "category":"Shopping",
            "subcategory":"Beauty & Cosmetics",
            "type":"Retail Goods"
        },
        {
            "category":"Personal",
            "subcategory":"Barber",
            "type":"Services"
        }
    ],
    "sg:phone":"+1 586 757 2256",
    "sg:postcode":"48091",
    "sg:province":"MI",
    "sg:tags":[
        "equipment",
        "manufacturer",
        "supplies-wholesale",
        "salons-equipment",
        "supply"
    ],
    "wof:name":"Nubian Beauty Supply",
    "wof:placetype":"venue"
},
  "geometry": {"coordinates":[-83.080078,42.449202],"type":"Point"}
}