{
  "type": "Feature",
  "properties": {
    "iso:country":"US",
    "sg:address":"4499 Davison Rd",
    "sg:city":"Burton",
    "sg:classifiers":[
        {
            "category":"Building & Trades",
            "subcategory":"Construction",
            "type":"Services"
        }
    ],
    "sg:phone":"+1 810 715 0261",
    "sg:postcode":"48509",
    "sg:province":"MI",
    "sg:tags":[
        "waterproofing",
        "contractor"
    ],
    "wof:name":"Foundation Stabilization Co",
    "wof:placetype":"venue"
},
  "geometry": {"coordinates":[-83.61629000000001,43.033127],"type":"Point"}
}