{
  "type": "Feature",
  "properties": {
    "iso:country":"US",
    "sg:address":"3087 Margaret St",
    "sg:city":"Auburn Hills",
    "sg:classifiers":[
        {
            "category":"Building & Trades",
            "subcategory":"Construction",
            "type":"Services"
        }
    ],
    "sg:phone":"+1 248 299 5568",
    "sg:postcode":"48326",
    "sg:province":"MI",
    "sg:tags":[
        "dry wall",
        "contractor"
    ],
    "wof:name":"Dan Whitemore Drywall",
    "wof:placetype":"venue"
},
  "geometry": {"coordinates":[-83.226553,42.628179],"type":"Point"}
}