{
  "type": "Feature",
  "properties": {
    "iso:country":"US",
    "sg:address":"9212 N Dort Hwy",
    "sg:city":"Mt Morris",
    "sg:classifiers":[
        {
            "category":"Home & Garden",
            "subcategory":"Furniture",
            "type":"Retail Goods"
        }
    ],
    "sg:phone":"+1 810 686 6820",
    "sg:postcode":"48458",
    "sg:province":"MI",
    "wof:name":"Cole Furniture Ctr",
    "wof:placetype":"venue"
},
  "geometry": {"coordinates":[-83.686825,43.13886],"type":"Point"}
}