{
  "type": "Feature",
  "properties": {
    "iso:country":"US",
    "sg:address":"4400 Dryden Rd",
    "sg:city":"Dryden",
    "sg:classifiers":[
        {
            "category":"Building & Trades",
            "subcategory":"Construction",
            "type":"Services"
        }
    ],
    "sg:phone":"+1 810 796 3917",
    "sg:postcode":"48428",
    "sg:province":"MI",
    "sg:tags":[
        "excavating",
        "contractor"
    ],
    "wof:name":"Dryden Excavating",
    "wof:placetype":"venue"
},
  "geometry": {"coordinates":[-83.174651,42.944627],"type":"Point"}
}