{
  "type": "Feature",
  "properties": {
    "iso:country":"US",
    "sg:address":"10300 Tyler St",
    "sg:city":"Zeeland",
    "sg:classifiers":[
        {
            "category":"Farming",
            "subcategory":"Nursery",
            "type":"Manufacturing & Wholesale Goods"
        }
    ],
    "sg:phone":"+1 616 875 6100",
    "sg:postcode":"49464",
    "sg:province":"MI",
    "sg:tags":[
        "ornamental"
    ],
    "wof:name":"Independent Climbing Service",
    "wof:placetype":"venue"
},
  "geometry": {"coordinates":[-86.038449,42.899365],"type":"Point"}
}