{
  "type": "Feature",
  "properties": {
    "iso:country":"US",
    "sg:address":"64892 Gratiot Ave",
    "sg:city":"Lenox",
    "sg:classifiers":[
        {
            "category":"Organizations",
            "subcategory":"Religious Organization",
            "type":"Services"
        }
    ],
    "sg:phone":"+1 586 727 7250",
    "sg:postcode":"48050",
    "sg:province":"MI",
    "sg:tags":[
        "church"
    ],
    "wof:name":"Richmond Assembly Of God Chr",
    "wof:placetype":"venue"
},
  "geometry": {"coordinates":[-82.75189899999999,42.778962],"type":"Point"}
}