{
  "type": "Feature",
  "properties": {
    "iso:country":"US",
    "sg:address":"2204 Turner Ave NW",
    "sg:city":"Grand Rapids",
    "sg:classifiers":[
        {
            "category":"Building & Trades",
            "subcategory":"Electrical",
            "type":"Services"
        }
    ],
    "sg:phone":"+1 616 451 2701",
    "sg:postcode":"49544",
    "sg:province":"MI",
    "sg:tags":[
        "electric",
        "contractor"
    ],
    "wof:name":"Graybar Electric Co",
    "wof:placetype":"venue"
},
  "geometry": {"coordinates":[-85.678595,43.003049],"type":"Point"}
}