{
  "type": "Feature",
  "properties": {
    "iso:country":"US",
    "sg:address":"36343 Ford Rd",
    "sg:city":"Westland",
    "sg:classifiers":[
        {
            "category":"Retail",
            "subcategory":"Veterinary Services",
            "type":"Services"
        }
    ],
    "sg:phone":"+1 734 728 2520",
    "sg:postcode":"48185",
    "sg:province":"MI",
    "sg:tags":[
        "veterinarian"
    ],
    "sg:website":"www.griffithvet.com",
    "wof:name":"Griffith Veterinary Hospital",
    "wof:placetype":"venue"
},
  "geometry": {"coordinates":[-83.398697,42.3242],"type":"Point"}
}