{
  "type": "Feature",
  "properties": {
    "iso:country":"US",
    "sg:address":"24730 Rockford St",
    "sg:city":"Dearborn",
    "sg:classifiers":[
        {
            "category":"Building & Trades",
            "subcategory":"Construction",
            "type":"Services"
        }
    ],
    "sg:phone":"+1 313 274 7284",
    "sg:postcode":"48124",
    "sg:province":"MI",
    "sg:tags":[
        "general",
        "remodeling",
        "contractor"
    ],
    "wof:name":"Rj Hendricks Home Improvement",
    "wof:placetype":"venue"
},
  "geometry": {"coordinates":[-83.27923800000001,42.30888],"type":"Point"}
}