{
  "type": "Feature",
  "properties": {
    "iso:country":"US",
    "sg:address":"46146 Snowbird Dr",
    "sg:city":"Macomb",
    "sg:classifiers":[
        {
            "category":"Professional",
            "type":"Services"
        }
    ],
    "sg:phone":"+1 586 566 4907",
    "sg:postcode":"48044",
    "sg:province":"MI",
    "wof:name":"Mariann Abate",
    "wof:placetype":"venue"
},
  "geometry": {"coordinates":[-82.970282,42.636038],"type":"Point"}
}