{
  "type": "Feature",
  "properties": {
    "iso:country":"US",
    "sg:address":"1468 Mason St",
    "sg:city":"Dansville",
    "sg:classifiers":[
        {
            "category":"Professional",
            "subcategory":"Computer Services",
            "type":"Services"
        }
    ],
    "sg:phone":"+1 517 202 8724",
    "sg:postcode":"48819",
    "sg:province":"MI",
    "sg:tags":[
        "programing",
        "custom"
    ],
    "wof:name":"H & H Electronics",
    "wof:placetype":"venue"
},
  "geometry": {"coordinates":[-84.298731,42.55578],"type":"Point"}
}