{
  "type": "Feature",
  "properties": {
    "iso:country":"US",
    "sg:address":"1521 N Telegraph Rd",
    "sg:city":"Monroe",
    "sg:classifiers":[
        {
            "category":"Personal",
            "subcategory":"Beauty Salon",
            "type":"Services"
        }
    ],
    "sg:phone":"+1 734 457 5515",
    "sg:postcode":"48162",
    "sg:province":"MI",
    "sg:tags":[
        "shop"
    ],
    "wof:name":"Nail Tech",
    "wof:placetype":"venue"
},
  "geometry": {"coordinates":[-83.405877,41.939545],"type":"Point"}
}