{
  "type": "Feature",
  "properties": {
    "iso:country":"US",
    "sg:address":"3406 Fenkell St",
    "sg:city":"Detroit",
    "sg:classifiers":[
        {
            "category":"Food & Beverages",
            "subcategory":"Liquor & Beverages",
            "type":"Retail Goods"
        }
    ],
    "sg:phone":"+1 313 342 2026",
    "sg:postcode":"48238",
    "sg:province":"MI",
    "sg:tags":[
        "beer",
        "spirit",
        "wine"
    ],
    "wof:name":"Trade Fair Market",
    "wof:placetype":"venue"
},
  "geometry": {"coordinates":[-83.134598,42.402901],"type":"Point"}
}