{
  "type": "Feature",
  "properties": {
    "iso:country":"US",
    "sg:address":"3202 Old Farm Ln",
    "sg:city":"Commerce Twp",
    "sg:classifiers":[
        {
            "category":"Wholesale",
            "subcategory":"Stationery",
            "type":"Manufacturing & Wholesale Goods"
        }
    ],
    "sg:phone":"+1 248 960 3320",
    "sg:postcode":"48390",
    "sg:province":"MI",
    "sg:tags":[
        "product",
        "paper"
    ],
    "wof:name":"Expert Paper & Packaging",
    "wof:placetype":"venue"
},
  "geometry": {"coordinates":[-83.44297,42.570711],"type":"Point"}
}