{
  "type": "Feature",
  "properties": {
    "iso:country":"US",
    "sg:address":"4103 Cornell Rd",
    "sg:city":"Okemos",
    "sg:classifiers":[
        {
            "category":"Professional",
            "subcategory":"Computer Services",
            "type":"Services"
        },
        {
            "category":"Shopping",
            "subcategory":"Computers & Home Electronics",
            "type":"Retail Goods"
        }
    ],
    "sg:phone":"+1 517 347 7170",
    "sg:postcode":"48864",
    "sg:province":"MI",
    "sg:tags":[
        "consultant",
        "designer",
        "programing",
        "custom"
    ],
    "wof:name":"Software Conceptions Inc",
    "wof:placetype":"venue"
},
  "geometry": {"coordinates":[-84.39309,42.699053],"type":"Point"}
}