{
  "type": "Feature",
  "properties": {
    "iso:country":"US",
    "sg:address":"5560 Delmas Rd",
    "sg:city":"Clarkston",
    "sg:classifiers":[
        {
            "category":"Professional",
            "subcategory":"Business Services",
            "type":"Services"
        }
    ],
    "sg:phone":"+1 248 214 1565",
    "sg:postcode":"48348",
    "sg:province":"MI",
    "wof:name":"A I Infosys Inc",
    "wof:placetype":"venue"
},
  "geometry": {"coordinates":[-83.374566,42.771496],"type":"Point"}
}