{
  "type": "Feature",
  "properties": {
    "iso:country":"US",
    "sg:address":"28380 Lange Rd",
    "sg:city":"Chesterfield",
    "sg:classifiers":[
        {
            "category":"Professional",
            "subcategory":"Business Services",
            "type":"Services"
        }
    ],
    "sg:phone":"+1 586 468 7207",
    "sg:postcode":"48047",
    "sg:province":"MI",
    "sg:tags":[
        "transcribing",
        "disc"
    ],
    "wof:name":"Windows Of Heaven Inc",
    "wof:placetype":"venue"
},
  "geometry": {"coordinates":[-82.826188,42.658162],"type":"Point"}
}