{
  "type": "Feature",
  "properties": {
    "iso:country":"US",
    "sg:address":"1008 Cleveland Ave",
    "sg:city":"Lincoln Park",
    "sg:classifiers":[
        {
            "category":"Building & Trades",
            "subcategory":"Construction",
            "type":"Services"
        }
    ],
    "sg:phone":"+1 313 388 9018",
    "sg:postcode":"48146",
    "sg:province":"MI",
    "sg:tags":[
        "contractor"
    ],
    "wof:name":"Northern Lights Carpentry",
    "wof:placetype":"venue"
},
  "geometry": {"coordinates":[-83.174018,42.244528],"type":"Point"}
}