{
  "type": "Feature",
  "properties": {
    "iso:country":"US",
    "sg:address":"203 W Main St",
    "sg:city":"Carson City",
    "sg:classifiers":[
        {
            "category":"Retail",
            "subcategory":"Auto Repair",
            "type":"Services"
        }
    ],
    "sg:phone":"+1 989 584 6725",
    "sg:postcode":"48811",
    "sg:province":"MI",
    "sg:tags":[
        "repairing",
        "automobile"
    ],
    "wof:name":"Hevel AUTO Repair",
    "wof:placetype":"venue"
},
  "geometry": {"coordinates":[-84.84896999999999,43.177029],"type":"Point"}
}