{
  "type": "Feature",
  "properties": {
    "iso:country":"US",
    "sg:address":"1830 Terminal Rd",
    "sg:city":"Niles",
    "sg:classifiers":[
        {
            "category":"Professional",
            "type":"Services"
        }
    ],
    "sg:phone":"+1 269 684 5060",
    "sg:postcode":"49120",
    "sg:province":"MI",
    "wof:name":"Carapace Inc",
    "wof:placetype":"venue"
},
  "geometry": {"coordinates":[-86.227384,41.853664],"type":"Point"}
}