{
  "type": "Feature",
  "properties": {
    "iso:country":"US",
    "sg:address":"3137 S Baker Side Rd",
    "sg:city":"Sault Ste Marie",
    "sg:classifiers":[
        {
            "category":"Wholesale",
            "subcategory":"Construction Materials",
            "type":"Manufacturing & Wholesale Goods"
        }
    ],
    "sg:phone":"+1 906 635 1731",
    "sg:postcode":"49783",
    "sg:province":"MI",
    "sg:tags":[
        "fence"
    ],
    "wof:name":"D & S Fence",
    "wof:placetype":"venue"
},
  "geometry": {"coordinates":[-84.405089,46.455901],"type":"Point"}
}