{
  "type": "Feature",
  "properties": {
    "iso:country":"US",
    "sg:address":"326 E Hoover Ave",
    "sg:city":"Ann Arbor",
    "sg:classifiers":[
        {
            "category":"Education",
            "subcategory":"College",
            "type":"Public Place"
        }
    ],
    "sg:phone":"+1 734 764 8294",
    "sg:postcode":"48104",
    "sg:province":"MI",
    "wof:name":"Interior Design",
    "wof:placetype":"venue"
},
  "geometry": {"coordinates":[-83.747338,42.269383],"type":"Point"}
}