{
  "type": "Feature",
  "properties": {
    "iso:country":"US",
    "sg:address":"1295 S 11th St",
    "sg:city":"Niles",
    "sg:classifiers":[
        {
            "category":"Restaurant",
            "type":"Food & Drink"
        }
    ],
    "sg:menulink":"http://www.allmenus.com/mi/niles/176524-kfc---kentucky-fried-chicken/menu/",
    "sg:phone":"+1 616 683 1530",
    "sg:postcode":"49120",
    "sg:province":"MI",
    "sg:tags":[
        "american",
        "chicken"
    ],
    "wof:name":"KFC - Kentucky Fried Chicken",
    "wof:placetype":"venue"
},
  "geometry": {"coordinates":[-86.24805499999999,41.812563],"type":"Point"}
}