{
  "type": "Feature",
  "properties": {
    "iso:country":"US",
    "sg:address":"5323 E Court St N",
    "sg:city":"Burton",
    "sg:classifiers":[
        {
            "category":"Banks & Credit Unions",
            "subcategory":"Bank",
            "type":"Services"
        }
    ],
    "sg:phone":"+1 810 743 3378",
    "sg:postcode":"48509",
    "sg:province":"MI",
    "wof:name":"Bank Of America",
    "wof:placetype":"venue"
},
  "geometry": {"coordinates":[-83.61286699999999,43.019213],"type":"Point"}
}