{
  "type": "Feature",
  "properties": {
    "iso:country":"US",
    "sg:address":"1101 N Chevrolet Ave",
    "sg:city":"Flint",
    "sg:classifiers":[
        {
            "category":"Professional",
            "subcategory":"Accounting & Tax Preparation",
            "type":"Services"
        }
    ],
    "sg:phone":"+1 810 232 3557",
    "sg:postcode":"48504",
    "sg:province":"MI",
    "sg:tags":[
        "return",
        "filing"
    ],
    "wof:name":"Liberty Tax Svc",
    "wof:placetype":"venue"
},
  "geometry": {"coordinates":[-83.721232,43.022458],"type":"Point"}
}