{
  "type": "Feature",
  "properties": {
    "iso:country":"US",
    "sg:address":"682 S Angola Rd",
    "sg:city":"Coldwater",
    "sg:classifiers":[
        {
            "category":"Real Estate",
            "subcategory":"Real Estate Operator",
            "type":"Services"
        }
    ],
    "sg:phone":"+1 517 238 2567",
    "sg:postcode":"49036",
    "sg:province":"MI",
    "sg:tags":[
        "property",
        "lessor"
    ],
    "wof:name":"Madge Scheidler",
    "wof:placetype":"venue"
},
  "geometry": {"coordinates":[-85.005104,41.81369],"type":"Point"}
}