{
  "type": "Feature",
  "properties": {
    "iso:country":"US",
    "sg:address":"1600 Boulder Lake Dr",
    "sg:city":"Milford",
    "sg:classifiers":[
        {
            "category":"Professional",
            "subcategory":"Management & Consulting",
            "type":"Services"
        }
    ],
    "sg:phone":"+1 248 684 5628",
    "sg:postcode":"48380",
    "sg:province":"MI",
    "wof:name":"Elements Marketing LLC",
    "wof:placetype":"venue"
},
  "geometry": {"coordinates":[-83.649176,42.600524],"type":"Point"}
}