{
  "type": "Feature",
  "properties": {
    "iso:country":"US",
    "sg:address":"6551 Grand River Ave",
    "sg:city":"Detroit",
    "sg:classifiers":[
        {
            "category":"Personal",
            "type":"Services"
        }
    ],
    "sg:phone":"+1 313 895 0249",
    "sg:postcode":"48208",
    "sg:province":"MI",
    "sg:tags":[
        "towing"
    ],
    "wof:name":"Precise Towing",
    "wof:placetype":"venue"
},
  "geometry": {"coordinates":[-83.110462,42.357213],"type":"Point"}
}