{
  "type": "Feature",
  "properties": {
    "iso:country":"US",
    "sg:address":"5970 Shaftsburg Rd",
    "sg:city":"Williamston",
    "sg:classifiers":[
        {
            "category":"Organizations",
            "subcategory":"Membership Organization",
            "type":"Services"
        }
    ],
    "sg:phone":"+1 517 655 2493",
    "sg:postcode":"48895",
    "sg:province":"MI",
    "wof:name":"Michigan Steam Engine & Train",
    "wof:placetype":"venue"
},
  "geometry": {"coordinates":[-84.27103700000001,42.764604],"type":"Point"}
}