{
  "type": "Feature",
  "properties": {
    "iso:country":"US",
    "sg:address":"413 S Kalamazoo St",
    "sg:city":"Paw Paw",
    "sg:classifiers":[
        {
            "category":"Retail",
            "subcategory":"Auto Repair",
            "type":"Services"
        }
    ],
    "sg:phone":"+1 269 657 7063",
    "sg:postcode":"49079",
    "sg:province":"MI",
    "sg:tags":[
        "automotive"
    ],
    "wof:name":"Dr Lube",
    "wof:placetype":"venue"
},
  "geometry": {"coordinates":[-85.891187,42.214824],"type":"Point"}
}