{
  "type": "Feature",
  "properties": {
    "iso:country":"US",
    "sg:address":"42778 Mound Rd",
    "sg:city":"Sterling Heights",
    "sg:classifiers":[
        {
            "category":"Building & Trades",
            "subcategory":"Construction",
            "type":"Services"
        }
    ],
    "sg:phone":"+1 586 726 8655",
    "sg:postcode":"48314",
    "sg:province":"MI",
    "sg:tags":[
        "maintenance",
        "contractor"
    ],
    "wof:name":"First Class Mntnc Systems LLC",
    "wof:placetype":"venue"
},
  "geometry": {"coordinates":[-83.05105,42.608711],"type":"Point"}
}