{
  "type": "Feature",
  "properties": {
    "iso:country":"US",
    "sg:address":"4905 Burgis Ave SE",
    "sg:city":"Grand Rapids",
    "sg:classifiers":[
        {
            "category":"Social Services",
            "subcategory":"Child Care",
            "type":"Services"
        }
    ],
    "sg:phone":"+1 616 538 6117",
    "sg:postcode":"49508",
    "sg:province":"MI",
    "sg:tags":[
        "day"
    ],
    "wof:name":"Denise Ann Herrema",
    "wof:placetype":"venue"
},
  "geometry": {"coordinates":[-85.638328,42.874643],"type":"Point"}
}