{
  "type": "Feature",
  "properties": {
    "iso:country":"US",
    "sg:address":"2074 S Custer Rd",
    "sg:city":"Monroe",
    "sg:classifiers":[
        {
            "category":"Organizations",
            "subcategory":"Political Organization",
            "type":"Services"
        }
    ],
    "sg:phone":"+1 734 457 1994",
    "sg:postcode":"48161",
    "sg:province":"MI",
    "wof:name":"Monroe County Republican Party",
    "wof:placetype":"venue"
},
  "geometry": {"coordinates":[-83.428594,41.921762],"type":"Point"}
}