{
  "type": "Feature",
  "properties": {
    "iso:country":"US",
    "sg:address":"914 Georgia Ave",
    "sg:city":"Marysville",
    "sg:classifiers":[
        {
            "category":"Building & Trades",
            "subcategory":"Pest Control",
            "type":"Services"
        }
    ],
    "sg:phone":"+1 810 982 1678",
    "sg:postcode":"48040",
    "sg:province":"MI",
    "wof:name":"Rox Ex Port Huron Pest Control",
    "wof:placetype":"venue"
},
  "geometry": {"coordinates":[-82.492862,42.9162],"type":"Point"}
}