{
  "type": "Feature",
  "properties": {
    "iso:country":"US",
    "sg:address":"32681 Mackenzie Dr",
    "sg:city":"Westland",
    "sg:classifiers":[
        {
            "category":"Professional",
            "subcategory":"Management & Consulting",
            "type":"Services"
        }
    ],
    "sg:phone":"+1 734 422 9309",
    "sg:postcode":"48185",
    "sg:province":"MI",
    "wof:name":"Brodie Mgmt Co",
    "wof:placetype":"venue"
},
  "geometry": {"coordinates":[-83.36275000000001,42.34946],"type":"Point"}
}