{
  "type": "Feature",
  "properties": {
    "iso:country":"US",
    "sg:address":"201 S Delaney Rd",
    "sg:city":"Owosso",
    "sg:classifiers":[
        {
            "category":"Manufacturing",
            "subcategory":"Tools & Machinery",
            "type":"Manufacturing & Wholesale Goods"
        }
    ],
    "sg:phone":"+1 989 725 5151",
    "sg:postcode":"48867",
    "sg:province":"MI",
    "sg:tags":[
        "motor",
        "generator"
    ],
    "sg:website":"www.motorproducts.net",
    "wof:name":"Motor Products Corp",
    "wof:placetype":"venue"
},
  "geometry": {"coordinates":[-84.206272,42.996608],"type":"Point"}
}