{
  "type": "Feature",
  "properties": {
    "iso:country":"US",
    "sg:address":"3019 26th St",
    "sg:city":"Hopkins",
    "sg:classifiers":[
        {
            "category":"Building & Trades",
            "subcategory":"Construction",
            "type":"Services"
        }
    ],
    "sg:phone":"+1 269 793 8708",
    "sg:postcode":"49328",
    "sg:province":"MI",
    "sg:tags":[
        "contractor"
    ],
    "wof:name":"Morley Welding Serbice",
    "wof:placetype":"venue"
},
  "geometry": {"coordinates":[-85.800414,42.640915],"type":"Point"}
}