{
  "type": "Feature",
  "properties": {
    "iso:country":"US",
    "sg:address":"30569 Beck Rd",
    "sg:city":"Wixom",
    "sg:classifiers":[
        {
            "category":"Manufacturing",
            "subcategory":"Metals",
            "type":"Manufacturing & Wholesale Goods"
        }
    ],
    "sg:phone":"+1 248 624 7700",
    "sg:postcode":"48393",
    "sg:province":"MI",
    "sg:tags":[
        "valve"
    ],
    "wof:name":"Mac Valves Inc",
    "wof:placetype":"venue"
},
  "geometry": {"coordinates":[-83.51736099999999,42.520747],"type":"Point"}
}