{
  "type": "Feature",
  "properties": {
    "iso:country":"US",
    "sg:address":"2025 W Cheesman Rd",
    "sg:city":"Alma",
    "sg:classifiers":[
        {
            "category":"Health Services",
            "subcategory":"Doctor",
            "type":"Services"
        }
    ],
    "sg:phone":"+1 989 463 3451",
    "sg:postcode":"48801",
    "sg:province":"MI",
    "sg:tags":[
        "physician",
        "surgeon"
    ],
    "wof:name":"Sacred Heart Mercy Health Care",
    "wof:placetype":"venue"
},
  "geometry": {"coordinates":[-84.64760099999999,43.400576],"type":"Point"}
}