{
  "type": "Feature",
  "properties": {
    "iso:country":"US",
    "sg:address":"311 W Baraga Ave",
    "sg:city":"Marquette",
    "sg:classifiers":[
        {
            "category":"Organizations",
            "subcategory":"Religious Organization",
            "type":"Services"
        }
    ],
    "sg:phone":"+1 906 226 6548",
    "sg:postcode":"49855",
    "sg:province":"MI",
    "sg:tags":[
        "catholic",
        "church"
    ],
    "sg:website":"www.stpetercathedral.org",
    "wof:name":"St Peters Cathedral",
    "wof:placetype":"venue"
},
  "geometry": {"coordinates":[-87.400502,46.541685],"type":"Point"}
}